Workbook

Sheet README
B1: DCT Laboratory — Vol II, Ch 10: Neuro-Fuzzy Robust Enterprise Optimization
B2: Seed 26210 · Companion to DCT_V2_Ch10_Lab.ipynb and AXIOM Lab 2.10 (module AXIOM-10). Money in $ million.
B4: Worked Example 10.1, What Can Meridian Guarantee Without Odds?, with the book's declarations: Chapter 9's levers and floor; the engineering office's bound on deviations and the treasury's bound on a closure, crisp and in graded words; the board's graded goal for cost. Chances are judged under Chapter 9's law on the book's 100,000 paths (seed 8) and its 100,000 fresh paths (seed 26209).
B5: Declarations: the law, the levers and their prices, the offices' words, the board's goal, the bank's cap.
B6: Plan: the plan's margin above the floor and the lift of a quarter of delay, quarter by quarter; the binding quarter and the prices of a dollar by line and by delay (Section 10.2).
B7: Robust: packages robust on declared sets in closed form, with the binding quarter and a cap on the line (Proposition 10.1(ii); Steps 1-2 and 5); Proposition 10.3(iii)'s quiet-then-damage future.
B8: Graded: the 101 cuts of the offices' words, the graded price, the board's goal and the max-min choice (Theorem 10.2; Proposition 10.2; Figure 10.1; Step 3).
B9: Frontier: Chapter 9's cheapest package for each appetite and Table 10.3 (Theorem 10.1(iii); Figure 10.3; Step 4).
B10: Rules: the eight neuro-fuzzy rules, their conclusions and slopes, and the Sugeno output at any declaration against the exact robust cost (Theorem 10.3; Equation 10.2; Step 5).
B11: Engine values (green) are what needs Chapter 9's simulated paths (chances, the share of paths inside a set, the frontier's lines and delays) or the neuro-fuzzy training (widths, coefficients, the certification grid). Everything else is a formula.
B12: Reference_Values and Checks: the engine's numbers and a PASS/FAIL comparison with this workbook's formulas.
B14: LEGEND
... B18: Cross-sheet link: green.

Sheet Declarations
A1: Declarations (Worked Example 10.1, Step 1; Chapter 9's law and levers). Money in $ million.
A3: Quantity | B3: Value | C3: Source
A4: Liquidity today | B4: 620 | C4: Meridian's state (Volume I, Chapter 1)
A5: $ million per index point | B5: =B4/100 -> 6.2 | C5: Index 100 = $620 million
A6: Plan without the draw: long-run index | B6: 112 | C6: The Chapter 1 plan relaxes from 100 toward 112
A7: at the rate (a year) | B7: 0.35
A8: The draw's depth (index points) | B8: 28 | C8: The digital program's draw, deepest at two years
A9: The draw is deepest at (years) | B9: 2 | C9: Shape S(t) = (t/2) e^(1 - t/2)
A10: Floor | B10: 350 | C10: The board's floor
A11: Persistence of a deviation a quarter | B11: 0.6 | C11: E' = 0.6 E + w (Volume I, Chapter 8)
A12: Standard deviation of w, a quarter | B12: 50
A13: Funding-window closures a year | B13: 0.1 | C13: About once a decade
A14: Closure size: mean | B14: 120 | C14: Gamma-distributed, never recovered
A15: Closure size: standard deviation | B15: 50
A16: Line fees over the program, per $ of line | B16: 0.03 | C16: The treasury
A17: A quarter of delay | B17: 8 | C17: The transformation office
A18: Depth cut by a quarter of delay (points) | B18: 4
A19: The appetite | B19: 0.05 | C19: At most a 5 percent chance of a breach in some quarter
A20: Paths (the book's, seed 8; fresh, seed 26209) | B20: 100000 | C20: Chapter 9's law
A22: The new declarations: bounds without odds, graded words, the board's goal (Worked Example 10.1, Steps 1-4)
A23: Deviations: usually within | B23: 50 | C23: The engineering office: possibility 1 up to here
A24: Deviations: never beyond | B24: 200 | C24: Possibility 0 beyond; the cut at alpha: 200 - 150 alpha
A25: A closure: most plausibly about | B25: 120 | C25: The treasury: possibility 1 up to here
A26: A closure: never above | B26: 300 | C26: Possibility 0 beyond; the cut at alpha: 300 - 180 alpha
A27: The board's goal: a guarantee should cost about ... or less | B27: 5 | C27: Goal 1 up to here
A28: and surely no more than | B28: 20 | C28: Goal 0 beyond; linear between
A29: A bank's cap on the line | B29: 100 | C29: Worked Example 10.1, Step 4
A30: Volume I's joint check: one closure of at most | B30: 187 | C30: Volume I, Worked Example 13.1: the 90th percentile, at the deepest draw
A31: A closure's 90th percentile under the law | B31: =GAMMAINV(0.9,(B14/B15)^2,B15^2/B14) -> 186.86698 | C31: Gamma with mean 120 and standard deviation 50: $187 million

Sheet Plan
A1: The plan's margin above the floor and the lift of a quarter of delay (Section 10.2; Proposition 10.1(ii); AXIOM Lab 2.10, step 1)
A2: On U(D, S) the floor holds in quarter k exactly when m_k + l_k phi - D - (S - l)^+ >= 0. A line covers a dollar of closure for 3 cents; delay buys a dollar of liquidity in quarter k for 8 / l_k.
A4: Quarter k | B4: t (years) | C4: Plan index without the draw | D4: Without the draw ($m) | E4: The draw's shape S | F4: $m per point of depth | G4: Planned liquidity ($m) | H4: Margin above the floor, m_k | I4: Lift of a quarter of delay, l_k | J4: Delay's price a dollar of liquidity
A5: 1 | B5: =A5/4 -> 0.25 | C5: =Xinf+(100-Xinf)*EXP(-Krel*B5) -> 101.00537 | D5: =PerPt*C5 -> 626.23332 | E5: =(B5/Tpk)*EXP(1-B5/Tpk) -> 0.29985941 | F5: =PerPt*E5 -> 1.8591284 | G5: =D5-Depth0*F5 -> 574.17772 | H5: =G5-FloorL -> 224.17772 | I5: =DPQ*F5 -> 7.4365134 | J5: =VQ/I5 -> 1.075773
A6: 2 | B6: =A6/4 -> 0.5 | C6: =Xinf+(100-Xinf)*EXP(-Krel*B6) -> 101.92652 | D6: =PerPt*C6 -> 631.9444 | E6: =(B6/Tpk)*EXP(1-B6/Tpk) -> 0.52925 | F6: =PerPt*E6 -> 3.28135 | G6: =D6-Depth0*F6 -> 540.0666 | H6: =G6-FloorL -> 190.0666 | I6: =DPQ*F6 -> 13.1254 | J6: =VQ/I6 -> 0.60950523
A7: 3 | B7: =A7/4 -> 0.75 | C7: =Xinf+(100-Xinf)*EXP(-Krel*B7) -> 102.77048 | D7: =PerPt*C7 -> 637.177 | E7: =(B7/Tpk)*EXP(1-B7/Tpk) -> 0.70059223 | F7: =PerPt*E7 -> 4.3436719 | G7: =D7-Depth0*F7 -> 515.55419 | H7: =G7-FloorL -> 165.55419 | I7: =DPQ*F7 -> 17.374687 | J7: =VQ/I7 -> 0.46043994
A8: 4 | B8: =A8/4 -> 1 | C8: =Xinf+(100-Xinf)*EXP(-Krel*B8) -> 103.54374 | D8: =PerPt*C8 -> 641.97121 | E8: =(B8/Tpk)*EXP(1-B8/Tpk) -> 0.82436064 | F8: =PerPt*E8 -> 5.1110359 | G8: =D8-Depth0*F8 -> 498.8622 | H8: =G8-FloorL -> 148.8622 | I8: =DPQ*F8 -> 20.444144 | J8: =VQ/I8 -> 0.3913101
A9: 5 | B9: =A9/4 -> 1.25 | C9: =Xinf+(100-Xinf)*EXP(-Krel*B9) -> 104.25222 | D9: =PerPt*C9 -> 646.36375 | E9: =(B9/Tpk)*EXP(1-B9/Tpk) -> 0.90936963 | F9: =PerPt*E9 -> 5.6380917 | G9: =D9-Depth0*F9 -> 488.49718 | H9: =G9-FloorL -> 138.49718 | I9: =DPQ*F9 -> 22.552367 | J9: =VQ/I9 -> 0.35472995
A10: 6 | B10: =A10/4 -> 1.5 | C10: =Xinf+(100-Xinf)*EXP(-Krel*B10) -> 104.90134 | D10: =PerPt*C10 -> 650.38828 | E10: =(B10/Tpk)*EXP(1-B10/Tpk) -> 0.96301906 | F10: =PerPt*E10 -> 5.9707182 | G10: =D10-Depth0*F10 -> 483.20817 | H10: =G10-FloorL -> 133.20817 | I10: =DPQ*F10 -> 23.882873 | J10: =VQ/I10 -> 0.33496808
A11: 7 | B11: =A11/4 -> 1.75 | C11: =Xinf+(100-Xinf)*EXP(-Krel*B11) -> 105.49607 | D11: =PerPt*C11 -> 654.07563 | E11: =(B11/Tpk)*EXP(1-B11/Tpk) -> 0.9915049 | F11: =PerPt*E11 -> 6.1473304 | G11: =D11-Depth0*F11 -> 481.95038 | H11: =G11-FloorL -> 131.95038 | I11: =DPQ*F11 -> 24.589321 | J11: =VQ/I11 -> 0.32534448
A12: 8 | B12: =A12/4 -> 2 | C12: =Xinf+(100-Xinf)*EXP(-Krel*B12) -> 106.04098 | D12: =PerPt*C12 -> 657.45405 | E12: =(B12/Tpk)*EXP(1-B12/Tpk) -> 1 | F12: =PerPt*E12 -> 6.2 | G12: =D12-Depth0*F12 -> 483.85405 | H12: =G12-FloorL -> 133.85405 | I12: =DPQ*F12 -> 24.8 | J12: =VQ/I12 -> 0.32258065
A13: 9 | B13: =A13/4 -> 2.25 | C13: =Xinf+(100-Xinf)*EXP(-Krel*B13) -> 106.54023 | D13: =PerPt*C13 -> 660.54943 | E13: =(B13/Tpk)*EXP(1-B13/Tpk) -> 0.99280902 | F13: =PerPt*E13 -> 6.1554159 | G13: =D13-Depth0*F13 -> 488.19778 | H13: =G13-FloorL -> 138.19778 | I13: =DPQ*F13 -> 24.621664 | J13: =VQ/I13 -> 0.32491712
A14: 10 | B14: =A14/4 -> 2.5 | C14: =Xinf+(100-Xinf)*EXP(-Krel*B14) -> 106.99766 | D14: =PerPt*C14 -> 663.38547 | E14: =(B14/Tpk)*EXP(1-B14/Tpk) -> 0.97350098 | F14: =PerPt*E14 -> 6.0357061 | G14: =D14-Depth0*F14 -> 494.3857 | H14: =G14-FloorL -> 144.3857 | I14: =DPQ*F14 -> 24.142824 | J14: =VQ/I14 -> 0.3313614
A15: 11 | B15: =A15/4 -> 2.75 | C15: =Xinf+(100-Xinf)*EXP(-Krel*B15) -> 107.41676 | D15: =PerPt*C15 -> 665.9839 | E15: =(B15/Tpk)*EXP(1-B15/Tpk) -> 0.94502276 | F15: =PerPt*E15 -> 5.8591411 | G15: =D15-Depth0*F15 -> 501.92795 | H15: =G15-FloorL -> 151.92795 | I15: =DPQ*F15 -> 23.436564 | J15: =VQ/I15 -> 0.34134696
A16: 12 | B16: =A16/4 -> 3 | C16: =Xinf+(100-Xinf)*EXP(-Krel*B16) -> 107.80075 | D16: =PerPt*C16 -> 668.36463 | E16: =(B16/Tpk)*EXP(1-B16/Tpk) -> 0.90979599 | F16: =PerPt*E16 -> 5.6407351 | G16: =D16-Depth0*F16 -> 510.42405 | H16: =G16-FloorL -> 160.42405 | I16: =DPQ*F16 -> 22.562941 | J16: =VQ/I16 -> 0.35456371
A19: The plan's least margin above the floor | B19: =MIN(H5:H16) -> 131.95038 | C19: $132 million
A20: in quarter | B20: =MATCH(B19,H5:H16,0) -> 7 | C20: 7: the binding quarter of the crisp set
A21: A quarter of delay lifts that quarter by | B21: =INDEX(I5:I16,B20) -> 24.589321 | C21: $24.6 million
A22: The line's price a dollar of closure | B22: =Fee -> 0.03 | C22: 3 cents
A23: Delay's price a dollar of liquidity there | B23: =VQ/B21 -> 0.32534448 | C23: About 33 cents
A24: Planned liquidity at its low point | B24: =MIN(G5:G16) -> 481.95038 | C24: $482 million

Sheet Robust
A1: Robust packages on declared sets (Proposition 10.1(ii); Worked Example 10.1, Steps 1-2 and 5; AXIOM Lab 2.10, step 1)
A2: The least delay the deviations need, phi* = max(0, max_k (D - m_k)/l_k); the margin absorbs u* = min(S, min_k (m_k - D + l_k phi*)) of a closure; the line covers the rest, l = S - u*. With a cap on the line, u = S - cap and the delay carries it. The binding quarter is where (D + u - m_k)/l_k is largest.
A4: Declared set | B4: Cut alpha | C4: D: deviations' bound | D4: S: closure's bound | E4: Cap on the line | F4: Delay the deviations need | G4: Margin absorbs (no cap) | H4: Capped? | I4: Margin absorbs | J4: Line | K4: Delay | L4: Cost | M4: Need, q1 | N4: Need, q2 | O4: Need, q3 | P4: Need, q4 | Q4: Need, q5 | R4: Need, q6 | S4: Need, q7 | T4: Need, q8 | U4: Need, q9 | V4: Need, q10 | W4: Need, q11 | X4: Need, q12 | Y4: Binding quarter | Z4: Paths in the set (engine) | AA4: Breach under the law (engine) | AB4: Fresh paths (engine)
A5: Volume I's joint check | C5: 0 | D5: =SJoint -> 187 | F5: =MAX(0,(C5-Plan!$H$5)/Plan!$I$5,(C5-Plan!$H$6)/Plan!$I$6,(C5-Plan!$H$7)/Plan!$I$7,(C5-Plan!$H$8)/Plan!$I$8,(C5-Plan!$H$9)/Plan!$I$9,(C5-Plan!$H$10)/Plan!$I$10,(C5-Plan!$H$11)/Plan!$I$11,(C5-Plan!$H$12)/Plan!$I$12,(C5-Plan!$H$13)/Plan!$I$13,(C5-Plan!$H$14)/Plan!$I$14,(C5-Plan!$H$15)/Plan!$I$15,(C5-Plan!$H$16)/Plan!$I$16) -> 0 | G5: =MIN(D5,Plan!$H$5-C5+Plan!$I$5*F5,Plan!$H$6-C5+Plan!$I$6*F5,Plan!$H$7-C5+Plan!$I$7*F5,Plan!$H$8-C5+Plan!$I$8*F5,Plan!$H$9-C5+Plan!$I$9*F5,Plan!$H$10-C5+Plan!$I$10*F5,Plan!$H$11-C5+Plan!$I$11*F5,Plan!$H$12-C5+Plan!$I$12*F5,Plan!$H$13-C5+Plan!$I$13*F5,Plan!$H$14-C5+Plan!$I$14*F5,Plan!$H$15-C5+Plan!$I$15*F5,Plan!$H$16-C5+Plan!$I$16*F5) -> 131.95038 | H5: =IF(ISNUMBER(E5),IF(D5-G5>E5,1,0),0) -> 0 | I5: =IF(H5=1,D5-E5,G5) -> 131.95038 | J5: =D5-I5 -> 55.049618 | K5: =IF(H5=1,MAX(0,(C5+I5-Plan!$H$5)/Plan!$I$5,(C5+I5-Plan!$H$6)/Plan!$I$6,(C5+I5-Plan!$H$7)/Plan!$I$7,(C5+I5-Plan!$H$8)/Plan!$I$8,(C5+I5-Plan!$H$9)/Plan!$I$9,(C5+I5-Plan!$H$10)/Plan!$I$10,(C5+I5-Plan!$H$11)/Plan!$I$11,(C5+I5-Plan!$H$12)/Plan!$I$12,(C5+I5-Plan!$H$13)/Plan!$I$13,(C5+I5-Plan!$H$14)/Plan!$I$14,(C5+I5-Plan!$H$15)/Plan!$I$15,(C5+I5-Plan!$H$16)/Plan!$I$16),F5) -> 0 | L5: =Fee*J5+VQ*K5 -> 1.6514885 | M5: =(C5+I5-Plan!$H$5)/Plan!$I$5 -> -12.40196 | N5: =(C5+I5-Plan!$H$6)/Plan!$I$6 -> -4.4277671 | O5: =(C5+I5-Plan!$H$7)/Plan!$I$7 -> -1.9340667 | P5: =(C5+I5-Plan!$H$8)/Plan!$I$8 -> -0.82722063 | Q5: =(C5+I5-Plan!$H$9)/Plan!$I$9 -> -0.2902932 | R5: =(C5+I5-Plan!$H$10)/Plan!$I$10 -> -0.052664907 | S5: =(C5+I5-Plan!$H$11)/Plan!$I$11 -> 0 | T5: =(C5+I5-Plan!$H$12)/Plan!$I$12 -> -0.076760929 | U5: =(C5+I5-Plan!$H$13)/Plan!$I$13 -> -0.25373586 | V5: =(C5+I5-Plan!$H$14)/Plan!$I$14 -> -0.51507286 | W5: =(C5+I5-Plan!$H$15)/Plan!$I$15 -> -0.85241014 | X5: =(C5+I5-Plan!$H$16)/Plan!$I$16 -> -1.2619661 | Y5: =MATCH(MAX(M5:X5),M5:X5,0) -> 7 | Z5: 0.01488 | AA5: 0.17388 | AB5: 0.17124
A6: Crisp set (the 0.5-cut) | B6: 0.5 | C6: =DNever-(DNever-DUsual)*B6 -> 125 | D6: =SNever-(SNever-SPlaus)*B6 -> 210 | F6: =MAX(0,(C6-Plan!$H$5)/Plan!$I$5,(C6-Plan!$H$6)/Plan!$I$6,(C6-Plan!$H$7)/Plan!$I$7,(C6-Plan!$H$8)/Plan!$I$8,(C6-Plan!$H$9)/Plan!$I$9,(C6-Plan!$H$10)/Plan!$I$10,(C6-Plan!$H$11)/Plan!$I$11,(C6-Plan!$H$12)/Plan!$I$12,(C6-Plan!$H$13)/Plan!$I$13,(C6-Plan!$H$14)/Plan!$I$14,(C6-Plan!$H$15)/Plan!$I$15,(C6-Plan!$H$16)/Plan!$I$16) -> 0 | G6: =MIN(D6,Plan!$H$5-C6+Plan!$I$5*F6,Plan!$H$6-C6+Plan!$I$6*F6,Plan!$H$7-C6+Plan!$I$7*F6,Plan!$H$8-C6+Plan!$I$8*F6,Plan!$H$9-C6+Plan!$I$9*F6,Plan!$H$10-C6+Plan!$I$10*F6,Plan!$H$11-C6+Plan!$I$11*F6,Plan!$H$12-C6+Plan!$I$12*F6,Plan!$H$13-C6+Plan!$I$13*F6,Plan!$H$14-C6+Plan!$I$14*F6,Plan!$H$15-C6+Plan!$I$15*F6,Plan!$H$16-C6+Plan!$I$16*F6) -> 6.9503824 | H6: =IF(ISNUMBER(E6),IF(D6-G6>E6,1,0),0) -> 0 | I6: =IF(H6=1,D6-E6,G6) -> 6.9503824 | J6: =D6-I6 -> 203.04962 | K6: =IF(H6=1,MAX(0,(C6+I6-Plan!$H$5)/Plan!$I$5,(C6+I6-Plan!$H$6)/Plan!$I$6,(C6+I6-Plan!$H$7)/Plan!$I$7,(C6+I6-Plan!$H$8)/Plan!$I$8,(C6+I6-Plan!$H$9)/Plan!$I$9,(C6+I6-Plan!$H$10)/Plan!$I$10,(C6+I6-Plan!$H$11)/Plan!$I$11,(C6+I6-Plan!$H$12)/Plan!$I$12,(C6+I6-Plan!$H$13)/Plan!$I$13,(C6+I6-Plan!$H$14)/Plan!$I$14,(C6+I6-Plan!$H$15)/Plan!$I$15,(C6+I6-Plan!$H$16)/Plan!$I$16),F6) -> 0 | L6: =Fee*J6+VQ*K6 -> 6.0914885 | M6: =(C6+I6-Plan!$H$5)/Plan!$I$5 -> -12.40196 | N6: =(C6+I6-Plan!$H$6)/Plan!$I$6 -> -4.4277671 | O6: =(C6+I6-Plan!$H$7)/Plan!$I$7 -> -1.9340667 | P6: =(C6+I6-Plan!$H$8)/Plan!$I$8 -> -0.82722063 | Q6: =(C6+I6-Plan!$H$9)/Plan!$I$9 -> -0.2902932 | R6: =(C6+I6-Plan!$H$10)/Plan!$I$10 -> -0.052664907 | S6: =(C6+I6-Plan!$H$11)/Plan!$I$11 -> 0 | T6: =(C6+I6-Plan!$H$12)/Plan!$I$12 -> -0.076760929 | U6: =(C6+I6-Plan!$H$13)/Plan!$I$13 -> -0.25373586 | V6: =(C6+I6-Plan!$H$14)/Plan!$I$14 -> -0.51507286 | W6: =(C6+I6-Plan!$H$15)/Plan!$I$15 -> -0.85241014 | X6: =(C6+I6-Plan!$H$16)/Plan!$I$16 -> -1.2619661 | Y6: =MATCH(MAX(M6:X6),M6:X6,0) -> 7 | Z6: 0.78907 | AA6: 0.08645 | AB6: 0.08435
A7: Max-min choice | B7: =Graded!$U$7 -> 0.38 | C7: =DNever-(DNever-DUsual)*B7 -> 143 | D7: =SNever-(SNever-SPlaus)*B7 -> 231.6 | F7: =MAX(0,(C7-Plan!$H$5)/Plan!$I$5,(C7-Plan!$H$6)/Plan!$I$6,(C7-Plan!$H$7)/Plan!$I$7,(C7-Plan!$H$8)/Plan!$I$8,(C7-Plan!$H$9)/Plan!$I$9,(C7-Plan!$H$10)/Plan!$I$10,(C7-Plan!$H$11)/Plan!$I$11,(C7-Plan!$H$12)/Plan!$I$12,(C7-Plan!$H$13)/Plan!$I$13,(C7-Plan!$H$14)/Plan!$I$14,(C7-Plan!$H$15)/Plan!$I$15,(C7-Plan!$H$16)/Plan!$I$16) -> 0.44936651 | G7: =MIN(D7,Plan!$H$5-C7+Plan!$I$5*F7,Plan!$H$6-C7+Plan!$I$6*F7,Plan!$H$7-C7+Plan!$I$7*F7,Plan!$H$8-C7+Plan!$I$8*F7,Plan!$H$9-C7+Plan!$I$9*F7,Plan!$H$10-C7+Plan!$I$10*F7,Plan!$H$11-C7+Plan!$I$11*F7,Plan!$H$12-C7+Plan!$I$12*F7,Plan!$H$13-C7+Plan!$I$13*F7,Plan!$H$14-C7+Plan!$I$14*F7,Plan!$H$15-C7+Plan!$I$15*F7,Plan!$H$16-C7+Plan!$I$16*F7) -> 0 | H7: =IF(ISNUMBER(E7),IF(D7-G7>E7,1,0),0) -> 0 | I7: =IF(H7=1,D7-E7,G7) -> 0 | J7: =D7-I7 -> 231.6 | K7: =IF(H7=1,MAX(0,(C7+I7-Plan!$H$5)/Plan!$I$5,(C7+I7-Plan!$H$6)/Plan!$I$6,(C7+I7-Plan!$H$7)/Plan!$I$7,(C7+I7-Plan!$H$8)/Plan!$I$8,(C7+I7-Plan!$H$9)/Plan!$I$9,(C7+I7-Plan!$H$10)/Plan!$I$10,(C7+I7-Plan!$H$11)/Plan!$I$11,(C7+I7-Plan!$H$12)/Plan!$I$12,(C7+I7-Plan!$H$13)/Plan!$I$13,(C7+I7-Plan!$H$14)/Plan!$I$14,(C7+I7-Plan!$H$15)/Plan!$I$15,(C7+I7-Plan!$H$16)/Plan!$I$16),F7) -> 0.44936651 | L7: =Fee*J7+VQ*K7 -> 10.542932 | M7: =(C7+I7-Plan!$H$5)/Plan!$I$5 -> -10.9161 | N7: =(C7+I7-Plan!$H$6)/Plan!$I$6 -> -3.5859171 | O7: =(C7+I7-Plan!$H$7)/Plan!$I$7 -> -1.298106 | P7: =(C7+I7-Plan!$H$8)/Plan!$I$8 -> -0.28674225 | Q7: =(C7+I7-Plan!$H$9)/Plan!$I$9 -> 0.19966059 | R7: =(C7+I7-Plan!$H$10)/Plan!$I$10 -> 0.40999374 | S7: =(C7+I7-Plan!$H$11)/Plan!$I$11 -> 0.44936651 | T7: =(C7+I7-Plan!$H$12)/Plan!$I$12 -> 0.36878817 | U7: =(C7+I7-Plan!$H$13)/Plan!$I$13 -> 0.19504038 | V7: =(C7+I7-Plan!$H$14)/Plan!$I$14 -> -0.057395763 | W7: =(C7+I7-Plan!$H$15)/Plan!$I$15 -> -0.38094097 | X7: =(C7+I7-Plan!$H$16)/Plan!$I$16 -> -0.77224188 | Y7: =MATCH(MAX(M7:X7),M7:X7,0) -> 7 | Z7: 0.87036 | AA7: 0.05637 | AB7: 0.05508
A8: Meeting 5% under the law | B8: =Graded!$U$12 -> 0.35 | C8: =DNever-(DNever-DUsual)*B8 -> 147.5 | D8: =SNever-(SNever-SPlaus)*B8 -> 237 | F8: =MAX(0,(C8-Plan!$H$5)/Plan!$I$5,(C8-Plan!$H$6)/Plan!$I$6,(C8-Plan!$H$7)/Plan!$I$7,(C8-Plan!$H$8)/Plan!$I$8,(C8-Plan!$H$9)/Plan!$I$9,(C8-Plan!$H$10)/Plan!$I$10,(C8-Plan!$H$11)/Plan!$I$11,(C8-Plan!$H$12)/Plan!$I$12,(C8-Plan!$H$13)/Plan!$I$13,(C8-Plan!$H$14)/Plan!$I$14,(C8-Plan!$H$15)/Plan!$I$15,(C8-Plan!$H$16)/Plan!$I$16) -> 0.63237278 | G8: =MIN(D8,Plan!$H$5-C8+Plan!$I$5*F8,Plan!$H$6-C8+Plan!$I$6*F8,Plan!$H$7-C8+Plan!$I$7*F8,Plan!$H$8-C8+Plan!$I$8*F8,Plan!$H$9-C8+Plan!$I$9*F8,Plan!$H$10-C8+Plan!$I$10*F8,Plan!$H$11-C8+Plan!$I$11*F8,Plan!$H$12-C8+Plan!$I$12*F8,Plan!$H$13-C8+Plan!$I$13*F8,Plan!$H$14-C8+Plan!$I$14*F8,Plan!$H$15-C8+Plan!$I$15*F8,Plan!$H$16-C8+Plan!$I$16*F8) -> 0 | H8: =IF(ISNUMBER(E8),IF(D8-G8>E8,1,0),0) -> 0 | I8: =IF(H8=1,D8-E8,G8) -> 0 | J8: =D8-I8 -> 237 | K8: =IF(H8=1,MAX(0,(C8+I8-Plan!$H$5)/Plan!$I$5,(C8+I8-Plan!$H$6)/Plan!$I$6,(C8+I8-Plan!$H$7)/Plan!$I$7,(C8+I8-Plan!$H$8)/Plan!$I$8,(C8+I8-Plan!$H$9)/Plan!$I$9,(C8+I8-Plan!$H$10)/Plan!$I$10,(C8+I8-Plan!$H$11)/Plan!$I$11,(C8+I8-Plan!$H$12)/Plan!$I$12,(C8+I8-Plan!$H$13)/Plan!$I$13,(C8+I8-Plan!$H$14)/Plan!$I$14,(C8+I8-Plan!$H$15)/Plan!$I$15,(C8+I8-Plan!$H$16)/Plan!$I$16),F8) -> 0.63237278 | L8: =Fee*J8+VQ*K8 -> 12.168982 | M8: =(C8+I8-Plan!$H$5)/Plan!$I$5 -> -10.310977 | N8: =(C8+I8-Plan!$H$6)/Plan!$I$6 -> -3.2430704 | O8: =(C8+I8-Plan!$H$7)/Plan!$I$7 -> -1.0391086 | P8: =(C8+I8-Plan!$H$8)/Plan!$I$8 -> -0.066630319 | Q8: =(C8+I8-Plan!$H$9)/Plan!$I$9 -> 0.39919619 | R8: =(C8+I8-Plan!$H$10)/Plan!$I$10 -> 0.59841329 | S8: =(C8+I8-Plan!$H$11)/Plan!$I$11 -> 0.63237278 | T8: =(C8+I8-Plan!$H$12)/Plan!$I$12 -> 0.55023978 | U8: =(C8+I8-Plan!$H$13)/Plan!$I$13 -> 0.37780626 | V8: =(C8+I8-Plan!$H$14)/Plan!$I$14 -> 0.12899502 | W8: =(C8+I8-Plan!$H$15)/Plan!$I$15 -> -0.1889333 | X8: =(C8+I8-Plan!$H$16)/Plan!$I$16 -> -0.57279979 | Y8: =MATCH(MAX(M8:X8),M8:X8,0) -> 7 | Z8: 0.88533 | AA8: 0.04712 | AB8: 0.04617
A9: 95% of paths in the set | B9: =Graded!$U$13 -> 0.08 | C9: =DNever-(DNever-DUsual)*B9 -> 188 | D9: =SNever-(SNever-SPlaus)*B9 -> 285.6 | F9: =MAX(0,(C9-Plan!$H$5)/Plan!$I$5,(C9-Plan!$H$6)/Plan!$I$6,(C9-Plan!$H$7)/Plan!$I$7,(C9-Plan!$H$8)/Plan!$I$8,(C9-Plan!$H$9)/Plan!$I$9,(C9-Plan!$H$10)/Plan!$I$10,(C9-Plan!$H$11)/Plan!$I$11,(C9-Plan!$H$12)/Plan!$I$12,(C9-Plan!$H$13)/Plan!$I$13,(C9-Plan!$H$14)/Plan!$I$14,(C9-Plan!$H$15)/Plan!$I$15,(C9-Plan!$H$16)/Plan!$I$16) -> 2.2941892 | G9: =MIN(D9,Plan!$H$5-C9+Plan!$I$5*F9,Plan!$H$6-C9+Plan!$I$6*F9,Plan!$H$7-C9+Plan!$I$7*F9,Plan!$H$8-C9+Plan!$I$8*F9,Plan!$H$9-C9+Plan!$I$9*F9,Plan!$H$10-C9+Plan!$I$10*F9,Plan!$H$11-C9+Plan!$I$11*F9,Plan!$H$12-C9+Plan!$I$12*F9,Plan!$H$13-C9+Plan!$I$13*F9,Plan!$H$14-C9+Plan!$I$14*F9,Plan!$H$15-C9+Plan!$I$15*F9,Plan!$H$16-C9+Plan!$I$16*F9) -> 0 | H9: =IF(ISNUMBER(E9),IF(D9-G9>E9,1,0),0) -> 0 | I9: =IF(H9=1,D9-E9,G9) -> 0 | J9: =D9-I9 -> 285.6 | K9: =IF(H9=1,MAX(0,(C9+I9-Plan!$H$5)/Plan!$I$5,(C9+I9-Plan!$H$6)/Plan!$I$6,(C9+I9-Plan!$H$7)/Plan!$I$7,(C9+I9-Plan!$H$8)/Plan!$I$8,(C9+I9-Plan!$H$9)/Plan!$I$9,(C9+I9-Plan!$H$10)/Plan!$I$10,(C9+I9-Plan!$H$11)/Plan!$I$11,(C9+I9-Plan!$H$12)/Plan!$I$12,(C9+I9-Plan!$H$13)/Plan!$I$13,(C9+I9-Plan!$H$14)/Plan!$I$14,(C9+I9-Plan!$H$15)/Plan!$I$15,(C9+I9-Plan!$H$16)/Plan!$I$16),F9) -> 2.2941892 | L9: =Fee*J9+VQ*K9 -> 26.921513 | M9: =(C9+I9-Plan!$H$5)/Plan!$I$5 -> -4.8648769 | N9: =(C9+I9-Plan!$H$6)/Plan!$I$6 -> -0.1574502 | O9: =(C9+I9-Plan!$H$7)/Plan!$I$7 -> 1.2918686 | P9: =(C9+I9-Plan!$H$8)/Plan!$I$8 -> 1.9143771 | Q9: =(C9+I9-Plan!$H$9)/Plan!$I$9 -> 2.1950166 | R9: =(C9+I9-Plan!$H$10)/Plan!$I$10 -> 2.2941892 | S9: =(C9+I9-Plan!$H$11)/Plan!$I$11 -> 2.2794292 | T9: =(C9+I9-Plan!$H$12)/Plan!$I$12 -> 2.1833043 | U9: =(C9+I9-Plan!$H$13)/Plan!$I$13 -> 2.0226992 | V9: =(C9+I9-Plan!$H$14)/Plan!$I$14 -> 1.8065121 | W9: =(C9+I9-Plan!$H$15)/Plan!$I$15 -> 1.5391357 | X9: =(C9+I9-Plan!$H$16)/Plan!$I$16 -> 1.222179 | Y9: =MATCH(MAX(M9:X9),M9:X9,0) -> 6 | Z9: 0.95021 | AA9: 0.00757 | AB9: 0.00731
A10: The whole support (the 0-cut) | B10: 0 | C10: =DNever-(DNever-DUsual)*B10 -> 200 | D10: =SNever-(SNever-SPlaus)*B10 -> 300 | F10: =MAX(0,(C10-Plan!$H$5)/Plan!$I$5,(C10-Plan!$H$6)/Plan!$I$6,(C10-Plan!$H$7)/Plan!$I$7,(C10-Plan!$H$8)/Plan!$I$8,(C10-Plan!$H$9)/Plan!$I$9,(C10-Plan!$H$10)/Plan!$I$10,(C10-Plan!$H$11)/Plan!$I$11,(C10-Plan!$H$12)/Plan!$I$12,(C10-Plan!$H$13)/Plan!$I$13,(C10-Plan!$H$14)/Plan!$I$14,(C10-Plan!$H$15)/Plan!$I$15,(C10-Plan!$H$16)/Plan!$I$16) -> 2.7966413 | G10: =MIN(D10,Plan!$H$5-C10+Plan!$I$5*F10,Plan!$H$6-C10+Plan!$I$6*F10,Plan!$H$7-C10+Plan!$I$7*F10,Plan!$H$8-C10+Plan!$I$8*F10,Plan!$H$9-C10+Plan!$I$9*F10,Plan!$H$10-C10+Plan!$I$10*F10,Plan!$H$11-C10+Plan!$I$11*F10,Plan!$H$12-C10+Plan!$I$12*F10,Plan!$H$13-C10+Plan!$I$13*F10,Plan!$H$14-C10+Plan!$I$14*F10,Plan!$H$15-C10+Plan!$I$15*F10,Plan!$H$16-C10+Plan!$I$16*F10) -> 0 | H10: =IF(ISNUMBER(E10),IF(D10-G10>E10,1,0),0) -> 0 | I10: =IF(H10=1,D10-E10,G10) -> 0 | J10: =D10-I10 -> 300 | K10: =IF(H10=1,MAX(0,(C10+I10-Plan!$H$5)/Plan!$I$5,(C10+I10-Plan!$H$6)/Plan!$I$6,(C10+I10-Plan!$H$7)/Plan!$I$7,(C10+I10-Plan!$H$8)/Plan!$I$8,(C10+I10-Plan!$H$9)/Plan!$I$9,(C10+I10-Plan!$H$10)/Plan!$I$10,(C10+I10-Plan!$H$11)/Plan!$I$11,(C10+I10-Plan!$H$12)/Plan!$I$12,(C10+I10-Plan!$H$13)/Plan!$I$13,(C10+I10-Plan!$H$14)/Plan!$I$14,(C10+I10-Plan!$H$15)/Plan!$I$15,(C10+I10-Plan!$H$16)/Plan!$I$16),F10) -> 2.7966413 | L10: =Fee*J10+VQ*K10 -> 31.37313 | M10: =(C10+I10-Plan!$H$5)/Plan!$I$5 -> -3.2512174 | N10: =(C10+I10-Plan!$H$6)/Plan!$I$6 -> 0.75680764 | O10: =(C10+I10-Plan!$H$7)/Plan!$I$7 -> 1.9825285 | P10: =(C10+I10-Plan!$H$8)/Plan!$I$8 -> 2.5013422 | Q10: =(C10+I10-Plan!$H$9)/Plan!$I$9 -> 2.7271115 | R10: =(C10+I10-Plan!$H$10)/Plan!$I$10 -> 2.7966413 | S10: =(C10+I10-Plan!$H$11)/Plan!$I$11 -> 2.7674459 | T10: =(C10+I10-Plan!$H$12)/Plan!$I$12 -> 2.6671753 | U10: =(C10+I10-Plan!$H$13)/Plan!$I$13 -> 2.5100749 | V10: =(C10+I10-Plan!$H$14)/Plan!$I$14 -> 2.3035542 | W10: =(C10+I10-Plan!$H$15)/Plan!$I$15 -> 2.0511561 | X10: =(C10+I10-Plan!$H$16)/Plan!$I$16 -> 1.7540246 | Y10: =MATCH(MAX(M10:X10),M10:X10,0) -> 6 | Z10: 0.95581 | AA10: 0.00393 | AB10: 0.00394
A11: The revision of Step 5 | C11: 140 | D11: 230 | F11: =MAX(0,(C11-Plan!$H$5)/Plan!$I$5,(C11-Plan!$H$6)/Plan!$I$6,(C11-Plan!$H$7)/Plan!$I$7,(C11-Plan!$H$8)/Plan!$I$8,(C11-Plan!$H$9)/Plan!$I$9,(C11-Plan!$H$10)/Plan!$I$10,(C11-Plan!$H$11)/Plan!$I$11,(C11-Plan!$H$12)/Plan!$I$12,(C11-Plan!$H$13)/Plan!$I$13,(C11-Plan!$H$14)/Plan!$I$14,(C11-Plan!$H$15)/Plan!$I$15,(C11-Plan!$H$16)/Plan!$I$16) -> 0.32736233 | G11: =MIN(D11,Plan!$H$5-C11+Plan!$I$5*F11,Plan!$H$6-C11+Plan!$I$6*F11,Plan!$H$7-C11+Plan!$I$7*F11,Plan!$H$8-C11+Plan!$I$8*F11,Plan!$H$9-C11+Plan!$I$9*F11,Plan!$H$10-C11+Plan!$I$10*F11,Plan!$H$11-C11+Plan!$I$11*F11,Plan!$H$12-C11+Plan!$I$12*F11,Plan!$H$13-C11+Plan!$I$13*F11,Plan!$H$14-C11+Plan!$I$14*F11,Plan!$H$15-C11+Plan!$I$15*F11,Plan!$H$16-C11+Plan!$I$16*F11) -> 0 | H11: =IF(ISNUMBER(E11),IF(D11-G11>E11,1,0),0) -> 0 | I11: =IF(H11=1,D11-E11,G11) -> 0 | J11: =D11-I11 -> 230 | K11: =IF(H11=1,MAX(0,(C11+I11-Plan!$H$5)/Plan!$I$5,(C11+I11-Plan!$H$6)/Plan!$I$6,(C11+I11-Plan!$H$7)/Plan!$I$7,(C11+I11-Plan!$H$8)/Plan!$I$8,(C11+I11-Plan!$H$9)/Plan!$I$9,(C11+I11-Plan!$H$10)/Plan!$I$10,(C11+I11-Plan!$H$11)/Plan!$I$11,(C11+I11-Plan!$H$12)/Plan!$I$12,(C11+I11-Plan!$H$13)/Plan!$I$13,(C11+I11-Plan!$H$14)/Plan!$I$14,(C11+I11-Plan!$H$15)/Plan!$I$15,(C11+I11-Plan!$H$16)/Plan!$I$16),F11) -> 0.32736233 | L11: =Fee*J11+VQ*K11 -> 9.5188987 | M11: =(C11+I11-Plan!$H$5)/Plan!$I$5 -> -11.319515 | N11: =(C11+I11-Plan!$H$6)/Plan!$I$6 -> -3.8144816 | O11: =(C11+I11-Plan!$H$7)/Plan!$I$7 -> -1.470771 | P11: =(C11+I11-Plan!$H$8)/Plan!$I$8 -> -0.43348354 | Q11: =(C11+I11-Plan!$H$9)/Plan!$I$9 -> 0.066636857 | R11: =(C11+I11-Plan!$H$10)/Plan!$I$10 -> 0.28438071 | S11: =(C11+I11-Plan!$H$11)/Plan!$I$11 -> 0.32736233 | T11: =(C11+I11-Plan!$H$12)/Plan!$I$12 -> 0.24782043 | U11: =(C11+I11-Plan!$H$13)/Plan!$I$13 -> 0.073196459 | V11: =(C11+I11-Plan!$H$14)/Plan!$I$14 -> -0.18165629 | W11: =(C11+I11-Plan!$H$15)/Plan!$I$15 -> -0.50894608 | X11: =(C11+I11-Plan!$H$16)/Plan!$I$16 -> -0.90520328 | Y11: =MATCH(MAX(M11:X11),M11:X11,0) -> 7 | Z11: 0.85976 | AA11: 0.06332 | AB11: 0.06137
A12: The crisp set, the line capped | B12: 0.5 | C12: =DNever-(DNever-DUsual)*B12 -> 125 | D12: =SNever-(SNever-SPlaus)*B12 -> 210 | E12: =CapL -> 100 | F12: =MAX(0,(C12-Plan!$H$5)/Plan!$I$5,(C12-Plan!$H$6)/Plan!$I$6,(C12-Plan!$H$7)/Plan!$I$7,(C12-Plan!$H$8)/Plan!$I$8,(C12-Plan!$H$9)/Plan!$I$9,(C12-Plan!$H$10)/Plan!$I$10,(C12-Plan!$H$11)/Plan!$I$11,(C12-Plan!$H$12)/Plan!$I$12,(C12-Plan!$H$13)/Plan!$I$13,(C12-Plan!$H$14)/Plan!$I$14,(C12-Plan!$H$15)/Plan!$I$15,(C12-Plan!$H$16)/Plan!$I$16) -> 0 | G12: =MIN(D12,Plan!$H$5-C12+Plan!$I$5*F12,Plan!$H$6-C12+Plan!$I$6*F12,Plan!$H$7-C12+Plan!$I$7*F12,Plan!$H$8-C12+Plan!$I$8*F12,Plan!$H$9-C12+Plan!$I$9*F12,Plan!$H$10-C12+Plan!$I$10*F12,Plan!$H$11-C12+Plan!$I$11*F12,Plan!$H$12-C12+Plan!$I$12*F12,Plan!$H$13-C12+Plan!$I$13*F12,Plan!$H$14-C12+Plan!$I$14*F12,Plan!$H$15-C12+Plan!$I$15*F12,Plan!$H$16-C12+Plan!$I$16*F12) -> 6.9503824 | H12: =IF(ISNUMBER(E12),IF(D12-G12>E12,1,0),0) -> 1 | I12: =IF(H12=1,D12-E12,G12) -> 110 | J12: =D12-I12 -> 100 | K12: =IF(H12=1,MAX(0,(C12+I12-Plan!$H$5)/Plan!$I$5,(C12+I12-Plan!$H$6)/Plan!$I$6,(C12+I12-Plan!$H$7)/Plan!$I$7,(C12+I12-Plan!$H$8)/Plan!$I$8,(C12+I12-Plan!$H$9)/Plan!$I$9,(C12+I12-Plan!$H$10)/Plan!$I$10,(C12+I12-Plan!$H$11)/Plan!$I$11,(C12+I12-Plan!$H$12)/Plan!$I$12,(C12+I12-Plan!$H$13)/Plan!$I$13,(C12+I12-Plan!$H$14)/Plan!$I$14,(C12+I12-Plan!$H$15)/Plan!$I$15,(C12+I12-Plan!$H$16)/Plan!$I$16),F12) -> 4.279055 | L12: =Fee*J12+VQ*K12 -> 37.23244 | M12: =(C12+I12-Plan!$H$5)/Plan!$I$5 -> 1.4552892 | N12: =(C12+I12-Plan!$H$6)/Plan!$I$6 -> 3.423393 | O12: =(C12+I12-Plan!$H$7)/Plan!$I$7 -> 3.9969533 | P12: =(C12+I12-Plan!$H$8)/Plan!$I$8 -> 4.2133239 | Q12: =(C12+I12-Plan!$H$9)/Plan!$I$9 -> 4.279055 | R12: =(C12+I12-Plan!$H$10)/Plan!$I$10 -> 4.2621266 | S12: =(C12+I12-Plan!$H$11)/Plan!$I$11 -> 4.190828 | T12: =(C12+I12-Plan!$H$12)/Plan!$I$12 -> 4.0784656 | U12: =(C12+I12-Plan!$H$13)/Plan!$I$13 -> 3.9315872 | V12: =(C12+I12-Plan!$H$14)/Plan!$I$14 -> 3.7532603 | W12: =(C12+I12-Plan!$H$15)/Plan!$I$15 -> 3.5445491 | X12: =(C12+I12-Plan!$H$16)/Plan!$I$16 -> 3.3052408 | Y12: =MATCH(MAX(M12:X12),M12:X12,0) -> 5 | Z12: 0.78907 | AA12: 0.00643 | AB12: 0.00664
A14: The crisp set: deviations use, of the least margin | B14: =C6 -> 125 | C14: $125 million of $132 million
A15: the closure's first part fits in the rest | B15: =I6 -> 6.9503824 | C15: $7 million
A16: the line covers the remainder | B16: =J6 -> 203.04962 | C16: $203 million, no delay: $6.09 million
A17: the set holds (engine) | B17: =Z6 -> 0.78907 | C17: 79 percent of the book's paths
A18: so Theorem 10.1(iii) promised a chance of at most | B18: =1-B17 -> 0.21093 | C18: 21 percent; under the law 8.6 percent
A19: Proposition 10.3(iii): quarter 7 on a future quiet through quarter 6, then deviations at -D and the closure, crisp package | B19: =FloorL+Plan!$H$11+Plan!$I$11*K6-C6-MAX(D6-J6,0) -> 350 | C19: Exactly the floor: cash read before quarter 7 saw nothing, so a rule that reads cash saves nothing
A20: Volume I's joint check: the margin absorbs | B20: =I5 -> 131.95038 | C20: All of quarter 7's margin
A21: breach under the law (engine) | B21: =AA5 -> 0.17388 | C21: 17.4 percent: its set left out the deviations, which alone breach 8.4 percent
A23: Change D, S or the cap in the blue cells: the package, its cost and the binding quarter recompute. The chances need Chapter 9's paths and stay the engine's.

Sheet Graded
A1: The offices' words cut by cut, the graded price, and the max-min choice (Theorem 10.2; Proposition 10.2; Figure 10.1; Worked Example 10.1, Step 3; AXIOM Lab 2.10, step 2)
A2: Cut at alpha: D = 200 - 150 alpha, S = 300 - 180 alpha (Theorem 10.2(i)); necessity of safety 1 - alpha (Theorem 10.2(ii)); the board's goal (20 - cost)/15, clipped to [0, 1]; the max-min choice maximizes the smaller of the goal and the necessity (Theorem 10.2(iii)), on the book's grid of 0.01.
A5: Cut alpha | B5: D | C5: S | D5: Delay | E5: Margin absorbs | F5: Line | G5: Delay | H5: Cost | I5: Goal for cost | J5: Necessity of safety | K5: Level: min(goal, necessity) | L5: Paths in the set (engine) | M5: Breach under the law (engine) | N5: Fresh paths (engine) | O5: Meets 5%: alpha | P5: Holds 95%: alpha | Q5: 'Very cheap': level | R5: 'Somewhat cheap': level
A6: 0 | B6: =DNever-(DNever-DUsual)*A6 -> 200 | C6: =SNever-(SNever-SPlaus)*A6 -> 300 | D6: =MAX(0,(B6-Plan!$H$5)/Plan!$I$5,(B6-Plan!$H$6)/Plan!$I$6,(B6-Plan!$H$7)/Plan!$I$7,(B6-Plan!$H$8)/Plan!$I$8,(B6-Plan!$H$9)/Plan!$I$9,(B6-Plan!$H$10)/Plan!$I$10,(B6-Plan!$H$11)/Plan!$I$11,(B6-Plan!$H$12)/Plan!$I$12,(B6-Plan!$H$13)/Plan!$I$13,(B6-Plan!$H$14)/Plan!$I$14,(B6-Plan!$H$15)/Plan!$I$15,(B6-Plan!$H$16)/Plan!$I$16) -> 2.7966413 | E6: =MIN(C6,Plan!$H$5-B6+Plan!$I$5*D6,Plan!$H$6-B6+Plan!$I$6*D6,Plan!$H$7-B6+Plan!$I$7*D6,Plan!$H$8-B6+Plan!$I$8*D6,Plan!$H$9-B6+Plan!$I$9*D6,Plan!$H$10-B6+Plan!$I$10*D6,Plan!$H$11-B6+Plan!$I$11*D6,Plan!$H$12-B6+Plan!$I$12*D6,Plan!$H$13-B6+Plan!$I$13*D6,Plan!$H$14-B6+Plan!$I$14*D6,Plan!$H$15-B6+Plan!$I$15*D6,Plan!$H$16-B6+Plan!$I$16*D6) -> 0 | F6: =C6-E6 -> 300 | G6: =D6 -> 2.7966413 | H6: =Fee*F6+VQ*G6 -> 31.37313 | I6: =MAX(0,MIN(1,(GNone-H6)/(GNone-GFull))) -> 0 | J6: =1-A6 -> 1 | K6: =MIN(I6,J6) -> 0 | L6: 0.95581 | M6: 0.00393 | N6: 0.00394 | O6: =IF(M6<=Alpha,A6,-1) -> 0 | P6: =IF(L6>=0.95,A6,-1) -> 0 | Q6: =MIN(I6^2,J6) -> 0 | R6: =MIN(SQRT(I6),J6) -> 0 | T6: Max-min level | U6: =MAX(K6:K106) -> 0.62 | V6: 0.62
A7: 0.01 | B7: =DNever-(DNever-DUsual)*A7 -> 198.5 | C7: =SNever-(SNever-SPlaus)*A7 -> 298.2 | D7: =MAX(0,(B7-Plan!$H$5)/Plan!$I$5,(B7-Plan!$H$6)/Plan!$I$6,(B7-Plan!$H$7)/Plan!$I$7,(B7-Plan!$H$8)/Plan!$I$8,(B7-Plan!$H$9)/Plan!$I$9,(B7-Plan!$H$10)/Plan!$I$10,(B7-Plan!$H$11)/Plan!$I$11,(B7-Plan!$H$12)/Plan!$I$12,(B7-Plan!$H$13)/Plan!$I$13,(B7-Plan!$H$14)/Plan!$I$14,(B7-Plan!$H$15)/Plan!$I$15,(B7-Plan!$H$16)/Plan!$I$16) -> 2.7338348 | E7: =MIN(C7,Plan!$H$5-B7+Plan!$I$5*D7,Plan!$H$6-B7+Plan!$I$6*D7,Plan!$H$7-B7+Plan!$I$7*D7,Plan!$H$8-B7+Plan!$I$8*D7,Plan!$H$9-B7+Plan!$I$9*D7,Plan!$H$10-B7+Plan!$I$10*D7,Plan!$H$11-B7+Plan!$I$11*D7,Plan!$H$12-B7+Plan!$I$12*D7,Plan!$H$13-B7+Plan!$I$13*D7,Plan!$H$14-B7+Plan!$I$14*D7,Plan!$H$15-B7+Plan!$I$15*D7,Plan!$H$16-B7+Plan!$I$16*D7) -> 0 | F7: =C7-E7 -> 298.2 | G7: =D7 -> 2.7338348 | H7: =Fee*F7+VQ*G7 -> 30.816678 | I7: =MAX(0,MIN(1,(GNone-H7)/(GNone-GFull))) -> 0 | J7: =1-A7 -> 0.99 | K7: =MIN(I7,J7) -> 0 | L7: 0.9552 | M7: 0.00423 | N7: 0.00418 | O7: =IF(M7<=Alpha,A7,-1) -> 0.01 | P7: =IF(L7>=0.95,A7,-1) -> 0.01 | Q7: =MIN(I7^2,J7) -> 0 | R7: =MIN(SQRT(I7),J7) -> 0 | T7: at the cut | U7: =INDEX(A6:A106,MATCH(U6,K6:K106,0)) -> 0.38 | V7: 0.38 (ties: the larger cut)
A8: 0.02 | B8: =DNever-(DNever-DUsual)*A8 -> 197 | C8: =SNever-(SNever-SPlaus)*A8 -> 296.4 | D8: =MAX(0,(B8-Plan!$H$5)/Plan!$I$5,(B8-Plan!$H$6)/Plan!$I$6,(B8-Plan!$H$7)/Plan!$I$7,(B8-Plan!$H$8)/Plan!$I$8,(B8-Plan!$H$9)/Plan!$I$9,(B8-Plan!$H$10)/Plan!$I$10,(B8-Plan!$H$11)/Plan!$I$11,(B8-Plan!$H$12)/Plan!$I$12,(B8-Plan!$H$13)/Plan!$I$13,(B8-Plan!$H$14)/Plan!$I$14,(B8-Plan!$H$15)/Plan!$I$15,(B8-Plan!$H$16)/Plan!$I$16) -> 2.6710283 | E8: =MIN(C8,Plan!$H$5-B8+Plan!$I$5*D8,Plan!$H$6-B8+Plan!$I$6*D8,Plan!$H$7-B8+Plan!$I$7*D8,Plan!$H$8-B8+Plan!$I$8*D8,Plan!$H$9-B8+Plan!$I$9*D8,Plan!$H$10-B8+Plan!$I$10*D8,Plan!$H$11-B8+Plan!$I$11*D8,Plan!$H$12-B8+Plan!$I$12*D8,Plan!$H$13-B8+Plan!$I$13*D8,Plan!$H$14-B8+Plan!$I$14*D8,Plan!$H$15-B8+Plan!$I$15*D8,Plan!$H$16-B8+Plan!$I$16*D8) -> 0 | F8: =C8-E8 -> 296.4 | G8: =D8 -> 2.6710283 | H8: =Fee*F8+VQ*G8 -> 30.260226 | I8: =MAX(0,MIN(1,(GNone-H8)/(GNone-GFull))) -> 0 | J8: =1-A8 -> 0.98 | K8: =MIN(I8,J8) -> 0 | L8: 0.9546 | M8: 0.00459 | N8: 0.00461 | O8: =IF(M8<=Alpha,A8,-1) -> 0.02 | P8: =IF(L8>=0.95,A8,-1) -> 0.02 | Q8: =MIN(I8^2,J8) -> 0 | R8: =MIN(SQRT(I8),J8) -> 0 | T8: necessity of safety | U8: =1-U7 -> 0.62 | V8: 0.62
A9: 0.03 | B9: =DNever-(DNever-DUsual)*A9 -> 195.5 | C9: =SNever-(SNever-SPlaus)*A9 -> 294.6 | D9: =MAX(0,(B9-Plan!$H$5)/Plan!$I$5,(B9-Plan!$H$6)/Plan!$I$6,(B9-Plan!$H$7)/Plan!$I$7,(B9-Plan!$H$8)/Plan!$I$8,(B9-Plan!$H$9)/Plan!$I$9,(B9-Plan!$H$10)/Plan!$I$10,(B9-Plan!$H$11)/Plan!$I$11,(B9-Plan!$H$12)/Plan!$I$12,(B9-Plan!$H$13)/Plan!$I$13,(B9-Plan!$H$14)/Plan!$I$14,(B9-Plan!$H$15)/Plan!$I$15,(B9-Plan!$H$16)/Plan!$I$16) -> 2.6082218 | E9: =MIN(C9,Plan!$H$5-B9+Plan!$I$5*D9,Plan!$H$6-B9+Plan!$I$6*D9,Plan!$H$7-B9+Plan!$I$7*D9,Plan!$H$8-B9+Plan!$I$8*D9,Plan!$H$9-B9+Plan!$I$9*D9,Plan!$H$10-B9+Plan!$I$10*D9,Plan!$H$11-B9+Plan!$I$11*D9,Plan!$H$12-B9+Plan!$I$12*D9,Plan!$H$13-B9+Plan!$I$13*D9,Plan!$H$14-B9+Plan!$I$14*D9,Plan!$H$15-B9+Plan!$I$15*D9,Plan!$H$16-B9+Plan!$I$16*D9) -> 0 | F9: =C9-E9 -> 294.6 | G9: =D9 -> 2.6082218 | H9: =Fee*F9+VQ*G9 -> 29.703774 | I9: =MAX(0,MIN(1,(GNone-H9)/(GNone-GFull))) -> 0 | J9: =1-A9 -> 0.97 | K9: =MIN(I9,J9) -> 0 | L9: 0.95389 | M9: 0.00506 | N9: 0.00498 | O9: =IF(M9<=Alpha,A9,-1) -> 0.03 | P9: =IF(L9>=0.95,A9,-1) -> 0.03 | Q9: =MIN(I9^2,J9) -> 0 | R9: =MIN(SQRT(I9),J9) -> 0 | T9: goal for its cost | U9: =INDEX(I6:I106,MATCH(U7,A6:A106,0)) -> 0.63047119 | V9: 0.630
A10: 0.04 | B10: =DNever-(DNever-DUsual)*A10 -> 194 | C10: =SNever-(SNever-SPlaus)*A10 -> 292.8 | D10: =MAX(0,(B10-Plan!$H$5)/Plan!$I$5,(B10-Plan!$H$6)/Plan!$I$6,(B10-Plan!$H$7)/Plan!$I$7,(B10-Plan!$H$8)/Plan!$I$8,(B10-Plan!$H$9)/Plan!$I$9,(B10-Plan!$H$10)/Plan!$I$10,(B10-Plan!$H$11)/Plan!$I$11,(B10-Plan!$H$12)/Plan!$I$12,(B10-Plan!$H$13)/Plan!$I$13,(B10-Plan!$H$14)/Plan!$I$14,(B10-Plan!$H$15)/Plan!$I$15,(B10-Plan!$H$16)/Plan!$I$16) -> 2.5454152 | E10: =MIN(C10,Plan!$H$5-B10+Plan!$I$5*D10,Plan!$H$6-B10+Plan!$I$6*D10,Plan!$H$7-B10+Plan!$I$7*D10,Plan!$H$8-B10+Plan!$I$8*D10,Plan!$H$9-B10+Plan!$I$9*D10,Plan!$H$10-B10+Plan!$I$10*D10,Plan!$H$11-B10+Plan!$I$11*D10,Plan!$H$12-B10+Plan!$I$12*D10,Plan!$H$13-B10+Plan!$I$13*D10,Plan!$H$14-B10+Plan!$I$14*D10,Plan!$H$15-B10+Plan!$I$15*D10,Plan!$H$16-B10+Plan!$I$16*D10) -> 0 | F10: =C10-E10 -> 292.8 | G10: =D10 -> 2.5454152 | H10: =Fee*F10+VQ*G10 -> 29.147322 | I10: =MAX(0,MIN(1,(GNone-H10)/(GNone-GFull))) -> 0 | J10: =1-A10 -> 0.96 | K10: =MIN(I10,J10) -> 0 | L10: 0.95319 | M10: 0.00557 | N10: 0.00539 | O10: =IF(M10<=Alpha,A10,-1) -> 0.04 | P10: =IF(L10>=0.95,A10,-1) -> 0.04 | Q10: =MIN(I10^2,J10) -> 0 | R10: =MIN(SQRT(I10),J10) -> 0 | T10: cost | U10: =INDEX(H6:H106,MATCH(U7,A6:A106,0)) -> 10.542932 | V10: $10.54 million; package on Robust
A11: 0.05 | B11: =DNever-(DNever-DUsual)*A11 -> 192.5 | C11: =SNever-(SNever-SPlaus)*A11 -> 291 | D11: =MAX(0,(B11-Plan!$H$5)/Plan!$I$5,(B11-Plan!$H$6)/Plan!$I$6,(B11-Plan!$H$7)/Plan!$I$7,(B11-Plan!$H$8)/Plan!$I$8,(B11-Plan!$H$9)/Plan!$I$9,(B11-Plan!$H$10)/Plan!$I$10,(B11-Plan!$H$11)/Plan!$I$11,(B11-Plan!$H$12)/Plan!$I$12,(B11-Plan!$H$13)/Plan!$I$13,(B11-Plan!$H$14)/Plan!$I$14,(B11-Plan!$H$15)/Plan!$I$15,(B11-Plan!$H$16)/Plan!$I$16) -> 2.4826087 | E11: =MIN(C11,Plan!$H$5-B11+Plan!$I$5*D11,Plan!$H$6-B11+Plan!$I$6*D11,Plan!$H$7-B11+Plan!$I$7*D11,Plan!$H$8-B11+Plan!$I$8*D11,Plan!$H$9-B11+Plan!$I$9*D11,Plan!$H$10-B11+Plan!$I$10*D11,Plan!$H$11-B11+Plan!$I$11*D11,Plan!$H$12-B11+Plan!$I$12*D11,Plan!$H$13-B11+Plan!$I$13*D11,Plan!$H$14-B11+Plan!$I$14*D11,Plan!$H$15-B11+Plan!$I$15*D11,Plan!$H$16-B11+Plan!$I$16*D11) -> 0 | F11: =C11-E11 -> 291 | G11: =D11 -> 2.4826087 | H11: =Fee*F11+VQ*G11 -> 28.59087 | I11: =MAX(0,MIN(1,(GNone-H11)/(GNone-GFull))) -> 0 | J11: =1-A11 -> 0.95 | K11: =MIN(I11,J11) -> 0 | L11: 0.95273 | M11: 0.0061 | N11: 0.00583 | O11: =IF(M11<=Alpha,A11,-1) -> 0.05 | P11: =IF(L11>=0.95,A11,-1) -> 0.05 | Q11: =MIN(I11^2,J11) -> 0 | R11: =MIN(SQRT(I11),J11) -> 0
A12: 0.06 | B12: =DNever-(DNever-DUsual)*A12 -> 191 | C12: =SNever-(SNever-SPlaus)*A12 -> 289.2 | D12: =MAX(0,(B12-Plan!$H$5)/Plan!$I$5,(B12-Plan!$H$6)/Plan!$I$6,(B12-Plan!$H$7)/Plan!$I$7,(B12-Plan!$H$8)/Plan!$I$8,(B12-Plan!$H$9)/Plan!$I$9,(B12-Plan!$H$10)/Plan!$I$10,(B12-Plan!$H$11)/Plan!$I$11,(B12-Plan!$H$12)/Plan!$I$12,(B12-Plan!$H$13)/Plan!$I$13,(B12-Plan!$H$14)/Plan!$I$14,(B12-Plan!$H$15)/Plan!$I$15,(B12-Plan!$H$16)/Plan!$I$16) -> 2.4198022 | E12: =MIN(C12,Plan!$H$5-B12+Plan!$I$5*D12,Plan!$H$6-B12+Plan!$I$6*D12,Plan!$H$7-B12+Plan!$I$7*D12,Plan!$H$8-B12+Plan!$I$8*D12,Plan!$H$9-B12+Plan!$I$9*D12,Plan!$H$10-B12+Plan!$I$10*D12,Plan!$H$11-B12+Plan!$I$11*D12,Plan!$H$12-B12+Plan!$I$12*D12,Plan!$H$13-B12+Plan!$I$13*D12,Plan!$H$14-B12+Plan!$I$14*D12,Plan!$H$15-B12+Plan!$I$15*D12,Plan!$H$16-B12+Plan!$I$16*D12) -> 0 | F12: =C12-E12 -> 289.2 | G12: =D12 -> 2.4198022 | H12: =Fee*F12+VQ*G12 -> 28.034418 | I12: =MAX(0,MIN(1,(GNone-H12)/(GNone-GFull))) -> 0 | J12: =1-A12 -> 0.94 | K12: =MIN(I12,J12) -> 0 | L12: 0.9519 | M12: 0.00659 | N12: 0.0064 | O12: =IF(M12<=Alpha,A12,-1) -> 0.06 | P12: =IF(L12>=0.95,A12,-1) -> 0.06 | Q12: =MIN(I12^2,J12) -> 0 | R12: =MIN(SQRT(I12),J12) -> 0 | T12: Cheapest cut meeting 5% under the law | U12: =MAX(O6:O106) -> 0.35 | V12: 0.35: $12.17 million
A13: 0.07 | B13: =DNever-(DNever-DUsual)*A13 -> 189.5 | C13: =SNever-(SNever-SPlaus)*A13 -> 287.4 | D13: =MAX(0,(B13-Plan!$H$5)/Plan!$I$5,(B13-Plan!$H$6)/Plan!$I$6,(B13-Plan!$H$7)/Plan!$I$7,(B13-Plan!$H$8)/Plan!$I$8,(B13-Plan!$H$9)/Plan!$I$9,(B13-Plan!$H$10)/Plan!$I$10,(B13-Plan!$H$11)/Plan!$I$11,(B13-Plan!$H$12)/Plan!$I$12,(B13-Plan!$H$13)/Plan!$I$13,(B13-Plan!$H$14)/Plan!$I$14,(B13-Plan!$H$15)/Plan!$I$15,(B13-Plan!$H$16)/Plan!$I$16) -> 2.3569957 | E13: =MIN(C13,Plan!$H$5-B13+Plan!$I$5*D13,Plan!$H$6-B13+Plan!$I$6*D13,Plan!$H$7-B13+Plan!$I$7*D13,Plan!$H$8-B13+Plan!$I$8*D13,Plan!$H$9-B13+Plan!$I$9*D13,Plan!$H$10-B13+Plan!$I$10*D13,Plan!$H$11-B13+Plan!$I$11*D13,Plan!$H$12-B13+Plan!$I$12*D13,Plan!$H$13-B13+Plan!$I$13*D13,Plan!$H$14-B13+Plan!$I$14*D13,Plan!$H$15-B13+Plan!$I$15*D13,Plan!$H$16-B13+Plan!$I$16*D13) -> 0 | F13: =C13-E13 -> 287.4 | G13: =D13 -> 2.3569957 | H13: =Fee*F13+VQ*G13 -> 27.477966 | I13: =MAX(0,MIN(1,(GNone-H13)/(GNone-GFull))) -> 0 | J13: =1-A13 -> 0.93 | K13: =MIN(I13,J13) -> 0 | L13: 0.95109 | M13: 0.007 | N13: 0.00685 | O13: =IF(M13<=Alpha,A13,-1) -> 0.07 | P13: =IF(L13>=0.95,A13,-1) -> 0.07 | Q13: =MIN(I13^2,J13) -> 0 | R13: =MIN(SQRT(I13),J13) -> 0 | T13: First cut holding 95% of the paths | U13: =MAX(P6:P106) -> 0.08 | V13: 0.08: $26.92 million (Theorem 10.1(iii))
A14: 0.08 | B14: =DNever-(DNever-DUsual)*A14 -> 188 | C14: =SNever-(SNever-SPlaus)*A14 -> 285.6 | D14: =MAX(0,(B14-Plan!$H$5)/Plan!$I$5,(B14-Plan!$H$6)/Plan!$I$6,(B14-Plan!$H$7)/Plan!$I$7,(B14-Plan!$H$8)/Plan!$I$8,(B14-Plan!$H$9)/Plan!$I$9,(B14-Plan!$H$10)/Plan!$I$10,(B14-Plan!$H$11)/Plan!$I$11,(B14-Plan!$H$12)/Plan!$I$12,(B14-Plan!$H$13)/Plan!$I$13,(B14-Plan!$H$14)/Plan!$I$14,(B14-Plan!$H$15)/Plan!$I$15,(B14-Plan!$H$16)/Plan!$I$16) -> 2.2941892 | E14: =MIN(C14,Plan!$H$5-B14+Plan!$I$5*D14,Plan!$H$6-B14+Plan!$I$6*D14,Plan!$H$7-B14+Plan!$I$7*D14,Plan!$H$8-B14+Plan!$I$8*D14,Plan!$H$9-B14+Plan!$I$9*D14,Plan!$H$10-B14+Plan!$I$10*D14,Plan!$H$11-B14+Plan!$I$11*D14,Plan!$H$12-B14+Plan!$I$12*D14,Plan!$H$13-B14+Plan!$I$13*D14,Plan!$H$14-B14+Plan!$I$14*D14,Plan!$H$15-B14+Plan!$I$15*D14,Plan!$H$16-B14+Plan!$I$16*D14) -> 0 | F14: =C14-E14 -> 285.6 | G14: =D14 -> 2.2941892 | H14: =Fee*F14+VQ*G14 -> 26.921513 | I14: =MAX(0,MIN(1,(GNone-H14)/(GNone-GFull))) -> 0 | J14: =1-A14 -> 0.92 | K14: =MIN(I14,J14) -> 0 | L14: 0.95021 | M14: 0.00757 | N14: 0.00731 | O14: =IF(M14<=Alpha,A14,-1) -> 0.08 | P14: =IF(L14>=0.95,A14,-1) -> 0.08 | Q14: =MIN(I14^2,J14) -> 0 | R14: =MIN(SQRT(I14),J14) -> 0
A15: 0.09 | B15: =DNever-(DNever-DUsual)*A15 -> 186.5 | C15: =SNever-(SNever-SPlaus)*A15 -> 283.8 | D15: =MAX(0,(B15-Plan!$H$5)/Plan!$I$5,(B15-Plan!$H$6)/Plan!$I$6,(B15-Plan!$H$7)/Plan!$I$7,(B15-Plan!$H$8)/Plan!$I$8,(B15-Plan!$H$9)/Plan!$I$9,(B15-Plan!$H$10)/Plan!$I$10,(B15-Plan!$H$11)/Plan!$I$11,(B15-Plan!$H$12)/Plan!$I$12,(B15-Plan!$H$13)/Plan!$I$13,(B15-Plan!$H$14)/Plan!$I$14,(B15-Plan!$H$15)/Plan!$I$15,(B15-Plan!$H$16)/Plan!$I$16) -> 2.2313827 | E15: =MIN(C15,Plan!$H$5-B15+Plan!$I$5*D15,Plan!$H$6-B15+Plan!$I$6*D15,Plan!$H$7-B15+Plan!$I$7*D15,Plan!$H$8-B15+Plan!$I$8*D15,Plan!$H$9-B15+Plan!$I$9*D15,Plan!$H$10-B15+Plan!$I$10*D15,Plan!$H$11-B15+Plan!$I$11*D15,Plan!$H$12-B15+Plan!$I$12*D15,Plan!$H$13-B15+Plan!$I$13*D15,Plan!$H$14-B15+Plan!$I$14*D15,Plan!$H$15-B15+Plan!$I$15*D15,Plan!$H$16-B15+Plan!$I$16*D15) -> 0 | F15: =C15-E15 -> 283.8 | G15: =D15 -> 2.2313827 | H15: =Fee*F15+VQ*G15 -> 26.365061 | I15: =MAX(0,MIN(1,(GNone-H15)/(GNone-GFull))) -> 0 | J15: =1-A15 -> 0.91 | K15: =MIN(I15,J15) -> 0 | L15: 0.94934 | M15: 0.00809 | N15: 0.00782 | O15: =IF(M15<=Alpha,A15,-1) -> 0.09 | P15: =IF(L15>=0.95,A15,-1) -> -1 | Q15: =MIN(I15^2,J15) -> 0 | R15: =MIN(SQRT(I15),J15) -> 0 | T15: Graded price at possibility 1 | U15: =H106 -> 1.1414885 | V15: $1.14 million
A16: 0.1 | B16: =DNever-(DNever-DUsual)*A16 -> 185 | C16: =SNever-(SNever-SPlaus)*A16 -> 282 | D16: =MAX(0,(B16-Plan!$H$5)/Plan!$I$5,(B16-Plan!$H$6)/Plan!$I$6,(B16-Plan!$H$7)/Plan!$I$7,(B16-Plan!$H$8)/Plan!$I$8,(B16-Plan!$H$9)/Plan!$I$9,(B16-Plan!$H$10)/Plan!$I$10,(B16-Plan!$H$11)/Plan!$I$11,(B16-Plan!$H$12)/Plan!$I$12,(B16-Plan!$H$13)/Plan!$I$13,(B16-Plan!$H$14)/Plan!$I$14,(B16-Plan!$H$15)/Plan!$I$15,(B16-Plan!$H$16)/Plan!$I$16) -> 2.1685762 | E16: =MIN(C16,Plan!$H$5-B16+Plan!$I$5*D16,Plan!$H$6-B16+Plan!$I$6*D16,Plan!$H$7-B16+Plan!$I$7*D16,Plan!$H$8-B16+Plan!$I$8*D16,Plan!$H$9-B16+Plan!$I$9*D16,Plan!$H$10-B16+Plan!$I$10*D16,Plan!$H$11-B16+Plan!$I$11*D16,Plan!$H$12-B16+Plan!$I$12*D16,Plan!$H$13-B16+Plan!$I$13*D16,Plan!$H$14-B16+Plan!$I$14*D16,Plan!$H$15-B16+Plan!$I$15*D16,Plan!$H$16-B16+Plan!$I$16*D16) -> 0 | F16: =C16-E16 -> 282 | G16: =D16 -> 2.1685762 | H16: =Fee*F16+VQ*G16 -> 25.808609 | I16: =MAX(0,MIN(1,(GNone-H16)/(GNone-GFull))) -> 0 | J16: =1-A16 -> 0.9 | K16: =MIN(I16,J16) -> 0 | L16: 0.94837 | M16: 0.00868 | N16: 0.00835 | O16: =IF(M16<=Alpha,A16,-1) -> 0.1 | P16: =IF(L16>=0.95,A16,-1) -> -1 | Q16: =MIN(I16^2,J16) -> 0 | R16: =MIN(SQRT(I16),J16) -> 0 | T16: at possibility 0 | U16: =H6 -> 31.37313 | V16: $31.37 million
A17: 0.11 | B17: =DNever-(DNever-DUsual)*A17 -> 183.5 | C17: =SNever-(SNever-SPlaus)*A17 -> 280.2 | D17: =MAX(0,(B17-Plan!$H$5)/Plan!$I$5,(B17-Plan!$H$6)/Plan!$I$6,(B17-Plan!$H$7)/Plan!$I$7,(B17-Plan!$H$8)/Plan!$I$8,(B17-Plan!$H$9)/Plan!$I$9,(B17-Plan!$H$10)/Plan!$I$10,(B17-Plan!$H$11)/Plan!$I$11,(B17-Plan!$H$12)/Plan!$I$12,(B17-Plan!$H$13)/Plan!$I$13,(B17-Plan!$H$14)/Plan!$I$14,(B17-Plan!$H$15)/Plan!$I$15,(B17-Plan!$H$16)/Plan!$I$16) -> 2.1057696 | E17: =MIN(C17,Plan!$H$5-B17+Plan!$I$5*D17,Plan!$H$6-B17+Plan!$I$6*D17,Plan!$H$7-B17+Plan!$I$7*D17,Plan!$H$8-B17+Plan!$I$8*D17,Plan!$H$9-B17+Plan!$I$9*D17,Plan!$H$10-B17+Plan!$I$10*D17,Plan!$H$11-B17+Plan!$I$11*D17,Plan!$H$12-B17+Plan!$I$12*D17,Plan!$H$13-B17+Plan!$I$13*D17,Plan!$H$14-B17+Plan!$I$14*D17,Plan!$H$15-B17+Plan!$I$15*D17,Plan!$H$16-B17+Plan!$I$16*D17) -> 0 | F17: =C17-E17 -> 280.2 | G17: =D17 -> 2.1057696 | H17: =Fee*F17+VQ*G17 -> 25.252157 | I17: =MAX(0,MIN(1,(GNone-H17)/(GNone-GFull))) -> 0 | J17: =1-A17 -> 0.89 | K17: =MIN(I17,J17) -> 0 | L17: 0.94735 | M17: 0.00944 | N17: 0.00896 | O17: =IF(M17<=Alpha,A17,-1) -> 0.11 | P17: =IF(L17>=0.95,A17,-1) -> -1 | Q17: =MIN(I17^2,J17) -> 0 | R17: =MIN(SQRT(I17),J17) -> 0 | T17: its 0.5-cut (Proposition 10.2(i)) | U17: =H56 -> 6.0914885 | V17: Step 2's crisp answer, $6.09 million
A18: 0.12 | B18: =DNever-(DNever-DUsual)*A18 -> 182 | C18: =SNever-(SNever-SPlaus)*A18 -> 278.4 | D18: =MAX(0,(B18-Plan!$H$5)/Plan!$I$5,(B18-Plan!$H$6)/Plan!$I$6,(B18-Plan!$H$7)/Plan!$I$7,(B18-Plan!$H$8)/Plan!$I$8,(B18-Plan!$H$9)/Plan!$I$9,(B18-Plan!$H$10)/Plan!$I$10,(B18-Plan!$H$11)/Plan!$I$11,(B18-Plan!$H$12)/Plan!$I$12,(B18-Plan!$H$13)/Plan!$I$13,(B18-Plan!$H$14)/Plan!$I$14,(B18-Plan!$H$15)/Plan!$I$15,(B18-Plan!$H$16)/Plan!$I$16) -> 2.0429631 | E18: =MIN(C18,Plan!$H$5-B18+Plan!$I$5*D18,Plan!$H$6-B18+Plan!$I$6*D18,Plan!$H$7-B18+Plan!$I$7*D18,Plan!$H$8-B18+Plan!$I$8*D18,Plan!$H$9-B18+Plan!$I$9*D18,Plan!$H$10-B18+Plan!$I$10*D18,Plan!$H$11-B18+Plan!$I$11*D18,Plan!$H$12-B18+Plan!$I$12*D18,Plan!$H$13-B18+Plan!$I$13*D18,Plan!$H$14-B18+Plan!$I$14*D18,Plan!$H$15-B18+Plan!$I$15*D18,Plan!$H$16-B18+Plan!$I$16*D18) -> 0 | F18: =C18-E18 -> 278.4 | G18: =D18 -> 2.0429631 | H18: =Fee*F18+VQ*G18 -> 24.695705 | I18: =MAX(0,MIN(1,(GNone-H18)/(GNone-GFull))) -> 0 | J18: =1-A18 -> 0.88 | K18: =MIN(I18,J18) -> 0 | L18: 0.94639 | M18: 0.0101 | N18: 0.00974 | O18: =IF(M18<=Alpha,A18,-1) -> 0.12 | P18: =IF(L18>=0.95,A18,-1) -> -1 | Q18: =MIN(I18^2,J18) -> 0 | R18: =MIN(SQRT(I18),J18) -> 0 | T18: the crisp set's package (Robust) | U18: =Robust!L6 -> 6.0914885
A19: 0.13 | B19: =DNever-(DNever-DUsual)*A19 -> 180.5 | C19: =SNever-(SNever-SPlaus)*A19 -> 276.6 | D19: =MAX(0,(B19-Plan!$H$5)/Plan!$I$5,(B19-Plan!$H$6)/Plan!$I$6,(B19-Plan!$H$7)/Plan!$I$7,(B19-Plan!$H$8)/Plan!$I$8,(B19-Plan!$H$9)/Plan!$I$9,(B19-Plan!$H$10)/Plan!$I$10,(B19-Plan!$H$11)/Plan!$I$11,(B19-Plan!$H$12)/Plan!$I$12,(B19-Plan!$H$13)/Plan!$I$13,(B19-Plan!$H$14)/Plan!$I$14,(B19-Plan!$H$15)/Plan!$I$15,(B19-Plan!$H$16)/Plan!$I$16) -> 1.9801566 | E19: =MIN(C19,Plan!$H$5-B19+Plan!$I$5*D19,Plan!$H$6-B19+Plan!$I$6*D19,Plan!$H$7-B19+Plan!$I$7*D19,Plan!$H$8-B19+Plan!$I$8*D19,Plan!$H$9-B19+Plan!$I$9*D19,Plan!$H$10-B19+Plan!$I$10*D19,Plan!$H$11-B19+Plan!$I$11*D19,Plan!$H$12-B19+Plan!$I$12*D19,Plan!$H$13-B19+Plan!$I$13*D19,Plan!$H$14-B19+Plan!$I$14*D19,Plan!$H$15-B19+Plan!$I$15*D19,Plan!$H$16-B19+Plan!$I$16*D19) -> 0 | F19: =C19-E19 -> 276.6 | G19: =D19 -> 1.9801566 | H19: =Fee*F19+VQ*G19 -> 24.139253 | I19: =MAX(0,MIN(1,(GNone-H19)/(GNone-GFull))) -> 0 | J19: =1-A19 -> 0.87 | K19: =MIN(I19,J19) -> 0 | L19: 0.94519 | M19: 0.01074 | N19: 0.01051 | O19: =IF(M19<=Alpha,A19,-1) -> 0.13 | P19: =IF(L19>=0.95,A19,-1) -> -1 | Q19: =MIN(I19^2,J19) -> 0 | R19: =MIN(SQRT(I19),J19) -> 0 | T19: Steps where the price falls as the set grows | U19: =SUMPRODUCT((H7:H106>H6:H105+0.000000001)*1) -> 0 | V19: None (Theorem 10.2(ii))
A20: 0.14 | B20: =DNever-(DNever-DUsual)*A20 -> 179 | C20: =SNever-(SNever-SPlaus)*A20 -> 274.8 | D20: =MAX(0,(B20-Plan!$H$5)/Plan!$I$5,(B20-Plan!$H$6)/Plan!$I$6,(B20-Plan!$H$7)/Plan!$I$7,(B20-Plan!$H$8)/Plan!$I$8,(B20-Plan!$H$9)/Plan!$I$9,(B20-Plan!$H$10)/Plan!$I$10,(B20-Plan!$H$11)/Plan!$I$11,(B20-Plan!$H$12)/Plan!$I$12,(B20-Plan!$H$13)/Plan!$I$13,(B20-Plan!$H$14)/Plan!$I$14,(B20-Plan!$H$15)/Plan!$I$15,(B20-Plan!$H$16)/Plan!$I$16) -> 1.9173501 | E20: =MIN(C20,Plan!$H$5-B20+Plan!$I$5*D20,Plan!$H$6-B20+Plan!$I$6*D20,Plan!$H$7-B20+Plan!$I$7*D20,Plan!$H$8-B20+Plan!$I$8*D20,Plan!$H$9-B20+Plan!$I$9*D20,Plan!$H$10-B20+Plan!$I$10*D20,Plan!$H$11-B20+Plan!$I$11*D20,Plan!$H$12-B20+Plan!$I$12*D20,Plan!$H$13-B20+Plan!$I$13*D20,Plan!$H$14-B20+Plan!$I$14*D20,Plan!$H$15-B20+Plan!$I$15*D20,Plan!$H$16-B20+Plan!$I$16*D20) -> 0 | F20: =C20-E20 -> 274.8 | G20: =D20 -> 1.9173501 | H20: =Fee*F20+VQ*G20 -> 23.582801 | I20: =MAX(0,MIN(1,(GNone-H20)/(GNone-GFull))) -> 0 | J20: =1-A20 -> 0.86 | K20: =MIN(I20,J20) -> 0 | L20: 0.94384 | M20: 0.01168 | N20: 0.01139 | O20: =IF(M20<=Alpha,A20,-1) -> 0.14 | P20: =IF(L20>=0.95,A20,-1) -> -1 | Q20: =MIN(I20^2,J20) -> 0 | R20: =MIN(SQRT(I20),J20) -> 0 | T20: Cuts whose chance exceeds the share of paths outside the set | U20: =SUMPRODUCT((M6:M106>1-L6:L106)*1) -> 0 | V20: None (Theorem 10.1(iii))
A21: 0.15 | B21: =DNever-(DNever-DUsual)*A21 -> 177.5 | C21: =SNever-(SNever-SPlaus)*A21 -> 273 | D21: =MAX(0,(B21-Plan!$H$5)/Plan!$I$5,(B21-Plan!$H$6)/Plan!$I$6,(B21-Plan!$H$7)/Plan!$I$7,(B21-Plan!$H$8)/Plan!$I$8,(B21-Plan!$H$9)/Plan!$I$9,(B21-Plan!$H$10)/Plan!$I$10,(B21-Plan!$H$11)/Plan!$I$11,(B21-Plan!$H$12)/Plan!$I$12,(B21-Plan!$H$13)/Plan!$I$13,(B21-Plan!$H$14)/Plan!$I$14,(B21-Plan!$H$15)/Plan!$I$15,(B21-Plan!$H$16)/Plan!$I$16) -> 1.8545436 | E21: =MIN(C21,Plan!$H$5-B21+Plan!$I$5*D21,Plan!$H$6-B21+Plan!$I$6*D21,Plan!$H$7-B21+Plan!$I$7*D21,Plan!$H$8-B21+Plan!$I$8*D21,Plan!$H$9-B21+Plan!$I$9*D21,Plan!$H$10-B21+Plan!$I$10*D21,Plan!$H$11-B21+Plan!$I$11*D21,Plan!$H$12-B21+Plan!$I$12*D21,Plan!$H$13-B21+Plan!$I$13*D21,Plan!$H$14-B21+Plan!$I$14*D21,Plan!$H$15-B21+Plan!$I$15*D21,Plan!$H$16-B21+Plan!$I$16*D21) -> 0 | F21: =C21-E21 -> 273 | G21: =D21 -> 1.8545436 | H21: =Fee*F21+VQ*G21 -> 23.026349 | I21: =MAX(0,MIN(1,(GNone-H21)/(GNone-GFull))) -> 0 | J21: =1-A21 -> 0.85 | K21: =MIN(I21,J21) -> 0 | L21: 0.94231 | M21: 0.01269 | N21: 0.01248 | O21: =IF(M21<=Alpha,A21,-1) -> 0.15 | P21: =IF(L21>=0.95,A21,-1) -> -1 | Q21: =MIN(I21^2,J21) -> 0 | R21: =MIN(SQRT(I21),J21) -> 0 | T21: Largest standard error of a chance (points) | U21: =100*SQRT(MAX(M6:M106)*(1-MAX(M6:M106))/NPaths) -> 0.12584862 | V21: Below 0.13 points
A22: 0.16 | B22: =DNever-(DNever-DUsual)*A22 -> 176 | C22: =SNever-(SNever-SPlaus)*A22 -> 271.2 | D22: =MAX(0,(B22-Plan!$H$5)/Plan!$I$5,(B22-Plan!$H$6)/Plan!$I$6,(B22-Plan!$H$7)/Plan!$I$7,(B22-Plan!$H$8)/Plan!$I$8,(B22-Plan!$H$9)/Plan!$I$9,(B22-Plan!$H$10)/Plan!$I$10,(B22-Plan!$H$11)/Plan!$I$11,(B22-Plan!$H$12)/Plan!$I$12,(B22-Plan!$H$13)/Plan!$I$13,(B22-Plan!$H$14)/Plan!$I$14,(B22-Plan!$H$15)/Plan!$I$15,(B22-Plan!$H$16)/Plan!$I$16) -> 1.7917371 | E22: =MIN(C22,Plan!$H$5-B22+Plan!$I$5*D22,Plan!$H$6-B22+Plan!$I$6*D22,Plan!$H$7-B22+Plan!$I$7*D22,Plan!$H$8-B22+Plan!$I$8*D22,Plan!$H$9-B22+Plan!$I$9*D22,Plan!$H$10-B22+Plan!$I$10*D22,Plan!$H$11-B22+Plan!$I$11*D22,Plan!$H$12-B22+Plan!$I$12*D22,Plan!$H$13-B22+Plan!$I$13*D22,Plan!$H$14-B22+Plan!$I$14*D22,Plan!$H$15-B22+Plan!$I$15*D22,Plan!$H$16-B22+Plan!$I$16*D22) -> 0 | F22: =C22-E22 -> 271.2 | G22: =D22 -> 1.7917371 | H22: =Fee*F22+VQ*G22 -> 22.469897 | I22: =MAX(0,MIN(1,(GNone-H22)/(GNone-GFull))) -> 0 | J22: =1-A22 -> 0.84 | K22: =MIN(I22,J22) -> 0 | L22: 0.94086 | M22: 0.0136 | N22: 0.01325 | O22: =IF(M22<=Alpha,A22,-1) -> 0.16 | P22: =IF(L22>=0.95,A22,-1) -> -1 | Q22: =MIN(I22^2,J22) -> 0 | R22: =MIN(SQRT(I22),J22) -> 0
A23: 0.17 | B23: =DNever-(DNever-DUsual)*A23 -> 174.5 | C23: =SNever-(SNever-SPlaus)*A23 -> 269.4 | D23: =MAX(0,(B23-Plan!$H$5)/Plan!$I$5,(B23-Plan!$H$6)/Plan!$I$6,(B23-Plan!$H$7)/Plan!$I$7,(B23-Plan!$H$8)/Plan!$I$8,(B23-Plan!$H$9)/Plan!$I$9,(B23-Plan!$H$10)/Plan!$I$10,(B23-Plan!$H$11)/Plan!$I$11,(B23-Plan!$H$12)/Plan!$I$12,(B23-Plan!$H$13)/Plan!$I$13,(B23-Plan!$H$14)/Plan!$I$14,(B23-Plan!$H$15)/Plan!$I$15,(B23-Plan!$H$16)/Plan!$I$16) -> 1.7304104 | E23: =MIN(C23,Plan!$H$5-B23+Plan!$I$5*D23,Plan!$H$6-B23+Plan!$I$6*D23,Plan!$H$7-B23+Plan!$I$7*D23,Plan!$H$8-B23+Plan!$I$8*D23,Plan!$H$9-B23+Plan!$I$9*D23,Plan!$H$10-B23+Plan!$I$10*D23,Plan!$H$11-B23+Plan!$I$11*D23,Plan!$H$12-B23+Plan!$I$12*D23,Plan!$H$13-B23+Plan!$I$13*D23,Plan!$H$14-B23+Plan!$I$14*D23,Plan!$H$15-B23+Plan!$I$15*D23,Plan!$H$16-B23+Plan!$I$16*D23) -> 0 | F23: =C23-E23 -> 269.4 | G23: =D23 -> 1.7304104 | H23: =Fee*F23+VQ*G23 -> 21.925283 | I23: =MAX(0,MIN(1,(GNone-H23)/(GNone-GFull))) -> 0 | J23: =1-A23 -> 0.83 | K23: =MIN(I23,J23) -> 0 | L23: 0.93923 | M23: 0.01446 | N23: 0.01421 | O23: =IF(M23<=Alpha,A23,-1) -> 0.17 | P23: =IF(L23>=0.95,A23,-1) -> -1 | Q23: =MIN(I23^2,J23) -> 0 | R23: =MIN(SQRT(I23),J23) -> 0 | T23: Hedges: the level with a goal 'very cheap' | U23: =MAX(Q6:Q106) -> 0.58 | V23: The goal squared (the lab's illustration)
A24: 0.18 | B24: =DNever-(DNever-DUsual)*A24 -> 173 | C24: =SNever-(SNever-SPlaus)*A24 -> 267.6 | D24: =MAX(0,(B24-Plan!$H$5)/Plan!$I$5,(B24-Plan!$H$6)/Plan!$I$6,(B24-Plan!$H$7)/Plan!$I$7,(B24-Plan!$H$8)/Plan!$I$8,(B24-Plan!$H$9)/Plan!$I$9,(B24-Plan!$H$10)/Plan!$I$10,(B24-Plan!$H$11)/Plan!$I$11,(B24-Plan!$H$12)/Plan!$I$12,(B24-Plan!$H$13)/Plan!$I$13,(B24-Plan!$H$14)/Plan!$I$14,(B24-Plan!$H$15)/Plan!$I$15,(B24-Plan!$H$16)/Plan!$I$16) -> 1.6694083 | E24: =MIN(C24,Plan!$H$5-B24+Plan!$I$5*D24,Plan!$H$6-B24+Plan!$I$6*D24,Plan!$H$7-B24+Plan!$I$7*D24,Plan!$H$8-B24+Plan!$I$8*D24,Plan!$H$9-B24+Plan!$I$9*D24,Plan!$H$10-B24+Plan!$I$10*D24,Plan!$H$11-B24+Plan!$I$11*D24,Plan!$H$12-B24+Plan!$I$12*D24,Plan!$H$13-B24+Plan!$I$13*D24,Plan!$H$14-B24+Plan!$I$14*D24,Plan!$H$15-B24+Plan!$I$15*D24,Plan!$H$16-B24+Plan!$I$16*D24) -> 0 | F24: =C24-E24 -> 267.6 | G24: =D24 -> 1.6694083 | H24: =Fee*F24+VQ*G24 -> 21.383267 | I24: =MAX(0,MIN(1,(GNone-H24)/(GNone-GFull))) -> 0 | J24: =1-A24 -> 0.82 | K24: =MIN(I24,J24) -> 0 | L24: 0.93744 | M24: 0.01554 | N24: 0.01524 | O24: =IF(M24<=Alpha,A24,-1) -> 0.18 | P24: =IF(L24>=0.95,A24,-1) -> -1 | Q24: =MIN(I24^2,J24) -> 0 | R24: =MIN(SQRT(I24),J24) -> 0 | T24: with a goal 'somewhat cheap' | U24: =MAX(R6:R106) -> 0.67 | V24: The goal's square root
A25: 0.19 | B25: =DNever-(DNever-DUsual)*A25 -> 171.5 | C25: =SNever-(SNever-SPlaus)*A25 -> 265.8 | D25: =MAX(0,(B25-Plan!$H$5)/Plan!$I$5,(B25-Plan!$H$6)/Plan!$I$6,(B25-Plan!$H$7)/Plan!$I$7,(B25-Plan!$H$8)/Plan!$I$8,(B25-Plan!$H$9)/Plan!$I$9,(B25-Plan!$H$10)/Plan!$I$10,(B25-Plan!$H$11)/Plan!$I$11,(B25-Plan!$H$12)/Plan!$I$12,(B25-Plan!$H$13)/Plan!$I$13,(B25-Plan!$H$14)/Plan!$I$14,(B25-Plan!$H$15)/Plan!$I$15,(B25-Plan!$H$16)/Plan!$I$16) -> 1.6084062 | E25: =MIN(C25,Plan!$H$5-B25+Plan!$I$5*D25,Plan!$H$6-B25+Plan!$I$6*D25,Plan!$H$7-B25+Plan!$I$7*D25,Plan!$H$8-B25+Plan!$I$8*D25,Plan!$H$9-B25+Plan!$I$9*D25,Plan!$H$10-B25+Plan!$I$10*D25,Plan!$H$11-B25+Plan!$I$11*D25,Plan!$H$12-B25+Plan!$I$12*D25,Plan!$H$13-B25+Plan!$I$13*D25,Plan!$H$14-B25+Plan!$I$14*D25,Plan!$H$15-B25+Plan!$I$15*D25,Plan!$H$16-B25+Plan!$I$16*D25) -> 0 | F25: =C25-E25 -> 265.8 | G25: =D25 -> 1.6084062 | H25: =Fee*F25+VQ*G25 -> 20.84125 | I25: =MAX(0,MIN(1,(GNone-H25)/(GNone-GFull))) -> 0 | J25: =1-A25 -> 0.81 | K25: =MIN(I25,J25) -> 0 | L25: 0.9356 | M25: 0.01671 | N25: 0.01621 | O25: =IF(M25<=Alpha,A25,-1) -> 0.19 | P25: =IF(L25>=0.95,A25,-1) -> -1 | Q25: =MIN(I25^2,J25) -> 0 | R25: =MIN(SQRT(I25),J25) -> 0 | T25: a stronger goal can only lower the level: violations | U25: =IF(AND(U23<=U6,U6<=U24),0,1) -> 0 | V25: Proposition 10.2(iii)
A26: 0.2 | B26: =DNever-(DNever-DUsual)*A26 -> 170 | C26: =SNever-(SNever-SPlaus)*A26 -> 264 | D26: =MAX(0,(B26-Plan!$H$5)/Plan!$I$5,(B26-Plan!$H$6)/Plan!$I$6,(B26-Plan!$H$7)/Plan!$I$7,(B26-Plan!$H$8)/Plan!$I$8,(B26-Plan!$H$9)/Plan!$I$9,(B26-Plan!$H$10)/Plan!$I$10,(B26-Plan!$H$11)/Plan!$I$11,(B26-Plan!$H$12)/Plan!$I$12,(B26-Plan!$H$13)/Plan!$I$13,(B26-Plan!$H$14)/Plan!$I$14,(B26-Plan!$H$15)/Plan!$I$15,(B26-Plan!$H$16)/Plan!$I$16) -> 1.5474041 | E26: =MIN(C26,Plan!$H$5-B26+Plan!$I$5*D26,Plan!$H$6-B26+Plan!$I$6*D26,Plan!$H$7-B26+Plan!$I$7*D26,Plan!$H$8-B26+Plan!$I$8*D26,Plan!$H$9-B26+Plan!$I$9*D26,Plan!$H$10-B26+Plan!$I$10*D26,Plan!$H$11-B26+Plan!$I$11*D26,Plan!$H$12-B26+Plan!$I$12*D26,Plan!$H$13-B26+Plan!$I$13*D26,Plan!$H$14-B26+Plan!$I$14*D26,Plan!$H$15-B26+Plan!$I$15*D26,Plan!$H$16-B26+Plan!$I$16*D26) -> 0 | F26: =C26-E26 -> 264 | G26: =D26 -> 1.5474041 | H26: =Fee*F26+VQ*G26 -> 20.299233 | I26: =MAX(0,MIN(1,(GNone-H26)/(GNone-GFull))) -> 0 | J26: =1-A26 -> 0.8 | K26: =MIN(I26,J26) -> 0 | L26: 0.93368 | M26: 0.01785 | N26: 0.01752 | O26: =IF(M26<=Alpha,A26,-1) -> 0.2 | P26: =IF(L26>=0.95,A26,-1) -> -1 | Q26: =MIN(I26^2,J26) -> 0 | R26: =MIN(SQRT(I26),J26) -> 0
A27: 0.21 | B27: =DNever-(DNever-DUsual)*A27 -> 168.5 | C27: =SNever-(SNever-SPlaus)*A27 -> 262.2 | D27: =MAX(0,(B27-Plan!$H$5)/Plan!$I$5,(B27-Plan!$H$6)/Plan!$I$6,(B27-Plan!$H$7)/Plan!$I$7,(B27-Plan!$H$8)/Plan!$I$8,(B27-Plan!$H$9)/Plan!$I$9,(B27-Plan!$H$10)/Plan!$I$10,(B27-Plan!$H$11)/Plan!$I$11,(B27-Plan!$H$12)/Plan!$I$12,(B27-Plan!$H$13)/Plan!$I$13,(B27-Plan!$H$14)/Plan!$I$14,(B27-Plan!$H$15)/Plan!$I$15,(B27-Plan!$H$16)/Plan!$I$16) -> 1.486402 | E27: =MIN(C27,Plan!$H$5-B27+Plan!$I$5*D27,Plan!$H$6-B27+Plan!$I$6*D27,Plan!$H$7-B27+Plan!$I$7*D27,Plan!$H$8-B27+Plan!$I$8*D27,Plan!$H$9-B27+Plan!$I$9*D27,Plan!$H$10-B27+Plan!$I$10*D27,Plan!$H$11-B27+Plan!$I$11*D27,Plan!$H$12-B27+Plan!$I$12*D27,Plan!$H$13-B27+Plan!$I$13*D27,Plan!$H$14-B27+Plan!$I$14*D27,Plan!$H$15-B27+Plan!$I$15*D27,Plan!$H$16-B27+Plan!$I$16*D27) -> 0 | F27: =C27-E27 -> 262.2 | G27: =D27 -> 1.486402 | H27: =Fee*F27+VQ*G27 -> 19.757216 | I27: =MAX(0,MIN(1,(GNone-H27)/(GNone-GFull))) -> 0.016185576 | J27: =1-A27 -> 0.79 | K27: =MIN(I27,J27) -> 0.016185576 | L27: 0.93158 | M27: 0.01906 | N27: 0.01865 | O27: =IF(M27<=Alpha,A27,-1) -> 0.21 | P27: =IF(L27>=0.95,A27,-1) -> -1 | Q27: =MIN(I27^2,J27) -> 0.00026197288 | R27: =MIN(SQRT(I27),J27) -> 0.12722255
A28: 0.22 | B28: =DNever-(DNever-DUsual)*A28 -> 167 | C28: =SNever-(SNever-SPlaus)*A28 -> 260.4 | D28: =MAX(0,(B28-Plan!$H$5)/Plan!$I$5,(B28-Plan!$H$6)/Plan!$I$6,(B28-Plan!$H$7)/Plan!$I$7,(B28-Plan!$H$8)/Plan!$I$8,(B28-Plan!$H$9)/Plan!$I$9,(B28-Plan!$H$10)/Plan!$I$10,(B28-Plan!$H$11)/Plan!$I$11,(B28-Plan!$H$12)/Plan!$I$12,(B28-Plan!$H$13)/Plan!$I$13,(B28-Plan!$H$14)/Plan!$I$14,(B28-Plan!$H$15)/Plan!$I$15,(B28-Plan!$H$16)/Plan!$I$16) -> 1.4254 | E28: =MIN(C28,Plan!$H$5-B28+Plan!$I$5*D28,Plan!$H$6-B28+Plan!$I$6*D28,Plan!$H$7-B28+Plan!$I$7*D28,Plan!$H$8-B28+Plan!$I$8*D28,Plan!$H$9-B28+Plan!$I$9*D28,Plan!$H$10-B28+Plan!$I$10*D28,Plan!$H$11-B28+Plan!$I$11*D28,Plan!$H$12-B28+Plan!$I$12*D28,Plan!$H$13-B28+Plan!$I$13*D28,Plan!$H$14-B28+Plan!$I$14*D28,Plan!$H$15-B28+Plan!$I$15*D28,Plan!$H$16-B28+Plan!$I$16*D28) -> 0 | F28: =C28-E28 -> 260.4 | G28: =D28 -> 1.4254 | H28: =Fee*F28+VQ*G28 -> 19.2152 | I28: =MAX(0,MIN(1,(GNone-H28)/(GNone-GFull))) -> 0.052320024 | J28: =1-A28 -> 0.78 | K28: =MIN(I28,J28) -> 0.052320024 | L28: 0.92919 | M28: 0.02041 | N28: 0.02023 | O28: =IF(M28<=Alpha,A28,-1) -> 0.22 | P28: =IF(L28>=0.95,A28,-1) -> -1 | Q28: =MIN(I28^2,J28) -> 0.002737385 | R28: =MIN(SQRT(I28),J28) -> 0.22873571
A29: 0.23 | B29: =DNever-(DNever-DUsual)*A29 -> 165.5 | C29: =SNever-(SNever-SPlaus)*A29 -> 258.6 | D29: =MAX(0,(B29-Plan!$H$5)/Plan!$I$5,(B29-Plan!$H$6)/Plan!$I$6,(B29-Plan!$H$7)/Plan!$I$7,(B29-Plan!$H$8)/Plan!$I$8,(B29-Plan!$H$9)/Plan!$I$9,(B29-Plan!$H$10)/Plan!$I$10,(B29-Plan!$H$11)/Plan!$I$11,(B29-Plan!$H$12)/Plan!$I$12,(B29-Plan!$H$13)/Plan!$I$13,(B29-Plan!$H$14)/Plan!$I$14,(B29-Plan!$H$15)/Plan!$I$15,(B29-Plan!$H$16)/Plan!$I$16) -> 1.3643979 | E29: =MIN(C29,Plan!$H$5-B29+Plan!$I$5*D29,Plan!$H$6-B29+Plan!$I$6*D29,Plan!$H$7-B29+Plan!$I$7*D29,Plan!$H$8-B29+Plan!$I$8*D29,Plan!$H$9-B29+Plan!$I$9*D29,Plan!$H$10-B29+Plan!$I$10*D29,Plan!$H$11-B29+Plan!$I$11*D29,Plan!$H$12-B29+Plan!$I$12*D29,Plan!$H$13-B29+Plan!$I$13*D29,Plan!$H$14-B29+Plan!$I$14*D29,Plan!$H$15-B29+Plan!$I$15*D29,Plan!$H$16-B29+Plan!$I$16*D29) -> 0 | F29: =C29-E29 -> 258.6 | G29: =D29 -> 1.3643979 | H29: =Fee*F29+VQ*G29 -> 18.673183 | I29: =MAX(0,MIN(1,(GNone-H29)/(GNone-GFull))) -> 0.088454472 | J29: =1-A29 -> 0.77 | K29: =MIN(I29,J29) -> 0.088454472 | L29: 0.92682 | M29: 0.02181 | N29: 0.02179 | O29: =IF(M29<=Alpha,A29,-1) -> 0.23 | P29: =IF(L29>=0.95,A29,-1) -> -1 | Q29: =MIN(I29^2,J29) -> 0.0078241937 | R29: =MIN(SQRT(I29),J29) -> 0.29741297
A30: 0.24 | B30: =DNever-(DNever-DUsual)*A30 -> 164 | C30: =SNever-(SNever-SPlaus)*A30 -> 256.8 | D30: =MAX(0,(B30-Plan!$H$5)/Plan!$I$5,(B30-Plan!$H$6)/Plan!$I$6,(B30-Plan!$H$7)/Plan!$I$7,(B30-Plan!$H$8)/Plan!$I$8,(B30-Plan!$H$9)/Plan!$I$9,(B30-Plan!$H$10)/Plan!$I$10,(B30-Plan!$H$11)/Plan!$I$11,(B30-Plan!$H$12)/Plan!$I$12,(B30-Plan!$H$13)/Plan!$I$13,(B30-Plan!$H$14)/Plan!$I$14,(B30-Plan!$H$15)/Plan!$I$15,(B30-Plan!$H$16)/Plan!$I$16) -> 1.3033958 | E30: =MIN(C30,Plan!$H$5-B30+Plan!$I$5*D30,Plan!$H$6-B30+Plan!$I$6*D30,Plan!$H$7-B30+Plan!$I$7*D30,Plan!$H$8-B30+Plan!$I$8*D30,Plan!$H$9-B30+Plan!$I$9*D30,Plan!$H$10-B30+Plan!$I$10*D30,Plan!$H$11-B30+Plan!$I$11*D30,Plan!$H$12-B30+Plan!$I$12*D30,Plan!$H$13-B30+Plan!$I$13*D30,Plan!$H$14-B30+Plan!$I$14*D30,Plan!$H$15-B30+Plan!$I$15*D30,Plan!$H$16-B30+Plan!$I$16*D30) -> 0 | F30: =C30-E30 -> 256.8 | G30: =D30 -> 1.3033958 | H30: =Fee*F30+VQ*G30 -> 18.131166 | I30: =MAX(0,MIN(1,(GNone-H30)/(GNone-GFull))) -> 0.12458892 | J30: =1-A30 -> 0.76 | K30: =MIN(I30,J30) -> 0.12458892 | L30: 0.92433 | M30: 0.02341 | N30: 0.02333 | O30: =IF(M30<=Alpha,A30,-1) -> 0.24 | P30: =IF(L30>=0.95,A30,-1) -> -1 | Q30: =MIN(I30^2,J30) -> 0.015522399 | R30: =MIN(SQRT(I30),J30) -> 0.35297156
A31: 0.25 | B31: =DNever-(DNever-DUsual)*A31 -> 162.5 | C31: =SNever-(SNever-SPlaus)*A31 -> 255 | D31: =MAX(0,(B31-Plan!$H$5)/Plan!$I$5,(B31-Plan!$H$6)/Plan!$I$6,(B31-Plan!$H$7)/Plan!$I$7,(B31-Plan!$H$8)/Plan!$I$8,(B31-Plan!$H$9)/Plan!$I$9,(B31-Plan!$H$10)/Plan!$I$10,(B31-Plan!$H$11)/Plan!$I$11,(B31-Plan!$H$12)/Plan!$I$12,(B31-Plan!$H$13)/Plan!$I$13,(B31-Plan!$H$14)/Plan!$I$14,(B31-Plan!$H$15)/Plan!$I$15,(B31-Plan!$H$16)/Plan!$I$16) -> 1.2423937 | E31: =MIN(C31,Plan!$H$5-B31+Plan!$I$5*D31,Plan!$H$6-B31+Plan!$I$6*D31,Plan!$H$7-B31+Plan!$I$7*D31,Plan!$H$8-B31+Plan!$I$8*D31,Plan!$H$9-B31+Plan!$I$9*D31,Plan!$H$10-B31+Plan!$I$10*D31,Plan!$H$11-B31+Plan!$I$11*D31,Plan!$H$12-B31+Plan!$I$12*D31,Plan!$H$13-B31+Plan!$I$13*D31,Plan!$H$14-B31+Plan!$I$14*D31,Plan!$H$15-B31+Plan!$I$15*D31,Plan!$H$16-B31+Plan!$I$16*D31) -> 0 | F31: =C31-E31 -> 255 | G31: =D31 -> 1.2423937 | H31: =Fee*F31+VQ*G31 -> 17.589149 | I31: =MAX(0,MIN(1,(GNone-H31)/(GNone-GFull))) -> 0.16072337 | J31: =1-A31 -> 0.75 | K31: =MIN(I31,J31) -> 0.16072337 | L31: 0.9218 | M31: 0.02502 | N31: 0.02485 | O31: =IF(M31<=Alpha,A31,-1) -> 0.25 | P31: =IF(L31>=0.95,A31,-1) -> -1 | Q31: =MIN(I31^2,J31) -> 0.025832001 | R31: =MIN(SQRT(I31),J31) -> 0.40090319
A32: 0.26 | B32: =DNever-(DNever-DUsual)*A32 -> 161 | C32: =SNever-(SNever-SPlaus)*A32 -> 253.2 | D32: =MAX(0,(B32-Plan!$H$5)/Plan!$I$5,(B32-Plan!$H$6)/Plan!$I$6,(B32-Plan!$H$7)/Plan!$I$7,(B32-Plan!$H$8)/Plan!$I$8,(B32-Plan!$H$9)/Plan!$I$9,(B32-Plan!$H$10)/Plan!$I$10,(B32-Plan!$H$11)/Plan!$I$11,(B32-Plan!$H$12)/Plan!$I$12,(B32-Plan!$H$13)/Plan!$I$13,(B32-Plan!$H$14)/Plan!$I$14,(B32-Plan!$H$15)/Plan!$I$15,(B32-Plan!$H$16)/Plan!$I$16) -> 1.1813916 | E32: =MIN(C32,Plan!$H$5-B32+Plan!$I$5*D32,Plan!$H$6-B32+Plan!$I$6*D32,Plan!$H$7-B32+Plan!$I$7*D32,Plan!$H$8-B32+Plan!$I$8*D32,Plan!$H$9-B32+Plan!$I$9*D32,Plan!$H$10-B32+Plan!$I$10*D32,Plan!$H$11-B32+Plan!$I$11*D32,Plan!$H$12-B32+Plan!$I$12*D32,Plan!$H$13-B32+Plan!$I$13*D32,Plan!$H$14-B32+Plan!$I$14*D32,Plan!$H$15-B32+Plan!$I$15*D32,Plan!$H$16-B32+Plan!$I$16*D32) -> 0 | F32: =C32-E32 -> 253.2 | G32: =D32 -> 1.1813916 | H32: =Fee*F32+VQ*G32 -> 17.047133 | I32: =MAX(0,MIN(1,(GNone-H32)/(GNone-GFull))) -> 0.19685782 | J32: =1-A32 -> 0.74 | K32: =MIN(I32,J32) -> 0.19685782 | L32: 0.91886 | M32: 0.02676 | N32: 0.02649 | O32: =IF(M32<=Alpha,A32,-1) -> 0.26 | P32: =IF(L32>=0.95,A32,-1) -> -1 | Q32: =MIN(I32^2,J32) -> 0.038753 | R32: =MIN(SQRT(I32),J32) -> 0.44368662
A33: 0.27 | B33: =DNever-(DNever-DUsual)*A33 -> 159.5 | C33: =SNever-(SNever-SPlaus)*A33 -> 251.4 | D33: =MAX(0,(B33-Plan!$H$5)/Plan!$I$5,(B33-Plan!$H$6)/Plan!$I$6,(B33-Plan!$H$7)/Plan!$I$7,(B33-Plan!$H$8)/Plan!$I$8,(B33-Plan!$H$9)/Plan!$I$9,(B33-Plan!$H$10)/Plan!$I$10,(B33-Plan!$H$11)/Plan!$I$11,(B33-Plan!$H$12)/Plan!$I$12,(B33-Plan!$H$13)/Plan!$I$13,(B33-Plan!$H$14)/Plan!$I$14,(B33-Plan!$H$15)/Plan!$I$15,(B33-Plan!$H$16)/Plan!$I$16) -> 1.1203895 | E33: =MIN(C33,Plan!$H$5-B33+Plan!$I$5*D33,Plan!$H$6-B33+Plan!$I$6*D33,Plan!$H$7-B33+Plan!$I$7*D33,Plan!$H$8-B33+Plan!$I$8*D33,Plan!$H$9-B33+Plan!$I$9*D33,Plan!$H$10-B33+Plan!$I$10*D33,Plan!$H$11-B33+Plan!$I$11*D33,Plan!$H$12-B33+Plan!$I$12*D33,Plan!$H$13-B33+Plan!$I$13*D33,Plan!$H$14-B33+Plan!$I$14*D33,Plan!$H$15-B33+Plan!$I$15*D33,Plan!$H$16-B33+Plan!$I$16*D33) -> 0 | F33: =C33-E33 -> 251.4 | G33: =D33 -> 1.1203895 | H33: =Fee*F33+VQ*G33 -> 16.505116 | I33: =MAX(0,MIN(1,(GNone-H33)/(GNone-GFull))) -> 0.23299226 | J33: =1-A33 -> 0.73 | K33: =MIN(I33,J33) -> 0.23299226 | L33: 0.9157 | M33: 0.02858 | N33: 0.02833 | O33: =IF(M33<=Alpha,A33,-1) -> 0.27 | P33: =IF(L33>=0.95,A33,-1) -> -1 | Q33: =MIN(I33^2,J33) -> 0.054285395 | R33: =MIN(SQRT(I33),J33) -> 0.48269272
A34: 0.28 | B34: =DNever-(DNever-DUsual)*A34 -> 158 | C34: =SNever-(SNever-SPlaus)*A34 -> 249.6 | D34: =MAX(0,(B34-Plan!$H$5)/Plan!$I$5,(B34-Plan!$H$6)/Plan!$I$6,(B34-Plan!$H$7)/Plan!$I$7,(B34-Plan!$H$8)/Plan!$I$8,(B34-Plan!$H$9)/Plan!$I$9,(B34-Plan!$H$10)/Plan!$I$10,(B34-Plan!$H$11)/Plan!$I$11,(B34-Plan!$H$12)/Plan!$I$12,(B34-Plan!$H$13)/Plan!$I$13,(B34-Plan!$H$14)/Plan!$I$14,(B34-Plan!$H$15)/Plan!$I$15,(B34-Plan!$H$16)/Plan!$I$16) -> 1.0593874 | E34: =MIN(C34,Plan!$H$5-B34+Plan!$I$5*D34,Plan!$H$6-B34+Plan!$I$6*D34,Plan!$H$7-B34+Plan!$I$7*D34,Plan!$H$8-B34+Plan!$I$8*D34,Plan!$H$9-B34+Plan!$I$9*D34,Plan!$H$10-B34+Plan!$I$10*D34,Plan!$H$11-B34+Plan!$I$11*D34,Plan!$H$12-B34+Plan!$I$12*D34,Plan!$H$13-B34+Plan!$I$13*D34,Plan!$H$14-B34+Plan!$I$14*D34,Plan!$H$15-B34+Plan!$I$15*D34,Plan!$H$16-B34+Plan!$I$16*D34) -> 0 | F34: =C34-E34 -> 249.6 | G34: =D34 -> 1.0593874 | H34: =Fee*F34+VQ*G34 -> 15.963099 | I34: =MAX(0,MIN(1,(GNone-H34)/(GNone-GFull))) -> 0.26912671 | J34: =1-A34 -> 0.72 | K34: =MIN(I34,J34) -> 0.26912671 | L34: 0.91244 | M34: 0.03064 | N34: 0.03024 | O34: =IF(M34<=Alpha,A34,-1) -> 0.28 | P34: =IF(L34>=0.95,A34,-1) -> -1 | Q34: =MIN(I34^2,J34) -> 0.072429187 | R34: =MIN(SQRT(I34),J34) -> 0.51877424
A35: 0.29 | B35: =DNever-(DNever-DUsual)*A35 -> 156.5 | C35: =SNever-(SNever-SPlaus)*A35 -> 247.8 | D35: =MAX(0,(B35-Plan!$H$5)/Plan!$I$5,(B35-Plan!$H$6)/Plan!$I$6,(B35-Plan!$H$7)/Plan!$I$7,(B35-Plan!$H$8)/Plan!$I$8,(B35-Plan!$H$9)/Plan!$I$9,(B35-Plan!$H$10)/Plan!$I$10,(B35-Plan!$H$11)/Plan!$I$11,(B35-Plan!$H$12)/Plan!$I$12,(B35-Plan!$H$13)/Plan!$I$13,(B35-Plan!$H$14)/Plan!$I$14,(B35-Plan!$H$15)/Plan!$I$15,(B35-Plan!$H$16)/Plan!$I$16) -> 0.99838532 | E35: =MIN(C35,Plan!$H$5-B35+Plan!$I$5*D35,Plan!$H$6-B35+Plan!$I$6*D35,Plan!$H$7-B35+Plan!$I$7*D35,Plan!$H$8-B35+Plan!$I$8*D35,Plan!$H$9-B35+Plan!$I$9*D35,Plan!$H$10-B35+Plan!$I$10*D35,Plan!$H$11-B35+Plan!$I$11*D35,Plan!$H$12-B35+Plan!$I$12*D35,Plan!$H$13-B35+Plan!$I$13*D35,Plan!$H$14-B35+Plan!$I$14*D35,Plan!$H$15-B35+Plan!$I$15*D35,Plan!$H$16-B35+Plan!$I$16*D35) -> 0 | F35: =C35-E35 -> 247.8 | G35: =D35 -> 0.99838532 | H35: =Fee*F35+VQ*G35 -> 15.421083 | I35: =MAX(0,MIN(1,(GNone-H35)/(GNone-GFull))) -> 0.30526116 | J35: =1-A35 -> 0.71 | K35: =MIN(I35,J35) -> 0.30526116 | L35: 0.90955 | M35: 0.03251 | N35: 0.03204 | O35: =IF(M35<=Alpha,A35,-1) -> 0.29 | P35: =IF(L35>=0.95,A35,-1) -> -1 | Q35: =MIN(I35^2,J35) -> 0.093184376 | R35: =MIN(SQRT(I35),J35) -> 0.55250444
A36: 0.3 | B36: =DNever-(DNever-DUsual)*A36 -> 155 | C36: =SNever-(SNever-SPlaus)*A36 -> 246 | D36: =MAX(0,(B36-Plan!$H$5)/Plan!$I$5,(B36-Plan!$H$6)/Plan!$I$6,(B36-Plan!$H$7)/Plan!$I$7,(B36-Plan!$H$8)/Plan!$I$8,(B36-Plan!$H$9)/Plan!$I$9,(B36-Plan!$H$10)/Plan!$I$10,(B36-Plan!$H$11)/Plan!$I$11,(B36-Plan!$H$12)/Plan!$I$12,(B36-Plan!$H$13)/Plan!$I$13,(B36-Plan!$H$14)/Plan!$I$14,(B36-Plan!$H$15)/Plan!$I$15,(B36-Plan!$H$16)/Plan!$I$16) -> 0.93738323 | E36: =MIN(C36,Plan!$H$5-B36+Plan!$I$5*D36,Plan!$H$6-B36+Plan!$I$6*D36,Plan!$H$7-B36+Plan!$I$7*D36,Plan!$H$8-B36+Plan!$I$8*D36,Plan!$H$9-B36+Plan!$I$9*D36,Plan!$H$10-B36+Plan!$I$10*D36,Plan!$H$11-B36+Plan!$I$11*D36,Plan!$H$12-B36+Plan!$I$12*D36,Plan!$H$13-B36+Plan!$I$13*D36,Plan!$H$14-B36+Plan!$I$14*D36,Plan!$H$15-B36+Plan!$I$15*D36,Plan!$H$16-B36+Plan!$I$16*D36) -> 0 | F36: =C36-E36 -> 246 | G36: =D36 -> 0.93738323 | H36: =Fee*F36+VQ*G36 -> 14.879066 | I36: =MAX(0,MIN(1,(GNone-H36)/(GNone-GFull))) -> 0.34139561 | J36: =1-A36 -> 0.7 | K36: =MIN(I36,J36) -> 0.34139561 | L36: 0.90589 | M36: 0.03454 | N36: 0.03425 | O36: =IF(M36<=Alpha,A36,-1) -> 0.3 | P36: =IF(L36>=0.95,A36,-1) -> -1 | Q36: =MIN(I36^2,J36) -> 0.11655096 | R36: =MIN(SQRT(I36),J36) -> 0.58429069
A37: 0.31 | B37: =DNever-(DNever-DUsual)*A37 -> 153.5 | C37: =SNever-(SNever-SPlaus)*A37 -> 244.2 | D37: =MAX(0,(B37-Plan!$H$5)/Plan!$I$5,(B37-Plan!$H$6)/Plan!$I$6,(B37-Plan!$H$7)/Plan!$I$7,(B37-Plan!$H$8)/Plan!$I$8,(B37-Plan!$H$9)/Plan!$I$9,(B37-Plan!$H$10)/Plan!$I$10,(B37-Plan!$H$11)/Plan!$I$11,(B37-Plan!$H$12)/Plan!$I$12,(B37-Plan!$H$13)/Plan!$I$13,(B37-Plan!$H$14)/Plan!$I$14,(B37-Plan!$H$15)/Plan!$I$15,(B37-Plan!$H$16)/Plan!$I$16) -> 0.87638114 | E37: =MIN(C37,Plan!$H$5-B37+Plan!$I$5*D37,Plan!$H$6-B37+Plan!$I$6*D37,Plan!$H$7-B37+Plan!$I$7*D37,Plan!$H$8-B37+Plan!$I$8*D37,Plan!$H$9-B37+Plan!$I$9*D37,Plan!$H$10-B37+Plan!$I$10*D37,Plan!$H$11-B37+Plan!$I$11*D37,Plan!$H$12-B37+Plan!$I$12*D37,Plan!$H$13-B37+Plan!$I$13*D37,Plan!$H$14-B37+Plan!$I$14*D37,Plan!$H$15-B37+Plan!$I$15*D37,Plan!$H$16-B37+Plan!$I$16*D37) -> 0 | F37: =C37-E37 -> 244.2 | G37: =D37 -> 0.87638114 | H37: =Fee*F37+VQ*G37 -> 14.337049 | I37: =MAX(0,MIN(1,(GNone-H37)/(GNone-GFull))) -> 0.37753006 | J37: =1-A37 -> 0.69 | K37: =MIN(I37,J37) -> 0.37753006 | L37: 0.90232 | M37: 0.03701 | N37: 0.0364 | O37: =IF(M37<=Alpha,A37,-1) -> 0.31 | P37: =IF(L37>=0.95,A37,-1) -> -1 | Q37: =MIN(I37^2,J37) -> 0.14252894 | R37: =MIN(SQRT(I37),J37) -> 0.61443475
... A106: 1 | B106: =DNever-(DNever-DUsual)*A106 -> 50 | C106: =SNever-(SNever-SPlaus)*A106 -> 120 | D106: =MAX(0,(B106-Plan!$H$5)/Plan!$I$5,(B106-Plan!$H$6)/Plan!$I$6,(B106-Plan!$H$7)/Plan!$I$7,(B106-Plan!$H$8)/Plan!$I$8,(B106-Plan!$H$9)/Plan!$I$9,(B106-Plan!$H$10)/Plan!$I$10,(B106-Plan!$H$11)/Plan!$I$11,(B106-Plan!$H$12)/Plan!$I$12,(B106-Plan!$H$13)/Plan!$I$13,(B106-Plan!$H$14)/Plan!$I$14,(B106-Plan!$H$15)/Plan!$I$15,(B106-Plan!$H$16)/Plan!$I$16) -> 0 | E106: =MIN(C106,Plan!$H$5-B106+Plan!$I$5*D106,Plan!$H$6-B106+Plan!$I$6*D106,Plan!$H$7-B106+Plan!$I$7*D106,Plan!$H$8-B106+Plan!$I$8*D106,Plan!$H$9-B106+Plan!$I$9*D106,Plan!$H$10-B106+Plan!$I$10*D106,Plan!$H$11-B106+Plan!$I$11*D106,Plan!$H$12-B106+Plan!$I$12*D106,Plan!$H$13-B106+Plan!$I$13*D106,Plan!$H$14-B106+Plan!$I$14*D106,Plan!$H$15-B106+Plan!$I$15*D106,Plan!$H$16-B106+Plan!$I$16*D106) -> 81.950382 | F106: =C106-E106 -> 38.049618 | G106: =D106 -> 0 | H106: =Fee*F106+VQ*G106 -> 1.1414885 | I106: =MAX(0,MIN(1,(GNone-H106)/(GNone-GFull))) -> 1 | J106: =1-A106 -> 0 | K106: =MIN(I106,J106) -> 0 | L106: 0.1784 | M106: 0.19731 | N106: 0.19477 | O106: =IF(M106<=Alpha,A106,-1) -> -1 | P106: =IF(L106>=0.95,A106,-1) -> -1 | Q106: =MIN(I106^2,J106) -> 0 | R106: =MIN(SQRT(I106),J106) -> 0

Sheet Frontier
A1: Chapter 9's frontier and Table 10.3: guarantees beside chances (Theorem 10.1(iii); Figure 10.3; Worked Example 10.1, Step 4; AXIOM Lab 2.10, step 3)
A2: For each appetite, Chapter 9's cheapest committed package under the law: the line on a $5 million grid and the delay continuous (engine, on the book's 100,000 paths); its cost is 0.03 l + 8 phi.
A4: Appetite | B4: Line (engine) | C4: Delay (engine) | D4: Fees | E4: Delay cost | F4: Cost
A5: 0.01 | B5: 190 | C5: 2.1736665 | D5: =Fee*B5 -> 5.7 | E5: =VQ*C5 -> 17.389332 | F5: =D5+E5 -> 23.089332
A6: 0.02 | B6: 170 | C6: 1.5951064 | D6: =Fee*B6 -> 5.1 | E6: =VQ*C6 -> 12.760851 | F6: =D6+E6 -> 17.860851
A7: 0.03 | B7: 180 | C7: 1.1605155 | D7: =Fee*B7 -> 5.4 | E7: =VQ*C7 -> 9.2841241 | F7: =D7+E7 -> 14.684124
A8: 0.04 | B8: 165 | C8: 0.9250572 | D8: =Fee*B8 -> 4.95 | E8: =VQ*C8 -> 7.4004576 | F8: =D8+E8 -> 12.350458
A9: 0.05 | B9: 170 | C9: 0.66757636 | D9: =Fee*B9 -> 5.1 | E9: =VQ*C9 -> 5.3406109 | F9: =D9+E9 -> 10.440611
A10: 0.06 | B10: 160 | C10: 0.50242646 | D10: =Fee*B10 -> 4.8 | E10: =VQ*C10 -> 4.0194117 | F10: =D10+E10 -> 8.8194117
A11: 0.08 | B11: 160 | C11: 0.18170472 | D11: =Fee*B11 -> 4.8 | E11: =VQ*C11 -> 1.4536377 | F11: =D11+E11 -> 6.2536377
A12: 0.1 | B12: 135 | C12: 0.015171616 | D12: =Fee*B12 -> 4.05 | E12: =VQ*C12 -> 0.12137293 | F12: =D12+E12 -> 4.1713729
A13: 0.125 | B13: 100 | C13: 0 | D13: =Fee*B13 -> 3 | E13: =VQ*C13 -> 0 | F13: =D13+E13 -> 3
A14: 0.15 | B14: 75 | C14: 0 | D14: =Fee*B14 -> 2.25 | E14: =VQ*C14 -> 0 | F14: =D14+E14 -> 2.25
A17: Table 10.3: packages robust on declared sets, and their chance of a breach under Chapter 9's law
A18: Set | B18: D | C18: S | D18: Line | E18: Delay | F18: Cost | G18: Paths in the set (engine) | H18: Breach (engine) | I18: Fresh paths (engine)
A19: Volume I's joint check | B19: =Robust!C5 -> 0 | C19: =Robust!D5 -> 187 | D19: =Robust!J5 -> 55.049618 | E19: =Robust!K5 -> 0 | F19: =Robust!L5 -> 1.6514885 | G19: =Robust!Z5 -> 0.01488 | H19: =Robust!AA5 -> 0.17388 | I19: =Robust!AB5 -> 0.17124
A20: Crisp set (the 0.5-cut) | B20: =Robust!C6 -> 125 | C20: =Robust!D6 -> 210 | D20: =Robust!J6 -> 203.04962 | E20: =Robust!K6 -> 0 | F20: =Robust!L6 -> 6.0914885 | G20: =Robust!Z6 -> 0.78907 | H20: =Robust!AA6 -> 0.08645 | I20: =Robust!AB6 -> 0.08435
A21: Max-min choice (0.38-cut) | B21: =Robust!C7 -> 143 | C21: =Robust!D7 -> 231.6 | D21: =Robust!J7 -> 231.6 | E21: =Robust!K7 -> 0.44936651 | F21: =Robust!L7 -> 10.542932 | G21: =Robust!Z7 -> 0.87036 | H21: =Robust!AA7 -> 0.05637 | I21: =Robust!AB7 -> 0.05508
A22: Meeting 5% (0.35-cut) | B22: =Robust!C8 -> 147.5 | C22: =Robust!D8 -> 237 | D22: =Robust!J8 -> 237 | E22: =Robust!K8 -> 0.63237278 | F22: =Robust!L8 -> 12.168982 | G22: =Robust!Z8 -> 0.88533 | H22: =Robust!AA8 -> 0.04712 | I22: =Robust!AB8 -> 0.04617
A23: 95% of paths (0.08-cut) | B23: =Robust!C9 -> 188 | C23: =Robust!D9 -> 285.6 | D23: =Robust!J9 -> 285.6 | E23: =Robust!K9 -> 2.2941892 | F23: =Robust!L9 -> 26.921513 | G23: =Robust!Z9 -> 0.95021 | H23: =Robust!AA9 -> 0.00757 | I23: =Robust!AB9 -> 0.00731
A24: The whole support (0-cut) | B24: =Robust!C10 -> 200 | C24: =Robust!D10 -> 300 | D24: =Robust!J10 -> 300 | E24: =Robust!K10 -> 2.7966413 | F24: =Robust!L10 -> 31.37313 | G24: =Robust!Z10 -> 0.95581 | H24: =Robust!AA10 -> 0.00393 | I24: =Robust!AB10 -> 0.00394
A25: Volume I's package (law) | D25: =B9 -> 170 | E25: =C9 -> 0.66757636 | F25: =F9 -> 10.440611 | H25: 0.05 | I25: 0.04907
A27: The max-min package costs more than Volume I's by | B27: =F21-F25 -> 0.10232122 | C27: $10.54 million against $10.44 million
A28: and breaches more often by (points) | B28: =100*(H21-H25) -> 0.637 | C28: 5.6 percent against 5.0
A29: Meeting 5% with a cut costs more than Volume I's package by | B29: =F22-F25 -> 1.7283714 | C29: $12.17 million: the set is designed for the set, not the law
A30: A set holding 95% of the paths: cost | B30: =F23 -> 26.921513 | C30: $26.92 million for 0.8 percent: Theorem 10.1(iii) is conservative
A31: A $100 million cap on the line, the crisp set: delay | B31: =Robust!K12 -> 4.279055 | C31: 4.3 quarters
A32: cost | B32: =Robust!L12 -> 37.23244 | C32: $37.23 million: the cap is worth negotiating

Sheet Rules
A1: The eight-rule neuro-fuzzy price surface (Theorem 10.3; Equation 10.2; Section 10.4; Worked Example 10.1, Step 5; AXIOM Lab 2.10, steps 4-5)
A2: Gaussian terms centred at the offices' anchors; each rule concludes theta0 + theta1 u + theta2 v, u = (D - 25)/225, v = S/350; the output is the firing-weighted average of the conclusions. Widths and conclusions come from the notebook's hybrid learning (engine); everything else is a formula.
A4: Normalized inputs
A5: Deviations' bound: low | B5: 25 | C5: u = (D - low) / (high - low)
A6: Deviations' bound: high | B6: 250
A7: Closure's bound: low | B7: 0 | C7: v = (S - low) / (high - low)
A8: Closure's bound: high | B8: 350
A10: Term | B10: Declaration | C10: Anchor ($m) | D10: Centre (normalized) | E10: Learned width (engine)
A11: mild | B11: deviations | C11: 25 | D11: =(C11-$B$5)/($B$6-$B$5) -> 0 | E11: 0.12576578
A12: moderate | B12: deviations | C12: 100 | D12: =(C12-$B$5)/($B$6-$B$5) -> 0.33333333 | E12: 0.061938971
A13: severe | B13: deviations | C13: 175 | D13: =(C13-$B$5)/($B$6-$B$5) -> 0.66666667 | E13: 0.066425833
A14: extreme | B14: deviations | C14: 250 | D14: =(C14-$B$5)/($B$6-$B$5) -> 1 | E14: 0.05277199
A15: small | B15: closures | C15: 0 | D15: =(C15-$B$7)/($B$8-$B$7) -> 0 | E15: 0.10992579
A16: large | B16: closures | C16: 350 | D16: =(C16-$B$7)/($B$8-$B$7) -> 1 | E16: 0.33117152
A18: Rule | B18: Anchor D | C18: Anchor S | D18: u at anchor | E18: v at anchor | F18: theta0 (engine) | G18: theta1 (engine) | H18: theta2 (engine) | I18: Conclusion at anchor | J18: Exact: delay | K18: Exact: margin absorbs | L18: Exact cost at anchor | M18: Per $m of D | N18: Per $m of S | O18: Conclusion less exact
A19: mild-small | B19: =C11 -> 25 | C19: =C15 -> 0 | D19: =D11 -> 0 | E19: =D15 -> 0 | F19: -0.044007784 | G19: 0.32394988 | H19: 0.54199547 | I19: =F19+G19*D19+H19*E19 -> -0.044007784 | J19: =MAX(0,(B19-Plan!$H$5)/Plan!$I$5,(B19-Plan!$H$6)/Plan!$I$6,(B19-Plan!$H$7)/Plan!$I$7,(B19-Plan!$H$8)/Plan!$I$8,(B19-Plan!$H$9)/Plan!$I$9,(B19-Plan!$H$10)/Plan!$I$10,(B19-Plan!$H$11)/Plan!$I$11,(B19-Plan!$H$12)/Plan!$I$12,(B19-Plan!$H$13)/Plan!$I$13,(B19-Plan!$H$14)/Plan!$I$14,(B19-Plan!$H$15)/Plan!$I$15,(B19-Plan!$H$16)/Plan!$I$16) -> 0 | K19: =MIN(C19,Plan!$H$5-B19+Plan!$I$5*J19,Plan!$H$6-B19+Plan!$I$6*J19,Plan!$H$7-B19+Plan!$I$7*J19,Plan!$H$8-B19+Plan!$I$8*J19,Plan!$H$9-B19+Plan!$I$9*J19,Plan!$H$10-B19+Plan!$I$10*J19,Plan!$H$11-B19+Plan!$I$11*J19,Plan!$H$12-B19+Plan!$I$12*J19,Plan!$H$13-B19+Plan!$I$13*J19,Plan!$H$14-B19+Plan!$I$14*J19,Plan!$H$15-B19+Plan!$I$15*J19,Plan!$H$16-B19+Plan!$I$16*J19) -> 0 | L19: =Fee*(C19-K19)+VQ*J19 -> 0 | M19: =G19/($B$6-$B$5) -> 0.0014397772 | N19: =H19/($B$8-$B$7) -> 0.0015485585 | O19: =I19-L19 -> -0.044007784
A20: mild-large | B20: =C11 -> 25 | C20: =C16 -> 350 | D20: =D11 -> 0 | E20: =D16 -> 1 | F20: -2.8834473 | G20: 6.6340802 | H20: 10.115302 | I20: =F20+G20*D20+H20*E20 -> 7.2318543 | J20: =MAX(0,(B20-Plan!$H$5)/Plan!$I$5,(B20-Plan!$H$6)/Plan!$I$6,(B20-Plan!$H$7)/Plan!$I$7,(B20-Plan!$H$8)/Plan!$I$8,(B20-Plan!$H$9)/Plan!$I$9,(B20-Plan!$H$10)/Plan!$I$10,(B20-Plan!$H$11)/Plan!$I$11,(B20-Plan!$H$12)/Plan!$I$12,(B20-Plan!$H$13)/Plan!$I$13,(B20-Plan!$H$14)/Plan!$I$14,(B20-Plan!$H$15)/Plan!$I$15,(B20-Plan!$H$16)/Plan!$I$16) -> 0 | K20: =MIN(C20,Plan!$H$5-B20+Plan!$I$5*J20,Plan!$H$6-B20+Plan!$I$6*J20,Plan!$H$7-B20+Plan!$I$7*J20,Plan!$H$8-B20+Plan!$I$8*J20,Plan!$H$9-B20+Plan!$I$9*J20,Plan!$H$10-B20+Plan!$I$10*J20,Plan!$H$11-B20+Plan!$I$11*J20,Plan!$H$12-B20+Plan!$I$12*J20,Plan!$H$13-B20+Plan!$I$13*J20,Plan!$H$14-B20+Plan!$I$14*J20,Plan!$H$15-B20+Plan!$I$15*J20,Plan!$H$16-B20+Plan!$I$16*J20) -> 106.95038 | L20: =Fee*(C20-K20)+VQ*J20 -> 7.2914885 | M20: =G20/($B$6-$B$5) -> 0.029484801 | N20: =H20/($B$8-$B$7) -> 0.028900862 | O20: =I20-L20 -> -0.059634245
A21: moderate-small | B21: =C12 -> 100 | C21: =C15 -> 0 | D21: =D12 -> 0.33333333 | E21: =D15 -> 0 | F21: -1.0347408 | G21: 2.7525616 | H21: 5.4500199 | I21: =F21+G21*D21+H21*E21 -> -0.11722028 | J21: =MAX(0,(B21-Plan!$H$5)/Plan!$I$5,(B21-Plan!$H$6)/Plan!$I$6,(B21-Plan!$H$7)/Plan!$I$7,(B21-Plan!$H$8)/Plan!$I$8,(B21-Plan!$H$9)/Plan!$I$9,(B21-Plan!$H$10)/Plan!$I$10,(B21-Plan!$H$11)/Plan!$I$11,(B21-Plan!$H$12)/Plan!$I$12,(B21-Plan!$H$13)/Plan!$I$13,(B21-Plan!$H$14)/Plan!$I$14,(B21-Plan!$H$15)/Plan!$I$15,(B21-Plan!$H$16)/Plan!$I$16) -> 0 | K21: =MIN(C21,Plan!$H$5-B21+Plan!$I$5*J21,Plan!$H$6-B21+Plan!$I$6*J21,Plan!$H$7-B21+Plan!$I$7*J21,Plan!$H$8-B21+Plan!$I$8*J21,Plan!$H$9-B21+Plan!$I$9*J21,Plan!$H$10-B21+Plan!$I$10*J21,Plan!$H$11-B21+Plan!$I$11*J21,Plan!$H$12-B21+Plan!$I$12*J21,Plan!$H$13-B21+Plan!$I$13*J21,Plan!$H$14-B21+Plan!$I$14*J21,Plan!$H$15-B21+Plan!$I$15*J21,Plan!$H$16-B21+Plan!$I$16*J21) -> 0 | L21: =Fee*(C21-K21)+VQ*J21 -> 0 | M21: =G21/($B$6-$B$5) -> 0.012233607 | N21: =H21/($B$8-$B$7) -> 0.015571485 | O21: =I21-L21 -> -0.11722028
A22: moderate-large | B22: =C12 -> 100 | C22: =C16 -> 350 | D22: =D12 -> 0.33333333 | E22: =D16 -> 1 | F22: -3.2782505 | G22: 7.092685 | H22: 10.452924 | I22: =F22+G22*D22+H22*E22 -> 9.5389017 | J22: =MAX(0,(B22-Plan!$H$5)/Plan!$I$5,(B22-Plan!$H$6)/Plan!$I$6,(B22-Plan!$H$7)/Plan!$I$7,(B22-Plan!$H$8)/Plan!$I$8,(B22-Plan!$H$9)/Plan!$I$9,(B22-Plan!$H$10)/Plan!$I$10,(B22-Plan!$H$11)/Plan!$I$11,(B22-Plan!$H$12)/Plan!$I$12,(B22-Plan!$H$13)/Plan!$I$13,(B22-Plan!$H$14)/Plan!$I$14,(B22-Plan!$H$15)/Plan!$I$15,(B22-Plan!$H$16)/Plan!$I$16) -> 0 | K22: =MIN(C22,Plan!$H$5-B22+Plan!$I$5*J22,Plan!$H$6-B22+Plan!$I$6*J22,Plan!$H$7-B22+Plan!$I$7*J22,Plan!$H$8-B22+Plan!$I$8*J22,Plan!$H$9-B22+Plan!$I$9*J22,Plan!$H$10-B22+Plan!$I$10*J22,Plan!$H$11-B22+Plan!$I$11*J22,Plan!$H$12-B22+Plan!$I$12*J22,Plan!$H$13-B22+Plan!$I$13*J22,Plan!$H$14-B22+Plan!$I$14*J22,Plan!$H$15-B22+Plan!$I$15*J22,Plan!$H$16-B22+Plan!$I$16*J22) -> 31.950382 | L22: =Fee*(C22-K22)+VQ*J22 -> 9.5414885 | M22: =G22/($B$6-$B$5) -> 0.031523045 | N22: =H22/($B$8-$B$7) -> 0.029865497 | O22: =I22-L22 -> -0.002586855
A23: severe-small | B23: =C13 -> 175 | C23: =C15 -> 0 | D23: =D13 -> 0.66666667 | E23: =D15 -> 0 | F23: -35.268782 | G23: 73.979732 | H23: 10.497186 | I23: =F23+G23*D23+H23*E23 -> 14.05104 | J23: =MAX(0,(B23-Plan!$H$5)/Plan!$I$5,(B23-Plan!$H$6)/Plan!$I$6,(B23-Plan!$H$7)/Plan!$I$7,(B23-Plan!$H$8)/Plan!$I$8,(B23-Plan!$H$9)/Plan!$I$9,(B23-Plan!$H$10)/Plan!$I$10,(B23-Plan!$H$11)/Plan!$I$11,(B23-Plan!$H$12)/Plan!$I$12,(B23-Plan!$H$13)/Plan!$I$13,(B23-Plan!$H$14)/Plan!$I$14,(B23-Plan!$H$15)/Plan!$I$15,(B23-Plan!$H$16)/Plan!$I$16) -> 1.7507444 | K23: =MIN(C23,Plan!$H$5-B23+Plan!$I$5*J23,Plan!$H$6-B23+Plan!$I$6*J23,Plan!$H$7-B23+Plan!$I$7*J23,Plan!$H$8-B23+Plan!$I$8*J23,Plan!$H$9-B23+Plan!$I$9*J23,Plan!$H$10-B23+Plan!$I$10*J23,Plan!$H$11-B23+Plan!$I$11*J23,Plan!$H$12-B23+Plan!$I$12*J23,Plan!$H$13-B23+Plan!$I$13*J23,Plan!$H$14-B23+Plan!$I$14*J23,Plan!$H$15-B23+Plan!$I$15*J23,Plan!$H$16-B23+Plan!$I$16*J23) -> 0 | L23: =Fee*(C23-K23)+VQ*J23 -> 14.005955 | M23: =G23/($B$6-$B$5) -> 0.32879881 | N23: =H23/($B$8-$B$7) -> 0.029991959 | O23: =I23-L23 -> 0.045084237
A24: severe-large | B24: =C13 -> 175 | C24: =C16 -> 350 | D24: =D13 -> 0.66666667 | E24: =D16 -> 1 | F24: -35.276503 | G24: 73.99073 | H24: 10.499984 | I24: =F24+G24*D24+H24*E24 -> 24.550634 | J24: =MAX(0,(B24-Plan!$H$5)/Plan!$I$5,(B24-Plan!$H$6)/Plan!$I$6,(B24-Plan!$H$7)/Plan!$I$7,(B24-Plan!$H$8)/Plan!$I$8,(B24-Plan!$H$9)/Plan!$I$9,(B24-Plan!$H$10)/Plan!$I$10,(B24-Plan!$H$11)/Plan!$I$11,(B24-Plan!$H$12)/Plan!$I$12,(B24-Plan!$H$13)/Plan!$I$13,(B24-Plan!$H$14)/Plan!$I$14,(B24-Plan!$H$15)/Plan!$I$15,(B24-Plan!$H$16)/Plan!$I$16) -> 1.7507444 | K24: =MIN(C24,Plan!$H$5-B24+Plan!$I$5*J24,Plan!$H$6-B24+Plan!$I$6*J24,Plan!$H$7-B24+Plan!$I$7*J24,Plan!$H$8-B24+Plan!$I$8*J24,Plan!$H$9-B24+Plan!$I$9*J24,Plan!$H$10-B24+Plan!$I$10*J24,Plan!$H$11-B24+Plan!$I$11*J24,Plan!$H$12-B24+Plan!$I$12*J24,Plan!$H$13-B24+Plan!$I$13*J24,Plan!$H$14-B24+Plan!$I$14*J24,Plan!$H$15-B24+Plan!$I$15*J24,Plan!$H$16-B24+Plan!$I$16*J24) -> 0 | L24: =Fee*(C24-K24)+VQ*J24 -> 24.505955 | M24: =G24/($B$6-$B$5) -> 0.32884769 | N24: =H24/($B$8-$B$7) -> 0.029999954 | O24: =I24-L24 -> 0.044678882
A25: extreme-small | B25: =C14 -> 250 | C25: =C15 -> 0 | D25: =D14 -> 1 | E25: =D15 -> 0 | F25: -39.872903 | G25: 79.449082 | H25: 10.5 | I25: =F25+G25*D25+H25*E25 -> 39.576179 | J25: =MAX(0,(B25-Plan!$H$5)/Plan!$I$5,(B25-Plan!$H$6)/Plan!$I$6,(B25-Plan!$H$7)/Plan!$I$7,(B25-Plan!$H$8)/Plan!$I$8,(B25-Plan!$H$9)/Plan!$I$9,(B25-Plan!$H$10)/Plan!$I$10,(B25-Plan!$H$11)/Plan!$I$11,(B25-Plan!$H$12)/Plan!$I$12,(B25-Plan!$H$13)/Plan!$I$13,(B25-Plan!$H$14)/Plan!$I$14,(B25-Plan!$H$15)/Plan!$I$15,(B25-Plan!$H$16)/Plan!$I$16) -> 4.9470304 | K25: =MIN(C25,Plan!$H$5-B25+Plan!$I$5*J25,Plan!$H$6-B25+Plan!$I$6*J25,Plan!$H$7-B25+Plan!$I$7*J25,Plan!$H$8-B25+Plan!$I$8*J25,Plan!$H$9-B25+Plan!$I$9*J25,Plan!$H$10-B25+Plan!$I$10*J25,Plan!$H$11-B25+Plan!$I$11*J25,Plan!$H$12-B25+Plan!$I$12*J25,Plan!$H$13-B25+Plan!$I$13*J25,Plan!$H$14-B25+Plan!$I$14*J25,Plan!$H$15-B25+Plan!$I$15*J25,Plan!$H$16-B25+Plan!$I$16*J25) -> 0 | L25: =Fee*(C25-K25)+VQ*J25 -> 39.576243 | M25: =G25/($B$6-$B$5) -> 0.35310703 | N25: =H25/($B$8-$B$7) -> 0.03 | O25: =I25-L25 -> -6.3813113e-05
A26: extreme-large | B26: =C14 -> 250 | C26: =C16 -> 350 | D26: =D14 -> 1 | E26: =D16 -> 1 | F26: -39.872903 | G26: 79.449082 | H26: 10.5 | I26: =F26+G26*D26+H26*E26 -> 50.076179 | J26: =MAX(0,(B26-Plan!$H$5)/Plan!$I$5,(B26-Plan!$H$6)/Plan!$I$6,(B26-Plan!$H$7)/Plan!$I$7,(B26-Plan!$H$8)/Plan!$I$8,(B26-Plan!$H$9)/Plan!$I$9,(B26-Plan!$H$10)/Plan!$I$10,(B26-Plan!$H$11)/Plan!$I$11,(B26-Plan!$H$12)/Plan!$I$12,(B26-Plan!$H$13)/Plan!$I$13,(B26-Plan!$H$14)/Plan!$I$14,(B26-Plan!$H$15)/Plan!$I$15,(B26-Plan!$H$16)/Plan!$I$16) -> 4.9470304 | K26: =MIN(C26,Plan!$H$5-B26+Plan!$I$5*J26,Plan!$H$6-B26+Plan!$I$6*J26,Plan!$H$7-B26+Plan!$I$7*J26,Plan!$H$8-B26+Plan!$I$8*J26,Plan!$H$9-B26+Plan!$I$9*J26,Plan!$H$10-B26+Plan!$I$10*J26,Plan!$H$11-B26+Plan!$I$11*J26,Plan!$H$12-B26+Plan!$I$12*J26,Plan!$H$13-B26+Plan!$I$13*J26,Plan!$H$14-B26+Plan!$I$14*J26,Plan!$H$15-B26+Plan!$I$15*J26,Plan!$H$16-B26+Plan!$I$16*J26) -> 0 | L26: =Fee*(C26-K26)+VQ*J26 -> 50.076243 | M26: =G26/($B$6-$B$5) -> 0.35310703 | N26: =H26/($B$8-$B$7) -> 0.03 | O26: =I26-L26 -> -6.3813113e-05
A28: Where the line is needed the rules charge about 3 cents a dollar of closure, the line's fee; the severe and extreme rules about 33 and 35 cents a dollar of deviation, the price of delay.
A30: The surface at any declaration (Equation 10.2), against the exact robust cost
A31: Quantity | B31: The revision of Step 5 | C31: The largest error on the grid
A32: D: deviations' bound | B32: 140 | C32: 135
A33: S: closure's bound | B33: 230 | C33: 70
A34: u | B34: =(B32-$B$5)/($B$6-$B$5) -> 0.51111111 | C34: =(C32-$B$5)/($B$6-$B$5) -> 0.48888889
A35: v | B35: =(B33-$B$7)/($B$8-$B$7) -> 0.65714286 | C35: =(C33-$B$7)/($B$8-$B$7) -> 0.2
A36: membership: deviations mild | B36: =EXP(-((B34-$D$11)^2)/(2*$E$11^2)) -> 0.00025917287 | C36: =EXP(-((C34-$D$11)^2)/(2*$E$11^2)) -> 0.00052320479
A37: membership: deviations moderate | B37: =EXP(-((B34-$D$12)^2)/(2*$E$12^2)) -> 0.016259967 | C37: =EXP(-((C34-$D$12)^2)/(2*$E$12^2)) -> 0.042696128
A38: membership: deviations severe | B38: =EXP(-((B34-$D$13)^2)/(2*$E$13^2)) -> 0.064441504 | C38: =EXP(-((C34-$D$13)^2)/(2*$E$13^2)) -> 0.027837135
A39: membership: deviations extreme | B39: =EXP(-((B34-$D$14)^2)/(2*$E$14^2)) -> 2.3086393e-19 | C39: =EXP(-((C34-$D$14)^2)/(2*$E$14^2)) -> 4.2717937e-21
A40: membership: closures small | B40: =EXP(-((B35-$D$15)^2)/(2*$E$15^2)) -> 1.7368744e-08 | C40: =EXP(-((C35-$D$15)^2)/(2*$E$15^2)) -> 0.19106819
A41: membership: closures large | B41: =EXP(-((B35-$D$16)^2)/(2*$E$16^2)) -> 0.5851376 | C41: =EXP(-((C35-$D$16)^2)/(2*$E$16^2)) -> 0.054056653
A42: firing: mild-small | B42: =B36*B40 -> 4.5015073e-12 | C42: =C36*C40 -> 9.9967789e-05
A43: firing: mild-large | B43: =B36*B41 -> 0.00015165179 | C43: =C36*C41 -> 2.82827e-05
A44: firing: moderate-small | B44: =B37*B40 -> 2.8241521e-10 | C44: =C37*C40 -> 0.0081578716
A45: firing: moderate-large | B45: =B37*B41 -> 0.009514318 | C45: =C37*C41 -> 0.0023080098
A46: firing: severe-small | B46: =B38*B40 -> 1.119268e-09 | C46: =C38*C40 -> 0.005318791
A47: firing: severe-large | B47: =B38*B41 -> 0.037707147 | C47: =C38*C41 -> 0.0015047824
A48: firing: extreme-small | B48: =B39*B40 -> 4.0098166e-27 | C48: =C39*C40 -> 8.1620387e-22
A49: firing: extreme-large | B49: =B39*B41 -> 1.3508717e-19 | C49: =C39*C41 -> 2.3091887e-22
A50: conclusion: mild-small | B50: =$F$19+$G$19*B34+$H$19*B35 -> 0.47773505 | C50: =$F$19+$G$19*C34+$H$19*C35 -> 0.2227668
A51: conclusion: mild-large | B51: =$F$20+$G$20*B34+$H$20*B35 -> 7.154503 | C51: =$F$20+$G$20*C34+$H$20*C35 -> 2.3829411
A52: conclusion: moderate-small | B52: =$F$21+$G$21*B34+$H$21*B35 -> 3.9535656 | C52: =$F$21+$G$21*C34+$H$21*C35 -> 1.4009599
A53: conclusion: moderate-large | B53: =$F$22+$G$22*B34+$H$22*B35 -> 7.2159639 | C53: =$F$22+$G$22*C34+$H$22*C35 -> 2.2798692
A54: conclusion: severe-small | B54: =$F$23+$G$23*B34+$H$23*B35 -> 9.4412319 | C54: =$F$23+$G$23*C34+$H$23*C35 -> 2.9985244
A55: conclusion: severe-large | B55: =$F$24+$G$24*B34+$H$24*B35 -> 9.4409707 | C55: =$F$24+$G$24*C34+$H$24*C35 -> 2.9967396
A56: conclusion: extreme-small | B56: =$F$25+$G$25*B34+$H$25*B35 -> 7.6344058 | C56: =$F$25+$G$25*C34+$H$25*C35 -> 1.0688707
A57: conclusion: extreme-large | B57: =$F$26+$G$26*B34+$H$26*B35 -> 7.6344058 | C57: =$F$26+$G$26*C34+$H$26*C35 -> 1.0688707
A58: The surface: firing-weighted average of the conclusions | B58: =SUMPRODUCT(B42:B49,B50:B57)/SUM(B42:B49) -> 8.9867855 | C58: =SUMPRODUCT(C42:C49,C50:C57)/SUM(C42:C49) -> 2.1379649
A59: Exact: the delay the deviations need | B59: =MAX(0,(B32-Plan!$H$5)/Plan!$I$5,(B32-Plan!$H$6)/Plan!$I$6,(B32-Plan!$H$7)/Plan!$I$7,(B32-Plan!$H$8)/Plan!$I$8,(B32-Plan!$H$9)/Plan!$I$9,(B32-Plan!$H$10)/Plan!$I$10,(B32-Plan!$H$11)/Plan!$I$11,(B32-Plan!$H$12)/Plan!$I$12,(B32-Plan!$H$13)/Plan!$I$13,(B32-Plan!$H$14)/Plan!$I$14,(B32-Plan!$H$15)/Plan!$I$15,(B32-Plan!$H$16)/Plan!$I$16) -> 0.32736233 | C59: =MAX(0,(C32-Plan!$H$5)/Plan!$I$5,(C32-Plan!$H$6)/Plan!$I$6,(C32-Plan!$H$7)/Plan!$I$7,(C32-Plan!$H$8)/Plan!$I$8,(C32-Plan!$H$9)/Plan!$I$9,(C32-Plan!$H$10)/Plan!$I$10,(C32-Plan!$H$11)/Plan!$I$11,(C32-Plan!$H$12)/Plan!$I$12,(C32-Plan!$H$13)/Plan!$I$13,(C32-Plan!$H$14)/Plan!$I$14,(C32-Plan!$H$15)/Plan!$I$15,(C32-Plan!$H$16)/Plan!$I$16) -> 0.12402203
A60: Exact: the margin absorbs | B60: =MIN(B33,Plan!$H$5-B32+Plan!$I$5*B59,Plan!$H$6-B32+Plan!$I$6*B59,Plan!$H$7-B32+Plan!$I$7*B59,Plan!$H$8-B32+Plan!$I$8*B59,Plan!$H$9-B32+Plan!$I$9*B59,Plan!$H$10-B32+Plan!$I$10*B59,Plan!$H$11-B32+Plan!$I$11*B59,Plan!$H$12-B32+Plan!$I$12*B59,Plan!$H$13-B32+Plan!$I$13*B59,Plan!$H$14-B32+Plan!$I$14*B59,Plan!$H$15-B32+Plan!$I$15*B59,Plan!$H$16-B32+Plan!$I$16*B59) -> 0 | C60: =MIN(C33,Plan!$H$5-C32+Plan!$I$5*C59,Plan!$H$6-C32+Plan!$I$6*C59,Plan!$H$7-C32+Plan!$I$7*C59,Plan!$H$8-C32+Plan!$I$8*C59,Plan!$H$9-C32+Plan!$I$9*C59,Plan!$H$10-C32+Plan!$I$10*C59,Plan!$H$11-C32+Plan!$I$11*C59,Plan!$H$12-C32+Plan!$I$12*C59,Plan!$H$13-C32+Plan!$I$13*C59,Plan!$H$14-C32+Plan!$I$14*C59,Plan!$H$15-C32+Plan!$I$15*C59,Plan!$H$16-C32+Plan!$I$16*C59) -> 0
A61: Exact: line | B61: =B33-B60 -> 230 | C61: =C33-C60 -> 70
A62: Exact robust cost | B62: =Fee*B61+VQ*B59 -> 9.5188987 | C62: =Fee*C61+VQ*C59 -> 3.0921763
A63: The surface less the exact cost | B63: =B58-B62 -> -0.5321132 | C63: =C58-C62 -> -0.95421134
A65: Training and certification (engine: the notebook's hybrid learning and its grid check)
A66: Exact robust costs learned from (grid D 25-250 by S 0-350, spacing 25) | B66: 150
A67: Armijo steps on the widths | B67: 300 | C67: Within [0.03, 0.6]
A68: Mean squared error at the start | B68: 0.080189139 | C68: 0.0802
A69: after training | B69: 0.0080593077 | C69: 0.00806
A70: Declarations certified (grid of spacing 5) | B70: 3266 | C70: 3,266
A71: Root-mean-square error | B71: 0.1584209 | C71: 0.158
A72: Within $0.25 million | B72: 0.93478261 | C72: 93.5 percent
A73: Largest error | B73: 0.95421134 | C73: 0.954 at D 135, S 70, beside the corner; column C above recomputes it
A74: Six rules trained for accuracy alone: root-mean-square error | B74: 0.18274919 | C74: 0.183, about as accurate
A75: their conclusions at their centres | B75: -0.03, 6.71, 58.64, -9.56, -19.49, 61.58 | C75: From -19 to 62: no office could read them

Sheet Reference_Values
A1: Checkpoint | B1: Engine value | C1: Meaning (where in the book)
A2: A closure's 90th percentile | B2: 186.86698 | C2: Section 10.1: $187 million
A3: The plan's least margin | B3: 131.95038 | C3: $132 million
A4: in quarter | B4: 7 | C4: Quarter 7
A5: A quarter of delay lifts quarter 7 by | B5: 24.589321 | C5: $24.6 million
A6: Delay's price a dollar at quarter 7 | B6: 0.32534448 | C6: About 33 cents
A7: Plan's margin, quarter 1 | B7: 224.17772 | C7: Online Appendix Example 10.B.2
A8: Plan's margin, quarter 2 | B8: 190.0666 | C8: Online Appendix Example 10.B.2
A9: Plan's margin, quarter 3 | B9: 165.55419 | C9: Online Appendix Example 10.B.2
A10: Plan's margin, quarter 4 | B10: 148.8622 | C10: Online Appendix Example 10.B.2
A11: Plan's margin, quarter 5 | B11: 138.49718 | C11: Online Appendix Example 10.B.2
A12: Plan's margin, quarter 6 | B12: 133.20817 | C12: Online Appendix Example 10.B.2
A13: Plan's margin, quarter 7 | B13: 131.95038 | C13: Online Appendix Example 10.B.2
... A30: Cut 1.0: line | B30: 38.049618 | C30: Online Appendix Example 10.B.2
A31: Cut 1.0: delay | B31: 0
A32: Cut 1.0: cost | B32: 1.1414885 | C32: $1.14 million at 1 to $31.37 million at 0
A33: Cut 0.9: line | B33: 71.049618 | C33: Online Appendix Example 10.B.2
A34: Cut 0.9: delay | B34: 0
A35: Cut 0.9: cost | B35: 2.1314885
A36: Cut 0.8: line | B36: 104.04962 | C36: Online Appendix Example 10.B.2
A37: Cut 0.8: delay | B37: 0
A38: Cut 0.8: cost | B38: 3.1214885
A39: Cut 0.7: line | B39: 137.04962 | C39: Online Appendix Example 10.B.2
A40: Cut 0.7: delay | B40: 0
A41: Cut 0.7: cost | B41: 4.1114885
A42: Cut 0.6: line | B42: 170.04962 | C42: Online Appendix Example 10.B.2
A43: Cut 0.6: delay | B43: 0
A44: Cut 0.6: cost | B44: 5.1014885
A45: Cut 0.5: line | B45: 203.04962 | C45: Online Appendix Example 10.B.2
A46: Cut 0.5: delay | B46: 0
A47: Cut 0.5: cost | B47: 6.0914885
A48: Cut 0.4: line | B48: 228 | C48: Online Appendix Example 10.B.2
A49: Cut 0.4: delay | B49: 0.32736233
A50: Cut 0.4: cost | B50: 9.4588987
A51: Cut 0.3: line | B51: 246 | C51: Online Appendix Example 10.B.2
A52: Cut 0.3: delay | B52: 0.93738323
A53: Cut 0.3: cost | B53: 14.879066
A54: Cut 0.2: line | B54: 264 | C54: Online Appendix Example 10.B.2
A55: Cut 0.2: delay | B55: 1.5474041
A56: Cut 0.2: cost | B56: 20.299233
A57: Cut 0.1: line | B57: 282 | C57: Online Appendix Example 10.B.2
A58: Cut 0.1: delay | B58: 2.1685762
A59: Cut 0.1: cost | B59: 25.808609
A60: Cut 0.0: line | B60: 300 | C60: Online Appendix Example 10.B.2
A61: Cut 0.0: delay | B61: 2.7966413
A62: Cut 0.0: cost | B62: 31.37313 | C62: $1.14 million at 1 to $31.37 million at 0
A63: Graded price at possibility 1 | B63: 1.1414885 | C63: $1.14 million
A64: Graded price at possibility 0 | B64: 31.37313 | C64: $31.37 million
A65: Steps where the price falls as the set grows | B65: 0 | C65: None
A66: Max-min: the cut | B66: 0.38 | C66: 0.38
A67: Max-min: necessity of safety | B67: 0.62 | C67: 0.62
A68: Max-min: goal | B68: 0.63047119 | C68: 0.630
A69: Max-min: D | B69: 143 | C69: $143 million
A70: Max-min: S | B70: 231.6 | C70: $232 million
A71: Max-min: line | B71: 231.6 | C71: $232 million
A72: Max-min: delay | B72: 0.44936651 | C72: 0.45 quarter
A73: Max-min: cost | B73: 10.542932 | C73: $10.54 million
... A96: Rule mild-small: conclusion at its anchor | B96: -0.044007784 | C96: Online Appendix Example 10.B.2
A97: Rule mild-small: exact cost at its anchor | B97: 0
A98: Rule mild-small: per $m of D | B98: 0.0014397772
A99: Rule mild-small: per $m of S | B99: 0.0015485585
A100: Rule mild-large: conclusion at its anchor | B100: 7.2318543 | C100: Online Appendix Example 10.B.2
A101: Rule mild-large: exact cost at its anchor | B101: 7.2914885
A102: Rule mild-large: per $m of D | B102: 0.029484801
A103: Rule mild-large: per $m of S | B103: 0.028900862
A104: Rule moderate-small: conclusion at its anchor | B104: -0.11722028 | C104: Online Appendix Example 10.B.2
A105: Rule moderate-small: exact cost at its anchor | B105: 0
A106: Rule moderate-small: per $m of D | B106: 0.012233607
A107: Rule moderate-small: per $m of S | B107: 0.015571485
A108: Rule moderate-large: conclusion at its anchor | B108: 9.5389017 | C108: Online Appendix Example 10.B.2
A109: Rule moderate-large: exact cost at its anchor | B109: 9.5414885
A110: Rule moderate-large: per $m of D | B110: 0.031523045
A111: Rule moderate-large: per $m of S | B111: 0.029865497
A112: Rule severe-small: conclusion at its anchor | B112: 14.05104 | C112: Online Appendix Example 10.B.2
A113: Rule severe-small: exact cost at its anchor | B113: 14.005955
A114: Rule severe-small: per $m of D | B114: 0.32879881
A115: Rule severe-small: per $m of S | B115: 0.029991959
A116: Rule severe-large: conclusion at its anchor | B116: 24.550634 | C116: Online Appendix Example 10.B.2
A117: Rule severe-large: exact cost at its anchor | B117: 24.505955
A118: Rule severe-large: per $m of D | B118: 0.32884769
A119: Rule severe-large: per $m of S | B119: 0.029999954
A120: Rule extreme-small: conclusion at its anchor | B120: 39.576179 | C120: Online Appendix Example 10.B.2
A121: Rule extreme-small: exact cost at its anchor | B121: 39.576243
A122: Rule extreme-small: per $m of D | B122: 0.35310703
A123: Rule extreme-small: per $m of S | B123: 0.03
A124: Rule extreme-large: conclusion at its anchor | B124: 50.076179 | C124: Online Appendix Example 10.B.2
A125: Rule extreme-large: exact cost at its anchor | B125: 50.076243
A126: Rule extreme-large: per $m of D | B126: 0.35310703
A127: Rule extreme-large: per $m of S | B127: 0.03
A128: Revision (140, 230): the surface | B128: 8.9867855 | C128: Step 5: $8.99 million
A129: Revision (140, 230): exact cost | B129: 9.5188987 | C129: $9.52 million
A130: Revision (140, 230): line | B130: 230 | C130: $230 million
A131: Revision (140, 230): delay | B131: 0.32736233 | C131: 0.33 quarter
A132: Revision (140, 230): the surface on Robust's exact cost | B132: 9.5188987 | C132: The same exact solve
A133: At (135, 70): the surface | B133: 2.1379649 | C133: The certification's worst point
A134: At (135, 70): the surface's error | B134: 0.95421134 | C134: $0.95 million, at the corner

Sheet Checks
A1: Checkpoint | B1: Workbook formula value | C1: Engine value | D1: |diff| | E1: Tolerance | F1: Status
A2: A closure's 90th percentile | B2: =Declarations!B31 -> 186.86698 | C2: =Reference_Values!B2 -> 186.86698 | D2: =ABS(B2-C2) -> 0 | E2: 0.0001 | F2: =IF(D2<=E2,"PASS","FAIL") -> PASS
A3: The plan's least margin | B3: =Plan!B19 -> 131.95038 | C3: =Reference_Values!B3 -> 131.95038 | D3: =ABS(B3-C3) -> 0 | E3: 1e-09 | F3: =IF(D3<=E3,"PASS","FAIL") -> PASS
A4: in quarter | B4: =Plan!B20 -> 7 | C4: =Reference_Values!B4 -> 7 | D4: =ABS(B4-C4) -> 0 | E4: 0 | F4: =IF(D4<=E4,"PASS","FAIL") -> PASS
A5: A quarter of delay lifts quarter 7 by | B5: =Plan!B21 -> 24.589321 | C5: =Reference_Values!B5 -> 24.589321 | D5: =ABS(B5-C5) -> 0 | E5: 1e-09 | F5: =IF(D5<=E5,"PASS","FAIL") -> PASS
A6: Delay's price a dollar at quarter 7 | B6: =Plan!B23 -> 0.32534448 | C6: =Reference_Values!B6 -> 0.32534448 | D6: =ABS(B6-C6) -> 0 | E6: 1e-09 | F6: =IF(D6<=E6,"PASS","FAIL") -> PASS
A7: Plan's margin, quarter 1 | B7: =Plan!H5 -> 224.17772 | C7: =Reference_Values!B7 -> 224.17772 | D7: =ABS(B7-C7) -> 0 | E7: 1e-09 | F7: =IF(D7<=E7,"PASS","FAIL") -> PASS
A8: Plan's margin, quarter 2 | B8: =Plan!H6 -> 190.0666 | C8: =Reference_Values!B8 -> 190.0666 | D8: =ABS(B8-C8) -> 0 | E8: 1e-09 | F8: =IF(D8<=E8,"PASS","FAIL") -> PASS
A9: Plan's margin, quarter 3 | B9: =Plan!H7 -> 165.55419 | C9: =Reference_Values!B9 -> 165.55419 | D9: =ABS(B9-C9) -> 0 | E9: 1e-09 | F9: =IF(D9<=E9,"PASS","FAIL") -> PASS
A10: Plan's margin, quarter 4 | B10: =Plan!H8 -> 148.8622 | C10: =Reference_Values!B10 -> 148.8622 | D10: =ABS(B10-C10) -> 0 | E10: 1e-09 | F10: =IF(D10<=E10,"PASS","FAIL") -> PASS
A11: Plan's margin, quarter 5 | B11: =Plan!H9 -> 138.49718 | C11: =Reference_Values!B11 -> 138.49718 | D11: =ABS(B11-C11) -> 0 | E11: 1e-09 | F11: =IF(D11<=E11,"PASS","FAIL") -> PASS
A12: Plan's margin, quarter 6 | B12: =Plan!H10 -> 133.20817 | C12: =Reference_Values!B12 -> 133.20817 | D12: =ABS(B12-C12) -> 0 | E12: 1e-09 | F12: =IF(D12<=E12,"PASS","FAIL") -> PASS
A13: Plan's margin, quarter 7 | B13: =Plan!H11 -> 131.95038 | C13: =Reference_Values!B13 -> 131.95038 | D13: =ABS(B13-C13) -> 0 | E13: 1e-09 | F13: =IF(D13<=E13,"PASS","FAIL") -> PASS
A14: Plan's margin, quarter 8 | B14: =Plan!H12 -> 133.85405 | C14: =Reference_Values!B14 -> 133.85405 | D14: =ABS(B14-C14) -> 0 | E14: 1e-09 | F14: =IF(D14<=E14,"PASS","FAIL") -> PASS
A15: Plan's margin, quarter 9 | B15: =Plan!H13 -> 138.19778 | C15: =Reference_Values!B15 -> 138.19778 | D15: =ABS(B15-C15) -> 0 | E15: 1e-09 | F15: =IF(D15<=E15,"PASS","FAIL") -> PASS
A16: Plan's margin, quarter 10 | B16: =Plan!H14 -> 144.3857 | C16: =Reference_Values!B16 -> 144.3857 | D16: =ABS(B16-C16) -> 0 | E16: 1e-09 | F16: =IF(D16<=E16,"PASS","FAIL") -> PASS
A17: Plan's margin, quarter 11 | B17: =Plan!H15 -> 151.92795 | C17: =Reference_Values!B17 -> 151.92795 | D17: =ABS(B17-C17) -> 0 | E17: 1e-09 | F17: =IF(D17<=E17,"PASS","FAIL") -> PASS
A18: Plan's margin, quarter 12 | B18: =Plan!H16 -> 160.42405 | C18: =Reference_Values!B18 -> 160.42405 | D18: =ABS(B18-C18) -> 0 | E18: 1e-09 | F18: =IF(D18<=E18,"PASS","FAIL") -> PASS
A19: Joint check: line | B19: =Robust!J5 -> 55.049618 | C19: =Reference_Values!B19 -> 55.049618 | D19: =ABS(B19-C19) -> 0 | E19: 1e-09 | F19: =IF(D19<=E19,"PASS","FAIL") -> PASS
A20: Joint check: delay | B20: =Robust!K5 -> 0 | C20: =Reference_Values!B20 -> 0 | D20: =ABS(B20-C20) -> 0 | E20: 1e-09 | F20: =IF(D20<=E20,"PASS","FAIL") -> PASS
A21: Joint check: cost | B21: =Robust!L5 -> 1.6514885 | C21: =Reference_Values!B21 -> 1.6514885 | D21: =ABS(B21-C21) -> 0 | E21: 1e-09 | F21: =IF(D21<=E21,"PASS","FAIL") -> PASS
A22: Crisp set: the margin absorbs | B22: =Robust!I6 -> 6.9503824 | C22: =Reference_Values!B22 -> 6.9503824 | D22: =ABS(B22-C22) -> 0 | E22: 1e-09 | F22: =IF(D22<=E22,"PASS","FAIL") -> PASS
A23: Crisp set: line | B23: =Robust!J6 -> 203.04962 | C23: =Reference_Values!B23 -> 203.04962 | D23: =ABS(B23-C23) -> 0 | E23: 1e-09 | F23: =IF(D23<=E23,"PASS","FAIL") -> PASS
A24: Crisp set: delay | B24: =Robust!K6 -> 0 | C24: =Reference_Values!B24 -> 0 | D24: =ABS(B24-C24) -> 0 | E24: 1e-09 | F24: =IF(D24<=E24,"PASS","FAIL") -> PASS
A25: Crisp set: cost | B25: =Robust!L6 -> 6.0914885 | C25: =Reference_Values!B25 -> 6.0914885 | D25: =ABS(B25-C25) -> 0 | E25: 1e-09 | F25: =IF(D25<=E25,"PASS","FAIL") -> PASS
A26: Crisp set: binding quarter | B26: =Robust!Y6 -> 7 | C26: =Reference_Values!B26 -> 7 | D26: =ABS(B26-C26) -> 0 | E26: 0 | F26: =IF(D26<=E26,"PASS","FAIL") -> PASS
A27: Crisp set: Theorem 10.1(iii) promised at most | B27: =Robust!B18 -> 0.21093 | C27: =Reference_Values!B27 -> 0.21093 | D27: =ABS(B27-C27) -> 0 | E27: 1e-12 | F27: =IF(D27<=E27,"PASS","FAIL") -> PASS
A28: Proposition 10.3(iii): quarter 7 on the damage path | B28: =Robust!B19 -> 350 | C28: =Reference_Values!B28 -> 350 | D28: =ABS(B28-C28) -> 0 | E28: 1e-09 | F28: =IF(D28<=E28,"PASS","FAIL") -> PASS
A29: The whole support: binding quarter | B29: =Robust!Y10 -> 6 | C29: =Reference_Values!B29 -> 6 | D29: =ABS(B29-C29) -> 0 | E29: 0 | F29: =IF(D29<=E29,"PASS","FAIL") -> PASS
A30: Cut 1.0: line | B30: =Graded!F106 -> 38.049618 | C30: =Reference_Values!B30 -> 38.049618 | D30: =ABS(B30-C30) -> 0 | E30: 1e-09 | F30: =IF(D30<=E30,"PASS","FAIL") -> PASS
A31: Cut 1.0: delay | B31: =Graded!G106 -> 0 | C31: =Reference_Values!B31 -> 0 | D31: =ABS(B31-C31) -> 0 | E31: 1e-09 | F31: =IF(D31<=E31,"PASS","FAIL") -> PASS
A32: Cut 1.0: cost | B32: =Graded!H106 -> 1.1414885 | C32: =Reference_Values!B32 -> 1.1414885 | D32: =ABS(B32-C32) -> 0 | E32: 1e-09 | F32: =IF(D32<=E32,"PASS","FAIL") -> PASS
A33: Cut 0.9: line | B33: =Graded!F96 -> 71.049618 | C33: =Reference_Values!B33 -> 71.049618 | D33: =ABS(B33-C33) -> 0 | E33: 1e-09 | F33: =IF(D33<=E33,"PASS","FAIL") -> PASS
A34: Cut 0.9: delay | B34: =Graded!G96 -> 0 | C34: =Reference_Values!B34 -> 0 | D34: =ABS(B34-C34) -> 0 | E34: 1e-09 | F34: =IF(D34<=E34,"PASS","FAIL") -> PASS
A35: Cut 0.9: cost | B35: =Graded!H96 -> 2.1314885 | C35: =Reference_Values!B35 -> 2.1314885 | D35: =ABS(B35-C35) -> 0 | E35: 1e-09 | F35: =IF(D35<=E35,"PASS","FAIL") -> PASS
A36: Cut 0.8: line | B36: =Graded!F86 -> 104.04962 | C36: =Reference_Values!B36 -> 104.04962 | D36: =ABS(B36-C36) -> 0 | E36: 1e-09 | F36: =IF(D36<=E36,"PASS","FAIL") -> PASS
A37: Cut 0.8: delay | B37: =Graded!G86 -> 0 | C37: =Reference_Values!B37 -> 0 | D37: =ABS(B37-C37) -> 0 | E37: 1e-09 | F37: =IF(D37<=E37,"PASS","FAIL") -> PASS
A38: Cut 0.8: cost | B38: =Graded!H86 -> 3.1214885 | C38: =Reference_Values!B38 -> 3.1214885 | D38: =ABS(B38-C38) -> 0 | E38: 1e-09 | F38: =IF(D38<=E38,"PASS","FAIL") -> PASS
A39: Cut 0.7: line | B39: =Graded!F76 -> 137.04962 | C39: =Reference_Values!B39 -> 137.04962 | D39: =ABS(B39-C39) -> 0 | E39: 1e-09 | F39: =IF(D39<=E39,"PASS","FAIL") -> PASS
A40: Cut 0.7: delay | B40: =Graded!G76 -> 0 | C40: =Reference_Values!B40 -> 0 | D40: =ABS(B40-C40) -> 0 | E40: 1e-09 | F40: =IF(D40<=E40,"PASS","FAIL") -> PASS
A41: Cut 0.7: cost | B41: =Graded!H76 -> 4.1114885 | C41: =Reference_Values!B41 -> 4.1114885 | D41: =ABS(B41-C41) -> 0 | E41: 1e-09 | F41: =IF(D41<=E41,"PASS","FAIL") -> PASS
A42: Cut 0.6: line | B42: =Graded!F66 -> 170.04962 | C42: =Reference_Values!B42 -> 170.04962 | D42: =ABS(B42-C42) -> 0 | E42: 1e-09 | F42: =IF(D42<=E42,"PASS","FAIL") -> PASS
A43: Cut 0.6: delay | B43: =Graded!G66 -> 0 | C43: =Reference_Values!B43 -> 0 | D43: =ABS(B43-C43) -> 0 | E43: 1e-09 | F43: =IF(D43<=E43,"PASS","FAIL") -> PASS
A44: Cut 0.6: cost | B44: =Graded!H66 -> 5.1014885 | C44: =Reference_Values!B44 -> 5.1014885 | D44: =ABS(B44-C44) -> 0 | E44: 1e-09 | F44: =IF(D44<=E44,"PASS","FAIL") -> PASS
A45: Cut 0.5: line | B45: =Graded!F56 -> 203.04962 | C45: =Reference_Values!B45 -> 203.04962 | D45: =ABS(B45-C45) -> 0 | E45: 1e-09 | F45: =IF(D45<=E45,"PASS","FAIL") -> PASS
A46: Cut 0.5: delay | B46: =Graded!G56 -> 0 | C46: =Reference_Values!B46 -> 0 | D46: =ABS(B46-C46) -> 0 | E46: 1e-09 | F46: =IF(D46<=E46,"PASS","FAIL") -> PASS
A47: Cut 0.5: cost | B47: =Graded!H56 -> 6.0914885 | C47: =Reference_Values!B47 -> 6.0914885 | D47: =ABS(B47-C47) -> 0 | E47: 1e-09 | F47: =IF(D47<=E47,"PASS","FAIL") -> PASS
A48: Cut 0.4: line | B48: =Graded!F46 -> 228 | C48: =Reference_Values!B48 -> 228 | D48: =ABS(B48-C48) -> 0 | E48: 1e-09 | F48: =IF(D48<=E48,"PASS","FAIL") -> PASS
A49: Cut 0.4: delay | B49: =Graded!G46 -> 0.32736233 | C49: =Reference_Values!B49 -> 0.32736233 | D49: =ABS(B49-C49) -> 0 | E49: 1e-09 | F49: =IF(D49<=E49,"PASS","FAIL") -> PASS
A50: Cut 0.4: cost | B50: =Graded!H46 -> 9.4588987 | C50: =Reference_Values!B50 -> 9.4588987 | D50: =ABS(B50-C50) -> 0 | E50: 1e-09 | F50: =IF(D50<=E50,"PASS","FAIL") -> PASS
A51: Cut 0.3: line | B51: =Graded!F36 -> 246 | C51: =Reference_Values!B51 -> 246 | D51: =ABS(B51-C51) -> 0 | E51: 1e-09 | F51: =IF(D51<=E51,"PASS","FAIL") -> PASS
A52: Cut 0.3: delay | B52: =Graded!G36 -> 0.93738323 | C52: =Reference_Values!B52 -> 0.93738323 | D52: =ABS(B52-C52) -> 0 | E52: 1e-09 | F52: =IF(D52<=E52,"PASS","FAIL") -> PASS
A53: Cut 0.3: cost | B53: =Graded!H36 -> 14.879066 | C53: =Reference_Values!B53 -> 14.879066 | D53: =ABS(B53-C53) -> 0 | E53: 1e-09 | F53: =IF(D53<=E53,"PASS","FAIL") -> PASS
A54: Cut 0.2: line | B54: =Graded!F26 -> 264 | C54: =Reference_Values!B54 -> 264 | D54: =ABS(B54-C54) -> 0 | E54: 1e-09 | F54: =IF(D54<=E54,"PASS","FAIL") -> PASS
A55: Cut 0.2: delay | B55: =Graded!G26 -> 1.5474041 | C55: =Reference_Values!B55 -> 1.5474041 | D55: =ABS(B55-C55) -> 0 | E55: 1e-09 | F55: =IF(D55<=E55,"PASS","FAIL") -> PASS
A56: Cut 0.2: cost | B56: =Graded!H26 -> 20.299233 | C56: =Reference_Values!B56 -> 20.299233 | D56: =ABS(B56-C56) -> 0 | E56: 1e-09 | F56: =IF(D56<=E56,"PASS","FAIL") -> PASS
A57: Cut 0.1: line | B57: =Graded!F16 -> 282 | C57: =Reference_Values!B57 -> 282 | D57: =ABS(B57-C57) -> 0 | E57: 1e-09 | F57: =IF(D57<=E57,"PASS","FAIL") -> PASS
A58: Cut 0.1: delay | B58: =Graded!G16 -> 2.1685762 | C58: =Reference_Values!B58 -> 2.1685762 | D58: =ABS(B58-C58) -> 0 | E58: 1e-09 | F58: =IF(D58<=E58,"PASS","FAIL") -> PASS
A59: Cut 0.1: cost | B59: =Graded!H16 -> 25.808609 | C59: =Reference_Values!B59 -> 25.808609 | D59: =ABS(B59-C59) -> 0 | E59: 1e-09 | F59: =IF(D59<=E59,"PASS","FAIL") -> PASS
A60: Cut 0.0: line | B60: =Graded!F6 -> 300 | C60: =Reference_Values!B60 -> 300 | D60: =ABS(B60-C60) -> 0 | E60: 1e-09 | F60: =IF(D60<=E60,"PASS","FAIL") -> PASS
A61: Cut 0.0: delay | B61: =Graded!G6 -> 2.7966413 | C61: =Reference_Values!B61 -> 2.7966413 | D61: =ABS(B61-C61) -> 0 | E61: 1e-09 | F61: =IF(D61<=E61,"PASS","FAIL") -> PASS
A62: Cut 0.0: cost | B62: =Graded!H6 -> 31.37313 | C62: =Reference_Values!B62 -> 31.37313 | D62: =ABS(B62-C62) -> 0 | E62: 1e-09 | F62: =IF(D62<=E62,"PASS","FAIL") -> PASS
A63: Graded price at possibility 1 | B63: =Graded!U15 -> 1.1414885 | C63: =Reference_Values!B63 -> 1.1414885 | D63: =ABS(B63-C63) -> 0 | E63: 1e-09 | F63: =IF(D63<=E63,"PASS","FAIL") -> PASS
A64: Graded price at possibility 0 | B64: =Graded!U16 -> 31.37313 | C64: =Reference_Values!B64 -> 31.37313 | D64: =ABS(B64-C64) -> 0 | E64: 1e-09 | F64: =IF(D64<=E64,"PASS","FAIL") -> PASS
A65: Steps where the price falls as the set grows | B65: =Graded!U19 -> 0 | C65: =Reference_Values!B65 -> 0 | D65: =ABS(B65-C65) -> 0 | E65: 0 | F65: =IF(D65<=E65,"PASS","FAIL") -> PASS
A66: Max-min: the cut | B66: =Graded!U7 -> 0.38 | C66: =Reference_Values!B66 -> 0.38 | D66: =ABS(B66-C66) -> 0 | E66: 1e-09 | F66: =IF(D66<=E66,"PASS","FAIL") -> PASS
A67: Max-min: necessity of safety | B67: =Graded!U8 -> 0.62 | C67: =Reference_Values!B67 -> 0.62 | D67: =ABS(B67-C67) -> 0 | E67: 1e-09 | F67: =IF(D67<=E67,"PASS","FAIL") -> PASS
A68: Max-min: goal | B68: =Graded!U9 -> 0.63047119 | C68: =Reference_Values!B68 -> 0.63047119 | D68: =ABS(B68-C68) -> 0 | E68: 1e-09 | F68: =IF(D68<=E68,"PASS","FAIL") -> PASS
A69: Max-min: D | B69: =Robust!C7 -> 143 | C69: =Reference_Values!B69 -> 143 | D69: =ABS(B69-C69) -> 0 | E69: 1e-09 | F69: =IF(D69<=E69,"PASS","FAIL") -> PASS
A70: Max-min: S | B70: =Robust!D7 -> 231.6 | C70: =Reference_Values!B70 -> 231.6 | D70: =ABS(B70-C70) -> 0 | E70: 1e-09 | F70: =IF(D70<=E70,"PASS","FAIL") -> PASS
A71: Max-min: line | B71: =Robust!J7 -> 231.6 | C71: =Reference_Values!B71 -> 231.6 | D71: =ABS(B71-C71) -> 0 | E71: 1e-09 | F71: =IF(D71<=E71,"PASS","FAIL") -> PASS
A72: Max-min: delay | B72: =Robust!K7 -> 0.44936651 | C72: =Reference_Values!B72 -> 0.44936651 | D72: =ABS(B72-C72) -> 0 | E72: 1e-09 | F72: =IF(D72<=E72,"PASS","FAIL") -> PASS
A73: Max-min: cost | B73: =Robust!L7 -> 10.542932 | C73: =Reference_Values!B73 -> 10.542932 | D73: =ABS(B73-C73) -> 0 | E73: 1e-09 | F73: =IF(D73<=E73,"PASS","FAIL") -> PASS
A74: Max-min: cost on the Graded sheet | B74: =Graded!U10 -> 10.542932 | C74: =Reference_Values!B74 -> 10.542932 | D74: =ABS(B74-C74) -> 0 | E74: 1e-09 | F74: =IF(D74<=E74,"PASS","FAIL") -> PASS
A75: Hedges: violations | B75: =Graded!U25 -> 0 | C75: =Reference_Values!B75 -> 0 | D75: =ABS(B75-C75) -> 0 | E75: 0 | F75: =IF(D75<=E75,"PASS","FAIL") -> PASS
A76: Meeting 5%: the cut | B76: =Graded!U12 -> 0.35 | C76: =Reference_Values!B76 -> 0.35 | D76: =ABS(B76-C76) -> 0 | E76: 1e-09 | F76: =IF(D76<=E76,"PASS","FAIL") -> PASS
A77: Meeting 5%: delay | B77: =Robust!K8 -> 0.63237278 | C77: =Reference_Values!B77 -> 0.63237278 | D77: =ABS(B77-C77) -> 0 | E77: 1e-09 | F77: =IF(D77<=E77,"PASS","FAIL") -> PASS
A78: Meeting 5%: cost | B78: =Robust!L8 -> 12.168982 | C78: =Reference_Values!B78 -> 12.168982 | D78: =ABS(B78-C78) -> 0 | E78: 1e-09 | F78: =IF(D78<=E78,"PASS","FAIL") -> PASS
A79: 95% of paths: the cut | B79: =Graded!U13 -> 0.08 | C79: =Reference_Values!B79 -> 0.08 | D79: =ABS(B79-C79) -> 0 | E79: 1e-09 | F79: =IF(D79<=E79,"PASS","FAIL") -> PASS
A80: 95% of paths: delay | B80: =Robust!K9 -> 2.2941892 | C80: =Reference_Values!B80 -> 2.2941892 | D80: =ABS(B80-C80) -> 0 | E80: 1e-09 | F80: =IF(D80<=E80,"PASS","FAIL") -> PASS
A81: 95% of paths: cost | B81: =Robust!L9 -> 26.921513 | C81: =Reference_Values!B81 -> 26.921513 | D81: =ABS(B81-C81) -> 0 | E81: 1e-09 | F81: =IF(D81<=E81,"PASS","FAIL") -> PASS
A82: A $100m cap: delay | B82: =Robust!K12 -> 4.279055 | C82: =Reference_Values!B82 -> 4.279055 | D82: =ABS(B82-C82) -> 0 | E82: 1e-09 | F82: =IF(D82<=E82,"PASS","FAIL") -> PASS
A83: A $100m cap: cost | B83: =Robust!L12 -> 37.23244 | C83: =Reference_Values!B83 -> 37.23244 | D83: =ABS(B83-C83) -> 0 | E83: 1e-09 | F83: =IF(D83<=E83,"PASS","FAIL") -> PASS
A84: Cuts whose chance exceeds 1 - coverage | B84: =Graded!U20 -> 0 | C84: =Reference_Values!B84 -> 0 | D84: =ABS(B84-C84) -> 0 | E84: 0 | F84: =IF(D84<=E84,"PASS","FAIL") -> PASS
A85: Largest standard error of a chance, points | B85: =Graded!U21 -> 0.12584862 | C85: =Reference_Values!B85 -> 0.12584862 | D85: =ABS(B85-C85) -> 0 | E85: 1e-09 | F85: =IF(D85<=E85,"PASS","FAIL") -> PASS
A86: Frontier 1%: cost | B86: =Frontier!F5 -> 23.089332 | C86: =Reference_Values!B86 -> 23.089332 | D86: =ABS(B86-C86) -> 0 | E86: 1e-09 | F86: =IF(D86<=E86,"PASS","FAIL") -> PASS
A87: Frontier 2%: cost | B87: =Frontier!F6 -> 17.860851 | C87: =Reference_Values!B87 -> 17.860851 | D87: =ABS(B87-C87) -> 0 | E87: 1e-09 | F87: =IF(D87<=E87,"PASS","FAIL") -> PASS
A88: Frontier 3%: cost | B88: =Frontier!F7 -> 14.684124 | C88: =Reference_Values!B88 -> 14.684124 | D88: =ABS(B88-C88) -> 0 | E88: 1e-09 | F88: =IF(D88<=E88,"PASS","FAIL") -> PASS
A89: Frontier 4%: cost | B89: =Frontier!F8 -> 12.350458 | C89: =Reference_Values!B89 -> 12.350458 | D89: =ABS(B89-C89) -> 0 | E89: 1e-09 | F89: =IF(D89<=E89,"PASS","FAIL") -> PASS
A90: Frontier 5%: cost | B90: =Frontier!F9 -> 10.440611 | C90: =Reference_Values!B90 -> 10.440611 | D90: =ABS(B90-C90) -> 0 | E90: 1e-09 | F90: =IF(D90<=E90,"PASS","FAIL") -> PASS
A91: Frontier 6%: cost | B91: =Frontier!F10 -> 8.8194117 | C91: =Reference_Values!B91 -> 8.8194117 | D91: =ABS(B91-C91) -> 0 | E91: 1e-09 | F91: =IF(D91<=E91,"PASS","FAIL") -> PASS
A92: Frontier 8%: cost | B92: =Frontier!F11 -> 6.2536377 | C92: =Reference_Values!B92 -> 6.2536377 | D92: =ABS(B92-C92) -> 0 | E92: 1e-09 | F92: =IF(D92<=E92,"PASS","FAIL") -> PASS
A93: Frontier 10%: cost | B93: =Frontier!F12 -> 4.1713729 | C93: =Reference_Values!B93 -> 4.1713729 | D93: =ABS(B93-C93) -> 0 | E93: 1e-09 | F93: =IF(D93<=E93,"PASS","FAIL") -> PASS
A94: Frontier 12.5%: cost | B94: =Frontier!F13 -> 3 | C94: =Reference_Values!B94 -> 3 | D94: =ABS(B94-C94) -> 0 | E94: 1e-09 | F94: =IF(D94<=E94,"PASS","FAIL") -> PASS
A95: Frontier 15%: cost | B95: =Frontier!F14 -> 2.25 | C95: =Reference_Values!B95 -> 2.25 | D95: =ABS(B95-C95) -> 0 | E95: 1e-09 | F95: =IF(D95<=E95,"PASS","FAIL") -> PASS
A96: Rule mild-small: conclusion at its anchor | B96: =Rules!I19 -> -0.044007784 | C96: =Reference_Values!B96 -> -0.044007784 | D96: =ABS(B96-C96) -> 0 | E96: 1e-09 | F96: =IF(D96<=E96,"PASS","FAIL") -> PASS
A97: Rule mild-small: exact cost at its anchor | B97: =Rules!L19 -> 0 | C97: =Reference_Values!B97 -> 0 | D97: =ABS(B97-C97) -> 0 | E97: 1e-09 | F97: =IF(D97<=E97,"PASS","FAIL") -> PASS
A98: Rule mild-small: per $m of D | B98: =Rules!M19 -> 0.0014397772 | C98: =Reference_Values!B98 -> 0.0014397772 | D98: =ABS(B98-C98) -> 0 | E98: 1e-12 | F98: =IF(D98<=E98,"PASS","FAIL") -> PASS
A99: Rule mild-small: per $m of S | B99: =Rules!N19 -> 0.0015485585 | C99: =Reference_Values!B99 -> 0.0015485585 | D99: =ABS(B99-C99) -> 0 | E99: 1e-12 | F99: =IF(D99<=E99,"PASS","FAIL") -> PASS
A100: Rule mild-large: conclusion at its anchor | B100: =Rules!I20 -> 7.2318543 | C100: =Reference_Values!B100 -> 7.2318543 | D100: =ABS(B100-C100) -> 0 | E100: 1e-09 | F100: =IF(D100<=E100,"PASS","FAIL") -> PASS
...
