Workbook

Sheet README
B1: DCT Laboratory — Vol II, Ch 12: Multi-Objective Enterprise Optimization
B2: Seed 26212 · Companion to DCT_V2_Ch12_Lab.ipynb and AXIOM Lab 2.12 (module AXIOM-12). Money in $ million.
B4: Worked Example 12.1, Whose Objective Runs the Automation Program?, with the book's declarations: Chapter 5's automation program and the three owners' objectives (the CFO's present value of the payouts, the COO's run-rate savings in year 6, the treasury's reserve on every cash commitment). Deterministic: no random draw enters the book's numbers.
B5: Declarations: the program, the board's commitments and rate, and the reserve, price and goals to explore.
B6: Schedules: all 64 schedules with Chapter 5's war chest raised by the reserve, their best payouts, dominance, the board value, and the war chest recomputed at any reserve with the reserve's price (Steps 1-2).
B7: Frontier: the best schedule with each number of rounds, the five efficient plans, the prices between them, the board's weighted sum and a price to explore; the ideal point; bounds on all objectives but one (Step 3).
B8: Reserve: the reserve's price, the largest reserve each schedule keeps, and the three-round trade-off surface with its two jumps (Step 4).
B9: Grid and Plans: the best payouts for every number of rounds and reserve on the $1 million grid, the 992 plans and the 740 efficient ones; the engine's support test for each, with its certificate checked by formulas.
B10: Choose: the ideal and nadir points, the Chebyshev choices, any efficient plan reached by its own weights, the owners' own bests, and goal programming with and without a second stage (Step 5). Table12_3: Table 12.3.
B11: Computing: Section 12.4's counts and hypervolume, and the lab's own weight sweep and evolutionary search (seed 26212). Uncertainty: Chapter 9's cost-chance frontier as the book prints it and the price of the appetite (Section 12.5).
B12: Engine values (green) are what needs a linear program per plan, or the notebook's searches; everything else is a formula.
B13: Reference_Values and Checks: the engine's numbers and a PASS/FAIL comparison with this workbook's formulas.
... B19: Cross-sheet link: green.

Sheet Declarations
A1: Declarations (Worked Example 12.1, Step 1; Online Appendix Remark 12.B.1). Money in $ million.
A3: Quantity | B3: Value | C3: Source
A4: Today's cash, q_0 | B4: 620 | C4: Chapter 5's program (Volume I, Worked Example 6.1)
A5: Today's efficiency, e_0 (points) | B5: 71
A6: Efficiency ceiling (points) | B6: 85 | C6: A round halves the remaining gap to 85
A7: Share of the gap a round closes | B7: 0.5
A8: Savings per point above 71, a year | B8: 10 | C8: S_k = 10 (e_k - 71)
A9: Cost of a round | B9: 120
A10: Floor on cash at every year end | B10: 350 | C10: The board's commitments
A11: Cash a round needs before it starts | B11: 470
A12: End condition: cash at the end of year 6 | B12: 470
A13: Hurdle rate r (a year) | B13: 0.1 | C13: Payouts discounted at 10 percent; cash earns nothing
A14: Discount factor, beta = 1/(1 + r) | B14: =1/(1+Hurdle_r) -> 0.90909091 | C14: Also the reserve's price: $0.909 of payouts per dollar (Step 4)
A15: Chapter 5's price of savings, beta^6 / r | B15: =Beta_y^6/Hurdle_r -> 5.6447393 | C15: $5.645 of payouts today per dollar a year of year-6 savings (Section 12.2)
A17: Reserve to explore, b (above 0) | B17: 50 | C17: Schedules: the war chest recomputed at this reserve (Section 12.1's example: a $50 million reserve)
A18: Price of savings to explore, w | B18: 10 | C18: Frontier: the plan a weighted sum picks at this price; try 3, 5.645, 10, 20, 40
A20: Goal: payouts of at least | B20: 300 | C20: Worked Example 12.1, Step 5
A21: Goal: savings of at least, a year | B21: 122.5
A22: Goal: a reserve of | B22: 25
A23: Augmentation of the Chebyshev program, rho | B23: 0.0001 | C23: Online Appendix Example 12.B.2
A25: Dynamics: e_k = e_(k-1) + z_k (85 - e_(k-1))/2; S_k = 10 (e_k - 71); q_k = q_(k-1) - 120 z_k + S_k - p_k, p_k >= 0. Commitments, each kept with the reserve b to spare: q_k >= 350 + b every year; q_(k-1) >= 470 + b before a round in year k; q_6 >= 470 + b.
A26: The three owners' objectives (new declarations): the CFO's present value of the payouts at 10 percent; the COO's run-rate savings in year 6, S_6 = 140 - 140/2^n for n rounds; the treasury's reserve b.
A27: Chapter 5's board value is the weighted sum: payouts + (beta^6 / r) x savings. No plan keeps a reserve above $150 million: before the first round, or at the end without one, the cash is at most $620 million against $470 million plus the reserve.

Sheet Schedules
A1: All 64 schedules of rounds, each with its best payouts: Chapter 5's war chest raised by the reserve (Worked Example 12.1, Steps 1-2; Online Appendix Remark 12.B.1; AXIOM Lab 2.12, step 1)
A2: Each row is a schedule (z_k = 1: a round in year k; # is z_1...z_6 read as a binary number). Its best payouts pay out, every year end, everything above the war chest R_k: R_6 = 470 + b; R_(k-1) = max(R_k + 120 z_k - S_k, (470 + b) z_k, 350 + b), with no floor term for R_0.
A3: The schedule keeps every commitment while 620 >= R_0, so the largest reserve it keeps is 620 - R_0 at b = 0. Then p_1 = 620 - 120 z_1 + S_1 - R_1 and p_k = R_(k-1) - 120 z_k + S_k - R_k: the reserve raises every R_k by b, so only p_1 falls, by b. The notebook checks the war chest against the linear program for all 9,664 pairs.
A4: Right-hand block: the war chest recomputed from scratch at the reserve on Declarations (Res_b), and the reserve's price, (PV at 0 - PV at b) / b, for every schedule that keeps it.
AD6: Discount factor | AE6: =Beta_y^1 -> 0.90909091 | AF6: =Beta_y^2 -> 0.82644628 | AG6: =Beta_y^3 -> 0.7513148 | AH6: =Beta_y^4 -> 0.68301346 | AI6: =Beta_y^5 -> 0.62092132 | AJ6: =Beta_y^6 -> 0.56447393 | AY6: =Beta_y^1 -> 0.90909091 | AZ6: =Beta_y^2 -> 0.82644628 | BA6: =Beta_y^3 -> 0.7513148 | BB6: =Beta_y^4 -> 0.68301346 | BC6: =Beta_y^5 -> 0.62092132 | BD6: =Beta_y^6 -> 0.56447393
A7: # | B7: Rounds (years) | C7: z1 | D7: z2 | E7: z3 | F7: z4 | G7: z5 | H7: z6 | I7: Rounds n | J7: e1 | K7: e2 | L7: e3 | M7: e4 | N7: e5 | O7: e6 | P7: S1 | Q7: S2 | R7: S3 | S7: S4 | T7: S5 | U7: S6 | V7: R0 | W7: R1 | X7: R2 | Y7: R3 | Z7: R4 | AA7: R5 | AB7: R6 | AC7: Largest reserve it keeps | AD7: Keeps every commitment, no reserve | AE7: p1 | AF7: p2 | AG7: p3 | AH7: p4 | AI7: p5 | AJ7: p6 | AK7: Payouts, PV (CFO) | AL7: Savings, year 6 (COO) | AM7: Dominated (payouts, savings) | AN7: Efficient | AO7: Board value (Chapter 5) | AP7: Weighted sum at the price to explore | AQ7: R0 at Res_b | AR7: R1 at Res_b | AS7: R2 at Res_b | AT7: R3 at Res_b | AU7: R4 at Res_b | AV7: R5 at Res_b | AW7: R6 at Res_b | AX7: Keeps every commitment at Res_b | AY7: p1 at Res_b | AZ7: p2 at Res_b | BA7: p3 at Res_b | BB7: p4 at Res_b | BC7: p5 at Res_b | BD7: p6 at Res_b | BE7: Payouts, PV, at Res_b | BF7: Reserve's price: (PV at 0 - PV at Res_b) / Res_b | BG7: Payouts, PV, at the goal reserve | BH7: Meets every goal
A8: 0 | B8: none | C8: =MOD(INT($A8/32),2) -> 0 | D8: =MOD(INT($A8/16),2) -> 0 | E8: =MOD(INT($A8/8),2) -> 0 | F8: =MOD(INT($A8/4),2) -> 0 | G8: =MOD(INT($A8/2),2) -> 0 | H8: =MOD(INT($A8/1),2) -> 0 | I8: =SUM(C8:H8) -> 0 | J8: =E_zero+C8*Half_gap*(Ceiling_e-E_zero) -> 71 | K8: =J8+D8*Half_gap*(Ceiling_e-J8) -> 71 | L8: =K8+E8*Half_gap*(Ceiling_e-K8) -> 71 | M8: =L8+F8*Half_gap*(Ceiling_e-L8) -> 71 | N8: =M8+G8*Half_gap*(Ceiling_e-M8) -> 71 | O8: =N8+H8*Half_gap*(Ceiling_e-N8) -> 71 | P8: =Val_pt*(J8-E_zero) -> 0 | Q8: =Val_pt*(K8-E_zero) -> 0 | R8: =Val_pt*(L8-E_zero) -> 0 | S8: =Val_pt*(M8-E_zero) -> 0 | T8: =Val_pt*(N8-E_zero) -> 0 | U8: =Val_pt*(O8-E_zero) -> 0 | V8: =MAX(W8+Cost_round*C8-P8,IF(C8=1,Pre_q,0)) -> 470 | W8: =MAX(X8+Cost_round*D8-Q8,IF(D8=1,Pre_q,0),Floor_q) -> 470 | X8: =MAX(Y8+Cost_round*E8-R8,IF(E8=1,Pre_q,0),Floor_q) -> 470 | Y8: =MAX(Z8+Cost_round*F8-S8,IF(F8=1,Pre_q,0),Floor_q) -> 470 | Z8: =MAX(AA8+Cost_round*G8-T8,IF(G8=1,Pre_q,0),Floor_q) -> 470 | AA8: =MAX(AB8+Cost_round*H8-U8,IF(H8=1,Pre_q,0),Floor_q) -> 470 | AB8: =End_q -> 470 | AC8: =Q_zero-V8 -> 150 | AD8: =IF(AC8>=-0.000000001,1,0) -> 1 | AE8: =IF($AD8=1,Q_zero-Cost_round*C8+P8-W8,"") -> 150 | AF8: =IF($AD8=1,W8-Cost_round*D8+Q8-X8,"") -> 0 | AG8: =IF($AD8=1,X8-Cost_round*E8+R8-Y8,"") -> 0 | AH8: =IF($AD8=1,Y8-Cost_round*F8+S8-Z8,"") -> 0 | AI8: =IF($AD8=1,Z8-Cost_round*G8+T8-AA8,"") -> 0 | AJ8: =IF($AD8=1,AA8-Cost_round*H8+U8-AB8,"") -> 0 | AK8: =IF($AD8=1,SUMPRODUCT(AE8:AJ8,$AE$6:$AJ$6),"") -> 136.36364 | AL8: =U8 -> 0 | AM8: =IF(SUMPRODUCT(($AK$8:$AK$71>=AK8-0.000000001)*($AL$8:$AL$71>=AL8-0.000000001)*((($AK$8:$AK$71>AK8+0.000000001)+($AL$8:$AL$71>AL8+0.000000001))>0))>0,1,0) -> 1 | AN8: =1-AM8 -> 0 | AO8: =AK8+W_board*AL8 -> 136.36364 | AP8: =AK8+W_try*AL8 -> 136.36364 | AQ8: =MAX(AR8+Cost_round*C8-P8,IF(C8=1,Pre_q+Res_b,0)) -> 520 | AR8: =MAX(AS8+Cost_round*D8-Q8,IF(D8=1,Pre_q+Res_b,0),Floor_q+Res_b) -> 520 | AS8: =MAX(AT8+Cost_round*E8-R8,IF(E8=1,Pre_q+Res_b,0),Floor_q+Res_b) -> 520 | AT8: =MAX(AU8+Cost_round*F8-S8,IF(F8=1,Pre_q+Res_b,0),Floor_q+Res_b) -> 520 | AU8: =MAX(AV8+Cost_round*G8-T8,IF(G8=1,Pre_q+Res_b,0),Floor_q+Res_b) -> 520 | AV8: =MAX(AW8+Cost_round*H8-U8,IF(H8=1,Pre_q+Res_b,0),Floor_q+Res_b) -> 520 | AW8: =End_q+Res_b -> 520 | AX8: =IF(Q_zero>=AQ8-0.000000001,1,0) -> 1 | AY8: =IF($AX8=1,Q_zero-Cost_round*C8+P8-AR8,"") -> 100 | AZ8: =IF($AX8=1,AR8-Cost_round*D8+Q8-AS8,"") -> 0 | BA8: =IF($AX8=1,AS8-Cost_round*E8+R8-AT8,"") -> 0 | BB8: =IF($AX8=1,AT8-Cost_round*F8+S8-AU8,"") -> 0 | BC8: =IF($AX8=1,AU8-Cost_round*G8+T8-AV8,"") -> 0 | BD8: =IF($AX8=1,AV8-Cost_round*H8+U8-AW8,"") -> 0 | BE8: =IF($AX8=1,SUMPRODUCT(AY8:BD8,$AY$6:$BD$6),"") -> 90.909091 | BF8: =IF(AND($AX8=1,Res_b>0),(AK8-BE8)/Res_b,"") -> 0.90909091 | BG8: =IF(AC8>=Goal_b-0.000000001,AK8-Beta_y*Goal_b,"") -> 113.63636 | BH8: =IF(AC8>=Goal_b-0.000000001,IF(AND(AL8>=Goal_S-0.000000001,BG8>=Goal_P-0.000000001),1,0),0) -> 0
A9: 1 | B9: 6 | C9: =MOD(INT($A9/32),2) -> 0 | D9: =MOD(INT($A9/16),2) -> 0 | E9: =MOD(INT($A9/8),2) -> 0 | F9: =MOD(INT($A9/4),2) -> 0 | G9: =MOD(INT($A9/2),2) -> 0 | H9: =MOD(INT($A9/1),2) -> 1 | I9: =SUM(C9:H9) -> 1 | J9: =E_zero+C9*Half_gap*(Ceiling_e-E_zero) -> 71 | K9: =J9+D9*Half_gap*(Ceiling_e-J9) -> 71 | L9: =K9+E9*Half_gap*(Ceiling_e-K9) -> 71 | M9: =L9+F9*Half_gap*(Ceiling_e-L9) -> 71 | N9: =M9+G9*Half_gap*(Ceiling_e-M9) -> 71 | O9: =N9+H9*Half_gap*(Ceiling_e-N9) -> 78 | P9: =Val_pt*(J9-E_zero) -> 0 | Q9: =Val_pt*(K9-E_zero) -> 0 | R9: =Val_pt*(L9-E_zero) -> 0 | S9: =Val_pt*(M9-E_zero) -> 0 | T9: =Val_pt*(N9-E_zero) -> 0 | U9: =Val_pt*(O9-E_zero) -> 70 | V9: =MAX(W9+Cost_round*C9-P9,IF(C9=1,Pre_q,0)) -> 520 | W9: =MAX(X9+Cost_round*D9-Q9,IF(D9=1,Pre_q,0),Floor_q) -> 520 | X9: =MAX(Y9+Cost_round*E9-R9,IF(E9=1,Pre_q,0),Floor_q) -> 520 | Y9: =MAX(Z9+Cost_round*F9-S9,IF(F9=1,Pre_q,0),Floor_q) -> 520 | Z9: =MAX(AA9+Cost_round*G9-T9,IF(G9=1,Pre_q,0),Floor_q) -> 520 | AA9: =MAX(AB9+Cost_round*H9-U9,IF(H9=1,Pre_q,0),Floor_q) -> 520 | AB9: =End_q -> 470 | AC9: =Q_zero-V9 -> 100 | AD9: =IF(AC9>=-0.000000001,1,0) -> 1 | AE9: =IF($AD9=1,Q_zero-Cost_round*C9+P9-W9,"") -> 100 | AF9: =IF($AD9=1,W9-Cost_round*D9+Q9-X9,"") -> 0 | AG9: =IF($AD9=1,X9-Cost_round*E9+R9-Y9,"") -> 0 | AH9: =IF($AD9=1,Y9-Cost_round*F9+S9-Z9,"") -> 0 | AI9: =IF($AD9=1,Z9-Cost_round*G9+T9-AA9,"") -> 0 | AJ9: =IF($AD9=1,AA9-Cost_round*H9+U9-AB9,"") -> 0 | AK9: =IF($AD9=1,SUMPRODUCT(AE9:AJ9,$AE$6:$AJ$6),"") -> 90.909091 | AL9: =U9 -> 70 | AM9: =IF(SUMPRODUCT(($AK$8:$AK$71>=AK9-0.000000001)*($AL$8:$AL$71>=AL9-0.000000001)*((($AK$8:$AK$71>AK9+0.000000001)+($AL$8:$AL$71>AL9+0.000000001))>0))>0,1,0) -> 1 | AN9: =1-AM9 -> 0 | AO9: =AK9+W_board*AL9 -> 486.04084 | AP9: =AK9+W_try*AL9 -> 790.90909 | AQ9: =MAX(AR9+Cost_round*C9-P9,IF(C9=1,Pre_q+Res_b,0)) -> 570 | AR9: =MAX(AS9+Cost_round*D9-Q9,IF(D9=1,Pre_q+Res_b,0),Floor_q+Res_b) -> 570 | AS9: =MAX(AT9+Cost_round*E9-R9,IF(E9=1,Pre_q+Res_b,0),Floor_q+Res_b) -> 570 | AT9: =MAX(AU9+Cost_round*F9-S9,IF(F9=1,Pre_q+Res_b,0),Floor_q+Res_b) -> 570 | AU9: =MAX(AV9+Cost_round*G9-T9,IF(G9=1,Pre_q+Res_b,0),Floor_q+Res_b) -> 570 | AV9: =MAX(AW9+Cost_round*H9-U9,IF(H9=1,Pre_q+Res_b,0),Floor_q+Res_b) -> 570 | AW9: =End_q+Res_b -> 520 | AX9: =IF(Q_zero>=AQ9-0.000000001,1,0) -> 1 | AY9: =IF($AX9=1,Q_zero-Cost_round*C9+P9-AR9,"") -> 50 | AZ9: =IF($AX9=1,AR9-Cost_round*D9+Q9-AS9,"") -> 0 | BA9: =IF($AX9=1,AS9-Cost_round*E9+R9-AT9,"") -> 0 | BB9: =IF($AX9=1,AT9-Cost_round*F9+S9-AU9,"") -> 0 | BC9: =IF($AX9=1,AU9-Cost_round*G9+T9-AV9,"") -> 0 | BD9: =IF($AX9=1,AV9-Cost_round*H9+U9-AW9,"") -> 0 | BE9: =IF($AX9=1,SUMPRODUCT(AY9:BD9,$AY$6:$BD$6),"") -> 45.454545 | BF9: =IF(AND($AX9=1,Res_b>0),(AK9-BE9)/Res_b,"") -> 0.90909091 | BG9: =IF(AC9>=Goal_b-0.000000001,AK9-Beta_y*Goal_b,"") -> 68.181818 | BH9: =IF(AC9>=Goal_b-0.000000001,IF(AND(AL9>=Goal_S-0.000000001,BG9>=Goal_P-0.000000001),1,0),0) -> 0
A10: 2 | B10: 5 | C10: =MOD(INT($A10/32),2) -> 0 | D10: =MOD(INT($A10/16),2) -> 0 | E10: =MOD(INT($A10/8),2) -> 0 | F10: =MOD(INT($A10/4),2) -> 0 | G10: =MOD(INT($A10/2),2) -> 1 | H10: =MOD(INT($A10/1),2) -> 0 | I10: =SUM(C10:H10) -> 1 | J10: =E_zero+C10*Half_gap*(Ceiling_e-E_zero) -> 71 | K10: =J10+D10*Half_gap*(Ceiling_e-J10) -> 71 | L10: =K10+E10*Half_gap*(Ceiling_e-K10) -> 71 | M10: =L10+F10*Half_gap*(Ceiling_e-L10) -> 71 | N10: =M10+G10*Half_gap*(Ceiling_e-M10) -> 78 | O10: =N10+H10*Half_gap*(Ceiling_e-N10) -> 78 | P10: =Val_pt*(J10-E_zero) -> 0 | Q10: =Val_pt*(K10-E_zero) -> 0 | R10: =Val_pt*(L10-E_zero) -> 0 | S10: =Val_pt*(M10-E_zero) -> 0 | T10: =Val_pt*(N10-E_zero) -> 70 | U10: =Val_pt*(O10-E_zero) -> 70 | V10: =MAX(W10+Cost_round*C10-P10,IF(C10=1,Pre_q,0)) -> 470 | W10: =MAX(X10+Cost_round*D10-Q10,IF(D10=1,Pre_q,0),Floor_q) -> 470 | X10: =MAX(Y10+Cost_round*E10-R10,IF(E10=1,Pre_q,0),Floor_q) -> 470 | Y10: =MAX(Z10+Cost_round*F10-S10,IF(F10=1,Pre_q,0),Floor_q) -> 470 | Z10: =MAX(AA10+Cost_round*G10-T10,IF(G10=1,Pre_q,0),Floor_q) -> 470 | AA10: =MAX(AB10+Cost_round*H10-U10,IF(H10=1,Pre_q,0),Floor_q) -> 400 | AB10: =End_q -> 470 | AC10: =Q_zero-V10 -> 150 | AD10: =IF(AC10>=-0.000000001,1,0) -> 1 | AE10: =IF($AD10=1,Q_zero-Cost_round*C10+P10-W10,"") -> 150 | AF10: =IF($AD10=1,W10-Cost_round*D10+Q10-X10,"") -> 0 | AG10: =IF($AD10=1,X10-Cost_round*E10+R10-Y10,"") -> 0 | AH10: =IF($AD10=1,Y10-Cost_round*F10+S10-Z10,"") -> 0 | AI10: =IF($AD10=1,Z10-Cost_round*G10+T10-AA10,"") -> 20 | AJ10: =IF($AD10=1,AA10-Cost_round*H10+U10-AB10,"") -> 0 | AK10: =IF($AD10=1,SUMPRODUCT(AE10:AJ10,$AE$6:$AJ$6),"") -> 148.78206 | AL10: =U10 -> 70 | AM10: =IF(SUMPRODUCT(($AK$8:$AK$71>=AK10-0.000000001)*($AL$8:$AL$71>=AL10-0.000000001)*((($AK$8:$AK$71>AK10+0.000000001)+($AL$8:$AL$71>AL10+0.000000001))>0))>0,1,0) -> 1 | AN10: =1-AM10 -> 0 | AO10: =AK10+W_board*AL10 -> 543.91381 | AP10: =AK10+W_try*AL10 -> 848.78206 | AQ10: =MAX(AR10+Cost_round*C10-P10,IF(C10=1,Pre_q+Res_b,0)) -> 520 | AR10: =MAX(AS10+Cost_round*D10-Q10,IF(D10=1,Pre_q+Res_b,0),Floor_q+Res_b) -> 520 | AS10: =MAX(AT10+Cost_round*E10-R10,IF(E10=1,Pre_q+Res_b,0),Floor_q+Res_b) -> 520 | AT10: =MAX(AU10+Cost_round*F10-S10,IF(F10=1,Pre_q+Res_b,0),Floor_q+Res_b) -> 520 | AU10: =MAX(AV10+Cost_round*G10-T10,IF(G10=1,Pre_q+Res_b,0),Floor_q+Res_b) -> 520 | AV10: =MAX(AW10+Cost_round*H10-U10,IF(H10=1,Pre_q+Res_b,0),Floor_q+Res_b) -> 450 | AW10: =End_q+Res_b -> 520 | AX10: =IF(Q_zero>=AQ10-0.000000001,1,0) -> 1 | AY10: =IF($AX10=1,Q_zero-Cost_round*C10+P10-AR10,"") -> 100 | AZ10: =IF($AX10=1,AR10-Cost_round*D10+Q10-AS10,"") -> 0 | BA10: =IF($AX10=1,AS10-Cost_round*E10+R10-AT10,"") -> 0 | BB10: =IF($AX10=1,AT10-Cost_round*F10+S10-AU10,"") -> 0 | BC10: =IF($AX10=1,AU10-Cost_round*G10+T10-AV10,"") -> 20 | BD10: =IF($AX10=1,AV10-Cost_round*H10+U10-AW10,"") -> 0 | BE10: =IF($AX10=1,SUMPRODUCT(AY10:BD10,$AY$6:$BD$6),"") -> 103.32752 | BF10: =IF(AND($AX10=1,Res_b>0),(AK10-BE10)/Res_b,"") -> 0.90909091 | BG10: =IF(AC10>=Goal_b-0.000000001,AK10-Beta_y*Goal_b,"") -> 126.05479 | BH10: =IF(AC10>=Goal_b-0.000000001,IF(AND(AL10>=Goal_S-0.000000001,BG10>=Goal_P-0.000000001),1,0),0) -> 0
A11: 3 | B11: 5, 6 | C11: =MOD(INT($A11/32),2) -> 0 | D11: =MOD(INT($A11/16),2) -> 0 | E11: =MOD(INT($A11/8),2) -> 0 | F11: =MOD(INT($A11/4),2) -> 0 | G11: =MOD(INT($A11/2),2) -> 1 | H11: =MOD(INT($A11/1),2) -> 1 | I11: =SUM(C11:H11) -> 2 | J11: =E_zero+C11*Half_gap*(Ceiling_e-E_zero) -> 71 | K11: =J11+D11*Half_gap*(Ceiling_e-J11) -> 71 | L11: =K11+E11*Half_gap*(Ceiling_e-K11) -> 71 | M11: =L11+F11*Half_gap*(Ceiling_e-L11) -> 71 | N11: =M11+G11*Half_gap*(Ceiling_e-M11) -> 78 | O11: =N11+H11*Half_gap*(Ceiling_e-N11) -> 81.5 | P11: =Val_pt*(J11-E_zero) -> 0 | Q11: =Val_pt*(K11-E_zero) -> 0 | R11: =Val_pt*(L11-E_zero) -> 0 | S11: =Val_pt*(M11-E_zero) -> 0 | T11: =Val_pt*(N11-E_zero) -> 70 | U11: =Val_pt*(O11-E_zero) -> 105 | V11: =MAX(W11+Cost_round*C11-P11,IF(C11=1,Pre_q,0)) -> 535 | W11: =MAX(X11+Cost_round*D11-Q11,IF(D11=1,Pre_q,0),Floor_q) -> 535 | X11: =MAX(Y11+Cost_round*E11-R11,IF(E11=1,Pre_q,0),Floor_q) -> 535 | Y11: =MAX(Z11+Cost_round*F11-S11,IF(F11=1,Pre_q,0),Floor_q) -> 535 | Z11: =MAX(AA11+Cost_round*G11-T11,IF(G11=1,Pre_q,0),Floor_q) -> 535 | AA11: =MAX(AB11+Cost_round*H11-U11,IF(H11=1,Pre_q,0),Floor_q) -> 485 | AB11: =End_q -> 470 | AC11: =Q_zero-V11 -> 85 | AD11: =IF(AC11>=-0.000000001,1,0) -> 1 | AE11: =IF($AD11=1,Q_zero-Cost_round*C11+P11-W11,"") -> 85 | AF11: =IF($AD11=1,W11-Cost_round*D11+Q11-X11,"") -> 0 | AG11: =IF($AD11=1,X11-Cost_round*E11+R11-Y11,"") -> 0 | AH11: =IF($AD11=1,Y11-Cost_round*F11+S11-Z11,"") -> 0 | AI11: =IF($AD11=1,Z11-Cost_round*G11+T11-AA11,"") -> 0 | AJ11: =IF($AD11=1,AA11-Cost_round*H11+U11-AB11,"") -> 0 | AK11: =IF($AD11=1,SUMPRODUCT(AE11:AJ11,$AE$6:$AJ$6),"") -> 77.272727 | AL11: =U11 -> 105 | AM11: =IF(SUMPRODUCT(($AK$8:$AK$71>=AK11-0.000000001)*($AL$8:$AL$71>=AL11-0.000000001)*((($AK$8:$AK$71>AK11+0.000000001)+($AL$8:$AL$71>AL11+0.000000001))>0))>0,1,0) -> 1 | AN11: =1-AM11 -> 0 | AO11: =AK11+W_board*AL11 -> 669.97035 | AP11: =AK11+W_try*AL11 -> 1127.2727 | AQ11: =MAX(AR11+Cost_round*C11-P11,IF(C11=1,Pre_q+Res_b,0)) -> 585 | AR11: =MAX(AS11+Cost_round*D11-Q11,IF(D11=1,Pre_q+Res_b,0),Floor_q+Res_b) -> 585 | AS11: =MAX(AT11+Cost_round*E11-R11,IF(E11=1,Pre_q+Res_b,0),Floor_q+Res_b) -> 585 | AT11: =MAX(AU11+Cost_round*F11-S11,IF(F11=1,Pre_q+Res_b,0),Floor_q+Res_b) -> 585 | AU11: =MAX(AV11+Cost_round*G11-T11,IF(G11=1,Pre_q+Res_b,0),Floor_q+Res_b) -> 585 | AV11: =MAX(AW11+Cost_round*H11-U11,IF(H11=1,Pre_q+Res_b,0),Floor_q+Res_b) -> 535 | AW11: =End_q+Res_b -> 520 | AX11: =IF(Q_zero>=AQ11-0.000000001,1,0) -> 1 | AY11: =IF($AX11=1,Q_zero-Cost_round*C11+P11-AR11,"") -> 35 | AZ11: =IF($AX11=1,AR11-Cost_round*D11+Q11-AS11,"") -> 0 | BA11: =IF($AX11=1,AS11-Cost_round*E11+R11-AT11,"") -> 0 | BB11: =IF($AX11=1,AT11-Cost_round*F11+S11-AU11,"") -> 0 | BC11: =IF($AX11=1,AU11-Cost_round*G11+T11-AV11,"") -> 0 | BD11: =IF($AX11=1,AV11-Cost_round*H11+U11-AW11,"") -> 0 | BE11: =IF($AX11=1,SUMPRODUCT(AY11:BD11,$AY$6:$BD$6),"") -> 31.818182 | BF11: =IF(AND($AX11=1,Res_b>0),(AK11-BE11)/Res_b,"") -> 0.90909091 | BG11: =IF(AC11>=Goal_b-0.000000001,AK11-Beta_y*Goal_b,"") -> 54.545455 | BH11: =IF(AC11>=Goal_b-0.000000001,IF(AND(AL11>=Goal_S-0.000000001,BG11>=Goal_P-0.000000001),1,0),0) -> 0
A12: 4 | B12: 4 | C12: =MOD(INT($A12/32),2) -> 0 | D12: =MOD(INT($A12/16),2) -> 0 | E12: =MOD(INT($A12/8),2) -> 0 | F12: =MOD(INT($A12/4),2) -> 1 | G12: =MOD(INT($A12/2),2) -> 0 | H12: =MOD(INT($A12/1),2) -> 0 | I12: =SUM(C12:H12) -> 1 | J12: =E_zero+C12*Half_gap*(Ceiling_e-E_zero) -> 71 | K12: =J12+D12*Half_gap*(Ceiling_e-J12) -> 71 | L12: =K12+E12*Half_gap*(Ceiling_e-K12) -> 71 | M12: =L12+F12*Half_gap*(Ceiling_e-L12) -> 78 | N12: =M12+G12*Half_gap*(Ceiling_e-M12) -> 78 | O12: =N12+H12*Half_gap*(Ceiling_e-N12) -> 78 | P12: =Val_pt*(J12-E_zero) -> 0 | Q12: =Val_pt*(K12-E_zero) -> 0 | R12: =Val_pt*(L12-E_zero) -> 0 | S12: =Val_pt*(M12-E_zero) -> 70 | T12: =Val_pt*(N12-E_zero) -> 70 | U12: =Val_pt*(O12-E_zero) -> 70 | V12: =MAX(W12+Cost_round*C12-P12,IF(C12=1,Pre_q,0)) -> 470 | W12: =MAX(X12+Cost_round*D12-Q12,IF(D12=1,Pre_q,0),Floor_q) -> 470 | X12: =MAX(Y12+Cost_round*E12-R12,IF(E12=1,Pre_q,0),Floor_q) -> 470 | Y12: =MAX(Z12+Cost_round*F12-S12,IF(F12=1,Pre_q,0),Floor_q) -> 470 | Z12: =MAX(AA12+Cost_round*G12-T12,IF(G12=1,Pre_q,0),Floor_q) -> 350 | AA12: =MAX(AB12+Cost_round*H12-U12,IF(H12=1,Pre_q,0),Floor_q) -> 400 | AB12: =End_q -> 470 | AC12: =Q_zero-V12 -> 150 | AD12: =IF(AC12>=-0.000000001,1,0) -> 1 | AE12: =IF($AD12=1,Q_zero-Cost_round*C12+P12-W12,"") -> 150 | AF12: =IF($AD12=1,W12-Cost_round*D12+Q12-X12,"") -> 0 | AG12: =IF($AD12=1,X12-Cost_round*E12+R12-Y12,"") -> 0 | AH12: =IF($AD12=1,Y12-Cost_round*F12+S12-Z12,"") -> 70 | AI12: =IF($AD12=1,Z12-Cost_round*G12+T12-AA12,"") -> 20 | AJ12: =IF($AD12=1,AA12-Cost_round*H12+U12-AB12,"") -> 0 | AK12: =IF($AD12=1,SUMPRODUCT(AE12:AJ12,$AE$6:$AJ$6),"") -> 196.593 | AL12: =U12 -> 70 | AM12: =IF(SUMPRODUCT(($AK$8:$AK$71>=AK12-0.000000001)*($AL$8:$AL$71>=AL12-0.000000001)*((($AK$8:$AK$71>AK12+0.000000001)+($AL$8:$AL$71>AL12+0.000000001))>0))>0,1,0) -> 1 | AN12: =1-AM12 -> 0 | AO12: =AK12+W_board*AL12 -> 591.72476 | AP12: =AK12+W_try*AL12 -> 896.593 | AQ12: =MAX(AR12+Cost_round*C12-P12,IF(C12=1,Pre_q+Res_b,0)) -> 520 | AR12: =MAX(AS12+Cost_round*D12-Q12,IF(D12=1,Pre_q+Res_b,0),Floor_q+Res_b) -> 520 | AS12: =MAX(AT12+Cost_round*E12-R12,IF(E12=1,Pre_q+Res_b,0),Floor_q+Res_b) -> 520 | AT12: =MAX(AU12+Cost_round*F12-S12,IF(F12=1,Pre_q+Res_b,0),Floor_q+Res_b) -> 520 | AU12: =MAX(AV12+Cost_round*G12-T12,IF(G12=1,Pre_q+Res_b,0),Floor_q+Res_b) -> 400 | AV12: =MAX(AW12+Cost_round*H12-U12,IF(H12=1,Pre_q+Res_b,0),Floor_q+Res_b) -> 450 | AW12: =End_q+Res_b -> 520 | AX12: =IF(Q_zero>=AQ12-0.000000001,1,0) -> 1 | AY12: =IF($AX12=1,Q_zero-Cost_round*C12+P12-AR12,"") -> 100 | AZ12: =IF($AX12=1,AR12-Cost_round*D12+Q12-AS12,"") -> 0 | BA12: =IF($AX12=1,AS12-Cost_round*E12+R12-AT12,"") -> 0 | BB12: =IF($AX12=1,AT12-Cost_round*F12+S12-AU12,"") -> 70 | BC12: =IF($AX12=1,AU12-Cost_round*G12+T12-AV12,"") -> 20 | BD12: =IF($AX12=1,AV12-Cost_round*H12+U12-AW12,"") -> 0 | BE12: =IF($AX12=1,SUMPRODUCT(AY12:BD12,$AY$6:$BD$6),"") -> 151.13846 | BF12: =IF(AND($AX12=1,Res_b>0),(AK12-BE12)/Res_b,"") -> 0.90909091 | BG12: =IF(AC12>=Goal_b-0.000000001,AK12-Beta_y*Goal_b,"") -> 173.86573 | BH12: =IF(AC12>=Goal_b-0.000000001,IF(AND(AL12>=Goal_S-0.000000001,BG12>=Goal_P-0.000000001),1,0),0) -> 0
A13: 5 | B13: 4, 6 | C13: =MOD(INT($A13/32),2) -> 0 | D13: =MOD(INT($A13/16),2) -> 0 | E13: =MOD(INT($A13/8),2) -> 0 | F13: =MOD(INT($A13/4),2) -> 1 | G13: =MOD(INT($A13/2),2) -> 0 | H13: =MOD(INT($A13/1),2) -> 1 | I13: =SUM(C13:H13) -> 2 | J13: =E_zero+C13*Half_gap*(Ceiling_e-E_zero) -> 71 | K13: =J13+D13*Half_gap*(Ceiling_e-J13) -> 71 | L13: =K13+E13*Half_gap*(Ceiling_e-K13) -> 71 | M13: =L13+F13*Half_gap*(Ceiling_e-L13) -> 78 | N13: =M13+G13*Half_gap*(Ceiling_e-M13) -> 78 | O13: =N13+H13*Half_gap*(Ceiling_e-N13) -> 81.5 | P13: =Val_pt*(J13-E_zero) -> 0 | Q13: =Val_pt*(K13-E_zero) -> 0 | R13: =Val_pt*(L13-E_zero) -> 0 | S13: =Val_pt*(M13-E_zero) -> 70 | T13: =Val_pt*(N13-E_zero) -> 70 | U13: =Val_pt*(O13-E_zero) -> 105 | V13: =MAX(W13+Cost_round*C13-P13,IF(C13=1,Pre_q,0)) -> 470 | W13: =MAX(X13+Cost_round*D13-Q13,IF(D13=1,Pre_q,0),Floor_q) -> 470 | X13: =MAX(Y13+Cost_round*E13-R13,IF(E13=1,Pre_q,0),Floor_q) -> 470 | Y13: =MAX(Z13+Cost_round*F13-S13,IF(F13=1,Pre_q,0),Floor_q) -> 470 | Z13: =MAX(AA13+Cost_round*G13-T13,IF(G13=1,Pre_q,0),Floor_q) -> 415 | AA13: =MAX(AB13+Cost_round*H13-U13,IF(H13=1,Pre_q,0),Floor_q) -> 485 | AB13: =End_q -> 470 | AC13: =Q_zero-V13 -> 150 | AD13: =IF(AC13>=-0.000000001,1,0) -> 1 | AE13: =IF($AD13=1,Q_zero-Cost_round*C13+P13-W13,"") -> 150 | AF13: =IF($AD13=1,W13-Cost_round*D13+Q13-X13,"") -> 0 | AG13: =IF($AD13=1,X13-Cost_round*E13+R13-Y13,"") -> 0 | AH13: =IF($AD13=1,Y13-Cost_round*F13+S13-Z13,"") -> 5 | AI13: =IF($AD13=1,Z13-Cost_round*G13+T13-AA13,"") -> 0 | AJ13: =IF($AD13=1,AA13-Cost_round*H13+U13-AB13,"") -> 0 | AK13: =IF($AD13=1,SUMPRODUCT(AE13:AJ13,$AE$6:$AJ$6),"") -> 139.7787 | AL13: =U13 -> 105 | AM13: =IF(SUMPRODUCT(($AK$8:$AK$71>=AK13-0.000000001)*($AL$8:$AL$71>=AL13-0.000000001)*((($AK$8:$AK$71>AK13+0.000000001)+($AL$8:$AL$71>AL13+0.000000001))>0))>0,1,0) -> 1 | AN13: =1-AM13 -> 0 | AO13: =AK13+W_board*AL13 -> 732.47633 | AP13: =AK13+W_try*AL13 -> 1189.7787 | AQ13: =MAX(AR13+Cost_round*C13-P13,IF(C13=1,Pre_q+Res_b,0)) -> 520 | AR13: =MAX(AS13+Cost_round*D13-Q13,IF(D13=1,Pre_q+Res_b,0),Floor_q+Res_b) -> 520 | AS13: =MAX(AT13+Cost_round*E13-R13,IF(E13=1,Pre_q+Res_b,0),Floor_q+Res_b) -> 520 | AT13: =MAX(AU13+Cost_round*F13-S13,IF(F13=1,Pre_q+Res_b,0),Floor_q+Res_b) -> 520 | AU13: =MAX(AV13+Cost_round*G13-T13,IF(G13=1,Pre_q+Res_b,0),Floor_q+Res_b) -> 465 | AV13: =MAX(AW13+Cost_round*H13-U13,IF(H13=1,Pre_q+Res_b,0),Floor_q+Res_b) -> 535 | AW13: =End_q+Res_b -> 520 | AX13: =IF(Q_zero>=AQ13-0.000000001,1,0) -> 1 | AY13: =IF($AX13=1,Q_zero-Cost_round*C13+P13-AR13,"") -> 100 | AZ13: =IF($AX13=1,AR13-Cost_round*D13+Q13-AS13,"") -> 0 | BA13: =IF($AX13=1,AS13-Cost_round*E13+R13-AT13,"") -> 0 | BB13: =IF($AX13=1,AT13-Cost_round*F13+S13-AU13,"") -> 5 | BC13: =IF($AX13=1,AU13-Cost_round*G13+T13-AV13,"") -> 0 | BD13: =IF($AX13=1,AV13-Cost_round*H13+U13-AW13,"") -> 0 | BE13: =IF($AX13=1,SUMPRODUCT(AY13:BD13,$AY$6:$BD$6),"") -> 94.324158 | BF13: =IF(AND($AX13=1,Res_b>0),(AK13-BE13)/Res_b,"") -> 0.90909091 | BG13: =IF(AC13>=Goal_b-0.000000001,AK13-Beta_y*Goal_b,"") -> 117.05143 | BH13: =IF(AC13>=Goal_b-0.000000001,IF(AND(AL13>=Goal_S-0.000000001,BG13>=Goal_P-0.000000001),1,0),0) -> 0
A14: 6 | B14: 4, 5 | C14: =MOD(INT($A14/32),2) -> 0 | D14: =MOD(INT($A14/16),2) -> 0 | E14: =MOD(INT($A14/8),2) -> 0 | F14: =MOD(INT($A14/4),2) -> 1 | G14: =MOD(INT($A14/2),2) -> 1 | H14: =MOD(INT($A14/1),2) -> 0 | I14: =SUM(C14:H14) -> 2 | J14: =E_zero+C14*Half_gap*(Ceiling_e-E_zero) -> 71 | K14: =J14+D14*Half_gap*(Ceiling_e-J14) -> 71 | L14: =K14+E14*Half_gap*(Ceiling_e-K14) -> 71 | M14: =L14+F14*Half_gap*(Ceiling_e-L14) -> 78 | N14: =M14+G14*Half_gap*(Ceiling_e-M14) -> 81.5 | O14: =N14+H14*Half_gap*(Ceiling_e-N14) -> 81.5 | P14: =Val_pt*(J14-E_zero) -> 0 | Q14: =Val_pt*(K14-E_zero) -> 0 | R14: =Val_pt*(L14-E_zero) -> 0 | S14: =Val_pt*(M14-E_zero) -> 70 | T14: =Val_pt*(N14-E_zero) -> 105 | U14: =Val_pt*(O14-E_zero) -> 105 | V14: =MAX(W14+Cost_round*C14-P14,IF(C14=1,Pre_q,0)) -> 520 | W14: =MAX(X14+Cost_round*D14-Q14,IF(D14=1,Pre_q,0),Floor_q) -> 520 | X14: =MAX(Y14+Cost_round*E14-R14,IF(E14=1,Pre_q,0),Floor_q) -> 520 | Y14: =MAX(Z14+Cost_round*F14-S14,IF(F14=1,Pre_q,0),Floor_q) -> 520 | Z14: =MAX(AA14+Cost_round*G14-T14,IF(G14=1,Pre_q,0),Floor_q) -> 470 | AA14: =MAX(AB14+Cost_round*H14-U14,IF(H14=1,Pre_q,0),Floor_q) -> 365 | AB14: =End_q -> 470 | AC14: =Q_zero-V14 -> 100 | AD14: =IF(AC14>=-0.000000001,1,0) -> 1 | AE14: =IF($AD14=1,Q_zero-Cost_round*C14+P14-W14,"") -> 100 | AF14: =IF($AD14=1,W14-Cost_round*D14+Q14-X14,"") -> 0 | AG14: =IF($AD14=1,X14-Cost_round*E14+R14-Y14,"") -> 0 | AH14: =IF($AD14=1,Y14-Cost_round*F14+S14-Z14,"") -> 0 | AI14: =IF($AD14=1,Z14-Cost_round*G14+T14-AA14,"") -> 90 | AJ14: =IF($AD14=1,AA14-Cost_round*H14+U14-AB14,"") -> 0 | AK14: =IF($AD14=1,SUMPRODUCT(AE14:AJ14,$AE$6:$AJ$6),"") -> 146.79201 | AL14: =U14 -> 105 | AM14: =IF(SUMPRODUCT(($AK$8:$AK$71>=AK14-0.000000001)*($AL$8:$AL$71>=AL14-0.000000001)*((($AK$8:$AK$71>AK14+0.000000001)+($AL$8:$AL$71>AL14+0.000000001))>0))>0,1,0) -> 1 | AN14: =1-AM14 -> 0 | AO14: =AK14+W_board*AL14 -> 739.48964 | AP14: =AK14+W_try*AL14 -> 1196.792 | AQ14: =MAX(AR14+Cost_round*C14-P14,IF(C14=1,Pre_q+Res_b,0)) -> 570 | AR14: =MAX(AS14+Cost_round*D14-Q14,IF(D14=1,Pre_q+Res_b,0),Floor_q+Res_b) -> 570 | AS14: =MAX(AT14+Cost_round*E14-R14,IF(E14=1,Pre_q+Res_b,0),Floor_q+Res_b) -> 570 | AT14: =MAX(AU14+Cost_round*F14-S14,IF(F14=1,Pre_q+Res_b,0),Floor_q+Res_b) -> 570 | AU14: =MAX(AV14+Cost_round*G14-T14,IF(G14=1,Pre_q+Res_b,0),Floor_q+Res_b) -> 520 | AV14: =MAX(AW14+Cost_round*H14-U14,IF(H14=1,Pre_q+Res_b,0),Floor_q+Res_b) -> 415 | AW14: =End_q+Res_b -> 520 | AX14: =IF(Q_zero>=AQ14-0.000000001,1,0) -> 1 | AY14: =IF($AX14=1,Q_zero-Cost_round*C14+P14-AR14,"") -> 50 | AZ14: =IF($AX14=1,AR14-Cost_round*D14+Q14-AS14,"") -> 0 | BA14: =IF($AX14=1,AS14-Cost_round*E14+R14-AT14,"") -> 0 | BB14: =IF($AX14=1,AT14-Cost_round*F14+S14-AU14,"") -> 0 | BC14: =IF($AX14=1,AU14-Cost_round*G14+T14-AV14,"") -> 90 | BD14: =IF($AX14=1,AV14-Cost_round*H14+U14-AW14,"") -> 0 | BE14: =IF($AX14=1,SUMPRODUCT(AY14:BD14,$AY$6:$BD$6),"") -> 101.33746 | BF14: =IF(AND($AX14=1,Res_b>0),(AK14-BE14)/Res_b,"") -> 0.90909091 | BG14: =IF(AC14>=Goal_b-0.000000001,AK14-Beta_y*Goal_b,"") -> 124.06474 | BH14: =IF(AC14>=Goal_b-0.000000001,IF(AND(AL14>=Goal_S-0.000000001,BG14>=Goal_P-0.000000001),1,0),0) -> 0
A15: 7 | B15: 4–6 | C15: =MOD(INT($A15/32),2) -> 0 | D15: =MOD(INT($A15/16),2) -> 0 | E15: =MOD(INT($A15/8),2) -> 0 | F15: =MOD(INT($A15/4),2) -> 1 | G15: =MOD(INT($A15/2),2) -> 1 | H15: =MOD(INT($A15/1),2) -> 1 | I15: =SUM(C15:H15) -> 3 | J15: =E_zero+C15*Half_gap*(Ceiling_e-E_zero) -> 71 | K15: =J15+D15*Half_gap*(Ceiling_e-J15) -> 71 | L15: =K15+E15*Half_gap*(Ceiling_e-K15) -> 71 | M15: =L15+F15*Half_gap*(Ceiling_e-L15) -> 78 | N15: =M15+G15*Half_gap*(Ceiling_e-M15) -> 81.5 | O15: =N15+H15*Half_gap*(Ceiling_e-N15) -> 83.25 | P15: =Val_pt*(J15-E_zero) -> 0 | Q15: =Val_pt*(K15-E_zero) -> 0 | R15: =Val_pt*(L15-E_zero) -> 0 | S15: =Val_pt*(M15-E_zero) -> 70 | T15: =Val_pt*(N15-E_zero) -> 105 | U15: =Val_pt*(O15-E_zero) -> 122.5 | V15: =MAX(W15+Cost_round*C15-P15,IF(C15=1,Pre_q,0)) -> 535 | W15: =MAX(X15+Cost_round*D15-Q15,IF(D15=1,Pre_q,0),Floor_q) -> 535 | X15: =MAX(Y15+Cost_round*E15-R15,IF(E15=1,Pre_q,0),Floor_q) -> 535 | Y15: =MAX(Z15+Cost_round*F15-S15,IF(F15=1,Pre_q,0),Floor_q) -> 535 | Z15: =MAX(AA15+Cost_round*G15-T15,IF(G15=1,Pre_q,0),Floor_q) -> 485 | AA15: =MAX(AB15+Cost_round*H15-U15,IF(H15=1,Pre_q,0),Floor_q) -> 470 | AB15: =End_q -> 470 | AC15: =Q_zero-V15 -> 85 | AD15: =IF(AC15>=-0.000000001,1,0) -> 1 | AE15: =IF($AD15=1,Q_zero-Cost_round*C15+P15-W15,"") -> 85 | AF15: =IF($AD15=1,W15-Cost_round*D15+Q15-X15,"") -> 0 | AG15: =IF($AD15=1,X15-Cost_round*E15+R15-Y15,"") -> 0 | AH15: =IF($AD15=1,Y15-Cost_round*F15+S15-Z15,"") -> 0 | AI15: =IF($AD15=1,Z15-Cost_round*G15+T15-AA15,"") -> 0 | AJ15: =IF($AD15=1,AA15-Cost_round*H15+U15-AB15,"") -> 2.5 | AK15: =IF($AD15=1,SUMPRODUCT(AE15:AJ15,$AE$6:$AJ$6),"") -> 78.683912 | AL15: =U15 -> 122.5 | AM15: =IF(SUMPRODUCT(($AK$8:$AK$71>=AK15-0.000000001)*($AL$8:$AL$71>=AL15-0.000000001)*((($AK$8:$AK$71>AK15+0.000000001)+($AL$8:$AL$71>AL15+0.000000001))>0))>0,1,0) -> 1 | AN15: =1-AM15 -> 0 | AO15: =AK15+W_board*AL15 -> 770.16448 | AP15: =AK15+W_try*AL15 -> 1303.6839 | AQ15: =MAX(AR15+Cost_round*C15-P15,IF(C15=1,Pre_q+Res_b,0)) -> 585 | AR15: =MAX(AS15+Cost_round*D15-Q15,IF(D15=1,Pre_q+Res_b,0),Floor_q+Res_b) -> 585 | AS15: =MAX(AT15+Cost_round*E15-R15,IF(E15=1,Pre_q+Res_b,0),Floor_q+Res_b) -> 585 | AT15: =MAX(AU15+Cost_round*F15-S15,IF(F15=1,Pre_q+Res_b,0),Floor_q+Res_b) -> 585 | AU15: =MAX(AV15+Cost_round*G15-T15,IF(G15=1,Pre_q+Res_b,0),Floor_q+Res_b) -> 535 | AV15: =MAX(AW15+Cost_round*H15-U15,IF(H15=1,Pre_q+Res_b,0),Floor_q+Res_b) -> 520 | AW15: =End_q+Res_b -> 520 | AX15: =IF(Q_zero>=AQ15-0.000000001,1,0) -> 1 | AY15: =IF($AX15=1,Q_zero-Cost_round*C15+P15-AR15,"") -> 35 | AZ15: =IF($AX15=1,AR15-Cost_round*D15+Q15-AS15,"") -> 0 | BA15: =IF($AX15=1,AS15-Cost_round*E15+R15-AT15,"") -> 0 | BB15: =IF($AX15=1,AT15-Cost_round*F15+S15-AU15,"") -> 0 | BC15: =IF($AX15=1,AU15-Cost_round*G15+T15-AV15,"") -> 0 | BD15: =IF($AX15=1,AV15-Cost_round*H15+U15-AW15,"") -> 2.5 | BE15: =IF($AX15=1,SUMPRODUCT(AY15:BD15,$AY$6:$BD$6),"") -> 33.229367 | BF15: =IF(AND($AX15=1,Res_b>0),(AK15-BE15)/Res_b,"") -> 0.90909091 | BG15: =IF(AC15>=Goal_b-0.000000001,AK15-Beta_y*Goal_b,"") -> 55.956639 | BH15: =IF(AC15>=Goal_b-0.000000001,IF(AND(AL15>=Goal_S-0.000000001,BG15>=Goal_P-0.000000001),1,0),0) -> 0
A16: 8 | B16: 3 | C16: =MOD(INT($A16/32),2) -> 0 | D16: =MOD(INT($A16/16),2) -> 0 | E16: =MOD(INT($A16/8),2) -> 1 | F16: =MOD(INT($A16/4),2) -> 0 | G16: =MOD(INT($A16/2),2) -> 0 | H16: =MOD(INT($A16/1),2) -> 0 | I16: =SUM(C16:H16) -> 1 | J16: =E_zero+C16*Half_gap*(Ceiling_e-E_zero) -> 71 | K16: =J16+D16*Half_gap*(Ceiling_e-J16) -> 71 | L16: =K16+E16*Half_gap*(Ceiling_e-K16) -> 78 | M16: =L16+F16*Half_gap*(Ceiling_e-L16) -> 78 | N16: =M16+G16*Half_gap*(Ceiling_e-M16) -> 78 | O16: =N16+H16*Half_gap*(Ceiling_e-N16) -> 78 | P16: =Val_pt*(J16-E_zero) -> 0 | Q16: =Val_pt*(K16-E_zero) -> 0 | R16: =Val_pt*(L16-E_zero) -> 70 | S16: =Val_pt*(M16-E_zero) -> 70 | T16: =Val_pt*(N16-E_zero) -> 70 | U16: =Val_pt*(O16-E_zero) -> 70 | V16: =MAX(W16+Cost_round*C16-P16,IF(C16=1,Pre_q,0)) -> 470 | W16: =MAX(X16+Cost_round*D16-Q16,IF(D16=1,Pre_q,0),Floor_q) -> 470 | X16: =MAX(Y16+Cost_round*E16-R16,IF(E16=1,Pre_q,0),Floor_q) -> 470 | Y16: =MAX(Z16+Cost_round*F16-S16,IF(F16=1,Pre_q,0),Floor_q) -> 350 | Z16: =MAX(AA16+Cost_round*G16-T16,IF(G16=1,Pre_q,0),Floor_q) -> 350 | AA16: =MAX(AB16+Cost_round*H16-U16,IF(H16=1,Pre_q,0),Floor_q) -> 400 | AB16: =End_q -> 470 | AC16: =Q_zero-V16 -> 150 | AD16: =IF(AC16>=-0.000000001,1,0) -> 1 | AE16: =IF($AD16=1,Q_zero-Cost_round*C16+P16-W16,"") -> 150 | AF16: =IF($AD16=1,W16-Cost_round*D16+Q16-X16,"") -> 0 | AG16: =IF($AD16=1,X16-Cost_round*E16+R16-Y16,"") -> 70 | AH16: =IF($AD16=1,Y16-Cost_round*F16+S16-Z16,"") -> 70 | AI16: =IF($AD16=1,Z16-Cost_round*G16+T16-AA16,"") -> 20 | AJ16: =IF($AD16=1,AA16-Cost_round*H16+U16-AB16,"") -> 0 | AK16: =IF($AD16=1,SUMPRODUCT(AE16:AJ16,$AE$6:$AJ$6),"") -> 249.18504 | AL16: =U16 -> 70 | AM16: =IF(SUMPRODUCT(($AK$8:$AK$71>=AK16-0.000000001)*($AL$8:$AL$71>=AL16-0.000000001)*((($AK$8:$AK$71>AK16+0.000000001)+($AL$8:$AL$71>AL16+0.000000001))>0))>0,1,0) -> 1 | AN16: =1-AM16 -> 0 | AO16: =AK16+W_board*AL16 -> 644.31679 | AP16: =AK16+W_try*AL16 -> 949.18504 | AQ16: =MAX(AR16+Cost_round*C16-P16,IF(C16=1,Pre_q+Res_b,0)) -> 520 | AR16: =MAX(AS16+Cost_round*D16-Q16,IF(D16=1,Pre_q+Res_b,0),Floor_q+Res_b) -> 520 | AS16: =MAX(AT16+Cost_round*E16-R16,IF(E16=1,Pre_q+Res_b,0),Floor_q+Res_b) -> 520 | AT16: =MAX(AU16+Cost_round*F16-S16,IF(F16=1,Pre_q+Res_b,0),Floor_q+Res_b) -> 400 | AU16: =MAX(AV16+Cost_round*G16-T16,IF(G16=1,Pre_q+Res_b,0),Floor_q+Res_b) -> 400 | AV16: =MAX(AW16+Cost_round*H16-U16,IF(H16=1,Pre_q+Res_b,0),Floor_q+Res_b) -> 450 | AW16: =End_q+Res_b -> 520 | AX16: =IF(Q_zero>=AQ16-0.000000001,1,0) -> 1 | AY16: =IF($AX16=1,Q_zero-Cost_round*C16+P16-AR16,"") -> 100 | AZ16: =IF($AX16=1,AR16-Cost_round*D16+Q16-AS16,"") -> 0 | BA16: =IF($AX16=1,AS16-Cost_round*E16+R16-AT16,"") -> 70 | BB16: =IF($AX16=1,AT16-Cost_round*F16+S16-AU16,"") -> 70 | BC16: =IF($AX16=1,AU16-Cost_round*G16+T16-AV16,"") -> 20 | BD16: =IF($AX16=1,AV16-Cost_round*H16+U16-AW16,"") -> 0 | BE16: =IF($AX16=1,SUMPRODUCT(AY16:BD16,$AY$6:$BD$6),"") -> 203.7305 | BF16: =IF(AND($AX16=1,Res_b>0),(AK16-BE16)/Res_b,"") -> 0.90909091 | BG16: =IF(AC16>=Goal_b-0.000000001,AK16-Beta_y*Goal_b,"") -> 226.45777 | BH16: =IF(AC16>=Goal_b-0.000000001,IF(AND(AL16>=Goal_S-0.000000001,BG16>=Goal_P-0.000000001),1,0),0) -> 0
A17: 9 | B17: 3, 6 | C17: =MOD(INT($A17/32),2) -> 0 | D17: =MOD(INT($A17/16),2) -> 0 | E17: =MOD(INT($A17/8),2) -> 1 | F17: =MOD(INT($A17/4),2) -> 0 | G17: =MOD(INT($A17/2),2) -> 0 | H17: =MOD(INT($A17/1),2) -> 1 | I17: =SUM(C17:H17) -> 2 | J17: =E_zero+C17*Half_gap*(Ceiling_e-E_zero) -> 71 | K17: =J17+D17*Half_gap*(Ceiling_e-J17) -> 71 | L17: =K17+E17*Half_gap*(Ceiling_e-K17) -> 78 | M17: =L17+F17*Half_gap*(Ceiling_e-L17) -> 78 | N17: =M17+G17*Half_gap*(Ceiling_e-M17) -> 78 | O17: =N17+H17*Half_gap*(Ceiling_e-N17) -> 81.5 | P17: =Val_pt*(J17-E_zero) -> 0 | Q17: =Val_pt*(K17-E_zero) -> 0 | R17: =Val_pt*(L17-E_zero) -> 70 | S17: =Val_pt*(M17-E_zero) -> 70 | T17: =Val_pt*(N17-E_zero) -> 70 | U17: =Val_pt*(O17-E_zero) -> 105 | V17: =MAX(W17+Cost_round*C17-P17,IF(C17=1,Pre_q,0)) -> 470 | W17: =MAX(X17+Cost_round*D17-Q17,IF(D17=1,Pre_q,0),Floor_q) -> 470 | X17: =MAX(Y17+Cost_round*E17-R17,IF(E17=1,Pre_q,0),Floor_q) -> 470 | Y17: =MAX(Z17+Cost_round*F17-S17,IF(F17=1,Pre_q,0),Floor_q) -> 350 | Z17: =MAX(AA17+Cost_round*G17-T17,IF(G17=1,Pre_q,0),Floor_q) -> 415 | AA17: =MAX(AB17+Cost_round*H17-U17,IF(H17=1,Pre_q,0),Floor_q) -> 485 | AB17: =End_q -> 470 | AC17: =Q_zero-V17 -> 150 | AD17: =IF(AC17>=-0.000000001,1,0) -> 1 | AE17: =IF($AD17=1,Q_zero-Cost_round*C17+P17-W17,"") -> 150 | AF17: =IF($AD17=1,W17-Cost_round*D17+Q17-X17,"") -> 0 | AG17: =IF($AD17=1,X17-Cost_round*E17+R17-Y17,"") -> 70 | AH17: =IF($AD17=1,Y17-Cost_round*F17+S17-Z17,"") -> 5 | AI17: =IF($AD17=1,Z17-Cost_round*G17+T17-AA17,"") -> 0 | AJ17: =IF($AD17=1,AA17-Cost_round*H17+U17-AB17,"") -> 0 | AK17: =IF($AD17=1,SUMPRODUCT(AE17:AJ17,$AE$6:$AJ$6),"") -> 192.37074 | AL17: =U17 -> 105 | AM17: =IF(SUMPRODUCT(($AK$8:$AK$71>=AK17-0.000000001)*($AL$8:$AL$71>=AL17-0.000000001)*((($AK$8:$AK$71>AK17+0.000000001)+($AL$8:$AL$71>AL17+0.000000001))>0))>0,1,0) -> 1 | AN17: =1-AM17 -> 0 | AO17: =AK17+W_board*AL17 -> 785.06837 | AP17: =AK17+W_try*AL17 -> 1242.3707 | AQ17: =MAX(AR17+Cost_round*C17-P17,IF(C17=1,Pre_q+Res_b,0)) -> 520 | AR17: =MAX(AS17+Cost_round*D17-Q17,IF(D17=1,Pre_q+Res_b,0),Floor_q+Res_b) -> 520 | AS17: =MAX(AT17+Cost_round*E17-R17,IF(E17=1,Pre_q+Res_b,0),Floor_q+Res_b) -> 520 | AT17: =MAX(AU17+Cost_round*F17-S17,IF(F17=1,Pre_q+Res_b,0),Floor_q+Res_b) -> 400 | AU17: =MAX(AV17+Cost_round*G17-T17,IF(G17=1,Pre_q+Res_b,0),Floor_q+Res_b) -> 465 | AV17: =MAX(AW17+Cost_round*H17-U17,IF(H17=1,Pre_q+Res_b,0),Floor_q+Res_b) -> 535 | AW17: =End_q+Res_b -> 520 | AX17: =IF(Q_zero>=AQ17-0.000000001,1,0) -> 1 | AY17: =IF($AX17=1,Q_zero-Cost_round*C17+P17-AR17,"") -> 100 | AZ17: =IF($AX17=1,AR17-Cost_round*D17+Q17-AS17,"") -> 0 | BA17: =IF($AX17=1,AS17-Cost_round*E17+R17-AT17,"") -> 70 | BB17: =IF($AX17=1,AT17-Cost_round*F17+S17-AU17,"") -> 5 | BC17: =IF($AX17=1,AU17-Cost_round*G17+T17-AV17,"") -> 0 | BD17: =IF($AX17=1,AV17-Cost_round*H17+U17-AW17,"") -> 0 | BE17: =IF($AX17=1,SUMPRODUCT(AY17:BD17,$AY$6:$BD$6),"") -> 146.91619 | BF17: =IF(AND($AX17=1,Res_b>0),(AK17-BE17)/Res_b,"") -> 0.90909091 | BG17: =IF(AC17>=Goal_b-0.000000001,AK17-Beta_y*Goal_b,"") -> 169.64347 | BH17: =IF(AC17>=Goal_b-0.000000001,IF(AND(AL17>=Goal_S-0.000000001,BG17>=Goal_P-0.000000001),1,0),0) -> 0
A18: 10 | B18: 3, 5 | C18: =MOD(INT($A18/32),2) -> 0 | D18: =MOD(INT($A18/16),2) -> 0 | E18: =MOD(INT($A18/8),2) -> 1 | F18: =MOD(INT($A18/4),2) -> 0 | G18: =MOD(INT($A18/2),2) -> 1 | H18: =MOD(INT($A18/1),2) -> 0 | I18: =SUM(C18:H18) -> 2 | J18: =E_zero+C18*Half_gap*(Ceiling_e-E_zero) -> 71 | K18: =J18+D18*Half_gap*(Ceiling_e-J18) -> 71 | L18: =K18+E18*Half_gap*(Ceiling_e-K18) -> 78 | M18: =L18+F18*Half_gap*(Ceiling_e-L18) -> 78 | N18: =M18+G18*Half_gap*(Ceiling_e-M18) -> 81.5 | O18: =N18+H18*Half_gap*(Ceiling_e-N18) -> 81.5 | P18: =Val_pt*(J18-E_zero) -> 0 | Q18: =Val_pt*(K18-E_zero) -> 0 | R18: =Val_pt*(L18-E_zero) -> 70 | S18: =Val_pt*(M18-E_zero) -> 70 | T18: =Val_pt*(N18-E_zero) -> 105 | U18: =Val_pt*(O18-E_zero) -> 105 | V18: =MAX(W18+Cost_round*C18-P18,IF(C18=1,Pre_q,0)) -> 470 | W18: =MAX(X18+Cost_round*D18-Q18,IF(D18=1,Pre_q,0),Floor_q) -> 470 | X18: =MAX(Y18+Cost_round*E18-R18,IF(E18=1,Pre_q,0),Floor_q) -> 470 | Y18: =MAX(Z18+Cost_round*F18-S18,IF(F18=1,Pre_q,0),Floor_q) -> 400 | Z18: =MAX(AA18+Cost_round*G18-T18,IF(G18=1,Pre_q,0),Floor_q) -> 470 | AA18: =MAX(AB18+Cost_round*H18-U18,IF(H18=1,Pre_q,0),Floor_q) -> 365 | AB18: =End_q -> 470 | AC18: =Q_zero-V18 -> 150 | AD18: =IF(AC18>=-0.000000001,1,0) -> 1 | AE18: =IF($AD18=1,Q_zero-Cost_round*C18+P18-W18,"") -> 150 | AF18: =IF($AD18=1,W18-Cost_round*D18+Q18-X18,"") -> 0 | AG18: =IF($AD18=1,X18-Cost_round*E18+R18-Y18,"") -> 20 | AH18: =IF($AD18=1,Y18-Cost_round*F18+S18-Z18,"") -> 0 | AI18: =IF($AD18=1,Z18-Cost_round*G18+T18-AA18,"") -> 90 | AJ18: =IF($AD18=1,AA18-Cost_round*H18+U18-AB18,"") -> 0 | AK18: =IF($AD18=1,SUMPRODUCT(AE18:AJ18,$AE$6:$AJ$6),"") -> 207.27285 | AL18: =U18 -> 105 | AM18: =IF(SUMPRODUCT(($AK$8:$AK$71>=AK18-0.000000001)*($AL$8:$AL$71>=AL18-0.000000001)*((($AK$8:$AK$71>AK18+0.000000001)+($AL$8:$AL$71>AL18+0.000000001))>0))>0,1,0) -> 1 | AN18: =1-AM18 -> 0 | AO18: =AK18+W_board*AL18 -> 799.97048 | AP18: =AK18+W_try*AL18 -> 1257.2729 | AQ18: =MAX(AR18+Cost_round*C18-P18,IF(C18=1,Pre_q+Res_b,0)) -> 520 | AR18: =MAX(AS18+Cost_round*D18-Q18,IF(D18=1,Pre_q+Res_b,0),Floor_q+Res_b) -> 520 | AS18: =MAX(AT18+Cost_round*E18-R18,IF(E18=1,Pre_q+Res_b,0),Floor_q+Res_b) -> 520 | AT18: =MAX(AU18+Cost_round*F18-S18,IF(F18=1,Pre_q+Res_b,0),Floor_q+Res_b) -> 450 | AU18: =MAX(AV18+Cost_round*G18-T18,IF(G18=1,Pre_q+Res_b,0),Floor_q+Res_b) -> 520 | AV18: =MAX(AW18+Cost_round*H18-U18,IF(H18=1,Pre_q+Res_b,0),Floor_q+Res_b) -> 415 | AW18: =End_q+Res_b -> 520 | AX18: =IF(Q_zero>=AQ18-0.000000001,1,0) -> 1 | AY18: =IF($AX18=1,Q_zero-Cost_round*C18+P18-AR18,"") -> 100 | AZ18: =IF($AX18=1,AR18-Cost_round*D18+Q18-AS18,"") -> 0 | BA18: =IF($AX18=1,AS18-Cost_round*E18+R18-AT18,"") -> 20 | BB18: =IF($AX18=1,AT18-Cost_round*F18+S18-AU18,"") -> 0 | BC18: =IF($AX18=1,AU18-Cost_round*G18+T18-AV18,"") -> 90 | BD18: =IF($AX18=1,AV18-Cost_round*H18+U18-AW18,"") -> 0 | BE18: =IF($AX18=1,SUMPRODUCT(AY18:BD18,$AY$6:$BD$6),"") -> 161.81831 | BF18: =IF(AND($AX18=1,Res_b>0),(AK18-BE18)/Res_b,"") -> 0.90909091 | BG18: =IF(AC18>=Goal_b-0.000000001,AK18-Beta_y*Goal_b,"") -> 184.54558 | BH18: =IF(AC18>=Goal_b-0.000000001,IF(AND(AL18>=Goal_S-0.000000001,BG18>=Goal_P-0.000000001),1,0),0) -> 0
A19: 11 | B19: 3, 5, 6 | C19: =MOD(INT($A19/32),2) -> 0 | D19: =MOD(INT($A19/16),2) -> 0 | E19: =MOD(INT($A19/8),2) -> 1 | F19: =MOD(INT($A19/4),2) -> 0 | G19: =MOD(INT($A19/2),2) -> 1 | H19: =MOD(INT($A19/1),2) -> 1 | I19: =SUM(C19:H19) -> 3 | J19: =E_zero+C19*Half_gap*(Ceiling_e-E_zero) -> 71 | K19: =J19+D19*Half_gap*(Ceiling_e-J19) -> 71 | L19: =K19+E19*Half_gap*(Ceiling_e-K19) -> 78 | M19: =L19+F19*Half_gap*(Ceiling_e-L19) -> 78 | N19: =M19+G19*Half_gap*(Ceiling_e-M19) -> 81.5 | O19: =N19+H19*Half_gap*(Ceiling_e-N19) -> 83.25 | P19: =Val_pt*(J19-E_zero) -> 0 | Q19: =Val_pt*(K19-E_zero) -> 0 | R19: =Val_pt*(L19-E_zero) -> 70 | S19: =Val_pt*(M19-E_zero) -> 70 | T19: =Val_pt*(N19-E_zero) -> 105 | U19: =Val_pt*(O19-E_zero) -> 122.5 | V19: =MAX(W19+Cost_round*C19-P19,IF(C19=1,Pre_q,0)) -> 470 | W19: =MAX(X19+Cost_round*D19-Q19,IF(D19=1,Pre_q,0),Floor_q) -> 470 | X19: =MAX(Y19+Cost_round*E19-R19,IF(E19=1,Pre_q,0),Floor_q) -> 470 | Y19: =MAX(Z19+Cost_round*F19-S19,IF(F19=1,Pre_q,0),Floor_q) -> 415 | Z19: =MAX(AA19+Cost_round*G19-T19,IF(G19=1,Pre_q,0),Floor_q) -> 485 | AA19: =MAX(AB19+Cost_round*H19-U19,IF(H19=1,Pre_q,0),Floor_q) -> 470 | AB19: =End_q -> 470 | AC19: =Q_zero-V19 -> 150 | AD19: =IF(AC19>=-0.000000001,1,0) -> 1 | AE19: =IF($AD19=1,Q_zero-Cost_round*C19+P19-W19,"") -> 150 | AF19: =IF($AD19=1,W19-Cost_round*D19+Q19-X19,"") -> 0 | AG19: =IF($AD19=1,X19-Cost_round*E19+R19-Y19,"") -> 5 | AH19: =IF($AD19=1,Y19-Cost_round*F19+S19-Z19,"") -> 0 | AI19: =IF($AD19=1,Z19-Cost_round*G19+T19-AA19,"") -> 0 | AJ19: =IF($AD19=1,AA19-Cost_round*H19+U19-AB19,"") -> 2.5 | AK19: =IF($AD19=1,SUMPRODUCT(AE19:AJ19,$AE$6:$AJ$6),"") -> 141.5314 | AL19: =U19 -> 122.5 | AM19: =IF(SUMPRODUCT(($AK$8:$AK$71>=AK19-0.000000001)*($AL$8:$AL$71>=AL19-0.000000001)*((($AK$8:$AK$71>AK19+0.000000001)+($AL$8:$AL$71>AL19+0.000000001))>0))>0,1,0) -> 1 | AN19: =1-AM19 -> 0 | AO19: =AK19+W_board*AL19 -> 833.01196 | AP19: =AK19+W_try*AL19 -> 1366.5314 | AQ19: =MAX(AR19+Cost_round*C19-P19,IF(C19=1,Pre_q+Res_b,0)) -> 520 | AR19: =MAX(AS19+Cost_round*D19-Q19,IF(D19=1,Pre_q+Res_b,0),Floor_q+Res_b) -> 520 | AS19: =MAX(AT19+Cost_round*E19-R19,IF(E19=1,Pre_q+Res_b,0),Floor_q+Res_b) -> 520 | AT19: =MAX(AU19+Cost_round*F19-S19,IF(F19=1,Pre_q+Res_b,0),Floor_q+Res_b) -> 465 | AU19: =MAX(AV19+Cost_round*G19-T19,IF(G19=1,Pre_q+Res_b,0),Floor_q+Res_b) -> 535 | AV19: =MAX(AW19+Cost_round*H19-U19,IF(H19=1,Pre_q+Res_b,0),Floor_q+Res_b) -> 520 | AW19: =End_q+Res_b -> 520 | AX19: =IF(Q_zero>=AQ19-0.000000001,1,0) -> 1 | AY19: =IF($AX19=1,Q_zero-Cost_round*C19+P19-AR19,"") -> 100 | AZ19: =IF($AX19=1,AR19-Cost_round*D19+Q19-AS19,"") -> 0 | BA19: =IF($AX19=1,AS19-Cost_round*E19+R19-AT19,"") -> 5 | BB19: =IF($AX19=1,AT19-Cost_round*F19+S19-AU19,"") -> 0 | BC19: =IF($AX19=1,AU19-Cost_round*G19+T19-AV19,"") -> 0 | BD19: =IF($AX19=1,AV19-Cost_round*H19+U19-AW19,"") -> 2.5 | BE19: =IF($AX19=1,SUMPRODUCT(AY19:BD19,$AY$6:$BD$6),"") -> 96.07685 | BF19: =IF(AND($AX19=1,Res_b>0),(AK19-BE19)/Res_b,"") -> 0.90909091 | BG19: =IF(AC19>=Goal_b-0.000000001,AK19-Beta_y*Goal_b,"") -> 118.80412 | BH19: =IF(AC19>=Goal_b-0.000000001,IF(AND(AL19>=Goal_S-0.000000001,BG19>=Goal_P-0.000000001),1,0),0) -> 0
... A71: 63 | B71: 1–6 | C71: =MOD(INT($A71/32),2) -> 1 | D71: =MOD(INT($A71/16),2) -> 1 | E71: =MOD(INT($A71/8),2) -> 1 | F71: =MOD(INT($A71/4),2) -> 1 | G71: =MOD(INT($A71/2),2) -> 1 | H71: =MOD(INT($A71/1),2) -> 1 | I71: =SUM(C71:H71) -> 6 | J71: =E_zero+C71*Half_gap*(Ceiling_e-E_zero) -> 78 | K71: =J71+D71*Half_gap*(Ceiling_e-J71) -> 81.5 | L71: =K71+E71*Half_gap*(Ceiling_e-K71) -> 83.25 | M71: =L71+F71*Half_gap*(Ceiling_e-L71) -> 84.125 | N71: =M71+G71*Half_gap*(Ceiling_e-M71) -> 84.5625 | O71: =N71+H71*Half_gap*(Ceiling_e-N71) -> 84.78125 | P71: =Val_pt*(J71-E_zero) -> 70 | Q71: =Val_pt*(K71-E_zero) -> 105 | R71: =Val_pt*(L71-E_zero) -> 122.5 | S71: =Val_pt*(M71-E_zero) -> 131.25 | T71: =Val_pt*(N71-E_zero) -> 135.625 | U71: =Val_pt*(O71-E_zero) -> 137.8125 | V71: =MAX(W71+Cost_round*C71-P71,IF(C71=1,Pre_q,0)) -> 535 | W71: =MAX(X71+Cost_round*D71-Q71,IF(D71=1,Pre_q,0),Floor_q) -> 485 | X71: =MAX(Y71+Cost_round*E71-R71,IF(E71=1,Pre_q,0),Floor_q) -> 470 | Y71: =MAX(Z71+Cost_round*F71-S71,IF(F71=1,Pre_q,0),Floor_q) -> 470 | Z71: =MAX(AA71+Cost_round*G71-T71,IF(G71=1,Pre_q,0),Floor_q) -> 470 | AA71: =MAX(AB71+Cost_round*H71-U71,IF(H71=1,Pre_q,0),Floor_q) -> 470 | AB71: =End_q -> 470 | AC71: =Q_zero-V71 -> 85 | AD71: =IF(AC71>=-0.000000001,1,0) -> 1 | AE71: =IF($AD71=1,Q_zero-Cost_round*C71+P71-W71,"") -> 85 | AF71: =IF($AD71=1,W71-Cost_round*D71+Q71-X71,"") -> 0 | AG71: =IF($AD71=1,X71-Cost_round*E71+R71-Y71,"") -> 2.5 | AH71: =IF($AD71=1,Y71-Cost_round*F71+S71-Z71,"") -> 11.25 | AI71: =IF($AD71=1,Z71-Cost_round*G71+T71-AA71,"") -> 15.625 | AJ71: =IF($AD71=1,AA71-Cost_round*H71+U71-AB71,"") -> 17.8125 | AK71: =IF($AD71=1,SUMPRODUCT(AE71:AJ71,$AE$6:$AJ$6),"") -> 106.5915 | AL71: =U71 -> 137.8125 | AM71: =IF(SUMPRODUCT(($AK$8:$AK$71>=AK71-0.000000001)*($AL$8:$AL$71>=AL71-0.000000001)*((($AK$8:$AK$71>AK71+0.000000001)+($AL$8:$AL$71>AL71+0.000000001))>0))>0,1,0) -> 0 | AN71: =1-AM71 -> 1 | AO71: =AK71+W_board*AL71 -> 884.50714 | AP71: =AK71+W_try*AL71 -> 1484.7165 | AQ71: =MAX(AR71+Cost_round*C71-P71,IF(C71=1,Pre_q+Res_b,0)) -> 585 | AR71: =MAX(AS71+Cost_round*D71-Q71,IF(D71=1,Pre_q+Res_b,0),Floor_q+Res_b) -> 535 | AS71: =MAX(AT71+Cost_round*E71-R71,IF(E71=1,Pre_q+Res_b,0),Floor_q+Res_b) -> 520 | AT71: =MAX(AU71+Cost_round*F71-S71,IF(F71=1,Pre_q+Res_b,0),Floor_q+Res_b) -> 520 | AU71: =MAX(AV71+Cost_round*G71-T71,IF(G71=1,Pre_q+Res_b,0),Floor_q+Res_b) -> 520 | AV71: =MAX(AW71+Cost_round*H71-U71,IF(H71=1,Pre_q+Res_b,0),Floor_q+Res_b) -> 520 | AW71: =End_q+Res_b -> 520 | AX71: =IF(Q_zero>=AQ71-0.000000001,1,0) -> 1 | AY71: =IF($AX71=1,Q_zero-Cost_round*C71+P71-AR71,"") -> 35 | AZ71: =IF($AX71=1,AR71-Cost_round*D71+Q71-AS71,"") -> 0 | BA71: =IF($AX71=1,AS71-Cost_round*E71+R71-AT71,"") -> 2.5 | BB71: =IF($AX71=1,AT71-Cost_round*F71+S71-AU71,"") -> 11.25 | BC71: =IF($AX71=1,AU71-Cost_round*G71+T71-AV71,"") -> 15.625 | BD71: =IF($AX71=1,AV71-Cost_round*H71+U71-AW71,"") -> 17.8125 | BE71: =IF($AX71=1,SUMPRODUCT(AY71:BD71,$AY$6:$BD$6),"") -> 61.136958 | BF71: =IF(AND($AX71=1,Res_b>0),(AK71-BE71)/Res_b,"") -> 0.90909091 | BG71: =IF(AC71>=Goal_b-0.000000001,AK71-Beta_y*Goal_b,"") -> 83.86423 | BH71: =IF(AC71>=Goal_b-0.000000001,IF(AND(AL71>=Goal_S-0.000000001,BG71>=Goal_P-0.000000001),1,0),0) -> 0

Sheet Frontier
A1: The frontier first: dominated and efficient schedules, their prices, and the board's weighted sum (Theorems 12.1 and 12.2; Worked Example 12.1, Steps 2-3; Figure 12.1; AXIOM Lab 2.12, steps 1-2)
A2: No reserve. A schedule is dominated when another pays at least as much and saves at least as much, and more of one. Savings depend only on the number of rounds, so only the best schedule with each number can be efficient.
A4: Schedules that keep every commitment, no reserve | B4: =SUM(Sch_feas) -> 64 | C4: All 64 (Step 2)
A5: Dominated | B5: =SUM(Sch_dom) -> 59 | C5: 59
A6: Efficient | B6: =COUNTIFS(Sch_dom,0,Sch_feas,1) -> 5 | C6: Five: the best with two to six rounds
A8: Rounds n | B8: Best payouts (PV) | C8: Its schedule # | D8: Rounds (years) | E8: Savings, year 6 | F8: Efficient? | G8: Board value | H8: p1 | I8: p2 | J8: p3 | K8: p4 | L8: p5 | M8: p6
A9: 0 | B9: =_xlfn.MAXIFS(Sch_P0,Sch_n,A9) -> 136.36364 | C9: =_xlfn.MINIFS(Sch_idx,Sch_n,A9,Sch_P0,">="&(B9-0.000000001)) -> 0 | D9: =INDEX(Sch_label,C9+1) -> none | E9: =INDEX(Sch_S6,C9+1) -> 0 | F9: =IF(INDEX(Sch_dom,C9+1)=1,"dominated","efficient") -> dominated | G9: =B9+W_board*E9 -> 136.36364 | H9: =INDEX(Sch_p1,$C9+1) -> 150 | I9: =INDEX(Sch_p2,$C9+1) -> 0 | J9: =INDEX(Sch_p3,$C9+1) -> 0 | K9: =INDEX(Sch_p4,$C9+1) -> 0 | L9: =INDEX(Sch_p5,$C9+1) -> 0 | M9: =INDEX(Sch_p6,$C9+1) -> 0
A10: 1 | B10: =_xlfn.MAXIFS(Sch_P0,Sch_n,A10) -> 370.67264 | C10: =_xlfn.MINIFS(Sch_idx,Sch_n,A10,Sch_P0,">="&(B10-0.000000001)) -> 32 | D10: =INDEX(Sch_label,C10+1) -> 1 | E10: =INDEX(Sch_S6,C10+1) -> 70 | F10: =IF(INDEX(Sch_dom,C10+1)=1,"dominated","efficient") -> dominated | G10: =B10+W_board*E10 -> 765.8044 | H10: =INDEX(Sch_p1,$C10+1) -> 220 | I10: =INDEX(Sch_p2,$C10+1) -> 70 | J10: =INDEX(Sch_p3,$C10+1) -> 70 | K10: =INDEX(Sch_p4,$C10+1) -> 70 | L10: =INDEX(Sch_p5,$C10+1) -> 20 | M10: =INDEX(Sch_p6,$C10+1) -> 0
A11: 2 | B11: =_xlfn.MAXIFS(Sch_P0,Sch_n,A11) -> 384.17334 | C11: =_xlfn.MINIFS(Sch_idx,Sch_n,A11,Sch_P0,">="&(B11-0.000000001)) -> 48 | D11: =INDEX(Sch_label,C11+1) -> 1, 2 | E11: =INDEX(Sch_S6,C11+1) -> 105 | F11: =IF(INDEX(Sch_dom,C11+1)=1,"dominated","efficient") -> efficient | G11: =B11+W_board*E11 -> 976.87096 | H11: =INDEX(Sch_p1,$C11+1) -> 100 | I11: =INDEX(Sch_p2,$C11+1) -> 105 | J11: =INDEX(Sch_p3,$C11+1) -> 105 | K11: =INDEX(Sch_p4,$C11+1) -> 105 | L11: =INDEX(Sch_p5,$C11+1) -> 90 | M11: =INDEX(Sch_p6,$C11+1) -> 0
A12: 3 | B12: =_xlfn.MAXIFS(Sch_P0,Sch_n,A12) -> 330.45199 | C12: =_xlfn.MINIFS(Sch_idx,Sch_n,A12,Sch_P0,">="&(B12-0.000000001)) -> 56 | D12: =INDEX(Sch_label,C12+1) -> 1–3 | E12: =INDEX(Sch_S6,C12+1) -> 122.5 | F12: =IF(INDEX(Sch_dom,C12+1)=1,"dominated","efficient") -> efficient | G12: =B12+W_board*E12 -> 1021.9325 | H12: =INDEX(Sch_p1,$C12+1) -> 85 | I12: =INDEX(Sch_p2,$C12+1) -> 0 | J12: =INDEX(Sch_p3,$C12+1) -> 122.5 | K12: =INDEX(Sch_p4,$C12+1) -> 122.5 | L12: =INDEX(Sch_p5,$C12+1) -> 122.5 | M12: =INDEX(Sch_p6,$C12+1) -> 2.5
A13: 4 | B13: =_xlfn.MAXIFS(Sch_P0,Sch_n,A13) -> 260.88057 | C13: =_xlfn.MINIFS(Sch_idx,Sch_n,A13,Sch_P0,">="&(B13-0.000000001)) -> 57 | D13: =INDEX(Sch_label,C13+1) -> 1–3, 6 | E13: =INDEX(Sch_S6,C13+1) -> 131.25 | F13: =IF(INDEX(Sch_dom,C13+1)=1,"dominated","efficient") -> efficient | G13: =B13+W_board*E13 -> 1001.7526 | H13: =INDEX(Sch_p1,$C13+1) -> 85 | I13: =INDEX(Sch_p2,$C13+1) -> 0 | J13: =INDEX(Sch_p3,$C13+1) -> 122.5 | K13: =INDEX(Sch_p4,$C13+1) -> 122.5 | L13: =INDEX(Sch_p5,$C13+1) -> 2.5 | M13: =INDEX(Sch_p6,$C13+1) -> 11.25
A14: 5 | B14: =_xlfn.MAXIFS(Sch_P0,Sch_n,A14) -> 186.82159 | C14: =_xlfn.MINIFS(Sch_idx,Sch_n,A14,Sch_P0,">="&(B14-0.000000001)) -> 59 | D14: =INDEX(Sch_label,C14+1) -> 1–3, 5, 6 | E14: =INDEX(Sch_S6,C14+1) -> 135.625 | F14: =IF(INDEX(Sch_dom,C14+1)=1,"dominated","efficient") -> efficient | G14: =B14+W_board*E14 -> 952.38936 | H14: =INDEX(Sch_p1,$C14+1) -> 85 | I14: =INDEX(Sch_p2,$C14+1) -> 0 | J14: =INDEX(Sch_p3,$C14+1) -> 122.5 | K14: =INDEX(Sch_p4,$C14+1) -> 2.5 | L14: =INDEX(Sch_p5,$C14+1) -> 11.25 | M14: =INDEX(Sch_p6,$C14+1) -> 15.625
A15: 6 | B15: =_xlfn.MAXIFS(Sch_P0,Sch_n,A15) -> 106.5915 | C15: =_xlfn.MINIFS(Sch_idx,Sch_n,A15,Sch_P0,">="&(B15-0.000000001)) -> 63 | D15: =INDEX(Sch_label,C15+1) -> 1–6 | E15: =INDEX(Sch_S6,C15+1) -> 137.8125 | F15: =IF(INDEX(Sch_dom,C15+1)=1,"dominated","efficient") -> efficient | G15: =B15+W_board*E15 -> 884.50714 | H15: =INDEX(Sch_p1,$C15+1) -> 85 | I15: =INDEX(Sch_p2,$C15+1) -> 0 | J15: =INDEX(Sch_p3,$C15+1) -> 2.5 | K15: =INDEX(Sch_p4,$C15+1) -> 11.25 | L15: =INDEX(Sch_p5,$C15+1) -> 15.625 | M15: =INDEX(Sch_p6,$C15+1) -> 17.8125
A17: Three rounds: year-end cash, years 1 to 6 | H17: =Q_zero-Cost_round*INDEX(Sch_z1,$C$12+1)+INDEX(Sch_s1,$C$12+1)-H12 -> 485 | I17: =H17-Cost_round*INDEX(Sch_z2,$C$12+1)+INDEX(Sch_s2,$C$12+1)-I12 -> 470 | J17: =I17-Cost_round*INDEX(Sch_z3,$C$12+1)+INDEX(Sch_s3,$C$12+1)-J12 -> 350 | K17: =J17-Cost_round*INDEX(Sch_z4,$C$12+1)+INDEX(Sch_s4,$C$12+1)-K12 -> 350 | L17: =K17-Cost_round*INDEX(Sch_z5,$C$12+1)+INDEX(Sch_s5,$C$12+1)-L12 -> 350 | M17: =L17-Cost_round*INDEX(Sch_z6,$C$12+1)+INDEX(Sch_S6,$C$12+1)-M12 -> 470
A18: Three rounds: paid out in all | B18: =SUM(H12:M12) -> 455 | C18: $455 million (Worked Example 12.1)
A19: One round is dominated by two (1 = yes) | B19: =IF(AND(B11>=B10,E11>=E10,OR(B11>B10,E11>E10)),1,0) -> 1 | C19: Two rounds pay more and save more
A21: From (rounds) | B21: To (rounds) | C21: Payouts given up | D21: Savings gained, a year | E21: Price: payouts per dollar a year
A22: 2 | B22: 3 | C22: =INDEX($B$9:$B$15,A22+1)-INDEX($B$9:$B$15,B22+1) -> 53.721351 | D22: =INDEX($E$9:$E$15,B22+1)-INDEX($E$9:$E$15,A22+1) -> 17.5 | E22: =C22/D22 -> 3.0697915
A23: 3 | B23: 4 | C23: =INDEX($B$9:$B$15,A23+1)-INDEX($B$9:$B$15,B23+1) -> 69.571412 | D23: =INDEX($E$9:$E$15,B23+1)-INDEX($E$9:$E$15,A23+1) -> 8.75 | E23: =C23/D23 -> 7.9510185
A24: 4 | B24: 5 | C24: =INDEX($B$9:$B$15,A24+1)-INDEX($B$9:$B$15,B24+1) -> 74.05898 | D24: =INDEX($E$9:$E$15,B24+1)-INDEX($E$9:$E$15,A24+1) -> 4.375 | E24: =C24/D24 -> 16.927767
A25: 5 | B25: 6 | C25: =INDEX($B$9:$B$15,A25+1)-INDEX($B$9:$B$15,B25+1) -> 80.230091 | D25: =INDEX($E$9:$E$15,B25+1)-INDEX($E$9:$E$15,A25+1) -> 2.1875 | E25: =C25/D25 -> 36.676613
A26: The prices rise along the frontier (1 = yes) | B26: =IF(AND(E22<E23,E23<E24,E24<E25),1,0) -> 1 | C26: So with no reserve every efficient plan wins some weighted sum
A28: Rounds | B28: Wins a weighted sum for prices from | C28: to
A29: 2 | B29: 0 | C29: =E22 -> 3.0697915
A30: 3 | B30: =E22 -> 3.0697915 | C30: =E23 -> 7.9510185
A31: 4 | B31: =E23 -> 7.9510185 | C31: =E24 -> 16.927767
A32: 5 | B32: =E24 -> 16.927767 | C32: =E25 -> 36.676613
A33: 6 | B33: =E25 -> 36.676613 | C33: and above
A35: Chapter 5's price of savings, w | B35: =W_board -> 5.6447393 | C35: $5.645 (Section 12.2)
A36: The board's value of its best plan | B36: =MAX(Sch_board) -> 1021.9325 | C36: $1,021.93 million (Section 12.1)
A37: Its schedule # | B37: =MATCH(B36,Sch_board,0)-1 -> 56
A38: Rounds (years) | B38: =INDEX(Sch_label,B37+1) -> 1–3 | C38: Three rounds, in years 1-3
A39: Rounds | B39: =INDEX(Sch_n,B37+1) -> 3
A40: Payouts (PV) | B40: =INDEX(Sch_P0,B37+1) -> 330.45199
A41: Savings, year 6 | B41: =INDEX(Sch_S6,B37+1) -> 122.5
A43: A price to explore (Declarations) | B43: =W_try -> 10 | C43: Change it on Declarations
A44: The best weighted sum at that price | B44: =MAX(Sch_try) -> 1573.3806
A45: Rounds (years) | B45: =INDEX(Sch_label,MATCH(B44,Sch_try,0)) -> 1–3, 6 | C45: Below 3.07 two rounds; to 7.95 three; to 16.93 four; to 36.68 five; above, six
A47: Ideal point: payouts | B47: =MAX(Sch_P0) -> 384.17334 | C47: $384.17 million
A48: Ideal point: savings | B48: =MAX(Sch_S6) -> 137.8125 | C48: $137.81 million a year
A49: Some schedule attains it (1 = yes) | B49: =IF(COUNTIFS(Sch_P0,">="&(B47-0.000000001),Sch_S6,">="&(B48-0.000000001))>0,1,0) -> 0 | C49: 0: out of reach (Theorem 12.1(iii))
A51: A bound on savings (Theorem 12.1(ii)) | B51: 122.5 | C51: Section 12.1: savings of $122.5 million a year
A52: A bound on the reserve | B52: 50 | C52: ... and a $50 million reserve
A53: Most payouts with savings at least the bound, no reserve | B53: =_xlfn.MAXIFS(Sch_P0,Sch_S6,">="&(B51-0.000000001)) -> 330.45199 | C53: 330.45: three rounds, the only answer, hence efficient
A54: Rounds (years) | B54: =INDEX(Sch_label,MATCH(B53,Sch_P0,0)) -> 1–3
A55: ... and a reserve at least its bound | B55: =_xlfn.MAXIFS(Sch_P0,Sch_S6,">="&(B51-0.000000001),Sch_bmax,">="&(B52-0.000000001))-Beta_y*B52 -> 284.99744 | C55: 285.00 (Online Appendix 12.B.2)
A56: Rounds (years) | B56: =INDEX(Sch_label,_xlfn.MINIFS(Sch_idx,Sch_S6,">="&(B51-0.000000001),Sch_bmax,">="&(B52-0.000000001),Sch_P0,">="&(B55+Beta_y*B52-0.000000001))+1) -> 1–3

Sheet Reserve
A1: Bound the reserve: its price, the largest reserve each schedule keeps, and where the rounds move (Theorem 12.2(iv); Worked Example 12.1, Step 4; Figure 12.2; AXIOM Lab 2.12, step 3)
A2: The reserve raises every term of the war chest by b, so the war chest rises by b in every year and only the year-1 payout falls, by b: a year-1 payout held back until the end, worth beta = $0.909 per dollar.
A4: The reserve's price, beta | B4: =Beta_y -> 0.90909091 | C4: Step 4: $0.909 of payouts for each dollar
A5: The reserve to explore (Declarations) | B5: =Res_b -> 50
A6: Schedules that keep every commitment at that reserve | B6: =SUM(Sch_feasb) -> 64
A7: Price from the war chest recomputed at that reserve: smallest | B7: =MIN(Sch_price) -> 0.90909091 | C7: Every schedule: (PV at 0 - PV at b) / b
A8: largest | B8: =MAX(Sch_price) -> 0.90909091 | C8: The same price whatever the schedule
A9: largest gap from beta | B9: =MAX(ABS(B7-B4),ABS(B8-B4)) -> 0
A11: Schedules keeping at most $85 million | B11: =COUNTIFS(Sch_bmax,">=84.5",Sch_bmax,"<=85.5") -> 16 | C11: Rounds in years 1-3, for instance
A12: Schedules keeping at most $100 million | B12: =COUNTIFS(Sch_bmax,">=99.5",Sch_bmax,"<=100.5") -> 16 | C12: Rounds in years 1 and 2 but not 3, for instance
A13: Schedules keeping up to $150 million | B13: =COUNTIFS(Sch_bmax,">=149.5",Sch_bmax,"<=150.5") -> 32 | C13: A single round in year 1, or rounds in years 1, 3 and 4, for instance
A14: Cash before a year-2 round, after a year-1 round | B14: =Q_zero-Cost_round+Val_pt*Half_gap*(Ceiling_e-E_zero) -> 570 | C14: 620 - 120 + 70 = 570 (Online Appendix 12.B.2)
A15: rounds in years 1 and 2 need a reserve of at most | B15: =B14-Pre_q -> 100 | C15: $100 million
A16: Cash before a year-3 round, after rounds in years 1 and 2 | B16: =B14-Cost_round+Val_pt*(Ceiling_e-E_zero)*(1-(1-Half_gap)^2) -> 555 | C16: 570 - 120 + 105 = 555
A17: rounds in years 1-3 need a reserve of at most | B17: =B16-Pre_q -> 85 | C17: $85 million
A18: The largest reserve any plan keeps | B18: =MAX(Sch_bmax) -> 150 | C18: $150 million
A19: Payout programs on the $1 million grid: 64 schedules x 151 reserves | B19: =COUNT(Sch_idx)*151 -> 9664 | C19: 9,664 (Section 12.4)
A20: that keep every commitment | B20: =SUMPRODUCT((Sch_bmax>=-0.000000001)*(INT(Sch_bmax+0.000000001)+1)) -> 7824 | C20: 7,824 (Online Appendix Remark 12.B.1)
A22: The trade-off surface: the most payouts with savings of at least the bound on Frontier ($122.5 million a year: three rounds) and a reserve of b
A23: Reserve b | B23: Most payouts | C23: Its schedule # | D23: Rounds (years) | E23: Rounds move (1 = yes) | F23: Fall from b - 1 | G23: Fall beyond the price
A24: 0 | B24: =IF(COUNTIFS(Sch_S6,">="&(Bound_S-0.000000001),Sch_bmax,">="&(A24-0.000000001))=0,"",_xlfn.MAXIFS(Sch_P0,Sch_S6,">="&(Bound_S-0.000000001),Sch_bmax,">="&(A24-0.000000001))-Beta_y*A24) -> 330.45199 | C24: =IF(B24="","",_xlfn.MINIFS(Sch_idx,Sch_S6,">="&(Bound_S-0.000000001),Sch_bmax,">="&(A24-0.000000001),Sch_P0,">="&(B24+Beta_y*A24-0.000000001))) -> 56 | D24: =IF(B24="","",INDEX(Sch_label,C24+1)) -> 1–3 | I24: First reserve where the rounds move | J24: =_xlfn.MINIFS($A$25:$A$174,$E$25:$E$174,1) -> 86 | K24: 86: years 1, 2, 4
A25: 1 | B25: =IF(COUNTIFS(Sch_S6,">="&(Bound_S-0.000000001),Sch_bmax,">="&(A25-0.000000001))=0,"",_xlfn.MAXIFS(Sch_P0,Sch_S6,">="&(Bound_S-0.000000001),Sch_bmax,">="&(A25-0.000000001))-Beta_y*A25) -> 329.54289 | C25: =IF(B25="","",_xlfn.MINIFS(Sch_idx,Sch_S6,">="&(Bound_S-0.000000001),Sch_bmax,">="&(A25-0.000000001),Sch_P0,">="&(B25+Beta_y*A25-0.000000001))) -> 56 | D25: =IF(B25="","",INDEX(Sch_label,C25+1)) -> 1–3 | E25: =IF(OR(B25="",B24=""),0,IF(C25<>C24,1,0)) -> 0 | F25: =IF(OR(B25="",B24=""),0,B24-B25) -> 0.90909091 | G25: =F25-Beta_y -> 2.5868196e-14 | I25: Second | J25: =_xlfn.MINIFS($A$25:$A$174,$E$25:$E$174,1,$A$25:$A$174,">"&J24) -> 101 | K25: 101: years 1, 3, 4
A26: 2 | B26: =IF(COUNTIFS(Sch_S6,">="&(Bound_S-0.000000001),Sch_bmax,">="&(A26-0.000000001))=0,"",_xlfn.MAXIFS(Sch_P0,Sch_S6,">="&(Bound_S-0.000000001),Sch_bmax,">="&(A26-0.000000001))-Beta_y*A26) -> 328.6338 | C26: =IF(B26="","",_xlfn.MINIFS(Sch_idx,Sch_S6,">="&(Bound_S-0.000000001),Sch_bmax,">="&(A26-0.000000001),Sch_P0,">="&(B26+Beta_y*A26-0.000000001))) -> 56 | D26: =IF(B26="","",INDEX(Sch_label,C26+1)) -> 1–3 | E26: =IF(OR(B26="",B25=""),0,IF(C26<>C25,1,0)) -> 0 | F26: =IF(OR(B26="",B25=""),0,B25-B26) -> 0.90909091 | G26: =F26-Beta_y -> -3.0975222e-14 | I26: Moves in all | J26: =SUM($E$25:$E$174) -> 2
A27: 3 | B27: =IF(COUNTIFS(Sch_S6,">="&(Bound_S-0.000000001),Sch_bmax,">="&(A27-0.000000001))=0,"",_xlfn.MAXIFS(Sch_P0,Sch_S6,">="&(Bound_S-0.000000001),Sch_bmax,">="&(A27-0.000000001))-Beta_y*A27) -> 327.72471 | C27: =IF(B27="","",_xlfn.MINIFS(Sch_idx,Sch_S6,">="&(Bound_S-0.000000001),Sch_bmax,">="&(A27-0.000000001),Sch_P0,">="&(B27+Beta_y*A27-0.000000001))) -> 56 | D27: =IF(B27="","",INDEX(Sch_label,C27+1)) -> 1–3 | E27: =IF(OR(B27="",B26=""),0,IF(C27<>C26,1,0)) -> 0 | F27: =IF(OR(B27="",B26=""),0,B26-B27) -> 0.90909091 | G27: =F27-Beta_y -> 2.5868196e-14 | I27: Drop beyond the price at the first | J27: =INDEX($G$24:$G$174,J24+1) -> 4.0195342 | K27: $4.02 million
A28: 4 | B28: =IF(COUNTIFS(Sch_S6,">="&(Bound_S-0.000000001),Sch_bmax,">="&(A28-0.000000001))=0,"",_xlfn.MAXIFS(Sch_P0,Sch_S6,">="&(Bound_S-0.000000001),Sch_bmax,">="&(A28-0.000000001))-Beta_y*A28) -> 326.81562 | C28: =IF(B28="","",_xlfn.MINIFS(Sch_idx,Sch_S6,">="&(Bound_S-0.000000001),Sch_bmax,">="&(A28-0.000000001),Sch_P0,">="&(B28+Beta_y*A28-0.000000001))) -> 56 | D28: =IF(B28="","",INDEX(Sch_label,C28+1)) -> 1–3 | E28: =IF(OR(B28="",B27=""),0,IF(C28<>C27,1,0)) -> 0 | F28: =IF(OR(B28="",B27=""),0,B27-B28) -> 0.90909091 | G28: =F28-Beta_y -> -3.0975222e-14 | I28: Drop beyond the price at the second | J28: =INDEX($G$24:$G$174,J25+1) -> 24.380165 | K28: $24.38 million
A29: 5 | B29: =IF(COUNTIFS(Sch_S6,">="&(Bound_S-0.000000001),Sch_bmax,">="&(A29-0.000000001))=0,"",_xlfn.MAXIFS(Sch_P0,Sch_S6,">="&(Bound_S-0.000000001),Sch_bmax,">="&(A29-0.000000001))-Beta_y*A29) -> 325.90653 | C29: =IF(B29="","",_xlfn.MINIFS(Sch_idx,Sch_S6,">="&(Bound_S-0.000000001),Sch_bmax,">="&(A29-0.000000001),Sch_P0,">="&(B29+Beta_y*A29-0.000000001))) -> 56 | D29: =IF(B29="","",INDEX(Sch_label,C29+1)) -> 1–3 | E29: =IF(OR(B29="",B28=""),0,IF(C29<>C28,1,0)) -> 0 | F29: =IF(OR(B29="",B28=""),0,B28-B29) -> 0.90909091 | G29: =F29-Beta_y -> 2.5868196e-14 | I29: Largest |fall - price| where the rounds stay | J29: =SUMPRODUCT(MAX(ABS($G$25:$G$174)*($E$25:$E$174=0))) -> 3.0975222e-14 | K29: Smooth: the surface falls at the multiplier (Theorem 12.2(iv))
A30: 6 | B30: =IF(COUNTIFS(Sch_S6,">="&(Bound_S-0.000000001),Sch_bmax,">="&(A30-0.000000001))=0,"",_xlfn.MAXIFS(Sch_P0,Sch_S6,">="&(Bound_S-0.000000001),Sch_bmax,">="&(A30-0.000000001))-Beta_y*A30) -> 324.99744 | C30: =IF(B30="","",_xlfn.MINIFS(Sch_idx,Sch_S6,">="&(Bound_S-0.000000001),Sch_bmax,">="&(A30-0.000000001),Sch_P0,">="&(B30+Beta_y*A30-0.000000001))) -> 56 | D30: =IF(B30="","",INDEX(Sch_label,C30+1)) -> 1–3 | E30: =IF(OR(B30="",B29=""),0,IF(C30<>C29,1,0)) -> 0 | F30: =IF(OR(B30="",B29=""),0,B29-B30) -> 0.90909091 | G30: =F30-Beta_y -> -3.0975222e-14
A31: 7 | B31: =IF(COUNTIFS(Sch_S6,">="&(Bound_S-0.000000001),Sch_bmax,">="&(A31-0.000000001))=0,"",_xlfn.MAXIFS(Sch_P0,Sch_S6,">="&(Bound_S-0.000000001),Sch_bmax,">="&(A31-0.000000001))-Beta_y*A31) -> 324.08835 | C31: =IF(B31="","",_xlfn.MINIFS(Sch_idx,Sch_S6,">="&(Bound_S-0.000000001),Sch_bmax,">="&(A31-0.000000001),Sch_P0,">="&(B31+Beta_y*A31-0.000000001))) -> 56 | D31: =IF(B31="","",INDEX(Sch_label,C31+1)) -> 1–3 | E31: =IF(OR(B31="",B30=""),0,IF(C31<>C30,1,0)) -> 0 | F31: =IF(OR(B31="",B30=""),0,B30-B31) -> 0.90909091 | G31: =F31-Beta_y -> 2.5868196e-14 | I31: Reserve | J31: Most payouts | K31: Rounds (years)
A32: 8 | B32: =IF(COUNTIFS(Sch_S6,">="&(Bound_S-0.000000001),Sch_bmax,">="&(A32-0.000000001))=0,"",_xlfn.MAXIFS(Sch_P0,Sch_S6,">="&(Bound_S-0.000000001),Sch_bmax,">="&(A32-0.000000001))-Beta_y*A32) -> 323.17926 | C32: =IF(B32="","",_xlfn.MINIFS(Sch_idx,Sch_S6,">="&(Bound_S-0.000000001),Sch_bmax,">="&(A32-0.000000001),Sch_P0,">="&(B32+Beta_y*A32-0.000000001))) -> 56 | D32: =IF(B32="","",INDEX(Sch_label,C32+1)) -> 1–3 | E32: =IF(OR(B32="",B31=""),0,IF(C32<>C31,1,0)) -> 0 | F32: =IF(OR(B32="",B31=""),0,B31-B32) -> 0.90909091 | G32: =F32-Beta_y -> -3.0975222e-14 | I32: 0 | J32: =INDEX($B$24:$B$174,I32+1) -> 330.45199 | K32: =INDEX($D$24:$D$174,I32+1) -> 1–3
A33: 9 | B33: =IF(COUNTIFS(Sch_S6,">="&(Bound_S-0.000000001),Sch_bmax,">="&(A33-0.000000001))=0,"",_xlfn.MAXIFS(Sch_P0,Sch_S6,">="&(Bound_S-0.000000001),Sch_bmax,">="&(A33-0.000000001))-Beta_y*A33) -> 322.27017 | C33: =IF(B33="","",_xlfn.MINIFS(Sch_idx,Sch_S6,">="&(Bound_S-0.000000001),Sch_bmax,">="&(A33-0.000000001),Sch_P0,">="&(B33+Beta_y*A33-0.000000001))) -> 56 | D33: =IF(B33="","",INDEX(Sch_label,C33+1)) -> 1–3 | E33: =IF(OR(B33="",B32=""),0,IF(C33<>C32,1,0)) -> 0 | F33: =IF(OR(B33="",B32=""),0,B32-B33) -> 0.90909091 | G33: =F33-Beta_y -> 2.5868196e-14 | I33: 25 | J33: =INDEX($B$24:$B$174,I33+1) -> 307.72471 | K33: =INDEX($D$24:$D$174,I33+1) -> 1–3
A34: 10 | B34: =IF(COUNTIFS(Sch_S6,">="&(Bound_S-0.000000001),Sch_bmax,">="&(A34-0.000000001))=0,"",_xlfn.MAXIFS(Sch_P0,Sch_S6,">="&(Bound_S-0.000000001),Sch_bmax,">="&(A34-0.000000001))-Beta_y*A34) -> 321.36108 | C34: =IF(B34="","",_xlfn.MINIFS(Sch_idx,Sch_S6,">="&(Bound_S-0.000000001),Sch_bmax,">="&(A34-0.000000001),Sch_P0,">="&(B34+Beta_y*A34-0.000000001))) -> 56 | D34: =IF(B34="","",INDEX(Sch_label,C34+1)) -> 1–3 | E34: =IF(OR(B34="",B33=""),0,IF(C34<>C33,1,0)) -> 0 | F34: =IF(OR(B34="",B33=""),0,B33-B34) -> 0.90909091 | G34: =F34-Beta_y -> -3.0975222e-14 | I34: 50 | J34: =INDEX($B$24:$B$174,I34+1) -> 284.99744 | K34: =INDEX($D$24:$D$174,I34+1) -> 1–3
A35: 11 | B35: =IF(COUNTIFS(Sch_S6,">="&(Bound_S-0.000000001),Sch_bmax,">="&(A35-0.000000001))=0,"",_xlfn.MAXIFS(Sch_P0,Sch_S6,">="&(Bound_S-0.000000001),Sch_bmax,">="&(A35-0.000000001))-Beta_y*A35) -> 320.45199 | C35: =IF(B35="","",_xlfn.MINIFS(Sch_idx,Sch_S6,">="&(Bound_S-0.000000001),Sch_bmax,">="&(A35-0.000000001),Sch_P0,">="&(B35+Beta_y*A35-0.000000001))) -> 56 | D35: =IF(B35="","",INDEX(Sch_label,C35+1)) -> 1–3 | E35: =IF(OR(B35="",B34=""),0,IF(C35<>C34,1,0)) -> 0 | F35: =IF(OR(B35="",B34=""),0,B34-B35) -> 0.90909091 | G35: =F35-Beta_y -> 2.5868196e-14 | I35: 85 | J35: =INDEX($B$24:$B$174,I35+1) -> 253.17926 | K35: =INDEX($D$24:$D$174,I35+1) -> 1–3
A36: 12 | B36: =IF(COUNTIFS(Sch_S6,">="&(Bound_S-0.000000001),Sch_bmax,">="&(A36-0.000000001))=0,"",_xlfn.MAXIFS(Sch_P0,Sch_S6,">="&(Bound_S-0.000000001),Sch_bmax,">="&(A36-0.000000001))-Beta_y*A36) -> 319.54289 | C36: =IF(B36="","",_xlfn.MINIFS(Sch_idx,Sch_S6,">="&(Bound_S-0.000000001),Sch_bmax,">="&(A36-0.000000001),Sch_P0,">="&(B36+Beta_y*A36-0.000000001))) -> 56 | D36: =IF(B36="","",INDEX(Sch_label,C36+1)) -> 1–3 | E36: =IF(OR(B36="",B35=""),0,IF(C36<>C35,1,0)) -> 0 | F36: =IF(OR(B36="",B35=""),0,B35-B36) -> 0.90909091 | G36: =F36-Beta_y -> 2.5868196e-14 | I36: 86 | J36: =INDEX($B$24:$B$174,I36+1) -> 248.25063 | K36: =INDEX($D$24:$D$174,I36+1) -> 1, 2, 4
A37: 13 | B37: =IF(COUNTIFS(Sch_S6,">="&(Bound_S-0.000000001),Sch_bmax,">="&(A37-0.000000001))=0,"",_xlfn.MAXIFS(Sch_P0,Sch_S6,">="&(Bound_S-0.000000001),Sch_bmax,">="&(A37-0.000000001))-Beta_y*A37) -> 318.6338 | C37: =IF(B37="","",_xlfn.MINIFS(Sch_idx,Sch_S6,">="&(Bound_S-0.000000001),Sch_bmax,">="&(A37-0.000000001),Sch_P0,">="&(B37+Beta_y*A37-0.000000001))) -> 56 | D37: =IF(B37="","",INDEX(Sch_label,C37+1)) -> 1–3 | E37: =IF(OR(B37="",B36=""),0,IF(C37<>C36,1,0)) -> 0 | F37: =IF(OR(B37="",B36=""),0,B36-B37) -> 0.90909091 | G37: =F37-Beta_y -> -3.0975222e-14 | I37: 90 | J37: =INDEX($B$24:$B$174,I37+1) -> 244.61427 | K37: =INDEX($D$24:$D$174,I37+1) -> 1, 2, 4
A38: 14 | B38: =IF(COUNTIFS(Sch_S6,">="&(Bound_S-0.000000001),Sch_bmax,">="&(A38-0.000000001))=0,"",_xlfn.MAXIFS(Sch_P0,Sch_S6,">="&(Bound_S-0.000000001),Sch_bmax,">="&(A38-0.000000001))-Beta_y*A38) -> 317.72471 | C38: =IF(B38="","",_xlfn.MINIFS(Sch_idx,Sch_S6,">="&(Bound_S-0.000000001),Sch_bmax,">="&(A38-0.000000001),Sch_P0,">="&(B38+Beta_y*A38-0.000000001))) -> 56 | D38: =IF(B38="","",INDEX(Sch_label,C38+1)) -> 1–3 | E38: =IF(OR(B38="",B37=""),0,IF(C38<>C37,1,0)) -> 0 | F38: =IF(OR(B38="",B37=""),0,B37-B38) -> 0.90909091 | G38: =F38-Beta_y -> 2.5868196e-14 | I38: 100 | J38: =INDEX($B$24:$B$174,I38+1) -> 235.52336 | K38: =INDEX($D$24:$D$174,I38+1) -> 1, 2, 4
A39: 15 | B39: =IF(COUNTIFS(Sch_S6,">="&(Bound_S-0.000000001),Sch_bmax,">="&(A39-0.000000001))=0,"",_xlfn.MAXIFS(Sch_P0,Sch_S6,">="&(Bound_S-0.000000001),Sch_bmax,">="&(A39-0.000000001))-Beta_y*A39) -> 316.81562 | C39: =IF(B39="","",_xlfn.MINIFS(Sch_idx,Sch_S6,">="&(Bound_S-0.000000001),Sch_bmax,">="&(A39-0.000000001),Sch_P0,">="&(B39+Beta_y*A39-0.000000001))) -> 56 | D39: =IF(B39="","",INDEX(Sch_label,C39+1)) -> 1–3 | E39: =IF(OR(B39="",B38=""),0,IF(C39<>C38,1,0)) -> 0 | F39: =IF(OR(B39="",B38=""),0,B38-B39) -> 0.90909091 | G39: =F39-Beta_y -> -3.0975222e-14 | I39: 101 | J39: =INDEX($B$24:$B$174,I39+1) -> 210.2341 | K39: =INDEX($D$24:$D$174,I39+1) -> 1, 3, 4
A40: 16 | B40: =IF(COUNTIFS(Sch_S6,">="&(Bound_S-0.000000001),Sch_bmax,">="&(A40-0.000000001))=0,"",_xlfn.MAXIFS(Sch_P0,Sch_S6,">="&(Bound_S-0.000000001),Sch_bmax,">="&(A40-0.000000001))-Beta_y*A40) -> 315.90653 | C40: =IF(B40="","",_xlfn.MINIFS(Sch_idx,Sch_S6,">="&(Bound_S-0.000000001),Sch_bmax,">="&(A40-0.000000001),Sch_P0,">="&(B40+Beta_y*A40-0.000000001))) -> 56 | D40: =IF(B40="","",INDEX(Sch_label,C40+1)) -> 1–3 | E40: =IF(OR(B40="",B39=""),0,IF(C40<>C39,1,0)) -> 0 | F40: =IF(OR(B40="",B39=""),0,B39-B40) -> 0.90909091 | G40: =F40-Beta_y -> 2.5868196e-14 | I40: 105 | J40: =INDEX($B$24:$B$174,I40+1) -> 206.59774 | K40: =INDEX($D$24:$D$174,I40+1) -> 1, 3, 4
A41: 17 | B41: =IF(COUNTIFS(Sch_S6,">="&(Bound_S-0.000000001),Sch_bmax,">="&(A41-0.000000001))=0,"",_xlfn.MAXIFS(Sch_P0,Sch_S6,">="&(Bound_S-0.000000001),Sch_bmax,">="&(A41-0.000000001))-Beta_y*A41) -> 314.99744 | C41: =IF(B41="","",_xlfn.MINIFS(Sch_idx,Sch_S6,">="&(Bound_S-0.000000001),Sch_bmax,">="&(A41-0.000000001),Sch_P0,">="&(B41+Beta_y*A41-0.000000001))) -> 56 | D41: =IF(B41="","",INDEX(Sch_label,C41+1)) -> 1–3 | E41: =IF(OR(B41="",B40=""),0,IF(C41<>C40,1,0)) -> 0 | F41: =IF(OR(B41="",B40=""),0,B40-B41) -> 0.90909091 | G41: =F41-Beta_y -> -3.0975222e-14 | I41: 120 | J41: =INDEX($B$24:$B$174,I41+1) -> 192.96138 | K41: =INDEX($D$24:$D$174,I41+1) -> 1, 3, 4
A42: 18 | B42: =IF(COUNTIFS(Sch_S6,">="&(Bound_S-0.000000001),Sch_bmax,">="&(A42-0.000000001))=0,"",_xlfn.MAXIFS(Sch_P0,Sch_S6,">="&(Bound_S-0.000000001),Sch_bmax,">="&(A42-0.000000001))-Beta_y*A42) -> 314.08835 | C42: =IF(B42="","",_xlfn.MINIFS(Sch_idx,Sch_S6,">="&(Bound_S-0.000000001),Sch_bmax,">="&(A42-0.000000001),Sch_P0,">="&(B42+Beta_y*A42-0.000000001))) -> 56 | D42: =IF(B42="","",INDEX(Sch_label,C42+1)) -> 1–3 | E42: =IF(OR(B42="",B41=""),0,IF(C42<>C41,1,0)) -> 0 | F42: =IF(OR(B42="",B41=""),0,B41-B42) -> 0.90909091 | G42: =F42-Beta_y -> 2.5868196e-14 | I42: 150 | J42: =INDEX($B$24:$B$174,I42+1) -> 165.68865 | K42: =INDEX($D$24:$D$174,I42+1) -> 1, 3, 4
A43: 19 | B43: =IF(COUNTIFS(Sch_S6,">="&(Bound_S-0.000000001),Sch_bmax,">="&(A43-0.000000001))=0,"",_xlfn.MAXIFS(Sch_P0,Sch_S6,">="&(Bound_S-0.000000001),Sch_bmax,">="&(A43-0.000000001))-Beta_y*A43) -> 313.17926 | C43: =IF(B43="","",_xlfn.MINIFS(Sch_idx,Sch_S6,">="&(Bound_S-0.000000001),Sch_bmax,">="&(A43-0.000000001),Sch_P0,">="&(B43+Beta_y*A43-0.000000001))) -> 56 | D43: =IF(B43="","",INDEX(Sch_label,C43+1)) -> 1–3 | E43: =IF(OR(B43="",B42=""),0,IF(C43<>C42,1,0)) -> 0 | F43: =IF(OR(B43="",B42=""),0,B42-B43) -> 0.90909091 | G43: =F43-Beta_y -> -3.0975222e-14
A44: 20 | B44: =IF(COUNTIFS(Sch_S6,">="&(Bound_S-0.000000001),Sch_bmax,">="&(A44-0.000000001))=0,"",_xlfn.MAXIFS(Sch_P0,Sch_S6,">="&(Bound_S-0.000000001),Sch_bmax,">="&(A44-0.000000001))-Beta_y*A44) -> 312.27017 | C44: =IF(B44="","",_xlfn.MINIFS(Sch_idx,Sch_S6,">="&(Bound_S-0.000000001),Sch_bmax,">="&(A44-0.000000001),Sch_P0,">="&(B44+Beta_y*A44-0.000000001))) -> 56 | D44: =IF(B44="","",INDEX(Sch_label,C44+1)) -> 1–3 | E44: =IF(OR(B44="",B43=""),0,IF(C44<>C43,1,0)) -> 0 | F44: =IF(OR(B44="",B43=""),0,B43-B44) -> 0.90909091 | G44: =F44-Beta_y -> 2.5868196e-14
A45: 21 | B45: =IF(COUNTIFS(Sch_S6,">="&(Bound_S-0.000000001),Sch_bmax,">="&(A45-0.000000001))=0,"",_xlfn.MAXIFS(Sch_P0,Sch_S6,">="&(Bound_S-0.000000001),Sch_bmax,">="&(A45-0.000000001))-Beta_y*A45) -> 311.36108 | C45: =IF(B45="","",_xlfn.MINIFS(Sch_idx,Sch_S6,">="&(Bound_S-0.000000001),Sch_bmax,">="&(A45-0.000000001),Sch_P0,">="&(B45+Beta_y*A45-0.000000001))) -> 56 | D45: =IF(B45="","",INDEX(Sch_label,C45+1)) -> 1–3 | E45: =IF(OR(B45="",B44=""),0,IF(C45<>C44,1,0)) -> 0 | F45: =IF(OR(B45="",B44=""),0,B44-B45) -> 0.90909091 | G45: =F45-Beta_y -> -3.0975222e-14
A46: 22 | B46: =IF(COUNTIFS(Sch_S6,">="&(Bound_S-0.000000001),Sch_bmax,">="&(A46-0.000000001))=0,"",_xlfn.MAXIFS(Sch_P0,Sch_S6,">="&(Bound_S-0.000000001),Sch_bmax,">="&(A46-0.000000001))-Beta_y*A46) -> 310.45199 | C46: =IF(B46="","",_xlfn.MINIFS(Sch_idx,Sch_S6,">="&(Bound_S-0.000000001),Sch_bmax,">="&(A46-0.000000001),Sch_P0,">="&(B46+Beta_y*A46-0.000000001))) -> 56 | D46: =IF(B46="","",INDEX(Sch_label,C46+1)) -> 1–3 | E46: =IF(OR(B46="",B45=""),0,IF(C46<>C45,1,0)) -> 0 | F46: =IF(OR(B46="",B45=""),0,B45-B46) -> 0.90909091 | G46: =F46-Beta_y -> 2.5868196e-14
A47: 23 | B47: =IF(COUNTIFS(Sch_S6,">="&(Bound_S-0.000000001),Sch_bmax,">="&(A47-0.000000001))=0,"",_xlfn.MAXIFS(Sch_P0,Sch_S6,">="&(Bound_S-0.000000001),Sch_bmax,">="&(A47-0.000000001))-Beta_y*A47) -> 309.54289 | C47: =IF(B47="","",_xlfn.MINIFS(Sch_idx,Sch_S6,">="&(Bound_S-0.000000001),Sch_bmax,">="&(A47-0.000000001),Sch_P0,">="&(B47+Beta_y*A47-0.000000001))) -> 56 | D47: =IF(B47="","",INDEX(Sch_label,C47+1)) -> 1–3 | E47: =IF(OR(B47="",B46=""),0,IF(C47<>C46,1,0)) -> 0 | F47: =IF(OR(B47="",B46=""),0,B46-B47) -> 0.90909091 | G47: =F47-Beta_y -> 2.5868196e-14
A48: 24 | B48: =IF(COUNTIFS(Sch_S6,">="&(Bound_S-0.000000001),Sch_bmax,">="&(A48-0.000000001))=0,"",_xlfn.MAXIFS(Sch_P0,Sch_S6,">="&(Bound_S-0.000000001),Sch_bmax,">="&(A48-0.000000001))-Beta_y*A48) -> 308.6338 | C48: =IF(B48="","",_xlfn.MINIFS(Sch_idx,Sch_S6,">="&(Bound_S-0.000000001),Sch_bmax,">="&(A48-0.000000001),Sch_P0,">="&(B48+Beta_y*A48-0.000000001))) -> 56 | D48: =IF(B48="","",INDEX(Sch_label,C48+1)) -> 1–3 | E48: =IF(OR(B48="",B47=""),0,IF(C48<>C47,1,0)) -> 0 | F48: =IF(OR(B48="",B47=""),0,B47-B48) -> 0.90909091 | G48: =F48-Beta_y -> -3.0975222e-14
A49: 25 | B49: =IF(COUNTIFS(Sch_S6,">="&(Bound_S-0.000000001),Sch_bmax,">="&(A49-0.000000001))=0,"",_xlfn.MAXIFS(Sch_P0,Sch_S6,">="&(Bound_S-0.000000001),Sch_bmax,">="&(A49-0.000000001))-Beta_y*A49) -> 307.72471 | C49: =IF(B49="","",_xlfn.MINIFS(Sch_idx,Sch_S6,">="&(Bound_S-0.000000001),Sch_bmax,">="&(A49-0.000000001),Sch_P0,">="&(B49+Beta_y*A49-0.000000001))) -> 56 | D49: =IF(B49="","",INDEX(Sch_label,C49+1)) -> 1–3 | E49: =IF(OR(B49="",B48=""),0,IF(C49<>C48,1,0)) -> 0 | F49: =IF(OR(B49="",B48=""),0,B48-B49) -> 0.90909091 | G49: =F49-Beta_y -> 2.5868196e-14
A50: 26 | B50: =IF(COUNTIFS(Sch_S6,">="&(Bound_S-0.000000001),Sch_bmax,">="&(A50-0.000000001))=0,"",_xlfn.MAXIFS(Sch_P0,Sch_S6,">="&(Bound_S-0.000000001),Sch_bmax,">="&(A50-0.000000001))-Beta_y*A50) -> 306.81562 | C50: =IF(B50="","",_xlfn.MINIFS(Sch_idx,Sch_S6,">="&(Bound_S-0.000000001),Sch_bmax,">="&(A50-0.000000001),Sch_P0,">="&(B50+Beta_y*A50-0.000000001))) -> 56 | D50: =IF(B50="","",INDEX(Sch_label,C50+1)) -> 1–3 | E50: =IF(OR(B50="",B49=""),0,IF(C50<>C49,1,0)) -> 0 | F50: =IF(OR(B50="",B49=""),0,B49-B50) -> 0.90909091 | G50: =F50-Beta_y -> -3.0975222e-14
A51: 27 | B51: =IF(COUNTIFS(Sch_S6,">="&(Bound_S-0.000000001),Sch_bmax,">="&(A51-0.000000001))=0,"",_xlfn.MAXIFS(Sch_P0,Sch_S6,">="&(Bound_S-0.000000001),Sch_bmax,">="&(A51-0.000000001))-Beta_y*A51) -> 305.90653 | C51: =IF(B51="","",_xlfn.MINIFS(Sch_idx,Sch_S6,">="&(Bound_S-0.000000001),Sch_bmax,">="&(A51-0.000000001),Sch_P0,">="&(B51+Beta_y*A51-0.000000001))) -> 56 | D51: =IF(B51="","",INDEX(Sch_label,C51+1)) -> 1–3 | E51: =IF(OR(B51="",B50=""),0,IF(C51<>C50,1,0)) -> 0 | F51: =IF(OR(B51="",B50=""),0,B50-B51) -> 0.90909091 | G51: =F51-Beta_y -> 2.5868196e-14
A52: 28 | B52: =IF(COUNTIFS(Sch_S6,">="&(Bound_S-0.000000001),Sch_bmax,">="&(A52-0.000000001))=0,"",_xlfn.MAXIFS(Sch_P0,Sch_S6,">="&(Bound_S-0.000000001),Sch_bmax,">="&(A52-0.000000001))-Beta_y*A52) -> 304.99744 | C52: =IF(B52="","",_xlfn.MINIFS(Sch_idx,Sch_S6,">="&(Bound_S-0.000000001),Sch_bmax,">="&(A52-0.000000001),Sch_P0,">="&(B52+Beta_y*A52-0.000000001))) -> 56 | D52: =IF(B52="","",INDEX(Sch_label,C52+1)) -> 1–3 | E52: =IF(OR(B52="",B51=""),0,IF(C52<>C51,1,0)) -> 0 | F52: =IF(OR(B52="",B51=""),0,B51-B52) -> 0.90909091 | G52: =F52-Beta_y -> -3.0975222e-14
A53: 29 | B53: =IF(COUNTIFS(Sch_S6,">="&(Bound_S-0.000000001),Sch_bmax,">="&(A53-0.000000001))=0,"",_xlfn.MAXIFS(Sch_P0,Sch_S6,">="&(Bound_S-0.000000001),Sch_bmax,">="&(A53-0.000000001))-Beta_y*A53) -> 304.08835 | C53: =IF(B53="","",_xlfn.MINIFS(Sch_idx,Sch_S6,">="&(Bound_S-0.000000001),Sch_bmax,">="&(A53-0.000000001),Sch_P0,">="&(B53+Beta_y*A53-0.000000001))) -> 56 | D53: =IF(B53="","",INDEX(Sch_label,C53+1)) -> 1–3 | E53: =IF(OR(B53="",B52=""),0,IF(C53<>C52,1,0)) -> 0 | F53: =IF(OR(B53="",B52=""),0,B52-B53) -> 0.90909091 | G53: =F53-Beta_y -> 2.5868196e-14
A54: 30 | B54: =IF(COUNTIFS(Sch_S6,">="&(Bound_S-0.000000001),Sch_bmax,">="&(A54-0.000000001))=0,"",_xlfn.MAXIFS(Sch_P0,Sch_S6,">="&(Bound_S-0.000000001),Sch_bmax,">="&(A54-0.000000001))-Beta_y*A54) -> 303.17926 | C54: =IF(B54="","",_xlfn.MINIFS(Sch_idx,Sch_S6,">="&(Bound_S-0.000000001),Sch_bmax,">="&(A54-0.000000001),Sch_P0,">="&(B54+Beta_y*A54-0.000000001))) -> 56 | D54: =IF(B54="","",INDEX(Sch_label,C54+1)) -> 1–3 | E54: =IF(OR(B54="",B53=""),0,IF(C54<>C53,1,0)) -> 0 | F54: =IF(OR(B54="",B53=""),0,B53-B54) -> 0.90909091 | G54: =F54-Beta_y -> -3.0975222e-14
... A174: 150 | B174: =IF(COUNTIFS(Sch_S6,">="&(Bound_S-0.000000001),Sch_bmax,">="&(A174-0.000000001))=0,"",_xlfn.MAXIFS(Sch_P0,Sch_S6,">="&(Bound_S-0.000000001),Sch_bmax,">="&(A174-0.000000001))-Beta_y*A174) -> 165.68865 | C174: =IF(B174="","",_xlfn.MINIFS(Sch_idx,Sch_S6,">="&(Bound_S-0.000000001),Sch_bmax,">="&(A174-0.000000001),Sch_P0,">="&(B174+Beta_y*A174-0.000000001))) -> 44 | D174: =IF(B174="","",INDEX(Sch_label,C174+1)) -> 1, 3, 4 | E174: =IF(OR(B174="",B173=""),0,IF(C174<>C173,1,0)) -> 0 | F174: =IF(OR(B174="",B173=""),0,B173-B174) -> 0.90909091 | G174: =F174-Beta_y -> 0

Sheet Grid
A1: The best payouts for every number of rounds and every reserve on a $1 million grid (Online Appendix Remark 12.B.1; Figure 12.2)
A2: Payouts: the most any schedule with n rounds pays while keeping the reserve, its present value at b = 0 less beta x b (the shift checked on Schedules). Schedule #: the first in binary order among the best. Efficient: no plan with more rounds pays as much at the same reserve; savings rise with the rounds, and payouts fall with the reserve, so these are the only plans that could dominate it.
B4: Payouts (PV) with n rounds | J4: Keeps every commitment | R4: Schedule # | Z4: Efficient
A5: Reserve b | B5: 0 | C5: 1 | D5: 2 | E5: 3 | F5: 4 | G5: 5 | H5: 6 | J5: 0 | K5: 1 | L5: 2 | M5: 3 | N5: 4 | O5: 5 | P5: 6 | R5: 0 | S5: 1 | T5: 2 | U5: 3 | V5: 4 | W5: 5 | X5: 6 | Z5: 0 | AA5: 1 | AB5: 2 | AC5: 3 | AD5: 4 | AE5: 5 | AF5: 6
A6: 0 | B6: =IF(COUNTIFS(Sch_n,B$5,Sch_bmax,">="&($A6-0.000000001))>0,_xlfn.MAXIFS(Sch_P0,Sch_n,B$5,Sch_bmax,">="&($A6-0.000000001))-Beta_y*$A6,"") -> 136.36364 | C6: =IF(COUNTIFS(Sch_n,C$5,Sch_bmax,">="&($A6-0.000000001))>0,_xlfn.MAXIFS(Sch_P0,Sch_n,C$5,Sch_bmax,">="&($A6-0.000000001))-Beta_y*$A6,"") -> 370.67264 | D6: =IF(COUNTIFS(Sch_n,D$5,Sch_bmax,">="&($A6-0.000000001))>0,_xlfn.MAXIFS(Sch_P0,Sch_n,D$5,Sch_bmax,">="&($A6-0.000000001))-Beta_y*$A6,"") -> 384.17334 | E6: =IF(COUNTIFS(Sch_n,E$5,Sch_bmax,">="&($A6-0.000000001))>0,_xlfn.MAXIFS(Sch_P0,Sch_n,E$5,Sch_bmax,">="&($A6-0.000000001))-Beta_y*$A6,"") -> 330.45199 | F6: =IF(COUNTIFS(Sch_n,F$5,Sch_bmax,">="&($A6-0.000000001))>0,_xlfn.MAXIFS(Sch_P0,Sch_n,F$5,Sch_bmax,">="&($A6-0.000000001))-Beta_y*$A6,"") -> 260.88057 | G6: =IF(COUNTIFS(Sch_n,G$5,Sch_bmax,">="&($A6-0.000000001))>0,_xlfn.MAXIFS(Sch_P0,Sch_n,G$5,Sch_bmax,">="&($A6-0.000000001))-Beta_y*$A6,"") -> 186.82159 | H6: =IF(COUNTIFS(Sch_n,H$5,Sch_bmax,">="&($A6-0.000000001))>0,_xlfn.MAXIFS(Sch_P0,Sch_n,H$5,Sch_bmax,">="&($A6-0.000000001))-Beta_y*$A6,"") -> 106.5915 | J6: =IF(ISNUMBER(B6),1,0) -> 1 | K6: =IF(ISNUMBER(C6),1,0) -> 1 | L6: =IF(ISNUMBER(D6),1,0) -> 1 | M6: =IF(ISNUMBER(E6),1,0) -> 1 | N6: =IF(ISNUMBER(F6),1,0) -> 1 | O6: =IF(ISNUMBER(G6),1,0) -> 1 | P6: =IF(ISNUMBER(H6),1,0) -> 1 | R6: =IF(J6=1,_xlfn.MINIFS(Sch_idx,Sch_n,B$5,Sch_bmax,">="&($A6-0.000000001),Sch_P0,">="&(B6+Beta_y*$A6-0.000000001)),"") -> 0 | S6: =IF(K6=1,_xlfn.MINIFS(Sch_idx,Sch_n,C$5,Sch_bmax,">="&($A6-0.000000001),Sch_P0,">="&(C6+Beta_y*$A6-0.000000001)),"") -> 32 | T6: =IF(L6=1,_xlfn.MINIFS(Sch_idx,Sch_n,D$5,Sch_bmax,">="&($A6-0.000000001),Sch_P0,">="&(D6+Beta_y*$A6-0.000000001)),"") -> 48 | U6: =IF(M6=1,_xlfn.MINIFS(Sch_idx,Sch_n,E$5,Sch_bmax,">="&($A6-0.000000001),Sch_P0,">="&(E6+Beta_y*$A6-0.000000001)),"") -> 56 | V6: =IF(N6=1,_xlfn.MINIFS(Sch_idx,Sch_n,F$5,Sch_bmax,">="&($A6-0.000000001),Sch_P0,">="&(F6+Beta_y*$A6-0.000000001)),"") -> 57 | W6: =IF(O6=1,_xlfn.MINIFS(Sch_idx,Sch_n,G$5,Sch_bmax,">="&($A6-0.000000001),Sch_P0,">="&(G6+Beta_y*$A6-0.000000001)),"") -> 59 | X6: =IF(P6=1,_xlfn.MINIFS(Sch_idx,Sch_n,H$5,Sch_bmax,">="&($A6-0.000000001),Sch_P0,">="&(H6+Beta_y*$A6-0.000000001)),"") -> 63 | Z6: =IF(J6=1,IF(COUNTIFS(K6:$P6,1,C6:$H6,">="&(B6-0.000000001))>0,0,1),"") -> 0 | AA6: =IF(K6=1,IF(COUNTIFS(L6:$P6,1,D6:$H6,">="&(C6-0.000000001))>0,0,1),"") -> 0 | AB6: =IF(L6=1,IF(COUNTIFS(M6:$P6,1,E6:$H6,">="&(D6-0.000000001))>0,0,1),"") -> 1 | AC6: =IF(M6=1,IF(COUNTIFS(N6:$P6,1,F6:$H6,">="&(E6-0.000000001))>0,0,1),"") -> 1 | AD6: =IF(N6=1,IF(COUNTIFS(O6:$P6,1,G6:$H6,">="&(F6-0.000000001))>0,0,1),"") -> 1 | AE6: =IF(O6=1,IF(COUNTIFS(P6:$P6,1,H6:$H6,">="&(G6-0.000000001))>0,0,1),"") -> 1 | AF6: =IF(P6=1,1,"") -> 1
A7: 1 | B7: =IF(COUNTIFS(Sch_n,B$5,Sch_bmax,">="&($A7-0.000000001))>0,_xlfn.MAXIFS(Sch_P0,Sch_n,B$5,Sch_bmax,">="&($A7-0.000000001))-Beta_y*$A7,"") -> 135.45455 | C7: =IF(COUNTIFS(Sch_n,C$5,Sch_bmax,">="&($A7-0.000000001))>0,_xlfn.MAXIFS(Sch_P0,Sch_n,C$5,Sch_bmax,">="&($A7-0.000000001))-Beta_y*$A7,"") -> 369.76355 | D7: =IF(COUNTIFS(Sch_n,D$5,Sch_bmax,">="&($A7-0.000000001))>0,_xlfn.MAXIFS(Sch_P0,Sch_n,D$5,Sch_bmax,">="&($A7-0.000000001))-Beta_y*$A7,"") -> 383.26425 | E7: =IF(COUNTIFS(Sch_n,E$5,Sch_bmax,">="&($A7-0.000000001))>0,_xlfn.MAXIFS(Sch_P0,Sch_n,E$5,Sch_bmax,">="&($A7-0.000000001))-Beta_y*$A7,"") -> 329.54289 | F7: =IF(COUNTIFS(Sch_n,F$5,Sch_bmax,">="&($A7-0.000000001))>0,_xlfn.MAXIFS(Sch_P0,Sch_n,F$5,Sch_bmax,">="&($A7-0.000000001))-Beta_y*$A7,"") -> 259.97148 | G7: =IF(COUNTIFS(Sch_n,G$5,Sch_bmax,">="&($A7-0.000000001))>0,_xlfn.MAXIFS(Sch_P0,Sch_n,G$5,Sch_bmax,">="&($A7-0.000000001))-Beta_y*$A7,"") -> 185.9125 | H7: =IF(COUNTIFS(Sch_n,H$5,Sch_bmax,">="&($A7-0.000000001))>0,_xlfn.MAXIFS(Sch_P0,Sch_n,H$5,Sch_bmax,">="&($A7-0.000000001))-Beta_y*$A7,"") -> 105.68241 | J7: =IF(ISNUMBER(B7),1,0) -> 1 | K7: =IF(ISNUMBER(C7),1,0) -> 1 | L7: =IF(ISNUMBER(D7),1,0) -> 1 | M7: =IF(ISNUMBER(E7),1,0) -> 1 | N7: =IF(ISNUMBER(F7),1,0) -> 1 | O7: =IF(ISNUMBER(G7),1,0) -> 1 | P7: =IF(ISNUMBER(H7),1,0) -> 1 | R7: =IF(J7=1,_xlfn.MINIFS(Sch_idx,Sch_n,B$5,Sch_bmax,">="&($A7-0.000000001),Sch_P0,">="&(B7+Beta_y*$A7-0.000000001)),"") -> 0 | S7: =IF(K7=1,_xlfn.MINIFS(Sch_idx,Sch_n,C$5,Sch_bmax,">="&($A7-0.000000001),Sch_P0,">="&(C7+Beta_y*$A7-0.000000001)),"") -> 32 | T7: =IF(L7=1,_xlfn.MINIFS(Sch_idx,Sch_n,D$5,Sch_bmax,">="&($A7-0.000000001),Sch_P0,">="&(D7+Beta_y*$A7-0.000000001)),"") -> 48 | U7: =IF(M7=1,_xlfn.MINIFS(Sch_idx,Sch_n,E$5,Sch_bmax,">="&($A7-0.000000001),Sch_P0,">="&(E7+Beta_y*$A7-0.000000001)),"") -> 56 | V7: =IF(N7=1,_xlfn.MINIFS(Sch_idx,Sch_n,F$5,Sch_bmax,">="&($A7-0.000000001),Sch_P0,">="&(F7+Beta_y*$A7-0.000000001)),"") -> 57 | W7: =IF(O7=1,_xlfn.MINIFS(Sch_idx,Sch_n,G$5,Sch_bmax,">="&($A7-0.000000001),Sch_P0,">="&(G7+Beta_y*$A7-0.000000001)),"") -> 59 | X7: =IF(P7=1,_xlfn.MINIFS(Sch_idx,Sch_n,H$5,Sch_bmax,">="&($A7-0.000000001),Sch_P0,">="&(H7+Beta_y*$A7-0.000000001)),"") -> 63 | Z7: =IF(J7=1,IF(COUNTIFS(K7:$P7,1,C7:$H7,">="&(B7-0.000000001))>0,0,1),"") -> 0 | AA7: =IF(K7=1,IF(COUNTIFS(L7:$P7,1,D7:$H7,">="&(C7-0.000000001))>0,0,1),"") -> 0 | AB7: =IF(L7=1,IF(COUNTIFS(M7:$P7,1,E7:$H7,">="&(D7-0.000000001))>0,0,1),"") -> 1 | AC7: =IF(M7=1,IF(COUNTIFS(N7:$P7,1,F7:$H7,">="&(E7-0.000000001))>0,0,1),"") -> 1 | AD7: =IF(N7=1,IF(COUNTIFS(O7:$P7,1,G7:$H7,">="&(F7-0.000000001))>0,0,1),"") -> 1 | AE7: =IF(O7=1,IF(COUNTIFS(P7:$P7,1,H7:$H7,">="&(G7-0.000000001))>0,0,1),"") -> 1 | AF7: =IF(P7=1,1,"") -> 1
A8: 2 | B8: =IF(COUNTIFS(Sch_n,B$5,Sch_bmax,">="&($A8-0.000000001))>0,_xlfn.MAXIFS(Sch_P0,Sch_n,B$5,Sch_bmax,">="&($A8-0.000000001))-Beta_y*$A8,"") -> 134.54545 | C8: =IF(COUNTIFS(Sch_n,C$5,Sch_bmax,">="&($A8-0.000000001))>0,_xlfn.MAXIFS(Sch_P0,Sch_n,C$5,Sch_bmax,">="&($A8-0.000000001))-Beta_y*$A8,"") -> 368.85446 | D8: =IF(COUNTIFS(Sch_n,D$5,Sch_bmax,">="&($A8-0.000000001))>0,_xlfn.MAXIFS(Sch_P0,Sch_n,D$5,Sch_bmax,">="&($A8-0.000000001))-Beta_y*$A8,"") -> 382.35515 | E8: =IF(COUNTIFS(Sch_n,E$5,Sch_bmax,">="&($A8-0.000000001))>0,_xlfn.MAXIFS(Sch_P0,Sch_n,E$5,Sch_bmax,">="&($A8-0.000000001))-Beta_y*$A8,"") -> 328.6338 | F8: =IF(COUNTIFS(Sch_n,F$5,Sch_bmax,">="&($A8-0.000000001))>0,_xlfn.MAXIFS(Sch_P0,Sch_n,F$5,Sch_bmax,">="&($A8-0.000000001))-Beta_y*$A8,"") -> 259.06239 | G8: =IF(COUNTIFS(Sch_n,G$5,Sch_bmax,">="&($A8-0.000000001))>0,_xlfn.MAXIFS(Sch_P0,Sch_n,G$5,Sch_bmax,">="&($A8-0.000000001))-Beta_y*$A8,"") -> 185.00341 | H8: =IF(COUNTIFS(Sch_n,H$5,Sch_bmax,">="&($A8-0.000000001))>0,_xlfn.MAXIFS(Sch_P0,Sch_n,H$5,Sch_bmax,">="&($A8-0.000000001))-Beta_y*$A8,"") -> 104.77332 | J8: =IF(ISNUMBER(B8),1,0) -> 1 | K8: =IF(ISNUMBER(C8),1,0) -> 1 | L8: =IF(ISNUMBER(D8),1,0) -> 1 | M8: =IF(ISNUMBER(E8),1,0) -> 1 | N8: =IF(ISNUMBER(F8),1,0) -> 1 | O8: =IF(ISNUMBER(G8),1,0) -> 1 | P8: =IF(ISNUMBER(H8),1,0) -> 1 | R8: =IF(J8=1,_xlfn.MINIFS(Sch_idx,Sch_n,B$5,Sch_bmax,">="&($A8-0.000000001),Sch_P0,">="&(B8+Beta_y*$A8-0.000000001)),"") -> 0 | S8: =IF(K8=1,_xlfn.MINIFS(Sch_idx,Sch_n,C$5,Sch_bmax,">="&($A8-0.000000001),Sch_P0,">="&(C8+Beta_y*$A8-0.000000001)),"") -> 32 | T8: =IF(L8=1,_xlfn.MINIFS(Sch_idx,Sch_n,D$5,Sch_bmax,">="&($A8-0.000000001),Sch_P0,">="&(D8+Beta_y*$A8-0.000000001)),"") -> 48 | U8: =IF(M8=1,_xlfn.MINIFS(Sch_idx,Sch_n,E$5,Sch_bmax,">="&($A8-0.000000001),Sch_P0,">="&(E8+Beta_y*$A8-0.000000001)),"") -> 56 | V8: =IF(N8=1,_xlfn.MINIFS(Sch_idx,Sch_n,F$5,Sch_bmax,">="&($A8-0.000000001),Sch_P0,">="&(F8+Beta_y*$A8-0.000000001)),"") -> 57 | W8: =IF(O8=1,_xlfn.MINIFS(Sch_idx,Sch_n,G$5,Sch_bmax,">="&($A8-0.000000001),Sch_P0,">="&(G8+Beta_y*$A8-0.000000001)),"") -> 59 | X8: =IF(P8=1,_xlfn.MINIFS(Sch_idx,Sch_n,H$5,Sch_bmax,">="&($A8-0.000000001),Sch_P0,">="&(H8+Beta_y*$A8-0.000000001)),"") -> 63 | Z8: =IF(J8=1,IF(COUNTIFS(K8:$P8,1,C8:$H8,">="&(B8-0.000000001))>0,0,1),"") -> 0 | AA8: =IF(K8=1,IF(COUNTIFS(L8:$P8,1,D8:$H8,">="&(C8-0.000000001))>0,0,1),"") -> 0 | AB8: =IF(L8=1,IF(COUNTIFS(M8:$P8,1,E8:$H8,">="&(D8-0.000000001))>0,0,1),"") -> 1 | AC8: =IF(M8=1,IF(COUNTIFS(N8:$P8,1,F8:$H8,">="&(E8-0.000000001))>0,0,1),"") -> 1 | AD8: =IF(N8=1,IF(COUNTIFS(O8:$P8,1,G8:$H8,">="&(F8-0.000000001))>0,0,1),"") -> 1 | AE8: =IF(O8=1,IF(COUNTIFS(P8:$P8,1,H8:$H8,">="&(G8-0.000000001))>0,0,1),"") -> 1 | AF8: =IF(P8=1,1,"") -> 1
A9: 3 | B9: =IF(COUNTIFS(Sch_n,B$5,Sch_bmax,">="&($A9-0.000000001))>0,_xlfn.MAXIFS(Sch_P0,Sch_n,B$5,Sch_bmax,">="&($A9-0.000000001))-Beta_y*$A9,"") -> 133.63636 | C9: =IF(COUNTIFS(Sch_n,C$5,Sch_bmax,">="&($A9-0.000000001))>0,_xlfn.MAXIFS(Sch_P0,Sch_n,C$5,Sch_bmax,">="&($A9-0.000000001))-Beta_y*$A9,"") -> 367.94537 | D9: =IF(COUNTIFS(Sch_n,D$5,Sch_bmax,">="&($A9-0.000000001))>0,_xlfn.MAXIFS(Sch_P0,Sch_n,D$5,Sch_bmax,">="&($A9-0.000000001))-Beta_y*$A9,"") -> 381.44606 | E9: =IF(COUNTIFS(Sch_n,E$5,Sch_bmax,">="&($A9-0.000000001))>0,_xlfn.MAXIFS(Sch_P0,Sch_n,E$5,Sch_bmax,">="&($A9-0.000000001))-Beta_y*$A9,"") -> 327.72471 | F9: =IF(COUNTIFS(Sch_n,F$5,Sch_bmax,">="&($A9-0.000000001))>0,_xlfn.MAXIFS(Sch_P0,Sch_n,F$5,Sch_bmax,">="&($A9-0.000000001))-Beta_y*$A9,"") -> 258.1533 | G9: =IF(COUNTIFS(Sch_n,G$5,Sch_bmax,">="&($A9-0.000000001))>0,_xlfn.MAXIFS(Sch_P0,Sch_n,G$5,Sch_bmax,">="&($A9-0.000000001))-Beta_y*$A9,"") -> 184.09432 | H9: =IF(COUNTIFS(Sch_n,H$5,Sch_bmax,">="&($A9-0.000000001))>0,_xlfn.MAXIFS(Sch_P0,Sch_n,H$5,Sch_bmax,">="&($A9-0.000000001))-Beta_y*$A9,"") -> 103.86423 | J9: =IF(ISNUMBER(B9),1,0) -> 1 | K9: =IF(ISNUMBER(C9),1,0) -> 1 | L9: =IF(ISNUMBER(D9),1,0) -> 1 | M9: =IF(ISNUMBER(E9),1,0) -> 1 | N9: =IF(ISNUMBER(F9),1,0) -> 1 | O9: =IF(ISNUMBER(G9),1,0) -> 1 | P9: =IF(ISNUMBER(H9),1,0) -> 1 | R9: =IF(J9=1,_xlfn.MINIFS(Sch_idx,Sch_n,B$5,Sch_bmax,">="&($A9-0.000000001),Sch_P0,">="&(B9+Beta_y*$A9-0.000000001)),"") -> 0 | S9: =IF(K9=1,_xlfn.MINIFS(Sch_idx,Sch_n,C$5,Sch_bmax,">="&($A9-0.000000001),Sch_P0,">="&(C9+Beta_y*$A9-0.000000001)),"") -> 32 | T9: =IF(L9=1,_xlfn.MINIFS(Sch_idx,Sch_n,D$5,Sch_bmax,">="&($A9-0.000000001),Sch_P0,">="&(D9+Beta_y*$A9-0.000000001)),"") -> 48 | U9: =IF(M9=1,_xlfn.MINIFS(Sch_idx,Sch_n,E$5,Sch_bmax,">="&($A9-0.000000001),Sch_P0,">="&(E9+Beta_y*$A9-0.000000001)),"") -> 56 | V9: =IF(N9=1,_xlfn.MINIFS(Sch_idx,Sch_n,F$5,Sch_bmax,">="&($A9-0.000000001),Sch_P0,">="&(F9+Beta_y*$A9-0.000000001)),"") -> 57 | W9: =IF(O9=1,_xlfn.MINIFS(Sch_idx,Sch_n,G$5,Sch_bmax,">="&($A9-0.000000001),Sch_P0,">="&(G9+Beta_y*$A9-0.000000001)),"") -> 59 | X9: =IF(P9=1,_xlfn.MINIFS(Sch_idx,Sch_n,H$5,Sch_bmax,">="&($A9-0.000000001),Sch_P0,">="&(H9+Beta_y*$A9-0.000000001)),"") -> 63 | Z9: =IF(J9=1,IF(COUNTIFS(K9:$P9,1,C9:$H9,">="&(B9-0.000000001))>0,0,1),"") -> 0 | AA9: =IF(K9=1,IF(COUNTIFS(L9:$P9,1,D9:$H9,">="&(C9-0.000000001))>0,0,1),"") -> 0 | AB9: =IF(L9=1,IF(COUNTIFS(M9:$P9,1,E9:$H9,">="&(D9-0.000000001))>0,0,1),"") -> 1 | AC9: =IF(M9=1,IF(COUNTIFS(N9:$P9,1,F9:$H9,">="&(E9-0.000000001))>0,0,1),"") -> 1 | AD9: =IF(N9=1,IF(COUNTIFS(O9:$P9,1,G9:$H9,">="&(F9-0.000000001))>0,0,1),"") -> 1 | AE9: =IF(O9=1,IF(COUNTIFS(P9:$P9,1,H9:$H9,">="&(G9-0.000000001))>0,0,1),"") -> 1 | AF9: =IF(P9=1,1,"") -> 1
A10: 4 | B10: =IF(COUNTIFS(Sch_n,B$5,Sch_bmax,">="&($A10-0.000000001))>0,_xlfn.MAXIFS(Sch_P0,Sch_n,B$5,Sch_bmax,">="&($A10-0.000000001))-Beta_y*$A10,"") -> 132.72727 | C10: =IF(COUNTIFS(Sch_n,C$5,Sch_bmax,">="&($A10-0.000000001))>0,_xlfn.MAXIFS(Sch_P0,Sch_n,C$5,Sch_bmax,">="&($A10-0.000000001))-Beta_y*$A10,"") -> 367.03628 | D10: =IF(COUNTIFS(Sch_n,D$5,Sch_bmax,">="&($A10-0.000000001))>0,_xlfn.MAXIFS(Sch_P0,Sch_n,D$5,Sch_bmax,">="&($A10-0.000000001))-Beta_y*$A10,"") -> 380.53697 | E10: =IF(COUNTIFS(Sch_n,E$5,Sch_bmax,">="&($A10-0.000000001))>0,_xlfn.MAXIFS(Sch_P0,Sch_n,E$5,Sch_bmax,">="&($A10-0.000000001))-Beta_y*$A10,"") -> 326.81562 | F10: =IF(COUNTIFS(Sch_n,F$5,Sch_bmax,">="&($A10-0.000000001))>0,_xlfn.MAXIFS(Sch_P0,Sch_n,F$5,Sch_bmax,">="&($A10-0.000000001))-Beta_y*$A10,"") -> 257.24421 | G10: =IF(COUNTIFS(Sch_n,G$5,Sch_bmax,">="&($A10-0.000000001))>0,_xlfn.MAXIFS(Sch_P0,Sch_n,G$5,Sch_bmax,">="&($A10-0.000000001))-Beta_y*$A10,"") -> 183.18523 | H10: =IF(COUNTIFS(Sch_n,H$5,Sch_bmax,">="&($A10-0.000000001))>0,_xlfn.MAXIFS(Sch_P0,Sch_n,H$5,Sch_bmax,">="&($A10-0.000000001))-Beta_y*$A10,"") -> 102.95514 | J10: =IF(ISNUMBER(B10),1,0) -> 1 | K10: =IF(ISNUMBER(C10),1,0) -> 1 | L10: =IF(ISNUMBER(D10),1,0) -> 1 | M10: =IF(ISNUMBER(E10),1,0) -> 1 | N10: =IF(ISNUMBER(F10),1,0) -> 1 | O10: =IF(ISNUMBER(G10),1,0) -> 1 | P10: =IF(ISNUMBER(H10),1,0) -> 1 | R10: =IF(J10=1,_xlfn.MINIFS(Sch_idx,Sch_n,B$5,Sch_bmax,">="&($A10-0.000000001),Sch_P0,">="&(B10+Beta_y*$A10-0.000000001)),"") -> 0 | S10: =IF(K10=1,_xlfn.MINIFS(Sch_idx,Sch_n,C$5,Sch_bmax,">="&($A10-0.000000001),Sch_P0,">="&(C10+Beta_y*$A10-0.000000001)),"") -> 32 | T10: =IF(L10=1,_xlfn.MINIFS(Sch_idx,Sch_n,D$5,Sch_bmax,">="&($A10-0.000000001),Sch_P0,">="&(D10+Beta_y*$A10-0.000000001)),"") -> 48 | U10: =IF(M10=1,_xlfn.MINIFS(Sch_idx,Sch_n,E$5,Sch_bmax,">="&($A10-0.000000001),Sch_P0,">="&(E10+Beta_y*$A10-0.000000001)),"") -> 56 | V10: =IF(N10=1,_xlfn.MINIFS(Sch_idx,Sch_n,F$5,Sch_bmax,">="&($A10-0.000000001),Sch_P0,">="&(F10+Beta_y*$A10-0.000000001)),"") -> 57 | W10: =IF(O10=1,_xlfn.MINIFS(Sch_idx,Sch_n,G$5,Sch_bmax,">="&($A10-0.000000001),Sch_P0,">="&(G10+Beta_y*$A10-0.000000001)),"") -> 59 | X10: =IF(P10=1,_xlfn.MINIFS(Sch_idx,Sch_n,H$5,Sch_bmax,">="&($A10-0.000000001),Sch_P0,">="&(H10+Beta_y*$A10-0.000000001)),"") -> 63 | Z10: =IF(J10=1,IF(COUNTIFS(K10:$P10,1,C10:$H10,">="&(B10-0.000000001))>0,0,1),"") -> 0 | AA10: =IF(K10=1,IF(COUNTIFS(L10:$P10,1,D10:$H10,">="&(C10-0.000000001))>0,0,1),"") -> 0 | AB10: =IF(L10=1,IF(COUNTIFS(M10:$P10,1,E10:$H10,">="&(D10-0.000000001))>0,0,1),"") -> 1 | AC10: =IF(M10=1,IF(COUNTIFS(N10:$P10,1,F10:$H10,">="&(E10-0.000000001))>0,0,1),"") -> 1 | AD10: =IF(N10=1,IF(COUNTIFS(O10:$P10,1,G10:$H10,">="&(F10-0.000000001))>0,0,1),"") -> 1 | AE10: =IF(O10=1,IF(COUNTIFS(P10:$P10,1,H10:$H10,">="&(G10-0.000000001))>0,0,1),"") -> 1 | AF10: =IF(P10=1,1,"") -> 1
A11: 5 | B11: =IF(COUNTIFS(Sch_n,B$5,Sch_bmax,">="&($A11-0.000000001))>0,_xlfn.MAXIFS(Sch_P0,Sch_n,B$5,Sch_bmax,">="&($A11-0.000000001))-Beta_y*$A11,"") -> 131.81818 | C11: =IF(COUNTIFS(Sch_n,C$5,Sch_bmax,">="&($A11-0.000000001))>0,_xlfn.MAXIFS(Sch_P0,Sch_n,C$5,Sch_bmax,">="&($A11-0.000000001))-Beta_y*$A11,"") -> 366.12719 | D11: =IF(COUNTIFS(Sch_n,D$5,Sch_bmax,">="&($A11-0.000000001))>0,_xlfn.MAXIFS(Sch_P0,Sch_n,D$5,Sch_bmax,">="&($A11-0.000000001))-Beta_y*$A11,"") -> 379.62788 | E11: =IF(COUNTIFS(Sch_n,E$5,Sch_bmax,">="&($A11-0.000000001))>0,_xlfn.MAXIFS(Sch_P0,Sch_n,E$5,Sch_bmax,">="&($A11-0.000000001))-Beta_y*$A11,"") -> 325.90653 | F11: =IF(COUNTIFS(Sch_n,F$5,Sch_bmax,">="&($A11-0.000000001))>0,_xlfn.MAXIFS(Sch_P0,Sch_n,F$5,Sch_bmax,">="&($A11-0.000000001))-Beta_y*$A11,"") -> 256.33512 | G11: =IF(COUNTIFS(Sch_n,G$5,Sch_bmax,">="&($A11-0.000000001))>0,_xlfn.MAXIFS(Sch_P0,Sch_n,G$5,Sch_bmax,">="&($A11-0.000000001))-Beta_y*$A11,"") -> 182.27614 | H11: =IF(COUNTIFS(Sch_n,H$5,Sch_bmax,">="&($A11-0.000000001))>0,_xlfn.MAXIFS(Sch_P0,Sch_n,H$5,Sch_bmax,">="&($A11-0.000000001))-Beta_y*$A11,"") -> 102.04605 | J11: =IF(ISNUMBER(B11),1,0) -> 1 | K11: =IF(ISNUMBER(C11),1,0) -> 1 | L11: =IF(ISNUMBER(D11),1,0) -> 1 | M11: =IF(ISNUMBER(E11),1,0) -> 1 | N11: =IF(ISNUMBER(F11),1,0) -> 1 | O11: =IF(ISNUMBER(G11),1,0) -> 1 | P11: =IF(ISNUMBER(H11),1,0) -> 1 | R11: =IF(J11=1,_xlfn.MINIFS(Sch_idx,Sch_n,B$5,Sch_bmax,">="&($A11-0.000000001),Sch_P0,">="&(B11+Beta_y*$A11-0.000000001)),"") -> 0 | S11: =IF(K11=1,_xlfn.MINIFS(Sch_idx,Sch_n,C$5,Sch_bmax,">="&($A11-0.000000001),Sch_P0,">="&(C11+Beta_y*$A11-0.000000001)),"") -> 32 | T11: =IF(L11=1,_xlfn.MINIFS(Sch_idx,Sch_n,D$5,Sch_bmax,">="&($A11-0.000000001),Sch_P0,">="&(D11+Beta_y*$A11-0.000000001)),"") -> 48 | U11: =IF(M11=1,_xlfn.MINIFS(Sch_idx,Sch_n,E$5,Sch_bmax,">="&($A11-0.000000001),Sch_P0,">="&(E11+Beta_y*$A11-0.000000001)),"") -> 56 | V11: =IF(N11=1,_xlfn.MINIFS(Sch_idx,Sch_n,F$5,Sch_bmax,">="&($A11-0.000000001),Sch_P0,">="&(F11+Beta_y*$A11-0.000000001)),"") -> 57 | W11: =IF(O11=1,_xlfn.MINIFS(Sch_idx,Sch_n,G$5,Sch_bmax,">="&($A11-0.000000001),Sch_P0,">="&(G11+Beta_y*$A11-0.000000001)),"") -> 59 | X11: =IF(P11=1,_xlfn.MINIFS(Sch_idx,Sch_n,H$5,Sch_bmax,">="&($A11-0.000000001),Sch_P0,">="&(H11+Beta_y*$A11-0.000000001)),"") -> 63 | Z11: =IF(J11=1,IF(COUNTIFS(K11:$P11,1,C11:$H11,">="&(B11-0.000000001))>0,0,1),"") -> 0 | AA11: =IF(K11=1,IF(COUNTIFS(L11:$P11,1,D11:$H11,">="&(C11-0.000000001))>0,0,1),"") -> 0 | AB11: =IF(L11=1,IF(COUNTIFS(M11:$P11,1,E11:$H11,">="&(D11-0.000000001))>0,0,1),"") -> 1 | AC11: =IF(M11=1,IF(COUNTIFS(N11:$P11,1,F11:$H11,">="&(E11-0.000000001))>0,0,1),"") -> 1 | AD11: =IF(N11=1,IF(COUNTIFS(O11:$P11,1,G11:$H11,">="&(F11-0.000000001))>0,0,1),"") -> 1 | AE11: =IF(O11=1,IF(COUNTIFS(P11:$P11,1,H11:$H11,">="&(G11-0.000000001))>0,0,1),"") -> 1 | AF11: =IF(P11=1,1,"") -> 1
A12: 6 | B12: =IF(COUNTIFS(Sch_n,B$5,Sch_bmax,">="&($A12-0.000000001))>0,_xlfn.MAXIFS(Sch_P0,Sch_n,B$5,Sch_bmax,">="&($A12-0.000000001))-Beta_y*$A12,"") -> 130.90909 | C12: =IF(COUNTIFS(Sch_n,C$5,Sch_bmax,">="&($A12-0.000000001))>0,_xlfn.MAXIFS(Sch_P0,Sch_n,C$5,Sch_bmax,">="&($A12-0.000000001))-Beta_y*$A12,"") -> 365.2181 | D12: =IF(COUNTIFS(Sch_n,D$5,Sch_bmax,">="&($A12-0.000000001))>0,_xlfn.MAXIFS(Sch_P0,Sch_n,D$5,Sch_bmax,">="&($A12-0.000000001))-Beta_y*$A12,"") -> 378.71879 | E12: =IF(COUNTIFS(Sch_n,E$5,Sch_bmax,">="&($A12-0.000000001))>0,_xlfn.MAXIFS(Sch_P0,Sch_n,E$5,Sch_bmax,">="&($A12-0.000000001))-Beta_y*$A12,"") -> 324.99744 | F12: =IF(COUNTIFS(Sch_n,F$5,Sch_bmax,">="&($A12-0.000000001))>0,_xlfn.MAXIFS(Sch_P0,Sch_n,F$5,Sch_bmax,">="&($A12-0.000000001))-Beta_y*$A12,"") -> 255.42603 | G12: =IF(COUNTIFS(Sch_n,G$5,Sch_bmax,">="&($A12-0.000000001))>0,_xlfn.MAXIFS(Sch_P0,Sch_n,G$5,Sch_bmax,">="&($A12-0.000000001))-Beta_y*$A12,"") -> 181.36705 | H12: =IF(COUNTIFS(Sch_n,H$5,Sch_bmax,">="&($A12-0.000000001))>0,_xlfn.MAXIFS(Sch_P0,Sch_n,H$5,Sch_bmax,">="&($A12-0.000000001))-Beta_y*$A12,"") -> 101.13696 | J12: =IF(ISNUMBER(B12),1,0) -> 1 | K12: =IF(ISNUMBER(C12),1,0) -> 1 | L12: =IF(ISNUMBER(D12),1,0) -> 1 | M12: =IF(ISNUMBER(E12),1,0) -> 1 | N12: =IF(ISNUMBER(F12),1,0) -> 1 | O12: =IF(ISNUMBER(G12),1,0) -> 1 | P12: =IF(ISNUMBER(H12),1,0) -> 1 | R12: =IF(J12=1,_xlfn.MINIFS(Sch_idx,Sch_n,B$5,Sch_bmax,">="&($A12-0.000000001),Sch_P0,">="&(B12+Beta_y*$A12-0.000000001)),"") -> 0 | S12: =IF(K12=1,_xlfn.MINIFS(Sch_idx,Sch_n,C$5,Sch_bmax,">="&($A12-0.000000001),Sch_P0,">="&(C12+Beta_y*$A12-0.000000001)),"") -> 32 | T12: =IF(L12=1,_xlfn.MINIFS(Sch_idx,Sch_n,D$5,Sch_bmax,">="&($A12-0.000000001),Sch_P0,">="&(D12+Beta_y*$A12-0.000000001)),"") -> 48 | U12: =IF(M12=1,_xlfn.MINIFS(Sch_idx,Sch_n,E$5,Sch_bmax,">="&($A12-0.000000001),Sch_P0,">="&(E12+Beta_y*$A12-0.000000001)),"") -> 56 | V12: =IF(N12=1,_xlfn.MINIFS(Sch_idx,Sch_n,F$5,Sch_bmax,">="&($A12-0.000000001),Sch_P0,">="&(F12+Beta_y*$A12-0.000000001)),"") -> 57 | W12: =IF(O12=1,_xlfn.MINIFS(Sch_idx,Sch_n,G$5,Sch_bmax,">="&($A12-0.000000001),Sch_P0,">="&(G12+Beta_y*$A12-0.000000001)),"") -> 59 | X12: =IF(P12=1,_xlfn.MINIFS(Sch_idx,Sch_n,H$5,Sch_bmax,">="&($A12-0.000000001),Sch_P0,">="&(H12+Beta_y*$A12-0.000000001)),"") -> 63 | Z12: =IF(J12=1,IF(COUNTIFS(K12:$P12,1,C12:$H12,">="&(B12-0.000000001))>0,0,1),"") -> 0 | AA12: =IF(K12=1,IF(COUNTIFS(L12:$P12,1,D12:$H12,">="&(C12-0.000000001))>0,0,1),"") -> 0 | AB12: =IF(L12=1,IF(COUNTIFS(M12:$P12,1,E12:$H12,">="&(D12-0.000000001))>0,0,1),"") -> 1 | AC12: =IF(M12=1,IF(COUNTIFS(N12:$P12,1,F12:$H12,">="&(E12-0.000000001))>0,0,1),"") -> 1 | AD12: =IF(N12=1,IF(COUNTIFS(O12:$P12,1,G12:$H12,">="&(F12-0.000000001))>0,0,1),"") -> 1 | AE12: =IF(O12=1,IF(COUNTIFS(P12:$P12,1,H12:$H12,">="&(G12-0.000000001))>0,0,1),"") -> 1 | AF12: =IF(P12=1,1,"") -> 1
A13: 7 | B13: =IF(COUNTIFS(Sch_n,B$5,Sch_bmax,">="&($A13-0.000000001))>0,_xlfn.MAXIFS(Sch_P0,Sch_n,B$5,Sch_bmax,">="&($A13-0.000000001))-Beta_y*$A13,"") -> 130 | C13: =IF(COUNTIFS(Sch_n,C$5,Sch_bmax,">="&($A13-0.000000001))>0,_xlfn.MAXIFS(Sch_P0,Sch_n,C$5,Sch_bmax,">="&($A13-0.000000001))-Beta_y*$A13,"") -> 364.30901 | D13: =IF(COUNTIFS(Sch_n,D$5,Sch_bmax,">="&($A13-0.000000001))>0,_xlfn.MAXIFS(Sch_P0,Sch_n,D$5,Sch_bmax,">="&($A13-0.000000001))-Beta_y*$A13,"") -> 377.8097 | E13: =IF(COUNTIFS(Sch_n,E$5,Sch_bmax,">="&($A13-0.000000001))>0,_xlfn.MAXIFS(Sch_P0,Sch_n,E$5,Sch_bmax,">="&($A13-0.000000001))-Beta_y*$A13,"") -> 324.08835 | F13: =IF(COUNTIFS(Sch_n,F$5,Sch_bmax,">="&($A13-0.000000001))>0,_xlfn.MAXIFS(Sch_P0,Sch_n,F$5,Sch_bmax,">="&($A13-0.000000001))-Beta_y*$A13,"") -> 254.51694 | G13: =IF(COUNTIFS(Sch_n,G$5,Sch_bmax,">="&($A13-0.000000001))>0,_xlfn.MAXIFS(Sch_P0,Sch_n,G$5,Sch_bmax,">="&($A13-0.000000001))-Beta_y*$A13,"") -> 180.45796 | H13: =IF(COUNTIFS(Sch_n,H$5,Sch_bmax,">="&($A13-0.000000001))>0,_xlfn.MAXIFS(Sch_P0,Sch_n,H$5,Sch_bmax,">="&($A13-0.000000001))-Beta_y*$A13,"") -> 100.22787 | J13: =IF(ISNUMBER(B13),1,0) -> 1 | K13: =IF(ISNUMBER(C13),1,0) -> 1 | L13: =IF(ISNUMBER(D13),1,0) -> 1 | M13: =IF(ISNUMBER(E13),1,0) -> 1 | N13: =IF(ISNUMBER(F13),1,0) -> 1 | O13: =IF(ISNUMBER(G13),1,0) -> 1 | P13: =IF(ISNUMBER(H13),1,0) -> 1 | R13: =IF(J13=1,_xlfn.MINIFS(Sch_idx,Sch_n,B$5,Sch_bmax,">="&($A13-0.000000001),Sch_P0,">="&(B13+Beta_y*$A13-0.000000001)),"") -> 0 | S13: =IF(K13=1,_xlfn.MINIFS(Sch_idx,Sch_n,C$5,Sch_bmax,">="&($A13-0.000000001),Sch_P0,">="&(C13+Beta_y*$A13-0.000000001)),"") -> 32 | T13: =IF(L13=1,_xlfn.MINIFS(Sch_idx,Sch_n,D$5,Sch_bmax,">="&($A13-0.000000001),Sch_P0,">="&(D13+Beta_y*$A13-0.000000001)),"") -> 48 | U13: =IF(M13=1,_xlfn.MINIFS(Sch_idx,Sch_n,E$5,Sch_bmax,">="&($A13-0.000000001),Sch_P0,">="&(E13+Beta_y*$A13-0.000000001)),"") -> 56 | V13: =IF(N13=1,_xlfn.MINIFS(Sch_idx,Sch_n,F$5,Sch_bmax,">="&($A13-0.000000001),Sch_P0,">="&(F13+Beta_y*$A13-0.000000001)),"") -> 57 | W13: =IF(O13=1,_xlfn.MINIFS(Sch_idx,Sch_n,G$5,Sch_bmax,">="&($A13-0.000000001),Sch_P0,">="&(G13+Beta_y*$A13-0.000000001)),"") -> 59 | X13: =IF(P13=1,_xlfn.MINIFS(Sch_idx,Sch_n,H$5,Sch_bmax,">="&($A13-0.000000001),Sch_P0,">="&(H13+Beta_y*$A13-0.000000001)),"") -> 63 | Z13: =IF(J13=1,IF(COUNTIFS(K13:$P13,1,C13:$H13,">="&(B13-0.000000001))>0,0,1),"") -> 0 | AA13: =IF(K13=1,IF(COUNTIFS(L13:$P13,1,D13:$H13,">="&(C13-0.000000001))>0,0,1),"") -> 0 | AB13: =IF(L13=1,IF(COUNTIFS(M13:$P13,1,E13:$H13,">="&(D13-0.000000001))>0,0,1),"") -> 1 | AC13: =IF(M13=1,IF(COUNTIFS(N13:$P13,1,F13:$H13,">="&(E13-0.000000001))>0,0,1),"") -> 1 | AD13: =IF(N13=1,IF(COUNTIFS(O13:$P13,1,G13:$H13,">="&(F13-0.000000001))>0,0,1),"") -> 1 | AE13: =IF(O13=1,IF(COUNTIFS(P13:$P13,1,H13:$H13,">="&(G13-0.000000001))>0,0,1),"") -> 1 | AF13: =IF(P13=1,1,"") -> 1
A14: 8 | B14: =IF(COUNTIFS(Sch_n,B$5,Sch_bmax,">="&($A14-0.000000001))>0,_xlfn.MAXIFS(Sch_P0,Sch_n,B$5,Sch_bmax,">="&($A14-0.000000001))-Beta_y*$A14,"") -> 129.09091 | C14: =IF(COUNTIFS(Sch_n,C$5,Sch_bmax,">="&($A14-0.000000001))>0,_xlfn.MAXIFS(Sch_P0,Sch_n,C$5,Sch_bmax,">="&($A14-0.000000001))-Beta_y*$A14,"") -> 363.39992 | D14: =IF(COUNTIFS(Sch_n,D$5,Sch_bmax,">="&($A14-0.000000001))>0,_xlfn.MAXIFS(Sch_P0,Sch_n,D$5,Sch_bmax,">="&($A14-0.000000001))-Beta_y*$A14,"") -> 376.90061 | E14: =IF(COUNTIFS(Sch_n,E$5,Sch_bmax,">="&($A14-0.000000001))>0,_xlfn.MAXIFS(Sch_P0,Sch_n,E$5,Sch_bmax,">="&($A14-0.000000001))-Beta_y*$A14,"") -> 323.17926 | F14: =IF(COUNTIFS(Sch_n,F$5,Sch_bmax,">="&($A14-0.000000001))>0,_xlfn.MAXIFS(Sch_P0,Sch_n,F$5,Sch_bmax,">="&($A14-0.000000001))-Beta_y*$A14,"") -> 253.60785 | G14: =IF(COUNTIFS(Sch_n,G$5,Sch_bmax,">="&($A14-0.000000001))>0,_xlfn.MAXIFS(Sch_P0,Sch_n,G$5,Sch_bmax,">="&($A14-0.000000001))-Beta_y*$A14,"") -> 179.54887 | H14: =IF(COUNTIFS(Sch_n,H$5,Sch_bmax,">="&($A14-0.000000001))>0,_xlfn.MAXIFS(Sch_P0,Sch_n,H$5,Sch_bmax,">="&($A14-0.000000001))-Beta_y*$A14,"") -> 99.318776 | J14: =IF(ISNUMBER(B14),1,0) -> 1 | K14: =IF(ISNUMBER(C14),1,0) -> 1 | L14: =IF(ISNUMBER(D14),1,0) -> 1 | M14: =IF(ISNUMBER(E14),1,0) -> 1 | N14: =IF(ISNUMBER(F14),1,0) -> 1 | O14: =IF(ISNUMBER(G14),1,0) -> 1 | P14: =IF(ISNUMBER(H14),1,0) -> 1 | R14: =IF(J14=1,_xlfn.MINIFS(Sch_idx,Sch_n,B$5,Sch_bmax,">="&($A14-0.000000001),Sch_P0,">="&(B14+Beta_y*$A14-0.000000001)),"") -> 0 | S14: =IF(K14=1,_xlfn.MINIFS(Sch_idx,Sch_n,C$5,Sch_bmax,">="&($A14-0.000000001),Sch_P0,">="&(C14+Beta_y*$A14-0.000000001)),"") -> 32 | T14: =IF(L14=1,_xlfn.MINIFS(Sch_idx,Sch_n,D$5,Sch_bmax,">="&($A14-0.000000001),Sch_P0,">="&(D14+Beta_y*$A14-0.000000001)),"") -> 48 | U14: =IF(M14=1,_xlfn.MINIFS(Sch_idx,Sch_n,E$5,Sch_bmax,">="&($A14-0.000000001),Sch_P0,">="&(E14+Beta_y*$A14-0.000000001)),"") -> 56 | V14: =IF(N14=1,_xlfn.MINIFS(Sch_idx,Sch_n,F$5,Sch_bmax,">="&($A14-0.000000001),Sch_P0,">="&(F14+Beta_y*$A14-0.000000001)),"") -> 57 | W14: =IF(O14=1,_xlfn.MINIFS(Sch_idx,Sch_n,G$5,Sch_bmax,">="&($A14-0.000000001),Sch_P0,">="&(G14+Beta_y*$A14-0.000000001)),"") -> 59 | X14: =IF(P14=1,_xlfn.MINIFS(Sch_idx,Sch_n,H$5,Sch_bmax,">="&($A14-0.000000001),Sch_P0,">="&(H14+Beta_y*$A14-0.000000001)),"") -> 63 | Z14: =IF(J14=1,IF(COUNTIFS(K14:$P14,1,C14:$H14,">="&(B14-0.000000001))>0,0,1),"") -> 0 | AA14: =IF(K14=1,IF(COUNTIFS(L14:$P14,1,D14:$H14,">="&(C14-0.000000001))>0,0,1),"") -> 0 | AB14: =IF(L14=1,IF(COUNTIFS(M14:$P14,1,E14:$H14,">="&(D14-0.000000001))>0,0,1),"") -> 1 | AC14: =IF(M14=1,IF(COUNTIFS(N14:$P14,1,F14:$H14,">="&(E14-0.000000001))>0,0,1),"") -> 1 | AD14: =IF(N14=1,IF(COUNTIFS(O14:$P14,1,G14:$H14,">="&(F14-0.000000001))>0,0,1),"") -> 1 | AE14: =IF(O14=1,IF(COUNTIFS(P14:$P14,1,H14:$H14,">="&(G14-0.000000001))>0,0,1),"") -> 1 | AF14: =IF(P14=1,1,"") -> 1
A15: 9 | B15: =IF(COUNTIFS(Sch_n,B$5,Sch_bmax,">="&($A15-0.000000001))>0,_xlfn.MAXIFS(Sch_P0,Sch_n,B$5,Sch_bmax,">="&($A15-0.000000001))-Beta_y*$A15,"") -> 128.18182 | C15: =IF(COUNTIFS(Sch_n,C$5,Sch_bmax,">="&($A15-0.000000001))>0,_xlfn.MAXIFS(Sch_P0,Sch_n,C$5,Sch_bmax,">="&($A15-0.000000001))-Beta_y*$A15,"") -> 362.49083 | D15: =IF(COUNTIFS(Sch_n,D$5,Sch_bmax,">="&($A15-0.000000001))>0,_xlfn.MAXIFS(Sch_P0,Sch_n,D$5,Sch_bmax,">="&($A15-0.000000001))-Beta_y*$A15,"") -> 375.99152 | E15: =IF(COUNTIFS(Sch_n,E$5,Sch_bmax,">="&($A15-0.000000001))>0,_xlfn.MAXIFS(Sch_P0,Sch_n,E$5,Sch_bmax,">="&($A15-0.000000001))-Beta_y*$A15,"") -> 322.27017 | F15: =IF(COUNTIFS(Sch_n,F$5,Sch_bmax,">="&($A15-0.000000001))>0,_xlfn.MAXIFS(Sch_P0,Sch_n,F$5,Sch_bmax,">="&($A15-0.000000001))-Beta_y*$A15,"") -> 252.69876 | G15: =IF(COUNTIFS(Sch_n,G$5,Sch_bmax,">="&($A15-0.000000001))>0,_xlfn.MAXIFS(Sch_P0,Sch_n,G$5,Sch_bmax,">="&($A15-0.000000001))-Beta_y*$A15,"") -> 178.63978 | H15: =IF(COUNTIFS(Sch_n,H$5,Sch_bmax,">="&($A15-0.000000001))>0,_xlfn.MAXIFS(Sch_P0,Sch_n,H$5,Sch_bmax,">="&($A15-0.000000001))-Beta_y*$A15,"") -> 98.409685 | J15: =IF(ISNUMBER(B15),1,0) -> 1 | K15: =IF(ISNUMBER(C15),1,0) -> 1 | L15: =IF(ISNUMBER(D15),1,0) -> 1 | M15: =IF(ISNUMBER(E15),1,0) -> 1 | N15: =IF(ISNUMBER(F15),1,0) -> 1 | O15: =IF(ISNUMBER(G15),1,0) -> 1 | P15: =IF(ISNUMBER(H15),1,0) -> 1 | R15: =IF(J15=1,_xlfn.MINIFS(Sch_idx,Sch_n,B$5,Sch_bmax,">="&($A15-0.000000001),Sch_P0,">="&(B15+Beta_y*$A15-0.000000001)),"") -> 0 | S15: =IF(K15=1,_xlfn.MINIFS(Sch_idx,Sch_n,C$5,Sch_bmax,">="&($A15-0.000000001),Sch_P0,">="&(C15+Beta_y*$A15-0.000000001)),"") -> 32 | T15: =IF(L15=1,_xlfn.MINIFS(Sch_idx,Sch_n,D$5,Sch_bmax,">="&($A15-0.000000001),Sch_P0,">="&(D15+Beta_y*$A15-0.000000001)),"") -> 48 | U15: =IF(M15=1,_xlfn.MINIFS(Sch_idx,Sch_n,E$5,Sch_bmax,">="&($A15-0.000000001),Sch_P0,">="&(E15+Beta_y*$A15-0.000000001)),"") -> 56 | V15: =IF(N15=1,_xlfn.MINIFS(Sch_idx,Sch_n,F$5,Sch_bmax,">="&($A15-0.000000001),Sch_P0,">="&(F15+Beta_y*$A15-0.000000001)),"") -> 57 | W15: =IF(O15=1,_xlfn.MINIFS(Sch_idx,Sch_n,G$5,Sch_bmax,">="&($A15-0.000000001),Sch_P0,">="&(G15+Beta_y*$A15-0.000000001)),"") -> 59 | X15: =IF(P15=1,_xlfn.MINIFS(Sch_idx,Sch_n,H$5,Sch_bmax,">="&($A15-0.000000001),Sch_P0,">="&(H15+Beta_y*$A15-0.000000001)),"") -> 63 | Z15: =IF(J15=1,IF(COUNTIFS(K15:$P15,1,C15:$H15,">="&(B15-0.000000001))>0,0,1),"") -> 0 | AA15: =IF(K15=1,IF(COUNTIFS(L15:$P15,1,D15:$H15,">="&(C15-0.000000001))>0,0,1),"") -> 0 | AB15: =IF(L15=1,IF(COUNTIFS(M15:$P15,1,E15:$H15,">="&(D15-0.000000001))>0,0,1),"") -> 1 | AC15: =IF(M15=1,IF(COUNTIFS(N15:$P15,1,F15:$H15,">="&(E15-0.000000001))>0,0,1),"") -> 1 | AD15: =IF(N15=1,IF(COUNTIFS(O15:$P15,1,G15:$H15,">="&(F15-0.000000001))>0,0,1),"") -> 1 | AE15: =IF(O15=1,IF(COUNTIFS(P15:$P15,1,H15:$H15,">="&(G15-0.000000001))>0,0,1),"") -> 1 | AF15: =IF(P15=1,1,"") -> 1
A16: 10 | B16: =IF(COUNTIFS(Sch_n,B$5,Sch_bmax,">="&($A16-0.000000001))>0,_xlfn.MAXIFS(Sch_P0,Sch_n,B$5,Sch_bmax,">="&($A16-0.000000001))-Beta_y*$A16,"") -> 127.27273 | C16: =IF(COUNTIFS(Sch_n,C$5,Sch_bmax,">="&($A16-0.000000001))>0,_xlfn.MAXIFS(Sch_P0,Sch_n,C$5,Sch_bmax,">="&($A16-0.000000001))-Beta_y*$A16,"") -> 361.58173 | D16: =IF(COUNTIFS(Sch_n,D$5,Sch_bmax,">="&($A16-0.000000001))>0,_xlfn.MAXIFS(Sch_P0,Sch_n,D$5,Sch_bmax,">="&($A16-0.000000001))-Beta_y*$A16,"") -> 375.08243 | E16: =IF(COUNTIFS(Sch_n,E$5,Sch_bmax,">="&($A16-0.000000001))>0,_xlfn.MAXIFS(Sch_P0,Sch_n,E$5,Sch_bmax,">="&($A16-0.000000001))-Beta_y*$A16,"") -> 321.36108 | F16: =IF(COUNTIFS(Sch_n,F$5,Sch_bmax,">="&($A16-0.000000001))>0,_xlfn.MAXIFS(Sch_P0,Sch_n,F$5,Sch_bmax,">="&($A16-0.000000001))-Beta_y*$A16,"") -> 251.78966 | G16: =IF(COUNTIFS(Sch_n,G$5,Sch_bmax,">="&($A16-0.000000001))>0,_xlfn.MAXIFS(Sch_P0,Sch_n,G$5,Sch_bmax,">="&($A16-0.000000001))-Beta_y*$A16,"") -> 177.73068 | H16: =IF(COUNTIFS(Sch_n,H$5,Sch_bmax,">="&($A16-0.000000001))>0,_xlfn.MAXIFS(Sch_P0,Sch_n,H$5,Sch_bmax,">="&($A16-0.000000001))-Beta_y*$A16,"") -> 97.500594 | J16: =IF(ISNUMBER(B16),1,0) -> 1 | K16: =IF(ISNUMBER(C16),1,0) -> 1 | L16: =IF(ISNUMBER(D16),1,0) -> 1 | M16: =IF(ISNUMBER(E16),1,0) -> 1 | N16: =IF(ISNUMBER(F16),1,0) -> 1 | O16: =IF(ISNUMBER(G16),1,0) -> 1 | P16: =IF(ISNUMBER(H16),1,0) -> 1 | R16: =IF(J16=1,_xlfn.MINIFS(Sch_idx,Sch_n,B$5,Sch_bmax,">="&($A16-0.000000001),Sch_P0,">="&(B16+Beta_y*$A16-0.000000001)),"") -> 0 | S16: =IF(K16=1,_xlfn.MINIFS(Sch_idx,Sch_n,C$5,Sch_bmax,">="&($A16-0.000000001),Sch_P0,">="&(C16+Beta_y*$A16-0.000000001)),"") -> 32 | T16: =IF(L16=1,_xlfn.MINIFS(Sch_idx,Sch_n,D$5,Sch_bmax,">="&($A16-0.000000001),Sch_P0,">="&(D16+Beta_y*$A16-0.000000001)),"") -> 48 | U16: =IF(M16=1,_xlfn.MINIFS(Sch_idx,Sch_n,E$5,Sch_bmax,">="&($A16-0.000000001),Sch_P0,">="&(E16+Beta_y*$A16-0.000000001)),"") -> 56 | V16: =IF(N16=1,_xlfn.MINIFS(Sch_idx,Sch_n,F$5,Sch_bmax,">="&($A16-0.000000001),Sch_P0,">="&(F16+Beta_y*$A16-0.000000001)),"") -> 57 | W16: =IF(O16=1,_xlfn.MINIFS(Sch_idx,Sch_n,G$5,Sch_bmax,">="&($A16-0.000000001),Sch_P0,">="&(G16+Beta_y*$A16-0.000000001)),"") -> 59 | X16: =IF(P16=1,_xlfn.MINIFS(Sch_idx,Sch_n,H$5,Sch_bmax,">="&($A16-0.000000001),Sch_P0,">="&(H16+Beta_y*$A16-0.000000001)),"") -> 63 | Z16: =IF(J16=1,IF(COUNTIFS(K16:$P16,1,C16:$H16,">="&(B16-0.000000001))>0,0,1),"") -> 0 | AA16: =IF(K16=1,IF(COUNTIFS(L16:$P16,1,D16:$H16,">="&(C16-0.000000001))>0,0,1),"") -> 0 | AB16: =IF(L16=1,IF(COUNTIFS(M16:$P16,1,E16:$H16,">="&(D16-0.000000001))>0,0,1),"") -> 1 | AC16: =IF(M16=1,IF(COUNTIFS(N16:$P16,1,F16:$H16,">="&(E16-0.000000001))>0,0,1),"") -> 1 | AD16: =IF(N16=1,IF(COUNTIFS(O16:$P16,1,G16:$H16,">="&(F16-0.000000001))>0,0,1),"") -> 1 | AE16: =IF(O16=1,IF(COUNTIFS(P16:$P16,1,H16:$H16,">="&(G16-0.000000001))>0,0,1),"") -> 1 | AF16: =IF(P16=1,1,"") -> 1
A17: 11 | B17: =IF(COUNTIFS(Sch_n,B$5,Sch_bmax,">="&($A17-0.000000001))>0,_xlfn.MAXIFS(Sch_P0,Sch_n,B$5,Sch_bmax,">="&($A17-0.000000001))-Beta_y*$A17,"") -> 126.36364 | C17: =IF(COUNTIFS(Sch_n,C$5,Sch_bmax,">="&($A17-0.000000001))>0,_xlfn.MAXIFS(Sch_P0,Sch_n,C$5,Sch_bmax,">="&($A17-0.000000001))-Beta_y*$A17,"") -> 360.67264 | D17: =IF(COUNTIFS(Sch_n,D$5,Sch_bmax,">="&($A17-0.000000001))>0,_xlfn.MAXIFS(Sch_P0,Sch_n,D$5,Sch_bmax,">="&($A17-0.000000001))-Beta_y*$A17,"") -> 374.17334 | E17: =IF(COUNTIFS(Sch_n,E$5,Sch_bmax,">="&($A17-0.000000001))>0,_xlfn.MAXIFS(Sch_P0,Sch_n,E$5,Sch_bmax,">="&($A17-0.000000001))-Beta_y*$A17,"") -> 320.45199 | F17: =IF(COUNTIFS(Sch_n,F$5,Sch_bmax,">="&($A17-0.000000001))>0,_xlfn.MAXIFS(Sch_P0,Sch_n,F$5,Sch_bmax,">="&($A17-0.000000001))-Beta_y*$A17,"") -> 250.88057 | G17: =IF(COUNTIFS(Sch_n,G$5,Sch_bmax,">="&($A17-0.000000001))>0,_xlfn.MAXIFS(Sch_P0,Sch_n,G$5,Sch_bmax,">="&($A17-0.000000001))-Beta_y*$A17,"") -> 176.82159 | H17: =IF(COUNTIFS(Sch_n,H$5,Sch_bmax,">="&($A17-0.000000001))>0,_xlfn.MAXIFS(Sch_P0,Sch_n,H$5,Sch_bmax,">="&($A17-0.000000001))-Beta_y*$A17,"") -> 96.591503 | J17: =IF(ISNUMBER(B17),1,0) -> 1 | K17: =IF(ISNUMBER(C17),1,0) -> 1 | L17: =IF(ISNUMBER(D17),1,0) -> 1 | M17: =IF(ISNUMBER(E17),1,0) -> 1 | N17: =IF(ISNUMBER(F17),1,0) -> 1 | O17: =IF(ISNUMBER(G17),1,0) -> 1 | P17: =IF(ISNUMBER(H17),1,0) -> 1 | R17: =IF(J17=1,_xlfn.MINIFS(Sch_idx,Sch_n,B$5,Sch_bmax,">="&($A17-0.000000001),Sch_P0,">="&(B17+Beta_y*$A17-0.000000001)),"") -> 0 | S17: =IF(K17=1,_xlfn.MINIFS(Sch_idx,Sch_n,C$5,Sch_bmax,">="&($A17-0.000000001),Sch_P0,">="&(C17+Beta_y*$A17-0.000000001)),"") -> 32 | T17: =IF(L17=1,_xlfn.MINIFS(Sch_idx,Sch_n,D$5,Sch_bmax,">="&($A17-0.000000001),Sch_P0,">="&(D17+Beta_y*$A17-0.000000001)),"") -> 48 | U17: =IF(M17=1,_xlfn.MINIFS(Sch_idx,Sch_n,E$5,Sch_bmax,">="&($A17-0.000000001),Sch_P0,">="&(E17+Beta_y*$A17-0.000000001)),"") -> 56 | V17: =IF(N17=1,_xlfn.MINIFS(Sch_idx,Sch_n,F$5,Sch_bmax,">="&($A17-0.000000001),Sch_P0,">="&(F17+Beta_y*$A17-0.000000001)),"") -> 57 | W17: =IF(O17=1,_xlfn.MINIFS(Sch_idx,Sch_n,G$5,Sch_bmax,">="&($A17-0.000000001),Sch_P0,">="&(G17+Beta_y*$A17-0.000000001)),"") -> 59 | X17: =IF(P17=1,_xlfn.MINIFS(Sch_idx,Sch_n,H$5,Sch_bmax,">="&($A17-0.000000001),Sch_P0,">="&(H17+Beta_y*$A17-0.000000001)),"") -> 63 | Z17: =IF(J17=1,IF(COUNTIFS(K17:$P17,1,C17:$H17,">="&(B17-0.000000001))>0,0,1),"") -> 0 | AA17: =IF(K17=1,IF(COUNTIFS(L17:$P17,1,D17:$H17,">="&(C17-0.000000001))>0,0,1),"") -> 0 | AB17: =IF(L17=1,IF(COUNTIFS(M17:$P17,1,E17:$H17,">="&(D17-0.000000001))>0,0,1),"") -> 1 | AC17: =IF(M17=1,IF(COUNTIFS(N17:$P17,1,F17:$H17,">="&(E17-0.000000001))>0,0,1),"") -> 1 | AD17: =IF(N17=1,IF(COUNTIFS(O17:$P17,1,G17:$H17,">="&(F17-0.000000001))>0,0,1),"") -> 1 | AE17: =IF(O17=1,IF(COUNTIFS(P17:$P17,1,H17:$H17,">="&(G17-0.000000001))>0,0,1),"") -> 1 | AF17: =IF(P17=1,1,"") -> 1
... A156: 150 | B156: =IF(COUNTIFS(Sch_n,B$5,Sch_bmax,">="&($A156-0.000000001))>0,_xlfn.MAXIFS(Sch_P0,Sch_n,B$5,Sch_bmax,">="&($A156-0.000000001))-Beta_y*$A156,"") -> 0 | C156: =IF(COUNTIFS(Sch_n,C$5,Sch_bmax,">="&($A156-0.000000001))>0,_xlfn.MAXIFS(Sch_P0,Sch_n,C$5,Sch_bmax,">="&($A156-0.000000001))-Beta_y*$A156,"") -> 234.30901 | D156: =IF(COUNTIFS(Sch_n,D$5,Sch_bmax,">="&($A156-0.000000001))>0,_xlfn.MAXIFS(Sch_P0,Sch_n,D$5,Sch_bmax,">="&($A156-0.000000001))-Beta_y*$A156,"") -> 224.6692 | E156: =IF(COUNTIFS(Sch_n,E$5,Sch_bmax,">="&($A156-0.000000001))>0,_xlfn.MAXIFS(Sch_P0,Sch_n,E$5,Sch_bmax,">="&($A156-0.000000001))-Beta_y*$A156,"") -> 165.68865 | F156: =IF(COUNTIFS(Sch_n,F$5,Sch_bmax,">="&($A156-0.000000001))>0,_xlfn.MAXIFS(Sch_P0,Sch_n,F$5,Sch_bmax,">="&($A156-0.000000001))-Beta_y*$A156,"") -> 96.117238 | G156: =IF(COUNTIFS(Sch_n,G$5,Sch_bmax,">="&($A156-0.000000001))>0,_xlfn.MAXIFS(Sch_P0,Sch_n,G$5,Sch_bmax,">="&($A156-0.000000001))-Beta_y*$A156,"") -> 22.058258 | H156: =IF(COUNTIFS(Sch_n,H$5,Sch_bmax,">="&($A156-0.000000001))>0,_xlfn.MAXIFS(Sch_P0,Sch_n,H$5,Sch_bmax,">="&($A156-0.000000001))-Beta_y*$A156,"") | J156: =IF(ISNUMBER(B156),1,0) -> 1 | K156: =IF(ISNUMBER(C156),1,0) -> 1 | L156: =IF(ISNUMBER(D156),1,0) -> 1 | M156: =IF(ISNUMBER(E156),1,0) -> 1 | N156: =IF(ISNUMBER(F156),1,0) -> 1 | O156: =IF(ISNUMBER(G156),1,0) -> 1 | P156: =IF(ISNUMBER(H156),1,0) -> 0 | R156: =IF(J156=1,_xlfn.MINIFS(Sch_idx,Sch_n,B$5,Sch_bmax,">="&($A156-0.000000001),Sch_P0,">="&(B156+Beta_y*$A156-0.000000001)),"") -> 0 | S156: =IF(K156=1,_xlfn.MINIFS(Sch_idx,Sch_n,C$5,Sch_bmax,">="&($A156-0.000000001),Sch_P0,">="&(C156+Beta_y*$A156-0.000000001)),"") -> 32 | T156: =IF(L156=1,_xlfn.MINIFS(Sch_idx,Sch_n,D$5,Sch_bmax,">="&($A156-0.000000001),Sch_P0,">="&(D156+Beta_y*$A156-0.000000001)),"") -> 40 | U156: =IF(M156=1,_xlfn.MINIFS(Sch_idx,Sch_n,E$5,Sch_bmax,">="&($A156-0.000000001),Sch_P0,">="&(E156+Beta_y*$A156-0.000000001)),"") -> 44 | V156: =IF(N156=1,_xlfn.MINIFS(Sch_idx,Sch_n,F$5,Sch_bmax,">="&($A156-0.000000001),Sch_P0,">="&(F156+Beta_y*$A156-0.000000001)),"") -> 45 | W156: =IF(O156=1,_xlfn.MINIFS(Sch_idx,Sch_n,G$5,Sch_bmax,">="&($A156-0.000000001),Sch_P0,">="&(G156+Beta_y*$A156-0.000000001)),"") -> 47 | X156: =IF(P156=1,_xlfn.MINIFS(Sch_idx,Sch_n,H$5,Sch_bmax,">="&($A156-0.000000001),Sch_P0,">="&(H156+Beta_y*$A156-0.000000001)),"") | Z156: =IF(J156=1,IF(COUNTIFS(K156:$P156,1,C156:$H156,">="&(B156-0.000000001))>0,0,1),"") -> 0 | AA156: =IF(K156=1,IF(COUNTIFS(L156:$P156,1,D156:$H156,">="&(C156-0.000000001))>0,0,1),"") -> 1 | AB156: =IF(L156=1,IF(COUNTIFS(M156:$P156,1,E156:$H156,">="&(D156-0.000000001))>0,0,1),"") -> 1 | AC156: =IF(M156=1,IF(COUNTIFS(N156:$P156,1,F156:$H156,">="&(E156-0.000000001))>0,0,1),"") -> 1 | AD156: =IF(N156=1,IF(COUNTIFS(O156:$P156,1,G156:$H156,">="&(F156-0.000000001))>0,0,1),"") -> 1 | AE156: =IF(O156=1,IF(COUNTIFS(P156:$P156,1,H156:$H156,">="&(G156-0.000000001))>0,0,1),"") -> 1 | AF156: =IF(P156=1,1,"")
A158: Plans | B158: =SUM(J6:P156) -> 992 | C158: 992 plans: the best for their number of rounds and reserve (six rounds stop at $85 million) | J158: =SUM(J6:J156) -> 151 | K158: =SUM(K6:K156) -> 151 | L158: =SUM(L6:L156) -> 151 | M158: =SUM(M6:M156) -> 151 | N158: =SUM(N6:N156) -> 151 | O158: =SUM(O6:O156) -> 151 | P158: =SUM(P6:P156) -> 86
A159: Efficient | B159: =SUM(Z6:AF156) -> 740 | C159: 740 efficient (Online Appendix Example 12.B.2) | Z159: =SUM(Z6:Z156) -> 0 | AA159: =SUM(AA6:AA156) -> 50 | AB159: =SUM(AB6:AB156) -> 151 | AC159: =SUM(AC6:AC156) -> 151 | AD159: =SUM(AD6:AD156) -> 151 | AE159: =SUM(AE6:AE156) -> 151 | AF159: =SUM(AF6:AF156) -> 86

Sheet Plans
A1: The three-objective frontier: every (rounds, reserve) pair, its efficiency, the engine's support test with its certificate, and the Chebyshev values (Theorems 12.2(iii) and 12.3; Worked Example 12.1, Steps 4-5)
A2: Supported: some weights, each at least 0.001 of their sum, on the objectives scaled by their ranges, make the plan the best weighted sum (engine: one linear program per efficient plan). Certificate, checked by formulas: the weights, for a supported plan; for a plan in a dent, an average of at most three efficient plans that is better in every objective, which rules out every choice of nonnegative weights (Theorem 12.2(iii)).
A3: Chebyshev: shortfalls from the ideal point as shares of the ideal-nadir range, weighted; the value is the largest plus rho times their sum (Choose holds the weights).
A5: k | B5: Rounds n | C5: Reserve b | D5: Feasible | E5: Payouts (PV) | F5: Savings, year 6 | G5: Reserve | H5: Schedule # | I5: Rounds (years) | J5: Efficient | K5: Payouts if efficient, else 0 | L5: Board value | M5: Supported (engine) | N5: Weight w1 (engine) | O5: w2 (engine) | P5: w3 (engine) | Q5: Average: plan 1 rounds (engine) | R5: plan 1 reserve | S5: plan 1 share | T5: plan 2 rounds | U5: plan 2 reserve | V5: plan 2 share | W5: plan 3 rounds | X5: plan 3 reserve | Y5: plan 3 share | Z5: Its weighted value at its weights | AA5: Best weighted value of any efficient plan | AB5: Best at its weights (1 = yes) | AC5: Average's payouts | AD5: Average's savings | AE5: Average's reserve | AF5: Average's least margin (share of range) | AG5: Beaten in every objective (1 = yes) | AH5: Certified (1 = yes) | AI5: Shortfall: payouts | AJ5: Shortfall: savings | AK5: Shortfall: reserve | AL5: Chebyshev value, weights A | AM5: Chebyshev value, weights B | AN5: Chebyshev value, the explorer's weights
A6: 0 | B6: =INT(A6/151) -> 0 | C6: =MOD(A6,151) -> 0 | D6: =INDEX(Grid!$J$6:$P$156,C6+1,B6+1) -> 1 | E6: =IF(D6=1,INDEX(Grid!$B$6:$H$156,C6+1,B6+1),"") -> 136.36364 | F6: =Val_pt*(Ceiling_e-E_zero)*(1-(1-Half_gap)^B6) -> 0 | G6: =C6 -> 0 | H6: =IF(D6=1,INDEX(Grid!$R$6:$X$156,C6+1,B6+1),"") -> 0 | I6: =IF(D6=1,INDEX(Sch_label,H6+1),"") -> none | J6: =IF(D6=1,INDEX(Grid!$Z$6:$AF$156,C6+1,B6+1),0) -> 0 | K6: =IF(J6=1,E6,0) -> 0 | L6: =IF(D6=1,E6+W_board*F6,"") -> 136.36364 | Z6: =IF(AND($J6=1,$M6=1),N6*E6/Span_P+O6*F6/Span_S+P6*G6/Span_B,"") | AA6: =IF(AND($J6=1,$M6=1),SUMPRODUCT(MAX($J$6:$J$1062*(N6*$K$6:$K$1062/Span_P+O6*$F$6:$F$1062/Span_S+P6*$G$6:$G$1062/Span_B)-(1-$J$6:$J$1062)*1000000000)),"") | AB6: =IF(AND($J6=1,$M6=1),IF(AA6-Z6<=0.000000001,1,0),"") | AC6: =IF(AND($J6=1,$M6=0),IF(S6="",0,S6*INDEX(Grid!$B$6:$H$156,R6+1,Q6+1))+IF(V6="",0,V6*INDEX(Grid!$B$6:$H$156,U6+1,T6+1))+IF(Y6="",0,Y6*INDEX(Grid!$B$6:$H$156,X6+1,W6+1)),"") | AD6: =IF(AND($J6=1,$M6=0),IF(S6="",0,S6*Val_pt*(Ceiling_e-E_zero)*(1-(1-Half_gap)^Q6))+IF(V6="",0,V6*Val_pt*(Ceiling_e-E_zero)*(1-(1-Half_gap)^T6))+IF(Y6="",0,Y6*Val_pt*(Ceiling_e-E_zero)*(1-(1-Half_gap)^W6)),"") | AE6: =IF(AND($J6=1,$M6=0),IF(S6="",0,S6*R6)+IF(V6="",0,V6*U6)+IF(Y6="",0,Y6*X6),"") | AF6: =IF(AND($J6=1,$M6=0),MIN((AC6-E6)/Span_P,(AD6-F6)/Span_S,(AE6-G6)/Span_B),"") | AG6: =IF(AND($J6=1,$M6=0),IF(AF6>0.0000001,1,0),"") | AH6: =IF($J6=1,IF($M6=1,AB6,AG6),"") | AI6: =IF($J6=1,(Ideal_P-E6)/Span_P,"") | AJ6: =IF($J6=1,(Ideal_S-F6)/Span_S,"") | AK6: =IF($J6=1,(Ideal_B-G6)/Span_B,"") | AL6: =IF($J6=1,MAX(ChA_1*AI6,ChA_2*AJ6,ChA_3*AK6)+Rho*(ChA_1*AI6+ChA_2*AJ6+ChA_3*AK6),"") | AM6: =IF($J6=1,MAX(ChB_1*AI6,ChB_2*AJ6,ChB_3*AK6)+Rho*(ChB_1*AI6+ChB_2*AJ6+ChB_3*AK6),"") | AN6: =IF($J6=1,MAX(Cx_1*(Ref_P-E6)/Span_P,Cx_2*(Ref_S-F6)/Span_S,Cx_3*(Ref_B-G6)/Span_B),"")
A7: 1 | B7: =INT(A7/151) -> 0 | C7: =MOD(A7,151) -> 1 | D7: =INDEX(Grid!$J$6:$P$156,C7+1,B7+1) -> 1 | E7: =IF(D7=1,INDEX(Grid!$B$6:$H$156,C7+1,B7+1),"") -> 135.45455 | F7: =Val_pt*(Ceiling_e-E_zero)*(1-(1-Half_gap)^B7) -> 0 | G7: =C7 -> 1 | H7: =IF(D7=1,INDEX(Grid!$R$6:$X$156,C7+1,B7+1),"") -> 0 | I7: =IF(D7=1,INDEX(Sch_label,H7+1),"") -> none | J7: =IF(D7=1,INDEX(Grid!$Z$6:$AF$156,C7+1,B7+1),0) -> 0 | K7: =IF(J7=1,E7,0) -> 0 | L7: =IF(D7=1,E7+W_board*F7,"") -> 135.45455 | Z7: =IF(AND($J7=1,$M7=1),N7*E7/Span_P+O7*F7/Span_S+P7*G7/Span_B,"") | AA7: =IF(AND($J7=1,$M7=1),SUMPRODUCT(MAX($J$6:$J$1062*(N7*$K$6:$K$1062/Span_P+O7*$F$6:$F$1062/Span_S+P7*$G$6:$G$1062/Span_B)-(1-$J$6:$J$1062)*1000000000)),"") | AB7: =IF(AND($J7=1,$M7=1),IF(AA7-Z7<=0.000000001,1,0),"") | AC7: =IF(AND($J7=1,$M7=0),IF(S7="",0,S7*INDEX(Grid!$B$6:$H$156,R7+1,Q7+1))+IF(V7="",0,V7*INDEX(Grid!$B$6:$H$156,U7+1,T7+1))+IF(Y7="",0,Y7*INDEX(Grid!$B$6:$H$156,X7+1,W7+1)),"") | AD7: =IF(AND($J7=1,$M7=0),IF(S7="",0,S7*Val_pt*(Ceiling_e-E_zero)*(1-(1-Half_gap)^Q7))+IF(V7="",0,V7*Val_pt*(Ceiling_e-E_zero)*(1-(1-Half_gap)^T7))+IF(Y7="",0,Y7*Val_pt*(Ceiling_e-E_zero)*(1-(1-Half_gap)^W7)),"") | AE7: =IF(AND($J7=1,$M7=0),IF(S7="",0,S7*R7)+IF(V7="",0,V7*U7)+IF(Y7="",0,Y7*X7),"") | AF7: =IF(AND($J7=1,$M7=0),MIN((AC7-E7)/Span_P,(AD7-F7)/Span_S,(AE7-G7)/Span_B),"") | AG7: =IF(AND($J7=1,$M7=0),IF(AF7>0.0000001,1,0),"") | AH7: =IF($J7=1,IF($M7=1,AB7,AG7),"") | AI7: =IF($J7=1,(Ideal_P-E7)/Span_P,"") | AJ7: =IF($J7=1,(Ideal_S-F7)/Span_S,"") | AK7: =IF($J7=1,(Ideal_B-G7)/Span_B,"") | AL7: =IF($J7=1,MAX(ChA_1*AI7,ChA_2*AJ7,ChA_3*AK7)+Rho*(ChA_1*AI7+ChA_2*AJ7+ChA_3*AK7),"") | AM7: =IF($J7=1,MAX(ChB_1*AI7,ChB_2*AJ7,ChB_3*AK7)+Rho*(ChB_1*AI7+ChB_2*AJ7+ChB_3*AK7),"") | AN7: =IF($J7=1,MAX(Cx_1*(Ref_P-E7)/Span_P,Cx_2*(Ref_S-F7)/Span_S,Cx_3*(Ref_B-G7)/Span_B),"")
A8: 2 | B8: =INT(A8/151) -> 0 | C8: =MOD(A8,151) -> 2 | D8: =INDEX(Grid!$J$6:$P$156,C8+1,B8+1) -> 1 | E8: =IF(D8=1,INDEX(Grid!$B$6:$H$156,C8+1,B8+1),"") -> 134.54545 | F8: =Val_pt*(Ceiling_e-E_zero)*(1-(1-Half_gap)^B8) -> 0 | G8: =C8 -> 2 | H8: =IF(D8=1,INDEX(Grid!$R$6:$X$156,C8+1,B8+1),"") -> 0 | I8: =IF(D8=1,INDEX(Sch_label,H8+1),"") -> none | J8: =IF(D8=1,INDEX(Grid!$Z$6:$AF$156,C8+1,B8+1),0) -> 0 | K8: =IF(J8=1,E8,0) -> 0 | L8: =IF(D8=1,E8+W_board*F8,"") -> 134.54545 | Z8: =IF(AND($J8=1,$M8=1),N8*E8/Span_P+O8*F8/Span_S+P8*G8/Span_B,"") | AA8: =IF(AND($J8=1,$M8=1),SUMPRODUCT(MAX($J$6:$J$1062*(N8*$K$6:$K$1062/Span_P+O8*$F$6:$F$1062/Span_S+P8*$G$6:$G$1062/Span_B)-(1-$J$6:$J$1062)*1000000000)),"") | AB8: =IF(AND($J8=1,$M8=1),IF(AA8-Z8<=0.000000001,1,0),"") | AC8: =IF(AND($J8=1,$M8=0),IF(S8="",0,S8*INDEX(Grid!$B$6:$H$156,R8+1,Q8+1))+IF(V8="",0,V8*INDEX(Grid!$B$6:$H$156,U8+1,T8+1))+IF(Y8="",0,Y8*INDEX(Grid!$B$6:$H$156,X8+1,W8+1)),"") | AD8: =IF(AND($J8=1,$M8=0),IF(S8="",0,S8*Val_pt*(Ceiling_e-E_zero)*(1-(1-Half_gap)^Q8))+IF(V8="",0,V8*Val_pt*(Ceiling_e-E_zero)*(1-(1-Half_gap)^T8))+IF(Y8="",0,Y8*Val_pt*(Ceiling_e-E_zero)*(1-(1-Half_gap)^W8)),"") | AE8: =IF(AND($J8=1,$M8=0),IF(S8="",0,S8*R8)+IF(V8="",0,V8*U8)+IF(Y8="",0,Y8*X8),"") | AF8: =IF(AND($J8=1,$M8=0),MIN((AC8-E8)/Span_P,(AD8-F8)/Span_S,(AE8-G8)/Span_B),"") | AG8: =IF(AND($J8=1,$M8=0),IF(AF8>0.0000001,1,0),"") | AH8: =IF($J8=1,IF($M8=1,AB8,AG8),"") | AI8: =IF($J8=1,(Ideal_P-E8)/Span_P,"") | AJ8: =IF($J8=1,(Ideal_S-F8)/Span_S,"") | AK8: =IF($J8=1,(Ideal_B-G8)/Span_B,"") | AL8: =IF($J8=1,MAX(ChA_1*AI8,ChA_2*AJ8,ChA_3*AK8)+Rho*(ChA_1*AI8+ChA_2*AJ8+ChA_3*AK8),"") | AM8: =IF($J8=1,MAX(ChB_1*AI8,ChB_2*AJ8,ChB_3*AK8)+Rho*(ChB_1*AI8+ChB_2*AJ8+ChB_3*AK8),"") | AN8: =IF($J8=1,MAX(Cx_1*(Ref_P-E8)/Span_P,Cx_2*(Ref_S-F8)/Span_S,Cx_3*(Ref_B-G8)/Span_B),"")
A9: 3 | B9: =INT(A9/151) -> 0 | C9: =MOD(A9,151) -> 3 | D9: =INDEX(Grid!$J$6:$P$156,C9+1,B9+1) -> 1 | E9: =IF(D9=1,INDEX(Grid!$B$6:$H$156,C9+1,B9+1),"") -> 133.63636 | F9: =Val_pt*(Ceiling_e-E_zero)*(1-(1-Half_gap)^B9) -> 0 | G9: =C9 -> 3 | H9: =IF(D9=1,INDEX(Grid!$R$6:$X$156,C9+1,B9+1),"") -> 0 | I9: =IF(D9=1,INDEX(Sch_label,H9+1),"") -> none | J9: =IF(D9=1,INDEX(Grid!$Z$6:$AF$156,C9+1,B9+1),0) -> 0 | K9: =IF(J9=1,E9,0) -> 0 | L9: =IF(D9=1,E9+W_board*F9,"") -> 133.63636 | Z9: =IF(AND($J9=1,$M9=1),N9*E9/Span_P+O9*F9/Span_S+P9*G9/Span_B,"") | AA9: =IF(AND($J9=1,$M9=1),SUMPRODUCT(MAX($J$6:$J$1062*(N9*$K$6:$K$1062/Span_P+O9*$F$6:$F$1062/Span_S+P9*$G$6:$G$1062/Span_B)-(1-$J$6:$J$1062)*1000000000)),"") | AB9: =IF(AND($J9=1,$M9=1),IF(AA9-Z9<=0.000000001,1,0),"") | AC9: =IF(AND($J9=1,$M9=0),IF(S9="",0,S9*INDEX(Grid!$B$6:$H$156,R9+1,Q9+1))+IF(V9="",0,V9*INDEX(Grid!$B$6:$H$156,U9+1,T9+1))+IF(Y9="",0,Y9*INDEX(Grid!$B$6:$H$156,X9+1,W9+1)),"") | AD9: =IF(AND($J9=1,$M9=0),IF(S9="",0,S9*Val_pt*(Ceiling_e-E_zero)*(1-(1-Half_gap)^Q9))+IF(V9="",0,V9*Val_pt*(Ceiling_e-E_zero)*(1-(1-Half_gap)^T9))+IF(Y9="",0,Y9*Val_pt*(Ceiling_e-E_zero)*(1-(1-Half_gap)^W9)),"") | AE9: =IF(AND($J9=1,$M9=0),IF(S9="",0,S9*R9)+IF(V9="",0,V9*U9)+IF(Y9="",0,Y9*X9),"") | AF9: =IF(AND($J9=1,$M9=0),MIN((AC9-E9)/Span_P,(AD9-F9)/Span_S,(AE9-G9)/Span_B),"") | AG9: =IF(AND($J9=1,$M9=0),IF(AF9>0.0000001,1,0),"") | AH9: =IF($J9=1,IF($M9=1,AB9,AG9),"") | AI9: =IF($J9=1,(Ideal_P-E9)/Span_P,"") | AJ9: =IF($J9=1,(Ideal_S-F9)/Span_S,"") | AK9: =IF($J9=1,(Ideal_B-G9)/Span_B,"") | AL9: =IF($J9=1,MAX(ChA_1*AI9,ChA_2*AJ9,ChA_3*AK9)+Rho*(ChA_1*AI9+ChA_2*AJ9+ChA_3*AK9),"") | AM9: =IF($J9=1,MAX(ChB_1*AI9,ChB_2*AJ9,ChB_3*AK9)+Rho*(ChB_1*AI9+ChB_2*AJ9+ChB_3*AK9),"") | AN9: =IF($J9=1,MAX(Cx_1*(Ref_P-E9)/Span_P,Cx_2*(Ref_S-F9)/Span_S,Cx_3*(Ref_B-G9)/Span_B),"")
A10: 4 | B10: =INT(A10/151) -> 0 | C10: =MOD(A10,151) -> 4 | D10: =INDEX(Grid!$J$6:$P$156,C10+1,B10+1) -> 1 | E10: =IF(D10=1,INDEX(Grid!$B$6:$H$156,C10+1,B10+1),"") -> 132.72727 | F10: =Val_pt*(Ceiling_e-E_zero)*(1-(1-Half_gap)^B10) -> 0 | G10: =C10 -> 4 | H10: =IF(D10=1,INDEX(Grid!$R$6:$X$156,C10+1,B10+1),"") -> 0 | I10: =IF(D10=1,INDEX(Sch_label,H10+1),"") -> none | J10: =IF(D10=1,INDEX(Grid!$Z$6:$AF$156,C10+1,B10+1),0) -> 0 | K10: =IF(J10=1,E10,0) -> 0 | L10: =IF(D10=1,E10+W_board*F10,"") -> 132.72727 | Z10: =IF(AND($J10=1,$M10=1),N10*E10/Span_P+O10*F10/Span_S+P10*G10/Span_B,"") | AA10: =IF(AND($J10=1,$M10=1),SUMPRODUCT(MAX($J$6:$J$1062*(N10*$K$6:$K$1062/Span_P+O10*$F$6:$F$1062/Span_S+P10*$G$6:$G$1062/Span_B)-(1-$J$6:$J$1062)*1000000000)),"") | AB10: =IF(AND($J10=1,$M10=1),IF(AA10-Z10<=0.000000001,1,0),"") | AC10: =IF(AND($J10=1,$M10=0),IF(S10="",0,S10*INDEX(Grid!$B$6:$H$156,R10+1,Q10+1))+IF(V10="",0,V10*INDEX(Grid!$B$6:$H$156,U10+1,T10+1))+IF(Y10="",0,Y10*INDEX(Grid!$B$6:$H$156,X10+1,W10+1)),"") | AD10: =IF(AND($J10=1,$M10=0),IF(S10="",0,S10*Val_pt*(Ceiling_e-E_zero)*(1-(1-Half_gap)^Q10))+IF(V10="",0,V10*Val_pt*(Ceiling_e-E_zero)*(1-(1-Half_gap)^T10))+IF(Y10="",0,Y10*Val_pt*(Ceiling_e-E_zero)*(1-(1-Half_gap)^W10)),"") | AE10: =IF(AND($J10=1,$M10=0),IF(S10="",0,S10*R10)+IF(V10="",0,V10*U10)+IF(Y10="",0,Y10*X10),"") | AF10: =IF(AND($J10=1,$M10=0),MIN((AC10-E10)/Span_P,(AD10-F10)/Span_S,(AE10-G10)/Span_B),"") | AG10: =IF(AND($J10=1,$M10=0),IF(AF10>0.0000001,1,0),"") | AH10: =IF($J10=1,IF($M10=1,AB10,AG10),"") | AI10: =IF($J10=1,(Ideal_P-E10)/Span_P,"") | AJ10: =IF($J10=1,(Ideal_S-F10)/Span_S,"") | AK10: =IF($J10=1,(Ideal_B-G10)/Span_B,"") | AL10: =IF($J10=1,MAX(ChA_1*AI10,ChA_2*AJ10,ChA_3*AK10)+Rho*(ChA_1*AI10+ChA_2*AJ10+ChA_3*AK10),"") | AM10: =IF($J10=1,MAX(ChB_1*AI10,ChB_2*AJ10,ChB_3*AK10)+Rho*(ChB_1*AI10+ChB_2*AJ10+ChB_3*AK10),"") | AN10: =IF($J10=1,MAX(Cx_1*(Ref_P-E10)/Span_P,Cx_2*(Ref_S-F10)/Span_S,Cx_3*(Ref_B-G10)/Span_B),"")
A11: 5 | B11: =INT(A11/151) -> 0 | C11: =MOD(A11,151) -> 5 | D11: =INDEX(Grid!$J$6:$P$156,C11+1,B11+1) -> 1 | E11: =IF(D11=1,INDEX(Grid!$B$6:$H$156,C11+1,B11+1),"") -> 131.81818 | F11: =Val_pt*(Ceiling_e-E_zero)*(1-(1-Half_gap)^B11) -> 0 | G11: =C11 -> 5 | H11: =IF(D11=1,INDEX(Grid!$R$6:$X$156,C11+1,B11+1),"") -> 0 | I11: =IF(D11=1,INDEX(Sch_label,H11+1),"") -> none | J11: =IF(D11=1,INDEX(Grid!$Z$6:$AF$156,C11+1,B11+1),0) -> 0 | K11: =IF(J11=1,E11,0) -> 0 | L11: =IF(D11=1,E11+W_board*F11,"") -> 131.81818 | Z11: =IF(AND($J11=1,$M11=1),N11*E11/Span_P+O11*F11/Span_S+P11*G11/Span_B,"") | AA11: =IF(AND($J11=1,$M11=1),SUMPRODUCT(MAX($J$6:$J$1062*(N11*$K$6:$K$1062/Span_P+O11*$F$6:$F$1062/Span_S+P11*$G$6:$G$1062/Span_B)-(1-$J$6:$J$1062)*1000000000)),"") | AB11: =IF(AND($J11=1,$M11=1),IF(AA11-Z11<=0.000000001,1,0),"") | AC11: =IF(AND($J11=1,$M11=0),IF(S11="",0,S11*INDEX(Grid!$B$6:$H$156,R11+1,Q11+1))+IF(V11="",0,V11*INDEX(Grid!$B$6:$H$156,U11+1,T11+1))+IF(Y11="",0,Y11*INDEX(Grid!$B$6:$H$156,X11+1,W11+1)),"") | AD11: =IF(AND($J11=1,$M11=0),IF(S11="",0,S11*Val_pt*(Ceiling_e-E_zero)*(1-(1-Half_gap)^Q11))+IF(V11="",0,V11*Val_pt*(Ceiling_e-E_zero)*(1-(1-Half_gap)^T11))+IF(Y11="",0,Y11*Val_pt*(Ceiling_e-E_zero)*(1-(1-Half_gap)^W11)),"") | AE11: =IF(AND($J11=1,$M11=0),IF(S11="",0,S11*R11)+IF(V11="",0,V11*U11)+IF(Y11="",0,Y11*X11),"") | AF11: =IF(AND($J11=1,$M11=0),MIN((AC11-E11)/Span_P,(AD11-F11)/Span_S,(AE11-G11)/Span_B),"") | AG11: =IF(AND($J11=1,$M11=0),IF(AF11>0.0000001,1,0),"") | AH11: =IF($J11=1,IF($M11=1,AB11,AG11),"") | AI11: =IF($J11=1,(Ideal_P-E11)/Span_P,"") | AJ11: =IF($J11=1,(Ideal_S-F11)/Span_S,"") | AK11: =IF($J11=1,(Ideal_B-G11)/Span_B,"") | AL11: =IF($J11=1,MAX(ChA_1*AI11,ChA_2*AJ11,ChA_3*AK11)+Rho*(ChA_1*AI11+ChA_2*AJ11+ChA_3*AK11),"") | AM11: =IF($J11=1,MAX(ChB_1*AI11,ChB_2*AJ11,ChB_3*AK11)+Rho*(ChB_1*AI11+ChB_2*AJ11+ChB_3*AK11),"") | AN11: =IF($J11=1,MAX(Cx_1*(Ref_P-E11)/Span_P,Cx_2*(Ref_S-F11)/Span_S,Cx_3*(Ref_B-G11)/Span_B),"")
A12: 6 | B12: =INT(A12/151) -> 0 | C12: =MOD(A12,151) -> 6 | D12: =INDEX(Grid!$J$6:$P$156,C12+1,B12+1) -> 1 | E12: =IF(D12=1,INDEX(Grid!$B$6:$H$156,C12+1,B12+1),"") -> 130.90909 | F12: =Val_pt*(Ceiling_e-E_zero)*(1-(1-Half_gap)^B12) -> 0 | G12: =C12 -> 6 | H12: =IF(D12=1,INDEX(Grid!$R$6:$X$156,C12+1,B12+1),"") -> 0 | I12: =IF(D12=1,INDEX(Sch_label,H12+1),"") -> none | J12: =IF(D12=1,INDEX(Grid!$Z$6:$AF$156,C12+1,B12+1),0) -> 0 | K12: =IF(J12=1,E12,0) -> 0 | L12: =IF(D12=1,E12+W_board*F12,"") -> 130.90909 | Z12: =IF(AND($J12=1,$M12=1),N12*E12/Span_P+O12*F12/Span_S+P12*G12/Span_B,"") | AA12: =IF(AND($J12=1,$M12=1),SUMPRODUCT(MAX($J$6:$J$1062*(N12*$K$6:$K$1062/Span_P+O12*$F$6:$F$1062/Span_S+P12*$G$6:$G$1062/Span_B)-(1-$J$6:$J$1062)*1000000000)),"") | AB12: =IF(AND($J12=1,$M12=1),IF(AA12-Z12<=0.000000001,1,0),"") | AC12: =IF(AND($J12=1,$M12=0),IF(S12="",0,S12*INDEX(Grid!$B$6:$H$156,R12+1,Q12+1))+IF(V12="",0,V12*INDEX(Grid!$B$6:$H$156,U12+1,T12+1))+IF(Y12="",0,Y12*INDEX(Grid!$B$6:$H$156,X12+1,W12+1)),"") | AD12: =IF(AND($J12=1,$M12=0),IF(S12="",0,S12*Val_pt*(Ceiling_e-E_zero)*(1-(1-Half_gap)^Q12))+IF(V12="",0,V12*Val_pt*(Ceiling_e-E_zero)*(1-(1-Half_gap)^T12))+IF(Y12="",0,Y12*Val_pt*(Ceiling_e-E_zero)*(1-(1-Half_gap)^W12)),"") | AE12: =IF(AND($J12=1,$M12=0),IF(S12="",0,S12*R12)+IF(V12="",0,V12*U12)+IF(Y12="",0,Y12*X12),"") | AF12: =IF(AND($J12=1,$M12=0),MIN((AC12-E12)/Span_P,(AD12-F12)/Span_S,(AE12-G12)/Span_B),"") | AG12: =IF(AND($J12=1,$M12=0),IF(AF12>0.0000001,1,0),"") | AH12: =IF($J12=1,IF($M12=1,AB12,AG12),"") | AI12: =IF($J12=1,(Ideal_P-E12)/Span_P,"") | AJ12: =IF($J12=1,(Ideal_S-F12)/Span_S,"") | AK12: =IF($J12=1,(Ideal_B-G12)/Span_B,"") | AL12: =IF($J12=1,MAX(ChA_1*AI12,ChA_2*AJ12,ChA_3*AK12)+Rho*(ChA_1*AI12+ChA_2*AJ12+ChA_3*AK12),"") | AM12: =IF($J12=1,MAX(ChB_1*AI12,ChB_2*AJ12,ChB_3*AK12)+Rho*(ChB_1*AI12+ChB_2*AJ12+ChB_3*AK12),"") | AN12: =IF($J12=1,MAX(Cx_1*(Ref_P-E12)/Span_P,Cx_2*(Ref_S-F12)/Span_S,Cx_3*(Ref_B-G12)/Span_B),"")
A13: 7 | B13: =INT(A13/151) -> 0 | C13: =MOD(A13,151) -> 7 | D13: =INDEX(Grid!$J$6:$P$156,C13+1,B13+1) -> 1 | E13: =IF(D13=1,INDEX(Grid!$B$6:$H$156,C13+1,B13+1),"") -> 130 | F13: =Val_pt*(Ceiling_e-E_zero)*(1-(1-Half_gap)^B13) -> 0 | G13: =C13 -> 7 | H13: =IF(D13=1,INDEX(Grid!$R$6:$X$156,C13+1,B13+1),"") -> 0 | I13: =IF(D13=1,INDEX(Sch_label,H13+1),"") -> none | J13: =IF(D13=1,INDEX(Grid!$Z$6:$AF$156,C13+1,B13+1),0) -> 0 | K13: =IF(J13=1,E13,0) -> 0 | L13: =IF(D13=1,E13+W_board*F13,"") -> 130 | Z13: =IF(AND($J13=1,$M13=1),N13*E13/Span_P+O13*F13/Span_S+P13*G13/Span_B,"") | AA13: =IF(AND($J13=1,$M13=1),SUMPRODUCT(MAX($J$6:$J$1062*(N13*$K$6:$K$1062/Span_P+O13*$F$6:$F$1062/Span_S+P13*$G$6:$G$1062/Span_B)-(1-$J$6:$J$1062)*1000000000)),"") | AB13: =IF(AND($J13=1,$M13=1),IF(AA13-Z13<=0.000000001,1,0),"") | AC13: =IF(AND($J13=1,$M13=0),IF(S13="",0,S13*INDEX(Grid!$B$6:$H$156,R13+1,Q13+1))+IF(V13="",0,V13*INDEX(Grid!$B$6:$H$156,U13+1,T13+1))+IF(Y13="",0,Y13*INDEX(Grid!$B$6:$H$156,X13+1,W13+1)),"") | AD13: =IF(AND($J13=1,$M13=0),IF(S13="",0,S13*Val_pt*(Ceiling_e-E_zero)*(1-(1-Half_gap)^Q13))+IF(V13="",0,V13*Val_pt*(Ceiling_e-E_zero)*(1-(1-Half_gap)^T13))+IF(Y13="",0,Y13*Val_pt*(Ceiling_e-E_zero)*(1-(1-Half_gap)^W13)),"") | AE13: =IF(AND($J13=1,$M13=0),IF(S13="",0,S13*R13)+IF(V13="",0,V13*U13)+IF(Y13="",0,Y13*X13),"") | AF13: =IF(AND($J13=1,$M13=0),MIN((AC13-E13)/Span_P,(AD13-F13)/Span_S,(AE13-G13)/Span_B),"") | AG13: =IF(AND($J13=1,$M13=0),IF(AF13>0.0000001,1,0),"") | AH13: =IF($J13=1,IF($M13=1,AB13,AG13),"") | AI13: =IF($J13=1,(Ideal_P-E13)/Span_P,"") | AJ13: =IF($J13=1,(Ideal_S-F13)/Span_S,"") | AK13: =IF($J13=1,(Ideal_B-G13)/Span_B,"") | AL13: =IF($J13=1,MAX(ChA_1*AI13,ChA_2*AJ13,ChA_3*AK13)+Rho*(ChA_1*AI13+ChA_2*AJ13+ChA_3*AK13),"") | AM13: =IF($J13=1,MAX(ChB_1*AI13,ChB_2*AJ13,ChB_3*AK13)+Rho*(ChB_1*AI13+ChB_2*AJ13+ChB_3*AK13),"") | AN13: =IF($J13=1,MAX(Cx_1*(Ref_P-E13)/Span_P,Cx_2*(Ref_S-F13)/Span_S,Cx_3*(Ref_B-G13)/Span_B),"")
A14: 8 | B14: =INT(A14/151) -> 0 | C14: =MOD(A14,151) -> 8 | D14: =INDEX(Grid!$J$6:$P$156,C14+1,B14+1) -> 1 | E14: =IF(D14=1,INDEX(Grid!$B$6:$H$156,C14+1,B14+1),"") -> 129.09091 | F14: =Val_pt*(Ceiling_e-E_zero)*(1-(1-Half_gap)^B14) -> 0 | G14: =C14 -> 8 | H14: =IF(D14=1,INDEX(Grid!$R$6:$X$156,C14+1,B14+1),"") -> 0 | I14: =IF(D14=1,INDEX(Sch_label,H14+1),"") -> none | J14: =IF(D14=1,INDEX(Grid!$Z$6:$AF$156,C14+1,B14+1),0) -> 0 | K14: =IF(J14=1,E14,0) -> 0 | L14: =IF(D14=1,E14+W_board*F14,"") -> 129.09091 | Z14: =IF(AND($J14=1,$M14=1),N14*E14/Span_P+O14*F14/Span_S+P14*G14/Span_B,"") | AA14: =IF(AND($J14=1,$M14=1),SUMPRODUCT(MAX($J$6:$J$1062*(N14*$K$6:$K$1062/Span_P+O14*$F$6:$F$1062/Span_S+P14*$G$6:$G$1062/Span_B)-(1-$J$6:$J$1062)*1000000000)),"") | AB14: =IF(AND($J14=1,$M14=1),IF(AA14-Z14<=0.000000001,1,0),"") | AC14: =IF(AND($J14=1,$M14=0),IF(S14="",0,S14*INDEX(Grid!$B$6:$H$156,R14+1,Q14+1))+IF(V14="",0,V14*INDEX(Grid!$B$6:$H$156,U14+1,T14+1))+IF(Y14="",0,Y14*INDEX(Grid!$B$6:$H$156,X14+1,W14+1)),"") | AD14: =IF(AND($J14=1,$M14=0),IF(S14="",0,S14*Val_pt*(Ceiling_e-E_zero)*(1-(1-Half_gap)^Q14))+IF(V14="",0,V14*Val_pt*(Ceiling_e-E_zero)*(1-(1-Half_gap)^T14))+IF(Y14="",0,Y14*Val_pt*(Ceiling_e-E_zero)*(1-(1-Half_gap)^W14)),"") | AE14: =IF(AND($J14=1,$M14=0),IF(S14="",0,S14*R14)+IF(V14="",0,V14*U14)+IF(Y14="",0,Y14*X14),"") | AF14: =IF(AND($J14=1,$M14=0),MIN((AC14-E14)/Span_P,(AD14-F14)/Span_S,(AE14-G14)/Span_B),"") | AG14: =IF(AND($J14=1,$M14=0),IF(AF14>0.0000001,1,0),"") | AH14: =IF($J14=1,IF($M14=1,AB14,AG14),"") | AI14: =IF($J14=1,(Ideal_P-E14)/Span_P,"") | AJ14: =IF($J14=1,(Ideal_S-F14)/Span_S,"") | AK14: =IF($J14=1,(Ideal_B-G14)/Span_B,"") | AL14: =IF($J14=1,MAX(ChA_1*AI14,ChA_2*AJ14,ChA_3*AK14)+Rho*(ChA_1*AI14+ChA_2*AJ14+ChA_3*AK14),"") | AM14: =IF($J14=1,MAX(ChB_1*AI14,ChB_2*AJ14,ChB_3*AK14)+Rho*(ChB_1*AI14+ChB_2*AJ14+ChB_3*AK14),"") | AN14: =IF($J14=1,MAX(Cx_1*(Ref_P-E14)/Span_P,Cx_2*(Ref_S-F14)/Span_S,Cx_3*(Ref_B-G14)/Span_B),"")
A15: 9 | B15: =INT(A15/151) -> 0 | C15: =MOD(A15,151) -> 9 | D15: =INDEX(Grid!$J$6:$P$156,C15+1,B15+1) -> 1 | E15: =IF(D15=1,INDEX(Grid!$B$6:$H$156,C15+1,B15+1),"") -> 128.18182 | F15: =Val_pt*(Ceiling_e-E_zero)*(1-(1-Half_gap)^B15) -> 0 | G15: =C15 -> 9 | H15: =IF(D15=1,INDEX(Grid!$R$6:$X$156,C15+1,B15+1),"") -> 0 | I15: =IF(D15=1,INDEX(Sch_label,H15+1),"") -> none | J15: =IF(D15=1,INDEX(Grid!$Z$6:$AF$156,C15+1,B15+1),0) -> 0 | K15: =IF(J15=1,E15,0) -> 0 | L15: =IF(D15=1,E15+W_board*F15,"") -> 128.18182 | Z15: =IF(AND($J15=1,$M15=1),N15*E15/Span_P+O15*F15/Span_S+P15*G15/Span_B,"") | AA15: =IF(AND($J15=1,$M15=1),SUMPRODUCT(MAX($J$6:$J$1062*(N15*$K$6:$K$1062/Span_P+O15*$F$6:$F$1062/Span_S+P15*$G$6:$G$1062/Span_B)-(1-$J$6:$J$1062)*1000000000)),"") | AB15: =IF(AND($J15=1,$M15=1),IF(AA15-Z15<=0.000000001,1,0),"") | AC15: =IF(AND($J15=1,$M15=0),IF(S15="",0,S15*INDEX(Grid!$B$6:$H$156,R15+1,Q15+1))+IF(V15="",0,V15*INDEX(Grid!$B$6:$H$156,U15+1,T15+1))+IF(Y15="",0,Y15*INDEX(Grid!$B$6:$H$156,X15+1,W15+1)),"") | AD15: =IF(AND($J15=1,$M15=0),IF(S15="",0,S15*Val_pt*(Ceiling_e-E_zero)*(1-(1-Half_gap)^Q15))+IF(V15="",0,V15*Val_pt*(Ceiling_e-E_zero)*(1-(1-Half_gap)^T15))+IF(Y15="",0,Y15*Val_pt*(Ceiling_e-E_zero)*(1-(1-Half_gap)^W15)),"") | AE15: =IF(AND($J15=1,$M15=0),IF(S15="",0,S15*R15)+IF(V15="",0,V15*U15)+IF(Y15="",0,Y15*X15),"") | AF15: =IF(AND($J15=1,$M15=0),MIN((AC15-E15)/Span_P,(AD15-F15)/Span_S,(AE15-G15)/Span_B),"") | AG15: =IF(AND($J15=1,$M15=0),IF(AF15>0.0000001,1,0),"") | AH15: =IF($J15=1,IF($M15=1,AB15,AG15),"") | AI15: =IF($J15=1,(Ideal_P-E15)/Span_P,"") | AJ15: =IF($J15=1,(Ideal_S-F15)/Span_S,"") | AK15: =IF($J15=1,(Ideal_B-G15)/Span_B,"") | AL15: =IF($J15=1,MAX(ChA_1*AI15,ChA_2*AJ15,ChA_3*AK15)+Rho*(ChA_1*AI15+ChA_2*AJ15+ChA_3*AK15),"") | AM15: =IF($J15=1,MAX(ChB_1*AI15,ChB_2*AJ15,ChB_3*AK15)+Rho*(ChB_1*AI15+ChB_2*AJ15+ChB_3*AK15),"") | AN15: =IF($J15=1,MAX(Cx_1*(Ref_P-E15)/Span_P,Cx_2*(Ref_S-F15)/Span_S,Cx_3*(Ref_B-G15)/Span_B),"")
A16: 10 | B16: =INT(A16/151) -> 0 | C16: =MOD(A16,151) -> 10 | D16: =INDEX(Grid!$J$6:$P$156,C16+1,B16+1) -> 1 | E16: =IF(D16=1,INDEX(Grid!$B$6:$H$156,C16+1,B16+1),"") -> 127.27273 | F16: =Val_pt*(Ceiling_e-E_zero)*(1-(1-Half_gap)^B16) -> 0 | G16: =C16 -> 10 | H16: =IF(D16=1,INDEX(Grid!$R$6:$X$156,C16+1,B16+1),"") -> 0 | I16: =IF(D16=1,INDEX(Sch_label,H16+1),"") -> none | J16: =IF(D16=1,INDEX(Grid!$Z$6:$AF$156,C16+1,B16+1),0) -> 0 | K16: =IF(J16=1,E16,0) -> 0 | L16: =IF(D16=1,E16+W_board*F16,"") -> 127.27273 | Z16: =IF(AND($J16=1,$M16=1),N16*E16/Span_P+O16*F16/Span_S+P16*G16/Span_B,"") | AA16: =IF(AND($J16=1,$M16=1),SUMPRODUCT(MAX($J$6:$J$1062*(N16*$K$6:$K$1062/Span_P+O16*$F$6:$F$1062/Span_S+P16*$G$6:$G$1062/Span_B)-(1-$J$6:$J$1062)*1000000000)),"") | AB16: =IF(AND($J16=1,$M16=1),IF(AA16-Z16<=0.000000001,1,0),"") | AC16: =IF(AND($J16=1,$M16=0),IF(S16="",0,S16*INDEX(Grid!$B$6:$H$156,R16+1,Q16+1))+IF(V16="",0,V16*INDEX(Grid!$B$6:$H$156,U16+1,T16+1))+IF(Y16="",0,Y16*INDEX(Grid!$B$6:$H$156,X16+1,W16+1)),"") | AD16: =IF(AND($J16=1,$M16=0),IF(S16="",0,S16*Val_pt*(Ceiling_e-E_zero)*(1-(1-Half_gap)^Q16))+IF(V16="",0,V16*Val_pt*(Ceiling_e-E_zero)*(1-(1-Half_gap)^T16))+IF(Y16="",0,Y16*Val_pt*(Ceiling_e-E_zero)*(1-(1-Half_gap)^W16)),"") | AE16: =IF(AND($J16=1,$M16=0),IF(S16="",0,S16*R16)+IF(V16="",0,V16*U16)+IF(Y16="",0,Y16*X16),"") | AF16: =IF(AND($J16=1,$M16=0),MIN((AC16-E16)/Span_P,(AD16-F16)/Span_S,(AE16-G16)/Span_B),"") | AG16: =IF(AND($J16=1,$M16=0),IF(AF16>0.0000001,1,0),"") | AH16: =IF($J16=1,IF($M16=1,AB16,AG16),"") | AI16: =IF($J16=1,(Ideal_P-E16)/Span_P,"") | AJ16: =IF($J16=1,(Ideal_S-F16)/Span_S,"") | AK16: =IF($J16=1,(Ideal_B-G16)/Span_B,"") | AL16: =IF($J16=1,MAX(ChA_1*AI16,ChA_2*AJ16,ChA_3*AK16)+Rho*(ChA_1*AI16+ChA_2*AJ16+ChA_3*AK16),"") | AM16: =IF($J16=1,MAX(ChB_1*AI16,ChB_2*AJ16,ChB_3*AK16)+Rho*(ChB_1*AI16+ChB_2*AJ16+ChB_3*AK16),"") | AN16: =IF($J16=1,MAX(Cx_1*(Ref_P-E16)/Span_P,Cx_2*(Ref_S-F16)/Span_S,Cx_3*(Ref_B-G16)/Span_B),"")
A17: 11 | B17: =INT(A17/151) -> 0 | C17: =MOD(A17,151) -> 11 | D17: =INDEX(Grid!$J$6:$P$156,C17+1,B17+1) -> 1 | E17: =IF(D17=1,INDEX(Grid!$B$6:$H$156,C17+1,B17+1),"") -> 126.36364 | F17: =Val_pt*(Ceiling_e-E_zero)*(1-(1-Half_gap)^B17) -> 0 | G17: =C17 -> 11 | H17: =IF(D17=1,INDEX(Grid!$R$6:$X$156,C17+1,B17+1),"") -> 0 | I17: =IF(D17=1,INDEX(Sch_label,H17+1),"") -> none | J17: =IF(D17=1,INDEX(Grid!$Z$6:$AF$156,C17+1,B17+1),0) -> 0 | K17: =IF(J17=1,E17,0) -> 0 | L17: =IF(D17=1,E17+W_board*F17,"") -> 126.36364 | Z17: =IF(AND($J17=1,$M17=1),N17*E17/Span_P+O17*F17/Span_S+P17*G17/Span_B,"") | AA17: =IF(AND($J17=1,$M17=1),SUMPRODUCT(MAX($J$6:$J$1062*(N17*$K$6:$K$1062/Span_P+O17*$F$6:$F$1062/Span_S+P17*$G$6:$G$1062/Span_B)-(1-$J$6:$J$1062)*1000000000)),"") | AB17: =IF(AND($J17=1,$M17=1),IF(AA17-Z17<=0.000000001,1,0),"") | AC17: =IF(AND($J17=1,$M17=0),IF(S17="",0,S17*INDEX(Grid!$B$6:$H$156,R17+1,Q17+1))+IF(V17="",0,V17*INDEX(Grid!$B$6:$H$156,U17+1,T17+1))+IF(Y17="",0,Y17*INDEX(Grid!$B$6:$H$156,X17+1,W17+1)),"") | AD17: =IF(AND($J17=1,$M17=0),IF(S17="",0,S17*Val_pt*(Ceiling_e-E_zero)*(1-(1-Half_gap)^Q17))+IF(V17="",0,V17*Val_pt*(Ceiling_e-E_zero)*(1-(1-Half_gap)^T17))+IF(Y17="",0,Y17*Val_pt*(Ceiling_e-E_zero)*(1-(1-Half_gap)^W17)),"") | AE17: =IF(AND($J17=1,$M17=0),IF(S17="",0,S17*R17)+IF(V17="",0,V17*U17)+IF(Y17="",0,Y17*X17),"") | AF17: =IF(AND($J17=1,$M17=0),MIN((AC17-E17)/Span_P,(AD17-F17)/Span_S,(AE17-G17)/Span_B),"") | AG17: =IF(AND($J17=1,$M17=0),IF(AF17>0.0000001,1,0),"") | AH17: =IF($J17=1,IF($M17=1,AB17,AG17),"") | AI17: =IF($J17=1,(Ideal_P-E17)/Span_P,"") | AJ17: =IF($J17=1,(Ideal_S-F17)/Span_S,"") | AK17: =IF($J17=1,(Ideal_B-G17)/Span_B,"") | AL17: =IF($J17=1,MAX(ChA_1*AI17,ChA_2*AJ17,ChA_3*AK17)+Rho*(ChA_1*AI17+ChA_2*AJ17+ChA_3*AK17),"") | AM17: =IF($J17=1,MAX(ChB_1*AI17,ChB_2*AJ17,ChB_3*AK17)+Rho*(ChB_1*AI17+ChB_2*AJ17+ChB_3*AK17),"") | AN17: =IF($J17=1,MAX(Cx_1*(Ref_P-E17)/Span_P,Cx_2*(Ref_S-F17)/Span_S,Cx_3*(Ref_B-G17)/Span_B),"")
... A257: 251 | B257: =INT(A257/151) -> 1 | C257: =MOD(A257,151) -> 100 | D257: =INDEX(Grid!$J$6:$P$156,C257+1,B257+1) -> 1 | E257: =IF(D257=1,INDEX(Grid!$B$6:$H$156,C257+1,B257+1),"") -> 279.76355 | F257: =Val_pt*(Ceiling_e-E_zero)*(1-(1-Half_gap)^B257) -> 70 | G257: =C257 -> 100 | H257: =IF(D257=1,INDEX(Grid!$R$6:$X$156,C257+1,B257+1),"") -> 32 | I257: =IF(D257=1,INDEX(Sch_label,H257+1),"") -> 1 | J257: =IF(D257=1,INDEX(Grid!$Z$6:$AF$156,C257+1,B257+1),0) -> 0 | K257: =IF(J257=1,E257,0) -> 0 | L257: =IF(D257=1,E257+W_board*F257,"") -> 674.8953 | Z257: =IF(AND($J257=1,$M257=1),N257*E257/Span_P+O257*F257/Span_S+P257*G257/Span_B,"") | AA257: =IF(AND($J257=1,$M257=1),SUMPRODUCT(MAX($J$6:$J$1062*(N257*$K$6:$K$1062/Span_P+O257*$F$6:$F$1062/Span_S+P257*$G$6:$G$1062/Span_B)-(1-$J$6:$J$1062)*1000000000)),"") | AB257: =IF(AND($J257=1,$M257=1),IF(AA257-Z257<=0.000000001,1,0),"") | AC257: =IF(AND($J257=1,$M257=0),IF(S257="",0,S257*INDEX(Grid!$B$6:$H$156,R257+1,Q257+1))+IF(V257="",0,V257*INDEX(Grid!$B$6:$H$156,U257+1,T257+1))+IF(Y257="",0,Y257*INDEX(Grid!$B$6:$H$156,X257+1,W257+1)),"") | AD257: =IF(AND($J257=1,$M257=0),IF(S257="",0,S257*Val_pt*(Ceiling_e-E_zero)*(1-(1-Half_gap)^Q257))+IF(V257="",0,V257*Val_pt*(Ceiling_e-E_zero)*(1-(1-Half_gap)^T257))+IF(Y257="",0,Y257*Val_pt*(Ceiling_e-E_zero)*(1-(1-Half_gap)^W257)),"") | AE257: =IF(AND($J257=1,$M257=0),IF(S257="",0,S257*R257)+IF(V257="",0,V257*U257)+IF(Y257="",0,Y257*X257),"") | AF257: =IF(AND($J257=1,$M257=0),MIN((AC257-E257)/Span_P,(AD257-F257)/Span_S,(AE257-G257)/Span_B),"") | AG257: =IF(AND($J257=1,$M257=0),IF(AF257>0.0000001,1,0),"") | AH257: =IF($J257=1,IF($M257=1,AB257,AG257),"") | AI257: =IF($J257=1,(Ideal_P-E257)/Span_P,"") | AJ257: =IF($J257=1,(Ideal_S-F257)/Span_S,"") | AK257: =IF($J257=1,(Ideal_B-G257)/Span_B,"") | AL257: =IF($J257=1,MAX(ChA_1*AI257,ChA_2*AJ257,ChA_3*AK257)+Rho*(ChA_1*AI257+ChA_2*AJ257+ChA_3*AK257),"") | AM257: =IF($J257=1,MAX(ChB_1*AI257,ChB_2*AJ257,ChB_3*AK257)+Rho*(ChB_1*AI257+ChB_2*AJ257+ChB_3*AK257),"") | AN257: =IF($J257=1,MAX(Cx_1*(Ref_P-E257)/Span_P,Cx_2*(Ref_S-F257)/Span_S,Cx_3*(Ref_B-G257)/Span_B),"")
A258: 252 | B258: =INT(A258/151) -> 1 | C258: =MOD(A258,151) -> 101 | D258: =INDEX(Grid!$J$6:$P$156,C258+1,B258+1) -> 1 | E258: =IF(D258=1,INDEX(Grid!$B$6:$H$156,C258+1,B258+1),"") -> 278.85446 | F258: =Val_pt*(Ceiling_e-E_zero)*(1-(1-Half_gap)^B258) -> 70 | G258: =C258 -> 101 | H258: =IF(D258=1,INDEX(Grid!$R$6:$X$156,C258+1,B258+1),"") -> 32 | I258: =IF(D258=1,INDEX(Sch_label,H258+1),"") -> 1 | J258: =IF(D258=1,INDEX(Grid!$Z$6:$AF$156,C258+1,B258+1),0) -> 1 | K258: =IF(J258=1,E258,0) -> 278.85446 | L258: =IF(D258=1,E258+W_board*F258,"") -> 673.98621 | M258: 0 | Q258: 1 | R258: 150 | S258: 0.093642764 | T258: 2 | U258: 100 | V258: 0.90635724 | Z258: =IF(AND($J258=1,$M258=1),N258*E258/Span_P+O258*F258/Span_S+P258*G258/Span_B,"") | AA258: =IF(AND($J258=1,$M258=1),SUMPRODUCT(MAX($J$6:$J$1062*(N258*$K$6:$K$1062/Span_P+O258*$F$6:$F$1062/Span_S+P258*$G$6:$G$1062/Span_B)-(1-$J$6:$J$1062)*1000000000)),"") | AB258: =IF(AND($J258=1,$M258=1),IF(AA258-Z258<=0.000000001,1,0),"") | AC258: =IF(AND($J258=1,$M258=0),IF(S258="",0,S258*INDEX(Grid!$B$6:$H$156,R258+1,Q258+1))+IF(V258="",0,V258*INDEX(Grid!$B$6:$H$156,U258+1,T258+1))+IF(Y258="",0,Y258*INDEX(Grid!$B$6:$H$156,X258+1,W258+1)),"") -> 287.74351 | AD258: =IF(AND($J258=1,$M258=0),IF(S258="",0,S258*Val_pt*(Ceiling_e-E_zero)*(1-(1-Half_gap)^Q258))+IF(V258="",0,V258*Val_pt*(Ceiling_e-E_zero)*(1-(1-Half_gap)^T258))+IF(Y258="",0,Y258*Val_pt*(Ceiling_e-E_zero)*(1-(1-Half_gap)^W258)),"") -> 101.7225 | AE258: =IF(AND($J258=1,$M258=0),IF(S258="",0,S258*R258)+IF(V258="",0,V258*U258)+IF(Y258="",0,Y258*X258),"") -> 104.68214 | AF258: =IF(AND($J258=1,$M258=0),MIN((AC258-E258)/Span_P,(AD258-F258)/Span_S,(AE258-G258)/Span_B),"") -> 0.024547588 | AG258: =IF(AND($J258=1,$M258=0),IF(AF258>0.0000001,1,0),"") -> 1 | AH258: =IF($J258=1,IF($M258=1,AB258,AG258),"") -> 1 | AI258: =IF($J258=1,(Ideal_P-E258)/Span_P,"") -> 0.29084366 | AJ258: =IF($J258=1,(Ideal_S-F258)/Span_S,"") -> 1 | AK258: =IF($J258=1,(Ideal_B-G258)/Span_B,"") -> 0.32666667 | AL258: =IF($J258=1,MAX(ChA_1*AI258,ChA_2*AJ258,ChA_3*AK258)+Rho*(ChA_1*AI258+ChA_2*AJ258+ChA_3*AK258),"") -> 1.0001618 | AM258: =IF($J258=1,MAX(ChB_1*AI258,ChB_2*AJ258,ChB_3*AK258)+Rho*(ChB_1*AI258+ChB_2*AJ258+ChB_3*AK258),"") -> 1.0001908 | AN258: =IF($J258=1,MAX(Cx_1*(Ref_P-E258)/Span_P,Cx_2*(Ref_S-F258)/Span_S,Cx_3*(Ref_B-G258)/Span_B),"") -> 4.2831737
A259: 253 | B259: =INT(A259/151) -> 1 | C259: =MOD(A259,151) -> 102 | D259: =INDEX(Grid!$J$6:$P$156,C259+1,B259+1) -> 1 | E259: =IF(D259=1,INDEX(Grid!$B$6:$H$156,C259+1,B259+1),"") -> 277.94537 | F259: =Val_pt*(Ceiling_e-E_zero)*(1-(1-Half_gap)^B259) -> 70 | G259: =C259 -> 102 | H259: =IF(D259=1,INDEX(Grid!$R$6:$X$156,C259+1,B259+1),"") -> 32 | I259: =IF(D259=1,INDEX(Sch_label,H259+1),"") -> 1 | J259: =IF(D259=1,INDEX(Grid!$Z$6:$AF$156,C259+1,B259+1),0) -> 1 | K259: =IF(J259=1,E259,0) -> 277.94537 | L259: =IF(D259=1,E259+W_board*F259,"") -> 673.07712 | M259: 0 | Q259: 1 | R259: 150 | S259: 0.11213985 | T259: 2 | U259: 100 | V259: 0.88786015 | Z259: =IF(AND($J259=1,$M259=1),N259*E259/Span_P+O259*F259/Span_S+P259*G259/Span_B,"") | AA259: =IF(AND($J259=1,$M259=1),SUMPRODUCT(MAX($J$6:$J$1062*(N259*$K$6:$K$1062/Span_P+O259*$F$6:$F$1062/Span_S+P259*$G$6:$G$1062/Span_B)-(1-$J$6:$J$1062)*1000000000)),"") | AB259: =IF(AND($J259=1,$M259=1),IF(AA259-Z259<=0.000000001,1,0),"") | AC259: =IF(AND($J259=1,$M259=0),IF(S259="",0,S259*INDEX(Grid!$B$6:$H$156,R259+1,Q259+1))+IF(V259="",0,V259*INDEX(Grid!$B$6:$H$156,U259+1,T259+1))+IF(Y259="",0,Y259*INDEX(Grid!$B$6:$H$156,X259+1,W259+1)),"") -> 286.65301 | AD259: =IF(AND($J259=1,$M259=0),IF(S259="",0,S259*Val_pt*(Ceiling_e-E_zero)*(1-(1-Half_gap)^Q259))+IF(V259="",0,V259*Val_pt*(Ceiling_e-E_zero)*(1-(1-Half_gap)^T259))+IF(Y259="",0,Y259*Val_pt*(Ceiling_e-E_zero)*(1-(1-Half_gap)^W259)),"") -> 101.07511 | AE259: =IF(AND($J259=1,$M259=0),IF(S259="",0,S259*R259)+IF(V259="",0,V259*U259)+IF(Y259="",0,Y259*X259),"") -> 105.60699 | AF259: =IF(AND($J259=1,$M259=0),MIN((AC259-E259)/Span_P,(AD259-F259)/Span_S,(AE259-G259)/Span_B),"") -> 0.024046617 | AG259: =IF(AND($J259=1,$M259=0),IF(AF259>0.0000001,1,0),"") -> 1 | AH259: =IF($J259=1,IF($M259=1,AB259,AG259),"") -> 1 | AI259: =IF($J259=1,(Ideal_P-E259)/Span_P,"") -> 0.29335416 | AJ259: =IF($J259=1,(Ideal_S-F259)/Span_S,"") -> 1 | AK259: =IF($J259=1,(Ideal_B-G259)/Span_B,"") -> 0.32 | AL259: =IF($J259=1,MAX(ChA_1*AI259,ChA_2*AJ259,ChA_3*AK259)+Rho*(ChA_1*AI259+ChA_2*AJ259+ChA_3*AK259),"") -> 1.0001613 | AM259: =IF($J259=1,MAX(ChB_1*AI259,ChB_2*AJ259,ChB_3*AK259)+Rho*(ChB_1*AI259+ChB_2*AJ259+ChB_3*AK259),"") -> 1.0001907 | AN259: =IF($J259=1,MAX(Cx_1*(Ref_P-E259)/Span_P,Cx_2*(Ref_S-F259)/Span_S,Cx_3*(Ref_B-G259)/Span_B),"") -> 4.2831737
A260: 254 | B260: =INT(A260/151) -> 1 | C260: =MOD(A260,151) -> 103 | D260: =INDEX(Grid!$J$6:$P$156,C260+1,B260+1) -> 1 | E260: =IF(D260=1,INDEX(Grid!$B$6:$H$156,C260+1,B260+1),"") -> 277.03628 | F260: =Val_pt*(Ceiling_e-E_zero)*(1-(1-Half_gap)^B260) -> 70 | G260: =C260 -> 103 | H260: =IF(D260=1,INDEX(Grid!$R$6:$X$156,C260+1,B260+1),"") -> 32 | I260: =IF(D260=1,INDEX(Sch_label,H260+1),"") -> 1 | J260: =IF(D260=1,INDEX(Grid!$Z$6:$AF$156,C260+1,B260+1),0) -> 1 | K260: =IF(J260=1,E260,0) -> 277.03628 | L260: =IF(D260=1,E260+W_board*F260,"") -> 672.16803 | M260: 0 | Q260: 1 | R260: 150 | S260: 0.13063694 | T260: 2 | U260: 100 | V260: 0.86936306 | Z260: =IF(AND($J260=1,$M260=1),N260*E260/Span_P+O260*F260/Span_S+P260*G260/Span_B,"") | AA260: =IF(AND($J260=1,$M260=1),SUMPRODUCT(MAX($J$6:$J$1062*(N260*$K$6:$K$1062/Span_P+O260*$F$6:$F$1062/Span_S+P260*$G$6:$G$1062/Span_B)-(1-$J$6:$J$1062)*1000000000)),"") | AB260: =IF(AND($J260=1,$M260=1),IF(AA260-Z260<=0.000000001,1,0),"") | AC260: =IF(AND($J260=1,$M260=0),IF(S260="",0,S260*INDEX(Grid!$B$6:$H$156,R260+1,Q260+1))+IF(V260="",0,V260*INDEX(Grid!$B$6:$H$156,U260+1,T260+1))+IF(Y260="",0,Y260*INDEX(Grid!$B$6:$H$156,X260+1,W260+1)),"") -> 285.56251 | AD260: =IF(AND($J260=1,$M260=0),IF(S260="",0,S260*Val_pt*(Ceiling_e-E_zero)*(1-(1-Half_gap)^Q260))+IF(V260="",0,V260*Val_pt*(Ceiling_e-E_zero)*(1-(1-Half_gap)^T260))+IF(Y260="",0,Y260*Val_pt*(Ceiling_e-E_zero)*(1-(1-Half_gap)^W260)),"") -> 100.42771 | AE260: =IF(AND($J260=1,$M260=0),IF(S260="",0,S260*R260)+IF(V260="",0,V260*U260)+IF(Y260="",0,Y260*X260),"") -> 106.53185 | AF260: =IF(AND($J260=1,$M260=0),MIN((AC260-E260)/Span_P,(AD260-F260)/Span_S,(AE260-G260)/Span_B),"") -> 0.023545646 | AG260: =IF(AND($J260=1,$M260=0),IF(AF260>0.0000001,1,0),"") -> 1 | AH260: =IF($J260=1,IF($M260=1,AB260,AG260),"") -> 1 | AI260: =IF($J260=1,(Ideal_P-E260)/Span_P,"") -> 0.29586466 | AJ260: =IF($J260=1,(Ideal_S-F260)/Span_S,"") -> 1 | AK260: =IF($J260=1,(Ideal_B-G260)/Span_B,"") -> 0.31333333 | AL260: =IF($J260=1,MAX(ChA_1*AI260,ChA_2*AJ260,ChA_3*AK260)+Rho*(ChA_1*AI260+ChA_2*AJ260+ChA_3*AK260),"") -> 1.0001609 | AM260: =IF($J260=1,MAX(ChB_1*AI260,ChB_2*AJ260,ChB_3*AK260)+Rho*(ChB_1*AI260+ChB_2*AJ260+ChB_3*AK260),"") -> 1.0001905 | AN260: =IF($J260=1,MAX(Cx_1*(Ref_P-E260)/Span_P,Cx_2*(Ref_S-F260)/Span_S,Cx_3*(Ref_B-G260)/Span_B),"") -> 4.2831737
A261: 255 | B261: =INT(A261/151) -> 1 | C261: =MOD(A261,151) -> 104 | D261: =INDEX(Grid!$J$6:$P$156,C261+1,B261+1) -> 1 | E261: =IF(D261=1,INDEX(Grid!$B$6:$H$156,C261+1,B261+1),"") -> 276.12719 | F261: =Val_pt*(Ceiling_e-E_zero)*(1-(1-Half_gap)^B261) -> 70 | G261: =C261 -> 104 | H261: =IF(D261=1,INDEX(Grid!$R$6:$X$156,C261+1,B261+1),"") -> 32 | I261: =IF(D261=1,INDEX(Sch_label,H261+1),"") -> 1 | J261: =IF(D261=1,INDEX(Grid!$Z$6:$AF$156,C261+1,B261+1),0) -> 1 | K261: =IF(J261=1,E261,0) -> 276.12719 | L261: =IF(D261=1,E261+W_board*F261,"") -> 671.25894 | M261: 0 | Q261: 1 | R261: 150 | S261: 0.14913402 | T261: 2 | U261: 100 | V261: 0.85086598 | Z261: =IF(AND($J261=1,$M261=1),N261*E261/Span_P+O261*F261/Span_S+P261*G261/Span_B,"") | AA261: =IF(AND($J261=1,$M261=1),SUMPRODUCT(MAX($J$6:$J$1062*(N261*$K$6:$K$1062/Span_P+O261*$F$6:$F$1062/Span_S+P261*$G$6:$G$1062/Span_B)-(1-$J$6:$J$1062)*1000000000)),"") | AB261: =IF(AND($J261=1,$M261=1),IF(AA261-Z261<=0.000000001,1,0),"") | AC261: =IF(AND($J261=1,$M261=0),IF(S261="",0,S261*INDEX(Grid!$B$6:$H$156,R261+1,Q261+1))+IF(V261="",0,V261*INDEX(Grid!$B$6:$H$156,U261+1,T261+1))+IF(Y261="",0,Y261*INDEX(Grid!$B$6:$H$156,X261+1,W261+1)),"") -> 284.47201 | AD261: =IF(AND($J261=1,$M261=0),IF(S261="",0,S261*Val_pt*(Ceiling_e-E_zero)*(1-(1-Half_gap)^Q261))+IF(V261="",0,V261*Val_pt*(Ceiling_e-E_zero)*(1-(1-Half_gap)^T261))+IF(Y261="",0,Y261*Val_pt*(Ceiling_e-E_zero)*(1-(1-Half_gap)^W261)),"") -> 99.780309 | AE261: =IF(AND($J261=1,$M261=0),IF(S261="",0,S261*R261)+IF(V261="",0,V261*U261)+IF(Y261="",0,Y261*X261),"") -> 107.4567 | AF261: =IF(AND($J261=1,$M261=0),MIN((AC261-E261)/Span_P,(AD261-F261)/Span_S,(AE261-G261)/Span_B),"") -> 0.023044675 | AG261: =IF(AND($J261=1,$M261=0),IF(AF261>0.0000001,1,0),"") -> 1 | AH261: =IF($J261=1,IF($M261=1,AB261,AG261),"") -> 1 | AI261: =IF($J261=1,(Ideal_P-E261)/Span_P,"") -> 0.29837517 | AJ261: =IF($J261=1,(Ideal_S-F261)/Span_S,"") -> 1 | AK261: =IF($J261=1,(Ideal_B-G261)/Span_B,"") -> 0.30666667 | AL261: =IF($J261=1,MAX(ChA_1*AI261,ChA_2*AJ261,ChA_3*AK261)+Rho*(ChA_1*AI261+ChA_2*AJ261+ChA_3*AK261),"") -> 1.0001605 | AM261: =IF($J261=1,MAX(ChB_1*AI261,ChB_2*AJ261,ChB_3*AK261)+Rho*(ChB_1*AI261+ChB_2*AJ261+ChB_3*AK261),"") -> 1.0001903 | AN261: =IF($J261=1,MAX(Cx_1*(Ref_P-E261)/Span_P,Cx_2*(Ref_S-F261)/Span_S,Cx_3*(Ref_B-G261)/Span_B),"") -> 4.2831737
A262: 256 | B262: =INT(A262/151) -> 1 | C262: =MOD(A262,151) -> 105 | D262: =INDEX(Grid!$J$6:$P$156,C262+1,B262+1) -> 1 | E262: =IF(D262=1,INDEX(Grid!$B$6:$H$156,C262+1,B262+1),"") -> 275.2181 | F262: =Val_pt*(Ceiling_e-E_zero)*(1-(1-Half_gap)^B262) -> 70 | G262: =C262 -> 105 | H262: =IF(D262=1,INDEX(Grid!$R$6:$X$156,C262+1,B262+1),"") -> 32 | I262: =IF(D262=1,INDEX(Sch_label,H262+1),"") -> 1 | J262: =IF(D262=1,INDEX(Grid!$Z$6:$AF$156,C262+1,B262+1),0) -> 1 | K262: =IF(J262=1,E262,0) -> 275.2181 | L262: =IF(D262=1,E262+W_board*F262,"") -> 670.34985 | M262: 0 | Q262: 1 | R262: 150 | S262: 0.16763111 | T262: 2 | U262: 100 | V262: 0.83236889 | Z262: =IF(AND($J262=1,$M262=1),N262*E262/Span_P+O262*F262/Span_S+P262*G262/Span_B,"") | AA262: =IF(AND($J262=1,$M262=1),SUMPRODUCT(MAX($J$6:$J$1062*(N262*$K$6:$K$1062/Span_P+O262*$F$6:$F$1062/Span_S+P262*$G$6:$G$1062/Span_B)-(1-$J$6:$J$1062)*1000000000)),"") | AB262: =IF(AND($J262=1,$M262=1),IF(AA262-Z262<=0.000000001,1,0),"") | AC262: =IF(AND($J262=1,$M262=0),IF(S262="",0,S262*INDEX(Grid!$B$6:$H$156,R262+1,Q262+1))+IF(V262="",0,V262*INDEX(Grid!$B$6:$H$156,U262+1,T262+1))+IF(Y262="",0,Y262*INDEX(Grid!$B$6:$H$156,X262+1,W262+1)),"") -> 283.38151 | AD262: =IF(AND($J262=1,$M262=0),IF(S262="",0,S262*Val_pt*(Ceiling_e-E_zero)*(1-(1-Half_gap)^Q262))+IF(V262="",0,V262*Val_pt*(Ceiling_e-E_zero)*(1-(1-Half_gap)^T262))+IF(Y262="",0,Y262*Val_pt*(Ceiling_e-E_zero)*(1-(1-Half_gap)^W262)),"") -> 99.132911 | AE262: =IF(AND($J262=1,$M262=0),IF(S262="",0,S262*R262)+IF(V262="",0,V262*U262)+IF(Y262="",0,Y262*X262),"") -> 108.38156 | AF262: =IF(AND($J262=1,$M262=0),MIN((AC262-E262)/Span_P,(AD262-F262)/Span_S,(AE262-G262)/Span_B),"") -> 0.022543703 | AG262: =IF(AND($J262=1,$M262=0),IF(AF262>0.0000001,1,0),"") -> 1 | AH262: =IF($J262=1,IF($M262=1,AB262,AG262),"") -> 1 | AI262: =IF($J262=1,(Ideal_P-E262)/Span_P,"") -> 0.30088567 | AJ262: =IF($J262=1,(Ideal_S-F262)/Span_S,"") -> 1 | AK262: =IF($J262=1,(Ideal_B-G262)/Span_B,"") -> 0.3 | AL262: =IF($J262=1,MAX(ChA_1*AI262,ChA_2*AJ262,ChA_3*AK262)+Rho*(ChA_1*AI262+ChA_2*AJ262+ChA_3*AK262),"") -> 1.0001601 | AM262: =IF($J262=1,MAX(ChB_1*AI262,ChB_2*AJ262,ChB_3*AK262)+Rho*(ChB_1*AI262+ChB_2*AJ262+ChB_3*AK262),"") -> 1.0001902 | AN262: =IF($J262=1,MAX(Cx_1*(Ref_P-E262)/Span_P,Cx_2*(Ref_S-F262)/Span_S,Cx_3*(Ref_B-G262)/Span_B),"") -> 4.2831737
A263: 257 | B263: =INT(A263/151) -> 1 | C263: =MOD(A263,151) -> 106 | D263: =INDEX(Grid!$J$6:$P$156,C263+1,B263+1) -> 1 | E263: =IF(D263=1,INDEX(Grid!$B$6:$H$156,C263+1,B263+1),"") -> 274.30901 | F263: =Val_pt*(Ceiling_e-E_zero)*(1-(1-Half_gap)^B263) -> 70 | G263: =C263 -> 106 | H263: =IF(D263=1,INDEX(Grid!$R$6:$X$156,C263+1,B263+1),"") -> 32 | I263: =IF(D263=1,INDEX(Sch_label,H263+1),"") -> 1 | J263: =IF(D263=1,INDEX(Grid!$Z$6:$AF$156,C263+1,B263+1),0) -> 1 | K263: =IF(J263=1,E263,0) -> 274.30901 | L263: =IF(D263=1,E263+W_board*F263,"") -> 669.44076 | M263: 0 | Q263: 1 | R263: 150 | S263: 0.1861282 | T263: 2 | U263: 100 | V263: 0.8138718 | Z263: =IF(AND($J263=1,$M263=1),N263*E263/Span_P+O263*F263/Span_S+P263*G263/Span_B,"") | AA263: =IF(AND($J263=1,$M263=1),SUMPRODUCT(MAX($J$6:$J$1062*(N263*$K$6:$K$1062/Span_P+O263*$F$6:$F$1062/Span_S+P263*$G$6:$G$1062/Span_B)-(1-$J$6:$J$1062)*1000000000)),"") | AB263: =IF(AND($J263=1,$M263=1),IF(AA263-Z263<=0.000000001,1,0),"") | AC263: =IF(AND($J263=1,$M263=0),IF(S263="",0,S263*INDEX(Grid!$B$6:$H$156,R263+1,Q263+1))+IF(V263="",0,V263*INDEX(Grid!$B$6:$H$156,U263+1,T263+1))+IF(Y263="",0,Y263*INDEX(Grid!$B$6:$H$156,X263+1,W263+1)),"") -> 282.29101 | AD263: =IF(AND($J263=1,$M263=0),IF(S263="",0,S263*Val_pt*(Ceiling_e-E_zero)*(1-(1-Half_gap)^Q263))+IF(V263="",0,V263*Val_pt*(Ceiling_e-E_zero)*(1-(1-Half_gap)^T263))+IF(Y263="",0,Y263*Val_pt*(Ceiling_e-E_zero)*(1-(1-Half_gap)^W263)),"") -> 98.485513 | AE263: =IF(AND($J263=1,$M263=0),IF(S263="",0,S263*R263)+IF(V263="",0,V263*U263)+IF(Y263="",0,Y263*X263),"") -> 109.30641 | AF263: =IF(AND($J263=1,$M263=0),MIN((AC263-E263)/Span_P,(AD263-F263)/Span_S,(AE263-G263)/Span_B),"") -> 0.022042732 | AG263: =IF(AND($J263=1,$M263=0),IF(AF263>0.0000001,1,0),"") -> 1 | AH263: =IF($J263=1,IF($M263=1,AB263,AG263),"") -> 1 | AI263: =IF($J263=1,(Ideal_P-E263)/Span_P,"") -> 0.30339617 | AJ263: =IF($J263=1,(Ideal_S-F263)/Span_S,"") -> 1 | AK263: =IF($J263=1,(Ideal_B-G263)/Span_B,"") -> 0.29333333 | AL263: =IF($J263=1,MAX(ChA_1*AI263,ChA_2*AJ263,ChA_3*AK263)+Rho*(ChA_1*AI263+ChA_2*AJ263+ChA_3*AK263),"") -> 1.0001597 | AM263: =IF($J263=1,MAX(ChB_1*AI263,ChB_2*AJ263,ChB_3*AK263)+Rho*(ChB_1*AI263+ChB_2*AJ263+ChB_3*AK263),"") -> 1.00019 | AN263: =IF($J263=1,MAX(Cx_1*(Ref_P-E263)/Span_P,Cx_2*(Ref_S-F263)/Span_S,Cx_3*(Ref_B-G263)/Span_B),"") -> 4.2831737
A264: 258 | B264: =INT(A264/151) -> 1 | C264: =MOD(A264,151) -> 107 | D264: =INDEX(Grid!$J$6:$P$156,C264+1,B264+1) -> 1 | E264: =IF(D264=1,INDEX(Grid!$B$6:$H$156,C264+1,B264+1),"") -> 273.39992 | F264: =Val_pt*(Ceiling_e-E_zero)*(1-(1-Half_gap)^B264) -> 70 | G264: =C264 -> 107 | H264: =IF(D264=1,INDEX(Grid!$R$6:$X$156,C264+1,B264+1),"") -> 32 | I264: =IF(D264=1,INDEX(Sch_label,H264+1),"") -> 1 | J264: =IF(D264=1,INDEX(Grid!$Z$6:$AF$156,C264+1,B264+1),0) -> 1 | K264: =IF(J264=1,E264,0) -> 273.39992 | L264: =IF(D264=1,E264+W_board*F264,"") -> 668.53167 | M264: 0 | Q264: 1 | R264: 150 | S264: 0.20462528 | T264: 2 | U264: 100 | V264: 0.79537472 | Z264: =IF(AND($J264=1,$M264=1),N264*E264/Span_P+O264*F264/Span_S+P264*G264/Span_B,"") | AA264: =IF(AND($J264=1,$M264=1),SUMPRODUCT(MAX($J$6:$J$1062*(N264*$K$6:$K$1062/Span_P+O264*$F$6:$F$1062/Span_S+P264*$G$6:$G$1062/Span_B)-(1-$J$6:$J$1062)*1000000000)),"") | AB264: =IF(AND($J264=1,$M264=1),IF(AA264-Z264<=0.000000001,1,0),"") | AC264: =IF(AND($J264=1,$M264=0),IF(S264="",0,S264*INDEX(Grid!$B$6:$H$156,R264+1,Q264+1))+IF(V264="",0,V264*INDEX(Grid!$B$6:$H$156,U264+1,T264+1))+IF(Y264="",0,Y264*INDEX(Grid!$B$6:$H$156,X264+1,W264+1)),"") -> 281.20051 | AD264: =IF(AND($J264=1,$M264=0),IF(S264="",0,S264*Val_pt*(Ceiling_e-E_zero)*(1-(1-Half_gap)^Q264))+IF(V264="",0,V264*Val_pt*(Ceiling_e-E_zero)*(1-(1-Half_gap)^T264))+IF(Y264="",0,Y264*Val_pt*(Ceiling_e-E_zero)*(1-(1-Half_gap)^W264)),"") -> 97.838115 | AE264: =IF(AND($J264=1,$M264=0),IF(S264="",0,S264*R264)+IF(V264="",0,V264*U264)+IF(Y264="",0,Y264*X264),"") -> 110.23126 | AF264: =IF(AND($J264=1,$M264=0),MIN((AC264-E264)/Span_P,(AD264-F264)/Span_S,(AE264-G264)/Span_B),"") -> 0.021541761 | AG264: =IF(AND($J264=1,$M264=0),IF(AF264>0.0000001,1,0),"") -> 1 | AH264: =IF($J264=1,IF($M264=1,AB264,AG264),"") -> 1 | AI264: =IF($J264=1,(Ideal_P-E264)/Span_P,"") -> 0.30590668 | AJ264: =IF($J264=1,(Ideal_S-F264)/Span_S,"") -> 1 | AK264: =IF($J264=1,(Ideal_B-G264)/Span_B,"") -> 0.28666667 | AL264: =IF($J264=1,MAX(ChA_1*AI264,ChA_2*AJ264,ChA_3*AK264)+Rho*(ChA_1*AI264+ChA_2*AJ264+ChA_3*AK264),"") -> 1.0001593 | AM264: =IF($J264=1,MAX(ChB_1*AI264,ChB_2*AJ264,ChB_3*AK264)+Rho*(ChB_1*AI264+ChB_2*AJ264+ChB_3*AK264),"") -> 1.0001898 | AN264: =IF($J264=1,MAX(Cx_1*(Ref_P-E264)/Span_P,Cx_2*(Ref_S-F264)/Span_S,Cx_3*(Ref_B-G264)/Span_B),"") -> 4.2831737
A265: 259 | B265: =INT(A265/151) -> 1 | C265: =MOD(A265,151) -> 108 | D265: =INDEX(Grid!$J$6:$P$156,C265+1,B265+1) -> 1 | E265: =IF(D265=1,INDEX(Grid!$B$6:$H$156,C265+1,B265+1),"") -> 272.49083 | F265: =Val_pt*(Ceiling_e-E_zero)*(1-(1-Half_gap)^B265) -> 70 | G265: =C265 -> 108 | H265: =IF(D265=1,INDEX(Grid!$R$6:$X$156,C265+1,B265+1),"") -> 32 | I265: =IF(D265=1,INDEX(Sch_label,H265+1),"") -> 1 | J265: =IF(D265=1,INDEX(Grid!$Z$6:$AF$156,C265+1,B265+1),0) -> 1 | K265: =IF(J265=1,E265,0) -> 272.49083 | L265: =IF(D265=1,E265+W_board*F265,"") -> 667.62258 | M265: 0 | Q265: 1 | R265: 150 | S265: 0.22312237 | T265: 2 | U265: 100 | V265: 0.77687763 | Z265: =IF(AND($J265=1,$M265=1),N265*E265/Span_P+O265*F265/Span_S+P265*G265/Span_B,"") | AA265: =IF(AND($J265=1,$M265=1),SUMPRODUCT(MAX($J$6:$J$1062*(N265*$K$6:$K$1062/Span_P+O265*$F$6:$F$1062/Span_S+P265*$G$6:$G$1062/Span_B)-(1-$J$6:$J$1062)*1000000000)),"") | AB265: =IF(AND($J265=1,$M265=1),IF(AA265-Z265<=0.000000001,1,0),"") | AC265: =IF(AND($J265=1,$M265=0),IF(S265="",0,S265*INDEX(Grid!$B$6:$H$156,R265+1,Q265+1))+IF(V265="",0,V265*INDEX(Grid!$B$6:$H$156,U265+1,T265+1))+IF(Y265="",0,Y265*INDEX(Grid!$B$6:$H$156,X265+1,W265+1)),"") -> 280.11001 | AD265: =IF(AND($J265=1,$M265=0),IF(S265="",0,S265*Val_pt*(Ceiling_e-E_zero)*(1-(1-Half_gap)^Q265))+IF(V265="",0,V265*Val_pt*(Ceiling_e-E_zero)*(1-(1-Half_gap)^T265))+IF(Y265="",0,Y265*Val_pt*(Ceiling_e-E_zero)*(1-(1-Half_gap)^W265)),"") -> 97.190717 | AE265: =IF(AND($J265=1,$M265=0),IF(S265="",0,S265*R265)+IF(V265="",0,V265*U265)+IF(Y265="",0,Y265*X265),"") -> 111.15612 | AF265: =IF(AND($J265=1,$M265=0),MIN((AC265-E265)/Span_P,(AD265-F265)/Span_S,(AE265-G265)/Span_B),"") -> 0.02104079 | AG265: =IF(AND($J265=1,$M265=0),IF(AF265>0.0000001,1,0),"") -> 1 | AH265: =IF($J265=1,IF($M265=1,AB265,AG265),"") -> 1 | AI265: =IF($J265=1,(Ideal_P-E265)/Span_P,"") -> 0.30841718 | AJ265: =IF($J265=1,(Ideal_S-F265)/Span_S,"") -> 1 | AK265: =IF($J265=1,(Ideal_B-G265)/Span_B,"") -> 0.28 | AL265: =IF($J265=1,MAX(ChA_1*AI265,ChA_2*AJ265,ChA_3*AK265)+Rho*(ChA_1*AI265+ChA_2*AJ265+ChA_3*AK265),"") -> 1.0001588 | AM265: =IF($J265=1,MAX(ChB_1*AI265,ChB_2*AJ265,ChB_3*AK265)+Rho*(ChB_1*AI265+ChB_2*AJ265+ChB_3*AK265),"") -> 1.0001897 | AN265: =IF($J265=1,MAX(Cx_1*(Ref_P-E265)/Span_P,Cx_2*(Ref_S-F265)/Span_S,Cx_3*(Ref_B-G265)/Span_B),"") -> 4.2831737
A266: 260 | B266: =INT(A266/151) -> 1 | C266: =MOD(A266,151) -> 109 | D266: =INDEX(Grid!$J$6:$P$156,C266+1,B266+1) -> 1 | E266: =IF(D266=1,INDEX(Grid!$B$6:$H$156,C266+1,B266+1),"") -> 271.58173 | F266: =Val_pt*(Ceiling_e-E_zero)*(1-(1-Half_gap)^B266) -> 70 | G266: =C266 -> 109 | H266: =IF(D266=1,INDEX(Grid!$R$6:$X$156,C266+1,B266+1),"") -> 32 | I266: =IF(D266=1,INDEX(Sch_label,H266+1),"") -> 1 | J266: =IF(D266=1,INDEX(Grid!$Z$6:$AF$156,C266+1,B266+1),0) -> 1 | K266: =IF(J266=1,E266,0) -> 271.58173 | L266: =IF(D266=1,E266+W_board*F266,"") -> 666.71349 | M266: 0 | Q266: 1 | R266: 150 | S266: 0.24161946 | T266: 2 | U266: 100 | V266: 0.75838054 | Z266: =IF(AND($J266=1,$M266=1),N266*E266/Span_P+O266*F266/Span_S+P266*G266/Span_B,"") | AA266: =IF(AND($J266=1,$M266=1),SUMPRODUCT(MAX($J$6:$J$1062*(N266*$K$6:$K$1062/Span_P+O266*$F$6:$F$1062/Span_S+P266*$G$6:$G$1062/Span_B)-(1-$J$6:$J$1062)*1000000000)),"") | AB266: =IF(AND($J266=1,$M266=1),IF(AA266-Z266<=0.000000001,1,0),"") | AC266: =IF(AND($J266=1,$M266=0),IF(S266="",0,S266*INDEX(Grid!$B$6:$H$156,R266+1,Q266+1))+IF(V266="",0,V266*INDEX(Grid!$B$6:$H$156,U266+1,T266+1))+IF(Y266="",0,Y266*INDEX(Grid!$B$6:$H$156,X266+1,W266+1)),"") -> 279.01951 | AD266: =IF(AND($J266=1,$M266=0),IF(S266="",0,S266*Val_pt*(Ceiling_e-E_zero)*(1-(1-Half_gap)^Q266))+IF(V266="",0,V266*Val_pt*(Ceiling_e-E_zero)*(1-(1-Half_gap)^T266))+IF(Y266="",0,Y266*Val_pt*(Ceiling_e-E_zero)*(1-(1-Half_gap)^W266)),"") -> 96.543319 | AE266: =IF(AND($J266=1,$M266=0),IF(S266="",0,S266*R266)+IF(V266="",0,V266*U266)+IF(Y266="",0,Y266*X266),"") -> 112.08097 | AF266: =IF(AND($J266=1,$M266=0),MIN((AC266-E266)/Span_P,(AD266-F266)/Span_S,(AE266-G266)/Span_B),"") -> 0.020539819 | AG266: =IF(AND($J266=1,$M266=0),IF(AF266>0.0000001,1,0),"") -> 1 | AH266: =IF($J266=1,IF($M266=1,AB266,AG266),"") -> 1 | AI266: =IF($J266=1,(Ideal_P-E266)/Span_P,"") -> 0.31092768 | AJ266: =IF($J266=1,(Ideal_S-F266)/Span_S,"") -> 1 | AK266: =IF($J266=1,(Ideal_B-G266)/Span_B,"") -> 0.27333333 | AL266: =IF($J266=1,MAX(ChA_1*AI266,ChA_2*AJ266,ChA_3*AK266)+Rho*(ChA_1*AI266+ChA_2*AJ266+ChA_3*AK266),"") -> 1.0001584 | AM266: =IF($J266=1,MAX(ChB_1*AI266,ChB_2*AJ266,ChB_3*AK266)+Rho*(ChB_1*AI266+ChB_2*AJ266+ChB_3*AK266),"") -> 1.0001895 | AN266: =IF($J266=1,MAX(Cx_1*(Ref_P-E266)/Span_P,Cx_2*(Ref_S-F266)/Span_S,Cx_3*(Ref_B-G266)/Span_B),"") -> 4.2831737
A267: 261 | B267: =INT(A267/151) -> 1 | C267: =MOD(A267,151) -> 110 | D267: =INDEX(Grid!$J$6:$P$156,C267+1,B267+1) -> 1 | E267: =IF(D267=1,INDEX(Grid!$B$6:$H$156,C267+1,B267+1),"") -> 270.67264 | F267: =Val_pt*(Ceiling_e-E_zero)*(1-(1-Half_gap)^B267) -> 70 | G267: =C267 -> 110 | H267: =IF(D267=1,INDEX(Grid!$R$6:$X$156,C267+1,B267+1),"") -> 32 | I267: =IF(D267=1,INDEX(Sch_label,H267+1),"") -> 1 | J267: =IF(D267=1,INDEX(Grid!$Z$6:$AF$156,C267+1,B267+1),0) -> 1 | K267: =IF(J267=1,E267,0) -> 270.67264 | L267: =IF(D267=1,E267+W_board*F267,"") -> 665.8044 | M267: 0 | Q267: 1 | R267: 150 | S267: 0.26011654 | T267: 2 | U267: 100 | V267: 0.73988346 | Z267: =IF(AND($J267=1,$M267=1),N267*E267/Span_P+O267*F267/Span_S+P267*G267/Span_B,"") | AA267: =IF(AND($J267=1,$M267=1),SUMPRODUCT(MAX($J$6:$J$1062*(N267*$K$6:$K$1062/Span_P+O267*$F$6:$F$1062/Span_S+P267*$G$6:$G$1062/Span_B)-(1-$J$6:$J$1062)*1000000000)),"") | AB267: =IF(AND($J267=1,$M267=1),IF(AA267-Z267<=0.000000001,1,0),"") | AC267: =IF(AND($J267=1,$M267=0),IF(S267="",0,S267*INDEX(Grid!$B$6:$H$156,R267+1,Q267+1))+IF(V267="",0,V267*INDEX(Grid!$B$6:$H$156,U267+1,T267+1))+IF(Y267="",0,Y267*INDEX(Grid!$B$6:$H$156,X267+1,W267+1)),"") -> 277.92901 | AD267: =IF(AND($J267=1,$M267=0),IF(S267="",0,S267*Val_pt*(Ceiling_e-E_zero)*(1-(1-Half_gap)^Q267))+IF(V267="",0,V267*Val_pt*(Ceiling_e-E_zero)*(1-(1-Half_gap)^T267))+IF(Y267="",0,Y267*Val_pt*(Ceiling_e-E_zero)*(1-(1-Half_gap)^W267)),"") -> 95.895921 | AE267: =IF(AND($J267=1,$M267=0),IF(S267="",0,S267*R267)+IF(V267="",0,V267*U267)+IF(Y267="",0,Y267*X267),"") -> 113.00583 | AF267: =IF(AND($J267=1,$M267=0),MIN((AC267-E267)/Span_P,(AD267-F267)/Span_S,(AE267-G267)/Span_B),"") -> 0.020038847 | AG267: =IF(AND($J267=1,$M267=0),IF(AF267>0.0000001,1,0),"") -> 1 | AH267: =IF($J267=1,IF($M267=1,AB267,AG267),"") -> 1 | AI267: =IF($J267=1,(Ideal_P-E267)/Span_P,"") -> 0.31343818 | AJ267: =IF($J267=1,(Ideal_S-F267)/Span_S,"") -> 1 | AK267: =IF($J267=1,(Ideal_B-G267)/Span_B,"") -> 0.26666667 | AL267: =IF($J267=1,MAX(ChA_1*AI267,ChA_2*AJ267,ChA_3*AK267)+Rho*(ChA_1*AI267+ChA_2*AJ267+ChA_3*AK267),"") -> 1.000158 | AM267: =IF($J267=1,MAX(ChB_1*AI267,ChB_2*AJ267,ChB_3*AK267)+Rho*(ChB_1*AI267+ChB_2*AJ267+ChB_3*AK267),"") -> 1.0001894 | AN267: =IF($J267=1,MAX(Cx_1*(Ref_P-E267)/Span_P,Cx_2*(Ref_S-F267)/Span_S,Cx_3*(Ref_B-G267)/Span_B),"") -> 4.2831737
A268: 262 | B268: =INT(A268/151) -> 1 | C268: =MOD(A268,151) -> 111 | D268: =INDEX(Grid!$J$6:$P$156,C268+1,B268+1) -> 1 | E268: =IF(D268=1,INDEX(Grid!$B$6:$H$156,C268+1,B268+1),"") -> 269.76355 | F268: =Val_pt*(Ceiling_e-E_zero)*(1-(1-Half_gap)^B268) -> 70 | G268: =C268 -> 111 | H268: =IF(D268=1,INDEX(Grid!$R$6:$X$156,C268+1,B268+1),"") -> 32 | I268: =IF(D268=1,INDEX(Sch_label,H268+1),"") -> 1 | J268: =IF(D268=1,INDEX(Grid!$Z$6:$AF$156,C268+1,B268+1),0) -> 1 | K268: =IF(J268=1,E268,0) -> 269.76355 | L268: =IF(D268=1,E268+W_board*F268,"") -> 664.8953 | M268: 0 | Q268: 1 | R268: 150 | S268: 0.27861363 | T268: 2 | U268: 100 | V268: 0.72138637 | Z268: =IF(AND($J268=1,$M268=1),N268*E268/Span_P+O268*F268/Span_S+P268*G268/Span_B,"") | AA268: =IF(AND($J268=1,$M268=1),SUMPRODUCT(MAX($J$6:$J$1062*(N268*$K$6:$K$1062/Span_P+O268*$F$6:$F$1062/Span_S+P268*$G$6:$G$1062/Span_B)-(1-$J$6:$J$1062)*1000000000)),"") | AB268: =IF(AND($J268=1,$M268=1),IF(AA268-Z268<=0.000000001,1,0),"") | AC268: =IF(AND($J268=1,$M268=0),IF(S268="",0,S268*INDEX(Grid!$B$6:$H$156,R268+1,Q268+1))+IF(V268="",0,V268*INDEX(Grid!$B$6:$H$156,U268+1,T268+1))+IF(Y268="",0,Y268*INDEX(Grid!$B$6:$H$156,X268+1,W268+1)),"") -> 276.83851 | AD268: =IF(AND($J268=1,$M268=0),IF(S268="",0,S268*Val_pt*(Ceiling_e-E_zero)*(1-(1-Half_gap)^Q268))+IF(V268="",0,V268*Val_pt*(Ceiling_e-E_zero)*(1-(1-Half_gap)^T268))+IF(Y268="",0,Y268*Val_pt*(Ceiling_e-E_zero)*(1-(1-Half_gap)^W268)),"") -> 95.248523 | AE268: =IF(AND($J268=1,$M268=0),IF(S268="",0,S268*R268)+IF(V268="",0,V268*U268)+IF(Y268="",0,Y268*X268),"") -> 113.93068 | AF268: =IF(AND($J268=1,$M268=0),MIN((AC268-E268)/Span_P,(AD268-F268)/Span_S,(AE268-G268)/Span_B),"") -> 0.019537876 | AG268: =IF(AND($J268=1,$M268=0),IF(AF268>0.0000001,1,0),"") -> 1 | AH268: =IF($J268=1,IF($M268=1,AB268,AG268),"") -> 1 | AI268: =IF($J268=1,(Ideal_P-E268)/Span_P,"") -> 0.31594869 | AJ268: =IF($J268=1,(Ideal_S-F268)/Span_S,"") -> 1 | AK268: =IF($J268=1,(Ideal_B-G268)/Span_B,"") -> 0.26 | AL268: =IF($J268=1,MAX(ChA_1*AI268,ChA_2*AJ268,ChA_3*AK268)+Rho*(ChA_1*AI268+ChA_2*AJ268+ChA_3*AK268),"") -> 1.0001576 | AM268: =IF($J268=1,MAX(ChB_1*AI268,ChB_2*AJ268,ChB_3*AK268)+Rho*(ChB_1*AI268+ChB_2*AJ268+ChB_3*AK268),"") -> 1.0001892 | AN268: =IF($J268=1,MAX(Cx_1*(Ref_P-E268)/Span_P,Cx_2*(Ref_S-F268)/Span_S,Cx_3*(Ref_B-G268)/Span_B),"") -> 4.2831737
A269: 263 | B269: =INT(A269/151) -> 1 | C269: =MOD(A269,151) -> 112 | D269: =INDEX(Grid!$J$6:$P$156,C269+1,B269+1) -> 1 | E269: =IF(D269=1,INDEX(Grid!$B$6:$H$156,C269+1,B269+1),"") -> 268.85446 | F269: =Val_pt*(Ceiling_e-E_zero)*(1-(1-Half_gap)^B269) -> 70 | G269: =C269 -> 112 | H269: =IF(D269=1,INDEX(Grid!$R$6:$X$156,C269+1,B269+1),"") -> 32 | I269: =IF(D269=1,INDEX(Sch_label,H269+1),"") -> 1 | J269: =IF(D269=1,INDEX(Grid!$Z$6:$AF$156,C269+1,B269+1),0) -> 1 | K269: =IF(J269=1,E269,0) -> 268.85446 | L269: =IF(D269=1,E269+W_board*F269,"") -> 663.98621 | M269: 0 | Q269: 1 | R269: 150 | S269: 0.29711072 | T269: 2 | U269: 100 | V269: 0.70288928 | Z269: =IF(AND($J269=1,$M269=1),N269*E269/Span_P+O269*F269/Span_S+P269*G269/Span_B,"") | AA269: =IF(AND($J269=1,$M269=1),SUMPRODUCT(MAX($J$6:$J$1062*(N269*$K$6:$K$1062/Span_P+O269*$F$6:$F$1062/Span_S+P269*$G$6:$G$1062/Span_B)-(1-$J$6:$J$1062)*1000000000)),"") | AB269: =IF(AND($J269=1,$M269=1),IF(AA269-Z269<=0.000000001,1,0),"") | AC269: =IF(AND($J269=1,$M269=0),IF(S269="",0,S269*INDEX(Grid!$B$6:$H$156,R269+1,Q269+1))+IF(V269="",0,V269*INDEX(Grid!$B$6:$H$156,U269+1,T269+1))+IF(Y269="",0,Y269*INDEX(Grid!$B$6:$H$156,X269+1,W269+1)),"") -> 275.74801 | AD269: =IF(AND($J269=1,$M269=0),IF(S269="",0,S269*Val_pt*(Ceiling_e-E_zero)*(1-(1-Half_gap)^Q269))+IF(V269="",0,V269*Val_pt*(Ceiling_e-E_zero)*(1-(1-Half_gap)^T269))+IF(Y269="",0,Y269*Val_pt*(Ceiling_e-E_zero)*(1-(1-Half_gap)^W269)),"") -> 94.601125 | AE269: =IF(AND($J269=1,$M269=0),IF(S269="",0,S269*R269)+IF(V269="",0,V269*U269)+IF(Y269="",0,Y269*X269),"") -> 114.85554 | AF269: =IF(AND($J269=1,$M269=0),MIN((AC269-E269)/Span_P,(AD269-F269)/Span_S,(AE269-G269)/Span_B),"") -> 0.019036905 | AG269: =IF(AND($J269=1,$M269=0),IF(AF269>0.0000001,1,0),"") -> 1 | AH269: =IF($J269=1,IF($M269=1,AB269,AG269),"") -> 1 | AI269: =IF($J269=1,(Ideal_P-E269)/Span_P,"") -> 0.31845919 | AJ269: =IF($J269=1,(Ideal_S-F269)/Span_S,"") -> 1 | AK269: =IF($J269=1,(Ideal_B-G269)/Span_B,"") -> 0.25333333 | AL269: =IF($J269=1,MAX(ChA_1*AI269,ChA_2*AJ269,ChA_3*AK269)+Rho*(ChA_1*AI269+ChA_2*AJ269+ChA_3*AK269),"") -> 1.0001572 | AM269: =IF($J269=1,MAX(ChB_1*AI269,ChB_2*AJ269,ChB_3*AK269)+Rho*(ChB_1*AI269+ChB_2*AJ269+ChB_3*AK269),"") -> 1.000189 | AN269: =IF($J269=1,MAX(Cx_1*(Ref_P-E269)/Span_P,Cx_2*(Ref_S-F269)/Span_S,Cx_3*(Ref_B-G269)/Span_B),"") -> 4.2831737
... A306: 300 | B306: =INT(A306/151) -> 1 | C306: =MOD(A306,151) -> 149 | D306: =INDEX(Grid!$J$6:$P$156,C306+1,B306+1) -> 1 | E306: =IF(D306=1,INDEX(Grid!$B$6:$H$156,C306+1,B306+1),"") -> 235.2181 | F306: =Val_pt*(Ceiling_e-E_zero)*(1-(1-Half_gap)^B306) -> 70 | G306: =C306 -> 149 | H306: =IF(D306=1,INDEX(Grid!$R$6:$X$156,C306+1,B306+1),"") -> 32 | I306: =IF(D306=1,INDEX(Sch_label,H306+1),"") -> 1 | J306: =IF(D306=1,INDEX(Grid!$Z$6:$AF$156,C306+1,B306+1),0) -> 1 | K306: =IF(J306=1,E306,0) -> 235.2181 | L306: =IF(D306=1,E306+W_board*F306,"") -> 630.34985 | M306: 0 | Q306: 1 | R306: 150 | S306: 0.98150291 | T306: 2 | U306: 100 | V306: 0.018497086 | Z306: =IF(AND($J306=1,$M306=1),N306*E306/Span_P+O306*F306/Span_S+P306*G306/Span_B,"") | AA306: =IF(AND($J306=1,$M306=1),SUMPRODUCT(MAX($J$6:$J$1062*(N306*$K$6:$K$1062/Span_P+O306*$F$6:$F$1062/Span_S+P306*$G$6:$G$1062/Span_B)-(1-$J$6:$J$1062)*1000000000)),"") | AB306: =IF(AND($J306=1,$M306=1),IF(AA306-Z306<=0.000000001,1,0),"") | AC306: =IF(AND($J306=1,$M306=0),IF(S306="",0,S306*INDEX(Grid!$B$6:$H$156,R306+1,Q306+1))+IF(V306="",0,V306*INDEX(Grid!$B$6:$H$156,U306+1,T306+1))+IF(Y306="",0,Y306*INDEX(Grid!$B$6:$H$156,X306+1,W306+1)),"") -> 235.39951 | AD306: =IF(AND($J306=1,$M306=0),IF(S306="",0,S306*Val_pt*(Ceiling_e-E_zero)*(1-(1-Half_gap)^Q306))+IF(V306="",0,V306*Val_pt*(Ceiling_e-E_zero)*(1-(1-Half_gap)^T306))+IF(Y306="",0,Y306*Val_pt*(Ceiling_e-E_zero)*(1-(1-Half_gap)^W306)),"") -> 70.647398 | AE306: =IF(AND($J306=1,$M306=0),IF(S306="",0,S306*R306)+IF(V306="",0,V306*U306)+IF(Y306="",0,Y306*X306),"") -> 149.07515 | AF306: =IF(AND($J306=1,$M306=0),MIN((AC306-E306)/Span_P,(AD306-F306)/Span_S,(AE306-G306)/Span_B),"") -> 0.00050097119 | AG306: =IF(AND($J306=1,$M306=0),IF(AF306>0.0000001,1,0),"") -> 1 | AH306: =IF($J306=1,IF($M306=1,AB306,AG306),"") -> 1 | AI306: =IF($J306=1,(Ideal_P-E306)/Span_P,"") -> 0.41134779 | AJ306: =IF($J306=1,(Ideal_S-F306)/Span_S,"") -> 1 | AK306: =IF($J306=1,(Ideal_B-G306)/Span_B,"") -> 0.0066666667 | AL306: =IF($J306=1,MAX(ChA_1*AI306,ChA_2*AJ306,ChA_3*AK306)+Rho*(ChA_1*AI306+ChA_2*AJ306+ChA_3*AK306),"") -> 1.0001418 | AM306: =IF($J306=1,MAX(ChB_1*AI306,ChB_2*AJ306,ChB_3*AK306)+Rho*(ChB_1*AI306+ChB_2*AJ306+ChB_3*AK306),"") -> 1.0001829 | AN306: =IF($J306=1,MAX(Cx_1*(Ref_P-E306)/Span_P,Cx_2*(Ref_S-F306)/Span_S,Cx_3*(Ref_B-G306)/Span_B),"") -> 4.2831737
A307: 301 | B307: =INT(A307/151) -> 1 | C307: =MOD(A307,151) -> 150 | D307: =INDEX(Grid!$J$6:$P$156,C307+1,B307+1) -> 1 | E307: =IF(D307=1,INDEX(Grid!$B$6:$H$156,C307+1,B307+1),"") -> 234.30901 | F307: =Val_pt*(Ceiling_e-E_zero)*(1-(1-Half_gap)^B307) -> 70 | G307: =C307 -> 150 | H307: =IF(D307=1,INDEX(Grid!$R$6:$X$156,C307+1,B307+1),"") -> 32 | I307: =IF(D307=1,INDEX(Sch_label,H307+1),"") -> 1 | J307: =IF(D307=1,INDEX(Grid!$Z$6:$AF$156,C307+1,B307+1),0) -> 1 | K307: =IF(J307=1,E307,0) -> 234.30901 | L307: =IF(D307=1,E307+W_board*F307,"") -> 629.44076 | M307: 1 | N307: 0.019388165 | O307: 0.001 | P307: 0.97961183 | Z307: =IF(AND($J307=1,$M307=1),N307*E307/Span_P+O307*F307/Span_S+P307*G307/Span_B,"") -> 0.99318934 | AA307: =IF(AND($J307=1,$M307=1),SUMPRODUCT(MAX($J$6:$J$1062*(N307*$K$6:$K$1062/Span_P+O307*$F$6:$F$1062/Span_S+P307*$G$6:$G$1062/Span_B)-(1-$J$6:$J$1062)*1000000000)),"") -> 0.99318934 | AB307: =IF(AND($J307=1,$M307=1),IF(AA307-Z307<=0.000000001,1,0),"") -> 1 | AC307: =IF(AND($J307=1,$M307=0),IF(S307="",0,S307*INDEX(Grid!$B$6:$H$156,R307+1,Q307+1))+IF(V307="",0,V307*INDEX(Grid!$B$6:$H$156,U307+1,T307+1))+IF(Y307="",0,Y307*INDEX(Grid!$B$6:$H$156,X307+1,W307+1)),"") | AD307: =IF(AND($J307=1,$M307=0),IF(S307="",0,S307*Val_pt*(Ceiling_e-E_zero)*(1-(1-Half_gap)^Q307))+IF(V307="",0,V307*Val_pt*(Ceiling_e-E_zero)*(1-(1-Half_gap)^T307))+IF(Y307="",0,Y307*Val_pt*(Ceiling_e-E_zero)*(1-(1-Half_gap)^W307)),"") | AE307: =IF(AND($J307=1,$M307=0),IF(S307="",0,S307*R307)+IF(V307="",0,V307*U307)+IF(Y307="",0,Y307*X307),"") | AF307: =IF(AND($J307=1,$M307=0),MIN((AC307-E307)/Span_P,(AD307-F307)/Span_S,(AE307-G307)/Span_B),"") | AG307: =IF(AND($J307=1,$M307=0),IF(AF307>0.0000001,1,0),"") | AH307: =IF($J307=1,IF($M307=1,AB307,AG307),"") -> 1 | AI307: =IF($J307=1,(Ideal_P-E307)/Span_P,"") -> 0.41385829 | AJ307: =IF($J307=1,(Ideal_S-F307)/Span_S,"") -> 1 | AK307: =IF($J307=1,(Ideal_B-G307)/Span_B,"") -> 0 | AL307: =IF($J307=1,MAX(ChA_1*AI307,ChA_2*AJ307,ChA_3*AK307)+Rho*(ChA_1*AI307+ChA_2*AJ307+ChA_3*AK307),"") -> 1.0001414 | AM307: =IF($J307=1,MAX(ChB_1*AI307,ChB_2*AJ307,ChB_3*AK307)+Rho*(ChB_1*AI307+ChB_2*AJ307+ChB_3*AK307),"") -> 1.0001828 | AN307: =IF($J307=1,MAX(Cx_1*(Ref_P-E307)/Span_P,Cx_2*(Ref_S-F307)/Span_S,Cx_3*(Ref_B-G307)/Span_B),"") -> 4.2831737
A308: 302 | B308: =INT(A308/151) -> 2 | C308: =MOD(A308,151) -> 0 | D308: =INDEX(Grid!$J$6:$P$156,C308+1,B308+1) -> 1 | E308: =IF(D308=1,INDEX(Grid!$B$6:$H$156,C308+1,B308+1),"") -> 384.17334 | F308: =Val_pt*(Ceiling_e-E_zero)*(1-(1-Half_gap)^B308) -> 105 | G308: =C308 -> 0 | H308: =IF(D308=1,INDEX(Grid!$R$6:$X$156,C308+1,B308+1),"") -> 48 | I308: =IF(D308=1,INDEX(Sch_label,H308+1),"") -> 1, 2 | J308: =IF(D308=1,INDEX(Grid!$Z$6:$AF$156,C308+1,B308+1),0) -> 1 | K308: =IF(J308=1,E308,0) -> 384.17334 | L308: =IF(D308=1,E308+W_board*F308,"") -> 976.87096 | M308: 1 | N308: 0.998 | O308: 0.001 | P308: 0.001 | Z308: =IF(AND($J308=1,$M308=1),N308*E308/Span_P+O308*F308/Span_S+P308*G308/Span_B,"") -> 1.0603416 | AA308: =IF(AND($J308=1,$M308=1),SUMPRODUCT(MAX($J$6:$J$1062*(N308*$K$6:$K$1062/Span_P+O308*$F$6:$F$1062/Span_S+P308*$G$6:$G$1062/Span_B)-(1-$J$6:$J$1062)*1000000000)),"") -> 1.0603416 | AB308: =IF(AND($J308=1,$M308=1),IF(AA308-Z308<=0.000000001,1,0),"") -> 1 | AC308: =IF(AND($J308=1,$M308=0),IF(S308="",0,S308*INDEX(Grid!$B$6:$H$156,R308+1,Q308+1))+IF(V308="",0,V308*INDEX(Grid!$B$6:$H$156,U308+1,T308+1))+IF(Y308="",0,Y308*INDEX(Grid!$B$6:$H$156,X308+1,W308+1)),"") | AD308: =IF(AND($J308=1,$M308=0),IF(S308="",0,S308*Val_pt*(Ceiling_e-E_zero)*(1-(1-Half_gap)^Q308))+IF(V308="",0,V308*Val_pt*(Ceiling_e-E_zero)*(1-(1-Half_gap)^T308))+IF(Y308="",0,Y308*Val_pt*(Ceiling_e-E_zero)*(1-(1-Half_gap)^W308)),"") | AE308: =IF(AND($J308=1,$M308=0),IF(S308="",0,S308*R308)+IF(V308="",0,V308*U308)+IF(Y308="",0,Y308*X308),"") | AF308: =IF(AND($J308=1,$M308=0),MIN((AC308-E308)/Span_P,(AD308-F308)/Span_S,(AE308-G308)/Span_B),"") | AG308: =IF(AND($J308=1,$M308=0),IF(AF308>0.0000001,1,0),"") | AH308: =IF($J308=1,IF($M308=1,AB308,AG308),"") -> 1 | AI308: =IF($J308=1,(Ideal_P-E308)/Span_P,"") -> 0 | AJ308: =IF($J308=1,(Ideal_S-F308)/Span_S,"") -> 0.48387097 | AK308: =IF($J308=1,(Ideal_B-G308)/Span_B,"") -> 1 | AL308: =IF($J308=1,MAX(ChA_1*AI308,ChA_2*AJ308,ChA_3*AK308)+Rho*(ChA_1*AI308+ChA_2*AJ308+ChA_3*AK308),"") -> 1.0001484 | AM308: =IF($J308=1,MAX(ChB_1*AI308,ChB_2*AJ308,ChB_3*AK308)+Rho*(ChB_1*AI308+ChB_2*AJ308+ChB_3*AK308),"") -> 1.0001484 | AN308: =IF($J308=1,MAX(Cx_1*(Ref_P-E308)/Span_P,Cx_2*(Ref_S-F308)/Span_S,Cx_3*(Ref_B-G308)/Span_B),"") -> 2.5462185
A309: 303 | B309: =INT(A309/151) -> 2 | C309: =MOD(A309,151) -> 1 | D309: =INDEX(Grid!$J$6:$P$156,C309+1,B309+1) -> 1 | E309: =IF(D309=1,INDEX(Grid!$B$6:$H$156,C309+1,B309+1),"") -> 383.26425 | F309: =Val_pt*(Ceiling_e-E_zero)*(1-(1-Half_gap)^B309) -> 105 | G309: =C309 -> 1 | H309: =IF(D309=1,INDEX(Grid!$R$6:$X$156,C309+1,B309+1),"") -> 48 | I309: =IF(D309=1,INDEX(Sch_label,H309+1),"") -> 1, 2 | J309: =IF(D309=1,INDEX(Grid!$Z$6:$AF$156,C309+1,B309+1),0) -> 1 | K309: =IF(J309=1,E309,0) -> 383.26425 | L309: =IF(D309=1,E309+W_board*F309,"") -> 975.96187 | M309: 1 | N309: 0.72571396 | O309: 0.001 | P309: 0.27328604 | Z309: =IF(AND($J309=1,$M309=1),N309*E309/Span_P+O309*F309/Span_S+P309*G309/Span_B,"") -> 0.77146925 | AA309: =IF(AND($J309=1,$M309=1),SUMPRODUCT(MAX($J$6:$J$1062*(N309*$K$6:$K$1062/Span_P+O309*$F$6:$F$1062/Span_S+P309*$G$6:$G$1062/Span_B)-(1-$J$6:$J$1062)*1000000000)),"") -> 0.77146925 | AB309: =IF(AND($J309=1,$M309=1),IF(AA309-Z309<=0.000000001,1,0),"") -> 1 | AC309: =IF(AND($J309=1,$M309=0),IF(S309="",0,S309*INDEX(Grid!$B$6:$H$156,R309+1,Q309+1))+IF(V309="",0,V309*INDEX(Grid!$B$6:$H$156,U309+1,T309+1))+IF(Y309="",0,Y309*INDEX(Grid!$B$6:$H$156,X309+1,W309+1)),"") | AD309: =IF(AND($J309=1,$M309=0),IF(S309="",0,S309*Val_pt*(Ceiling_e-E_zero)*(1-(1-Half_gap)^Q309))+IF(V309="",0,V309*Val_pt*(Ceiling_e-E_zero)*(1-(1-Half_gap)^T309))+IF(Y309="",0,Y309*Val_pt*(Ceiling_e-E_zero)*(1-(1-Half_gap)^W309)),"") | AE309: =IF(AND($J309=1,$M309=0),IF(S309="",0,S309*R309)+IF(V309="",0,V309*U309)+IF(Y309="",0,Y309*X309),"") | AF309: =IF(AND($J309=1,$M309=0),MIN((AC309-E309)/Span_P,(AD309-F309)/Span_S,(AE309-G309)/Span_B),"") | AG309: =IF(AND($J309=1,$M309=0),IF(AF309>0.0000001,1,0),"") | AH309: =IF($J309=1,IF($M309=1,AB309,AG309),"") -> 1 | AI309: =IF($J309=1,(Ideal_P-E309)/Span_P,"") -> 0.0025105028 | AJ309: =IF($J309=1,(Ideal_S-F309)/Span_S,"") -> 0.48387097 | AK309: =IF($J309=1,(Ideal_B-G309)/Span_B,"") -> 0.99333333 | AL309: =IF($J309=1,MAX(ChA_1*AI309,ChA_2*AJ309,ChA_3*AK309)+Rho*(ChA_1*AI309+ChA_2*AJ309+ChA_3*AK309),"") -> 0.9934813 | AM309: =IF($J309=1,MAX(ChB_1*AI309,ChB_2*AJ309,ChB_3*AK309)+Rho*(ChB_1*AI309+ChB_2*AJ309+ChB_3*AK309),"") -> 0.99348156 | AN309: =IF($J309=1,MAX(Cx_1*(Ref_P-E309)/Span_P,Cx_2*(Ref_S-F309)/Span_S,Cx_3*(Ref_B-G309)/Span_B),"") -> 2.5294118
A310: 304 | B310: =INT(A310/151) -> 2 | C310: =MOD(A310,151) -> 2 | D310: =INDEX(Grid!$J$6:$P$156,C310+1,B310+1) -> 1 | E310: =IF(D310=1,INDEX(Grid!$B$6:$H$156,C310+1,B310+1),"") -> 382.35515 | F310: =Val_pt*(Ceiling_e-E_zero)*(1-(1-Half_gap)^B310) -> 105 | G310: =C310 -> 2 | H310: =IF(D310=1,INDEX(Grid!$R$6:$X$156,C310+1,B310+1),"") -> 48 | I310: =IF(D310=1,INDEX(Sch_label,H310+1),"") -> 1, 2 | J310: =IF(D310=1,INDEX(Grid!$Z$6:$AF$156,C310+1,B310+1),0) -> 1 | K310: =IF(J310=1,E310,0) -> 382.35515 | L310: =IF(D310=1,E310+W_board*F310,"") -> 975.05278 | M310: 1 | N310: 0.72571396 | O310: 0.001 | P310: 0.27328604 | Z310: =IF(AND($J310=1,$M310=1),N310*E310/Span_P+O310*F310/Span_S+P310*G310/Span_B,"") -> 0.77146925 | AA310: =IF(AND($J310=1,$M310=1),SUMPRODUCT(MAX($J$6:$J$1062*(N310*$K$6:$K$1062/Span_P+O310*$F$6:$F$1062/Span_S+P310*$G$6:$G$1062/Span_B)-(1-$J$6:$J$1062)*1000000000)),"") -> 0.77146925 | AB310: =IF(AND($J310=1,$M310=1),IF(AA310-Z310<=0.000000001,1,0),"") -> 1 | AC310: =IF(AND($J310=1,$M310=0),IF(S310="",0,S310*INDEX(Grid!$B$6:$H$156,R310+1,Q310+1))+IF(V310="",0,V310*INDEX(Grid!$B$6:$H$156,U310+1,T310+1))+IF(Y310="",0,Y310*INDEX(Grid!$B$6:$H$156,X310+1,W310+1)),"") | AD310: =IF(AND($J310=1,$M310=0),IF(S310="",0,S310*Val_pt*(Ceiling_e-E_zero)*(1-(1-Half_gap)^Q310))+IF(V310="",0,V310*Val_pt*(Ceiling_e-E_zero)*(1-(1-Half_gap)^T310))+IF(Y310="",0,Y310*Val_pt*(Ceiling_e-E_zero)*(1-(1-Half_gap)^W310)),"") | AE310: =IF(AND($J310=1,$M310=0),IF(S310="",0,S310*R310)+IF(V310="",0,V310*U310)+IF(Y310="",0,Y310*X310),"") | AF310: =IF(AND($J310=1,$M310=0),MIN((AC310-E310)/Span_P,(AD310-F310)/Span_S,(AE310-G310)/Span_B),"") | AG310: =IF(AND($J310=1,$M310=0),IF(AF310>0.0000001,1,0),"") | AH310: =IF($J310=1,IF($M310=1,AB310,AG310),"") -> 1 | AI310: =IF($J310=1,(Ideal_P-E310)/Span_P,"") -> 0.0050210056 | AJ310: =IF($J310=1,(Ideal_S-F310)/Span_S,"") -> 0.48387097 | AK310: =IF($J310=1,(Ideal_B-G310)/Span_B,"") -> 0.98666667 | AL310: =IF($J310=1,MAX(ChA_1*AI310,ChA_2*AJ310,ChA_3*AK310)+Rho*(ChA_1*AI310+ChA_2*AJ310+ChA_3*AK310),"") -> 0.98681422 | AM310: =IF($J310=1,MAX(ChB_1*AI310,ChB_2*AJ310,ChB_3*AK310)+Rho*(ChB_1*AI310+ChB_2*AJ310+ChB_3*AK310),"") -> 0.98681472 | AN310: =IF($J310=1,MAX(Cx_1*(Ref_P-E310)/Span_P,Cx_2*(Ref_S-F310)/Span_S,Cx_3*(Ref_B-G310)/Span_B),"") -> 2.512605
A311: 305 | B311: =INT(A311/151) -> 2 | C311: =MOD(A311,151) -> 3 | D311: =INDEX(Grid!$J$6:$P$156,C311+1,B311+1) -> 1 | E311: =IF(D311=1,INDEX(Grid!$B$6:$H$156,C311+1,B311+1),"") -> 381.44606 | F311: =Val_pt*(Ceiling_e-E_zero)*(1-(1-Half_gap)^B311) -> 105 | G311: =C311 -> 3 | H311: =IF(D311=1,INDEX(Grid!$R$6:$X$156,C311+1,B311+1),"") -> 48 | I311: =IF(D311=1,INDEX(Sch_label,H311+1),"") -> 1, 2 | J311: =IF(D311=1,INDEX(Grid!$Z$6:$AF$156,C311+1,B311+1),0) -> 1 | K311: =IF(J311=1,E311,0) -> 381.44606 | L311: =IF(D311=1,E311+W_board*F311,"") -> 974.14369 | M311: 1 | N311: 0.72571396 | O311: 0.001 | P311: 0.27328604 | Z311: =IF(AND($J311=1,$M311=1),N311*E311/Span_P+O311*F311/Span_S+P311*G311/Span_B,"") -> 0.77146925 | AA311: =IF(AND($J311=1,$M311=1),SUMPRODUCT(MAX($J$6:$J$1062*(N311*$K$6:$K$1062/Span_P+O311*$F$6:$F$1062/Span_S+P311*$G$6:$G$1062/Span_B)-(1-$J$6:$J$1062)*1000000000)),"") -> 0.77146925 | AB311: =IF(AND($J311=1,$M311=1),IF(AA311-Z311<=0.000000001,1,0),"") -> 1 | AC311: =IF(AND($J311=1,$M311=0),IF(S311="",0,S311*INDEX(Grid!$B$6:$H$156,R311+1,Q311+1))+IF(V311="",0,V311*INDEX(Grid!$B$6:$H$156,U311+1,T311+1))+IF(Y311="",0,Y311*INDEX(Grid!$B$6:$H$156,X311+1,W311+1)),"") | AD311: =IF(AND($J311=1,$M311=0),IF(S311="",0,S311*Val_pt*(Ceiling_e-E_zero)*(1-(1-Half_gap)^Q311))+IF(V311="",0,V311*Val_pt*(Ceiling_e-E_zero)*(1-(1-Half_gap)^T311))+IF(Y311="",0,Y311*Val_pt*(Ceiling_e-E_zero)*(1-(1-Half_gap)^W311)),"") | AE311: =IF(AND($J311=1,$M311=0),IF(S311="",0,S311*R311)+IF(V311="",0,V311*U311)+IF(Y311="",0,Y311*X311),"") | AF311: =IF(AND($J311=1,$M311=0),MIN((AC311-E311)/Span_P,(AD311-F311)/Span_S,(AE311-G311)/Span_B),"") | AG311: =IF(AND($J311=1,$M311=0),IF(AF311>0.0000001,1,0),"") | AH311: =IF($J311=1,IF($M311=1,AB311,AG311),"") -> 1 | AI311: =IF($J311=1,(Ideal_P-E311)/Span_P,"") -> 0.0075315083 | AJ311: =IF($J311=1,(Ideal_S-F311)/Span_S,"") -> 0.48387097 | AK311: =IF($J311=1,(Ideal_B-G311)/Span_B,"") -> 0.98 | AL311: =IF($J311=1,MAX(ChA_1*AI311,ChA_2*AJ311,ChA_3*AK311)+Rho*(ChA_1*AI311+ChA_2*AJ311+ChA_3*AK311),"") -> 0.98014714 | AM311: =IF($J311=1,MAX(ChB_1*AI311,ChB_2*AJ311,ChB_3*AK311)+Rho*(ChB_1*AI311+ChB_2*AJ311+ChB_3*AK311),"") -> 0.98014789 | AN311: =IF($J311=1,MAX(Cx_1*(Ref_P-E311)/Span_P,Cx_2*(Ref_S-F311)/Span_S,Cx_3*(Ref_B-G311)/Span_B),"") -> 2.4957983
A312: 306 | B312: =INT(A312/151) -> 2 | C312: =MOD(A312,151) -> 4 | D312: =INDEX(Grid!$J$6:$P$156,C312+1,B312+1) -> 1 | E312: =IF(D312=1,INDEX(Grid!$B$6:$H$156,C312+1,B312+1),"") -> 380.53697 | F312: =Val_pt*(Ceiling_e-E_zero)*(1-(1-Half_gap)^B312) -> 105 | G312: =C312 -> 4 | H312: =IF(D312=1,INDEX(Grid!$R$6:$X$156,C312+1,B312+1),"") -> 48 | I312: =IF(D312=1,INDEX(Sch_label,H312+1),"") -> 1, 2 | J312: =IF(D312=1,INDEX(Grid!$Z$6:$AF$156,C312+1,B312+1),0) -> 1 | K312: =IF(J312=1,E312,0) -> 380.53697 | L312: =IF(D312=1,E312+W_board*F312,"") -> 973.2346 | M312: 1 | N312: 0.72571396 | O312: 0.001 | P312: 0.27328604 | Z312: =IF(AND($J312=1,$M312=1),N312*E312/Span_P+O312*F312/Span_S+P312*G312/Span_B,"") -> 0.77146925 | AA312: =IF(AND($J312=1,$M312=1),SUMPRODUCT(MAX($J$6:$J$1062*(N312*$K$6:$K$1062/Span_P+O312*$F$6:$F$1062/Span_S+P312*$G$6:$G$1062/Span_B)-(1-$J$6:$J$1062)*1000000000)),"") -> 0.77146925 | AB312: =IF(AND($J312=1,$M312=1),IF(AA312-Z312<=0.000000001,1,0),"") -> 1 | AC312: =IF(AND($J312=1,$M312=0),IF(S312="",0,S312*INDEX(Grid!$B$6:$H$156,R312+1,Q312+1))+IF(V312="",0,V312*INDEX(Grid!$B$6:$H$156,U312+1,T312+1))+IF(Y312="",0,Y312*INDEX(Grid!$B$6:$H$156,X312+1,W312+1)),"") | AD312: =IF(AND($J312=1,$M312=0),IF(S312="",0,S312*Val_pt*(Ceiling_e-E_zero)*(1-(1-Half_gap)^Q312))+IF(V312="",0,V312*Val_pt*(Ceiling_e-E_zero)*(1-(1-Half_gap)^T312))+IF(Y312="",0,Y312*Val_pt*(Ceiling_e-E_zero)*(1-(1-Half_gap)^W312)),"") | AE312: =IF(AND($J312=1,$M312=0),IF(S312="",0,S312*R312)+IF(V312="",0,V312*U312)+IF(Y312="",0,Y312*X312),"") | AF312: =IF(AND($J312=1,$M312=0),MIN((AC312-E312)/Span_P,(AD312-F312)/Span_S,(AE312-G312)/Span_B),"") | AG312: =IF(AND($J312=1,$M312=0),IF(AF312>0.0000001,1,0),"") | AH312: =IF($J312=1,IF($M312=1,AB312,AG312),"") -> 1 | AI312: =IF($J312=1,(Ideal_P-E312)/Span_P,"") -> 0.010042011 | AJ312: =IF($J312=1,(Ideal_S-F312)/Span_S,"") -> 0.48387097 | AK312: =IF($J312=1,(Ideal_B-G312)/Span_B,"") -> 0.97333333 | AL312: =IF($J312=1,MAX(ChA_1*AI312,ChA_2*AJ312,ChA_3*AK312)+Rho*(ChA_1*AI312+ChA_2*AJ312+ChA_3*AK312),"") -> 0.97348006 | AM312: =IF($J312=1,MAX(ChB_1*AI312,ChB_2*AJ312,ChB_3*AK312)+Rho*(ChB_1*AI312+ChB_2*AJ312+ChB_3*AK312),"") -> 0.97348106 | AN312: =IF($J312=1,MAX(Cx_1*(Ref_P-E312)/Span_P,Cx_2*(Ref_S-F312)/Span_S,Cx_3*(Ref_B-G312)/Span_B),"") -> 2.4789916
A313: 307 | B313: =INT(A313/151) -> 2 | C313: =MOD(A313,151) -> 5 | D313: =INDEX(Grid!$J$6:$P$156,C313+1,B313+1) -> 1 | E313: =IF(D313=1,INDEX(Grid!$B$6:$H$156,C313+1,B313+1),"") -> 379.62788 | F313: =Val_pt*(Ceiling_e-E_zero)*(1-(1-Half_gap)^B313) -> 105 | G313: =C313 -> 5 | H313: =IF(D313=1,INDEX(Grid!$R$6:$X$156,C313+1,B313+1),"") -> 48 | I313: =IF(D313=1,INDEX(Sch_label,H313+1),"") -> 1, 2 | J313: =IF(D313=1,INDEX(Grid!$Z$6:$AF$156,C313+1,B313+1),0) -> 1 | K313: =IF(J313=1,E313,0) -> 379.62788 | L313: =IF(D313=1,E313+W_board*F313,"") -> 972.32551 | M313: 1 | N313: 0.72571396 | O313: 0.001 | P313: 0.27328604 | Z313: =IF(AND($J313=1,$M313=1),N313*E313/Span_P+O313*F313/Span_S+P313*G313/Span_B,"") -> 0.77146925 | AA313: =IF(AND($J313=1,$M313=1),SUMPRODUCT(MAX($J$6:$J$1062*(N313*$K$6:$K$1062/Span_P+O313*$F$6:$F$1062/Span_S+P313*$G$6:$G$1062/Span_B)-(1-$J$6:$J$1062)*1000000000)),"") -> 0.77146925 | AB313: =IF(AND($J313=1,$M313=1),IF(AA313-Z313<=0.000000001,1,0),"") -> 1 | AC313: =IF(AND($J313=1,$M313=0),IF(S313="",0,S313*INDEX(Grid!$B$6:$H$156,R313+1,Q313+1))+IF(V313="",0,V313*INDEX(Grid!$B$6:$H$156,U313+1,T313+1))+IF(Y313="",0,Y313*INDEX(Grid!$B$6:$H$156,X313+1,W313+1)),"") | AD313: =IF(AND($J313=1,$M313=0),IF(S313="",0,S313*Val_pt*(Ceiling_e-E_zero)*(1-(1-Half_gap)^Q313))+IF(V313="",0,V313*Val_pt*(Ceiling_e-E_zero)*(1-(1-Half_gap)^T313))+IF(Y313="",0,Y313*Val_pt*(Ceiling_e-E_zero)*(1-(1-Half_gap)^W313)),"") | AE313: =IF(AND($J313=1,$M313=0),IF(S313="",0,S313*R313)+IF(V313="",0,V313*U313)+IF(Y313="",0,Y313*X313),"") | AF313: =IF(AND($J313=1,$M313=0),MIN((AC313-E313)/Span_P,(AD313-F313)/Span_S,(AE313-G313)/Span_B),"") | AG313: =IF(AND($J313=1,$M313=0),IF(AF313>0.0000001,1,0),"") | AH313: =IF($J313=1,IF($M313=1,AB313,AG313),"") -> 1 | AI313: =IF($J313=1,(Ideal_P-E313)/Span_P,"") -> 0.012552514 | AJ313: =IF($J313=1,(Ideal_S-F313)/Span_S,"") -> 0.48387097 | AK313: =IF($J313=1,(Ideal_B-G313)/Span_B,"") -> 0.96666667 | AL313: =IF($J313=1,MAX(ChA_1*AI313,ChA_2*AJ313,ChA_3*AK313)+Rho*(ChA_1*AI313+ChA_2*AJ313+ChA_3*AK313),"") -> 0.96681298 | AM313: =IF($J313=1,MAX(ChB_1*AI313,ChB_2*AJ313,ChB_3*AK313)+Rho*(ChB_1*AI313+ChB_2*AJ313+ChB_3*AK313),"") -> 0.96681423 | AN313: =IF($J313=1,MAX(Cx_1*(Ref_P-E313)/Span_P,Cx_2*(Ref_S-F313)/Span_S,Cx_3*(Ref_B-G313)/Span_B),"") -> 2.4621849
A314: 308 | B314: =INT(A314/151) -> 2 | C314: =MOD(A314,151) -> 6 | D314: =INDEX(Grid!$J$6:$P$156,C314+1,B314+1) -> 1 | E314: =IF(D314=1,INDEX(Grid!$B$6:$H$156,C314+1,B314+1),"") -> 378.71879 | F314: =Val_pt*(Ceiling_e-E_zero)*(1-(1-Half_gap)^B314) -> 105 | G314: =C314 -> 6 | H314: =IF(D314=1,INDEX(Grid!$R$6:$X$156,C314+1,B314+1),"") -> 48 | I314: =IF(D314=1,INDEX(Sch_label,H314+1),"") -> 1, 2 | J314: =IF(D314=1,INDEX(Grid!$Z$6:$AF$156,C314+1,B314+1),0) -> 1 | K314: =IF(J314=1,E314,0) -> 378.71879 | L314: =IF(D314=1,E314+W_board*F314,"") -> 971.41642 | M314: 1 | N314: 0.72571396 | O314: 0.001 | P314: 0.27328604 | Z314: =IF(AND($J314=1,$M314=1),N314*E314/Span_P+O314*F314/Span_S+P314*G314/Span_B,"") -> 0.77146925 | AA314: =IF(AND($J314=1,$M314=1),SUMPRODUCT(MAX($J$6:$J$1062*(N314*$K$6:$K$1062/Span_P+O314*$F$6:$F$1062/Span_S+P314*$G$6:$G$1062/Span_B)-(1-$J$6:$J$1062)*1000000000)),"") -> 0.77146925 | AB314: =IF(AND($J314=1,$M314=1),IF(AA314-Z314<=0.000000001,1,0),"") -> 1 | AC314: =IF(AND($J314=1,$M314=0),IF(S314="",0,S314*INDEX(Grid!$B$6:$H$156,R314+1,Q314+1))+IF(V314="",0,V314*INDEX(Grid!$B$6:$H$156,U314+1,T314+1))+IF(Y314="",0,Y314*INDEX(Grid!$B$6:$H$156,X314+1,W314+1)),"") | AD314: =IF(AND($J314=1,$M314=0),IF(S314="",0,S314*Val_pt*(Ceiling_e-E_zero)*(1-(1-Half_gap)^Q314))+IF(V314="",0,V314*Val_pt*(Ceiling_e-E_zero)*(1-(1-Half_gap)^T314))+IF(Y314="",0,Y314*Val_pt*(Ceiling_e-E_zero)*(1-(1-Half_gap)^W314)),"") | AE314: =IF(AND($J314=1,$M314=0),IF(S314="",0,S314*R314)+IF(V314="",0,V314*U314)+IF(Y314="",0,Y314*X314),"") | AF314: =IF(AND($J314=1,$M314=0),MIN((AC314-E314)/Span_P,(AD314-F314)/Span_S,(AE314-G314)/Span_B),"") | AG314: =IF(AND($J314=1,$M314=0),IF(AF314>0.0000001,1,0),"") | AH314: =IF($J314=1,IF($M314=1,AB314,AG314),"") -> 1 | AI314: =IF($J314=1,(Ideal_P-E314)/Span_P,"") -> 0.015063017 | AJ314: =IF($J314=1,(Ideal_S-F314)/Span_S,"") -> 0.48387097 | AK314: =IF($J314=1,(Ideal_B-G314)/Span_B,"") -> 0.96 | AL314: =IF($J314=1,MAX(ChA_1*AI314,ChA_2*AJ314,ChA_3*AK314)+Rho*(ChA_1*AI314+ChA_2*AJ314+ChA_3*AK314),"") -> 0.96014589 | AM314: =IF($J314=1,MAX(ChB_1*AI314,ChB_2*AJ314,ChB_3*AK314)+Rho*(ChB_1*AI314+ChB_2*AJ314+ChB_3*AK314),"") -> 0.9601474 | AN314: =IF($J314=1,MAX(Cx_1*(Ref_P-E314)/Span_P,Cx_2*(Ref_S-F314)/Span_S,Cx_3*(Ref_B-G314)/Span_B),"") -> 2.4453782
A315: 309 | B315: =INT(A315/151) -> 2 | C315: =MOD(A315,151) -> 7 | D315: =INDEX(Grid!$J$6:$P$156,C315+1,B315+1) -> 1 | E315: =IF(D315=1,INDEX(Grid!$B$6:$H$156,C315+1,B315+1),"") -> 377.8097 | F315: =Val_pt*(Ceiling_e-E_zero)*(1-(1-Half_gap)^B315) -> 105 | G315: =C315 -> 7 | H315: =IF(D315=1,INDEX(Grid!$R$6:$X$156,C315+1,B315+1),"") -> 48 | I315: =IF(D315=1,INDEX(Sch_label,H315+1),"") -> 1, 2 | J315: =IF(D315=1,INDEX(Grid!$Z$6:$AF$156,C315+1,B315+1),0) -> 1 | K315: =IF(J315=1,E315,0) -> 377.8097 | L315: =IF(D315=1,E315+W_board*F315,"") -> 970.50733 | M315: 1 | N315: 0.72571396 | O315: 0.001 | P315: 0.27328604 | Z315: =IF(AND($J315=1,$M315=1),N315*E315/Span_P+O315*F315/Span_S+P315*G315/Span_B,"") -> 0.77146925 | AA315: =IF(AND($J315=1,$M315=1),SUMPRODUCT(MAX($J$6:$J$1062*(N315*$K$6:$K$1062/Span_P+O315*$F$6:$F$1062/Span_S+P315*$G$6:$G$1062/Span_B)-(1-$J$6:$J$1062)*1000000000)),"") -> 0.77146925 | AB315: =IF(AND($J315=1,$M315=1),IF(AA315-Z315<=0.000000001,1,0),"") -> 1 | AC315: =IF(AND($J315=1,$M315=0),IF(S315="",0,S315*INDEX(Grid!$B$6:$H$156,R315+1,Q315+1))+IF(V315="",0,V315*INDEX(Grid!$B$6:$H$156,U315+1,T315+1))+IF(Y315="",0,Y315*INDEX(Grid!$B$6:$H$156,X315+1,W315+1)),"") | AD315: =IF(AND($J315=1,$M315=0),IF(S315="",0,S315*Val_pt*(Ceiling_e-E_zero)*(1-(1-Half_gap)^Q315))+IF(V315="",0,V315*Val_pt*(Ceiling_e-E_zero)*(1-(1-Half_gap)^T315))+IF(Y315="",0,Y315*Val_pt*(Ceiling_e-E_zero)*(1-(1-Half_gap)^W315)),"") | AE315: =IF(AND($J315=1,$M315=0),IF(S315="",0,S315*R315)+IF(V315="",0,V315*U315)+IF(Y315="",0,Y315*X315),"") | AF315: =IF(AND($J315=1,$M315=0),MIN((AC315-E315)/Span_P,(AD315-F315)/Span_S,(AE315-G315)/Span_B),"") | AG315: =IF(AND($J315=1,$M315=0),IF(AF315>0.0000001,1,0),"") | AH315: =IF($J315=1,IF($M315=1,AB315,AG315),"") -> 1 | AI315: =IF($J315=1,(Ideal_P-E315)/Span_P,"") -> 0.017573519 | AJ315: =IF($J315=1,(Ideal_S-F315)/Span_S,"") -> 0.48387097 | AK315: =IF($J315=1,(Ideal_B-G315)/Span_B,"") -> 0.95333333 | AL315: =IF($J315=1,MAX(ChA_1*AI315,ChA_2*AJ315,ChA_3*AK315)+Rho*(ChA_1*AI315+ChA_2*AJ315+ChA_3*AK315),"") -> 0.95347881 | AM315: =IF($J315=1,MAX(ChB_1*AI315,ChB_2*AJ315,ChB_3*AK315)+Rho*(ChB_1*AI315+ChB_2*AJ315+ChB_3*AK315),"") -> 0.95348057 | AN315: =IF($J315=1,MAX(Cx_1*(Ref_P-E315)/Span_P,Cx_2*(Ref_S-F315)/Span_S,Cx_3*(Ref_B-G315)/Span_B),"") -> 2.4285714
A316: 310 | B316: =INT(A316/151) -> 2 | C316: =MOD(A316,151) -> 8 | D316: =INDEX(Grid!$J$6:$P$156,C316+1,B316+1) -> 1 | E316: =IF(D316=1,INDEX(Grid!$B$6:$H$156,C316+1,B316+1),"") -> 376.90061 | F316: =Val_pt*(Ceiling_e-E_zero)*(1-(1-Half_gap)^B316) -> 105 | G316: =C316 -> 8 | H316: =IF(D316=1,INDEX(Grid!$R$6:$X$156,C316+1,B316+1),"") -> 48 | I316: =IF(D316=1,INDEX(Sch_label,H316+1),"") -> 1, 2 | J316: =IF(D316=1,INDEX(Grid!$Z$6:$AF$156,C316+1,B316+1),0) -> 1 | K316: =IF(J316=1,E316,0) -> 376.90061 | L316: =IF(D316=1,E316+W_board*F316,"") -> 969.59824 | M316: 1 | N316: 0.72571396 | O316: 0.001 | P316: 0.27328604 | Z316: =IF(AND($J316=1,$M316=1),N316*E316/Span_P+O316*F316/Span_S+P316*G316/Span_B,"") -> 0.77146925 | AA316: =IF(AND($J316=1,$M316=1),SUMPRODUCT(MAX($J$6:$J$1062*(N316*$K$6:$K$1062/Span_P+O316*$F$6:$F$1062/Span_S+P316*$G$6:$G$1062/Span_B)-(1-$J$6:$J$1062)*1000000000)),"") -> 0.77146925 | AB316: =IF(AND($J316=1,$M316=1),IF(AA316-Z316<=0.000000001,1,0),"") -> 1 | AC316: =IF(AND($J316=1,$M316=0),IF(S316="",0,S316*INDEX(Grid!$B$6:$H$156,R316+1,Q316+1))+IF(V316="",0,V316*INDEX(Grid!$B$6:$H$156,U316+1,T316+1))+IF(Y316="",0,Y316*INDEX(Grid!$B$6:$H$156,X316+1,W316+1)),"") | AD316: =IF(AND($J316=1,$M316=0),IF(S316="",0,S316*Val_pt*(Ceiling_e-E_zero)*(1-(1-Half_gap)^Q316))+IF(V316="",0,V316*Val_pt*(Ceiling_e-E_zero)*(1-(1-Half_gap)^T316))+IF(Y316="",0,Y316*Val_pt*(Ceiling_e-E_zero)*(1-(1-Half_gap)^W316)),"") | AE316: =IF(AND($J316=1,$M316=0),IF(S316="",0,S316*R316)+IF(V316="",0,V316*U316)+IF(Y316="",0,Y316*X316),"") | AF316: =IF(AND($J316=1,$M316=0),MIN((AC316-E316)/Span_P,(AD316-F316)/Span_S,(AE316-G316)/Span_B),"") | AG316: =IF(AND($J316=1,$M316=0),IF(AF316>0.0000001,1,0),"") | AH316: =IF($J316=1,IF($M316=1,AB316,AG316),"") -> 1 | AI316: =IF($J316=1,(Ideal_P-E316)/Span_P,"") -> 0.020084022 | AJ316: =IF($J316=1,(Ideal_S-F316)/Span_S,"") -> 0.48387097 | AK316: =IF($J316=1,(Ideal_B-G316)/Span_B,"") -> 0.94666667 | AL316: =IF($J316=1,MAX(ChA_1*AI316,ChA_2*AJ316,ChA_3*AK316)+Rho*(ChA_1*AI316+ChA_2*AJ316+ChA_3*AK316),"") -> 0.94681173 | AM316: =IF($J316=1,MAX(ChB_1*AI316,ChB_2*AJ316,ChB_3*AK316)+Rho*(ChB_1*AI316+ChB_2*AJ316+ChB_3*AK316),"") -> 0.94681374 | AN316: =IF($J316=1,MAX(Cx_1*(Ref_P-E316)/Span_P,Cx_2*(Ref_S-F316)/Span_S,Cx_3*(Ref_B-G316)/Span_B),"") -> 2.4117647
