Workbook

Sheet README
B1: DCT Laboratory — Vol I, Ch 2: Enterprise Systems and Transformation
B2: Seed 26102 · Companion to DCT_V1_Ch02_Lab.ipynb and AXIOM Lab 1.2 (module AXIOM-02). Money in $ million a year.
B4: Worked Example 2.1, Where Does Meridian End?, with the book's declarations.
B5: Declarations: the inputs of Step 1, the six entities with boundary A, boundary B and one you draw, and the nine flows of Table 2.6; for the feedback bench, Meridian's efficiency and the turnaround's target and speed.
B6: Boundaries: every flow classified under each boundary (Definition 2.3) and checked against Table 2.6; the counts, the goods output and the $308 million gap.
B7: AllBoundaries: the 64 ways to draw the line; each classifies the same nine flows (Theorem 2.2), and flows by type show which entities can move freely (Corollary 2.B.2).
B8: Levels: Meridian's group, divisions and units (Figure 2.3), the environment of a subsystem you choose, and the coupling classified level by level.
B9: Feedback: the turnaround's efficiency program as a feedback rule, a gain to explore, and Proposition 2.2's closed-loop map.
B10: Adaptation: the bench's adaptive rule after a shift in the environment (bench settings, not book numbers), and Online Appendix 2.B's adaptive company as one map of the augmented state (Proposition 2.3).
B11: OutputFeedback: Remark 2.B.1's algebraic loops. Loops: the migration loop and the efficiency program, signed.
B12: The checks over 1,000 random histories (seed 26102) run in the notebook.
B13: Reference_Values and Checks: the engine's numbers and a PASS/FAIL comparison with this workbook's formulas.
... B19: Cross-sheet link: green.

Sheet Declarations
A1: Declarations (Worked Example 2.1, Step 1). Money in $ million a year.
A3: Quantity | B3: Value | C3: Source
A4: Meridian's revenue | B4: 4200 | C4: Chapter 1: $4.2 billion
A5: Industrial Systems' share of revenue | B5: 0.61 | C5: Chapter 1: 61 percent
A6: Industrial Systems' sales | B6: =B4*B5 -> 2562 | C6: $2.56 billion
A7: Shipped to independent dealers | B7: 1540 | C7: Worked Example 2.1: $1.54 billion
A8: Share of Industrial Systems' sales shipped to dealers | B8: =B7/B6 -> 0.6010929 | C8: about 60 percent
A9: Dealers' resale price above Meridian's | B9: 0.2 | C9: about 20 percent
A10: Dealers' sales to end customers | B10: =B7*(1+B9) -> 1848 | C10: $1,848 million (flow F5)
A11: Dealers' gross margin | B11: =B10-B7 -> 308 | C11: $308 million
A12: The feedback bench (AXIOM Lab 1.2, step 4): Meridian's efficiency under the turnaround's program
A13: Operational efficiency today (index, 0-100) | B13: 71 | C13: Table 3.1
A14: The turnaround's efficiency target | B14: 79 | C14: Online Appendix Table 1.B.1 (Chapter 1 model)
A15: The turnaround's speed of adjustment a year | B15: 0.6 | C15: Online Appendix Table 1.B.1
A16: Share of the gap closed a year, K = 1 - exp(-speed) | B16: =1-EXP(-B15) -> 0.45118836 | C16: 45 percent (Worked Example 5.1)
A17: Gap factor a year, 1 - K | B17: =1-B16 -> 0.54881164 | C17: 0.549 (Worked Example 5.1)
A19: Entity | B19: Inside boundary A | C19: Inside boundary B | D19: Inside your boundary
A20: Suppliers | B20: 0 | C20: 0 | D20: 0
A21: Meridian | B21: 1 | C21: 1 | D21: 1
A22: Dealer network | B22: 0 | C22: 1 | D22: 0
A23: End customers | B23: 0 | C23: 0 | D23: 0
A24: Capital markets | B24: 0 | C24: 0 | D24: 0
A25: Regulator | B25: 0 | C25: 0 | D25: 0
A26: 1 = inside the perimeter, 0 = outside. Boundary A: only Meridian; boundary B: Meridian and the dealer network. Draw your own in column D.
A28: Flow | B28: From | C28: To | D28: What flows | E28: Type | F28: Value a year | G28: Table 2.6: boundary A | H28: Table 2.6: boundary B
A29: F1 | B29: Suppliers | C29: Meridian | D29: components | E29: goods | G29: input | H29: input
A30: F2 | B30: Meridian | C30: Suppliers | D30: payments | E30: capital | G30: output | H30: output
A31: F3 | B31: Meridian | C31: Dealer network | D31: shipments | E31: goods | F31: =B7 -> 1540 | G31: output | H31: interior
A32: F4 | B32: Dealer network | C32: Meridian | D32: payments | E32: capital | F32: =B7 -> 1540 | G32: input | H32: interior
A33: F5 | B33: Dealer network | C33: End customers | D33: sales | E33: goods | F33: =B10 -> 1848 | G33: environmental | H33: output
A34: F6 | B34: End customers | C34: Dealer network | D34: payments | E34: capital | F34: =B10 -> 1848 | G34: environmental | H34: input
A35: F7 | B35: Dealer network | C35: Meridian | D35: market intelligence | E35: information | G35: input | H35: interior
A36: F8 | B36: Capital markets | C36: Meridian | D36: funding | E36: capital | G36: input | H36: input
A37: F9 | B37: Regulator | C37: Meridian | D37: rules | E37: information | G37: input | H37: input
A39: Types from Definition 2.3's list (capital, goods, services, information, personnel). The book values four flows; the others carry no value in Table 2.6.

Sheet Boundaries
A1: Draw boundary A, move the dealers inside (Worked Example 2.1, Steps 2-5; Theorem 2.2; AXIOM Lab 1.2, steps 1-2)
A2: Definition 2.3: a flow is interior if both ends lie inside the boundary, an input if it enters, an output if it leaves, environmental if neither end is inside. 1 = inside, 0 = outside.
A4: Flow | B4: From inside A | C4: To inside A | D4: Class under A | E4: Table 2.6 | F4: Match | G4: From inside B | H4: To inside B | I4: Class under B | J4: Table 2.6 | K4: Match | L4: Relabeled A to B | M4: From inside yours | N4: To inside yours | O4: Class under yours
A5: =Declarations!A29 -> F1 | B5: =INDEX(Flags_A,MATCH(Declarations!$B29,Entities,0)) -> 0 | C5: =INDEX(Flags_A,MATCH(Declarations!$C29,Entities,0)) -> 1 | D5: =IF(AND(B5=1,C5=1),"interior",IF(AND(B5=0,C5=1),"input",IF(AND(B5=1,C5=0),"output","environmental"))) -> input | E5: =Declarations!G29 -> input | F5: =IF(D5=E5,1,0) -> 1 | G5: =INDEX(Flags_B,MATCH(Declarations!$B29,Entities,0)) -> 0 | H5: =INDEX(Flags_B,MATCH(Declarations!$C29,Entities,0)) -> 1 | I5: =IF(AND(G5=1,H5=1),"interior",IF(AND(G5=0,H5=1),"input",IF(AND(G5=1,H5=0),"output","environmental"))) -> input | J5: =Declarations!H29 -> input | K5: =IF(I5=J5,1,0) -> 1 | L5: =IF(D5<>I5,1,0) -> 0 | M5: =INDEX(Flags_you,MATCH(Declarations!$B29,Entities,0)) -> 0 | N5: =INDEX(Flags_you,MATCH(Declarations!$C29,Entities,0)) -> 1 | O5: =IF(AND(M5=1,N5=1),"interior",IF(AND(M5=0,N5=1),"input",IF(AND(M5=1,N5=0),"output","environmental"))) -> input
A6: =Declarations!A30 -> F2 | B6: =INDEX(Flags_A,MATCH(Declarations!$B30,Entities,0)) -> 1 | C6: =INDEX(Flags_A,MATCH(Declarations!$C30,Entities,0)) -> 0 | D6: =IF(AND(B6=1,C6=1),"interior",IF(AND(B6=0,C6=1),"input",IF(AND(B6=1,C6=0),"output","environmental"))) -> output | E6: =Declarations!G30 -> output | F6: =IF(D6=E6,1,0) -> 1 | G6: =INDEX(Flags_B,MATCH(Declarations!$B30,Entities,0)) -> 1 | H6: =INDEX(Flags_B,MATCH(Declarations!$C30,Entities,0)) -> 0 | I6: =IF(AND(G6=1,H6=1),"interior",IF(AND(G6=0,H6=1),"input",IF(AND(G6=1,H6=0),"output","environmental"))) -> output | J6: =Declarations!H30 -> output | K6: =IF(I6=J6,1,0) -> 1 | L6: =IF(D6<>I6,1,0) -> 0 | M6: =INDEX(Flags_you,MATCH(Declarations!$B30,Entities,0)) -> 1 | N6: =INDEX(Flags_you,MATCH(Declarations!$C30,Entities,0)) -> 0 | O6: =IF(AND(M6=1,N6=1),"interior",IF(AND(M6=0,N6=1),"input",IF(AND(M6=1,N6=0),"output","environmental"))) -> output
A7: =Declarations!A31 -> F3 | B7: =INDEX(Flags_A,MATCH(Declarations!$B31,Entities,0)) -> 1 | C7: =INDEX(Flags_A,MATCH(Declarations!$C31,Entities,0)) -> 0 | D7: =IF(AND(B7=1,C7=1),"interior",IF(AND(B7=0,C7=1),"input",IF(AND(B7=1,C7=0),"output","environmental"))) -> output | E7: =Declarations!G31 -> output | F7: =IF(D7=E7,1,0) -> 1 | G7: =INDEX(Flags_B,MATCH(Declarations!$B31,Entities,0)) -> 1 | H7: =INDEX(Flags_B,MATCH(Declarations!$C31,Entities,0)) -> 1 | I7: =IF(AND(G7=1,H7=1),"interior",IF(AND(G7=0,H7=1),"input",IF(AND(G7=1,H7=0),"output","environmental"))) -> interior | J7: =Declarations!H31 -> interior | K7: =IF(I7=J7,1,0) -> 1 | L7: =IF(D7<>I7,1,0) -> 1 | M7: =INDEX(Flags_you,MATCH(Declarations!$B31,Entities,0)) -> 1 | N7: =INDEX(Flags_you,MATCH(Declarations!$C31,Entities,0)) -> 0 | O7: =IF(AND(M7=1,N7=1),"interior",IF(AND(M7=0,N7=1),"input",IF(AND(M7=1,N7=0),"output","environmental"))) -> output
A8: =Declarations!A32 -> F4 | B8: =INDEX(Flags_A,MATCH(Declarations!$B32,Entities,0)) -> 0 | C8: =INDEX(Flags_A,MATCH(Declarations!$C32,Entities,0)) -> 1 | D8: =IF(AND(B8=1,C8=1),"interior",IF(AND(B8=0,C8=1),"input",IF(AND(B8=1,C8=0),"output","environmental"))) -> input | E8: =Declarations!G32 -> input | F8: =IF(D8=E8,1,0) -> 1 | G8: =INDEX(Flags_B,MATCH(Declarations!$B32,Entities,0)) -> 1 | H8: =INDEX(Flags_B,MATCH(Declarations!$C32,Entities,0)) -> 1 | I8: =IF(AND(G8=1,H8=1),"interior",IF(AND(G8=0,H8=1),"input",IF(AND(G8=1,H8=0),"output","environmental"))) -> interior | J8: =Declarations!H32 -> interior | K8: =IF(I8=J8,1,0) -> 1 | L8: =IF(D8<>I8,1,0) -> 1 | M8: =INDEX(Flags_you,MATCH(Declarations!$B32,Entities,0)) -> 0 | N8: =INDEX(Flags_you,MATCH(Declarations!$C32,Entities,0)) -> 1 | O8: =IF(AND(M8=1,N8=1),"interior",IF(AND(M8=0,N8=1),"input",IF(AND(M8=1,N8=0),"output","environmental"))) -> input
A9: =Declarations!A33 -> F5 | B9: =INDEX(Flags_A,MATCH(Declarations!$B33,Entities,0)) -> 0 | C9: =INDEX(Flags_A,MATCH(Declarations!$C33,Entities,0)) -> 0 | D9: =IF(AND(B9=1,C9=1),"interior",IF(AND(B9=0,C9=1),"input",IF(AND(B9=1,C9=0),"output","environmental"))) -> environmental | E9: =Declarations!G33 -> environmental | F9: =IF(D9=E9,1,0) -> 1 | G9: =INDEX(Flags_B,MATCH(Declarations!$B33,Entities,0)) -> 1 | H9: =INDEX(Flags_B,MATCH(Declarations!$C33,Entities,0)) -> 0 | I9: =IF(AND(G9=1,H9=1),"interior",IF(AND(G9=0,H9=1),"input",IF(AND(G9=1,H9=0),"output","environmental"))) -> output | J9: =Declarations!H33 -> output | K9: =IF(I9=J9,1,0) -> 1 | L9: =IF(D9<>I9,1,0) -> 1 | M9: =INDEX(Flags_you,MATCH(Declarations!$B33,Entities,0)) -> 0 | N9: =INDEX(Flags_you,MATCH(Declarations!$C33,Entities,0)) -> 0 | O9: =IF(AND(M9=1,N9=1),"interior",IF(AND(M9=0,N9=1),"input",IF(AND(M9=1,N9=0),"output","environmental"))) -> environmental
A10: =Declarations!A34 -> F6 | B10: =INDEX(Flags_A,MATCH(Declarations!$B34,Entities,0)) -> 0 | C10: =INDEX(Flags_A,MATCH(Declarations!$C34,Entities,0)) -> 0 | D10: =IF(AND(B10=1,C10=1),"interior",IF(AND(B10=0,C10=1),"input",IF(AND(B10=1,C10=0),"output","environmental"))) -> environmental | E10: =Declarations!G34 -> environmental | F10: =IF(D10=E10,1,0) -> 1 | G10: =INDEX(Flags_B,MATCH(Declarations!$B34,Entities,0)) -> 0 | H10: =INDEX(Flags_B,MATCH(Declarations!$C34,Entities,0)) -> 1 | I10: =IF(AND(G10=1,H10=1),"interior",IF(AND(G10=0,H10=1),"input",IF(AND(G10=1,H10=0),"output","environmental"))) -> input | J10: =Declarations!H34 -> input | K10: =IF(I10=J10,1,0) -> 1 | L10: =IF(D10<>I10,1,0) -> 1 | M10: =INDEX(Flags_you,MATCH(Declarations!$B34,Entities,0)) -> 0 | N10: =INDEX(Flags_you,MATCH(Declarations!$C34,Entities,0)) -> 0 | O10: =IF(AND(M10=1,N10=1),"interior",IF(AND(M10=0,N10=1),"input",IF(AND(M10=1,N10=0),"output","environmental"))) -> environmental
A11: =Declarations!A35 -> F7 | B11: =INDEX(Flags_A,MATCH(Declarations!$B35,Entities,0)) -> 0 | C11: =INDEX(Flags_A,MATCH(Declarations!$C35,Entities,0)) -> 1 | D11: =IF(AND(B11=1,C11=1),"interior",IF(AND(B11=0,C11=1),"input",IF(AND(B11=1,C11=0),"output","environmental"))) -> input | E11: =Declarations!G35 -> input | F11: =IF(D11=E11,1,0) -> 1 | G11: =INDEX(Flags_B,MATCH(Declarations!$B35,Entities,0)) -> 1 | H11: =INDEX(Flags_B,MATCH(Declarations!$C35,Entities,0)) -> 1 | I11: =IF(AND(G11=1,H11=1),"interior",IF(AND(G11=0,H11=1),"input",IF(AND(G11=1,H11=0),"output","environmental"))) -> interior | J11: =Declarations!H35 -> interior | K11: =IF(I11=J11,1,0) -> 1 | L11: =IF(D11<>I11,1,0) -> 1 | M11: =INDEX(Flags_you,MATCH(Declarations!$B35,Entities,0)) -> 0 | N11: =INDEX(Flags_you,MATCH(Declarations!$C35,Entities,0)) -> 1 | O11: =IF(AND(M11=1,N11=1),"interior",IF(AND(M11=0,N11=1),"input",IF(AND(M11=1,N11=0),"output","environmental"))) -> input
A12: =Declarations!A36 -> F8 | B12: =INDEX(Flags_A,MATCH(Declarations!$B36,Entities,0)) -> 0 | C12: =INDEX(Flags_A,MATCH(Declarations!$C36,Entities,0)) -> 1 | D12: =IF(AND(B12=1,C12=1),"interior",IF(AND(B12=0,C12=1),"input",IF(AND(B12=1,C12=0),"output","environmental"))) -> input | E12: =Declarations!G36 -> input | F12: =IF(D12=E12,1,0) -> 1 | G12: =INDEX(Flags_B,MATCH(Declarations!$B36,Entities,0)) -> 0 | H12: =INDEX(Flags_B,MATCH(Declarations!$C36,Entities,0)) -> 1 | I12: =IF(AND(G12=1,H12=1),"interior",IF(AND(G12=0,H12=1),"input",IF(AND(G12=1,H12=0),"output","environmental"))) -> input | J12: =Declarations!H36 -> input | K12: =IF(I12=J12,1,0) -> 1 | L12: =IF(D12<>I12,1,0) -> 0 | M12: =INDEX(Flags_you,MATCH(Declarations!$B36,Entities,0)) -> 0 | N12: =INDEX(Flags_you,MATCH(Declarations!$C36,Entities,0)) -> 1 | O12: =IF(AND(M12=1,N12=1),"interior",IF(AND(M12=0,N12=1),"input",IF(AND(M12=1,N12=0),"output","environmental"))) -> input
A13: =Declarations!A37 -> F9 | B13: =INDEX(Flags_A,MATCH(Declarations!$B37,Entities,0)) -> 0 | C13: =INDEX(Flags_A,MATCH(Declarations!$C37,Entities,0)) -> 1 | D13: =IF(AND(B13=1,C13=1),"interior",IF(AND(B13=0,C13=1),"input",IF(AND(B13=1,C13=0),"output","environmental"))) -> input | E13: =Declarations!G37 -> input | F13: =IF(D13=E13,1,0) -> 1 | G13: =INDEX(Flags_B,MATCH(Declarations!$B37,Entities,0)) -> 0 | H13: =INDEX(Flags_B,MATCH(Declarations!$C37,Entities,0)) -> 1 | I13: =IF(AND(G13=1,H13=1),"interior",IF(AND(G13=0,H13=1),"input",IF(AND(G13=1,H13=0),"output","environmental"))) -> input | J13: =Declarations!H37 -> input | K13: =IF(I13=J13,1,0) -> 1 | L13: =IF(D13<>I13,1,0) -> 0 | M13: =INDEX(Flags_you,MATCH(Declarations!$B37,Entities,0)) -> 0 | N13: =INDEX(Flags_you,MATCH(Declarations!$C37,Entities,0)) -> 1 | O13: =IF(AND(M13=1,N13=1),"interior",IF(AND(M13=0,N13=1),"input",IF(AND(M13=1,N13=0),"output","environmental"))) -> input
A16: Class | B16: Boundary A | C16: Boundary B | D16: Your boundary
A17: interior | B17: =COUNTIF(D$5:D$13,$A17) -> 0 | C17: =COUNTIF(I$5:I$13,$A17) -> 3 | D17: =COUNTIF(O$5:O$13,$A17) -> 0
A18: input | B18: =COUNTIF(D$5:D$13,$A18) -> 5 | C18: =COUNTIF(I$5:I$13,$A18) -> 4 | D18: =COUNTIF(O$5:O$13,$A18) -> 5
A19: output | B19: =COUNTIF(D$5:D$13,$A19) -> 2 | C19: =COUNTIF(I$5:I$13,$A19) -> 2 | D19: =COUNTIF(O$5:O$13,$A19) -> 2
A20: environmental | B20: =COUNTIF(D$5:D$13,$A20) -> 2 | C20: =COUNTIF(I$5:I$13,$A20) -> 0 | D20: =COUNTIF(O$5:O$13,$A20) -> 2
A21: Total: the same nine flows | B21: =SUM(B17:B20) -> 9 | C21: =SUM(C17:C20) -> 9 | D21: =SUM(D17:D20) -> 9
A22: Rows that reproduce Table 2.6 (of 9) | B22: =SUM(F5:F13) -> 9 | C22: =SUM(K5:K13) -> 9
A23: Flows relabeled by moving the dealers inside | C23: =SUM(L5:L13) -> 5
A24: Goods output: valued goods flows leaving the boundary | B24: =SUMIFS(Declarations!$F$29:$F$37,D$5:D$13,"output",Declarations!$E$29:$E$37,"goods") -> 1540 | C24: =SUMIFS(Declarations!$F$29:$F$37,I$5:I$13,"output",Declarations!$E$29:$E$37,"goods") -> 1848 | D24: =SUMIFS(Declarations!$F$29:$F$37,O$5:O$13,"output",Declarations!$E$29:$E$37,"goods") -> 1540
A25: Difference from boundary A | C25: =C24-B24 -> 308 | D25: =D24-B24 -> 0
A26: Difference as a share of boundary A's goods output | C26: =C25/B24 -> 0.2
A27: The dealers' gross margin (Declarations) | C27: =Margin -> 308
A29: Valued flows by class ($ million a year) | B29: Boundary A | C29: Boundary B | D29: Your boundary
A30: interior | B30: =SUMIFS(Declarations!$F$29:$F$37,D$5:D$13,$A30) -> 0 | C30: =SUMIFS(Declarations!$F$29:$F$37,I$5:I$13,$A30) -> 3080 | D30: =SUMIFS(Declarations!$F$29:$F$37,O$5:O$13,$A30) -> 0
A31: input | B31: =SUMIFS(Declarations!$F$29:$F$37,D$5:D$13,$A31) -> 1540 | C31: =SUMIFS(Declarations!$F$29:$F$37,I$5:I$13,$A31) -> 1848 | D31: =SUMIFS(Declarations!$F$29:$F$37,O$5:O$13,$A31) -> 1540
A32: output | B32: =SUMIFS(Declarations!$F$29:$F$37,D$5:D$13,$A32) -> 1540 | C32: =SUMIFS(Declarations!$F$29:$F$37,I$5:I$13,$A32) -> 1848 | D32: =SUMIFS(Declarations!$F$29:$F$37,O$5:O$13,$A32) -> 1540
A33: environmental | B33: =SUMIFS(Declarations!$F$29:$F$37,D$5:D$13,$A33) -> 3696 | C33: =SUMIFS(Declarations!$F$29:$F$37,I$5:I$13,$A33) -> 0 | D33: =SUMIFS(Declarations!$F$29:$F$37,O$5:O$13,$A33) -> 3696
A34: Total: the money is the same money | B34: =SUM(B30:B33) -> 6776 | C34: =SUM(C30:C33) -> 6776 | D34: =SUM(D30:D33) -> 6776
A36: The $308 million gap is a boundary difference, not a performance difference: compare options under one declared boundary (Worked Example 2.1, Step 6). Drawing the dealers inside does not give Meridian control of their prices.

Sheet AllBoundaries
A1: Every boundary: the 64 ways to draw the line around six entities (Theorem 2.2; Corollary 2.B.2)
A2: Boundary n puts entity j inside when bit j of n is 1. Codes: I interior, N input, O output, E environmental. Rows 3-4: each flow's two ends, as entity numbers.
A3: from (entity no.) | H3: =MATCH(Declarations!B29,Entities,0) -> 1 | I3: =MATCH(Declarations!B30,Entities,0) -> 2 | J3: =MATCH(Declarations!B31,Entities,0) -> 2 | K3: =MATCH(Declarations!B32,Entities,0) -> 3 | L3: =MATCH(Declarations!B33,Entities,0) -> 3 | M3: =MATCH(Declarations!B34,Entities,0) -> 4 | N3: =MATCH(Declarations!B35,Entities,0) -> 3 | O3: =MATCH(Declarations!B36,Entities,0) -> 5 | P3: =MATCH(Declarations!B37,Entities,0) -> 6
A4: to (entity no.) | H4: =MATCH(Declarations!C29,Entities,0) -> 2 | I4: =MATCH(Declarations!C30,Entities,0) -> 1 | J4: =MATCH(Declarations!C31,Entities,0) -> 3 | K4: =MATCH(Declarations!C32,Entities,0) -> 2 | L4: =MATCH(Declarations!C33,Entities,0) -> 4 | M4: =MATCH(Declarations!C34,Entities,0) -> 3 | N4: =MATCH(Declarations!C35,Entities,0) -> 2 | O4: =MATCH(Declarations!C36,Entities,0) -> 2 | P4: =MATCH(Declarations!C37,Entities,0) -> 2
A5: n | B5: Suppliers | C5: Meridian | D5: Dealer network | E5: End customers | F5: Capital markets | G5: Regulator | H5: F1 | I5: F2 | J5: F3 | K5: F4 | L5: F5 | M5: F6 | N5: F7 | O5: F8 | P5: F9 | Q5: interior | R5: input | S5: output | T5: environmental | U5: total | V5: signature | W5: goods | X5: capital | Y5: information | AA5: Summary | AB5: Value
A6: 0 | B6: =MOD(INT($A6/2^0),2) -> 0 | C6: =MOD(INT($A6/2^1),2) -> 0 | D6: =MOD(INT($A6/2^2),2) -> 0 | E6: =MOD(INT($A6/2^3),2) -> 0 | F6: =MOD(INT($A6/2^4),2) -> 0 | G6: =MOD(INT($A6/2^5),2) -> 0 | H6: =CHOOSE(1+2*INDEX($B6:$G6,H$3)+INDEX($B6:$G6,H$4),"E","N","O","I") -> E | I6: =CHOOSE(1+2*INDEX($B6:$G6,I$3)+INDEX($B6:$G6,I$4),"E","N","O","I") -> E | J6: =CHOOSE(1+2*INDEX($B6:$G6,J$3)+INDEX($B6:$G6,J$4),"E","N","O","I") -> E | K6: =CHOOSE(1+2*INDEX($B6:$G6,K$3)+INDEX($B6:$G6,K$4),"E","N","O","I") -> E | L6: =CHOOSE(1+2*INDEX($B6:$G6,L$3)+INDEX($B6:$G6,L$4),"E","N","O","I") -> E | M6: =CHOOSE(1+2*INDEX($B6:$G6,M$3)+INDEX($B6:$G6,M$4),"E","N","O","I") -> E | N6: =CHOOSE(1+2*INDEX($B6:$G6,N$3)+INDEX($B6:$G6,N$4),"E","N","O","I") -> E | O6: =CHOOSE(1+2*INDEX($B6:$G6,O$3)+INDEX($B6:$G6,O$4),"E","N","O","I") -> E | P6: =CHOOSE(1+2*INDEX($B6:$G6,P$3)+INDEX($B6:$G6,P$4),"E","N","O","I") -> E | Q6: =COUNTIF($H6:$P6,"I") -> 0 | R6: =COUNTIF($H6:$P6,"N") -> 0 | S6: =COUNTIF($H6:$P6,"O") -> 0 | T6: =COUNTIF($H6:$P6,"E") -> 9 | U6: =SUM(Q6:T6) -> 9 | V6: =H6&I6&J6&K6&L6&M6&N6&O6&P6 -> EEEEEEEEE | W6: =IF(Declarations!$E$29="goods",H6,"")&IF(Declarations!$E$30="goods",I6,"")&IF(Declarations!$E$31="goods",J6,"")&IF(Declarations!$E$32="goods",K6,"")&IF(Declarations!$E$33="goods",L6,"")&IF(Declarations!$E$34="goods",M6,"")&IF(Declarations!$E$35="goods",N6,"")&IF(Declarations!$E$36="goods",O6,"")&IF(Declarations!$E$37="goods",P6,"") -> EEE | X6: =IF(Declarations!$E$29="capital",H6,"")&IF(Declarations!$E$30="capital",I6,"")&IF(Declarations!$E$31="capital",J6,"")&IF(Declarations!$E$32="capital",K6,"")&IF(Declarations!$E$33="capital",L6,"")&IF(Declarations!$E$34="capital",M6,"")&IF(Declarations!$E$35="capital",N6,"")&IF(Declarations!$E$36="capital",O6,"")&IF(Declarations!$E$37="capital",P6,"") -> EEEE | Y6: =IF(Declarations!$E$29="information",H6,"")&IF(Declarations!$E$30="information",I6,"")&IF(Declarations!$E$31="information",J6,"")&IF(Declarations!$E$32="information",K6,"")&IF(Declarations!$E$33="information",L6,"")&IF(Declarations!$E$34="information",M6,"")&IF(Declarations!$E$35="information",N6,"")&IF(Declarations!$E$36="information",O6,"")&IF(Declarations!$E$37="information",P6,"") -> EE | AA6: Boundaries | AB6: =COUNT(A6:A69) -> 64
A7: 1 | B7: =MOD(INT($A7/2^0),2) -> 1 | C7: =MOD(INT($A7/2^1),2) -> 0 | D7: =MOD(INT($A7/2^2),2) -> 0 | E7: =MOD(INT($A7/2^3),2) -> 0 | F7: =MOD(INT($A7/2^4),2) -> 0 | G7: =MOD(INT($A7/2^5),2) -> 0 | H7: =CHOOSE(1+2*INDEX($B7:$G7,H$3)+INDEX($B7:$G7,H$4),"E","N","O","I") -> O | I7: =CHOOSE(1+2*INDEX($B7:$G7,I$3)+INDEX($B7:$G7,I$4),"E","N","O","I") -> N | J7: =CHOOSE(1+2*INDEX($B7:$G7,J$3)+INDEX($B7:$G7,J$4),"E","N","O","I") -> E | K7: =CHOOSE(1+2*INDEX($B7:$G7,K$3)+INDEX($B7:$G7,K$4),"E","N","O","I") -> E | L7: =CHOOSE(1+2*INDEX($B7:$G7,L$3)+INDEX($B7:$G7,L$4),"E","N","O","I") -> E | M7: =CHOOSE(1+2*INDEX($B7:$G7,M$3)+INDEX($B7:$G7,M$4),"E","N","O","I") -> E | N7: =CHOOSE(1+2*INDEX($B7:$G7,N$3)+INDEX($B7:$G7,N$4),"E","N","O","I") -> E | O7: =CHOOSE(1+2*INDEX($B7:$G7,O$3)+INDEX($B7:$G7,O$4),"E","N","O","I") -> E | P7: =CHOOSE(1+2*INDEX($B7:$G7,P$3)+INDEX($B7:$G7,P$4),"E","N","O","I") -> E | Q7: =COUNTIF($H7:$P7,"I") -> 0 | R7: =COUNTIF($H7:$P7,"N") -> 1 | S7: =COUNTIF($H7:$P7,"O") -> 1 | T7: =COUNTIF($H7:$P7,"E") -> 7 | U7: =SUM(Q7:T7) -> 9 | V7: =H7&I7&J7&K7&L7&M7&N7&O7&P7 -> ONEEEEEEE | W7: =IF(Declarations!$E$29="goods",H7,"")&IF(Declarations!$E$30="goods",I7,"")&IF(Declarations!$E$31="goods",J7,"")&IF(Declarations!$E$32="goods",K7,"")&IF(Declarations!$E$33="goods",L7,"")&IF(Declarations!$E$34="goods",M7,"")&IF(Declarations!$E$35="goods",N7,"")&IF(Declarations!$E$36="goods",O7,"")&IF(Declarations!$E$37="goods",P7,"") -> OEE | X7: =IF(Declarations!$E$29="capital",H7,"")&IF(Declarations!$E$30="capital",I7,"")&IF(Declarations!$E$31="capital",J7,"")&IF(Declarations!$E$32="capital",K7,"")&IF(Declarations!$E$33="capital",L7,"")&IF(Declarations!$E$34="capital",M7,"")&IF(Declarations!$E$35="capital",N7,"")&IF(Declarations!$E$36="capital",O7,"")&IF(Declarations!$E$37="capital",P7,"") -> NEEE | Y7: =IF(Declarations!$E$29="information",H7,"")&IF(Declarations!$E$30="information",I7,"")&IF(Declarations!$E$31="information",J7,"")&IF(Declarations!$E$32="information",K7,"")&IF(Declarations!$E$33="information",L7,"")&IF(Declarations!$E$34="information",M7,"")&IF(Declarations!$E$35="information",N7,"")&IF(Declarations!$E$36="information",O7,"")&IF(Declarations!$E$37="information",P7,"") -> EE | AA7: Flows under every boundary: fewest | AB7: =MIN(U6:U69) -> 9
A8: 2 | B8: =MOD(INT($A8/2^0),2) -> 0 | C8: =MOD(INT($A8/2^1),2) -> 1 | D8: =MOD(INT($A8/2^2),2) -> 0 | E8: =MOD(INT($A8/2^3),2) -> 0 | F8: =MOD(INT($A8/2^4),2) -> 0 | G8: =MOD(INT($A8/2^5),2) -> 0 | H8: =CHOOSE(1+2*INDEX($B8:$G8,H$3)+INDEX($B8:$G8,H$4),"E","N","O","I") -> N | I8: =CHOOSE(1+2*INDEX($B8:$G8,I$3)+INDEX($B8:$G8,I$4),"E","N","O","I") -> O | J8: =CHOOSE(1+2*INDEX($B8:$G8,J$3)+INDEX($B8:$G8,J$4),"E","N","O","I") -> O | K8: =CHOOSE(1+2*INDEX($B8:$G8,K$3)+INDEX($B8:$G8,K$4),"E","N","O","I") -> N | L8: =CHOOSE(1+2*INDEX($B8:$G8,L$3)+INDEX($B8:$G8,L$4),"E","N","O","I") -> E | M8: =CHOOSE(1+2*INDEX($B8:$G8,M$3)+INDEX($B8:$G8,M$4),"E","N","O","I") -> E | N8: =CHOOSE(1+2*INDEX($B8:$G8,N$3)+INDEX($B8:$G8,N$4),"E","N","O","I") -> N | O8: =CHOOSE(1+2*INDEX($B8:$G8,O$3)+INDEX($B8:$G8,O$4),"E","N","O","I") -> N | P8: =CHOOSE(1+2*INDEX($B8:$G8,P$3)+INDEX($B8:$G8,P$4),"E","N","O","I") -> N | Q8: =COUNTIF($H8:$P8,"I") -> 0 | R8: =COUNTIF($H8:$P8,"N") -> 5 | S8: =COUNTIF($H8:$P8,"O") -> 2 | T8: =COUNTIF($H8:$P8,"E") -> 2 | U8: =SUM(Q8:T8) -> 9 | V8: =H8&I8&J8&K8&L8&M8&N8&O8&P8 -> NOONEENNN | W8: =IF(Declarations!$E$29="goods",H8,"")&IF(Declarations!$E$30="goods",I8,"")&IF(Declarations!$E$31="goods",J8,"")&IF(Declarations!$E$32="goods",K8,"")&IF(Declarations!$E$33="goods",L8,"")&IF(Declarations!$E$34="goods",M8,"")&IF(Declarations!$E$35="goods",N8,"")&IF(Declarations!$E$36="goods",O8,"")&IF(Declarations!$E$37="goods",P8,"") -> NOE | X8: =IF(Declarations!$E$29="capital",H8,"")&IF(Declarations!$E$30="capital",I8,"")&IF(Declarations!$E$31="capital",J8,"")&IF(Declarations!$E$32="capital",K8,"")&IF(Declarations!$E$33="capital",L8,"")&IF(Declarations!$E$34="capital",M8,"")&IF(Declarations!$E$35="capital",N8,"")&IF(Declarations!$E$36="capital",O8,"")&IF(Declarations!$E$37="capital",P8,"") -> ONEN | Y8: =IF(Declarations!$E$29="information",H8,"")&IF(Declarations!$E$30="information",I8,"")&IF(Declarations!$E$31="information",J8,"")&IF(Declarations!$E$32="information",K8,"")&IF(Declarations!$E$33="information",L8,"")&IF(Declarations!$E$34="information",M8,"")&IF(Declarations!$E$35="information",N8,"")&IF(Declarations!$E$36="information",O8,"")&IF(Declarations!$E$37="information",P8,"") -> NN | AA8: Flows under every boundary: most | AB8: =MAX(U6:U69) -> 9
A9: 3 | B9: =MOD(INT($A9/2^0),2) -> 1 | C9: =MOD(INT($A9/2^1),2) -> 1 | D9: =MOD(INT($A9/2^2),2) -> 0 | E9: =MOD(INT($A9/2^3),2) -> 0 | F9: =MOD(INT($A9/2^4),2) -> 0 | G9: =MOD(INT($A9/2^5),2) -> 0 | H9: =CHOOSE(1+2*INDEX($B9:$G9,H$3)+INDEX($B9:$G9,H$4),"E","N","O","I") -> I | I9: =CHOOSE(1+2*INDEX($B9:$G9,I$3)+INDEX($B9:$G9,I$4),"E","N","O","I") -> I | J9: =CHOOSE(1+2*INDEX($B9:$G9,J$3)+INDEX($B9:$G9,J$4),"E","N","O","I") -> O | K9: =CHOOSE(1+2*INDEX($B9:$G9,K$3)+INDEX($B9:$G9,K$4),"E","N","O","I") -> N | L9: =CHOOSE(1+2*INDEX($B9:$G9,L$3)+INDEX($B9:$G9,L$4),"E","N","O","I") -> E | M9: =CHOOSE(1+2*INDEX($B9:$G9,M$3)+INDEX($B9:$G9,M$4),"E","N","O","I") -> E | N9: =CHOOSE(1+2*INDEX($B9:$G9,N$3)+INDEX($B9:$G9,N$4),"E","N","O","I") -> N | O9: =CHOOSE(1+2*INDEX($B9:$G9,O$3)+INDEX($B9:$G9,O$4),"E","N","O","I") -> N | P9: =CHOOSE(1+2*INDEX($B9:$G9,P$3)+INDEX($B9:$G9,P$4),"E","N","O","I") -> N | Q9: =COUNTIF($H9:$P9,"I") -> 2 | R9: =COUNTIF($H9:$P9,"N") -> 4 | S9: =COUNTIF($H9:$P9,"O") -> 1 | T9: =COUNTIF($H9:$P9,"E") -> 2 | U9: =SUM(Q9:T9) -> 9 | V9: =H9&I9&J9&K9&L9&M9&N9&O9&P9 -> IIONEENNN | W9: =IF(Declarations!$E$29="goods",H9,"")&IF(Declarations!$E$30="goods",I9,"")&IF(Declarations!$E$31="goods",J9,"")&IF(Declarations!$E$32="goods",K9,"")&IF(Declarations!$E$33="goods",L9,"")&IF(Declarations!$E$34="goods",M9,"")&IF(Declarations!$E$35="goods",N9,"")&IF(Declarations!$E$36="goods",O9,"")&IF(Declarations!$E$37="goods",P9,"") -> IOE | X9: =IF(Declarations!$E$29="capital",H9,"")&IF(Declarations!$E$30="capital",I9,"")&IF(Declarations!$E$31="capital",J9,"")&IF(Declarations!$E$32="capital",K9,"")&IF(Declarations!$E$33="capital",L9,"")&IF(Declarations!$E$34="capital",M9,"")&IF(Declarations!$E$35="capital",N9,"")&IF(Declarations!$E$36="capital",O9,"")&IF(Declarations!$E$37="capital",P9,"") -> INEN | Y9: =IF(Declarations!$E$29="information",H9,"")&IF(Declarations!$E$30="information",I9,"")&IF(Declarations!$E$31="information",J9,"")&IF(Declarations!$E$32="information",K9,"")&IF(Declarations!$E$33="information",L9,"")&IF(Declarations!$E$34="information",M9,"")&IF(Declarations!$E$35="information",N9,"")&IF(Declarations!$E$36="information",O9,"")&IF(Declarations!$E$37="information",P9,"") -> NN | AA9: Flows not in exactly one class, all boundaries (Theorem 2.2(i)) | AB9: =SUMPRODUCT(ABS(U6:U69-9)) -> 0
A10: 4 | B10: =MOD(INT($A10/2^0),2) -> 0 | C10: =MOD(INT($A10/2^1),2) -> 0 | D10: =MOD(INT($A10/2^2),2) -> 1 | E10: =MOD(INT($A10/2^3),2) -> 0 | F10: =MOD(INT($A10/2^4),2) -> 0 | G10: =MOD(INT($A10/2^5),2) -> 0 | H10: =CHOOSE(1+2*INDEX($B10:$G10,H$3)+INDEX($B10:$G10,H$4),"E","N","O","I") -> E | I10: =CHOOSE(1+2*INDEX($B10:$G10,I$3)+INDEX($B10:$G10,I$4),"E","N","O","I") -> E | J10: =CHOOSE(1+2*INDEX($B10:$G10,J$3)+INDEX($B10:$G10,J$4),"E","N","O","I") -> N | K10: =CHOOSE(1+2*INDEX($B10:$G10,K$3)+INDEX($B10:$G10,K$4),"E","N","O","I") -> O | L10: =CHOOSE(1+2*INDEX($B10:$G10,L$3)+INDEX($B10:$G10,L$4),"E","N","O","I") -> O | M10: =CHOOSE(1+2*INDEX($B10:$G10,M$3)+INDEX($B10:$G10,M$4),"E","N","O","I") -> N | N10: =CHOOSE(1+2*INDEX($B10:$G10,N$3)+INDEX($B10:$G10,N$4),"E","N","O","I") -> O | O10: =CHOOSE(1+2*INDEX($B10:$G10,O$3)+INDEX($B10:$G10,O$4),"E","N","O","I") -> E | P10: =CHOOSE(1+2*INDEX($B10:$G10,P$3)+INDEX($B10:$G10,P$4),"E","N","O","I") -> E | Q10: =COUNTIF($H10:$P10,"I") -> 0 | R10: =COUNTIF($H10:$P10,"N") -> 2 | S10: =COUNTIF($H10:$P10,"O") -> 3 | T10: =COUNTIF($H10:$P10,"E") -> 4 | U10: =SUM(Q10:T10) -> 9 | V10: =H10&I10&J10&K10&L10&M10&N10&O10&P10 -> EENOONOEE | W10: =IF(Declarations!$E$29="goods",H10,"")&IF(Declarations!$E$30="goods",I10,"")&IF(Declarations!$E$31="goods",J10,"")&IF(Declarations!$E$32="goods",K10,"")&IF(Declarations!$E$33="goods",L10,"")&IF(Declarations!$E$34="goods",M10,"")&IF(Declarations!$E$35="goods",N10,"")&IF(Declarations!$E$36="goods",O10,"")&IF(Declarations!$E$37="goods",P10,"") -> ENO | X10: =IF(Declarations!$E$29="capital",H10,"")&IF(Declarations!$E$30="capital",I10,"")&IF(Declarations!$E$31="capital",J10,"")&IF(Declarations!$E$32="capital",K10,"")&IF(Declarations!$E$33="capital",L10,"")&IF(Declarations!$E$34="capital",M10,"")&IF(Declarations!$E$35="capital",N10,"")&IF(Declarations!$E$36="capital",O10,"")&IF(Declarations!$E$37="capital",P10,"") -> EONE | Y10: =IF(Declarations!$E$29="information",H10,"")&IF(Declarations!$E$30="information",I10,"")&IF(Declarations!$E$31="information",J10,"")&IF(Declarations!$E$32="information",K10,"")&IF(Declarations!$E$33="information",L10,"")&IF(Declarations!$E$34="information",M10,"")&IF(Declarations!$E$35="information",N10,"")&IF(Declarations!$E$36="information",O10,"")&IF(Declarations!$E$37="information",P10,"") -> OE | AA10: Distinct classifications of the nine flows (Theorem 2.2(iii)) | AB10: =SUMPRODUCT(1/COUNTIF(V6:V69,V6:V69)) -> 64
A11: 5 | B11: =MOD(INT($A11/2^0),2) -> 1 | C11: =MOD(INT($A11/2^1),2) -> 0 | D11: =MOD(INT($A11/2^2),2) -> 1 | E11: =MOD(INT($A11/2^3),2) -> 0 | F11: =MOD(INT($A11/2^4),2) -> 0 | G11: =MOD(INT($A11/2^5),2) -> 0 | H11: =CHOOSE(1+2*INDEX($B11:$G11,H$3)+INDEX($B11:$G11,H$4),"E","N","O","I") -> O | I11: =CHOOSE(1+2*INDEX($B11:$G11,I$3)+INDEX($B11:$G11,I$4),"E","N","O","I") -> N | J11: =CHOOSE(1+2*INDEX($B11:$G11,J$3)+INDEX($B11:$G11,J$4),"E","N","O","I") -> N | K11: =CHOOSE(1+2*INDEX($B11:$G11,K$3)+INDEX($B11:$G11,K$4),"E","N","O","I") -> O | L11: =CHOOSE(1+2*INDEX($B11:$G11,L$3)+INDEX($B11:$G11,L$4),"E","N","O","I") -> O | M11: =CHOOSE(1+2*INDEX($B11:$G11,M$3)+INDEX($B11:$G11,M$4),"E","N","O","I") -> N | N11: =CHOOSE(1+2*INDEX($B11:$G11,N$3)+INDEX($B11:$G11,N$4),"E","N","O","I") -> O | O11: =CHOOSE(1+2*INDEX($B11:$G11,O$3)+INDEX($B11:$G11,O$4),"E","N","O","I") -> E | P11: =CHOOSE(1+2*INDEX($B11:$G11,P$3)+INDEX($B11:$G11,P$4),"E","N","O","I") -> E | Q11: =COUNTIF($H11:$P11,"I") -> 0 | R11: =COUNTIF($H11:$P11,"N") -> 3 | S11: =COUNTIF($H11:$P11,"O") -> 4 | T11: =COUNTIF($H11:$P11,"E") -> 2 | U11: =SUM(Q11:T11) -> 9 | V11: =H11&I11&J11&K11&L11&M11&N11&O11&P11 -> ONNOONOEE | W11: =IF(Declarations!$E$29="goods",H11,"")&IF(Declarations!$E$30="goods",I11,"")&IF(Declarations!$E$31="goods",J11,"")&IF(Declarations!$E$32="goods",K11,"")&IF(Declarations!$E$33="goods",L11,"")&IF(Declarations!$E$34="goods",M11,"")&IF(Declarations!$E$35="goods",N11,"")&IF(Declarations!$E$36="goods",O11,"")&IF(Declarations!$E$37="goods",P11,"") -> ONO | X11: =IF(Declarations!$E$29="capital",H11,"")&IF(Declarations!$E$30="capital",I11,"")&IF(Declarations!$E$31="capital",J11,"")&IF(Declarations!$E$32="capital",K11,"")&IF(Declarations!$E$33="capital",L11,"")&IF(Declarations!$E$34="capital",M11,"")&IF(Declarations!$E$35="capital",N11,"")&IF(Declarations!$E$36="capital",O11,"")&IF(Declarations!$E$37="capital",P11,"") -> NONE | Y11: =IF(Declarations!$E$29="information",H11,"")&IF(Declarations!$E$30="information",I11,"")&IF(Declarations!$E$31="information",J11,"")&IF(Declarations!$E$32="information",K11,"")&IF(Declarations!$E$33="information",L11,"")&IF(Declarations!$E$34="information",M11,"")&IF(Declarations!$E$35="information",N11,"")&IF(Declarations!$E$36="information",O11,"")&IF(Declarations!$E$37="information",P11,"") -> OE | AA11: Distinct classifications of the goods flows | AB11: =SUMPRODUCT(1/COUNTIF(W6:W69,W6:W69)) -> 16
A12: 6 | B12: =MOD(INT($A12/2^0),2) -> 0 | C12: =MOD(INT($A12/2^1),2) -> 1 | D12: =MOD(INT($A12/2^2),2) -> 1 | E12: =MOD(INT($A12/2^3),2) -> 0 | F12: =MOD(INT($A12/2^4),2) -> 0 | G12: =MOD(INT($A12/2^5),2) -> 0 | H12: =CHOOSE(1+2*INDEX($B12:$G12,H$3)+INDEX($B12:$G12,H$4),"E","N","O","I") -> N | I12: =CHOOSE(1+2*INDEX($B12:$G12,I$3)+INDEX($B12:$G12,I$4),"E","N","O","I") -> O | J12: =CHOOSE(1+2*INDEX($B12:$G12,J$3)+INDEX($B12:$G12,J$4),"E","N","O","I") -> I | K12: =CHOOSE(1+2*INDEX($B12:$G12,K$3)+INDEX($B12:$G12,K$4),"E","N","O","I") -> I | L12: =CHOOSE(1+2*INDEX($B12:$G12,L$3)+INDEX($B12:$G12,L$4),"E","N","O","I") -> O | M12: =CHOOSE(1+2*INDEX($B12:$G12,M$3)+INDEX($B12:$G12,M$4),"E","N","O","I") -> N | N12: =CHOOSE(1+2*INDEX($B12:$G12,N$3)+INDEX($B12:$G12,N$4),"E","N","O","I") -> I | O12: =CHOOSE(1+2*INDEX($B12:$G12,O$3)+INDEX($B12:$G12,O$4),"E","N","O","I") -> N | P12: =CHOOSE(1+2*INDEX($B12:$G12,P$3)+INDEX($B12:$G12,P$4),"E","N","O","I") -> N | Q12: =COUNTIF($H12:$P12,"I") -> 3 | R12: =COUNTIF($H12:$P12,"N") -> 4 | S12: =COUNTIF($H12:$P12,"O") -> 2 | T12: =COUNTIF($H12:$P12,"E") -> 0 | U12: =SUM(Q12:T12) -> 9 | V12: =H12&I12&J12&K12&L12&M12&N12&O12&P12 -> NOIIONINN | W12: =IF(Declarations!$E$29="goods",H12,"")&IF(Declarations!$E$30="goods",I12,"")&IF(Declarations!$E$31="goods",J12,"")&IF(Declarations!$E$32="goods",K12,"")&IF(Declarations!$E$33="goods",L12,"")&IF(Declarations!$E$34="goods",M12,"")&IF(Declarations!$E$35="goods",N12,"")&IF(Declarations!$E$36="goods",O12,"")&IF(Declarations!$E$37="goods",P12,"") -> NIO | X12: =IF(Declarations!$E$29="capital",H12,"")&IF(Declarations!$E$30="capital",I12,"")&IF(Declarations!$E$31="capital",J12,"")&IF(Declarations!$E$32="capital",K12,"")&IF(Declarations!$E$33="capital",L12,"")&IF(Declarations!$E$34="capital",M12,"")&IF(Declarations!$E$35="capital",N12,"")&IF(Declarations!$E$36="capital",O12,"")&IF(Declarations!$E$37="capital",P12,"") -> OINN | Y12: =IF(Declarations!$E$29="information",H12,"")&IF(Declarations!$E$30="information",I12,"")&IF(Declarations!$E$31="information",J12,"")&IF(Declarations!$E$32="information",K12,"")&IF(Declarations!$E$33="information",L12,"")&IF(Declarations!$E$34="information",M12,"")&IF(Declarations!$E$35="information",N12,"")&IF(Declarations!$E$36="information",O12,"")&IF(Declarations!$E$37="information",P12,"") -> IN | AA12: Distinct classifications of the capital flows | AB12: =SUMPRODUCT(1/COUNTIF(X6:X69,X6:X69)) -> 32
A13: 7 | B13: =MOD(INT($A13/2^0),2) -> 1 | C13: =MOD(INT($A13/2^1),2) -> 1 | D13: =MOD(INT($A13/2^2),2) -> 1 | E13: =MOD(INT($A13/2^3),2) -> 0 | F13: =MOD(INT($A13/2^4),2) -> 0 | G13: =MOD(INT($A13/2^5),2) -> 0 | H13: =CHOOSE(1+2*INDEX($B13:$G13,H$3)+INDEX($B13:$G13,H$4),"E","N","O","I") -> I | I13: =CHOOSE(1+2*INDEX($B13:$G13,I$3)+INDEX($B13:$G13,I$4),"E","N","O","I") -> I | J13: =CHOOSE(1+2*INDEX($B13:$G13,J$3)+INDEX($B13:$G13,J$4),"E","N","O","I") -> I | K13: =CHOOSE(1+2*INDEX($B13:$G13,K$3)+INDEX($B13:$G13,K$4),"E","N","O","I") -> I | L13: =CHOOSE(1+2*INDEX($B13:$G13,L$3)+INDEX($B13:$G13,L$4),"E","N","O","I") -> O | M13: =CHOOSE(1+2*INDEX($B13:$G13,M$3)+INDEX($B13:$G13,M$4),"E","N","O","I") -> N | N13: =CHOOSE(1+2*INDEX($B13:$G13,N$3)+INDEX($B13:$G13,N$4),"E","N","O","I") -> I | O13: =CHOOSE(1+2*INDEX($B13:$G13,O$3)+INDEX($B13:$G13,O$4),"E","N","O","I") -> N | P13: =CHOOSE(1+2*INDEX($B13:$G13,P$3)+INDEX($B13:$G13,P$4),"E","N","O","I") -> N | Q13: =COUNTIF($H13:$P13,"I") -> 5 | R13: =COUNTIF($H13:$P13,"N") -> 3 | S13: =COUNTIF($H13:$P13,"O") -> 1 | T13: =COUNTIF($H13:$P13,"E") -> 0 | U13: =SUM(Q13:T13) -> 9 | V13: =H13&I13&J13&K13&L13&M13&N13&O13&P13 -> IIIIONINN | W13: =IF(Declarations!$E$29="goods",H13,"")&IF(Declarations!$E$30="goods",I13,"")&IF(Declarations!$E$31="goods",J13,"")&IF(Declarations!$E$32="goods",K13,"")&IF(Declarations!$E$33="goods",L13,"")&IF(Declarations!$E$34="goods",M13,"")&IF(Declarations!$E$35="goods",N13,"")&IF(Declarations!$E$36="goods",O13,"")&IF(Declarations!$E$37="goods",P13,"") -> IIO | X13: =IF(Declarations!$E$29="capital",H13,"")&IF(Declarations!$E$30="capital",I13,"")&IF(Declarations!$E$31="capital",J13,"")&IF(Declarations!$E$32="capital",K13,"")&IF(Declarations!$E$33="capital",L13,"")&IF(Declarations!$E$34="capital",M13,"")&IF(Declarations!$E$35="capital",N13,"")&IF(Declarations!$E$36="capital",O13,"")&IF(Declarations!$E$37="capital",P13,"") -> IINN | Y13: =IF(Declarations!$E$29="information",H13,"")&IF(Declarations!$E$30="information",I13,"")&IF(Declarations!$E$31="information",J13,"")&IF(Declarations!$E$32="information",K13,"")&IF(Declarations!$E$33="information",L13,"")&IF(Declarations!$E$34="information",M13,"")&IF(Declarations!$E$35="information",N13,"")&IF(Declarations!$E$36="information",O13,"")&IF(Declarations!$E$37="information",P13,"") -> IN | AA13: Distinct classifications of the information flows | AB13: =SUMPRODUCT(1/COUNTIF(Y6:Y69,Y6:Y69)) -> 8
A14: 8 | B14: =MOD(INT($A14/2^0),2) -> 0 | C14: =MOD(INT($A14/2^1),2) -> 0 | D14: =MOD(INT($A14/2^2),2) -> 0 | E14: =MOD(INT($A14/2^3),2) -> 1 | F14: =MOD(INT($A14/2^4),2) -> 0 | G14: =MOD(INT($A14/2^5),2) -> 0 | H14: =CHOOSE(1+2*INDEX($B14:$G14,H$3)+INDEX($B14:$G14,H$4),"E","N","O","I") -> E | I14: =CHOOSE(1+2*INDEX($B14:$G14,I$3)+INDEX($B14:$G14,I$4),"E","N","O","I") -> E | J14: =CHOOSE(1+2*INDEX($B14:$G14,J$3)+INDEX($B14:$G14,J$4),"E","N","O","I") -> E | K14: =CHOOSE(1+2*INDEX($B14:$G14,K$3)+INDEX($B14:$G14,K$4),"E","N","O","I") -> E | L14: =CHOOSE(1+2*INDEX($B14:$G14,L$3)+INDEX($B14:$G14,L$4),"E","N","O","I") -> N | M14: =CHOOSE(1+2*INDEX($B14:$G14,M$3)+INDEX($B14:$G14,M$4),"E","N","O","I") -> O | N14: =CHOOSE(1+2*INDEX($B14:$G14,N$3)+INDEX($B14:$G14,N$4),"E","N","O","I") -> E | O14: =CHOOSE(1+2*INDEX($B14:$G14,O$3)+INDEX($B14:$G14,O$4),"E","N","O","I") -> E | P14: =CHOOSE(1+2*INDEX($B14:$G14,P$3)+INDEX($B14:$G14,P$4),"E","N","O","I") -> E | Q14: =COUNTIF($H14:$P14,"I") -> 0 | R14: =COUNTIF($H14:$P14,"N") -> 1 | S14: =COUNTIF($H14:$P14,"O") -> 1 | T14: =COUNTIF($H14:$P14,"E") -> 7 | U14: =SUM(Q14:T14) -> 9 | V14: =H14&I14&J14&K14&L14&M14&N14&O14&P14 -> EEEENOEEE | W14: =IF(Declarations!$E$29="goods",H14,"")&IF(Declarations!$E$30="goods",I14,"")&IF(Declarations!$E$31="goods",J14,"")&IF(Declarations!$E$32="goods",K14,"")&IF(Declarations!$E$33="goods",L14,"")&IF(Declarations!$E$34="goods",M14,"")&IF(Declarations!$E$35="goods",N14,"")&IF(Declarations!$E$36="goods",O14,"")&IF(Declarations!$E$37="goods",P14,"") -> EEN | X14: =IF(Declarations!$E$29="capital",H14,"")&IF(Declarations!$E$30="capital",I14,"")&IF(Declarations!$E$31="capital",J14,"")&IF(Declarations!$E$32="capital",K14,"")&IF(Declarations!$E$33="capital",L14,"")&IF(Declarations!$E$34="capital",M14,"")&IF(Declarations!$E$35="capital",N14,"")&IF(Declarations!$E$36="capital",O14,"")&IF(Declarations!$E$37="capital",P14,"") -> EEOE | Y14: =IF(Declarations!$E$29="information",H14,"")&IF(Declarations!$E$30="information",I14,"")&IF(Declarations!$E$31="information",J14,"")&IF(Declarations!$E$32="information",K14,"")&IF(Declarations!$E$33="information",L14,"")&IF(Declarations!$E$34="information",M14,"")&IF(Declarations!$E$35="information",N14,"")&IF(Declarations!$E$36="information",O14,"")&IF(Declarations!$E$37="information",P14,"") -> EE
A15: 9 | B15: =MOD(INT($A15/2^0),2) -> 1 | C15: =MOD(INT($A15/2^1),2) -> 0 | D15: =MOD(INT($A15/2^2),2) -> 0 | E15: =MOD(INT($A15/2^3),2) -> 1 | F15: =MOD(INT($A15/2^4),2) -> 0 | G15: =MOD(INT($A15/2^5),2) -> 0 | H15: =CHOOSE(1+2*INDEX($B15:$G15,H$3)+INDEX($B15:$G15,H$4),"E","N","O","I") -> O | I15: =CHOOSE(1+2*INDEX($B15:$G15,I$3)+INDEX($B15:$G15,I$4),"E","N","O","I") -> N | J15: =CHOOSE(1+2*INDEX($B15:$G15,J$3)+INDEX($B15:$G15,J$4),"E","N","O","I") -> E | K15: =CHOOSE(1+2*INDEX($B15:$G15,K$3)+INDEX($B15:$G15,K$4),"E","N","O","I") -> E | L15: =CHOOSE(1+2*INDEX($B15:$G15,L$3)+INDEX($B15:$G15,L$4),"E","N","O","I") -> N | M15: =CHOOSE(1+2*INDEX($B15:$G15,M$3)+INDEX($B15:$G15,M$4),"E","N","O","I") -> O | N15: =CHOOSE(1+2*INDEX($B15:$G15,N$3)+INDEX($B15:$G15,N$4),"E","N","O","I") -> E | O15: =CHOOSE(1+2*INDEX($B15:$G15,O$3)+INDEX($B15:$G15,O$4),"E","N","O","I") -> E | P15: =CHOOSE(1+2*INDEX($B15:$G15,P$3)+INDEX($B15:$G15,P$4),"E","N","O","I") -> E | Q15: =COUNTIF($H15:$P15,"I") -> 0 | R15: =COUNTIF($H15:$P15,"N") -> 2 | S15: =COUNTIF($H15:$P15,"O") -> 2 | T15: =COUNTIF($H15:$P15,"E") -> 5 | U15: =SUM(Q15:T15) -> 9 | V15: =H15&I15&J15&K15&L15&M15&N15&O15&P15 -> ONEENOEEE | W15: =IF(Declarations!$E$29="goods",H15,"")&IF(Declarations!$E$30="goods",I15,"")&IF(Declarations!$E$31="goods",J15,"")&IF(Declarations!$E$32="goods",K15,"")&IF(Declarations!$E$33="goods",L15,"")&IF(Declarations!$E$34="goods",M15,"")&IF(Declarations!$E$35="goods",N15,"")&IF(Declarations!$E$36="goods",O15,"")&IF(Declarations!$E$37="goods",P15,"") -> OEN | X15: =IF(Declarations!$E$29="capital",H15,"")&IF(Declarations!$E$30="capital",I15,"")&IF(Declarations!$E$31="capital",J15,"")&IF(Declarations!$E$32="capital",K15,"")&IF(Declarations!$E$33="capital",L15,"")&IF(Declarations!$E$34="capital",M15,"")&IF(Declarations!$E$35="capital",N15,"")&IF(Declarations!$E$36="capital",O15,"")&IF(Declarations!$E$37="capital",P15,"") -> NEOE | Y15: =IF(Declarations!$E$29="information",H15,"")&IF(Declarations!$E$30="information",I15,"")&IF(Declarations!$E$31="information",J15,"")&IF(Declarations!$E$32="information",K15,"")&IF(Declarations!$E$33="information",L15,"")&IF(Declarations!$E$34="information",M15,"")&IF(Declarations!$E$35="information",N15,"")&IF(Declarations!$E$36="information",O15,"")&IF(Declarations!$E$37="information",P15,"") -> EE | AA15: Move one entity, starting from boundary A | AB15: Flows relabeled
A16: 10 | B16: =MOD(INT($A16/2^0),2) -> 0 | C16: =MOD(INT($A16/2^1),2) -> 1 | D16: =MOD(INT($A16/2^2),2) -> 0 | E16: =MOD(INT($A16/2^3),2) -> 1 | F16: =MOD(INT($A16/2^4),2) -> 0 | G16: =MOD(INT($A16/2^5),2) -> 0 | H16: =CHOOSE(1+2*INDEX($B16:$G16,H$3)+INDEX($B16:$G16,H$4),"E","N","O","I") -> N | I16: =CHOOSE(1+2*INDEX($B16:$G16,I$3)+INDEX($B16:$G16,I$4),"E","N","O","I") -> O | J16: =CHOOSE(1+2*INDEX($B16:$G16,J$3)+INDEX($B16:$G16,J$4),"E","N","O","I") -> O | K16: =CHOOSE(1+2*INDEX($B16:$G16,K$3)+INDEX($B16:$G16,K$4),"E","N","O","I") -> N | L16: =CHOOSE(1+2*INDEX($B16:$G16,L$3)+INDEX($B16:$G16,L$4),"E","N","O","I") -> N | M16: =CHOOSE(1+2*INDEX($B16:$G16,M$3)+INDEX($B16:$G16,M$4),"E","N","O","I") -> O | N16: =CHOOSE(1+2*INDEX($B16:$G16,N$3)+INDEX($B16:$G16,N$4),"E","N","O","I") -> N | O16: =CHOOSE(1+2*INDEX($B16:$G16,O$3)+INDEX($B16:$G16,O$4),"E","N","O","I") -> N | P16: =CHOOSE(1+2*INDEX($B16:$G16,P$3)+INDEX($B16:$G16,P$4),"E","N","O","I") -> N | Q16: =COUNTIF($H16:$P16,"I") -> 0 | R16: =COUNTIF($H16:$P16,"N") -> 6 | S16: =COUNTIF($H16:$P16,"O") -> 3 | T16: =COUNTIF($H16:$P16,"E") -> 0 | U16: =SUM(Q16:T16) -> 9 | V16: =H16&I16&J16&K16&L16&M16&N16&O16&P16 -> NOONNONNN | W16: =IF(Declarations!$E$29="goods",H16,"")&IF(Declarations!$E$30="goods",I16,"")&IF(Declarations!$E$31="goods",J16,"")&IF(Declarations!$E$32="goods",K16,"")&IF(Declarations!$E$33="goods",L16,"")&IF(Declarations!$E$34="goods",M16,"")&IF(Declarations!$E$35="goods",N16,"")&IF(Declarations!$E$36="goods",O16,"")&IF(Declarations!$E$37="goods",P16,"") -> NON | X16: =IF(Declarations!$E$29="capital",H16,"")&IF(Declarations!$E$30="capital",I16,"")&IF(Declarations!$E$31="capital",J16,"")&IF(Declarations!$E$32="capital",K16,"")&IF(Declarations!$E$33="capital",L16,"")&IF(Declarations!$E$34="capital",M16,"")&IF(Declarations!$E$35="capital",N16,"")&IF(Declarations!$E$36="capital",O16,"")&IF(Declarations!$E$37="capital",P16,"") -> ONON | Y16: =IF(Declarations!$E$29="information",H16,"")&IF(Declarations!$E$30="information",I16,"")&IF(Declarations!$E$31="information",J16,"")&IF(Declarations!$E$32="information",K16,"")&IF(Declarations!$E$33="information",L16,"")&IF(Declarations!$E$34="information",M16,"")&IF(Declarations!$E$35="information",N16,"")&IF(Declarations!$E$36="information",O16,"")&IF(Declarations!$E$37="information",P16,"") -> NN | AA16: Suppliers inside (boundary 3) | AB16: =SUMPRODUCT(--($H$8:$P$8<>H9:P9)) -> 2
A17: 11 | B17: =MOD(INT($A17/2^0),2) -> 1 | C17: =MOD(INT($A17/2^1),2) -> 1 | D17: =MOD(INT($A17/2^2),2) -> 0 | E17: =MOD(INT($A17/2^3),2) -> 1 | F17: =MOD(INT($A17/2^4),2) -> 0 | G17: =MOD(INT($A17/2^5),2) -> 0 | H17: =CHOOSE(1+2*INDEX($B17:$G17,H$3)+INDEX($B17:$G17,H$4),"E","N","O","I") -> I | I17: =CHOOSE(1+2*INDEX($B17:$G17,I$3)+INDEX($B17:$G17,I$4),"E","N","O","I") -> I | J17: =CHOOSE(1+2*INDEX($B17:$G17,J$3)+INDEX($B17:$G17,J$4),"E","N","O","I") -> O | K17: =CHOOSE(1+2*INDEX($B17:$G17,K$3)+INDEX($B17:$G17,K$4),"E","N","O","I") -> N | L17: =CHOOSE(1+2*INDEX($B17:$G17,L$3)+INDEX($B17:$G17,L$4),"E","N","O","I") -> N | M17: =CHOOSE(1+2*INDEX($B17:$G17,M$3)+INDEX($B17:$G17,M$4),"E","N","O","I") -> O | N17: =CHOOSE(1+2*INDEX($B17:$G17,N$3)+INDEX($B17:$G17,N$4),"E","N","O","I") -> N | O17: =CHOOSE(1+2*INDEX($B17:$G17,O$3)+INDEX($B17:$G17,O$4),"E","N","O","I") -> N | P17: =CHOOSE(1+2*INDEX($B17:$G17,P$3)+INDEX($B17:$G17,P$4),"E","N","O","I") -> N | Q17: =COUNTIF($H17:$P17,"I") -> 2 | R17: =COUNTIF($H17:$P17,"N") -> 5 | S17: =COUNTIF($H17:$P17,"O") -> 2 | T17: =COUNTIF($H17:$P17,"E") -> 0 | U17: =SUM(Q17:T17) -> 9 | V17: =H17&I17&J17&K17&L17&M17&N17&O17&P17 -> IIONNONNN | W17: =IF(Declarations!$E$29="goods",H17,"")&IF(Declarations!$E$30="goods",I17,"")&IF(Declarations!$E$31="goods",J17,"")&IF(Declarations!$E$32="goods",K17,"")&IF(Declarations!$E$33="goods",L17,"")&IF(Declarations!$E$34="goods",M17,"")&IF(Declarations!$E$35="goods",N17,"")&IF(Declarations!$E$36="goods",O17,"")&IF(Declarations!$E$37="goods",P17,"") -> ION | X17: =IF(Declarations!$E$29="capital",H17,"")&IF(Declarations!$E$30="capital",I17,"")&IF(Declarations!$E$31="capital",J17,"")&IF(Declarations!$E$32="capital",K17,"")&IF(Declarations!$E$33="capital",L17,"")&IF(Declarations!$E$34="capital",M17,"")&IF(Declarations!$E$35="capital",N17,"")&IF(Declarations!$E$36="capital",O17,"")&IF(Declarations!$E$37="capital",P17,"") -> INON | Y17: =IF(Declarations!$E$29="information",H17,"")&IF(Declarations!$E$30="information",I17,"")&IF(Declarations!$E$31="information",J17,"")&IF(Declarations!$E$32="information",K17,"")&IF(Declarations!$E$33="information",L17,"")&IF(Declarations!$E$34="information",M17,"")&IF(Declarations!$E$35="information",N17,"")&IF(Declarations!$E$36="information",O17,"")&IF(Declarations!$E$37="information",P17,"") -> NN | AA17: Meridian outside (boundary 0) | AB17: =SUMPRODUCT(--($H$8:$P$8<>H6:P6)) -> 7
A18: 12 | B18: =MOD(INT($A18/2^0),2) -> 0 | C18: =MOD(INT($A18/2^1),2) -> 0 | D18: =MOD(INT($A18/2^2),2) -> 1 | E18: =MOD(INT($A18/2^3),2) -> 1 | F18: =MOD(INT($A18/2^4),2) -> 0 | G18: =MOD(INT($A18/2^5),2) -> 0 | H18: =CHOOSE(1+2*INDEX($B18:$G18,H$3)+INDEX($B18:$G18,H$4),"E","N","O","I") -> E | I18: =CHOOSE(1+2*INDEX($B18:$G18,I$3)+INDEX($B18:$G18,I$4),"E","N","O","I") -> E | J18: =CHOOSE(1+2*INDEX($B18:$G18,J$3)+INDEX($B18:$G18,J$4),"E","N","O","I") -> N | K18: =CHOOSE(1+2*INDEX($B18:$G18,K$3)+INDEX($B18:$G18,K$4),"E","N","O","I") -> O | L18: =CHOOSE(1+2*INDEX($B18:$G18,L$3)+INDEX($B18:$G18,L$4),"E","N","O","I") -> I | M18: =CHOOSE(1+2*INDEX($B18:$G18,M$3)+INDEX($B18:$G18,M$4),"E","N","O","I") -> I | N18: =CHOOSE(1+2*INDEX($B18:$G18,N$3)+INDEX($B18:$G18,N$4),"E","N","O","I") -> O | O18: =CHOOSE(1+2*INDEX($B18:$G18,O$3)+INDEX($B18:$G18,O$4),"E","N","O","I") -> E | P18: =CHOOSE(1+2*INDEX($B18:$G18,P$3)+INDEX($B18:$G18,P$4),"E","N","O","I") -> E | Q18: =COUNTIF($H18:$P18,"I") -> 2 | R18: =COUNTIF($H18:$P18,"N") -> 1 | S18: =COUNTIF($H18:$P18,"O") -> 2 | T18: =COUNTIF($H18:$P18,"E") -> 4 | U18: =SUM(Q18:T18) -> 9 | V18: =H18&I18&J18&K18&L18&M18&N18&O18&P18 -> EENOIIOEE | W18: =IF(Declarations!$E$29="goods",H18,"")&IF(Declarations!$E$30="goods",I18,"")&IF(Declarations!$E$31="goods",J18,"")&IF(Declarations!$E$32="goods",K18,"")&IF(Declarations!$E$33="goods",L18,"")&IF(Declarations!$E$34="goods",M18,"")&IF(Declarations!$E$35="goods",N18,"")&IF(Declarations!$E$36="goods",O18,"")&IF(Declarations!$E$37="goods",P18,"") -> ENI | X18: =IF(Declarations!$E$29="capital",H18,"")&IF(Declarations!$E$30="capital",I18,"")&IF(Declarations!$E$31="capital",J18,"")&IF(Declarations!$E$32="capital",K18,"")&IF(Declarations!$E$33="capital",L18,"")&IF(Declarations!$E$34="capital",M18,"")&IF(Declarations!$E$35="capital",N18,"")&IF(Declarations!$E$36="capital",O18,"")&IF(Declarations!$E$37="capital",P18,"") -> EOIE | Y18: =IF(Declarations!$E$29="information",H18,"")&IF(Declarations!$E$30="information",I18,"")&IF(Declarations!$E$31="information",J18,"")&IF(Declarations!$E$32="information",K18,"")&IF(Declarations!$E$33="information",L18,"")&IF(Declarations!$E$34="information",M18,"")&IF(Declarations!$E$35="information",N18,"")&IF(Declarations!$E$36="information",O18,"")&IF(Declarations!$E$37="information",P18,"") -> OE | AA18: Dealer network inside (boundary 6) | AB18: =SUMPRODUCT(--($H$8:$P$8<>H12:P12)) -> 5
A19: 13 | B19: =MOD(INT($A19/2^0),2) -> 1 | C19: =MOD(INT($A19/2^1),2) -> 0 | D19: =MOD(INT($A19/2^2),2) -> 1 | E19: =MOD(INT($A19/2^3),2) -> 1 | F19: =MOD(INT($A19/2^4),2) -> 0 | G19: =MOD(INT($A19/2^5),2) -> 0 | H19: =CHOOSE(1+2*INDEX($B19:$G19,H$3)+INDEX($B19:$G19,H$4),"E","N","O","I") -> O | I19: =CHOOSE(1+2*INDEX($B19:$G19,I$3)+INDEX($B19:$G19,I$4),"E","N","O","I") -> N | J19: =CHOOSE(1+2*INDEX($B19:$G19,J$3)+INDEX($B19:$G19,J$4),"E","N","O","I") -> N | K19: =CHOOSE(1+2*INDEX($B19:$G19,K$3)+INDEX($B19:$G19,K$4),"E","N","O","I") -> O | L19: =CHOOSE(1+2*INDEX($B19:$G19,L$3)+INDEX($B19:$G19,L$4),"E","N","O","I") -> I | M19: =CHOOSE(1+2*INDEX($B19:$G19,M$3)+INDEX($B19:$G19,M$4),"E","N","O","I") -> I | N19: =CHOOSE(1+2*INDEX($B19:$G19,N$3)+INDEX($B19:$G19,N$4),"E","N","O","I") -> O | O19: =CHOOSE(1+2*INDEX($B19:$G19,O$3)+INDEX($B19:$G19,O$4),"E","N","O","I") -> E | P19: =CHOOSE(1+2*INDEX($B19:$G19,P$3)+INDEX($B19:$G19,P$4),"E","N","O","I") -> E | Q19: =COUNTIF($H19:$P19,"I") -> 2 | R19: =COUNTIF($H19:$P19,"N") -> 2 | S19: =COUNTIF($H19:$P19,"O") -> 3 | T19: =COUNTIF($H19:$P19,"E") -> 2 | U19: =SUM(Q19:T19) -> 9 | V19: =H19&I19&J19&K19&L19&M19&N19&O19&P19 -> ONNOIIOEE | W19: =IF(Declarations!$E$29="goods",H19,"")&IF(Declarations!$E$30="goods",I19,"")&IF(Declarations!$E$31="goods",J19,"")&IF(Declarations!$E$32="goods",K19,"")&IF(Declarations!$E$33="goods",L19,"")&IF(Declarations!$E$34="goods",M19,"")&IF(Declarations!$E$35="goods",N19,"")&IF(Declarations!$E$36="goods",O19,"")&IF(Declarations!$E$37="goods",P19,"") -> ONI | X19: =IF(Declarations!$E$29="capital",H19,"")&IF(Declarations!$E$30="capital",I19,"")&IF(Declarations!$E$31="capital",J19,"")&IF(Declarations!$E$32="capital",K19,"")&IF(Declarations!$E$33="capital",L19,"")&IF(Declarations!$E$34="capital",M19,"")&IF(Declarations!$E$35="capital",N19,"")&IF(Declarations!$E$36="capital",O19,"")&IF(Declarations!$E$37="capital",P19,"") -> NOIE | Y19: =IF(Declarations!$E$29="information",H19,"")&IF(Declarations!$E$30="information",I19,"")&IF(Declarations!$E$31="information",J19,"")&IF(Declarations!$E$32="information",K19,"")&IF(Declarations!$E$33="information",L19,"")&IF(Declarations!$E$34="information",M19,"")&IF(Declarations!$E$35="information",N19,"")&IF(Declarations!$E$36="information",O19,"")&IF(Declarations!$E$37="information",P19,"") -> OE | AA19: End customers inside (boundary 10) | AB19: =SUMPRODUCT(--($H$8:$P$8<>H16:P16)) -> 2
A20: 14 | B20: =MOD(INT($A20/2^0),2) -> 0 | C20: =MOD(INT($A20/2^1),2) -> 1 | D20: =MOD(INT($A20/2^2),2) -> 1 | E20: =MOD(INT($A20/2^3),2) -> 1 | F20: =MOD(INT($A20/2^4),2) -> 0 | G20: =MOD(INT($A20/2^5),2) -> 0 | H20: =CHOOSE(1+2*INDEX($B20:$G20,H$3)+INDEX($B20:$G20,H$4),"E","N","O","I") -> N | I20: =CHOOSE(1+2*INDEX($B20:$G20,I$3)+INDEX($B20:$G20,I$4),"E","N","O","I") -> O | J20: =CHOOSE(1+2*INDEX($B20:$G20,J$3)+INDEX($B20:$G20,J$4),"E","N","O","I") -> I | K20: =CHOOSE(1+2*INDEX($B20:$G20,K$3)+INDEX($B20:$G20,K$4),"E","N","O","I") -> I | L20: =CHOOSE(1+2*INDEX($B20:$G20,L$3)+INDEX($B20:$G20,L$4),"E","N","O","I") -> I | M20: =CHOOSE(1+2*INDEX($B20:$G20,M$3)+INDEX($B20:$G20,M$4),"E","N","O","I") -> I | N20: =CHOOSE(1+2*INDEX($B20:$G20,N$3)+INDEX($B20:$G20,N$4),"E","N","O","I") -> I | O20: =CHOOSE(1+2*INDEX($B20:$G20,O$3)+INDEX($B20:$G20,O$4),"E","N","O","I") -> N | P20: =CHOOSE(1+2*INDEX($B20:$G20,P$3)+INDEX($B20:$G20,P$4),"E","N","O","I") -> N | Q20: =COUNTIF($H20:$P20,"I") -> 5 | R20: =COUNTIF($H20:$P20,"N") -> 3 | S20: =COUNTIF($H20:$P20,"O") -> 1 | T20: =COUNTIF($H20:$P20,"E") -> 0 | U20: =SUM(Q20:T20) -> 9 | V20: =H20&I20&J20&K20&L20&M20&N20&O20&P20 -> NOIIIIINN | W20: =IF(Declarations!$E$29="goods",H20,"")&IF(Declarations!$E$30="goods",I20,"")&IF(Declarations!$E$31="goods",J20,"")&IF(Declarations!$E$32="goods",K20,"")&IF(Declarations!$E$33="goods",L20,"")&IF(Declarations!$E$34="goods",M20,"")&IF(Declarations!$E$35="goods",N20,"")&IF(Declarations!$E$36="goods",O20,"")&IF(Declarations!$E$37="goods",P20,"") -> NII | X20: =IF(Declarations!$E$29="capital",H20,"")&IF(Declarations!$E$30="capital",I20,"")&IF(Declarations!$E$31="capital",J20,"")&IF(Declarations!$E$32="capital",K20,"")&IF(Declarations!$E$33="capital",L20,"")&IF(Declarations!$E$34="capital",M20,"")&IF(Declarations!$E$35="capital",N20,"")&IF(Declarations!$E$36="capital",O20,"")&IF(Declarations!$E$37="capital",P20,"") -> OIIN | Y20: =IF(Declarations!$E$29="information",H20,"")&IF(Declarations!$E$30="information",I20,"")&IF(Declarations!$E$31="information",J20,"")&IF(Declarations!$E$32="information",K20,"")&IF(Declarations!$E$33="information",L20,"")&IF(Declarations!$E$34="information",M20,"")&IF(Declarations!$E$35="information",N20,"")&IF(Declarations!$E$36="information",O20,"")&IF(Declarations!$E$37="information",P20,"") -> IN | AA20: Capital markets inside (boundary 18) | AB20: =SUMPRODUCT(--($H$8:$P$8<>H24:P24)) -> 1
A21: 15 | B21: =MOD(INT($A21/2^0),2) -> 1 | C21: =MOD(INT($A21/2^1),2) -> 1 | D21: =MOD(INT($A21/2^2),2) -> 1 | E21: =MOD(INT($A21/2^3),2) -> 1 | F21: =MOD(INT($A21/2^4),2) -> 0 | G21: =MOD(INT($A21/2^5),2) -> 0 | H21: =CHOOSE(1+2*INDEX($B21:$G21,H$3)+INDEX($B21:$G21,H$4),"E","N","O","I") -> I | I21: =CHOOSE(1+2*INDEX($B21:$G21,I$3)+INDEX($B21:$G21,I$4),"E","N","O","I") -> I | J21: =CHOOSE(1+2*INDEX($B21:$G21,J$3)+INDEX($B21:$G21,J$4),"E","N","O","I") -> I | K21: =CHOOSE(1+2*INDEX($B21:$G21,K$3)+INDEX($B21:$G21,K$4),"E","N","O","I") -> I | L21: =CHOOSE(1+2*INDEX($B21:$G21,L$3)+INDEX($B21:$G21,L$4),"E","N","O","I") -> I | M21: =CHOOSE(1+2*INDEX($B21:$G21,M$3)+INDEX($B21:$G21,M$4),"E","N","O","I") -> I | N21: =CHOOSE(1+2*INDEX($B21:$G21,N$3)+INDEX($B21:$G21,N$4),"E","N","O","I") -> I | O21: =CHOOSE(1+2*INDEX($B21:$G21,O$3)+INDEX($B21:$G21,O$4),"E","N","O","I") -> N | P21: =CHOOSE(1+2*INDEX($B21:$G21,P$3)+INDEX($B21:$G21,P$4),"E","N","O","I") -> N | Q21: =COUNTIF($H21:$P21,"I") -> 7 | R21: =COUNTIF($H21:$P21,"N") -> 2 | S21: =COUNTIF($H21:$P21,"O") -> 0 | T21: =COUNTIF($H21:$P21,"E") -> 0 | U21: =SUM(Q21:T21) -> 9 | V21: =H21&I21&J21&K21&L21&M21&N21&O21&P21 -> IIIIIIINN | W21: =IF(Declarations!$E$29="goods",H21,"")&IF(Declarations!$E$30="goods",I21,"")&IF(Declarations!$E$31="goods",J21,"")&IF(Declarations!$E$32="goods",K21,"")&IF(Declarations!$E$33="goods",L21,"")&IF(Declarations!$E$34="goods",M21,"")&IF(Declarations!$E$35="goods",N21,"")&IF(Declarations!$E$36="goods",O21,"")&IF(Declarations!$E$37="goods",P21,"") -> III | X21: =IF(Declarations!$E$29="capital",H21,"")&IF(Declarations!$E$30="capital",I21,"")&IF(Declarations!$E$31="capital",J21,"")&IF(Declarations!$E$32="capital",K21,"")&IF(Declarations!$E$33="capital",L21,"")&IF(Declarations!$E$34="capital",M21,"")&IF(Declarations!$E$35="capital",N21,"")&IF(Declarations!$E$36="capital",O21,"")&IF(Declarations!$E$37="capital",P21,"") -> IIIN | Y21: =IF(Declarations!$E$29="information",H21,"")&IF(Declarations!$E$30="information",I21,"")&IF(Declarations!$E$31="information",J21,"")&IF(Declarations!$E$32="information",K21,"")&IF(Declarations!$E$33="information",L21,"")&IF(Declarations!$E$34="information",M21,"")&IF(Declarations!$E$35="information",N21,"")&IF(Declarations!$E$36="information",O21,"")&IF(Declarations!$E$37="information",P21,"") -> IN | AA21: Regulator inside (boundary 34) | AB21: =SUMPRODUCT(--($H$8:$P$8<>H40:P40)) -> 1
A22: 16 | B22: =MOD(INT($A22/2^0),2) -> 0 | C22: =MOD(INT($A22/2^1),2) -> 0 | D22: =MOD(INT($A22/2^2),2) -> 0 | E22: =MOD(INT($A22/2^3),2) -> 0 | F22: =MOD(INT($A22/2^4),2) -> 1 | G22: =MOD(INT($A22/2^5),2) -> 0 | H22: =CHOOSE(1+2*INDEX($B22:$G22,H$3)+INDEX($B22:$G22,H$4),"E","N","O","I") -> E | I22: =CHOOSE(1+2*INDEX($B22:$G22,I$3)+INDEX($B22:$G22,I$4),"E","N","O","I") -> E | J22: =CHOOSE(1+2*INDEX($B22:$G22,J$3)+INDEX($B22:$G22,J$4),"E","N","O","I") -> E | K22: =CHOOSE(1+2*INDEX($B22:$G22,K$3)+INDEX($B22:$G22,K$4),"E","N","O","I") -> E | L22: =CHOOSE(1+2*INDEX($B22:$G22,L$3)+INDEX($B22:$G22,L$4),"E","N","O","I") -> E | M22: =CHOOSE(1+2*INDEX($B22:$G22,M$3)+INDEX($B22:$G22,M$4),"E","N","O","I") -> E | N22: =CHOOSE(1+2*INDEX($B22:$G22,N$3)+INDEX($B22:$G22,N$4),"E","N","O","I") -> E | O22: =CHOOSE(1+2*INDEX($B22:$G22,O$3)+INDEX($B22:$G22,O$4),"E","N","O","I") -> O | P22: =CHOOSE(1+2*INDEX($B22:$G22,P$3)+INDEX($B22:$G22,P$4),"E","N","O","I") -> E | Q22: =COUNTIF($H22:$P22,"I") -> 0 | R22: =COUNTIF($H22:$P22,"N") -> 0 | S22: =COUNTIF($H22:$P22,"O") -> 1 | T22: =COUNTIF($H22:$P22,"E") -> 8 | U22: =SUM(Q22:T22) -> 9 | V22: =H22&I22&J22&K22&L22&M22&N22&O22&P22 -> EEEEEEEOE | W22: =IF(Declarations!$E$29="goods",H22,"")&IF(Declarations!$E$30="goods",I22,"")&IF(Declarations!$E$31="goods",J22,"")&IF(Declarations!$E$32="goods",K22,"")&IF(Declarations!$E$33="goods",L22,"")&IF(Declarations!$E$34="goods",M22,"")&IF(Declarations!$E$35="goods",N22,"")&IF(Declarations!$E$36="goods",O22,"")&IF(Declarations!$E$37="goods",P22,"") -> EEE | X22: =IF(Declarations!$E$29="capital",H22,"")&IF(Declarations!$E$30="capital",I22,"")&IF(Declarations!$E$31="capital",J22,"")&IF(Declarations!$E$32="capital",K22,"")&IF(Declarations!$E$33="capital",L22,"")&IF(Declarations!$E$34="capital",M22,"")&IF(Declarations!$E$35="capital",N22,"")&IF(Declarations!$E$36="capital",O22,"")&IF(Declarations!$E$37="capital",P22,"") -> EEEO | Y22: =IF(Declarations!$E$29="information",H22,"")&IF(Declarations!$E$30="information",I22,"")&IF(Declarations!$E$31="information",J22,"")&IF(Declarations!$E$32="information",K22,"")&IF(Declarations!$E$33="information",L22,"")&IF(Declarations!$E$34="information",M22,"")&IF(Declarations!$E$35="information",N22,"")&IF(Declarations!$E$36="information",O22,"")&IF(Declarations!$E$37="information",P22,"") -> EE
A23: 17 | B23: =MOD(INT($A23/2^0),2) -> 1 | C23: =MOD(INT($A23/2^1),2) -> 0 | D23: =MOD(INT($A23/2^2),2) -> 0 | E23: =MOD(INT($A23/2^3),2) -> 0 | F23: =MOD(INT($A23/2^4),2) -> 1 | G23: =MOD(INT($A23/2^5),2) -> 0 | H23: =CHOOSE(1+2*INDEX($B23:$G23,H$3)+INDEX($B23:$G23,H$4),"E","N","O","I") -> O | I23: =CHOOSE(1+2*INDEX($B23:$G23,I$3)+INDEX($B23:$G23,I$4),"E","N","O","I") -> N | J23: =CHOOSE(1+2*INDEX($B23:$G23,J$3)+INDEX($B23:$G23,J$4),"E","N","O","I") -> E | K23: =CHOOSE(1+2*INDEX($B23:$G23,K$3)+INDEX($B23:$G23,K$4),"E","N","O","I") -> E | L23: =CHOOSE(1+2*INDEX($B23:$G23,L$3)+INDEX($B23:$G23,L$4),"E","N","O","I") -> E | M23: =CHOOSE(1+2*INDEX($B23:$G23,M$3)+INDEX($B23:$G23,M$4),"E","N","O","I") -> E | N23: =CHOOSE(1+2*INDEX($B23:$G23,N$3)+INDEX($B23:$G23,N$4),"E","N","O","I") -> E | O23: =CHOOSE(1+2*INDEX($B23:$G23,O$3)+INDEX($B23:$G23,O$4),"E","N","O","I") -> O | P23: =CHOOSE(1+2*INDEX($B23:$G23,P$3)+INDEX($B23:$G23,P$4),"E","N","O","I") -> E | Q23: =COUNTIF($H23:$P23,"I") -> 0 | R23: =COUNTIF($H23:$P23,"N") -> 1 | S23: =COUNTIF($H23:$P23,"O") -> 2 | T23: =COUNTIF($H23:$P23,"E") -> 6 | U23: =SUM(Q23:T23) -> 9 | V23: =H23&I23&J23&K23&L23&M23&N23&O23&P23 -> ONEEEEEOE | W23: =IF(Declarations!$E$29="goods",H23,"")&IF(Declarations!$E$30="goods",I23,"")&IF(Declarations!$E$31="goods",J23,"")&IF(Declarations!$E$32="goods",K23,"")&IF(Declarations!$E$33="goods",L23,"")&IF(Declarations!$E$34="goods",M23,"")&IF(Declarations!$E$35="goods",N23,"")&IF(Declarations!$E$36="goods",O23,"")&IF(Declarations!$E$37="goods",P23,"") -> OEE | X23: =IF(Declarations!$E$29="capital",H23,"")&IF(Declarations!$E$30="capital",I23,"")&IF(Declarations!$E$31="capital",J23,"")&IF(Declarations!$E$32="capital",K23,"")&IF(Declarations!$E$33="capital",L23,"")&IF(Declarations!$E$34="capital",M23,"")&IF(Declarations!$E$35="capital",N23,"")&IF(Declarations!$E$36="capital",O23,"")&IF(Declarations!$E$37="capital",P23,"") -> NEEO | Y23: =IF(Declarations!$E$29="information",H23,"")&IF(Declarations!$E$30="information",I23,"")&IF(Declarations!$E$31="information",J23,"")&IF(Declarations!$E$32="information",K23,"")&IF(Declarations!$E$33="information",L23,"")&IF(Declarations!$E$34="information",M23,"")&IF(Declarations!$E$35="information",N23,"")&IF(Declarations!$E$36="information",O23,"")&IF(Declarations!$E$37="information",P23,"") -> EE | AA23: Every entity takes part in some flow, so every move relabels something. For the goods question alone, capital markets and the regulator take part in no flow: 2^4 = 16 goods classifications, whatever side of the line they sit on (Corollary 2.B.2).
A24: 18 | B24: =MOD(INT($A24/2^0),2) -> 0 | C24: =MOD(INT($A24/2^1),2) -> 1 | D24: =MOD(INT($A24/2^2),2) -> 0 | E24: =MOD(INT($A24/2^3),2) -> 0 | F24: =MOD(INT($A24/2^4),2) -> 1 | G24: =MOD(INT($A24/2^5),2) -> 0 | H24: =CHOOSE(1+2*INDEX($B24:$G24,H$3)+INDEX($B24:$G24,H$4),"E","N","O","I") -> N | I24: =CHOOSE(1+2*INDEX($B24:$G24,I$3)+INDEX($B24:$G24,I$4),"E","N","O","I") -> O | J24: =CHOOSE(1+2*INDEX($B24:$G24,J$3)+INDEX($B24:$G24,J$4),"E","N","O","I") -> O | K24: =CHOOSE(1+2*INDEX($B24:$G24,K$3)+INDEX($B24:$G24,K$4),"E","N","O","I") -> N | L24: =CHOOSE(1+2*INDEX($B24:$G24,L$3)+INDEX($B24:$G24,L$4),"E","N","O","I") -> E | M24: =CHOOSE(1+2*INDEX($B24:$G24,M$3)+INDEX($B24:$G24,M$4),"E","N","O","I") -> E | N24: =CHOOSE(1+2*INDEX($B24:$G24,N$3)+INDEX($B24:$G24,N$4),"E","N","O","I") -> N | O24: =CHOOSE(1+2*INDEX($B24:$G24,O$3)+INDEX($B24:$G24,O$4),"E","N","O","I") -> I | P24: =CHOOSE(1+2*INDEX($B24:$G24,P$3)+INDEX($B24:$G24,P$4),"E","N","O","I") -> N | Q24: =COUNTIF($H24:$P24,"I") -> 1 | R24: =COUNTIF($H24:$P24,"N") -> 4 | S24: =COUNTIF($H24:$P24,"O") -> 2 | T24: =COUNTIF($H24:$P24,"E") -> 2 | U24: =SUM(Q24:T24) -> 9 | V24: =H24&I24&J24&K24&L24&M24&N24&O24&P24 -> NOONEENIN | W24: =IF(Declarations!$E$29="goods",H24,"")&IF(Declarations!$E$30="goods",I24,"")&IF(Declarations!$E$31="goods",J24,"")&IF(Declarations!$E$32="goods",K24,"")&IF(Declarations!$E$33="goods",L24,"")&IF(Declarations!$E$34="goods",M24,"")&IF(Declarations!$E$35="goods",N24,"")&IF(Declarations!$E$36="goods",O24,"")&IF(Declarations!$E$37="goods",P24,"") -> NOE | X24: =IF(Declarations!$E$29="capital",H24,"")&IF(Declarations!$E$30="capital",I24,"")&IF(Declarations!$E$31="capital",J24,"")&IF(Declarations!$E$32="capital",K24,"")&IF(Declarations!$E$33="capital",L24,"")&IF(Declarations!$E$34="capital",M24,"")&IF(Declarations!$E$35="capital",N24,"")&IF(Declarations!$E$36="capital",O24,"")&IF(Declarations!$E$37="capital",P24,"") -> ONEI | Y24: =IF(Declarations!$E$29="information",H24,"")&IF(Declarations!$E$30="information",I24,"")&IF(Declarations!$E$31="information",J24,"")&IF(Declarations!$E$32="information",K24,"")&IF(Declarations!$E$33="information",L24,"")&IF(Declarations!$E$34="information",M24,"")&IF(Declarations!$E$35="information",N24,"")&IF(Declarations!$E$36="information",O24,"")&IF(Declarations!$E$37="information",P24,"") -> NN
A25: 19 | B25: =MOD(INT($A25/2^0),2) -> 1 | C25: =MOD(INT($A25/2^1),2) -> 1 | D25: =MOD(INT($A25/2^2),2) -> 0 | E25: =MOD(INT($A25/2^3),2) -> 0 | F25: =MOD(INT($A25/2^4),2) -> 1 | G25: =MOD(INT($A25/2^5),2) -> 0 | H25: =CHOOSE(1+2*INDEX($B25:$G25,H$3)+INDEX($B25:$G25,H$4),"E","N","O","I") -> I | I25: =CHOOSE(1+2*INDEX($B25:$G25,I$3)+INDEX($B25:$G25,I$4),"E","N","O","I") -> I | J25: =CHOOSE(1+2*INDEX($B25:$G25,J$3)+INDEX($B25:$G25,J$4),"E","N","O","I") -> O | K25: =CHOOSE(1+2*INDEX($B25:$G25,K$3)+INDEX($B25:$G25,K$4),"E","N","O","I") -> N | L25: =CHOOSE(1+2*INDEX($B25:$G25,L$3)+INDEX($B25:$G25,L$4),"E","N","O","I") -> E | M25: =CHOOSE(1+2*INDEX($B25:$G25,M$3)+INDEX($B25:$G25,M$4),"E","N","O","I") -> E | N25: =CHOOSE(1+2*INDEX($B25:$G25,N$3)+INDEX($B25:$G25,N$4),"E","N","O","I") -> N | O25: =CHOOSE(1+2*INDEX($B25:$G25,O$3)+INDEX($B25:$G25,O$4),"E","N","O","I") -> I | P25: =CHOOSE(1+2*INDEX($B25:$G25,P$3)+INDEX($B25:$G25,P$4),"E","N","O","I") -> N | Q25: =COUNTIF($H25:$P25,"I") -> 3 | R25: =COUNTIF($H25:$P25,"N") -> 3 | S25: =COUNTIF($H25:$P25,"O") -> 1 | T25: =COUNTIF($H25:$P25,"E") -> 2 | U25: =SUM(Q25:T25) -> 9 | V25: =H25&I25&J25&K25&L25&M25&N25&O25&P25 -> IIONEENIN | W25: =IF(Declarations!$E$29="goods",H25,"")&IF(Declarations!$E$30="goods",I25,"")&IF(Declarations!$E$31="goods",J25,"")&IF(Declarations!$E$32="goods",K25,"")&IF(Declarations!$E$33="goods",L25,"")&IF(Declarations!$E$34="goods",M25,"")&IF(Declarations!$E$35="goods",N25,"")&IF(Declarations!$E$36="goods",O25,"")&IF(Declarations!$E$37="goods",P25,"") -> IOE | X25: =IF(Declarations!$E$29="capital",H25,"")&IF(Declarations!$E$30="capital",I25,"")&IF(Declarations!$E$31="capital",J25,"")&IF(Declarations!$E$32="capital",K25,"")&IF(Declarations!$E$33="capital",L25,"")&IF(Declarations!$E$34="capital",M25,"")&IF(Declarations!$E$35="capital",N25,"")&IF(Declarations!$E$36="capital",O25,"")&IF(Declarations!$E$37="capital",P25,"") -> INEI | Y25: =IF(Declarations!$E$29="information",H25,"")&IF(Declarations!$E$30="information",I25,"")&IF(Declarations!$E$31="information",J25,"")&IF(Declarations!$E$32="information",K25,"")&IF(Declarations!$E$33="information",L25,"")&IF(Declarations!$E$34="information",M25,"")&IF(Declarations!$E$35="information",N25,"")&IF(Declarations!$E$36="information",O25,"")&IF(Declarations!$E$37="information",P25,"") -> NN
A26: 20 | B26: =MOD(INT($A26/2^0),2) -> 0 | C26: =MOD(INT($A26/2^1),2) -> 0 | D26: =MOD(INT($A26/2^2),2) -> 1 | E26: =MOD(INT($A26/2^3),2) -> 0 | F26: =MOD(INT($A26/2^4),2) -> 1 | G26: =MOD(INT($A26/2^5),2) -> 0 | H26: =CHOOSE(1+2*INDEX($B26:$G26,H$3)+INDEX($B26:$G26,H$4),"E","N","O","I") -> E | I26: =CHOOSE(1+2*INDEX($B26:$G26,I$3)+INDEX($B26:$G26,I$4),"E","N","O","I") -> E | J26: =CHOOSE(1+2*INDEX($B26:$G26,J$3)+INDEX($B26:$G26,J$4),"E","N","O","I") -> N | K26: =CHOOSE(1+2*INDEX($B26:$G26,K$3)+INDEX($B26:$G26,K$4),"E","N","O","I") -> O | L26: =CHOOSE(1+2*INDEX($B26:$G26,L$3)+INDEX($B26:$G26,L$4),"E","N","O","I") -> O | M26: =CHOOSE(1+2*INDEX($B26:$G26,M$3)+INDEX($B26:$G26,M$4),"E","N","O","I") -> N | N26: =CHOOSE(1+2*INDEX($B26:$G26,N$3)+INDEX($B26:$G26,N$4),"E","N","O","I") -> O | O26: =CHOOSE(1+2*INDEX($B26:$G26,O$3)+INDEX($B26:$G26,O$4),"E","N","O","I") -> O | P26: =CHOOSE(1+2*INDEX($B26:$G26,P$3)+INDEX($B26:$G26,P$4),"E","N","O","I") -> E | Q26: =COUNTIF($H26:$P26,"I") -> 0 | R26: =COUNTIF($H26:$P26,"N") -> 2 | S26: =COUNTIF($H26:$P26,"O") -> 4 | T26: =COUNTIF($H26:$P26,"E") -> 3 | U26: =SUM(Q26:T26) -> 9 | V26: =H26&I26&J26&K26&L26&M26&N26&O26&P26 -> EENOONOOE | W26: =IF(Declarations!$E$29="goods",H26,"")&IF(Declarations!$E$30="goods",I26,"")&IF(Declarations!$E$31="goods",J26,"")&IF(Declarations!$E$32="goods",K26,"")&IF(Declarations!$E$33="goods",L26,"")&IF(Declarations!$E$34="goods",M26,"")&IF(Declarations!$E$35="goods",N26,"")&IF(Declarations!$E$36="goods",O26,"")&IF(Declarations!$E$37="goods",P26,"") -> ENO | X26: =IF(Declarations!$E$29="capital",H26,"")&IF(Declarations!$E$30="capital",I26,"")&IF(Declarations!$E$31="capital",J26,"")&IF(Declarations!$E$32="capital",K26,"")&IF(Declarations!$E$33="capital",L26,"")&IF(Declarations!$E$34="capital",M26,"")&IF(Declarations!$E$35="capital",N26,"")&IF(Declarations!$E$36="capital",O26,"")&IF(Declarations!$E$37="capital",P26,"") -> EONO | Y26: =IF(Declarations!$E$29="information",H26,"")&IF(Declarations!$E$30="information",I26,"")&IF(Declarations!$E$31="information",J26,"")&IF(Declarations!$E$32="information",K26,"")&IF(Declarations!$E$33="information",L26,"")&IF(Declarations!$E$34="information",M26,"")&IF(Declarations!$E$35="information",N26,"")&IF(Declarations!$E$36="information",O26,"")&IF(Declarations!$E$37="information",P26,"") -> OE
A27: 21 | B27: =MOD(INT($A27/2^0),2) -> 1 | C27: =MOD(INT($A27/2^1),2) -> 0 | D27: =MOD(INT($A27/2^2),2) -> 1 | E27: =MOD(INT($A27/2^3),2) -> 0 | F27: =MOD(INT($A27/2^4),2) -> 1 | G27: =MOD(INT($A27/2^5),2) -> 0 | H27: =CHOOSE(1+2*INDEX($B27:$G27,H$3)+INDEX($B27:$G27,H$4),"E","N","O","I") -> O | I27: =CHOOSE(1+2*INDEX($B27:$G27,I$3)+INDEX($B27:$G27,I$4),"E","N","O","I") -> N | J27: =CHOOSE(1+2*INDEX($B27:$G27,J$3)+INDEX($B27:$G27,J$4),"E","N","O","I") -> N | K27: =CHOOSE(1+2*INDEX($B27:$G27,K$3)+INDEX($B27:$G27,K$4),"E","N","O","I") -> O | L27: =CHOOSE(1+2*INDEX($B27:$G27,L$3)+INDEX($B27:$G27,L$4),"E","N","O","I") -> O | M27: =CHOOSE(1+2*INDEX($B27:$G27,M$3)+INDEX($B27:$G27,M$4),"E","N","O","I") -> N | N27: =CHOOSE(1+2*INDEX($B27:$G27,N$3)+INDEX($B27:$G27,N$4),"E","N","O","I") -> O | O27: =CHOOSE(1+2*INDEX($B27:$G27,O$3)+INDEX($B27:$G27,O$4),"E","N","O","I") -> O | P27: =CHOOSE(1+2*INDEX($B27:$G27,P$3)+INDEX($B27:$G27,P$4),"E","N","O","I") -> E | Q27: =COUNTIF($H27:$P27,"I") -> 0 | R27: =COUNTIF($H27:$P27,"N") -> 3 | S27: =COUNTIF($H27:$P27,"O") -> 5 | T27: =COUNTIF($H27:$P27,"E") -> 1 | U27: =SUM(Q27:T27) -> 9 | V27: =H27&I27&J27&K27&L27&M27&N27&O27&P27 -> ONNOONOOE | W27: =IF(Declarations!$E$29="goods",H27,"")&IF(Declarations!$E$30="goods",I27,"")&IF(Declarations!$E$31="goods",J27,"")&IF(Declarations!$E$32="goods",K27,"")&IF(Declarations!$E$33="goods",L27,"")&IF(Declarations!$E$34="goods",M27,"")&IF(Declarations!$E$35="goods",N27,"")&IF(Declarations!$E$36="goods",O27,"")&IF(Declarations!$E$37="goods",P27,"") -> ONO | X27: =IF(Declarations!$E$29="capital",H27,"")&IF(Declarations!$E$30="capital",I27,"")&IF(Declarations!$E$31="capital",J27,"")&IF(Declarations!$E$32="capital",K27,"")&IF(Declarations!$E$33="capital",L27,"")&IF(Declarations!$E$34="capital",M27,"")&IF(Declarations!$E$35="capital",N27,"")&IF(Declarations!$E$36="capital",O27,"")&IF(Declarations!$E$37="capital",P27,"") -> NONO | Y27: =IF(Declarations!$E$29="information",H27,"")&IF(Declarations!$E$30="information",I27,"")&IF(Declarations!$E$31="information",J27,"")&IF(Declarations!$E$32="information",K27,"")&IF(Declarations!$E$33="information",L27,"")&IF(Declarations!$E$34="information",M27,"")&IF(Declarations!$E$35="information",N27,"")&IF(Declarations!$E$36="information",O27,"")&IF(Declarations!$E$37="information",P27,"") -> OE
A28: 22 | B28: =MOD(INT($A28/2^0),2) -> 0 | C28: =MOD(INT($A28/2^1),2) -> 1 | D28: =MOD(INT($A28/2^2),2) -> 1 | E28: =MOD(INT($A28/2^3),2) -> 0 | F28: =MOD(INT($A28/2^4),2) -> 1 | G28: =MOD(INT($A28/2^5),2) -> 0 | H28: =CHOOSE(1+2*INDEX($B28:$G28,H$3)+INDEX($B28:$G28,H$4),"E","N","O","I") -> N | I28: =CHOOSE(1+2*INDEX($B28:$G28,I$3)+INDEX($B28:$G28,I$4),"E","N","O","I") -> O | J28: =CHOOSE(1+2*INDEX($B28:$G28,J$3)+INDEX($B28:$G28,J$4),"E","N","O","I") -> I | K28: =CHOOSE(1+2*INDEX($B28:$G28,K$3)+INDEX($B28:$G28,K$4),"E","N","O","I") -> I | L28: =CHOOSE(1+2*INDEX($B28:$G28,L$3)+INDEX($B28:$G28,L$4),"E","N","O","I") -> O | M28: =CHOOSE(1+2*INDEX($B28:$G28,M$3)+INDEX($B28:$G28,M$4),"E","N","O","I") -> N | N28: =CHOOSE(1+2*INDEX($B28:$G28,N$3)+INDEX($B28:$G28,N$4),"E","N","O","I") -> I | O28: =CHOOSE(1+2*INDEX($B28:$G28,O$3)+INDEX($B28:$G28,O$4),"E","N","O","I") -> I | P28: =CHOOSE(1+2*INDEX($B28:$G28,P$3)+INDEX($B28:$G28,P$4),"E","N","O","I") -> N | Q28: =COUNTIF($H28:$P28,"I") -> 4 | R28: =COUNTIF($H28:$P28,"N") -> 3 | S28: =COUNTIF($H28:$P28,"O") -> 2 | T28: =COUNTIF($H28:$P28,"E") -> 0 | U28: =SUM(Q28:T28) -> 9 | V28: =H28&I28&J28&K28&L28&M28&N28&O28&P28 -> NOIIONIIN | W28: =IF(Declarations!$E$29="goods",H28,"")&IF(Declarations!$E$30="goods",I28,"")&IF(Declarations!$E$31="goods",J28,"")&IF(Declarations!$E$32="goods",K28,"")&IF(Declarations!$E$33="goods",L28,"")&IF(Declarations!$E$34="goods",M28,"")&IF(Declarations!$E$35="goods",N28,"")&IF(Declarations!$E$36="goods",O28,"")&IF(Declarations!$E$37="goods",P28,"") -> NIO | X28: =IF(Declarations!$E$29="capital",H28,"")&IF(Declarations!$E$30="capital",I28,"")&IF(Declarations!$E$31="capital",J28,"")&IF(Declarations!$E$32="capital",K28,"")&IF(Declarations!$E$33="capital",L28,"")&IF(Declarations!$E$34="capital",M28,"")&IF(Declarations!$E$35="capital",N28,"")&IF(Declarations!$E$36="capital",O28,"")&IF(Declarations!$E$37="capital",P28,"") -> OINI | Y28: =IF(Declarations!$E$29="information",H28,"")&IF(Declarations!$E$30="information",I28,"")&IF(Declarations!$E$31="information",J28,"")&IF(Declarations!$E$32="information",K28,"")&IF(Declarations!$E$33="information",L28,"")&IF(Declarations!$E$34="information",M28,"")&IF(Declarations!$E$35="information",N28,"")&IF(Declarations!$E$36="information",O28,"")&IF(Declarations!$E$37="information",P28,"") -> IN
A29: 23 | B29: =MOD(INT($A29/2^0),2) -> 1 | C29: =MOD(INT($A29/2^1),2) -> 1 | D29: =MOD(INT($A29/2^2),2) -> 1 | E29: =MOD(INT($A29/2^3),2) -> 0 | F29: =MOD(INT($A29/2^4),2) -> 1 | G29: =MOD(INT($A29/2^5),2) -> 0 | H29: =CHOOSE(1+2*INDEX($B29:$G29,H$3)+INDEX($B29:$G29,H$4),"E","N","O","I") -> I | I29: =CHOOSE(1+2*INDEX($B29:$G29,I$3)+INDEX($B29:$G29,I$4),"E","N","O","I") -> I | J29: =CHOOSE(1+2*INDEX($B29:$G29,J$3)+INDEX($B29:$G29,J$4),"E","N","O","I") -> I | K29: =CHOOSE(1+2*INDEX($B29:$G29,K$3)+INDEX($B29:$G29,K$4),"E","N","O","I") -> I | L29: =CHOOSE(1+2*INDEX($B29:$G29,L$3)+INDEX($B29:$G29,L$4),"E","N","O","I") -> O | M29: =CHOOSE(1+2*INDEX($B29:$G29,M$3)+INDEX($B29:$G29,M$4),"E","N","O","I") -> N | N29: =CHOOSE(1+2*INDEX($B29:$G29,N$3)+INDEX($B29:$G29,N$4),"E","N","O","I") -> I | O29: =CHOOSE(1+2*INDEX($B29:$G29,O$3)+INDEX($B29:$G29,O$4),"E","N","O","I") -> I | P29: =CHOOSE(1+2*INDEX($B29:$G29,P$3)+INDEX($B29:$G29,P$4),"E","N","O","I") -> N | Q29: =COUNTIF($H29:$P29,"I") -> 6 | R29: =COUNTIF($H29:$P29,"N") -> 2 | S29: =COUNTIF($H29:$P29,"O") -> 1 | T29: =COUNTIF($H29:$P29,"E") -> 0 | U29: =SUM(Q29:T29) -> 9 | V29: =H29&I29&J29&K29&L29&M29&N29&O29&P29 -> IIIIONIIN | W29: =IF(Declarations!$E$29="goods",H29,"")&IF(Declarations!$E$30="goods",I29,"")&IF(Declarations!$E$31="goods",J29,"")&IF(Declarations!$E$32="goods",K29,"")&IF(Declarations!$E$33="goods",L29,"")&IF(Declarations!$E$34="goods",M29,"")&IF(Declarations!$E$35="goods",N29,"")&IF(Declarations!$E$36="goods",O29,"")&IF(Declarations!$E$37="goods",P29,"") -> IIO | X29: =IF(Declarations!$E$29="capital",H29,"")&IF(Declarations!$E$30="capital",I29,"")&IF(Declarations!$E$31="capital",J29,"")&IF(Declarations!$E$32="capital",K29,"")&IF(Declarations!$E$33="capital",L29,"")&IF(Declarations!$E$34="capital",M29,"")&IF(Declarations!$E$35="capital",N29,"")&IF(Declarations!$E$36="capital",O29,"")&IF(Declarations!$E$37="capital",P29,"") -> IINI | Y29: =IF(Declarations!$E$29="information",H29,"")&IF(Declarations!$E$30="information",I29,"")&IF(Declarations!$E$31="information",J29,"")&IF(Declarations!$E$32="information",K29,"")&IF(Declarations!$E$33="information",L29,"")&IF(Declarations!$E$34="information",M29,"")&IF(Declarations!$E$35="information",N29,"")&IF(Declarations!$E$36="information",O29,"")&IF(Declarations!$E$37="information",P29,"") -> IN
A30: 24 | B30: =MOD(INT($A30/2^0),2) -> 0 | C30: =MOD(INT($A30/2^1),2) -> 0 | D30: =MOD(INT($A30/2^2),2) -> 0 | E30: =MOD(INT($A30/2^3),2) -> 1 | F30: =MOD(INT($A30/2^4),2) -> 1 | G30: =MOD(INT($A30/2^5),2) -> 0 | H30: =CHOOSE(1+2*INDEX($B30:$G30,H$3)+INDEX($B30:$G30,H$4),"E","N","O","I") -> E | I30: =CHOOSE(1+2*INDEX($B30:$G30,I$3)+INDEX($B30:$G30,I$4),"E","N","O","I") -> E | J30: =CHOOSE(1+2*INDEX($B30:$G30,J$3)+INDEX($B30:$G30,J$4),"E","N","O","I") -> E | K30: =CHOOSE(1+2*INDEX($B30:$G30,K$3)+INDEX($B30:$G30,K$4),"E","N","O","I") -> E | L30: =CHOOSE(1+2*INDEX($B30:$G30,L$3)+INDEX($B30:$G30,L$4),"E","N","O","I") -> N | M30: =CHOOSE(1+2*INDEX($B30:$G30,M$3)+INDEX($B30:$G30,M$4),"E","N","O","I") -> O | N30: =CHOOSE(1+2*INDEX($B30:$G30,N$3)+INDEX($B30:$G30,N$4),"E","N","O","I") -> E | O30: =CHOOSE(1+2*INDEX($B30:$G30,O$3)+INDEX($B30:$G30,O$4),"E","N","O","I") -> O | P30: =CHOOSE(1+2*INDEX($B30:$G30,P$3)+INDEX($B30:$G30,P$4),"E","N","O","I") -> E | Q30: =COUNTIF($H30:$P30,"I") -> 0 | R30: =COUNTIF($H30:$P30,"N") -> 1 | S30: =COUNTIF($H30:$P30,"O") -> 2 | T30: =COUNTIF($H30:$P30,"E") -> 6 | U30: =SUM(Q30:T30) -> 9 | V30: =H30&I30&J30&K30&L30&M30&N30&O30&P30 -> EEEENOEOE | W30: =IF(Declarations!$E$29="goods",H30,"")&IF(Declarations!$E$30="goods",I30,"")&IF(Declarations!$E$31="goods",J30,"")&IF(Declarations!$E$32="goods",K30,"")&IF(Declarations!$E$33="goods",L30,"")&IF(Declarations!$E$34="goods",M30,"")&IF(Declarations!$E$35="goods",N30,"")&IF(Declarations!$E$36="goods",O30,"")&IF(Declarations!$E$37="goods",P30,"") -> EEN | X30: =IF(Declarations!$E$29="capital",H30,"")&IF(Declarations!$E$30="capital",I30,"")&IF(Declarations!$E$31="capital",J30,"")&IF(Declarations!$E$32="capital",K30,"")&IF(Declarations!$E$33="capital",L30,"")&IF(Declarations!$E$34="capital",M30,"")&IF(Declarations!$E$35="capital",N30,"")&IF(Declarations!$E$36="capital",O30,"")&IF(Declarations!$E$37="capital",P30,"") -> EEOO | Y30: =IF(Declarations!$E$29="information",H30,"")&IF(Declarations!$E$30="information",I30,"")&IF(Declarations!$E$31="information",J30,"")&IF(Declarations!$E$32="information",K30,"")&IF(Declarations!$E$33="information",L30,"")&IF(Declarations!$E$34="information",M30,"")&IF(Declarations!$E$35="information",N30,"")&IF(Declarations!$E$36="information",O30,"")&IF(Declarations!$E$37="information",P30,"") -> EE
A31: 25 | B31: =MOD(INT($A31/2^0),2) -> 1 | C31: =MOD(INT($A31/2^1),2) -> 0 | D31: =MOD(INT($A31/2^2),2) -> 0 | E31: =MOD(INT($A31/2^3),2) -> 1 | F31: =MOD(INT($A31/2^4),2) -> 1 | G31: =MOD(INT($A31/2^5),2) -> 0 | H31: =CHOOSE(1+2*INDEX($B31:$G31,H$3)+INDEX($B31:$G31,H$4),"E","N","O","I") -> O | I31: =CHOOSE(1+2*INDEX($B31:$G31,I$3)+INDEX($B31:$G31,I$4),"E","N","O","I") -> N | J31: =CHOOSE(1+2*INDEX($B31:$G31,J$3)+INDEX($B31:$G31,J$4),"E","N","O","I") -> E | K31: =CHOOSE(1+2*INDEX($B31:$G31,K$3)+INDEX($B31:$G31,K$4),"E","N","O","I") -> E | L31: =CHOOSE(1+2*INDEX($B31:$G31,L$3)+INDEX($B31:$G31,L$4),"E","N","O","I") -> N | M31: =CHOOSE(1+2*INDEX($B31:$G31,M$3)+INDEX($B31:$G31,M$4),"E","N","O","I") -> O | N31: =CHOOSE(1+2*INDEX($B31:$G31,N$3)+INDEX($B31:$G31,N$4),"E","N","O","I") -> E | O31: =CHOOSE(1+2*INDEX($B31:$G31,O$3)+INDEX($B31:$G31,O$4),"E","N","O","I") -> O | P31: =CHOOSE(1+2*INDEX($B31:$G31,P$3)+INDEX($B31:$G31,P$4),"E","N","O","I") -> E | Q31: =COUNTIF($H31:$P31,"I") -> 0 | R31: =COUNTIF($H31:$P31,"N") -> 2 | S31: =COUNTIF($H31:$P31,"O") -> 3 | T31: =COUNTIF($H31:$P31,"E") -> 4 | U31: =SUM(Q31:T31) -> 9 | V31: =H31&I31&J31&K31&L31&M31&N31&O31&P31 -> ONEENOEOE | W31: =IF(Declarations!$E$29="goods",H31,"")&IF(Declarations!$E$30="goods",I31,"")&IF(Declarations!$E$31="goods",J31,"")&IF(Declarations!$E$32="goods",K31,"")&IF(Declarations!$E$33="goods",L31,"")&IF(Declarations!$E$34="goods",M31,"")&IF(Declarations!$E$35="goods",N31,"")&IF(Declarations!$E$36="goods",O31,"")&IF(Declarations!$E$37="goods",P31,"") -> OEN | X31: =IF(Declarations!$E$29="capital",H31,"")&IF(Declarations!$E$30="capital",I31,"")&IF(Declarations!$E$31="capital",J31,"")&IF(Declarations!$E$32="capital",K31,"")&IF(Declarations!$E$33="capital",L31,"")&IF(Declarations!$E$34="capital",M31,"")&IF(Declarations!$E$35="capital",N31,"")&IF(Declarations!$E$36="capital",O31,"")&IF(Declarations!$E$37="capital",P31,"") -> NEOO | Y31: =IF(Declarations!$E$29="information",H31,"")&IF(Declarations!$E$30="information",I31,"")&IF(Declarations!$E$31="information",J31,"")&IF(Declarations!$E$32="information",K31,"")&IF(Declarations!$E$33="information",L31,"")&IF(Declarations!$E$34="information",M31,"")&IF(Declarations!$E$35="information",N31,"")&IF(Declarations!$E$36="information",O31,"")&IF(Declarations!$E$37="information",P31,"") -> EE
A32: 26 | B32: =MOD(INT($A32/2^0),2) -> 0 | C32: =MOD(INT($A32/2^1),2) -> 1 | D32: =MOD(INT($A32/2^2),2) -> 0 | E32: =MOD(INT($A32/2^3),2) -> 1 | F32: =MOD(INT($A32/2^4),2) -> 1 | G32: =MOD(INT($A32/2^5),2) -> 0 | H32: =CHOOSE(1+2*INDEX($B32:$G32,H$3)+INDEX($B32:$G32,H$4),"E","N","O","I") -> N | I32: =CHOOSE(1+2*INDEX($B32:$G32,I$3)+INDEX($B32:$G32,I$4),"E","N","O","I") -> O | J32: =CHOOSE(1+2*INDEX($B32:$G32,J$3)+INDEX($B32:$G32,J$4),"E","N","O","I") -> O | K32: =CHOOSE(1+2*INDEX($B32:$G32,K$3)+INDEX($B32:$G32,K$4),"E","N","O","I") -> N | L32: =CHOOSE(1+2*INDEX($B32:$G32,L$3)+INDEX($B32:$G32,L$4),"E","N","O","I") -> N | M32: =CHOOSE(1+2*INDEX($B32:$G32,M$3)+INDEX($B32:$G32,M$4),"E","N","O","I") -> O | N32: =CHOOSE(1+2*INDEX($B32:$G32,N$3)+INDEX($B32:$G32,N$4),"E","N","O","I") -> N | O32: =CHOOSE(1+2*INDEX($B32:$G32,O$3)+INDEX($B32:$G32,O$4),"E","N","O","I") -> I | P32: =CHOOSE(1+2*INDEX($B32:$G32,P$3)+INDEX($B32:$G32,P$4),"E","N","O","I") -> N | Q32: =COUNTIF($H32:$P32,"I") -> 1 | R32: =COUNTIF($H32:$P32,"N") -> 5 | S32: =COUNTIF($H32:$P32,"O") -> 3 | T32: =COUNTIF($H32:$P32,"E") -> 0 | U32: =SUM(Q32:T32) -> 9 | V32: =H32&I32&J32&K32&L32&M32&N32&O32&P32 -> NOONNONIN | W32: =IF(Declarations!$E$29="goods",H32,"")&IF(Declarations!$E$30="goods",I32,"")&IF(Declarations!$E$31="goods",J32,"")&IF(Declarations!$E$32="goods",K32,"")&IF(Declarations!$E$33="goods",L32,"")&IF(Declarations!$E$34="goods",M32,"")&IF(Declarations!$E$35="goods",N32,"")&IF(Declarations!$E$36="goods",O32,"")&IF(Declarations!$E$37="goods",P32,"") -> NON | X32: =IF(Declarations!$E$29="capital",H32,"")&IF(Declarations!$E$30="capital",I32,"")&IF(Declarations!$E$31="capital",J32,"")&IF(Declarations!$E$32="capital",K32,"")&IF(Declarations!$E$33="capital",L32,"")&IF(Declarations!$E$34="capital",M32,"")&IF(Declarations!$E$35="capital",N32,"")&IF(Declarations!$E$36="capital",O32,"")&IF(Declarations!$E$37="capital",P32,"") -> ONOI | Y32: =IF(Declarations!$E$29="information",H32,"")&IF(Declarations!$E$30="information",I32,"")&IF(Declarations!$E$31="information",J32,"")&IF(Declarations!$E$32="information",K32,"")&IF(Declarations!$E$33="information",L32,"")&IF(Declarations!$E$34="information",M32,"")&IF(Declarations!$E$35="information",N32,"")&IF(Declarations!$E$36="information",O32,"")&IF(Declarations!$E$37="information",P32,"") -> NN
A33: 27 | B33: =MOD(INT($A33/2^0),2) -> 1 | C33: =MOD(INT($A33/2^1),2) -> 1 | D33: =MOD(INT($A33/2^2),2) -> 0 | E33: =MOD(INT($A33/2^3),2) -> 1 | F33: =MOD(INT($A33/2^4),2) -> 1 | G33: =MOD(INT($A33/2^5),2) -> 0 | H33: =CHOOSE(1+2*INDEX($B33:$G33,H$3)+INDEX($B33:$G33,H$4),"E","N","O","I") -> I | I33: =CHOOSE(1+2*INDEX($B33:$G33,I$3)+INDEX($B33:$G33,I$4),"E","N","O","I") -> I | J33: =CHOOSE(1+2*INDEX($B33:$G33,J$3)+INDEX($B33:$G33,J$4),"E","N","O","I") -> O | K33: =CHOOSE(1+2*INDEX($B33:$G33,K$3)+INDEX($B33:$G33,K$4),"E","N","O","I") -> N | L33: =CHOOSE(1+2*INDEX($B33:$G33,L$3)+INDEX($B33:$G33,L$4),"E","N","O","I") -> N | M33: =CHOOSE(1+2*INDEX($B33:$G33,M$3)+INDEX($B33:$G33,M$4),"E","N","O","I") -> O | N33: =CHOOSE(1+2*INDEX($B33:$G33,N$3)+INDEX($B33:$G33,N$4),"E","N","O","I") -> N | O33: =CHOOSE(1+2*INDEX($B33:$G33,O$3)+INDEX($B33:$G33,O$4),"E","N","O","I") -> I | P33: =CHOOSE(1+2*INDEX($B33:$G33,P$3)+INDEX($B33:$G33,P$4),"E","N","O","I") -> N | Q33: =COUNTIF($H33:$P33,"I") -> 3 | R33: =COUNTIF($H33:$P33,"N") -> 4 | S33: =COUNTIF($H33:$P33,"O") -> 2 | T33: =COUNTIF($H33:$P33,"E") -> 0 | U33: =SUM(Q33:T33) -> 9 | V33: =H33&I33&J33&K33&L33&M33&N33&O33&P33 -> IIONNONIN | W33: =IF(Declarations!$E$29="goods",H33,"")&IF(Declarations!$E$30="goods",I33,"")&IF(Declarations!$E$31="goods",J33,"")&IF(Declarations!$E$32="goods",K33,"")&IF(Declarations!$E$33="goods",L33,"")&IF(Declarations!$E$34="goods",M33,"")&IF(Declarations!$E$35="goods",N33,"")&IF(Declarations!$E$36="goods",O33,"")&IF(Declarations!$E$37="goods",P33,"") -> ION | X33: =IF(Declarations!$E$29="capital",H33,"")&IF(Declarations!$E$30="capital",I33,"")&IF(Declarations!$E$31="capital",J33,"")&IF(Declarations!$E$32="capital",K33,"")&IF(Declarations!$E$33="capital",L33,"")&IF(Declarations!$E$34="capital",M33,"")&IF(Declarations!$E$35="capital",N33,"")&IF(Declarations!$E$36="capital",O33,"")&IF(Declarations!$E$37="capital",P33,"") -> INOI | Y33: =IF(Declarations!$E$29="information",H33,"")&IF(Declarations!$E$30="information",I33,"")&IF(Declarations!$E$31="information",J33,"")&IF(Declarations!$E$32="information",K33,"")&IF(Declarations!$E$33="information",L33,"")&IF(Declarations!$E$34="information",M33,"")&IF(Declarations!$E$35="information",N33,"")&IF(Declarations!$E$36="information",O33,"")&IF(Declarations!$E$37="information",P33,"") -> NN
A34: 28 | B34: =MOD(INT($A34/2^0),2) -> 0 | C34: =MOD(INT($A34/2^1),2) -> 0 | D34: =MOD(INT($A34/2^2),2) -> 1 | E34: =MOD(INT($A34/2^3),2) -> 1 | F34: =MOD(INT($A34/2^4),2) -> 1 | G34: =MOD(INT($A34/2^5),2) -> 0 | H34: =CHOOSE(1+2*INDEX($B34:$G34,H$3)+INDEX($B34:$G34,H$4),"E","N","O","I") -> E | I34: =CHOOSE(1+2*INDEX($B34:$G34,I$3)+INDEX($B34:$G34,I$4),"E","N","O","I") -> E | J34: =CHOOSE(1+2*INDEX($B34:$G34,J$3)+INDEX($B34:$G34,J$4),"E","N","O","I") -> N | K34: =CHOOSE(1+2*INDEX($B34:$G34,K$3)+INDEX($B34:$G34,K$4),"E","N","O","I") -> O | L34: =CHOOSE(1+2*INDEX($B34:$G34,L$3)+INDEX($B34:$G34,L$4),"E","N","O","I") -> I | M34: =CHOOSE(1+2*INDEX($B34:$G34,M$3)+INDEX($B34:$G34,M$4),"E","N","O","I") -> I | N34: =CHOOSE(1+2*INDEX($B34:$G34,N$3)+INDEX($B34:$G34,N$4),"E","N","O","I") -> O | O34: =CHOOSE(1+2*INDEX($B34:$G34,O$3)+INDEX($B34:$G34,O$4),"E","N","O","I") -> O | P34: =CHOOSE(1+2*INDEX($B34:$G34,P$3)+INDEX($B34:$G34,P$4),"E","N","O","I") -> E | Q34: =COUNTIF($H34:$P34,"I") -> 2 | R34: =COUNTIF($H34:$P34,"N") -> 1 | S34: =COUNTIF($H34:$P34,"O") -> 3 | T34: =COUNTIF($H34:$P34,"E") -> 3 | U34: =SUM(Q34:T34) -> 9 | V34: =H34&I34&J34&K34&L34&M34&N34&O34&P34 -> EENOIIOOE | W34: =IF(Declarations!$E$29="goods",H34,"")&IF(Declarations!$E$30="goods",I34,"")&IF(Declarations!$E$31="goods",J34,"")&IF(Declarations!$E$32="goods",K34,"")&IF(Declarations!$E$33="goods",L34,"")&IF(Declarations!$E$34="goods",M34,"")&IF(Declarations!$E$35="goods",N34,"")&IF(Declarations!$E$36="goods",O34,"")&IF(Declarations!$E$37="goods",P34,"") -> ENI | X34: =IF(Declarations!$E$29="capital",H34,"")&IF(Declarations!$E$30="capital",I34,"")&IF(Declarations!$E$31="capital",J34,"")&IF(Declarations!$E$32="capital",K34,"")&IF(Declarations!$E$33="capital",L34,"")&IF(Declarations!$E$34="capital",M34,"")&IF(Declarations!$E$35="capital",N34,"")&IF(Declarations!$E$36="capital",O34,"")&IF(Declarations!$E$37="capital",P34,"") -> EOIO | Y34: =IF(Declarations!$E$29="information",H34,"")&IF(Declarations!$E$30="information",I34,"")&IF(Declarations!$E$31="information",J34,"")&IF(Declarations!$E$32="information",K34,"")&IF(Declarations!$E$33="information",L34,"")&IF(Declarations!$E$34="information",M34,"")&IF(Declarations!$E$35="information",N34,"")&IF(Declarations!$E$36="information",O34,"")&IF(Declarations!$E$37="information",P34,"") -> OE
A35: 29 | B35: =MOD(INT($A35/2^0),2) -> 1 | C35: =MOD(INT($A35/2^1),2) -> 0 | D35: =MOD(INT($A35/2^2),2) -> 1 | E35: =MOD(INT($A35/2^3),2) -> 1 | F35: =MOD(INT($A35/2^4),2) -> 1 | G35: =MOD(INT($A35/2^5),2) -> 0 | H35: =CHOOSE(1+2*INDEX($B35:$G35,H$3)+INDEX($B35:$G35,H$4),"E","N","O","I") -> O | I35: =CHOOSE(1+2*INDEX($B35:$G35,I$3)+INDEX($B35:$G35,I$4),"E","N","O","I") -> N | J35: =CHOOSE(1+2*INDEX($B35:$G35,J$3)+INDEX($B35:$G35,J$4),"E","N","O","I") -> N | K35: =CHOOSE(1+2*INDEX($B35:$G35,K$3)+INDEX($B35:$G35,K$4),"E","N","O","I") -> O | L35: =CHOOSE(1+2*INDEX($B35:$G35,L$3)+INDEX($B35:$G35,L$4),"E","N","O","I") -> I | M35: =CHOOSE(1+2*INDEX($B35:$G35,M$3)+INDEX($B35:$G35,M$4),"E","N","O","I") -> I | N35: =CHOOSE(1+2*INDEX($B35:$G35,N$3)+INDEX($B35:$G35,N$4),"E","N","O","I") -> O | O35: =CHOOSE(1+2*INDEX($B35:$G35,O$3)+INDEX($B35:$G35,O$4),"E","N","O","I") -> O | P35: =CHOOSE(1+2*INDEX($B35:$G35,P$3)+INDEX($B35:$G35,P$4),"E","N","O","I") -> E | Q35: =COUNTIF($H35:$P35,"I") -> 2 | R35: =COUNTIF($H35:$P35,"N") -> 2 | S35: =COUNTIF($H35:$P35,"O") -> 4 | T35: =COUNTIF($H35:$P35,"E") -> 1 | U35: =SUM(Q35:T35) -> 9 | V35: =H35&I35&J35&K35&L35&M35&N35&O35&P35 -> ONNOIIOOE | W35: =IF(Declarations!$E$29="goods",H35,"")&IF(Declarations!$E$30="goods",I35,"")&IF(Declarations!$E$31="goods",J35,"")&IF(Declarations!$E$32="goods",K35,"")&IF(Declarations!$E$33="goods",L35,"")&IF(Declarations!$E$34="goods",M35,"")&IF(Declarations!$E$35="goods",N35,"")&IF(Declarations!$E$36="goods",O35,"")&IF(Declarations!$E$37="goods",P35,"") -> ONI | X35: =IF(Declarations!$E$29="capital",H35,"")&IF(Declarations!$E$30="capital",I35,"")&IF(Declarations!$E$31="capital",J35,"")&IF(Declarations!$E$32="capital",K35,"")&IF(Declarations!$E$33="capital",L35,"")&IF(Declarations!$E$34="capital",M35,"")&IF(Declarations!$E$35="capital",N35,"")&IF(Declarations!$E$36="capital",O35,"")&IF(Declarations!$E$37="capital",P35,"") -> NOIO | Y35: =IF(Declarations!$E$29="information",H35,"")&IF(Declarations!$E$30="information",I35,"")&IF(Declarations!$E$31="information",J35,"")&IF(Declarations!$E$32="information",K35,"")&IF(Declarations!$E$33="information",L35,"")&IF(Declarations!$E$34="information",M35,"")&IF(Declarations!$E$35="information",N35,"")&IF(Declarations!$E$36="information",O35,"")&IF(Declarations!$E$37="information",P35,"") -> OE
... A69: 63 | B69: =MOD(INT($A69/2^0),2) -> 1 | C69: =MOD(INT($A69/2^1),2) -> 1 | D69: =MOD(INT($A69/2^2),2) -> 1 | E69: =MOD(INT($A69/2^3),2) -> 1 | F69: =MOD(INT($A69/2^4),2) -> 1 | G69: =MOD(INT($A69/2^5),2) -> 1 | H69: =CHOOSE(1+2*INDEX($B69:$G69,H$3)+INDEX($B69:$G69,H$4),"E","N","O","I") -> I | I69: =CHOOSE(1+2*INDEX($B69:$G69,I$3)+INDEX($B69:$G69,I$4),"E","N","O","I") -> I | J69: =CHOOSE(1+2*INDEX($B69:$G69,J$3)+INDEX($B69:$G69,J$4),"E","N","O","I") -> I | K69: =CHOOSE(1+2*INDEX($B69:$G69,K$3)+INDEX($B69:$G69,K$4),"E","N","O","I") -> I | L69: =CHOOSE(1+2*INDEX($B69:$G69,L$3)+INDEX($B69:$G69,L$4),"E","N","O","I") -> I | M69: =CHOOSE(1+2*INDEX($B69:$G69,M$3)+INDEX($B69:$G69,M$4),"E","N","O","I") -> I | N69: =CHOOSE(1+2*INDEX($B69:$G69,N$3)+INDEX($B69:$G69,N$4),"E","N","O","I") -> I | O69: =CHOOSE(1+2*INDEX($B69:$G69,O$3)+INDEX($B69:$G69,O$4),"E","N","O","I") -> I | P69: =CHOOSE(1+2*INDEX($B69:$G69,P$3)+INDEX($B69:$G69,P$4),"E","N","O","I") -> I | Q69: =COUNTIF($H69:$P69,"I") -> 9 | R69: =COUNTIF($H69:$P69,"N") -> 0 | S69: =COUNTIF($H69:$P69,"O") -> 0 | T69: =COUNTIF($H69:$P69,"E") -> 0 | U69: =SUM(Q69:T69) -> 9 | V69: =H69&I69&J69&K69&L69&M69&N69&O69&P69 -> IIIIIIIII | W69: =IF(Declarations!$E$29="goods",H69,"")&IF(Declarations!$E$30="goods",I69,"")&IF(Declarations!$E$31="goods",J69,"")&IF(Declarations!$E$32="goods",K69,"")&IF(Declarations!$E$33="goods",L69,"")&IF(Declarations!$E$34="goods",M69,"")&IF(Declarations!$E$35="goods",N69,"")&IF(Declarations!$E$36="goods",O69,"")&IF(Declarations!$E$37="goods",P69,"") -> III | X69: =IF(Declarations!$E$29="capital",H69,"")&IF(Declarations!$E$30="capital",I69,"")&IF(Declarations!$E$31="capital",J69,"")&IF(Declarations!$E$32="capital",K69,"")&IF(Declarations!$E$33="capital",L69,"")&IF(Declarations!$E$34="capital",M69,"")&IF(Declarations!$E$35="capital",N69,"")&IF(Declarations!$E$36="capital",O69,"")&IF(Declarations!$E$37="capital",P69,"") -> IIII | Y69: =IF(Declarations!$E$29="information",H69,"")&IF(Declarations!$E$30="information",I69,"")&IF(Declarations!$E$31="information",J69,"")&IF(Declarations!$E$32="information",K69,"")&IF(Declarations!$E$33="information",L69,"")&IF(Declarations!$E$34="information",M69,"")&IF(Declarations!$E$35="information",N69,"")&IF(Declarations!$E$36="information",O69,"")&IF(Declarations!$E$37="information",P69,"") -> II

Sheet Levels
A1: Change levels: each subsystem's environment includes its siblings (Definition 2.4; Figure 2.3; AXIOM Lab 1.2, step 3)
A3: Subsystem to inspect | B3: Digital Solutions
A4: Its parent | B4: =INDEX(C7:C16,MATCH(B3,A7:A16,0)) -> Meridian Group
A6: Subsystem | B6: Level | C6: Parent | D6: Sibling: in its environment | E6: One of its units | F6: A sibling's unit: in its environment
A7: Meridian Group | B7: group | C7: - | D7: =IF(AND(C7=$B$4,A7<>$B$3),1,0) -> 0 | E7: =IF(C7=$B$3,1,0) -> 0 | F7: =IF(COUNTIFS($A$7:$A$16,C7,$D$7:$D$16,1)>0,1,0) -> 0
A8: Industrial Systems | B8: division | C8: Meridian Group | D8: =IF(AND(C8=$B$4,A8<>$B$3),1,0) -> 1 | E8: =IF(C8=$B$3,1,0) -> 0 | F8: =IF(COUNTIFS($A$7:$A$16,C8,$D$7:$D$16,1)>0,1,0) -> 0
A9: Digital Solutions | B9: division | C9: Meridian Group | D9: =IF(AND(C9=$B$4,A9<>$B$3),1,0) -> 0 | E9: =IF(C9=$B$3,1,0) -> 0 | F9: =IF(COUNTIFS($A$7:$A$16,C9,$D$7:$D$16,1)>0,1,0) -> 0
A10: Advanced Materials | B10: division | C10: Meridian Group | D10: =IF(AND(C10=$B$4,A10<>$B$3),1,0) -> 1 | E10: =IF(C10=$B$3,1,0) -> 0 | F10: =IF(COUNTIFS($A$7:$A$16,C10,$D$7:$D$16,1)>0,1,0) -> 0
A11: Plants | B11: unit | C11: Industrial Systems | D11: =IF(AND(C11=$B$4,A11<>$B$3),1,0) -> 0 | E11: =IF(C11=$B$3,1,0) -> 0 | F11: =IF(COUNTIFS($A$7:$A$16,C11,$D$7:$D$16,1)>0,1,0) -> 1
A12: Service | B12: unit | C12: Industrial Systems | D12: =IF(AND(C12=$B$4,A12<>$B$3),1,0) -> 0 | E12: =IF(C12=$B$3,1,0) -> 0 | F12: =IF(COUNTIFS($A$7:$A$16,C12,$D$7:$D$16,1)>0,1,0) -> 1
A13: Platform | B13: unit | C13: Digital Solutions | D13: =IF(AND(C13=$B$4,A13<>$B$3),1,0) -> 0 | E13: =IF(C13=$B$3,1,0) -> 1 | F13: =IF(COUNTIFS($A$7:$A$16,C13,$D$7:$D$16,1)>0,1,0) -> 0
A14: Apps | B14: unit | C14: Digital Solutions | D14: =IF(AND(C14=$B$4,A14<>$B$3),1,0) -> 0 | E14: =IF(C14=$B$3,1,0) -> 1 | F14: =IF(COUNTIFS($A$7:$A$16,C14,$D$7:$D$16,1)>0,1,0) -> 0
A15: Polymers | B15: unit | C15: Advanced Materials | D15: =IF(AND(C15=$B$4,A15<>$B$3),1,0) -> 0 | E15: =IF(C15=$B$3,1,0) -> 0 | F15: =IF(COUNTIFS($A$7:$A$16,C15,$D$7:$D$16,1)>0,1,0) -> 1
A16: Composites | B16: unit | C16: Advanced Materials | D16: =IF(AND(C16=$B$4,A16<>$B$3),1,0) -> 0 | E16: =IF(C16=$B$3,1,0) -> 0 | F16: =IF(COUNTIFS($A$7:$A$16,C16,$D$7:$D$16,1)>0,1,0) -> 1
A18: Divisions (Figure 2.3) | B18: =COUNTIF(B7:B16,"division") -> 3
A19: Units (Figure 2.3) | B19: =COUNTIF(B7:B16,"unit") -> 6
A20: Sibling subsystems in its environment | B20: =SUM(D7:D16) -> 2
A21: Siblings' units in its environment | B21: =SUM(F7:F16) -> 4
A22: Its own units | B22: =SUM(E7:E16) -> 2
A23: Plus the external environment at every level: demand, technology, regulation, capital markets (Figure 2.3). Try Platform, or Industrial Systems.
A25: Coupling (Figure 2.3) | B25: From | C25: To | D25: Group boundary | E25: Industrial Systems | F25: Digital Solutions | G25: Advanced Materials
A26: Inside the boundary? | D26: all three | E26: IS only | F26: DS only | G26: AM only
A27: C1 | B27: Industrial Systems | C27: Digital Solutions | D27: =IF(AND(IF(OR($B27="Industrial Systems",$B27="Digital Solutions",$B27="Advanced Materials"),1,0)=1,IF(OR($C27="Industrial Systems",$C27="Digital Solutions",$C27="Advanced Materials"),1,0)=1),"interior",IF(AND(IF(OR($B27="Industrial Systems",$B27="Digital Solutions",$B27="Advanced Materials"),1,0)=0,IF(OR($C27="Industrial Systems",$C27="Digital Solutions",$C27="Advanced Materials"),1,0)=1),"input",IF(AND(IF(OR($B27="Industrial Systems",$B27="Digital Solutions",$B27="Advanced Materials"),1,0)=1,IF(OR($C27="Industrial Systems",$C27="Digital Solutions",$C27="Advanced Materials"),1,0)=0),"output","environmental"))) -> interior | E27: =IF(AND(IF(OR($B27="Industrial Systems"),1,0)=1,IF(OR($C27="Industrial Systems"),1,0)=1),"interior",IF(AND(IF(OR($B27="Industrial Systems"),1,0)=0,IF(OR($C27="Industrial Systems"),1,0)=1),"input",IF(AND(IF(OR($B27="Industrial Systems"),1,0)=1,IF(OR($C27="Industrial Systems"),1,0)=0),"output","environmental"))) -> output | F27: =IF(AND(IF(OR($B27="Digital Solutions"),1,0)=1,IF(OR($C27="Digital Solutions"),1,0)=1),"interior",IF(AND(IF(OR($B27="Digital Solutions"),1,0)=0,IF(OR($C27="Digital Solutions"),1,0)=1),"input",IF(AND(IF(OR($B27="Digital Solutions"),1,0)=1,IF(OR($C27="Digital Solutions"),1,0)=0),"output","environmental"))) -> input | G27: =IF(AND(IF(OR($B27="Advanced Materials"),1,0)=1,IF(OR($C27="Advanced Materials"),1,0)=1),"interior",IF(AND(IF(OR($B27="Advanced Materials"),1,0)=0,IF(OR($C27="Advanced Materials"),1,0)=1),"input",IF(AND(IF(OR($B27="Advanced Materials"),1,0)=1,IF(OR($C27="Advanced Materials"),1,0)=0),"output","environmental"))) -> environmental
A28: C2 | B28: Digital Solutions | C28: Industrial Systems | D28: =IF(AND(IF(OR($B28="Industrial Systems",$B28="Digital Solutions",$B28="Advanced Materials"),1,0)=1,IF(OR($C28="Industrial Systems",$C28="Digital Solutions",$C28="Advanced Materials"),1,0)=1),"interior",IF(AND(IF(OR($B28="Industrial Systems",$B28="Digital Solutions",$B28="Advanced Materials"),1,0)=0,IF(OR($C28="Industrial Systems",$C28="Digital Solutions",$C28="Advanced Materials"),1,0)=1),"input",IF(AND(IF(OR($B28="Industrial Systems",$B28="Digital Solutions",$B28="Advanced Materials"),1,0)=1,IF(OR($C28="Industrial Systems",$C28="Digital Solutions",$C28="Advanced Materials"),1,0)=0),"output","environmental"))) -> interior | E28: =IF(AND(IF(OR($B28="Industrial Systems"),1,0)=1,IF(OR($C28="Industrial Systems"),1,0)=1),"interior",IF(AND(IF(OR($B28="Industrial Systems"),1,0)=0,IF(OR($C28="Industrial Systems"),1,0)=1),"input",IF(AND(IF(OR($B28="Industrial Systems"),1,0)=1,IF(OR($C28="Industrial Systems"),1,0)=0),"output","environmental"))) -> input | F28: =IF(AND(IF(OR($B28="Digital Solutions"),1,0)=1,IF(OR($C28="Digital Solutions"),1,0)=1),"interior",IF(AND(IF(OR($B28="Digital Solutions"),1,0)=0,IF(OR($C28="Digital Solutions"),1,0)=1),"input",IF(AND(IF(OR($B28="Digital Solutions"),1,0)=1,IF(OR($C28="Digital Solutions"),1,0)=0),"output","environmental"))) -> output | G28: =IF(AND(IF(OR($B28="Advanced Materials"),1,0)=1,IF(OR($C28="Advanced Materials"),1,0)=1),"interior",IF(AND(IF(OR($B28="Advanced Materials"),1,0)=0,IF(OR($C28="Advanced Materials"),1,0)=1),"input",IF(AND(IF(OR($B28="Advanced Materials"),1,0)=1,IF(OR($C28="Advanced Materials"),1,0)=0),"output","environmental"))) -> environmental
A29: C3 | B29: Digital Solutions | C29: Advanced Materials | D29: =IF(AND(IF(OR($B29="Industrial Systems",$B29="Digital Solutions",$B29="Advanced Materials"),1,0)=1,IF(OR($C29="Industrial Systems",$C29="Digital Solutions",$C29="Advanced Materials"),1,0)=1),"interior",IF(AND(IF(OR($B29="Industrial Systems",$B29="Digital Solutions",$B29="Advanced Materials"),1,0)=0,IF(OR($C29="Industrial Systems",$C29="Digital Solutions",$C29="Advanced Materials"),1,0)=1),"input",IF(AND(IF(OR($B29="Industrial Systems",$B29="Digital Solutions",$B29="Advanced Materials"),1,0)=1,IF(OR($C29="Industrial Systems",$C29="Digital Solutions",$C29="Advanced Materials"),1,0)=0),"output","environmental"))) -> interior | E29: =IF(AND(IF(OR($B29="Industrial Systems"),1,0)=1,IF(OR($C29="Industrial Systems"),1,0)=1),"interior",IF(AND(IF(OR($B29="Industrial Systems"),1,0)=0,IF(OR($C29="Industrial Systems"),1,0)=1),"input",IF(AND(IF(OR($B29="Industrial Systems"),1,0)=1,IF(OR($C29="Industrial Systems"),1,0)=0),"output","environmental"))) -> environmental | F29: =IF(AND(IF(OR($B29="Digital Solutions"),1,0)=1,IF(OR($C29="Digital Solutions"),1,0)=1),"interior",IF(AND(IF(OR($B29="Digital Solutions"),1,0)=0,IF(OR($C29="Digital Solutions"),1,0)=1),"input",IF(AND(IF(OR($B29="Digital Solutions"),1,0)=1,IF(OR($C29="Digital Solutions"),1,0)=0),"output","environmental"))) -> output | G29: =IF(AND(IF(OR($B29="Advanced Materials"),1,0)=1,IF(OR($C29="Advanced Materials"),1,0)=1),"interior",IF(AND(IF(OR($B29="Advanced Materials"),1,0)=0,IF(OR($C29="Advanced Materials"),1,0)=1),"input",IF(AND(IF(OR($B29="Advanced Materials"),1,0)=1,IF(OR($C29="Advanced Materials"),1,0)=0),"output","environmental"))) -> input
A30: C4 | B30: Advanced Materials | C30: Digital Solutions | D30: =IF(AND(IF(OR($B30="Industrial Systems",$B30="Digital Solutions",$B30="Advanced Materials"),1,0)=1,IF(OR($C30="Industrial Systems",$C30="Digital Solutions",$C30="Advanced Materials"),1,0)=1),"interior",IF(AND(IF(OR($B30="Industrial Systems",$B30="Digital Solutions",$B30="Advanced Materials"),1,0)=0,IF(OR($C30="Industrial Systems",$C30="Digital Solutions",$C30="Advanced Materials"),1,0)=1),"input",IF(AND(IF(OR($B30="Industrial Systems",$B30="Digital Solutions",$B30="Advanced Materials"),1,0)=1,IF(OR($C30="Industrial Systems",$C30="Digital Solutions",$C30="Advanced Materials"),1,0)=0),"output","environmental"))) -> interior | E30: =IF(AND(IF(OR($B30="Industrial Systems"),1,0)=1,IF(OR($C30="Industrial Systems"),1,0)=1),"interior",IF(AND(IF(OR($B30="Industrial Systems"),1,0)=0,IF(OR($C30="Industrial Systems"),1,0)=1),"input",IF(AND(IF(OR($B30="Industrial Systems"),1,0)=1,IF(OR($C30="Industrial Systems"),1,0)=0),"output","environmental"))) -> environmental | F30: =IF(AND(IF(OR($B30="Digital Solutions"),1,0)=1,IF(OR($C30="Digital Solutions"),1,0)=1),"interior",IF(AND(IF(OR($B30="Digital Solutions"),1,0)=0,IF(OR($C30="Digital Solutions"),1,0)=1),"input",IF(AND(IF(OR($B30="Digital Solutions"),1,0)=1,IF(OR($C30="Digital Solutions"),1,0)=0),"output","environmental"))) -> input | G30: =IF(AND(IF(OR($B30="Advanced Materials"),1,0)=1,IF(OR($C30="Advanced Materials"),1,0)=1),"interior",IF(AND(IF(OR($B30="Advanced Materials"),1,0)=0,IF(OR($C30="Advanced Materials"),1,0)=1),"input",IF(AND(IF(OR($B30="Advanced Materials"),1,0)=1,IF(OR($C30="Advanced Materials"),1,0)=0),"output","environmental"))) -> output
A32: Interior at the group level; at the division level the coupling crosses the boundary of each division it joins and is environmental for the third.

Sheet Feedback
A1: Close the loop: the turnaround's efficiency program as state feedback (Definition 2.5; Proposition 2.2; AXIOM Lab 1.2, step 4)
A2: Rule u_k = K (target - x_k); transition x_k+1 = x_k + u_k + w_k. Chapter 1's model: target 79, speed 0.60 a year, K = 1 - exp(-0.60) = 0.451 (Declarations).
A4: A gain to explore (try 0.25, 1, 1.6, 2.2) | B4: 1.6
A6: Year | B6: Feedback off | C6: The turnaround's rule | D6: The gain to explore | E6: Environment input w | F6: Rule, then transition | G6: Closed-loop map | H6: |difference|
A7: 0 | B7: =Eff_today -> 71 | C7: =Eff_today -> 71 | D7: =Eff_today -> 71 | E7: =IF(A7>=5,-1,0)+0.5*(-1)^A7 -> 0.5 | F7: =Eff_today -> 71 | G7: =Eff_today -> 71 | H7: =ABS(F7-G7) -> 0
A8: 1 | B8: =B7+0*(Eff_target-B7) -> 71 | C8: =C7+K_turn*(Eff_target-C7) -> 74.609507 | D8: =D7+$B$4*(Eff_target-D7) -> 83.8 | E8: =IF(A8>=5,-1,0)+0.5*(-1)^A8 -> -0.5 | F8: =F7+K_turn*(Eff_target-F7)+E7 -> 75.109507 | G8: =(1-K_turn)*G7+K_turn*Eff_target+E7 -> 75.109507 | H8: =ABS(F8-G8) -> 0
A9: 2 | B9: =B8+0*(Eff_target-B8) -> 71 | C9: =C8+K_turn*(Eff_target-C8) -> 76.590446 | D9: =D8+$B$4*(Eff_target-D8) -> 76.12 | E9: =IF(A9>=5,-1,0)+0.5*(-1)^A9 -> 0.5 | F9: =F8+K_turn*(Eff_target-F8)+E8 -> 76.364852 | G9: =(1-K_turn)*G8+K_turn*Eff_target+E8 -> 76.364852 | H9: =ABS(F9-G9) -> 0
A10: 3 | B10: =B9+0*(Eff_target-B9) -> 71 | C10: =C9+K_turn*(Eff_target-C9) -> 77.677609 | D10: =D9+$B$4*(Eff_target-D9) -> 80.728 | E10: =IF(A10>=5,-1,0)+0.5*(-1)^A10 -> -0.5 | F10: =F9+K_turn*(Eff_target-F9)+E9 -> 78.0538 | G10: =(1-K_turn)*G9+K_turn*Eff_target+E9 -> 78.0538 | H10: =ABS(F10-G10) -> 0
A11: 4 | B11: =B10+0*(Eff_target-B10) -> 71 | C11: =C10+K_turn*(Eff_target-C10) -> 78.274256 | D11: =D10+$B$4*(Eff_target-D10) -> 77.9632 | E11: =IF(A11>=5,-1,0)+0.5*(-1)^A11 -> 0.5 | F11: =F10+K_turn*(Eff_target-F10)+E10 -> 77.980715 | G11: =(1-K_turn)*G10+K_turn*Eff_target+E10 -> 77.980715 | H11: =ABS(F11-G11) -> 0
A12: 5 | B12: =B11+0*(Eff_target-B11) -> 71 | C12: =C11+K_turn*(Eff_target-C11) -> 78.601703 | D12: =D11+$B$4*(Eff_target-D11) -> 79.62208 | E12: =IF(A12>=5,-1,0)+0.5*(-1)^A12 -> -1.5 | F12: =F11+K_turn*(Eff_target-F11)+E11 -> 78.940604 | G12: =(1-K_turn)*G11+K_turn*Eff_target+E11 -> 78.940604 | H12: =ABS(F12-G12) -> 0
A13: 6 | B13: =B12+0*(Eff_target-B12) -> 71 | C13: =C12+K_turn*(Eff_target-C12) -> 78.78141 | D13: =D12+$B$4*(Eff_target-D12) -> 78.626752 | E13: =IF(A13>=5,-1,0)+0.5*(-1)^A13 -> -0.5 | F13: =F12+K_turn*(Eff_target-F12)+E12 -> 77.467403 | G13: =(1-K_turn)*G12+K_turn*Eff_target+E12 -> 77.467403 | H13: =ABS(F13-G13) -> 0
A14: 7 | B14: =B13+0*(Eff_target-B13) -> 71 | C14: =C13+K_turn*(Eff_target-C13) -> 78.880035 | D14: =D13+$B$4*(Eff_target-D13) -> 79.223949 | E14: =IF(A14>=5,-1,0)+0.5*(-1)^A14 -> -1.5 | F14: =F13+K_turn*(Eff_target-F13)+E13 -> 77.658893 | G14: =(1-K_turn)*G13+K_turn*Eff_target+E13 -> 77.658893 | H14: =ABS(F14-G14) -> 0
A15: 8 | B15: =B14+0*(Eff_target-B14) -> 71 | C15: =C14+K_turn*(Eff_target-C14) -> 78.934162 | D15: =D14+$B$4*(Eff_target-D14) -> 78.865631 | E15: =IF(A15>=5,-1,0)+0.5*(-1)^A15 -> -0.5 | F15: =F14+K_turn*(Eff_target-F14)+E14 -> 76.763985 | G15: =(1-K_turn)*G14+K_turn*Eff_target+E14 -> 76.763985 | H15: =ABS(F15-G15) -> 0
A16: 9 | B16: =B15+0*(Eff_target-B15) -> 71 | C16: =C15+K_turn*(Eff_target-C15) -> 78.963867 | D16: =D15+$B$4*(Eff_target-D15) -> 79.080622 | E16: =IF(A16>=5,-1,0)+0.5*(-1)^A16 -> -1.5 | F16: =F15+K_turn*(Eff_target-F15)+E15 -> 77.272849 | G16: =(1-K_turn)*G15+K_turn*Eff_target+E15 -> 77.272849 | H16: =ABS(F16-G16) -> 0
A17: 10 | B17: =B16+0*(Eff_target-B16) -> 71 | C17: =C16+K_turn*(Eff_target-C16) -> 78.98017 | D17: =D16+$B$4*(Eff_target-D16) -> 78.951627 | E17: =IF(A17>=5,-1,0)+0.5*(-1)^A17 -> -0.5 | F17: =F16+K_turn*(Eff_target-F16)+E16 -> 76.552119 | G17: =(1-K_turn)*G16+K_turn*Eff_target+E16 -> 76.552119 | H17: =ABS(F17-G17) -> 0
A18: 11 | B18: =B17+0*(Eff_target-B17) -> 71 | C18: =C17+K_turn*(Eff_target-C17) -> 78.989117 | D18: =D17+$B$4*(Eff_target-D17) -> 79.029024 | E18: =IF(A18>=5,-1,0)+0.5*(-1)^A18 -> -1.5 | F18: =F17+K_turn*(Eff_target-F17)+E17 -> 77.156575 | G18: =(1-K_turn)*G17+K_turn*Eff_target+E17 -> 77.156575 | H18: =ABS(F18-G18) -> 0
A19: 12 | B19: =B18+0*(Eff_target-B18) -> 71 | C19: =C18+K_turn*(Eff_target-C18) -> 78.994027 | D19: =D18+$B$4*(Eff_target-D18) -> 78.982586 | E19: =IF(A19>=5,-1,0)+0.5*(-1)^A19 -> -0.5 | F19: =F18+K_turn*(Eff_target-F18)+E18 -> 76.488307 | G19: =(1-K_turn)*G18+K_turn*Eff_target+E18 -> 76.488307 | H19: =ABS(F19-G19) -> 0
... A27: 20 | B27: =B26+0*(Eff_target-B26) -> 71 | C27: =C26+K_turn*(Eff_target-C26) -> 78.999951 | D27: =D26+$B$4*(Eff_target-D26) -> 78.999708 | E27: =IF(A27>=5,-1,0)+0.5*(-1)^A27 -> -0.5 | F27: =F26+K_turn*(Eff_target-F26)+E26 -> 76.461029 | G27: =(1-K_turn)*G26+K_turn*Eff_target+E26 -> 76.461029 | H27: =ABS(F27-G27) -> 0
A29: Year | B29: The turnaround's rule | C29: Tables 1.9 and 5.5
A30: 1 | B30: =INDEX($C$7:$C$27,A30+1) -> 74.609507 | C30: 74.6
A31: 3 | B31: =INDEX($C$7:$C$27,A31+1) -> 77.677609 | C31: 77.7
A32: 5 | B32: =INDEX($C$7:$C$27,A32+1) -> 78.601703 | C32: 78.6
A33: 11 | B33: =INDEX($C$7:$C$27,A33+1) -> 78.989117 | C33: 79
A35: Proposition 2.2: largest difference, rule then transition vs the closed-loop map | C35: =MAX(H7:H27) -> 0
A36: Column E is an environment path (any path will do): a shift of one point a year from year 5 plus an alternating half point. Substituting the rule into the transition gives one map of state and input: the closed loop is again a system (Proposition 2.2).

Sheet Adaptation
A1: Adaptation: the rule's gain becomes a state (Definition 2.6; Proposition 2.3; Online Appendix 2.B; AXIOM Lab 1.2, step 4)
A2: Bench settings, not book numbers: the book prints none for this step. Change them and watch the fixed rule stay predictable while the adaptive one does not.
A3: Year the environment shifts and the adaptation law is switched on | B3: 5
A4: Shift: efficiency points the environment takes a year | B4: 1
A5: Adaptation speed eta | B5: 0.05
A6: Tolerated squared gap c | B6: 1
A7: theta_k+1 = theta_k + eta ((x_k - 79)^2 - c) after the shift: revised upward when the gap is large, downward when it is small (the law of Online Appendix 2.B).
A9: Year | B9: Environment input w | C9: Feedback off after the shift | D9: Fixed rule | E9: Adaptive rule | F9: Adaptive gain theta | G9: Frozen-rule forecast error
A10: 0 | B10: =IF(A10>=$B$3,-$B$4,0) -> 0 | C10: =Eff_today -> 71 | D10: =Eff_today -> 71 | E10: =Eff_today -> 71 | F10: =K_turn -> 0.45118836 | G10: =E10-D10 -> 0
A11: 1 | B11: =IF(A11>=$B$3,-$B$4,0) -> 0 | C11: =IF(A10<$B$3,D11,C10+B10) -> 74.609507 | D11: =D10+K_turn*(Eff_target-D10)+B10 -> 74.609507 | E11: =E10+F10*(Eff_target-E10)+B10 -> 74.609507 | F11: =F10+IF(A10>=$B$3,$B$5*((E10-Eff_target)^2-$B$6),0) -> 0.45118836 | G11: =E11-D11 -> 0
A12: 2 | B12: =IF(A12>=$B$3,-$B$4,0) -> 0 | C12: =IF(A11<$B$3,D12,C11+B11) -> 76.590446 | D12: =D11+K_turn*(Eff_target-D11)+B11 -> 76.590446 | E12: =E11+F11*(Eff_target-E11)+B11 -> 76.590446 | F12: =F11+IF(A11>=$B$3,$B$5*((E11-Eff_target)^2-$B$6),0) -> 0.45118836 | G12: =E12-D12 -> 0
A13: 3 | B13: =IF(A13>=$B$3,-$B$4,0) -> 0 | C13: =IF(A12<$B$3,D13,C12+B12) -> 77.677609 | D13: =D12+K_turn*(Eff_target-D12)+B12 -> 77.677609 | E13: =E12+F12*(Eff_target-E12)+B12 -> 77.677609 | F13: =F12+IF(A12>=$B$3,$B$5*((E12-Eff_target)^2-$B$6),0) -> 0.45118836 | G13: =E13-D13 -> 0
A14: 4 | B14: =IF(A14>=$B$3,-$B$4,0) -> 0 | C14: =IF(A13<$B$3,D14,C13+B13) -> 78.274256 | D14: =D13+K_turn*(Eff_target-D13)+B13 -> 78.274256 | E14: =E13+F13*(Eff_target-E13)+B13 -> 78.274256 | F14: =F13+IF(A13>=$B$3,$B$5*((E13-Eff_target)^2-$B$6),0) -> 0.45118836 | G14: =E14-D14 -> 0
A15: 5 | B15: =IF(A15>=$B$3,-$B$4,0) -> -1 | C15: =IF(A14<$B$3,D15,C14+B14) -> 78.601703 | D15: =D14+K_turn*(Eff_target-D14)+B14 -> 78.601703 | E15: =E14+F14*(Eff_target-E14)+B14 -> 78.601703 | F15: =F14+IF(A14>=$B$3,$B$5*((E14-Eff_target)^2-$B$6),0) -> 0.45118836 | G15: =E15-D15 -> 0
A16: 6 | B16: =IF(A16>=$B$3,-$B$4,0) -> -1 | C16: =IF(A15<$B$3,D16,C15+B15) -> 77.601703 | D16: =D15+K_turn*(Eff_target-D15)+B15 -> 77.78141 | E16: =E15+F15*(Eff_target-E15)+B15 -> 77.78141 | F16: =F15+IF(A15>=$B$3,$B$5*((E15-Eff_target)^2-$B$6),0) -> 0.40912037 | G16: =E16-D16 -> 0
A17: 7 | B17: =IF(A17>=$B$3,-$B$4,0) -> -1 | C17: =IF(A16<$B$3,D17,C16+B16) -> 76.601703 | D17: =D16+K_turn*(Eff_target-D16)+B16 -> 77.331224 | E17: =E16+F16*(Eff_target-E16)+B16 -> 77.27996 | F17: =F16+IF(A16>=$B$3,$B$5*((E16-Eff_target)^2-$B$6),0) -> 0.43336842 | G17: =E17-D17 -> -0.051263626
A18: 8 | B18: =IF(A18>=$B$3,-$B$4,0) -> -1 | C18: =IF(A17<$B$3,D18,C17+B17) -> 75.601703 | D18: =D17+K_turn*(Eff_target-D17)+B17 -> 77.084156 | E18: =E17+F17*(Eff_target-E17)+B17 -> 77.025371 | F18: =F17+IF(A17>=$B$3,$B$5*((E17-Eff_target)^2-$B$6),0) -> 0.53129528 | G18: =E18-D18 -> -0.058785083
A19: 9 | B19: =IF(A19>=$B$3,-$B$4,0) -> -1 | C19: =IF(A18<$B$3,D19,C18+B18) -> 74.601703 | D19: =D18+K_turn*(Eff_target-D18)+B18 -> 76.948563 | E19: =E18+F18*(Eff_target-E18)+B18 -> 77.074482 | F19: =F18+IF(A18>=$B$3,$B$5*((E18-Eff_target)^2-$B$6),0) -> 0.67625325 | G19: =E19-D19 -> 0.1259195
A20: 10 | B20: =IF(A20>=$B$3,-$B$4,0) -> -1 | C20: =IF(A19<$B$3,D20,C19+B19) -> 73.601703 | D20: =D19+K_turn*(Eff_target-D19)+B19 -> 76.874147 | E20: =E19+F19*(Eff_target-E19)+B19 -> 77.37662 | F20: =F19+IF(A19>=$B$3,$B$5*((E19-Eff_target)^2-$B$6),0) -> 0.8116342 | G20: =E20-D20 -> 0.50247255
A21: 11 | B21: =IF(A21>=$B$3,-$B$4,0) -> -1 | C21: =IF(A20<$B$3,D21,C20+B20) -> 72.601703 | D21: =D20+K_turn*(Eff_target-D20)+B20 -> 76.833307 | E21: =E20+F20*(Eff_target-E20)+B20 -> 77.694211 | F21: =F20+IF(A20>=$B$3,$B$5*((E20-Eff_target)^2-$B$6),0) -> 0.89340236 | G21: =E21-D21 -> 0.86090341
A22: 12 | B22: =IF(A22>=$B$3,-$B$4,0) -> -1 | C22: =IF(A21<$B$3,D22,C21+B21) -> 71.601703 | D22: =D21+K_turn*(Eff_target-D21)+B21 -> 76.810894 | E22: =E21+F21*(Eff_target-E21)+B21 -> 77.860806 | F22: =F21+IF(A21>=$B$3,$B$5*((E21-Eff_target)^2-$B$6),0) -> 0.92865665 | G22: =E22-D22 -> 1.0499121
... A30: 20 | B30: =IF(A30>=$B$3,-$B$4,0) -> -1 | C30: =IF(A29<$B$3,D30,C29+B29) -> 63.601703 | D30: =D29+K_turn*(Eff_target-D29)+B29 -> 76.783855 | E30: =E29+F29*(Eff_target-E29)+B29 -> 77.974534 | F30: =F29+IF(A29>=$B$3,$B$5*((E29-Eff_target)^2-$B$6),0) -> 0.9782013 | G30: =E30-D30 -> 1.1906789
A32: Fixed rule: long-run shortfall, shift / K | B32: =$B$4/K_turn -> 2.2163692
A33: Fixed rule: settles at, 79 - shift / K | B33: =Eff_target-$B$4/K_turn -> 76.783631
A34: Adaptive rule: efficiency in year 20 | B34: =E30 -> 77.974534
A35: Adaptive rule: gain in year 20 | B35: =F30 -> 0.9782013
A36: Adaptive rule: where it settles if it does, 79 - sqrt(c) | B36: =Eff_target-SQRT($B$6) -> 78
A39: Online Appendix 2.B's adaptive company | B39: Value
A40: Starting deviation x_0 | B40: 1.5
A41: Starting rule theta_0 | B41: 0.4
A42: eta | B42: 0.05
A43: c | B43: 1
A44: Own persistence a | B44: 0.9
A45: k | B45: w (any path) | C45: Decision u = -theta x | D45: x: a x + u + w | E45: theta: two loops | F45: x: one map F | G45: theta: one map F | H45: |difference|
A46: 0 | B46: =0.5*(-1)^A46 -> 0.5 | C46: =-E46*D46 -> -0.6 | D46: =$B$40 -> 1.5 | E46: =$B$41 -> 0.4 | F46: =$B$40 -> 1.5 | G46: =$B$41 -> 0.4 | H46: =MAX(ABS(D46-F46),ABS(E46-G46)) -> 0
A47: 1 | B47: =0.5*(-1)^A47 -> -0.5 | C47: =-E47*D47 -> -0.578125 | D47: =$B$44*D46+C46+B46 -> 1.25 | E47: =E46+$B$42*(D46^2-$B$43) -> 0.4625 | F47: =($B$44-G46)*F46+B46 -> 1.25 | G47: =G46+$B$42*(F46^2-$B$43) -> 0.4625 | H47: =MAX(ABS(D47-F47),ABS(E47-G47)) -> 0
A48: 2 | B48: =0.5*(-1)^A48 -> 0.5 | C48: =-E48*D48 -> -0.022998047 | D48: =$B$44*D47+C47+B47 -> 0.046875 | E48: =E47+$B$42*(D47^2-$B$43) -> 0.490625 | F48: =($B$44-G47)*F47+B47 -> 0.046875 | G48: =G47+$B$42*(F47^2-$B$43) -> 0.490625 | H48: =MAX(ABS(D48-F48),ABS(E48-G48)) -> 0
A49: 3 | B49: =0.5*(-1)^A49 -> -0.5 | C49: =-E49*D49 -> -0.22882489 | D49: =$B$44*D48+C48+B48 -> 0.51918945 | E49: =E48+$B$42*(D48^2-$B$43) -> 0.44073486 | F49: =($B$44-G48)*F48+B48 -> 0.51918945 | G49: =G48+$B$42*(F48^2-$B$43) -> 0.44073486 | H49: =MAX(ABS(D49-F49),ABS(E49-G49)) -> 0
A50: 4 | B50: =0.5*(-1)^A50 -> 0.5 | C50: =-E50*D50 -> 0.10572362 | D50: =$B$44*D49+C49+B49 -> -0.26155438 | E50: =E49+$B$42*(D49^2-$B$43) -> 0.40421275 | F50: =($B$44-G49)*F49+B49 -> -0.26155438 | G50: =G49+$B$42*(F49^2-$B$43) -> 0.40421275 | H50: =MAX(ABS(D50-F50),ABS(E50-G50)) -> 0
A51: 5 | B51: =0.5*(-1)^A51 -> -0.5 | C51: =-E51*D51 -> -0.13244043 | D51: =$B$44*D50+C50+B50 -> 0.37032467 | E51: =E50+$B$42*(D50^2-$B$43) -> 0.35763328 | F51: =($B$44-G50)*F50+B50 -> 0.37032467 | G51: =G50+$B$42*(F50^2-$B$43) -> 0.35763328 | H51: =MAX(ABS(D51-F51),ABS(E51-G51)) -> 0
A52: 6 | B52: =0.5*(-1)^A52 -> 0.5 | C52: =-E52*D52 -> 0.094079215 | D52: =$B$44*D51+C51+B51 -> -0.29914822 | E52: =E51+$B$42*(D51^2-$B$43) -> 0.3144903 | F52: =($B$44-G51)*F51+B51 -> -0.29914822 | G52: =G51+$B$42*(F51^2-$B$43) -> 0.3144903 | H52: =MAX(ABS(D52-F52),ABS(E52-G52)) -> 0
A53: 7 | B53: =0.5*(-1)^A53 -> -0.5 | C53: =-E53*D53 -> -0.087372084 | D53: =$B$44*D52+C52+B52 -> 0.32484581 | E53: =E52+$B$42*(D52^2-$B$43) -> 0.26896478 | F53: =($B$44-G52)*F52+B52 -> 0.32484581 | G53: =G52+$B$42*(F52^2-$B$43) -> 0.26896478 | H53: =MAX(ABS(D53-F53),ABS(E53-G53)) -> 0
A54: 8 | B54: =0.5*(-1)^A54 -> 0.5 | C54: =-E54*D54 -> 0.066153535 | D54: =$B$44*D53+C53+B53 -> -0.29501085 | E54: =E53+$B$42*(D53^2-$B$43) -> 0.22424102 | F54: =($B$44-G53)*F53+B53 -> -0.29501085 | G54: =G53+$B$42*(F53^2-$B$43) -> 0.22424102 | H54: =MAX(ABS(D54-F54),ABS(E54-G54)) -> 0
A55: 9 | B55: =0.5*(-1)^A55 -> -0.5 | C55: =-E55*D55 -> -0.05369275 | D55: =$B$44*D54+C54+B54 -> 0.30064377 | E55: =E54+$B$42*(D54^2-$B$43) -> 0.17859259 | F55: =($B$44-G54)*F54+B54 -> 0.30064377 | G55: =G54+$B$42*(F54^2-$B$43) -> 0.17859259 | H55: =MAX(ABS(D55-F55),ABS(E55-G55)) -> 0
A56: 10 | B56: =0.5*(-1)^A56 -> 0.5 | C56: =-E56*D56 -> 0.037685765 | D56: =$B$44*D55+C55+B55 -> -0.28311336 | E56: =E55+$B$42*(D55^2-$B$43) -> 0.13311193 | F56: =($B$44-G55)*F55+B55 -> -0.28311336 | G56: =G55+$B$42*(F55^2-$B$43) -> 0.13311193 | H56: =MAX(ABS(D56-F56),ABS(E56-G56)) -> 0
A57: 11 | B57: =0.5*(-1)^A57 -> -0.5 | C57: =-E57*D57 -> -0.024644715 | D57: =$B$44*D56+C56+B56 -> 0.28288374 | E57: =E56+$B$42*(D56^2-$B$43) -> 0.087119586 | F57: =($B$44-G56)*F56+B56 -> 0.28288374 | G57: =G56+$B$42*(F56^2-$B$43) -> 0.087119586 | H57: =MAX(ABS(D57-F57),ABS(E57-G57)) -> 0
A58: 12 | B58: =0.5*(-1)^A58 -> 0.5 | C58: =-E58*D58 -> 0.011104631 | D58: =$B$44*D57+C57+B57 -> -0.27004935 | E58: =E57+$B$42*(D57^2-$B$43) -> 0.041120747 | F58: =($B$44-G57)*F57+B57 -> -0.27004935 | G58: =G57+$B$42*(F57^2-$B$43) -> 0.041120747 | H58: =MAX(ABS(D58-F58),ABS(E58-G58)) -> 0
A60: Proposition 2.3: largest difference between the two loops and the one map | B60: =MAX(H46:H58) -> 0

Sheet OutputFeedback
A1: Output feedback needs a reporting lag (Online Appendix Remark 2.B.1)
A2: If the reported figure responds instantly to the decision, y = g(x, u) = u, output feedback must solve u = phi(u).
A4: u | B4: phi(u) = u + 1: phi(u) - u | C4: phi(u) = u^2: phi(u) - u
A5: -2 | B5: =(A5+1)-A5 -> 1 | C5: =A5^2-A5 -> 6
A6: -1.75 | B6: =(A6+1)-A6 -> 1 | C6: =A6^2-A6 -> 4.8125
A7: -1.5 | B7: =(A7+1)-A7 -> 1 | C7: =A7^2-A7 -> 3.75
A8: -1.25 | B8: =(A8+1)-A8 -> 1 | C8: =A8^2-A8 -> 2.8125
A9: -1 | B9: =(A9+1)-A9 -> 1 | C9: =A9^2-A9 -> 2
A10: -0.75 | B10: =(A10+1)-A10 -> 1 | C10: =A10^2-A10 -> 1.3125
A11: -0.5 | B11: =(A11+1)-A11 -> 1 | C11: =A11^2-A11 -> 0.75
A12: -0.25 | B12: =(A12+1)-A12 -> 1 | C12: =A12^2-A12 -> 0.3125
A13: 0 | B13: =(A13+1)-A13 -> 1 | C13: =A13^2-A13 -> 0
A14: 0.25 | B14: =(A14+1)-A14 -> 1 | C14: =A14^2-A14 -> -0.1875
A15: 0.5 | B15: =(A15+1)-A15 -> 1 | C15: =A15^2-A15 -> -0.25
A16: 0.75 | B16: =(A16+1)-A16 -> 1 | C16: =A16^2-A16 -> -0.1875
... A21: 2 | B21: =(A21+1)-A21 -> 1 | C21: =A21^2-A21 -> 2
A23: phi(y) = y + 1: grid points that solve u = phi(u) | B23: =COUNTIF(B5:B21,0) -> 0
A24: phi(y) = y + 1: smallest residual phi(u) - u on the grid (never zero) | B24: =MIN(B5:B21) -> 1
A25: phi(y) = y^2: u^2 - u = 0, discriminant | B25: =(-1)^2-4*1*0 -> 1
A26: phi(y) = y^2: number of real solutions | B26: =IF(B25>0,2,IF(B25=0,1,0)) -> 2
A27: phi(y) = y^2: the smaller solution | B27: =(1-SQRT(B25))/2 -> 0
A28: phi(y) = y^2: the larger solution | B28: =(1+SQRT(B25))/2 -> 1
A29: phi(y) = y^2: grid points that solve u = phi(u) | B29: =COUNTIF(C5:C21,0) -> 2
A31: Period | B31: With a one-period lag: u_k = phi(y_k-1), phi(y) = y + 1
A32: 0 | B32: 0
A33: 1 | B33: =B32+1 -> 1
A34: 2 | B34: =B33+1 -> 2
A35: 3 | B35: =B34+1 -> 3
A36: 4 | B36: =B35+1 -> 4
A37: 5 | B37: =B36+1 -> 5
A38: 6 | B38: =B37+1 -> 6
A39: 7 | B39: =B38+1 -> 7
A41: With the lag every rule gives one path, as the book's discrete-time convention builds in.

Sheet Loops
A1: Map a loop: signs, polarity, kind (Tables 2.4 and 2.5; AXIOM Lab 1.2, step 5)
A2: +1: the link moves its target the same way; -1: the opposite way. A loop's polarity is the product of its links' signs: +1 reinforcing, -1 balancing.
A4: Industrial Systems' migration loop (Table 2.5)
A5: From | B5: To | C5: Sign | D5: Meaning
A6: customer migration | B6: volume | C6: -1 | D6: migration cuts volume
A7: volume | B7: unit cost | C7: -1 | D7: less volume raises unit cost
A8: unit cost | B8: customer migration | C8: 1 | D8: higher unit cost speeds migration
A9: Opposite links | C9: =COUNTIF(C6:C8,-1) -> 2
A10: Polarity: the product of the signs | C10: =PRODUCT(C6:C8) -> 1 | D10: =IF(C10>0,"reinforcing","balancing") -> reinforcing
A12: The turnaround's efficiency program (Table 2.4: balancing)
A13: From | B13: To | C13: Sign | D13: Meaning
A14: efficiency gap | B14: program effort | C14: 1 | D14: a wider gap draws more effort
A15: program effort | B15: efficiency | C15: 1 | D15: effort raises efficiency
A16: efficiency | B16: efficiency gap | C16: -1 | D16: higher efficiency narrows the gap
A17: Opposite links | C17: =COUNTIF(C14:C16,-1) -> 1
A18: Polarity: the product of the signs | C18: =PRODUCT(C14:C16) -> -1 | D18: =IF(C18>0,"reinforcing","balancing") -> balancing

Sheet Reference_Values
A1: Checkpoint | B1: Engine value | C1: Meaning (where in the book)
A2: Industrial Systems' sales | B2: 2562 | C2: Worked Example 2.1: $2.56 billion
A3: Share shipped to dealers | B3: 0.6010929 | C3: about 60 percent
A4: Dealers' sales to end customers | B4: 1848 | C4: Table 2.6: $1,848m (F5)
A5: Goods output, boundary A | B5: 1540 | C5: Worked Example 2.1, Step 2: $1,540m
A6: Goods output, boundary B | B6: 1848 | C6: Worked Example 2.1, Step 3: $1,848m
A7: The gap, B less A | B7: 308 | C7: Worked Example 2.1, Step 5: $308m
A8: The gap as a share of shipments | B8: 20 | C8: 20 percent
A9: Boundary A: interior | B9: 0 | C9: Table 2.6: 0 / 5 / 2 / 2
A10: Boundary A: input | B10: 5 | C10: Table 2.6: 0 / 5 / 2 / 2
A11: Boundary A: output | B11: 2 | C11: Table 2.6: 0 / 5 / 2 / 2
A12: Boundary A: environmental | B12: 2 | C12: Table 2.6: 0 / 5 / 2 / 2
A13: Boundary B: interior | B13: 3 | C13: Table 2.6: 3 / 4 / 2 / 0
... A45: Efficiency program polarity | B45: -1 | C45: Table 2.4: balancing

Sheet Checks
A1: Checkpoint | B1: Workbook formula value | C1: Engine value | D1: |diff| | E1: Tolerance | F1: Status
A2: Industrial Systems' sales | B2: =Declarations!B6 -> 2562 | C2: =Reference_Values!B2 -> 2562 | D2: =ABS(B2-C2) -> 0 | E2: 1e-09 | F2: =IF(D2<=E2,"PASS","FAIL") -> PASS
A3: Share shipped to dealers | B3: =Declarations!B8 -> 0.6010929 | C3: =Reference_Values!B3 -> 0.6010929 | D3: =ABS(B3-C3) -> 0 | E3: 1e-09 | F3: =IF(D3<=E3,"PASS","FAIL") -> PASS
A4: Dealers' sales to end customers | B4: =Declarations!B10 -> 1848 | C4: =Reference_Values!B4 -> 1848 | D4: =ABS(B4-C4) -> 0 | E4: 1e-09 | F4: =IF(D4<=E4,"PASS","FAIL") -> PASS
A5: Goods output, boundary A | B5: =Boundaries!B24 -> 1540 | C5: =Reference_Values!B5 -> 1540 | D5: =ABS(B5-C5) -> 0 | E5: 1e-09 | F5: =IF(D5<=E5,"PASS","FAIL") -> PASS
A6: Goods output, boundary B | B6: =Boundaries!C24 -> 1848 | C6: =Reference_Values!B6 -> 1848 | D6: =ABS(B6-C6) -> 0 | E6: 1e-09 | F6: =IF(D6<=E6,"PASS","FAIL") -> PASS
A7: The gap, B less A | B7: =Boundaries!C25 -> 308 | C7: =Reference_Values!B7 -> 308 | D7: =ABS(B7-C7) -> 0 | E7: 1e-09 | F7: =IF(D7<=E7,"PASS","FAIL") -> PASS
A8: The gap as a share of shipments | B8: =100*Boundaries!C26 -> 20 | C8: =Reference_Values!B8 -> 20 | D8: =ABS(B8-C8) -> 0 | E8: 1e-09 | F8: =IF(D8<=E8,"PASS","FAIL") -> PASS
A9: Boundary A: interior | B9: =Boundaries!B17 -> 0 | C9: =Reference_Values!B9 -> 0 | D9: =ABS(B9-C9) -> 0 | E9: 0 | F9: =IF(D9<=E9,"PASS","FAIL") -> PASS
A10: Boundary A: input | B10: =Boundaries!B18 -> 5 | C10: =Reference_Values!B10 -> 5 | D10: =ABS(B10-C10) -> 0 | E10: 0 | F10: =IF(D10<=E10,"PASS","FAIL") -> PASS
A11: Boundary A: output | B11: =Boundaries!B19 -> 2 | C11: =Reference_Values!B11 -> 2 | D11: =ABS(B11-C11) -> 0 | E11: 0 | F11: =IF(D11<=E11,"PASS","FAIL") -> PASS
A12: Boundary A: environmental | B12: =Boundaries!B20 -> 2 | C12: =Reference_Values!B12 -> 2 | D12: =ABS(B12-C12) -> 0 | E12: 0 | F12: =IF(D12<=E12,"PASS","FAIL") -> PASS
A13: Boundary B: interior | B13: =Boundaries!C17 -> 3 | C13: =Reference_Values!B13 -> 3 | D13: =ABS(B13-C13) -> 0 | E13: 0 | F13: =IF(D13<=E13,"PASS","FAIL") -> PASS
A14: Boundary B: input | B14: =Boundaries!C18 -> 4 | C14: =Reference_Values!B14 -> 4 | D14: =ABS(B14-C14) -> 0 | E14: 0 | F14: =IF(D14<=E14,"PASS","FAIL") -> PASS
A15: Boundary B: output | B15: =Boundaries!C19 -> 2 | C15: =Reference_Values!B15 -> 2 | D15: =ABS(B15-C15) -> 0 | E15: 0 | F15: =IF(D15<=E15,"PASS","FAIL") -> PASS
A16: Boundary B: environmental | B16: =Boundaries!C20 -> 0 | C16: =Reference_Values!B16 -> 0 | D16: =ABS(B16-C16) -> 0 | E16: 0 | F16: =IF(D16<=E16,"PASS","FAIL") -> PASS
A17: Table 2.6 rows reproduced, boundary A | B17: =Boundaries!B22 -> 9 | C17: =Reference_Values!B17 -> 9 | D17: =ABS(B17-C17) -> 0 | E17: 0 | F17: =IF(D17<=E17,"PASS","FAIL") -> PASS
A18: Table 2.6 rows reproduced, boundary B | B18: =Boundaries!C22 -> 9 | C18: =Reference_Values!B18 -> 9 | D18: =ABS(B18-C18) -> 0 | E18: 0 | F18: =IF(D18<=E18,"PASS","FAIL") -> PASS
A19: Flows relabeled by the move | B19: =Boundaries!C23 -> 5 | C19: =Reference_Values!B19 -> 5 | D19: =ABS(B19-C19) -> 0 | E19: 0 | F19: =IF(D19<=E19,"PASS","FAIL") -> PASS
A20: All boundaries: flows not in exactly one class | B20: =AllBoundaries!AB9 -> 0 | C20: =Reference_Values!B20 -> 0 | D20: =ABS(B20-C20) -> 0 | E20: 0 | F20: =IF(D20<=E20,"PASS","FAIL") -> PASS
A21: All boundaries: fewest flows | B21: =AllBoundaries!AB7 -> 9 | C21: =Reference_Values!B21 -> 9 | D21: =ABS(B21-C21) -> 0 | E21: 0 | F21: =IF(D21<=E21,"PASS","FAIL") -> PASS
A22: All boundaries: distinct classifications | B22: =AllBoundaries!AB10 -> 64 | C22: =Reference_Values!B22 -> 64 | D22: =ABS(B22-C22) -> 0 | E22: 0 | F22: =IF(D22<=E22,"PASS","FAIL") -> PASS
A23: Goods flows: distinct classifications | B23: =AllBoundaries!AB11 -> 16 | C23: =Reference_Values!B23 -> 16 | D23: =ABS(B23-C23) -> 0 | E23: 0 | F23: =IF(D23<=E23,"PASS","FAIL") -> PASS
A24: Capital flows: distinct classifications | B24: =AllBoundaries!AB12 -> 32 | C24: =Reference_Values!B24 -> 32 | D24: =ABS(B24-C24) -> 0 | E24: 0 | F24: =IF(D24<=E24,"PASS","FAIL") -> PASS
A25: Information flows: distinct classifications | B25: =AllBoundaries!AB13 -> 8 | C25: =Reference_Values!B25 -> 8 | D25: =ABS(B25-C25) -> 0 | E25: 0 | F25: =IF(D25<=E25,"PASS","FAIL") -> PASS
A26: Moving the dealers inside relabels | B26: =AllBoundaries!AB18 -> 5 | C26: =Reference_Values!B26 -> 5 | D26: =ABS(B26-C26) -> 0 | E26: 0 | F26: =IF(D26<=E26,"PASS","FAIL") -> PASS
A27: Moving Meridian outside relabels | B27: =AllBoundaries!AB17 -> 7 | C27: =Reference_Values!B27 -> 7 | D27: =ABS(B27-C27) -> 0 | E27: 0 | F27: =IF(D27<=E27,"PASS","FAIL") -> PASS
A28: Figure 2.3: divisions | B28: =Levels!B18 -> 3 | C28: =Reference_Values!B28 -> 3 | D28: =ABS(B28-C28) -> 0 | E28: 0 | F28: =IF(D28<=E28,"PASS","FAIL") -> PASS
A29: Figure 2.3: units | B29: =Levels!B19 -> 6 | C29: =Reference_Values!B29 -> 6 | D29: =ABS(B29-C29) -> 0 | E29: 0 | F29: =IF(D29<=E29,"PASS","FAIL") -> PASS
A30: Digital Solutions' sibling divisions | B30: =Levels!B20 -> 2 | C30: =Reference_Values!B30 -> 2 | D30: =ABS(B30-C30) -> 0 | E30: 0 | F30: =IF(D30<=E30,"PASS","FAIL") -> PASS
A31: Turnaround efficiency, year 1 | B31: =Feedback!B30 -> 74.609507 | C31: =Reference_Values!B31 -> 74.609507 | D31: =ABS(B31-C31) -> 0 | E31: 1e-09 | F31: =IF(D31<=E31,"PASS","FAIL") -> PASS
A32: Turnaround efficiency, year 3 | B32: =Feedback!B31 -> 77.677609 | C32: =Reference_Values!B32 -> 77.677609 | D32: =ABS(B32-C32) -> 0 | E32: 1e-09 | F32: =IF(D32<=E32,"PASS","FAIL") -> PASS
A33: Turnaround efficiency, year 5 | B33: =Feedback!B32 -> 78.601703 | C33: =Reference_Values!B33 -> 78.601703 | D33: =ABS(B33-C33) -> 0 | E33: 1e-09 | F33: =IF(D33<=E33,"PASS","FAIL") -> PASS
A34: Turnaround efficiency, year 11 | B34: =Feedback!B33 -> 78.989117 | C34: =Reference_Values!B34 -> 78.989117 | D34: =ABS(B34-C34) -> 0 | E34: 1e-09 | F34: =IF(D34<=E34,"PASS","FAIL") -> PASS
A35: Gap factor a year | B35: =Declarations!B17 -> 0.54881164 | C35: =Reference_Values!B35 -> 0.54881164 | D35: =ABS(B35-C35) -> 0 | E35: 1e-09 | F35: =IF(D35<=E35,"PASS","FAIL") -> PASS
A36: Proposition 2.2: closed-loop map vs rule | B36: =Feedback!C35 -> 0 | C36: =Reference_Values!B36 -> 2.8421709e-14 | D36: =ABS(B36-C36) -> 2.8421709e-14 | E36: 1e-09 | F36: =IF(D36<=E36,"PASS","FAIL") -> PASS
A37: Bench: fixed rule, year 20 (shift 1) | B37: =Adaptation!D30 -> 76.783855 | C37: =Reference_Values!B37 -> 76.783855 | D37: =ABS(B37-C37) -> 0 | E37: 1e-09 | F37: =IF(D37<=E37,"PASS","FAIL") -> PASS
A38: Bench: adaptive rule, year 20 (shift 1) | B38: =Adaptation!E30 -> 77.974534 | C38: =Reference_Values!B38 -> 77.974534 | D38: =ABS(B38-C38) -> 0 | E38: 1e-09 | F38: =IF(D38<=E38,"PASS","FAIL") -> PASS
A39: Bench: adaptive gain, year 20 (shift 1) | B39: =Adaptation!F30 -> 0.9782013 | C39: =Reference_Values!B39 -> 0.9782013 | D39: =ABS(B39-C39) -> 0 | E39: 1e-09 | F39: =IF(D39<=E39,"PASS","FAIL") -> PASS
A40: Proposition 2.3: two loops vs one map | B40: =Adaptation!B60 -> 0 | C40: =Reference_Values!B40 -> 8.8817842e-16 | D40: =ABS(B40-C40) -> 8.8817842e-16 | E40: 1e-09 | F40: =IF(D40<=E40,"PASS","FAIL") -> PASS
A41: Remark 2.B.1: solutions of u = u + 1 | B41: =OutputFeedback!B23 -> 0 | C41: =Reference_Values!B41 -> 0 | D41: =ABS(B41-C41) -> 0 | E41: 0 | F41: =IF(D41<=E41,"PASS","FAIL") -> PASS
A42: Remark 2.B.1: solutions of u = u^2 | B42: =OutputFeedback!B26 -> 2 | C42: =Reference_Values!B42 -> 2 | D42: =ABS(B42-C42) -> 0 | E42: 0 | F42: =IF(D42<=E42,"PASS","FAIL") -> PASS
A43: Remark 2.B.1: the larger solution | B43: =OutputFeedback!B28 -> 1 | C43: =Reference_Values!B43 -> 1 | D43: =ABS(B43-C43) -> 0 | E43: 1e-09 | F43: =IF(D43<=E43,"PASS","FAIL") -> PASS
A44: Migration loop polarity | B44: =Loops!C10 -> 1 | C44: =Reference_Values!B44 -> 1 | D44: =ABS(B44-C44) -> 0 | E44: 0 | F44: =IF(D44<=E44,"PASS","FAIL") -> PASS
A45: Efficiency program polarity | B45: =Loops!C18 -> -1 | C45: =Reference_Values!B45 -> -1 | D45: =ABS(B45-C45) -> 0 | E45: 0 | F45: =IF(D45<=E45,"PASS","FAIL") -> PASS
A47: All checkpoints | F47: =IF(COUNTIF(F2:F45,"PASS")=44,"ALL PASS","CHECK") -> ALL PASS
