Workbook

Sheet README
B1: DCT Laboratory — Vol II, Ch 7: Dynamic Programming for Enterprise Systems
B2: Seed 26207 · Companion to DCT_V2_Ch07_Lab.ipynb and AXIOM Lab 2.7 (module AXIOM-07). Money in $ million.
B4: Worked Example 7.1, How Much Margin Should Meridian Hold Above the Capability Floor?, with the book's declarations.
B5: Declarations: the inputs of Step 1. CriticalRatio: Theorem 7.2's critical ratio and the target 55.75.
B6: BackwardInduction: a twelve-quarter horizon solved by formulas on a grid of 0.25 points, with its rule table.
B7: LookAhead: the value of each hiring decision one quarter ahead at three capability levels.
B8: Values: the engine's value function V* on a grid of 0.05 points; the formulas apply the Bellman operator to it and certify it by its residual.
B9: Prices: the price of a point and the engineering team's value. UpperBound: Theorem 7.2(iii), a bound on what any rule can achieve.
B10: RulesAndPlans: Table 7.3 and the value of responding, from the engine's exact evaluations.
B11: Value iteration (813 sweeps), policy iteration, the simulation and the finer calendars run in the notebook.
B12: Reference_Values and Checks: the engine's numbers and a PASS/FAIL comparison with this workbook's formulas.
B14: LEGEND
... B18: Cross-sheet link: green.

Sheet Declarations
A1: Declarations (Worked Example 7.1, Step 1). Money in $ million; capability in points.
A3: Quantity | B3: Value | C3: Source
A4: Discount rate a year | B4: 0.1 | C4: The board's 10 percent a year
A5: Discount factor a quarter, beta | B5: =(1+B4)^(-1/4) -> 0.97645409 | C5: beta = 1.1^(-1/4)
A6: Capability kept each quarter, alpha | B6: 0.975 | C6: 2.5 percent attrition a quarter (Volume I, Chapter 10)
A7: Cost of hiring and training a point, k | B7: 4 | C7: $4 million a point
A8: Hiring cap a quarter (points) | B8: 2.5 | C8: At most 2.5 points a quarter
A9: Capability floor | B9: 55 | C9: Below 55 the digital build slows (Chapter 6)
A10: Delay cost of the digital build a year | B10: 32 | C10: $32 million a year (Chapter 6)
A11: Slowdown per point short | B11: 0.2 | C11: A fifth per point short
A12: Cost of a point short for a quarter, p | B12: =B10/4*B11 -> 1.6 | C12: 8/5 = $1.6 million
A13: Effective horizon 1/(1 - beta), quarters | B13: =1/(1-B5) -> 42.47022
A15: Unplanned loss w (points) | B15: Probability | C15: P(loss > w) | D15: P(loss >= w)
A16: 1.5 | B16: 0.05 | C16: =SUMIF($A$16:$A$20,">"&A16,$B$16:$B$20) -> 0 | D16: =SUMIF($A$16:$A$20,">="&A16,$B$16:$B$20) -> 0.05
A17: 0.75 | B17: 0.2 | C17: =SUMIF($A$16:$A$20,">"&A17,$B$16:$B$20) -> 0.05 | D17: =SUMIF($A$16:$A$20,">="&A17,$B$16:$B$20) -> 0.25
A18: 0 | B18: 0.5 | C18: =SUMIF($A$16:$A$20,">"&A18,$B$16:$B$20) -> 0.25 | D18: =SUMIF($A$16:$A$20,">="&A18,$B$16:$B$20) -> 0.75
A19: -0.75 | B19: 0.2 | C19: =SUMIF($A$16:$A$20,">"&A19,$B$16:$B$20) -> 0.75 | D19: =SUMIF($A$16:$A$20,">="&A19,$B$16:$B$20) -> 0.95
A20: -1.5 | B20: 0.05 | C20: =SUMIF($A$16:$A$20,">"&A20,$B$16:$B$20) -> 0.95 | D20: =SUMIF($A$16:$A$20,">="&A20,$B$16:$B$20) -> 1
A21: Total probability | B21: =SUM(B16:B20) -> 1
A22: Mean loss a quarter | B22: =SUMPRODUCT(A16:A20,B16:B20) -> 0
A23: Standard deviation a quarter | B23: =SQRT(SUMPRODUCT(A16:A20,A16:A20,B16:B20)-B22^2) -> 0.67082039
A25: The engineering office's record: capability moves as c' = 0.975c + h - w each quarter.

Sheet CriticalRatio
A1: Look one quarter ahead: the critical ratio and the target (Theorem 7.2; AXIOM Lab 2.7, step 1)
A2: Quantity | B2: Value | C2: Reading
A3: Holding a planned point for a quarter, k(1 - alpha beta) | B3: =Cost_k*(1-Alpha_keep*Beta_q) -> 0.19182905 | C3: 0.767 a year
A4: A point short next quarter, beta p | B4: =Beta_q*Short_p -> 1.5623265
A5: Critical ratio | B5: =B3/B4 -> 0.12278422 | C5: Theorem 7.2(ii)
A6: Margin: smallest loss w with P(loss > w) <= ratio | B6: =_xlfn.MINIFS(Loss_w,Declarations!$C$16:$C$20,"<="&B5) -> 0.75 | C6: P(loss > 0.75) = 0.05 <= ratio <= P(loss >= 0.75) = 0.25
A7: Target for planned capability, floor + margin | B7: =Floor_c+B6 -> 55.75 | C7: Top up to 55.75
A8: Hire nothing above (target / alpha) | B8: =B7/Alpha_keep -> 57.179487
A9: Hire at the cap below ((target - cap) / alpha) | B9: =(B7-Cap_h)/Alpha_keep -> 54.615385
A10: Holding a planned point for a year | B10: =4*B3 -> 0.7673162
A12: Loss w last quarter | B12: Hiring needed to restore the target | C12: Hiring done (cap, no firing) | D12: Planned capability reached
A13: =Declarations!A16 -> 1.5 | B13: =(1-Alpha_keep)*$B$7+Alpha_keep*A13 -> 2.85625 | C13: =MIN(Cap_h,MAX(0,B13)) -> 2.5 | D13: =Alpha_keep*($B$7-A13)+C13 -> 55.39375
A14: =Declarations!A17 -> 0.75 | B14: =(1-Alpha_keep)*$B$7+Alpha_keep*A14 -> 2.125 | C14: =MIN(Cap_h,MAX(0,B14)) -> 2.125 | D14: =Alpha_keep*($B$7-A14)+C14 -> 55.75
A15: =Declarations!A18 -> 0 | B15: =(1-Alpha_keep)*$B$7+Alpha_keep*A15 -> 1.39375 | C15: =MIN(Cap_h,MAX(0,B15)) -> 1.39375 | D15: =Alpha_keep*($B$7-A15)+C15 -> 55.75
A16: =Declarations!A19 -> -0.75 | B16: =(1-Alpha_keep)*$B$7+Alpha_keep*A16 -> 0.6625 | C16: =MIN(Cap_h,MAX(0,B16)) -> 0.6625 | D16: =Alpha_keep*($B$7-A16)+C16 -> 55.75
A17: =Declarations!A20 -> -1.5 | B17: =(1-Alpha_keep)*$B$7+Alpha_keep*A17 -> -0.06875 | C17: =MIN(Cap_h,MAX(0,B17)) -> 0 | D17: =Alpha_keep*($B$7-A17)+C17 -> 55.81875
A19: After the worst loss the cap cannot restore the target; after the best gain capability stays above it with no hiring. The recursion, not the formula, certifies the target (Worked Example 7.1, Step 3).

Sheet BackwardInduction
A1: Solve backward: twelve quarters from V_12 = 0 on a grid of 0.25 points (Theorem 7.1(i); AXIOM Lab 2.7, step 2)
A2: Each quarter: G(y) = -k y + beta E V_next(y - w) at the nodes; V(c) = g(c) + k alpha c + the best G over the reachable planned levels [L, U] (nodes, and the ends by interpolation). Values are linear between nodes. Rule 'none': hiring is not worth its cost at any capability above 50.
C3: capability levels: | D3: 53 | E3: 54 | F3: 55 | G3: 56 | H3: 57 | I3: 58
A4: Quarter k | B4: Target (best planned level) | C4: Rule | D4: Hiring at 53 | E4: Hiring at 54 | F4: Hiring at 55 | G4: Hiring at 56 | H4: Hiring at 57 | I4: Hiring at 58 | J4: Engine target | K4: V_k(58) | L4: V_k(53)
A5: 0 | B5: =_xlfn.MINIFS($A$21:$A$141,$BF$21:$BF$141,">="&(MAX($BF$21:$BF$141)-0.000000001)) -> 55.75 | C5: =IF(B5>=Alpha_keep*50,"top up to "&TEXT(B5,"0.00"),"none: hire nothing") -> top up to 55.75 | D5: =MIN(Cap_h,MAX(0,$B5-Alpha_keep*D$3)) -> 2.5 | E5: =MIN(Cap_h,MAX(0,$B5-Alpha_keep*E$3)) -> 2.5 | F5: =MIN(Cap_h,MAX(0,$B5-Alpha_keep*F$3)) -> 2.125 | G5: =MIN(Cap_h,MAX(0,$B5-Alpha_keep*G$3)) -> 1.15 | H5: =MIN(Cap_h,MAX(0,$B5-Alpha_keep*H$3)) -> 0.175 | I5: =MIN(Cap_h,MAX(0,$B5-Alpha_keep*I$3)) -> 0 | J5: 55.75 | K5: =INDEX($BI$21:$BI$141,MATCH(58,$A$21:$A$141,0)) -> -40.454736 | L5: =INDEX($BI$21:$BI$141,MATCH(53,$A$21:$A$141,0)) -> -64.299579
A6: 1 | B6: =_xlfn.MINIFS($A$21:$A$141,$BB$21:$BB$141,">="&(MAX($BB$21:$BB$141)-0.000000001)) -> 55.75 | C6: =IF(B6>=Alpha_keep*50,"top up to "&TEXT(B6,"0.00"),"none: hire nothing") -> top up to 55.75 | D6: =MIN(Cap_h,MAX(0,$B6-Alpha_keep*D$3)) -> 2.5 | E6: =MIN(Cap_h,MAX(0,$B6-Alpha_keep*E$3)) -> 2.5 | F6: =MIN(Cap_h,MAX(0,$B6-Alpha_keep*F$3)) -> 2.125 | G6: =MIN(Cap_h,MAX(0,$B6-Alpha_keep*G$3)) -> 1.15 | H6: =MIN(Cap_h,MAX(0,$B6-Alpha_keep*H$3)) -> 0.175 | I6: =MIN(Cap_h,MAX(0,$B6-Alpha_keep*I$3)) -> 0 | J6: 55.75 | K6: =INDEX($BE$21:$BE$141,MATCH(58,$A$21:$A$141,0)) -> -35.865734 | L6: =INDEX($BE$21:$BE$141,MATCH(53,$A$21:$A$141,0)) -> -59.710559
A7: 2 | B7: =_xlfn.MINIFS($A$21:$A$141,$AX$21:$AX$141,">="&(MAX($AX$21:$AX$141)-0.000000001)) -> 55.75 | C7: =IF(B7>=Alpha_keep*50,"top up to "&TEXT(B7,"0.00"),"none: hire nothing") -> top up to 55.75 | D7: =MIN(Cap_h,MAX(0,$B7-Alpha_keep*D$3)) -> 2.5 | E7: =MIN(Cap_h,MAX(0,$B7-Alpha_keep*E$3)) -> 2.5 | F7: =MIN(Cap_h,MAX(0,$B7-Alpha_keep*F$3)) -> 2.125 | G7: =MIN(Cap_h,MAX(0,$B7-Alpha_keep*G$3)) -> 1.15 | H7: =MIN(Cap_h,MAX(0,$B7-Alpha_keep*H$3)) -> 0.175 | I7: =MIN(Cap_h,MAX(0,$B7-Alpha_keep*I$3)) -> 0 | J7: 55.75 | K7: =INDEX($BA$21:$BA$141,MATCH(58,$A$21:$A$141,0)) -> -31.166077 | L7: =INDEX($BA$21:$BA$141,MATCH(53,$A$21:$A$141,0)) -> -55.010807
A8: 3 | B8: =_xlfn.MINIFS($A$21:$A$141,$AT$21:$AT$141,">="&(MAX($AT$21:$AT$141)-0.000000001)) -> 55.75 | C8: =IF(B8>=Alpha_keep*50,"top up to "&TEXT(B8,"0.00"),"none: hire nothing") -> top up to 55.75 | D8: =MIN(Cap_h,MAX(0,$B8-Alpha_keep*D$3)) -> 2.5 | E8: =MIN(Cap_h,MAX(0,$B8-Alpha_keep*E$3)) -> 2.5 | F8: =MIN(Cap_h,MAX(0,$B8-Alpha_keep*F$3)) -> 2.125 | G8: =MIN(Cap_h,MAX(0,$B8-Alpha_keep*G$3)) -> 1.15 | H8: =MIN(Cap_h,MAX(0,$B8-Alpha_keep*H$3)) -> 0.175 | I8: =MIN(Cap_h,MAX(0,$B8-Alpha_keep*I$3)) -> 0 | J8: 55.75 | K8: =INDEX($AW$21:$AW$141,MATCH(58,$A$21:$A$141,0)) -> -26.353107 | L8: =INDEX($AW$21:$AW$141,MATCH(53,$A$21:$A$141,0)) -> -50.197335
A9: 4 | B9: =_xlfn.MINIFS($A$21:$A$141,$AP$21:$AP$141,">="&(MAX($AP$21:$AP$141)-0.000000001)) -> 55.75 | C9: =IF(B9>=Alpha_keep*50,"top up to "&TEXT(B9,"0.00"),"none: hire nothing") -> top up to 55.75 | D9: =MIN(Cap_h,MAX(0,$B9-Alpha_keep*D$3)) -> 2.5 | E9: =MIN(Cap_h,MAX(0,$B9-Alpha_keep*E$3)) -> 2.5 | F9: =MIN(Cap_h,MAX(0,$B9-Alpha_keep*F$3)) -> 2.125 | G9: =MIN(Cap_h,MAX(0,$B9-Alpha_keep*G$3)) -> 1.15 | H9: =MIN(Cap_h,MAX(0,$B9-Alpha_keep*H$3)) -> 0.175 | I9: =MIN(Cap_h,MAX(0,$B9-Alpha_keep*I$3)) -> 0 | J9: 55.75 | K9: =INDEX($AS$21:$AS$141,MATCH(58,$A$21:$A$141,0)) -> -21.424217 | L9: =INDEX($AS$21:$AS$141,MATCH(53,$A$21:$A$141,0)) -> -45.265743
A10: 5 | B10: =_xlfn.MINIFS($A$21:$A$141,$AL$21:$AL$141,">="&(MAX($AL$21:$AL$141)-0.000000001)) -> 55.75 | C10: =IF(B10>=Alpha_keep*50,"top up to "&TEXT(B10,"0.00"),"none: hire nothing") -> top up to 55.75 | D10: =MIN(Cap_h,MAX(0,$B10-Alpha_keep*D$3)) -> 2.5 | E10: =MIN(Cap_h,MAX(0,$B10-Alpha_keep*E$3)) -> 2.5 | F10: =MIN(Cap_h,MAX(0,$B10-Alpha_keep*F$3)) -> 2.125 | G10: =MIN(Cap_h,MAX(0,$B10-Alpha_keep*G$3)) -> 1.15 | H10: =MIN(Cap_h,MAX(0,$B10-Alpha_keep*H$3)) -> 0.175 | I10: =MIN(Cap_h,MAX(0,$B10-Alpha_keep*I$3)) -> 0 | J10: 55.75 | K10: =INDEX($AO$21:$AO$141,MATCH(58,$A$21:$A$141,0)) -> -16.378054 | L10: =INDEX($AO$21:$AO$141,MATCH(53,$A$21:$A$141,0)) -> -40.20487
A11: 6 | B11: =_xlfn.MINIFS($A$21:$A$141,$AH$21:$AH$141,">="&(MAX($AH$21:$AH$141)-0.000000001)) -> 55.75 | C11: =IF(B11>=Alpha_keep*50,"top up to "&TEXT(B11,"0.00"),"none: hire nothing") -> top up to 55.75 | D11: =MIN(Cap_h,MAX(0,$B11-Alpha_keep*D$3)) -> 2.5 | E11: =MIN(Cap_h,MAX(0,$B11-Alpha_keep*E$3)) -> 2.5 | F11: =MIN(Cap_h,MAX(0,$B11-Alpha_keep*F$3)) -> 2.125 | G11: =MIN(Cap_h,MAX(0,$B11-Alpha_keep*G$3)) -> 1.15 | H11: =MIN(Cap_h,MAX(0,$B11-Alpha_keep*H$3)) -> 0.175 | I11: =MIN(Cap_h,MAX(0,$B11-Alpha_keep*I$3)) -> 0 | J11: 55.75 | K11: =INDEX($AK$21:$AK$141,MATCH(58,$A$21:$A$141,0)) -> -11.229682 | L11: =INDEX($AK$21:$AK$141,MATCH(53,$A$21:$A$141,0)) -> -34.972059
A12: 7 | B12: =_xlfn.MINIFS($A$21:$A$141,$AD$21:$AD$141,">="&(MAX($AD$21:$AD$141)-0.000000001)) -> 55.75 | C12: =IF(B12>=Alpha_keep*50,"top up to "&TEXT(B12,"0.00"),"none: hire nothing") -> top up to 55.75 | D12: =MIN(Cap_h,MAX(0,$B12-Alpha_keep*D$3)) -> 2.5 | E12: =MIN(Cap_h,MAX(0,$B12-Alpha_keep*E$3)) -> 2.5 | F12: =MIN(Cap_h,MAX(0,$B12-Alpha_keep*F$3)) -> 2.125 | G12: =MIN(Cap_h,MAX(0,$B12-Alpha_keep*G$3)) -> 1.15 | H12: =MIN(Cap_h,MAX(0,$B12-Alpha_keep*H$3)) -> 0.175 | I12: =MIN(Cap_h,MAX(0,$B12-Alpha_keep*I$3)) -> 0 | J12: 55.75 | K12: =INDEX($AG$21:$AG$141,MATCH(58,$A$21:$A$141,0)) -> -6.2002755 | L12: =INDEX($AG$21:$AG$141,MATCH(53,$A$21:$A$141,0)) -> -29.448414
A13: 8 | B13: =_xlfn.MINIFS($A$21:$A$141,$Z$21:$Z$141,">="&(MAX($Z$21:$Z$141)-0.000000001)) -> 54.75 | C13: =IF(B13>=Alpha_keep*50,"top up to "&TEXT(B13,"0.00"),"none: hire nothing") -> top up to 54.75 | D13: =MIN(Cap_h,MAX(0,$B13-Alpha_keep*D$3)) -> 2.5 | E13: =MIN(Cap_h,MAX(0,$B13-Alpha_keep*E$3)) -> 2.1 | F13: =MIN(Cap_h,MAX(0,$B13-Alpha_keep*F$3)) -> 1.125 | G13: =MIN(Cap_h,MAX(0,$B13-Alpha_keep*G$3)) -> 0.15 | H13: =MIN(Cap_h,MAX(0,$B13-Alpha_keep*H$3)) -> 0 | I13: =MIN(Cap_h,MAX(0,$B13-Alpha_keep*I$3)) -> 0 | J13: 54.75 | K13: =INDEX($AC$21:$AC$141,MATCH(58,$A$21:$A$141,0)) -> -2.4348266 | L13: =INDEX($AC$21:$AC$141,MATCH(53,$A$21:$A$141,0)) -> -23.085896
A14: 9 | B14: =_xlfn.MINIFS($A$21:$A$141,$V$21:$V$141,">="&(MAX($V$21:$V$141)-0.000000001)) -> 44.25 | C14: =IF(B14>=Alpha_keep*50,"top up to "&TEXT(B14,"0.00"),"none: hire nothing") -> none: hire nothing | D14: =MIN(Cap_h,MAX(0,$B14-Alpha_keep*D$3)) -> 0 | E14: =MIN(Cap_h,MAX(0,$B14-Alpha_keep*E$3)) -> 0 | F14: =MIN(Cap_h,MAX(0,$B14-Alpha_keep*F$3)) -> 0 | G14: =MIN(Cap_h,MAX(0,$B14-Alpha_keep*G$3)) -> 0 | H14: =MIN(Cap_h,MAX(0,$B14-Alpha_keep*H$3)) -> 0 | I14: =MIN(Cap_h,MAX(0,$B14-Alpha_keep*I$3)) -> 0 | J14: 44.25 | K14: =INDEX($Y$21:$Y$141,MATCH(58,$A$21:$A$141,0)) -> -0.46191925 | L14: =INDEX($Y$21:$Y$141,MATCH(53,$A$21:$A$141,0)) -> -15.437964
A15: 10 | B15: =_xlfn.MINIFS($A$21:$A$141,$R$21:$R$141,">="&(MAX($R$21:$R$141)-0.000000001)) -> 42.5 | C15: =IF(B15>=Alpha_keep*50,"top up to "&TEXT(B15,"0.00"),"none: hire nothing") -> none: hire nothing | D15: =MIN(Cap_h,MAX(0,$B15-Alpha_keep*D$3)) -> 0 | E15: =MIN(Cap_h,MAX(0,$B15-Alpha_keep*E$3)) -> 0 | F15: =MIN(Cap_h,MAX(0,$B15-Alpha_keep*F$3)) -> 0 | G15: =MIN(Cap_h,MAX(0,$B15-Alpha_keep*G$3)) -> 0 | H15: =MIN(Cap_h,MAX(0,$B15-Alpha_keep*H$3)) -> 0 | I15: =MIN(Cap_h,MAX(0,$B15-Alpha_keep*I$3)) -> 0 | J15: 42.5 | K15: =INDEX($U$21:$U$141,MATCH(58,$A$21:$A$141,0)) -> 0 | L15: =INDEX($U$21:$U$141,MATCH(53,$A$21:$A$141,0)) -> -8.3947358
A16: 11 | B16: =_xlfn.MINIFS($A$21:$A$141,$N$21:$N$141,">="&(MAX($N$21:$N$141)-0.000000001)) -> 40 | C16: =IF(B16>=Alpha_keep*50,"top up to "&TEXT(B16,"0.00"),"none: hire nothing") -> none: hire nothing | D16: =MIN(Cap_h,MAX(0,$B16-Alpha_keep*D$3)) -> 0 | E16: =MIN(Cap_h,MAX(0,$B16-Alpha_keep*E$3)) -> 0 | F16: =MIN(Cap_h,MAX(0,$B16-Alpha_keep*F$3)) -> 0 | G16: =MIN(Cap_h,MAX(0,$B16-Alpha_keep*G$3)) -> 0 | H16: =MIN(Cap_h,MAX(0,$B16-Alpha_keep*H$3)) -> 0 | I16: =MIN(Cap_h,MAX(0,$B16-Alpha_keep*I$3)) -> 0 | J16: 40 | K16: =INDEX($Q$21:$Q$141,MATCH(58,$A$21:$A$141,0)) -> 0 | L16: =INDEX($Q$21:$Q$141,MATCH(53,$A$21:$A$141,0)) -> -3.2
A17: Value of the team over twelve quarters, V_0(58) - V_0(53) | F17: =K5-L5 -> 23.844843
A18: Grid: lowest node | B18: 40 | C18: spacing | D18: 0.25 | E18: highest node | F18: =B18+120*D18 -> 70 | G18: Quarters whose target matches the engine | J18: =SUMPRODUCT(--(ABS(B5:B16-J5:J16)<0.000000001)) -> 12
G19: Largest gap to the engine's V_0 | J19: =MAX(BK21:BK141) -> 1.1368684e-13
A20: c | B20: node | C20: g(c) | D20: k alpha c | E20: a (lowest hire) | F20: b (highest hire) | G20: L | H20: U | I20: jL | J20: tL | K20: jU | L20: tU | M20: V_12 | N20: G_11 | O20: G_11(L) | P20: G_11(U) | Q20: V_11 | R20: G_10 | S20: G_10(L) | T20: G_10(U) | U20: V_10 | V20: G_9 | W20: G_9(L) | X20: G_9(U) | Y20: V_9 | Z20: G_8 | AA20: G_8(L) | AB20: G_8(U) | AC20: V_8 | AD20: G_7 | AE20: G_7(L) | AF20: G_7(U) | AG20: V_7 | AH20: G_6 | AI20: G_6(L) | AJ20: G_6(U) | AK20: V_6 | AL20: G_5 | AM20: G_5(L) | AN20: G_5(U) | AO20: V_5 | AP20: G_4 | AQ20: G_4(L) | AR20: G_4(U) | AS20: V_4 | AT20: G_3 | AU20: G_3(L) | AV20: G_3(U) | AW20: V_3 | AX20: G_2 | AY20: G_2(L) | AZ20: G_2(U) | BA20: V_2 | BB20: G_1 | BC20: G_1(L) | BD20: G_1(U) | BE20: V_1 | BF20: G_0 | BG20: G_0(L) | BH20: G_0(U) | BI20: V_0 | BJ20: Engine V_0 | BK20: |V_0 - engine|
A21: =$B$18 -> 40 | B21: 1 | C21: =-Short_p*MAX(Floor_c-A21,0) -> -24 | D21: =Cost_k*Alpha_keep*A21 -> 156 | E21: =MIN(Cap_h,MAX(0,$B$18+MAX(Loss_w)-Alpha_keep*A21)) -> 2.5 | F21: =MAX(MIN(Cap_h,$F$18+MIN(Loss_w)-Alpha_keep*A21),E21) -> 2.5 | G21: =Alpha_keep*A21+E21 -> 41.5 | H21: =Alpha_keep*A21+F21 -> 41.5 | I21: =MIN(INT((G21-$B$18)/$D$18+0.000000001),119) -> 6 | J21: =(G21-$B$18)/$D$18-I21 -> 0 | K21: =MIN(INT((H21-$B$18)/$D$18+0.000000001),119) -> 6 | L21: =(H21-$B$18)/$D$18-K21 -> 0 | M21: 0 | N21: =-Cost_k*$A21+Beta_q*(Declarations!$B$16*INDEX(M$21:M$141,MAX(1,MIN(121,$B21-ROUND(Declarations!$A$16/$D$18,0))))+Declarations!$B$17*INDEX(M$21:M$141,MAX(1,MIN(121,$B21-ROUND(Declarations!$A$17/$D$18,0))))+Declarations!$B$18*INDEX(M$21:M$141,MAX(1,MIN(121,$B21-ROUND(Declarations!$A$18/$D$18,0))))+Declarations!$B$19*INDEX(M$21:M$141,MAX(1,MIN(121,$B21-ROUND(Declarations!$A$19/$D$18,0))))+Declarations!$B$20*INDEX(M$21:M$141,MAX(1,MIN(121,$B21-ROUND(Declarations!$A$20/$D$18,0))))) -> -160 | O21: =INDEX(N$21:N$141,$I21+1)*(1-$J21)+INDEX(N$21:N$141,$I21+2)*$J21 -> -166 | P21: =INDEX(N$21:N$141,$K21+1)*(1-$L21)+INDEX(N$21:N$141,$K21+2)*$L21 -> -166 | Q21: =$C21+$D21+MAX(O21,P21,IF(COUNTIFS($A$21:$A$141,">="&$G21,$A$21:$A$141,"<="&$H21)>0,_xlfn.MAXIFS(N$21:N$141,$A$21:$A$141,">="&$G21,$A$21:$A$141,"<="&$H21),O21)) -> -34 | R21: =-Cost_k*$A21+Beta_q*(Declarations!$B$16*INDEX(Q$21:Q$141,MAX(1,MIN(121,$B21-ROUND(Declarations!$A$16/$D$18,0))))+Declarations!$B$17*INDEX(Q$21:Q$141,MAX(1,MIN(121,$B21-ROUND(Declarations!$A$17/$D$18,0))))+Declarations!$B$18*INDEX(Q$21:Q$141,MAX(1,MIN(121,$B21-ROUND(Declarations!$A$18/$D$18,0))))+Declarations!$B$19*INDEX(Q$21:Q$141,MAX(1,MIN(121,$B21-ROUND(Declarations!$A$19/$D$18,0))))+Declarations!$B$20*INDEX(Q$21:Q$141,MAX(1,MIN(121,$B21-ROUND(Declarations!$A$20/$D$18,0))))) -> -191.99108 | S21: =INDEX(R$21:R$141,$I21+1)*(1-$J21)+INDEX(R$21:R$141,$I21+2)*$J21 -> -191.22669 | T21: =INDEX(R$21:R$141,$K21+1)*(1-$L21)+INDEX(R$21:R$141,$K21+2)*$L21 -> -191.22669 | U21: =$C21+$D21+MAX(S21,T21,IF(COUNTIFS($A$21:$A$141,">="&$G21,$A$21:$A$141,"<="&$H21)>0,_xlfn.MAXIFS(R$21:R$141,$A$21:$A$141,">="&$G21,$A$21:$A$141,"<="&$H21),S21)) -> -59.226691 | V21: =-Cost_k*$A21+Beta_q*(Declarations!$B$16*INDEX(U$21:U$141,MAX(1,MIN(121,$B21-ROUND(Declarations!$A$16/$D$18,0))))+Declarations!$B$17*INDEX(U$21:U$141,MAX(1,MIN(121,$B21-ROUND(Declarations!$A$17/$D$18,0))))+Declarations!$B$18*INDEX(U$21:U$141,MAX(1,MIN(121,$B21-ROUND(Declarations!$A$18/$D$18,0))))+Declarations!$B$19*INDEX(U$21:U$141,MAX(1,MIN(121,$B21-ROUND(Declarations!$A$19/$D$18,0))))+Declarations!$B$20*INDEX(U$21:U$141,MAX(1,MIN(121,$B21-ROUND(Declarations!$A$20/$D$18,0))))) -> -216.4852 | W21: =INDEX(V$21:V$141,$I21+1)*(1-$J21)+INDEX(V$21:V$141,$I21+2)*$J21 -> -215.18827 | X21: =INDEX(V$21:V$141,$K21+1)*(1-$L21)+INDEX(V$21:V$141,$K21+2)*$L21 -> -215.18827 | Y21: =$C21+$D21+MAX(W21,X21,IF(COUNTIFS($A$21:$A$141,">="&$G21,$A$21:$A$141,"<="&$H21)>0,_xlfn.MAXIFS(V$21:V$141,$A$21:$A$141,">="&$G21,$A$21:$A$141,"<="&$H21),W21)) -> -83.188271 | Z21: =-Cost_k*$A21+Beta_q*(Declarations!$B$16*INDEX(Y$21:Y$141,MAX(1,MIN(121,$B21-ROUND(Declarations!$A$16/$D$18,0))))+Declarations!$B$17*INDEX(Y$21:Y$141,MAX(1,MIN(121,$B21-ROUND(Declarations!$A$17/$D$18,0))))+Declarations!$B$18*INDEX(Y$21:Y$141,MAX(1,MIN(121,$B21-ROUND(Declarations!$A$18/$D$18,0))))+Declarations!$B$19*INDEX(Y$21:Y$141,MAX(1,MIN(121,$B21-ROUND(Declarations!$A$19/$D$18,0))))+Declarations!$B$20*INDEX(Y$21:Y$141,MAX(1,MIN(121,$B21-ROUND(Declarations!$A$20/$D$18,0))))) -> -239.72106 | AA21: =INDEX(Z$21:Z$141,$I21+1)*(1-$J21)+INDEX(Z$21:Z$141,$I21+2)*$J21 -> -237.35706 | AB21: =INDEX(Z$21:Z$141,$K21+1)*(1-$L21)+INDEX(Z$21:Z$141,$K21+2)*$L21 -> -237.35706 | AC21: =$C21+$D21+MAX(AA21,AB21,IF(COUNTIFS($A$21:$A$141,">="&$G21,$A$21:$A$141,"<="&$H21)>0,_xlfn.MAXIFS(Z$21:Z$141,$A$21:$A$141,">="&$G21,$A$21:$A$141,"<="&$H21),AA21)) -> -105.35706 | AD21: =-Cost_k*$A21+Beta_q*(Declarations!$B$16*INDEX(AC$21:AC$141,MAX(1,MIN(121,$B21-ROUND(Declarations!$A$16/$D$18,0))))+Declarations!$B$17*INDEX(AC$21:AC$141,MAX(1,MIN(121,$B21-ROUND(Declarations!$A$17/$D$18,0))))+Declarations!$B$18*INDEX(AC$21:AC$141,MAX(1,MIN(121,$B21-ROUND(Declarations!$A$18/$D$18,0))))+Declarations!$B$19*INDEX(AC$21:AC$141,MAX(1,MIN(121,$B21-ROUND(Declarations!$A$19/$D$18,0))))+Declarations!$B$20*INDEX(AC$21:AC$141,MAX(1,MIN(121,$B21-ROUND(Declarations!$A$20/$D$18,0))))) -> -261.22411 | AE21: =INDEX(AD$21:AD$141,$I21+1)*(1-$J21)+INDEX(AD$21:AD$141,$I21+2)*$J21 -> -258.14726 | AF21: =INDEX(AD$21:AD$141,$K21+1)*(1-$L21)+INDEX(AD$21:AD$141,$K21+2)*$L21 -> -258.14726 | AG21: =$C21+$D21+MAX(AE21,AF21,IF(COUNTIFS($A$21:$A$141,">="&$G21,$A$21:$A$141,"<="&$H21)>0,_xlfn.MAXIFS(AD$21:AD$141,$A$21:$A$141,">="&$G21,$A$21:$A$141,"<="&$H21),AE21)) -> -126.14726 | AH21: =-Cost_k*$A21+Beta_q*(Declarations!$B$16*INDEX(AG$21:AG$141,MAX(1,MIN(121,$B21-ROUND(Declarations!$A$16/$D$18,0))))+Declarations!$B$17*INDEX(AG$21:AG$141,MAX(1,MIN(121,$B21-ROUND(Declarations!$A$17/$D$18,0))))+Declarations!$B$18*INDEX(AG$21:AG$141,MAX(1,MIN(121,$B21-ROUND(Declarations!$A$18/$D$18,0))))+Declarations!$B$19*INDEX(AG$21:AG$141,MAX(1,MIN(121,$B21-ROUND(Declarations!$A$19/$D$18,0))))+Declarations!$B$20*INDEX(AG$21:AG$141,MAX(1,MIN(121,$B21-ROUND(Declarations!$A$20/$D$18,0))))) -> -281.37102 | AI21: =INDEX(AH$21:AH$141,$I21+1)*(1-$J21)+INDEX(AH$21:AH$141,$I21+2)*$J21 -> -277.23377 | AJ21: =INDEX(AH$21:AH$141,$K21+1)*(1-$L21)+INDEX(AH$21:AH$141,$K21+2)*$L21 -> -277.23377 | AK21: =$C21+$D21+MAX(AI21,AJ21,IF(COUNTIFS($A$21:$A$141,">="&$G21,$A$21:$A$141,"<="&$H21)>0,_xlfn.MAXIFS(AH$21:AH$141,$A$21:$A$141,">="&$G21,$A$21:$A$141,"<="&$H21),AI21)) -> -145.23377 | AL21: =-Cost_k*$A21+Beta_q*(Declarations!$B$16*INDEX(AK$21:AK$141,MAX(1,MIN(121,$B21-ROUND(Declarations!$A$16/$D$18,0))))+Declarations!$B$17*INDEX(AK$21:AK$141,MAX(1,MIN(121,$B21-ROUND(Declarations!$A$17/$D$18,0))))+Declarations!$B$18*INDEX(AK$21:AK$141,MAX(1,MIN(121,$B21-ROUND(Declarations!$A$18/$D$18,0))))+Declarations!$B$19*INDEX(AK$21:AK$141,MAX(1,MIN(121,$B21-ROUND(Declarations!$A$19/$D$18,0))))+Declarations!$B$20*INDEX(AK$21:AK$141,MAX(1,MIN(121,$B21-ROUND(Declarations!$A$20/$D$18,0))))) -> -299.79743 | AM21: =INDEX(AL$21:AL$141,$I21+1)*(1-$J21)+INDEX(AL$21:AL$141,$I21+2)*$J21 -> -294.49319 | AN21: =INDEX(AL$21:AL$141,$K21+1)*(1-$L21)+INDEX(AL$21:AL$141,$K21+2)*$L21 -> -294.49319 | AO21: =$C21+$D21+MAX(AM21,AN21,IF(COUNTIFS($A$21:$A$141,">="&$G21,$A$21:$A$141,"<="&$H21)>0,_xlfn.MAXIFS(AL$21:AL$141,$A$21:$A$141,">="&$G21,$A$21:$A$141,"<="&$H21),AM21)) -> -162.49319 | AP21: =-Cost_k*$A21+Beta_q*(Declarations!$B$16*INDEX(AO$21:AO$141,MAX(1,MIN(121,$B21-ROUND(Declarations!$A$16/$D$18,0))))+Declarations!$B$17*INDEX(AO$21:AO$141,MAX(1,MIN(121,$B21-ROUND(Declarations!$A$17/$D$18,0))))+Declarations!$B$18*INDEX(AO$21:AO$141,MAX(1,MIN(121,$B21-ROUND(Declarations!$A$18/$D$18,0))))+Declarations!$B$19*INDEX(AO$21:AO$141,MAX(1,MIN(121,$B21-ROUND(Declarations!$A$19/$D$18,0))))+Declarations!$B$20*INDEX(AO$21:AO$141,MAX(1,MIN(121,$B21-ROUND(Declarations!$A$20/$D$18,0))))) -> -316.4619 | AQ21: =INDEX(AP$21:AP$141,$I21+1)*(1-$J21)+INDEX(AP$21:AP$141,$I21+2)*$J21 -> -310.06124 | AR21: =INDEX(AP$21:AP$141,$K21+1)*(1-$L21)+INDEX(AP$21:AP$141,$K21+2)*$L21 -> -310.06124 | AS21: =$C21+$D21+MAX(AQ21,AR21,IF(COUNTIFS($A$21:$A$141,">="&$G21,$A$21:$A$141,"<="&$H21)>0,_xlfn.MAXIFS(AP$21:AP$141,$A$21:$A$141,">="&$G21,$A$21:$A$141,"<="&$H21),AQ21)) -> -178.06124 | AT21: =-Cost_k*$A21+Beta_q*(Declarations!$B$16*INDEX(AS$21:AS$141,MAX(1,MIN(121,$B21-ROUND(Declarations!$A$16/$D$18,0))))+Declarations!$B$17*INDEX(AS$21:AS$141,MAX(1,MIN(121,$B21-ROUND(Declarations!$A$17/$D$18,0))))+Declarations!$B$18*INDEX(AS$21:AS$141,MAX(1,MIN(121,$B21-ROUND(Declarations!$A$18/$D$18,0))))+Declarations!$B$19*INDEX(AS$21:AS$141,MAX(1,MIN(121,$B21-ROUND(Declarations!$A$19/$D$18,0))))+Declarations!$B$20*INDEX(AS$21:AS$141,MAX(1,MIN(121,$B21-ROUND(Declarations!$A$20/$D$18,0))))) -> -331.46133 | AU21: =INDEX(AT$21:AT$141,$I21+1)*(1-$J21)+INDEX(AT$21:AT$141,$I21+2)*$J21 -> -323.8599 | AV21: =INDEX(AT$21:AT$141,$K21+1)*(1-$L21)+INDEX(AT$21:AT$141,$K21+2)*$L21 -> -323.8599 | AW21: =$C21+$D21+MAX(AU21,AV21,IF(COUNTIFS($A$21:$A$141,">="&$G21,$A$21:$A$141,"<="&$H21)>0,_xlfn.MAXIFS(AT$21:AT$141,$A$21:$A$141,">="&$G21,$A$21:$A$141,"<="&$H21),AU21)) -> -191.8599 | AX21: =-Cost_k*$A21+Beta_q*(Declarations!$B$16*INDEX(AW$21:AW$141,MAX(1,MIN(121,$B21-ROUND(Declarations!$A$16/$D$18,0))))+Declarations!$B$17*INDEX(AW$21:AW$141,MAX(1,MIN(121,$B21-ROUND(Declarations!$A$17/$D$18,0))))+Declarations!$B$18*INDEX(AW$21:AW$141,MAX(1,MIN(121,$B21-ROUND(Declarations!$A$18/$D$18,0))))+Declarations!$B$19*INDEX(AW$21:AW$141,MAX(1,MIN(121,$B21-ROUND(Declarations!$A$19/$D$18,0))))+Declarations!$B$20*INDEX(AW$21:AW$141,MAX(1,MIN(121,$B21-ROUND(Declarations!$A$20/$D$18,0))))) -> -344.71587 | AY21: =INDEX(AX$21:AX$141,$I21+1)*(1-$J21)+INDEX(AX$21:AX$141,$I21+2)*$J21 -> -335.84434 | AZ21: =INDEX(AX$21:AX$141,$K21+1)*(1-$L21)+INDEX(AX$21:AX$141,$K21+2)*$L21 -> -335.84434 | BA21: =$C21+$D21+MAX(AY21,AZ21,IF(COUNTIFS($A$21:$A$141,">="&$G21,$A$21:$A$141,"<="&$H21)>0,_xlfn.MAXIFS(AX$21:AX$141,$A$21:$A$141,">="&$G21,$A$21:$A$141,"<="&$H21),AY21)) -> -203.84434 | BB21: =-Cost_k*$A21+Beta_q*(Declarations!$B$16*INDEX(BA$21:BA$141,MAX(1,MIN(121,$B21-ROUND(Declarations!$A$16/$D$18,0))))+Declarations!$B$17*INDEX(BA$21:BA$141,MAX(1,MIN(121,$B21-ROUND(Declarations!$A$17/$D$18,0))))+Declarations!$B$18*INDEX(BA$21:BA$141,MAX(1,MIN(121,$B21-ROUND(Declarations!$A$18/$D$18,0))))+Declarations!$B$19*INDEX(BA$21:BA$141,MAX(1,MIN(121,$B21-ROUND(Declarations!$A$19/$D$18,0))))+Declarations!$B$20*INDEX(BA$21:BA$141,MAX(1,MIN(121,$B21-ROUND(Declarations!$A$20/$D$18,0))))) -> -356.19776 | BC21: =INDEX(BB$21:BB$141,$I21+1)*(1-$J21)+INDEX(BB$21:BB$141,$I21+2)*$J21 -> -346.07244 | BD21: =INDEX(BB$21:BB$141,$K21+1)*(1-$L21)+INDEX(BB$21:BB$141,$K21+2)*$L21 -> -346.07244 | BE21: =$C21+$D21+MAX(BC21,BD21,IF(COUNTIFS($A$21:$A$141,">="&$G21,$A$21:$A$141,"<="&$H21)>0,_xlfn.MAXIFS(BB$21:BB$141,$A$21:$A$141,">="&$G21,$A$21:$A$141,"<="&$H21),BC21)) -> -214.07244 | BF21: =-Cost_k*$A21+Beta_q*(Declarations!$B$16*INDEX(BE$21:BE$141,MAX(1,MIN(121,$B21-ROUND(Declarations!$A$16/$D$18,0))))+Declarations!$B$17*INDEX(BE$21:BE$141,MAX(1,MIN(121,$B21-ROUND(Declarations!$A$17/$D$18,0))))+Declarations!$B$18*INDEX(BE$21:BE$141,MAX(1,MIN(121,$B21-ROUND(Declarations!$A$18/$D$18,0))))+Declarations!$B$19*INDEX(BE$21:BE$141,MAX(1,MIN(121,$B21-ROUND(Declarations!$A$19/$D$18,0))))+Declarations!$B$20*INDEX(BE$21:BE$141,MAX(1,MIN(121,$B21-ROUND(Declarations!$A$20/$D$18,0))))) -> -365.97493 | BG21: =INDEX(BF$21:BF$141,$I21+1)*(1-$J21)+INDEX(BF$21:BF$141,$I21+2)*$J21 -> -354.67259 | BH21: =INDEX(BF$21:BF$141,$K21+1)*(1-$L21)+INDEX(BF$21:BF$141,$K21+2)*$L21 -> -354.67259 | BI21: =$C21+$D21+MAX(BG21,BH21,IF(COUNTIFS($A$21:$A$141,">="&$G21,$A$21:$A$141,"<="&$H21)>0,_xlfn.MAXIFS(BF$21:BF$141,$A$21:$A$141,">="&$G21,$A$21:$A$141,"<="&$H21),BG21)) -> -222.67259 | BJ21: -222.67259 | BK21: =ABS(BI21-BJ21) -> 0
A22: =A21+$D$18 -> 40.25 | B22: 2 | C22: =-Short_p*MAX(Floor_c-A22,0) -> -23.6 | D22: =Cost_k*Alpha_keep*A22 -> 156.975 | E22: =MIN(Cap_h,MAX(0,$B$18+MAX(Loss_w)-Alpha_keep*A22)) -> 2.25625 | F22: =MAX(MIN(Cap_h,$F$18+MIN(Loss_w)-Alpha_keep*A22),E22) -> 2.5 | G22: =Alpha_keep*A22+E22 -> 41.5 | H22: =Alpha_keep*A22+F22 -> 41.74375 | I22: =MIN(INT((G22-$B$18)/$D$18+0.000000001),119) -> 6 | J22: =(G22-$B$18)/$D$18-I22 -> 0 | K22: =MIN(INT((H22-$B$18)/$D$18+0.000000001),119) -> 6 | L22: =(H22-$B$18)/$D$18-K22 -> 0.975 | M22: 0 | N22: =-Cost_k*$A22+Beta_q*(Declarations!$B$16*INDEX(M$21:M$141,MAX(1,MIN(121,$B22-ROUND(Declarations!$A$16/$D$18,0))))+Declarations!$B$17*INDEX(M$21:M$141,MAX(1,MIN(121,$B22-ROUND(Declarations!$A$17/$D$18,0))))+Declarations!$B$18*INDEX(M$21:M$141,MAX(1,MIN(121,$B22-ROUND(Declarations!$A$18/$D$18,0))))+Declarations!$B$19*INDEX(M$21:M$141,MAX(1,MIN(121,$B22-ROUND(Declarations!$A$19/$D$18,0))))+Declarations!$B$20*INDEX(M$21:M$141,MAX(1,MIN(121,$B22-ROUND(Declarations!$A$20/$D$18,0))))) -> -161 | O22: =INDEX(N$21:N$141,$I22+1)*(1-$J22)+INDEX(N$21:N$141,$I22+2)*$J22 -> -166 | P22: =INDEX(N$21:N$141,$K22+1)*(1-$L22)+INDEX(N$21:N$141,$K22+2)*$L22 -> -166.975 | Q22: =$C22+$D22+MAX(O22,P22,IF(COUNTIFS($A$21:$A$141,">="&$G22,$A$21:$A$141,"<="&$H22)>0,_xlfn.MAXIFS(N$21:N$141,$A$21:$A$141,">="&$G22,$A$21:$A$141,"<="&$H22),O22)) -> -32.625 | R22: =-Cost_k*$A22+Beta_q*(Declarations!$B$16*INDEX(Q$21:Q$141,MAX(1,MIN(121,$B22-ROUND(Declarations!$A$16/$D$18,0))))+Declarations!$B$17*INDEX(Q$21:Q$141,MAX(1,MIN(121,$B22-ROUND(Declarations!$A$17/$D$18,0))))+Declarations!$B$18*INDEX(Q$21:Q$141,MAX(1,MIN(121,$B22-ROUND(Declarations!$A$18/$D$18,0))))+Declarations!$B$19*INDEX(Q$21:Q$141,MAX(1,MIN(121,$B22-ROUND(Declarations!$A$19/$D$18,0))))+Declarations!$B$20*INDEX(Q$21:Q$141,MAX(1,MIN(121,$B22-ROUND(Declarations!$A$20/$D$18,0))))) -> -191.98411 | S22: =INDEX(R$21:R$141,$I22+1)*(1-$J22)+INDEX(R$21:R$141,$I22+2)*$J22 -> -191.22669 | T22: =INDEX(R$21:R$141,$K22+1)*(1-$L22)+INDEX(R$21:R$141,$K22+2)*$L22 -> -190.93904 | U22: =$C22+$D22+MAX(S22,T22,IF(COUNTIFS($A$21:$A$141,">="&$G22,$A$21:$A$141,"<="&$H22)>0,_xlfn.MAXIFS(R$21:R$141,$A$21:$A$141,">="&$G22,$A$21:$A$141,"<="&$H22),S22)) -> -57.564045 | V22: =-Cost_k*$A22+Beta_q*(Declarations!$B$16*INDEX(U$21:U$141,MAX(1,MIN(121,$B22-ROUND(Declarations!$A$16/$D$18,0))))+Declarations!$B$17*INDEX(U$21:U$141,MAX(1,MIN(121,$B22-ROUND(Declarations!$A$17/$D$18,0))))+Declarations!$B$18*INDEX(U$21:U$141,MAX(1,MIN(121,$B22-ROUND(Declarations!$A$18/$D$18,0))))+Declarations!$B$19*INDEX(U$21:U$141,MAX(1,MIN(121,$B22-ROUND(Declarations!$A$19/$D$18,0))))+Declarations!$B$20*INDEX(U$21:U$141,MAX(1,MIN(121,$B22-ROUND(Declarations!$A$20/$D$18,0))))) -> -216.31787 | W22: =INDEX(V$21:V$141,$I22+1)*(1-$J22)+INDEX(V$21:V$141,$I22+2)*$J22 -> -215.18827 | X22: =INDEX(V$21:V$141,$K22+1)*(1-$L22)+INDEX(V$21:V$141,$K22+2)*$L22 -> -214.8211 | Y22: =$C22+$D22+MAX(W22,X22,IF(COUNTIFS($A$21:$A$141,">="&$G22,$A$21:$A$141,"<="&$H22)>0,_xlfn.MAXIFS(V$21:V$141,$A$21:$A$141,">="&$G22,$A$21:$A$141,"<="&$H22),W22)) -> -81.446098 | Z22: =-Cost_k*$A22+Beta_q*(Declarations!$B$16*INDEX(Y$21:Y$141,MAX(1,MIN(121,$B22-ROUND(Declarations!$A$16/$D$18,0))))+Declarations!$B$17*INDEX(Y$21:Y$141,MAX(1,MIN(121,$B22-ROUND(Declarations!$A$17/$D$18,0))))+Declarations!$B$18*INDEX(Y$21:Y$141,MAX(1,MIN(121,$B22-ROUND(Declarations!$A$18/$D$18,0))))+Declarations!$B$19*INDEX(Y$21:Y$141,MAX(1,MIN(121,$B22-ROUND(Declarations!$A$19/$D$18,0))))+Declarations!$B$20*INDEX(Y$21:Y$141,MAX(1,MIN(121,$B22-ROUND(Declarations!$A$20/$D$18,0))))) -> -239.45906 | AA22: =INDEX(Z$21:Z$141,$I22+1)*(1-$J22)+INDEX(Z$21:Z$141,$I22+2)*$J22 -> -237.35706 | AB22: =INDEX(Z$21:Z$141,$K22+1)*(1-$L22)+INDEX(Z$21:Z$141,$K22+2)*$L22 -> -236.80811 | AC22: =$C22+$D22+MAX(AA22,AB22,IF(COUNTIFS($A$21:$A$141,">="&$G22,$A$21:$A$141,"<="&$H22)>0,_xlfn.MAXIFS(Z$21:Z$141,$A$21:$A$141,">="&$G22,$A$21:$A$141,"<="&$H22),AA22)) -> -103.43311 | AD22: =-Cost_k*$A22+Beta_q*(Declarations!$B$16*INDEX(AC$21:AC$141,MAX(1,MIN(121,$B22-ROUND(Declarations!$A$16/$D$18,0))))+Declarations!$B$17*INDEX(AC$21:AC$141,MAX(1,MIN(121,$B22-ROUND(Declarations!$A$17/$D$18,0))))+Declarations!$B$18*INDEX(AC$21:AC$141,MAX(1,MIN(121,$B22-ROUND(Declarations!$A$18/$D$18,0))))+Declarations!$B$19*INDEX(AC$21:AC$141,MAX(1,MIN(121,$B22-ROUND(Declarations!$A$19/$D$18,0))))+Declarations!$B$20*INDEX(AC$21:AC$141,MAX(1,MIN(121,$B22-ROUND(Declarations!$A$20/$D$18,0))))) -> -260.84571 | AE22: =INDEX(AD$21:AD$141,$I22+1)*(1-$J22)+INDEX(AD$21:AD$141,$I22+2)*$J22 -> -258.14726 | AF22: =INDEX(AD$21:AD$141,$K22+1)*(1-$L22)+INDEX(AD$21:AD$141,$K22+2)*$L22 -> -257.45025 | AG22: =$C22+$D22+MAX(AE22,AF22,IF(COUNTIFS($A$21:$A$141,">="&$G22,$A$21:$A$141,"<="&$H22)>0,_xlfn.MAXIFS(AD$21:AD$141,$A$21:$A$141,">="&$G22,$A$21:$A$141,"<="&$H22),AE22)) -> -124.07525 | AH22: =-Cost_k*$A22+Beta_q*(Declarations!$B$16*INDEX(AG$21:AG$141,MAX(1,MIN(121,$B22-ROUND(Declarations!$A$16/$D$18,0))))+Declarations!$B$17*INDEX(AG$21:AG$141,MAX(1,MIN(121,$B22-ROUND(Declarations!$A$17/$D$18,0))))+Declarations!$B$18*INDEX(AG$21:AG$141,MAX(1,MIN(121,$B22-ROUND(Declarations!$A$18/$D$18,0))))+Declarations!$B$19*INDEX(AG$21:AG$141,MAX(1,MIN(121,$B22-ROUND(Declarations!$A$19/$D$18,0))))+Declarations!$B$20*INDEX(AG$21:AG$141,MAX(1,MIN(121,$B22-ROUND(Declarations!$A$20/$D$18,0))))) -> -280.86333 | AI22: =INDEX(AH$21:AH$141,$I22+1)*(1-$J22)+INDEX(AH$21:AH$141,$I22+2)*$J22 -> -277.23377 | AJ22: =INDEX(AH$21:AH$141,$K22+1)*(1-$L22)+INDEX(AH$21:AH$141,$K22+2)*$L22 -> -276.29621 | AK22: =$C22+$D22+MAX(AI22,AJ22,IF(COUNTIFS($A$21:$A$141,">="&$G22,$A$21:$A$141,"<="&$H22)>0,_xlfn.MAXIFS(AH$21:AH$141,$A$21:$A$141,">="&$G22,$A$21:$A$141,"<="&$H22),AI22)) -> -142.92121 | AL22: =-Cost_k*$A22+Beta_q*(Declarations!$B$16*INDEX(AK$21:AK$141,MAX(1,MIN(121,$B22-ROUND(Declarations!$A$16/$D$18,0))))+Declarations!$B$17*INDEX(AK$21:AK$141,MAX(1,MIN(121,$B22-ROUND(Declarations!$A$17/$D$18,0))))+Declarations!$B$18*INDEX(AK$21:AK$141,MAX(1,MIN(121,$B22-ROUND(Declarations!$A$18/$D$18,0))))+Declarations!$B$19*INDEX(AK$21:AK$141,MAX(1,MIN(121,$B22-ROUND(Declarations!$A$19/$D$18,0))))+Declarations!$B$20*INDEX(AK$21:AK$141,MAX(1,MIN(121,$B22-ROUND(Declarations!$A$20/$D$18,0))))) -> -299.11454 | AM22: =INDEX(AL$21:AL$141,$I22+1)*(1-$J22)+INDEX(AL$21:AL$141,$I22+2)*$J22 -> -294.49319 | AN22: =INDEX(AL$21:AL$141,$K22+1)*(1-$L22)+INDEX(AL$21:AL$141,$K22+2)*$L22 -> -293.34105 | AO22: =$C22+$D22+MAX(AM22,AN22,IF(COUNTIFS($A$21:$A$141,">="&$G22,$A$21:$A$141,"<="&$H22)>0,_xlfn.MAXIFS(AL$21:AL$141,$A$21:$A$141,">="&$G22,$A$21:$A$141,"<="&$H22),AM22)) -> -159.96605 | AP22: =-Cost_k*$A22+Beta_q*(Declarations!$B$16*INDEX(AO$21:AO$141,MAX(1,MIN(121,$B22-ROUND(Declarations!$A$16/$D$18,0))))+Declarations!$B$17*INDEX(AO$21:AO$141,MAX(1,MIN(121,$B22-ROUND(Declarations!$A$17/$D$18,0))))+Declarations!$B$18*INDEX(AO$21:AO$141,MAX(1,MIN(121,$B22-ROUND(Declarations!$A$18/$D$18,0))))+Declarations!$B$19*INDEX(AO$21:AO$141,MAX(1,MIN(121,$B22-ROUND(Declarations!$A$19/$D$18,0))))+Declarations!$B$20*INDEX(AO$21:AO$141,MAX(1,MIN(121,$B22-ROUND(Declarations!$A$20/$D$18,0))))) -> -315.62139 | AQ22: =INDEX(AP$21:AP$141,$I22+1)*(1-$J22)+INDEX(AP$21:AP$141,$I22+2)*$J22 -> -310.06124 | AR22: =INDEX(AP$21:AP$141,$K22+1)*(1-$L22)+INDEX(AP$21:AP$141,$K22+2)*$L22 -> -308.68812 | AS22: =$C22+$D22+MAX(AQ22,AR22,IF(COUNTIFS($A$21:$A$141,">="&$G22,$A$21:$A$141,"<="&$H22)>0,_xlfn.MAXIFS(AP$21:AP$141,$A$21:$A$141,">="&$G22,$A$21:$A$141,"<="&$H22),AQ22)) -> -175.31312 | AT22: =-Cost_k*$A22+Beta_q*(Declarations!$B$16*INDEX(AS$21:AS$141,MAX(1,MIN(121,$B22-ROUND(Declarations!$A$16/$D$18,0))))+Declarations!$B$17*INDEX(AS$21:AS$141,MAX(1,MIN(121,$B22-ROUND(Declarations!$A$17/$D$18,0))))+Declarations!$B$18*INDEX(AS$21:AS$141,MAX(1,MIN(121,$B22-ROUND(Declarations!$A$18/$D$18,0))))+Declarations!$B$19*INDEX(AS$21:AS$141,MAX(1,MIN(121,$B22-ROUND(Declarations!$A$19/$D$18,0))))+Declarations!$B$20*INDEX(AS$21:AS$141,MAX(1,MIN(121,$B22-ROUND(Declarations!$A$20/$D$18,0))))) -> -330.45356 | AU22: =INDEX(AT$21:AT$141,$I22+1)*(1-$J22)+INDEX(AT$21:AT$141,$I22+2)*$J22 -> -323.8599 | AV22: =INDEX(AT$21:AT$141,$K22+1)*(1-$L22)+INDEX(AT$21:AT$141,$K22+2)*$L22 -> -322.24323 | AW22: =$C22+$D22+MAX(AU22,AV22,IF(COUNTIFS($A$21:$A$141,">="&$G22,$A$21:$A$141,"<="&$H22)>0,_xlfn.MAXIFS(AT$21:AT$141,$A$21:$A$141,">="&$G22,$A$21:$A$141,"<="&$H22),AU22)) -> -188.86823 | AX22: =-Cost_k*$A22+Beta_q*(Declarations!$B$16*INDEX(AW$21:AW$141,MAX(1,MIN(121,$B22-ROUND(Declarations!$A$16/$D$18,0))))+Declarations!$B$17*INDEX(AW$21:AW$141,MAX(1,MIN(121,$B22-ROUND(Declarations!$A$17/$D$18,0))))+Declarations!$B$18*INDEX(AW$21:AW$141,MAX(1,MIN(121,$B22-ROUND(Declarations!$A$18/$D$18,0))))+Declarations!$B$19*INDEX(AW$21:AW$141,MAX(1,MIN(121,$B22-ROUND(Declarations!$A$19/$D$18,0))))+Declarations!$B$20*INDEX(AW$21:AW$141,MAX(1,MIN(121,$B22-ROUND(Declarations!$A$20/$D$18,0))))) -> -343.52648 | AY22: =INDEX(AX$21:AX$141,$I22+1)*(1-$J22)+INDEX(AX$21:AX$141,$I22+2)*$J22 -> -335.84434 | AZ22: =INDEX(AX$21:AX$141,$K22+1)*(1-$L22)+INDEX(AX$21:AX$141,$K22+2)*$L22 -> -333.97881 | BA22: =$C22+$D22+MAX(AY22,AZ22,IF(COUNTIFS($A$21:$A$141,">="&$G22,$A$21:$A$141,"<="&$H22)>0,_xlfn.MAXIFS(AX$21:AX$141,$A$21:$A$141,">="&$G22,$A$21:$A$141,"<="&$H22),AY22)) -> -200.60381 | BB22: =-Cost_k*$A22+Beta_q*(Declarations!$B$16*INDEX(BA$21:BA$141,MAX(1,MIN(121,$B22-ROUND(Declarations!$A$16/$D$18,0))))+Declarations!$B$17*INDEX(BA$21:BA$141,MAX(1,MIN(121,$B22-ROUND(Declarations!$A$17/$D$18,0))))+Declarations!$B$18*INDEX(BA$21:BA$141,MAX(1,MIN(121,$B22-ROUND(Declarations!$A$18/$D$18,0))))+Declarations!$B$19*INDEX(BA$21:BA$141,MAX(1,MIN(121,$B22-ROUND(Declarations!$A$19/$D$18,0))))+Declarations!$B$20*INDEX(BA$21:BA$141,MAX(1,MIN(121,$B22-ROUND(Declarations!$A$20/$D$18,0))))) -> -354.82518 | BC22: =INDEX(BB$21:BB$141,$I22+1)*(1-$J22)+INDEX(BB$21:BB$141,$I22+2)*$J22 -> -346.07244 | BD22: =INDEX(BB$21:BB$141,$K22+1)*(1-$L22)+INDEX(BB$21:BB$141,$K22+2)*$L22 -> -343.96684 | BE22: =$C22+$D22+MAX(BC22,BD22,IF(COUNTIFS($A$21:$A$141,">="&$G22,$A$21:$A$141,"<="&$H22)>0,_xlfn.MAXIFS(BB$21:BB$141,$A$21:$A$141,">="&$G22,$A$21:$A$141,"<="&$H22),BC22)) -> -210.59184 | BF22: =-Cost_k*$A22+Beta_q*(Declarations!$B$16*INDEX(BE$21:BE$141,MAX(1,MIN(121,$B22-ROUND(Declarations!$A$16/$D$18,0))))+Declarations!$B$17*INDEX(BE$21:BE$141,MAX(1,MIN(121,$B22-ROUND(Declarations!$A$17/$D$18,0))))+Declarations!$B$18*INDEX(BE$21:BE$141,MAX(1,MIN(121,$B22-ROUND(Declarations!$A$18/$D$18,0))))+Declarations!$B$19*INDEX(BE$21:BE$141,MAX(1,MIN(121,$B22-ROUND(Declarations!$A$19/$D$18,0))))+Declarations!$B$20*INDEX(BE$21:BE$141,MAX(1,MIN(121,$B22-ROUND(Declarations!$A$20/$D$18,0))))) -> -364.4273 | BG22: =INDEX(BF$21:BF$141,$I22+1)*(1-$J22)+INDEX(BF$21:BF$141,$I22+2)*$J22 -> -354.67259 | BH22: =INDEX(BF$21:BF$141,$K22+1)*(1-$L22)+INDEX(BF$21:BF$141,$K22+2)*$L22 -> -352.34687 | BI22: =$C22+$D22+MAX(BG22,BH22,IF(COUNTIFS($A$21:$A$141,">="&$G22,$A$21:$A$141,"<="&$H22)>0,_xlfn.MAXIFS(BF$21:BF$141,$A$21:$A$141,">="&$G22,$A$21:$A$141,"<="&$H22),BG22)) -> -218.97187 | BJ22: -218.97187 | BK22: =ABS(BI22-BJ22) -> 0
A23: =A22+$D$18 -> 40.5 | B23: 3 | C23: =-Short_p*MAX(Floor_c-A23,0) -> -23.2 | D23: =Cost_k*Alpha_keep*A23 -> 157.95 | E23: =MIN(Cap_h,MAX(0,$B$18+MAX(Loss_w)-Alpha_keep*A23)) -> 2.0125 | F23: =MAX(MIN(Cap_h,$F$18+MIN(Loss_w)-Alpha_keep*A23),E23) -> 2.5 | G23: =Alpha_keep*A23+E23 -> 41.5 | H23: =Alpha_keep*A23+F23 -> 41.9875 | I23: =MIN(INT((G23-$B$18)/$D$18+0.000000001),119) -> 6 | J23: =(G23-$B$18)/$D$18-I23 -> 0 | K23: =MIN(INT((H23-$B$18)/$D$18+0.000000001),119) -> 7 | L23: =(H23-$B$18)/$D$18-K23 -> 0.95 | M23: 0 | N23: =-Cost_k*$A23+Beta_q*(Declarations!$B$16*INDEX(M$21:M$141,MAX(1,MIN(121,$B23-ROUND(Declarations!$A$16/$D$18,0))))+Declarations!$B$17*INDEX(M$21:M$141,MAX(1,MIN(121,$B23-ROUND(Declarations!$A$17/$D$18,0))))+Declarations!$B$18*INDEX(M$21:M$141,MAX(1,MIN(121,$B23-ROUND(Declarations!$A$18/$D$18,0))))+Declarations!$B$19*INDEX(M$21:M$141,MAX(1,MIN(121,$B23-ROUND(Declarations!$A$19/$D$18,0))))+Declarations!$B$20*INDEX(M$21:M$141,MAX(1,MIN(121,$B23-ROUND(Declarations!$A$20/$D$18,0))))) -> -162 | O23: =INDEX(N$21:N$141,$I23+1)*(1-$J23)+INDEX(N$21:N$141,$I23+2)*$J23 -> -166 | P23: =INDEX(N$21:N$141,$K23+1)*(1-$L23)+INDEX(N$21:N$141,$K23+2)*$L23 -> -167.95 | Q23: =$C23+$D23+MAX(O23,P23,IF(COUNTIFS($A$21:$A$141,">="&$G23,$A$21:$A$141,"<="&$H23)>0,_xlfn.MAXIFS(N$21:N$141,$A$21:$A$141,">="&$G23,$A$21:$A$141,"<="&$H23),O23)) -> -31.25 | R23: =-Cost_k*$A23+Beta_q*(Declarations!$B$16*INDEX(Q$21:Q$141,MAX(1,MIN(121,$B23-ROUND(Declarations!$A$16/$D$18,0))))+Declarations!$B$17*INDEX(Q$21:Q$141,MAX(1,MIN(121,$B23-ROUND(Declarations!$A$17/$D$18,0))))+Declarations!$B$18*INDEX(Q$21:Q$141,MAX(1,MIN(121,$B23-ROUND(Declarations!$A$18/$D$18,0))))+Declarations!$B$19*INDEX(Q$21:Q$141,MAX(1,MIN(121,$B23-ROUND(Declarations!$A$19/$D$18,0))))+Declarations!$B$20*INDEX(Q$21:Q$141,MAX(1,MIN(121,$B23-ROUND(Declarations!$A$20/$D$18,0))))) -> -191.97714 | S23: =INDEX(R$21:R$141,$I23+1)*(1-$J23)+INDEX(R$21:R$141,$I23+2)*$J23 -> -191.22669 | T23: =INDEX(R$21:R$141,$K23+1)*(1-$L23)+INDEX(R$21:R$141,$K23+2)*$L23 -> -190.7859 | U23: =$C23+$D23+MAX(S23,T23,IF(COUNTIFS($A$21:$A$141,">="&$G23,$A$21:$A$141,"<="&$H23)>0,_xlfn.MAXIFS(R$21:R$141,$A$21:$A$141,">="&$G23,$A$21:$A$141,"<="&$H23),S23)) -> -56.035905 | V23: =-Cost_k*$A23+Beta_q*(Declarations!$B$16*INDEX(U$21:U$141,MAX(1,MIN(121,$B23-ROUND(Declarations!$A$16/$D$18,0))))+Declarations!$B$17*INDEX(U$21:U$141,MAX(1,MIN(121,$B23-ROUND(Declarations!$A$17/$D$18,0))))+Declarations!$B$18*INDEX(U$21:U$141,MAX(1,MIN(121,$B23-ROUND(Declarations!$A$18/$D$18,0))))+Declarations!$B$19*INDEX(U$21:U$141,MAX(1,MIN(121,$B23-ROUND(Declarations!$A$19/$D$18,0))))+Declarations!$B$20*INDEX(U$21:U$141,MAX(1,MIN(121,$B23-ROUND(Declarations!$A$20/$D$18,0))))) -> -216.23409 | W23: =INDEX(V$21:V$141,$I23+1)*(1-$J23)+INDEX(V$21:V$141,$I23+2)*$J23 -> -215.18827 | X23: =INDEX(V$21:V$141,$K23+1)*(1-$L23)+INDEX(V$21:V$141,$K23+2)*$L23 -> -214.47715 | Y23: =$C23+$D23+MAX(W23,X23,IF(COUNTIFS($A$21:$A$141,">="&$G23,$A$21:$A$141,"<="&$H23)>0,_xlfn.MAXIFS(V$21:V$141,$A$21:$A$141,">="&$G23,$A$21:$A$141,"<="&$H23),W23)) -> -79.727147 | Z23: =-Cost_k*$A23+Beta_q*(Declarations!$B$16*INDEX(Y$21:Y$141,MAX(1,MIN(121,$B23-ROUND(Declarations!$A$16/$D$18,0))))+Declarations!$B$17*INDEX(Y$21:Y$141,MAX(1,MIN(121,$B23-ROUND(Declarations!$A$17/$D$18,0))))+Declarations!$B$18*INDEX(Y$21:Y$141,MAX(1,MIN(121,$B23-ROUND(Declarations!$A$18/$D$18,0))))+Declarations!$B$19*INDEX(Y$21:Y$141,MAX(1,MIN(121,$B23-ROUND(Declarations!$A$19/$D$18,0))))+Declarations!$B$20*INDEX(Y$21:Y$141,MAX(1,MIN(121,$B23-ROUND(Declarations!$A$20/$D$18,0))))) -> -239.2103 | AA23: =INDEX(Z$21:Z$141,$I23+1)*(1-$J23)+INDEX(Z$21:Z$141,$I23+2)*$J23 -> -237.35706 | AB23: =INDEX(Z$21:Z$141,$K23+1)*(1-$L23)+INDEX(Z$21:Z$141,$K23+2)*$L23 -> -236.27526 | AC23: =$C23+$D23+MAX(AA23,AB23,IF(COUNTIFS($A$21:$A$141,">="&$G23,$A$21:$A$141,"<="&$H23)>0,_xlfn.MAXIFS(Z$21:Z$141,$A$21:$A$141,">="&$G23,$A$21:$A$141,"<="&$H23),AA23)) -> -101.52526 | AD23: =-Cost_k*$A23+Beta_q*(Declarations!$B$16*INDEX(AC$21:AC$141,MAX(1,MIN(121,$B23-ROUND(Declarations!$A$16/$D$18,0))))+Declarations!$B$17*INDEX(AC$21:AC$141,MAX(1,MIN(121,$B23-ROUND(Declarations!$A$17/$D$18,0))))+Declarations!$B$18*INDEX(AC$21:AC$141,MAX(1,MIN(121,$B23-ROUND(Declarations!$A$18/$D$18,0))))+Declarations!$B$19*INDEX(AC$21:AC$141,MAX(1,MIN(121,$B23-ROUND(Declarations!$A$19/$D$18,0))))+Declarations!$B$20*INDEX(AC$21:AC$141,MAX(1,MIN(121,$B23-ROUND(Declarations!$A$20/$D$18,0))))) -> -260.48038 | AE23: =INDEX(AD$21:AD$141,$I23+1)*(1-$J23)+INDEX(AD$21:AD$141,$I23+2)*$J23 -> -258.14726 | AF23: =INDEX(AD$21:AD$141,$K23+1)*(1-$L23)+INDEX(AD$21:AD$141,$K23+2)*$L23 -> -256.76467 | AG23: =$C23+$D23+MAX(AE23,AF23,IF(COUNTIFS($A$21:$A$141,">="&$G23,$A$21:$A$141,"<="&$H23)>0,_xlfn.MAXIFS(AD$21:AD$141,$A$21:$A$141,">="&$G23,$A$21:$A$141,"<="&$H23),AE23)) -> -122.01467 | AH23: =-Cost_k*$A23+Beta_q*(Declarations!$B$16*INDEX(AG$21:AG$141,MAX(1,MIN(121,$B23-ROUND(Declarations!$A$16/$D$18,0))))+Declarations!$B$17*INDEX(AG$21:AG$141,MAX(1,MIN(121,$B23-ROUND(Declarations!$A$17/$D$18,0))))+Declarations!$B$18*INDEX(AG$21:AG$141,MAX(1,MIN(121,$B23-ROUND(Declarations!$A$18/$D$18,0))))+Declarations!$B$19*INDEX(AG$21:AG$141,MAX(1,MIN(121,$B23-ROUND(Declarations!$A$19/$D$18,0))))+Declarations!$B$20*INDEX(AG$21:AG$141,MAX(1,MIN(121,$B23-ROUND(Declarations!$A$20/$D$18,0))))) -> -280.36342 | AI23: =INDEX(AH$21:AH$141,$I23+1)*(1-$J23)+INDEX(AH$21:AH$141,$I23+2)*$J23 -> -277.23377 | AJ23: =INDEX(AH$21:AH$141,$K23+1)*(1-$L23)+INDEX(AH$21:AH$141,$K23+2)*$L23 -> -275.36959 | AK23: =$C23+$D23+MAX(AI23,AJ23,IF(COUNTIFS($A$21:$A$141,">="&$G23,$A$21:$A$141,"<="&$H23)>0,_xlfn.MAXIFS(AH$21:AH$141,$A$21:$A$141,">="&$G23,$A$21:$A$141,"<="&$H23),AI23)) -> -140.61959 | AL23: =-Cost_k*$A23+Beta_q*(Declarations!$B$16*INDEX(AK$21:AK$141,MAX(1,MIN(121,$B23-ROUND(Declarations!$A$16/$D$18,0))))+Declarations!$B$17*INDEX(AK$21:AK$141,MAX(1,MIN(121,$B23-ROUND(Declarations!$A$17/$D$18,0))))+Declarations!$B$18*INDEX(AK$21:AK$141,MAX(1,MIN(121,$B23-ROUND(Declarations!$A$18/$D$18,0))))+Declarations!$B$19*INDEX(AK$21:AK$141,MAX(1,MIN(121,$B23-ROUND(Declarations!$A$19/$D$18,0))))+Declarations!$B$20*INDEX(AK$21:AK$141,MAX(1,MIN(121,$B23-ROUND(Declarations!$A$20/$D$18,0))))) -> -298.44029 | AM23: =INDEX(AL$21:AL$141,$I23+1)*(1-$J23)+INDEX(AL$21:AL$141,$I23+2)*$J23 -> -294.49319 | AN23: =INDEX(AL$21:AL$141,$K23+1)*(1-$L23)+INDEX(AL$21:AL$141,$K23+2)*$L23 -> -292.20076 | AO23: =$C23+$D23+MAX(AM23,AN23,IF(COUNTIFS($A$21:$A$141,">="&$G23,$A$21:$A$141,"<="&$H23)>0,_xlfn.MAXIFS(AL$21:AL$141,$A$21:$A$141,">="&$G23,$A$21:$A$141,"<="&$H23),AM23)) -> -157.45076 | AP23: =-Cost_k*$A23+Beta_q*(Declarations!$B$16*INDEX(AO$21:AO$141,MAX(1,MIN(121,$B23-ROUND(Declarations!$A$16/$D$18,0))))+Declarations!$B$17*INDEX(AO$21:AO$141,MAX(1,MIN(121,$B23-ROUND(Declarations!$A$17/$D$18,0))))+Declarations!$B$18*INDEX(AO$21:AO$141,MAX(1,MIN(121,$B23-ROUND(Declarations!$A$18/$D$18,0))))+Declarations!$B$19*INDEX(AO$21:AO$141,MAX(1,MIN(121,$B23-ROUND(Declarations!$A$19/$D$18,0))))+Declarations!$B$20*INDEX(AO$21:AO$141,MAX(1,MIN(121,$B23-ROUND(Declarations!$A$20/$D$18,0))))) -> -314.78897 | AQ23: =INDEX(AP$21:AP$141,$I23+1)*(1-$J23)+INDEX(AP$21:AP$141,$I23+2)*$J23 -> -310.06124 | AR23: =INDEX(AP$21:AP$141,$K23+1)*(1-$L23)+INDEX(AP$21:AP$141,$K23+2)*$L23 -> -307.32158 | AS23: =$C23+$D23+MAX(AQ23,AR23,IF(COUNTIFS($A$21:$A$141,">="&$G23,$A$21:$A$141,"<="&$H23)>0,_xlfn.MAXIFS(AP$21:AP$141,$A$21:$A$141,">="&$G23,$A$21:$A$141,"<="&$H23),AQ23)) -> -172.57158 | AT23: =-Cost_k*$A23+Beta_q*(Declarations!$B$16*INDEX(AS$21:AS$141,MAX(1,MIN(121,$B23-ROUND(Declarations!$A$16/$D$18,0))))+Declarations!$B$17*INDEX(AS$21:AS$141,MAX(1,MIN(121,$B23-ROUND(Declarations!$A$17/$D$18,0))))+Declarations!$B$18*INDEX(AS$21:AS$141,MAX(1,MIN(121,$B23-ROUND(Declarations!$A$18/$D$18,0))))+Declarations!$B$19*INDEX(AS$21:AS$141,MAX(1,MIN(121,$B23-ROUND(Declarations!$A$19/$D$18,0))))+Declarations!$B$20*INDEX(AS$21:AS$141,MAX(1,MIN(121,$B23-ROUND(Declarations!$A$20/$D$18,0))))) -> -329.44993 | AU23: =INDEX(AT$21:AT$141,$I23+1)*(1-$J23)+INDEX(AT$21:AT$141,$I23+2)*$J23 -> -323.8599 | AV23: =INDEX(AT$21:AT$141,$K23+1)*(1-$L23)+INDEX(AT$21:AT$141,$K23+2)*$L23 -> -320.62889 | AW23: =$C23+$D23+MAX(AU23,AV23,IF(COUNTIFS($A$21:$A$141,">="&$G23,$A$21:$A$141,"<="&$H23)>0,_xlfn.MAXIFS(AT$21:AT$141,$A$21:$A$141,">="&$G23,$A$21:$A$141,"<="&$H23),AU23)) -> -185.87889 | AX23: =-Cost_k*$A23+Beta_q*(Declarations!$B$16*INDEX(AW$21:AW$141,MAX(1,MIN(121,$B23-ROUND(Declarations!$A$16/$D$18,0))))+Declarations!$B$17*INDEX(AW$21:AW$141,MAX(1,MIN(121,$B23-ROUND(Declarations!$A$17/$D$18,0))))+Declarations!$B$18*INDEX(AW$21:AW$141,MAX(1,MIN(121,$B23-ROUND(Declarations!$A$18/$D$18,0))))+Declarations!$B$19*INDEX(AW$21:AW$141,MAX(1,MIN(121,$B23-ROUND(Declarations!$A$19/$D$18,0))))+Declarations!$B$20*INDEX(AW$21:AW$141,MAX(1,MIN(121,$B23-ROUND(Declarations!$A$20/$D$18,0))))) -> -342.3385 | AY23: =INDEX(AX$21:AX$141,$I23+1)*(1-$J23)+INDEX(AX$21:AX$141,$I23+2)*$J23 -> -335.84434 | AZ23: =INDEX(AX$21:AX$141,$K23+1)*(1-$L23)+INDEX(AX$21:AX$141,$K23+2)*$L23 -> -332.11406 | BA23: =$C23+$D23+MAX(AY23,AZ23,IF(COUNTIFS($A$21:$A$141,">="&$G23,$A$21:$A$141,"<="&$H23)>0,_xlfn.MAXIFS(AX$21:AX$141,$A$21:$A$141,">="&$G23,$A$21:$A$141,"<="&$H23),AY23)) -> -197.36406 | BB23: =-Cost_k*$A23+Beta_q*(Declarations!$B$16*INDEX(BA$21:BA$141,MAX(1,MIN(121,$B23-ROUND(Declarations!$A$16/$D$18,0))))+Declarations!$B$17*INDEX(BA$21:BA$141,MAX(1,MIN(121,$B23-ROUND(Declarations!$A$17/$D$18,0))))+Declarations!$B$18*INDEX(BA$21:BA$141,MAX(1,MIN(121,$B23-ROUND(Declarations!$A$18/$D$18,0))))+Declarations!$B$19*INDEX(BA$21:BA$141,MAX(1,MIN(121,$B23-ROUND(Declarations!$A$19/$D$18,0))))+Declarations!$B$20*INDEX(BA$21:BA$141,MAX(1,MIN(121,$B23-ROUND(Declarations!$A$20/$D$18,0))))) -> -353.45316 | BC23: =INDEX(BB$21:BB$141,$I23+1)*(1-$J23)+INDEX(BB$21:BB$141,$I23+2)*$J23 -> -346.07244 | BD23: =INDEX(BB$21:BB$141,$K23+1)*(1-$L23)+INDEX(BB$21:BB$141,$K23+2)*$L23 -> -341.86235 | BE23: =$C23+$D23+MAX(BC23,BD23,IF(COUNTIFS($A$21:$A$141,">="&$G23,$A$21:$A$141,"<="&$H23)>0,_xlfn.MAXIFS(BB$21:BB$141,$A$21:$A$141,">="&$G23,$A$21:$A$141,"<="&$H23),BC23)) -> -207.11235 | BF23: =-Cost_k*$A23+Beta_q*(Declarations!$B$16*INDEX(BE$21:BE$141,MAX(1,MIN(121,$B23-ROUND(Declarations!$A$16/$D$18,0))))+Declarations!$B$17*INDEX(BE$21:BE$141,MAX(1,MIN(121,$B23-ROUND(Declarations!$A$17/$D$18,0))))+Declarations!$B$18*INDEX(BE$21:BE$141,MAX(1,MIN(121,$B23-ROUND(Declarations!$A$18/$D$18,0))))+Declarations!$B$19*INDEX(BE$21:BE$141,MAX(1,MIN(121,$B23-ROUND(Declarations!$A$19/$D$18,0))))+Declarations!$B$20*INDEX(BE$21:BE$141,MAX(1,MIN(121,$B23-ROUND(Declarations!$A$20/$D$18,0))))) -> -362.88076 | BG23: =INDEX(BF$21:BF$141,$I23+1)*(1-$J23)+INDEX(BF$21:BF$141,$I23+2)*$J23 -> -354.67259 | BH23: =INDEX(BF$21:BF$141,$K23+1)*(1-$L23)+INDEX(BF$21:BF$141,$K23+2)*$L23 -> -350.02455 | BI23: =$C23+$D23+MAX(BG23,BH23,IF(COUNTIFS($A$21:$A$141,">="&$G23,$A$21:$A$141,"<="&$H23)>0,_xlfn.MAXIFS(BF$21:BF$141,$A$21:$A$141,">="&$G23,$A$21:$A$141,"<="&$H23),BG23)) -> -215.27455 | BJ23: -215.27455 | BK23: =ABS(BI23-BJ23) -> 0
A24: =A23+$D$18 -> 40.75 | B24: 4 | C24: =-Short_p*MAX(Floor_c-A24,0) -> -22.8 | D24: =Cost_k*Alpha_keep*A24 -> 158.925 | E24: =MIN(Cap_h,MAX(0,$B$18+MAX(Loss_w)-Alpha_keep*A24)) -> 1.76875 | F24: =MAX(MIN(Cap_h,$F$18+MIN(Loss_w)-Alpha_keep*A24),E24) -> 2.5 | G24: =Alpha_keep*A24+E24 -> 41.5 | H24: =Alpha_keep*A24+F24 -> 42.23125 | I24: =MIN(INT((G24-$B$18)/$D$18+0.000000001),119) -> 6 | J24: =(G24-$B$18)/$D$18-I24 -> 0 | K24: =MIN(INT((H24-$B$18)/$D$18+0.000000001),119) -> 8 | L24: =(H24-$B$18)/$D$18-K24 -> 0.925 | M24: 0 | N24: =-Cost_k*$A24+Beta_q*(Declarations!$B$16*INDEX(M$21:M$141,MAX(1,MIN(121,$B24-ROUND(Declarations!$A$16/$D$18,0))))+Declarations!$B$17*INDEX(M$21:M$141,MAX(1,MIN(121,$B24-ROUND(Declarations!$A$17/$D$18,0))))+Declarations!$B$18*INDEX(M$21:M$141,MAX(1,MIN(121,$B24-ROUND(Declarations!$A$18/$D$18,0))))+Declarations!$B$19*INDEX(M$21:M$141,MAX(1,MIN(121,$B24-ROUND(Declarations!$A$19/$D$18,0))))+Declarations!$B$20*INDEX(M$21:M$141,MAX(1,MIN(121,$B24-ROUND(Declarations!$A$20/$D$18,0))))) -> -163 | O24: =INDEX(N$21:N$141,$I24+1)*(1-$J24)+INDEX(N$21:N$141,$I24+2)*$J24 -> -166 | P24: =INDEX(N$21:N$141,$K24+1)*(1-$L24)+INDEX(N$21:N$141,$K24+2)*$L24 -> -168.925 | Q24: =$C24+$D24+MAX(O24,P24,IF(COUNTIFS($A$21:$A$141,">="&$G24,$A$21:$A$141,"<="&$H24)>0,_xlfn.MAXIFS(N$21:N$141,$A$21:$A$141,">="&$G24,$A$21:$A$141,"<="&$H24),O24)) -> -29.875 | R24: =-Cost_k*$A24+Beta_q*(Declarations!$B$16*INDEX(Q$21:Q$141,MAX(1,MIN(121,$B24-ROUND(Declarations!$A$16/$D$18,0))))+Declarations!$B$17*INDEX(Q$21:Q$141,MAX(1,MIN(121,$B24-ROUND(Declarations!$A$17/$D$18,0))))+Declarations!$B$18*INDEX(Q$21:Q$141,MAX(1,MIN(121,$B24-ROUND(Declarations!$A$18/$D$18,0))))+Declarations!$B$19*INDEX(Q$21:Q$141,MAX(1,MIN(121,$B24-ROUND(Declarations!$A$19/$D$18,0))))+Declarations!$B$20*INDEX(Q$21:Q$141,MAX(1,MIN(121,$B24-ROUND(Declarations!$A$20/$D$18,0))))) -> -191.97017 | S24: =INDEX(R$21:R$141,$I24+1)*(1-$J24)+INDEX(R$21:R$141,$I24+2)*$J24 -> -191.22669 | T24: =INDEX(R$21:R$141,$K24+1)*(1-$L24)+INDEX(R$21:R$141,$K24+2)*$L24 -> -190.68147 | U24: =$C24+$D24+MAX(S24,T24,IF(COUNTIFS($A$21:$A$141,">="&$G24,$A$21:$A$141,"<="&$H24)>0,_xlfn.MAXIFS(R$21:R$141,$A$21:$A$141,">="&$G24,$A$21:$A$141,"<="&$H24),S24)) -> -54.556465 | V24: =-Cost_k*$A24+Beta_q*(Declarations!$B$16*INDEX(U$21:U$141,MAX(1,MIN(121,$B24-ROUND(Declarations!$A$16/$D$18,0))))+Declarations!$B$17*INDEX(U$21:U$141,MAX(1,MIN(121,$B24-ROUND(Declarations!$A$17/$D$18,0))))+Declarations!$B$18*INDEX(U$21:U$141,MAX(1,MIN(121,$B24-ROUND(Declarations!$A$18/$D$18,0))))+Declarations!$B$19*INDEX(U$21:U$141,MAX(1,MIN(121,$B24-ROUND(Declarations!$A$19/$D$18,0))))+Declarations!$B$20*INDEX(U$21:U$141,MAX(1,MIN(121,$B24-ROUND(Declarations!$A$20/$D$18,0))))) -> -216.17613 | W24: =INDEX(V$21:V$141,$I24+1)*(1-$J24)+INDEX(V$21:V$141,$I24+2)*$J24 -> -215.18827 | X24: =INDEX(V$21:V$141,$K24+1)*(1-$L24)+INDEX(V$21:V$141,$K24+2)*$L24 -> -214.14493 | Y24: =$C24+$D24+MAX(W24,X24,IF(COUNTIFS($A$21:$A$141,">="&$G24,$A$21:$A$141,"<="&$H24)>0,_xlfn.MAXIFS(V$21:V$141,$A$21:$A$141,">="&$G24,$A$21:$A$141,"<="&$H24),W24)) -> -78.019933 | Z24: =-Cost_k*$A24+Beta_q*(Declarations!$B$16*INDEX(Y$21:Y$141,MAX(1,MIN(121,$B24-ROUND(Declarations!$A$16/$D$18,0))))+Declarations!$B$17*INDEX(Y$21:Y$141,MAX(1,MIN(121,$B24-ROUND(Declarations!$A$17/$D$18,0))))+Declarations!$B$18*INDEX(Y$21:Y$141,MAX(1,MIN(121,$B24-ROUND(Declarations!$A$18/$D$18,0))))+Declarations!$B$19*INDEX(Y$21:Y$141,MAX(1,MIN(121,$B24-ROUND(Declarations!$A$19/$D$18,0))))+Declarations!$B$20*INDEX(Y$21:Y$141,MAX(1,MIN(121,$B24-ROUND(Declarations!$A$20/$D$18,0))))) -> -238.97675 | AA24: =INDEX(Z$21:Z$141,$I24+1)*(1-$J24)+INDEX(Z$21:Z$141,$I24+2)*$J24 -> -237.35706 | AB24: =INDEX(Z$21:Z$141,$K24+1)*(1-$L24)+INDEX(Z$21:Z$141,$K24+2)*$L24 -> -235.78685 | AC24: =$C24+$D24+MAX(AA24,AB24,IF(COUNTIFS($A$21:$A$141,">="&$G24,$A$21:$A$141,"<="&$H24)>0,_xlfn.MAXIFS(Z$21:Z$141,$A$21:$A$141,">="&$G24,$A$21:$A$141,"<="&$H24),AA24)) -> -99.661851 | AD24: =-Cost_k*$A24+Beta_q*(Declarations!$B$16*INDEX(AC$21:AC$141,MAX(1,MIN(121,$B24-ROUND(Declarations!$A$16/$D$18,0))))+Declarations!$B$17*INDEX(AC$21:AC$141,MAX(1,MIN(121,$B24-ROUND(Declarations!$A$17/$D$18,0))))+Declarations!$B$18*INDEX(AC$21:AC$141,MAX(1,MIN(121,$B24-ROUND(Declarations!$A$18/$D$18,0))))+Declarations!$B$19*INDEX(AC$21:AC$141,MAX(1,MIN(121,$B24-ROUND(Declarations!$A$19/$D$18,0))))+Declarations!$B$20*INDEX(AC$21:AC$141,MAX(1,MIN(121,$B24-ROUND(Declarations!$A$20/$D$18,0))))) -> -260.14247 | AE24: =INDEX(AD$21:AD$141,$I24+1)*(1-$J24)+INDEX(AD$21:AD$141,$I24+2)*$J24 -> -258.14726 | AF24: =INDEX(AD$21:AD$141,$K24+1)*(1-$L24)+INDEX(AD$21:AD$141,$K24+2)*$L24 -> -256.09133 | AG24: =$C24+$D24+MAX(AE24,AF24,IF(COUNTIFS($A$21:$A$141,">="&$G24,$A$21:$A$141,"<="&$H24)>0,_xlfn.MAXIFS(AD$21:AD$141,$A$21:$A$141,">="&$G24,$A$21:$A$141,"<="&$H24),AE24)) -> -119.96633 | AH24: =-Cost_k*$A24+Beta_q*(Declarations!$B$16*INDEX(AG$21:AG$141,MAX(1,MIN(121,$B24-ROUND(Declarations!$A$16/$D$18,0))))+Declarations!$B$17*INDEX(AG$21:AG$141,MAX(1,MIN(121,$B24-ROUND(Declarations!$A$17/$D$18,0))))+Declarations!$B$18*INDEX(AG$21:AG$141,MAX(1,MIN(121,$B24-ROUND(Declarations!$A$18/$D$18,0))))+Declarations!$B$19*INDEX(AG$21:AG$141,MAX(1,MIN(121,$B24-ROUND(Declarations!$A$19/$D$18,0))))+Declarations!$B$20*INDEX(AG$21:AG$141,MAX(1,MIN(121,$B24-ROUND(Declarations!$A$20/$D$18,0))))) -> -279.87167 | AI24: =INDEX(AH$21:AH$141,$I24+1)*(1-$J24)+INDEX(AH$21:AH$141,$I24+2)*$J24 -> -277.23377 | AJ24: =INDEX(AH$21:AH$141,$K24+1)*(1-$L24)+INDEX(AH$21:AH$141,$K24+2)*$L24 -> -274.45548 | AK24: =$C24+$D24+MAX(AI24,AJ24,IF(COUNTIFS($A$21:$A$141,">="&$G24,$A$21:$A$141,"<="&$H24)>0,_xlfn.MAXIFS(AH$21:AH$141,$A$21:$A$141,">="&$G24,$A$21:$A$141,"<="&$H24),AI24)) -> -138.33048 | AL24: =-Cost_k*$A24+Beta_q*(Declarations!$B$16*INDEX(AK$21:AK$141,MAX(1,MIN(121,$B24-ROUND(Declarations!$A$16/$D$18,0))))+Declarations!$B$17*INDEX(AK$21:AK$141,MAX(1,MIN(121,$B24-ROUND(Declarations!$A$17/$D$18,0))))+Declarations!$B$18*INDEX(AK$21:AK$141,MAX(1,MIN(121,$B24-ROUND(Declarations!$A$18/$D$18,0))))+Declarations!$B$19*INDEX(AK$21:AK$141,MAX(1,MIN(121,$B24-ROUND(Declarations!$A$19/$D$18,0))))+Declarations!$B$20*INDEX(AK$21:AK$141,MAX(1,MIN(121,$B24-ROUND(Declarations!$A$20/$D$18,0))))) -> -297.77599 | AM24: =INDEX(AL$21:AL$141,$I24+1)*(1-$J24)+INDEX(AL$21:AL$141,$I24+2)*$J24 -> -294.49319 | AN24: =INDEX(AL$21:AL$141,$K24+1)*(1-$L24)+INDEX(AL$21:AL$141,$K24+2)*$L24 -> -291.07318 | AO24: =$C24+$D24+MAX(AM24,AN24,IF(COUNTIFS($A$21:$A$141,">="&$G24,$A$21:$A$141,"<="&$H24)>0,_xlfn.MAXIFS(AL$21:AL$141,$A$21:$A$141,">="&$G24,$A$21:$A$141,"<="&$H24),AM24)) -> -154.94818 | AP24: =-Cost_k*$A24+Beta_q*(Declarations!$B$16*INDEX(AO$21:AO$141,MAX(1,MIN(121,$B24-ROUND(Declarations!$A$16/$D$18,0))))+Declarations!$B$17*INDEX(AO$21:AO$141,MAX(1,MIN(121,$B24-ROUND(Declarations!$A$17/$D$18,0))))+Declarations!$B$18*INDEX(AO$21:AO$141,MAX(1,MIN(121,$B24-ROUND(Declarations!$A$18/$D$18,0))))+Declarations!$B$19*INDEX(AO$21:AO$141,MAX(1,MIN(121,$B24-ROUND(Declarations!$A$19/$D$18,0))))+Declarations!$B$20*INDEX(AO$21:AO$141,MAX(1,MIN(121,$B24-ROUND(Declarations!$A$20/$D$18,0))))) -> -313.96493 | AQ24: =INDEX(AP$21:AP$141,$I24+1)*(1-$J24)+INDEX(AP$21:AP$141,$I24+2)*$J24 -> -310.06124 | AR24: =INDEX(AP$21:AP$141,$K24+1)*(1-$L24)+INDEX(AP$21:AP$141,$K24+2)*$L24 -> -305.96087 | AS24: =$C24+$D24+MAX(AQ24,AR24,IF(COUNTIFS($A$21:$A$141,">="&$G24,$A$21:$A$141,"<="&$H24)>0,_xlfn.MAXIFS(AP$21:AP$141,$A$21:$A$141,">="&$G24,$A$21:$A$141,"<="&$H24),AQ24)) -> -169.83587 | AT24: =-Cost_k*$A24+Beta_q*(Declarations!$B$16*INDEX(AS$21:AS$141,MAX(1,MIN(121,$B24-ROUND(Declarations!$A$16/$D$18,0))))+Declarations!$B$17*INDEX(AS$21:AS$141,MAX(1,MIN(121,$B24-ROUND(Declarations!$A$17/$D$18,0))))+Declarations!$B$18*INDEX(AS$21:AS$141,MAX(1,MIN(121,$B24-ROUND(Declarations!$A$18/$D$18,0))))+Declarations!$B$19*INDEX(AS$21:AS$141,MAX(1,MIN(121,$B24-ROUND(Declarations!$A$19/$D$18,0))))+Declarations!$B$20*INDEX(AS$21:AS$141,MAX(1,MIN(121,$B24-ROUND(Declarations!$A$20/$D$18,0))))) -> -328.4499 | AU24: =INDEX(AT$21:AT$141,$I24+1)*(1-$J24)+INDEX(AT$21:AT$141,$I24+2)*$J24 -> -323.8599 | AV24: =INDEX(AT$21:AT$141,$K24+1)*(1-$L24)+INDEX(AT$21:AT$141,$K24+2)*$L24 -> -319.01641 | AW24: =$C24+$D24+MAX(AU24,AV24,IF(COUNTIFS($A$21:$A$141,">="&$G24,$A$21:$A$141,"<="&$H24)>0,_xlfn.MAXIFS(AT$21:AT$141,$A$21:$A$141,">="&$G24,$A$21:$A$141,"<="&$H24),AU24)) -> -182.89141 | AX24: =-Cost_k*$A24+Beta_q*(Declarations!$B$16*INDEX(AW$21:AW$141,MAX(1,MIN(121,$B24-ROUND(Declarations!$A$16/$D$18,0))))+Declarations!$B$17*INDEX(AW$21:AW$141,MAX(1,MIN(121,$B24-ROUND(Declarations!$A$17/$D$18,0))))+Declarations!$B$18*INDEX(AW$21:AW$141,MAX(1,MIN(121,$B24-ROUND(Declarations!$A$18/$D$18,0))))+Declarations!$B$19*INDEX(AW$21:AW$141,MAX(1,MIN(121,$B24-ROUND(Declarations!$A$19/$D$18,0))))+Declarations!$B$20*INDEX(AW$21:AW$141,MAX(1,MIN(121,$B24-ROUND(Declarations!$A$20/$D$18,0))))) -> -341.15163 | AY24: =INDEX(AX$21:AX$141,$I24+1)*(1-$J24)+INDEX(AX$21:AX$141,$I24+2)*$J24 -> -335.84434 | AZ24: =INDEX(AX$21:AX$141,$K24+1)*(1-$L24)+INDEX(AX$21:AX$141,$K24+2)*$L24 -> -330.24994 | BA24: =$C24+$D24+MAX(AY24,AZ24,IF(COUNTIFS($A$21:$A$141,">="&$G24,$A$21:$A$141,"<="&$H24)>0,_xlfn.MAXIFS(AX$21:AX$141,$A$21:$A$141,">="&$G24,$A$21:$A$141,"<="&$H24),AY24)) -> -194.12494 | BB24: =-Cost_k*$A24+Beta_q*(Declarations!$B$16*INDEX(BA$21:BA$141,MAX(1,MIN(121,$B24-ROUND(Declarations!$A$16/$D$18,0))))+Declarations!$B$17*INDEX(BA$21:BA$141,MAX(1,MIN(121,$B24-ROUND(Declarations!$A$17/$D$18,0))))+Declarations!$B$18*INDEX(BA$21:BA$141,MAX(1,MIN(121,$B24-ROUND(Declarations!$A$18/$D$18,0))))+Declarations!$B$19*INDEX(BA$21:BA$141,MAX(1,MIN(121,$B24-ROUND(Declarations!$A$19/$D$18,0))))+Declarations!$B$20*INDEX(BA$21:BA$141,MAX(1,MIN(121,$B24-ROUND(Declarations!$A$20/$D$18,0))))) -> -352.08165 | BC24: =INDEX(BB$21:BB$141,$I24+1)*(1-$J24)+INDEX(BB$21:BB$141,$I24+2)*$J24 -> -346.07244 | BD24: =INDEX(BB$21:BB$141,$K24+1)*(1-$L24)+INDEX(BB$21:BB$141,$K24+2)*$L24 -> -339.7593 | BE24: =$C24+$D24+MAX(BC24,BD24,IF(COUNTIFS($A$21:$A$141,">="&$G24,$A$21:$A$141,"<="&$H24)>0,_xlfn.MAXIFS(BB$21:BB$141,$A$21:$A$141,">="&$G24,$A$21:$A$141,"<="&$H24),BC24)) -> -203.6343 | BF24: =-Cost_k*$A24+Beta_q*(Declarations!$B$16*INDEX(BE$21:BE$141,MAX(1,MIN(121,$B24-ROUND(Declarations!$A$16/$D$18,0))))+Declarations!$B$17*INDEX(BE$21:BE$141,MAX(1,MIN(121,$B24-ROUND(Declarations!$A$17/$D$18,0))))+Declarations!$B$18*INDEX(BE$21:BE$141,MAX(1,MIN(121,$B24-ROUND(Declarations!$A$18/$D$18,0))))+Declarations!$B$19*INDEX(BE$21:BE$141,MAX(1,MIN(121,$B24-ROUND(Declarations!$A$19/$D$18,0))))+Declarations!$B$20*INDEX(BE$21:BE$141,MAX(1,MIN(121,$B24-ROUND(Declarations!$A$20/$D$18,0))))) -> -361.33563 | BG24: =INDEX(BF$21:BF$141,$I24+1)*(1-$J24)+INDEX(BF$21:BF$141,$I24+2)*$J24 -> -354.67259 | BH24: =INDEX(BF$21:BF$141,$K24+1)*(1-$L24)+INDEX(BF$21:BF$141,$K24+2)*$L24 -> -347.70654 | BI24: =$C24+$D24+MAX(BG24,BH24,IF(COUNTIFS($A$21:$A$141,">="&$G24,$A$21:$A$141,"<="&$H24)>0,_xlfn.MAXIFS(BF$21:BF$141,$A$21:$A$141,">="&$G24,$A$21:$A$141,"<="&$H24),BG24)) -> -211.58154 | BJ24: -211.58154 | BK24: =ABS(BI24-BJ24) -> 0
A25: =A24+$D$18 -> 41 | B25: 5 | C25: =-Short_p*MAX(Floor_c-A25,0) -> -22.4 | D25: =Cost_k*Alpha_keep*A25 -> 159.9 | E25: =MIN(Cap_h,MAX(0,$B$18+MAX(Loss_w)-Alpha_keep*A25)) -> 1.525 | F25: =MAX(MIN(Cap_h,$F$18+MIN(Loss_w)-Alpha_keep*A25),E25) -> 2.5 | G25: =Alpha_keep*A25+E25 -> 41.5 | H25: =Alpha_keep*A25+F25 -> 42.475 | I25: =MIN(INT((G25-$B$18)/$D$18+0.000000001),119) -> 6 | J25: =(G25-$B$18)/$D$18-I25 -> 0 | K25: =MIN(INT((H25-$B$18)/$D$18+0.000000001),119) -> 9 | L25: =(H25-$B$18)/$D$18-K25 -> 0.9 | M25: 0 | N25: =-Cost_k*$A25+Beta_q*(Declarations!$B$16*INDEX(M$21:M$141,MAX(1,MIN(121,$B25-ROUND(Declarations!$A$16/$D$18,0))))+Declarations!$B$17*INDEX(M$21:M$141,MAX(1,MIN(121,$B25-ROUND(Declarations!$A$17/$D$18,0))))+Declarations!$B$18*INDEX(M$21:M$141,MAX(1,MIN(121,$B25-ROUND(Declarations!$A$18/$D$18,0))))+Declarations!$B$19*INDEX(M$21:M$141,MAX(1,MIN(121,$B25-ROUND(Declarations!$A$19/$D$18,0))))+Declarations!$B$20*INDEX(M$21:M$141,MAX(1,MIN(121,$B25-ROUND(Declarations!$A$20/$D$18,0))))) -> -164 | O25: =INDEX(N$21:N$141,$I25+1)*(1-$J25)+INDEX(N$21:N$141,$I25+2)*$J25 -> -166 | P25: =INDEX(N$21:N$141,$K25+1)*(1-$L25)+INDEX(N$21:N$141,$K25+2)*$L25 -> -169.9 | Q25: =$C25+$D25+MAX(O25,P25,IF(COUNTIFS($A$21:$A$141,">="&$G25,$A$21:$A$141,"<="&$H25)>0,_xlfn.MAXIFS(N$21:N$141,$A$21:$A$141,">="&$G25,$A$21:$A$141,"<="&$H25),O25)) -> -28.5 | R25: =-Cost_k*$A25+Beta_q*(Declarations!$B$16*INDEX(Q$21:Q$141,MAX(1,MIN(121,$B25-ROUND(Declarations!$A$16/$D$18,0))))+Declarations!$B$17*INDEX(Q$21:Q$141,MAX(1,MIN(121,$B25-ROUND(Declarations!$A$17/$D$18,0))))+Declarations!$B$18*INDEX(Q$21:Q$141,MAX(1,MIN(121,$B25-ROUND(Declarations!$A$18/$D$18,0))))+Declarations!$B$19*INDEX(Q$21:Q$141,MAX(1,MIN(121,$B25-ROUND(Declarations!$A$19/$D$18,0))))+Declarations!$B$20*INDEX(Q$21:Q$141,MAX(1,MIN(121,$B25-ROUND(Declarations!$A$20/$D$18,0))))) -> -191.69468 | S25: =INDEX(R$21:R$141,$I25+1)*(1-$J25)+INDEX(R$21:R$141,$I25+2)*$J25 -> -191.22669 | T25: =INDEX(R$21:R$141,$K25+1)*(1-$L25)+INDEX(R$21:R$141,$K25+2)*$L25 -> -190.57947 | U25: =$C25+$D25+MAX(S25,T25,IF(COUNTIFS($A$21:$A$141,">="&$G25,$A$21:$A$141,"<="&$H25)>0,_xlfn.MAXIFS(R$21:R$141,$A$21:$A$141,">="&$G25,$A$21:$A$141,"<="&$H25),S25)) -> -53.079467 | V25: =-Cost_k*$A25+Beta_q*(Declarations!$B$16*INDEX(U$21:U$141,MAX(1,MIN(121,$B25-ROUND(Declarations!$A$16/$D$18,0))))+Declarations!$B$17*INDEX(U$21:U$141,MAX(1,MIN(121,$B25-ROUND(Declarations!$A$17/$D$18,0))))+Declarations!$B$18*INDEX(U$21:U$141,MAX(1,MIN(121,$B25-ROUND(Declarations!$A$18/$D$18,0))))+Declarations!$B$19*INDEX(U$21:U$141,MAX(1,MIN(121,$B25-ROUND(Declarations!$A$19/$D$18,0))))+Declarations!$B$20*INDEX(U$21:U$141,MAX(1,MIN(121,$B25-ROUND(Declarations!$A$20/$D$18,0))))) -> -215.79467 | W25: =INDEX(V$21:V$141,$I25+1)*(1-$J25)+INDEX(V$21:V$141,$I25+2)*$J25 -> -215.18827 | X25: =INDEX(V$21:V$141,$K25+1)*(1-$L25)+INDEX(V$21:V$141,$K25+2)*$L25 -> -213.82048 | Y25: =$C25+$D25+MAX(W25,X25,IF(COUNTIFS($A$21:$A$141,">="&$G25,$A$21:$A$141,"<="&$H25)>0,_xlfn.MAXIFS(V$21:V$141,$A$21:$A$141,">="&$G25,$A$21:$A$141,"<="&$H25),W25)) -> -76.320482 | Z25: =-Cost_k*$A25+Beta_q*(Declarations!$B$16*INDEX(Y$21:Y$141,MAX(1,MIN(121,$B25-ROUND(Declarations!$A$16/$D$18,0))))+Declarations!$B$17*INDEX(Y$21:Y$141,MAX(1,MIN(121,$B25-ROUND(Declarations!$A$17/$D$18,0))))+Declarations!$B$18*INDEX(Y$21:Y$141,MAX(1,MIN(121,$B25-ROUND(Declarations!$A$18/$D$18,0))))+Declarations!$B$19*INDEX(Y$21:Y$141,MAX(1,MIN(121,$B25-ROUND(Declarations!$A$19/$D$18,0))))+Declarations!$B$20*INDEX(Y$21:Y$141,MAX(1,MIN(121,$B25-ROUND(Declarations!$A$20/$D$18,0))))) -> -238.41776 | AA25: =INDEX(Z$21:Z$141,$I25+1)*(1-$J25)+INDEX(Z$21:Z$141,$I25+2)*$J25 -> -237.35706 | AB25: =INDEX(Z$21:Z$141,$K25+1)*(1-$L25)+INDEX(Z$21:Z$141,$K25+2)*$L25 -> -235.34833 | AC25: =$C25+$D25+MAX(AA25,AB25,IF(COUNTIFS($A$21:$A$141,">="&$G25,$A$21:$A$141,"<="&$H25)>0,_xlfn.MAXIFS(Z$21:Z$141,$A$21:$A$141,">="&$G25,$A$21:$A$141,"<="&$H25),AA25)) -> -97.848333 | AD25: =-Cost_k*$A25+Beta_q*(Declarations!$B$16*INDEX(AC$21:AC$141,MAX(1,MIN(121,$B25-ROUND(Declarations!$A$16/$D$18,0))))+Declarations!$B$17*INDEX(AC$21:AC$141,MAX(1,MIN(121,$B25-ROUND(Declarations!$A$17/$D$18,0))))+Declarations!$B$18*INDEX(AC$21:AC$141,MAX(1,MIN(121,$B25-ROUND(Declarations!$A$18/$D$18,0))))+Declarations!$B$19*INDEX(AC$21:AC$141,MAX(1,MIN(121,$B25-ROUND(Declarations!$A$19/$D$18,0))))+Declarations!$B$20*INDEX(AC$21:AC$141,MAX(1,MIN(121,$B25-ROUND(Declarations!$A$20/$D$18,0))))) -> -259.458 | AE25: =INDEX(AD$21:AD$141,$I25+1)*(1-$J25)+INDEX(AD$21:AD$141,$I25+2)*$J25 -> -258.14726 | AF25: =INDEX(AD$21:AD$141,$K25+1)*(1-$L25)+INDEX(AD$21:AD$141,$K25+2)*$L25 -> -255.42928 | AG25: =$C25+$D25+MAX(AE25,AF25,IF(COUNTIFS($A$21:$A$141,">="&$G25,$A$21:$A$141,"<="&$H25)>0,_xlfn.MAXIFS(AD$21:AD$141,$A$21:$A$141,">="&$G25,$A$21:$A$141,"<="&$H25),AE25)) -> -117.92928 | AH25: =-Cost_k*$A25+Beta_q*(Declarations!$B$16*INDEX(AG$21:AG$141,MAX(1,MIN(121,$B25-ROUND(Declarations!$A$16/$D$18,0))))+Declarations!$B$17*INDEX(AG$21:AG$141,MAX(1,MIN(121,$B25-ROUND(Declarations!$A$17/$D$18,0))))+Declarations!$B$18*INDEX(AG$21:AG$141,MAX(1,MIN(121,$B25-ROUND(Declarations!$A$18/$D$18,0))))+Declarations!$B$19*INDEX(AG$21:AG$141,MAX(1,MIN(121,$B25-ROUND(Declarations!$A$19/$D$18,0))))+Declarations!$B$20*INDEX(AG$21:AG$141,MAX(1,MIN(121,$B25-ROUND(Declarations!$A$20/$D$18,0))))) -> -278.9829 | AI25: =INDEX(AH$21:AH$141,$I25+1)*(1-$J25)+INDEX(AH$21:AH$141,$I25+2)*$J25 -> -277.23377 | AJ25: =INDEX(AH$21:AH$141,$K25+1)*(1-$L25)+INDEX(AH$21:AH$141,$K25+2)*$L25 -> -273.55296 | AK25: =$C25+$D25+MAX(AI25,AJ25,IF(COUNTIFS($A$21:$A$141,">="&$G25,$A$21:$A$141,"<="&$H25)>0,_xlfn.MAXIFS(AH$21:AH$141,$A$21:$A$141,">="&$G25,$A$21:$A$141,"<="&$H25),AI25)) -> -136.05296 | AL25: =-Cost_k*$A25+Beta_q*(Declarations!$B$16*INDEX(AK$21:AK$141,MAX(1,MIN(121,$B25-ROUND(Declarations!$A$16/$D$18,0))))+Declarations!$B$17*INDEX(AK$21:AK$141,MAX(1,MIN(121,$B25-ROUND(Declarations!$A$17/$D$18,0))))+Declarations!$B$18*INDEX(AK$21:AK$141,MAX(1,MIN(121,$B25-ROUND(Declarations!$A$18/$D$18,0))))+Declarations!$B$19*INDEX(AK$21:AK$141,MAX(1,MIN(121,$B25-ROUND(Declarations!$A$19/$D$18,0))))+Declarations!$B$20*INDEX(AK$21:AK$141,MAX(1,MIN(121,$B25-ROUND(Declarations!$A$20/$D$18,0))))) -> -296.6692 | AM25: =INDEX(AL$21:AL$141,$I25+1)*(1-$J25)+INDEX(AL$21:AL$141,$I25+2)*$J25 -> -294.49319 | AN25: =INDEX(AL$21:AL$141,$K25+1)*(1-$L25)+INDEX(AL$21:AL$141,$K25+2)*$L25 -> -289.95719 | AO25: =$C25+$D25+MAX(AM25,AN25,IF(COUNTIFS($A$21:$A$141,">="&$G25,$A$21:$A$141,"<="&$H25)>0,_xlfn.MAXIFS(AL$21:AL$141,$A$21:$A$141,">="&$G25,$A$21:$A$141,"<="&$H25),AM25)) -> -152.45719 | AP25: =-Cost_k*$A25+Beta_q*(Declarations!$B$16*INDEX(AO$21:AO$141,MAX(1,MIN(121,$B25-ROUND(Declarations!$A$16/$D$18,0))))+Declarations!$B$17*INDEX(AO$21:AO$141,MAX(1,MIN(121,$B25-ROUND(Declarations!$A$17/$D$18,0))))+Declarations!$B$18*INDEX(AO$21:AO$141,MAX(1,MIN(121,$B25-ROUND(Declarations!$A$18/$D$18,0))))+Declarations!$B$19*INDEX(AO$21:AO$141,MAX(1,MIN(121,$B25-ROUND(Declarations!$A$19/$D$18,0))))+Declarations!$B$20*INDEX(AO$21:AO$141,MAX(1,MIN(121,$B25-ROUND(Declarations!$A$20/$D$18,0))))) -> -312.65499 | AQ25: =INDEX(AP$21:AP$141,$I25+1)*(1-$J25)+INDEX(AP$21:AP$141,$I25+2)*$J25 -> -310.06124 | AR25: =INDEX(AP$21:AP$141,$K25+1)*(1-$L25)+INDEX(AP$21:AP$141,$K25+2)*$L25 -> -304.6053 | AS25: =$C25+$D25+MAX(AQ25,AR25,IF(COUNTIFS($A$21:$A$141,">="&$G25,$A$21:$A$141,"<="&$H25)>0,_xlfn.MAXIFS(AP$21:AP$141,$A$21:$A$141,">="&$G25,$A$21:$A$141,"<="&$H25),AQ25)) -> -167.1053 | AT25: =-Cost_k*$A25+Beta_q*(Declarations!$B$16*INDEX(AS$21:AS$141,MAX(1,MIN(121,$B25-ROUND(Declarations!$A$16/$D$18,0))))+Declarations!$B$17*INDEX(AS$21:AS$141,MAX(1,MIN(121,$B25-ROUND(Declarations!$A$17/$D$18,0))))+Declarations!$B$18*INDEX(AS$21:AS$141,MAX(1,MIN(121,$B25-ROUND(Declarations!$A$18/$D$18,0))))+Declarations!$B$19*INDEX(AS$21:AS$141,MAX(1,MIN(121,$B25-ROUND(Declarations!$A$19/$D$18,0))))+Declarations!$B$20*INDEX(AS$21:AS$141,MAX(1,MIN(121,$B25-ROUND(Declarations!$A$20/$D$18,0))))) -> -326.9163 | AU25: =INDEX(AT$21:AT$141,$I25+1)*(1-$J25)+INDEX(AT$21:AT$141,$I25+2)*$J25 -> -323.8599 | AV25: =INDEX(AT$21:AT$141,$K25+1)*(1-$L25)+INDEX(AT$21:AT$141,$K25+2)*$L25 -> -317.40545 | AW25: =$C25+$D25+MAX(AU25,AV25,IF(COUNTIFS($A$21:$A$141,">="&$G25,$A$21:$A$141,"<="&$H25)>0,_xlfn.MAXIFS(AT$21:AT$141,$A$21:$A$141,">="&$G25,$A$21:$A$141,"<="&$H25),AU25)) -> -179.90545 | AX25: =-Cost_k*$A25+Beta_q*(Declarations!$B$16*INDEX(AW$21:AW$141,MAX(1,MIN(121,$B25-ROUND(Declarations!$A$16/$D$18,0))))+Declarations!$B$17*INDEX(AW$21:AW$141,MAX(1,MIN(121,$B25-ROUND(Declarations!$A$17/$D$18,0))))+Declarations!$B$18*INDEX(AW$21:AW$141,MAX(1,MIN(121,$B25-ROUND(Declarations!$A$18/$D$18,0))))+Declarations!$B$19*INDEX(AW$21:AW$141,MAX(1,MIN(121,$B25-ROUND(Declarations!$A$19/$D$18,0))))+Declarations!$B$20*INDEX(AW$21:AW$141,MAX(1,MIN(121,$B25-ROUND(Declarations!$A$20/$D$18,0))))) -> -339.38142 | AY25: =INDEX(AX$21:AX$141,$I25+1)*(1-$J25)+INDEX(AX$21:AX$141,$I25+2)*$J25 -> -335.84434 | AZ25: =INDEX(AX$21:AX$141,$K25+1)*(1-$L25)+INDEX(AX$21:AX$141,$K25+2)*$L25 -> -328.38641 | BA25: =$C25+$D25+MAX(AY25,AZ25,IF(COUNTIFS($A$21:$A$141,">="&$G25,$A$21:$A$141,"<="&$H25)>0,_xlfn.MAXIFS(AX$21:AX$141,$A$21:$A$141,">="&$G25,$A$21:$A$141,"<="&$H25),AY25)) -> -190.88641 | BB25: =-Cost_k*$A25+Beta_q*(Declarations!$B$16*INDEX(BA$21:BA$141,MAX(1,MIN(121,$B25-ROUND(Declarations!$A$16/$D$18,0))))+Declarations!$B$17*INDEX(BA$21:BA$141,MAX(1,MIN(121,$B25-ROUND(Declarations!$A$17/$D$18,0))))+Declarations!$B$18*INDEX(BA$21:BA$141,MAX(1,MIN(121,$B25-ROUND(Declarations!$A$18/$D$18,0))))+Declarations!$B$19*INDEX(BA$21:BA$141,MAX(1,MIN(121,$B25-ROUND(Declarations!$A$19/$D$18,0))))+Declarations!$B$20*INDEX(BA$21:BA$141,MAX(1,MIN(121,$B25-ROUND(Declarations!$A$20/$D$18,0))))) -> -350.07779 | BC25: =INDEX(BB$21:BB$141,$I25+1)*(1-$J25)+INDEX(BB$21:BB$141,$I25+2)*$J25 -> -346.07244 | BD25: =INDEX(BB$21:BB$141,$K25+1)*(1-$L25)+INDEX(BB$21:BB$141,$K25+2)*$L25 -> -337.65779 | BE25: =$C25+$D25+MAX(BC25,BD25,IF(COUNTIFS($A$21:$A$141,">="&$G25,$A$21:$A$141,"<="&$H25)>0,_xlfn.MAXIFS(BB$21:BB$141,$A$21:$A$141,">="&$G25,$A$21:$A$141,"<="&$H25),BC25)) -> -200.15779 | BF25: =-Cost_k*$A25+Beta_q*(Declarations!$B$16*INDEX(BE$21:BE$141,MAX(1,MIN(121,$B25-ROUND(Declarations!$A$16/$D$18,0))))+Declarations!$B$17*INDEX(BE$21:BE$141,MAX(1,MIN(121,$B25-ROUND(Declarations!$A$17/$D$18,0))))+Declarations!$B$18*INDEX(BE$21:BE$141,MAX(1,MIN(121,$B25-ROUND(Declarations!$A$18/$D$18,0))))+Declarations!$B$19*INDEX(BE$21:BE$141,MAX(1,MIN(121,$B25-ROUND(Declarations!$A$19/$D$18,0))))+Declarations!$B$20*INDEX(BE$21:BE$141,MAX(1,MIN(121,$B25-ROUND(Declarations!$A$20/$D$18,0))))) -> -359.11232 | BG25: =INDEX(BF$21:BF$141,$I25+1)*(1-$J25)+INDEX(BF$21:BF$141,$I25+2)*$J25 -> -354.67259 | BH25: =INDEX(BF$21:BF$141,$K25+1)*(1-$L25)+INDEX(BF$21:BF$141,$K25+2)*$L25 -> -345.39352 | BI25: =$C25+$D25+MAX(BG25,BH25,IF(COUNTIFS($A$21:$A$141,">="&$G25,$A$21:$A$141,"<="&$H25)>0,_xlfn.MAXIFS(BF$21:BF$141,$A$21:$A$141,">="&$G25,$A$21:$A$141,"<="&$H25),BG25)) -> -207.89352 | BJ25: -207.89352 | BK25: =ABS(BI25-BJ25) -> 0
A26: =A25+$D$18 -> 41.25 | B26: 6 | C26: =-Short_p*MAX(Floor_c-A26,0) -> -22 | D26: =Cost_k*Alpha_keep*A26 -> 160.875 | E26: =MIN(Cap_h,MAX(0,$B$18+MAX(Loss_w)-Alpha_keep*A26)) -> 1.28125 | F26: =MAX(MIN(Cap_h,$F$18+MIN(Loss_w)-Alpha_keep*A26),E26) -> 2.5 | G26: =Alpha_keep*A26+E26 -> 41.5 | H26: =Alpha_keep*A26+F26 -> 42.71875 | I26: =MIN(INT((G26-$B$18)/$D$18+0.000000001),119) -> 6 | J26: =(G26-$B$18)/$D$18-I26 -> 0 | K26: =MIN(INT((H26-$B$18)/$D$18+0.000000001),119) -> 10 | L26: =(H26-$B$18)/$D$18-K26 -> 0.875 | M26: 0 | N26: =-Cost_k*$A26+Beta_q*(Declarations!$B$16*INDEX(M$21:M$141,MAX(1,MIN(121,$B26-ROUND(Declarations!$A$16/$D$18,0))))+Declarations!$B$17*INDEX(M$21:M$141,MAX(1,MIN(121,$B26-ROUND(Declarations!$A$17/$D$18,0))))+Declarations!$B$18*INDEX(M$21:M$141,MAX(1,MIN(121,$B26-ROUND(Declarations!$A$18/$D$18,0))))+Declarations!$B$19*INDEX(M$21:M$141,MAX(1,MIN(121,$B26-ROUND(Declarations!$A$19/$D$18,0))))+Declarations!$B$20*INDEX(M$21:M$141,MAX(1,MIN(121,$B26-ROUND(Declarations!$A$20/$D$18,0))))) -> -165 | O26: =INDEX(N$21:N$141,$I26+1)*(1-$J26)+INDEX(N$21:N$141,$I26+2)*$J26 -> -166 | P26: =INDEX(N$21:N$141,$K26+1)*(1-$L26)+INDEX(N$21:N$141,$K26+2)*$L26 -> -170.875 | Q26: =$C26+$D26+MAX(O26,P26,IF(COUNTIFS($A$21:$A$141,">="&$G26,$A$21:$A$141,"<="&$H26)>0,_xlfn.MAXIFS(N$21:N$141,$A$21:$A$141,">="&$G26,$A$21:$A$141,"<="&$H26),O26)) -> -27.125 | R26: =-Cost_k*$A26+Beta_q*(Declarations!$B$16*INDEX(Q$21:Q$141,MAX(1,MIN(121,$B26-ROUND(Declarations!$A$16/$D$18,0))))+Declarations!$B$17*INDEX(Q$21:Q$141,MAX(1,MIN(121,$B26-ROUND(Declarations!$A$17/$D$18,0))))+Declarations!$B$18*INDEX(Q$21:Q$141,MAX(1,MIN(121,$B26-ROUND(Declarations!$A$18/$D$18,0))))+Declarations!$B$19*INDEX(Q$21:Q$141,MAX(1,MIN(121,$B26-ROUND(Declarations!$A$19/$D$18,0))))+Declarations!$B$20*INDEX(Q$21:Q$141,MAX(1,MIN(121,$B26-ROUND(Declarations!$A$20/$D$18,0))))) -> -191.45458 | S26: =INDEX(R$21:R$141,$I26+1)*(1-$J26)+INDEX(R$21:R$141,$I26+2)*$J26 -> -191.22669 | T26: =INDEX(R$21:R$141,$K26+1)*(1-$L26)+INDEX(R$21:R$141,$K26+2)*$L26 -> -190.78719 | U26: =$C26+$D26+MAX(S26,T26,IF(COUNTIFS($A$21:$A$141,">="&$G26,$A$21:$A$141,"<="&$H26)>0,_xlfn.MAXIFS(R$21:R$141,$A$21:$A$141,">="&$G26,$A$21:$A$141,"<="&$H26),S26)) -> -51.694005 | V26: =-Cost_k*$A26+Beta_q*(Declarations!$B$16*INDEX(U$21:U$141,MAX(1,MIN(121,$B26-ROUND(Declarations!$A$16/$D$18,0))))+Declarations!$B$17*INDEX(U$21:U$141,MAX(1,MIN(121,$B26-ROUND(Declarations!$A$17/$D$18,0))))+Declarations!$B$18*INDEX(U$21:U$141,MAX(1,MIN(121,$B26-ROUND(Declarations!$A$18/$D$18,0))))+Declarations!$B$19*INDEX(U$21:U$141,MAX(1,MIN(121,$B26-ROUND(Declarations!$A$19/$D$18,0))))+Declarations!$B$20*INDEX(U$21:U$141,MAX(1,MIN(121,$B26-ROUND(Declarations!$A$20/$D$18,0))))) -> -215.48416 | W26: =INDEX(V$21:V$141,$I26+1)*(1-$J26)+INDEX(V$21:V$141,$I26+2)*$J26 -> -215.18827 | X26: =INDEX(V$21:V$141,$K26+1)*(1-$L26)+INDEX(V$21:V$141,$K26+2)*$L26 -> -213.50249 | Y26: =$C26+$D26+MAX(W26,X26,IF(COUNTIFS($A$21:$A$141,">="&$G26,$A$21:$A$141,"<="&$H26)>0,_xlfn.MAXIFS(V$21:V$141,$A$21:$A$141,">="&$G26,$A$21:$A$141,"<="&$H26),W26)) -> -74.627492 | Z26: =-Cost_k*$A26+Beta_q*(Declarations!$B$16*INDEX(Y$21:Y$141,MAX(1,MIN(121,$B26-ROUND(Declarations!$A$16/$D$18,0))))+Declarations!$B$17*INDEX(Y$21:Y$141,MAX(1,MIN(121,$B26-ROUND(Declarations!$A$17/$D$18,0))))+Declarations!$B$18*INDEX(Y$21:Y$141,MAX(1,MIN(121,$B26-ROUND(Declarations!$A$18/$D$18,0))))+Declarations!$B$19*INDEX(Y$21:Y$141,MAX(1,MIN(121,$B26-ROUND(Declarations!$A$19/$D$18,0))))+Declarations!$B$20*INDEX(Y$21:Y$141,MAX(1,MIN(121,$B26-ROUND(Declarations!$A$20/$D$18,0))))) -> -237.87107 | AA26: =INDEX(Z$21:Z$141,$I26+1)*(1-$J26)+INDEX(Z$21:Z$141,$I26+2)*$J26 -> -237.35706 | AB26: =INDEX(Z$21:Z$141,$K26+1)*(1-$L26)+INDEX(Z$21:Z$141,$K26+2)*$L26 -> -234.93393 | AC26: =$C26+$D26+MAX(AA26,AB26,IF(COUNTIFS($A$21:$A$141,">="&$G26,$A$21:$A$141,"<="&$H26)>0,_xlfn.MAXIFS(Z$21:Z$141,$A$21:$A$141,">="&$G26,$A$21:$A$141,"<="&$H26),AA26)) -> -96.058929 | AD26: =-Cost_k*$A26+Beta_q*(Declarations!$B$16*INDEX(AC$21:AC$141,MAX(1,MIN(121,$B26-ROUND(Declarations!$A$16/$D$18,0))))+Declarations!$B$17*INDEX(AC$21:AC$141,MAX(1,MIN(121,$B26-ROUND(Declarations!$A$17/$D$18,0))))+Declarations!$B$18*INDEX(AC$21:AC$141,MAX(1,MIN(121,$B26-ROUND(Declarations!$A$18/$D$18,0))))+Declarations!$B$19*INDEX(AC$21:AC$141,MAX(1,MIN(121,$B26-ROUND(Declarations!$A$19/$D$18,0))))+Declarations!$B$20*INDEX(AC$21:AC$141,MAX(1,MIN(121,$B26-ROUND(Declarations!$A$20/$D$18,0))))) -> -258.79074 | AE26: =INDEX(AD$21:AD$141,$I26+1)*(1-$J26)+INDEX(AD$21:AD$141,$I26+2)*$J26 -> -258.14726 | AF26: =INDEX(AD$21:AD$141,$K26+1)*(1-$L26)+INDEX(AD$21:AD$141,$K26+2)*$L26 -> -254.77574 | AG26: =$C26+$D26+MAX(AE26,AF26,IF(COUNTIFS($A$21:$A$141,">="&$G26,$A$21:$A$141,"<="&$H26)>0,_xlfn.MAXIFS(AD$21:AD$141,$A$21:$A$141,">="&$G26,$A$21:$A$141,"<="&$H26),AE26)) -> -115.90074 | AH26: =-Cost_k*$A26+Beta_q*(Declarations!$B$16*INDEX(AG$21:AG$141,MAX(1,MIN(121,$B26-ROUND(Declarations!$A$16/$D$18,0))))+Declarations!$B$17*INDEX(AG$21:AG$141,MAX(1,MIN(121,$B26-ROUND(Declarations!$A$17/$D$18,0))))+Declarations!$B$18*INDEX(AG$21:AG$141,MAX(1,MIN(121,$B26-ROUND(Declarations!$A$18/$D$18,0))))+Declarations!$B$19*INDEX(AG$21:AG$141,MAX(1,MIN(121,$B26-ROUND(Declarations!$A$19/$D$18,0))))+Declarations!$B$20*INDEX(AG$21:AG$141,MAX(1,MIN(121,$B26-ROUND(Declarations!$A$20/$D$18,0))))) -> -278.10344 | AI26: =INDEX(AH$21:AH$141,$I26+1)*(1-$J26)+INDEX(AH$21:AH$141,$I26+2)*$J26 -> -277.23377 | AJ26: =INDEX(AH$21:AH$141,$K26+1)*(1-$L26)+INDEX(AH$21:AH$141,$K26+2)*$L26 -> -272.66393 | AK26: =$C26+$D26+MAX(AI26,AJ26,IF(COUNTIFS($A$21:$A$141,">="&$G26,$A$21:$A$141,"<="&$H26)>0,_xlfn.MAXIFS(AH$21:AH$141,$A$21:$A$141,">="&$G26,$A$21:$A$141,"<="&$H26),AI26)) -> -133.78893 | AL26: =-Cost_k*$A26+Beta_q*(Declarations!$B$16*INDEX(AK$21:AK$141,MAX(1,MIN(121,$B26-ROUND(Declarations!$A$16/$D$18,0))))+Declarations!$B$17*INDEX(AK$21:AK$141,MAX(1,MIN(121,$B26-ROUND(Declarations!$A$17/$D$18,0))))+Declarations!$B$18*INDEX(AK$21:AK$141,MAX(1,MIN(121,$B26-ROUND(Declarations!$A$18/$D$18,0))))+Declarations!$B$19*INDEX(AK$21:AK$141,MAX(1,MIN(121,$B26-ROUND(Declarations!$A$19/$D$18,0))))+Declarations!$B$20*INDEX(AK$21:AK$141,MAX(1,MIN(121,$B26-ROUND(Declarations!$A$20/$D$18,0))))) -> -295.57437 | AM26: =INDEX(AL$21:AL$141,$I26+1)*(1-$J26)+INDEX(AL$21:AL$141,$I26+2)*$J26 -> -294.49319 | AN26: =INDEX(AL$21:AL$141,$K26+1)*(1-$L26)+INDEX(AL$21:AL$141,$K26+2)*$L26 -> -288.85124 | AO26: =$C26+$D26+MAX(AM26,AN26,IF(COUNTIFS($A$21:$A$141,">="&$G26,$A$21:$A$141,"<="&$H26)>0,_xlfn.MAXIFS(AL$21:AL$141,$A$21:$A$141,">="&$G26,$A$21:$A$141,"<="&$H26),AM26)) -> -149.97624 | AP26: =-Cost_k*$A26+Beta_q*(Declarations!$B$16*INDEX(AO$21:AO$141,MAX(1,MIN(121,$B26-ROUND(Declarations!$A$16/$D$18,0))))+Declarations!$B$17*INDEX(AO$21:AO$141,MAX(1,MIN(121,$B26-ROUND(Declarations!$A$17/$D$18,0))))+Declarations!$B$18*INDEX(AO$21:AO$141,MAX(1,MIN(121,$B26-ROUND(Declarations!$A$18/$D$18,0))))+Declarations!$B$19*INDEX(AO$21:AO$141,MAX(1,MIN(121,$B26-ROUND(Declarations!$A$19/$D$18,0))))+Declarations!$B$20*INDEX(AO$21:AO$141,MAX(1,MIN(121,$B26-ROUND(Declarations!$A$20/$D$18,0))))) -> -311.35385 | AQ26: =INDEX(AP$21:AP$141,$I26+1)*(1-$J26)+INDEX(AP$21:AP$141,$I26+2)*$J26 -> -310.06124 | AR26: =INDEX(AP$21:AP$141,$K26+1)*(1-$L26)+INDEX(AP$21:AP$141,$K26+2)*$L26 -> -303.25391 | AS26: =$C26+$D26+MAX(AQ26,AR26,IF(COUNTIFS($A$21:$A$141,">="&$G26,$A$21:$A$141,"<="&$H26)>0,_xlfn.MAXIFS(AP$21:AP$141,$A$21:$A$141,">="&$G26,$A$21:$A$141,"<="&$H26),AQ26)) -> -164.37891 | AT26: =-Cost_k*$A26+Beta_q*(Declarations!$B$16*INDEX(AS$21:AS$141,MAX(1,MIN(121,$B26-ROUND(Declarations!$A$16/$D$18,0))))+Declarations!$B$17*INDEX(AS$21:AS$141,MAX(1,MIN(121,$B26-ROUND(Declarations!$A$17/$D$18,0))))+Declarations!$B$18*INDEX(AS$21:AS$141,MAX(1,MIN(121,$B26-ROUND(Declarations!$A$18/$D$18,0))))+Declarations!$B$19*INDEX(AS$21:AS$141,MAX(1,MIN(121,$B26-ROUND(Declarations!$A$19/$D$18,0))))+Declarations!$B$20*INDEX(AS$21:AS$141,MAX(1,MIN(121,$B26-ROUND(Declarations!$A$20/$D$18,0))))) -> -325.38652 | AU26: =INDEX(AT$21:AT$141,$I26+1)*(1-$J26)+INDEX(AT$21:AT$141,$I26+2)*$J26 -> -323.8599 | AV26: =INDEX(AT$21:AT$141,$K26+1)*(1-$L26)+INDEX(AT$21:AT$141,$K26+2)*$L26 -> -315.79569 | AW26: =$C26+$D26+MAX(AU26,AV26,IF(COUNTIFS($A$21:$A$141,">="&$G26,$A$21:$A$141,"<="&$H26)>0,_xlfn.MAXIFS(AT$21:AT$141,$A$21:$A$141,">="&$G26,$A$21:$A$141,"<="&$H26),AU26)) -> -176.92069 | AX26: =-Cost_k*$A26+Beta_q*(Declarations!$B$16*INDEX(AW$21:AW$141,MAX(1,MIN(121,$B26-ROUND(Declarations!$A$16/$D$18,0))))+Declarations!$B$17*INDEX(AW$21:AW$141,MAX(1,MIN(121,$B26-ROUND(Declarations!$A$17/$D$18,0))))+Declarations!$B$18*INDEX(AW$21:AW$141,MAX(1,MIN(121,$B26-ROUND(Declarations!$A$18/$D$18,0))))+Declarations!$B$19*INDEX(AW$21:AW$141,MAX(1,MIN(121,$B26-ROUND(Declarations!$A$19/$D$18,0))))+Declarations!$B$20*INDEX(AW$21:AW$141,MAX(1,MIN(121,$B26-ROUND(Declarations!$A$20/$D$18,0))))) -> -337.61241 | AY26: =INDEX(AX$21:AX$141,$I26+1)*(1-$J26)+INDEX(AX$21:AX$141,$I26+2)*$J26 -> -335.84434 | AZ26: =INDEX(AX$21:AX$141,$K26+1)*(1-$L26)+INDEX(AX$21:AX$141,$K26+2)*$L26 -> -326.52355 | BA26: =$C26+$D26+MAX(AY26,AZ26,IF(COUNTIFS($A$21:$A$141,">="&$G26,$A$21:$A$141,"<="&$H26)>0,_xlfn.MAXIFS(AX$21:AX$141,$A$21:$A$141,">="&$G26,$A$21:$A$141,"<="&$H26),AY26)) -> -187.64855 | BB26: =-Cost_k*$A26+Beta_q*(Declarations!$B$16*INDEX(BA$21:BA$141,MAX(1,MIN(121,$B26-ROUND(Declarations!$A$16/$D$18,0))))+Declarations!$B$17*INDEX(BA$21:BA$141,MAX(1,MIN(121,$B26-ROUND(Declarations!$A$17/$D$18,0))))+Declarations!$B$18*INDEX(BA$21:BA$141,MAX(1,MIN(121,$B26-ROUND(Declarations!$A$18/$D$18,0))))+Declarations!$B$19*INDEX(BA$21:BA$141,MAX(1,MIN(121,$B26-ROUND(Declarations!$A$19/$D$18,0))))+Declarations!$B$20*INDEX(BA$21:BA$141,MAX(1,MIN(121,$B26-ROUND(Declarations!$A$20/$D$18,0))))) -> -348.07469 | BC26: =INDEX(BB$21:BB$141,$I26+1)*(1-$J26)+INDEX(BB$21:BB$141,$I26+2)*$J26 -> -346.07244 | BD26: =INDEX(BB$21:BB$141,$K26+1)*(1-$L26)+INDEX(BB$21:BB$141,$K26+2)*$L26 -> -335.5582 | BE26: =$C26+$D26+MAX(BC26,BD26,IF(COUNTIFS($A$21:$A$141,">="&$G26,$A$21:$A$141,"<="&$H26)>0,_xlfn.MAXIFS(BB$21:BB$141,$A$21:$A$141,">="&$G26,$A$21:$A$141,"<="&$H26),BC26)) -> -196.6832 | BF26: =-Cost_k*$A26+Beta_q*(Declarations!$B$16*INDEX(BE$21:BE$141,MAX(1,MIN(121,$B26-ROUND(Declarations!$A$16/$D$18,0))))+Declarations!$B$17*INDEX(BE$21:BE$141,MAX(1,MIN(121,$B26-ROUND(Declarations!$A$17/$D$18,0))))+Declarations!$B$18*INDEX(BE$21:BE$141,MAX(1,MIN(121,$B26-ROUND(Declarations!$A$18/$D$18,0))))+Declarations!$B$19*INDEX(BE$21:BE$141,MAX(1,MIN(121,$B26-ROUND(Declarations!$A$19/$D$18,0))))+Declarations!$B$20*INDEX(BE$21:BE$141,MAX(1,MIN(121,$B26-ROUND(Declarations!$A$20/$D$18,0))))) -> -356.8911 | BG26: =INDEX(BF$21:BF$141,$I26+1)*(1-$J26)+INDEX(BF$21:BF$141,$I26+2)*$J26 -> -354.67259 | BH26: =INDEX(BF$21:BF$141,$K26+1)*(1-$L26)+INDEX(BF$21:BF$141,$K26+2)*$L26 -> -343.08601 | BI26: =$C26+$D26+MAX(BG26,BH26,IF(COUNTIFS($A$21:$A$141,">="&$G26,$A$21:$A$141,"<="&$H26)>0,_xlfn.MAXIFS(BF$21:BF$141,$A$21:$A$141,">="&$G26,$A$21:$A$141,"<="&$H26),BG26)) -> -204.21101 | BJ26: -204.21101 | BK26: =ABS(BI26-BJ26) -> 0
A27: =A26+$D$18 -> 41.5 | B27: 7 | C27: =-Short_p*MAX(Floor_c-A27,0) -> -21.6 | D27: =Cost_k*Alpha_keep*A27 -> 161.85 | E27: =MIN(Cap_h,MAX(0,$B$18+MAX(Loss_w)-Alpha_keep*A27)) -> 1.0375 | F27: =MAX(MIN(Cap_h,$F$18+MIN(Loss_w)-Alpha_keep*A27),E27) -> 2.5 | G27: =Alpha_keep*A27+E27 -> 41.5 | H27: =Alpha_keep*A27+F27 -> 42.9625 | I27: =MIN(INT((G27-$B$18)/$D$18+0.000000001),119) -> 6 | J27: =(G27-$B$18)/$D$18-I27 -> 0 | K27: =MIN(INT((H27-$B$18)/$D$18+0.000000001),119) -> 11 | L27: =(H27-$B$18)/$D$18-K27 -> 0.85 | M27: 0 | N27: =-Cost_k*$A27+Beta_q*(Declarations!$B$16*INDEX(M$21:M$141,MAX(1,MIN(121,$B27-ROUND(Declarations!$A$16/$D$18,0))))+Declarations!$B$17*INDEX(M$21:M$141,MAX(1,MIN(121,$B27-ROUND(Declarations!$A$17/$D$18,0))))+Declarations!$B$18*INDEX(M$21:M$141,MAX(1,MIN(121,$B27-ROUND(Declarations!$A$18/$D$18,0))))+Declarations!$B$19*INDEX(M$21:M$141,MAX(1,MIN(121,$B27-ROUND(Declarations!$A$19/$D$18,0))))+Declarations!$B$20*INDEX(M$21:M$141,MAX(1,MIN(121,$B27-ROUND(Declarations!$A$20/$D$18,0))))) -> -166 | O27: =INDEX(N$21:N$141,$I27+1)*(1-$J27)+INDEX(N$21:N$141,$I27+2)*$J27 -> -166 | P27: =INDEX(N$21:N$141,$K27+1)*(1-$L27)+INDEX(N$21:N$141,$K27+2)*$L27 -> -171.85 | Q27: =$C27+$D27+MAX(O27,P27,IF(COUNTIFS($A$21:$A$141,">="&$G27,$A$21:$A$141,"<="&$H27)>0,_xlfn.MAXIFS(N$21:N$141,$A$21:$A$141,">="&$G27,$A$21:$A$141,"<="&$H27),O27)) -> -25.75 | R27: =-Cost_k*$A27+Beta_q*(Declarations!$B$16*INDEX(Q$21:Q$141,MAX(1,MIN(121,$B27-ROUND(Declarations!$A$16/$D$18,0))))+Declarations!$B$17*INDEX(Q$21:Q$141,MAX(1,MIN(121,$B27-ROUND(Declarations!$A$17/$D$18,0))))+Declarations!$B$18*INDEX(Q$21:Q$141,MAX(1,MIN(121,$B27-ROUND(Declarations!$A$18/$D$18,0))))+Declarations!$B$19*INDEX(Q$21:Q$141,MAX(1,MIN(121,$B27-ROUND(Declarations!$A$19/$D$18,0))))+Declarations!$B$20*INDEX(Q$21:Q$141,MAX(1,MIN(121,$B27-ROUND(Declarations!$A$20/$D$18,0))))) -> -191.22669 | S27: =INDEX(R$21:R$141,$I27+1)*(1-$J27)+INDEX(R$21:R$141,$I27+2)*$J27 -> -191.22669 | T27: =INDEX(R$21:R$141,$K27+1)*(1-$L27)+INDEX(R$21:R$141,$K27+2)*$L27 -> -191.13405 | U27: =$C27+$D27+MAX(S27,T27,IF(COUNTIFS($A$21:$A$141,">="&$G27,$A$21:$A$141,"<="&$H27)>0,_xlfn.MAXIFS(R$21:R$141,$A$21:$A$141,">="&$G27,$A$21:$A$141,"<="&$H27),S27)) -> -50.319005 | V27: =-Cost_k*$A27+Beta_q*(Declarations!$B$16*INDEX(U$21:U$141,MAX(1,MIN(121,$B27-ROUND(Declarations!$A$16/$D$18,0))))+Declarations!$B$17*INDEX(U$21:U$141,MAX(1,MIN(121,$B27-ROUND(Declarations!$A$17/$D$18,0))))+Declarations!$B$18*INDEX(U$21:U$141,MAX(1,MIN(121,$B27-ROUND(Declarations!$A$18/$D$18,0))))+Declarations!$B$19*INDEX(U$21:U$141,MAX(1,MIN(121,$B27-ROUND(Declarations!$A$19/$D$18,0))))+Declarations!$B$20*INDEX(U$21:U$141,MAX(1,MIN(121,$B27-ROUND(Declarations!$A$20/$D$18,0))))) -> -215.18827 | W27: =INDEX(V$21:V$141,$I27+1)*(1-$J27)+INDEX(V$21:V$141,$I27+2)*$J27 -> -215.18827 | X27: =INDEX(V$21:V$141,$K27+1)*(1-$L27)+INDEX(V$21:V$141,$K27+2)*$L27 -> -213.21471 | Y27: =$C27+$D27+MAX(W27,X27,IF(COUNTIFS($A$21:$A$141,">="&$G27,$A$21:$A$141,"<="&$H27)>0,_xlfn.MAXIFS(V$21:V$141,$A$21:$A$141,">="&$G27,$A$21:$A$141,"<="&$H27),W27)) -> -72.964709 | Z27: =-Cost_k*$A27+Beta_q*(Declarations!$B$16*INDEX(Y$21:Y$141,MAX(1,MIN(121,$B27-ROUND(Declarations!$A$16/$D$18,0))))+Declarations!$B$17*INDEX(Y$21:Y$141,MAX(1,MIN(121,$B27-ROUND(Declarations!$A$17/$D$18,0))))+Declarations!$B$18*INDEX(Y$21:Y$141,MAX(1,MIN(121,$B27-ROUND(Declarations!$A$18/$D$18,0))))+Declarations!$B$19*INDEX(Y$21:Y$141,MAX(1,MIN(121,$B27-ROUND(Declarations!$A$19/$D$18,0))))+Declarations!$B$20*INDEX(Y$21:Y$141,MAX(1,MIN(121,$B27-ROUND(Declarations!$A$20/$D$18,0))))) -> -237.35706 | AA27: =INDEX(Z$21:Z$141,$I27+1)*(1-$J27)+INDEX(Z$21:Z$141,$I27+2)*$J27 -> -237.35706 | AB27: =INDEX(Z$21:Z$141,$K27+1)*(1-$L27)+INDEX(Z$21:Z$141,$K27+2)*$L27 -> -234.54669 | AC27: =$C27+$D27+MAX(AA27,AB27,IF(COUNTIFS($A$21:$A$141,">="&$G27,$A$21:$A$141,"<="&$H27)>0,_xlfn.MAXIFS(Z$21:Z$141,$A$21:$A$141,">="&$G27,$A$21:$A$141,"<="&$H27),AA27)) -> -94.296688 | AD27: =-Cost_k*$A27+Beta_q*(Declarations!$B$16*INDEX(AC$21:AC$141,MAX(1,MIN(121,$B27-ROUND(Declarations!$A$16/$D$18,0))))+Declarations!$B$17*INDEX(AC$21:AC$141,MAX(1,MIN(121,$B27-ROUND(Declarations!$A$17/$D$18,0))))+Declarations!$B$18*INDEX(AC$21:AC$141,MAX(1,MIN(121,$B27-ROUND(Declarations!$A$18/$D$18,0))))+Declarations!$B$19*INDEX(AC$21:AC$141,MAX(1,MIN(121,$B27-ROUND(Declarations!$A$19/$D$18,0))))+Declarations!$B$20*INDEX(AC$21:AC$141,MAX(1,MIN(121,$B27-ROUND(Declarations!$A$20/$D$18,0))))) -> -258.14726 | AE27: =INDEX(AD$21:AD$141,$I27+1)*(1-$J27)+INDEX(AD$21:AD$141,$I27+2)*$J27 -> -258.14726 | AF27: =INDEX(AD$21:AD$141,$K27+1)*(1-$L27)+INDEX(AD$21:AD$141,$K27+2)*$L27 -> -254.13029 | AG27: =$C27+$D27+MAX(AE27,AF27,IF(COUNTIFS($A$21:$A$141,">="&$G27,$A$21:$A$141,"<="&$H27)>0,_xlfn.MAXIFS(AD$21:AD$141,$A$21:$A$141,">="&$G27,$A$21:$A$141,"<="&$H27),AE27)) -> -113.88029 | AH27: =-Cost_k*$A27+Beta_q*(Declarations!$B$16*INDEX(AG$21:AG$141,MAX(1,MIN(121,$B27-ROUND(Declarations!$A$16/$D$18,0))))+Declarations!$B$17*INDEX(AG$21:AG$141,MAX(1,MIN(121,$B27-ROUND(Declarations!$A$17/$D$18,0))))+Declarations!$B$18*INDEX(AG$21:AG$141,MAX(1,MIN(121,$B27-ROUND(Declarations!$A$18/$D$18,0))))+Declarations!$B$19*INDEX(AG$21:AG$141,MAX(1,MIN(121,$B27-ROUND(Declarations!$A$19/$D$18,0))))+Declarations!$B$20*INDEX(AG$21:AG$141,MAX(1,MIN(121,$B27-ROUND(Declarations!$A$20/$D$18,0))))) -> -277.23377 | AI27: =INDEX(AH$21:AH$141,$I27+1)*(1-$J27)+INDEX(AH$21:AH$141,$I27+2)*$J27 -> -277.23377 | AJ27: =INDEX(AH$21:AH$141,$K27+1)*(1-$L27)+INDEX(AH$21:AH$141,$K27+2)*$L27 -> -271.79075 | AK27: =$C27+$D27+MAX(AI27,AJ27,IF(COUNTIFS($A$21:$A$141,">="&$G27,$A$21:$A$141,"<="&$H27)>0,_xlfn.MAXIFS(AH$21:AH$141,$A$21:$A$141,">="&$G27,$A$21:$A$141,"<="&$H27),AI27)) -> -131.54075 | AL27: =-Cost_k*$A27+Beta_q*(Declarations!$B$16*INDEX(AK$21:AK$141,MAX(1,MIN(121,$B27-ROUND(Declarations!$A$16/$D$18,0))))+Declarations!$B$17*INDEX(AK$21:AK$141,MAX(1,MIN(121,$B27-ROUND(Declarations!$A$17/$D$18,0))))+Declarations!$B$18*INDEX(AK$21:AK$141,MAX(1,MIN(121,$B27-ROUND(Declarations!$A$18/$D$18,0))))+Declarations!$B$19*INDEX(AK$21:AK$141,MAX(1,MIN(121,$B27-ROUND(Declarations!$A$19/$D$18,0))))+Declarations!$B$20*INDEX(AK$21:AK$141,MAX(1,MIN(121,$B27-ROUND(Declarations!$A$20/$D$18,0))))) -> -294.49319 | AM27: =INDEX(AL$21:AL$141,$I27+1)*(1-$J27)+INDEX(AL$21:AL$141,$I27+2)*$J27 -> -294.49319 | AN27: =INDEX(AL$21:AL$141,$K27+1)*(1-$L27)+INDEX(AL$21:AL$141,$K27+2)*$L27 -> -287.75494 | AO27: =$C27+$D27+MAX(AM27,AN27,IF(COUNTIFS($A$21:$A$141,">="&$G27,$A$21:$A$141,"<="&$H27)>0,_xlfn.MAXIFS(AL$21:AL$141,$A$21:$A$141,">="&$G27,$A$21:$A$141,"<="&$H27),AM27)) -> -147.50494 | AP27: =-Cost_k*$A27+Beta_q*(Declarations!$B$16*INDEX(AO$21:AO$141,MAX(1,MIN(121,$B27-ROUND(Declarations!$A$16/$D$18,0))))+Declarations!$B$17*INDEX(AO$21:AO$141,MAX(1,MIN(121,$B27-ROUND(Declarations!$A$17/$D$18,0))))+Declarations!$B$18*INDEX(AO$21:AO$141,MAX(1,MIN(121,$B27-ROUND(Declarations!$A$18/$D$18,0))))+Declarations!$B$19*INDEX(AO$21:AO$141,MAX(1,MIN(121,$B27-ROUND(Declarations!$A$19/$D$18,0))))+Declarations!$B$20*INDEX(AO$21:AO$141,MAX(1,MIN(121,$B27-ROUND(Declarations!$A$20/$D$18,0))))) -> -310.06124 | AQ27: =INDEX(AP$21:AP$141,$I27+1)*(1-$J27)+INDEX(AP$21:AP$141,$I27+2)*$J27 -> -310.06124 | AR27: =INDEX(AP$21:AP$141,$K27+1)*(1-$L27)+INDEX(AP$21:AP$141,$K27+2)*$L27 -> -301.90591 | AS27: =$C27+$D27+MAX(AQ27,AR27,IF(COUNTIFS($A$21:$A$141,">="&$G27,$A$21:$A$141,"<="&$H27)>0,_xlfn.MAXIFS(AP$21:AP$141,$A$21:$A$141,">="&$G27,$A$21:$A$141,"<="&$H27),AQ27)) -> -161.65591 | AT27: =-Cost_k*$A27+Beta_q*(Declarations!$B$16*INDEX(AS$21:AS$141,MAX(1,MIN(121,$B27-ROUND(Declarations!$A$16/$D$18,0))))+Declarations!$B$17*INDEX(AS$21:AS$141,MAX(1,MIN(121,$B27-ROUND(Declarations!$A$17/$D$18,0))))+Declarations!$B$18*INDEX(AS$21:AS$141,MAX(1,MIN(121,$B27-ROUND(Declarations!$A$18/$D$18,0))))+Declarations!$B$19*INDEX(AS$21:AS$141,MAX(1,MIN(121,$B27-ROUND(Declarations!$A$19/$D$18,0))))+Declarations!$B$20*INDEX(AS$21:AS$141,MAX(1,MIN(121,$B27-ROUND(Declarations!$A$20/$D$18,0))))) -> -323.8599 | AU27: =INDEX(AT$21:AT$141,$I27+1)*(1-$J27)+INDEX(AT$21:AT$141,$I27+2)*$J27 -> -323.8599 | AV27: =INDEX(AT$21:AT$141,$K27+1)*(1-$L27)+INDEX(AT$21:AT$141,$K27+2)*$L27 -> -314.18687 | AW27: =$C27+$D27+MAX(AU27,AV27,IF(COUNTIFS($A$21:$A$141,">="&$G27,$A$21:$A$141,"<="&$H27)>0,_xlfn.MAXIFS(AT$21:AT$141,$A$21:$A$141,">="&$G27,$A$21:$A$141,"<="&$H27),AU27)) -> -173.93687 | AX27: =-Cost_k*$A27+Beta_q*(Declarations!$B$16*INDEX(AW$21:AW$141,MAX(1,MIN(121,$B27-ROUND(Declarations!$A$16/$D$18,0))))+Declarations!$B$17*INDEX(AW$21:AW$141,MAX(1,MIN(121,$B27-ROUND(Declarations!$A$17/$D$18,0))))+Declarations!$B$18*INDEX(AW$21:AW$141,MAX(1,MIN(121,$B27-ROUND(Declarations!$A$18/$D$18,0))))+Declarations!$B$19*INDEX(AW$21:AW$141,MAX(1,MIN(121,$B27-ROUND(Declarations!$A$19/$D$18,0))))+Declarations!$B$20*INDEX(AW$21:AW$141,MAX(1,MIN(121,$B27-ROUND(Declarations!$A$20/$D$18,0))))) -> -335.84434 | AY27: =INDEX(AX$21:AX$141,$I27+1)*(1-$J27)+INDEX(AX$21:AX$141,$I27+2)*$J27 -> -335.84434 | AZ27: =INDEX(AX$21:AX$141,$K27+1)*(1-$L27)+INDEX(AX$21:AX$141,$K27+2)*$L27 -> -324.6614 | BA27: =$C27+$D27+MAX(AY27,AZ27,IF(COUNTIFS($A$21:$A$141,">="&$G27,$A$21:$A$141,"<="&$H27)>0,_xlfn.MAXIFS(AX$21:AX$141,$A$21:$A$141,">="&$G27,$A$21:$A$141,"<="&$H27),AY27)) -> -184.4114 | BB27: =-Cost_k*$A27+Beta_q*(Declarations!$B$16*INDEX(BA$21:BA$141,MAX(1,MIN(121,$B27-ROUND(Declarations!$A$16/$D$18,0))))+Declarations!$B$17*INDEX(BA$21:BA$141,MAX(1,MIN(121,$B27-ROUND(Declarations!$A$17/$D$18,0))))+Declarations!$B$18*INDEX(BA$21:BA$141,MAX(1,MIN(121,$B27-ROUND(Declarations!$A$18/$D$18,0))))+Declarations!$B$19*INDEX(BA$21:BA$141,MAX(1,MIN(121,$B27-ROUND(Declarations!$A$19/$D$18,0))))+Declarations!$B$20*INDEX(BA$21:BA$141,MAX(1,MIN(121,$B27-ROUND(Declarations!$A$20/$D$18,0))))) -> -346.07244 | BC27: =INDEX(BB$21:BB$141,$I27+1)*(1-$J27)+INDEX(BB$21:BB$141,$I27+2)*$J27 -> -346.07244 | BD27: =INDEX(BB$21:BB$141,$K27+1)*(1-$L27)+INDEX(BB$21:BB$141,$K27+2)*$L27 -> -333.46117 | BE27: =$C27+$D27+MAX(BC27,BD27,IF(COUNTIFS($A$21:$A$141,">="&$G27,$A$21:$A$141,"<="&$H27)>0,_xlfn.MAXIFS(BB$21:BB$141,$A$21:$A$141,">="&$G27,$A$21:$A$141,"<="&$H27),BC27)) -> -193.21117 | BF27: =-Cost_k*$A27+Beta_q*(Declarations!$B$16*INDEX(BE$21:BE$141,MAX(1,MIN(121,$B27-ROUND(Declarations!$A$16/$D$18,0))))+Declarations!$B$17*INDEX(BE$21:BE$141,MAX(1,MIN(121,$B27-ROUND(Declarations!$A$17/$D$18,0))))+Declarations!$B$18*INDEX(BE$21:BE$141,MAX(1,MIN(121,$B27-ROUND(Declarations!$A$18/$D$18,0))))+Declarations!$B$19*INDEX(BE$21:BE$141,MAX(1,MIN(121,$B27-ROUND(Declarations!$A$19/$D$18,0))))+Declarations!$B$20*INDEX(BE$21:BE$141,MAX(1,MIN(121,$B27-ROUND(Declarations!$A$20/$D$18,0))))) -> -354.67259 | BG27: =INDEX(BF$21:BF$141,$I27+1)*(1-$J27)+INDEX(BF$21:BF$141,$I27+2)*$J27 -> -354.67259 | BH27: =INDEX(BF$21:BF$141,$K27+1)*(1-$L27)+INDEX(BF$21:BF$141,$K27+2)*$L27 -> -340.78516 | BI27: =$C27+$D27+MAX(BG27,BH27,IF(COUNTIFS($A$21:$A$141,">="&$G27,$A$21:$A$141,"<="&$H27)>0,_xlfn.MAXIFS(BF$21:BF$141,$A$21:$A$141,">="&$G27,$A$21:$A$141,"<="&$H27),BG27)) -> -200.53516 | BJ27: -200.53516 | BK27: =ABS(BI27-BJ27) -> 0
A28: =A27+$D$18 -> 41.75 | B28: 8 | C28: =-Short_p*MAX(Floor_c-A28,0) -> -21.2 | D28: =Cost_k*Alpha_keep*A28 -> 162.825 | E28: =MIN(Cap_h,MAX(0,$B$18+MAX(Loss_w)-Alpha_keep*A28)) -> 0.79375 | F28: =MAX(MIN(Cap_h,$F$18+MIN(Loss_w)-Alpha_keep*A28),E28) -> 2.5 | G28: =Alpha_keep*A28+E28 -> 41.5 | H28: =Alpha_keep*A28+F28 -> 43.20625 | I28: =MIN(INT((G28-$B$18)/$D$18+0.000000001),119) -> 6 | J28: =(G28-$B$18)/$D$18-I28 -> 0 | K28: =MIN(INT((H28-$B$18)/$D$18+0.000000001),119) -> 12 | L28: =(H28-$B$18)/$D$18-K28 -> 0.825 | M28: 0 | N28: =-Cost_k*$A28+Beta_q*(Declarations!$B$16*INDEX(M$21:M$141,MAX(1,MIN(121,$B28-ROUND(Declarations!$A$16/$D$18,0))))+Declarations!$B$17*INDEX(M$21:M$141,MAX(1,MIN(121,$B28-ROUND(Declarations!$A$17/$D$18,0))))+Declarations!$B$18*INDEX(M$21:M$141,MAX(1,MIN(121,$B28-ROUND(Declarations!$A$18/$D$18,0))))+Declarations!$B$19*INDEX(M$21:M$141,MAX(1,MIN(121,$B28-ROUND(Declarations!$A$19/$D$18,0))))+Declarations!$B$20*INDEX(M$21:M$141,MAX(1,MIN(121,$B28-ROUND(Declarations!$A$20/$D$18,0))))) -> -167 | O28: =INDEX(N$21:N$141,$I28+1)*(1-$J28)+INDEX(N$21:N$141,$I28+2)*$J28 -> -166 | P28: =INDEX(N$21:N$141,$K28+1)*(1-$L28)+INDEX(N$21:N$141,$K28+2)*$L28 -> -172.825 | Q28: =$C28+$D28+MAX(O28,P28,IF(COUNTIFS($A$21:$A$141,">="&$G28,$A$21:$A$141,"<="&$H28)>0,_xlfn.MAXIFS(N$21:N$141,$A$21:$A$141,">="&$G28,$A$21:$A$141,"<="&$H28),O28)) -> -24.375 | R28: =-Cost_k*$A28+Beta_q*(Declarations!$B$16*INDEX(Q$21:Q$141,MAX(1,MIN(121,$B28-ROUND(Declarations!$A$16/$D$18,0))))+Declarations!$B$17*INDEX(Q$21:Q$141,MAX(1,MIN(121,$B28-ROUND(Declarations!$A$17/$D$18,0))))+Declarations!$B$18*INDEX(Q$21:Q$141,MAX(1,MIN(121,$B28-ROUND(Declarations!$A$18/$D$18,0))))+Declarations!$B$19*INDEX(Q$21:Q$141,MAX(1,MIN(121,$B28-ROUND(Declarations!$A$19/$D$18,0))))+Declarations!$B$20*INDEX(Q$21:Q$141,MAX(1,MIN(121,$B28-ROUND(Declarations!$A$20/$D$18,0))))) -> -190.93167 | S28: =INDEX(R$21:R$141,$I28+1)*(1-$J28)+INDEX(R$21:R$141,$I28+2)*$J28 -> -191.22669 | T28: =INDEX(R$21:R$141,$K28+1)*(1-$L28)+INDEX(R$21:R$141,$K28+2)*$L28 -> -191.49618 | U28: =$C28+$D28+MAX(S28,T28,IF(COUNTIFS($A$21:$A$141,">="&$G28,$A$21:$A$141,"<="&$H28)>0,_xlfn.MAXIFS(R$21:R$141,$A$21:$A$141,">="&$G28,$A$21:$A$141,"<="&$H28),S28)) -> -48.944005 | V28: =-Cost_k*$A28+Beta_q*(Declarations!$B$16*INDEX(U$21:U$141,MAX(1,MIN(121,$B28-ROUND(Declarations!$A$16/$D$18,0))))+Declarations!$B$17*INDEX(U$21:U$141,MAX(1,MIN(121,$B28-ROUND(Declarations!$A$17/$D$18,0))))+Declarations!$B$18*INDEX(U$21:U$141,MAX(1,MIN(121,$B28-ROUND(Declarations!$A$18/$D$18,0))))+Declarations!$B$19*INDEX(U$21:U$141,MAX(1,MIN(121,$B28-ROUND(Declarations!$A$19/$D$18,0))))+Declarations!$B$20*INDEX(U$21:U$141,MAX(1,MIN(121,$B28-ROUND(Declarations!$A$20/$D$18,0))))) -> -214.81168 | W28: =INDEX(V$21:V$141,$I28+1)*(1-$J28)+INDEX(V$21:V$141,$I28+2)*$J28 -> -215.18827 | X28: =INDEX(V$21:V$141,$K28+1)*(1-$L28)+INDEX(V$21:V$141,$K28+2)*$L28 -> -212.96059 | Y28: =$C28+$D28+MAX(W28,X28,IF(COUNTIFS($A$21:$A$141,">="&$G28,$A$21:$A$141,"<="&$H28)>0,_xlfn.MAXIFS(V$21:V$141,$A$21:$A$141,">="&$G28,$A$21:$A$141,"<="&$H28),W28)) -> -71.335585 | Z28: =-Cost_k*$A28+Beta_q*(Declarations!$B$16*INDEX(Y$21:Y$141,MAX(1,MIN(121,$B28-ROUND(Declarations!$A$16/$D$18,0))))+Declarations!$B$17*INDEX(Y$21:Y$141,MAX(1,MIN(121,$B28-ROUND(Declarations!$A$17/$D$18,0))))+Declarations!$B$18*INDEX(Y$21:Y$141,MAX(1,MIN(121,$B28-ROUND(Declarations!$A$18/$D$18,0))))+Declarations!$B$19*INDEX(Y$21:Y$141,MAX(1,MIN(121,$B28-ROUND(Declarations!$A$19/$D$18,0))))+Declarations!$B$20*INDEX(Y$21:Y$141,MAX(1,MIN(121,$B28-ROUND(Declarations!$A$20/$D$18,0))))) -> -236.79403 | AA28: =INDEX(Z$21:Z$141,$I28+1)*(1-$J28)+INDEX(Z$21:Z$141,$I28+2)*$J28 -> -237.35706 | AB28: =INDEX(Z$21:Z$141,$K28+1)*(1-$L28)+INDEX(Z$21:Z$141,$K28+2)*$L28 -> -234.18236 | AC28: =$C28+$D28+MAX(AA28,AB28,IF(COUNTIFS($A$21:$A$141,">="&$G28,$A$21:$A$141,"<="&$H28)>0,_xlfn.MAXIFS(Z$21:Z$141,$A$21:$A$141,">="&$G28,$A$21:$A$141,"<="&$H28),AA28)) -> -92.557363 | AD28: =-Cost_k*$A28+Beta_q*(Declarations!$B$16*INDEX(AC$21:AC$141,MAX(1,MIN(121,$B28-ROUND(Declarations!$A$16/$D$18,0))))+Declarations!$B$17*INDEX(AC$21:AC$141,MAX(1,MIN(121,$B28-ROUND(Declarations!$A$17/$D$18,0))))+Declarations!$B$18*INDEX(AC$21:AC$141,MAX(1,MIN(121,$B28-ROUND(Declarations!$A$18/$D$18,0))))+Declarations!$B$19*INDEX(AC$21:AC$141,MAX(1,MIN(121,$B28-ROUND(Declarations!$A$19/$D$18,0))))+Declarations!$B$20*INDEX(AC$21:AC$141,MAX(1,MIN(121,$B28-ROUND(Declarations!$A$20/$D$18,0))))) -> -257.43238 | AE28: =INDEX(AD$21:AD$141,$I28+1)*(1-$J28)+INDEX(AD$21:AD$141,$I28+2)*$J28 -> -258.14726 | AF28: =INDEX(AD$21:AD$141,$K28+1)*(1-$L28)+INDEX(AD$21:AD$141,$K28+2)*$L28 -> -253.49268 | AG28: =$C28+$D28+MAX(AE28,AF28,IF(COUNTIFS($A$21:$A$141,">="&$G28,$A$21:$A$141,"<="&$H28)>0,_xlfn.MAXIFS(AD$21:AD$141,$A$21:$A$141,">="&$G28,$A$21:$A$141,"<="&$H28),AE28)) -> -111.86768 | AH28: =-Cost_k*$A28+Beta_q*(Declarations!$B$16*INDEX(AG$21:AG$141,MAX(1,MIN(121,$B28-ROUND(Declarations!$A$16/$D$18,0))))+Declarations!$B$17*INDEX(AG$21:AG$141,MAX(1,MIN(121,$B28-ROUND(Declarations!$A$17/$D$18,0))))+Declarations!$B$18*INDEX(AG$21:AG$141,MAX(1,MIN(121,$B28-ROUND(Declarations!$A$18/$D$18,0))))+Declarations!$B$19*INDEX(AG$21:AG$141,MAX(1,MIN(121,$B28-ROUND(Declarations!$A$19/$D$18,0))))+Declarations!$B$20*INDEX(AG$21:AG$141,MAX(1,MIN(121,$B28-ROUND(Declarations!$A$20/$D$18,0))))) -> -276.27217 | AI28: =INDEX(AH$21:AH$141,$I28+1)*(1-$J28)+INDEX(AH$21:AH$141,$I28+2)*$J28 -> -277.23377 | AJ28: =INDEX(AH$21:AH$141,$K28+1)*(1-$L28)+INDEX(AH$21:AH$141,$K28+2)*$L28 -> -270.93195 | AK28: =$C28+$D28+MAX(AI28,AJ28,IF(COUNTIFS($A$21:$A$141,">="&$G28,$A$21:$A$141,"<="&$H28)>0,_xlfn.MAXIFS(AH$21:AH$141,$A$21:$A$141,">="&$G28,$A$21:$A$141,"<="&$H28),AI28)) -> -129.30695 | AL28: =-Cost_k*$A28+Beta_q*(Declarations!$B$16*INDEX(AK$21:AK$141,MAX(1,MIN(121,$B28-ROUND(Declarations!$A$16/$D$18,0))))+Declarations!$B$17*INDEX(AK$21:AK$141,MAX(1,MIN(121,$B28-ROUND(Declarations!$A$17/$D$18,0))))+Declarations!$B$18*INDEX(AK$21:AK$141,MAX(1,MIN(121,$B28-ROUND(Declarations!$A$18/$D$18,0))))+Declarations!$B$19*INDEX(AK$21:AK$141,MAX(1,MIN(121,$B28-ROUND(Declarations!$A$19/$D$18,0))))+Declarations!$B$20*INDEX(AK$21:AK$141,MAX(1,MIN(121,$B28-ROUND(Declarations!$A$20/$D$18,0))))) -> -293.31151 | AM28: =INDEX(AL$21:AL$141,$I28+1)*(1-$J28)+INDEX(AL$21:AL$141,$I28+2)*$J28 -> -294.49319 | AN28: =INDEX(AL$21:AL$141,$K28+1)*(1-$L28)+INDEX(AL$21:AL$141,$K28+2)*$L28 -> -286.66738 | AO28: =$C28+$D28+MAX(AM28,AN28,IF(COUNTIFS($A$21:$A$141,">="&$G28,$A$21:$A$141,"<="&$H28)>0,_xlfn.MAXIFS(AL$21:AL$141,$A$21:$A$141,">="&$G28,$A$21:$A$141,"<="&$H28),AM28)) -> -145.04238 | AP28: =-Cost_k*$A28+Beta_q*(Declarations!$B$16*INDEX(AO$21:AO$141,MAX(1,MIN(121,$B28-ROUND(Declarations!$A$16/$D$18,0))))+Declarations!$B$17*INDEX(AO$21:AO$141,MAX(1,MIN(121,$B28-ROUND(Declarations!$A$17/$D$18,0))))+Declarations!$B$18*INDEX(AO$21:AO$141,MAX(1,MIN(121,$B28-ROUND(Declarations!$A$18/$D$18,0))))+Declarations!$B$19*INDEX(AO$21:AO$141,MAX(1,MIN(121,$B28-ROUND(Declarations!$A$19/$D$18,0))))+Declarations!$B$20*INDEX(AO$21:AO$141,MAX(1,MIN(121,$B28-ROUND(Declarations!$A$20/$D$18,0))))) -> -308.65291 | AQ28: =INDEX(AP$21:AP$141,$I28+1)*(1-$J28)+INDEX(AP$21:AP$141,$I28+2)*$J28 -> -310.06124 | AR28: =INDEX(AP$21:AP$141,$K28+1)*(1-$L28)+INDEX(AP$21:AP$141,$K28+2)*$L28 -> -300.56072 | AS28: =$C28+$D28+MAX(AQ28,AR28,IF(COUNTIFS($A$21:$A$141,">="&$G28,$A$21:$A$141,"<="&$H28)>0,_xlfn.MAXIFS(AP$21:AP$141,$A$21:$A$141,">="&$G28,$A$21:$A$141,"<="&$H28),AQ28)) -> -158.93572 | AT28: =-Cost_k*$A28+Beta_q*(Declarations!$B$16*INDEX(AS$21:AS$141,MAX(1,MIN(121,$B28-ROUND(Declarations!$A$16/$D$18,0))))+Declarations!$B$17*INDEX(AS$21:AS$141,MAX(1,MIN(121,$B28-ROUND(Declarations!$A$17/$D$18,0))))+Declarations!$B$18*INDEX(AS$21:AS$141,MAX(1,MIN(121,$B28-ROUND(Declarations!$A$18/$D$18,0))))+Declarations!$B$19*INDEX(AS$21:AS$141,MAX(1,MIN(121,$B28-ROUND(Declarations!$A$19/$D$18,0))))+Declarations!$B$20*INDEX(AS$21:AS$141,MAX(1,MIN(121,$B28-ROUND(Declarations!$A$20/$D$18,0))))) -> -322.20177 | AU28: =INDEX(AT$21:AT$141,$I28+1)*(1-$J28)+INDEX(AT$21:AT$141,$I28+2)*$J28 -> -323.8599 | AV28: =INDEX(AT$21:AT$141,$K28+1)*(1-$L28)+INDEX(AT$21:AT$141,$K28+2)*$L28 -> -312.57879 | AW28: =$C28+$D28+MAX(AU28,AV28,IF(COUNTIFS($A$21:$A$141,">="&$G28,$A$21:$A$141,"<="&$H28)>0,_xlfn.MAXIFS(AT$21:AT$141,$A$21:$A$141,">="&$G28,$A$21:$A$141,"<="&$H28),AU28)) -> -170.95379 | AX28: =-Cost_k*$A28+Beta_q*(Declarations!$B$16*INDEX(AW$21:AW$141,MAX(1,MIN(121,$B28-ROUND(Declarations!$A$16/$D$18,0))))+Declarations!$B$17*INDEX(AW$21:AW$141,MAX(1,MIN(121,$B28-ROUND(Declarations!$A$17/$D$18,0))))+Declarations!$B$18*INDEX(AW$21:AW$141,MAX(1,MIN(121,$B28-ROUND(Declarations!$A$18/$D$18,0))))+Declarations!$B$19*INDEX(AW$21:AW$141,MAX(1,MIN(121,$B28-ROUND(Declarations!$A$19/$D$18,0))))+Declarations!$B$20*INDEX(AW$21:AW$141,MAX(1,MIN(121,$B28-ROUND(Declarations!$A$20/$D$18,0))))) -> -333.93098 | AY28: =INDEX(AX$21:AX$141,$I28+1)*(1-$J28)+INDEX(AX$21:AX$141,$I28+2)*$J28 -> -335.84434 | AZ28: =INDEX(AX$21:AX$141,$K28+1)*(1-$L28)+INDEX(AX$21:AX$141,$K28+2)*$L28 -> -322.79996 | BA28: =$C28+$D28+MAX(AY28,AZ28,IF(COUNTIFS($A$21:$A$141,">="&$G28,$A$21:$A$141,"<="&$H28)>0,_xlfn.MAXIFS(AX$21:AX$141,$A$21:$A$141,">="&$G28,$A$21:$A$141,"<="&$H28),AY28)) -> -181.17496 | BB28: =-Cost_k*$A28+Beta_q*(Declarations!$B$16*INDEX(BA$21:BA$141,MAX(1,MIN(121,$B28-ROUND(Declarations!$A$16/$D$18,0))))+Declarations!$B$17*INDEX(BA$21:BA$141,MAX(1,MIN(121,$B28-ROUND(Declarations!$A$17/$D$18,0))))+Declarations!$B$18*INDEX(BA$21:BA$141,MAX(1,MIN(121,$B28-ROUND(Declarations!$A$18/$D$18,0))))+Declarations!$B$19*INDEX(BA$21:BA$141,MAX(1,MIN(121,$B28-ROUND(Declarations!$A$19/$D$18,0))))+Declarations!$B$20*INDEX(BA$21:BA$141,MAX(1,MIN(121,$B28-ROUND(Declarations!$A$20/$D$18,0))))) -> -343.91285 | BC28: =INDEX(BB$21:BB$141,$I28+1)*(1-$J28)+INDEX(BB$21:BB$141,$I28+2)*$J28 -> -346.07244 | BD28: =INDEX(BB$21:BB$141,$K28+1)*(1-$L28)+INDEX(BB$21:BB$141,$K28+2)*$L28 -> -331.36701 | BE28: =$C28+$D28+MAX(BC28,BD28,IF(COUNTIFS($A$21:$A$141,">="&$G28,$A$21:$A$141,"<="&$H28)>0,_xlfn.MAXIFS(BB$21:BB$141,$A$21:$A$141,">="&$G28,$A$21:$A$141,"<="&$H28),BC28)) -> -189.74201 | BF28: =-Cost_k*$A28+Beta_q*(Declarations!$B$16*INDEX(BE$21:BE$141,MAX(1,MIN(121,$B28-ROUND(Declarations!$A$16/$D$18,0))))+Declarations!$B$17*INDEX(BE$21:BE$141,MAX(1,MIN(121,$B28-ROUND(Declarations!$A$17/$D$18,0))))+Declarations!$B$18*INDEX(BE$21:BE$141,MAX(1,MIN(121,$B28-ROUND(Declarations!$A$18/$D$18,0))))+Declarations!$B$19*INDEX(BE$21:BE$141,MAX(1,MIN(121,$B28-ROUND(Declarations!$A$19/$D$18,0))))+Declarations!$B$20*INDEX(BE$21:BE$141,MAX(1,MIN(121,$B28-ROUND(Declarations!$A$20/$D$18,0))))) -> -352.28724 | BG28: =INDEX(BF$21:BF$141,$I28+1)*(1-$J28)+INDEX(BF$21:BF$141,$I28+2)*$J28 -> -354.67259 | BH28: =INDEX(BF$21:BF$141,$K28+1)*(1-$L28)+INDEX(BF$21:BF$141,$K28+2)*$L28 -> -338.49213 | BI28: =$C28+$D28+MAX(BG28,BH28,IF(COUNTIFS($A$21:$A$141,">="&$G28,$A$21:$A$141,"<="&$H28)>0,_xlfn.MAXIFS(BF$21:BF$141,$A$21:$A$141,">="&$G28,$A$21:$A$141,"<="&$H28),BG28)) -> -196.86713 | BJ28: -196.86713 | BK28: =ABS(BI28-BJ28) -> 0
A29: =A28+$D$18 -> 42 | B29: 9 | C29: =-Short_p*MAX(Floor_c-A29,0) -> -20.8 | D29: =Cost_k*Alpha_keep*A29 -> 163.8 | E29: =MIN(Cap_h,MAX(0,$B$18+MAX(Loss_w)-Alpha_keep*A29)) -> 0.55 | F29: =MAX(MIN(Cap_h,$F$18+MIN(Loss_w)-Alpha_keep*A29),E29) -> 2.5 | G29: =Alpha_keep*A29+E29 -> 41.5 | H29: =Alpha_keep*A29+F29 -> 43.45 | I29: =MIN(INT((G29-$B$18)/$D$18+0.000000001),119) -> 6 | J29: =(G29-$B$18)/$D$18-I29 -> 0 | K29: =MIN(INT((H29-$B$18)/$D$18+0.000000001),119) -> 13 | L29: =(H29-$B$18)/$D$18-K29 -> 0.8 | M29: 0 | N29: =-Cost_k*$A29+Beta_q*(Declarations!$B$16*INDEX(M$21:M$141,MAX(1,MIN(121,$B29-ROUND(Declarations!$A$16/$D$18,0))))+Declarations!$B$17*INDEX(M$21:M$141,MAX(1,MIN(121,$B29-ROUND(Declarations!$A$17/$D$18,0))))+Declarations!$B$18*INDEX(M$21:M$141,MAX(1,MIN(121,$B29-ROUND(Declarations!$A$18/$D$18,0))))+Declarations!$B$19*INDEX(M$21:M$141,MAX(1,MIN(121,$B29-ROUND(Declarations!$A$19/$D$18,0))))+Declarations!$B$20*INDEX(M$21:M$141,MAX(1,MIN(121,$B29-ROUND(Declarations!$A$20/$D$18,0))))) -> -168 | O29: =INDEX(N$21:N$141,$I29+1)*(1-$J29)+INDEX(N$21:N$141,$I29+2)*$J29 -> -166 | P29: =INDEX(N$21:N$141,$K29+1)*(1-$L29)+INDEX(N$21:N$141,$K29+2)*$L29 -> -173.8 | Q29: =$C29+$D29+MAX(O29,P29,IF(COUNTIFS($A$21:$A$141,">="&$G29,$A$21:$A$141,"<="&$H29)>0,_xlfn.MAXIFS(N$21:N$141,$A$21:$A$141,">="&$G29,$A$21:$A$141,"<="&$H29),O29)) -> -23 | R29: =-Cost_k*$A29+Beta_q*(Declarations!$B$16*INDEX(Q$21:Q$141,MAX(1,MIN(121,$B29-ROUND(Declarations!$A$16/$D$18,0))))+Declarations!$B$17*INDEX(Q$21:Q$141,MAX(1,MIN(121,$B29-ROUND(Declarations!$A$17/$D$18,0))))+Declarations!$B$18*INDEX(Q$21:Q$141,MAX(1,MIN(121,$B29-ROUND(Declarations!$A$18/$D$18,0))))+Declarations!$B$19*INDEX(Q$21:Q$141,MAX(1,MIN(121,$B29-ROUND(Declarations!$A$19/$D$18,0))))+Declarations!$B$20*INDEX(Q$21:Q$141,MAX(1,MIN(121,$B29-ROUND(Declarations!$A$20/$D$18,0))))) -> -190.77823 | S29: =INDEX(R$21:R$141,$I29+1)*(1-$J29)+INDEX(R$21:R$141,$I29+2)*$J29 -> -191.22669 | T29: =INDEX(R$21:R$141,$K29+1)*(1-$L29)+INDEX(R$21:R$141,$K29+2)*$L29 -> -191.97157 | U29: =$C29+$D29+MAX(S29,T29,IF(COUNTIFS($A$21:$A$141,">="&$G29,$A$21:$A$141,"<="&$H29)>0,_xlfn.MAXIFS(R$21:R$141,$A$21:$A$141,">="&$G29,$A$21:$A$141,"<="&$H29),S29)) -> -47.569005 | V29: =-Cost_k*$A29+Beta_q*(Declarations!$B$16*INDEX(U$21:U$141,MAX(1,MIN(121,$B29-ROUND(Declarations!$A$16/$D$18,0))))+Declarations!$B$17*INDEX(U$21:U$141,MAX(1,MIN(121,$B29-ROUND(Declarations!$A$17/$D$18,0))))+Declarations!$B$18*INDEX(U$21:U$141,MAX(1,MIN(121,$B29-ROUND(Declarations!$A$18/$D$18,0))))+Declarations!$B$19*INDEX(U$21:U$141,MAX(1,MIN(121,$B29-ROUND(Declarations!$A$19/$D$18,0))))+Declarations!$B$20*INDEX(U$21:U$141,MAX(1,MIN(121,$B29-ROUND(Declarations!$A$20/$D$18,0))))) -> -214.45954 | W29: =INDEX(V$21:V$141,$I29+1)*(1-$J29)+INDEX(V$21:V$141,$I29+2)*$J29 -> -215.18827 | X29: =INDEX(V$21:V$141,$K29+1)*(1-$L29)+INDEX(V$21:V$141,$K29+2)*$L29 -> -212.7198 | Y29: =$C29+$D29+MAX(W29,X29,IF(COUNTIFS($A$21:$A$141,">="&$G29,$A$21:$A$141,"<="&$H29)>0,_xlfn.MAXIFS(V$21:V$141,$A$21:$A$141,">="&$G29,$A$21:$A$141,"<="&$H29),W29)) -> -69.719801 | Z29: =-Cost_k*$A29+Beta_q*(Declarations!$B$16*INDEX(Y$21:Y$141,MAX(1,MIN(121,$B29-ROUND(Declarations!$A$16/$D$18,0))))+Declarations!$B$17*INDEX(Y$21:Y$141,MAX(1,MIN(121,$B29-ROUND(Declarations!$A$17/$D$18,0))))+Declarations!$B$18*INDEX(Y$21:Y$141,MAX(1,MIN(121,$B29-ROUND(Declarations!$A$18/$D$18,0))))+Declarations!$B$19*INDEX(Y$21:Y$141,MAX(1,MIN(121,$B29-ROUND(Declarations!$A$19/$D$18,0))))+Declarations!$B$20*INDEX(Y$21:Y$141,MAX(1,MIN(121,$B29-ROUND(Declarations!$A$20/$D$18,0))))) -> -236.24796 | AA29: =INDEX(Z$21:Z$141,$I29+1)*(1-$J29)+INDEX(Z$21:Z$141,$I29+2)*$J29 -> -237.35706 | AB29: =INDEX(Z$21:Z$141,$K29+1)*(1-$L29)+INDEX(Z$21:Z$141,$K29+2)*$L29 -> -233.8285 | AC29: =$C29+$D29+MAX(AA29,AB29,IF(COUNTIFS($A$21:$A$141,">="&$G29,$A$21:$A$141,"<="&$H29)>0,_xlfn.MAXIFS(Z$21:Z$141,$A$21:$A$141,">="&$G29,$A$21:$A$141,"<="&$H29),AA29)) -> -90.828498 | AD29: =-Cost_k*$A29+Beta_q*(Declarations!$B$16*INDEX(AC$21:AC$141,MAX(1,MIN(121,$B29-ROUND(Declarations!$A$16/$D$18,0))))+Declarations!$B$17*INDEX(AC$21:AC$141,MAX(1,MIN(121,$B29-ROUND(Declarations!$A$17/$D$18,0))))+Declarations!$B$18*INDEX(AC$21:AC$141,MAX(1,MIN(121,$B29-ROUND(Declarations!$A$18/$D$18,0))))+Declarations!$B$19*INDEX(AC$21:AC$141,MAX(1,MIN(121,$B29-ROUND(Declarations!$A$19/$D$18,0))))+Declarations!$B$20*INDEX(AC$21:AC$141,MAX(1,MIN(121,$B29-ROUND(Declarations!$A$20/$D$18,0))))) -> -256.72953 | AE29: =INDEX(AD$21:AD$141,$I29+1)*(1-$J29)+INDEX(AD$21:AD$141,$I29+2)*$J29 -> -258.14726 | AF29: =INDEX(AD$21:AD$141,$K29+1)*(1-$L29)+INDEX(AD$21:AD$141,$K29+2)*$L29 -> -252.86588 | AG29: =$C29+$D29+MAX(AE29,AF29,IF(COUNTIFS($A$21:$A$141,">="&$G29,$A$21:$A$141,"<="&$H29)>0,_xlfn.MAXIFS(AD$21:AD$141,$A$21:$A$141,">="&$G29,$A$21:$A$141,"<="&$H29),AE29)) -> -109.86588 | AH29: =-Cost_k*$A29+Beta_q*(Declarations!$B$16*INDEX(AG$21:AG$141,MAX(1,MIN(121,$B29-ROUND(Declarations!$A$16/$D$18,0))))+Declarations!$B$17*INDEX(AG$21:AG$141,MAX(1,MIN(121,$B29-ROUND(Declarations!$A$17/$D$18,0))))+Declarations!$B$18*INDEX(AG$21:AG$141,MAX(1,MIN(121,$B29-ROUND(Declarations!$A$18/$D$18,0))))+Declarations!$B$19*INDEX(AG$21:AG$141,MAX(1,MIN(121,$B29-ROUND(Declarations!$A$19/$D$18,0))))+Declarations!$B$20*INDEX(AG$21:AG$141,MAX(1,MIN(121,$B29-ROUND(Declarations!$A$20/$D$18,0))))) -> -275.32209 | AI29: =INDEX(AH$21:AH$141,$I29+1)*(1-$J29)+INDEX(AH$21:AH$141,$I29+2)*$J29 -> -277.23377 | AJ29: =INDEX(AH$21:AH$141,$K29+1)*(1-$L29)+INDEX(AH$21:AH$141,$K29+2)*$L29 -> -270.08698 | AK29: =$C29+$D29+MAX(AI29,AJ29,IF(COUNTIFS($A$21:$A$141,">="&$G29,$A$21:$A$141,"<="&$H29)>0,_xlfn.MAXIFS(AH$21:AH$141,$A$21:$A$141,">="&$G29,$A$21:$A$141,"<="&$H29),AI29)) -> -127.08698 | AL29: =-Cost_k*$A29+Beta_q*(Declarations!$B$16*INDEX(AK$21:AK$141,MAX(1,MIN(121,$B29-ROUND(Declarations!$A$16/$D$18,0))))+Declarations!$B$17*INDEX(AK$21:AK$141,MAX(1,MIN(121,$B29-ROUND(Declarations!$A$17/$D$18,0))))+Declarations!$B$18*INDEX(AK$21:AK$141,MAX(1,MIN(121,$B29-ROUND(Declarations!$A$18/$D$18,0))))+Declarations!$B$19*INDEX(AK$21:AK$141,MAX(1,MIN(121,$B29-ROUND(Declarations!$A$19/$D$18,0))))+Declarations!$B$20*INDEX(AK$21:AK$141,MAX(1,MIN(121,$B29-ROUND(Declarations!$A$20/$D$18,0))))) -> -292.1423 | AM29: =INDEX(AL$21:AL$141,$I29+1)*(1-$J29)+INDEX(AL$21:AL$141,$I29+2)*$J29 -> -294.49319 | AN29: =INDEX(AL$21:AL$141,$K29+1)*(1-$L29)+INDEX(AL$21:AL$141,$K29+2)*$L29 -> -285.58694 | AO29: =$C29+$D29+MAX(AM29,AN29,IF(COUNTIFS($A$21:$A$141,">="&$G29,$A$21:$A$141,"<="&$H29)>0,_xlfn.MAXIFS(AL$21:AL$141,$A$21:$A$141,">="&$G29,$A$21:$A$141,"<="&$H29),AM29)) -> -142.58694 | AP29: =-Cost_k*$A29+Beta_q*(Declarations!$B$16*INDEX(AO$21:AO$141,MAX(1,MIN(121,$B29-ROUND(Declarations!$A$16/$D$18,0))))+Declarations!$B$17*INDEX(AO$21:AO$141,MAX(1,MIN(121,$B29-ROUND(Declarations!$A$17/$D$18,0))))+Declarations!$B$18*INDEX(AO$21:AO$141,MAX(1,MIN(121,$B29-ROUND(Declarations!$A$18/$D$18,0))))+Declarations!$B$19*INDEX(AO$21:AO$141,MAX(1,MIN(121,$B29-ROUND(Declarations!$A$19/$D$18,0))))+Declarations!$B$20*INDEX(AO$21:AO$141,MAX(1,MIN(121,$B29-ROUND(Declarations!$A$20/$D$18,0))))) -> -307.25151 | AQ29: =INDEX(AP$21:AP$141,$I29+1)*(1-$J29)+INDEX(AP$21:AP$141,$I29+2)*$J29 -> -310.06124 | AR29: =INDEX(AP$21:AP$141,$K29+1)*(1-$L29)+INDEX(AP$21:AP$141,$K29+2)*$L29 -> -299.21778 | AS29: =$C29+$D29+MAX(AQ29,AR29,IF(COUNTIFS($A$21:$A$141,">="&$G29,$A$21:$A$141,"<="&$H29)>0,_xlfn.MAXIFS(AP$21:AP$141,$A$21:$A$141,">="&$G29,$A$21:$A$141,"<="&$H29),AQ29)) -> -156.21778 | AT29: =-Cost_k*$A29+Beta_q*(Declarations!$B$16*INDEX(AS$21:AS$141,MAX(1,MIN(121,$B29-ROUND(Declarations!$A$16/$D$18,0))))+Declarations!$B$17*INDEX(AS$21:AS$141,MAX(1,MIN(121,$B29-ROUND(Declarations!$A$17/$D$18,0))))+Declarations!$B$18*INDEX(AS$21:AS$141,MAX(1,MIN(121,$B29-ROUND(Declarations!$A$18/$D$18,0))))+Declarations!$B$19*INDEX(AS$21:AS$141,MAX(1,MIN(121,$B29-ROUND(Declarations!$A$19/$D$18,0))))+Declarations!$B$20*INDEX(AS$21:AS$141,MAX(1,MIN(121,$B29-ROUND(Declarations!$A$20/$D$18,0))))) -> -320.5461 | AU29: =INDEX(AT$21:AT$141,$I29+1)*(1-$J29)+INDEX(AT$21:AT$141,$I29+2)*$J29 -> -323.8599 | AV29: =INDEX(AT$21:AT$141,$K29+1)*(1-$L29)+INDEX(AT$21:AT$141,$K29+2)*$L29 -> -310.97134 | AW29: =$C29+$D29+MAX(AU29,AV29,IF(COUNTIFS($A$21:$A$141,">="&$G29,$A$21:$A$141,"<="&$H29)>0,_xlfn.MAXIFS(AT$21:AT$141,$A$21:$A$141,">="&$G29,$A$21:$A$141,"<="&$H29),AU29)) -> -167.97134 | AX29: =-Cost_k*$A29+Beta_q*(Declarations!$B$16*INDEX(AW$21:AW$141,MAX(1,MIN(121,$B29-ROUND(Declarations!$A$16/$D$18,0))))+Declarations!$B$17*INDEX(AW$21:AW$141,MAX(1,MIN(121,$B29-ROUND(Declarations!$A$17/$D$18,0))))+Declarations!$B$18*INDEX(AW$21:AW$141,MAX(1,MIN(121,$B29-ROUND(Declarations!$A$18/$D$18,0))))+Declarations!$B$19*INDEX(AW$21:AW$141,MAX(1,MIN(121,$B29-ROUND(Declarations!$A$19/$D$18,0))))+Declarations!$B$20*INDEX(AW$21:AW$141,MAX(1,MIN(121,$B29-ROUND(Declarations!$A$20/$D$18,0))))) -> -332.01843 | AY29: =INDEX(AX$21:AX$141,$I29+1)*(1-$J29)+INDEX(AX$21:AX$141,$I29+2)*$J29 -> -335.84434 | AZ29: =INDEX(AX$21:AX$141,$K29+1)*(1-$L29)+INDEX(AX$21:AX$141,$K29+2)*$L29 -> -320.93953 | BA29: =$C29+$D29+MAX(AY29,AZ29,IF(COUNTIFS($A$21:$A$141,">="&$G29,$A$21:$A$141,"<="&$H29)>0,_xlfn.MAXIFS(AX$21:AX$141,$A$21:$A$141,">="&$G29,$A$21:$A$141,"<="&$H29),AY29)) -> -177.93953 | BB29: =-Cost_k*$A29+Beta_q*(Declarations!$B$16*INDEX(BA$21:BA$141,MAX(1,MIN(121,$B29-ROUND(Declarations!$A$16/$D$18,0))))+Declarations!$B$17*INDEX(BA$21:BA$141,MAX(1,MIN(121,$B29-ROUND(Declarations!$A$17/$D$18,0))))+Declarations!$B$18*INDEX(BA$21:BA$141,MAX(1,MIN(121,$B29-ROUND(Declarations!$A$18/$D$18,0))))+Declarations!$B$19*INDEX(BA$21:BA$141,MAX(1,MIN(121,$B29-ROUND(Declarations!$A$19/$D$18,0))))+Declarations!$B$20*INDEX(BA$21:BA$141,MAX(1,MIN(121,$B29-ROUND(Declarations!$A$20/$D$18,0))))) -> -341.75443 | BC29: =INDEX(BB$21:BB$141,$I29+1)*(1-$J29)+INDEX(BB$21:BB$141,$I29+2)*$J29 -> -346.07244 | BD29: =INDEX(BB$21:BB$141,$K29+1)*(1-$L29)+INDEX(BB$21:BB$141,$K29+2)*$L29 -> -329.27619 | BE29: =$C29+$D29+MAX(BC29,BD29,IF(COUNTIFS($A$21:$A$141,">="&$G29,$A$21:$A$141,"<="&$H29)>0,_xlfn.MAXIFS(BB$21:BB$141,$A$21:$A$141,">="&$G29,$A$21:$A$141,"<="&$H29),BC29)) -> -186.27619 | BF29: =-Cost_k*$A29+Beta_q*(Declarations!$B$16*INDEX(BE$21:BE$141,MAX(1,MIN(121,$B29-ROUND(Declarations!$A$16/$D$18,0))))+Declarations!$B$17*INDEX(BE$21:BE$141,MAX(1,MIN(121,$B29-ROUND(Declarations!$A$17/$D$18,0))))+Declarations!$B$18*INDEX(BE$21:BE$141,MAX(1,MIN(121,$B29-ROUND(Declarations!$A$18/$D$18,0))))+Declarations!$B$19*INDEX(BE$21:BE$141,MAX(1,MIN(121,$B29-ROUND(Declarations!$A$19/$D$18,0))))+Declarations!$B$20*INDEX(BE$21:BE$141,MAX(1,MIN(121,$B29-ROUND(Declarations!$A$20/$D$18,0))))) -> -349.90546 | BG29: =INDEX(BF$21:BF$141,$I29+1)*(1-$J29)+INDEX(BF$21:BF$141,$I29+2)*$J29 -> -354.67259 | BH29: =INDEX(BF$21:BF$141,$K29+1)*(1-$L29)+INDEX(BF$21:BF$141,$K29+2)*$L29 -> -336.20762 | BI29: =$C29+$D29+MAX(BG29,BH29,IF(COUNTIFS($A$21:$A$141,">="&$G29,$A$21:$A$141,"<="&$H29)>0,_xlfn.MAXIFS(BF$21:BF$141,$A$21:$A$141,">="&$G29,$A$21:$A$141,"<="&$H29),BG29)) -> -193.20762 | BJ29: -193.20762 | BK29: =ABS(BI29-BJ29) -> 0
A30: =A29+$D$18 -> 42.25 | B30: 10 | C30: =-Short_p*MAX(Floor_c-A30,0) -> -20.4 | D30: =Cost_k*Alpha_keep*A30 -> 164.775 | E30: =MIN(Cap_h,MAX(0,$B$18+MAX(Loss_w)-Alpha_keep*A30)) -> 0.30625 | F30: =MAX(MIN(Cap_h,$F$18+MIN(Loss_w)-Alpha_keep*A30),E30) -> 2.5 | G30: =Alpha_keep*A30+E30 -> 41.5 | H30: =Alpha_keep*A30+F30 -> 43.69375 | I30: =MIN(INT((G30-$B$18)/$D$18+0.000000001),119) -> 6 | J30: =(G30-$B$18)/$D$18-I30 -> 0 | K30: =MIN(INT((H30-$B$18)/$D$18+0.000000001),119) -> 14 | L30: =(H30-$B$18)/$D$18-K30 -> 0.775 | M30: 0 | N30: =-Cost_k*$A30+Beta_q*(Declarations!$B$16*INDEX(M$21:M$141,MAX(1,MIN(121,$B30-ROUND(Declarations!$A$16/$D$18,0))))+Declarations!$B$17*INDEX(M$21:M$141,MAX(1,MIN(121,$B30-ROUND(Declarations!$A$17/$D$18,0))))+Declarations!$B$18*INDEX(M$21:M$141,MAX(1,MIN(121,$B30-ROUND(Declarations!$A$18/$D$18,0))))+Declarations!$B$19*INDEX(M$21:M$141,MAX(1,MIN(121,$B30-ROUND(Declarations!$A$19/$D$18,0))))+Declarations!$B$20*INDEX(M$21:M$141,MAX(1,MIN(121,$B30-ROUND(Declarations!$A$20/$D$18,0))))) -> -169 | O30: =INDEX(N$21:N$141,$I30+1)*(1-$J30)+INDEX(N$21:N$141,$I30+2)*$J30 -> -166 | P30: =INDEX(N$21:N$141,$K30+1)*(1-$L30)+INDEX(N$21:N$141,$K30+2)*$L30 -> -174.775 | Q30: =$C30+$D30+MAX(O30,P30,IF(COUNTIFS($A$21:$A$141,">="&$G30,$A$21:$A$141,"<="&$H30)>0,_xlfn.MAXIFS(N$21:N$141,$A$21:$A$141,">="&$G30,$A$21:$A$141,"<="&$H30),O30)) -> -21.625 | R30: =-Cost_k*$A30+Beta_q*(Declarations!$B$16*INDEX(Q$21:Q$141,MAX(1,MIN(121,$B30-ROUND(Declarations!$A$16/$D$18,0))))+Declarations!$B$17*INDEX(Q$21:Q$141,MAX(1,MIN(121,$B30-ROUND(Declarations!$A$17/$D$18,0))))+Declarations!$B$18*INDEX(Q$21:Q$141,MAX(1,MIN(121,$B30-ROUND(Declarations!$A$18/$D$18,0))))+Declarations!$B$19*INDEX(Q$21:Q$141,MAX(1,MIN(121,$B30-ROUND(Declarations!$A$19/$D$18,0))))+Declarations!$B$20*INDEX(Q$21:Q$141,MAX(1,MIN(121,$B30-ROUND(Declarations!$A$20/$D$18,0))))) -> -190.67362 | S30: =INDEX(R$21:R$141,$I30+1)*(1-$J30)+INDEX(R$21:R$141,$I30+2)*$J30 -> -191.22669 | T30: =INDEX(R$21:R$141,$K30+1)*(1-$L30)+INDEX(R$21:R$141,$K30+2)*$L30 -> -192.50957 | U30: =$C30+$D30+MAX(S30,T30,IF(COUNTIFS($A$21:$A$141,">="&$G30,$A$21:$A$141,"<="&$H30)>0,_xlfn.MAXIFS(R$21:R$141,$A$21:$A$141,">="&$G30,$A$21:$A$141,"<="&$H30),S30)) -> -46.194005 | V30: =-Cost_k*$A30+Beta_q*(Declarations!$B$16*INDEX(U$21:U$141,MAX(1,MIN(121,$B30-ROUND(Declarations!$A$16/$D$18,0))))+Declarations!$B$17*INDEX(U$21:U$141,MAX(1,MIN(121,$B30-ROUND(Declarations!$A$17/$D$18,0))))+Declarations!$B$18*INDEX(U$21:U$141,MAX(1,MIN(121,$B30-ROUND(Declarations!$A$18/$D$18,0))))+Declarations!$B$19*INDEX(U$21:U$141,MAX(1,MIN(121,$B30-ROUND(Declarations!$A$19/$D$18,0))))+Declarations!$B$20*INDEX(U$21:U$141,MAX(1,MIN(121,$B30-ROUND(Declarations!$A$20/$D$18,0))))) -> -214.11942 | W30: =INDEX(V$21:V$141,$I30+1)*(1-$J30)+INDEX(V$21:V$141,$I30+2)*$J30 -> -215.18827 | X30: =INDEX(V$21:V$141,$K30+1)*(1-$L30)+INDEX(V$21:V$141,$K30+2)*$L30 -> -212.55216 | Y30: =$C30+$D30+MAX(W30,X30,IF(COUNTIFS($A$21:$A$141,">="&$G30,$A$21:$A$141,"<="&$H30)>0,_xlfn.MAXIFS(V$21:V$141,$A$21:$A$141,">="&$G30,$A$21:$A$141,"<="&$H30),W30)) -> -68.177158 | Z30: =-Cost_k*$A30+Beta_q*(Declarations!$B$16*INDEX(Y$21:Y$141,MAX(1,MIN(121,$B30-ROUND(Declarations!$A$16/$D$18,0))))+Declarations!$B$17*INDEX(Y$21:Y$141,MAX(1,MIN(121,$B30-ROUND(Declarations!$A$17/$D$18,0))))+Declarations!$B$18*INDEX(Y$21:Y$141,MAX(1,MIN(121,$B30-ROUND(Declarations!$A$18/$D$18,0))))+Declarations!$B$19*INDEX(Y$21:Y$141,MAX(1,MIN(121,$B30-ROUND(Declarations!$A$19/$D$18,0))))+Declarations!$B$20*INDEX(Y$21:Y$141,MAX(1,MIN(121,$B30-ROUND(Declarations!$A$20/$D$18,0))))) -> -235.74946 | AA30: =INDEX(Z$21:Z$141,$I30+1)*(1-$J30)+INDEX(Z$21:Z$141,$I30+2)*$J30 -> -237.35706 | AB30: =INDEX(Z$21:Z$141,$K30+1)*(1-$L30)+INDEX(Z$21:Z$141,$K30+2)*$L30 -> -233.4831 | AC30: =$C30+$D30+MAX(AA30,AB30,IF(COUNTIFS($A$21:$A$141,">="&$G30,$A$21:$A$141,"<="&$H30)>0,_xlfn.MAXIFS(Z$21:Z$141,$A$21:$A$141,">="&$G30,$A$21:$A$141,"<="&$H30),AA30)) -> -89.108103 | AD30: =-Cost_k*$A30+Beta_q*(Declarations!$B$16*INDEX(AC$21:AC$141,MAX(1,MIN(121,$B30-ROUND(Declarations!$A$16/$D$18,0))))+Declarations!$B$17*INDEX(AC$21:AC$141,MAX(1,MIN(121,$B30-ROUND(Declarations!$A$17/$D$18,0))))+Declarations!$B$18*INDEX(AC$21:AC$141,MAX(1,MIN(121,$B30-ROUND(Declarations!$A$18/$D$18,0))))+Declarations!$B$19*INDEX(AC$21:AC$141,MAX(1,MIN(121,$B30-ROUND(Declarations!$A$19/$D$18,0))))+Declarations!$B$20*INDEX(AC$21:AC$141,MAX(1,MIN(121,$B30-ROUND(Declarations!$A$20/$D$18,0))))) -> -256.03958 | AE30: =INDEX(AD$21:AD$141,$I30+1)*(1-$J30)+INDEX(AD$21:AD$141,$I30+2)*$J30 -> -258.14726 | AF30: =INDEX(AD$21:AD$141,$K30+1)*(1-$L30)+INDEX(AD$21:AD$141,$K30+2)*$L30 -> -252.2517 | AG30: =$C30+$D30+MAX(AE30,AF30,IF(COUNTIFS($A$21:$A$141,">="&$G30,$A$21:$A$141,"<="&$H30)>0,_xlfn.MAXIFS(AD$21:AD$141,$A$21:$A$141,">="&$G30,$A$21:$A$141,"<="&$H30),AE30)) -> -107.8767 | AH30: =-Cost_k*$A30+Beta_q*(Declarations!$B$16*INDEX(AG$21:AG$141,MAX(1,MIN(121,$B30-ROUND(Declarations!$A$16/$D$18,0))))+Declarations!$B$17*INDEX(AG$21:AG$141,MAX(1,MIN(121,$B30-ROUND(Declarations!$A$17/$D$18,0))))+Declarations!$B$18*INDEX(AG$21:AG$141,MAX(1,MIN(121,$B30-ROUND(Declarations!$A$18/$D$18,0))))+Declarations!$B$19*INDEX(AG$21:AG$141,MAX(1,MIN(121,$B30-ROUND(Declarations!$A$19/$D$18,0))))+Declarations!$B$20*INDEX(AG$21:AG$141,MAX(1,MIN(121,$B30-ROUND(Declarations!$A$20/$D$18,0))))) -> -274.38522 | AI30: =INDEX(AH$21:AH$141,$I30+1)*(1-$J30)+INDEX(AH$21:AH$141,$I30+2)*$J30 -> -277.23377 | AJ30: =INDEX(AH$21:AH$141,$K30+1)*(1-$L30)+INDEX(AH$21:AH$141,$K30+2)*$L30 -> -269.25706 | AK30: =$C30+$D30+MAX(AI30,AJ30,IF(COUNTIFS($A$21:$A$141,">="&$G30,$A$21:$A$141,"<="&$H30)>0,_xlfn.MAXIFS(AH$21:AH$141,$A$21:$A$141,">="&$G30,$A$21:$A$141,"<="&$H30),AI30)) -> -124.88206 | AL30: =-Cost_k*$A30+Beta_q*(Declarations!$B$16*INDEX(AK$21:AK$141,MAX(1,MIN(121,$B30-ROUND(Declarations!$A$16/$D$18,0))))+Declarations!$B$17*INDEX(AK$21:AK$141,MAX(1,MIN(121,$B30-ROUND(Declarations!$A$17/$D$18,0))))+Declarations!$B$18*INDEX(AK$21:AK$141,MAX(1,MIN(121,$B30-ROUND(Declarations!$A$18/$D$18,0))))+Declarations!$B$19*INDEX(AK$21:AK$141,MAX(1,MIN(121,$B30-ROUND(Declarations!$A$19/$D$18,0))))+Declarations!$B$20*INDEX(AK$21:AK$141,MAX(1,MIN(121,$B30-ROUND(Declarations!$A$20/$D$18,0))))) -> -290.9865 | AM30: =INDEX(AL$21:AL$141,$I30+1)*(1-$J30)+INDEX(AL$21:AL$141,$I30+2)*$J30 -> -294.49319 | AN30: =INDEX(AL$21:AL$141,$K30+1)*(1-$L30)+INDEX(AL$21:AL$141,$K30+2)*$L30 -> -284.51251 | AO30: =$C30+$D30+MAX(AM30,AN30,IF(COUNTIFS($A$21:$A$141,">="&$G30,$A$21:$A$141,"<="&$H30)>0,_xlfn.MAXIFS(AL$21:AL$141,$A$21:$A$141,">="&$G30,$A$21:$A$141,"<="&$H30),AM30)) -> -140.13751 | AP30: =-Cost_k*$A30+Beta_q*(Declarations!$B$16*INDEX(AO$21:AO$141,MAX(1,MIN(121,$B30-ROUND(Declarations!$A$16/$D$18,0))))+Declarations!$B$17*INDEX(AO$21:AO$141,MAX(1,MIN(121,$B30-ROUND(Declarations!$A$17/$D$18,0))))+Declarations!$B$18*INDEX(AO$21:AO$141,MAX(1,MIN(121,$B30-ROUND(Declarations!$A$18/$D$18,0))))+Declarations!$B$19*INDEX(AO$21:AO$141,MAX(1,MIN(121,$B30-ROUND(Declarations!$A$19/$D$18,0))))+Declarations!$B$20*INDEX(AO$21:AO$141,MAX(1,MIN(121,$B30-ROUND(Declarations!$A$20/$D$18,0))))) -> -305.85622 | AQ30: =INDEX(AP$21:AP$141,$I30+1)*(1-$J30)+INDEX(AP$21:AP$141,$I30+2)*$J30 -> -310.06124 | AR30: =INDEX(AP$21:AP$141,$K30+1)*(1-$L30)+INDEX(AP$21:AP$141,$K30+2)*$L30 -> -297.87655 | AS30: =$C30+$D30+MAX(AQ30,AR30,IF(COUNTIFS($A$21:$A$141,">="&$G30,$A$21:$A$141,"<="&$H30)>0,_xlfn.MAXIFS(AP$21:AP$141,$A$21:$A$141,">="&$G30,$A$21:$A$141,"<="&$H30),AQ30)) -> -153.50155 | AT30: =-Cost_k*$A30+Beta_q*(Declarations!$B$16*INDEX(AS$21:AS$141,MAX(1,MIN(121,$B30-ROUND(Declarations!$A$16/$D$18,0))))+Declarations!$B$17*INDEX(AS$21:AS$141,MAX(1,MIN(121,$B30-ROUND(Declarations!$A$17/$D$18,0))))+Declarations!$B$18*INDEX(AS$21:AS$141,MAX(1,MIN(121,$B30-ROUND(Declarations!$A$18/$D$18,0))))+Declarations!$B$19*INDEX(AS$21:AS$141,MAX(1,MIN(121,$B30-ROUND(Declarations!$A$19/$D$18,0))))+Declarations!$B$20*INDEX(AS$21:AS$141,MAX(1,MIN(121,$B30-ROUND(Declarations!$A$20/$D$18,0))))) -> -318.89238 | AU30: =INDEX(AT$21:AT$141,$I30+1)*(1-$J30)+INDEX(AT$21:AT$141,$I30+2)*$J30 -> -323.8599 | AV30: =INDEX(AT$21:AT$141,$K30+1)*(1-$L30)+INDEX(AT$21:AT$141,$K30+2)*$L30 -> -309.36438 | AW30: =$C30+$D30+MAX(AU30,AV30,IF(COUNTIFS($A$21:$A$141,">="&$G30,$A$21:$A$141,"<="&$H30)>0,_xlfn.MAXIFS(AT$21:AT$141,$A$21:$A$141,">="&$G30,$A$21:$A$141,"<="&$H30),AU30)) -> -164.98938 | AX30: =-Cost_k*$A30+Beta_q*(Declarations!$B$16*INDEX(AW$21:AW$141,MAX(1,MIN(121,$B30-ROUND(Declarations!$A$16/$D$18,0))))+Declarations!$B$17*INDEX(AW$21:AW$141,MAX(1,MIN(121,$B30-ROUND(Declarations!$A$17/$D$18,0))))+Declarations!$B$18*INDEX(AW$21:AW$141,MAX(1,MIN(121,$B30-ROUND(Declarations!$A$18/$D$18,0))))+Declarations!$B$19*INDEX(AW$21:AW$141,MAX(1,MIN(121,$B30-ROUND(Declarations!$A$19/$D$18,0))))+Declarations!$B$20*INDEX(AW$21:AW$141,MAX(1,MIN(121,$B30-ROUND(Declarations!$A$20/$D$18,0))))) -> -330.10655 | AY30: =INDEX(AX$21:AX$141,$I30+1)*(1-$J30)+INDEX(AX$21:AX$141,$I30+2)*$J30 -> -335.84434 | AZ30: =INDEX(AX$21:AX$141,$K30+1)*(1-$L30)+INDEX(AX$21:AX$141,$K30+2)*$L30 -> -319.0804 | BA30: =$C30+$D30+MAX(AY30,AZ30,IF(COUNTIFS($A$21:$A$141,">="&$G30,$A$21:$A$141,"<="&$H30)>0,_xlfn.MAXIFS(AX$21:AX$141,$A$21:$A$141,">="&$G30,$A$21:$A$141,"<="&$H30),AY30)) -> -174.7054 | BB30: =-Cost_k*$A30+Beta_q*(Declarations!$B$16*INDEX(BA$21:BA$141,MAX(1,MIN(121,$B30-ROUND(Declarations!$A$16/$D$18,0))))+Declarations!$B$17*INDEX(BA$21:BA$141,MAX(1,MIN(121,$B30-ROUND(Declarations!$A$17/$D$18,0))))+Declarations!$B$18*INDEX(BA$21:BA$141,MAX(1,MIN(121,$B30-ROUND(Declarations!$A$18/$D$18,0))))+Declarations!$B$19*INDEX(BA$21:BA$141,MAX(1,MIN(121,$B30-ROUND(Declarations!$A$19/$D$18,0))))+Declarations!$B$20*INDEX(BA$21:BA$141,MAX(1,MIN(121,$B30-ROUND(Declarations!$A$20/$D$18,0))))) -> -339.59753 | BC30: =INDEX(BB$21:BB$141,$I30+1)*(1-$J30)+INDEX(BB$21:BB$141,$I30+2)*$J30 -> -346.07244 | BD30: =INDEX(BB$21:BB$141,$K30+1)*(1-$L30)+INDEX(BB$21:BB$141,$K30+2)*$L30 -> -327.18972 | BE30: =$C30+$D30+MAX(BC30,BD30,IF(COUNTIFS($A$21:$A$141,">="&$G30,$A$21:$A$141,"<="&$H30)>0,_xlfn.MAXIFS(BB$21:BB$141,$A$21:$A$141,">="&$G30,$A$21:$A$141,"<="&$H30),BC30)) -> -182.81472 | BF30: =-Cost_k*$A30+Beta_q*(Declarations!$B$16*INDEX(BE$21:BE$141,MAX(1,MIN(121,$B30-ROUND(Declarations!$A$16/$D$18,0))))+Declarations!$B$17*INDEX(BE$21:BE$141,MAX(1,MIN(121,$B30-ROUND(Declarations!$A$17/$D$18,0))))+Declarations!$B$18*INDEX(BE$21:BE$141,MAX(1,MIN(121,$B30-ROUND(Declarations!$A$18/$D$18,0))))+Declarations!$B$19*INDEX(BE$21:BE$141,MAX(1,MIN(121,$B30-ROUND(Declarations!$A$19/$D$18,0))))+Declarations!$B$20*INDEX(BE$21:BE$141,MAX(1,MIN(121,$B30-ROUND(Declarations!$A$20/$D$18,0))))) -> -347.52825 | BG30: =INDEX(BF$21:BF$141,$I30+1)*(1-$J30)+INDEX(BF$21:BF$141,$I30+2)*$J30 -> -354.67259 | BH30: =INDEX(BF$21:BF$141,$K30+1)*(1-$L30)+INDEX(BF$21:BF$141,$K30+2)*$L30 -> -333.93295 | BI30: =$C30+$D30+MAX(BG30,BH30,IF(COUNTIFS($A$21:$A$141,">="&$G30,$A$21:$A$141,"<="&$H30)>0,_xlfn.MAXIFS(BF$21:BF$141,$A$21:$A$141,">="&$G30,$A$21:$A$141,"<="&$H30),BG30)) -> -189.55795 | BJ30: -189.55795 | BK30: =ABS(BI30-BJ30) -> 0
A31: =A30+$D$18 -> 42.5 | B31: 11 | C31: =-Short_p*MAX(Floor_c-A31,0) -> -20 | D31: =Cost_k*Alpha_keep*A31 -> 165.75 | E31: =MIN(Cap_h,MAX(0,$B$18+MAX(Loss_w)-Alpha_keep*A31)) -> 0.0625 | F31: =MAX(MIN(Cap_h,$F$18+MIN(Loss_w)-Alpha_keep*A31),E31) -> 2.5 | G31: =Alpha_keep*A31+E31 -> 41.5 | H31: =Alpha_keep*A31+F31 -> 43.9375 | I31: =MIN(INT((G31-$B$18)/$D$18+0.000000001),119) -> 6 | J31: =(G31-$B$18)/$D$18-I31 -> 0 | K31: =MIN(INT((H31-$B$18)/$D$18+0.000000001),119) -> 15 | L31: =(H31-$B$18)/$D$18-K31 -> 0.75 | M31: 0 | N31: =-Cost_k*$A31+Beta_q*(Declarations!$B$16*INDEX(M$21:M$141,MAX(1,MIN(121,$B31-ROUND(Declarations!$A$16/$D$18,0))))+Declarations!$B$17*INDEX(M$21:M$141,MAX(1,MIN(121,$B31-ROUND(Declarations!$A$17/$D$18,0))))+Declarations!$B$18*INDEX(M$21:M$141,MAX(1,MIN(121,$B31-ROUND(Declarations!$A$18/$D$18,0))))+Declarations!$B$19*INDEX(M$21:M$141,MAX(1,MIN(121,$B31-ROUND(Declarations!$A$19/$D$18,0))))+Declarations!$B$20*INDEX(M$21:M$141,MAX(1,MIN(121,$B31-ROUND(Declarations!$A$20/$D$18,0))))) -> -170 | O31: =INDEX(N$21:N$141,$I31+1)*(1-$J31)+INDEX(N$21:N$141,$I31+2)*$J31 -> -166 | P31: =INDEX(N$21:N$141,$K31+1)*(1-$L31)+INDEX(N$21:N$141,$K31+2)*$L31 -> -175.75 | Q31: =$C31+$D31+MAX(O31,P31,IF(COUNTIFS($A$21:$A$141,">="&$G31,$A$21:$A$141,"<="&$H31)>0,_xlfn.MAXIFS(N$21:N$141,$A$21:$A$141,">="&$G31,$A$21:$A$141,"<="&$H31),O31)) -> -20.25 | R31: =-Cost_k*$A31+Beta_q*(Declarations!$B$16*INDEX(Q$21:Q$141,MAX(1,MIN(121,$B31-ROUND(Declarations!$A$16/$D$18,0))))+Declarations!$B$17*INDEX(Q$21:Q$141,MAX(1,MIN(121,$B31-ROUND(Declarations!$A$17/$D$18,0))))+Declarations!$B$18*INDEX(Q$21:Q$141,MAX(1,MIN(121,$B31-ROUND(Declarations!$A$18/$D$18,0))))+Declarations!$B$19*INDEX(Q$21:Q$141,MAX(1,MIN(121,$B31-ROUND(Declarations!$A$19/$D$18,0))))+Declarations!$B$20*INDEX(Q$21:Q$141,MAX(1,MIN(121,$B31-ROUND(Declarations!$A$20/$D$18,0))))) -> -190.56901 | S31: =INDEX(R$21:R$141,$I31+1)*(1-$J31)+INDEX(R$21:R$141,$I31+2)*$J31 -> -191.22669 | T31: =INDEX(R$21:R$141,$K31+1)*(1-$L31)+INDEX(R$21:R$141,$K31+2)*$L31 -> -193.05734 | U31: =$C31+$D31+MAX(S31,T31,IF(COUNTIFS($A$21:$A$141,">="&$G31,$A$21:$A$141,"<="&$H31)>0,_xlfn.MAXIFS(R$21:R$141,$A$21:$A$141,">="&$G31,$A$21:$A$141,"<="&$H31),S31)) -> -44.819005 | V31: =-Cost_k*$A31+Beta_q*(Declarations!$B$16*INDEX(U$21:U$141,MAX(1,MIN(121,$B31-ROUND(Declarations!$A$16/$D$18,0))))+Declarations!$B$17*INDEX(U$21:U$141,MAX(1,MIN(121,$B31-ROUND(Declarations!$A$17/$D$18,0))))+Declarations!$B$18*INDEX(U$21:U$141,MAX(1,MIN(121,$B31-ROUND(Declarations!$A$18/$D$18,0))))+Declarations!$B$19*INDEX(U$21:U$141,MAX(1,MIN(121,$B31-ROUND(Declarations!$A$19/$D$18,0))))+Declarations!$B$20*INDEX(U$21:U$141,MAX(1,MIN(121,$B31-ROUND(Declarations!$A$20/$D$18,0))))) -> -213.78727 | W31: =INDEX(V$21:V$141,$I31+1)*(1-$J31)+INDEX(V$21:V$141,$I31+2)*$J31 -> -215.18827 | X31: =INDEX(V$21:V$141,$K31+1)*(1-$L31)+INDEX(V$21:V$141,$K31+2)*$L31 -> -212.47513 | Y31: =$C31+$D31+MAX(W31,X31,IF(COUNTIFS($A$21:$A$141,">="&$G31,$A$21:$A$141,"<="&$H31)>0,_xlfn.MAXIFS(V$21:V$141,$A$21:$A$141,">="&$G31,$A$21:$A$141,"<="&$H31),W31)) -> -66.725129 | Z31: =-Cost_k*$A31+Beta_q*(Declarations!$B$16*INDEX(Y$21:Y$141,MAX(1,MIN(121,$B31-ROUND(Declarations!$A$16/$D$18,0))))+Declarations!$B$17*INDEX(Y$21:Y$141,MAX(1,MIN(121,$B31-ROUND(Declarations!$A$17/$D$18,0))))+Declarations!$B$18*INDEX(Y$21:Y$141,MAX(1,MIN(121,$B31-ROUND(Declarations!$A$18/$D$18,0))))+Declarations!$B$19*INDEX(Y$21:Y$141,MAX(1,MIN(121,$B31-ROUND(Declarations!$A$19/$D$18,0))))+Declarations!$B$20*INDEX(Y$21:Y$141,MAX(1,MIN(121,$B31-ROUND(Declarations!$A$20/$D$18,0))))) -> -235.30376 | AA31: =INDEX(Z$21:Z$141,$I31+1)*(1-$J31)+INDEX(Z$21:Z$141,$I31+2)*$J31 -> -237.35706 | AB31: =INDEX(Z$21:Z$141,$K31+1)*(1-$L31)+INDEX(Z$21:Z$141,$K31+2)*$L31 -> -233.14471 | AC31: =$C31+$D31+MAX(AA31,AB31,IF(COUNTIFS($A$21:$A$141,">="&$G31,$A$21:$A$141,"<="&$H31)>0,_xlfn.MAXIFS(Z$21:Z$141,$A$21:$A$141,">="&$G31,$A$21:$A$141,"<="&$H31),AA31)) -> -87.394712 | AD31: =-Cost_k*$A31+Beta_q*(Declarations!$B$16*INDEX(AC$21:AC$141,MAX(1,MIN(121,$B31-ROUND(Declarations!$A$16/$D$18,0))))+Declarations!$B$17*INDEX(AC$21:AC$141,MAX(1,MIN(121,$B31-ROUND(Declarations!$A$17/$D$18,0))))+Declarations!$B$18*INDEX(AC$21:AC$141,MAX(1,MIN(121,$B31-ROUND(Declarations!$A$18/$D$18,0))))+Declarations!$B$19*INDEX(AC$21:AC$141,MAX(1,MIN(121,$B31-ROUND(Declarations!$A$19/$D$18,0))))+Declarations!$B$20*INDEX(AC$21:AC$141,MAX(1,MIN(121,$B31-ROUND(Declarations!$A$20/$D$18,0))))) -> -255.36147 | AE31: =INDEX(AD$21:AD$141,$I31+1)*(1-$J31)+INDEX(AD$21:AD$141,$I31+2)*$J31 -> -258.14726 | AF31: =INDEX(AD$21:AD$141,$K31+1)*(1-$L31)+INDEX(AD$21:AD$141,$K31+2)*$L31 -> -251.64954 | AG31: =$C31+$D31+MAX(AE31,AF31,IF(COUNTIFS($A$21:$A$141,">="&$G31,$A$21:$A$141,"<="&$H31)>0,_xlfn.MAXIFS(AD$21:AD$141,$A$21:$A$141,">="&$G31,$A$21:$A$141,"<="&$H31),AE31)) -> -105.89954 | AH31: =-Cost_k*$A31+Beta_q*(Declarations!$B$16*INDEX(AG$21:AG$141,MAX(1,MIN(121,$B31-ROUND(Declarations!$A$16/$D$18,0))))+Declarations!$B$17*INDEX(AG$21:AG$141,MAX(1,MIN(121,$B31-ROUND(Declarations!$A$17/$D$18,0))))+Declarations!$B$18*INDEX(AG$21:AG$141,MAX(1,MIN(121,$B31-ROUND(Declarations!$A$18/$D$18,0))))+Declarations!$B$19*INDEX(AG$21:AG$141,MAX(1,MIN(121,$B31-ROUND(Declarations!$A$19/$D$18,0))))+Declarations!$B$20*INDEX(AG$21:AG$141,MAX(1,MIN(121,$B31-ROUND(Declarations!$A$20/$D$18,0))))) -> -273.46049 | AI31: =INDEX(AH$21:AH$141,$I31+1)*(1-$J31)+INDEX(AH$21:AH$141,$I31+2)*$J31 -> -277.23377 | AJ31: =INDEX(AH$21:AH$141,$K31+1)*(1-$L31)+INDEX(AH$21:AH$141,$K31+2)*$L31 -> -268.44077 | AK31: =$C31+$D31+MAX(AI31,AJ31,IF(COUNTIFS($A$21:$A$141,">="&$G31,$A$21:$A$141,"<="&$H31)>0,_xlfn.MAXIFS(AH$21:AH$141,$A$21:$A$141,">="&$G31,$A$21:$A$141,"<="&$H31),AI31)) -> -122.69077 | AL31: =-Cost_k*$A31+Beta_q*(Declarations!$B$16*INDEX(AK$21:AK$141,MAX(1,MIN(121,$B31-ROUND(Declarations!$A$16/$D$18,0))))+Declarations!$B$17*INDEX(AK$21:AK$141,MAX(1,MIN(121,$B31-ROUND(Declarations!$A$17/$D$18,0))))+Declarations!$B$18*INDEX(AK$21:AK$141,MAX(1,MIN(121,$B31-ROUND(Declarations!$A$18/$D$18,0))))+Declarations!$B$19*INDEX(AK$21:AK$141,MAX(1,MIN(121,$B31-ROUND(Declarations!$A$19/$D$18,0))))+Declarations!$B$20*INDEX(AK$21:AK$141,MAX(1,MIN(121,$B31-ROUND(Declarations!$A$20/$D$18,0))))) -> -289.84282 | AM31: =INDEX(AL$21:AL$141,$I31+1)*(1-$J31)+INDEX(AL$21:AL$141,$I31+2)*$J31 -> -294.49319 | AN31: =INDEX(AL$21:AL$141,$K31+1)*(1-$L31)+INDEX(AL$21:AL$141,$K31+2)*$L31 -> -283.4433 | AO31: =$C31+$D31+MAX(AM31,AN31,IF(COUNTIFS($A$21:$A$141,">="&$G31,$A$21:$A$141,"<="&$H31)>0,_xlfn.MAXIFS(AL$21:AL$141,$A$21:$A$141,">="&$G31,$A$21:$A$141,"<="&$H31),AM31)) -> -137.6933 | AP31: =-Cost_k*$A31+Beta_q*(Declarations!$B$16*INDEX(AO$21:AO$141,MAX(1,MIN(121,$B31-ROUND(Declarations!$A$16/$D$18,0))))+Declarations!$B$17*INDEX(AO$21:AO$141,MAX(1,MIN(121,$B31-ROUND(Declarations!$A$17/$D$18,0))))+Declarations!$B$18*INDEX(AO$21:AO$141,MAX(1,MIN(121,$B31-ROUND(Declarations!$A$18/$D$18,0))))+Declarations!$B$19*INDEX(AO$21:AO$141,MAX(1,MIN(121,$B31-ROUND(Declarations!$A$19/$D$18,0))))+Declarations!$B$20*INDEX(AO$21:AO$141,MAX(1,MIN(121,$B31-ROUND(Declarations!$A$20/$D$18,0))))) -> -304.46631 | AQ31: =INDEX(AP$21:AP$141,$I31+1)*(1-$J31)+INDEX(AP$21:AP$141,$I31+2)*$J31 -> -310.06124 | AR31: =INDEX(AP$21:AP$141,$K31+1)*(1-$L31)+INDEX(AP$21:AP$141,$K31+2)*$L31 -> -296.53665 | AS31: =$C31+$D31+MAX(AQ31,AR31,IF(COUNTIFS($A$21:$A$141,">="&$G31,$A$21:$A$141,"<="&$H31)>0,_xlfn.MAXIFS(AP$21:AP$141,$A$21:$A$141,">="&$G31,$A$21:$A$141,"<="&$H31),AQ31)) -> -150.78665 | AT31: =-Cost_k*$A31+Beta_q*(Declarations!$B$16*INDEX(AS$21:AS$141,MAX(1,MIN(121,$B31-ROUND(Declarations!$A$16/$D$18,0))))+Declarations!$B$17*INDEX(AS$21:AS$141,MAX(1,MIN(121,$B31-ROUND(Declarations!$A$17/$D$18,0))))+Declarations!$B$18*INDEX(AS$21:AS$141,MAX(1,MIN(121,$B31-ROUND(Declarations!$A$18/$D$18,0))))+Declarations!$B$19*INDEX(AS$21:AS$141,MAX(1,MIN(121,$B31-ROUND(Declarations!$A$19/$D$18,0))))+Declarations!$B$20*INDEX(AS$21:AS$141,MAX(1,MIN(121,$B31-ROUND(Declarations!$A$20/$D$18,0))))) -> -317.24023 | AU31: =INDEX(AT$21:AT$141,$I31+1)*(1-$J31)+INDEX(AT$21:AT$141,$I31+2)*$J31 -> -323.8599 | AV31: =INDEX(AT$21:AT$141,$K31+1)*(1-$L31)+INDEX(AT$21:AT$141,$K31+2)*$L31 -> -307.75788 | AW31: =$C31+$D31+MAX(AU31,AV31,IF(COUNTIFS($A$21:$A$141,">="&$G31,$A$21:$A$141,"<="&$H31)>0,_xlfn.MAXIFS(AT$21:AT$141,$A$21:$A$141,">="&$G31,$A$21:$A$141,"<="&$H31),AU31)) -> -162.00788 | AX31: =-Cost_k*$A31+Beta_q*(Declarations!$B$16*INDEX(AW$21:AW$141,MAX(1,MIN(121,$B31-ROUND(Declarations!$A$16/$D$18,0))))+Declarations!$B$17*INDEX(AW$21:AW$141,MAX(1,MIN(121,$B31-ROUND(Declarations!$A$17/$D$18,0))))+Declarations!$B$18*INDEX(AW$21:AW$141,MAX(1,MIN(121,$B31-ROUND(Declarations!$A$18/$D$18,0))))+Declarations!$B$19*INDEX(AW$21:AW$141,MAX(1,MIN(121,$B31-ROUND(Declarations!$A$19/$D$18,0))))+Declarations!$B$20*INDEX(AW$21:AW$141,MAX(1,MIN(121,$B31-ROUND(Declarations!$A$20/$D$18,0))))) -> -328.19529 | AY31: =INDEX(AX$21:AX$141,$I31+1)*(1-$J31)+INDEX(AX$21:AX$141,$I31+2)*$J31 -> -335.84434 | AZ31: =INDEX(AX$21:AX$141,$K31+1)*(1-$L31)+INDEX(AX$21:AX$141,$K31+2)*$L31 -> -317.22264 | BA31: =$C31+$D31+MAX(AY31,AZ31,IF(COUNTIFS($A$21:$A$141,">="&$G31,$A$21:$A$141,"<="&$H31)>0,_xlfn.MAXIFS(AX$21:AX$141,$A$21:$A$141,">="&$G31,$A$21:$A$141,"<="&$H31),AY31)) -> -171.47264 | BB31: =-Cost_k*$A31+Beta_q*(Declarations!$B$16*INDEX(BA$21:BA$141,MAX(1,MIN(121,$B31-ROUND(Declarations!$A$16/$D$18,0))))+Declarations!$B$17*INDEX(BA$21:BA$141,MAX(1,MIN(121,$B31-ROUND(Declarations!$A$17/$D$18,0))))+Declarations!$B$18*INDEX(BA$21:BA$141,MAX(1,MIN(121,$B31-ROUND(Declarations!$A$18/$D$18,0))))+Declarations!$B$19*INDEX(BA$21:BA$141,MAX(1,MIN(121,$B31-ROUND(Declarations!$A$19/$D$18,0))))+Declarations!$B$20*INDEX(BA$21:BA$141,MAX(1,MIN(121,$B31-ROUND(Declarations!$A$20/$D$18,0))))) -> -337.44227 | BC31: =INDEX(BB$21:BB$141,$I31+1)*(1-$J31)+INDEX(BB$21:BB$141,$I31+2)*$J31 -> -346.07244 | BD31: =INDEX(BB$21:BB$141,$K31+1)*(1-$L31)+INDEX(BB$21:BB$141,$K31+2)*$L31 -> -325.10828 | BE31: =$C31+$D31+MAX(BC31,BD31,IF(COUNTIFS($A$21:$A$141,">="&$G31,$A$21:$A$141,"<="&$H31)>0,_xlfn.MAXIFS(BB$21:BB$141,$A$21:$A$141,">="&$G31,$A$21:$A$141,"<="&$H31),BC31)) -> -179.35828 | BF31: =-Cost_k*$A31+Beta_q*(Declarations!$B$16*INDEX(BE$21:BE$141,MAX(1,MIN(121,$B31-ROUND(Declarations!$A$16/$D$18,0))))+Declarations!$B$17*INDEX(BE$21:BE$141,MAX(1,MIN(121,$B31-ROUND(Declarations!$A$17/$D$18,0))))+Declarations!$B$18*INDEX(BE$21:BE$141,MAX(1,MIN(121,$B31-ROUND(Declarations!$A$18/$D$18,0))))+Declarations!$B$19*INDEX(BE$21:BE$141,MAX(1,MIN(121,$B31-ROUND(Declarations!$A$19/$D$18,0))))+Declarations!$B$20*INDEX(BE$21:BE$141,MAX(1,MIN(121,$B31-ROUND(Declarations!$A$20/$D$18,0))))) -> -345.15633 | BG31: =INDEX(BF$21:BF$141,$I31+1)*(1-$J31)+INDEX(BF$21:BF$141,$I31+2)*$J31 -> -354.67259 | BH31: =INDEX(BF$21:BF$141,$K31+1)*(1-$L31)+INDEX(BF$21:BF$141,$K31+2)*$L31 -> -331.66979 | BI31: =$C31+$D31+MAX(BG31,BH31,IF(COUNTIFS($A$21:$A$141,">="&$G31,$A$21:$A$141,"<="&$H31)>0,_xlfn.MAXIFS(BF$21:BF$141,$A$21:$A$141,">="&$G31,$A$21:$A$141,"<="&$H31),BG31)) -> -185.91979 | BJ31: -185.91979 | BK31: =ABS(BI31-BJ31) -> 0
A32: =A31+$D$18 -> 42.75 | B32: 12 | C32: =-Short_p*MAX(Floor_c-A32,0) -> -19.6 | D32: =Cost_k*Alpha_keep*A32 -> 166.725 | E32: =MIN(Cap_h,MAX(0,$B$18+MAX(Loss_w)-Alpha_keep*A32)) -> 0 | F32: =MAX(MIN(Cap_h,$F$18+MIN(Loss_w)-Alpha_keep*A32),E32) -> 2.5 | G32: =Alpha_keep*A32+E32 -> 41.68125 | H32: =Alpha_keep*A32+F32 -> 44.18125 | I32: =MIN(INT((G32-$B$18)/$D$18+0.000000001),119) -> 6 | J32: =(G32-$B$18)/$D$18-I32 -> 0.725 | K32: =MIN(INT((H32-$B$18)/$D$18+0.000000001),119) -> 16 | L32: =(H32-$B$18)/$D$18-K32 -> 0.725 | M32: 0 | N32: =-Cost_k*$A32+Beta_q*(Declarations!$B$16*INDEX(M$21:M$141,MAX(1,MIN(121,$B32-ROUND(Declarations!$A$16/$D$18,0))))+Declarations!$B$17*INDEX(M$21:M$141,MAX(1,MIN(121,$B32-ROUND(Declarations!$A$17/$D$18,0))))+Declarations!$B$18*INDEX(M$21:M$141,MAX(1,MIN(121,$B32-ROUND(Declarations!$A$18/$D$18,0))))+Declarations!$B$19*INDEX(M$21:M$141,MAX(1,MIN(121,$B32-ROUND(Declarations!$A$19/$D$18,0))))+Declarations!$B$20*INDEX(M$21:M$141,MAX(1,MIN(121,$B32-ROUND(Declarations!$A$20/$D$18,0))))) -> -171 | O32: =INDEX(N$21:N$141,$I32+1)*(1-$J32)+INDEX(N$21:N$141,$I32+2)*$J32 -> -166.725 | P32: =INDEX(N$21:N$141,$K32+1)*(1-$L32)+INDEX(N$21:N$141,$K32+2)*$L32 -> -176.725 | Q32: =$C32+$D32+MAX(O32,P32,IF(COUNTIFS($A$21:$A$141,">="&$G32,$A$21:$A$141,"<="&$H32)>0,_xlfn.MAXIFS(N$21:N$141,$A$21:$A$141,">="&$G32,$A$21:$A$141,"<="&$H32),O32)) -> -19.6 | R32: =-Cost_k*$A32+Beta_q*(Declarations!$B$16*INDEX(Q$21:Q$141,MAX(1,MIN(121,$B32-ROUND(Declarations!$A$16/$D$18,0))))+Declarations!$B$17*INDEX(Q$21:Q$141,MAX(1,MIN(121,$B32-ROUND(Declarations!$A$17/$D$18,0))))+Declarations!$B$18*INDEX(Q$21:Q$141,MAX(1,MIN(121,$B32-ROUND(Declarations!$A$18/$D$18,0))))+Declarations!$B$19*INDEX(Q$21:Q$141,MAX(1,MIN(121,$B32-ROUND(Declarations!$A$19/$D$18,0))))+Declarations!$B$20*INDEX(Q$21:Q$141,MAX(1,MIN(121,$B32-ROUND(Declarations!$A$20/$D$18,0))))) -> -190.81836 | S32: =INDEX(R$21:R$141,$I32+1)*(1-$J32)+INDEX(R$21:R$141,$I32+2)*$J32 -> -191.0128 | T32: =INDEX(R$21:R$141,$K32+1)*(1-$L32)+INDEX(R$21:R$141,$K32+2)*$L32 -> -193.63078 | U32: =$C32+$D32+MAX(S32,T32,IF(COUNTIFS($A$21:$A$141,">="&$G32,$A$21:$A$141,"<="&$H32)>0,_xlfn.MAXIFS(R$21:R$141,$A$21:$A$141,">="&$G32,$A$21:$A$141,"<="&$H32),S32)) -> -43.444005 | V32: =-Cost_k*$A32+Beta_q*(Declarations!$B$16*INDEX(U$21:U$141,MAX(1,MIN(121,$B32-ROUND(Declarations!$A$16/$D$18,0))))+Declarations!$B$17*INDEX(U$21:U$141,MAX(1,MIN(121,$B32-ROUND(Declarations!$A$17/$D$18,0))))+Declarations!$B$18*INDEX(U$21:U$141,MAX(1,MIN(121,$B32-ROUND(Declarations!$A$18/$D$18,0))))+Declarations!$B$19*INDEX(U$21:U$141,MAX(1,MIN(121,$B32-ROUND(Declarations!$A$19/$D$18,0))))+Declarations!$B$20*INDEX(U$21:U$141,MAX(1,MIN(121,$B32-ROUND(Declarations!$A$20/$D$18,0))))) -> -213.46181 | W32: =INDEX(V$21:V$141,$I32+1)*(1-$J32)+INDEX(V$21:V$141,$I32+2)*$J32 -> -214.91525 | X32: =INDEX(V$21:V$141,$K32+1)*(1-$L32)+INDEX(V$21:V$141,$K32+2)*$L32 -> -212.43929 | Y32: =$C32+$D32+MAX(W32,X32,IF(COUNTIFS($A$21:$A$141,">="&$G32,$A$21:$A$141,"<="&$H32)>0,_xlfn.MAXIFS(V$21:V$141,$A$21:$A$141,">="&$G32,$A$21:$A$141,"<="&$H32),W32)) -> -65.314295 | Z32: =-Cost_k*$A32+Beta_q*(Declarations!$B$16*INDEX(Y$21:Y$141,MAX(1,MIN(121,$B32-ROUND(Declarations!$A$16/$D$18,0))))+Declarations!$B$17*INDEX(Y$21:Y$141,MAX(1,MIN(121,$B32-ROUND(Declarations!$A$17/$D$18,0))))+Declarations!$B$18*INDEX(Y$21:Y$141,MAX(1,MIN(121,$B32-ROUND(Declarations!$A$18/$D$18,0))))+Declarations!$B$19*INDEX(Y$21:Y$141,MAX(1,MIN(121,$B32-ROUND(Declarations!$A$19/$D$18,0))))+Declarations!$B$20*INDEX(Y$21:Y$141,MAX(1,MIN(121,$B32-ROUND(Declarations!$A$20/$D$18,0))))) -> -234.8811 | AA32: =INDEX(Z$21:Z$141,$I32+1)*(1-$J32)+INDEX(Z$21:Z$141,$I32+2)*$J32 -> -236.94886 | AB32: =INDEX(Z$21:Z$141,$K32+1)*(1-$L32)+INDEX(Z$21:Z$141,$K32+2)*$L32 -> -232.81129 | AC32: =$C32+$D32+MAX(AA32,AB32,IF(COUNTIFS($A$21:$A$141,">="&$G32,$A$21:$A$141,"<="&$H32)>0,_xlfn.MAXIFS(Z$21:Z$141,$A$21:$A$141,">="&$G32,$A$21:$A$141,"<="&$H32),AA32)) -> -85.68629 | AD32: =-Cost_k*$A32+Beta_q*(Declarations!$B$16*INDEX(AC$21:AC$141,MAX(1,MIN(121,$B32-ROUND(Declarations!$A$16/$D$18,0))))+Declarations!$B$17*INDEX(AC$21:AC$141,MAX(1,MIN(121,$B32-ROUND(Declarations!$A$17/$D$18,0))))+Declarations!$B$18*INDEX(AC$21:AC$141,MAX(1,MIN(121,$B32-ROUND(Declarations!$A$18/$D$18,0))))+Declarations!$B$19*INDEX(AC$21:AC$141,MAX(1,MIN(121,$B32-ROUND(Declarations!$A$19/$D$18,0))))+Declarations!$B$20*INDEX(AC$21:AC$141,MAX(1,MIN(121,$B32-ROUND(Declarations!$A$20/$D$18,0))))) -> -254.69207 | AE32: =INDEX(AD$21:AD$141,$I32+1)*(1-$J32)+INDEX(AD$21:AD$141,$I32+2)*$J32 -> -257.62897 | AF32: =INDEX(AD$21:AD$141,$K32+1)*(1-$L32)+INDEX(AD$21:AD$141,$K32+2)*$L32 -> -251.06375 | AG32: =$C32+$D32+MAX(AE32,AF32,IF(COUNTIFS($A$21:$A$141,">="&$G32,$A$21:$A$141,"<="&$H32)>0,_xlfn.MAXIFS(AD$21:AD$141,$A$21:$A$141,">="&$G32,$A$21:$A$141,"<="&$H32),AE32)) -> -103.93875 | AH32: =-Cost_k*$A32+Beta_q*(Declarations!$B$16*INDEX(AG$21:AG$141,MAX(1,MIN(121,$B32-ROUND(Declarations!$A$16/$D$18,0))))+Declarations!$B$17*INDEX(AG$21:AG$141,MAX(1,MIN(121,$B32-ROUND(Declarations!$A$17/$D$18,0))))+Declarations!$B$18*INDEX(AG$21:AG$141,MAX(1,MIN(121,$B32-ROUND(Declarations!$A$18/$D$18,0))))+Declarations!$B$19*INDEX(AG$21:AG$141,MAX(1,MIN(121,$B32-ROUND(Declarations!$A$19/$D$18,0))))+Declarations!$B$20*INDEX(AG$21:AG$141,MAX(1,MIN(121,$B32-ROUND(Declarations!$A$20/$D$18,0))))) -> -272.55013 | AI32: =INDEX(AH$21:AH$141,$I32+1)*(1-$J32)+INDEX(AH$21:AH$141,$I32+2)*$J32 -> -276.53661 | AJ32: =INDEX(AH$21:AH$141,$K32+1)*(1-$L32)+INDEX(AH$21:AH$141,$K32+2)*$L32 -> -267.63573 | AK32: =$C32+$D32+MAX(AI32,AJ32,IF(COUNTIFS($A$21:$A$141,">="&$G32,$A$21:$A$141,"<="&$H32)>0,_xlfn.MAXIFS(AH$21:AH$141,$A$21:$A$141,">="&$G32,$A$21:$A$141,"<="&$H32),AI32)) -> -120.51073 | AL32: =-Cost_k*$A32+Beta_q*(Declarations!$B$16*INDEX(AK$21:AK$141,MAX(1,MIN(121,$B32-ROUND(Declarations!$A$16/$D$18,0))))+Declarations!$B$17*INDEX(AK$21:AK$141,MAX(1,MIN(121,$B32-ROUND(Declarations!$A$17/$D$18,0))))+Declarations!$B$18*INDEX(AK$21:AK$141,MAX(1,MIN(121,$B32-ROUND(Declarations!$A$18/$D$18,0))))+Declarations!$B$19*INDEX(AK$21:AK$141,MAX(1,MIN(121,$B32-ROUND(Declarations!$A$19/$D$18,0))))+Declarations!$B$20*INDEX(AK$21:AK$141,MAX(1,MIN(121,$B32-ROUND(Declarations!$A$20/$D$18,0))))) -> -288.70958 | AM32: =INDEX(AL$21:AL$141,$I32+1)*(1-$J32)+INDEX(AL$21:AL$141,$I32+2)*$J32 -> -293.63647 | AN32: =INDEX(AL$21:AL$141,$K32+1)*(1-$L32)+INDEX(AL$21:AL$141,$K32+2)*$L32 -> -282.37824 | AO32: =$C32+$D32+MAX(AM32,AN32,IF(COUNTIFS($A$21:$A$141,">="&$G32,$A$21:$A$141,"<="&$H32)>0,_xlfn.MAXIFS(AL$21:AL$141,$A$21:$A$141,">="&$G32,$A$21:$A$141,"<="&$H32),AM32)) -> -135.25324 | AP32: =-Cost_k*$A32+Beta_q*(Declarations!$B$16*INDEX(AO$21:AO$141,MAX(1,MIN(121,$B32-ROUND(Declarations!$A$16/$D$18,0))))+Declarations!$B$17*INDEX(AO$21:AO$141,MAX(1,MIN(121,$B32-ROUND(Declarations!$A$17/$D$18,0))))+Declarations!$B$18*INDEX(AO$21:AO$141,MAX(1,MIN(121,$B32-ROUND(Declarations!$A$18/$D$18,0))))+Declarations!$B$19*INDEX(AO$21:AO$141,MAX(1,MIN(121,$B32-ROUND(Declarations!$A$19/$D$18,0))))+Declarations!$B$20*INDEX(AO$21:AO$141,MAX(1,MIN(121,$B32-ROUND(Declarations!$A$20/$D$18,0))))) -> -303.08071 | AQ32: =INDEX(AP$21:AP$141,$I32+1)*(1-$J32)+INDEX(AP$21:AP$141,$I32+2)*$J32 -> -309.0402 | AR32: =INDEX(AP$21:AP$141,$K32+1)*(1-$L32)+INDEX(AP$21:AP$141,$K32+2)*$L32 -> -295.19777 | AS32: =$C32+$D32+MAX(AQ32,AR32,IF(COUNTIFS($A$21:$A$141,">="&$G32,$A$21:$A$141,"<="&$H32)>0,_xlfn.MAXIFS(AP$21:AP$141,$A$21:$A$141,">="&$G32,$A$21:$A$141,"<="&$H32),AQ32)) -> -148.07277 | AT32: =-Cost_k*$A32+Beta_q*(Declarations!$B$16*INDEX(AS$21:AS$141,MAX(1,MIN(121,$B32-ROUND(Declarations!$A$16/$D$18,0))))+Declarations!$B$17*INDEX(AS$21:AS$141,MAX(1,MIN(121,$B32-ROUND(Declarations!$A$17/$D$18,0))))+Declarations!$B$18*INDEX(AS$21:AS$141,MAX(1,MIN(121,$B32-ROUND(Declarations!$A$18/$D$18,0))))+Declarations!$B$19*INDEX(AS$21:AS$141,MAX(1,MIN(121,$B32-ROUND(Declarations!$A$19/$D$18,0))))+Declarations!$B$20*INDEX(AS$21:AS$141,MAX(1,MIN(121,$B32-ROUND(Declarations!$A$20/$D$18,0))))) -> -315.58933 | AU32: =INDEX(AT$21:AT$141,$I32+1)*(1-$J32)+INDEX(AT$21:AT$141,$I32+2)*$J32 -> -322.65776 | AV32: =INDEX(AT$21:AT$141,$K32+1)*(1-$L32)+INDEX(AT$21:AT$141,$K32+2)*$L32 -> -306.15192 | AW32: =$C32+$D32+MAX(AU32,AV32,IF(COUNTIFS($A$21:$A$141,">="&$G32,$A$21:$A$141,"<="&$H32)>0,_xlfn.MAXIFS(AT$21:AT$141,$A$21:$A$141,">="&$G32,$A$21:$A$141,"<="&$H32),AU32)) -> -159.02692 | AX32: =-Cost_k*$A32+Beta_q*(Declarations!$B$16*INDEX(AW$21:AW$141,MAX(1,MIN(121,$B32-ROUND(Declarations!$A$16/$D$18,0))))+Declarations!$B$17*INDEX(AW$21:AW$141,MAX(1,MIN(121,$B32-ROUND(Declarations!$A$17/$D$18,0))))+Declarations!$B$18*INDEX(AW$21:AW$141,MAX(1,MIN(121,$B32-ROUND(Declarations!$A$18/$D$18,0))))+Declarations!$B$19*INDEX(AW$21:AW$141,MAX(1,MIN(121,$B32-ROUND(Declarations!$A$19/$D$18,0))))+Declarations!$B$20*INDEX(AW$21:AW$141,MAX(1,MIN(121,$B32-ROUND(Declarations!$A$20/$D$18,0))))) -> -326.28473 | AY32: =INDEX(AX$21:AX$141,$I32+1)*(1-$J32)+INDEX(AX$21:AX$141,$I32+2)*$J32 -> -334.45715 | AZ32: =INDEX(AX$21:AX$141,$K32+1)*(1-$L32)+INDEX(AX$21:AX$141,$K32+2)*$L32 -> -315.36672 | BA32: =$C32+$D32+MAX(AY32,AZ32,IF(COUNTIFS($A$21:$A$141,">="&$G32,$A$21:$A$141,"<="&$H32)>0,_xlfn.MAXIFS(AX$21:AX$141,$A$21:$A$141,">="&$G32,$A$21:$A$141,"<="&$H32),AY32)) -> -168.24172 | BB32: =-Cost_k*$A32+Beta_q*(Declarations!$B$16*INDEX(BA$21:BA$141,MAX(1,MIN(121,$B32-ROUND(Declarations!$A$16/$D$18,0))))+Declarations!$B$17*INDEX(BA$21:BA$141,MAX(1,MIN(121,$B32-ROUND(Declarations!$A$17/$D$18,0))))+Declarations!$B$18*INDEX(BA$21:BA$141,MAX(1,MIN(121,$B32-ROUND(Declarations!$A$18/$D$18,0))))+Declarations!$B$19*INDEX(BA$21:BA$141,MAX(1,MIN(121,$B32-ROUND(Declarations!$A$19/$D$18,0))))+Declarations!$B$20*INDEX(BA$21:BA$141,MAX(1,MIN(121,$B32-ROUND(Declarations!$A$20/$D$18,0))))) -> -335.28905 | BC32: =INDEX(BB$21:BB$141,$I32+1)*(1-$J32)+INDEX(BB$21:BB$141,$I32+2)*$J32 -> -344.50673 | BD32: =INDEX(BB$21:BB$141,$K32+1)*(1-$L32)+INDEX(BB$21:BB$141,$K32+2)*$L32 -> -323.03241 | BE32: =$C32+$D32+MAX(BC32,BD32,IF(COUNTIFS($A$21:$A$141,">="&$G32,$A$21:$A$141,"<="&$H32)>0,_xlfn.MAXIFS(BB$21:BB$141,$A$21:$A$141,">="&$G32,$A$21:$A$141,"<="&$H32),BC32)) -> -175.90741 | BF32: =-Cost_k*$A32+Beta_q*(Declarations!$B$16*INDEX(BE$21:BE$141,MAX(1,MIN(121,$B32-ROUND(Declarations!$A$16/$D$18,0))))+Declarations!$B$17*INDEX(BE$21:BE$141,MAX(1,MIN(121,$B32-ROUND(Declarations!$A$17/$D$18,0))))+Declarations!$B$18*INDEX(BE$21:BE$141,MAX(1,MIN(121,$B32-ROUND(Declarations!$A$18/$D$18,0))))+Declarations!$B$19*INDEX(BE$21:BE$141,MAX(1,MIN(121,$B32-ROUND(Declarations!$A$19/$D$18,0))))+Declarations!$B$20*INDEX(BE$21:BE$141,MAX(1,MIN(121,$B32-ROUND(Declarations!$A$20/$D$18,0))))) -> -342.79025 | BG32: =INDEX(BF$21:BF$141,$I32+1)*(1-$J32)+INDEX(BF$21:BF$141,$I32+2)*$J32 -> -352.94321 | BH32: =INDEX(BF$21:BF$141,$K32+1)*(1-$L32)+INDEX(BF$21:BF$141,$K32+2)*$L32 -> -329.41917 | BI32: =$C32+$D32+MAX(BG32,BH32,IF(COUNTIFS($A$21:$A$141,">="&$G32,$A$21:$A$141,"<="&$H32)>0,_xlfn.MAXIFS(BF$21:BF$141,$A$21:$A$141,">="&$G32,$A$21:$A$141,"<="&$H32),BG32)) -> -182.29417 | BJ32: -182.29417 | BK32: =ABS(BI32-BJ32) -> 0
A33: =A32+$D$18 -> 43 | B33: 13 | C33: =-Short_p*MAX(Floor_c-A33,0) -> -19.2 | D33: =Cost_k*Alpha_keep*A33 -> 167.7 | E33: =MIN(Cap_h,MAX(0,$B$18+MAX(Loss_w)-Alpha_keep*A33)) -> 0 | F33: =MAX(MIN(Cap_h,$F$18+MIN(Loss_w)-Alpha_keep*A33),E33) -> 2.5 | G33: =Alpha_keep*A33+E33 -> 41.925 | H33: =Alpha_keep*A33+F33 -> 44.425 | I33: =MIN(INT((G33-$B$18)/$D$18+0.000000001),119) -> 7 | J33: =(G33-$B$18)/$D$18-I33 -> 0.7 | K33: =MIN(INT((H33-$B$18)/$D$18+0.000000001),119) -> 17 | L33: =(H33-$B$18)/$D$18-K33 -> 0.7 | M33: 0 | N33: =-Cost_k*$A33+Beta_q*(Declarations!$B$16*INDEX(M$21:M$141,MAX(1,MIN(121,$B33-ROUND(Declarations!$A$16/$D$18,0))))+Declarations!$B$17*INDEX(M$21:M$141,MAX(1,MIN(121,$B33-ROUND(Declarations!$A$17/$D$18,0))))+Declarations!$B$18*INDEX(M$21:M$141,MAX(1,MIN(121,$B33-ROUND(Declarations!$A$18/$D$18,0))))+Declarations!$B$19*INDEX(M$21:M$141,MAX(1,MIN(121,$B33-ROUND(Declarations!$A$19/$D$18,0))))+Declarations!$B$20*INDEX(M$21:M$141,MAX(1,MIN(121,$B33-ROUND(Declarations!$A$20/$D$18,0))))) -> -172 | O33: =INDEX(N$21:N$141,$I33+1)*(1-$J33)+INDEX(N$21:N$141,$I33+2)*$J33 -> -167.7 | P33: =INDEX(N$21:N$141,$K33+1)*(1-$L33)+INDEX(N$21:N$141,$K33+2)*$L33 -> -177.7 | Q33: =$C33+$D33+MAX(O33,P33,IF(COUNTIFS($A$21:$A$141,">="&$G33,$A$21:$A$141,"<="&$H33)>0,_xlfn.MAXIFS(N$21:N$141,$A$21:$A$141,">="&$G33,$A$21:$A$141,"<="&$H33),O33)) -> -19.2 | R33: =-Cost_k*$A33+Beta_q*(Declarations!$B$16*INDEX(Q$21:Q$141,MAX(1,MIN(121,$B33-ROUND(Declarations!$A$16/$D$18,0))))+Declarations!$B$17*INDEX(Q$21:Q$141,MAX(1,MIN(121,$B33-ROUND(Declarations!$A$17/$D$18,0))))+Declarations!$B$18*INDEX(Q$21:Q$141,MAX(1,MIN(121,$B33-ROUND(Declarations!$A$18/$D$18,0))))+Declarations!$B$19*INDEX(Q$21:Q$141,MAX(1,MIN(121,$B33-ROUND(Declarations!$A$19/$D$18,0))))+Declarations!$B$20*INDEX(Q$21:Q$141,MAX(1,MIN(121,$B33-ROUND(Declarations!$A$20/$D$18,0))))) -> -191.18976 | S33: =INDEX(R$21:R$141,$I33+1)*(1-$J33)+INDEX(R$21:R$141,$I33+2)*$J33 -> -190.82426 | T33: =INDEX(R$21:R$141,$K33+1)*(1-$L33)+INDEX(R$21:R$141,$K33+2)*$L33 -> -194.2216 | U33: =$C33+$D33+MAX(S33,T33,IF(COUNTIFS($A$21:$A$141,">="&$G33,$A$21:$A$141,"<="&$H33)>0,_xlfn.MAXIFS(R$21:R$141,$A$21:$A$141,">="&$G33,$A$21:$A$141,"<="&$H33),S33)) -> -42.069005 | V33: =-Cost_k*$A33+Beta_q*(Declarations!$B$16*INDEX(U$21:U$141,MAX(1,MIN(121,$B33-ROUND(Declarations!$A$16/$D$18,0))))+Declarations!$B$17*INDEX(U$21:U$141,MAX(1,MIN(121,$B33-ROUND(Declarations!$A$17/$D$18,0))))+Declarations!$B$18*INDEX(U$21:U$141,MAX(1,MIN(121,$B33-ROUND(Declarations!$A$18/$D$18,0))))+Declarations!$B$19*INDEX(U$21:U$141,MAX(1,MIN(121,$B33-ROUND(Declarations!$A$19/$D$18,0))))+Declarations!$B$20*INDEX(U$21:U$141,MAX(1,MIN(121,$B33-ROUND(Declarations!$A$20/$D$18,0))))) -> -213.1711 | W33: =INDEX(V$21:V$141,$I33+1)*(1-$J33)+INDEX(V$21:V$141,$I33+2)*$J33 -> -214.56518 | X33: =INDEX(V$21:V$141,$K33+1)*(1-$L33)+INDEX(V$21:V$141,$K33+2)*$L33 -> -212.46042 | Y33: =$C33+$D33+MAX(W33,X33,IF(COUNTIFS($A$21:$A$141,">="&$G33,$A$21:$A$141,"<="&$H33)>0,_xlfn.MAXIFS(V$21:V$141,$A$21:$A$141,">="&$G33,$A$21:$A$141,"<="&$H33),W33)) -> -63.931088 | Z33: =-Cost_k*$A33+Beta_q*(Declarations!$B$16*INDEX(Y$21:Y$141,MAX(1,MIN(121,$B33-ROUND(Declarations!$A$16/$D$18,0))))+Declarations!$B$17*INDEX(Y$21:Y$141,MAX(1,MIN(121,$B33-ROUND(Declarations!$A$17/$D$18,0))))+Declarations!$B$18*INDEX(Y$21:Y$141,MAX(1,MIN(121,$B33-ROUND(Declarations!$A$18/$D$18,0))))+Declarations!$B$19*INDEX(Y$21:Y$141,MAX(1,MIN(121,$B33-ROUND(Declarations!$A$19/$D$18,0))))+Declarations!$B$20*INDEX(Y$21:Y$141,MAX(1,MIN(121,$B33-ROUND(Declarations!$A$20/$D$18,0))))) -> -234.48767 | AA33: =INDEX(Z$21:Z$141,$I33+1)*(1-$J33)+INDEX(Z$21:Z$141,$I33+2)*$J33 -> -236.41178 | AB33: =INDEX(Z$21:Z$141,$K33+1)*(1-$L33)+INDEX(Z$21:Z$141,$K33+2)*$L33 -> -232.48174 | AC33: =$C33+$D33+MAX(AA33,AB33,IF(COUNTIFS($A$21:$A$141,">="&$G33,$A$21:$A$141,"<="&$H33)>0,_xlfn.MAXIFS(Z$21:Z$141,$A$21:$A$141,">="&$G33,$A$21:$A$141,"<="&$H33),AA33)) -> -83.981736 | AD33: =-Cost_k*$A33+Beta_q*(Declarations!$B$16*INDEX(AC$21:AC$141,MAX(1,MIN(121,$B33-ROUND(Declarations!$A$16/$D$18,0))))+Declarations!$B$17*INDEX(AC$21:AC$141,MAX(1,MIN(121,$B33-ROUND(Declarations!$A$17/$D$18,0))))+Declarations!$B$18*INDEX(AC$21:AC$141,MAX(1,MIN(121,$B33-ROUND(Declarations!$A$18/$D$18,0))))+Declarations!$B$19*INDEX(AC$21:AC$141,MAX(1,MIN(121,$B33-ROUND(Declarations!$A$19/$D$18,0))))+Declarations!$B$20*INDEX(AC$21:AC$141,MAX(1,MIN(121,$B33-ROUND(Declarations!$A$20/$D$18,0))))) -> -254.03115 | AE33: =INDEX(AD$21:AD$141,$I33+1)*(1-$J33)+INDEX(AD$21:AD$141,$I33+2)*$J33 -> -256.94038 | AF33: =INDEX(AD$21:AD$141,$K33+1)*(1-$L33)+INDEX(AD$21:AD$141,$K33+2)*$L33 -> -250.49825 | AG33: =$C33+$D33+MAX(AE33,AF33,IF(COUNTIFS($A$21:$A$141,">="&$G33,$A$21:$A$141,"<="&$H33)>0,_xlfn.MAXIFS(AD$21:AD$141,$A$21:$A$141,">="&$G33,$A$21:$A$141,"<="&$H33),AE33)) -> -101.99825 | AH33: =-Cost_k*$A33+Beta_q*(Declarations!$B$16*INDEX(AG$21:AG$141,MAX(1,MIN(121,$B33-ROUND(Declarations!$A$16/$D$18,0))))+Declarations!$B$17*INDEX(AG$21:AG$141,MAX(1,MIN(121,$B33-ROUND(Declarations!$A$17/$D$18,0))))+Declarations!$B$18*INDEX(AG$21:AG$141,MAX(1,MIN(121,$B33-ROUND(Declarations!$A$18/$D$18,0))))+Declarations!$B$19*INDEX(AG$21:AG$141,MAX(1,MIN(121,$B33-ROUND(Declarations!$A$19/$D$18,0))))+Declarations!$B$20*INDEX(AG$21:AG$141,MAX(1,MIN(121,$B33-ROUND(Declarations!$A$20/$D$18,0))))) -> -271.65674 | AI33: =INDEX(AH$21:AH$141,$I33+1)*(1-$J33)+INDEX(AH$21:AH$141,$I33+2)*$J33 -> -275.60711 | AJ33: =INDEX(AH$21:AH$141,$K33+1)*(1-$L33)+INDEX(AH$21:AH$141,$K33+2)*$L33 -> -266.84128 | AK33: =$C33+$D33+MAX(AI33,AJ33,IF(COUNTIFS($A$21:$A$141,">="&$G33,$A$21:$A$141,"<="&$H33)>0,_xlfn.MAXIFS(AH$21:AH$141,$A$21:$A$141,">="&$G33,$A$21:$A$141,"<="&$H33),AI33)) -> -118.34128 | AL33: =-Cost_k*$A33+Beta_q*(Declarations!$B$16*INDEX(AK$21:AK$141,MAX(1,MIN(121,$B33-ROUND(Declarations!$A$16/$D$18,0))))+Declarations!$B$17*INDEX(AK$21:AK$141,MAX(1,MIN(121,$B33-ROUND(Declarations!$A$17/$D$18,0))))+Declarations!$B$18*INDEX(AK$21:AK$141,MAX(1,MIN(121,$B33-ROUND(Declarations!$A$18/$D$18,0))))+Declarations!$B$19*INDEX(AK$21:AK$141,MAX(1,MIN(121,$B33-ROUND(Declarations!$A$19/$D$18,0))))+Declarations!$B$20*INDEX(AK$21:AK$141,MAX(1,MIN(121,$B33-ROUND(Declarations!$A$20/$D$18,0))))) -> -287.58647 | AM33: =INDEX(AL$21:AL$141,$I33+1)*(1-$J33)+INDEX(AL$21:AL$141,$I33+2)*$J33 -> -292.49307 | AN33: =INDEX(AL$21:AL$141,$K33+1)*(1-$L33)+INDEX(AL$21:AL$141,$K33+2)*$L33 -> -281.31632 | AO33: =$C33+$D33+MAX(AM33,AN33,IF(COUNTIFS($A$21:$A$141,">="&$G33,$A$21:$A$141,"<="&$H33)>0,_xlfn.MAXIFS(AL$21:AL$141,$A$21:$A$141,">="&$G33,$A$21:$A$141,"<="&$H33),AM33)) -> -132.81632 | AP33: =-Cost_k*$A33+Beta_q*(Declarations!$B$16*INDEX(AO$21:AO$141,MAX(1,MIN(121,$B33-ROUND(Declarations!$A$16/$D$18,0))))+Declarations!$B$17*INDEX(AO$21:AO$141,MAX(1,MIN(121,$B33-ROUND(Declarations!$A$17/$D$18,0))))+Declarations!$B$18*INDEX(AO$21:AO$141,MAX(1,MIN(121,$B33-ROUND(Declarations!$A$18/$D$18,0))))+Declarations!$B$19*INDEX(AO$21:AO$141,MAX(1,MIN(121,$B33-ROUND(Declarations!$A$19/$D$18,0))))+Declarations!$B$20*INDEX(AO$21:AO$141,MAX(1,MIN(121,$B33-ROUND(Declarations!$A$20/$D$18,0))))) -> -301.69859 | AQ33: =INDEX(AP$21:AP$141,$I33+1)*(1-$J33)+INDEX(AP$21:AP$141,$I33+2)*$J33 -> -307.67193 | AR33: =INDEX(AP$21:AP$141,$K33+1)*(1-$L33)+INDEX(AP$21:AP$141,$K33+2)*$L33 -> -293.85964 | AS33: =$C33+$D33+MAX(AQ33,AR33,IF(COUNTIFS($A$21:$A$141,">="&$G33,$A$21:$A$141,"<="&$H33)>0,_xlfn.MAXIFS(AP$21:AP$141,$A$21:$A$141,">="&$G33,$A$21:$A$141,"<="&$H33),AQ33)) -> -145.35964 | AT33: =-Cost_k*$A33+Beta_q*(Declarations!$B$16*INDEX(AS$21:AS$141,MAX(1,MIN(121,$B33-ROUND(Declarations!$A$16/$D$18,0))))+Declarations!$B$17*INDEX(AS$21:AS$141,MAX(1,MIN(121,$B33-ROUND(Declarations!$A$17/$D$18,0))))+Declarations!$B$18*INDEX(AS$21:AS$141,MAX(1,MIN(121,$B33-ROUND(Declarations!$A$18/$D$18,0))))+Declarations!$B$19*INDEX(AS$21:AS$141,MAX(1,MIN(121,$B33-ROUND(Declarations!$A$19/$D$18,0))))+Declarations!$B$20*INDEX(AS$21:AS$141,MAX(1,MIN(121,$B33-ROUND(Declarations!$A$20/$D$18,0))))) -> -313.93937 | AU33: =INDEX(AT$21:AT$141,$I33+1)*(1-$J33)+INDEX(AT$21:AT$141,$I33+2)*$J33 -> -321.0428 | AV33: =INDEX(AT$21:AT$141,$K33+1)*(1-$L33)+INDEX(AT$21:AT$141,$K33+2)*$L33 -> -304.54648 | AW33: =$C33+$D33+MAX(AU33,AV33,IF(COUNTIFS($A$21:$A$141,">="&$G33,$A$21:$A$141,"<="&$H33)>0,_xlfn.MAXIFS(AT$21:AT$141,$A$21:$A$141,">="&$G33,$A$21:$A$141,"<="&$H33),AU33)) -> -156.04648 | AX33: =-Cost_k*$A33+Beta_q*(Declarations!$B$16*INDEX(AW$21:AW$141,MAX(1,MIN(121,$B33-ROUND(Declarations!$A$16/$D$18,0))))+Declarations!$B$17*INDEX(AW$21:AW$141,MAX(1,MIN(121,$B33-ROUND(Declarations!$A$17/$D$18,0))))+Declarations!$B$18*INDEX(AW$21:AW$141,MAX(1,MIN(121,$B33-ROUND(Declarations!$A$18/$D$18,0))))+Declarations!$B$19*INDEX(AW$21:AW$141,MAX(1,MIN(121,$B33-ROUND(Declarations!$A$19/$D$18,0))))+Declarations!$B$20*INDEX(AW$21:AW$141,MAX(1,MIN(121,$B33-ROUND(Declarations!$A$20/$D$18,0))))) -> -324.37493 | AY33: =INDEX(AX$21:AX$141,$I33+1)*(1-$J33)+INDEX(AX$21:AX$141,$I33+2)*$J33 -> -332.59219 | AZ33: =INDEX(AX$21:AX$141,$K33+1)*(1-$L33)+INDEX(AX$21:AX$141,$K33+2)*$L33 -> -313.51332 | BA33: =$C33+$D33+MAX(AY33,AZ33,IF(COUNTIFS($A$21:$A$141,">="&$G33,$A$21:$A$141,"<="&$H33)>0,_xlfn.MAXIFS(AX$21:AX$141,$A$21:$A$141,">="&$G33,$A$21:$A$141,"<="&$H33),AY33)) -> -165.01332 | BB33: =-Cost_k*$A33+Beta_q*(Declarations!$B$16*INDEX(BA$21:BA$141,MAX(1,MIN(121,$B33-ROUND(Declarations!$A$16/$D$18,0))))+Declarations!$B$17*INDEX(BA$21:BA$141,MAX(1,MIN(121,$B33-ROUND(Declarations!$A$17/$D$18,0))))+Declarations!$B$18*INDEX(BA$21:BA$141,MAX(1,MIN(121,$B33-ROUND(Declarations!$A$18/$D$18,0))))+Declarations!$B$19*INDEX(BA$21:BA$141,MAX(1,MIN(121,$B33-ROUND(Declarations!$A$19/$D$18,0))))+Declarations!$B$20*INDEX(BA$21:BA$141,MAX(1,MIN(121,$B33-ROUND(Declarations!$A$20/$D$18,0))))) -> -333.1386 | BC33: =INDEX(BB$21:BB$141,$I33+1)*(1-$J33)+INDEX(BB$21:BB$141,$I33+2)*$J33 -> -342.40196 | BD33: =INDEX(BB$21:BB$141,$K33+1)*(1-$L33)+INDEX(BB$21:BB$141,$K33+2)*$L33 -> -320.96349 | BE33: =$C33+$D33+MAX(BC33,BD33,IF(COUNTIFS($A$21:$A$141,">="&$G33,$A$21:$A$141,"<="&$H33)>0,_xlfn.MAXIFS(BB$21:BB$141,$A$21:$A$141,">="&$G33,$A$21:$A$141,"<="&$H33),BC33)) -> -172.46349 | BF33: =-Cost_k*$A33+Beta_q*(Declarations!$B$16*INDEX(BE$21:BE$141,MAX(1,MIN(121,$B33-ROUND(Declarations!$A$16/$D$18,0))))+Declarations!$B$17*INDEX(BE$21:BE$141,MAX(1,MIN(121,$B33-ROUND(Declarations!$A$17/$D$18,0))))+Declarations!$B$18*INDEX(BE$21:BE$141,MAX(1,MIN(121,$B33-ROUND(Declarations!$A$18/$D$18,0))))+Declarations!$B$19*INDEX(BE$21:BE$141,MAX(1,MIN(121,$B33-ROUND(Declarations!$A$19/$D$18,0))))+Declarations!$B$20*INDEX(BE$21:BE$141,MAX(1,MIN(121,$B33-ROUND(Declarations!$A$20/$D$18,0))))) -> -340.43132 | BG33: =INDEX(BF$21:BF$141,$I33+1)*(1-$J33)+INDEX(BF$21:BF$141,$I33+2)*$J33 -> -350.62 | BH33: =INDEX(BF$21:BF$141,$K33+1)*(1-$L33)+INDEX(BF$21:BF$141,$K33+2)*$L33 -> -327.18247 | BI33: =$C33+$D33+MAX(BG33,BH33,IF(COUNTIFS($A$21:$A$141,">="&$G33,$A$21:$A$141,"<="&$H33)>0,_xlfn.MAXIFS(BF$21:BF$141,$A$21:$A$141,">="&$G33,$A$21:$A$141,"<="&$H33),BG33)) -> -178.68247 | BJ33: -178.68247 | BK33: =ABS(BI33-BJ33) -> 0
... A141: =A140+$D$18 -> 70 | B141: 121 | C141: =-Short_p*MAX(Floor_c-A141,0) -> 0 | D141: =Cost_k*Alpha_keep*A141 -> 273 | E141: =MIN(Cap_h,MAX(0,$B$18+MAX(Loss_w)-Alpha_keep*A141)) -> 0 | F141: =MAX(MIN(Cap_h,$F$18+MIN(Loss_w)-Alpha_keep*A141),E141) -> 0.25 | G141: =Alpha_keep*A141+E141 -> 68.25 | H141: =Alpha_keep*A141+F141 -> 68.5 | I141: =MIN(INT((G141-$B$18)/$D$18+0.000000001),119) -> 113 | J141: =(G141-$B$18)/$D$18-I141 -> 0 | K141: =MIN(INT((H141-$B$18)/$D$18+0.000000001),119) -> 114 | L141: =(H141-$B$18)/$D$18-K141 -> 0 | M141: 0 | N141: =-Cost_k*$A141+Beta_q*(Declarations!$B$16*INDEX(M$21:M$141,MAX(1,MIN(121,$B141-ROUND(Declarations!$A$16/$D$18,0))))+Declarations!$B$17*INDEX(M$21:M$141,MAX(1,MIN(121,$B141-ROUND(Declarations!$A$17/$D$18,0))))+Declarations!$B$18*INDEX(M$21:M$141,MAX(1,MIN(121,$B141-ROUND(Declarations!$A$18/$D$18,0))))+Declarations!$B$19*INDEX(M$21:M$141,MAX(1,MIN(121,$B141-ROUND(Declarations!$A$19/$D$18,0))))+Declarations!$B$20*INDEX(M$21:M$141,MAX(1,MIN(121,$B141-ROUND(Declarations!$A$20/$D$18,0))))) -> -280 | O141: =INDEX(N$21:N$141,$I141+1)*(1-$J141)+INDEX(N$21:N$141,$I141+2)*$J141 -> -273 | P141: =INDEX(N$21:N$141,$K141+1)*(1-$L141)+INDEX(N$21:N$141,$K141+2)*$L141 -> -274 | Q141: =$C141+$D141+MAX(O141,P141,IF(COUNTIFS($A$21:$A$141,">="&$G141,$A$21:$A$141,"<="&$H141)>0,_xlfn.MAXIFS(N$21:N$141,$A$21:$A$141,">="&$G141,$A$21:$A$141,"<="&$H141),O141)) -> 0 | R141: =-Cost_k*$A141+Beta_q*(Declarations!$B$16*INDEX(Q$21:Q$141,MAX(1,MIN(121,$B141-ROUND(Declarations!$A$16/$D$18,0))))+Declarations!$B$17*INDEX(Q$21:Q$141,MAX(1,MIN(121,$B141-ROUND(Declarations!$A$17/$D$18,0))))+Declarations!$B$18*INDEX(Q$21:Q$141,MAX(1,MIN(121,$B141-ROUND(Declarations!$A$18/$D$18,0))))+Declarations!$B$19*INDEX(Q$21:Q$141,MAX(1,MIN(121,$B141-ROUND(Declarations!$A$19/$D$18,0))))+Declarations!$B$20*INDEX(Q$21:Q$141,MAX(1,MIN(121,$B141-ROUND(Declarations!$A$20/$D$18,0))))) -> -280 | S141: =INDEX(R$21:R$141,$I141+1)*(1-$J141)+INDEX(R$21:R$141,$I141+2)*$J141 -> -273 | T141: =INDEX(R$21:R$141,$K141+1)*(1-$L141)+INDEX(R$21:R$141,$K141+2)*$L141 -> -274 | U141: =$C141+$D141+MAX(S141,T141,IF(COUNTIFS($A$21:$A$141,">="&$G141,$A$21:$A$141,"<="&$H141)>0,_xlfn.MAXIFS(R$21:R$141,$A$21:$A$141,">="&$G141,$A$21:$A$141,"<="&$H141),S141)) -> 0 | V141: =-Cost_k*$A141+Beta_q*(Declarations!$B$16*INDEX(U$21:U$141,MAX(1,MIN(121,$B141-ROUND(Declarations!$A$16/$D$18,0))))+Declarations!$B$17*INDEX(U$21:U$141,MAX(1,MIN(121,$B141-ROUND(Declarations!$A$17/$D$18,0))))+Declarations!$B$18*INDEX(U$21:U$141,MAX(1,MIN(121,$B141-ROUND(Declarations!$A$18/$D$18,0))))+Declarations!$B$19*INDEX(U$21:U$141,MAX(1,MIN(121,$B141-ROUND(Declarations!$A$19/$D$18,0))))+Declarations!$B$20*INDEX(U$21:U$141,MAX(1,MIN(121,$B141-ROUND(Declarations!$A$20/$D$18,0))))) -> -280 | W141: =INDEX(V$21:V$141,$I141+1)*(1-$J141)+INDEX(V$21:V$141,$I141+2)*$J141 -> -273 | X141: =INDEX(V$21:V$141,$K141+1)*(1-$L141)+INDEX(V$21:V$141,$K141+2)*$L141 -> -274 | Y141: =$C141+$D141+MAX(W141,X141,IF(COUNTIFS($A$21:$A$141,">="&$G141,$A$21:$A$141,"<="&$H141)>0,_xlfn.MAXIFS(V$21:V$141,$A$21:$A$141,">="&$G141,$A$21:$A$141,"<="&$H141),W141)) -> 0 | Z141: =-Cost_k*$A141+Beta_q*(Declarations!$B$16*INDEX(Y$21:Y$141,MAX(1,MIN(121,$B141-ROUND(Declarations!$A$16/$D$18,0))))+Declarations!$B$17*INDEX(Y$21:Y$141,MAX(1,MIN(121,$B141-ROUND(Declarations!$A$17/$D$18,0))))+Declarations!$B$18*INDEX(Y$21:Y$141,MAX(1,MIN(121,$B141-ROUND(Declarations!$A$18/$D$18,0))))+Declarations!$B$19*INDEX(Y$21:Y$141,MAX(1,MIN(121,$B141-ROUND(Declarations!$A$19/$D$18,0))))+Declarations!$B$20*INDEX(Y$21:Y$141,MAX(1,MIN(121,$B141-ROUND(Declarations!$A$20/$D$18,0))))) -> -280 | AA141: =INDEX(Z$21:Z$141,$I141+1)*(1-$J141)+INDEX(Z$21:Z$141,$I141+2)*$J141 -> -273 | AB141: =INDEX(Z$21:Z$141,$K141+1)*(1-$L141)+INDEX(Z$21:Z$141,$K141+2)*$L141 -> -274 | AC141: =$C141+$D141+MAX(AA141,AB141,IF(COUNTIFS($A$21:$A$141,">="&$G141,$A$21:$A$141,"<="&$H141)>0,_xlfn.MAXIFS(Z$21:Z$141,$A$21:$A$141,">="&$G141,$A$21:$A$141,"<="&$H141),AA141)) -> 0 | AD141: =-Cost_k*$A141+Beta_q*(Declarations!$B$16*INDEX(AC$21:AC$141,MAX(1,MIN(121,$B141-ROUND(Declarations!$A$16/$D$18,0))))+Declarations!$B$17*INDEX(AC$21:AC$141,MAX(1,MIN(121,$B141-ROUND(Declarations!$A$17/$D$18,0))))+Declarations!$B$18*INDEX(AC$21:AC$141,MAX(1,MIN(121,$B141-ROUND(Declarations!$A$18/$D$18,0))))+Declarations!$B$19*INDEX(AC$21:AC$141,MAX(1,MIN(121,$B141-ROUND(Declarations!$A$19/$D$18,0))))+Declarations!$B$20*INDEX(AC$21:AC$141,MAX(1,MIN(121,$B141-ROUND(Declarations!$A$20/$D$18,0))))) -> -280 | AE141: =INDEX(AD$21:AD$141,$I141+1)*(1-$J141)+INDEX(AD$21:AD$141,$I141+2)*$J141 -> -273 | AF141: =INDEX(AD$21:AD$141,$K141+1)*(1-$L141)+INDEX(AD$21:AD$141,$K141+2)*$L141 -> -274 | AG141: =$C141+$D141+MAX(AE141,AF141,IF(COUNTIFS($A$21:$A$141,">="&$G141,$A$21:$A$141,"<="&$H141)>0,_xlfn.MAXIFS(AD$21:AD$141,$A$21:$A$141,">="&$G141,$A$21:$A$141,"<="&$H141),AE141)) -> 0 | AH141: =-Cost_k*$A141+Beta_q*(Declarations!$B$16*INDEX(AG$21:AG$141,MAX(1,MIN(121,$B141-ROUND(Declarations!$A$16/$D$18,0))))+Declarations!$B$17*INDEX(AG$21:AG$141,MAX(1,MIN(121,$B141-ROUND(Declarations!$A$17/$D$18,0))))+Declarations!$B$18*INDEX(AG$21:AG$141,MAX(1,MIN(121,$B141-ROUND(Declarations!$A$18/$D$18,0))))+Declarations!$B$19*INDEX(AG$21:AG$141,MAX(1,MIN(121,$B141-ROUND(Declarations!$A$19/$D$18,0))))+Declarations!$B$20*INDEX(AG$21:AG$141,MAX(1,MIN(121,$B141-ROUND(Declarations!$A$20/$D$18,0))))) -> -280 | AI141: =INDEX(AH$21:AH$141,$I141+1)*(1-$J141)+INDEX(AH$21:AH$141,$I141+2)*$J141 -> -273 | AJ141: =INDEX(AH$21:AH$141,$K141+1)*(1-$L141)+INDEX(AH$21:AH$141,$K141+2)*$L141 -> -274 | AK141: =$C141+$D141+MAX(AI141,AJ141,IF(COUNTIFS($A$21:$A$141,">="&$G141,$A$21:$A$141,"<="&$H141)>0,_xlfn.MAXIFS(AH$21:AH$141,$A$21:$A$141,">="&$G141,$A$21:$A$141,"<="&$H141),AI141)) -> -2.3590991e-07 | AL141: =-Cost_k*$A141+Beta_q*(Declarations!$B$16*INDEX(AK$21:AK$141,MAX(1,MIN(121,$B141-ROUND(Declarations!$A$16/$D$18,0))))+Declarations!$B$17*INDEX(AK$21:AK$141,MAX(1,MIN(121,$B141-ROUND(Declarations!$A$17/$D$18,0))))+Declarations!$B$18*INDEX(AK$21:AK$141,MAX(1,MIN(121,$B141-ROUND(Declarations!$A$18/$D$18,0))))+Declarations!$B$19*INDEX(AK$21:AK$141,MAX(1,MIN(121,$B141-ROUND(Declarations!$A$19/$D$18,0))))+Declarations!$B$20*INDEX(AK$21:AK$141,MAX(1,MIN(121,$B141-ROUND(Declarations!$A$20/$D$18,0))))) -> -280 | AM141: =INDEX(AL$21:AL$141,$I141+1)*(1-$J141)+INDEX(AL$21:AL$141,$I141+2)*$J141 -> -273.00027 | AN141: =INDEX(AL$21:AL$141,$K141+1)*(1-$L141)+INDEX(AL$21:AL$141,$K141+2)*$L141 -> -274.00016 | AO141: =$C141+$D141+MAX(AM141,AN141,IF(COUNTIFS($A$21:$A$141,">="&$G141,$A$21:$A$141,"<="&$H141)>0,_xlfn.MAXIFS(AL$21:AL$141,$A$21:$A$141,">="&$G141,$A$21:$A$141,"<="&$H141),AM141)) -> -0.00027280599 | AP141: =-Cost_k*$A141+Beta_q*(Declarations!$B$16*INDEX(AO$21:AO$141,MAX(1,MIN(121,$B141-ROUND(Declarations!$A$16/$D$18,0))))+Declarations!$B$17*INDEX(AO$21:AO$141,MAX(1,MIN(121,$B141-ROUND(Declarations!$A$17/$D$18,0))))+Declarations!$B$18*INDEX(AO$21:AO$141,MAX(1,MIN(121,$B141-ROUND(Declarations!$A$18/$D$18,0))))+Declarations!$B$19*INDEX(AO$21:AO$141,MAX(1,MIN(121,$B141-ROUND(Declarations!$A$19/$D$18,0))))+Declarations!$B$20*INDEX(AO$21:AO$141,MAX(1,MIN(121,$B141-ROUND(Declarations!$A$20/$D$18,0))))) -> -280.00069 | AQ141: =INDEX(AP$21:AP$141,$I141+1)*(1-$J141)+INDEX(AP$21:AP$141,$I141+2)*$J141 -> -273.01194 | AR141: =INDEX(AP$21:AP$141,$K141+1)*(1-$L141)+INDEX(AP$21:AP$141,$K141+2)*$L141 -> -274.00832 | AS141: =$C141+$D141+MAX(AQ141,AR141,IF(COUNTIFS($A$21:$A$141,">="&$G141,$A$21:$A$141,"<="&$H141)>0,_xlfn.MAXIFS(AP$21:AP$141,$A$21:$A$141,">="&$G141,$A$21:$A$141,"<="&$H141),AQ141)) -> -0.011937605 | AT141: =-Cost_k*$A141+Beta_q*(Declarations!$B$16*INDEX(AS$21:AS$141,MAX(1,MIN(121,$B141-ROUND(Declarations!$A$16/$D$18,0))))+Declarations!$B$17*INDEX(AS$21:AS$141,MAX(1,MIN(121,$B141-ROUND(Declarations!$A$17/$D$18,0))))+Declarations!$B$18*INDEX(AS$21:AS$141,MAX(1,MIN(121,$B141-ROUND(Declarations!$A$18/$D$18,0))))+Declarations!$B$19*INDEX(AS$21:AS$141,MAX(1,MIN(121,$B141-ROUND(Declarations!$A$19/$D$18,0))))+Declarations!$B$20*INDEX(AS$21:AS$141,MAX(1,MIN(121,$B141-ROUND(Declarations!$A$20/$D$18,0))))) -> -280.01932 | AU141: =INDEX(AT$21:AT$141,$I141+1)*(1-$J141)+INDEX(AT$21:AT$141,$I141+2)*$J141 -> -273.13396 | AV141: =INDEX(AT$21:AT$141,$K141+1)*(1-$L141)+INDEX(AT$21:AT$141,$K141+2)*$L141 -> -274.10345 | AW141: =$C141+$D141+MAX(AU141,AV141,IF(COUNTIFS($A$21:$A$141,">="&$G141,$A$21:$A$141,"<="&$H141)>0,_xlfn.MAXIFS(AT$21:AT$141,$A$21:$A$141,">="&$G141,$A$21:$A$141,"<="&$H141),AU141)) -> -0.13395692 | AX141: =-Cost_k*$A141+Beta_q*(Declarations!$B$16*INDEX(AW$21:AW$141,MAX(1,MIN(121,$B141-ROUND(Declarations!$A$16/$D$18,0))))+Declarations!$B$17*INDEX(AW$21:AW$141,MAX(1,MIN(121,$B141-ROUND(Declarations!$A$17/$D$18,0))))+Declarations!$B$18*INDEX(AW$21:AW$141,MAX(1,MIN(121,$B141-ROUND(Declarations!$A$18/$D$18,0))))+Declarations!$B$19*INDEX(AW$21:AW$141,MAX(1,MIN(121,$B141-ROUND(Declarations!$A$19/$D$18,0))))+Declarations!$B$20*INDEX(AW$21:AW$141,MAX(1,MIN(121,$B141-ROUND(Declarations!$A$20/$D$18,0))))) -> -280.17693 | AY141: =INDEX(AX$21:AX$141,$I141+1)*(1-$J141)+INDEX(AX$21:AX$141,$I141+2)*$J141 -> -273.68138 | AZ141: =INDEX(AX$21:AX$141,$K141+1)*(1-$L141)+INDEX(AX$21:AX$141,$K141+2)*$L141 -> -274.5658 | BA141: =$C141+$D141+MAX(AY141,AZ141,IF(COUNTIFS($A$21:$A$141,">="&$G141,$A$21:$A$141,"<="&$H141)>0,_xlfn.MAXIFS(AX$21:AX$141,$A$21:$A$141,">="&$G141,$A$21:$A$141,"<="&$H141),AY141)) -> -0.68137518 | BB141: =-Cost_k*$A141+Beta_q*(Declarations!$B$16*INDEX(BA$21:BA$141,MAX(1,MIN(121,$B141-ROUND(Declarations!$A$16/$D$18,0))))+Declarations!$B$17*INDEX(BA$21:BA$141,MAX(1,MIN(121,$B141-ROUND(Declarations!$A$17/$D$18,0))))+Declarations!$B$18*INDEX(BA$21:BA$141,MAX(1,MIN(121,$B141-ROUND(Declarations!$A$18/$D$18,0))))+Declarations!$B$19*INDEX(BA$21:BA$141,MAX(1,MIN(121,$B141-ROUND(Declarations!$A$19/$D$18,0))))+Declarations!$B$20*INDEX(BA$21:BA$141,MAX(1,MIN(121,$B141-ROUND(Declarations!$A$20/$D$18,0))))) -> -280.80769 | BC141: =INDEX(BB$21:BB$141,$I141+1)*(1-$J141)+INDEX(BB$21:BB$141,$I141+2)*$J141 -> -275.103 | BD141: =INDEX(BB$21:BB$141,$K141+1)*(1-$L141)+INDEX(BB$21:BB$141,$K141+2)*$L141 -> -275.83737 | BE141: =$C141+$D141+MAX(BC141,BD141,IF(COUNTIFS($A$21:$A$141,">="&$G141,$A$21:$A$141,"<="&$H141)>0,_xlfn.MAXIFS(BB$21:BB$141,$A$21:$A$141,">="&$G141,$A$21:$A$141,"<="&$H141),BC141)) -> -2.1030034 | BF141: =-Cost_k*$A141+Beta_q*(Declarations!$B$16*INDEX(BE$21:BE$141,MAX(1,MIN(121,$B141-ROUND(Declarations!$A$16/$D$18,0))))+Declarations!$B$17*INDEX(BE$21:BE$141,MAX(1,MIN(121,$B141-ROUND(Declarations!$A$17/$D$18,0))))+Declarations!$B$18*INDEX(BE$21:BE$141,MAX(1,MIN(121,$B141-ROUND(Declarations!$A$18/$D$18,0))))+Declarations!$B$19*INDEX(BE$21:BE$141,MAX(1,MIN(121,$B141-ROUND(Declarations!$A$19/$D$18,0))))+Declarations!$B$20*INDEX(BE$21:BE$141,MAX(1,MIN(121,$B141-ROUND(Declarations!$A$20/$D$18,0))))) -> -282.33962 | BG141: =INDEX(BF$21:BF$141,$I141+1)*(1-$J141)+INDEX(BF$21:BF$141,$I141+2)*$J141 -> -277.65122 | BH141: =INDEX(BF$21:BF$141,$K141+1)*(1-$L141)+INDEX(BF$21:BF$141,$K141+2)*$L141 -> -278.21527 | BI141: =$C141+$D141+MAX(BG141,BH141,IF(COUNTIFS($A$21:$A$141,">="&$G141,$A$21:$A$141,"<="&$H141)>0,_xlfn.MAXIFS(BF$21:BF$141,$A$21:$A$141,">="&$G141,$A$21:$A$141,"<="&$H141),BG141)) -> -4.6512214 | BJ141: -4.6512214 | BK141: =ABS(BI141-BJ141) -> 5.6843419e-14

Sheet LookAhead
A1: Look one quarter ahead: the value of each hiring decision (Figure 7.1(b); AXIOM Lab 2.7, step 1)
A2: Value of hiring h at capability c: g(c) - k h + beta E V*(0.975c + h - w) = g(c) + k alpha c + G(0.975c + h).
A4: Capability c | B4: 53 | C4: 56 | D4: 58
A5: Planned level with no hiring, alpha c | B5: =Alpha_keep*B4 -> 51.675 | C5: =Alpha_keep*C4 -> 54.6 | D5: =Alpha_keep*D4 -> 56.55
A6: g(c) + k alpha c | B6: =-Short_p*MAX(Floor_c-B4,0)+Cost_k*Alpha_keep*B4 -> 203.5 | C6: =-Short_p*MAX(Floor_c-C4,0)+Cost_k*Alpha_keep*C4 -> 218.4 | D6: =-Short_p*MAX(Floor_c-D4,0)+Cost_k*Alpha_keep*D4 -> 226.2
A8: Hiring h | B8: Value at c (1) | C8: Value at c (2) | D8: Value at c (3)
A9: 0 | B9: =B$6+(INDEX(Values!$D$5:$D$425,MIN(INT(((B$5+$A9)-45)/0.05+0.000000001),419)+1)*(1-(((B$5+$A9)-45)/0.05-MIN(INT(((B$5+$A9)-45)/0.05+0.000000001),419)))+INDEX(Values!$D$5:$D$425,MIN(INT(((B$5+$A9)-45)/0.05+0.000000001),419)+2)*(((B$5+$A9)-45)/0.05-MIN(INT(((B$5+$A9)-45)/0.05+0.000000001),419))) -> -262.1569 | C9: =C$6+(INDEX(Values!$D$5:$D$425,MIN(INT(((C$5+$A9)-45)/0.05+0.000000001),419)+1)*(1-(((C$5+$A9)-45)/0.05-MIN(INT(((C$5+$A9)-45)/0.05+0.000000001),419)))+INDEX(Values!$D$5:$D$425,MIN(INT(((C$5+$A9)-45)/0.05+0.000000001),419)+2)*(((C$5+$A9)-45)/0.05-MIN(INT(((C$5+$A9)-45)/0.05+0.000000001),419))) -> -239.08366 | D9: =D$6+(INDEX(Values!$D$5:$D$425,MIN(INT(((D$5+$A9)-45)/0.05+0.000000001),419)+1)*(1-(((D$5+$A9)-45)/0.05-MIN(INT(((D$5+$A9)-45)/0.05+0.000000001),419)))+INDEX(Values!$D$5:$D$425,MIN(INT(((D$5+$A9)-45)/0.05+0.000000001),419)+2)*(((D$5+$A9)-45)/0.05-MIN(INT(((D$5+$A9)-45)/0.05+0.000000001),419))) -> -230.75501
A10: 0.05 | B10: =B$6+(INDEX(Values!$D$5:$D$425,MIN(INT(((B$5+$A10)-45)/0.05+0.000000001),419)+1)*(1-(((B$5+$A10)-45)/0.05-MIN(INT(((B$5+$A10)-45)/0.05+0.000000001),419)))+INDEX(Values!$D$5:$D$425,MIN(INT(((B$5+$A10)-45)/0.05+0.000000001),419)+2)*(((B$5+$A10)-45)/0.05-MIN(INT(((B$5+$A10)-45)/0.05+0.000000001),419))) -> -261.94154 | C10: =C$6+(INDEX(Values!$D$5:$D$425,MIN(INT(((C$5+$A10)-45)/0.05+0.000000001),419)+1)*(1-(((C$5+$A10)-45)/0.05-MIN(INT(((C$5+$A10)-45)/0.05+0.000000001),419)))+INDEX(Values!$D$5:$D$425,MIN(INT(((C$5+$A10)-45)/0.05+0.000000001),419)+2)*(((C$5+$A10)-45)/0.05-MIN(INT(((C$5+$A10)-45)/0.05+0.000000001),419))) -> -239.02711 | D10: =D$6+(INDEX(Values!$D$5:$D$425,MIN(INT(((D$5+$A10)-45)/0.05+0.000000001),419)+1)*(1-(((D$5+$A10)-45)/0.05-MIN(INT(((D$5+$A10)-45)/0.05+0.000000001),419)))+INDEX(Values!$D$5:$D$425,MIN(INT(((D$5+$A10)-45)/0.05+0.000000001),419)+2)*(((D$5+$A10)-45)/0.05-MIN(INT(((D$5+$A10)-45)/0.05+0.000000001),419))) -> -230.76617
A11: 0.1 | B11: =B$6+(INDEX(Values!$D$5:$D$425,MIN(INT(((B$5+$A11)-45)/0.05+0.000000001),419)+1)*(1-(((B$5+$A11)-45)/0.05-MIN(INT(((B$5+$A11)-45)/0.05+0.000000001),419)))+INDEX(Values!$D$5:$D$425,MIN(INT(((B$5+$A11)-45)/0.05+0.000000001),419)+2)*(((B$5+$A11)-45)/0.05-MIN(INT(((B$5+$A11)-45)/0.05+0.000000001),419))) -> -261.72767 | C11: =C$6+(INDEX(Values!$D$5:$D$425,MIN(INT(((C$5+$A11)-45)/0.05+0.000000001),419)+1)*(1-(((C$5+$A11)-45)/0.05-MIN(INT(((C$5+$A11)-45)/0.05+0.000000001),419)))+INDEX(Values!$D$5:$D$425,MIN(INT(((C$5+$A11)-45)/0.05+0.000000001),419)+2)*(((C$5+$A11)-45)/0.05-MIN(INT(((C$5+$A11)-45)/0.05+0.000000001),419))) -> -238.97206 | D11: =D$6+(INDEX(Values!$D$5:$D$425,MIN(INT(((D$5+$A11)-45)/0.05+0.000000001),419)+1)*(1-(((D$5+$A11)-45)/0.05-MIN(INT(((D$5+$A11)-45)/0.05+0.000000001),419)))+INDEX(Values!$D$5:$D$425,MIN(INT(((D$5+$A11)-45)/0.05+0.000000001),419)+2)*(((D$5+$A11)-45)/0.05-MIN(INT(((D$5+$A11)-45)/0.05+0.000000001),419))) -> -230.77733
A12: 0.15 | B12: =B$6+(INDEX(Values!$D$5:$D$425,MIN(INT(((B$5+$A12)-45)/0.05+0.000000001),419)+1)*(1-(((B$5+$A12)-45)/0.05-MIN(INT(((B$5+$A12)-45)/0.05+0.000000001),419)))+INDEX(Values!$D$5:$D$425,MIN(INT(((B$5+$A12)-45)/0.05+0.000000001),419)+2)*(((B$5+$A12)-45)/0.05-MIN(INT(((B$5+$A12)-45)/0.05+0.000000001),419))) -> -261.51582 | C12: =C$6+(INDEX(Values!$D$5:$D$425,MIN(INT(((C$5+$A12)-45)/0.05+0.000000001),419)+1)*(1-(((C$5+$A12)-45)/0.05-MIN(INT(((C$5+$A12)-45)/0.05+0.000000001),419)))+INDEX(Values!$D$5:$D$425,MIN(INT(((C$5+$A12)-45)/0.05+0.000000001),419)+2)*(((C$5+$A12)-45)/0.05-MIN(INT(((C$5+$A12)-45)/0.05+0.000000001),419))) -> -238.91701 | D12: =D$6+(INDEX(Values!$D$5:$D$425,MIN(INT(((D$5+$A12)-45)/0.05+0.000000001),419)+1)*(1-(((D$5+$A12)-45)/0.05-MIN(INT(((D$5+$A12)-45)/0.05+0.000000001),419)))+INDEX(Values!$D$5:$D$425,MIN(INT(((D$5+$A12)-45)/0.05+0.000000001),419)+2)*(((D$5+$A12)-45)/0.05-MIN(INT(((D$5+$A12)-45)/0.05+0.000000001),419))) -> -230.78849
A13: 0.2 | B13: =B$6+(INDEX(Values!$D$5:$D$425,MIN(INT(((B$5+$A13)-45)/0.05+0.000000001),419)+1)*(1-(((B$5+$A13)-45)/0.05-MIN(INT(((B$5+$A13)-45)/0.05+0.000000001),419)))+INDEX(Values!$D$5:$D$425,MIN(INT(((B$5+$A13)-45)/0.05+0.000000001),419)+2)*(((B$5+$A13)-45)/0.05-MIN(INT(((B$5+$A13)-45)/0.05+0.000000001),419))) -> -261.30723 | C13: =C$6+(INDEX(Values!$D$5:$D$425,MIN(INT(((C$5+$A13)-45)/0.05+0.000000001),419)+1)*(1-(((C$5+$A13)-45)/0.05-MIN(INT(((C$5+$A13)-45)/0.05+0.000000001),419)))+INDEX(Values!$D$5:$D$425,MIN(INT(((C$5+$A13)-45)/0.05+0.000000001),419)+2)*(((C$5+$A13)-45)/0.05-MIN(INT(((C$5+$A13)-45)/0.05+0.000000001),419))) -> -238.86196 | D13: =D$6+(INDEX(Values!$D$5:$D$425,MIN(INT(((D$5+$A13)-45)/0.05+0.000000001),419)+1)*(1-(((D$5+$A13)-45)/0.05-MIN(INT(((D$5+$A13)-45)/0.05+0.000000001),419)))+INDEX(Values!$D$5:$D$425,MIN(INT(((D$5+$A13)-45)/0.05+0.000000001),419)+2)*(((D$5+$A13)-45)/0.05-MIN(INT(((D$5+$A13)-45)/0.05+0.000000001),419))) -> -230.79965
A14: 0.25 | B14: =B$6+(INDEX(Values!$D$5:$D$425,MIN(INT(((B$5+$A14)-45)/0.05+0.000000001),419)+1)*(1-(((B$5+$A14)-45)/0.05-MIN(INT(((B$5+$A14)-45)/0.05+0.000000001),419)))+INDEX(Values!$D$5:$D$425,MIN(INT(((B$5+$A14)-45)/0.05+0.000000001),419)+2)*(((B$5+$A14)-45)/0.05-MIN(INT(((B$5+$A14)-45)/0.05+0.000000001),419))) -> -261.10511 | C14: =C$6+(INDEX(Values!$D$5:$D$425,MIN(INT(((C$5+$A14)-45)/0.05+0.000000001),419)+1)*(1-(((C$5+$A14)-45)/0.05-MIN(INT(((C$5+$A14)-45)/0.05+0.000000001),419)))+INDEX(Values!$D$5:$D$425,MIN(INT(((C$5+$A14)-45)/0.05+0.000000001),419)+2)*(((C$5+$A14)-45)/0.05-MIN(INT(((C$5+$A14)-45)/0.05+0.000000001),419))) -> -238.80692 | D14: =D$6+(INDEX(Values!$D$5:$D$425,MIN(INT(((D$5+$A14)-45)/0.05+0.000000001),419)+1)*(1-(((D$5+$A14)-45)/0.05-MIN(INT(((D$5+$A14)-45)/0.05+0.000000001),419)))+INDEX(Values!$D$5:$D$425,MIN(INT(((D$5+$A14)-45)/0.05+0.000000001),419)+2)*(((D$5+$A14)-45)/0.05-MIN(INT(((D$5+$A14)-45)/0.05+0.000000001),419))) -> -230.81083
A15: 0.3 | B15: =B$6+(INDEX(Values!$D$5:$D$425,MIN(INT(((B$5+$A15)-45)/0.05+0.000000001),419)+1)*(1-(((B$5+$A15)-45)/0.05-MIN(INT(((B$5+$A15)-45)/0.05+0.000000001),419)))+INDEX(Values!$D$5:$D$425,MIN(INT(((B$5+$A15)-45)/0.05+0.000000001),419)+2)*(((B$5+$A15)-45)/0.05-MIN(INT(((B$5+$A15)-45)/0.05+0.000000001),419))) -> -260.90827 | C15: =C$6+(INDEX(Values!$D$5:$D$425,MIN(INT(((C$5+$A15)-45)/0.05+0.000000001),419)+1)*(1-(((C$5+$A15)-45)/0.05-MIN(INT(((C$5+$A15)-45)/0.05+0.000000001),419)))+INDEX(Values!$D$5:$D$425,MIN(INT(((C$5+$A15)-45)/0.05+0.000000001),419)+2)*(((C$5+$A15)-45)/0.05-MIN(INT(((C$5+$A15)-45)/0.05+0.000000001),419))) -> -238.75191 | D15: =D$6+(INDEX(Values!$D$5:$D$425,MIN(INT(((D$5+$A15)-45)/0.05+0.000000001),419)+1)*(1-(((D$5+$A15)-45)/0.05-MIN(INT(((D$5+$A15)-45)/0.05+0.000000001),419)))+INDEX(Values!$D$5:$D$425,MIN(INT(((D$5+$A15)-45)/0.05+0.000000001),419)+2)*(((D$5+$A15)-45)/0.05-MIN(INT(((D$5+$A15)-45)/0.05+0.000000001),419))) -> -230.82207
A16: 0.35 | B16: =B$6+(INDEX(Values!$D$5:$D$425,MIN(INT(((B$5+$A16)-45)/0.05+0.000000001),419)+1)*(1-(((B$5+$A16)-45)/0.05-MIN(INT(((B$5+$A16)-45)/0.05+0.000000001),419)))+INDEX(Values!$D$5:$D$425,MIN(INT(((B$5+$A16)-45)/0.05+0.000000001),419)+2)*(((B$5+$A16)-45)/0.05-MIN(INT(((B$5+$A16)-45)/0.05+0.000000001),419))) -> -260.71253 | C16: =C$6+(INDEX(Values!$D$5:$D$425,MIN(INT(((C$5+$A16)-45)/0.05+0.000000001),419)+1)*(1-(((C$5+$A16)-45)/0.05-MIN(INT(((C$5+$A16)-45)/0.05+0.000000001),419)))+INDEX(Values!$D$5:$D$425,MIN(INT(((C$5+$A16)-45)/0.05+0.000000001),419)+2)*(((C$5+$A16)-45)/0.05-MIN(INT(((C$5+$A16)-45)/0.05+0.000000001),419))) -> -238.69713 | D16: =D$6+(INDEX(Values!$D$5:$D$425,MIN(INT(((D$5+$A16)-45)/0.05+0.000000001),419)+1)*(1-(((D$5+$A16)-45)/0.05-MIN(INT(((D$5+$A16)-45)/0.05+0.000000001),419)))+INDEX(Values!$D$5:$D$425,MIN(INT(((D$5+$A16)-45)/0.05+0.000000001),419)+2)*(((D$5+$A16)-45)/0.05-MIN(INT(((D$5+$A16)-45)/0.05+0.000000001),419))) -> -230.83334
A17: 0.4 | B17: =B$6+(INDEX(Values!$D$5:$D$425,MIN(INT(((B$5+$A17)-45)/0.05+0.000000001),419)+1)*(1-(((B$5+$A17)-45)/0.05-MIN(INT(((B$5+$A17)-45)/0.05+0.000000001),419)))+INDEX(Values!$D$5:$D$425,MIN(INT(((B$5+$A17)-45)/0.05+0.000000001),419)+2)*(((B$5+$A17)-45)/0.05-MIN(INT(((B$5+$A17)-45)/0.05+0.000000001),419))) -> -260.51709 | C17: =C$6+(INDEX(Values!$D$5:$D$425,MIN(INT(((C$5+$A17)-45)/0.05+0.000000001),419)+1)*(1-(((C$5+$A17)-45)/0.05-MIN(INT(((C$5+$A17)-45)/0.05+0.000000001),419)))+INDEX(Values!$D$5:$D$425,MIN(INT(((C$5+$A17)-45)/0.05+0.000000001),419)+2)*(((C$5+$A17)-45)/0.05-MIN(INT(((C$5+$A17)-45)/0.05+0.000000001),419))) -> -238.64326 | D17: =D$6+(INDEX(Values!$D$5:$D$425,MIN(INT(((D$5+$A17)-45)/0.05+0.000000001),419)+1)*(1-(((D$5+$A17)-45)/0.05-MIN(INT(((D$5+$A17)-45)/0.05+0.000000001),419)))+INDEX(Values!$D$5:$D$425,MIN(INT(((D$5+$A17)-45)/0.05+0.000000001),419)+2)*(((D$5+$A17)-45)/0.05-MIN(INT(((D$5+$A17)-45)/0.05+0.000000001),419))) -> -230.8446
A18: 0.45 | B18: =B$6+(INDEX(Values!$D$5:$D$425,MIN(INT(((B$5+$A18)-45)/0.05+0.000000001),419)+1)*(1-(((B$5+$A18)-45)/0.05-MIN(INT(((B$5+$A18)-45)/0.05+0.000000001),419)))+INDEX(Values!$D$5:$D$425,MIN(INT(((B$5+$A18)-45)/0.05+0.000000001),419)+2)*(((B$5+$A18)-45)/0.05-MIN(INT(((B$5+$A18)-45)/0.05+0.000000001),419))) -> -260.32212 | C18: =C$6+(INDEX(Values!$D$5:$D$425,MIN(INT(((C$5+$A18)-45)/0.05+0.000000001),419)+1)*(1-(((C$5+$A18)-45)/0.05-MIN(INT(((C$5+$A18)-45)/0.05+0.000000001),419)))+INDEX(Values!$D$5:$D$425,MIN(INT(((C$5+$A18)-45)/0.05+0.000000001),419)+2)*(((C$5+$A18)-45)/0.05-MIN(INT(((C$5+$A18)-45)/0.05+0.000000001),419))) -> -238.62866 | D18: =D$6+(INDEX(Values!$D$5:$D$425,MIN(INT(((D$5+$A18)-45)/0.05+0.000000001),419)+1)*(1-(((D$5+$A18)-45)/0.05-MIN(INT(((D$5+$A18)-45)/0.05+0.000000001),419)))+INDEX(Values!$D$5:$D$425,MIN(INT(((D$5+$A18)-45)/0.05+0.000000001),419)+2)*(((D$5+$A18)-45)/0.05-MIN(INT(((D$5+$A18)-45)/0.05+0.000000001),419))) -> -230.85587
A19: 0.5 | B19: =B$6+(INDEX(Values!$D$5:$D$425,MIN(INT(((B$5+$A19)-45)/0.05+0.000000001),419)+1)*(1-(((B$5+$A19)-45)/0.05-MIN(INT(((B$5+$A19)-45)/0.05+0.000000001),419)))+INDEX(Values!$D$5:$D$425,MIN(INT(((B$5+$A19)-45)/0.05+0.000000001),419)+2)*(((B$5+$A19)-45)/0.05-MIN(INT(((B$5+$A19)-45)/0.05+0.000000001),419))) -> -260.12835 | C19: =C$6+(INDEX(Values!$D$5:$D$425,MIN(INT(((C$5+$A19)-45)/0.05+0.000000001),419)+1)*(1-(((C$5+$A19)-45)/0.05-MIN(INT(((C$5+$A19)-45)/0.05+0.000000001),419)))+INDEX(Values!$D$5:$D$425,MIN(INT(((C$5+$A19)-45)/0.05+0.000000001),419)+2)*(((C$5+$A19)-45)/0.05-MIN(INT(((C$5+$A19)-45)/0.05+0.000000001),419))) -> -238.61408 | D19: =D$6+(INDEX(Values!$D$5:$D$425,MIN(INT(((D$5+$A19)-45)/0.05+0.000000001),419)+1)*(1-(((D$5+$A19)-45)/0.05-MIN(INT(((D$5+$A19)-45)/0.05+0.000000001),419)))+INDEX(Values!$D$5:$D$425,MIN(INT(((D$5+$A19)-45)/0.05+0.000000001),419)+2)*(((D$5+$A19)-45)/0.05-MIN(INT(((D$5+$A19)-45)/0.05+0.000000001),419))) -> -230.86713
A20: 0.55 | B20: =B$6+(INDEX(Values!$D$5:$D$425,MIN(INT(((B$5+$A20)-45)/0.05+0.000000001),419)+1)*(1-(((B$5+$A20)-45)/0.05-MIN(INT(((B$5+$A20)-45)/0.05+0.000000001),419)))+INDEX(Values!$D$5:$D$425,MIN(INT(((B$5+$A20)-45)/0.05+0.000000001),419)+2)*(((B$5+$A20)-45)/0.05-MIN(INT(((B$5+$A20)-45)/0.05+0.000000001),419))) -> -259.93759 | C20: =C$6+(INDEX(Values!$D$5:$D$425,MIN(INT(((C$5+$A20)-45)/0.05+0.000000001),419)+1)*(1-(((C$5+$A20)-45)/0.05-MIN(INT(((C$5+$A20)-45)/0.05+0.000000001),419)))+INDEX(Values!$D$5:$D$425,MIN(INT(((C$5+$A20)-45)/0.05+0.000000001),419)+2)*(((C$5+$A20)-45)/0.05-MIN(INT(((C$5+$A20)-45)/0.05+0.000000001),419))) -> -238.59949 | D20: =D$6+(INDEX(Values!$D$5:$D$425,MIN(INT(((D$5+$A20)-45)/0.05+0.000000001),419)+1)*(1-(((D$5+$A20)-45)/0.05-MIN(INT(((D$5+$A20)-45)/0.05+0.000000001),419)))+INDEX(Values!$D$5:$D$425,MIN(INT(((D$5+$A20)-45)/0.05+0.000000001),419)+2)*(((D$5+$A20)-45)/0.05-MIN(INT(((D$5+$A20)-45)/0.05+0.000000001),419))) -> -230.87841
... A59: 2.5 | B59: =B$6+(INDEX(Values!$D$5:$D$425,MIN(INT(((B$5+$A59)-45)/0.05+0.000000001),419)+1)*(1-(((B$5+$A59)-45)/0.05-MIN(INT(((B$5+$A59)-45)/0.05+0.000000001),419)))+INDEX(Values!$D$5:$D$425,MIN(INT(((B$5+$A59)-45)/0.05+0.000000001),419)+2)*(((B$5+$A59)-45)/0.05-MIN(INT(((B$5+$A59)-45)/0.05+0.000000001),419))) -> -254.59289 | C59: =C$6+(INDEX(Values!$D$5:$D$425,MIN(INT(((C$5+$A59)-45)/0.05+0.000000001),419)+1)*(1-(((C$5+$A59)-45)/0.05-MIN(INT(((C$5+$A59)-45)/0.05+0.000000001),419)))+INDEX(Values!$D$5:$D$425,MIN(INT(((C$5+$A59)-45)/0.05+0.000000001),419)+2)*(((C$5+$A59)-45)/0.05-MIN(INT(((C$5+$A59)-45)/0.05+0.000000001),419))) -> -238.67841 | D59: =D$6+(INDEX(Values!$D$5:$D$425,MIN(INT(((D$5+$A59)-45)/0.05+0.000000001),419)+1)*(1-(((D$5+$A59)-45)/0.05-MIN(INT(((D$5+$A59)-45)/0.05+0.000000001),419)))+INDEX(Values!$D$5:$D$425,MIN(INT(((D$5+$A59)-45)/0.05+0.000000001),419)+2)*(((D$5+$A59)-45)/0.05-MIN(INT(((D$5+$A59)-45)/0.05+0.000000001),419))) -> -231.60207
A61: Best hiring (least, if tied) | B61: =_xlfn.MINIFS($A$9:$A$59,B9:B59,">="&(MAX(B9:B59)-0.000000001)) -> 2.5 | C61: =_xlfn.MINIFS($A$9:$A$59,C9:C59,">="&(MAX(C9:C59)-0.000000001)) -> 1.15 | D61: =_xlfn.MINIFS($A$9:$A$59,D9:D59,">="&(MAX(D9:D59)-0.000000001)) -> 0
A62: By the target rule: min(cap, max(0, target - alpha c)) | B62: =MIN(Cap_h,MAX(0,CriticalRatio!$B$7-Alpha_keep*B4)) -> 2.5 | C62: =MIN(Cap_h,MAX(0,CriticalRatio!$B$7-Alpha_keep*C4)) -> 1.15 | D62: =MIN(Cap_h,MAX(0,CriticalRatio!$B$7-Alpha_keep*D4)) -> 0

Sheet Values
A1: Read values; certify them: the engine's V* and its Bellman image (Theorem 7.3(ii); AXIOM Lab 2.7, step 4)
A2: Column B is the engine's value function from policy iteration (pasted). The formulas apply the Bellman operator to it: a residual near zero certifies it.
M3: Certificate | N3: Value
A4: c | B4: V*(c) (engine) | C4: node | D4: G(y = c) | E4: L | F4: U | G4: G(L) | H4: G(U) | I4: best G at nodes | J4: (TV*)(c) | K4: |TV* - V*| | M4: Largest Bellman residual at the nodes from 50 to 62 | N4: =MAX(K105:K345) -> 0
A5: 45 | B5: -341.16552 | C5: 1 | M5: Breakpoint c*: where 0.975c + 2.5 meets the node 53.85 | N5: =(53.85-Cap_h)/Alpha_keep -> 52.666667
A6: 45.05 | B6: -340.46735 | C6: 2 | M6: V*(c*), linear between nodes | N6: =(INDEX($B$5:$B$425,MIN(INT((N5-45)/0.05+0.000000001),419)+1)*(1-((N5-45)/0.05-MIN(INT((N5-45)/0.05+0.000000001),419)))+INDEX($B$5:$B$425,MIN(INT((N5-45)/0.05+0.000000001),419)+2)*((N5-45)/0.05-MIN(INT((N5-45)/0.05+0.000000001),419))) -> -257.01619
A7: 45.1 | B7: -339.77076 | C7: 3 | M7: L* = alpha c* | N7: =Alpha_keep*N5 -> 51.35
A8: 45.15 | B8: -339.07591 | C8: 4 | M8: U* = alpha c* + cap | N8: =N7+Cap_h -> 53.85
A9: 45.2 | B9: -338.38289 | C9: 5 | M9: G(L*) | N9: =(INDEX($D$5:$D$425,MIN(INT((N7-45)/0.05+0.000000001),419)+1)*(1-((N7-45)/0.05-MIN(INT((N7-45)/0.05+0.000000001),419)))+INDEX($D$5:$D$425,MIN(INT((N7-45)/0.05+0.000000001),419)+2)*((N7-45)/0.05-MIN(INT((N7-45)/0.05+0.000000001),419))) -> -467.09901
A10: 45.25 | B10: -337.69161 | C10: 6 | M10: G(U*) | N10: =(INDEX($D$5:$D$425,MIN(INT((N8-45)/0.05+0.000000001),419)+1)*(1-((N8-45)/0.05-MIN(INT((N8-45)/0.05+0.000000001),419)))+INDEX($D$5:$D$425,MIN(INT((N8-45)/0.05+0.000000001),419)+2)*((N8-45)/0.05-MIN(INT((N8-45)/0.05+0.000000001),419))) -> -458.67845
A11: 45.3 | B11: -337.00193 | C11: 7 | M11: Best G at the nodes in [L*, U*] | N11: =_xlfn.MAXIFS($D$5:$D$425,$A$5:$A$425,">="&N7,$A$5:$A$425,"<="&N8) -> -458.67845
A12: 45.35 | B12: -336.31386 | C12: 8 | M12: (TV*)(c*) | N12: =-Short_p*MAX(Floor_c-N5,0)+Cost_k*Alpha_keep*N5+MAX(N9,N10,N11) -> -257.01178
A13: 45.4 | B13: -335.62753 | C13: 9 | M13: Bellman residual at c* (the largest over the continuum) | N13: =ABS(N12-N6) -> 0.0044034805
A14: 45.45 | B14: -334.94313 | C14: 10 | M14: So V* is within residual/(1 - beta) of the declared model's | N14: =N13/(1-Beta_q) -> 0.18701679
A15: 45.5 | B15: -334.26071 | C15: 11
A16: 45.55 | B16: -333.58011 | C16: 12
A17: 45.6 | B17: -332.90118 | C17: 13
A18: 45.65 | B18: -332.22384 | C18: 14
A19: 45.7 | B19: -331.54817 | C19: 15
A20: 45.75 | B20: -330.87425 | C20: 16
A21: 45.8 | B21: -330.20207 | C21: 17
A22: 45.85 | B22: -329.53141 | C22: 18
A23: 45.9 | B23: -328.86233 | C23: 19
A24: 45.95 | B24: -328.19513 | C24: 20
A25: 46 | B25: -327.53007 | C25: 21
A26: 46.05 | B26: -326.86719 | C26: 22
... A34: 46.45 | B34: -321.62678 | C34: 30
A35: 46.5 | B35: -320.97977 | C35: 31 | D35: =-Cost_k*A35+Beta_q*(Declarations!$B$16*INDEX($B$5:$B$425,$C35-ROUND(Declarations!$A$16/0.05,0))+Declarations!$B$17*INDEX($B$5:$B$425,$C35-ROUND(Declarations!$A$17/0.05,0))+Declarations!$B$18*INDEX($B$5:$B$425,$C35-ROUND(Declarations!$A$18/0.05,0))+Declarations!$B$19*INDEX($B$5:$B$425,$C35-ROUND(Declarations!$A$19/0.05,0))+Declarations!$B$20*INDEX($B$5:$B$425,$C35-ROUND(Declarations!$A$20/0.05,0))) -> -499.58345
A36: 46.55 | B36: -320.33485 | C36: 32 | D36: =-Cost_k*A36+Beta_q*(Declarations!$B$16*INDEX($B$5:$B$425,$C36-ROUND(Declarations!$A$16/0.05,0))+Declarations!$B$17*INDEX($B$5:$B$425,$C36-ROUND(Declarations!$A$17/0.05,0))+Declarations!$B$18*INDEX($B$5:$B$425,$C36-ROUND(Declarations!$A$18/0.05,0))+Declarations!$B$19*INDEX($B$5:$B$425,$C36-ROUND(Declarations!$A$19/0.05,0))+Declarations!$B$20*INDEX($B$5:$B$425,$C36-ROUND(Declarations!$A$20/0.05,0))) -> -499.15394
A37: 46.6 | B37: -319.69173 | C37: 33 | D37: =-Cost_k*A37+Beta_q*(Declarations!$B$16*INDEX($B$5:$B$425,$C37-ROUND(Declarations!$A$16/0.05,0))+Declarations!$B$17*INDEX($B$5:$B$425,$C37-ROUND(Declarations!$A$17/0.05,0))+Declarations!$B$18*INDEX($B$5:$B$425,$C37-ROUND(Declarations!$A$18/0.05,0))+Declarations!$B$19*INDEX($B$5:$B$425,$C37-ROUND(Declarations!$A$19/0.05,0))+Declarations!$B$20*INDEX($B$5:$B$425,$C37-ROUND(Declarations!$A$20/0.05,0))) -> -498.72632
A38: 46.65 | B38: -319.0501 | C38: 34 | D38: =-Cost_k*A38+Beta_q*(Declarations!$B$16*INDEX($B$5:$B$425,$C38-ROUND(Declarations!$A$16/0.05,0))+Declarations!$B$17*INDEX($B$5:$B$425,$C38-ROUND(Declarations!$A$17/0.05,0))+Declarations!$B$18*INDEX($B$5:$B$425,$C38-ROUND(Declarations!$A$18/0.05,0))+Declarations!$B$19*INDEX($B$5:$B$425,$C38-ROUND(Declarations!$A$19/0.05,0))+Declarations!$B$20*INDEX($B$5:$B$425,$C38-ROUND(Declarations!$A$20/0.05,0))) -> -498.30042
A39: 46.7 | B39: -318.40998 | C39: 35 | D39: =-Cost_k*A39+Beta_q*(Declarations!$B$16*INDEX($B$5:$B$425,$C39-ROUND(Declarations!$A$16/0.05,0))+Declarations!$B$17*INDEX($B$5:$B$425,$C39-ROUND(Declarations!$A$17/0.05,0))+Declarations!$B$18*INDEX($B$5:$B$425,$C39-ROUND(Declarations!$A$18/0.05,0))+Declarations!$B$19*INDEX($B$5:$B$425,$C39-ROUND(Declarations!$A$19/0.05,0))+Declarations!$B$20*INDEX($B$5:$B$425,$C39-ROUND(Declarations!$A$20/0.05,0))) -> -497.87617
A40: 46.75 | B40: -317.77172 | C40: 36 | D40: =-Cost_k*A40+Beta_q*(Declarations!$B$16*INDEX($B$5:$B$425,$C40-ROUND(Declarations!$A$16/0.05,0))+Declarations!$B$17*INDEX($B$5:$B$425,$C40-ROUND(Declarations!$A$17/0.05,0))+Declarations!$B$18*INDEX($B$5:$B$425,$C40-ROUND(Declarations!$A$18/0.05,0))+Declarations!$B$19*INDEX($B$5:$B$425,$C40-ROUND(Declarations!$A$19/0.05,0))+Declarations!$B$20*INDEX($B$5:$B$425,$C40-ROUND(Declarations!$A$20/0.05,0))) -> -497.45368
A41: 46.8 | B41: -317.13578 | C41: 37 | D41: =-Cost_k*A41+Beta_q*(Declarations!$B$16*INDEX($B$5:$B$425,$C41-ROUND(Declarations!$A$16/0.05,0))+Declarations!$B$17*INDEX($B$5:$B$425,$C41-ROUND(Declarations!$A$17/0.05,0))+Declarations!$B$18*INDEX($B$5:$B$425,$C41-ROUND(Declarations!$A$18/0.05,0))+Declarations!$B$19*INDEX($B$5:$B$425,$C41-ROUND(Declarations!$A$19/0.05,0))+Declarations!$B$20*INDEX($B$5:$B$425,$C41-ROUND(Declarations!$A$20/0.05,0))) -> -497.03319
A42: 46.85 | B42: -316.50232 | C42: 38 | D42: =-Cost_k*A42+Beta_q*(Declarations!$B$16*INDEX($B$5:$B$425,$C42-ROUND(Declarations!$A$16/0.05,0))+Declarations!$B$17*INDEX($B$5:$B$425,$C42-ROUND(Declarations!$A$17/0.05,0))+Declarations!$B$18*INDEX($B$5:$B$425,$C42-ROUND(Declarations!$A$18/0.05,0))+Declarations!$B$19*INDEX($B$5:$B$425,$C42-ROUND(Declarations!$A$19/0.05,0))+Declarations!$B$20*INDEX($B$5:$B$425,$C42-ROUND(Declarations!$A$20/0.05,0))) -> -496.61481
A43: 46.9 | B43: -315.87095 | C43: 39 | D43: =-Cost_k*A43+Beta_q*(Declarations!$B$16*INDEX($B$5:$B$425,$C43-ROUND(Declarations!$A$16/0.05,0))+Declarations!$B$17*INDEX($B$5:$B$425,$C43-ROUND(Declarations!$A$17/0.05,0))+Declarations!$B$18*INDEX($B$5:$B$425,$C43-ROUND(Declarations!$A$18/0.05,0))+Declarations!$B$19*INDEX($B$5:$B$425,$C43-ROUND(Declarations!$A$19/0.05,0))+Declarations!$B$20*INDEX($B$5:$B$425,$C43-ROUND(Declarations!$A$20/0.05,0))) -> -496.19841
A44: 46.95 | B44: -315.24124 | C44: 40 | D44: =-Cost_k*A44+Beta_q*(Declarations!$B$16*INDEX($B$5:$B$425,$C44-ROUND(Declarations!$A$16/0.05,0))+Declarations!$B$17*INDEX($B$5:$B$425,$C44-ROUND(Declarations!$A$17/0.05,0))+Declarations!$B$18*INDEX($B$5:$B$425,$C44-ROUND(Declarations!$A$18/0.05,0))+Declarations!$B$19*INDEX($B$5:$B$425,$C44-ROUND(Declarations!$A$19/0.05,0))+Declarations!$B$20*INDEX($B$5:$B$425,$C44-ROUND(Declarations!$A$20/0.05,0))) -> -495.78377
A45: 47 | B45: -314.61307 | C45: 41 | D45: =-Cost_k*A45+Beta_q*(Declarations!$B$16*INDEX($B$5:$B$425,$C45-ROUND(Declarations!$A$16/0.05,0))+Declarations!$B$17*INDEX($B$5:$B$425,$C45-ROUND(Declarations!$A$17/0.05,0))+Declarations!$B$18*INDEX($B$5:$B$425,$C45-ROUND(Declarations!$A$18/0.05,0))+Declarations!$B$19*INDEX($B$5:$B$425,$C45-ROUND(Declarations!$A$19/0.05,0))+Declarations!$B$20*INDEX($B$5:$B$425,$C45-ROUND(Declarations!$A$20/0.05,0))) -> -495.37081
A46: 47.05 | B46: -313.98656 | C46: 42 | D46: =-Cost_k*A46+Beta_q*(Declarations!$B$16*INDEX($B$5:$B$425,$C46-ROUND(Declarations!$A$16/0.05,0))+Declarations!$B$17*INDEX($B$5:$B$425,$C46-ROUND(Declarations!$A$17/0.05,0))+Declarations!$B$18*INDEX($B$5:$B$425,$C46-ROUND(Declarations!$A$18/0.05,0))+Declarations!$B$19*INDEX($B$5:$B$425,$C46-ROUND(Declarations!$A$19/0.05,0))+Declarations!$B$20*INDEX($B$5:$B$425,$C46-ROUND(Declarations!$A$20/0.05,0))) -> -494.95958
... A104: 49.95 | B104: -281.07111 | C104: 100 | D104: =-Cost_k*A104+Beta_q*(Declarations!$B$16*INDEX($B$5:$B$425,$C104-ROUND(Declarations!$A$16/0.05,0))+Declarations!$B$17*INDEX($B$5:$B$425,$C104-ROUND(Declarations!$A$17/0.05,0))+Declarations!$B$18*INDEX($B$5:$B$425,$C104-ROUND(Declarations!$A$18/0.05,0))+Declarations!$B$19*INDEX($B$5:$B$425,$C104-ROUND(Declarations!$A$19/0.05,0))+Declarations!$B$20*INDEX($B$5:$B$425,$C104-ROUND(Declarations!$A$20/0.05,0))) -> -474.44754
A105: 50 | B105: -280.5669 | C105: 101 | D105: =-Cost_k*A105+Beta_q*(Declarations!$B$16*INDEX($B$5:$B$425,$C105-ROUND(Declarations!$A$16/0.05,0))+Declarations!$B$17*INDEX($B$5:$B$425,$C105-ROUND(Declarations!$A$17/0.05,0))+Declarations!$B$18*INDEX($B$5:$B$425,$C105-ROUND(Declarations!$A$18/0.05,0))+Declarations!$B$19*INDEX($B$5:$B$425,$C105-ROUND(Declarations!$A$19/0.05,0))+Declarations!$B$20*INDEX($B$5:$B$425,$C105-ROUND(Declarations!$A$20/0.05,0))) -> -474.15605 | E105: =Alpha_keep*A105 -> 48.75 | F105: =Alpha_keep*A105+Cap_h -> 51.25 | G105: =(INDEX($D$5:$D$425,MIN(INT((E105-45)/0.05+0.000000001),419)+1)*(1-((E105-45)/0.05-MIN(INT((E105-45)/0.05+0.000000001),419)))+INDEX($D$5:$D$425,MIN(INT((E105-45)/0.05+0.000000001),419)+2)*((E105-45)/0.05-MIN(INT((E105-45)/0.05+0.000000001),419))) -> -482.11282 | H105: =(INDEX($D$5:$D$425,MIN(INT((F105-45)/0.05+0.000000001),419)+1)*(1-((F105-45)/0.05-MIN(INT((F105-45)/0.05+0.000000001),419)))+INDEX($D$5:$D$425,MIN(INT((F105-45)/0.05+0.000000001),419)+2)*((F105-45)/0.05-MIN(INT((F105-45)/0.05+0.000000001),419))) -> -467.5669 | I105: =_xlfn.MAXIFS($D$5:$D$425,$A$5:$A$425,">="&E105,$A$5:$A$425,"<="&F105) -> -467.5669 | J105: =-Short_p*MAX(Floor_c-A105,0)+Cost_k*Alpha_keep*A105+MAX(G105,H105,I105) -> -280.5669 | K105: =ABS(J105-B105) -> 0
A106: 50.05 | B106: -280.06335 | C106: 102 | D106: =-Cost_k*A106+Beta_q*(Declarations!$B$16*INDEX($B$5:$B$425,$C106-ROUND(Declarations!$A$16/0.05,0))+Declarations!$B$17*INDEX($B$5:$B$425,$C106-ROUND(Declarations!$A$17/0.05,0))+Declarations!$B$18*INDEX($B$5:$B$425,$C106-ROUND(Declarations!$A$18/0.05,0))+Declarations!$B$19*INDEX($B$5:$B$425,$C106-ROUND(Declarations!$A$19/0.05,0))+Declarations!$B$20*INDEX($B$5:$B$425,$C106-ROUND(Declarations!$A$20/0.05,0))) -> -473.86564 | E106: =Alpha_keep*A106 -> 48.79875 | F106: =Alpha_keep*A106+Cap_h -> 51.29875 | G106: =(INDEX($D$5:$D$425,MIN(INT((E106-45)/0.05+0.000000001),419)+1)*(1-((E106-45)/0.05-MIN(INT((E106-45)/0.05+0.000000001),419)))+INDEX($D$5:$D$425,MIN(INT((E106-45)/0.05+0.000000001),419)+2)*((E106-45)/0.05-MIN(INT((E106-45)/0.05+0.000000001),419))) -> -481.77801 | H106: =(INDEX($D$5:$D$425,MIN(INT((F106-45)/0.05+0.000000001),419)+1)*(1-((F106-45)/0.05-MIN(INT((F106-45)/0.05+0.000000001),419)))+INDEX($D$5:$D$425,MIN(INT((F106-45)/0.05+0.000000001),419)+2)*((F106-45)/0.05-MIN(INT((F106-45)/0.05+0.000000001),419))) -> -467.33835 | I106: =_xlfn.MAXIFS($D$5:$D$425,$A$5:$A$425,">="&E106,$A$5:$A$425,"<="&F106) -> -467.5669 | J106: =-Short_p*MAX(Floor_c-A106,0)+Cost_k*Alpha_keep*A106+MAX(G106,H106,I106) -> -280.06335 | K106: =ABS(J106-B106) -> 0
A107: 50.1 | B107: -279.56069 | C107: 103 | D107: =-Cost_k*A107+Beta_q*(Declarations!$B$16*INDEX($B$5:$B$425,$C107-ROUND(Declarations!$A$16/0.05,0))+Declarations!$B$17*INDEX($B$5:$B$425,$C107-ROUND(Declarations!$A$17/0.05,0))+Declarations!$B$18*INDEX($B$5:$B$425,$C107-ROUND(Declarations!$A$18/0.05,0))+Declarations!$B$19*INDEX($B$5:$B$425,$C107-ROUND(Declarations!$A$19/0.05,0))+Declarations!$B$20*INDEX($B$5:$B$425,$C107-ROUND(Declarations!$A$20/0.05,0))) -> -473.57623 | E107: =Alpha_keep*A107 -> 48.8475 | F107: =Alpha_keep*A107+Cap_h -> 51.3475 | G107: =(INDEX($D$5:$D$425,MIN(INT((E107-45)/0.05+0.000000001),419)+1)*(1-((E107-45)/0.05-MIN(INT((E107-45)/0.05+0.000000001),419)))+INDEX($D$5:$D$425,MIN(INT((E107-45)/0.05+0.000000001),419)+2)*((E107-45)/0.05-MIN(INT((E107-45)/0.05+0.000000001),419))) -> -481.44463 | H107: =(INDEX($D$5:$D$425,MIN(INT((F107-45)/0.05+0.000000001),419)+1)*(1-((F107-45)/0.05-MIN(INT((F107-45)/0.05+0.000000001),419)))+INDEX($D$5:$D$425,MIN(INT((F107-45)/0.05+0.000000001),419)+2)*((F107-45)/0.05-MIN(INT((F107-45)/0.05+0.000000001),419))) -> -467.11069 | I107: =_xlfn.MAXIFS($D$5:$D$425,$A$5:$A$425,">="&E107,$A$5:$A$425,"<="&F107) -> -467.33249 | J107: =-Short_p*MAX(Floor_c-A107,0)+Cost_k*Alpha_keep*A107+MAX(G107,H107,I107) -> -279.56069 | K107: =ABS(J107-B107) -> 0
A108: 50.15 | B108: -279.05957 | C108: 104 | D108: =-Cost_k*A108+Beta_q*(Declarations!$B$16*INDEX($B$5:$B$425,$C108-ROUND(Declarations!$A$16/0.05,0))+Declarations!$B$17*INDEX($B$5:$B$425,$C108-ROUND(Declarations!$A$17/0.05,0))+Declarations!$B$18*INDEX($B$5:$B$425,$C108-ROUND(Declarations!$A$18/0.05,0))+Declarations!$B$19*INDEX($B$5:$B$425,$C108-ROUND(Declarations!$A$19/0.05,0))+Declarations!$B$20*INDEX($B$5:$B$425,$C108-ROUND(Declarations!$A$20/0.05,0))) -> -473.28849 | E108: =Alpha_keep*A108 -> 48.89625 | F108: =Alpha_keep*A108+Cap_h -> 51.39625 | G108: =(INDEX($D$5:$D$425,MIN(INT((E108-45)/0.05+0.000000001),419)+1)*(1-((E108-45)/0.05-MIN(INT((E108-45)/0.05+0.000000001),419)))+INDEX($D$5:$D$425,MIN(INT((E108-45)/0.05+0.000000001),419)+2)*((E108-45)/0.05-MIN(INT((E108-45)/0.05+0.000000001),419))) -> -481.11324 | H108: =(INDEX($D$5:$D$425,MIN(INT((F108-45)/0.05+0.000000001),419)+1)*(1-((F108-45)/0.05-MIN(INT((F108-45)/0.05+0.000000001),419)))+INDEX($D$5:$D$425,MIN(INT((F108-45)/0.05+0.000000001),419)+2)*((F108-45)/0.05-MIN(INT((F108-45)/0.05+0.000000001),419))) -> -466.88457 | I108: =_xlfn.MAXIFS($D$5:$D$425,$A$5:$A$425,">="&E108,$A$5:$A$425,"<="&F108) -> -467.09901 | J108: =-Short_p*MAX(Floor_c-A108,0)+Cost_k*Alpha_keep*A108+MAX(G108,H108,I108) -> -279.05957 | K108: =ABS(J108-B108) -> 0
A109: 50.2 | B109: -278.56215 | C109: 105 | D109: =-Cost_k*A109+Beta_q*(Declarations!$B$16*INDEX($B$5:$B$425,$C109-ROUND(Declarations!$A$16/0.05,0))+Declarations!$B$17*INDEX($B$5:$B$425,$C109-ROUND(Declarations!$A$17/0.05,0))+Declarations!$B$18*INDEX($B$5:$B$425,$C109-ROUND(Declarations!$A$18/0.05,0))+Declarations!$B$19*INDEX($B$5:$B$425,$C109-ROUND(Declarations!$A$19/0.05,0))+Declarations!$B$20*INDEX($B$5:$B$425,$C109-ROUND(Declarations!$A$20/0.05,0))) -> -473.00379 | E109: =Alpha_keep*A109 -> 48.945 | F109: =Alpha_keep*A109+Cap_h -> 51.445 | G109: =(INDEX($D$5:$D$425,MIN(INT((E109-45)/0.05+0.000000001),419)+1)*(1-((E109-45)/0.05-MIN(INT((E109-45)/0.05+0.000000001),419)))+INDEX($D$5:$D$425,MIN(INT((E109-45)/0.05+0.000000001),419)+2)*((E109-45)/0.05-MIN(INT((E109-45)/0.05+0.000000001),419))) -> -480.78433 | H109: =(INDEX($D$5:$D$425,MIN(INT((F109-45)/0.05+0.000000001),419)+1)*(1-((F109-45)/0.05-MIN(INT((F109-45)/0.05+0.000000001),419)))+INDEX($D$5:$D$425,MIN(INT((F109-45)/0.05+0.000000001),419)+2)*((F109-45)/0.05-MIN(INT((F109-45)/0.05+0.000000001),419))) -> -466.66215 | I109: =_xlfn.MAXIFS($D$5:$D$425,$A$5:$A$425,">="&E109,$A$5:$A$425,"<="&F109) -> -466.86719 | J109: =-Short_p*MAX(Floor_c-A109,0)+Cost_k*Alpha_keep*A109+MAX(G109,H109,I109) -> -278.56215 | K109: =ABS(J109-B109) -> 0
