Workbook

Sheet README
B1: DCT Laboratory — Vol II, Ch 16: Enterprise Applications and Integrated Transformation Case Studies
B2: Seed 26216 · Companion to DCT_V2_Ch16_Lab.ipynb and AXIOM Lab 2.16 (module AXIOM-16). Money in $ million.
B4: Worked Example 16.1, Can Meridian Run Its Whole Program?, with the book's declarations: the build's law and levers (Volume I's law on Chapter 9's 100,000 paths, seed 8; fresh paths seed 26209), the sale with the engineers kept, Chapter 5's automation program, Chapter 11's family of laws (seed 1108), Volume I's feedback core; the new declarations put them on one account (Online Appendix Remark 16.B.1).
B5: Declarations: the inputs, the plan's shapes, the closure buffer (the 90th-percentile closure), the seeds.
B6: Chapter5: Chapter 5's plan on its own account, its war chest and payouts, worth $1,021.93m.
B7: OneAccount: the one account by quarter in closed form (Volume I's plan, the automation program's cash, the sale), the planned margins, and the joint check at quarter 9 against the room of 270 or 362 (Step 2).
B8: Programs: every program's war chest and payouts after the build and its value, payouts at 10 percent plus the year-6 savings forever less the levers 0.03 l + 8 phi; the eight timings of the rounds, no sale, the sale after the build, a dollar of room, the trigger's other branch, Chapter 5's year-1 payout released (Steps 3-4).
B9: Prices: the value of the sale, the appetite's price, each lever's cost per point of chance, the payouts' prices, a dollar of room, capability, holding the payouts (Step 4; Figure 16.2).
B10: Trigger: round 3 on a trigger at 33 triggers and the best one (Step 5; Figure 16.3(b)); Proposition 16.2.
B11: Certify: the margins and their certified region, the records' corner and the price of ambiguity, the triggers (Step 6; Figure 16.3(a)). Core: the feedback core's phases, closed form and power iteration.
B12: Table16_3: the Worked Example's table, linked to the sheets.
B13: Engine values (green) are what needs the 100,000 paths: breach chances, cheapest packages, the trigger rule's packages and shares, the certified region's edges.
... B20: Cross-sheet link: green.

Sheet Declarations
A1: Declarations (Worked Example 16.1, Step 1; Table 16.1; Online Appendix Remark 16.B.1). Money in $ million.
A3: Quantity | B3: Value | C3: Source
A4: The board's hurdle rate a year, r | B4: 0.1 | C4: Chapter 5
A5: A year's discount, beta = 1/(1 + r) | B5: =1/(1+B4) -> 0.90909091
A6: A dollar a year of savings from year 6 on, beta^6 / r | B6: =B5^6/B4 -> 5.6447393 | C6: $5.645 (Step 1; Chapter 12)
A7: Liquidity today | B7: 620 | C7: Volume I
A8: The board's floor | B8: 350
A9: Room above the floor | B9: =B7-B8 -> 270 | C9: $270m
A10: The sale's proceeds with the shared engineering team | B10: 112 | C10: Volume I, Worked Example 3.1
A11: The buyer's discount if Meridian keeps the team | B11: 20 | C11: Chapters 6-7 priced the team at $23.8m
A12: The sale's proceeds with the engineers kept, G | B12: =B10-B11 -> 92 | C12: $92m, at the start
A13: Cost of an automation round | B13: 120 | C13: Volume I, Worked Example 6.1
A14: Efficiency today | B14: 71
A15: Efficiency ceiling | B15: 85
A16: Share of the gap to the ceiling a round closes | B16: 0.5 | C16: A round halves the gap
A17: Savings a point of efficiency, a year | B17: 10
A18: Cash before a round | B18: 470 | C18: Chapter 5's commitments
A19: Cash at the end of year 6 | B19: 470 | C19: The board's end condition
A20: Line fees over the program, per $ of line | B20: 0.03 | C20: Volume I, Worked Example 15.1
A21: A quarter of delay | B21: 8 | C21: The transformation office
A22: The draw's depth with no delay (index points) | B22: 28
A23: Points of depth a quarter of delay removes | B23: 4 | C23: Depth 28 - 4 phi
A24: The board's appetite | B24: 0.05 | C24: At most a 5% chance below the floor in a quarter of 12
A25: Volume I's package: line | B25: 170 | C25: As Chapter 9 designed it on the book's paths
A26: Volume I's package: delay (quarters) | B26: 0.66757636 | C26: 0.668 quarter
A27: Volume I's package: levers, 0.03 l + 8 phi | B27: =B20*B25+B21*B26 -> 10.440611 | C27: $10.44m
A28: Liquidity at index 100 ($ billion) | B28: 0.62 | C28: Volume I, Chapter 1
A29: The plan without the draw: index today | B29: 100 | C29: relax(100, 112, 0.35, t)
A30: its long-run index | B30: 112
A31: its speed a year | B31: 0.35
A32: The draw's deepest point (years) | B32: 2 | C32: trough(D, 2, t) = D (t/2) e^(1 - t/2)
A33: The draw at its deepest, $m a point of depth | B33: =1000*B28/100 -> 6.2 | C33: $6.2m (Remark 16.B.1)
A34: The plan without the draw, long run | B34: =1000*B28*B30/100 -> 694.4 | C34: Toward $694m (Remark 16.B.1)
A35: Closure sizes: mean | B35: 120 | C35: Volume I, Chapter 8
A36: standard deviation | B36: 50
A37: gamma shape, (mean / sd)^2 | B37: =(B35/B36)^2 -> 5.76
A38: gamma scale, sd^2 / mean | B38: =B36^2/B35 -> 20.833333
A39: Volume I's closure buffer: the 90th-percentile closure | B39: =GAMMAINV(0.9,B37,B38) -> 186.86698 | C39: $186.9m (Volume I, Chapter 13)
A40: Closures a year | B40: 0.1
A41: Persistence of execution deviations | B41: 0.6 | C41: E' = 0.6 E + w
A42: Spread of the innovations w, a quarter | B42: 50
A43: Capability kept a quarter (Chapter 7) | B43: 0.975
A44: Cost of a point of capability hired (Chapter 7) | B44: 4
A45: A point of capability on the floor, in hiring | B45: =B43*B44 -> 3.9 | C45: $3.90m (Section 16.3)
A46: Capability with the engineers kept after the sale | B46: 58 | C46: Volume I, Worked Example 3.1
A47: Capability if the sale takes the engineers | B47: 53
A48: Capability the build and the rounds need | B48: 55
A50: Seeds (Online Appendix Remark 16.B.1)
A51: The book's 100,000 paths (Volume I, Chapter 8's stream) | B51: 8 | C51: Chapter 9
A52: The book's 100,000 fresh paths | B52: 26209 | C52: Every answer is checked on them
A53: Chapter 11's family: extra closures and thinning uniforms | B53: 1108 | C53: Book paths
A54: The lab's seed (new draws only) | B54: 26216 | C54: The notebook's Panel 6
A56: One account: liquidity at the end of quarter k is the plan without the draw less the draw (depth 28 - 4 phi times its shape), plus the deviations, less the closures the line leaves uncovered, plus the sale's proceeds and the automation program's cash so far.

Sheet Chapter5
A1: Chapter 5's automation program on its own account: the war chest and the payouts (Worked Example 16.1, Step 1; Chapter 5)
A2: Efficiency e_k = e_(k-1) + z_k (85 - e_(k-1))/2; savings S_k = 10 (e_k - 71); the war chest W_6 = 470, W_(k-1) = max{W_k + 120 z_k - S_k, 470 if z_k, 350 (from year 1)}; pay out everything above it. Value: payouts at 10 percent plus the year-6 savings forever.
A4: Year | B4: Round z (1 = yes) | C4: Efficiency | D4: Savings | E4: War chest | F4: Cash before the payout | G4: Payout | H4: Year-end cash | I4: beta^k | J4: PV of the payout | K4: Commitments kept
A5: 0 | C5: =Eff_0 -> 71 | E5: =MAX(E6+Round_cost*B6-D6,IF(B6=1,Pre_cash,-1000000000),-1000000000) -> 535 | H5: =Liq_today -> 620
A6: 1 | B6: 1 | C6: =IF(B6=1,C5+Gap_share*(Eff_ceil-C5),C5) -> 78 | D6: =Save_pt*(C6-Eff_0) -> 70 | E6: =MAX(E7+Round_cost*B7-D7,IF(B7=1,Pre_cash,-1000000000),Floor_cash) -> 485 | F6: =H5-Round_cost*B6+D6 -> 570 | G6: =MAX(0,F6-E6) -> 85 | H6: =F6-G6 -> 485 | I6: =Beta_y^A6 -> 0.90909091 | J6: =I6*G6 -> 77.272727 | K6: =IF(AND(H6>=Floor_cash-0.000000001,IF(B6=1,H5>=Pre_cash-0.000000001,TRUE())),1,0) -> 1
A7: 2 | B7: 1 | C7: =IF(B7=1,C6+Gap_share*(Eff_ceil-C6),C6) -> 81.5 | D7: =Save_pt*(C7-Eff_0) -> 105 | E7: =MAX(E8+Round_cost*B8-D8,IF(B8=1,Pre_cash,-1000000000),Floor_cash) -> 470 | F7: =H6-Round_cost*B7+D7 -> 470 | G7: =MAX(0,F7-E7) -> 0 | H7: =F7-G7 -> 470 | I7: =Beta_y^A7 -> 0.82644628 | J7: =I7*G7 -> 0 | K7: =IF(AND(H7>=Floor_cash-0.000000001,IF(B7=1,H6>=Pre_cash-0.000000001,TRUE())),1,0) -> 1
A8: 3 | B8: 1 | C8: =IF(B8=1,C7+Gap_share*(Eff_ceil-C7),C7) -> 83.25 | D8: =Save_pt*(C8-Eff_0) -> 122.5 | E8: =MAX(E9+Round_cost*B9-D9,IF(B9=1,Pre_cash,-1000000000),Floor_cash) -> 350 | F8: =H7-Round_cost*B8+D8 -> 472.5 | G8: =MAX(0,F8-E8) -> 122.5 | H8: =F8-G8 -> 350 | I8: =Beta_y^A8 -> 0.7513148 | J8: =I8*G8 -> 92.036063 | K8: =IF(AND(H8>=Floor_cash-0.000000001,IF(B8=1,H7>=Pre_cash-0.000000001,TRUE())),1,0) -> 1
A9: 4 | B9: 0 | C9: =IF(B9=1,C8+Gap_share*(Eff_ceil-C8),C8) -> 83.25 | D9: =Save_pt*(C9-Eff_0) -> 122.5 | E9: =MAX(E10+Round_cost*B10-D10,IF(B10=1,Pre_cash,-1000000000),Floor_cash) -> 350 | F9: =H8-Round_cost*B9+D9 -> 472.5 | G9: =MAX(0,F9-E9) -> 122.5 | H9: =F9-G9 -> 350 | I9: =Beta_y^A9 -> 0.68301346 | J9: =I9*G9 -> 83.669148 | K9: =IF(AND(H9>=Floor_cash-0.000000001,IF(B9=1,H8>=Pre_cash-0.000000001,TRUE())),1,0) -> 1
A10: 5 | B10: 0 | C10: =IF(B10=1,C9+Gap_share*(Eff_ceil-C9),C9) -> 83.25 | D10: =Save_pt*(C10-Eff_0) -> 122.5 | E10: =MAX(E11+Round_cost*B11-D11,IF(B11=1,Pre_cash,-1000000000),Floor_cash) -> 350 | F10: =H9-Round_cost*B10+D10 -> 472.5 | G10: =MAX(0,F10-E10) -> 122.5 | H10: =F10-G10 -> 350 | I10: =Beta_y^A10 -> 0.62092132 | J10: =I10*G10 -> 76.062862 | K10: =IF(AND(H10>=Floor_cash-0.000000001,IF(B10=1,H9>=Pre_cash-0.000000001,TRUE())),1,0) -> 1
A11: 6 | B11: 0 | C11: =IF(B11=1,C10+Gap_share*(Eff_ceil-C10),C10) -> 83.25 | D11: =Save_pt*(C11-Eff_0) -> 122.5 | E11: =MAX(End_cash,Floor_cash) -> 470 | F11: =H10-Round_cost*B11+D11 -> 472.5 | G11: =MAX(0,F11-E11) -> 2.5 | H11: =F11-G11 -> 470 | I11: =Beta_y^A11 -> 0.56447393 | J11: =I11*G11 -> 1.4111848 | K11: =IF(AND(H11>=Floor_cash-0.000000001,IF(B11=1,H10>=Pre_cash-0.000000001,TRUE())),1,0) -> 1
A13: Payouts at 10 percent | B13: =SUM(J6:J11) -> 330.45199 | C13: $330.45m
A14: The year-6 savings forever, beta^6 S_6 / r | B14: =I11*D11/R_hurdle -> 691.48056 | C14: $691.48m
A15: Value of Chapter 5's plan alone | B15: =B13+B14 -> 1021.9325 | C15: $1,021.93m (Worked Example 5.1)
A16: Every commitment kept (1 = yes) | B16: =IF(AND(SUM(K6:K11)=6,H11>=End_cash-0.000000001),1,0) -> 1 | C16: Floor at year ends, 470 before a round, 470 in year 6
A18: The rounds (column B) are Chapter 5's best plan; change them to see another schedule's war chest.

Sheet OneAccount
A1: One account, quarter by quarter, and the joint check at the binding quarter (Theorem 16.1(i); Worked Example 16.1, Steps 1-2; Figure 16.1)
A2: Volume I's plan: the plan without the draw 1000 x 0.62 x relax(100, 112, 0.35, t)/100 less the depth times the draw's shape 1000 x 0.62 x (t/2) e^(1 - t/2)/100. The automation program's cash: a round at the start of its year, savings evenly over the year, payouts at year ends counted from the next quarter. With no deviations and no closures; the breach chances on the paths are the engine's.
A4: Quarter | B4: Years in | C4: Plan without the draw | D4: Draw per point of depth | E4: Year | F4: Quarter of the year | G4: Volume I's plan (its package) | H4: Automation cash: pieces | I4: One account: pieces, with the sale | J4: Margin: pieces, with the sale | K4: Margin: pieces, without the sale | L4: The program's plan (its package) | M4: Automation cash: program | N4: One account: program | O4: Margin: program
A5: 1 | B5: =A5/4 -> 0.25 | C5: =1000*Idx_bn*(Rel_inf+(Rel_0-Rel_inf)*EXP(-Rel_k*B5))/100 -> 626.23332 | D5: =1000*Idx_bn*(B5/Tau_draw)*EXP(1-B5/Tau_draw)/100 -> 1.8591284 | E5: =INT((A5-1)/4)+1 -> 1 | F5: =MOD(A5-1,4)+1 -> 1 | G5: =C5-(Depth_0-Depth_pq*Pkg_delay)*D5 -> 579.14216 | H5: =INDEX($E$21:$E$23,E5)-Round_cost*INDEX($B$22:$B$24,E5)+F5*INDEX($C$22:$C$24,E5)/4 -> -102.5 | I5: =G5+H5+Sale_G -> 568.64216 | J5: =I5-Floor_cash -> 218.64216 | K5: =G5+H5-Floor_cash -> 126.64216 | L5: =C5-(Depth_0-Depth_pq*$B$28)*D5 -> 589.58233 | M5: =INDEX($G$21:$G$23,E5)-Round_cost*INDEX($B$22:$B$24,E5)+F5*INDEX($C$22:$C$24,E5)/4 -> -102.5 | N5: =L5+M5+Sale_G -> 579.08233 | O5: =N5-Floor_cash -> 229.08233
A6: 2 | B6: =A6/4 -> 0.5 | C6: =1000*Idx_bn*(Rel_inf+(Rel_0-Rel_inf)*EXP(-Rel_k*B6))/100 -> 631.9444 | D6: =1000*Idx_bn*(B6/Tau_draw)*EXP(1-B6/Tau_draw)/100 -> 3.28135 | E6: =INT((A6-1)/4)+1 -> 1 | F6: =MOD(A6-1,4)+1 -> 2 | G6: =C6-(Depth_0-Depth_pq*Pkg_delay)*D6 -> 548.8288 | H6: =INDEX($E$21:$E$23,E6)-Round_cost*INDEX($B$22:$B$24,E6)+F6*INDEX($C$22:$C$24,E6)/4 -> -85 | I6: =G6+H6+Sale_G -> 555.8288 | J6: =I6-Floor_cash -> 205.8288 | K6: =G6+H6-Floor_cash -> 113.8288 | L6: =C6-(Depth_0-Depth_pq*$B$28)*D6 -> 567.25563 | M6: =INDEX($G$21:$G$23,E6)-Round_cost*INDEX($B$22:$B$24,E6)+F6*INDEX($C$22:$C$24,E6)/4 -> -85 | N6: =L6+M6+Sale_G -> 574.25563 | O6: =N6-Floor_cash -> 224.25563
A7: 3 | B7: =A7/4 -> 0.75 | C7: =1000*Idx_bn*(Rel_inf+(Rel_0-Rel_inf)*EXP(-Rel_k*B7))/100 -> 637.177 | D7: =1000*Idx_bn*(B7/Tau_draw)*EXP(1-B7/Tau_draw)/100 -> 4.3436719 | E7: =INT((A7-1)/4)+1 -> 1 | F7: =MOD(A7-1,4)+1 -> 3 | G7: =C7-(Depth_0-Depth_pq*Pkg_delay)*D7 -> 527.15312 | H7: =INDEX($E$21:$E$23,E7)-Round_cost*INDEX($B$22:$B$24,E7)+F7*INDEX($C$22:$C$24,E7)/4 -> -67.5 | I7: =G7+H7+Sale_G -> 551.65312 | J7: =I7-Floor_cash -> 201.65312 | K7: =G7+H7-Floor_cash -> 109.65312 | L7: =C7-(Depth_0-Depth_pq*$B$28)*D7 -> 551.54555 | M7: =INDEX($G$21:$G$23,E7)-Round_cost*INDEX($B$22:$B$24,E7)+F7*INDEX($C$22:$C$24,E7)/4 -> -67.5 | N7: =L7+M7+Sale_G -> 576.04555 | O7: =N7-Floor_cash -> 226.04555
A8: 4 | B8: =A8/4 -> 1 | C8: =1000*Idx_bn*(Rel_inf+(Rel_0-Rel_inf)*EXP(-Rel_k*B8))/100 -> 641.97121 | D8: =1000*Idx_bn*(B8/Tau_draw)*EXP(1-B8/Tau_draw)/100 -> 5.1110359 | E8: =INT((A8-1)/4)+1 -> 1 | F8: =MOD(A8-1,4)+1 -> 4 | G8: =C8-(Depth_0-Depth_pq*Pkg_delay)*D8 -> 512.51023 | H8: =INDEX($E$21:$E$23,E8)-Round_cost*INDEX($B$22:$B$24,E8)+F8*INDEX($C$22:$C$24,E8)/4 -> -50 | I8: =G8+H8+Sale_G -> 554.51023 | J8: =I8-Floor_cash -> 204.51023 | K8: =G8+H8-Floor_cash -> 112.51023 | L8: =C8-(Depth_0-Depth_pq*$B$28)*D8 -> 541.21189 | M8: =INDEX($G$21:$G$23,E8)-Round_cost*INDEX($B$22:$B$24,E8)+F8*INDEX($C$22:$C$24,E8)/4 -> -50 | N8: =L8+M8+Sale_G -> 583.21189 | O8: =N8-Floor_cash -> 233.21189
A9: 5 | B9: =A9/4 -> 1.25 | C9: =1000*Idx_bn*(Rel_inf+(Rel_0-Rel_inf)*EXP(-Rel_k*B9))/100 -> 646.36375 | D9: =1000*Idx_bn*(B9/Tau_draw)*EXP(1-B9/Tau_draw)/100 -> 5.6380917 | E9: =INT((A9-1)/4)+1 -> 2 | F9: =MOD(A9-1,4)+1 -> 1 | G9: =C9-(Depth_0-Depth_pq*Pkg_delay)*D9 -> 503.55261 | H9: =INDEX($E$21:$E$23,E9)-Round_cost*INDEX($B$22:$B$24,E9)+F9*INDEX($C$22:$C$24,E9)/4 -> -228.75 | I9: =G9+H9+Sale_G -> 366.80261 | J9: =I9-Floor_cash -> 16.802608 | K9: =G9+H9-Floor_cash -> -75.197392 | L9: =C9-(Depth_0-Depth_pq*$B$28)*D9 -> 535.21401 | M9: =INDEX($G$21:$G$23,E9)-Round_cost*INDEX($B$22:$B$24,E9)+F9*INDEX($C$22:$C$24,E9)/4 -> -143.75 | N9: =L9+M9+Sale_G -> 483.46401 | O9: =N9-Floor_cash -> 133.46401
A10: 6 | B10: =A10/4 -> 1.5 | C10: =1000*Idx_bn*(Rel_inf+(Rel_0-Rel_inf)*EXP(-Rel_k*B10))/100 -> 650.38828 | D10: =1000*Idx_bn*(B10/Tau_draw)*EXP(1-B10/Tau_draw)/100 -> 5.9707182 | E10: =INT((A10-1)/4)+1 -> 2 | F10: =MOD(A10-1,4)+1 -> 2 | G10: =C10-(Depth_0-Depth_pq*Pkg_delay)*D10 -> 499.15181 | H10: =INDEX($E$21:$E$23,E10)-Round_cost*INDEX($B$22:$B$24,E10)+F10*INDEX($C$22:$C$24,E10)/4 -> -202.5 | I10: =G10+H10+Sale_G -> 388.65181 | J10: =I10-Floor_cash -> 38.651813 | K10: =G10+H10-Floor_cash -> -53.348187 | L10: =C10-(Depth_0-Depth_pq*$B$28)*D10 -> 532.68112 | M10: =INDEX($G$21:$G$23,E10)-Round_cost*INDEX($B$22:$B$24,E10)+F10*INDEX($C$22:$C$24,E10)/4 -> -117.5 | N10: =L10+M10+Sale_G -> 507.18112 | O10: =N10-Floor_cash -> 157.18112
A11: 7 | B11: =A11/4 -> 1.75 | C11: =1000*Idx_bn*(Rel_inf+(Rel_0-Rel_inf)*EXP(-Rel_k*B11))/100 -> 654.07563 | D11: =1000*Idx_bn*(B11/Tau_draw)*EXP(1-B11/Tau_draw)/100 -> 6.1473304 | E11: =INT((A11-1)/4)+1 -> 2 | F11: =MOD(A11-1,4)+1 -> 3 | G11: =C11-(Depth_0-Depth_pq*Pkg_delay)*D11 -> 498.36563 | H11: =INDEX($E$21:$E$23,E11)-Round_cost*INDEX($B$22:$B$24,E11)+F11*INDEX($C$22:$C$24,E11)/4 -> -176.25 | I11: =G11+H11+Sale_G -> 414.11563 | J11: =I11-Floor_cash -> 64.115632 | K11: =G11+H11-Floor_cash -> -27.884368 | L11: =C11-(Depth_0-Depth_pq*$B$28)*D11 -> 532.88673 | M11: =INDEX($G$21:$G$23,E11)-Round_cost*INDEX($B$22:$B$24,E11)+F11*INDEX($C$22:$C$24,E11)/4 -> -91.25 | N11: =L11+M11+Sale_G -> 533.63673 | O11: =N11-Floor_cash -> 183.63673
A12: 8 | B12: =A12/4 -> 2 | C12: =1000*Idx_bn*(Rel_inf+(Rel_0-Rel_inf)*EXP(-Rel_k*B12))/100 -> 657.45405 | D12: =1000*Idx_bn*(B12/Tau_draw)*EXP(1-B12/Tau_draw)/100 -> 6.2 | E12: =INT((A12-1)/4)+1 -> 2 | F12: =MOD(A12-1,4)+1 -> 4 | G12: =C12-(Depth_0-Depth_pq*Pkg_delay)*D12 -> 500.40995 | H12: =INDEX($E$21:$E$23,E12)-Round_cost*INDEX($B$22:$B$24,E12)+F12*INDEX($C$22:$C$24,E12)/4 -> -150 | I12: =G12+H12+Sale_G -> 442.40995 | J12: =I12-Floor_cash -> 92.409947 | K12: =G12+H12-Floor_cash -> 0.40994716 | L12: =C12-(Depth_0-Depth_pq*$B$28)*D12 -> 535.22682 | M12: =INDEX($G$21:$G$23,E12)-Round_cost*INDEX($B$22:$B$24,E12)+F12*INDEX($C$22:$C$24,E12)/4 -> -65 | N12: =L12+M12+Sale_G -> 562.22682 | O12: =N12-Floor_cash -> 212.22682
A13: 9 | B13: =A13/4 -> 2.25 | C13: =1000*Idx_bn*(Rel_inf+(Rel_0-Rel_inf)*EXP(-Rel_k*B13))/100 -> 660.54943 | D13: =1000*Idx_bn*(B13/Tau_draw)*EXP(1-B13/Tau_draw)/100 -> 6.1554159 | E13: =INT((A13-1)/4)+1 -> 3 | F13: =MOD(A13-1,4)+1 -> 1 | G13: =C13-(Depth_0-Depth_pq*Pkg_delay)*D13 -> 504.63462 | H13: =INDEX($E$21:$E$23,E13)-Round_cost*INDEX($B$22:$B$24,E13)+F13*INDEX($C$22:$C$24,E13)/4 -> -239.375 | I13: =G13+H13+Sale_G -> 357.25962 | J13: =I13-Floor_cash -> 7.259622 | K13: =G13+H13-Floor_cash -> -84.740378 | L13: =C13-(Depth_0-Depth_pq*$B$28)*D13 -> 539.20113 | M13: =INDEX($G$21:$G$23,E13)-Round_cost*INDEX($B$22:$B$24,E13)+F13*INDEX($C$22:$C$24,E13)/4 -> -154.375 | N13: =L13+M13+Sale_G -> 476.82613 | O13: =N13-Floor_cash -> 126.82613
A14: 10 | B14: =A14/4 -> 2.5 | C14: =1000*Idx_bn*(Rel_inf+(Rel_0-Rel_inf)*EXP(-Rel_k*B14))/100 -> 663.38547 | D14: =1000*Idx_bn*(B14/Tau_draw)*EXP(1-B14/Tau_draw)/100 -> 6.0357061 | E14: =INT((A14-1)/4)+1 -> 3 | F14: =MOD(A14-1,4)+1 -> 2 | G14: =C14-(Depth_0-Depth_pq*Pkg_delay)*D14 -> 510.50287 | H14: =INDEX($E$21:$E$23,E14)-Round_cost*INDEX($B$22:$B$24,E14)+F14*INDEX($C$22:$C$24,E14)/4 -> -208.75 | I14: =G14+H14+Sale_G -> 393.75287 | J14: =I14-Floor_cash -> 43.752875 | K14: =G14+H14-Floor_cash -> -48.247125 | L14: =C14-(Depth_0-Depth_pq*$B$28)*D14 -> 544.39713 | M14: =INDEX($G$21:$G$23,E14)-Round_cost*INDEX($B$22:$B$24,E14)+F14*INDEX($C$22:$C$24,E14)/4 -> -123.75 | N14: =L14+M14+Sale_G -> 512.64713 | O14: =N14-Floor_cash -> 162.64713
A15: 11 | B15: =A15/4 -> 2.75 | C15: =1000*Idx_bn*(Rel_inf+(Rel_0-Rel_inf)*EXP(-Rel_k*B15))/100 -> 665.9839 | D15: =1000*Idx_bn*(B15/Tau_draw)*EXP(1-B15/Tau_draw)/100 -> 5.8591411 | E15: =INT((A15-1)/4)+1 -> 3 | F15: =MOD(A15-1,4)+1 -> 3 | G15: =C15-(Depth_0-Depth_pq*Pkg_delay)*D15 -> 517.57364 | H15: =INDEX($E$21:$E$23,E15)-Round_cost*INDEX($B$22:$B$24,E15)+F15*INDEX($C$22:$C$24,E15)/4 -> -178.125 | I15: =G15+H15+Sale_G -> 431.44864 | J15: =I15-Floor_cash -> 81.448644 | K15: =G15+H15-Floor_cash -> -10.551356 | L15: =C15-(Depth_0-Depth_pq*$B$28)*D15 -> 550.47638 | M15: =INDEX($G$21:$G$23,E15)-Round_cost*INDEX($B$22:$B$24,E15)+F15*INDEX($C$22:$C$24,E15)/4 -> -93.125 | N15: =L15+M15+Sale_G -> 549.35138 | O15: =N15-Floor_cash -> 199.35138
A16: 12 | B16: =A16/4 -> 3 | C16: =1000*Idx_bn*(Rel_inf+(Rel_0-Rel_inf)*EXP(-Rel_k*B16))/100 -> 668.36463 | D16: =1000*Idx_bn*(B16/Tau_draw)*EXP(1-B16/Tau_draw)/100 -> 5.6407351 | E16: =INT((A16-1)/4)+1 -> 3 | F16: =MOD(A16-1,4)+1 -> 4 | G16: =C16-(Depth_0-Depth_pq*Pkg_delay)*D16 -> 525.48653 | H16: =INDEX($E$21:$E$23,E16)-Round_cost*INDEX($B$22:$B$24,E16)+F16*INDEX($C$22:$C$24,E16)/4 -> -147.5 | I16: =G16+H16+Sale_G -> 469.98653 | J16: =I16-Floor_cash -> 119.98653 | K16: =G16+H16-Floor_cash -> 27.986533 | L16: =C16-(Depth_0-Depth_pq*$B$28)*D16 -> 557.16278 | M16: =INDEX($G$21:$G$23,E16)-Round_cost*INDEX($B$22:$B$24,E16)+F16*INDEX($C$22:$C$24,E16)/4 -> -62.5 | N16: =L16+M16+Sale_G -> 586.66278 | O16: =N16-Floor_cash -> 236.66278
A20: Year | B20: Round z | C20: Savings | D20: Pieces: payout | E20: Pieces: cash so far | F20: Program: payout | G20: Program: cash so far
A21: 0 | E21: 0 | G21: 0
A22: 1 | B22: =Chapter5!B6 -> 1 | C22: =Chapter5!D6 -> 70 | D22: =Chapter5!G6 -> 85 | E22: =E21-Round_cost*B22+C22-D22 -> -135 | F22: 0 | G22: =G21-Round_cost*B22+C22-F22 -> -50 | H22: The year-3 payout is made at the end of the build: it counts from quarter 13, after the window.
A23: 2 | B23: =Chapter5!B7 -> 1 | C23: =Chapter5!D7 -> 105 | D23: =Chapter5!G7 -> 0 | E23: =E22-Round_cost*B23+C23-D23 -> -150 | F23: 0 | G23: =G22-Round_cost*B23+C23-F23 -> -65
A24: 3 | B24: =Chapter5!B8 -> 1 | C24: =Chapter5!D8 -> 122.5 | D24: 0 | E24: =E23-Round_cost*B24+C24-D24 -> -147.5 | F24: 0 | G24: =G23-Round_cost*B24+C24-F24 -> -62.5
A27: The program's line (engine) | B27: 160 | C27: Worked Example 16.1, Step 4
A28: The program's delay (engine) | B28: 2.0714825 | C28: 2.071 quarters
A30: Joint check at the binding quarter | B30: Binding quarter | C30: The build's draw | D30: Rounds less savings | E30: Payouts made | F30: Closure buffer | G30: Claims | H30: Room | I30: Left
A31: Pieces, no sale | B31: =MATCH(MIN(K5:K16),K5:K16,0) -> 9 | C31: =Liq_today-INDEX(G5:G16,B31) -> 115.36538 | D31: =-(INDEX(H5:H16,B31)+E31) -> 154.375 | E31: =IF(B31>=5,Chapter5!G6,0)+IF(B31>=9,Chapter5!G7,0) -> 85 | F31: =MAX(P90_closure-Pkg_line,0) -> 16.866976 | G31: =C31+D31+E31+F31 -> 371.60735 | H31: =Room_0+0 -> 270 | I31: =H31-G31 -> -101.60735
A32: Pieces, with the sale | B32: =MATCH(MIN(J5:J16),J5:J16,0) -> 9 | C32: =Liq_today-INDEX(G5:G16,B32) -> 115.36538 | D32: =-(INDEX(H5:H16,B32)+E32) -> 154.375 | E32: =IF(B32>=5,Chapter5!G6,0)+IF(B32>=9,Chapter5!G7,0) -> 85 | F32: =MAX(P90_closure-Pkg_line,0) -> 16.866976 | G32: =C32+D32+E32+F32 -> 371.60735 | H32: =Room_0+Sale_G -> 362 | I32: =H32-G32 -> -9.6073544
A33: Program | B33: =MATCH(MIN(O5:O16),O5:O16,0) -> 9 | C33: =Liq_today-INDEX(L5:L16,B33) -> 80.798874 | D33: =-(INDEX(M5:M16,B33)+E33) -> 154.375 | E33: =IF(B33>=5,OneAccount!$F$22,0)+IF(B33>=9,OneAccount!$F$23,0) -> 0 | F33: =MAX(P90_closure-$B$27,0) -> 26.866976 | G33: =C33+D33+E33+F33 -> 262.04085 | H33: =Room_0+Sale_G -> 362 | I33: =H33-G33 -> 99.959149
A34: With no deviations and no closures the pieces' plan keeps 7.3 above the floor at quarter 9; the closure buffer (the 90th-percentile closure less the line) takes their claims past the room.
A36: The build alone (Volume I's joint check) | B36: Value | C36: Note
A37: Its deepest quarter | B37: =MATCH(MIN(G5:G16),G5:G16,0) -> 7 | C37: Quarter 7
A38: Its deepest draw | B38: =Liq_today-MIN(G5:G16) -> 121.63437 | C38: $121.6m
A39: The closure buffer the line leaves uncovered | B39: =MAX(P90_closure-Pkg_line,0) -> 16.866976 | C39: $16.9m
A40: Draw and buffer, against the room of 270 | B40: =B38+B39 -> 138.50134 | C40: Fits: Volume I, Worked Example 16.1
A42: Year end | B42: Volume I's plan, depth 28 | C42: Note
A43: 0 | B43: =1000*Idx_bn*((Rel_inf+(Rel_0-Rel_inf)*EXP(-Rel_k*A43))-Depth_0*(A43/Tau_draw)*EXP(1-A43/Tau_draw))/100 -> 620 | C43: After the build the plan continues by its own shapes, the delayed spending caught up (depth 28).
A44: 1 | B44: =1000*Idx_bn*((Rel_inf+(Rel_0-Rel_inf)*EXP(-Rel_k*A44))-Depth_0*(A44/Tau_draw)*EXP(1-A44/Tau_draw))/100 -> 498.8622
A45: 2 | B45: =1000*Idx_bn*((Rel_inf+(Rel_0-Rel_inf)*EXP(-Rel_k*A45))-Depth_0*(A45/Tau_draw)*EXP(1-A45/Tau_draw))/100 -> 483.85405
A46: 3 | B46: =1000*Idx_bn*((Rel_inf+(Rel_0-Rel_inf)*EXP(-Rel_k*A46))-Depth_0*(A46/Tau_draw)*EXP(1-A46/Tau_draw))/100 -> 510.42405
A47: 4 | B47: =1000*Idx_bn*((Rel_inf+(Rel_0-Rel_inf)*EXP(-Rel_k*A47))-Depth_0*(A47/Tau_draw)*EXP(1-A47/Tau_draw))/100 -> 548.32544
A48: 5 | B48: =1000*Idx_bn*((Rel_inf+(Rel_0-Rel_inf)*EXP(-Rel_k*A48))-Depth_0*(A48/Tau_draw)*EXP(1-A48/Tau_draw))/100 -> 584.63273
A49: 6 | B49: =1000*Idx_bn*((Rel_inf+(Rel_0-Rel_inf)*EXP(-Rel_k*A49))-Depth_0*(A49/Tau_draw)*EXP(1-A49/Tau_draw))/100 -> 614.80663

Sheet Programs
A1: Every program on one account: the war chest and payouts after the build, the levers and the value (Worked Example 16.1, Steps 3-4; Theorem 16.2; Table 16.3; Figure 16.2(a))
A2: Payouts in years 1-2 are the book's (each program's best, from the book's search); after the build each year pays out everything above the war chest on Volume I's planned path. The package (line, delay) is the engine's cheapest for the appetite on the book's 100,000 paths; the levers and the value are formulas.
A3: Program | B3: Rounds (years) | C3: Sale at the start | D3: Sale in year 4 | E3: Payout y1 | F3: Payout y2 | G3: Line (engine) | H3: Delay (engine) | I3: Levers | J3: Payout y3 | K3: Payout y4 | L3: Payout y5 | M3: Payout y6 | N3: Before the levers | O3: Value | P3: Below the best | Q3: Kept (1 = yes)
A4: Rounds in years 1, 2, 3 | B4: 1, 2, 3 | C4: =O23 -> 92 | D4: =O24 -> 0 | E4: =H25 -> 0 | F4: =H26 -> 0 | G4: =O25 -> 160 | H4: =O26 -> 2.0714825 | I4: =O27 -> 21.37186 | J4: =H27 -> 189.92405 | K4: =H28 -> 160.4014 | L4: =H29 -> 158.80729 | M4: =H30 -> 32.673897 | N4: =O28 -> 1060.78 | O4: =O29 -> 1039.4082 | P4: =$O$4-O4 -> 0 | Q4: =O30 -> 1
A5: Rounds in years 1, 2, 4 | B5: 1, 2, 4 | C5: =O35 -> 92 | D5: =O36 -> 0 | E5: =H37 -> 0 | F5: =H38 -> 77 | G5: =O37 -> 160 | H5: =O38 -> 1.4770281 | I5: =O39 -> 16.616225 | J5: =H39 -> 95.424048 | K5: =H40 -> 160.4014 | L5: =H41 -> 158.80729 | M5: =H42 -> 32.673897 | N5: =O40 -> 1053.4171 | O5: =O41 -> 1036.8009 | P5: =$O$4-O5 -> 2.6072499 | Q5: =O42 -> 1
A6: Rounds in years 1, 3, 4 | B6: 1, 3, 4 | C6: =O47 -> 92 | D6: =O48 -> 0 | E6: =H49 -> 35 | F6: =H50 -> 0 | G6: =O49 -> 140 | H6: =O50 -> 0.011534323 | I6: =O51 -> 4.2922746 | J6: =H51 -> 102.42405 | K6: =H52 -> 160.4014 | L6: =H53 -> 158.80729 | M6: =H54 -> 32.673897 | N6: =O52 -> 1026.8582 | O6: =O53 -> 1022.5659 | P6: =$O$4-O6 -> 16.842278 | Q6: =O54 -> 1
A7: Rounds in years 1, 4, 5 | B7: 1, 4, 5 | C7: =O59 -> 92 | D7: =O60 -> 0 | E7: =H61 -> 61 | F7: =H62 -> 65 | G7: =O61 -> 140 | H7: =O62 -> 0 | I7: =O63 -> 4.2 | J7: =H63 -> 96.424048 | K7: =H64 -> 22.901396 | L7: =H65 -> 158.80729 | M7: =H66 -> 32.673897 | N7: =O64 -> 1005.7913 | O7: =O65 -> 1001.5913 | P7: =$O$4-O7 -> 37.816871 | Q7: =O66 -> 1
A8: Rounds in years 2, 3, 4 | B8: 2, 3, 4 | C8: =O71 -> 92 | D8: =O72 -> 0 | E8: =H73 -> 0 | F8: =H74 -> 0 | G8: =O73 -> 170 | H8: =O74 -> 1.2585203 | I8: =O75 -> 15.168162 | J8: =H75 -> 67.424048 | K8: =H76 -> 160.4014 | L8: =H77 -> 158.80729 | M8: =H78 -> 32.673897 | N8: =O76 -> 968.74395 | O8: =O77 -> 953.57579 | P8: =$O$4-O8 -> 85.832365 | Q8: =O78 -> 1
A9: Rounds in years 2, 4, 5 | B9: 2, 4, 5 | C9: =O83 -> 92 | D9: =O84 -> 0 | E9: =H85 -> 0 | F9: =H86 -> 48 | G9: =O85 -> 155 | H9: =O86 -> 0.006246131 | I9: =O87 -> 4.699969 | J9: =H87 -> 104.42405 | K9: =H88 -> 22.901396 | L9: =H89 -> 158.80729 | M9: =H90 -> 32.673897 | N9: =O88 -> 942.29767 | O9: =O89 -> 937.5977 | P9: =$O$4-O9 -> 101.81045 | Q9: =O90 -> 1
A10: Rounds in years 3, 4, 5 | B10: 3, 4, 5 | C10: =O95 -> 92 | D10: =O96 -> 0 | E10: =H97 -> 8 | F10: =H98 -> 0 | G10: =O97 -> 140 | H10: =O98 -> 0 | I10: =O99 -> 4.2 | J10: =H99 -> 74.424048 | K10: =H100 -> 22.901396 | L10: =H101 -> 158.80729 | M10: =H102 -> 32.673897 | N10: =O100 -> 887.36153 | O10: =O101 -> 883.16153 | P10: =$O$4-O10 -> 156.24662 | Q10: =O102 -> 1
A11: Rounds in years 4, 5, 6 | B11: 4, 5, 6 | C11: =O107 -> 92 | D11: =O108 -> 0 | E11: =H109 -> 64 | F11: =H110 -> 20 | G11: =O109 -> 135 | H11: =O110 -> 0 | I11: =O111 -> 4.05 | J11: =H111 -> 36.325444 | K11: =H112 -> 0 | L11: =H113 -> 21.307285 | M11: =H114 -> 32.673897 | N11: =O112 -> 825.15686 | O11: =O113 -> 821.10686 | P11: =$O$4-O11 -> 218.30129 | Q11: =O114 -> 1
A12: No sale | B12: 1, 2, 3 | C12: =O119 -> 0 | D12: =O120 -> 0 | E12: =H121 -> 0 | F12: =H122 -> 0 | G12: =O121 -> 165 | H12: =O122 -> 5.970015 | I12: =O123 -> 52.71012 | J12: =H123 -> 97.924048 | K12: =H124 -> 160.4014 | L12: =H125 -> 158.80729 | M12: =H126 -> 32.673897 | N12: =O124 -> 991.65906 | O12: =O125 -> 938.94894 | P12: =$O$4-O12 -> 100.45922 | Q12: =O126 -> 1
A13: Sale after the build | B13: 1, 2, 3 | C13: =O131 -> 0 | D13: =O132 -> 92 | E13: =H133 -> 0 | F13: =H134 -> 0 | G13: =O133 -> 165 | H13: =O134 -> 5.970015 | I13: =O135 -> 52.71012 | J13: =H135 -> 97.924048 | K13: =H136 -> 252.4014 | L13: =H137 -> 158.80729 | M13: =H138 -> 32.673897 | N13: =O136 -> 1054.4963 | O13: =O137 -> 1001.7862 | P13: =$O$4-O13 -> 37.621984 | Q13: =O138 -> 1
A14: One more dollar of room at the start | B14: 1, 2, 3 | C14: =O143 -> 93 | D14: =O144 -> 0 | E14: =H145 -> 0 | F14: =H146 -> 0 | G14: =O145 -> 160 | H14: =O146 -> 2.0293931 | I14: =O147 -> 21.035145 | J14: =H147 -> 190.92405 | K14: =H148 -> 160.4014 | L14: =H149 -> 158.80729 | M14: =H150 -> 32.673897 | N14: =O148 -> 1061.5313 | O14: =O149 -> 1040.4962 | P14: =$O$4-O14 -> -1.0880297 | Q14: =O150 -> 1
A15: Round 3 in year 4, payouts held (the trigger's other branch) | B15: 1, 2, 4 | C15: =O155 -> 92 | D15: =O156 -> 0 | E15: =H157 -> 0 | F15: =H158 -> 0 | G15: =O157 -> 0 | H15: =O158 -> 0 | I15: – | J15: =H159 -> 172.42405 | K15: =H160 -> 160.4014 | L15: =H161 -> 158.80729 | M15: =H162 -> 32.673897 | N15: =O160 -> 1047.632 | O15: – | P15: – | Q15: =O162 -> 1
A16: Chapter 5's year-1 payout released | B16: 1, 2, 3 | C16: =O167 -> 92 | D16: =O168 -> 0 | E16: =H169 -> 85 | F16: =H170 -> 0 | G16: =O169 -> 165 | H16: =O170 -> 5.6336263 | I16: =O171 -> 50.01901 | J16: =H171 -> 104.92405 | K16: =H172 -> 160.4014 | L16: =H173 -> 158.80729 | M16: =H174 -> 32.673897 | N16: =O172 -> 1074.191 | O16: =O173 -> 1024.172 | P16: =$O$4-O16 -> 15.236181 | Q16: =O174 -> 1
A17: The round-3 branch's levers are not needed: under the trigger rule one package covers both branches (sheet Trigger), so only its value before the levers is used.
A22: Rounds in years 1, 2, 3
A23: Year | B23: Round z | C23: Efficiency | D23: Savings | E23: Volume I's plan | F23: War chest | G23: Cash before the payout | H23: Payout | I23: Cash after the payout | J23: beta^k | K23: PV of the payout | L23: Commitments kept | N23: Sale at the start, G | O23: =Sale_G -> 92
A24: 0 | C24: =Eff_0 -> 71 | E24: =INDEX(Plan_years,A24+1) -> 620 | N24: Sale in year 4, after the build | O24: 0
A25: 1 | B25: 1 | C25: =IF(B25=1,C24+Gap_share*(Eff_ceil-C24),C24) -> 78 | D25: =Save_pt*(C25-Eff_0) -> 70 | E25: =INDEX(Plan_years,A25+1) -> 498.8622 | H25: 0 | J25: =Beta_y^A25 -> 0.90909091 | K25: =J25*H25 -> 0 | N25: Line (engine) | O25: 160
A26: 2 | B26: 1 | C26: =IF(B26=1,C25+Gap_share*(Eff_ceil-C25),C25) -> 81.5 | D26: =Save_pt*(C26-Eff_0) -> 105 | E26: =INDEX(Plan_years,A26+1) -> 483.85405 | H26: 0 | J26: =Beta_y^A26 -> 0.82644628 | K26: =J26*H26 -> 0 | N26: Delay, quarters (engine) | O26: 2.0714825
A27: 3 | B27: 1 | C27: =IF(B27=1,C26+Gap_share*(Eff_ceil-C26),C26) -> 83.25 | D27: =Save_pt*(C27-Eff_0) -> 122.5 | E27: =INDEX(Plan_years,A27+1) -> 510.42405 | F27: =MAX(IF(B28=1,MAX((F28+Round_cost*B28-D28-(E28-E27)-$O$24),Pre_cash),(F28+Round_cost*B28-D28-(E28-E27)-$O$24)),Floor_cash) -> 350 | G27: =E27+$O$23+SUMPRODUCT(-Round_cost*B25:B27+D25:D27)-H25-H26 -> 539.92405 | H27: =MAX(0,G27-F27) -> 189.92405 | I27: =G27-H27 -> 350 | J27: =Beta_y^A27 -> 0.7513148 | K27: =J27*H27 -> 142.69275 | L27: =IF(AND(I27>=Floor_cash-0.000000001),1,0) -> 1 | N27: Levers, 0.03 l + 8 phi | O27: =Fee_line*O25+Cost_delay*O26 -> 21.37186
A28: 4 | B28: 0 | C28: =IF(B28=1,C27+Gap_share*(Eff_ceil-C27),C27) -> 83.25 | D28: =Save_pt*(C28-Eff_0) -> 122.5 | E28: =INDEX(Plan_years,A28+1) -> 548.32544 | F28: =MAX(IF(B29=1,MAX((F29+Round_cost*B29-D29-(E29-E28)),Pre_cash),(F29+Round_cost*B29-D29-(E29-E28))),Floor_cash) -> 350 | G28: =I27-Round_cost*B28+D28+(E28-E27)+$O$24 -> 510.4014 | H28: =MAX(0,G28-F28) -> 160.4014 | I28: =G28-H28 -> 350 | J28: =Beta_y^A28 -> 0.68301346 | K28: =J28*H28 -> 109.55631 | L28: =IF(AND(I28>=Floor_cash-0.000000001,IF(B28=1,I27>=Pre_cash-0.000000001,TRUE())),1,0) -> 1 | N28: Payouts and savings, before the levers | O28: =SUM(K25:K30)+J30*D30/R_hurdle -> 1060.78
A29: 5 | B29: 0 | C29: =IF(B29=1,C28+Gap_share*(Eff_ceil-C28),C28) -> 83.25 | D29: =Save_pt*(C29-Eff_0) -> 122.5 | E29: =INDEX(Plan_years,A29+1) -> 584.63273 | F29: =MAX(IF(B30=1,MAX((F30+Round_cost*B30-D30-(E30-E29)),Pre_cash),(F30+Round_cost*B30-D30-(E30-E29))),Floor_cash) -> 350 | G29: =I28-Round_cost*B29+D29+(E29-E28) -> 508.80729 | H29: =MAX(0,G29-F29) -> 158.80729 | I29: =G29-H29 -> 350 | J29: =Beta_y^A29 -> 0.62092132 | K29: =J29*H29 -> 98.60683 | L29: =IF(AND(I29>=Floor_cash-0.000000001,IF(B29=1,I28>=Pre_cash-0.000000001,TRUE())),1,0) -> 1 | N29: Value | O29: =O28-O27 -> 1039.4082
A30: 6 | B30: 0 | C30: =IF(B30=1,C29+Gap_share*(Eff_ceil-C29),C29) -> 83.25 | D30: =Save_pt*(C30-Eff_0) -> 122.5 | E30: =INDEX(Plan_years,A30+1) -> 614.80663 | F30: =End_cash -> 470 | G30: =I29-Round_cost*B30+D30+(E30-E29) -> 502.6739 | H30: =MAX(0,G30-F30) -> 32.673897 | I30: =G30-H30 -> 470 | J30: =Beta_y^A30 -> 0.56447393 | K30: =J30*H30 -> 18.443563 | L30: =IF(AND(I30>=Floor_cash-0.000000001,IF(B30=1,I29>=Pre_cash-0.000000001,TRUE()),I30>=End_cash-0.000000001),1,0) -> 1 | N30: Commitments after the build kept (1 = yes) | O30: =IF(SUM(L27:L30)=4,1,0) -> 1
A34: Rounds in years 1, 2, 4
A35: Year | B35: Round z | C35: Efficiency | D35: Savings | E35: Volume I's plan | F35: War chest | G35: Cash before the payout | H35: Payout | I35: Cash after the payout | J35: beta^k | K35: PV of the payout | L35: Commitments kept | N35: Sale at the start, G | O35: =Sale_G -> 92
A36: 0 | C36: =Eff_0 -> 71 | E36: =INDEX(Plan_years,A36+1) -> 620 | N36: Sale in year 4, after the build | O36: 0
A37: 1 | B37: 1 | C37: =IF(B37=1,C36+Gap_share*(Eff_ceil-C36),C36) -> 78 | D37: =Save_pt*(C37-Eff_0) -> 70 | E37: =INDEX(Plan_years,A37+1) -> 498.8622 | H37: 0 | J37: =Beta_y^A37 -> 0.90909091 | K37: =J37*H37 -> 0 | N37: Line (engine) | O37: 160
A38: 2 | B38: 1 | C38: =IF(B38=1,C37+Gap_share*(Eff_ceil-C37),C37) -> 81.5 | D38: =Save_pt*(C38-Eff_0) -> 105 | E38: =INDEX(Plan_years,A38+1) -> 483.85405 | H38: 77 | J38: =Beta_y^A38 -> 0.82644628 | K38: =J38*H38 -> 63.636364 | N38: Delay, quarters (engine) | O38: 1.4770281
A39: 3 | B39: 0 | C39: =IF(B39=1,C38+Gap_share*(Eff_ceil-C38),C38) -> 81.5 | D39: =Save_pt*(C39-Eff_0) -> 105 | E39: =INDEX(Plan_years,A39+1) -> 510.42405 | F39: =MAX(IF(B40=1,MAX((F40+Round_cost*B40-D40-(E40-E39)-$O$36),Pre_cash),(F40+Round_cost*B40-D40-(E40-E39)-$O$36)),Floor_cash) -> 470 | G39: =E39+$O$35+SUMPRODUCT(-Round_cost*B37:B39+D37:D39)-H37-H38 -> 565.42405 | H39: =MAX(0,G39-F39) -> 95.424048 | I39: =G39-H39 -> 470 | J39: =Beta_y^A39 -> 0.7513148 | K39: =J39*H39 -> 71.693499 | L39: =IF(AND(I39>=Floor_cash-0.000000001),1,0) -> 1 | N39: Levers, 0.03 l + 8 phi | O39: =Fee_line*O37+Cost_delay*O38 -> 16.616225
A40: 4 | B40: 1 | C40: =IF(B40=1,C39+Gap_share*(Eff_ceil-C39),C39) -> 83.25 | D40: =Save_pt*(C40-Eff_0) -> 122.5 | E40: =INDEX(Plan_years,A40+1) -> 548.32544 | F40: =MAX(IF(B41=1,MAX((F41+Round_cost*B41-D41-(E41-E40)),Pre_cash),(F41+Round_cost*B41-D41-(E41-E40))),Floor_cash) -> 350 | G40: =I39-Round_cost*B40+D40+(E40-E39)+$O$36 -> 510.4014 | H40: =MAX(0,G40-F40) -> 160.4014 | I40: =G40-H40 -> 350 | J40: =Beta_y^A40 -> 0.68301346 | K40: =J40*H40 -> 109.55631 | L40: =IF(AND(I40>=Floor_cash-0.000000001,IF(B40=1,I39>=Pre_cash-0.000000001,TRUE())),1,0) -> 1 | N40: Payouts and savings, before the levers | O40: =SUM(K37:K42)+J42*D42/R_hurdle -> 1053.4171
A41: 5 | B41: 0 | C41: =IF(B41=1,C40+Gap_share*(Eff_ceil-C40),C40) -> 83.25 | D41: =Save_pt*(C41-Eff_0) -> 122.5 | E41: =INDEX(Plan_years,A41+1) -> 584.63273 | F41: =MAX(IF(B42=1,MAX((F42+Round_cost*B42-D42-(E42-E41)),Pre_cash),(F42+Round_cost*B42-D42-(E42-E41))),Floor_cash) -> 350 | G41: =I40-Round_cost*B41+D41+(E41-E40) -> 508.80729 | H41: =MAX(0,G41-F41) -> 158.80729 | I41: =G41-H41 -> 350 | J41: =Beta_y^A41 -> 0.62092132 | K41: =J41*H41 -> 98.60683 | L41: =IF(AND(I41>=Floor_cash-0.000000001,IF(B41=1,I40>=Pre_cash-0.000000001,TRUE())),1,0) -> 1 | N41: Value | O41: =O40-O39 -> 1036.8009
A42: 6 | B42: 0 | C42: =IF(B42=1,C41+Gap_share*(Eff_ceil-C41),C41) -> 83.25 | D42: =Save_pt*(C42-Eff_0) -> 122.5 | E42: =INDEX(Plan_years,A42+1) -> 614.80663 | F42: =End_cash -> 470 | G42: =I41-Round_cost*B42+D42+(E42-E41) -> 502.6739 | H42: =MAX(0,G42-F42) -> 32.673897 | I42: =G42-H42 -> 470 | J42: =Beta_y^A42 -> 0.56447393 | K42: =J42*H42 -> 18.443563 | L42: =IF(AND(I42>=Floor_cash-0.000000001,IF(B42=1,I41>=Pre_cash-0.000000001,TRUE()),I42>=End_cash-0.000000001),1,0) -> 1 | N42: Commitments after the build kept (1 = yes) | O42: =IF(SUM(L39:L42)=4,1,0) -> 1
A46: Rounds in years 1, 3, 4
A47: Year | B47: Round z | C47: Efficiency | D47: Savings | E47: Volume I's plan | F47: War chest | G47: Cash before the payout | H47: Payout | I47: Cash after the payout | J47: beta^k | K47: PV of the payout | L47: Commitments kept | N47: Sale at the start, G | O47: =Sale_G -> 92
A48: 0 | C48: =Eff_0 -> 71 | E48: =INDEX(Plan_years,A48+1) -> 620 | N48: Sale in year 4, after the build | O48: 0
A49: 1 | B49: 1 | C49: =IF(B49=1,C48+Gap_share*(Eff_ceil-C48),C48) -> 78 | D49: =Save_pt*(C49-Eff_0) -> 70 | E49: =INDEX(Plan_years,A49+1) -> 498.8622 | H49: 35 | J49: =Beta_y^A49 -> 0.90909091 | K49: =J49*H49 -> 31.818182 | N49: Line (engine) | O49: 140
A50: 2 | B50: 0 | C50: =IF(B50=1,C49+Gap_share*(Eff_ceil-C49),C49) -> 78 | D50: =Save_pt*(C50-Eff_0) -> 70 | E50: =INDEX(Plan_years,A50+1) -> 483.85405 | H50: 0 | J50: =Beta_y^A50 -> 0.82644628 | K50: =J50*H50 -> 0 | N50: Delay, quarters (engine) | O50: 0.011534323
A51: 3 | B51: 1 | C51: =IF(B51=1,C50+Gap_share*(Eff_ceil-C50),C50) -> 81.5 | D51: =Save_pt*(C51-Eff_0) -> 105 | E51: =INDEX(Plan_years,A51+1) -> 510.42405 | F51: =MAX(IF(B52=1,MAX((F52+Round_cost*B52-D52-(E52-E51)-$O$48),Pre_cash),(F52+Round_cost*B52-D52-(E52-E51)-$O$48)),Floor_cash) -> 470 | G51: =E51+$O$47+SUMPRODUCT(-Round_cost*B49:B51+D49:D51)-H49-H50 -> 572.42405 | H51: =MAX(0,G51-F51) -> 102.42405 | I51: =G51-H51 -> 470 | J51: =Beta_y^A51 -> 0.7513148 | K51: =J51*H51 -> 76.952703 | L51: =IF(AND(I51>=Floor_cash-0.000000001),1,0) -> 1 | N51: Levers, 0.03 l + 8 phi | O51: =Fee_line*O49+Cost_delay*O50 -> 4.2922746
A52: 4 | B52: 1 | C52: =IF(B52=1,C51+Gap_share*(Eff_ceil-C51),C51) -> 83.25 | D52: =Save_pt*(C52-Eff_0) -> 122.5 | E52: =INDEX(Plan_years,A52+1) -> 548.32544 | F52: =MAX(IF(B53=1,MAX((F53+Round_cost*B53-D53-(E53-E52)),Pre_cash),(F53+Round_cost*B53-D53-(E53-E52))),Floor_cash) -> 350 | G52: =I51-Round_cost*B52+D52+(E52-E51)+$O$48 -> 510.4014 | H52: =MAX(0,G52-F52) -> 160.4014 | I52: =G52-H52 -> 350 | J52: =Beta_y^A52 -> 0.68301346 | K52: =J52*H52 -> 109.55631 | L52: =IF(AND(I52>=Floor_cash-0.000000001,IF(B52=1,I51>=Pre_cash-0.000000001,TRUE())),1,0) -> 1 | N52: Payouts and savings, before the levers | O52: =SUM(K49:K54)+J54*D54/R_hurdle -> 1026.8582
A53: 5 | B53: 0 | C53: =IF(B53=1,C52+Gap_share*(Eff_ceil-C52),C52) -> 83.25 | D53: =Save_pt*(C53-Eff_0) -> 122.5 | E53: =INDEX(Plan_years,A53+1) -> 584.63273 | F53: =MAX(IF(B54=1,MAX((F54+Round_cost*B54-D54-(E54-E53)),Pre_cash),(F54+Round_cost*B54-D54-(E54-E53))),Floor_cash) -> 350 | G53: =I52-Round_cost*B53+D53+(E53-E52) -> 508.80729 | H53: =MAX(0,G53-F53) -> 158.80729 | I53: =G53-H53 -> 350 | J53: =Beta_y^A53 -> 0.62092132 | K53: =J53*H53 -> 98.60683 | L53: =IF(AND(I53>=Floor_cash-0.000000001,IF(B53=1,I52>=Pre_cash-0.000000001,TRUE())),1,0) -> 1 | N53: Value | O53: =O52-O51 -> 1022.5659
A54: 6 | B54: 0 | C54: =IF(B54=1,C53+Gap_share*(Eff_ceil-C53),C53) -> 83.25 | D54: =Save_pt*(C54-Eff_0) -> 122.5 | E54: =INDEX(Plan_years,A54+1) -> 614.80663 | F54: =End_cash -> 470 | G54: =I53-Round_cost*B54+D54+(E54-E53) -> 502.6739 | H54: =MAX(0,G54-F54) -> 32.673897 | I54: =G54-H54 -> 470 | J54: =Beta_y^A54 -> 0.56447393 | K54: =J54*H54 -> 18.443563 | L54: =IF(AND(I54>=Floor_cash-0.000000001,IF(B54=1,I53>=Pre_cash-0.000000001,TRUE()),I54>=End_cash-0.000000001),1,0) -> 1 | N54: Commitments after the build kept (1 = yes) | O54: =IF(SUM(L51:L54)=4,1,0) -> 1
A58: Rounds in years 1, 4, 5
A59: Year | B59: Round z | C59: Efficiency | D59: Savings | E59: Volume I's plan | F59: War chest | G59: Cash before the payout | H59: Payout | I59: Cash after the payout | J59: beta^k | K59: PV of the payout | L59: Commitments kept | N59: Sale at the start, G | O59: =Sale_G -> 92
A60: 0 | C60: =Eff_0 -> 71 | E60: =INDEX(Plan_years,A60+1) -> 620 | N60: Sale in year 4, after the build | O60: 0
A61: 1 | B61: 1 | C61: =IF(B61=1,C60+Gap_share*(Eff_ceil-C60),C60) -> 78 | D61: =Save_pt*(C61-Eff_0) -> 70 | E61: =INDEX(Plan_years,A61+1) -> 498.8622 | H61: 61 | J61: =Beta_y^A61 -> 0.90909091 | K61: =J61*H61 -> 55.454545 | N61: Line (engine) | O61: 140
A62: 2 | B62: 0 | C62: =IF(B62=1,C61+Gap_share*(Eff_ceil-C61),C61) -> 78 | D62: =Save_pt*(C62-Eff_0) -> 70 | E62: =INDEX(Plan_years,A62+1) -> 483.85405 | H62: 65 | J62: =Beta_y^A62 -> 0.82644628 | K62: =J62*H62 -> 53.719008 | N62: Delay, quarters (engine) | O62: 0
A63: 3 | B63: 0 | C63: =IF(B63=1,C62+Gap_share*(Eff_ceil-C62),C62) -> 78 | D63: =Save_pt*(C63-Eff_0) -> 70 | E63: =INDEX(Plan_years,A63+1) -> 510.42405 | F63: =MAX(IF(B64=1,MAX((F64+Round_cost*B64-D64-(E64-E63)-$O$60),Pre_cash),(F64+Round_cost*B64-D64-(E64-E63)-$O$60)),Floor_cash) -> 470 | G63: =E63+$O$59+SUMPRODUCT(-Round_cost*B61:B63+D61:D63)-H61-H62 -> 566.42405 | H63: =MAX(0,G63-F63) -> 96.424048 | I63: =G63-H63 -> 470 | J63: =Beta_y^A63 -> 0.7513148 | K63: =J63*H63 -> 72.444814 | L63: =IF(AND(I63>=Floor_cash-0.000000001),1,0) -> 1 | N63: Levers, 0.03 l + 8 phi | O63: =Fee_line*O61+Cost_delay*O62 -> 4.2
A64: 4 | B64: 1 | C64: =IF(B64=1,C63+Gap_share*(Eff_ceil-C63),C63) -> 81.5 | D64: =Save_pt*(C64-Eff_0) -> 105 | E64: =INDEX(Plan_years,A64+1) -> 548.32544 | F64: =MAX(IF(B65=1,MAX((F65+Round_cost*B65-D65-(E65-E64)),Pre_cash),(F65+Round_cost*B65-D65-(E65-E64))),Floor_cash) -> 470 | G64: =I63-Round_cost*B64+D64+(E64-E63)+$O$60 -> 492.9014 | H64: =MAX(0,G64-F64) -> 22.901396 | I64: =G64-H64 -> 470 | J64: =Beta_y^A64 -> 0.68301346 | K64: =J64*H64 -> 15.641962 | L64: =IF(AND(I64>=Floor_cash-0.000000001,IF(B64=1,I63>=Pre_cash-0.000000001,TRUE())),1,0) -> 1 | N64: Payouts and savings, before the levers | O64: =SUM(K61:K66)+J66*D66/R_hurdle -> 1005.7913
A65: 5 | B65: 1 | C65: =IF(B65=1,C64+Gap_share*(Eff_ceil-C64),C64) -> 83.25 | D65: =Save_pt*(C65-Eff_0) -> 122.5 | E65: =INDEX(Plan_years,A65+1) -> 584.63273 | F65: =MAX(IF(B66=1,MAX((F66+Round_cost*B66-D66-(E66-E65)),Pre_cash),(F66+Round_cost*B66-D66-(E66-E65))),Floor_cash) -> 350 | G65: =I64-Round_cost*B65+D65+(E65-E64) -> 508.80729 | H65: =MAX(0,G65-F65) -> 158.80729 | I65: =G65-H65 -> 350 | J65: =Beta_y^A65 -> 0.62092132 | K65: =J65*H65 -> 98.60683 | L65: =IF(AND(I65>=Floor_cash-0.000000001,IF(B65=1,I64>=Pre_cash-0.000000001,TRUE())),1,0) -> 1 | N65: Value | O65: =O64-O63 -> 1001.5913
A66: 6 | B66: 0 | C66: =IF(B66=1,C65+Gap_share*(Eff_ceil-C65),C65) -> 83.25 | D66: =Save_pt*(C66-Eff_0) -> 122.5 | E66: =INDEX(Plan_years,A66+1) -> 614.80663 | F66: =End_cash -> 470 | G66: =I65-Round_cost*B66+D66+(E66-E65) -> 502.6739 | H66: =MAX(0,G66-F66) -> 32.673897 | I66: =G66-H66 -> 470 | J66: =Beta_y^A66 -> 0.56447393 | K66: =J66*H66 -> 18.443563 | L66: =IF(AND(I66>=Floor_cash-0.000000001,IF(B66=1,I65>=Pre_cash-0.000000001,TRUE()),I66>=End_cash-0.000000001),1,0) -> 1 | N66: Commitments after the build kept (1 = yes) | O66: =IF(SUM(L63:L66)=4,1,0) -> 1
A70: Rounds in years 2, 3, 4
A71: Year | B71: Round z | C71: Efficiency | D71: Savings | E71: Volume I's plan | F71: War chest | G71: Cash before the payout | H71: Payout | I71: Cash after the payout | J71: beta^k | K71: PV of the payout | L71: Commitments kept | N71: Sale at the start, G | O71: =Sale_G -> 92
A72: 0 | C72: =Eff_0 -> 71 | E72: =INDEX(Plan_years,A72+1) -> 620 | N72: Sale in year 4, after the build | O72: 0
A73: 1 | B73: 0 | C73: =IF(B73=1,C72+Gap_share*(Eff_ceil-C72),C72) -> 71 | D73: =Save_pt*(C73-Eff_0) -> 0 | E73: =INDEX(Plan_years,A73+1) -> 498.8622 | H73: 0 | J73: =Beta_y^A73 -> 0.90909091 | K73: =J73*H73 -> 0 | N73: Line (engine) | O73: 170
A74: 2 | B74: 1 | C74: =IF(B74=1,C73+Gap_share*(Eff_ceil-C73),C73) -> 78 | D74: =Save_pt*(C74-Eff_0) -> 70 | E74: =INDEX(Plan_years,A74+1) -> 483.85405 | H74: 0 | J74: =Beta_y^A74 -> 0.82644628 | K74: =J74*H74 -> 0 | N74: Delay, quarters (engine) | O74: 1.2585203
A75: 3 | B75: 1 | C75: =IF(B75=1,C74+Gap_share*(Eff_ceil-C74),C74) -> 81.5 | D75: =Save_pt*(C75-Eff_0) -> 105 | E75: =INDEX(Plan_years,A75+1) -> 510.42405 | F75: =MAX(IF(B76=1,MAX((F76+Round_cost*B76-D76-(E76-E75)-$O$72),Pre_cash),(F76+Round_cost*B76-D76-(E76-E75)-$O$72)),Floor_cash) -> 470 | G75: =E75+$O$71+SUMPRODUCT(-Round_cost*B73:B75+D73:D75)-H73-H74 -> 537.42405 | H75: =MAX(0,G75-F75) -> 67.424048 | I75: =G75-H75 -> 470 | J75: =Beta_y^A75 -> 0.7513148 | K75: =J75*H75 -> 50.656685 | L75: =IF(AND(I75>=Floor_cash-0.000000001),1,0) -> 1 | N75: Levers, 0.03 l + 8 phi | O75: =Fee_line*O73+Cost_delay*O74 -> 15.168162
A76: 4 | B76: 1 | C76: =IF(B76=1,C75+Gap_share*(Eff_ceil-C75),C75) -> 83.25 | D76: =Save_pt*(C76-Eff_0) -> 122.5 | E76: =INDEX(Plan_years,A76+1) -> 548.32544 | F76: =MAX(IF(B77=1,MAX((F77+Round_cost*B77-D77-(E77-E76)),Pre_cash),(F77+Round_cost*B77-D77-(E77-E76))),Floor_cash) -> 350 | G76: =I75-Round_cost*B76+D76+(E76-E75)+$O$72 -> 510.4014 | H76: =MAX(0,G76-F76) -> 160.4014 | I76: =G76-H76 -> 350 | J76: =Beta_y^A76 -> 0.68301346 | K76: =J76*H76 -> 109.55631 | L76: =IF(AND(I76>=Floor_cash-0.000000001,IF(B76=1,I75>=Pre_cash-0.000000001,TRUE())),1,0) -> 1 | N76: Payouts and savings, before the levers | O76: =SUM(K73:K78)+J78*D78/R_hurdle -> 968.74395
A77: 5 | B77: 0 | C77: =IF(B77=1,C76+Gap_share*(Eff_ceil-C76),C76) -> 83.25 | D77: =Save_pt*(C77-Eff_0) -> 122.5 | E77: =INDEX(Plan_years,A77+1) -> 584.63273 | F77: =MAX(IF(B78=1,MAX((F78+Round_cost*B78-D78-(E78-E77)),Pre_cash),(F78+Round_cost*B78-D78-(E78-E77))),Floor_cash) -> 350 | G77: =I76-Round_cost*B77+D77+(E77-E76) -> 508.80729 | H77: =MAX(0,G77-F77) -> 158.80729 | I77: =G77-H77 -> 350 | J77: =Beta_y^A77 -> 0.62092132 | K77: =J77*H77 -> 98.60683 | L77: =IF(AND(I77>=Floor_cash-0.000000001,IF(B77=1,I76>=Pre_cash-0.000000001,TRUE())),1,0) -> 1 | N77: Value | O77: =O76-O75 -> 953.57579
A78: 6 | B78: 0 | C78: =IF(B78=1,C77+Gap_share*(Eff_ceil-C77),C77) -> 83.25 | D78: =Save_pt*(C78-Eff_0) -> 122.5 | E78: =INDEX(Plan_years,A78+1) -> 614.80663 | F78: =End_cash -> 470 | G78: =I77-Round_cost*B78+D78+(E78-E77) -> 502.6739 | H78: =MAX(0,G78-F78) -> 32.673897 | I78: =G78-H78 -> 470 | J78: =Beta_y^A78 -> 0.56447393 | K78: =J78*H78 -> 18.443563 | L78: =IF(AND(I78>=Floor_cash-0.000000001,IF(B78=1,I77>=Pre_cash-0.000000001,TRUE()),I78>=End_cash-0.000000001),1,0) -> 1 | N78: Commitments after the build kept (1 = yes) | O78: =IF(SUM(L75:L78)=4,1,0) -> 1
A82: Rounds in years 2, 4, 5
A83: Year | B83: Round z | C83: Efficiency | D83: Savings | E83: Volume I's plan | F83: War chest | G83: Cash before the payout | H83: Payout | I83: Cash after the payout | J83: beta^k | K83: PV of the payout | L83: Commitments kept | N83: Sale at the start, G | O83: =Sale_G -> 92
A84: 0 | C84: =Eff_0 -> 71 | E84: =INDEX(Plan_years,A84+1) -> 620 | N84: Sale in year 4, after the build | O84: 0
A85: 1 | B85: 0 | C85: =IF(B85=1,C84+Gap_share*(Eff_ceil-C84),C84) -> 71 | D85: =Save_pt*(C85-Eff_0) -> 0 | E85: =INDEX(Plan_years,A85+1) -> 498.8622 | H85: 0 | J85: =Beta_y^A85 -> 0.90909091 | K85: =J85*H85 -> 0 | N85: Line (engine) | O85: 155
A86: 2 | B86: 1 | C86: =IF(B86=1,C85+Gap_share*(Eff_ceil-C85),C85) -> 78 | D86: =Save_pt*(C86-Eff_0) -> 70 | E86: =INDEX(Plan_years,A86+1) -> 483.85405 | H86: 48 | J86: =Beta_y^A86 -> 0.82644628 | K86: =J86*H86 -> 39.669421 | N86: Delay, quarters (engine) | O86: 0.006246131
A87: 3 | B87: 0 | C87: =IF(B87=1,C86+Gap_share*(Eff_ceil-C86),C86) -> 78 | D87: =Save_pt*(C87-Eff_0) -> 70 | E87: =INDEX(Plan_years,A87+1) -> 510.42405 | F87: =MAX(IF(B88=1,MAX((F88+Round_cost*B88-D88-(E88-E87)-$O$84),Pre_cash),(F88+Round_cost*B88-D88-(E88-E87)-$O$84)),Floor_cash) -> 470 | G87: =E87+$O$83+SUMPRODUCT(-Round_cost*B85:B87+D85:D87)-H85-H86 -> 574.42405 | H87: =MAX(0,G87-F87) -> 104.42405 | I87: =G87-H87 -> 470 | J87: =Beta_y^A87 -> 0.7513148 | K87: =J87*H87 -> 78.455333 | L87: =IF(AND(I87>=Floor_cash-0.000000001),1,0) -> 1 | N87: Levers, 0.03 l + 8 phi | O87: =Fee_line*O85+Cost_delay*O86 -> 4.699969
A88: 4 | B88: 1 | C88: =IF(B88=1,C87+Gap_share*(Eff_ceil-C87),C87) -> 81.5 | D88: =Save_pt*(C88-Eff_0) -> 105 | E88: =INDEX(Plan_years,A88+1) -> 548.32544 | F88: =MAX(IF(B89=1,MAX((F89+Round_cost*B89-D89-(E89-E88)),Pre_cash),(F89+Round_cost*B89-D89-(E89-E88))),Floor_cash) -> 470 | G88: =I87-Round_cost*B88+D88+(E88-E87)+$O$84 -> 492.9014 | H88: =MAX(0,G88-F88) -> 22.901396 | I88: =G88-H88 -> 470 | J88: =Beta_y^A88 -> 0.68301346 | K88: =J88*H88 -> 15.641962 | L88: =IF(AND(I88>=Floor_cash-0.000000001,IF(B88=1,I87>=Pre_cash-0.000000001,TRUE())),1,0) -> 1 | N88: Payouts and savings, before the levers | O88: =SUM(K85:K90)+J90*D90/R_hurdle -> 942.29767
A89: 5 | B89: 1 | C89: =IF(B89=1,C88+Gap_share*(Eff_ceil-C88),C88) -> 83.25 | D89: =Save_pt*(C89-Eff_0) -> 122.5 | E89: =INDEX(Plan_years,A89+1) -> 584.63273 | F89: =MAX(IF(B90=1,MAX((F90+Round_cost*B90-D90-(E90-E89)),Pre_cash),(F90+Round_cost*B90-D90-(E90-E89))),Floor_cash) -> 350 | G89: =I88-Round_cost*B89+D89+(E89-E88) -> 508.80729 | H89: =MAX(0,G89-F89) -> 158.80729 | I89: =G89-H89 -> 350 | J89: =Beta_y^A89 -> 0.62092132 | K89: =J89*H89 -> 98.60683 | L89: =IF(AND(I89>=Floor_cash-0.000000001,IF(B89=1,I88>=Pre_cash-0.000000001,TRUE())),1,0) -> 1 | N89: Value | O89: =O88-O87 -> 937.5977
A90: 6 | B90: 0 | C90: =IF(B90=1,C89+Gap_share*(Eff_ceil-C89),C89) -> 83.25 | D90: =Save_pt*(C90-Eff_0) -> 122.5 | E90: =INDEX(Plan_years,A90+1) -> 614.80663 | F90: =End_cash -> 470 | G90: =I89-Round_cost*B90+D90+(E90-E89) -> 502.6739 | H90: =MAX(0,G90-F90) -> 32.673897 | I90: =G90-H90 -> 470 | J90: =Beta_y^A90 -> 0.56447393 | K90: =J90*H90 -> 18.443563 | L90: =IF(AND(I90>=Floor_cash-0.000000001,IF(B90=1,I89>=Pre_cash-0.000000001,TRUE()),I90>=End_cash-0.000000001),1,0) -> 1 | N90: Commitments after the build kept (1 = yes) | O90: =IF(SUM(L87:L90)=4,1,0) -> 1
A94: Rounds in years 3, 4, 5
A95: Year | B95: Round z | C95: Efficiency | D95: Savings | E95: Volume I's plan | F95: War chest | G95: Cash before the payout | H95: Payout | I95: Cash after the payout | J95: beta^k | K95: PV of the payout | L95: Commitments kept | N95: Sale at the start, G | O95: =Sale_G -> 92
A96: 0 | C96: =Eff_0 -> 71 | E96: =INDEX(Plan_years,A96+1) -> 620 | N96: Sale in year 4, after the build | O96: 0
A97: 1 | B97: 0 | C97: =IF(B97=1,C96+Gap_share*(Eff_ceil-C96),C96) -> 71 | D97: =Save_pt*(C97-Eff_0) -> 0 | E97: =INDEX(Plan_years,A97+1) -> 498.8622 | H97: 8 | J97: =Beta_y^A97 -> 0.90909091 | K97: =J97*H97 -> 7.2727273 | N97: Line (engine) | O97: 140
A98: 2 | B98: 0 | C98: =IF(B98=1,C97+Gap_share*(Eff_ceil-C97),C97) -> 71 | D98: =Save_pt*(C98-Eff_0) -> 0 | E98: =INDEX(Plan_years,A98+1) -> 483.85405 | H98: 0 | J98: =Beta_y^A98 -> 0.82644628 | K98: =J98*H98 -> 0 | N98: Delay, quarters (engine) | O98: 0
A99: 3 | B99: 1 | C99: =IF(B99=1,C98+Gap_share*(Eff_ceil-C98),C98) -> 78 | D99: =Save_pt*(C99-Eff_0) -> 70 | E99: =INDEX(Plan_years,A99+1) -> 510.42405 | F99: =MAX(IF(B100=1,MAX((F100+Round_cost*B100-D100-(E100-E99)-$O$96),Pre_cash),(F100+Round_cost*B100-D100-(E100-E99)-$O$96)),Floor_cash) -> 470 | G99: =E99+$O$95+SUMPRODUCT(-Round_cost*B97:B99+D97:D99)-H97-H98 -> 544.42405 | H99: =MAX(0,G99-F99) -> 74.424048 | I99: =G99-H99 -> 470 | J99: =Beta_y^A99 -> 0.7513148 | K99: =J99*H99 -> 55.915889 | L99: =IF(AND(I99>=Floor_cash-0.000000001),1,0) -> 1 | N99: Levers, 0.03 l + 8 phi | O99: =Fee_line*O97+Cost_delay*O98 -> 4.2
A100: 4 | B100: 1 | C100: =IF(B100=1,C99+Gap_share*(Eff_ceil-C99),C99) -> 81.5 | D100: =Save_pt*(C100-Eff_0) -> 105 | E100: =INDEX(Plan_years,A100+1) -> 548.32544 | F100: =MAX(IF(B101=1,MAX((F101+Round_cost*B101-D101-(E101-E100)),Pre_cash),(F101+Round_cost*B101-D101-(E101-E100))),Floor_cash) -> 470 | G100: =I99-Round_cost*B100+D100+(E100-E99)+$O$96 -> 492.9014 | H100: =MAX(0,G100-F100) -> 22.901396 | I100: =G100-H100 -> 470 | J100: =Beta_y^A100 -> 0.68301346 | K100: =J100*H100 -> 15.641962 | L100: =IF(AND(I100>=Floor_cash-0.000000001,IF(B100=1,I99>=Pre_cash-0.000000001,TRUE())),1,0) -> 1 | N100: Payouts and savings, before the levers | O100: =SUM(K97:K102)+J102*D102/R_hurdle -> 887.36153
A101: 5 | B101: 1 | C101: =IF(B101=1,C100+Gap_share*(Eff_ceil-C100),C100) -> 83.25 | D101: =Save_pt*(C101-Eff_0) -> 122.5 | E101: =INDEX(Plan_years,A101+1) -> 584.63273 | F101: =MAX(IF(B102=1,MAX((F102+Round_cost*B102-D102-(E102-E101)),Pre_cash),(F102+Round_cost*B102-D102-(E102-E101))),Floor_cash) -> 350 | G101: =I100-Round_cost*B101+D101+(E101-E100) -> 508.80729 | H101: =MAX(0,G101-F101) -> 158.80729 | I101: =G101-H101 -> 350 | J101: =Beta_y^A101 -> 0.62092132 | K101: =J101*H101 -> 98.60683 | L101: =IF(AND(I101>=Floor_cash-0.000000001,IF(B101=1,I100>=Pre_cash-0.000000001,TRUE())),1,0) -> 1 | N101: Value | O101: =O100-O99 -> 883.16153
A102: 6 | B102: 0 | C102: =IF(B102=1,C101+Gap_share*(Eff_ceil-C101),C101) -> 83.25 | D102: =Save_pt*(C102-Eff_0) -> 122.5 | E102: =INDEX(Plan_years,A102+1) -> 614.80663 | F102: =End_cash -> 470 | G102: =I101-Round_cost*B102+D102+(E102-E101) -> 502.6739 | H102: =MAX(0,G102-F102) -> 32.673897 | I102: =G102-H102 -> 470 | J102: =Beta_y^A102 -> 0.56447393 | K102: =J102*H102 -> 18.443563 | L102: =IF(AND(I102>=Floor_cash-0.000000001,IF(B102=1,I101>=Pre_cash-0.000000001,TRUE()),I102>=End_cash-0.000000001),1,0) -> 1 | N102: Commitments after the build kept (1 = yes) | O102: =IF(SUM(L99:L102)=4,1,0) -> 1
A106: Rounds in years 4, 5, 6
A107: Year | B107: Round z | C107: Efficiency | D107: Savings | E107: Volume I's plan | F107: War chest | G107: Cash before the payout | H107: Payout | I107: Cash after the payout | J107: beta^k | K107: PV of the payout | L107: Commitments kept | N107: Sale at the start, G | O107: =Sale_G -> 92
A108: 0 | C108: =Eff_0 -> 71 | E108: =INDEX(Plan_years,A108+1) -> 620 | N108: Sale in year 4, after the build | O108: 0
A109: 1 | B109: 0 | C109: =IF(B109=1,C108+Gap_share*(Eff_ceil-C108),C108) -> 71 | D109: =Save_pt*(C109-Eff_0) -> 0 | E109: =INDEX(Plan_years,A109+1) -> 498.8622 | H109: 64 | J109: =Beta_y^A109 -> 0.90909091 | K109: =J109*H109 -> 58.181818 | N109: Line (engine) | O109: 135
A110: 2 | B110: 0 | C110: =IF(B110=1,C109+Gap_share*(Eff_ceil-C109),C109) -> 71 | D110: =Save_pt*(C110-Eff_0) -> 0 | E110: =INDEX(Plan_years,A110+1) -> 483.85405 | H110: 20 | J110: =Beta_y^A110 -> 0.82644628 | K110: =J110*H110 -> 16.528926 | N110: Delay, quarters (engine) | O110: 0
A111: 3 | B111: 0 | C111: =IF(B111=1,C110+Gap_share*(Eff_ceil-C110),C110) -> 71 | D111: =Save_pt*(C111-Eff_0) -> 0 | E111: =INDEX(Plan_years,A111+1) -> 510.42405 | F111: =MAX(IF(B112=1,MAX((F112+Round_cost*B112-D112-(E112-E111)-$O$108),Pre_cash),(F112+Round_cost*B112-D112-(E112-E111)-$O$108)),Floor_cash) -> 482.0986 | G111: =E111+$O$107+SUMPRODUCT(-Round_cost*B109:B111+D109:D111)-H109-H110 -> 518.42405 | H111: =MAX(0,G111-F111) -> 36.325444 | I111: =G111-H111 -> 482.0986 | J111: =Beta_y^A111 -> 0.7513148 | K111: =J111*H111 -> 27.291844 | L111: =IF(AND(I111>=Floor_cash-0.000000001),1,0) -> 1 | N111: Levers, 0.03 l + 8 phi | O111: =Fee_line*O109+Cost_delay*O110 -> 4.05
A112: 4 | B112: 1 | C112: =IF(B112=1,C111+Gap_share*(Eff_ceil-C111),C111) -> 78 | D112: =Save_pt*(C112-Eff_0) -> 70 | E112: =INDEX(Plan_years,A112+1) -> 548.32544 | F112: =MAX(IF(B113=1,MAX((F113+Round_cost*B113-D113-(E113-E112)),Pre_cash),(F113+Round_cost*B113-D113-(E113-E112))),Floor_cash) -> 470 | G112: =I111-Round_cost*B112+D112+(E112-E111)+$O$108 -> 470 | H112: =MAX(0,G112-F112) -> 0 | I112: =G112-H112 -> 470 | J112: =Beta_y^A112 -> 0.68301346 | K112: =J112*H112 -> 0 | L112: =IF(AND(I112>=Floor_cash-0.000000001,IF(B112=1,I111>=Pre_cash-0.000000001,TRUE())),1,0) -> 1 | N112: Payouts and savings, before the levers | O112: =SUM(K109:K114)+J114*D114/R_hurdle -> 825.15686
A113: 5 | B113: 1 | C113: =IF(B113=1,C112+Gap_share*(Eff_ceil-C112),C112) -> 81.5 | D113: =Save_pt*(C113-Eff_0) -> 105 | E113: =INDEX(Plan_years,A113+1) -> 584.63273 | F113: =MAX(IF(B114=1,MAX((F114+Round_cost*B114-D114-(E114-E113)),Pre_cash),(F114+Round_cost*B114-D114-(E114-E113))),Floor_cash) -> 470 | G113: =I112-Round_cost*B113+D113+(E113-E112) -> 491.30729 | H113: =MAX(0,G113-F113) -> 21.307285 | I113: =G113-H113 -> 470 | J113: =Beta_y^A113 -> 0.62092132 | K113: =J113*H113 -> 13.230148 | L113: =IF(AND(I113>=Floor_cash-0.000000001,IF(B113=1,I112>=Pre_cash-0.000000001,TRUE())),1,0) -> 1 | N113: Value | O113: =O112-O111 -> 821.10686
A114: 6 | B114: 1 | C114: =IF(B114=1,C113+Gap_share*(Eff_ceil-C113),C113) -> 83.25 | D114: =Save_pt*(C114-Eff_0) -> 122.5 | E114: =INDEX(Plan_years,A114+1) -> 614.80663 | F114: =End_cash -> 470 | G114: =I113-Round_cost*B114+D114+(E114-E113) -> 502.6739 | H114: =MAX(0,G114-F114) -> 32.673897 | I114: =G114-H114 -> 470 | J114: =Beta_y^A114 -> 0.56447393 | K114: =J114*H114 -> 18.443563 | L114: =IF(AND(I114>=Floor_cash-0.000000001,IF(B114=1,I113>=Pre_cash-0.000000001,TRUE()),I114>=End_cash-0.000000001),1,0) -> 1 | N114: Commitments after the build kept (1 = yes) | O114: =IF(SUM(L111:L114)=4,1,0) -> 1
A118: No sale
A119: Year | B119: Round z | C119: Efficiency | D119: Savings | E119: Volume I's plan | F119: War chest | G119: Cash before the payout | H119: Payout | I119: Cash after the payout | J119: beta^k | K119: PV of the payout | L119: Commitments kept | N119: Sale at the start, G | O119: 0
A120: 0 | C120: =Eff_0 -> 71 | E120: =INDEX(Plan_years,A120+1) -> 620 | N120: Sale in year 4, after the build | O120: 0
A121: 1 | B121: 1 | C121: =IF(B121=1,C120+Gap_share*(Eff_ceil-C120),C120) -> 78 | D121: =Save_pt*(C121-Eff_0) -> 70 | E121: =INDEX(Plan_years,A121+1) -> 498.8622 | H121: 0 | J121: =Beta_y^A121 -> 0.90909091 | K121: =J121*H121 -> 0 | N121: Line (engine) | O121: 165
A122: 2 | B122: 1 | C122: =IF(B122=1,C121+Gap_share*(Eff_ceil-C121),C121) -> 81.5 | D122: =Save_pt*(C122-Eff_0) -> 105 | E122: =INDEX(Plan_years,A122+1) -> 483.85405 | H122: 0 | J122: =Beta_y^A122 -> 0.82644628 | K122: =J122*H122 -> 0 | N122: Delay, quarters (engine) | O122: 5.970015
A123: 3 | B123: 1 | C123: =IF(B123=1,C122+Gap_share*(Eff_ceil-C122),C122) -> 83.25 | D123: =Save_pt*(C123-Eff_0) -> 122.5 | E123: =INDEX(Plan_years,A123+1) -> 510.42405 | F123: =MAX(IF(B124=1,MAX((F124+Round_cost*B124-D124-(E124-E123)-$O$120),Pre_cash),(F124+Round_cost*B124-D124-(E124-E123)-$O$120)),Floor_cash) -> 350 | G123: =E123+$O$119+SUMPRODUCT(-Round_cost*B121:B123+D121:D123)-H121-H122 -> 447.92405 | H123: =MAX(0,G123-F123) -> 97.924048 | I123: =G123-H123 -> 350 | J123: =Beta_y^A123 -> 0.7513148 | K123: =J123*H123 -> 73.571786 | L123: =IF(AND(I123>=Floor_cash-0.000000001),1,0) -> 1 | N123: Levers, 0.03 l + 8 phi | O123: =Fee_line*O121+Cost_delay*O122 -> 52.71012
A124: 4 | B124: 0 | C124: =IF(B124=1,C123+Gap_share*(Eff_ceil-C123),C123) -> 83.25 | D124: =Save_pt*(C124-Eff_0) -> 122.5 | E124: =INDEX(Plan_years,A124+1) -> 548.32544 | F124: =MAX(IF(B125=1,MAX((F125+Round_cost*B125-D125-(E125-E124)),Pre_cash),(F125+Round_cost*B125-D125-(E125-E124))),Floor_cash) -> 350 | G124: =I123-Round_cost*B124+D124+(E124-E123)+$O$120 -> 510.4014 | H124: =MAX(0,G124-F124) -> 160.4014 | I124: =G124-H124 -> 350 | J124: =Beta_y^A124 -> 0.68301346 | K124: =J124*H124 -> 109.55631 | L124: =IF(AND(I124>=Floor_cash-0.000000001,IF(B124=1,I123>=Pre_cash-0.000000001,TRUE())),1,0) -> 1 | N124: Payouts and savings, before the levers | O124: =SUM(K121:K126)+J126*D126/R_hurdle -> 991.65906
A125: 5 | B125: 0 | C125: =IF(B125=1,C124+Gap_share*(Eff_ceil-C124),C124) -> 83.25 | D125: =Save_pt*(C125-Eff_0) -> 122.5 | E125: =INDEX(Plan_years,A125+1) -> 584.63273 | F125: =MAX(IF(B126=1,MAX((F126+Round_cost*B126-D126-(E126-E125)),Pre_cash),(F126+Round_cost*B126-D126-(E126-E125))),Floor_cash) -> 350 | G125: =I124-Round_cost*B125+D125+(E125-E124) -> 508.80729 | H125: =MAX(0,G125-F125) -> 158.80729 | I125: =G125-H125 -> 350 | J125: =Beta_y^A125 -> 0.62092132 | K125: =J125*H125 -> 98.60683 | L125: =IF(AND(I125>=Floor_cash-0.000000001,IF(B125=1,I124>=Pre_cash-0.000000001,TRUE())),1,0) -> 1 | N125: Value | O125: =O124-O123 -> 938.94894
A126: 6 | B126: 0 | C126: =IF(B126=1,C125+Gap_share*(Eff_ceil-C125),C125) -> 83.25 | D126: =Save_pt*(C126-Eff_0) -> 122.5 | E126: =INDEX(Plan_years,A126+1) -> 614.80663 | F126: =End_cash -> 470 | G126: =I125-Round_cost*B126+D126+(E126-E125) -> 502.6739 | H126: =MAX(0,G126-F126) -> 32.673897 | I126: =G126-H126 -> 470 | J126: =Beta_y^A126 -> 0.56447393 | K126: =J126*H126 -> 18.443563 | L126: =IF(AND(I126>=Floor_cash-0.000000001,IF(B126=1,I125>=Pre_cash-0.000000001,TRUE()),I126>=End_cash-0.000000001),1,0) -> 1 | N126: Commitments after the build kept (1 = yes) | O126: =IF(SUM(L123:L126)=4,1,0) -> 1
A130: Sale after the build
A131: Year | B131: Round z | C131: Efficiency | D131: Savings | E131: Volume I's plan | F131: War chest | G131: Cash before the payout | H131: Payout | I131: Cash after the payout | J131: beta^k | K131: PV of the payout | L131: Commitments kept | N131: Sale at the start, G | O131: 0
...

Sheet Prices
A1: Internal prices at the best program, and the value of the sale (Theorem 16.1(iii); Proposition 16.3; Worked Example 16.1, Steps 3-4; Figure 16.2(b))
A2: Each lever's cost per point of chance: what $5m more line or 0.05 quarter more delay costs, over the points of chance it buys on the book's paths; paying $5m early: what it earns, beta - beta^3 or beta^2 - beta^3 a dollar, over the points it spends. The chances and the re-optimized packages are the engine's.
A3: The best program | B3: Value | C3: Note
A4: Levers: a $160m line and 2.071 quarters | B4: =Programs!O27 -> 21.37186 | C4: $21.37m
A5: Payouts at 10 percent | B5: =SUM(Programs!K25:K30) -> 369.29945 | C5: 0, 0, 189.9, 160.4, 158.8, 32.7
A6: The year-6 savings forever | B6: =Programs!J30*Programs!D30/R_hurdle -> 691.48056
A7: Value | B7: =B5+B6-B4 -> 1039.4082 | C7: $1,039.41m
A9: The sale (Theorem 16.2(ii)) | B9: Value | C9: Note
A10: No sale: value | B10: =Programs!O125 -> 938.94894 | C10: $938.95m
A11: No sale: levers | B11: =Programs!O123 -> 52.71012 | C11: $52.71m
A12: Sale after the build: value | B12: =Programs!O137 -> 1001.7862 | C12: $1,001.79m
A13: The sale first is worth (the best less no sale) | B13: =B7-B10 -> 100.45922 | C13: $100.5m
A14: its proceeds paid out at the end of year 3, 92 beta^3 | B14: =Sale_G*Beta_y^3 -> 69.120962 | C14: $69.1m
A15: the levers it makes unnecessary | B15: =B11-B4 -> 31.33826 | C15: $31.3m
A16: together | B16: =B14+B15 -> 100.45922 | C16: More than its $92m of proceeds
A17: The sale first beats the sale after the build by | B17: =B7-B12 -> 37.621984 | C17: $37.6m
A18: a year later, 92 (beta^3 - beta^4), plus the levers | B18: =Sale_G*(Beta_y^3-Beta_y^4)+B15 -> 37.621984
A20: The appetite's price | B20: Line (engine) | C20: Delay (engine) | D20: Levers | E20: Value
A21: 0.045 | B21: 165 | C21: 2.1755945 | D21: =Fee_line*B21+Cost_delay*C21 -> 22.354756 | E21: =Programs!O28-D21 -> 1038.4253
A22: 0.055 | B22: 170 | C22: 1.9283346 | D22: =Fee_line*B22+Cost_delay*C22 -> 20.526677 | E22: =Programs!O28-D22 -> 1040.2533
A23: The appetite's price, $m a percentage point | E23: =(E22-E21)/((A22-A21)*100) -> 1.8280788
A25: Volume I's price, the build alone | B25: Line (engine) | C25: Delay (engine) | D25: Levers | E25: Note
A26: 0.045 | B26: 165 | C26: 0.80481304 | D26: =Fee_line*B26+Cost_delay*C26 -> 11.388504
A27: 0.055 | B27: 165 | C27: 0.57893619 | D27: =Fee_line*B27+Cost_delay*C27 -> 9.5814895
A28: Volume I's price for the build alone, $m a point | D28: =(D26-D27)/((A27-A26)*100) -> 1.8070148 | E28: $1.81m (Section 16.1)
A30: Levers and payouts at the best program | B30: Value | C30: Note
A31: Chance of a breach at the best program (engine) | B31: 0.05 | C31: 5.00%
A32: with $5m more line (engine) | B32: 0.04915
A33: with 0.05 quarter more delay (engine) | B33: 0.04825
A34: paying $5m in year 1 instead of year 3 (engine) | B34: 0.06018
A35: paying $5m in year 2 instead of year 3 (engine) | B35: 0.05561
A36: Step: line | B36: 5
A37: Step: delay | B37: 0.05
A38: Step: payout | B38: 5
A39: The line buys a point of chance for | B39: =Fee_line*B36/(100*(B31-B32)) -> 1.7647059 | C39: $1.76m
A40: The delay buys a point of chance for | B40: =Cost_delay*B37/(100*(B31-B33)) -> 2.2857143 | C40: $2.29m
A41: beta - beta^3: a dollar paid in year 1 rather than year 3 earns | B41: =Beta_y-Beta_y^3 -> 0.15777611 | C41: 0.158
A42: points of chance it spends | B42: =100*(B34-B31)/B38 -> 0.2036 | C42: 0.204
A43: Paying in year 1 earns, a point of chance | B43: =B38*B41/(100*(B34-B31)) -> 0.77493177 | C43: $0.77m
A44: beta^2 - beta^3: paid in year 2 rather than year 3 | B44: =Beta_y^2-Beta_y^3 -> 0.07513148
A45: Paying in year 2 earns, a point of chance | B45: =B38*B44/(100*(B35-B31)) -> 0.66962103 | C45: $0.67m
A46: Payouts wait: both earn less than the appetite's price (1 = yes) | B46: =IF(AND(B43<E23,B45<E23),1,0) -> 1 | C46: Proposition 16.3(iii)
A48: A dollar of room at the start (Proposition 16.3(i)) | B48: Value | C48: Note
A49: One more $1m of proceeds: the program's value | B49: =Programs!O149 -> 1040.4962 | C49: Re-optimized package
A50: A dollar of room is worth | B50: =B49-B7 -> 1.0880297 | C50: $1.088
A51: paid out at the end of year 3, beta^3 | B51: =Beta_y^3 -> 0.7513148 | C51: $0.75
A52: levers it makes unnecessary | B52: =B4-Programs!O147 -> 0.33671488 | C52: $0.34
A54: Capability (Section 16.3) | B54: Value | C54: Note
A55: A point of capability on the floor, at Chapter 7's price | B55: =Cap_price -> 3.9 | C55: $3.90m
A56: The rounds' points in present value: years 1-3 | B56: =Cap_price*SUMPRODUCT(Programs!B25:B30,Programs!J25:J30)/Beta_y -> 10.668595 | C56: $10.67m; a round at the start of year k is k - 1 years away
A57: years 1, 2, 4 | B57: =Cap_price*SUMPRODUCT(Programs!B37:B42,Programs!J37:J42)/Beta_y -> 10.375582 | C57: $10.38m
A59: Hold or release (AXIOM Lab 2.16, step 3) | B59: Value | C59: Note
A60: Release Chapter 5's year-1 payout: the levers | B60: =Programs!O171 -> 50.01901 | C60: The appetite then needs a $165m line and 5.63 quarters
A61: the program's value | B61: =Programs!O173 -> 1024.172
A62: Holding it is worth | B62: =B7-B61 -> 15.236181 | C62: Discussion question (1)

Sheet Trigger
A1: Round 3 on a trigger (Theorem 16.2(iii); Worked Example 16.1, Step 5; Figure 16.3(b)) and waiting under irreversibility (Proposition 16.2)
A2: Round 3 runs in year 3 if cash after the year-2 payout is at least the trigger, else in year 4. For each trigger the engine finds the cheapest package keeping the appetite under the rule and the share of paths that run round 3 in year 3; the value is that share times the year-3 program's value, plus the rest times the year-4 program's, less the levers.
A3: Round 3 in year 3: value before the levers | B3: =Programs!O28 -> 1060.78 | C3: Payouts held in years 1-2
A4: Round 3 in year 4: value before the levers | B4: =Programs!O160 -> 1047.632
A6: Trigger | B6: Line (engine) | C6: Delay (engine) | D6: Year 3 on, share of paths (engine) | E6: Breach (engine) | F6: Levers | G6: Value
A7: 380 | B7: 165 | C7: 2.040013 | D7: 0.99723 | E7: 0.05 | F7: =Fee_line*B7+Cost_delay*C7 -> 21.270104 | G7: =D7*$B$3+(1-D7)*$B$4-F7 -> 1039.4735
A8: 390 | B8: 155 | C8: 2.0654673 | D8: 0.99556 | E8: 0.05 | F8: =Fee_line*B8+Cost_delay*C8 -> 21.173739 | G8: =D8*$B$3+(1-D8)*$B$4-F8 -> 1039.5479
A9: 400 | B9: 165 | C9: 2.0146525 | D9: 0.99373 | E9: 0.05 | F9: =Fee_line*B9+Cost_delay*C9 -> 21.06722 | G9: =D9*$B$3+(1-D9)*$B$4-F9 -> 1039.6304
A10: 410 | B10: 155 | C10: 2.0361575 | D10: 0.99012 | E10: 0.05 | F10: =Fee_line*B10+Cost_delay*C10 -> 20.93926 | G10: =D10*$B$3+(1-D10)*$B$4-F10 -> 1039.7109
A11: 420 | B11: 155 | C11: 2.0103069 | D11: 0.98525 | E11: 0.05 | F11: =Fee_line*B11+Cost_delay*C11 -> 20.732455 | G11: =D11*$B$3+(1-D11)*$B$4-F11 -> 1039.8536
A12: 430 | B12: 150 | C12: 2.0005512 | D12: 0.97806 | E12: 0.05 | F12: =Fee_line*B12+Cost_delay*C12 -> 20.50441 | G12: =D12*$B$3+(1-D12)*$B$4-F12 -> 1039.9871
A13: 440 | B13: 150 | C13: 1.9568187 | D13: 0.96761 | E13: 0.05 | F13: =Fee_line*B13+Cost_delay*C13 -> 20.15455 | G13: =D13*$B$3+(1-D13)*$B$4-F13 -> 1040.1996
A14: 450 | B14: 155 | C14: 1.8885492 | D14: 0.95314 | E14: 0.05 | F14: =Fee_line*B14+Cost_delay*C14 -> 19.758393 | G14: =D14*$B$3+(1-D14)*$B$4-F14 -> 1040.4055
A15: 460 | B15: 150 | C15: 1.8541987 | D15: 0.93227 | E15: 0.05 | F15: =Fee_line*B15+Cost_delay*C15 -> 19.333589 | G15: =D15*$B$3+(1-D15)*$B$4-F15 -> 1040.5559
A16: 470 | B16: 155 | C16: 1.7829938 | D16: 0.90719 | E16: 0.05 | F16: =Fee_line*B16+Cost_delay*C16 -> 18.91395 | G16: =D16*$B$3+(1-D16)*$B$4-F16 -> 1040.6458
A17: 480 | B17: 150 | C17: 1.7361731 | D17: 0.87371 | E17: 0.05 | F17: =Fee_line*B17+Cost_delay*C17 -> 18.389385 | G17: =D17*$B$3+(1-D17)*$B$4-F17 -> 1040.7302
A18: 490 | B18: 155 | C18: 1.6423944 | D18: 0.83 | E18: 0.05 | F18: =Fee_line*B18+Cost_delay*C18 -> 17.789155 | G18: =D18*$B$3+(1-D18)*$B$4-F18 -> 1040.7557
... A39: 700 | B39: 150 | C39: 1.254017 | D39: 0.00546 | E39: 0.05 | F39: =Fee_line*B39+Cost_delay*C39 -> 14.532136 | G39: =D39*$B$3+(1-D39)*$B$4-F39 -> 1033.1717
A41: The best trigger's value | B41: =MAX(G7:G39) -> 1040.7557 | C41: $1,040.76m
A42: The best trigger | B42: =INDEX(A7:A39,MATCH(B41,G7:G39,0)) -> 490 | C42: $490m
A43: its line | B43: =INDEX(B7:B39,MATCH(B41,G7:G39,0)) -> 155 | C43: $155m
A44: its delay | B44: =INDEX(C7:C39,MATCH(B41,G7:G39,0)) -> 1.6423944 | C44: 1.642 quarters
A45: its levers | B45: =INDEX(F7:F39,MATCH(B41,G7:G39,0)) -> 17.789155 | C45: $17.79m
A46: share of paths running round 3 in year 3 | B46: =INDEX(D7:D39,MATCH(B41,G7:G39,0)) -> 0.83 | C46: 83.0%
A47: Committed to year 3 (the best program) | B47: =Programs!O29 -> 1039.4082 | C47: $1,039.41m
A48: Committed to year 4 | B48: =Programs!O41 -> 1036.8009 | C48: $1,036.80m
A49: The trigger is worth more than committing to year 3 by | B49: =B41-B47 -> 1.3475432 | C49: $1.35m
A50: and more than committing to year 4 by | B50: =B41-B48 -> 3.9547932
A51: Theorem 16.2(iii): the rule beats both timings (1 = yes) | B51: =IF(B41>MAX(B47,B48),1,0) -> 1 | C51: Strictly: the best timing depends on the reading
A53: Proposition 16.2 on Chapter 7's generic project (Online Appendix 7.B) | B53: Value | C53: Note
A54: Cost c | B54: 100
A55: Worth next year if good | B55: 150 | C55: Equal odds
A56: Worth next year if bad | B56: 60
A57: Chance of good | B57: 0.5
A58: Discount rate a year | B58: 0.1
A59: Cost of waiting, d | B59: 0
A60: Started now, E V - c | B60: =B57*B55+(1-B57)*B56-B54 -> 5 | C60: 5.00
A61: Started next year only if it pays, beta E(V - c)^+ - d | B61: =(B57*MAX(B55-B54,0)+(1-B57)*MAX(B56-B54,0))/(1+B58)-B59 -> 22.727273 | C61: 22.73
A62: Expected loss waiting avoids, E(c - V)^+ | B62: =B57*MAX(B54-B55,0)+(1-B57)*MAX(B54-B56,0) -> 20 | C62: 20
A63: What waiting costs, (1 - beta) E(V - c)^+ + d | B63: =(1-1/(1+B58))*(B57*MAX(B55-B54,0)+(1-B57)*MAX(B56-B54,0))+B59 -> 2.2727273 | C63: 2.27
A64: Wait (1 = yes): waiting beats starting now and never | B64: =IF(B61>MAX(B60,0),1,0) -> 1 | C64: Proposition 16.2(i)
A65: Part (iii): committing now is right only if the loss is at most the cost (1 = commit) | B65: =IF(B62<=B63,1,0) -> 0

Sheet Certify
A1: Certify: no slack, what a margin buys, the records' corner and the price of ambiguity (Theorem 16.3; Worked Example 16.1, Step 6; Figure 16.3(a))
A2: The program re-designed for a smaller appetite (schedule held, payouts re-optimized: held at every design) keeps the board's 5% along Chapter 11's family up to the closure rate and the spread shown, each edge by bisection on the book's paths (engine). Levers and values are formulas.
A4: Design appetite | B4: Line (engine) | C4: Delay (engine) | D4: Levers | E4: Value | F4: The margin's cost | G4: Breach at the declared law (engine) | H4: Closure rate certified (engine) | I4: At the family's ceiling, 0.40 (engine) | J4: Spread certified (engine) | K4: Breach at the records' corner (engine)
A5: 0.05 | B5: 160 | C5: 2.0714825 | D5: =Fee_line*B5+Cost_delay*C5 -> 21.37186 | E5: =Programs!O28-D5 -> 1039.4082 | F5: =$E$5-E5 -> 0 | G5: 0.05 | H5: 0.100062 | I5: 0 | J5: 50 | K5: 0.13878
A6: 0.045 | B6: 165 | C6: 2.1755945 | D6: =Fee_line*B6+Cost_delay*C6 -> 22.354756 | E6: =Programs!O28-D6 -> 1038.4253 | F6: =$E$5-E6 -> 0.98289616 | G6: 0.045 | H6: 0.19170445 | I6: 0 | J6: 51.049385 | K6: 0.12821
A7: 0.04 | B7: 165 | C7: 2.3108602 | D7: =Fee_line*B7+Cost_delay*C7 -> 23.436882 | E7: =Programs!O28-D7 -> 1037.3431 | F7: =$E$5-E7 -> 2.0650222 | G7: 0.04 | H7: 0.2984342 | I7: 0 | J7: 52.186734 | K7: 0.1185
A8: 0.035 | B8: 165 | C8: 2.4622866 | D8: =Fee_line*B8+Cost_delay*C8 -> 24.648293 | E8: =Programs!O28-D8 -> 1036.1317 | F8: =$E$5-E8 -> 3.2764329 | G8: 0.035 | H8: 0.4 | I8: 1 | J8: 53.487764 | K8: 0.10836
A9: 0.03 | B9: 170 | C9: 2.6153856 | D9: =Fee_line*B9+Cost_delay*C9 -> 26.023085 | E9: =Programs!O28-D9 -> 1034.7569 | F9: =$E$5-E9 -> 4.651225 | G9: 0.03 | H9: 0.4 | I9: 1 | J9: 54.957755 | K9: 0.09688
A10: 0.025 | B10: 170 | C10: 2.8004933 | D10: =Fee_line*B10+Cost_delay*C10 -> 27.503946 | E10: =Programs!O28-D10 -> 1033.2761 | F10: =$E$5-E10 -> 6.1320866 | G10: 0.025 | H10: 0.4 | I10: 1 | J10: 56.544584 | K10: 0.08646
A11: 0.02 | B11: 165 | C11: 3.0433671 | D11: =Fee_line*B11+Cost_delay*C11 -> 29.296937 | E11: =Programs!O28-D11 -> 1031.4831 | F11: =$E$5-E11 -> 7.9250771 | G11: 0.02 | H11: 0.4 | I11: 1 | J11: 58.448311 | K11: 0.07578
A13: The records (Chapter 11) | B13: Value | C13: Note
A14: The treasury: closures in its record | B14: 2 | C14: Twenty years
A15: years of record | B15: 20
A16: the rate's one-sided 95% bound (Garwood) | B16: =CHIINV(0.05,2*B14+2)/(2*B15) -> 0.31478968 | C16: 0.315 a year
A17: The engineering office: innovations in its record | B17: 39 | C17: Forty quarters
A18: the spread's one-sided 95% bound | B18: =Sig_0*SQRT(B17/CHIINV(0.95,B17)) -> 61.599147 | C18: $61.6m
A19: a record twice as long (79 innovations) | B19: =Sig_0*SQRT(79/CHIINV(0.95,79)) -> 57.602817 | C19: $57.6m
A20: The records' corner: the spread as the book prints it | B20: 61.6 | C20: Remark 16.B.1
A22: At the records' corner | B22: Value | C22: Note
A23: The program re-designed there: line (engine) | B23: 200 | C23: $200m
A24: delay (engine) | B24: 3.4395066 | C24: 3.440 quarters
A25: levers | B25: =Fee_line*B23+Cost_delay*B24 -> 33.516053 | C25: $33.52m
A26: value | B26: =Programs!O28-B25 -> 1027.264 | C26: $1,027.26m
A27: The program's price of ambiguity | B27: =B25-Programs!O27 -> 12.144193 | C27: Printed $12.14m (33.516 less 21.372)
A28: Chapter 11's package for the build alone at its corner: line (engine) | B28: 200 | C28: Worked Example 11.1
A29: delay (engine) | B29: 2.2504041
A30: levers | B30: =Fee_line*B28+Cost_delay*B29 -> 24.003233 | C30: $24.00m
A31: Chapter 11's price of ambiguity for the build alone | B31: =B30-Pkg_cost -> 13.562622 | C31: $13.56m
A33: Triggers (Theorem 16.3(iii)) | B33: Value | C33: Note
A34: Re-certify when the closure rate's estimate passes (4% design) | B34: =H7 -> 0.2984342 | C34: 0.30 a year
A35: or the spread's estimate passes (4% design) | B35: =J7 -> 52.186734 | C35: $52.2m
A36: or the twin's monitor alarms (Chapter 15) | B36: monitor
A37: The spread is guarded worst: certified to, against the record's bound | B37: =J7/B18 -> 0.84719897 | C37: Discussion question (3)

Sheet Core
A1: The feedback core's phases (Proposition 16.1; Volume I, Worked Example 14.1; Section 16.2)
A2: Volume I's register: engineering links e, treasury links t, the new Digital-Industrial link h; the spectral radius rho = (h + sqrt(h^2 + 8(e^2 + t^2)))/2, checked below by power iteration on the register plus the identity (the largest eigenvalue of M + I is rho + 1, and the iteration settles fast even when the register is bipartite). The board's rule: deviations halve within a year, rho <= 0.5^(1/4).
A3: The register's ceiling per link | B3: 0.4 | C3: Volume I, Chapter 12
A4: The board's rule, 0.5^(1/4) | B4: =0.5^(1/4) -> 0.84089642 | C4: Half-life at most four quarters
A5: Every existing link trimmed to, sqrt((rule^2 - h rule)/4) with h at the ceiling | B5: =SQRT((B4^2-B3*B4)/4) -> 0.30444549 | C5: 0.304
A6: The new link run light, (rule^2 - 2(e^2 + t^2))/rule | B6: =(B4^2-2*(B3^2+B3^2))/B4 -> 0.079803862 | C6: 0.080
A8: Phase | B8: e | C8: t | D8: h | E8: Radius, closed form | F8: Half-life (quarters) | G8: Stable (1 = yes) | H8: Within the board's rule (1 = yes) | I8: Radius by power iteration
A9: Today | B9: =$B$3 -> 0.4 | C9: =$B$3 -> 0.4 | D9: 0 | E9: =(D9+SQRT(D9^2+8*(B9^2+C9^2)))/2 -> 0.8 | F9: =IF(E9<1,LN(2)/LN(1/E9),"none") -> 3.1062837 | G9: =IF(E9<1,1,0) -> 1 | H9: =IF(E9<=$B$4+0.000000001,1,0) -> 1 | I9: =P52/P51-1 -> 0.8
A10: Phase two: the link added, not repaired | B10: =$B$3 -> 0.4 | C10: =$B$3 -> 0.4 | D10: =$B$3 -> 0.4 | E10: =(D10+SQRT(D10^2+8*(B10^2+C10^2)))/2 -> 1.0246211 | F10: =IF(E10<1,LN(2)/LN(1/E10),"none") -> none | G10: =IF(E10<1,1,0) -> 0 | H10: =IF(E10<=$B$4+0.000000001,1,0) -> 0 | I10: =P90/P89-1 -> 1.0246211
A11: Phase two: the link run light | B11: =$B$3 -> 0.4 | C11: =$B$3 -> 0.4 | D11: =$B$6 -> 0.079803862 | E11: =(D11+SQRT(D11^2+8*(B11^2+C11^2)))/2 -> 0.84089642 | F11: =IF(E11<1,LN(2)/LN(1/E11),"none") -> 4 | G11: =IF(E11<1,1,0) -> 1 | H11: =IF(E11<=$B$4+0.000000001,1,0) -> 1 | I11: =P128/P127-1 -> 0.84089642
A12: Phase two: every link trimmed | B12: =$B$5 -> 0.30444549 | C12: =$B$5 -> 0.30444549 | D12: =$B$3 -> 0.4 | E12: =(D12+SQRT(D12^2+8*(B12^2+C12^2)))/2 -> 0.84089642 | F12: =IF(E12<1,LN(2)/LN(1/E12),"none") -> 4 | G12: =IF(E12<1,1,0) -> 1 | H12: =IF(E12<=$B$4+0.000000001,1,0) -> 1 | I12: =P166/P165-1 -> 0.84089642
A13: Trim first, the link later: after the trim | B13: =$B$5 -> 0.30444549 | C13: =$B$5 -> 0.30444549 | D13: 0 | E13: =(D13+SQRT(D13^2+8*(B13^2+C13^2)))/2 -> 0.60889097 | F13: =IF(E13<1,LN(2)/LN(1/E13),"none") -> 1.3971472 | G13: =IF(E13<1,1,0) -> 1 | H13: =IF(E13<=$B$4+0.000000001,1,0) -> 1 | I13: =P204/P203-1 -> 0.60889097
A15: Proposition 16.1(ii): today and the end state are stable, the phase between is not if the link lands first; (iii) the register is symmetric, so phases each within the rule stay stable however they alternate.
K16: Today: the register (rows receive, columns pass on)
L17: Industrial | M17: Digital | N17: Engineering | O17: Treasury
K18: Industrial | L18: 0 | M18: =$D$9 -> 0 | N18: =$B$9 -> 0.4 | O18: =$C$9 -> 0.4
K19: Digital | L19: =$D$9 -> 0 | M19: 0 | N19: =$B$9 -> 0.4 | O19: =$C$9 -> 0.4
K20: Engineering | L20: =$B$9 -> 0.4 | M20: =$B$9 -> 0.4 | N20: 0 | O20: 0
K21: Treasury | L21: =$C$9 -> 0.4 | M21: =$C$9 -> 0.4 | N21: 0 | O21: 0
K23: Iteration | L23: Industrial | M23: Digital | N23: Engineering | O23: Treasury | P23: Sum
K24: 0 | L24: 1 | M24: 1 | N24: 1 | O24: 1 | P24: =SUM(L24:O24) -> 4
K25: 1 | L25: =SUMPRODUCT($L$18:$O$18,L24:O24)+L24 -> 1.8 | M25: =SUMPRODUCT($L$19:$O$19,L24:O24)+M24 -> 1.8 | N25: =SUMPRODUCT($L$20:$O$20,L24:O24)+N24 -> 1.8 | O25: =SUMPRODUCT($L$21:$O$21,L24:O24)+O24 -> 1.8 | P25: =SUM(L25:O25) -> 7.2
K26: 2 | L26: =SUMPRODUCT($L$18:$O$18,L25:O25)+L25 -> 3.24 | M26: =SUMPRODUCT($L$19:$O$19,L25:O25)+M25 -> 3.24 | N26: =SUMPRODUCT($L$20:$O$20,L25:O25)+N25 -> 3.24 | O26: =SUMPRODUCT($L$21:$O$21,L25:O25)+O25 -> 3.24 | P26: =SUM(L26:O26) -> 12.96
K27: 3 | L27: =SUMPRODUCT($L$18:$O$18,L26:O26)+L26 -> 5.832 | M27: =SUMPRODUCT($L$19:$O$19,L26:O26)+M26 -> 5.832 | N27: =SUMPRODUCT($L$20:$O$20,L26:O26)+N26 -> 5.832 | O27: =SUMPRODUCT($L$21:$O$21,L26:O26)+O26 -> 5.832 | P27: =SUM(L27:O27) -> 23.328
K28: 4 | L28: =SUMPRODUCT($L$18:$O$18,L27:O27)+L27 -> 10.4976 | M28: =SUMPRODUCT($L$19:$O$19,L27:O27)+M27 -> 10.4976 | N28: =SUMPRODUCT($L$20:$O$20,L27:O27)+N27 -> 10.4976 | O28: =SUMPRODUCT($L$21:$O$21,L27:O27)+O27 -> 10.4976 | P28: =SUM(L28:O28) -> 41.9904
K29: 5 | L29: =SUMPRODUCT($L$18:$O$18,L28:O28)+L28 -> 18.89568 | M29: =SUMPRODUCT($L$19:$O$19,L28:O28)+M28 -> 18.89568 | N29: =SUMPRODUCT($L$20:$O$20,L28:O28)+N28 -> 18.89568 | O29: =SUMPRODUCT($L$21:$O$21,L28:O28)+O28 -> 18.89568 | P29: =SUM(L29:O29) -> 75.58272
K30: 6 | L30: =SUMPRODUCT($L$18:$O$18,L29:O29)+L29 -> 34.012224 | M30: =SUMPRODUCT($L$19:$O$19,L29:O29)+M29 -> 34.012224 | N30: =SUMPRODUCT($L$20:$O$20,L29:O29)+N29 -> 34.012224 | O30: =SUMPRODUCT($L$21:$O$21,L29:O29)+O29 -> 34.012224 | P30: =SUM(L30:O30) -> 136.0489
K31: 7 | L31: =SUMPRODUCT($L$18:$O$18,L30:O30)+L30 -> 61.222003 | M31: =SUMPRODUCT($L$19:$O$19,L30:O30)+M30 -> 61.222003 | N31: =SUMPRODUCT($L$20:$O$20,L30:O30)+N30 -> 61.222003 | O31: =SUMPRODUCT($L$21:$O$21,L30:O30)+O30 -> 61.222003 | P31: =SUM(L31:O31) -> 244.88801
K32: 8 | L32: =SUMPRODUCT($L$18:$O$18,L31:O31)+L31 -> 110.19961 | M32: =SUMPRODUCT($L$19:$O$19,L31:O31)+M31 -> 110.19961 | N32: =SUMPRODUCT($L$20:$O$20,L31:O31)+N31 -> 110.19961 | O32: =SUMPRODUCT($L$21:$O$21,L31:O31)+O31 -> 110.19961 | P32: =SUM(L32:O32) -> 440.79842
K33: 9 | L33: =SUMPRODUCT($L$18:$O$18,L32:O32)+L32 -> 198.35929 | M33: =SUMPRODUCT($L$19:$O$19,L32:O32)+M32 -> 198.35929 | N33: =SUMPRODUCT($L$20:$O$20,L32:O32)+N32 -> 198.35929 | O33: =SUMPRODUCT($L$21:$O$21,L32:O32)+O32 -> 198.35929 | P33: =SUM(L33:O33) -> 793.43716
K34: 10 | L34: =SUMPRODUCT($L$18:$O$18,L33:O33)+L33 -> 357.04672 | M34: =SUMPRODUCT($L$19:$O$19,L33:O33)+M33 -> 357.04672 | N34: =SUMPRODUCT($L$20:$O$20,L33:O33)+N33 -> 357.04672 | O34: =SUMPRODUCT($L$21:$O$21,L33:O33)+O33 -> 357.04672 | P34: =SUM(L34:O34) -> 1428.1869
K35: 11 | L35: =SUMPRODUCT($L$18:$O$18,L34:O34)+L34 -> 642.6841 | M35: =SUMPRODUCT($L$19:$O$19,L34:O34)+M34 -> 642.6841 | N35: =SUMPRODUCT($L$20:$O$20,L34:O34)+N34 -> 642.6841 | O35: =SUMPRODUCT($L$21:$O$21,L34:O34)+O34 -> 642.6841 | P35: =SUM(L35:O35) -> 2570.7364
K36: 12 | L36: =SUMPRODUCT($L$18:$O$18,L35:O35)+L35 -> 1156.8314 | M36: =SUMPRODUCT($L$19:$O$19,L35:O35)+M35 -> 1156.8314 | N36: =SUMPRODUCT($L$20:$O$20,L35:O35)+N35 -> 1156.8314 | O36: =SUMPRODUCT($L$21:$O$21,L35:O35)+O35 -> 1156.8314 | P36: =SUM(L36:O36) -> 4627.3255
... K52: 28 | L52: =SUMPRODUCT($L$18:$O$18,L51:O51)+L51 -> 14048506 | M52: =SUMPRODUCT($L$19:$O$19,L51:O51)+M51 -> 14048506 | N52: =SUMPRODUCT($L$20:$O$20,L51:O51)+N51 -> 14048506 | O52: =SUMPRODUCT($L$21:$O$21,L51:O51)+O51 -> 14048506 | P52: =SUM(L52:O52) -> 56194024
K54: Phase two: the link added, not repaired: the register (rows receive, columns pass on)
L55: Industrial | M55: Digital | N55: Engineering | O55: Treasury
K56: Industrial | L56: 0 | M56: =$D$10 -> 0.4 | N56: =$B$10 -> 0.4 | O56: =$C$10 -> 0.4
K57: Digital | L57: =$D$10 -> 0.4 | M57: 0 | N57: =$B$10 -> 0.4 | O57: =$C$10 -> 0.4
K58: Engineering | L58: =$B$10 -> 0.4 | M58: =$B$10 -> 0.4 | N58: 0 | O58: 0
K59: Treasury | L59: =$C$10 -> 0.4 | M59: =$C$10 -> 0.4 | N59: 0 | O59: 0
K61: Iteration | L61: Industrial | M61: Digital | N61: Engineering | O61: Treasury | P61: Sum
K62: 0 | L62: 1 | M62: 1 | N62: 1 | O62: 1 | P62: =SUM(L62:O62) -> 4
K63: 1 | L63: =SUMPRODUCT($L$56:$O$56,L62:O62)+L62 -> 2.2 | M63: =SUMPRODUCT($L$57:$O$57,L62:O62)+M62 -> 2.2 | N63: =SUMPRODUCT($L$58:$O$58,L62:O62)+N62 -> 1.8 | O63: =SUMPRODUCT($L$59:$O$59,L62:O62)+O62 -> 1.8 | P63: =SUM(L63:O63) -> 8
K64: 2 | L64: =SUMPRODUCT($L$56:$O$56,L63:O63)+L63 -> 4.52 | M64: =SUMPRODUCT($L$57:$O$57,L63:O63)+M63 -> 4.52 | N64: =SUMPRODUCT($L$58:$O$58,L63:O63)+N63 -> 3.56 | O64: =SUMPRODUCT($L$59:$O$59,L63:O63)+O63 -> 3.56 | P64: =SUM(L64:O64) -> 16.16
K65: 3 | L65: =SUMPRODUCT($L$56:$O$56,L64:O64)+L64 -> 9.176 | M65: =SUMPRODUCT($L$57:$O$57,L64:O64)+M64 -> 9.176 | N65: =SUMPRODUCT($L$58:$O$58,L64:O64)+N64 -> 7.176 | O65: =SUMPRODUCT($L$59:$O$59,L64:O64)+O64 -> 7.176 | P65: =SUM(L65:O65) -> 32.704
K66: 4 | L66: =SUMPRODUCT($L$56:$O$56,L65:O65)+L65 -> 18.5872 | M66: =SUMPRODUCT($L$57:$O$57,L65:O65)+M65 -> 18.5872 | N66: =SUMPRODUCT($L$58:$O$58,L65:O65)+N65 -> 14.5168 | O66: =SUMPRODUCT($L$59:$O$59,L65:O65)+O65 -> 14.5168 | P66: =SUM(L66:O66) -> 66.208
K67: 5 | L67: =SUMPRODUCT($L$56:$O$56,L66:O66)+L66 -> 37.63552 | M67: =SUMPRODUCT($L$57:$O$57,L66:O66)+M66 -> 37.63552 | N67: =SUMPRODUCT($L$58:$O$58,L66:O66)+N66 -> 29.38656 | O67: =SUMPRODUCT($L$59:$O$59,L66:O66)+O66 -> 29.38656 | P67: =SUM(L67:O67) -> 134.04416
K68: 6 | L68: =SUMPRODUCT($L$56:$O$56,L67:O67)+L67 -> 76.198976 | M68: =SUMPRODUCT($L$57:$O$57,L67:O67)+M67 -> 76.198976 | N68: =SUMPRODUCT($L$58:$O$58,L67:O67)+N67 -> 59.494976 | O68: =SUMPRODUCT($L$59:$O$59,L67:O67)+O67 -> 59.494976 | P68: =SUM(L68:O68) -> 271.3879
K69: 7 | L69: =SUMPRODUCT($L$56:$O$56,L68:O68)+L68 -> 154.27455 | M69: =SUMPRODUCT($L$57:$O$57,L68:O68)+M68 -> 154.27455 | N69: =SUMPRODUCT($L$58:$O$58,L68:O68)+N68 -> 120.45416 | O69: =SUMPRODUCT($L$59:$O$59,L68:O68)+O68 -> 120.45416 | P69: =SUM(L69:O69) -> 549.45741
K70: 8 | L70: =SUMPRODUCT($L$56:$O$56,L69:O69)+L69 -> 312.34769 | M70: =SUMPRODUCT($L$57:$O$57,L69:O69)+M69 -> 312.34769 | N70: =SUMPRODUCT($L$58:$O$58,L69:O69)+N69 -> 243.87379 | O70: =SUMPRODUCT($L$59:$O$59,L69:O69)+O69 -> 243.87379 | P70: =SUM(L70:O70) -> 1112.443
K71: 9 | L71: =SUMPRODUCT($L$56:$O$56,L70:O70)+L70 -> 632.3858 | M71: =SUMPRODUCT($L$57:$O$57,L70:O70)+M70 -> 632.3858 | N71: =SUMPRODUCT($L$58:$O$58,L70:O70)+N70 -> 493.75195 | O71: =SUMPRODUCT($L$59:$O$59,L70:O70)+O70 -> 493.75195 | P71: =SUM(L71:O71) -> 2252.2755
K72: 10 | L72: =SUMPRODUCT($L$56:$O$56,L71:O71)+L71 -> 1280.3417 | M72: =SUMPRODUCT($L$57:$O$57,L71:O71)+M71 -> 1280.3417 | N72: =SUMPRODUCT($L$58:$O$58,L71:O71)+N71 -> 999.66059 | O72: =SUMPRODUCT($L$59:$O$59,L71:O71)+O71 -> 999.66059 | P72: =SUM(L72:O72) -> 4560.0045
K73: 11 | L73: =SUMPRODUCT($L$56:$O$56,L72:O72)+L72 -> 2592.2068 | M73: =SUMPRODUCT($L$57:$O$57,L72:O72)+M72 -> 2592.2068 | N73: =SUMPRODUCT($L$58:$O$58,L72:O72)+N72 -> 2023.9339 | O73: =SUMPRODUCT($L$59:$O$59,L72:O72)+O72 -> 2023.9339 | P73: =SUM(L73:O73) -> 9232.2815
K74: 12 | L74: =SUMPRODUCT($L$56:$O$56,L73:O73)+L73 -> 5248.2367 | M74: =SUMPRODUCT($L$57:$O$57,L73:O73)+M73 -> 5248.2367 | N74: =SUMPRODUCT($L$58:$O$58,L73:O73)+N73 -> 4097.6994 | O74: =SUMPRODUCT($L$59:$O$59,L73:O73)+O73 -> 4097.6994 | P74: =SUM(L74:O74) -> 18691.872
... K90: 28 | L90: =SUMPRODUCT($L$56:$O$56,L89:O89)+L89 -> 4.1832483e+08 | M90: =SUMPRODUCT($L$57:$O$57,L89:O89)+M89 -> 4.1832483e+08 | N90: =SUMPRODUCT($L$58:$O$58,L89:O89)+N89 -> 3.2661815e+08 | O90: =SUMPRODUCT($L$59:$O$59,L89:O89)+O89 -> 3.2661815e+08 | P90: =SUM(L90:O90) -> 1.489886e+09
K92: Phase two: the link run light: the register (rows receive, columns pass on)
L93: Industrial | M93: Digital | N93: Engineering | O93: Treasury
K94: Industrial | L94: 0 | M94: =$D$11 -> 0.079803862 | N94: =$B$11 -> 0.4 | O94: =$C$11 -> 0.4
K95: Digital | L95: =$D$11 -> 0.079803862 | M95: 0 | N95: =$B$11 -> 0.4 | O95: =$C$11 -> 0.4
K96: Engineering | L96: =$B$11 -> 0.4 | M96: =$B$11 -> 0.4 | N96: 0 | O96: 0
K97: Treasury | L97: =$C$11 -> 0.4 | M97: =$C$11 -> 0.4 | N97: 0 | O97: 0
K99: Iteration | L99: Industrial | M99: Digital | N99: Engineering | O99: Treasury | P99: Sum
K100: 0 | L100: 1 | M100: 1 | N100: 1 | O100: 1 | P100: =SUM(L100:O100) -> 4
K101: 1 | L101: =SUMPRODUCT($L$94:$O$94,L100:O100)+L100 -> 1.8798039 | M101: =SUMPRODUCT($L$95:$O$95,L100:O100)+M100 -> 1.8798039 | N101: =SUMPRODUCT($L$96:$O$96,L100:O100)+N100 -> 1.8 | O101: =SUMPRODUCT($L$97:$O$97,L100:O100)+O100 -> 1.8 | P101: =SUM(L101:O101) -> 7.3596077
K102: 2 | L102: =SUMPRODUCT($L$94:$O$94,L101:O101)+L101 -> 3.4698195 | M102: =SUMPRODUCT($L$95:$O$95,L101:O101)+M101 -> 3.4698195 | N102: =SUMPRODUCT($L$96:$O$96,L101:O101)+N101 -> 3.3038431 | O102: =SUMPRODUCT($L$97:$O$97,L101:O101)+O101 -> 3.3038431 | P102: =SUM(L102:O102) -> 13.547325
K103: 3 | L103: =SUMPRODUCT($L$94:$O$94,L102:O102)+L102 -> 6.3897989 | M103: =SUMPRODUCT($L$95:$O$95,L102:O102)+M102 -> 6.3897989 | N103: =SUMPRODUCT($L$96:$O$96,L102:O102)+N102 -> 6.0796987 | O103: =SUMPRODUCT($L$97:$O$97,L102:O102)+O102 -> 6.0796987 | P103: =SUM(L103:O103) -> 24.938995
K104: 4 | L104: =SUMPRODUCT($L$94:$O$94,L103:O103)+L103 -> 11.763488 | M104: =SUMPRODUCT($L$95:$O$95,L103:O103)+M103 -> 11.763488 | N104: =SUMPRODUCT($L$96:$O$96,L103:O103)+N103 -> 11.191538 | O104: =SUMPRODUCT($L$97:$O$97,L103:O103)+O103 -> 11.191538 | P104: =SUM(L104:O104) -> 45.910053
K105: 5 | L105: =SUMPRODUCT($L$94:$O$94,L104:O104)+L104 -> 21.655491 | M105: =SUMPRODUCT($L$95:$O$95,L104:O104)+M104 -> 21.655491 | N105: =SUMPRODUCT($L$96:$O$96,L104:O104)+N104 -> 20.602329 | O105: =SUMPRODUCT($L$97:$O$97,L104:O104)+O104 -> 20.602329 | P105: =SUM(L105:O105) -> 84.515638
K106: 6 | L106: =SUMPRODUCT($L$94:$O$94,L105:O105)+L105 -> 39.865545 | M106: =SUMPRODUCT($L$95:$O$95,L105:O105)+M105 -> 39.865545 | N106: =SUMPRODUCT($L$96:$O$96,L105:O105)+N105 -> 37.926721 | O106: =SUMPRODUCT($L$97:$O$97,L105:O105)+O105 -> 37.926721 | P106: =SUM(L106:O106) -> 155.58453
K107: 7 | L107: =SUMPRODUCT($L$94:$O$94,L106:O106)+L106 -> 73.388347 | M107: =SUMPRODUCT($L$95:$O$95,L106:O106)+M106 -> 73.388347 | N107: =SUMPRODUCT($L$96:$O$96,L106:O106)+N106 -> 69.819157 | O107: =SUMPRODUCT($L$97:$O$97,L106:O106)+O106 -> 69.819157 | P107: =SUM(L107:O107) -> 286.41501
K108: 8 | L108: =SUMPRODUCT($L$94:$O$94,L107:O107)+L107 -> 135.10035 | M108: =SUMPRODUCT($L$95:$O$95,L107:O107)+M107 -> 135.10035 | N108: =SUMPRODUCT($L$96:$O$96,L107:O107)+N107 -> 128.52983 | O108: =SUMPRODUCT($L$97:$O$97,L107:O107)+O107 -> 128.52983 | P108: =SUM(L108:O108) -> 527.26036
K109: 9 | L109: =SUMPRODUCT($L$94:$O$94,L108:O108)+L108 -> 248.70574 | M109: =SUMPRODUCT($L$95:$O$95,L108:O108)+M108 -> 248.70574 | N109: =SUMPRODUCT($L$96:$O$96,L108:O108)+N108 -> 236.61011 | O109: =SUMPRODUCT($L$97:$O$97,L108:O108)+O108 -> 236.61011 | P109: =SUM(L109:O109) -> 970.63171
K110: 10 | L110: =SUMPRODUCT($L$94:$O$94,L109:O109)+L109 -> 457.84151 | M110: =SUMPRODUCT($L$95:$O$95,L109:O109)+M109 -> 457.84151 | N110: =SUMPRODUCT($L$96:$O$96,L109:O109)+N109 -> 435.57471 | O110: =SUMPRODUCT($L$97:$O$97,L109:O109)+O109 -> 435.57471 | P110: =SUM(L110:O110) -> 1786.8324
K111: 11 | L111: =SUMPRODUCT($L$94:$O$94,L110:O110)+L110 -> 842.83879 | M111: =SUMPRODUCT($L$95:$O$95,L110:O110)+M110 -> 842.83879 | N111: =SUMPRODUCT($L$96:$O$96,L110:O110)+N110 -> 801.84791 | O111: =SUMPRODUCT($L$97:$O$97,L110:O110)+O110 -> 801.84791 | P111: =SUM(L111:O111) -> 3289.3734
K112: 12 | L112: =SUMPRODUCT($L$94:$O$94,L111:O111)+L111 -> 1551.5789 | M112: =SUMPRODUCT($L$95:$O$95,L111:O111)+M111 -> 1551.5789 | N112: =SUMPRODUCT($L$96:$O$96,L111:O111)+N111 -> 1476.1189 | O112: =SUMPRODUCT($L$97:$O$97,L111:O111)+O111 -> 1476.1189 | P112: =SUM(L112:O112) -> 6055.3957
... K128: 28 | L128: =SUMPRODUCT($L$94:$O$94,L127:O127)+L127 -> 26992524 | M128: =SUMPRODUCT($L$95:$O$95,L127:O127)+M127 -> 26992524 | N128: =SUMPRODUCT($L$96:$O$96,L127:O127)+N127 -> 25679762 | O128: =SUMPRODUCT($L$97:$O$97,L127:O127)+O127 -> 25679762 | P128: =SUM(L128:O128) -> 1.0534457e+08
K130: Phase two: every link trimmed: the register (rows receive, columns pass on)
L131: Industrial | M131: Digital | N131: Engineering | O131: Treasury
K132: Industrial | L132: 0 | M132: =$D$12 -> 0.4 | N132: =$B$12 -> 0.30444549 | O132: =$C$12 -> 0.30444549
K133: Digital | L133: =$D$12 -> 0.4 | M133: 0 | N133: =$B$12 -> 0.30444549 | O133: =$C$12 -> 0.30444549
K134: Engineering | L134: =$B$12 -> 0.30444549 | M134: =$B$12 -> 0.30444549 | N134: 0 | O134: 0
K135: Treasury | L135: =$C$12 -> 0.30444549 | M135: =$C$12 -> 0.30444549 | N135: 0 | O135: 0
K137: Iteration | L137: Industrial | M137: Digital | N137: Engineering | O137: Treasury | P137: Sum
K138: 0 | L138: 1 | M138: 1 | N138: 1 | O138: 1 | P138: =SUM(L138:O138) -> 4
K139: 1 | L139: =SUMPRODUCT($L$132:$O$132,L138:O138)+L138 -> 2.008891 | M139: =SUMPRODUCT($L$133:$O$133,L138:O138)+M138 -> 2.008891 | N139: =SUMPRODUCT($L$134:$O$134,L138:O138)+N138 -> 1.608891 | O139: =SUMPRODUCT($L$135:$O$135,L138:O138)+O138 -> 1.608891 | P139: =SUM(L139:O139) -> 7.2355639
K140: 2 | L140: =SUMPRODUCT($L$132:$O$132,L139:O139)+L139 -> 3.7920865 | M140: =SUMPRODUCT($L$133:$O$133,L139:O139)+M139 -> 3.7920865 | N140: =SUMPRODUCT($L$134:$O$134,L139:O139)+N139 -> 2.8320865 | O140: =SUMPRODUCT($L$135:$O$135,L139:O139)+O139 -> 2.8320865 | P140: =SUM(L140:O140) -> 13.248346
K141: 3 | L141: =SUMPRODUCT($L$132:$O$132,L140:O140)+L140 -> 7.0333531 | M141: =SUMPRODUCT($L$133:$O$133,L140:O140)+M140 -> 7.0333531 | N141: =SUMPRODUCT($L$134:$O$134,L140:O140)+N140 -> 5.1410538 | O141: =SUMPRODUCT($L$135:$O$135,L140:O140)+O140 -> 5.1410538 | P141: =SUM(L141:O141) -> 24.348814
K142: 4 | L142: =SUMPRODUCT($L$132:$O$132,L141:O141)+L141 -> 12.977036 | M142: =SUMPRODUCT($L$133:$O$133,L141:O141)+M141 -> 12.977036 | N142: =SUMPRODUCT($L$134:$O$134,L141:O141)+N141 -> 9.423599 | O142: =SUMPRODUCT($L$135:$O$135,L141:O141)+O141 -> 9.423599 | P142: =SUM(L142:O142) -> 44.801269
K143: 5 | L143: =SUMPRODUCT($L$132:$O$132,L142:O142)+L142 -> 23.905794 | M143: =SUMPRODUCT($L$133:$O$133,L142:O142)+M142 -> 23.905794 | N143: =SUMPRODUCT($L$134:$O$134,L142:O142)+N142 -> 17.325199 | O143: =SUMPRODUCT($L$135:$O$135,L142:O142)+O142 -> 17.325199 | P143: =SUM(L143:O143) -> 82.461986
K144: 6 | L144: =SUMPRODUCT($L$132:$O$132,L143:O143)+L143 -> 44.017269 | M144: =SUMPRODUCT($L$133:$O$133,L143:O143)+M143 -> 44.017269 | N144: =SUMPRODUCT($L$134:$O$134,L143:O143)+N143 -> 31.881221 | O144: =SUMPRODUCT($L$135:$O$135,L143:O143)+O143 -> 31.881221 | P144: =SUM(L144:O144) -> 151.79698
K145: 7 | L145: =SUMPRODUCT($L$132:$O$132,L144:O144)+L144 -> 81.036364 | M145: =SUMPRODUCT($L$133:$O$133,L144:O144)+M144 -> 81.036364 | N145: =SUMPRODUCT($L$134:$O$134,L144:O144)+N144 -> 58.682939 | O145: =SUMPRODUCT($L$135:$O$135,L144:O144)+O144 -> 58.682939 | P145: =SUM(L145:O145) -> 279.43861
K146: 8 | L146: =SUMPRODUCT($L$132:$O$132,L145:O145)+L145 -> 149.18242 | M146: =SUMPRODUCT($L$133:$O$133,L145:O145)+M145 -> 149.18242 | N146: =SUMPRODUCT($L$134:$O$134,L145:O145)+N145 -> 108.02525 | O146: =SUMPRODUCT($L$135:$O$135,L145:O145)+O145 -> 108.02525 | P146: =SUM(L146:O146) -> 514.41534
K147: 9 | L147: =SUMPRODUCT($L$132:$O$132,L146:O146)+L146 -> 274.63099 | M147: =SUMPRODUCT($L$133:$O$133,L146:O146)+M146 -> 274.63099 | N147: =SUMPRODUCT($L$134:$O$134,L146:O146)+N146 -> 198.86108 | O147: =SUMPRODUCT($L$135:$O$135,L146:O146)+O146 -> 198.86108 | P147: =SUM(L147:O147) -> 946.98414
K148: 10 | L148: =SUMPRODUCT($L$132:$O$132,L147:O147)+L147 -> 505.5681 | M148: =SUMPRODUCT($L$133:$O$133,L147:O147)+M147 -> 505.5681 | N148: =SUMPRODUCT($L$134:$O$134,L147:O147)+N147 -> 366.08141 | O148: =SUMPRODUCT($L$135:$O$135,L147:O147)+O147 -> 366.08141 | P148: =SUM(L148:O148) -> 1743.299
K149: 11 | L149: =SUMPRODUCT($L$132:$O$132,L148:O148)+L148 -> 930.699 | M149: =SUMPRODUCT($L$133:$O$133,L148:O148)+M148 -> 930.699 | N149: =SUMPRODUCT($L$134:$O$134,L148:O148)+N148 -> 673.91726 | O149: =SUMPRODUCT($L$135:$O$135,L148:O148)+O148 -> 673.91726 | P149: =SUM(L149:O149) -> 3209.2325
K150: 12 | L150: =SUMPRODUCT($L$132:$O$132,L149:O149)+L149 -> 1713.3207 | M150: =SUMPRODUCT($L$133:$O$133,L149:O149)+M149 -> 1713.3207 | N150: =SUMPRODUCT($L$134:$O$134,L149:O149)+N149 -> 1240.6115 | O150: =SUMPRODUCT($L$135:$O$135,L149:O149)+O149 -> 1240.6115 | P150: =SUM(L150:O150) -> 5907.8644
... K166: 28 | L166: =SUMPRODUCT($L$132:$O$132,L165:O165)+L165 -> 29806318 | M166: =SUMPRODUCT($L$133:$O$133,L165:O165)+M165 -> 29806318 | N166: =SUMPRODUCT($L$134:$O$134,L165:O165)+N165 -> 21582680 | O166: =SUMPRODUCT($L$135:$O$135,L165:O165)+O165 -> 21582680 | P166: =SUM(L166:O166) -> 1.02778e+08
K168: Trim first, the link later: after the trim: the register (rows receive, columns pass on)
L169: Industrial | M169: Digital | N169: Engineering | O169: Treasury
K170: Industrial | L170: 0 | M170: =$D$13 -> 0 | N170: =$B$13 -> 0.30444549 | O170: =$C$13 -> 0.30444549
...

Sheet Table16_3
A1: Table 16.3: programs on one account (Worked Example 16.1)
A2: Levers: the line's fees and the delay's cost; value: payouts at 10 percent plus the year-6 savings forever, less the levers; breach: the chance of liquidity below $350m in some quarter of the build, on the book's 100,000 paths (engine).
A4: Program | B4: Rounds (years) | C4: Line | D4: Delay (q) | E4: Levers | F4: Value | G4: Breach (%)
A5: Pieces as certified | B5: 1-3 | C5: =Pkg_line -> 170 | D5: =Pkg_delay -> 0.66757636 | E5: =Pkg_cost -> 10.440611 | F5: – | G5: 74.331
A6: levers to keep them | B6: 1-3 | C6: 165 | D6: 5.6336263 | E6: =Fee_line*C6+Cost_delay*D6 -> 50.01901 | F6: – | G6: 5
A7: Best program | B7: 1-3 | C7: =Programs!O25 -> 160 | D7: =Programs!O26 -> 2.0714825 | E7: =Programs!O27 -> 21.37186 | F7: =Programs!O29 -> 1039.4082 | G7: 5
A8: Round 3 in year 4 | B8: 1, 2, 4 | C8: =Programs!O37 -> 160 | D8: =Programs!O38 -> 1.4770281 | E8: =Programs!O39 -> 16.616225 | F8: =Programs!O41 -> 1036.8009 | G8: 5
A9: Round 3 on a trigger | B9: 1, 2, 3 or 4 | C9: =Trigger!B43 -> 155 | D9: =Trigger!B44 -> 1.6423944 | E9: =Trigger!B45 -> 17.789155 | F9: =Trigger!B41 -> 1040.7557 | G9: 5
A10: Sale after the build | B10: 1-3 | C10: =Programs!O133 -> 165 | D10: =Programs!O134 -> 5.970015 | E10: =Programs!O135 -> 52.71012 | F10: =Programs!O137 -> 1001.7862 | G10: 5
A11: No sale | B11: 1-3 | C11: =Programs!O121 -> 165 | D11: =Programs!O122 -> 5.970015 | E11: =Programs!O123 -> 52.71012 | F11: =Programs!O125 -> 938.94894 | G11: 5
A12: Designed for 4% | B12: 1-3 | C12: =Certify!B7 -> 165 | D12: =Certify!C7 -> 2.3108602 | E12: =Certify!D7 -> 23.436882 | F12: =Certify!E7 -> 1037.3431 | G12: 4
A13: At the records' corner | B13: 1-3 | C13: =Certify!B23 -> 200 | D13: =Certify!B24 -> 3.4395066 | E13: =Certify!B25 -> 33.516053 | F13: =Certify!B26 -> 1027.264 | G13: 5

Sheet Reference_Values
A1: Checkpoint | B1: Engine value | C1: Meaning (where in the book)
A2: The sale's proceeds with the engineers kept | B2: 92 | C2: $92m (Step 1)
A3: A dollar a year of savings, beta^6 / r | B3: 5.6447393 | C3: $5.645 (Step 1)
A4: Chapter 5's plan alone: value | B4: 1021.9325 | C4: $1,021.93m
A5: Chapter 5's plan alone: payout in year 1 | B5: 85 | C5: 85, 0, 122.5, 122.5, 122.5, 2.5
A6: Chapter 5's plan alone: payout in year 2 | B6: 0 | C6: 85, 0, 122.5, 122.5, 122.5, 2.5
A7: Chapter 5's plan alone: payout in year 3 | B7: 122.5 | C7: 85, 0, 122.5, 122.5, 122.5, 2.5
A8: Chapter 5's plan alone: payout in year 4 | B8: 122.5 | C8: 85, 0, 122.5, 122.5, 122.5, 2.5
A9: Chapter 5's plan alone: payout in year 5 | B9: 122.5 | C9: 85, 0, 122.5, 122.5, 122.5, 2.5
A10: Chapter 5's plan alone: payout in year 6 | B10: 2.5 | C10: 85, 0, 122.5, 122.5, 122.5, 2.5
A11: The draw at its deepest, a point of depth | B11: 6.2 | C11: $6.2m, quarter 8
A12: The plan without the draw, long run | B12: 694.4 | C12: Toward $694m
A13: Volume I's package: levers | B13: 10.440611 | C13: $10.44m
... A121: Core phase 5: power iteration agrees with the closed form | B121: 0 | C121: Volume I's register plus the identity, 28 iterations

Sheet Checks
A1: Checkpoint | B1: Workbook formula value | C1: Engine value | D1: |diff| | E1: Tolerance | F1: Status
A2: The sale's proceeds with the engineers kept | B2: =Sale_G -> 92 | C2: =Reference_Values!B2 -> 92 | D2: =ABS(B2-C2) -> 0 | E2: 0 | F2: =IF(D2<=E2,"PASS","FAIL") -> PASS
A3: A dollar a year of savings, beta^6 / r | B3: =Sav_price -> 5.6447393 | C3: =Reference_Values!B3 -> 5.6447393 | D3: =ABS(B3-C3) -> 0 | E3: 1e-12 | F3: =IF(D3<=E3,"PASS","FAIL") -> PASS
A4: Chapter 5's plan alone: value | B4: =Chapter5!B15 -> 1021.9325 | C4: =Reference_Values!B4 -> 1021.9325 | D4: =ABS(B4-C4) -> 0 | E4: 1e-09 | F4: =IF(D4<=E4,"PASS","FAIL") -> PASS
A5: Chapter 5's plan alone: payout in year 1 | B5: =Chapter5!G6 -> 85 | C5: =Reference_Values!B5 -> 85 | D5: =ABS(B5-C5) -> 0 | E5: 1e-09 | F5: =IF(D5<=E5,"PASS","FAIL") -> PASS
A6: Chapter 5's plan alone: payout in year 2 | B6: =Chapter5!G7 -> 0 | C6: =Reference_Values!B6 -> 0 | D6: =ABS(B6-C6) -> 0 | E6: 1e-09 | F6: =IF(D6<=E6,"PASS","FAIL") -> PASS
A7: Chapter 5's plan alone: payout in year 3 | B7: =Chapter5!G8 -> 122.5 | C7: =Reference_Values!B7 -> 122.5 | D7: =ABS(B7-C7) -> 0 | E7: 1e-09 | F7: =IF(D7<=E7,"PASS","FAIL") -> PASS
A8: Chapter 5's plan alone: payout in year 4 | B8: =Chapter5!G9 -> 122.5 | C8: =Reference_Values!B8 -> 122.5 | D8: =ABS(B8-C8) -> 0 | E8: 1e-09 | F8: =IF(D8<=E8,"PASS","FAIL") -> PASS
A9: Chapter 5's plan alone: payout in year 5 | B9: =Chapter5!G10 -> 122.5 | C9: =Reference_Values!B9 -> 122.5 | D9: =ABS(B9-C9) -> 0 | E9: 1e-09 | F9: =IF(D9<=E9,"PASS","FAIL") -> PASS
A10: Chapter 5's plan alone: payout in year 6 | B10: =Chapter5!G11 -> 2.5 | C10: =Reference_Values!B10 -> 2.5 | D10: =ABS(B10-C10) -> 0 | E10: 1e-09 | F10: =IF(D10<=E10,"PASS","FAIL") -> PASS
A11: The draw at its deepest, a point of depth | B11: =OneAccount!D12 -> 6.2 | C11: =Reference_Values!B11 -> 6.2 | D11: =ABS(B11-C11) -> 0 | E11: 1e-09 | F11: =IF(D11<=E11,"PASS","FAIL") -> PASS
A12: The plan without the draw, long run | B12: =Declarations!B34 -> 694.4 | C12: =Reference_Values!B12 -> 694.4 | D12: =ABS(B12-C12) -> 0 | E12: 1e-09 | F12: =IF(D12<=E12,"PASS","FAIL") -> PASS
A13: Volume I's package: levers | B13: =Pkg_cost -> 10.440611 | C13: =Reference_Values!B13 -> 10.440611 | D13: =ABS(B13-C13) -> 0 | E13: 1e-09 | F13: =IF(D13<=E13,"PASS","FAIL") -> PASS
A14: The build alone: its deepest quarter | B14: =OneAccount!B37 -> 7 | C14: =Reference_Values!B14 -> 7 | D14: =ABS(B14-C14) -> 0 | E14: 0 | F14: =IF(D14<=E14,"PASS","FAIL") -> PASS
A15: The build alone: its deepest draw | B15: =OneAccount!B38 -> 121.63437 | C15: =Reference_Values!B15 -> 121.63437 | D15: =ABS(B15-C15) -> 0 | E15: 1e-08 | F15: =IF(D15<=E15,"PASS","FAIL") -> PASS
A16: The build alone: closure buffer | B16: =OneAccount!B39 -> 16.866976 | C16: =Reference_Values!B16 -> 16.866976 | D16: =ABS(B16-C16) -> 0 | E16: 1e-06 | F16: =IF(D16<=E16,"PASS","FAIL") -> PASS
A17: Planned margin at quarter 9, with the sale | B17: =OneAccount!J13 -> 7.259622 | C17: =Reference_Values!B17 -> 7.259622 | D17: =ABS(B17-C17) -> 0 | E17: 1e-08 | F17: =IF(D17<=E17,"PASS","FAIL") -> PASS
A18: Planned margin at quarter 9, without the sale | B18: =OneAccount!K13 -> -84.740378 | C18: =Reference_Values!B18 -> -84.740378 | D18: =ABS(B18-C18) -> 0 | E18: 1e-08 | F18: =IF(D18<=E18,"PASS","FAIL") -> PASS
A19: The binding quarter of the joint check | B19: =OneAccount!B32 -> 9 | C19: =Reference_Values!B19 -> 9 | D19: =ABS(B19-C19) -> 0 | E19: 0 | F19: =IF(D19<=E19,"PASS","FAIL") -> PASS
A20: Claims at quarter 9, pieces: the build's draw | B20: =OneAccount!C32 -> 115.36538 | C20: =Reference_Values!B20 -> 115.36538 | D20: =ABS(B20-C20) -> 0 | E20: 1e-08 | F20: =IF(D20<=E20,"PASS","FAIL") -> PASS
A21: Claims at quarter 9, pieces: the rounds less their savings | B21: =OneAccount!D32 -> 154.375 | C21: =Reference_Values!B21 -> 154.375 | D21: =ABS(B21-C21) -> 0 | E21: 1e-08 | F21: =IF(D21<=E21,"PASS","FAIL") -> PASS
A22: Claims at quarter 9, pieces: the payouts made | B22: =OneAccount!E32 -> 85 | C22: =Reference_Values!B22 -> 85 | D22: =ABS(B22-C22) -> 0 | E22: 1e-08 | F22: =IF(D22<=E22,"PASS","FAIL") -> PASS
A23: Claims at quarter 9, pieces: the closure buffer | B23: =OneAccount!F32 -> 16.866976 | C23: =Reference_Values!B23 -> 16.866976 | D23: =ABS(B23-C23) -> 0 | E23: 1e-06 | F23: =IF(D23<=E23,"PASS","FAIL") -> PASS
A24: Claims at quarter 9, pieces with the sale: left of the room | B24: =OneAccount!I32 -> -9.6073544 | C24: =Reference_Values!B24 -> -9.6073544 | D24: =ABS(B24-C24) -> 0 | E24: 1e-06 | F24: =IF(D24<=E24,"PASS","FAIL") -> PASS
A25: Claims at quarter 9, pieces without the sale: left of the room | B25: =OneAccount!I31 -> -101.60735 | C25: =Reference_Values!B25 -> -101.60735 | D25: =ABS(B25-C25) -> 0 | E25: 1e-06 | F25: =IF(D25<=E25,"PASS","FAIL") -> PASS
A26: The room with the sale | B26: =OneAccount!H32 -> 362 | C26: =Reference_Values!B26 -> 362 | D26: =ABS(B26-C26) -> 0 | E26: 0 | F26: =IF(D26<=E26,"PASS","FAIL") -> PASS
A27: Claims at quarter 9, program: the build's draw | B27: =OneAccount!C33 -> 80.798874 | C27: =Reference_Values!B27 -> 80.798874 | D27: =ABS(B27-C27) -> 0 | E27: 1e-08 | F27: =IF(D27<=E27,"PASS","FAIL") -> PASS
A28: Claims at quarter 9, program: the rounds less their savings | B28: =OneAccount!D33 -> 154.375 | C28: =Reference_Values!B28 -> 154.375 | D28: =ABS(B28-C28) -> 0 | E28: 1e-08 | F28: =IF(D28<=E28,"PASS","FAIL") -> PASS
A29: Claims at quarter 9, program: the payouts made | B29: =OneAccount!E33 -> 0 | C29: =Reference_Values!B29 -> 0 | D29: =ABS(B29-C29) -> 0 | E29: 1e-08 | F29: =IF(D29<=E29,"PASS","FAIL") -> PASS
A30: Claims at quarter 9, program: the closure buffer | B30: =OneAccount!F33 -> 26.866976 | C30: =Reference_Values!B30 -> 26.866976 | D30: =ABS(B30-C30) -> 0 | E30: 1e-06 | F30: =IF(D30<=E30,"PASS","FAIL") -> PASS
A31: Claims at quarter 9, program: left of the room | B31: =OneAccount!I33 -> 99.959149 | C31: =Reference_Values!B31 -> 99.959149 | D31: =ABS(B31-C31) -> 0 | E31: 1e-06 | F31: =IF(D31<=E31,"PASS","FAIL") -> PASS
A32: Levers to keep the pieces as certified | B32: =Table16_3!E6 -> 50.01901 | C32: =Reference_Values!B32 -> 50.01901 | D32: =ABS(B32-C32) -> 0 | E32: 1e-08 | F32: =IF(D32<=E32,"PASS","FAIL") -> PASS
A33: Rounds in years 1, 2, 3: value | B33: =Programs!O29 -> 1039.4082 | C33: =Reference_Values!B33 -> 1039.4082 | D33: =ABS(B33-C33) -> 0 | E33: 1e-08 | F33: =IF(D33<=E33,"PASS","FAIL") -> PASS
A34: Rounds in years 1, 2, 4: value | B34: =Programs!O41 -> 1036.8009 | C34: =Reference_Values!B34 -> 1036.8009 | D34: =ABS(B34-C34) -> 0 | E34: 1e-08 | F34: =IF(D34<=E34,"PASS","FAIL") -> PASS
A35: Rounds in years 1, 3, 4: value | B35: =Programs!O53 -> 1022.5659 | C35: =Reference_Values!B35 -> 1022.5659 | D35: =ABS(B35-C35) -> 0 | E35: 1e-08 | F35: =IF(D35<=E35,"PASS","FAIL") -> PASS
A36: Rounds in years 1, 4, 5: value | B36: =Programs!O65 -> 1001.5913 | C36: =Reference_Values!B36 -> 1001.5913 | D36: =ABS(B36-C36) -> 0 | E36: 1e-08 | F36: =IF(D36<=E36,"PASS","FAIL") -> PASS
A37: Rounds in years 2, 3, 4: value | B37: =Programs!O77 -> 953.57579 | C37: =Reference_Values!B37 -> 953.57579 | D37: =ABS(B37-C37) -> 0 | E37: 1e-08 | F37: =IF(D37<=E37,"PASS","FAIL") -> PASS
A38: Rounds in years 2, 4, 5: value | B38: =Programs!O89 -> 937.5977 | C38: =Reference_Values!B38 -> 937.5977 | D38: =ABS(B38-C38) -> 0 | E38: 1e-08 | F38: =IF(D38<=E38,"PASS","FAIL") -> PASS
A39: Rounds in years 3, 4, 5: value | B39: =Programs!O101 -> 883.16153 | C39: =Reference_Values!B39 -> 883.16153 | D39: =ABS(B39-C39) -> 0 | E39: 1e-08 | F39: =IF(D39<=E39,"PASS","FAIL") -> PASS
A40: Rounds in years 4, 5, 6: value | B40: =Programs!O113 -> 821.10686 | C40: =Reference_Values!B40 -> 821.10686 | D40: =ABS(B40-C40) -> 0 | E40: 1e-08 | F40: =IF(D40<=E40,"PASS","FAIL") -> PASS
A41: Rounds in years 1, 2, 4: levers | B41: =Programs!O39 -> 16.616225 | C41: =Reference_Values!B41 -> 16.616225 | D41: =ABS(B41-C41) -> 0 | E41: 1e-08 | F41: =IF(D41<=E41,"PASS","FAIL") -> PASS
A42: Rounds in years 1, 3, 4: levers | B42: =Programs!O51 -> 4.2922746 | C42: =Reference_Values!B42 -> 4.2922746 | D42: =ABS(B42-C42) -> 0 | E42: 1e-08 | F42: =IF(D42<=E42,"PASS","FAIL") -> PASS
A43: Round 3 moved to year 4 costs | B43: =Programs!P5 -> 2.6072499 | C43: =Reference_Values!B43 -> 2.6072499 | D43: =ABS(B43-C43) -> 0 | E43: 1e-08 | F43: =IF(D43<=E43,"PASS","FAIL") -> PASS
A44: Rounds started in year 2 cost | B44: =Programs!P8 -> 85.832365 | C44: =Reference_Values!B44 -> 85.832365 | D44: =ABS(B44-C44) -> 0 | E44: 1e-08 | F44: =IF(D44<=E44,"PASS","FAIL") -> PASS
A45: Every program keeps its commitments after the build | B45: =SUM(Programs!Q4:Q16) -> 13 | C45: =Reference_Values!B45 -> 13 | D45: =ABS(B45-C45) -> 0 | E45: 0 | F45: =IF(D45<=E45,"PASS","FAIL") -> PASS
A46: No sale: levers | B46: =Prices!B11 -> 52.71012 | C46: =Reference_Values!B46 -> 52.71012 | D46: =ABS(B46-C46) -> 0 | E46: 1e-08 | F46: =IF(D46<=E46,"PASS","FAIL") -> PASS
A47: No sale: value | B47: =Prices!B10 -> 938.94894 | C47: =Reference_Values!B47 -> 938.94894 | D47: =ABS(B47-C47) -> 0 | E47: 1e-08 | F47: =IF(D47<=E47,"PASS","FAIL") -> PASS
A48: Sale after the build: value | B48: =Prices!B12 -> 1001.7862 | C48: =Reference_Values!B48 -> 1001.7862 | D48: =ABS(B48-C48) -> 0 | E48: 1e-08 | F48: =IF(D48<=E48,"PASS","FAIL") -> PASS
A49: The sale first is worth | B49: =Prices!B13 -> 100.45922 | C49: =Reference_Values!B49 -> 100.45922 | D49: =ABS(B49-C49) -> 0 | E49: 1e-08 | F49: =IF(D49<=E49,"PASS","FAIL") -> PASS
A50: The sale's proceeds paid out at the end of year 3 | B50: =Prices!B14 -> 69.120962 | C50: =Reference_Values!B50 -> 69.120962 | D50: =ABS(B50-C50) -> 0 | E50: 1e-09 | F50: =IF(D50<=E50,"PASS","FAIL") -> PASS
A51: The levers the sale makes unnecessary | B51: =Prices!B15 -> 31.33826 | C51: =Reference_Values!B51 -> 31.33826 | D51: =ABS(B51-C51) -> 0 | E51: 1e-08 | F51: =IF(D51<=E51,"PASS","FAIL") -> PASS
A52: The sale first beats the sale after the build by | B52: =Prices!B17 -> 37.621984 | C52: =Reference_Values!B52 -> 37.621984 | D52: =ABS(B52-C52) -> 0 | E52: 1e-08 | F52: =IF(D52<=E52,"PASS","FAIL") -> PASS
A53: The best program: levers | B53: =Prices!B4 -> 21.37186 | C53: =Reference_Values!B53 -> 21.37186 | D53: =ABS(B53-C53) -> 0 | E53: 1e-08 | F53: =IF(D53<=E53,"PASS","FAIL") -> PASS
A54: The best program: value from its parts | B54: =Prices!B7 -> 1039.4082 | C54: =Reference_Values!B54 -> 1039.4082 | D54: =ABS(B54-C54) -> 0 | E54: 1e-08 | F54: =IF(D54<=E54,"PASS","FAIL") -> PASS
A55: The best program: payout in year 3 | B55: =Programs!H27 -> 189.92405 | C55: =Reference_Values!B55 -> 189.92405 | D55: =ABS(B55-C55) -> 0 | E55: 1e-08 | F55: =IF(D55<=E55,"PASS","FAIL") -> PASS
A56: The best program: payout in year 4 | B56: =Programs!H28 -> 160.4014 | C56: =Reference_Values!B56 -> 160.4014 | D56: =ABS(B56-C56) -> 0 | E56: 1e-08 | F56: =IF(D56<=E56,"PASS","FAIL") -> PASS
A57: The best program: payout in year 5 | B57: =Programs!H29 -> 158.80729 | C57: =Reference_Values!B57 -> 158.80729 | D57: =ABS(B57-C57) -> 0 | E57: 1e-08 | F57: =IF(D57<=E57,"PASS","FAIL") -> PASS
A58: The best program: payout in year 6 | B58: =Programs!H30 -> 32.673897 | C58: =Reference_Values!B58 -> 32.673897 | D58: =ABS(B58-C58) -> 0 | E58: 1e-08 | F58: =IF(D58<=E58,"PASS","FAIL") -> PASS
A59: The appetite at 4.5%: value | B59: =Prices!E21 -> 1038.4253 | C59: =Reference_Values!B59 -> 1038.4253 | D59: =ABS(B59-C59) -> 0 | E59: 1e-08 | F59: =IF(D59<=E59,"PASS","FAIL") -> PASS
A60: The appetite at 5.5%: value | B60: =Prices!E22 -> 1040.2533 | C60: =Reference_Values!B60 -> 1040.2533 | D60: =ABS(B60-C60) -> 0 | E60: 1e-08 | F60: =IF(D60<=E60,"PASS","FAIL") -> PASS
A61: The appetite's price, a point | B61: =Prices!E23 -> 1.8280788 | C61: =Reference_Values!B61 -> 1.8280788 | D61: =ABS(B61-C61) -> 0 | E61: 1e-08 | F61: =IF(D61<=E61,"PASS","FAIL") -> PASS
A62: Volume I's price for the build alone | B62: =Prices!D28 -> 1.8070148 | C62: =Reference_Values!B62 -> 1.8070148 | D62: =ABS(B62-C62) -> 0 | E62: 1e-08 | F62: =IF(D62<=E62,"PASS","FAIL") -> PASS
A63: The line buys a point of chance for | B63: =Prices!B39 -> 1.7647059 | C63: =Reference_Values!B63 -> 1.7647059 | D63: =ABS(B63-C63) -> 0 | E63: 1e-08 | F63: =IF(D63<=E63,"PASS","FAIL") -> PASS
A64: The delay buys a point of chance for | B64: =Prices!B40 -> 2.2857143 | C64: =Reference_Values!B64 -> 2.2857143 | D64: =ABS(B64-C64) -> 0 | E64: 1e-08 | F64: =IF(D64<=E64,"PASS","FAIL") -> PASS
A65: Paying in year 1 earns a point | B65: =Prices!B43 -> 0.77493177 | C65: =Reference_Values!B65 -> 0.77493177 | D65: =ABS(B65-C65) -> 0 | E65: 1e-08 | F65: =IF(D65<=E65,"PASS","FAIL") -> PASS
A66: Paying in year 2 earns a point | B66: =Prices!B45 -> 0.66962103 | C66: =Reference_Values!B66 -> 0.66962103 | D66: =ABS(B66-C66) -> 0 | E66: 1e-08 | F66: =IF(D66<=E66,"PASS","FAIL") -> PASS
A67: beta - beta^3 | B67: =Prices!B41 -> 0.15777611 | C67: =Reference_Values!B67 -> 0.15777611 | D67: =ABS(B67-C67) -> 0 | E67: 1e-12 | F67: =IF(D67<=E67,"PASS","FAIL") -> PASS
A68: Points of chance a dollar paid in year 1 spends | B68: =Prices!B42 -> 0.2036 | C68: =Reference_Values!B68 -> 0.2036 | D68: =ABS(B68-C68) -> 0 | E68: 1e-09 | F68: =IF(D68<=E68,"PASS","FAIL") -> PASS
A69: A dollar of room at the start | B69: =Prices!B50 -> 1.0880297 | C69: =Reference_Values!B69 -> 1.0880297 | D69: =ABS(B69-C69) -> 0 | E69: 1e-08 | F69: =IF(D69<=E69,"PASS","FAIL") -> PASS
A70: A dollar of room: paid out at the end of year 3 | B70: =Prices!B51 -> 0.7513148 | C70: =Reference_Values!B70 -> 0.7513148 | D70: =ABS(B70-C70) -> 0 | E70: 1e-12 | F70: =IF(D70<=E70,"PASS","FAIL") -> PASS
A71: A dollar of room: levers made unnecessary | B71: =Prices!B52 -> 0.33671488 | C71: =Reference_Values!B71 -> 0.33671488 | D71: =ABS(B71-C71) -> 0 | E71: 1e-08 | F71: =IF(D71<=E71,"PASS","FAIL") -> PASS
A72: A point of capability at Chapter 7's price | B72: =Prices!B55 -> 3.9 | C72: =Reference_Values!B72 -> 3.9 | D72: =ABS(B72-C72) -> 0 | E72: 1e-12 | F72: =IF(D72<=E72,"PASS","FAIL") -> PASS
A73: Capability of rounds in years 1-3 | B73: =Prices!B56 -> 10.668595 | C73: =Reference_Values!B73 -> 10.668595 | D73: =ABS(B73-C73) -> 0 | E73: 1e-09 | F73: =IF(D73<=E73,"PASS","FAIL") -> PASS
A74: Capability of rounds in years 1, 2, 4 | B74: =Prices!B57 -> 10.375582 | C74: =Reference_Values!B74 -> 10.375582 | D74: =ABS(B74-C74) -> 0 | E74: 1e-09 | F74: =IF(D74<=E74,"PASS","FAIL") -> PASS
A75: Payouts wait: both earn less than the appetite's price | B75: =Prices!B46 -> 1 | C75: =Reference_Values!B75 -> 1 | D75: =ABS(B75-C75) -> 0 | E75: 0 | F75: =IF(D75<=E75,"PASS","FAIL") -> PASS
A76: Holding Chapter 5's year-1 payout is worth | B76: =Prices!B62 -> 15.236181 | C76: =Reference_Values!B76 -> 15.236181 | D76: =ABS(B76-C76) -> 2.3270275e-13 | E76: 1e-08 | F76: =IF(D76<=E76,"PASS","FAIL") -> PASS
A77: Round 3 on a trigger: the best trigger | B77: =Trigger!B42 -> 490 | C77: =Reference_Values!B77 -> 490 | D77: =ABS(B77-C77) -> 0 | E77: 0 | F77: =IF(D77<=E77,"PASS","FAIL") -> PASS
A78: Round 3 on a trigger: levers | B78: =Trigger!B45 -> 17.789155 | C78: =Reference_Values!B78 -> 17.789155 | D78: =ABS(B78-C78) -> 0 | E78: 1e-08 | F78: =IF(D78<=E78,"PASS","FAIL") -> PASS
A79: Round 3 on a trigger: value | B79: =Trigger!B41 -> 1040.7557 | C79: =Reference_Values!B79 -> 1040.7557 | D79: =ABS(B79-C79) -> 0 | E79: 1e-08 | F79: =IF(D79<=E79,"PASS","FAIL") -> PASS
A80: Round 3 on a trigger: more than committing to year 3 | B80: =Trigger!B49 -> 1.3475432 | C80: =Reference_Values!B80 -> 1.3475432 | D80: =ABS(B80-C80) -> 0 | E80: 1e-08 | F80: =IF(D80<=E80,"PASS","FAIL") -> PASS
A81: Round 3 on a trigger: more than committing to year 4 | B81: =Trigger!B50 -> 3.9547932 | C81: =Reference_Values!B81 -> 3.9547932 | D81: =ABS(B81-C81) -> 0 | E81: 1e-08 | F81: =IF(D81<=E81,"PASS","FAIL") -> PASS
A82: Theorem 16.2(iii): the rule beats both timings | B82: =Trigger!B51 -> 1 | C82: =Reference_Values!B82 -> 1 | D82: =ABS(B82-C82) -> 0 | E82: 0 | F82: =IF(D82<=E82,"PASS","FAIL") -> PASS
A83: Proposition 16.2: the project started now | B83: =Trigger!B60 -> 5 | C83: =Reference_Values!B83 -> 5 | D83: =ABS(B83-C83) -> 0 | E83: 1e-09 | F83: =IF(D83<=E83,"PASS","FAIL") -> PASS
A84: Proposition 16.2: the project if it waits | B84: =Trigger!B61 -> 22.727273 | C84: =Reference_Values!B84 -> 22.727273 | D84: =ABS(B84-C84) -> 0 | E84: 1e-09 | F84: =IF(D84<=E84,"PASS","FAIL") -> PASS
A85: Proposition 16.2: the loss waiting avoids | B85: =Trigger!B62 -> 20 | C85: =Reference_Values!B85 -> 20 | D85: =ABS(B85-C85) -> 0 | E85: 1e-09 | F85: =IF(D85<=E85,"PASS","FAIL") -> PASS
A86: Proposition 16.2: what waiting costs | B86: =Trigger!B63 -> 2.2727273 | C86: =Reference_Values!B86 -> 2.2727273 | D86: =ABS(B86-C86) -> 0 | E86: 1e-09 | F86: =IF(D86<=E86,"PASS","FAIL") -> PASS
A87: Design for 4.5%: levers | B87: =Certify!D6 -> 22.354756 | C87: =Reference_Values!B87 -> 22.354756 | D87: =ABS(B87-C87) -> 0 | E87: 1e-08 | F87: =IF(D87<=E87,"PASS","FAIL") -> PASS
A88: Design for 4.5%: value | B88: =Certify!E6 -> 1038.4253 | C88: =Reference_Values!B88 -> 1038.4253 | D88: =ABS(B88-C88) -> 0 | E88: 1e-08 | F88: =IF(D88<=E88,"PASS","FAIL") -> PASS
A89: Design for 4%: levers | B89: =Certify!D7 -> 23.436882 | C89: =Reference_Values!B89 -> 23.436882 | D89: =ABS(B89-C89) -> 0 | E89: 1e-08 | F89: =IF(D89<=E89,"PASS","FAIL") -> PASS
A90: Design for 4%: value | B90: =Certify!E7 -> 1037.3431 | C90: =Reference_Values!B90 -> 1037.3431 | D90: =ABS(B90-C90) -> 0 | E90: 1e-08 | F90: =IF(D90<=E90,"PASS","FAIL") -> PASS
A91: Design for 3.5%: levers | B91: =Certify!D8 -> 24.648293 | C91: =Reference_Values!B91 -> 24.648293 | D91: =ABS(B91-C91) -> 0 | E91: 1e-08 | F91: =IF(D91<=E91,"PASS","FAIL") -> PASS
A92: Design for 3.5%: value | B92: =Certify!E8 -> 1036.1317 | C92: =Reference_Values!B92 -> 1036.1317 | D92: =ABS(B92-C92) -> 0 | E92: 1e-08 | F92: =IF(D92<=E92,"PASS","FAIL") -> PASS
A93: Design for 3%: levers | B93: =Certify!D9 -> 26.023085 | C93: =Reference_Values!B93 -> 26.023085 | D93: =ABS(B93-C93) -> 0 | E93: 1e-08 | F93: =IF(D93<=E93,"PASS","FAIL") -> PASS
A94: Design for 3%: value | B94: =Certify!E9 -> 1034.7569 | C94: =Reference_Values!B94 -> 1034.7569 | D94: =ABS(B94-C94) -> 0 | E94: 1e-08 | F94: =IF(D94<=E94,"PASS","FAIL") -> PASS
A95: Design for 2.5%: levers | B95: =Certify!D10 -> 27.503946 | C95: =Reference_Values!B95 -> 27.503946 | D95: =ABS(B95-C95) -> 0 | E95: 1e-08 | F95: =IF(D95<=E95,"PASS","FAIL") -> PASS
A96: Design for 2.5%: value | B96: =Certify!E10 -> 1033.2761 | C96: =Reference_Values!B96 -> 1033.2761 | D96: =ABS(B96-C96) -> 0 | E96: 1e-08 | F96: =IF(D96<=E96,"PASS","FAIL") -> PASS
A97: Design for 2%: levers | B97: =Certify!D11 -> 29.296937 | C97: =Reference_Values!B97 -> 29.296937 | D97: =ABS(B97-C97) -> 0 | E97: 1e-08 | F97: =IF(D97<=E97,"PASS","FAIL") -> PASS
A98: Design for 2%: value | B98: =Certify!E11 -> 1031.4831 | C98: =Reference_Values!B98 -> 1031.4831 | D98: =ABS(B98-C98) -> 0 | E98: 1e-08 | F98: =IF(D98<=E98,"PASS","FAIL") -> PASS
A99: Design for 4%: the margin's cost | B99: =Certify!F7 -> 2.0650222 | C99: =Reference_Values!B99 -> 2.0650222 | D99: =ABS(B99-C99) -> 0 | E99: 1e-08 | F99: =IF(D99<=E99,"PASS","FAIL") -> PASS
A100: Design for 3%: the margin's cost | B100: =Certify!F9 -> 4.651225 | C100: =Reference_Values!B100 -> 4.651225 | D100: =ABS(B100-C100) -> 0 | E100: 1e-08 | F100: =IF(D100<=E100,"PASS","FAIL") -> PASS
...
