Workbook

Sheet README
B1: DCT Laboratory — Vol II, Ch 15: Enterprise Digital Twins and Autonomous Enterprise Transformation
B2: Seed 26215 · Companion to DCT_V2_Ch15_Lab.ipynb and AXIOM Lab 2.15 (module AXIOM-15). Money in $ million.
B4: Worked Example 15.1, Can a Digital Twin Replace the Engineering Office's Count?, with the book's declarations: Chapter 7's law and costs, an audited start at 58, the skills survey twice a year with an error of 2.5 points, the twin (a Kalman filter) running Chapter 7's target rule on its estimate, the monitor and the audit on an alarm, and a drift from quarter 8. Seeds as in Online Appendix Remark 15.B.1.
B5: Declarations: the law, the costs, the discount, the swings, the survey, the monitor, the drift, the seeds.
B6: Sync: the twin's error variance quarter by quarter for four surveys, the survey read as exact and no readings; the periodic fixed points in closed form; precisions add; a biased survey (Step 2; Theorem 15.1; Proposition 15.1).
B7: Program: one program from the audited 58 (Figure 15.1(a), seed 1503), run by formulas on the engine's draws.
B8: Decide: the design-path searches' best targets, Table 15.3's costs above the count and their yearly worth, the certification on fresh paths, and Theorem 15.2(iii)'s margins (Steps 3 and 6; Figure 15.2(a)).
B9: Readings: what better surveys are worth, and the readings study (Step 4; Figure 15.2(b)).
B10: Bias, Monitor, Drift: the twin that never questions its law, the cumulative sum and its threshold on a printed sample of innovations, the drift's costs and the detection delays (Step 5; Theorem 15.3; Figure 15.3).
B11: Envelope: the guardrail, the calendar of uncertainty, the loop's modes (Step 6; Proposition 15.3). Table15_3: the Worked Example's table, linked to the sheets.
B12: Engine values (green) are what needs simulation: costs on the design and fresh paths, shares below the floor, false-alarm rates, the drift's costs and delays, and the sample's innovations.
B13: Reference_Values and Checks: the engine's numbers and a PASS/FAIL comparison with this workbook's formulas.
... B19: Cross-sheet link: green.

Sheet Declarations
A1: Declarations (Worked Example 15.1, Step 1; Chapter 7's law and costs; the twin, its survey and its monitor; Online Appendix Remark 15.B.1). Money in $ million; capability in points.
A3: Quantity | B3: Value | C3: Source
A4: Discount rate a year | B4: 0.1 | C4: The board's 10 percent
A5: Discount factor a quarter, beta | B5: =(1+B4)^(-1/4) -> 0.97645409 | C5: beta = 1.1^(-1/4)
A6: Effective horizon 1/(1 - beta), quarters | B6: =1/(1-B5) -> 42.47022
A7: Capability kept each quarter, a | B7: 0.975 | C7: Chapter 7
A8: Cost of a point hired and trained, k | B8: 4 | C8: $4 million a point
A9: Hiring cap a quarter (points) | B9: 2.5
A10: Capability floor | B10: 55
A11: Cost of a point-quarter short | B11: 1.6 | C11: $1.6 million (Chapter 7)
A12: The audited start | B12: 58 | C12: Every design is priced from 58
A13: Chapter 7's target for planned capability | B13: 55.75 | C13: Worked Example 7.1, on the count
A14: Chapter 7's cost from 58 (its 0.05-point grid) | B14: 230.755 | C14: Worked Example 7.1
A15: The skills survey's error, sd (points) | B15: 2.5 | C15: 95 percent of readings within +/-5 (Volume I, Table 5.2)
A16: its variance r | B16: =B15^2 -> 6.25
A17: A survey twice as sharp, sd | B17: =B15/2 -> 1.25 | C17: 1.25 points
A18: its variance | B18: =B17^2 -> 1.5625
A19: The survey runs every (quarters) | B19: 2 | C19: Twice a year, at the start of quarters 2, 4, 6, ...
A20: A quarterly survey runs every (quarters) | B20: 1
A21: Quarters of present value | B21: 480 | C21: 120 years
A22: Long-run shares from quarter | B22: 40 | C22: Quarters 40-479
A23: The monitor's reference, kappa | B23: 0.5 | C23: Detects a shift of one standard deviation
A24: At most one false alarm in so many surveys | B24: 50 | C24: The threshold's calibration
A25: The drift begins at the start of quarter | B25: 8 | C25: A tighter labor market (Step 5)
A26: extra points lost each quarter | B26: 0.5
A27: Design paths | B27: 20000 | C27: Seed 1500
A28: Fresh paths (and drift paths) | B28: 100000 | C28: Seeds 1501 and 1507
A30: Swing w (points lost) | B30: Chance
A31: 1.5 | B31: 0.05
A32: 0.75 | B32: 0.2
A33: 0 | B33: 0.5
A34: -0.75 | B34: 0.2
A35: -1.5 | B35: 0.05
A36: Total | B36: =SUM(B31:B35) -> 1
A37: Mean swing | B37: =SUMPRODUCT(A31:A35,B31:B35) -> 0
A38: A swing's variance q | B38: =SUMPRODUCT(A31:A35,A31:A35,B31:B35)-B37^2 -> 0.45 | C38: 0.45
A39: its standard deviation | B39: =SQRT(B38) -> 0.67082039 | C39: 0.67 points (Section 15.2)
A40: c' = 0.975c + h - w; a quarter costs 4h + 1.6(55 - c)^+. The twin knows the law and its hires, not the swings: its filter uses the swings' mean 0 and variance q, and a variance of 0 at the audited start.
A42: Seeds (Online Appendix Remark 15.B.1)
A43: Design paths (20,000) | B43: 1500 | C43: Each design's best target
A44: Fresh paths (100,000) | B44: 1501 | C44: Table 15.3's costs
A45: The program of Figure 15.1(a) | B45: 1503 | C45: The Program sheet
A46: The monitor's calibration (20,000 paths, no drift) | B46: 1505
A47: The drift (100,000 paths) | B47: 1507
A48: The exact filter's check (300 programs of 40 quarters) | B48: 1509
A49: The lab's seed (new draws only) | B49: 26215 | C49: The notebook's Panels 2 and 5

Sheet Sync
A1: Synchronize: the twin's error, quarter by quarter (Equation 15.1; Theorem 15.1(iii)-(iv); Proposition 15.1; Worked Example 15.1, Step 2; Figure 15.1(b); AXIOM Lab 2.15, step 1)
A2: Prior P- = a^2 P + q; at a survey the gain K = P-/(P- + r) and the posterior (1 - K) P-; no survey, no correction. The variances do not depend on the readings (Proposition 15.3(iii)). Quarter 0 is the audited start, variance 0.
B4: Twin, survey twice a year | G4: Twin, quarterly survey | L4: Twin, survey twice as sharp | Q4: Twin, both | V4: Survey read as exact | X4: No readings after the audit | AA4: Steady state (closed form) | AB4: Survey every k | AC4: Variance r | AD4: a^(2k) | AE4: c_k = q(1 - a^(2k))/(1 - a^2) | AF4: P just after a survey (fixed point) | AG4: Error just after (sd) | AH4: A quarter later (sd) | AI4: Just before the next (sd) | AJ4: Gain | AK4: The recursion at quarter 60 (sd)
A5: Quarter | B5: Survey (1 = yes) | C5: Prior P- | D5: Gain K | E5: Posterior P | F5: Error the twin decides with (sd) | G5: Survey (1 = yes) | H5: Prior P- | I5: Gain K | J5: Posterior P | K5: Error the twin decides with (sd) | L5: Survey (1 = yes) | M5: Prior P- | N5: Gain K | O5: Posterior P | P5: Error the twin decides with (sd) | Q5: Survey (1 = yes) | R5: Prior P- | S5: Gain K | T5: Posterior P | U5: Error the twin decides with (sd) | V5: Variance | W5: Error (sd) | X5: Variance | Y5: Error (sd)
A6: 0 | B6: =IF(AND($A6>0,MOD($A6,Every2)=0),1,0) -> 0 | C6: 0 | D6: =IF(B6=1,C6/(C6+R_s),0) -> 0 | E6: =(1-D6)*C6 -> 0 | F6: =SQRT(E6) -> 0 | G6: =IF(AND($A6>0,MOD($A6,Every1)=0),1,0) -> 0 | H6: 0 | I6: =IF(G6=1,H6/(H6+R_s),0) -> 0 | J6: =(1-I6)*H6 -> 0 | K6: =SQRT(J6) -> 0 | L6: =IF(AND($A6>0,MOD($A6,Every2)=0),1,0) -> 0 | M6: 0 | N6: =IF(L6=1,M6/(M6+R_sharp),0) -> 0 | O6: =(1-N6)*M6 -> 0 | P6: =SQRT(O6) -> 0 | Q6: =IF(AND($A6>0,MOD($A6,Every1)=0),1,0) -> 0 | R6: 0 | S6: =IF(Q6=1,R6/(R6+R_sharp),0) -> 0 | T6: =(1-S6)*R6 -> 0 | U6: =SQRT(T6) -> 0 | V6: 0 | W6: =SQRT(V6) -> 0 | X6: 0 | Y6: =SQRT(X6) -> 0 | AA6: Twin, survey twice a year | AB6: =Every2 -> 2 | AC6: =R_s -> 6.25 | AD6: =Alpha_keep^(2*AB6) -> 0.90368789 | AE6: =Q_var*(1-AD6)/(1-Alpha_keep^2) -> 0.87778125 | AF6: =(-(AE6+AC6-AC6*AD6)+SQRT((AE6+AC6-AC6*AD6)^2+4*AD6*AC6*AE6))/(2*AD6) -> 1.7776496 | AG6: =SQRT(AF6) -> 1.3332852 | AH6: =IF(AB6=2,SQRT(Alpha_keep^2*AF6+Q_var),"") -> 1.4628322 | AI6: =SQRT(AD6*AF6+AE6) -> 1.5761414 | AJ6: =(AD6*AF6+AE6)/(AD6*AF6+AE6+AC6) -> 0.28442393 | AK6: =F66 -> 1.3332852
A7: 1 | B7: =IF(AND($A7>0,MOD($A7,Every2)=0),1,0) -> 0 | C7: =Alpha_keep^2*E6+Q_var -> 0.45 | D7: =IF(B7=1,C7/(C7+R_s),0) -> 0 | E7: =(1-D7)*C7 -> 0.45 | F7: =SQRT(E7) -> 0.67082039 | G7: =IF(AND($A7>0,MOD($A7,Every1)=0),1,0) -> 1 | H7: =Alpha_keep^2*J6+Q_var -> 0.45 | I7: =IF(G7=1,H7/(H7+R_s),0) -> 0.067164179 | J7: =(1-I7)*H7 -> 0.41977612 | K7: =SQRT(J7) -> 0.64790132 | L7: =IF(AND($A7>0,MOD($A7,Every2)=0),1,0) -> 0 | M7: =Alpha_keep^2*O6+Q_var -> 0.45 | N7: =IF(L7=1,M7/(M7+R_sharp),0) -> 0 | O7: =(1-N7)*M7 -> 0.45 | P7: =SQRT(O7) -> 0.67082039 | Q7: =IF(AND($A7>0,MOD($A7,Every1)=0),1,0) -> 1 | R7: =Alpha_keep^2*T6+Q_var -> 0.45 | S7: =IF(Q7=1,R7/(R7+R_sharp),0) -> 0.22360248 | T7: =(1-S7)*R7 -> 0.34937888 | U7: =SQRT(T7) -> 0.5910828 | V7: =IF(MOD($A7,Every2)=0,R_s,Alpha_keep^2*V6+Q_var) -> 0.45 | W7: =SQRT(V7) -> 0.67082039 | X7: =Alpha_keep^2*X6+Q_var -> 0.45 | Y7: =SQRT(X7) -> 0.67082039 | AA7: Twin, quarterly survey | AB7: =Every1 -> 1 | AC7: =R_s -> 6.25 | AD7: =Alpha_keep^(2*AB7) -> 0.950625 | AE7: =Q_var*(1-AD7)/(1-Alpha_keep^2) -> 0.45 | AF7: =(-(AE7+AC7-AC7*AD7)+SQRT((AE7+AC7-AC7*AD7)^2+4*AD7*AC7*AE7))/(2*AD7) -> 1.3667259 | AG7: =SQRT(AF7) -> 1.1690705 | AH7: =IF(AB7=2,SQRT(Alpha_keep^2*AF7+Q_var),"") | AI7: =SQRT(AD7*AF7+AE7) -> 1.3225898 | AJ7: =(AD7*AF7+AE7)/(AD7*AF7+AE7+AC7) -> 0.21867615 | AK7: =K66 -> 1.1690705
A8: 2 | B8: =IF(AND($A8>0,MOD($A8,Every2)=0),1,0) -> 1 | C8: =Alpha_keep^2*E7+Q_var -> 0.87778125 | D8: =IF(B8=1,C8/(C8+R_s),0) -> 0.1231493 | E8: =(1-D8)*C8 -> 0.76968311 | F8: =SQRT(E8) -> 0.87731585 | G8: =IF(AND($A8>0,MOD($A8,Every1)=0),1,0) -> 1 | H8: =Alpha_keep^2*J7+Q_var -> 0.84904967 | I8: =IF(G8=1,H8/(H8+R_s),0) -> 0.11960047 | J8: =(1-I8)*H8 -> 0.74750293 | K8: =SQRT(J8) -> 0.86458252 | L8: =IF(AND($A8>0,MOD($A8,Every2)=0),1,0) -> 1 | M8: =Alpha_keep^2*O7+Q_var -> 0.87778125 | N8: =IF(L8=1,M8/(M8+R_sharp),0) -> 0.35970495 | O8: =(1-N8)*M8 -> 0.56203899 | P8: =SQRT(O8) -> 0.7496926 | Q8: =IF(AND($A8>0,MOD($A8,Every1)=0),1,0) -> 1 | R8: =Alpha_keep^2*T7+Q_var -> 0.7821283 | S8: =IF(Q8=1,R8/(R8+R_sharp),0) -> 0.33358307 | T8: =(1-S8)*R8 -> 0.52122354 | U8: =SQRT(T8) -> 0.72195813 | V8: =IF(MOD($A8,Every2)=0,R_s,Alpha_keep^2*V7+Q_var) -> 6.25 | W8: =SQRT(V8) -> 2.5 | X8: =Alpha_keep^2*X7+Q_var -> 0.87778125 | Y8: =SQRT(X8) -> 0.93689981 | AA8: Twin, survey twice as sharp | AB8: =Every2 -> 2 | AC8: =R_sharp -> 1.5625 | AD8: =Alpha_keep^(2*AB8) -> 0.90368789 | AE8: =Q_var*(1-AD8)/(1-Alpha_keep^2) -> 0.87778125 | AF8: =(-(AE8+AC8-AC8*AD8)+SQRT((AE8+AC8-AC8*AD8)^2+4*AD8*AC8*AE8))/(2*AD8) -> 0.788048 | AG8: =SQRT(AF8) -> 0.88772068 | AH8: =IF(AB8=2,SQRT(Alpha_keep^2*AF8+Q_var),"") -> 1.0950517 | AI8: =SQRT(AD8*AF8+AE8) -> 1.2609245 | AJ8: =(AD8*AF8+AE8)/(AD8*AF8+AE8+AC8) -> 0.50435072 | AK8: =P66 -> 0.88772068
A9: 3 | B9: =IF(AND($A9>0,MOD($A9,Every2)=0),1,0) -> 0 | C9: =Alpha_keep^2*E8+Q_var -> 1.18168 | D9: =IF(B9=1,C9/(C9+R_s),0) -> 0 | E9: =(1-D9)*C9 -> 1.18168 | F9: =SQRT(E9) -> 1.0870511 | G9: =IF(AND($A9>0,MOD($A9,Every1)=0),1,0) -> 1 | H9: =Alpha_keep^2*J8+Q_var -> 1.160595 | I9: =IF(G9=1,H9/(H9+R_s),0) -> 0.15661293 | J9: =(1-I9)*H9 -> 0.9788308 | K9: =SQRT(J9) -> 0.98935878 | L9: =IF(AND($A9>0,MOD($A9,Every2)=0),1,0) -> 0 | M9: =Alpha_keep^2*O8+Q_var -> 0.98428831 | N9: =IF(L9=1,M9/(M9+R_sharp),0) -> 0 | O9: =(1-N9)*M9 -> 0.98428831 | P9: =SQRT(O9) -> 0.99211305 | Q9: =IF(AND($A9>0,MOD($A9,Every1)=0),1,0) -> 1 | R9: =Alpha_keep^2*T8+Q_var -> 0.94548813 | S9: =IF(Q9=1,R9/(R9+R_sharp),0) -> 0.37699067 | T9: =(1-S9)*R9 -> 0.58904792 | U9: =SQRT(T9) -> 0.76749458 | V9: =IF(MOD($A9,Every2)=0,R_s,Alpha_keep^2*V8+Q_var) -> 6.3914063 | W9: =SQRT(V9) -> 2.5281231 | X9: =Alpha_keep^2*X8+Q_var -> 1.2844408 | Y9: =SQRT(X9) -> 1.1333317 | AA9: Twin, both | AB9: =Every1 -> 1 | AC9: =R_sharp -> 1.5625 | AD9: =Alpha_keep^(2*AB9) -> 0.950625 | AE9: =Q_var*(1-AD9)/(1-Alpha_keep^2) -> 0.45 | AF9: =(-(AE9+AC9-AC9*AD9)+SQRT((AE9+AC9-AC9*AD9)^2+4*AD9*AC9*AE9))/(2*AD9) -> 0.62635103 | AG9: =SQRT(AF9) -> 0.79142342 | AH9: =IF(AB9=2,SQRT(Alpha_keep^2*AF9+Q_var),"") | AI9: =SQRT(AD9*AF9+AE9) -> 1.0224602 | AJ9: =(AD9*AF9+AE9)/(AD9*AF9+AE9+AC9) -> 0.40086466 | AK9: =U66 -> 0.79142342
A10: 4 | B10: =IF(AND($A10>0,MOD($A10,Every2)=0),1,0) -> 1 | C10: =Alpha_keep^2*E9+Q_var -> 1.5733346 | D10: =IF(B10=1,C10/(C10+R_s),0) -> 0.20110792 | E10: =(1-D10)*C10 -> 1.2569245 | F10: =SQRT(E10) -> 1.1211264 | G10: =IF(AND($A10>0,MOD($A10,Every1)=0),1,0) -> 1 | H10: =Alpha_keep^2*J9+Q_var -> 1.380501 | I10: =IF(G10=1,H10/(H10+R_s),0) -> 0.18091879 | J10: =(1-I10)*H10 -> 1.1307425 | K10: =SQRT(J10) -> 1.0633637 | L10: =IF(AND($A10>0,MOD($A10,Every2)=0),1,0) -> 1 | M10: =Alpha_keep^2*O9+Q_var -> 1.3856891 | N10: =IF(L10=1,M10/(M10+R_sharp),0) -> 0.47001364 | O10: =(1-N10)*M10 -> 0.73439631 | P10: =SQRT(O10) -> 0.85696926 | Q10: =IF(AND($A10>0,MOD($A10,Every1)=0),1,0) -> 1 | R10: =Alpha_keep^2*T9+Q_var -> 1.0099637 | S10: =IF(Q10=1,R10/(R10+R_sharp),0) -> 0.39260561 | T10: =(1-S10)*R10 -> 0.61344627 | U10: =SQRT(T10) -> 0.78322811 | V10: =IF(MOD($A10,Every2)=0,R_s,Alpha_keep^2*V9+Q_var) -> 6.25 | W10: =SQRT(V10) -> 2.5 | X10: =Alpha_keep^2*X9+Q_var -> 1.6710215 | Y10: =SQRT(X10) -> 1.29268 | AA10: Survey read as exact | AB10: =Every2 -> 2 | AC10: =R_s -> 6.25 | AG10: =SQRT(AC10) -> 2.5 | AI10: =SQRT(Alpha_keep^2*AC10+Q_var) -> 2.5281231
A11: 5 | B11: =IF(AND($A11>0,MOD($A11,Every2)=0),1,0) -> 0 | C11: =Alpha_keep^2*E10+Q_var -> 1.6448639 | D11: =IF(B11=1,C11/(C11+R_s),0) -> 0 | E11: =(1-D11)*C11 -> 1.6448639 | F11: =SQRT(E11) -> 1.2825225 | G11: =IF(AND($A11>0,MOD($A11,Every1)=0),1,0) -> 1 | H11: =Alpha_keep^2*J10+Q_var -> 1.524912 | I11: =IF(G11=1,H11/(H11+R_s),0) -> 0.19613238 | J11: =(1-I11)*H11 -> 1.2258274 | K11: =SQRT(J11) -> 1.1071709 | L11: =IF(AND($A11>0,MOD($A11,Every2)=0),1,0) -> 0 | M11: =Alpha_keep^2*O10+Q_var -> 1.1481355 | N11: =IF(L11=1,M11/(M11+R_sharp),0) -> 0 | O11: =(1-N11)*M11 -> 1.1481355 | P11: =SQRT(O11) -> 1.0715108 | Q11: =IF(AND($A11>0,MOD($A11,Every1)=0),1,0) -> 1 | R11: =Alpha_keep^2*T10+Q_var -> 1.0331574 | S11: =IF(Q11=1,R11/(R11+R_sharp),0) -> 0.39803303 | T11: =(1-S11)*R11 -> 0.62192661 | U11: =SQRT(T11) -> 0.78862324 | V11: =IF(MOD($A11,Every2)=0,R_s,Alpha_keep^2*V10+Q_var) -> 6.3914063 | W11: =SQRT(V11) -> 2.5281231 | X11: =Alpha_keep^2*X10+Q_var -> 2.0385148 | Y11: =SQRT(X11) -> 1.4277657 | AA11: No readings: the limit sqrt(q/(1 - a^2)) | AG11: =SQRT(Q_var/(1-Alpha_keep^2)) -> 3.0189276 | AK11: =Y66 -> 2.9456998
A12: 6 | B12: =IF(AND($A12>0,MOD($A12,Every2)=0),1,0) -> 1 | C12: =Alpha_keep^2*E11+Q_var -> 2.0136487 | D12: =IF(B12=1,C12/(C12+R_s),0) -> 0.2436755 | E12: =(1-D12)*C12 -> 1.5229719 | F12: =SQRT(E12) -> 1.2340875 | G12: =IF(AND($A12>0,MOD($A12,Every1)=0),1,0) -> 1 | H12: =Alpha_keep^2*J11+Q_var -> 1.6153022 | I12: =IF(G12=1,H12/(H12+R_s),0) -> 0.20537064 | J12: =(1-I12)*H12 -> 1.2835665 | K12: =SQRT(J12) -> 1.132946 | L12: =IF(AND($A12>0,MOD($A12,Every2)=0),1,0) -> 1 | M12: =Alpha_keep^2*O11+Q_var -> 1.5414463 | N12: =IF(L12=1,M12/(M12+R_sharp),0) -> 0.49660856 | O12: =(1-N12)*M12 -> 0.77595087 | P12: =SQRT(O12) -> 0.88088074 | Q12: =IF(AND($A12>0,MOD($A12,Every1)=0),1,0) -> 1 | R12: =Alpha_keep^2*T11+Q_var -> 1.041219 | S12: =IF(Q12=1,R12/(R12+R_sharp),0) -> 0.39989684 | T12: =(1-S12)*R12 -> 0.62483881 | U12: =SQRT(T12) -> 0.79046746 | V12: =IF(MOD($A12,Every2)=0,R_s,Alpha_keep^2*V11+Q_var) -> 6.25 | W12: =SQRT(V12) -> 2.5 | X12: =Alpha_keep^2*X11+Q_var -> 2.3878632 | Y12: =SQRT(X12) -> 1.5452712 | AA12: Theorem 15.1(iii): the variance just after a survey solves P = r psi(P)/(psi(P) + r), psi(P) = a^(2k) P + c_k, a quadratic with one positive root; the recursion reaches it from any start.
A13: 7 | B13: =IF(AND($A13>0,MOD($A13,Every2)=0),1,0) -> 0 | C13: =Alpha_keep^2*E12+Q_var -> 1.8977751 | D13: =IF(B13=1,C13/(C13+R_s),0) -> 0 | E13: =(1-D13)*C13 -> 1.8977751 | F13: =SQRT(E13) -> 1.3775976 | G13: =IF(AND($A13>0,MOD($A13,Every1)=0),1,0) -> 1 | H13: =Alpha_keep^2*J12+Q_var -> 1.6701904 | I13: =IF(G13=1,H13/(H13+R_s),0) -> 0.21087756 | J13: =(1-I13)*H13 -> 1.3179847 | K13: =SQRT(J13) -> 1.1480352 | L13: =IF(AND($A13>0,MOD($A13,Every2)=0),1,0) -> 0 | M13: =Alpha_keep^2*O12+Q_var -> 1.1876383 | N13: =IF(L13=1,M13/(M13+R_sharp),0) -> 0 | O13: =(1-N13)*M13 -> 1.1876383 | P13: =SQRT(O13) -> 1.0897882 | Q13: =IF(AND($A13>0,MOD($A13,Every1)=0),1,0) -> 1 | R13: =Alpha_keep^2*T12+Q_var -> 1.0439874 | S13: =IF(Q13=1,R13/(R13+R_sharp),0) -> 0.40053422 | T13: =(1-S13)*R13 -> 0.62583472 | U13: =SQRT(T13) -> 0.79109716 | V13: =IF(MOD($A13,Every2)=0,R_s,Alpha_keep^2*V12+Q_var) -> 6.3914063 | W13: =SQRT(V13) -> 2.5281231 | X13: =Alpha_keep^2*X12+Q_var -> 2.7199624 | Y13: =SQRT(X13) -> 1.6492309
A14: 8 | B14: =IF(AND($A14>0,MOD($A14,Every2)=0),1,0) -> 1 | C14: =Alpha_keep^2*E13+Q_var -> 2.2540725 | D14: =IF(B14=1,C14/(C14+R_s),0) -> 0.265058 | E14: =(1-D14)*C14 -> 1.6566125 | F14: =SQRT(E14) -> 1.2870946 | G14: =IF(AND($A14>0,MOD($A14,Every1)=0),1,0) -> 1 | H14: =Alpha_keep^2*J13+Q_var -> 1.7029093 | I14: =IF(G14=1,H14/(H14+R_s),0) -> 0.21412406 | J14: =(1-I14)*H14 -> 1.3382754 | K14: =SQRT(J14) -> 1.1568385 | L14: =IF(AND($A14>0,MOD($A14,Every2)=0),1,0) -> 1 | M14: =Alpha_keep^2*O13+Q_var -> 1.5789987 | N14: =IF(L14=1,M14/(M14+R_sharp),0) -> 0.50262592 | O14: =(1-N14)*M14 -> 0.785353 | P14: =SQRT(O14) -> 0.88620145 | Q14: =IF(AND($A14>0,MOD($A14,Every1)=0),1,0) -> 1 | R14: =Alpha_keep^2*T13+Q_var -> 1.0449341 | S14: =IF(Q14=1,R14/(R14+R_sharp),0) -> 0.40075188 | T14: =(1-S14)*R14 -> 0.62617481 | U14: =SQRT(T14) -> 0.79131208 | V14: =IF(MOD($A14,Every2)=0,R_s,Alpha_keep^2*V13+Q_var) -> 6.25 | W14: =SQRT(V14) -> 2.5 | X14: =Alpha_keep^2*X13+Q_var -> 3.0356643 | Y14: =SQRT(X14) -> 1.7423158 | AA14: Proposition 15.1(i): precisions add (the twin, just before a survey)
A15: 9 | B15: =IF(AND($A15>0,MOD($A15,Every2)=0),1,0) -> 0 | C15: =Alpha_keep^2*E14+Q_var -> 2.0248173 | D15: =IF(B15=1,C15/(C15+R_s),0) -> 0 | E15: =(1-D15)*C15 -> 2.0248173 | F15: =SQRT(E15) -> 1.4229607 | G15: =IF(AND($A15>0,MOD($A15,Every1)=0),1,0) -> 1 | H15: =Alpha_keep^2*J14+Q_var -> 1.7221981 | I15: =IF(G15=1,H15/(H15+R_s),0) -> 0.2160255 | J15: =(1-I15)*H15 -> 1.3501594 | K15: =SQRT(J15) -> 1.1619636 | L15: =IF(AND($A15>0,MOD($A15,Every2)=0),1,0) -> 0 | M15: =Alpha_keep^2*O14+Q_var -> 1.1965762 | N15: =IF(L15=1,M15/(M15+R_sharp),0) -> 0 | O15: =(1-N15)*M15 -> 1.1965762 | P15: =SQRT(O15) -> 1.0938813 | Q15: =IF(AND($A15>0,MOD($A15,Every1)=0),1,0) -> 1 | R15: =Alpha_keep^2*T14+Q_var -> 1.0452574 | S15: =IF(Q15=1,R15/(R15+R_sharp),0) -> 0.40082617 | T15: =(1-S15)*R15 -> 0.6262909 | U15: =SQRT(T15) -> 0.79138543 | V15: =IF(MOD($A15,Every2)=0,R_s,Alpha_keep^2*V14+Q_var) -> 6.3914063 | W15: =SQRT(V15) -> 2.5281231 | X15: =Alpha_keep^2*X14+Q_var -> 3.3357784 | Y15: =SQRT(X15) -> 1.8264113 | AA15: The law's prediction: variance P- | AB15: =AI6^2 -> 2.4842216
A16: 10 | B16: =IF(AND($A16>0,MOD($A16,Every2)=0),1,0) -> 1 | C16: =Alpha_keep^2*E15+Q_var -> 2.3748419 | D16: =IF(B16=1,C16/(C16+R_s),0) -> 0.27534904 | E16: =(1-D16)*C16 -> 1.7209315 | F16: =SQRT(E16) -> 1.3118428 | G16: =IF(AND($A16>0,MOD($A16,Every1)=0),1,0) -> 1 | H16: =Alpha_keep^2*J15+Q_var -> 1.7334952 | I16: =IF(G16=1,H16/(H16+R_s),0) -> 0.21713488 | J16: =(1-I16)*H16 -> 1.357093 | K16: =SQRT(J16) -> 1.1649433 | L16: =IF(AND($A16>0,MOD($A16,Every2)=0),1,0) -> 1 | M16: =Alpha_keep^2*O15+Q_var -> 1.5874952 | N16: =IF(L16=1,M16/(M16+R_sharp),0) -> 0.50396751 | O16: =(1-N16)*M16 -> 0.78744923 | P16: =SQRT(O16) -> 0.88738336 | Q16: =IF(AND($A16>0,MOD($A16,Every1)=0),1,0) -> 1 | R16: =Alpha_keep^2*T15+Q_var -> 1.0453678 | S16: =IF(Q16=1,R16/(R16+R_sharp),0) -> 0.40085153 | T16: =(1-S16)*R16 -> 0.62633051 | U16: =SQRT(T16) -> 0.79141046 | V16: =IF(MOD($A16,Every2)=0,R_s,Alpha_keep^2*V15+Q_var) -> 6.25 | W16: =SQRT(V16) -> 2.5 | X16: =Alpha_keep^2*X15+Q_var -> 3.6210743 | Y16: =SQRT(X16) -> 1.9029121 | AA16: The survey: variance r | AB16: =R_s -> 6.25
A17: 11 | B17: =IF(AND($A17>0,MOD($A17,Every2)=0),1,0) -> 0 | C17: =Alpha_keep^2*E16+Q_var -> 2.0859605 | D17: =IF(B17=1,C17/(C17+R_s),0) -> 0 | E17: =(1-D17)*C17 -> 2.0859605 | F17: =SQRT(E17) -> 1.4442855 | G17: =IF(AND($A17>0,MOD($A17,Every1)=0),1,0) -> 1 | H17: =Alpha_keep^2*J16+Q_var -> 1.7400865 | I17: =IF(G17=1,H17/(H17+R_s),0) -> 0.21778068 | J17: =(1-I17)*H17 -> 1.3611293 | K17: =SQRT(J17) -> 1.1666745 | L17: =IF(AND($A17>0,MOD($A17,Every2)=0),1,0) -> 0 | M17: =Alpha_keep^2*O16+Q_var -> 1.1985689 | N17: =IF(L17=1,M17/(M17+R_sharp),0) -> 0 | O17: =(1-N17)*M17 -> 1.1985689 | P17: =SQRT(O17) -> 1.0947917 | Q17: =IF(AND($A17>0,MOD($A17,Every1)=0),1,0) -> 1 | R17: =Alpha_keep^2*T16+Q_var -> 1.0454054 | S17: =IF(Q17=1,R17/(R17+R_sharp),0) -> 0.40086018 | T17: =(1-S17)*R17 -> 0.62634403 | U17: =SQRT(T17) -> 0.791419 | V17: =IF(MOD($A17,Every2)=0,R_s,Alpha_keep^2*V16+Q_var) -> 6.3914063 | W17: =SQRT(V17) -> 2.5281231 | X17: =Alpha_keep^2*X16+Q_var -> 3.8922838 | Y17: =SQRT(X17) -> 1.9728872 | AA17: Combined by precisions: 1/(1/P- + 1/r) | AB17: =1/(1/AB15+1/AB16) -> 1.7776496
A18: 12 | B18: =IF(AND($A18>0,MOD($A18,Every2)=0),1,0) -> 1 | C18: =Alpha_keep^2*E17+Q_var -> 2.4329662 | D18: =IF(B18=1,C18/(C18+R_s),0) -> 0.28019989 | E18: =(1-D18)*C18 -> 1.7512493 | F18: =SQRT(E18) -> 1.3233478 | G18: =IF(AND($A18>0,MOD($A18,Every1)=0),1,0) -> 1 | H18: =Alpha_keep^2*J17+Q_var -> 1.7439235 | I18: =IF(G18=1,H18/(H18+R_s),0) -> 0.21815614 | J18: =(1-I18)*H18 -> 1.3634759 | K18: =SQRT(J18) -> 1.1676797 | L18: =IF(AND($A18>0,MOD($A18,Every2)=0),1,0) -> 1 | M18: =Alpha_keep^2*O17+Q_var -> 1.5893896 | N18: =IF(L18=1,M18/(M18+R_sharp),0) -> 0.50426563 | O18: =(1-N18)*M18 -> 0.78791504 | P18: =SQRT(O18) -> 0.88764579 | Q18: =IF(AND($A18>0,MOD($A18,Every1)=0),1,0) -> 1 | R18: =Alpha_keep^2*T17+Q_var -> 1.0454183 | S18: =IF(Q18=1,R18/(R18+R_sharp),0) -> 0.40086313 | T18: =(1-S18)*R18 -> 0.62634864 | U18: =SQRT(T18) -> 0.79142191 | V18: =IF(MOD($A18,Every2)=0,R_s,Alpha_keep^2*V17+Q_var) -> 6.25 | W18: =SQRT(V18) -> 2.5 | X18: =Alpha_keep^2*X17+Q_var -> 4.1501023 | Y18: =SQRT(X18) -> 2.03718 | AA18: The fixed point just after a survey | AB18: =AF6 -> 1.7776496
A19: 13 | B19: =IF(AND($A19>0,MOD($A19,Every2)=0),1,0) -> 0 | C19: =Alpha_keep^2*E18+Q_var -> 2.1147814 | D19: =IF(B19=1,C19/(C19+R_s),0) -> 0 | E19: =(1-D19)*C19 -> 2.1147814 | F19: =SQRT(E19) -> 1.4542288 | G19: =IF(AND($A19>0,MOD($A19,Every1)=0),1,0) -> 1 | H19: =Alpha_keep^2*J18+Q_var -> 1.7461543 | I19: =IF(G19=1,H19/(H19+R_s),0) -> 0.21837426 | J19: =(1-I19)*H19 -> 1.3648391 | K19: =SQRT(J19) -> 1.1682633 | L19: =IF(AND($A19>0,MOD($A19,Every2)=0),1,0) -> 0 | M19: =Alpha_keep^2*O18+Q_var -> 1.1990117 | N19: =IF(L19=1,M19/(M19+R_sharp),0) -> 0 | O19: =(1-N19)*M19 -> 1.1990117 | P19: =SQRT(O19) -> 1.0949939 | Q19: =IF(AND($A19>0,MOD($A19,Every1)=0),1,0) -> 1 | R19: =Alpha_keep^2*T18+Q_var -> 1.0454227 | S19: =IF(Q19=1,R19/(R19+R_sharp),0) -> 0.40086414 | T19: =(1-S19)*R19 -> 0.62635022 | U19: =SQRT(T19) -> 0.79142291 | V19: =IF(MOD($A19,Every2)=0,R_s,Alpha_keep^2*V18+Q_var) -> 6.3914063 | W19: =SQRT(V19) -> 2.5281231 | X19: =Alpha_keep^2*X18+Q_var -> 4.395191 | Y19: =SQRT(X19) -> 2.0964711 | AA19: The same (1 = yes) | AB19: =IF(ABS(AB17-AB18)<0.000000000001,1,0) -> 1
A20: 14 | B20: =IF(AND($A20>0,MOD($A20,Every2)=0),1,0) -> 1 | C20: =Alpha_keep^2*E19+Q_var -> 2.4603641 | D20: =IF(B20=1,C20/(C20+R_s),0) -> 0.28246398 | E20: =(1-D20)*C20 -> 1.7653998 | F20: =SQRT(E20) -> 1.3286835 | G20: =IF(AND($A20>0,MOD($A20,Every1)=0),1,0) -> 1 | H20: =Alpha_keep^2*J19+Q_var -> 1.7474502 | I20: =IF(G20=1,H20/(H20+R_s),0) -> 0.21850092 | J20: =(1-I20)*H20 -> 1.3656307 | K20: =SQRT(J20) -> 1.168602 | L20: =IF(AND($A20>0,MOD($A20,Every2)=0),1,0) -> 1 | M20: =Alpha_keep^2*O19+Q_var -> 1.5898105 | N20: =IF(L20=1,M20/(M20+R_sharp),0) -> 0.50433183 | O20: =(1-N20)*M20 -> 0.78801848 | P20: =SQRT(O20) -> 0.88770405 | Q20: =IF(AND($A20>0,MOD($A20,Every1)=0),1,0) -> 1 | R20: =Alpha_keep^2*T19+Q_var -> 1.0454242 | S20: =IF(Q20=1,R20/(R20+R_sharp),0) -> 0.40086448 | T20: =(1-S20)*R20 -> 0.62635075 | U20: =SQRT(T20) -> 0.79142325 | V20: =IF(MOD($A20,Every2)=0,R_s,Alpha_keep^2*V19+Q_var) -> 6.25 | W20: =SQRT(V20) -> 2.5 | X20: =Alpha_keep^2*X19+Q_var -> 4.6281784 | Y20: =SQRT(X20) -> 2.1513202
A21: 15 | B21: =IF(AND($A21>0,MOD($A21,Every2)=0),1,0) -> 0 | C21: =Alpha_keep^2*E20+Q_var -> 2.1282332 | D21: =IF(B21=1,C21/(C21+R_s),0) -> 0 | E21: =(1-D21)*C21 -> 2.1282332 | F21: =SQRT(E21) -> 1.4588465 | G21: =IF(AND($A21>0,MOD($A21,Every1)=0),1,0) -> 1 | H21: =Alpha_keep^2*J20+Q_var -> 1.7482027 | I21: =IF(G21=1,H21/(H21+R_s),0) -> 0.21857444 | J21: =(1-I21)*H21 -> 1.3660903 | K21: =SQRT(J21) -> 1.1687986 | L21: =IF(AND($A21>0,MOD($A21,Every2)=0),1,0) -> 0 | M21: =Alpha_keep^2*O20+Q_var -> 1.1991101 | N21: =IF(L21=1,M21/(M21+R_sharp),0) -> 0 | O21: =(1-N21)*M21 -> 1.1991101 | P21: =SQRT(O21) -> 1.0950388 | Q21: =IF(AND($A21>0,MOD($A21,Every1)=0),1,0) -> 1 | R21: =Alpha_keep^2*T20+Q_var -> 1.0454247 | S21: =IF(Q21=1,R21/(R21+R_sharp),0) -> 0.4008646 | T21: =(1-S21)*R21 -> 0.62635094 | U21: =SQRT(T21) -> 0.79142336 | V21: =IF(MOD($A21,Every2)=0,R_s,Alpha_keep^2*V20+Q_var) -> 6.3914063 | W21: =SQRT(V21) -> 2.5281231 | X21: =Alpha_keep^2*X20+Q_var -> 4.8496621 | Y21: =SQRT(X21) -> 2.2021948 | AA21: Proposition 15.1(ii)-(iii): what a reading is worth, and a bias that survives (try your own)
A22: 16 | B22: =IF(AND($A22>0,MOD($A22,Every2)=0),1,0) -> 1 | C22: =Alpha_keep^2*E21+Q_var -> 2.4731517 | D22: =IF(B22=1,C22/(C22+R_s),0) -> 0.28351584 | E22: =(1-D22)*C22 -> 1.771974 | F22: =SQRT(E22) -> 1.3311551 | G22: =IF(AND($A22>0,MOD($A22,Every1)=0),1,0) -> 1 | H22: =Alpha_keep^2*J21+Q_var -> 1.7486396 | I22: =IF(G22=1,H22/(H22+R_s),0) -> 0.21861712 | J22: =(1-I22)*H22 -> 1.366357 | K22: =SQRT(J22) -> 1.1689127 | L22: =IF(AND($A22>0,MOD($A22,Every2)=0),1,0) -> 1 | M22: =Alpha_keep^2*O21+Q_var -> 1.589904 | N22: =IF(L22=1,M22/(M22+R_sharp),0) -> 0.50434653 | O22: =(1-N22)*M22 -> 0.78804145 | P22: =SQRT(O22) -> 0.88771699 | Q22: =IF(AND($A22>0,MOD($A22,Every1)=0),1,0) -> 1 | R22: =Alpha_keep^2*T21+Q_var -> 1.0454249 | S22: =IF(Q22=1,R22/(R22+R_sharp),0) -> 0.40086464 | T22: =(1-S22)*R22 -> 0.626351 | U22: =SQRT(T22) -> 0.7914234 | V22: =IF(MOD($A22,Every2)=0,R_s,Alpha_keep^2*V21+Q_var) -> 6.25 | W22: =SQRT(V22) -> 2.5 | X22: =Alpha_keep^2*X21+Q_var -> 5.06021 | Y22: =SQRT(X22) -> 2.2494911 | AA22: Variance before a reading, P | AB22: 4
A23: 17 | B23: =IF(AND($A23>0,MOD($A23,Every2)=0),1,0) -> 0 | C23: =Alpha_keep^2*E22+Q_var -> 2.1344828 | D23: =IF(B23=1,C23/(C23+R_s),0) -> 0 | E23: =(1-D23)*C23 -> 2.1344828 | F23: =SQRT(E23) -> 1.4609869 | G23: =IF(AND($A23>0,MOD($A23,Every1)=0),1,0) -> 1 | H23: =Alpha_keep^2*J22+Q_var -> 1.7488931 | I23: =IF(G23=1,H23/(H23+R_s),0) -> 0.21864189 | J23: =(1-I23)*H23 -> 1.3665118 | K23: =SQRT(J23) -> 1.168979 | L23: =IF(AND($A23>0,MOD($A23,Every2)=0),1,0) -> 0 | M23: =Alpha_keep^2*O22+Q_var -> 1.1991319 | N23: =IF(L23=1,M23/(M23+R_sharp),0) -> 0 | O23: =(1-N23)*M23 -> 1.1991319 | P23: =SQRT(O23) -> 1.0950488 | Q23: =IF(AND($A23>0,MOD($A23,Every1)=0),1,0) -> 1 | R23: =Alpha_keep^2*T22+Q_var -> 1.0454249 | S23: =IF(Q23=1,R23/(R23+R_sharp),0) -> 0.40086465 | T23: =(1-S23)*R23 -> 0.62635102 | U23: =SQRT(T23) -> 0.79142341 | V23: =IF(MOD($A23,Every2)=0,R_s,Alpha_keep^2*V22+Q_var) -> 6.3914063 | W23: =SQRT(V23) -> 2.5281231 | X23: =Alpha_keep^2*X22+Q_var -> 5.2603622 | Y23: =SQRT(X23) -> 2.2935479 | AA23: The reading's variance | AB23: =R_s -> 6.25
A24: 18 | B24: =IF(AND($A24>0,MOD($A24,Every2)=0),1,0) -> 1 | C24: =Alpha_keep^2*E23+Q_var -> 2.4790927 | D24: =IF(B24=1,C24/(C24+R_s),0) -> 0.28400348 | E24: =(1-D24)*C24 -> 1.7750218 | F24: =SQRT(E24) -> 1.3322994 | G24: =IF(AND($A24>0,MOD($A24,Every1)=0),1,0) -> 1 | H24: =Alpha_keep^2*J23+Q_var -> 1.7490403 | I24: =IF(G24=1,H24/(H24+R_s),0) -> 0.21865627 | J24: =(1-I24)*H24 -> 1.3666017 | K24: =SQRT(J24) -> 1.1690174 | L24: =IF(AND($A24>0,MOD($A24,Every2)=0),1,0) -> 1 | M24: =Alpha_keep^2*O23+Q_var -> 1.5899248 | N24: =IF(L24=1,M24/(M24+R_sharp),0) -> 0.50434979 | O24: =(1-N24)*M24 -> 0.78804654 | P24: =SQRT(O24) -> 0.88771986 | Q24: =IF(AND($A24>0,MOD($A24,Every1)=0),1,0) -> 1 | R24: =Alpha_keep^2*T23+Q_var -> 1.0454249 | S24: =IF(Q24=1,R24/(R24+R_sharp),0) -> 0.40086466 | T24: =(1-S24)*R24 -> 0.62635103 | U24: =SQRT(T24) -> 0.79142342 | V24: =IF(MOD($A24,Every2)=0,R_s,Alpha_keep^2*V23+Q_var) -> 6.25 | W24: =SQRT(V24) -> 2.5 | X24: =Alpha_keep^2*X23+Q_var -> 5.4506318 | Y24: =SQRT(X24) -> 2.3346588 | AA24: Variance after, P r/(P + r) | AB24: =AB22*AB23/(AB22+AB23) -> 2.4390244
A25: 19 | B25: =IF(AND($A25>0,MOD($A25,Every2)=0),1,0) -> 0 | C25: =Alpha_keep^2*E24+Q_var -> 2.1373801 | D25: =IF(B25=1,C25/(C25+R_s),0) -> 0 | E25: =(1-D25)*C25 -> 2.1373801 | F25: =SQRT(E25) -> 1.4619781 | G25: =IF(AND($A25>0,MOD($A25,Every1)=0),1,0) -> 1 | H25: =Alpha_keep^2*J24+Q_var -> 1.7491257 | I25: =IF(G25=1,H25/(H25+R_s),0) -> 0.21866461 | J25: =(1-I25)*H25 -> 1.3666538 | K25: =SQRT(J25) -> 1.1690397 | L25: =IF(AND($A25>0,MOD($A25,Every2)=0),1,0) -> 0 | M25: =Alpha_keep^2*O24+Q_var -> 1.1991367 | N25: =IF(L25=1,M25/(M25+R_sharp),0) -> 0 | O25: =(1-N25)*M25 -> 1.1991367 | P25: =SQRT(O25) -> 1.095051 | Q25: =IF(AND($A25>0,MOD($A25,Every1)=0),1,0) -> 1 | R25: =Alpha_keep^2*T24+Q_var -> 1.0454249 | S25: =IF(Q25=1,R25/(R25+R_sharp),0) -> 0.40086466 | T25: =(1-S25)*R25 -> 0.62635103 | U25: =SQRT(T25) -> 0.79142342 | V25: =IF(MOD($A25,Every2)=0,R_s,Alpha_keep^2*V24+Q_var) -> 6.3914063 | W25: =SQRT(V25) -> 2.5281231 | X25: =Alpha_keep^2*X24+Q_var -> 5.6315068 | Y25: =SQRT(X25) -> 2.3730796 | AA25: Share of P the reading removes, P/(P + r) | AB25: =AB22/(AB22+AB23) -> 0.3902439 | AC25: Large when the twin knows little
A26: 20 | B26: =IF(AND($A26>0,MOD($A26,Every2)=0),1,0) -> 1 | C26: =Alpha_keep^2*E25+Q_var -> 2.4818469 | D26: =IF(B26=1,C26/(C26+R_s),0) -> 0.28422932 | E26: =(1-D26)*C26 -> 1.7764333 | F26: =SQRT(E26) -> 1.332829 | G26: =IF(AND($A26>0,MOD($A26,Every1)=0),1,0) -> 1 | H26: =Alpha_keep^2*J25+Q_var -> 1.7491753 | I26: =IF(G26=1,H26/(H26+R_s),0) -> 0.21866945 | J26: =(1-I26)*H26 -> 1.3666841 | K26: =SQRT(J26) -> 1.1690526 | L26: =IF(AND($A26>0,MOD($A26,Every2)=0),1,0) -> 1 | M26: =Alpha_keep^2*O25+Q_var -> 1.5899294 | N26: =IF(L26=1,M26/(M26+R_sharp),0) -> 0.50435051 | O26: =(1-N26)*M26 -> 0.78804768 | P26: =SQRT(O26) -> 0.88772049 | Q26: =IF(AND($A26>0,MOD($A26,Every1)=0),1,0) -> 1 | R26: =Alpha_keep^2*T25+Q_var -> 1.0454249 | S26: =IF(Q26=1,R26/(R26+R_sharp),0) -> 0.40086466 | T26: =(1-S26)*R26 -> 0.62635103 | U26: =SQRT(T26) -> 0.79142342 | V26: =IF(MOD($A26,Every2)=0,R_s,Alpha_keep^2*V25+Q_var) -> 6.25 | W26: =SQRT(V26) -> 2.5 | X26: =Alpha_keep^2*X25+Q_var -> 5.8034512 | Y26: =SQRT(X26) -> 2.4090353 | AA26: A survey biased by beta0 (points) | AB26: 1 | AC26: Illustration
A27: 21 | B27: =IF(AND($A27>0,MOD($A27,Every2)=0),1,0) -> 0 | C27: =Alpha_keep^2*E26+Q_var -> 2.1387219 | D27: =IF(B27=1,C27/(C27+R_s),0) -> 0 | E27: =(1-D27)*C27 -> 2.1387219 | F27: =SQRT(E27) -> 1.462437 | G27: =IF(AND($A27>0,MOD($A27,Every1)=0),1,0) -> 1 | H27: =Alpha_keep^2*J26+Q_var -> 1.7492041 | I27: =IF(G27=1,H27/(H27+R_s),0) -> 0.21867226 | J27: =(1-I27)*H27 -> 1.3667016 | K27: =SQRT(J27) -> 1.1690602 | L27: =IF(AND($A27>0,MOD($A27,Every2)=0),1,0) -> 0 | M27: =Alpha_keep^2*O26+Q_var -> 1.1991378 | N27: =IF(L27=1,M27/(M27+R_sharp),0) -> 0 | O27: =(1-N27)*M27 -> 1.1991378 | P27: =SQRT(O27) -> 1.0950515 | Q27: =IF(AND($A27>0,MOD($A27,Every1)=0),1,0) -> 1 | R27: =Alpha_keep^2*T26+Q_var -> 1.0454249 | S27: =IF(Q27=1,R27/(R27+R_sharp),0) -> 0.40086466 | T27: =(1-S27)*R27 -> 0.62635103 | U27: =SQRT(T27) -> 0.79142342 | V27: =IF(MOD($A27,Every2)=0,R_s,Alpha_keep^2*V26+Q_var) -> 6.3914063 | W27: =SQRT(V27) -> 2.5281231 | X27: =Alpha_keep^2*X26+Q_var -> 5.9669058 | Y27: =SQRT(X27) -> 2.4427251 | AA27: The twin's mean error just after a survey, K beta0/(1 - (1 - K) a^k), k = 2 | AB27: =AJ6*AB26/(1-(1-AJ6)*Alpha_keep^AB6) -> 0.88950442 | AC27: Online Appendix 15.B, Proposition 15.1(iii)
A28: 22 | B28: =IF(AND($A28>0,MOD($A28,Every2)=0),1,0) -> 1 | C28: =Alpha_keep^2*E27+Q_var -> 2.4831225 | D28: =IF(B28=1,C28/(C28+R_s),0) -> 0.28433387 | E28: =(1-D28)*C28 -> 1.7770867 | F28: =SQRT(E28) -> 1.3330741 | G28: =IF(AND($A28>0,MOD($A28,Every1)=0),1,0) -> 1 | H28: =Alpha_keep^2*J27+Q_var -> 1.7492208 | I28: =IF(G28=1,H28/(H28+R_s),0) -> 0.21867389 | J28: =(1-I28)*H28 -> 1.3667118 | K28: =SQRT(J28) -> 1.1690645 | L28: =IF(AND($A28>0,MOD($A28,Every2)=0),1,0) -> 1 | M28: =Alpha_keep^2*O27+Q_var -> 1.5899304 | N28: =IF(L28=1,M28/(M28+R_sharp),0) -> 0.50435067 | O28: =(1-N28)*M28 -> 0.78804793 | P28: =SQRT(O28) -> 0.88772064 | Q28: =IF(AND($A28>0,MOD($A28,Every1)=0),1,0) -> 1 | R28: =Alpha_keep^2*T27+Q_var -> 1.0454249 | S28: =IF(Q28=1,R28/(R28+R_sharp),0) -> 0.40086466 | T28: =(1-S28)*R28 -> 0.62635103 | U28: =SQRT(T28) -> 0.79142342 | V28: =IF(MOD($A28,Every2)=0,R_s,Alpha_keep^2*V27+Q_var) -> 6.25 | W28: =SQRT(V28) -> 2.5 | X28: =Alpha_keep^2*X27+Q_var -> 6.1222898 | Y28: =SQRT(X28) -> 2.4743261 | AA28: The innovations' mean, beta0 (1 - a^k)/(1 - (1 - K) a^k) | AB28: =AB26*(1-Alpha_keep^AB6)/(1-(1-AJ6)*Alpha_keep^AB6) -> 0.15441486 | AC28: Only part of the bias shows
A29: 23 | B29: =IF(AND($A29>0,MOD($A29,Every2)=0),1,0) -> 0 | C29: =Alpha_keep^2*E28+Q_var -> 2.139343 | D29: =IF(B29=1,C29/(C29+R_s),0) -> 0 | E29: =(1-D29)*C29 -> 2.139343 | F29: =SQRT(E29) -> 1.4626493 | G29: =IF(AND($A29>0,MOD($A29,Every1)=0),1,0) -> 1 | H29: =Alpha_keep^2*J28+Q_var -> 1.7492304 | I29: =IF(G29=1,H29/(H29+R_s),0) -> 0.21867484 | J29: =(1-I29)*H29 -> 1.3667178 | K29: =SQRT(J29) -> 1.169067 | L29: =IF(AND($A29>0,MOD($A29,Every2)=0),1,0) -> 0 | M29: =Alpha_keep^2*O28+Q_var -> 1.1991381 | N29: =IF(L29=1,M29/(M29+R_sharp),0) -> 0 | O29: =(1-N29)*M29 -> 1.1991381 | P29: =SQRT(O29) -> 1.0950516 | Q29: =IF(AND($A29>0,MOD($A29,Every1)=0),1,0) -> 1 | R29: =Alpha_keep^2*T28+Q_var -> 1.0454249 | S29: =IF(Q29=1,R29/(R29+R_sharp),0) -> 0.40086466 | T29: =(1-S29)*R29 -> 0.62635103 | U29: =SQRT(T29) -> 0.79142342 | V29: =IF(MOD($A29,Every2)=0,R_s,Alpha_keep^2*V28+Q_var) -> 6.3914063 | W29: =SQRT(V29) -> 2.5281231 | X29: =Alpha_keep^2*X28+Q_var -> 6.2700017 | Y29: =SQRT(X29) -> 2.5039972 | AA29: as a share of the bias | AB29: =AB28/AB26 -> 0.15441486 | AC29: An audit, an independent reading, finds the rest
A30: 24 | B30: =IF(AND($A30>0,MOD($A30,Every2)=0),1,0) -> 1 | C30: =Alpha_keep^2*E29+Q_var -> 2.4837129 | D30: =IF(B30=1,C30/(C30+R_s),0) -> 0.28438225 | E30: =(1-D30)*C30 -> 1.7773891 | F30: =SQRT(E30) -> 1.3331876 | G30: =IF(AND($A30>0,MOD($A30,Every1)=0),1,0) -> 1 | H30: =Alpha_keep^2*J29+Q_var -> 1.7492361 | I30: =IF(G30=1,H30/(H30+R_s),0) -> 0.21867539 | J30: =(1-I30)*H30 -> 1.3667212 | K30: =SQRT(J30) -> 1.1690685 | L30: =IF(AND($A30>0,MOD($A30,Every2)=0),1,0) -> 1 | M30: =Alpha_keep^2*O29+Q_var -> 1.5899306 | N30: =IF(L30=1,M30/(M30+R_sharp),0) -> 0.50435071 | O30: =(1-N30)*M30 -> 0.78804798 | P30: =SQRT(O30) -> 0.88772067 | Q30: =IF(AND($A30>0,MOD($A30,Every1)=0),1,0) -> 1 | R30: =Alpha_keep^2*T29+Q_var -> 1.0454249 | S30: =IF(Q30=1,R30/(R30+R_sharp),0) -> 0.40086466 | T30: =(1-S30)*R30 -> 0.62635103 | U30: =SQRT(T30) -> 0.79142342 | V30: =IF(MOD($A30,Every2)=0,R_s,Alpha_keep^2*V29+Q_var) -> 6.25 | W30: =SQRT(V30) -> 2.5 | X30: =Alpha_keep^2*X29+Q_var -> 6.4104204 | Y30: =SQRT(X30) -> 2.5318808
A31: 25 | B31: =IF(AND($A31>0,MOD($A31,Every2)=0),1,0) -> 0 | C31: =Alpha_keep^2*E30+Q_var -> 2.1396305 | D31: =IF(B31=1,C31/(C31+R_s),0) -> 0 | E31: =(1-D31)*C31 -> 2.1396305 | F31: =SQRT(E31) -> 1.4627476 | G31: =IF(AND($A31>0,MOD($A31,Every1)=0),1,0) -> 1 | H31: =Alpha_keep^2*J30+Q_var -> 1.7492393 | I31: =IF(G31=1,H31/(H31+R_s),0) -> 0.21867571 | J31: =(1-I31)*H31 -> 1.3667232 | K31: =SQRT(J31) -> 1.1690694 | L31: =IF(AND($A31>0,MOD($A31,Every2)=0),1,0) -> 0 | M31: =Alpha_keep^2*O30+Q_var -> 1.1991381 | N31: =IF(L31=1,M31/(M31+R_sharp),0) -> 0 | O31: =(1-N31)*M31 -> 1.1991381 | P31: =SQRT(O31) -> 1.0950516 | Q31: =IF(AND($A31>0,MOD($A31,Every1)=0),1,0) -> 1 | R31: =Alpha_keep^2*T30+Q_var -> 1.0454249 | S31: =IF(Q31=1,R31/(R31+R_sharp),0) -> 0.40086466 | T31: =(1-S31)*R31 -> 0.62635103 | U31: =SQRT(T31) -> 0.79142342 | V31: =IF(MOD($A31,Every2)=0,R_s,Alpha_keep^2*V30+Q_var) -> 6.3914063 | W31: =SQRT(V31) -> 2.5281231 | X31: =Alpha_keep^2*X30+Q_var -> 6.5439059 | Y31: =SQRT(X31) -> 2.5581059
A32: 26 | B32: =IF(AND($A32>0,MOD($A32,Every2)=0),1,0) -> 1 | C32: =Alpha_keep^2*E31+Q_var -> 2.4839862 | D32: =IF(B32=1,C32/(C32+R_s),0) -> 0.28440464 | E32: =(1-D32)*C32 -> 1.777529 | F32: =SQRT(E32) -> 1.33324 | G32: =IF(AND($A32>0,MOD($A32,Every1)=0),1,0) -> 1 | H32: =Alpha_keep^2*J31+Q_var -> 1.7492412 | I32: =IF(G32=1,H32/(H32+R_s),0) -> 0.21867589 | J32: =(1-I32)*H32 -> 1.3667243 | K32: =SQRT(J32) -> 1.1690699 | L32: =IF(AND($A32>0,MOD($A32,Every2)=0),1,0) -> 1 | M32: =Alpha_keep^2*O31+Q_var -> 1.5899307 | N32: =IF(L32=1,M32/(M32+R_sharp),0) -> 0.50435072 | O32: =(1-N32)*M32 -> 0.788048 | P32: =SQRT(O32) -> 0.88772067 | Q32: =IF(AND($A32>0,MOD($A32,Every1)=0),1,0) -> 1 | R32: =Alpha_keep^2*T31+Q_var -> 1.0454249 | S32: =IF(Q32=1,R32/(R32+R_sharp),0) -> 0.40086466 | T32: =(1-S32)*R32 -> 0.62635103 | U32: =SQRT(T32) -> 0.79142342 | V32: =IF(MOD($A32,Every2)=0,R_s,Alpha_keep^2*V31+Q_var) -> 6.25 | W32: =SQRT(V32) -> 2.5 | X32: =Alpha_keep^2*X31+Q_var -> 6.6708005 | Y32: =SQRT(X32) -> 2.5827893
A33: 27 | B33: =IF(AND($A33>0,MOD($A33,Every2)=0),1,0) -> 0 | C33: =Alpha_keep^2*E32+Q_var -> 2.1397635 | D33: =IF(B33=1,C33/(C33+R_s),0) -> 0 | E33: =(1-D33)*C33 -> 2.1397635 | F33: =SQRT(E33) -> 1.4627931 | G33: =IF(AND($A33>0,MOD($A33,Every1)=0),1,0) -> 1 | H33: =Alpha_keep^2*J32+Q_var -> 1.7492423 | I33: =IF(G33=1,H33/(H33+R_s),0) -> 0.218676 | J33: =(1-I33)*H33 -> 1.366725 | K33: =SQRT(J33) -> 1.1690701 | L33: =IF(AND($A33>0,MOD($A33,Every2)=0),1,0) -> 0 | M33: =Alpha_keep^2*O32+Q_var -> 1.1991381 | N33: =IF(L33=1,M33/(M33+R_sharp),0) -> 0 | O33: =(1-N33)*M33 -> 1.1991381 | P33: =SQRT(O33) -> 1.0950517 | Q33: =IF(AND($A33>0,MOD($A33,Every1)=0),1,0) -> 1 | R33: =Alpha_keep^2*T32+Q_var -> 1.045425 | S33: =IF(Q33=1,R33/(R33+R_sharp),0) -> 0.40086466 | T33: =(1-S33)*R33 -> 0.62635103 | U33: =SQRT(T33) -> 0.79142342 | V33: =IF(MOD($A33,Every2)=0,R_s,Alpha_keep^2*V32+Q_var) -> 6.3914063 | W33: =SQRT(V33) -> 2.5281231 | X33: =Alpha_keep^2*X32+Q_var -> 6.7914298 | Y33: =SQRT(X33) -> 2.6060372
A34: 28 | B34: =IF(AND($A34>0,MOD($A34,Every2)=0),1,0) -> 1 | C34: =Alpha_keep^2*E33+Q_var -> 2.4841127 | D34: =IF(B34=1,C34/(C34+R_s),0) -> 0.284415 | E34: =(1-D34)*C34 -> 1.7775938 | F34: =SQRT(E34) -> 1.3332643 | G34: =IF(AND($A34>0,MOD($A34,Every1)=0),1,0) -> 1 | H34: =Alpha_keep^2*J33+Q_var -> 1.749243 | I34: =IF(G34=1,H34/(H34+R_s),0) -> 0.21867606 | J34: =(1-I34)*H34 -> 1.3667254 | K34: =SQRT(J34) -> 1.1690703 | L34: =IF(AND($A34>0,MOD($A34,Every2)=0),1,0) -> 1 | M34: =Alpha_keep^2*O33+Q_var -> 1.5899307 | N34: =IF(L34=1,M34/(M34+R_sharp),0) -> 0.50435072 | O34: =(1-N34)*M34 -> 0.788048 | P34: =SQRT(O34) -> 0.88772068 | Q34: =IF(AND($A34>0,MOD($A34,Every1)=0),1,0) -> 1 | R34: =Alpha_keep^2*T33+Q_var -> 1.045425 | S34: =IF(Q34=1,R34/(R34+R_sharp),0) -> 0.40086466 | T34: =(1-S34)*R34 -> 0.62635103 | U34: =SQRT(T34) -> 0.79142342 | V34: =IF(MOD($A34,Every2)=0,R_s,Alpha_keep^2*V33+Q_var) -> 6.25 | W34: =SQRT(V34) -> 2.5 | X34: =Alpha_keep^2*X33+Q_var -> 6.9061029 | Y34: =SQRT(X34) -> 2.6279465
A35: 29 | B35: =IF(AND($A35>0,MOD($A35,Every2)=0),1,0) -> 0 | C35: =Alpha_keep^2*E34+Q_var -> 2.1398251 | D35: =IF(B35=1,C35/(C35+R_s),0) -> 0 | E35: =(1-D35)*C35 -> 2.1398251 | F35: =SQRT(E35) -> 1.4628141 | G35: =IF(AND($A35>0,MOD($A35,Every1)=0),1,0) -> 1 | H35: =Alpha_keep^2*J34+Q_var -> 1.7492433 | I35: =IF(G35=1,H35/(H35+R_s),0) -> 0.2186761 | J35: =(1-I35)*H35 -> 1.3667256 | K35: =SQRT(J35) -> 1.1690704 | L35: =IF(AND($A35>0,MOD($A35,Every2)=0),1,0) -> 0 | M35: =Alpha_keep^2*O34+Q_var -> 1.1991381 | N35: =IF(L35=1,M35/(M35+R_sharp),0) -> 0 | O35: =(1-N35)*M35 -> 1.1991381 | P35: =SQRT(O35) -> 1.0950517 | Q35: =IF(AND($A35>0,MOD($A35,Every1)=0),1,0) -> 1 | R35: =Alpha_keep^2*T34+Q_var -> 1.045425 | S35: =IF(Q35=1,R35/(R35+R_sharp),0) -> 0.40086466 | T35: =(1-S35)*R35 -> 0.62635103 | U35: =SQRT(T35) -> 0.79142342 | V35: =IF(MOD($A35,Every2)=0,R_s,Alpha_keep^2*V34+Q_var) -> 6.3914063 | W35: =SQRT(V35) -> 2.5281231 | X35: =Alpha_keep^2*X34+Q_var -> 7.0151141 | Y35: =SQRT(X35) -> 2.6486061
A36: 30 | B36: =IF(AND($A36>0,MOD($A36,Every2)=0),1,0) -> 1 | C36: =Alpha_keep^2*E35+Q_var -> 2.4841712 | D36: =IF(B36=1,C36/(C36+R_s),0) -> 0.2844198 | E36: =(1-D36)*C36 -> 1.7776237 | F36: =SQRT(E36) -> 1.3332756 | G36: =IF(AND($A36>0,MOD($A36,Every1)=0),1,0) -> 1 | H36: =Alpha_keep^2*J35+Q_var -> 1.7492435 | I36: =IF(G36=1,H36/(H36+R_s),0) -> 0.21867612 | J36: =(1-I36)*H36 -> 1.3667258 | K36: =SQRT(J36) -> 1.1690705 | L36: =IF(AND($A36>0,MOD($A36,Every2)=0),1,0) -> 1 | M36: =Alpha_keep^2*O35+Q_var -> 1.5899307 | N36: =IF(L36=1,M36/(M36+R_sharp),0) -> 0.50435072 | O36: =(1-N36)*M36 -> 0.788048 | P36: =SQRT(O36) -> 0.88772068 | Q36: =IF(AND($A36>0,MOD($A36,Every1)=0),1,0) -> 1 | R36: =Alpha_keep^2*T35+Q_var -> 1.045425 | S36: =IF(Q36=1,R36/(R36+R_sharp),0) -> 0.40086466 | T36: =(1-S36)*R36 -> 0.62635103 | U36: =SQRT(T36) -> 0.79142342 | V36: =IF(MOD($A36,Every2)=0,R_s,Alpha_keep^2*V35+Q_var) -> 6.25 | W36: =SQRT(V36) -> 2.5 | X36: =Alpha_keep^2*X35+Q_var -> 7.1187428 | Y36: =SQRT(X36) -> 2.6680972
A37: 31 | B37: =IF(AND($A37>0,MOD($A37,Every2)=0),1,0) -> 0 | C37: =Alpha_keep^2*E36+Q_var -> 2.1398536 | D37: =IF(B37=1,C37/(C37+R_s),0) -> 0 | E37: =(1-D37)*C37 -> 2.1398536 | F37: =SQRT(E37) -> 1.4628238 | G37: =IF(AND($A37>0,MOD($A37,Every1)=0),1,0) -> 1 | H37: =Alpha_keep^2*J36+Q_var -> 1.7492437 | I37: =IF(G37=1,H37/(H37+R_s),0) -> 0.21867613 | J37: =(1-I37)*H37 -> 1.3667258 | K37: =SQRT(J37) -> 1.1690705 | L37: =IF(AND($A37>0,MOD($A37,Every2)=0),1,0) -> 0 | M37: =Alpha_keep^2*O36+Q_var -> 1.1991381 | N37: =IF(L37=1,M37/(M37+R_sharp),0) -> 0 | O37: =(1-N37)*M37 -> 1.1991381 | P37: =SQRT(O37) -> 1.0950517 | Q37: =IF(AND($A37>0,MOD($A37,Every1)=0),1,0) -> 1 | R37: =Alpha_keep^2*T36+Q_var -> 1.045425 | S37: =IF(Q37=1,R37/(R37+R_sharp),0) -> 0.40086466 | T37: =(1-S37)*R37 -> 0.62635103 | U37: =SQRT(T37) -> 0.79142342 | V37: =IF(MOD($A37,Every2)=0,R_s,Alpha_keep^2*V36+Q_var) -> 6.3914063 | W37: =SQRT(V37) -> 2.5281231 | X37: =Alpha_keep^2*X36+Q_var -> 7.2172549 | Y37: =SQRT(X37) -> 2.6864949
A38: 32 | B38: =IF(AND($A38>0,MOD($A38,Every2)=0),1,0) -> 1 | C38: =Alpha_keep^2*E37+Q_var -> 2.4841983 | D38: =IF(B38=1,C38/(C38+R_s),0) -> 0.28442202 | E38: =(1-D38)*C38 -> 1.7776376 | F38: =SQRT(E38) -> 1.3332808 | G38: =IF(AND($A38>0,MOD($A38,Every1)=0),1,0) -> 1 | H38: =Alpha_keep^2*J37+Q_var -> 1.7492437 | I38: =IF(G38=1,H38/(H38+R_s),0) -> 0.21867614 | J38: =(1-I38)*H38 -> 1.3667259 | K38: =SQRT(J38) -> 1.1690705 | L38: =IF(AND($A38>0,MOD($A38,Every2)=0),1,0) -> 1 | M38: =Alpha_keep^2*O37+Q_var -> 1.5899307 | N38: =IF(L38=1,M38/(M38+R_sharp),0) -> 0.50435072 | O38: =(1-N38)*M38 -> 0.788048 | P38: =SQRT(O38) -> 0.88772068 | Q38: =IF(AND($A38>0,MOD($A38,Every1)=0),1,0) -> 1 | R38: =Alpha_keep^2*T37+Q_var -> 1.045425 | S38: =IF(Q38=1,R38/(R38+R_sharp),0) -> 0.40086466 | T38: =(1-S38)*R38 -> 0.62635103 | U38: =SQRT(T38) -> 0.79142342 | V38: =IF(MOD($A38,Every2)=0,R_s,Alpha_keep^2*V37+Q_var) -> 6.25 | W38: =SQRT(V38) -> 2.5 | X38: =Alpha_keep^2*X37+Q_var -> 7.3109029 | Y38: =SQRT(X38) -> 2.7038681
A39: 33 | B39: =IF(AND($A39>0,MOD($A39,Every2)=0),1,0) -> 0 | C39: =Alpha_keep^2*E38+Q_var -> 2.1398668 | D39: =IF(B39=1,C39/(C39+R_s),0) -> 0 | E39: =(1-D39)*C39 -> 2.1398668 | F39: =SQRT(E39) -> 1.4628283 | G39: =IF(AND($A39>0,MOD($A39,Every1)=0),1,0) -> 1 | H39: =Alpha_keep^2*J38+Q_var -> 1.7492438 | I39: =IF(G39=1,H39/(H39+R_s),0) -> 0.21867614 | J39: =(1-I39)*H39 -> 1.3667259 | K39: =SQRT(J39) -> 1.1690705 | L39: =IF(AND($A39>0,MOD($A39,Every2)=0),1,0) -> 0 | M39: =Alpha_keep^2*O38+Q_var -> 1.1991381 | N39: =IF(L39=1,M39/(M39+R_sharp),0) -> 0 | O39: =(1-N39)*M39 -> 1.1991381 | P39: =SQRT(O39) -> 1.0950517 | Q39: =IF(AND($A39>0,MOD($A39,Every1)=0),1,0) -> 1 | R39: =Alpha_keep^2*T38+Q_var -> 1.045425 | S39: =IF(Q39=1,R39/(R39+R_sharp),0) -> 0.40086466 | T39: =(1-S39)*R39 -> 0.62635103 | U39: =SQRT(T39) -> 0.79142342 | V39: =IF(MOD($A39,Every2)=0,R_s,Alpha_keep^2*V38+Q_var) -> 6.3914063 | W39: =SQRT(V39) -> 2.5281231 | X39: =Alpha_keep^2*X38+Q_var -> 7.3999271 | Y39: =SQRT(X39) -> 2.7202807
A40: 34 | B40: =IF(AND($A40>0,MOD($A40,Every2)=0),1,0) -> 1 | C40: =Alpha_keep^2*E39+Q_var -> 2.4842108 | D40: =IF(B40=1,C40/(C40+R_s),0) -> 0.28442304 | E40: =(1-D40)*C40 -> 1.777644 | F40: =SQRT(E40) -> 1.3332832 | G40: =IF(AND($A40>0,MOD($A40,Every1)=0),1,0) -> 1 | H40: =Alpha_keep^2*J39+Q_var -> 1.7492438 | I40: =IF(G40=1,H40/(H40+R_s),0) -> 0.21867615 | J40: =(1-I40)*H40 -> 1.3667259 | K40: =SQRT(J40) -> 1.1690705 | L40: =IF(AND($A40>0,MOD($A40,Every2)=0),1,0) -> 1 | M40: =Alpha_keep^2*O39+Q_var -> 1.5899307 | N40: =IF(L40=1,M40/(M40+R_sharp),0) -> 0.50435072 | O40: =(1-N40)*M40 -> 0.788048 | P40: =SQRT(O40) -> 0.88772068 | Q40: =IF(AND($A40>0,MOD($A40,Every1)=0),1,0) -> 1 | R40: =Alpha_keep^2*T39+Q_var -> 1.045425 | S40: =IF(Q40=1,R40/(R40+R_sharp),0) -> 0.40086466 | T40: =(1-S40)*R40 -> 0.62635103 | U40: =SQRT(T40) -> 0.79142342 | V40: =IF(MOD($A40,Every2)=0,R_s,Alpha_keep^2*V39+Q_var) -> 6.25 | W40: =SQRT(V40) -> 2.5 | X40: =Alpha_keep^2*X39+Q_var -> 7.4845557 | Y40: =SQRT(X40) -> 2.7357916
A41: 35 | B41: =IF(AND($A41>0,MOD($A41,Every2)=0),1,0) -> 0 | C41: =Alpha_keep^2*E40+Q_var -> 2.1398729 | D41: =IF(B41=1,C41/(C41+R_s),0) -> 0 | E41: =(1-D41)*C41 -> 2.1398729 | F41: =SQRT(E41) -> 1.4628304 | G41: =IF(AND($A41>0,MOD($A41,Every1)=0),1,0) -> 1 | H41: =Alpha_keep^2*J40+Q_var -> 1.7492438 | I41: =IF(G41=1,H41/(H41+R_s),0) -> 0.21867615 | J41: =(1-I41)*H41 -> 1.3667259 | K41: =SQRT(J41) -> 1.1690705 | L41: =IF(AND($A41>0,MOD($A41,Every2)=0),1,0) -> 0 | M41: =Alpha_keep^2*O40+Q_var -> 1.1991381 | N41: =IF(L41=1,M41/(M41+R_sharp),0) -> 0 | O41: =(1-N41)*M41 -> 1.1991381 | P41: =SQRT(O41) -> 1.0950517 | Q41: =IF(AND($A41>0,MOD($A41,Every1)=0),1,0) -> 1 | R41: =Alpha_keep^2*T40+Q_var -> 1.045425 | S41: =IF(Q41=1,R41/(R41+R_sharp),0) -> 0.40086466 | T41: =(1-S41)*R41 -> 0.62635103 | U41: =SQRT(T41) -> 0.79142342 | V41: =IF(MOD($A41,Every2)=0,R_s,Alpha_keep^2*V40+Q_var) -> 6.3914063 | W41: =SQRT(V41) -> 2.5281231 | X41: =Alpha_keep^2*X40+Q_var -> 7.5650058 | Y41: =SQRT(X41) -> 2.7504556
... A66: 60 | B66: =IF(AND($A66>0,MOD($A66,Every2)=0),1,0) -> 1 | C66: =Alpha_keep^2*E65+Q_var -> 2.4842216 | D66: =IF(B66=1,C66/(C66+R_s),0) -> 0.28442393 | E66: =(1-D66)*C66 -> 1.7776496 | F66: =SQRT(E66) -> 1.3332852 | G66: =IF(AND($A66>0,MOD($A66,Every1)=0),1,0) -> 1 | H66: =Alpha_keep^2*J65+Q_var -> 1.7492438 | I66: =IF(G66=1,H66/(H66+R_s),0) -> 0.21867615 | J66: =(1-I66)*H66 -> 1.3667259 | K66: =SQRT(J66) -> 1.1690705 | L66: =IF(AND($A66>0,MOD($A66,Every2)=0),1,0) -> 1 | M66: =Alpha_keep^2*O65+Q_var -> 1.5899307 | N66: =IF(L66=1,M66/(M66+R_sharp),0) -> 0.50435072 | O66: =(1-N66)*M66 -> 0.788048 | P66: =SQRT(O66) -> 0.88772068 | Q66: =IF(AND($A66>0,MOD($A66,Every1)=0),1,0) -> 1 | R66: =Alpha_keep^2*T65+Q_var -> 1.045425 | S66: =IF(Q66=1,R66/(R66+R_sharp),0) -> 0.40086466 | T66: =(1-S66)*R66 -> 0.62635103 | U66: =SQRT(T66) -> 0.79142342 | V66: =IF(MOD($A66,Every2)=0,R_s,Alpha_keep^2*V65+Q_var) -> 6.25 | W66: =SQRT(V66) -> 2.5 | X66: =Alpha_keep^2*X65+Q_var -> 8.6771475 | Y66: =SQRT(X66) -> 2.9456998

Sheet Decide
A1: Decide on the twin: each design's best target and its cost (Theorem 15.2; Proposition 15.2; Worked Example 15.1, Steps 3 and 6; Table 15.3; Figure 15.2(a); AXIOM Lab 2.15, step 2)
A2: Mean costs from 58 on the 20,000 design paths (seed 1500) for seven targets around the book's best, and the best target's cost on the 100,000 fresh paths (seed 1501), are the engine's; every design runs on the same draws. The best targets, costs above the count and their yearly worth are formulas.
A4: Design | B4: Survey | C4: The book's best (window centre) | D4: Target 1 | E4: Target 2 | F4: Target 3 | G4: Target 4 | H4: Target 5 | I4: Target 6 | J4: Target 7 | K4: Design-path cost 1 (engine) | L4: Design-path cost 2 (engine) | M4: Design-path cost 3 (engine) | N4: Design-path cost 4 (engine) | O4: Design-path cost 5 (engine) | P4: Design-path cost 6 (engine) | Q4: Design-path cost 7 (engine) | R4: Best target | S4: Its design-path cost | T4: Margin over 55 | U4: Inside the window (1 = yes)
A5: Count (Chapter 7) | B5: -- | C5: 55.75 | D5: =ROUND($C5+0.05*(0-3),2) -> 55.6 | E5: =ROUND($C5+0.05*(1-3),2) -> 55.65 | F5: =ROUND($C5+0.05*(2-3),2) -> 55.7 | G5: =ROUND($C5+0.05*(3-3),2) -> 55.75 | H5: =ROUND($C5+0.05*(4-3),2) -> 55.8 | I5: =ROUND($C5+0.05*(5-3),2) -> 55.85 | J5: =ROUND($C5+0.05*(6-3),2) -> 55.9 | K5: 231.93434 | L5: 231.52444 | M5: 231.12612 | N5: 230.74711 | O5: 230.94972 | P5: 231.15233 | Q5: 231.35565 | R5: =INDEX(D5:J5,MATCH(MIN(K5:Q5),K5:Q5,0)) -> 55.75 | S5: =MIN(K5:Q5) -> 230.74711 | T5: =R5-Floor_c -> 0.75 | U5: =IF(AND(R5>D5,R5<J5),1,0) -> 1
A6: Twin | B6: twice a year | C6: 56.7 | D6: =ROUND($C6+0.05*(0-3),2) -> 56.55 | E6: =ROUND($C6+0.05*(1-3),2) -> 56.6 | F6: =ROUND($C6+0.05*(2-3),2) -> 56.65 | G6: =ROUND($C6+0.05*(3-3),2) -> 56.7 | H6: =ROUND($C6+0.05*(4-3),2) -> 56.75 | I6: =ROUND($C6+0.05*(5-3),2) -> 56.8 | J6: =ROUND($C6+0.05*(6-3),2) -> 56.85 | K6: 241.95481 | L6: 241.89726 | M6: 241.86329 | N6: 241.85194 | O6: 241.86227 | P6: 241.89345 | Q6: 241.94486 | R6: =INDEX(D6:J6,MATCH(MIN(K6:Q6),K6:Q6,0)) -> 56.7 | S6: =MIN(K6:Q6) -> 241.85194 | T6: =R6-Floor_c -> 1.7 | U6: =IF(AND(R6>D6,R6<J6),1,0) -> 1
A7: Survey read as exact | B7: twice a year | C7: 57.35 | D7: =ROUND($C7+0.05*(0-3),2) -> 57.2 | E7: =ROUND($C7+0.05*(1-3),2) -> 57.25 | F7: =ROUND($C7+0.05*(2-3),2) -> 57.3 | G7: =ROUND($C7+0.05*(3-3),2) -> 57.35 | H7: =ROUND($C7+0.05*(4-3),2) -> 57.4 | I7: =ROUND($C7+0.05*(5-3),2) -> 57.45 | J7: =ROUND($C7+0.05*(6-3),2) -> 57.5 | K7: 246.77565 | L7: 246.73164 | M7: 246.70558 | N7: 246.69617 | O7: 246.70279 | P7: 246.72531 | Q7: 246.76318 | R7: =INDEX(D7:J7,MATCH(MIN(K7:Q7),K7:Q7,0)) -> 57.35 | S7: =MIN(K7:Q7) -> 246.69617 | T7: =R7-Floor_c -> 2.35 | U7: =IF(AND(R7>D7,R7<J7),1,0) -> 1
A8: Twin | B8: quarterly | C8: 56.5 | D8: =ROUND($C8+0.05*(0-3),2) -> 56.35 | E8: =ROUND($C8+0.05*(1-3),2) -> 56.4 | F8: =ROUND($C8+0.05*(2-3),2) -> 56.45 | G8: =ROUND($C8+0.05*(3-3),2) -> 56.5 | H8: =ROUND($C8+0.05*(4-3),2) -> 56.55 | I8: =ROUND($C8+0.05*(5-3),2) -> 56.6 | J8: =ROUND($C8+0.05*(6-3),2) -> 56.65 | K8: 239.50723 | L8: 239.43437 | M8: 239.38921 | N8: 239.3707 | O8: 239.3777 | P8: 239.41885 | Q8: 239.48318 | R8: =INDEX(D8:J8,MATCH(MIN(K8:Q8),K8:Q8,0)) -> 56.5 | S8: =MIN(K8:Q8) -> 239.3707 | T8: =R8-Floor_c -> 1.5 | U8: =IF(AND(R8>D8,R8<J8),1,0) -> 1
A9: Twin | B9: twice as sharp | C9: 56.4 | D9: =ROUND($C9+0.05*(0-3),2) -> 56.25 | E9: =ROUND($C9+0.05*(1-3),2) -> 56.3 | F9: =ROUND($C9+0.05*(2-3),2) -> 56.35 | G9: =ROUND($C9+0.05*(3-3),2) -> 56.4 | H9: =ROUND($C9+0.05*(4-3),2) -> 56.45 | I9: =ROUND($C9+0.05*(5-3),2) -> 56.5 | J9: =ROUND($C9+0.05*(6-3),2) -> 56.55 | K9: 237.84776 | L9: 237.79065 | M9: 237.76239 | N9: 237.7612 | O9: 237.78608 | P9: 237.83843 | Q9: 237.91829 | R9: =INDEX(D9:J9,MATCH(MIN(K9:Q9),K9:Q9,0)) -> 56.4 | S9: =MIN(K9:Q9) -> 237.7612 | T9: =R9-Floor_c -> 1.4 | U9: =IF(AND(R9>D9,R9<J9),1,0) -> 1
A10: Twin | B10: both | C10: 56.2 | D10: =ROUND($C10+0.05*(0-3),2) -> 56.05 | E10: =ROUND($C10+0.05*(1-3),2) -> 56.1 | F10: =ROUND($C10+0.05*(2-3),2) -> 56.15 | G10: =ROUND($C10+0.05*(3-3),2) -> 56.2 | H10: =ROUND($C10+0.05*(4-3),2) -> 56.25 | I10: =ROUND($C10+0.05*(5-3),2) -> 56.3 | J10: =ROUND($C10+0.05*(6-3),2) -> 56.35 | K10: 235.79247 | L10: 235.71695 | M10: 235.67584 | N10: 235.66761 | O10: 235.69055 | P10: 235.74263 | Q10: 235.82242 | R10: =INDEX(D10:J10,MATCH(MIN(K10:Q10),K10:Q10,0)) -> 56.2 | S10: =MIN(K10:Q10) -> 235.66761 | T10: =R10-Floor_c -> 1.2 | U10: =IF(AND(R10>D10,R10<J10),1,0) -> 1
A11: No readings after the audit | B11: none | C11: 57.8 | D11: =ROUND($C11+0.05*(0-3),2) -> 57.65 | E11: =ROUND($C11+0.05*(1-3),2) -> 57.7 | F11: =ROUND($C11+0.05*(2-3),2) -> 57.75 | G11: =ROUND($C11+0.05*(3-3),2) -> 57.8 | H11: =ROUND($C11+0.05*(4-3),2) -> 57.85 | I11: =ROUND($C11+0.05*(5-3),2) -> 57.9 | J11: =ROUND($C11+0.05*(6-3),2) -> 57.95 | K11: 256.2146 | L11: 256.17753 | M11: 256.15423 | N11: 256.14506 | O11: 256.15012 | P11: 256.16914 | Q11: 256.20106 | R11: =INDEX(D11:J11,MATCH(MIN(K11:Q11),K11:Q11,0)) -> 57.8 | S11: =MIN(K11:Q11) -> 256.14506 | T11: =R11-Floor_c -> 2.8 | U11: =IF(AND(R11>D11,R11<J11),1,0) -> 1
A14: Design (100,000 fresh paths) | B14: Survey | C14: Target | D14: Cost from 58 (engine) | E14: Standard error (engine) | F14: Above the count | G14: Below the floor (engine) | H14: Worth a year, 4(1 - beta) x above | I14: Decisions at a hiring limit (engine)
A15: Count (Chapter 7) | B15: -- | C15: =R5 -> 55.75 | D15: 230.84371 | E15: 0.039547474 | F15: =D15-$D$15 -> 0 | G15: 0.060240023 | H15: =F15*4*(1-Beta_q) -> 0 | I15: 0.098035818
A16: Twin | B16: twice a year | C16: =R6 -> 56.7 | D16: 241.94431 | E16: 0.04159791 | F16: =D16-$D$15 -> 11.100596 | G16: 0.13374932 | H16: =F16*4*(1-Beta_q) -> 1.0454945 | I16: 0.069679568
A17: Survey read as exact | B17: twice a year | C17: =R7 -> 57.35 | D17: 246.79345 | E17: 0.041305416 | F17: =D17-$D$15 -> 15.949739 | G17: 0.13253332 | H17: =F17*4*(1-Beta_q) -> 1.5022045 | I17: 0.55689134
A18: Twin | B18: quarterly | C18: =R8 -> 56.5 | D18: 239.47751 | E18: 0.04049514 | F18: =D18-$D$15 -> 8.6337998 | G18: 0.12964216 | H18: =F18*4*(1-Beta_q) -> 0.8131627 | I18: 0.047302477
A19: Twin | B19: twice as sharp | C19: =R9 -> 56.4 | D19: 237.84907 | E19: 0.039861352 | F19: =D19-$D$15 -> 7.0053579 | G19: 0.12090391 | H19: =F19*4*(1-Beta_q) -> 0.65979011 | I19: 0.08278825
A20: Twin | B20: both | C20: =R10 -> 56.2 | D20: 235.76493 | E20: 0.039611139 | F20: =D20-$D$15 -> 4.9212146 | G20: 0.12220405 | H20: =F20*4*(1-Beta_q) -> 0.46349791 | I20: 0.057182091
A21: No readings after the audit | B21: none | C21: =R11 -> 57.8 | D21: 256.27706 | E21: 0.063087675 | F21: =D21-$D$15 -> 25.433345 | G21: 0.17617077 | H21: =F21*4*(1-Beta_q) -> 2.3954051 | I21: 0
A22: Twin, Chapter 7's target | B22: twice a year | C22: =Target7 -> 55.75 | D22: 247.15716 | F22: =D22-$D$15 -> 16.313442 | G22: 0.3132032 | H22: =F22*4*(1-Beta_q) -> 1.5364594
A23: Survey read as exact, Chapter 7's target | B23: twice a year | C23: =Target7 -> 55.75 | D23: 258.35238 | F23: =D23-$D$15 -> 27.508661 | G23: 0.38606593 | H23: =F23*4*(1-Beta_q) -> 2.5908659
A24: Survey read as exact, the whole error guarded | B24: twice a year | C24: =Target7+5 -> 60.75 | D24: 265.23979 | F24: =D24-$D$15 -> 34.396076 | G24: 0.0021979091 | H24: =F24*4*(1-Beta_q) -> 3.2395477
A25: 60.75 guards the survey's whole error, the five planned points Chapter 7 priced.
A27: Theorem 15.2(i): count < both < quarterly, sharper < twin < survey as exact < no readings (1 = yes) | B27: =IF(AND(D15<D20,D20<MIN(D19,D18),MAX(D19,D18)<D16,D16<D17,D17<D21),1,0) -> 1 | C27: Readings never cost
A28: The twin costs less than the survey read as exact by | B28: =F17-F16 -> 4.8491427 | C28: $4.8 million (the abstract)
A29: Proposition 15.2(i): the twin's target on its design paths | B29: =S6 -> 241.85194 | C29: 241.85
A30: on the fresh paths | B30: =D16 -> 241.94431 | C30: 241.94
A31: the design paths' standard error (engine) | B31: 0.092789062
A32: the difference, in standard errors | B32: =(B30-B29)/SQRT(B31^2+E16^2) -> 0.90841493 | C32: Within the simulation's error (Step 6)
A35: Theorem 15.2(iii): the margin is the (1 - k/b)-quantile of the swing less the twin's error
A36: k: holding a planned point a quarter, 4(1 - a beta) | B36: =Cost_k*(1-Alpha_keep*Beta_q) -> 0.19182905 | C36: Chapter 7
A37: b: a point short next quarter, 1.6 beta | B37: =Short_p*Beta_q -> 1.5623265
A38: Critical ratio k/b | B38: =B36/B37 -> 0.12278422 | C38: 0.1228 (Chapter 7)
A39: 1 - k/b | B39: =1-B38 -> 0.87721578
A41: Swing w, ascending | B41: Chance | C41: P(w <= x)
A42: =SMALL(Loss_w,1) -> -1.5 | B42: =SUMPRODUCT((Loss_w=A42)*Loss_p) -> 0.05 | C42: =SUM($B$42:B42) -> 0.05
A43: =SMALL(Loss_w,2) -> -0.75 | B43: =SUMPRODUCT((Loss_w=A43)*Loss_p) -> 0.2 | C43: =SUM($B$42:B43) -> 0.25
A44: =SMALL(Loss_w,3) -> 0 | B44: =SUMPRODUCT((Loss_w=A44)*Loss_p) -> 0.5 | C44: =SUM($B$42:B44) -> 0.75
A45: =SMALL(Loss_w,4) -> 0.75 | B45: =SUMPRODUCT((Loss_w=A45)*Loss_p) -> 0.2 | C45: =SUM($B$42:B45) -> 0.95
A46: =SMALL(Loss_w,5) -> 1.5 | B46: =SUMPRODUCT((Loss_w=A46)*Loss_p) -> 0.05 | C46: =SUM($B$42:B46) -> 1
A48: On the count, the swing's (1 - k/b)-quantile: the margin | B48: =INDEX(A42:A46,COUNTIF(C42:C46,"<"&B39)+1) -> 0.75 | C48: 0.75: Chapter 7's margin
A49: With normal swings and errors, z_(1 - k/b) | B49: =NORMSINV(B39) -> 1.1611806
A51: Design | B51: Twin's error s, at a survey (sd) | C51: s a quarter later | D51: z sqrt(q + (a s)^2), at a survey | E51: a quarter later | F51: The simulated best margin | G51: Decisions at a hiring limit (engine)
A52: Count (Chapter 7) | B52: =0 -> 0 | D52: =$B$49*SQRT(Q_var+(Alpha_keep*B52)^2) -> 0.77894365 | F52: =T5 -> 0.75 | G52: =I15 -> 0.098035818
A53: Twin, survey twice a year | B53: =Sync!AG6 -> 1.3332852 | C53: =Sync!AH6 -> 1.4628322 | D53: =$B$49*SQRT(Q_var+(Alpha_keep*B53)^2) -> 1.6986125 | E53: =$B$49*SQRT(Q_var+(Alpha_keep*C53)^2) -> 1.8301848 | F53: =T6 -> 1.7 | G53: =I16 -> 0.069679568
A54: Survey read as exact | B54: =Sync!AG10 -> 2.5 | C54: =Sync!AI10 -> 2.5281231 | D54: =$B$49*SQRT(Q_var+(Alpha_keep*B54)^2) -> 2.9356076 | E54: =$B$49*SQRT(Q_var+(Alpha_keep*C54)^2) -> 2.9663178 | F54: =T7 -> 2.35 | G54: =I17 -> 0.55689134
A55: Twin, quarterly survey | B55: =Sync!AG7 -> 1.1690705 | D55: =$B$49*SQRT(Q_var+(Alpha_keep*B55)^2) -> 1.5357657 | F55: =T8 -> 1.5 | G55: =I18 -> 0.047302477
A56: Twin, survey twice as sharp | B56: =Sync!AG8 -> 0.88772068 | C56: =SQRT(Alpha_keep^2*Sync!AF8+Q_var) -> 1.0950517 | D56: =$B$49*SQRT(Q_var+(Alpha_keep*B56)^2) -> 1.2715528 | E56: =$B$49*SQRT(Q_var+(Alpha_keep*C56)^2) -> 1.4641612 | F56: =T9 -> 1.4 | G56: =I19 -> 0.08278825
A57: Twin, both | B57: =Sync!AG9 -> 0.79142342 | D57: =$B$49*SQRT(Q_var+(Alpha_keep*B57)^2) -> 1.187261 | F57: =T10 -> 1.2 | G57: =I20 -> 0.057182091
A58: No readings after the audit | B58: =Sync!AG11 -> 3.0189276 | D58: =$B$49*SQRT(Q_var+(Alpha_keep*B58)^2) -> 3.5055203 | F58: =T11 -> 2.8 | G58: =I21 -> 0
A60: The twin's planned level is off by a times its error, so the margin is z times the error a quarter later. One quarter at a time, the formula sizes the count's and the twins' margins, where the hiring limits seldom bind; not the survey read as exact, whose readings push hires to 0 or to the cap in over half the quarters, nor no readings, whose error grows from 0 after the audit.

Sheet Program
A1: One program from the audited 58, run by the twin (Figure 15.1(a); seed 1503; Worked Example 15.1, Step 2; AXIOM Lab 2.15, step 1)
A2: The swings w and the survey's standard errors e are the engine's draws for seed 1503; everything else is a formula: capability, the readings z = c + 2.5 e, the filter, the twin's hires to its target, the costs, and the survey read as exact on the same readings and hires.
A4: Quarter | B4: Swing w (engine) | C4: Survey draw e (engine) | D4: Survey (1 = yes) | E4: Capability c | F4: Reading z | G4: Prior P- | H4: Gain K | I4: Posterior P | J4: Predicted estimate | K4: The twin's estimate | L4: Its error (sd) | M4: Hire h | N4: Quarter's cost | O4: Discount | P4: Present value | Q4: Survey read as exact | R4: Twin's error | S4: Survey-as-exact error
A5: 0 | B5: -0.75 | C5: 0.47995665 | D5: =IF(AND(A5>0,MOD(A5,Every2)=0),1,0) -> 0 | E5: =Start_c -> 58 | F5: =IF(D5=1,E5+SD_s*C5,"") | G5: 0 | H5: =IF(D5=1,G5/(G5+R_s),0) -> 0 | I5: =(1-H5)*G5 -> 0 | J5: =Start_c -> 58 | K5: =IF(D5=1,J5+H5*(F5-J5),J5) -> 58 | L5: =SQRT(I5) -> 0 | M5: =MIN(MAX($V$5-Alpha_keep*K5,0),Cap_h) -> 0.15 | N5: =Cost_k*M5+Short_p*MAX(Floor_c-E5,0) -> 0.6 | O5: =Beta_q^A5 -> 1 | P5: =N5*O5 -> 0.6 | Q5: =Start_c -> 58 | R5: =K5-E5 -> 0 | S5: =Q5-E5 -> 0 | U5: The twin's target (Decide) | V5: =Decide!R6 -> 56.7 | W5: 56.70
A6: 1 | B6: 0 | C6: -0.55002131 | D6: =IF(AND(A6>0,MOD(A6,Every2)=0),1,0) -> 0 | E6: =Alpha_keep*E5+M5-B5 -> 57.45 | F6: =IF(D6=1,E6+SD_s*C6,"") | G6: =Alpha_keep^2*I5+Q_var -> 0.45 | H6: =IF(D6=1,G6/(G6+R_s),0) -> 0 | I6: =(1-H6)*G6 -> 0.45 | J6: =Alpha_keep*K5+M5 -> 56.7 | K6: =IF(D6=1,J6+H6*(F6-J6),J6) -> 56.7 | L6: =SQRT(I6) -> 0.67082039 | M6: =MIN(MAX($V$5-Alpha_keep*K6,0),Cap_h) -> 1.4175 | N6: =Cost_k*M6+Short_p*MAX(Floor_c-E6,0) -> 5.67 | O6: =Beta_q^A6 -> 0.97645409 | P6: =N6*O6 -> 5.5364947 | Q6: =IF(D6=1,F6,Alpha_keep*Q5+M5) -> 56.7 | R6: =K6-E6 -> -0.75 | S6: =Q6-E6 -> -0.75 | U6: Present value of 25 quarters' costs | V6: =SUM(P5:P29) -> 107.4387
A7: 2 | B7: 0.75 | C7: 1.6331364 | D7: =IF(AND(A7>0,MOD(A7,Every2)=0),1,0) -> 1 | E7: =Alpha_keep*E6+M6-B6 -> 57.43125 | F7: =IF(D7=1,E7+SD_s*C7,"") -> 61.514091 | G7: =Alpha_keep^2*I6+Q_var -> 0.87778125 | H7: =IF(D7=1,G7/(G7+R_s),0) -> 0.1231493 | I7: =(1-H7)*G7 -> 0.76968311 | J7: =Alpha_keep*K6+M6 -> 56.7 | K7: =IF(D7=1,J7+H7*(F7-J7),J7) -> 57.292852 | L7: =SQRT(I7) -> 0.87731585 | M7: =MIN(MAX($V$5-Alpha_keep*K7,0),Cap_h) -> 0.83946938 | N7: =Cost_k*M7+Short_p*MAX(Floor_c-E7,0) -> 3.3578775 | O7: =Beta_q^A7 -> 0.95346259 | P7: =N7*O7 -> 3.2016106 | Q7: =IF(D7=1,F7,Alpha_keep*Q6+M6) -> 61.514091 | R7: =K7-E7 -> -0.13839808 | S7: =Q7-E7 -> 4.082841 | U7: The twin's estimate at quarter 24 | V7: =K29 -> 55.301895
A8: 3 | B8: -0.75 | C8: -0.22515684 | D8: =IF(AND(A8>0,MOD(A8,Every2)=0),1,0) -> 0 | E8: =Alpha_keep*E7+M7-B7 -> 56.084938 | F8: =IF(D8=1,E8+SD_s*C8,"") | G8: =Alpha_keep^2*I7+Q_var -> 1.18168 | H8: =IF(D8=1,G8/(G8+R_s),0) -> 0 | I8: =(1-H8)*G8 -> 1.18168 | J8: =Alpha_keep*K7+M7 -> 56.7 | K8: =IF(D8=1,J8+H8*(F8-J8),J8) -> 56.7 | L8: =SQRT(I8) -> 1.0870511 | M8: =MIN(MAX($V$5-Alpha_keep*K8,0),Cap_h) -> 1.4175 | N8: =Cost_k*M8+Short_p*MAX(Floor_c-E8,0) -> 5.67 | O8: =Beta_q^A8 -> 0.93101244 | P8: =N8*O8 -> 5.2788406 | Q8: =IF(D8=1,F8,Alpha_keep*Q7+M7) -> 60.815708 | R8: =K8-E8 -> 0.61506187 | S8: =Q8-E8 -> 4.7307699 | U8: Its error at quarter 24 (sd) | V8: =L29 -> 1.3331876
A9: 4 | B9: -0.75 | C9: -0.14443599 | D9: =IF(AND(A9>0,MOD(A9,Every2)=0),1,0) -> 1 | E9: =Alpha_keep*E8+M8-B8 -> 56.850315 | F9: =IF(D9=1,E9+SD_s*C9,"") -> 56.489225 | G9: =Alpha_keep^2*I8+Q_var -> 1.5733346 | H9: =IF(D9=1,G9/(G9+R_s),0) -> 0.20110792 | I9: =(1-H9)*G9 -> 1.2569245 | J9: =Alpha_keep*K8+M8 -> 56.7 | K9: =IF(D9=1,J9+H9*(F9-J9),J9) -> 56.657611 | L9: =SQRT(I9) -> 1.1211264 | M9: =MIN(MAX($V$5-Alpha_keep*K9,0),Cap_h) -> 1.4588289 | N9: =Cost_k*M9+Short_p*MAX(Floor_c-E9,0) -> 5.8353155 | O9: =Beta_q^A9 -> 0.90909091 | P9: =N9*O9 -> 5.3048322 | Q9: =IF(D9=1,F9,Alpha_keep*Q8+M8) -> 56.489225 | R9: =K9-E9 -> -0.19270326 | S9: =Q9-E9 -> -0.36108998 | U9: The twin's largest error | V9: =MAX(MAX(R5:R29),-MIN(R5:R29)) -> 3.2212689
A10: 5 | B10: 0 | C10: 0.83791857 | D10: =IF(AND(A10>0,MOD(A10,Every2)=0),1,0) -> 0 | E10: =Alpha_keep*E9+M9-B9 -> 57.637886 | F10: =IF(D10=1,E10+SD_s*C10,"") | G10: =Alpha_keep^2*I9+Q_var -> 1.6448639 | H10: =IF(D10=1,G10/(G10+R_s),0) -> 0 | I10: =(1-H10)*G10 -> 1.6448639 | J10: =Alpha_keep*K9+M9 -> 56.7 | K10: =IF(D10=1,J10+H10*(F10-J10),J10) -> 56.7 | L10: =SQRT(I10) -> 1.2825225 | M10: =MIN(MAX($V$5-Alpha_keep*K10,0),Cap_h) -> 1.4175 | N10: =Cost_k*M10+Short_p*MAX(Floor_c-E10,0) -> 5.67 | O10: =Beta_q^A10 -> 0.88768554 | P10: =N10*O10 -> 5.033177 | Q10: =IF(D10=1,F10,Alpha_keep*Q9+M9) -> 56.535823 | R10: =K10-E10 -> -0.93788568 | S10: =Q10-E10 -> -1.1020627 | U10: The survey read as exact: largest error | V10: =MAX(MAX(S5:S29),-MIN(S5:S29)) -> 7.2668633
A11: 6 | B11: -0.75 | C11: 1.459541 | D11: =IF(AND(A11>0,MOD(A11,Every2)=0),1,0) -> 1 | E11: =Alpha_keep*E10+M10-B10 -> 57.614439 | F11: =IF(D11=1,E11+SD_s*C11,"") -> 61.263291 | G11: =Alpha_keep^2*I10+Q_var -> 2.0136487 | H11: =IF(D11=1,G11/(G11+R_s),0) -> 0.2436755 | I11: =(1-H11)*G11 -> 1.5229719 | J11: =Alpha_keep*K10+M10 -> 56.7 | K11: =IF(D11=1,J11+H11*(F11-J11),J11) -> 57.811962 | L11: =SQRT(I11) -> 1.2340875 | M11: =MIN(MAX($V$5-Alpha_keep*K11,0),Cap_h) -> 0.33333685 | N11: =Cost_k*M11+Short_p*MAX(Floor_c-E11,0) -> 1.3333474 | O11: =Beta_q^A11 -> 0.86678417 | P11: =N11*O11 -> 1.1557244 | Q11: =IF(D11=1,F11,Alpha_keep*Q10+M10) -> 61.263291 | R11: =K11-E11 -> 0.19752367 | S11: =Q11-E11 -> 3.6488525
A12: 7 | B12: 0 | C12: 0.51400054 | D12: =IF(AND(A12>0,MOD(A12,Every2)=0),1,0) -> 0 | E12: =Alpha_keep*E11+M11-B11 -> 57.257414 | F12: =IF(D12=1,E12+SD_s*C12,"") | G12: =Alpha_keep^2*I11+Q_var -> 1.8977751 | H12: =IF(D12=1,G12/(G12+R_s),0) -> 0 | I12: =(1-H12)*G12 -> 1.8977751 | J12: =Alpha_keep*K11+M11 -> 56.7 | K12: =IF(D12=1,J12+H12*(F12-J12),J12) -> 56.7 | L12: =SQRT(I12) -> 1.3775976 | M12: =MIN(MAX($V$5-Alpha_keep*K12,0),Cap_h) -> 1.4175 | N12: =Cost_k*M12+Short_p*MAX(Floor_c-E12,0) -> 5.67 | O12: =Beta_q^A12 -> 0.84637495 | P12: =N12*O12 -> 4.798946 | Q12: =IF(D12=1,F12,Alpha_keep*Q11+M11) -> 60.065046 | R12: =K12-E12 -> -0.55741442 | S12: =Q12-E12 -> 2.8076312
A13: 8 | B13: 0 | C13: 1.3567389 | D13: =IF(AND(A13>0,MOD(A13,Every2)=0),1,0) -> 1 | E13: =Alpha_keep*E12+M12-B12 -> 57.243479 | F13: =IF(D13=1,E13+SD_s*C13,"") -> 60.635326 | G13: =Alpha_keep^2*I12+Q_var -> 2.2540725 | H13: =IF(D13=1,G13/(G13+R_s),0) -> 0.265058 | I13: =(1-H13)*G13 -> 1.6566125 | J13: =Alpha_keep*K12+M12 -> 56.7 | K13: =IF(D13=1,J13+H13*(F13-J13),J13) -> 57.74309 | L13: =SQRT(I13) -> 1.2870946 | M13: =MIN(MAX($V$5-Alpha_keep*K13,0),Cap_h) -> 0.40048749 | N13: =Cost_k*M13+Short_p*MAX(Floor_c-E13,0) -> 1.6019499 | O13: =Beta_q^A13 -> 0.82644628 | P13: =N13*O13 -> 1.3239256 | Q13: =IF(D13=1,F13,Alpha_keep*Q12+M12) -> 60.635326 | R13: =K13-E13 -> 0.4996107 | S13: =Q13-E13 -> 3.3918473
A14: 9 | B14: 0 | C14: 0.28840585 | D14: =IF(AND(A14>0,MOD(A14,Every2)=0),1,0) -> 0 | E14: =Alpha_keep*E13+M13-B13 -> 56.21288 | F14: =IF(D14=1,E14+SD_s*C14,"") | G14: =Alpha_keep^2*I13+Q_var -> 2.0248173 | H14: =IF(D14=1,G14/(G14+R_s),0) -> 0 | I14: =(1-H14)*G14 -> 2.0248173 | J14: =Alpha_keep*K13+M13 -> 56.7 | K14: =IF(D14=1,J14+H14*(F14-J14),J14) -> 56.7 | L14: =SQRT(I14) -> 1.4229607 | M14: =MIN(MAX($V$5-Alpha_keep*K14,0),Cap_h) -> 1.4175 | N14: =Cost_k*M14+Short_p*MAX(Floor_c-E14,0) -> 5.67 | O14: =Beta_q^A14 -> 0.80698685 | P14: =N14*O14 -> 4.5756154 | Q14: =IF(D14=1,F14,Alpha_keep*Q13+M13) -> 59.519931 | R14: =K14-E14 -> 0.48712043 | S14: =Q14-E14 -> 3.3070511
A15: 10 | B15: 0 | C15: 0.31266056 | D15: =IF(AND(A15>0,MOD(A15,Every2)=0),1,0) -> 1 | E15: =Alpha_keep*E14+M14-B14 -> 56.225058 | F15: =IF(D15=1,E15+SD_s*C15,"") -> 57.006709 | G15: =Alpha_keep^2*I14+Q_var -> 2.3748419 | H15: =IF(D15=1,G15/(G15+R_s),0) -> 0.27534904 | I15: =(1-H15)*G15 -> 1.7209315 | J15: =Alpha_keep*K14+M14 -> 56.7 | K15: =IF(D15=1,J15+H15*(F15-J15),J15) -> 56.784452 | L15: =SQRT(I15) -> 1.3118428 | M15: =MIN(MAX($V$5-Alpha_keep*K15,0),Cap_h) -> 1.3351593 | N15: =Cost_k*M15+Short_p*MAX(Floor_c-E15,0) -> 5.3406371 | O15: =Beta_q^A15 -> 0.78798561 | P15: =N15*O15 -> 4.2083452 | Q15: =IF(D15=1,F15,Alpha_keep*Q14+M14) -> 57.006709 | R15: =K15-E15 -> 0.55939444 | S15: =Q15-E15 -> 0.78165141
A16: 11 | B16: 0 | C16: 0.33084384 | D16: =IF(AND(A16>0,MOD(A16,Every2)=0),1,0) -> 0 | E16: =Alpha_keep*E15+M15-B15 -> 56.15459 | F16: =IF(D16=1,E16+SD_s*C16,"") | G16: =Alpha_keep^2*I15+Q_var -> 2.0859605 | H16: =IF(D16=1,G16/(G16+R_s),0) -> 0 | I16: =(1-H16)*G16 -> 2.0859605 | J16: =Alpha_keep*K15+M15 -> 56.7 | K16: =IF(D16=1,J16+H16*(F16-J16),J16) -> 56.7 | L16: =SQRT(I16) -> 1.4442855 | M16: =MIN(MAX($V$5-Alpha_keep*K16,0),Cap_h) -> 1.4175 | N16: =Cost_k*M16+Short_p*MAX(Floor_c-E16,0) -> 5.67 | O16: =Beta_q^A16 -> 0.76943177 | P16: =N16*O16 -> 4.3626781 | Q16: =IF(D16=1,F16,Alpha_keep*Q15+M15) -> 56.916701 | R16: =K16-E16 -> 0.54540958 | S16: =Q16-E16 -> 0.76211012
A17: 12 | B17: 0 | C17: 0.78201773 | D17: =IF(AND(A17>0,MOD(A17,Every2)=0),1,0) -> 1 | E17: =Alpha_keep*E16+M16-B16 -> 56.168226 | F17: =IF(D17=1,E17+SD_s*C17,"") -> 58.12327 | G17: =Alpha_keep^2*I16+Q_var -> 2.4329662 | H17: =IF(D17=1,G17/(G17+R_s),0) -> 0.28019989 | I17: =(1-H17)*G17 -> 1.7512493 | J17: =Alpha_keep*K16+M16 -> 56.7 | K17: =IF(D17=1,J17+H17*(F17-J17),J17) -> 57.0988 | L17: =SQRT(I17) -> 1.3233478 | M17: =MIN(MAX($V$5-Alpha_keep*K17,0),Cap_h) -> 1.0286699 | N17: =Cost_k*M17+Short_p*MAX(Floor_c-E17,0) -> 4.1146796 | O17: =Beta_q^A17 -> 0.7513148 | P17: =N17*O17 -> 3.0914197 | Q17: =IF(D17=1,F17,Alpha_keep*Q16+M16) -> 58.12327 | R17: =K17-E17 -> 0.93057444 | S17: =Q17-E17 -> 1.9550443
A18: 13 | B18: 0.75 | C18: -1.3876102 | D18: =IF(AND(A18>0,MOD(A18,Every2)=0),1,0) -> 0 | E18: =Alpha_keep*E17+M17-B17 -> 55.79269 | F18: =IF(D18=1,E18+SD_s*C18,"") | G18: =Alpha_keep^2*I17+Q_var -> 2.1147814 | H18: =IF(D18=1,G18/(G18+R_s),0) -> 0 | I18: =(1-H18)*G18 -> 2.1147814 | J18: =Alpha_keep*K17+M17 -> 56.7 | K18: =IF(D18=1,J18+H18*(F18-J18),J18) -> 56.7 | L18: =SQRT(I18) -> 1.4542288 | M18: =MIN(MAX($V$5-Alpha_keep*K18,0),Cap_h) -> 1.4175 | N18: =Cost_k*M18+Short_p*MAX(Floor_c-E18,0) -> 5.67 | O18: =Beta_q^A18 -> 0.73362441 | P18: =N18*O18 -> 4.1596504 | Q18: =IF(D18=1,F18,Alpha_keep*Q17+M17) -> 57.698858 | R18: =K18-E18 -> 0.90731008 | S18: =Q18-E18 -> 1.9061682
A19: 14 | B19: 1.5 | C19: 0.83904503 | D19: =IF(AND(A19>0,MOD(A19,Every2)=0),1,0) -> 1 | E19: =Alpha_keep*E18+M18-B18 -> 55.065373 | F19: =IF(D19=1,E19+SD_s*C19,"") -> 57.162985 | G19: =Alpha_keep^2*I18+Q_var -> 2.4603641 | H19: =IF(D19=1,G19/(G19+R_s),0) -> 0.28246398 | I19: =(1-H19)*G19 -> 1.7653998 | J19: =Alpha_keep*K18+M18 -> 56.7 | K19: =IF(D19=1,J19+H19*(F19-J19),J19) -> 56.830777 | L19: =SQRT(I19) -> 1.3286835 | M19: =MIN(MAX($V$5-Alpha_keep*K19,0),Cap_h) -> 1.2899928 | N19: =Cost_k*M19+Short_p*MAX(Floor_c-E19,0) -> 5.1599711 | O19: =Beta_q^A19 -> 0.71635056 | P19: =N19*O19 -> 3.6963481 | Q19: =IF(D19=1,F19,Alpha_keep*Q18+M18) -> 57.162985 | R19: =K19-E19 -> 1.765404 | S19: =Q19-E19 -> 2.0976126
A20: 15 | B20: 0 | C20: 1.2159444 | D20: =IF(AND(A20>0,MOD(A20,Every2)=0),1,0) -> 0 | E20: =Alpha_keep*E19+M19-B19 -> 53.478731 | F20: =IF(D20=1,E20+SD_s*C20,"") | G20: =Alpha_keep^2*I19+Q_var -> 2.1282332 | H20: =IF(D20=1,G20/(G20+R_s),0) -> 0 | I20: =(1-H20)*G20 -> 2.1282332 | J20: =Alpha_keep*K19+M19 -> 56.7 | K20: =IF(D20=1,J20+H20*(F20-J20),J20) -> 56.7 | L20: =SQRT(I20) -> 1.4588465 | M20: =MIN(MAX($V$5-Alpha_keep*K20,0),Cap_h) -> 1.4175 | N20: =Cost_k*M20+Short_p*MAX(Floor_c-E20,0) -> 8.1040302 | O20: =Beta_q^A20 -> 0.69948343 | P20: =N20*O20 -> 5.6686348 | Q20: =IF(D20=1,F20,Alpha_keep*Q19+M19) -> 57.023903 | R20: =K20-E20 -> 3.2212689 | S20: =Q20-E20 -> 3.5451723
A21: 16 | B21: 0.75 | C21: -0.76811439 | D21: =IF(AND(A21>0,MOD(A21,Every2)=0),1,0) -> 1 | E21: =Alpha_keep*E20+M20-B20 -> 53.559263 | F21: =IF(D21=1,E21+SD_s*C21,"") -> 51.638977 | G21: =Alpha_keep^2*I20+Q_var -> 2.4731517 | H21: =IF(D21=1,G21/(G21+R_s),0) -> 0.28351584 | I21: =(1-H21)*G21 -> 1.771974 | J21: =Alpha_keep*K20+M20 -> 56.7 | K21: =IF(D21=1,J21+H21*(F21-J21),J21) -> 55.26512 | L21: =SQRT(I21) -> 1.3311551 | M21: =MIN(MAX($V$5-Alpha_keep*K21,0),Cap_h) -> 2.5 | N21: =Cost_k*M21+Short_p*MAX(Floor_c-E21,0) -> 12.305179 | O21: =Beta_q^A21 -> 0.68301346 | P21: =N21*O21 -> 8.4046031 | Q21: =IF(D21=1,F21,Alpha_keep*Q20+M20) -> 51.638977 | R21: =K21-E21 -> 1.7058569 | S21: =Q21-E21 -> -1.920286
A22: 17 | B22: 0 | C22: 0.66360926 | D22: =IF(AND(A22>0,MOD(A22,Every2)=0),1,0) -> 0 | E22: =Alpha_keep*E21+M21-B21 -> 53.970281 | F22: =IF(D22=1,E22+SD_s*C22,"") | G22: =Alpha_keep^2*I21+Q_var -> 2.1344828 | H22: =IF(D22=1,G22/(G22+R_s),0) -> 0 | I22: =(1-H22)*G22 -> 2.1344828 | J22: =Alpha_keep*K21+M21 -> 56.383492 | K22: =IF(D22=1,J22+H22*(F22-J22),J22) -> 56.383492 | L22: =SQRT(I22) -> 1.4609869 | M22: =MIN(MAX($V$5-Alpha_keep*K22,0),Cap_h) -> 1.7260955 | N22: =Cost_k*M22+Short_p*MAX(Floor_c-E22,0) -> 8.5519321 | O22: =Beta_q^A22 -> 0.66693128 | P22: =N22*O22 -> 5.703551 | Q22: =IF(D22=1,F22,Alpha_keep*Q21+M21) -> 52.848002 | R22: =K22-E22 -> 2.4132105 | S22: =Q22-E22 -> -1.1222788
... A29: 24 | B29: 0 | C29: -1.3362014 | D29: =IF(AND(A29>0,MOD(A29,Every2)=0),1,0) -> 1 | E29: =Alpha_keep*E28+M28-B28 -> 55.124216 | F29: =IF(D29=1,E29+SD_s*C29,"") -> 51.783712 | G29: =Alpha_keep^2*I28+Q_var -> 2.4837129 | H29: =IF(D29=1,G29/(G29+R_s),0) -> 0.28438225 | I29: =(1-H29)*G29 -> 1.7773891 | J29: =Alpha_keep*K28+M28 -> 56.7 | K29: =IF(D29=1,J29+H29*(F29-J29),J29) -> 55.301895 | L29: =SQRT(I29) -> 1.3331876 | M29: =MIN(MAX($V$5-Alpha_keep*K29,0),Cap_h) -> 2.5 | N29: =Cost_k*M29+Short_p*MAX(Floor_c-E29,0) -> 10 | O29: =Beta_q^A29 -> 0.56447393 | P29: =N29*O29 -> 5.6447393 | Q29: =IF(D29=1,F29,Alpha_keep*Q28+M28) -> 51.783712 | R29: =K29-E29 -> 0.17767944 | S29: =Q29-E29 -> -3.3405035

Sheet Readings
A1: Price readings (Theorem 15.2(i); Worked Example 15.1, Step 4; Figure 15.2(b); AXIOM Lab 2.15, step 3)
A2: A rule on the true state costs no more than one on the twin's readings, which costs no more than one on coarser readings or none: each gap is the value of the information it adds. A present value V is worth 4(1 - beta) V a year, forever. The readings study (first 10,000 design and 40,000 fresh paths) is the engine's.
A4: A present value's yearly worth, forever: 4(1 - beta) | B4: =4*(1-Beta_q) -> 0.094183641
A5: The count, against the twin: a year | B5: =Decide!F16*B4 -> 1.0454945 | C5: About $1.0 million
A6: A quarterly survey: a year | B6: =(Decide!F16-Decide!F18)*B4 -> 0.23233184 | C6: Up to $0.23 million
A7: A survey twice as sharp: a year | B7: =(Decide!F16-Decide!F19)*B4 -> 0.38570443 | C7: $0.39 million
A8: Both: a year | B8: =(Decide!F16-Decide!F20)*B4 -> 0.58199664 | C8: $0.58 million
A10: Survey every (quarters) | B10: Survey error (sd) | C10: Best target (engine) | D10: Above the count (engine) | E10: Saved against today's survey | F10: Worth a year
A11: 2 | B11: 0.5 | C11: 56.1 | D11: 3.9005849 | E11: =$D$16-D11 -> 7.1985333 | F11: =E11*$B$4 -> 0.67798408
A12: 2 | B12: 1 | C12: 56.3 | D12: 6.0041758 | E12: =$D$16-D12 -> 5.0949425 | F12: =E12*$B$4 -> 0.47986023
A13: 2 | B13: 1.25 | C13: 56.4 | D13: 7.0077053 | E13: =$D$16-D13 -> 4.0914129 | F13: =E13*$B$4 -> 0.38534417
A14: 2 | B14: 1.5 | C14: 56.45 | D14: 7.9395911 | E14: =$D$16-D14 -> 3.1595271 | F14: =E14*$B$4 -> 0.29757577
A15: 2 | B15: 2 | C15: 56.6 | D15: 9.6301522 | E15: =$D$16-D15 -> 1.4689661 | F15: =E15*$B$4 -> 0.13835257
A16: 2 | B16: 2.5 | C16: 56.7 | D16: 11.099118 | E16: =$D$16-D16 -> 0 | F16: =E16*$B$4 -> 0
A17: 2 | B17: 3 | C17: 56.8 | D17: 12.375659 | E17: =$D$16-D17 -> -1.2765404 | F17: =E17*$B$4 -> -0.12022922
A18: 2 | B18: 4 | C18: 57 | D18: 14.474453 | E18: =$D$16-D18 -> -3.3753349 | F18: =E18*$B$4 -> -0.31790133
A19: 2 | B19: 5 | C19: 57.1 | D19: 16.11994 | E19: =$D$16-D19 -> -5.020822 | F19: =E19*$B$4 -> -0.47287929
A20: 1 | B20: 0.5 | C20: 55.9 | D20: 2.008844 | E20: =$D$16-D20 -> 9.0902742 | F20: =E20*$B$4 -> 0.85615513
A21: 1 | B21: 1 | C21: 56.1 | D21: 4.0024981 | E21: =$D$16-D21 -> 7.0966202 | F21: =E21*$B$4 -> 0.66838553
A22: 1 | B22: 1.25 | C22: 56.2 | D22: 4.9223367 | E22: =$D$16-D22 -> 6.1767816 | F22: =E22*$B$4 -> 0.58175178
... A28: 1 | B28: 5 | C28: 56.9 | D28: 13.468264 | E28: =$D$16-D28 -> -2.3691461 | F28: =E28*$B$4 -> -0.22313481
A31: The count on the first 40,000 fresh paths (engine) | B31: 230.83812
A32: Twice a year: a sharper survey never costs more (1 = yes) | B32: =IF(SUMPRODUCT(--(D12:D19>D11:D18))=8,1,0) -> 1
A33: Quarterly: a sharper survey never costs more (1 = yes) | B33: =IF(SUMPRODUCT(--(D21:D28>D20:D27))=8,1,0) -> 1
A34: A quarterly survey costs less at every error (1 = yes) | B34: =IF(SUMPRODUCT(--(D20:D28<D11:D19))=9,1,0) -> 1

Sheet Bias
A1: A twin that never questions its law (Theorem 15.3(i); Worked Example 15.1, Step 5; Section 15.4)
A2: From the start of quarter 8 each quarter loses an extra half point; the twin keeps mean 0. Its mean error e = estimate - capability grows by a e + d at each prediction and shrinks to (1 - K) e at each survey; the innovation is the reading less the prediction, so its mean is minus the predicted error.
A4: Extra points lost a quarter, d | B4: =Drift_d -> 0.5
A5: From the start of quarter | B5: =Drift_q -> 8
A6: Capability kept, a | B6: =Alpha_keep -> 0.975
A7: The twin's steady gain, K (Sync) | B7: =Sync!AJ6 -> 0.28442393 | C7: 0.284
A8: Bias just after a survey, b+ = (1 - K) d (1 + a)/(1 - (1 - K) a^2) | B8: =(1-B7)*B4*(1+B6)/(1-(1-B7)*B6^2) -> 2.2099116 | C8: 2.210
A9: Bias just before the next, a^2 b+ + d (1 + a) | B9: =B6^2*B8+B4*(1+B6) -> 3.0882972 | C9: 3.088
A10: The innovation's standard deviation just before a survey, sqrt(P- + r) | B10: =SQRT(Sync!AI6^2+R_s) -> 2.9553717
A11: The innovations' mean, in standard deviations | B11: =-B9/B10 -> -1.0449776 | C11: -1.045
A12: The recursion at quarter 40 | B12: =F55 -> 2.2054286
A13: The recursion at quarter 60 | B13: =F75 -> 2.2098165
A14: Quarter | B14: Survey (1 = yes) | C14: Gain K (Sync) | D14: Predicted mean error | E14: Innovations' mean (sd) | F14: Mean error after the survey
A15: 0 | B15: =Sync!B6 -> 0 | C15: =Sync!D6 -> 0 | D15: 0 | E15: =IF(B15=1,-D15/SQRT(Sync!C6+R_s),"") | F15: =(1-C15)*D15 -> 0
A16: 1 | B16: =Sync!B7 -> 0 | C16: =Sync!D7 -> 0 | D16: =Alpha_keep*F15+IF(A15>=Drift_q,Drift_d,0) -> 0 | E16: =IF(B16=1,-D16/SQRT(Sync!C7+R_s),"") | F16: =(1-C16)*D16 -> 0
A17: 2 | B17: =Sync!B8 -> 1 | C17: =Sync!D8 -> 0.1231493 | D17: =Alpha_keep*F16+IF(A16>=Drift_q,Drift_d,0) -> 0 | E17: =IF(B17=1,-D17/SQRT(Sync!C8+R_s),"") -> 0 | F17: =(1-C17)*D17 -> 0
A18: 3 | B18: =Sync!B9 -> 0 | C18: =Sync!D9 -> 0 | D18: =Alpha_keep*F17+IF(A17>=Drift_q,Drift_d,0) -> 0 | E18: =IF(B18=1,-D18/SQRT(Sync!C9+R_s),"") | F18: =(1-C18)*D18 -> 0
A19: 4 | B19: =Sync!B10 -> 1 | C19: =Sync!D10 -> 0.20110792 | D19: =Alpha_keep*F18+IF(A18>=Drift_q,Drift_d,0) -> 0 | E19: =IF(B19=1,-D19/SQRT(Sync!C10+R_s),"") -> 0 | F19: =(1-C19)*D19 -> 0
A20: 5 | B20: =Sync!B11 -> 0 | C20: =Sync!D11 -> 0 | D20: =Alpha_keep*F19+IF(A19>=Drift_q,Drift_d,0) -> 0 | E20: =IF(B20=1,-D20/SQRT(Sync!C11+R_s),"") | F20: =(1-C20)*D20 -> 0
A21: 6 | B21: =Sync!B12 -> 1 | C21: =Sync!D12 -> 0.2436755 | D21: =Alpha_keep*F20+IF(A20>=Drift_q,Drift_d,0) -> 0 | E21: =IF(B21=1,-D21/SQRT(Sync!C12+R_s),"") -> 0 | F21: =(1-C21)*D21 -> 0
A22: 7 | B22: =Sync!B13 -> 0 | C22: =Sync!D13 -> 0 | D22: =Alpha_keep*F21+IF(A21>=Drift_q,Drift_d,0) -> 0 | E22: =IF(B22=1,-D22/SQRT(Sync!C13+R_s),"") | F22: =(1-C22)*D22 -> 0
A23: 8 | B23: =Sync!B14 -> 1 | C23: =Sync!D14 -> 0.265058 | D23: =Alpha_keep*F22+IF(A22>=Drift_q,Drift_d,0) -> 0 | E23: =IF(B23=1,-D23/SQRT(Sync!C14+R_s),"") -> 0 | F23: =(1-C23)*D23 -> 0
A24: 9 | B24: =Sync!B15 -> 0 | C24: =Sync!D15 -> 0 | D24: =Alpha_keep*F23+IF(A23>=Drift_q,Drift_d,0) -> 0.5 | E24: =IF(B24=1,-D24/SQRT(Sync!C15+R_s),"") | F24: =(1-C24)*D24 -> 0.5
A25: 10 | B25: =Sync!B16 -> 1 | C25: =Sync!D16 -> 0.27534904 | D25: =Alpha_keep*F24+IF(A24>=Drift_q,Drift_d,0) -> 0.9875 | E25: =IF(B25=1,-D25/SQRT(Sync!C16+R_s),"") -> -0.33624941 | F25: =(1-C25)*D25 -> 0.71559282
A26: 11 | B26: =Sync!B17 -> 0 | C26: =Sync!D17 -> 0 | D26: =Alpha_keep*F25+IF(A25>=Drift_q,Drift_d,0) -> 1.197703 | E26: =IF(B26=1,-D26/SQRT(Sync!C17+R_s),"") | F26: =(1-C26)*D26 -> 1.197703
A27: 12 | B27: =Sync!B18 -> 1 | C27: =Sync!D18 -> 0.28019989 | D27: =Alpha_keep*F26+IF(A26>=Drift_q,Drift_d,0) -> 1.6677604 | E27: =IF(B27=1,-D27/SQRT(Sync!C18+R_s),"") -> -0.56597808 | F27: =(1-C27)*D27 -> 1.2004541
... A75: 60 | B75: =Sync!B66 -> 1 | C75: =Sync!D66 -> 0.28442393 | D75: =Alpha_keep*F74+IF(A74>=Drift_q,Drift_d,0) -> 3.0881643 | E75: =IF(B75=1,-D75/SQRT(Sync!C66+R_s),"") -> -1.0449326 | F75: =(1-C75)*D75 -> 2.2098165

Sheet Monitor
A1: The monitor: a cumulative sum of the surveys' surprises (Theorem 15.3(ii); Equation 15.2; Worked Example 15.1, Step 5; AXIOM Lab 2.15, step 4)
A2: False-alarm rates on 20,000 paths without a drift (seed 1505) are the engine's; the threshold is the least on the grid with at most one false alarm in 50 surveys. Below, the sum G = max(0, G - z - kappa) on the engine's standardized innovations of eight programs under the drift (seed 1507), restarting after each alarm.
A4: Threshold H | B4: False alarms a survey (engine) | C4: One in so many surveys | D4: One in so many years | E4: At most one in 50 (1 = yes)
A5: 1.5 | B5: 0.047122083 | C5: =1/B5 -> 21.221473 | D5: =C5/(4/Every2) -> 10.610736 | E5: =IF(B5<=1/FA_surveys,1,0) -> 0
A6: 1.75 | B6: 0.034686042 | C6: =1/B6 -> 28.830041 | D6: =C6/(4/Every2) -> 14.41502 | E6: =IF(B6<=1/FA_surveys,1,0) -> 0
A7: 2 | B7: 0.02575875 | C7: =1/B7 -> 38.82176 | D7: =C7/(4/Every2) -> 19.41088 | E7: =IF(B7<=1/FA_surveys,1,0) -> 0
A8: 2.25 | B8: 0.01923 | C8: =1/B8 -> 52.00208 | D8: =C8/(4/Every2) -> 26.00104 | E8: =IF(B8<=1/FA_surveys,1,0) -> 1
A9: 2.5 | B9: 0.014504583 | C9: =1/B9 -> 68.943725 | D9: =C9/(4/Every2) -> 34.471862 | E9: =IF(B9<=1/FA_surveys,1,0) -> 1
A10: 3 | B10: 0.008360625 | C10: =1/B10 -> 119.60828 | D10: =C10/(4/Every2) -> 59.804141 | E10: =IF(B10<=1/FA_surveys,1,0) -> 1
A12: The threshold: the least that keeps the rate | B12: =INDEX(A5:A10,MATCH(1,E5:E10,0)) -> 2.25 | C12: 2.25
A13: one false alarm in so many years | B13: =INDEX(D5:D10,MATCH(B12,A5:A10,0)) -> 26.00104 | C13: About 26
A15: Theorem 15.3(ii): the shift detected, delta = 2 kappa (standard deviations) | B15: =2*Kappa -> 1
A16: gamma = e^(H delta): at least so many surveys between false alarms | B16: =EXP(B12*B15) -> 9.4877358 | C16: A guarantee
A17: the simulation's surveys between false alarms | B17: =INDEX(C5:C10,MATCH(B12,A5:A10,0)) -> 52.00208
A18: delay about 2 ln(gamma)/delta^2, surveys | B18: =2*LN(B16)/B15^2 -> 4.5 | C18: Once the innovations have shifted
A19: in quarters | B19: =B18*Every2 -> 9
A22: Survey quarter | B22: Program 1: z (engine) | C22: G | D22: Alarm | E22: Program 2: z (engine) | F22: G | G22: Alarm | H22: Program 3: z (engine) | I22: G | J22: Alarm | K22: Program 4: z (engine) | L22: G | M22: Alarm | N22: Program 5: z (engine) | O22: G | P22: Alarm | Q22: Program 6: z (engine) | R22: G | S22: Alarm | T22: Program 7: z (engine) | U22: G | V22: Alarm | W22: Program 8: z (engine) | X22: G | Y22: Alarm
A23: 2 | B23: -0.85447031 | C23: =MAX(0,0-B23-Kappa) -> 0.35447031 | D23: =IF(C23>$B$12,1,0) -> 0 | E23: -0.16568063 | F23: =MAX(0,0-E23-Kappa) -> 0 | G23: =IF(F23>$B$12,1,0) -> 0 | H23: 0.20961893 | I23: =MAX(0,0-H23-Kappa) -> 0 | J23: =IF(I23>$B$12,1,0) -> 0 | K23: 0.21218445 | L23: =MAX(0,0-K23-Kappa) -> 0 | M23: =IF(L23>$B$12,1,0) -> 0 | N23: -0.31218488 | O23: =MAX(0,0-N23-Kappa) -> 0 | P23: =IF(O23>$B$12,1,0) -> 0 | Q23: -2.2224757 | R23: =MAX(0,0-Q23-Kappa) -> 1.7224757 | S23: =IF(R23>$B$12,1,0) -> 0 | T23: -1.8379147 | U23: =MAX(0,0-T23-Kappa) -> 1.3379147 | V23: =IF(U23>$B$12,1,0) -> 0 | W23: 1.346849 | X23: =MAX(0,0-W23-Kappa) -> 0 | Y23: =IF(X23>$B$12,1,0) -> 0
A24: 4 | B24: -0.7665561 | C24: =MAX(0,IF(D23=1,0,C23)-B24-Kappa) -> 0.62102641 | D24: =IF(C24>$B$12,1,0) -> 0 | E24: -1.0117942 | F24: =MAX(0,IF(G23=1,0,F23)-E24-Kappa) -> 0.51179422 | G24: =IF(F24>$B$12,1,0) -> 0 | H24: 1.12926 | I24: =MAX(0,IF(J23=1,0,I23)-H24-Kappa) -> 0 | J24: =IF(I24>$B$12,1,0) -> 0 | K24: -1.3776194 | L24: =MAX(0,IF(M23=1,0,L23)-K24-Kappa) -> 0.87761935 | M24: =IF(L24>$B$12,1,0) -> 0 | N24: -0.82445721 | O24: =MAX(0,IF(P23=1,0,O23)-N24-Kappa) -> 0.32445721 | P24: =IF(O24>$B$12,1,0) -> 0 | Q24: -1.5884011 | R24: =MAX(0,IF(S23=1,0,R23)-Q24-Kappa) -> 2.8108769 | S24: =IF(R24>$B$12,1,0) -> 1 | T24: 0.030722749 | U24: =MAX(0,IF(V23=1,0,U23)-T24-Kappa) -> 0.807192 | V24: =IF(U24>$B$12,1,0) -> 0 | W24: -0.052718814 | X24: =MAX(0,IF(Y23=1,0,X23)-W24-Kappa) -> 0 | Y24: =IF(X24>$B$12,1,0) -> 0
A25: 6 | B25: 0.999068 | C25: =MAX(0,IF(D24=1,0,C24)-B25-Kappa) -> 0 | D25: =IF(C25>$B$12,1,0) -> 0 | E25: -0.40473934 | F25: =MAX(0,IF(G24=1,0,F24)-E25-Kappa) -> 0.41653356 | G25: =IF(F25>$B$12,1,0) -> 0 | H25: -1.0003447 | I25: =MAX(0,IF(J24=1,0,I24)-H25-Kappa) -> 0.50034474 | J25: =IF(I25>$B$12,1,0) -> 0 | K25: -0.15828093 | L25: =MAX(0,IF(M24=1,0,L24)-K25-Kappa) -> 0.53590028 | M25: =IF(L25>$B$12,1,0) -> 0 | N25: 1.7038758 | O25: =MAX(0,IF(P24=1,0,O24)-N25-Kappa) -> 0 | P25: =IF(O25>$B$12,1,0) -> 0 | Q25: 0.9651468 | R25: =MAX(0,IF(S24=1,0,R24)-Q25-Kappa) -> 0 | S25: =IF(R25>$B$12,1,0) -> 0 | T25: 0.93783995 | U25: =MAX(0,IF(V24=1,0,U24)-T25-Kappa) -> 0 | V25: =IF(U25>$B$12,1,0) -> 0 | W25: 0.97661826 | X25: =MAX(0,IF(Y24=1,0,X24)-W25-Kappa) -> 0 | Y25: =IF(X25>$B$12,1,0) -> 0
A26: 8 | B26: 0.36224626 | C26: =MAX(0,IF(D25=1,0,C25)-B26-Kappa) -> 0 | D26: =IF(C26>$B$12,1,0) -> 0 | E26: -1.3681027 | F26: =MAX(0,IF(G25=1,0,F25)-E26-Kappa) -> 1.2846362 | G26: =IF(F26>$B$12,1,0) -> 0 | H26: -0.2189628 | I26: =MAX(0,IF(J25=1,0,I25)-H26-Kappa) -> 0.21930754 | J26: =IF(I26>$B$12,1,0) -> 0 | K26: -1.723674 | L26: =MAX(0,IF(M25=1,0,L25)-K26-Kappa) -> 1.7595743 | M26: =IF(L26>$B$12,1,0) -> 0 | N26: -1.259868 | O26: =MAX(0,IF(P25=1,0,O25)-N26-Kappa) -> 0.75986802 | P26: =IF(O26>$B$12,1,0) -> 0 | Q26: -0.76512195 | R26: =MAX(0,IF(S25=1,0,R25)-Q26-Kappa) -> 0.26512195 | S26: =IF(R26>$B$12,1,0) -> 0 | T26: -0.0515419 | U26: =MAX(0,IF(V25=1,0,U25)-T26-Kappa) -> 0 | V26: =IF(U26>$B$12,1,0) -> 0 | W26: 2.580952 | X26: =MAX(0,IF(Y25=1,0,X25)-W26-Kappa) -> 0 | Y26: =IF(X26>$B$12,1,0) -> 0
A27: 10 | B27: -1.7077897 | C27: =MAX(0,IF(D26=1,0,C26)-B27-Kappa) -> 1.2077897 | D27: =IF(C27>$B$12,1,0) -> 0 | E27: -1.8123126 | F27: =MAX(0,IF(G26=1,0,F26)-E27-Kappa) -> 2.5969488 | G27: =IF(F27>$B$12,1,0) -> 1 | H27: 0.11192642 | I27: =MAX(0,IF(J26=1,0,I26)-H27-Kappa) -> 0 | J27: =IF(I27>$B$12,1,0) -> 0 | K27: -0.44326774 | L27: =MAX(0,IF(M26=1,0,L26)-K27-Kappa) -> 1.702842 | M27: =IF(L27>$B$12,1,0) -> 0 | N27: -0.2931121 | O27: =MAX(0,IF(P26=1,0,O26)-N27-Kappa) -> 0.55298012 | P27: =IF(O27>$B$12,1,0) -> 0 | Q27: -0.4189275 | R27: =MAX(0,IF(S26=1,0,R26)-Q27-Kappa) -> 0.18404945 | S27: =IF(R27>$B$12,1,0) -> 0 | T27: 0.12207586 | U27: =MAX(0,IF(V26=1,0,U26)-T27-Kappa) -> 0 | V27: =IF(U27>$B$12,1,0) -> 0 | W27: -1.658161 | X27: =MAX(0,IF(Y26=1,0,X26)-W27-Kappa) -> 1.158161 | Y27: =IF(X27>$B$12,1,0) -> 0
A28: 12 | B28: -1.9932821 | C28: =MAX(0,IF(D27=1,0,C27)-B28-Kappa) -> 2.7010718 | D28: =IF(C28>$B$12,1,0) -> 1 | E28: 0.17131944 | F28: =MAX(0,IF(G27=1,0,F27)-E28-Kappa) -> 0 | G28: =IF(F28>$B$12,1,0) -> 0 | H28: -2.4612436 | I28: =MAX(0,IF(J27=1,0,I27)-H28-Kappa) -> 1.9612436 | J28: =IF(I28>$B$12,1,0) -> 0 | K28: 0.032339896 | L28: =MAX(0,IF(M27=1,0,L27)-K28-Kappa) -> 1.1705021 | M28: =IF(L28>$B$12,1,0) -> 0 | N28: -2.1108696 | O28: =MAX(0,IF(P27=1,0,O27)-N28-Kappa) -> 2.1638498 | P28: =IF(O28>$B$12,1,0) -> 0 | Q28: 0.052363393 | R28: =MAX(0,IF(S27=1,0,R27)-Q28-Kappa) -> 0 | S28: =IF(R28>$B$12,1,0) -> 0 | T28: -0.17989471 | U28: =MAX(0,IF(V27=1,0,U27)-T28-Kappa) -> 0 | V28: =IF(U28>$B$12,1,0) -> 0 | W28: -0.70666769 | X28: =MAX(0,IF(Y27=1,0,X27)-W28-Kappa) -> 1.3648287 | Y28: =IF(X28>$B$12,1,0) -> 0
A29: 14 | B29: -0.28719407 | C29: =MAX(0,IF(D28=1,0,C28)-B29-Kappa) -> 0 | D29: =IF(C29>$B$12,1,0) -> 0 | E29: -1.2809049 | F29: =MAX(0,IF(G28=1,0,F28)-E29-Kappa) -> 0.78090486 | G29: =IF(F29>$B$12,1,0) -> 0 | H29: -0.52020676 | I29: =MAX(0,IF(J28=1,0,I28)-H29-Kappa) -> 1.9814504 | J29: =IF(I29>$B$12,1,0) -> 0 | K29: -1.7208706 | L29: =MAX(0,IF(M28=1,0,L28)-K29-Kappa) -> 2.3913727 | M29: =IF(L29>$B$12,1,0) -> 1 | N29: -2.4075364 | O29: =MAX(0,IF(P28=1,0,O28)-N29-Kappa) -> 4.0713862 | P29: =IF(O29>$B$12,1,0) -> 1 | Q29: 0.24412306 | R29: =MAX(0,IF(S28=1,0,R28)-Q29-Kappa) -> 0 | S29: =IF(R29>$B$12,1,0) -> 0 | T29: -2.4495087 | U29: =MAX(0,IF(V28=1,0,U28)-T29-Kappa) -> 1.9495087 | V29: =IF(U29>$B$12,1,0) -> 0 | W29: -1.7307047 | X29: =MAX(0,IF(Y28=1,0,X28)-W29-Kappa) -> 2.5955334 | Y29: =IF(X29>$B$12,1,0) -> 1
A30: 16 | B30: -2.1871741 | C30: =MAX(0,IF(D29=1,0,C29)-B30-Kappa) -> 1.6871741 | D30: =IF(C30>$B$12,1,0) -> 0 | E30: 0.26410144 | F30: =MAX(0,IF(G29=1,0,F29)-E30-Kappa) -> 0.016803423 | G30: =IF(F30>$B$12,1,0) -> 0 | H30: -1.1927627 | I30: =MAX(0,IF(J29=1,0,I29)-H30-Kappa) -> 2.6742131 | J30: =IF(I30>$B$12,1,0) -> 1 | K30: 0.04487642 | L30: =MAX(0,IF(M29=1,0,L29)-K30-Kappa) -> 0 | M30: =IF(L30>$B$12,1,0) -> 0 | N30: -1.9310127 | O30: =MAX(0,IF(P29=1,0,O29)-N30-Kappa) -> 1.4310127 | P30: =IF(O30>$B$12,1,0) -> 0 | Q30: 0.18998595 | R30: =MAX(0,IF(S29=1,0,R29)-Q30-Kappa) -> 0 | S30: =IF(R30>$B$12,1,0) -> 0 | T30: 0.55418754 | U30: =MAX(0,IF(V29=1,0,U29)-T30-Kappa) -> 0.89532118 | V30: =IF(U30>$B$12,1,0) -> 0 | W30: 0.33698724 | X30: =MAX(0,IF(Y29=1,0,X29)-W30-Kappa) -> 0 | Y30: =IF(X30>$B$12,1,0) -> 0
A31: 18 | B31: -1.3295083 | C31: =MAX(0,IF(D30=1,0,C30)-B31-Kappa) -> 2.5166824 | D31: =IF(C31>$B$12,1,0) -> 1 | E31: 1.0533053 | F31: =MAX(0,IF(G30=1,0,F30)-E31-Kappa) -> 0 | G31: =IF(F31>$B$12,1,0) -> 0 | H31: -0.40657412 | I31: =MAX(0,IF(J30=1,0,I30)-H31-Kappa) -> 0 | J31: =IF(I31>$B$12,1,0) -> 0 | K31: -1.0694825 | L31: =MAX(0,IF(M30=1,0,L30)-K31-Kappa) -> 0.56948245 | M31: =IF(L31>$B$12,1,0) -> 0 | N31: -0.069611904 | O31: =MAX(0,IF(P30=1,0,O30)-N31-Kappa) -> 1.0006246 | P31: =IF(O31>$B$12,1,0) -> 0 | Q31: 0.72370712 | R31: =MAX(0,IF(S30=1,0,R30)-Q31-Kappa) -> 0 | S31: =IF(R31>$B$12,1,0) -> 0 | T31: -0.97078476 | U31: =MAX(0,IF(V30=1,0,U30)-T31-Kappa) -> 1.3661059 | V31: =IF(U31>$B$12,1,0) -> 0 | W31: 0.12043462 | X31: =MAX(0,IF(Y30=1,0,X30)-W31-Kappa) -> 0 | Y31: =IF(X31>$B$12,1,0) -> 0
A32: 20 | B32: -0.36219298 | C32: =MAX(0,IF(D31=1,0,C31)-B32-Kappa) -> 0 | D32: =IF(C32>$B$12,1,0) -> 0 | E32: -1.4003155 | F32: =MAX(0,IF(G31=1,0,F31)-E32-Kappa) -> 0.90031545 | G32: =IF(F32>$B$12,1,0) -> 0 | H32: -1.18589 | I32: =MAX(0,IF(J31=1,0,I31)-H32-Kappa) -> 0.68589002 | J32: =IF(I32>$B$12,1,0) -> 0 | K32: 2.1475752 | L32: =MAX(0,IF(M31=1,0,L31)-K32-Kappa) -> 0 | M32: =IF(L32>$B$12,1,0) -> 0 | N32: -0.56176474 | O32: =MAX(0,IF(P31=1,0,O31)-N32-Kappa) -> 1.0623894 | P32: =IF(O32>$B$12,1,0) -> 0 | Q32: 1.2253422 | R32: =MAX(0,IF(S31=1,0,R31)-Q32-Kappa) -> 0 | S32: =IF(R32>$B$12,1,0) -> 0 | T32: -0.592303 | U32: =MAX(0,IF(V31=1,0,U31)-T32-Kappa) -> 1.4584089 | V32: =IF(U32>$B$12,1,0) -> 0 | W32: -0.6180214 | X32: =MAX(0,IF(Y31=1,0,X31)-W32-Kappa) -> 0.1180214 | Y32: =IF(X32>$B$12,1,0) -> 0
A33: 22 | B33: 0.87146935 | C33: =MAX(0,IF(D32=1,0,C32)-B33-Kappa) -> 0 | D33: =IF(C33>$B$12,1,0) -> 0 | E33: -0.30335835 | F33: =MAX(0,IF(G32=1,0,F32)-E33-Kappa) -> 0.7036738 | G33: =IF(F33>$B$12,1,0) -> 0 | H33: 0.86764388 | I33: =MAX(0,IF(J32=1,0,I32)-H33-Kappa) -> 0 | J33: =IF(I33>$B$12,1,0) -> 0 | K33: -1.0968844 | L33: =MAX(0,IF(M32=1,0,L32)-K33-Kappa) -> 0.59688438 | M33: =IF(L33>$B$12,1,0) -> 0 | N33: 0.56865764 | O33: =MAX(0,IF(P32=1,0,O32)-N33-Kappa) -> 0 | P33: =IF(O33>$B$12,1,0) -> 0 | Q33: 0.42265558 | R33: =MAX(0,IF(S32=1,0,R32)-Q33-Kappa) -> 0 | S33: =IF(R33>$B$12,1,0) -> 0 | T33: -2.7642472 | U33: =MAX(0,IF(V32=1,0,U32)-T33-Kappa) -> 3.7226562 | V33: =IF(U33>$B$12,1,0) -> 1 | W33: 0.085323602 | X33: =MAX(0,IF(Y32=1,0,X32)-W33-Kappa) -> 0 | Y33: =IF(X33>$B$12,1,0) -> 0
A34: 24 | B34: 0.29898832 | C34: =MAX(0,IF(D33=1,0,C33)-B34-Kappa) -> 0 | D34: =IF(C34>$B$12,1,0) -> 0 | E34: 0.51076924 | F34: =MAX(0,IF(G33=1,0,F33)-E34-Kappa) -> 0 | G34: =IF(F34>$B$12,1,0) -> 0 | H34: 1.2450062 | I34: =MAX(0,IF(J33=1,0,I33)-H34-Kappa) -> 0 | J34: =IF(I34>$B$12,1,0) -> 0 | K34: -0.1120228 | L34: =MAX(0,IF(M33=1,0,L33)-K34-Kappa) -> 0.20890718 | M34: =IF(L34>$B$12,1,0) -> 0 | N34: -0.6527624 | O34: =MAX(0,IF(P33=1,0,O33)-N34-Kappa) -> 0.1527624 | P34: =IF(O34>$B$12,1,0) -> 0 | Q34: -1.2505113 | R34: =MAX(0,IF(S33=1,0,R33)-Q34-Kappa) -> 0.75051133 | S34: =IF(R34>$B$12,1,0) -> 0 | T34: 0.38325922 | U34: =MAX(0,IF(V33=1,0,U33)-T34-Kappa) -> 0 | V34: =IF(U34>$B$12,1,0) -> 0 | W34: 1.7609816 | X34: =MAX(0,IF(Y33=1,0,X33)-W34-Kappa) -> 0 | Y34: =IF(X34>$B$12,1,0) -> 0
A35: 26 | B35: 0.62055755 | C35: =MAX(0,IF(D34=1,0,C34)-B35-Kappa) -> 0 | D35: =IF(C35>$B$12,1,0) -> 0 | E35: 1.4878328 | F35: =MAX(0,IF(G34=1,0,F34)-E35-Kappa) -> 0 | G35: =IF(F35>$B$12,1,0) -> 0 | H35: -0.67656215 | I35: =MAX(0,IF(J34=1,0,I34)-H35-Kappa) -> 0.17656215 | J35: =IF(I35>$B$12,1,0) -> 0 | K35: 1.5822272 | L35: =MAX(0,IF(M34=1,0,L34)-K35-Kappa) -> 0 | M35: =IF(L35>$B$12,1,0) -> 0 | N35: -1.0917926 | O35: =MAX(0,IF(P34=1,0,O34)-N35-Kappa) -> 0.74455501 | P35: =IF(O35>$B$12,1,0) -> 0 | Q35: -0.42664828 | R35: =MAX(0,IF(S34=1,0,R34)-Q35-Kappa) -> 0.67715961 | S35: =IF(R35>$B$12,1,0) -> 0 | T35: -0.34534644 | U35: =MAX(0,IF(V34=1,0,U34)-T35-Kappa) -> 0 | V35: =IF(U35>$B$12,1,0) -> 0 | W35: -0.83632336 | X35: =MAX(0,IF(Y34=1,0,X34)-W35-Kappa) -> 0.33632336 | Y35: =IF(X35>$B$12,1,0) -> 0
... A42: 40 | B42: 1.1915557 | C42: =MAX(0,IF(D41=1,0,C41)-B42-Kappa) -> 0 | D42: =IF(C42>$B$12,1,0) -> 0 | E42: 1.0180016 | F42: =MAX(0,IF(G41=1,0,F41)-E42-Kappa) -> 0 | G42: =IF(F42>$B$12,1,0) -> 0 | H42: -0.087969723 | I42: =MAX(0,IF(J41=1,0,I41)-H42-Kappa) -> 0.173606 | J42: =IF(I42>$B$12,1,0) -> 0 | K42: 0.56164803 | L42: =MAX(0,IF(M41=1,0,L41)-K42-Kappa) -> 0 | M42: =IF(L42>$B$12,1,0) -> 0 | N42: 0.1743203 | O42: =MAX(0,IF(P41=1,0,O41)-N42-Kappa) -> 0 | P42: =IF(O42>$B$12,1,0) -> 0 | Q42: -1.7991099 | R42: =MAX(0,IF(S41=1,0,R41)-Q42-Kappa) -> 1.2991099 | S42: =IF(R42>$B$12,1,0) -> 0 | T42: 0.87480874 | U42: =MAX(0,IF(V41=1,0,U41)-T42-Kappa) -> 0 | V42: =IF(U42>$B$12,1,0) -> 0 | W42: -0.48003009 | X42: =MAX(0,IF(Y41=1,0,X41)-W42-Kappa) -> 0.96758821 | Y42: =IF(X42>$B$12,1,0) -> 0
A44: Program | B44: First alarm from the drift's quarter (formula) | C44: The engine's | D44: Same (1 = yes) | E44: Quarters after the drift began
A45: 1 | B45: =_xlfn.MINIFS($A$23:$A$42,D23:D42,1,$A$23:$A$42,">="&Drift_q) -> 12 | C45: 12 | D45: =IF(B45=C45,1,0) -> 1 | E45: =B45-Drift_q -> 4
A46: 2 | B46: =_xlfn.MINIFS($A$23:$A$42,G23:G42,1,$A$23:$A$42,">="&Drift_q) -> 10 | C46: 10 | D46: =IF(B46=C46,1,0) -> 1 | E46: =B46-Drift_q -> 2
A47: 3 | B47: =_xlfn.MINIFS($A$23:$A$42,J23:J42,1,$A$23:$A$42,">="&Drift_q) -> 16 | C47: 16 | D47: =IF(B47=C47,1,0) -> 1 | E47: =B47-Drift_q -> 8
A48: 4 | B48: =_xlfn.MINIFS($A$23:$A$42,M23:M42,1,$A$23:$A$42,">="&Drift_q) -> 14 | C48: 14 | D48: =IF(B48=C48,1,0) -> 1 | E48: =B48-Drift_q -> 6
A49: 5 | B49: =_xlfn.MINIFS($A$23:$A$42,P23:P42,1,$A$23:$A$42,">="&Drift_q) -> 14 | C49: 14 | D49: =IF(B49=C49,1,0) -> 1 | E49: =B49-Drift_q -> 6
A50: 6 | B50: =_xlfn.MINIFS($A$23:$A$42,S23:S42,1,$A$23:$A$42,">="&Drift_q) -> 30 | C50: 30 | D50: =IF(B50=C50,1,0) -> 1 | E50: =B50-Drift_q -> 22
A51: 7 | B51: =_xlfn.MINIFS($A$23:$A$42,V23:V42,1,$A$23:$A$42,">="&Drift_q) -> 22 | C51: 22 | D51: =IF(B51=C51,1,0) -> 1 | E51: =B51-Drift_q -> 14
A52: 8 | B52: =_xlfn.MINIFS($A$23:$A$42,Y23:Y42,1,$A$23:$A$42,">="&Drift_q) -> 14 | C52: 14 | D52: =IF(B52=C52,1,0) -> 1 | E52: =B52-Drift_q -> 6
A54: An alarm sends the engineering office to audit: the estimate is set to the count, the variance to 0, the sum restarts, and once the drift has begun the law's mean is re-estimated as the drift. The innovations after an audit are the engine's.

Sheet Drift
A1: A tighter labor market: the drift and the monitor (Theorem 15.3; Worked Example 15.1, Step 5; Table 15.3; Figure 15.3)
A2: From the start of quarter 8 each quarter loses an extra half point; 100,000 paths (seed 1507). Costs, shares below the floor and the detection delays are the engine's; the costs above the count and the delays' percentiles (numpy's linear interpolation, from the histogram) are formulas.
A4: Design, under the drift | B4: Cost from 58 (engine) | C4: Above the count | D4: Below the floor (engine)
A5: Count, the law re-estimated at once (target 56.25) | B5: 301.99187 | C5: =B5-$B$5 -> 0 | D5: 0.14067955
A6: Twin, law never questioned | B6: 358.4647 | C6: =B6-$B$5 -> 56.472827 | D6: 0.79870602
A7: Twin with the monitor | B7: 320.16905 | C7: =B7-$B$5 -> 18.177173 | D7: 0.14431484
A8: Twin told of the drift | B8: 312.28461 | C8: =B8-$B$5 -> 10.292736 | D8: 0.1455323
A10: Without a drift: the monitored twin (engine) | B10: 241.6379 | C10: 241.638
A11: the twin without a monitor (engine) | B11: 241.83697 | C11: 241.837
A12: what the audits save | B12: =B11-B10 -> 0.19907555
A13: audits in 120 years (engine) | B13: 4.60568 | C13: 4.6
A15: Delay (quarters after the drift began) | B15: Paths (engine) | C15: Cumulative | F15: Delays | G15: Value | H15: Rank h = (n - 1) p | I15: Lower rank | J15: Value at the lower rank | K15: At the next rank | L15: Percentile
A16: 0 | B16: 1807 | C16: =SUM($B$16:B16) -> 1807 | F16: Paths that detect the drift | G16: =SUM($B$16:$B$104) -> 100000
A17: 1 | B17: 0 | C17: =SUM($B$16:B17) -> 1807 | F17: share of the paths: every path | G17: =G16/Paths_fresh -> 1
A18: 2 | B18: 3512 | C18: =SUM($B$16:B18) -> 5319 | F18: Mean delay (quarters): 12.3 | G18: =SUMPRODUCT($A$16:$A$104,$B$16:$B$104)/G16 -> 12.26814
A19: 3 | B19: 0 | C19: =SUM($B$16:B19) -> 5319 | F19: 10th percentile | G19: 0.1 | H19: =($G$16-1)*G19 -> 9999.9 | I19: =INT(H19) -> 9999 | J19: =INDEX($A$16:$A$104,COUNTIF($C$16:$C$104,"<="&I19)+1) -> 4 | K19: =INDEX($A$16:$A$104,COUNTIF($C$16:$C$104,"<="&(I19+1))+1) -> 4 | L19: =J19+(H19-I19)*(K19-J19) -> 4
A20: 4 | B20: 6783 | C20: =SUM($B$16:B20) -> 12102 | F20: Median | G20: 0.5 | H20: =($G$16-1)*G20 -> 49999.5 | I20: =INT(H20) -> 49999 | J20: =INDEX($A$16:$A$104,COUNTIF($C$16:$C$104,"<="&I20)+1) -> 12 | K20: =INDEX($A$16:$A$104,COUNTIF($C$16:$C$104,"<="&(I20+1))+1) -> 12 | L20: =J20+(H20-I20)*(K20-J20) -> 12
A21: 5 | B21: 0 | C21: =SUM($B$16:B21) -> 12102 | F21: 90th percentile | G21: 0.9 | H21: =($G$16-1)*G21 -> 89999.1 | I21: =INT(H21) -> 89999 | J21: =INDEX($A$16:$A$104,COUNTIF($C$16:$C$104,"<="&I21)+1) -> 22 | K21: =INDEX($A$16:$A$104,COUNTIF($C$16:$C$104,"<="&(I21+1))+1) -> 22 | L21: =J21+(H21-I21)*(K21-J21) -> 22
A22: 6 | B22: 10508 | C22: =SUM($B$16:B22) -> 22610
A23: 7 | B23: 0 | C23: =SUM($B$16:B23) -> 22610
A24: 8 | B24: 12802 | C24: =SUM($B$16:B24) -> 35412 | F24: Quarter | G24: Monitors alarmed, drift (engine) | H24: Without a drift (engine)
A25: 9 | B25: 0 | C25: =SUM($B$16:B25) -> 35412 | F25: 0 | G25: 0 | H25: 0 | J25: Half the monitors have alarmed by quarter | K25: =INDEX(F25:F65,COUNTIF(G25:G65,"<0.5")+1) -> 20
A26: 10 | B26: 13332 | C26: =SUM($B$16:B26) -> 48744 | F26: 1 | G26: 0 | H26: 0 | J26: quarters after the drift began | K26: =K25-Drift_q -> 12 | L26: Figure 15.3(a): 12
A27: 11 | B27: 0 | C27: =SUM($B$16:B27) -> 48744 | F27: 2 | G27: 0 | H27: 0.00283 | J27: False alarms within 40 quarters, without a drift | K27: =H65 -> 0.30823
A28: 12 | B28: 12215 | C28: =SUM($B$16:B28) -> 60959 | F28: 3 | G28: 0 | H28: 0.00283
A29: 13 | B29: 0 | C29: =SUM($B$16:B29) -> 60959 | F29: 4 | G29: 0 | H29: 0.01392
A30: 14 | B30: 10149 | C30: =SUM($B$16:B30) -> 71108 | F30: 5 | G30: 0 | H30: 0.01392
A31: 15 | B31: 0 | C31: =SUM($B$16:B31) -> 71108 | F31: 6 | G31: 0 | H31: 0.03008
A32: 16 | B32: 7912 | C32: =SUM($B$16:B32) -> 79020 | F32: 7 | G32: 0 | H32: 0.03008
A33: 17 | B33: 0 | C33: =SUM($B$16:B33) -> 79020 | F33: 8 | G33: 0.01807 | H33: 0.04791
A34: 18 | B34: 6002 | C34: =SUM($B$16:B34) -> 85022 | F34: 9 | G34: 0.01807 | H34: 0.04791
A35: 19 | B35: 0 | C35: =SUM($B$16:B35) -> 85022 | F35: 10 | G35: 0.05319 | H35: 0.06646
A36: 20 | B36: 4301 | C36: =SUM($B$16:B36) -> 89323 | F36: 11 | G36: 0.05319 | H36: 0.06646
A37: 21 | B37: 0 | C37: =SUM($B$16:B37) -> 89323 | F37: 12 | G37: 0.12102 | H37: 0.08538
A38: 22 | B38: 3171 | C38: =SUM($B$16:B38) -> 92494 | F38: 13 | G38: 0.12102 | H38: 0.08538
A39: 23 | B39: 0 | C39: =SUM($B$16:B39) -> 92494 | F39: 14 | G39: 0.2261 | H39: 0.10297
... A65: 49 | B65: 0 | C65: =SUM($B$16:B65) -> 99946 | F65: 40 | G65: 0.9878 | H65: 0.30823
A66: 50 | B66: 18 | C66: =SUM($B$16:B66) -> 99964
A67: 51 | B67: 0 | C67: =SUM($B$16:B67) -> 99964
A68: 52 | B68: 12 | C68: =SUM($B$16:B68) -> 99976
A69: 53 | B69: 0 | C69: =SUM($B$16:B69) -> 99976
A70: 54 | B70: 5 | C70: =SUM($B$16:B70) -> 99981
A71: 55 | B71: 0 | C71: =SUM($B$16:B71) -> 99981
A72: 56 | B72: 3 | C72: =SUM($B$16:B72) -> 99984
A73: 57 | B73: 0 | C73: =SUM($B$16:B73) -> 99984
A74: 58 | B74: 9 | C74: =SUM($B$16:B74) -> 99993
A75: 59 | B75: 0 | C75: =SUM($B$16:B75) -> 99993
A76: 60 | B76: 2 | C76: =SUM($B$16:B76) -> 99995
A77: 61 | B77: 0 | C77: =SUM($B$16:B77) -> 99995
... A104: 88 | B104: 1 | C104: =SUM($B$16:B104) -> 100000

Sheet Envelope
A1: Set the envelope (Definition 15.3; Proposition 15.3; Worked Example 15.1, Step 6; AXIOM Lab 2.15, step 5)
A2: The twin hires alone inside Chapter 14's guardrail, never planning below 55 unless hiring at the cap, and escalates on its monitor's alarm. A trigger on its uncertainty would fire on a calendar: the variances do not depend on the readings.
A4: Design (Table 15.3) | B4: Target | C4: Plans at least 55 on its estimate unless at the cap (1 = yes)
A5: Count (Chapter 7) | B5: =Decide!R5 -> 55.75 | C5: =IF(B5>=Floor_c,1,0) -> 1
A6: No readings after the audit | B6: =Decide!R11 -> 57.8 | C6: =IF(B6>=Floor_c,1,0) -> 1
A7: Survey read as exact, Chapter 7's target | B7: =Decide!C23 -> 55.75 | C7: =IF(B7>=Floor_c,1,0) -> 1
A8: whole error guarded | B8: =Decide!C24 -> 60.75 | C8: =IF(B8>=Floor_c,1,0) -> 1
A9: best target | B9: =Decide!R7 -> 57.35 | C9: =IF(B9>=Floor_c,1,0) -> 1
A10: Twin, Chapter 7's target | B10: =Decide!C22 -> 55.75 | C10: =IF(B10>=Floor_c,1,0) -> 1
A11: Twin, best target | B11: =Decide!R6 -> 56.7 | C11: =IF(B11>=Floor_c,1,0) -> 1
A12: Twin, quarterly | B12: =Decide!R8 -> 56.5 | C12: =IF(B12>=Floor_c,1,0) -> 1
A13: Twin, twice as sharp | B13: =Decide!R9 -> 56.4 | C13: =IF(B13>=Floor_c,1,0) -> 1
A14: Twin, both | B14: =Decide!R10 -> 56.2 | C14: =IF(B14>=Floor_c,1,0) -> 1
A16: Targets that could break the guardrail | B16: =COUNTIF(C5:C14,0) -> 0 | C16: Planned level on the estimate = max(target, 0.975 c-hat) unless the cap binds
A17: Breaches on 100,000 fresh paths x 480 quarters, all designs (engine) | B17: 0
A19: Quarter | B19: Survey (1 = yes) | C19: The twin's error just before (sd) | D19: Trigger fires (1 = yes)
F20: A trigger on uncertainty: escalate when the error exceeds (points) | G20: 1.5 | H20: Try your own
A21: 0 | B21: =Sync!B6 -> 0 | C21: =SQRT(Sync!C6) -> 0 | D21: =IF(AND(B21=1,C21>$G$20),1,0) -> 0 | F21: It first fires at quarter | G21: =_xlfn.MINIFS(A21:A61,D21:D61,1) -> 8
A22: 1 | B22: =Sync!B7 -> 0 | C22: =SQRT(Sync!C7) -> 0.67082039 | D22: =IF(AND(B22=1,C22>$G$20),1,0) -> 0 | F22: and at every survey after it (1 = yes) | G22: =IF(COUNTIFS(A21:A61,">="&G21,B21:B61,1)=COUNTIFS(A21:A61,">="&G21,D21:D61,1),1,0) -> 1 | H22: A calendar, whatever the surveys say
A23: 2 | B23: =Sync!B8 -> 1 | C23: =SQRT(Sync!C8) -> 0.93689981 | D23: =IF(AND(B23=1,C23>$G$20),1,0) -> 0
A24: 3 | B24: =Sync!B9 -> 0 | C24: =SQRT(Sync!C9) -> 1.0870511 | D24: =IF(AND(B24=1,C24>$G$20),1,0) -> 0 | F24: Proposition 15.3(i): the rule h = T - a c-hat, on the true state: mode a - a | G24: =Alpha_keep-Alpha_keep -> 0 | H24: It restores the target in a quarter, inside the limits
A25: 4 | B25: =Sync!B10 -> 1 | C25: =SQRT(Sync!C10) -> 1.2543263 | D25: =IF(AND(B25=1,C25>$G$20),1,0) -> 0 | F25: the filter's error over a half year: mode (1 - K) a^2 | G25: =(1-Sync!AJ6)*Alpha_keep^2 -> 0.6802445
A26: 5 | B26: =Sync!B11 -> 0 | C26: =SQRT(Sync!C11) -> 1.2825225 | D26: =IF(AND(B26=1,C26>$G$20),1,0) -> 0 | F26: the loop is stable (1 = yes) | G26: =IF(AND(ABS(G24)<1,ABS(G25)<1),1,0) -> 1
A27: 6 | B27: =Sync!B12 -> 1 | C27: =SQRT(Sync!C12) -> 1.4190309 | D27: =IF(AND(B27=1,C27>$G$20),1,0) -> 0
A28: 7 | B28: =Sync!B13 -> 0 | C28: =SQRT(Sync!C13) -> 1.3775976 | D28: =IF(AND(B28=1,C28>$G$20),1,0) -> 0 | F28: Step 6: the twin's target on its design paths | G28: =Decide!S6 -> 241.85194 | H28: $241.85 million
A29: 8 | B29: =Sync!B14 -> 1 | C29: =SQRT(Sync!C14) -> 1.5013569 | D29: =IF(AND(B29=1,C29>$G$20),1,0) -> 1 | F29: on the fresh paths | G29: =Decide!D16 -> 241.94431 | H29: $241.94 million
A30: 9 | B30: =Sync!B15 -> 0 | C30: =SQRT(Sync!C15) -> 1.4229607 | D30: =IF(AND(B30=1,C30>$G$20),1,0) -> 0 | F30: the difference in standard errors | G30: =Decide!B32 -> 0.90841493 | H30: Within the simulation's error
A31: 10 | B31: =Sync!B16 -> 1 | C31: =SQRT(Sync!C16) -> 1.5410522 | D31: =IF(AND(B31=1,C31>$G$20),1,0) -> 1
A32: 11 | B32: =Sync!B17 -> 0 | C32: =SQRT(Sync!C17) -> 1.4442855 | D32: =IF(AND(B32=1,C32>$G$20),1,0) -> 0
A33: 12 | B33: =Sync!B18 -> 1 | C33: =SQRT(Sync!C18) -> 1.5597968 | D33: =IF(AND(B33=1,C33>$G$20),1,0) -> 1
A34: 13 | B34: =Sync!B19 -> 0 | C34: =SQRT(Sync!C19) -> 1.4542288 | D34: =IF(AND(B34=1,C34>$G$20),1,0) -> 0
A35: 14 | B35: =Sync!B20 -> 1 | C35: =SQRT(Sync!C20) -> 1.5685548 | D35: =IF(AND(B35=1,C35>$G$20),1,0) -> 1
A36: 15 | B36: =Sync!B21 -> 0 | C36: =SQRT(Sync!C21) -> 1.4588465 | D36: =IF(AND(B36=1,C36>$G$20),1,0) -> 0
A37: 16 | B37: =Sync!B22 -> 1 | C37: =SQRT(Sync!C22) -> 1.5726257 | D37: =IF(AND(B37=1,C37>$G$20),1,0) -> 1
A38: 17 | B38: =Sync!B23 -> 0 | C38: =SQRT(Sync!C23) -> 1.4609869 | D38: =IF(AND(B38=1,C38>$G$20),1,0) -> 0
A39: 18 | B39: =Sync!B24 -> 1 | C39: =SQRT(Sync!C24) -> 1.5745135 | D39: =IF(AND(B39=1,C39>$G$20),1,0) -> 1
A40: 19 | B40: =Sync!B25 -> 0 | C40: =SQRT(Sync!C25) -> 1.4619781 | D40: =IF(AND(B40=1,C40>$G$20),1,0) -> 0
A41: 20 | B41: =Sync!B26 -> 1 | C41: =SQRT(Sync!C26) -> 1.5753879 | D41: =IF(AND(B41=1,C41>$G$20),1,0) -> 1
A42: 21 | B42: =Sync!B27 -> 0 | C42: =SQRT(Sync!C27) -> 1.462437 | D42: =IF(AND(B42=1,C42>$G$20),1,0) -> 0
... A61: 40 | B61: =Sync!B46 -> 1 | C61: =SQRT(Sync!C46) -> 1.576141 | D61: =IF(AND(B61=1,C61>$G$20),1,0) -> 1

Sheet Table15_3
A1: Table 15.3: designs for knowing capability, from an audited 58 (Worked Example 15.1)
A2: Target: planned capability (points); error: the estimate's standard deviation just after and just before a survey; cost above the count: present value at 10 percent, $ million, on 100,000 fresh paths; below floor: long-run share of quarters below 55. All cells link to the sheets that compute them.
A4: Design | B4: Survey | C4: Target | D4: Error (sd) | E4: Cost above the count | F4: Below floor (%)
A5: Count (Chapter 7) | B5: -- | C5: =Decide!R5 -> 55.75 | D5: 0 | E5: =0 -> 0 | F5: =100*Decide!G15 -> 6.0240023
A6: No readings after the audit | B6: none | C6: =Decide!R11 -> 57.8 | D6: =TEXT(Sync!AG11,"0.00") -> 3.02 | E6: =Decide!F21 -> 25.433345 | F6: =100*Decide!G21 -> 17.617077
A7: Survey read as exact | B7: twice a year | C7: =Decide!C23 -> 55.75 | D7: =TEXT(Sync!AG10,"0.00")&"–"&TEXT(Sync!AI10,"0.00") -> 2.50–2.53 | E7: =Decide!F23 -> 27.508661 | F7: =100*Decide!G23 -> 38.606593
A8: whole error guarded | B8: twice a year | C8: =Decide!C24 -> 60.75 | D8: =TEXT(Sync!AG10,"0.00")&"–"&TEXT(Sync!AI10,"0.00") -> 2.50–2.53 | E8: =Decide!F24 -> 34.396076 | F8: =100*Decide!G24 -> 0.21979091
A9: best target | B9: twice a year | C9: =Decide!R7 -> 57.35 | D9: =TEXT(Sync!AG10,"0.00")&"–"&TEXT(Sync!AI10,"0.00") -> 2.50–2.53 | E9: =Decide!F17 -> 15.949739 | F9: =100*Decide!G17 -> 13.253332
A10: Twin, Chapter 7's target | B10: twice a year | C10: =Decide!C22 -> 55.75 | D10: =TEXT(Sync!AG6,"0.00")&"–"&TEXT(Sync!AI6,"0.00") -> 1.33–1.58 | E10: =Decide!F22 -> 16.313442 | F10: =100*Decide!G22 -> 31.32032
A11: Twin, best target | B11: twice a year | C11: =Decide!R6 -> 56.7 | D11: =TEXT(Sync!AG6,"0.00")&"–"&TEXT(Sync!AI6,"0.00") -> 1.33–1.58 | E11: =Decide!F16 -> 11.100596 | F11: =100*Decide!G16 -> 13.374932
A12: Twin | B12: quarterly | C12: =Decide!R8 -> 56.5 | D12: =TEXT(Sync!AG7,"0.00")&"–"&TEXT(Sync!AI7,"0.00") -> 1.17–1.32 | E12: =Decide!F18 -> 8.6337998 | F12: =100*Decide!G18 -> 12.964216
A13: Twin | B13: twice as sharp | C13: =Decide!R9 -> 56.4 | D13: =TEXT(Sync!AG8,"0.00")&"–"&TEXT(Sync!AI8,"0.00") -> 0.89–1.26 | E13: =Decide!F19 -> 7.0053579 | F13: =100*Decide!G19 -> 12.090391
A14: Twin | B14: both | C14: =Decide!R10 -> 56.2 | D14: =TEXT(Sync!AG9,"0.00")&"–"&TEXT(Sync!AI9,"0.00") -> 0.79–1.02 | E14: =Decide!F20 -> 4.9212146 | F14: =100*Decide!G20 -> 12.220405
A15: An extra half point lost each quarter from quarter 8 (cost above the count with the drift):
A16: Twin, law never questioned | B16: twice a year | C16: =Decide!R6 -> 56.7 | D16: -- | E16: =Drift!C6 -> 56.472827 | F16: =100*Drift!D6 -> 79.870602
A17: Twin with monitor | B17: twice a year | C17: =Decide!R6 -> 56.7 | D17: -- | E17: =Drift!C7 -> 18.177173 | F17: =100*Drift!D7 -> 14.431484
A18: Twin told of the drift | B18: twice a year | C18: =Decide!R6 -> 56.7 | D18: -- | E18: =Drift!C8 -> 10.292736 | F18: =100*Drift!D8 -> 14.55323

Sheet Reference_Values
A1: Checkpoint | B1: Engine value | C1: Meaning (where in the book)
A2: A swing's variance q | B2: 0.45 | C2: 0.45
A3: A swing's standard deviation | B3: 0.67082039 | C3: 0.67 (Section 15.2)
A4: No readings: the error's limit | B4: 3.0189276 | C4: 3.019
A5: Twin: error just after a survey (closed form) | B5: 1.3332852 | C5: 1.333
A6: Twin: error a quarter later | B6: 1.4628322 | C6: 1.463
A7: Twin: error just before the next survey | B7: 1.5761414 | C7: 1.576
A8: Twin: the gain | B8: 0.28442393 | C8: 0.284
A9: Twin: the recursion from the audit reaches the fixed point (quarter 60) | B9: 1.3332852 | C9: Theorem 15.1(iii)
A10: Quarterly survey: error just after | B10: 1.1690705 | C10: 1.169
A11: Quarterly survey: error just before | B11: 1.3225898 | C11: 1.323
A12: Quarterly survey: the gain | B12: 0.21867615 | C12: 0.219
A13: Twice as sharp: error just after | B13: 0.88772068 | C13: 0.888
... A20: Program (seed 1503): present value of 25 quarters | B20: 107.4387 | C20: Figure 15.1(a)
A21: Program (seed 1503): the twin's estimate at quarter 24 | B21: 55.301895
A22: Program (seed 1503): its error at quarter 24 | B22: 1.3331876
A23: Best target: count (Chapter 7) | B23: 55.75 | C23: 55.75
A24: Inside its window: count (Chapter 7) | B24: 1 | C24: Interior
A25: Best target: twin, survey twice a year | B25: 56.7 | C25: 56.70
A26: Inside its window: twin, survey twice a year | B26: 1 | C26: Interior
A27: Best target: survey read as exact | B27: 57.35 | C27: 57.35
A28: Inside its window: survey read as exact | B28: 1 | C28: Interior
A29: Best target: twin, quarterly survey | B29: 56.5 | C29: 56.50
A30: Inside its window: twin, quarterly survey | B30: 1 | C30: Interior
A31: Best target: twin, twice as sharp | B31: 56.4 | C31: 56.40
A32: Inside its window: twin, twice as sharp | B32: 1 | C32: Interior
A33: Best target: twin, both | B33: 56.2 | C33: 56.20
A34: Inside its window: twin, both | B34: 1 | C34: Interior
... A96: Table 15.3: law never questioned | B96: 56.472827 | C96: 56.47

Sheet Checks
A1: Checkpoint | B1: Workbook formula value | C1: Engine value | D1: |diff| | E1: Tolerance | F1: Status
A2: A swing's variance q | B2: =Declarations!B38 -> 0.45 | C2: =Reference_Values!B2 -> 0.45 | D2: =ABS(B2-C2) -> 0 | E2: 1e-12 | F2: =IF(D2<=E2,"PASS","FAIL") -> PASS
A3: A swing's standard deviation | B3: =Declarations!B39 -> 0.67082039 | C3: =Reference_Values!B3 -> 0.67082039 | D3: =ABS(B3-C3) -> 0 | E3: 1e-12 | F3: =IF(D3<=E3,"PASS","FAIL") -> PASS
A4: No readings: the error's limit | B4: =Sync!AG11 -> 3.0189276 | C4: =Reference_Values!B4 -> 3.0189276 | D4: =ABS(B4-C4) -> 0 | E4: 1e-12 | F4: =IF(D4<=E4,"PASS","FAIL") -> PASS
A5: Twin: error just after a survey (closed form) | B5: =Sync!AG6 -> 1.3332852 | C5: =Reference_Values!B5 -> 1.3332852 | D5: =ABS(B5-C5) -> 0 | E5: 1e-12 | F5: =IF(D5<=E5,"PASS","FAIL") -> PASS
A6: Twin: error a quarter later | B6: =Sync!AH6 -> 1.4628322 | C6: =Reference_Values!B6 -> 1.4628322 | D6: =ABS(B6-C6) -> 0 | E6: 1e-12 | F6: =IF(D6<=E6,"PASS","FAIL") -> PASS
A7: Twin: error just before the next survey | B7: =Sync!AI6 -> 1.5761414 | C7: =Reference_Values!B7 -> 1.5761414 | D7: =ABS(B7-C7) -> 0 | E7: 1e-12 | F7: =IF(D7<=E7,"PASS","FAIL") -> PASS
A8: Twin: the gain | B8: =Sync!AJ6 -> 0.28442393 | C8: =Reference_Values!B8 -> 0.28442393 | D8: =ABS(B8-C8) -> 0 | E8: 1e-12 | F8: =IF(D8<=E8,"PASS","FAIL") -> PASS
A9: Twin: the recursion from the audit reaches the fixed point (quarter 60) | B9: =Sync!AK6 -> 1.3332852 | C9: =Reference_Values!B9 -> 1.3332852 | D9: =ABS(B9-C9) -> 9.2428731e-11 | E9: 1e-09 | F9: =IF(D9<=E9,"PASS","FAIL") -> PASS
A10: Quarterly survey: error just after | B10: =Sync!AG7 -> 1.1690705 | C10: =Reference_Values!B10 -> 1.1690705 | D10: =ABS(B10-C10) -> 9.547918e-15 | E10: 1e-12 | F10: =IF(D10<=E10,"PASS","FAIL") -> PASS
A11: Quarterly survey: error just before | B11: =Sync!AI7 -> 1.3225898 | C11: =Reference_Values!B11 -> 1.3225898 | D11: =ABS(B11-C11) -> 8.2156504e-15 | E11: 1e-12 | F11: =IF(D11<=E11,"PASS","FAIL") -> PASS
A12: Quarterly survey: the gain | B12: =Sync!AJ7 -> 0.21867615 | C12: =Reference_Values!B12 -> 0.21867615 | D12: =ABS(B12-C12) -> 2.1371793e-15 | E12: 1e-12 | F12: =IF(D12<=E12,"PASS","FAIL") -> PASS
A13: Twice as sharp: error just after | B13: =Sync!AG8 -> 0.88772068 | C13: =Reference_Values!B13 -> 0.88772068 | D13: =ABS(B13-C13) -> 6.3282712e-15 | E13: 1e-12 | F13: =IF(D13<=E13,"PASS","FAIL") -> PASS
A14: Twice as sharp: error just before | B14: =Sync!AI8 -> 1.2609245 | C14: =Reference_Values!B14 -> 1.2609245 | D14: =ABS(B14-C14) -> 0 | E14: 1e-12 | F14: =IF(D14<=E14,"PASS","FAIL") -> PASS
A15: Both: error just after | B15: =Sync!AG9 -> 0.79142342 | C15: =Reference_Values!B15 -> 0.79142342 | D15: =ABS(B15-C15) -> 3.7747583e-15 | E15: 1e-12 | F15: =IF(D15<=E15,"PASS","FAIL") -> PASS
A16: Both: error just before | B16: =Sync!AI9 -> 1.0224602 | C16: =Reference_Values!B16 -> 1.0224602 | D16: =ABS(B16-C16) -> 0 | E16: 1e-12 | F16: =IF(D16<=E16,"PASS","FAIL") -> PASS
A17: Survey read as exact: error just after | B17: =Sync!AG10 -> 2.5 | C17: =Reference_Values!B17 -> 2.5 | D17: =ABS(B17-C17) -> 0 | E17: 1e-12 | F17: =IF(D17<=E17,"PASS","FAIL") -> PASS
A18: Survey read as exact: error just before | B18: =Sync!AI10 -> 2.5281231 | C18: =Reference_Values!B18 -> 2.5281231 | D18: =ABS(B18-C18) -> 0 | E18: 1e-12 | F18: =IF(D18<=E18,"PASS","FAIL") -> PASS
A19: Proposition 15.1(i): precisions add | B19: =Sync!AB19 -> 1 | C19: =Reference_Values!B19 -> 1 | D19: =ABS(B19-C19) -> 0 | E19: 0 | F19: =IF(D19<=E19,"PASS","FAIL") -> PASS
A20: Program (seed 1503): present value of 25 quarters | B20: =Program!V6 -> 107.4387 | C20: =Reference_Values!B20 -> 107.4387 | D20: =ABS(B20-C20) -> 0 | E20: 1e-09 | F20: =IF(D20<=E20,"PASS","FAIL") -> PASS
A21: Program (seed 1503): the twin's estimate at quarter 24 | B21: =Program!V7 -> 55.301895 | C21: =Reference_Values!B21 -> 55.301895 | D21: =ABS(B21-C21) -> 0 | E21: 1e-09 | F21: =IF(D21<=E21,"PASS","FAIL") -> PASS
A22: Program (seed 1503): its error at quarter 24 | B22: =Program!V8 -> 1.3331876 | C22: =Reference_Values!B22 -> 1.3331876 | D22: =ABS(B22-C22) -> 0 | E22: 1e-12 | F22: =IF(D22<=E22,"PASS","FAIL") -> PASS
A23: Best target: count (Chapter 7) | B23: =Decide!R5 -> 55.75 | C23: =Reference_Values!B23 -> 55.75 | D23: =ABS(B23-C23) -> 0 | E23: 1e-09 | F23: =IF(D23<=E23,"PASS","FAIL") -> PASS
A24: Inside its window: count (Chapter 7) | B24: =Decide!U5 -> 1 | C24: =Reference_Values!B24 -> 1 | D24: =ABS(B24-C24) -> 0 | E24: 0 | F24: =IF(D24<=E24,"PASS","FAIL") -> PASS
A25: Best target: twin, survey twice a year | B25: =Decide!R6 -> 56.7 | C25: =Reference_Values!B25 -> 56.7 | D25: =ABS(B25-C25) -> 0 | E25: 1e-09 | F25: =IF(D25<=E25,"PASS","FAIL") -> PASS
A26: Inside its window: twin, survey twice a year | B26: =Decide!U6 -> 1 | C26: =Reference_Values!B26 -> 1 | D26: =ABS(B26-C26) -> 0 | E26: 0 | F26: =IF(D26<=E26,"PASS","FAIL") -> PASS
A27: Best target: survey read as exact | B27: =Decide!R7 -> 57.35 | C27: =Reference_Values!B27 -> 57.35 | D27: =ABS(B27-C27) -> 0 | E27: 1e-09 | F27: =IF(D27<=E27,"PASS","FAIL") -> PASS
A28: Inside its window: survey read as exact | B28: =Decide!U7 -> 1 | C28: =Reference_Values!B28 -> 1 | D28: =ABS(B28-C28) -> 0 | E28: 0 | F28: =IF(D28<=E28,"PASS","FAIL") -> PASS
A29: Best target: twin, quarterly survey | B29: =Decide!R8 -> 56.5 | C29: =Reference_Values!B29 -> 56.5 | D29: =ABS(B29-C29) -> 0 | E29: 1e-09 | F29: =IF(D29<=E29,"PASS","FAIL") -> PASS
A30: Inside its window: twin, quarterly survey | B30: =Decide!U8 -> 1 | C30: =Reference_Values!B30 -> 1 | D30: =ABS(B30-C30) -> 0 | E30: 0 | F30: =IF(D30<=E30,"PASS","FAIL") -> PASS
A31: Best target: twin, twice as sharp | B31: =Decide!R9 -> 56.4 | C31: =Reference_Values!B31 -> 56.4 | D31: =ABS(B31-C31) -> 0 | E31: 1e-09 | F31: =IF(D31<=E31,"PASS","FAIL") -> PASS
A32: Inside its window: twin, twice as sharp | B32: =Decide!U9 -> 1 | C32: =Reference_Values!B32 -> 1 | D32: =ABS(B32-C32) -> 0 | E32: 0 | F32: =IF(D32<=E32,"PASS","FAIL") -> PASS
A33: Best target: twin, both | B33: =Decide!R10 -> 56.2 | C33: =Reference_Values!B33 -> 56.2 | D33: =ABS(B33-C33) -> 0 | E33: 1e-09 | F33: =IF(D33<=E33,"PASS","FAIL") -> PASS
A34: Inside its window: twin, both | B34: =Decide!U10 -> 1 | C34: =Reference_Values!B34 -> 1 | D34: =ABS(B34-C34) -> 0 | E34: 0 | F34: =IF(D34<=E34,"PASS","FAIL") -> PASS
A35: Best target: no readings after the audit | B35: =Decide!R11 -> 57.8 | C35: =Reference_Values!B35 -> 57.8 | D35: =ABS(B35-C35) -> 0 | E35: 1e-09 | F35: =IF(D35<=E35,"PASS","FAIL") -> PASS
A36: Inside its window: no readings after the audit | B36: =Decide!U11 -> 1 | C36: =Reference_Values!B36 -> 1 | D36: =ABS(B36-C36) -> 0 | E36: 0 | F36: =IF(D36<=E36,"PASS","FAIL") -> PASS
A37: Count: design-path cost | B37: =Decide!S5 -> 230.74711 | C37: =Reference_Values!B37 -> 230.74711 | D37: =ABS(B37-C37) -> 0 | E37: 1e-09 | F37: =IF(D37<=E37,"PASS","FAIL") -> PASS
A38: Twin: design-path cost | B38: =Decide!S6 -> 241.85194 | C38: =Reference_Values!B38 -> 241.85194 | D38: =ABS(B38-C38) -> 0 | E38: 1e-09 | F38: =IF(D38<=E38,"PASS","FAIL") -> PASS
A39: Twin: margin | B39: =Decide!T6 -> 1.7 | C39: =Reference_Values!B39 -> 1.7 | D39: =ABS(B39-C39) -> 0 | E39: 1e-09 | F39: =IF(D39<=E39,"PASS","FAIL") -> PASS
A40: Twin: above the count | B40: =Decide!F16 -> 11.100596 | C40: =Reference_Values!B40 -> 11.100596 | D40: =ABS(B40-C40) -> 0 | E40: 1e-09 | F40: =IF(D40<=E40,"PASS","FAIL") -> PASS
A41: Survey read as exact: above the count | B41: =Decide!F17 -> 15.949739 | C41: =Reference_Values!B41 -> 15.949739 | D41: =ABS(B41-C41) -> 0 | E41: 1e-09 | F41: =IF(D41<=E41,"PASS","FAIL") -> PASS
A42: Quarterly survey: above the count | B42: =Decide!F18 -> 8.6337998 | C42: =Reference_Values!B42 -> 8.6337998 | D42: =ABS(B42-C42) -> 0 | E42: 1e-09 | F42: =IF(D42<=E42,"PASS","FAIL") -> PASS
A43: Twice as sharp: above the count | B43: =Decide!F19 -> 7.0053579 | C43: =Reference_Values!B43 -> 7.0053579 | D43: =ABS(B43-C43) -> 0 | E43: 1e-09 | F43: =IF(D43<=E43,"PASS","FAIL") -> PASS
A44: Both: above the count | B44: =Decide!F20 -> 4.9212146 | C44: =Reference_Values!B44 -> 4.9212146 | D44: =ABS(B44-C44) -> 2.8421709e-14 | E44: 1e-09 | F44: =IF(D44<=E44,"PASS","FAIL") -> PASS
A45: No readings: above the count | B45: =Decide!F21 -> 25.433345 | C45: =Reference_Values!B45 -> 25.433345 | D45: =ABS(B45-C45) -> 0 | E45: 1e-09 | F45: =IF(D45<=E45,"PASS","FAIL") -> PASS
A46: Twin at Chapter 7's 55.75: above the count | B46: =Decide!F22 -> 16.313442 | C46: =Reference_Values!B46 -> 16.313442 | D46: =ABS(B46-C46) -> 0 | E46: 1e-09 | F46: =IF(D46<=E46,"PASS","FAIL") -> PASS
A47: Survey as exact at 55.75: above the count | B47: =Decide!F23 -> 27.508661 | C47: =Reference_Values!B47 -> 27.508661 | D47: =ABS(B47-C47) -> 0 | E47: 1e-09 | F47: =IF(D47<=E47,"PASS","FAIL") -> PASS
A48: Survey as exact at 60.75: above the count | B48: =Decide!F24 -> 34.396076 | C48: =Reference_Values!B48 -> 34.396076 | D48: =ABS(B48-C48) -> 0 | E48: 1e-09 | F48: =IF(D48<=E48,"PASS","FAIL") -> PASS
A49: The twin costs less than the survey read as exact | B49: =Decide!B28 -> 4.8491427 | C49: =Reference_Values!B49 -> 4.8491427 | D49: =ABS(B49-C49) -> 5.6843419e-14 | E49: 1e-09 | F49: =IF(D49<=E49,"PASS","FAIL") -> PASS
A50: Theorem 15.2(i): the costs in order | B50: =Decide!B27 -> 1 | C50: =Reference_Values!B50 -> 1 | D50: =ABS(B50-C50) -> 0 | E50: 0 | F50: =IF(D50<=E50,"PASS","FAIL") -> PASS
A51: Step 6: design-path and fresh costs, in standard errors | B51: =Decide!B32 -> 0.90841493 | C51: =Reference_Values!B51 -> 0.90841493 | D51: =ABS(B51-C51) -> 5.5899729e-13 | E51: 1e-09 | F51: =IF(D51<=E51,"PASS","FAIL") -> PASS
A52: Chapter 7's critical ratio k/b | B52: =Decide!B38 -> 0.12278422 | C52: =Reference_Values!B52 -> 0.12278422 | D52: =ABS(B52-C52) -> 0 | E52: 1e-12 | F52: =IF(D52<=E52,"PASS","FAIL") -> PASS
A53: Theorem 15.2(iii): the count's margin, the swing's quantile | B53: =Decide!B48 -> 0.75 | C53: =Reference_Values!B53 -> 0.75 | D53: =ABS(B53-C53) -> 0 | E53: 0 | F53: =IF(D53<=E53,"PASS","FAIL") -> PASS
A54: Theorem 15.2(iii): z | B54: =Decide!B49 -> 1.1611806 | C54: =Reference_Values!B54 -> 1.1611806 | D54: =ABS(B54-C54) -> 0 | E54: 1e-06 | F54: =IF(D54<=E54,"PASS","FAIL") -> PASS
A55: Theorem 15.2(iii): the twin's normal margin at a survey | B55: =Decide!D53 -> 1.6986125 | C55: =Reference_Values!B55 -> 1.6986125 | D55: =ABS(B55-C55) -> 0 | E55: 1e-06 | F55: =IF(D55<=E55,"PASS","FAIL") -> PASS
A56: The count is worth a year against the twin | B56: =Readings!B5 -> 1.0454945 | C56: =Reference_Values!B56 -> 1.0454945 | D56: =ABS(B56-C56) -> 0 | E56: 1e-09 | F56: =IF(D56<=E56,"PASS","FAIL") -> PASS
A57: A quarterly survey is worth a year | B57: =Readings!B6 -> 0.23233184 | C57: =Reference_Values!B57 -> 0.23233184 | D57: =ABS(B57-C57) -> 0 | E57: 1e-09 | F57: =IF(D57<=E57,"PASS","FAIL") -> PASS
A58: A survey twice as sharp is worth a year | B58: =Readings!B7 -> 0.38570443 | C58: =Reference_Values!B58 -> 0.38570443 | D58: =ABS(B58-C58) -> 2.7200464e-15 | E58: 1e-09 | F58: =IF(D58<=E58,"PASS","FAIL") -> PASS
A59: Both are worth a year | B59: =Readings!B8 -> 0.58199664 | C59: =Reference_Values!B59 -> 0.58199664 | D59: =ABS(B59-C59) -> 5.3290705e-15 | E59: 1e-09 | F59: =IF(D59<=E59,"PASS","FAIL") -> PASS
A60: Readings study: a sharper survey never costs more, twice a year | B60: =Readings!B32 -> 1 | C60: =Reference_Values!B60 -> 1 | D60: =ABS(B60-C60) -> 0 | E60: 0 | F60: =IF(D60<=E60,"PASS","FAIL") -> PASS
A61: Readings study: a sharper survey never costs more, quarterly | B61: =Readings!B33 -> 1 | C61: =Reference_Values!B61 -> 1 | D61: =ABS(B61-C61) -> 0 | E61: 0 | F61: =IF(D61<=E61,"PASS","FAIL") -> PASS
A62: Readings study: a quarterly survey costs less at every error | B62: =Readings!B34 -> 1 | C62: =Reference_Values!B62 -> 1 | D62: =ABS(B62-C62) -> 0 | E62: 0 | F62: =IF(D62<=E62,"PASS","FAIL") -> PASS
A63: Drift: the twin's bias just after a survey | B63: =Bias!B8 -> 2.2099116 | C63: =Reference_Values!B63 -> 2.2099116 | D63: =ABS(B63-C63) -> 0 | E63: 1e-09 | F63: =IF(D63<=E63,"PASS","FAIL") -> PASS
A64: Drift: the twin's bias just before the next | B64: =Bias!B9 -> 3.0882972 | C64: =Reference_Values!B64 -> 3.0882972 | D64: =ABS(B64-C64) -> 0 | E64: 1e-09 | F64: =IF(D64<=E64,"PASS","FAIL") -> PASS
A65: Drift: the innovations' mean, in sd | B65: =Bias!B11 -> -1.0449776 | C65: =Reference_Values!B65 -> -1.0449776 | D65: =ABS(B65-C65) -> 0 | E65: 1e-09 | F65: =IF(D65<=E65,"PASS","FAIL") -> PASS
A66: Drift: the bias recursion at quarter 40 | B66: =Bias!B12 -> 2.2054286 | C66: =Reference_Values!B66 -> 2.2054286 | D66: =ABS(B66-C66) -> 0 | E66: 1e-09 | F66: =IF(D66<=E66,"PASS","FAIL") -> PASS
A67: Calibration: one false alarm in so many years at 1.5 | B67: =Monitor!D5 -> 10.610736 | C67: =Reference_Values!B67 -> 10.610736 | D67: =ABS(B67-C67) -> 0 | E67: 1e-09 | F67: =IF(D67<=E67,"PASS","FAIL") -> PASS
A68: Calibration: one false alarm in so many years at 1.75 | B68: =Monitor!D6 -> 14.41502 | C68: =Reference_Values!B68 -> 14.41502 | D68: =ABS(B68-C68) -> 0 | E68: 1e-09 | F68: =IF(D68<=E68,"PASS","FAIL") -> PASS
A69: Calibration: one false alarm in so many years at 2.0 | B69: =Monitor!D7 -> 19.41088 | C69: =Reference_Values!B69 -> 19.41088 | D69: =ABS(B69-C69) -> 0 | E69: 1e-09 | F69: =IF(D69<=E69,"PASS","FAIL") -> PASS
A70: Calibration: one false alarm in so many years at 2.25 | B70: =Monitor!D8 -> 26.00104 | C70: =Reference_Values!B70 -> 26.00104 | D70: =ABS(B70-C70) -> 0 | E70: 1e-09 | F70: =IF(D70<=E70,"PASS","FAIL") -> PASS
A71: Calibration: one false alarm in so many years at 2.5 | B71: =Monitor!D9 -> 34.471862 | C71: =Reference_Values!B71 -> 34.471862 | D71: =ABS(B71-C71) -> 0 | E71: 1e-09 | F71: =IF(D71<=E71,"PASS","FAIL") -> PASS
A72: Calibration: one false alarm in so many years at 3.0 | B72: =Monitor!D10 -> 59.804141 | C72: =Reference_Values!B72 -> 59.804141 | D72: =ABS(B72-C72) -> 0 | E72: 1e-09 | F72: =IF(D72<=E72,"PASS","FAIL") -> PASS
A73: The threshold | B73: =Monitor!B12 -> 2.25 | C73: =Reference_Values!B73 -> 2.25 | D73: =ABS(B73-C73) -> 0 | E73: 0 | F73: =IF(D73<=E73,"PASS","FAIL") -> PASS
A74: Theorem 15.3(ii): gamma = e^(H delta) | B74: =Monitor!B16 -> 9.4877358 | C74: =Reference_Values!B74 -> 9.4877358 | D74: =ABS(B74-C74) -> 0 | E74: 1e-09 | F74: =IF(D74<=E74,"PASS","FAIL") -> PASS
A75: Drift: law never questioned, above the count | B75: =Drift!C6 -> 56.472827 | C75: =Reference_Values!B75 -> 56.472827 | D75: =ABS(B75-C75) -> 0 | E75: 1e-09 | F75: =IF(D75<=E75,"PASS","FAIL") -> PASS
A76: Drift: with the monitor, above the count | B76: =Drift!C7 -> 18.177173 | C76: =Reference_Values!B76 -> 18.177173 | D76: =ABS(B76-C76) -> 0 | E76: 1e-09 | F76: =IF(D76<=E76,"PASS","FAIL") -> PASS
A77: Drift: told of the drift, above the count | B77: =Drift!C8 -> 10.292736 | C77: =Reference_Values!B77 -> 10.292736 | D77: =ABS(B77-C77) -> 5.6843419e-14 | E77: 1e-09 | F77: =IF(D77<=E77,"PASS","FAIL") -> PASS
A78: Drift: delay, median | B78: =Drift!L20 -> 12 | C78: =Reference_Values!B78 -> 12 | D78: =ABS(B78-C78) -> 0 | E78: 1e-09 | F78: =IF(D78<=E78,"PASS","FAIL") -> PASS
A79: Drift: delay, 10th percentile | B79: =Drift!L19 -> 4 | C79: =Reference_Values!B79 -> 4 | D79: =ABS(B79-C79) -> 0 | E79: 1e-09 | F79: =IF(D79<=E79,"PASS","FAIL") -> PASS
A80: Drift: delay, 90th percentile | B80: =Drift!L21 -> 22 | C80: =Reference_Values!B80 -> 22 | D80: =ABS(B80-C80) -> 0 | E80: 1e-09 | F80: =IF(D80<=E80,"PASS","FAIL") -> PASS
A81: Drift: delay, mean | B81: =Drift!G18 -> 12.26814 | C81: =Reference_Values!B81 -> 12.26814 | D81: =ABS(B81-C81) -> 0 | E81: 1e-09 | F81: =IF(D81<=E81,"PASS","FAIL") -> PASS
A82: Figure 15.3(a): half the monitors alarmed, quarters after the drift | B82: =Drift!K26 -> 12 | C82: =Reference_Values!B82 -> 12 | D82: =ABS(B82-C82) -> 0 | E82: 0 | F82: =IF(D82<=E82,"PASS","FAIL") -> PASS
A83: Cumulative sum: program 1's first alarm from quarter 8 | B83: =Monitor!B45 -> 12 | C83: =Reference_Values!B83 -> 12 | D83: =ABS(B83-C83) -> 0 | E83: 0 | F83: =IF(D83<=E83,"PASS","FAIL") -> PASS
A84: Cumulative sum: program 2's first alarm from quarter 8 | B84: =Monitor!B46 -> 10 | C84: =Reference_Values!B84 -> 10 | D84: =ABS(B84-C84) -> 0 | E84: 0 | F84: =IF(D84<=E84,"PASS","FAIL") -> PASS
A85: Cumulative sum: program 3's first alarm from quarter 8 | B85: =Monitor!B47 -> 16 | C85: =Reference_Values!B85 -> 16 | D85: =ABS(B85-C85) -> 0 | E85: 0 | F85: =IF(D85<=E85,"PASS","FAIL") -> PASS
A86: Cumulative sum: program 4's first alarm from quarter 8 | B86: =Monitor!B48 -> 14 | C86: =Reference_Values!B86 -> 14 | D86: =ABS(B86-C86) -> 0 | E86: 0 | F86: =IF(D86<=E86,"PASS","FAIL") -> PASS
A87: Cumulative sum: program 5's first alarm from quarter 8 | B87: =Monitor!B49 -> 14 | C87: =Reference_Values!B87 -> 14 | D87: =ABS(B87-C87) -> 0 | E87: 0 | F87: =IF(D87<=E87,"PASS","FAIL") -> PASS
A88: Cumulative sum: program 6's first alarm from quarter 8 | B88: =Monitor!B50 -> 30 | C88: =Reference_Values!B88 -> 30 | D88: =ABS(B88-C88) -> 0 | E88: 0 | F88: =IF(D88<=E88,"PASS","FAIL") -> PASS
A89: Cumulative sum: program 7's first alarm from quarter 8 | B89: =Monitor!B51 -> 22 | C89: =Reference_Values!B89 -> 22 | D89: =ABS(B89-C89) -> 0 | E89: 0 | F89: =IF(D89<=E89,"PASS","FAIL") -> PASS
A90: Cumulative sum: program 8's first alarm from quarter 8 | B90: =Monitor!B52 -> 14 | C90: =Reference_Values!B90 -> 14 | D90: =ABS(B90-C90) -> 0 | E90: 0 | F90: =IF(D90<=E90,"PASS","FAIL") -> PASS
A91: Envelope: targets that could break the guardrail | B91: =Envelope!B16 -> 0 | C91: =Reference_Values!B91 -> 0 | D91: =ABS(B91-C91) -> 0 | E91: 0 | F91: =IF(D91<=E91,"PASS","FAIL") -> PASS
A92: Envelope: an uncertainty trigger at 1.5 first fires at quarter | B92: =Envelope!G21 -> 8 | C92: =Reference_Values!B92 -> 8 | D92: =ABS(B92-C92) -> 0 | E92: 0 | F92: =IF(D92<=E92,"PASS","FAIL") -> PASS
A93: Envelope: and at every survey after it | B93: =Envelope!G22 -> 1 | C93: =Reference_Values!B93 -> 1 | D93: =ABS(B93-C93) -> 0 | E93: 0 | F93: =IF(D93<=E93,"PASS","FAIL") -> PASS
A94: Proposition 15.3(i): the loop is stable | B94: =Envelope!G26 -> 1 | C94: =Reference_Values!B94 -> 1 | D94: =ABS(B94-C94) -> 0 | E94: 0 | F94: =IF(D94<=E94,"PASS","FAIL") -> PASS
A95: Table 15.3: the twin's cost above the count | B95: =Table15_3!E11 -> 11.100596 | C95: =Reference_Values!B95 -> 11.100596 | D95: =ABS(B95-C95) -> 0 | E95: 1e-09 | F95: =IF(D95<=E95,"PASS","FAIL") -> PASS
A96: Table 15.3: law never questioned | B96: =Table15_3!E16 -> 56.472827 | C96: =Reference_Values!B96 -> 56.472827 | D96: =ABS(B96-C96) -> 0 | E96: 1e-09 | F96: =IF(D96<=E96,"PASS","FAIL") -> PASS
A98: All checkpoints | F98: =IF(COUNTIF(F2:F96,"PASS")=95,"ALL PASS","CHECK") -> ALL PASS
