Workbook

Sheet README
B1: DCT Laboratory — Vol I, Ch 1: Introduction to Dynamic Corporate Transformation
B2: Seed 26101 · Companion to DCT_V1_Ch01_Lab.ipynb and AXIOM Lab 1.1 (module AXIOM-01). Money in $ million.
B4: Worked Example 1.1, Same Score, Different Company, with the book's declarations: Meridian's state of Chapter 3 and the Chapter 1 model of Online Appendix 1.B.4.
B5: Declarations: the eight readings, Table 1.B.1's parameters, the CFO's weights, and the digital program's declared uncertainty (Volume I, Worked Example 8.1).
B6: Dashboard: the eight readings, their sources and error bands, and today's score (lab step 1).
B7: Paths: Equation 1.B.1 month by month for the three options, with Table 1.9 and the scores (lab step 2).
B8: Compare: the digital low point, the sale-date jump, the strategic-risk margin and the scorecard's own path (lab step 3).
B9: Uncertainty: the quarterly plan, its headroom and the closed-form parts of the risk; the 100,000-path breach odds come from the notebook's simulation (lab step 4).
B10: Scorecard: the $25 million tie, the 1.6 weight points, your own weightings, and the directions that leave a score unchanged (lab step 5).
B11: Reference_Values and Checks: the engine's numbers and a PASS/FAIL comparison with this workbook's formulas.
B13: LEGEND
B14: Input: blue on pale gold. A declaration from the book; change it to explore.
... B17: Cross-sheet link: green.

Sheet Declarations
A1: Declarations (Worked Example 1.1, Step 1; Online Appendix 1.B.4). Money in $ million; liquidity also as an index, today = 100.
A3: Reading | B3: Symbol | C3: Today | D3: Unit | E3: Declared in
A4: liquidity | B4: x1 | C4: 100 | D4: index, today = 100 ($0.62 billion) | E4: Chapter 3, Table 3.1
A5: net leverage | B5: x2 | C5: 3.4 | D5: net debt / EBITDA | E5: Chapter 3, Table 3.1
A6: workforce capability | B6: x3 | C6: 58 | D6: index, 0-100 | E6: Chapter 3, Table 3.1
A7: technology platform | B7: x4 | C7: 41 | D7: index, 0-100 | E7: Chapter 3, Table 3.1
A8: operational efficiency | B8: x5 | C8: 71 | D8: index, 0-100 | E8: Chapter 3, Table 3.1
A9: return on invested capital | B9: x6 | C9: 0.083 | D9: ratio | E9: Chapter 3, Table 3.1
A10: strategic risk (lower is better) | B10: x7 | C10: 64 | D10: index, 0-100 | E10: Chapter 3, Table 3.1
A11: market share | B11: x8 | C11: 0.19 | D11: ratio | E11: Chapter 3, Table 3.1
A13: Quantity | C13: Value | E13: Declared in
A14: Liquidity today ($ million) | C14: 620 | E14: Chapter 3, Table 3.1: $0.62 billion
A15: $ million per liquidity point | C15: =C14/C4 -> 6.2 | E15: Online Appendix 1.B.2: $6.2 million
A16: The sale closes at t (years) | C16: 1 | E16: Online Appendix 1.B.4
A17: Strategic-risk ceiling | C17: 75 | E17: Chapter 5, Table 5.4; Table 1.5's margin
A19: Option | B19: Reading | C19: Target | D19: Speed k | E19: Trough (sign x depth) | F19: Trough time tau | G19: Jump at the sale
A20: Digital | B20: liquidity | C20: 112 | D20: 0.35 | E20: -28 | F20: 2 | G20: 0
B21: technology | C21: 78 | D21: 0.55 | E21: 0 | F21: 0 | G21: 0
B22: efficiency | C22: 77 | D22: 0.5 | E22: -9 | F22: 1.5 | G22: 0
B23: strategic risk | C23: 51 | D23: 0.4 | E23: 14 | F23: 1.2 | G23: 0
A24: Restructuring | B24: liquidity | C24: 104 | D24: 0.3 | E24: 0 | F24: 0 | G24: 18
B25: technology | C25: 38 | D25: 0.25 | E25: 0 | F25: 0 | G25: 0
B26: efficiency | C26: 74 | D26: 0.45 | E26: 0 | F26: 0 | G26: 0
B27: strategic risk | C27: 56 | D27: 0.35 | E27: 0 | F27: 0 | G27: -8
A28: Turnaround | B28: liquidity | C28: 106 | D28: 0.45 | E28: 0 | F28: 0 | G28: 0
B29: technology | C29: 33 | D29: 0.2 | E29: 0 | F29: 0 | G29: 0
B30: efficiency | C30: 79 | D30: 0.6 | E30: 0 | F30: 0 | G30: 0
B31: strategic risk | C31: 67 | D31: 0.3 | E31: 0 | F31: 0 | G31: 0
A32: Table 1.B.1 (Online Appendix 1.B.4); zeros are the table's blank cells. Efficiency and risk targets are the course model's re-based onto the book's state (+3 and +9).
A34: The CFO's scorecard (Worked Example 1.1) | C34: Weight
A35: liquidity | C35: 0.25
A36: technology platform | C36: 0.25
A37: operational efficiency | C37: 0.25
A38: strategic risk (subtracted) | C38: -0.25
A40: Uncertainty of the digital program (Volume I, Worked Example 8.1) | C40: Value | E40: Declared in
A41: Board liquidity floor ($ million) | C41: 350 | E41: Chapter 5, Table 5.4
A42: Execution and market surprise, sd a quarter ($ million) | C42: 50 | E42: Worked Example 8.1, Step 1
A43: Share of a surprise carried into the next quarter | C43: 0.6 | E43: Worked Example 8.1, Step 1
A44: Funding-window closures a year | C44: 0.1 | E44: Worked Example 8.1, Step 1
A45: Closure size, mean ($ million, not recovered) | C45: 120 | E45: Worked Example 8.1, Step 1
A46: Closure size, sd ($ million) | C46: 50 | E46: Worked Example 8.1, Step 1
A47: Standby line, per closure ($ million) | C47: 100 | E47: Worked Example 8.1, Step 5
A48: Phased build: trough depth (points; plan 28) | C48: 20 | E48: Worked Example 8.1, Step 5
A49: Program length (years) | C49: 3 | E49: Worked Example 8.1

Sheet Dashboard
A1: Read the dashboard: Meridian's eight readings (AXIOM Lab 1.1, step 1; Worked Example 1.1, Step 1)
A2: Sources and error bands: Chapter 5, Table 5.2. Declared scale: Chapter 3 (unbounded readings divided by today's value, indices by their range of 100).
A3: x | B3: Reading | C3: Today | D3: Chapter 1 model | E3: Measured by | F3: Error band | G3: Error in the reading's unit | H3: Declared scale | I3: Scaled error
A4: x1 | B4: liquidity | C4: =Declarations!C4 -> 100 | D4: moves | E4: treasury systems | F4: +/-1% | G4: =0.01*C4 -> 1 | H4: =C4 -> 100 | I4: =G4/H4 -> 0.01
A5: x2 | B5: net leverage | C5: =Declarations!C5 -> 3.4 | D5: held at today | E5: audited accounts | F5: +/-2% | G5: =0.02*C5 -> 0.068 | H5: =C5 -> 3.4 | I5: =G5/H5 -> 0.02
A6: x3 | B6: workforce capability | C6: =Declarations!C6 -> 58 | D6: held at today | E6: skills survey | F6: +/-5 | G6: 5 | H6: 100 | I6: =G6/H6 -> 0.05
A7: x4 | B7: technology platform | C7: =Declarations!C7 -> 41 | D7: moves | E7: architecture audit | F7: +/-4 | G7: 4 | H7: 100 | I7: =G7/H7 -> 0.04
A8: x5 | B8: operational efficiency | C8: =Declarations!C8 -> 71 | D8: moves | E8: cost benchmarking | F8: +/-3 | G8: 3 | H8: 100 | I8: =G8/H8 -> 0.03
A9: x6 | B9: return on invested capital | C9: =Declarations!C9 -> 0.083 | D9: held at today | E9: audited accounts | F9: +/-0.4 pp | G9: 0.004 | H9: =C9 -> 0.083 | I9: =G9/H9 -> 0.048192771
A10: x7 | B10: strategic risk | C10: =Declarations!C10 -> 64 | D10: moves | E10: risk committee | F10: +/-6 | G10: 6 | H10: 100 | I10: =G10/H10 -> 0.06
A11: x8 | B11: market share | C11: =Declarations!C11 -> 0.19 | D11: held at today | E11: industry data | F11: +/-0.8 pp | G11: 0.008 | H11: =C11 -> 0.19 | I11: =G11/H11 -> 0.042105263
A13: Widest scaled error band | C13: =INDEX(B4:B11,MATCH(LARGE(I4:I11,1),I4:I11,0)) -> strategic risk | E13: =LARGE(I4:I11,1) -> 0.06
A14: Second widest | C14: =INDEX(B4:B11,MATCH(LARGE(I4:I11,2),I4:I11,0)) -> workforce capability | E14: =LARGE(I4:I11,2) -> 0.05
A15: The two readings whose margins Chapter 16 finds thinner than their reading error (Table 1.5).
A17: Today's score, (liquidity + technology + efficiency - strategic risk)/4 | E17: =W_L*C4+W_T*C7+W_E*C8+W_R*C10 -> 37

Sheet Paths
A1: Play the three options: Equation 1.B.1 month by month for five years (AXIOM Lab 1.1, step 2; Worked Example 1.1, Step 2; Table 1.9)
A2: x(t) = target + (x(0) - target) exp(-k t) + trough x (t/tau) exp(1 - t/tau) + jump [t >= 1]; parameters on Declarations. Four readings move; the other four are held at today's values.
A4: Table 1.9 | B4: Today | C4: Digital | D4: Restructuring | E4: Turnaround
A5: liquidity (index) | B5: =Declarations!C4 -> 100 | C5: =C72 -> 94.295601 | D5: =G72 -> 121.10748 | E5: =K72 -> 105.3676 | F5: Year 5 (month 60). Lower strategic risk is better.
A6: technology platform | B6: =Declarations!C7 -> 41 | C6: =D72 -> 75.634669 | D6: =H72 -> 38.859514 | E6: =L72 -> 35.943036
A7: operational efficiency | B7: =Declarations!C8 -> 71 | C7: =E72 -> 73.598331 | D7: =I72 -> 73.683802 | E7: =M72 -> 78.601703
A8: strategic risk | B8: =Declarations!C10 -> 64 | C8: =F72 -> 55.21775 | D8: =J72 -> 49.390192 | E8: =N72 -> 66.33061
A9: score | B9: =W_L*B5+W_T*B6+W_E*B7+W_R*B8 -> 37 | C9: =O72 -> 47.077713 | D9: =P72 -> 46.065151 | E9: =Q72 -> 38.395434
A11: Month | B11: t (years) | C11: D: liquidity | D11: D: technology | E11: D: efficiency | F11: D: risk | G11: R: liquidity | H11: R: technology | I11: R: efficiency | J11: R: risk | K11: T: liquidity | L11: T: technology | M11: T: efficiency | N11: T: risk | O11: Score: digital | P11: Score: restructuring | Q11: Score: turnaround | R11: Digital back at today's score
A12: 0 | B12: =A12/12 -> 0 | C12: =Declarations!$C$20+(Declarations!$C$4-Declarations!$C$20)*EXP(-Declarations!$D$20*$B12)+IF(Declarations!$E$20=0,0,Declarations!$E$20*($B12/Declarations!$F$20)*EXP(1-$B12/Declarations!$F$20))+IF($B12>=T_sale,Declarations!$G$20,0) -> 100 | D12: =Declarations!$C$21+(Declarations!$C$7-Declarations!$C$21)*EXP(-Declarations!$D$21*$B12)+IF(Declarations!$E$21=0,0,Declarations!$E$21*($B12/Declarations!$F$21)*EXP(1-$B12/Declarations!$F$21))+IF($B12>=T_sale,Declarations!$G$21,0) -> 41 | E12: =Declarations!$C$22+(Declarations!$C$8-Declarations!$C$22)*EXP(-Declarations!$D$22*$B12)+IF(Declarations!$E$22=0,0,Declarations!$E$22*($B12/Declarations!$F$22)*EXP(1-$B12/Declarations!$F$22))+IF($B12>=T_sale,Declarations!$G$22,0) -> 71 | F12: =Declarations!$C$23+(Declarations!$C$10-Declarations!$C$23)*EXP(-Declarations!$D$23*$B12)+IF(Declarations!$E$23=0,0,Declarations!$E$23*($B12/Declarations!$F$23)*EXP(1-$B12/Declarations!$F$23))+IF($B12>=T_sale,Declarations!$G$23,0) -> 64 | G12: =Declarations!$C$24+(Declarations!$C$4-Declarations!$C$24)*EXP(-Declarations!$D$24*$B12)+IF(Declarations!$E$24=0,0,Declarations!$E$24*($B12/Declarations!$F$24)*EXP(1-$B12/Declarations!$F$24))+IF($B12>=T_sale,Declarations!$G$24,0) -> 100 | H12: =Declarations!$C$25+(Declarations!$C$7-Declarations!$C$25)*EXP(-Declarations!$D$25*$B12)+IF(Declarations!$E$25=0,0,Declarations!$E$25*($B12/Declarations!$F$25)*EXP(1-$B12/Declarations!$F$25))+IF($B12>=T_sale,Declarations!$G$25,0) -> 41 | I12: =Declarations!$C$26+(Declarations!$C$8-Declarations!$C$26)*EXP(-Declarations!$D$26*$B12)+IF(Declarations!$E$26=0,0,Declarations!$E$26*($B12/Declarations!$F$26)*EXP(1-$B12/Declarations!$F$26))+IF($B12>=T_sale,Declarations!$G$26,0) -> 71 | J12: =Declarations!$C$27+(Declarations!$C$10-Declarations!$C$27)*EXP(-Declarations!$D$27*$B12)+IF(Declarations!$E$27=0,0,Declarations!$E$27*($B12/Declarations!$F$27)*EXP(1-$B12/Declarations!$F$27))+IF($B12>=T_sale,Declarations!$G$27,0) -> 64 | K12: =Declarations!$C$28+(Declarations!$C$4-Declarations!$C$28)*EXP(-Declarations!$D$28*$B12)+IF(Declarations!$E$28=0,0,Declarations!$E$28*($B12/Declarations!$F$28)*EXP(1-$B12/Declarations!$F$28))+IF($B12>=T_sale,Declarations!$G$28,0) -> 100 | L12: =Declarations!$C$29+(Declarations!$C$7-Declarations!$C$29)*EXP(-Declarations!$D$29*$B12)+IF(Declarations!$E$29=0,0,Declarations!$E$29*($B12/Declarations!$F$29)*EXP(1-$B12/Declarations!$F$29))+IF($B12>=T_sale,Declarations!$G$29,0) -> 41 | M12: =Declarations!$C$30+(Declarations!$C$8-Declarations!$C$30)*EXP(-Declarations!$D$30*$B12)+IF(Declarations!$E$30=0,0,Declarations!$E$30*($B12/Declarations!$F$30)*EXP(1-$B12/Declarations!$F$30))+IF($B12>=T_sale,Declarations!$G$30,0) -> 71 | N12: =Declarations!$C$31+(Declarations!$C$10-Declarations!$C$31)*EXP(-Declarations!$D$31*$B12)+IF(Declarations!$E$31=0,0,Declarations!$E$31*($B12/Declarations!$F$31)*EXP(1-$B12/Declarations!$F$31))+IF($B12>=T_sale,Declarations!$G$31,0) -> 64 | O12: =W_L*C12+W_T*D12+W_E*E12+W_R*F12 -> 37 | P12: =W_L*G12+W_T*H12+W_E*I12+W_R*J12 -> 37 | Q12: =W_L*K12+W_T*L12+W_E*M12+W_R*N12 -> 37
A13: 1 | B13: =A13/12 -> 0.083333333 | C13: =Declarations!$C$20+(Declarations!$C$4-Declarations!$C$20)*EXP(-Declarations!$D$20*$B13)+IF(Declarations!$E$20=0,0,Declarations!$E$20*($B13/Declarations!$F$20)*EXP(1-$B13/Declarations!$F$20))+IF($B13>=T_sale,Declarations!$G$20,0) -> 97.30304 | D13: =Declarations!$C$21+(Declarations!$C$7-Declarations!$C$21)*EXP(-Declarations!$D$21*$B13)+IF(Declarations!$E$21=0,0,Declarations!$E$21*($B13/Declarations!$F$21)*EXP(1-$B13/Declarations!$F$21))+IF($B13>=T_sale,Declarations!$G$21,0) -> 42.657557 | E13: =Declarations!$C$22+(Declarations!$C$8-Declarations!$C$22)*EXP(-Declarations!$D$22*$B13)+IF(Declarations!$E$22=0,0,Declarations!$E$22*($B13/Declarations!$F$22)*EXP(1-$B13/Declarations!$F$22))+IF($B13>=T_sale,Declarations!$G$22,0) -> 69.959171 | F13: =Declarations!$C$23+(Declarations!$C$10-Declarations!$C$23)*EXP(-Declarations!$D$23*$B13)+IF(Declarations!$E$23=0,0,Declarations!$E$23*($B13/Declarations!$F$23)*EXP(1-$B13/Declarations!$F$23))+IF($B13>=T_sale,Declarations!$G$23,0) -> 66.039285 | G13: =Declarations!$C$24+(Declarations!$C$4-Declarations!$C$24)*EXP(-Declarations!$D$24*$B13)+IF(Declarations!$E$24=0,0,Declarations!$E$24*($B13/Declarations!$F$24)*EXP(1-$B13/Declarations!$F$24))+IF($B13>=T_sale,Declarations!$G$24,0) -> 100.09876 | H13: =Declarations!$C$25+(Declarations!$C$7-Declarations!$C$25)*EXP(-Declarations!$D$25*$B13)+IF(Declarations!$E$25=0,0,Declarations!$E$25*($B13/Declarations!$F$25)*EXP(1-$B13/Declarations!$F$25))+IF($B13>=T_sale,Declarations!$G$25,0) -> 40.938147 | I13: =Declarations!$C$26+(Declarations!$C$8-Declarations!$C$26)*EXP(-Declarations!$D$26*$B13)+IF(Declarations!$E$26=0,0,Declarations!$E$26*($B13/Declarations!$F$26)*EXP(1-$B13/Declarations!$F$26))+IF($B13>=T_sale,Declarations!$G$26,0) -> 71.110417 | J13: =Declarations!$C$27+(Declarations!$C$10-Declarations!$C$27)*EXP(-Declarations!$D$27*$B13)+IF(Declarations!$E$27=0,0,Declarations!$E$27*($B13/Declarations!$F$27)*EXP(1-$B13/Declarations!$F$27))+IF($B13>=T_sale,Declarations!$G$27,0) -> 63.770037 | K13: =Declarations!$C$28+(Declarations!$C$4-Declarations!$C$28)*EXP(-Declarations!$D$28*$B13)+IF(Declarations!$E$28=0,0,Declarations!$E$28*($B13/Declarations!$F$28)*EXP(1-$B13/Declarations!$F$28))+IF($B13>=T_sale,Declarations!$G$28,0) -> 100.22083 | L13: =Declarations!$C$29+(Declarations!$C$7-Declarations!$C$29)*EXP(-Declarations!$D$29*$B13)+IF(Declarations!$E$29=0,0,Declarations!$E$29*($B13/Declarations!$F$29)*EXP(1-$B13/Declarations!$F$29))+IF($B13>=T_sale,Declarations!$G$29,0) -> 40.867772 | M13: =Declarations!$C$30+(Declarations!$C$8-Declarations!$C$30)*EXP(-Declarations!$D$30*$B13)+IF(Declarations!$E$30=0,0,Declarations!$E$30*($B13/Declarations!$F$30)*EXP(1-$B13/Declarations!$F$30))+IF($B13>=T_sale,Declarations!$G$30,0) -> 71.390165 | N13: =Declarations!$C$31+(Declarations!$C$10-Declarations!$C$31)*EXP(-Declarations!$D$31*$B13)+IF(Declarations!$E$31=0,0,Declarations!$E$31*($B13/Declarations!$F$31)*EXP(1-$B13/Declarations!$F$31))+IF($B13>=T_sale,Declarations!$G$31,0) -> 64.07407 | O13: =W_L*C13+W_T*D13+W_E*E13+W_R*F13 -> 35.970121 | P13: =W_L*G13+W_T*H13+W_E*I13+W_R*J13 -> 37.094322 | Q13: =W_L*K13+W_T*L13+W_E*M13+W_R*N13 -> 37.101175 | R13: =IF(AND(O13>=$B$9,O12<$B$9),A13,"")
A14: 2 | B14: =A14/12 -> 0.16666667 | C14: =Declarations!$C$20+(Declarations!$C$4-Declarations!$C$20)*EXP(-Declarations!$D$20*$B14)+IF(Declarations!$E$20=0,0,Declarations!$E$20*($B14/Declarations!$F$20)*EXP(1-$B14/Declarations!$F$20))+IF($B14>=T_sale,Declarations!$G$20,0) -> 94.844448 | D14: =Declarations!$C$21+(Declarations!$C$7-Declarations!$C$21)*EXP(-Declarations!$D$21*$B14)+IF(Declarations!$E$21=0,0,Declarations!$E$21*($B14/Declarations!$F$21)*EXP(1-$B14/Declarations!$F$21))+IF($B14>=T_sale,Declarations!$G$21,0) -> 44.240858 | E14: =Declarations!$C$22+(Declarations!$C$8-Declarations!$C$22)*EXP(-Declarations!$D$22*$B14)+IF(Declarations!$E$22=0,0,Declarations!$E$22*($B14/Declarations!$F$22)*EXP(1-$B14/Declarations!$F$22))+IF($B14>=T_sale,Declarations!$G$22,0) -> 69.047308 | F14: =Declarations!$C$23+(Declarations!$C$10-Declarations!$C$23)*EXP(-Declarations!$D$23*$B14)+IF(Declarations!$E$23=0,0,Declarations!$E$23*($B14/Declarations!$F$23)*EXP(1-$B14/Declarations!$F$23))+IF($B14>=T_sale,Declarations!$G$23,0) -> 67.761734 | G14: =Declarations!$C$24+(Declarations!$C$4-Declarations!$C$24)*EXP(-Declarations!$D$24*$B14)+IF(Declarations!$E$24=0,0,Declarations!$E$24*($B14/Declarations!$F$24)*EXP(1-$B14/Declarations!$F$24))+IF($B14>=T_sale,Declarations!$G$24,0) -> 100.19508 | H14: =Declarations!$C$25+(Declarations!$C$7-Declarations!$C$25)*EXP(-Declarations!$D$25*$B14)+IF(Declarations!$E$25=0,0,Declarations!$E$25*($B14/Declarations!$F$25)*EXP(1-$B14/Declarations!$F$25))+IF($B14>=T_sale,Declarations!$G$25,0) -> 40.877568 | I14: =Declarations!$C$26+(Declarations!$C$8-Declarations!$C$26)*EXP(-Declarations!$D$26*$B14)+IF(Declarations!$E$26=0,0,Declarations!$E$26*($B14/Declarations!$F$26)*EXP(1-$B14/Declarations!$F$26))+IF($B14>=T_sale,Declarations!$G$26,0) -> 71.21677 | J14: =Declarations!$C$27+(Declarations!$C$10-Declarations!$C$27)*EXP(-Declarations!$D$27*$B14)+IF(Declarations!$E$27=0,0,Declarations!$E$27*($B14/Declarations!$F$27)*EXP(1-$B14/Declarations!$F$27))+IF($B14>=T_sale,Declarations!$G$27,0) -> 63.546684 | K14: =Declarations!$C$28+(Declarations!$C$4-Declarations!$C$28)*EXP(-Declarations!$D$28*$B14)+IF(Declarations!$E$28=0,0,Declarations!$E$28*($B14/Declarations!$F$28)*EXP(1-$B14/Declarations!$F$28))+IF($B14>=T_sale,Declarations!$G$28,0) -> 100.43354 | L14: =Declarations!$C$29+(Declarations!$C$7-Declarations!$C$29)*EXP(-Declarations!$D$29*$B14)+IF(Declarations!$E$29=0,0,Declarations!$E$29*($B14/Declarations!$F$29)*EXP(1-$B14/Declarations!$F$29))+IF($B14>=T_sale,Declarations!$G$29,0) -> 40.737729 | M14: =Declarations!$C$30+(Declarations!$C$8-Declarations!$C$30)*EXP(-Declarations!$D$30*$B14)+IF(Declarations!$E$30=0,0,Declarations!$E$30*($B14/Declarations!$F$30)*EXP(1-$B14/Declarations!$F$30))+IF($B14>=T_sale,Declarations!$G$30,0) -> 71.761301 | N14: =Declarations!$C$31+(Declarations!$C$10-Declarations!$C$31)*EXP(-Declarations!$D$31*$B14)+IF(Declarations!$E$31=0,0,Declarations!$E$31*($B14/Declarations!$F$31)*EXP(1-$B14/Declarations!$F$31))+IF($B14>=T_sale,Declarations!$G$31,0) -> 64.146312 | O14: =W_L*C14+W_T*D14+W_E*E14+W_R*F14 -> 35.09272 | P14: =W_L*G14+W_T*H14+W_E*I14+W_R*J14 -> 37.185684 | Q14: =W_L*K14+W_T*L14+W_E*M14+W_R*N14 -> 37.196564 | R14: =IF(AND(O14>=$B$9,O13<$B$9),A14,"")
A15: 3 | B15: =A15/12 -> 0.25 | C15: =Declarations!$C$20+(Declarations!$C$4-Declarations!$C$20)*EXP(-Declarations!$D$20*$B15)+IF(Declarations!$E$20=0,0,Declarations!$E$20*($B15/Declarations!$F$20)*EXP(1-$B15/Declarations!$F$20))+IF($B15>=T_sale,Declarations!$G$20,0) -> 92.60931 | D15: =Declarations!$C$21+(Declarations!$C$7-Declarations!$C$21)*EXP(-Declarations!$D$21*$B15)+IF(Declarations!$E$21=0,0,Declarations!$E$21*($B15/Declarations!$F$21)*EXP(1-$B15/Declarations!$F$21))+IF($B15>=T_sale,Declarations!$G$21,0) -> 45.753229 | E15: =Declarations!$C$22+(Declarations!$C$8-Declarations!$C$22)*EXP(-Declarations!$D$22*$B15)+IF(Declarations!$E$22=0,0,Declarations!$E$22*($B15/Declarations!$F$22)*EXP(1-$B15/Declarations!$F$22))+IF($B15>=T_sale,Declarations!$G$22,0) -> 68.253555 | F15: =Declarations!$C$23+(Declarations!$C$10-Declarations!$C$23)*EXP(-Declarations!$D$23*$B15)+IF(Declarations!$E$23=0,0,Declarations!$E$23*($B15/Declarations!$F$23)*EXP(1-$B15/Declarations!$F$23))+IF($B15>=T_sale,Declarations!$G$23,0) -> 69.200179 | G15: =Declarations!$C$24+(Declarations!$C$4-Declarations!$C$24)*EXP(-Declarations!$D$24*$B15)+IF(Declarations!$E$24=0,0,Declarations!$E$24*($B15/Declarations!$F$24)*EXP(1-$B15/Declarations!$F$24))+IF($B15>=T_sale,Declarations!$G$24,0) -> 100.28903 | H15: =Declarations!$C$25+(Declarations!$C$7-Declarations!$C$25)*EXP(-Declarations!$D$25*$B15)+IF(Declarations!$E$25=0,0,Declarations!$E$25*($B15/Declarations!$F$25)*EXP(1-$B15/Declarations!$F$25))+IF($B15>=T_sale,Declarations!$G$25,0) -> 40.818239 | I15: =Declarations!$C$26+(Declarations!$C$8-Declarations!$C$26)*EXP(-Declarations!$D$26*$B15)+IF(Declarations!$E$26=0,0,Declarations!$E$26*($B15/Declarations!$F$26)*EXP(1-$B15/Declarations!$F$26))+IF($B15>=T_sale,Declarations!$G$26,0) -> 71.319208 | J15: =Declarations!$C$27+(Declarations!$C$10-Declarations!$C$27)*EXP(-Declarations!$D$27*$B15)+IF(Declarations!$E$27=0,0,Declarations!$E$27*($B15/Declarations!$F$27)*EXP(1-$B15/Declarations!$F$27))+IF($B15>=T_sale,Declarations!$G$27,0) -> 63.329751 | K15: =Declarations!$C$28+(Declarations!$C$4-Declarations!$C$28)*EXP(-Declarations!$D$28*$B15)+IF(Declarations!$E$28=0,0,Declarations!$E$28*($B15/Declarations!$F$28)*EXP(1-$B15/Declarations!$F$28))+IF($B15>=T_sale,Declarations!$G$28,0) -> 100.63842 | L15: =Declarations!$C$29+(Declarations!$C$7-Declarations!$C$29)*EXP(-Declarations!$D$29*$B15)+IF(Declarations!$E$29=0,0,Declarations!$E$29*($B15/Declarations!$F$29)*EXP(1-$B15/Declarations!$F$29))+IF($B15>=T_sale,Declarations!$G$29,0) -> 40.609835 | M15: =Declarations!$C$30+(Declarations!$C$8-Declarations!$C$30)*EXP(-Declarations!$D$30*$B15)+IF(Declarations!$E$30=0,0,Declarations!$E$30*($B15/Declarations!$F$30)*EXP(1-$B15/Declarations!$F$30))+IF($B15>=T_sale,Declarations!$G$30,0) -> 72.114336 | N15: =Declarations!$C$31+(Declarations!$C$10-Declarations!$C$31)*EXP(-Declarations!$D$31*$B15)+IF(Declarations!$E$31=0,0,Declarations!$E$31*($B15/Declarations!$F$31)*EXP(1-$B15/Declarations!$F$31))+IF($B15>=T_sale,Declarations!$G$31,0) -> 64.21677 | O15: =W_L*C15+W_T*D15+W_E*E15+W_R*F15 -> 34.353979 | P15: =W_L*G15+W_T*H15+W_E*I15+W_R*J15 -> 37.274181 | Q15: =W_L*K15+W_T*L15+W_E*M15+W_R*N15 -> 37.286454 | R15: =IF(AND(O15>=$B$9,O14<$B$9),A15,"")
A16: 4 | B16: =A16/12 -> 0.33333333 | C16: =Declarations!$C$20+(Declarations!$C$4-Declarations!$C$20)*EXP(-Declarations!$D$20*$B16)+IF(Declarations!$E$20=0,0,Declarations!$E$20*($B16/Declarations!$F$20)*EXP(1-$B16/Declarations!$F$20))+IF($B16>=T_sale,Declarations!$G$20,0) -> 90.583531 | D16: =Declarations!$C$21+(Declarations!$C$7-Declarations!$C$21)*EXP(-Declarations!$D$21*$B16)+IF(Declarations!$E$21=0,0,Declarations!$E$21*($B16/Declarations!$F$21)*EXP(1-$B16/Declarations!$F$21))+IF($B16>=T_sale,Declarations!$G$21,0) -> 47.197847 | E16: =Declarations!$C$22+(Declarations!$C$8-Declarations!$C$22)*EXP(-Declarations!$D$22*$B16)+IF(Declarations!$E$22=0,0,Declarations!$E$22*($B16/Declarations!$F$22)*EXP(1-$B16/Declarations!$F$22))+IF($B16>=T_sale,Declarations!$G$22,0) -> 67.56785 | F16: =Declarations!$C$23+(Declarations!$C$10-Declarations!$C$23)*EXP(-Declarations!$D$23*$B16)+IF(Declarations!$E$23=0,0,Declarations!$E$23*($B16/Declarations!$F$23)*EXP(1-$B16/Declarations!$F$23))+IF($B16>=T_sale,Declarations!$G$23,0) -> 70.38449 | G16: =Declarations!$C$24+(Declarations!$C$4-Declarations!$C$24)*EXP(-Declarations!$D$24*$B16)+IF(Declarations!$E$24=0,0,Declarations!$E$24*($B16/Declarations!$F$24)*EXP(1-$B16/Declarations!$F$24))+IF($B16>=T_sale,Declarations!$G$24,0) -> 100.38065 | H16: =Declarations!$C$25+(Declarations!$C$7-Declarations!$C$25)*EXP(-Declarations!$D$25*$B16)+IF(Declarations!$E$25=0,0,Declarations!$E$25*($B16/Declarations!$F$25)*EXP(1-$B16/Declarations!$F$25))+IF($B16>=T_sale,Declarations!$G$25,0) -> 40.760133 | I16: =Declarations!$C$26+(Declarations!$C$8-Declarations!$C$26)*EXP(-Declarations!$D$26*$B16)+IF(Declarations!$E$26=0,0,Declarations!$E$26*($B16/Declarations!$F$26)*EXP(1-$B16/Declarations!$F$26))+IF($B16>=T_sale,Declarations!$G$26,0) -> 71.417876 | J16: =Declarations!$C$27+(Declarations!$C$10-Declarations!$C$27)*EXP(-Declarations!$D$27*$B16)+IF(Declarations!$E$27=0,0,Declarations!$E$27*($B16/Declarations!$F$27)*EXP(1-$B16/Declarations!$F$27))+IF($B16>=T_sale,Declarations!$G$27,0) -> 63.119054 | K16: =Declarations!$C$28+(Declarations!$C$4-Declarations!$C$28)*EXP(-Declarations!$D$28*$B16)+IF(Declarations!$E$28=0,0,Declarations!$E$28*($B16/Declarations!$F$28)*EXP(1-$B16/Declarations!$F$28))+IF($B16>=T_sale,Declarations!$G$28,0) -> 100.83575 | L16: =Declarations!$C$29+(Declarations!$C$7-Declarations!$C$29)*EXP(-Declarations!$D$29*$B16)+IF(Declarations!$E$29=0,0,Declarations!$E$29*($B16/Declarations!$F$29)*EXP(1-$B16/Declarations!$F$29))+IF($B16>=T_sale,Declarations!$G$29,0) -> 40.484056 | M16: =Declarations!$C$30+(Declarations!$C$8-Declarations!$C$30)*EXP(-Declarations!$D$30*$B16)+IF(Declarations!$E$30=0,0,Declarations!$E$30*($B16/Declarations!$F$30)*EXP(1-$B16/Declarations!$F$30))+IF($B16>=T_sale,Declarations!$G$30,0) -> 72.450154 | N16: =Declarations!$C$31+(Declarations!$C$10-Declarations!$C$31)*EXP(-Declarations!$D$31*$B16)+IF(Declarations!$E$31=0,0,Declarations!$E$31*($B16/Declarations!$F$31)*EXP(1-$B16/Declarations!$F$31))+IF($B16>=T_sale,Declarations!$G$31,0) -> 64.285488 | O16: =W_L*C16+W_T*D16+W_E*E16+W_R*F16 -> 33.741185 | P16: =W_L*G16+W_T*H16+W_E*I16+W_R*J16 -> 37.359901 | Q16: =W_L*K16+W_T*L16+W_E*M16+W_R*N16 -> 37.371119 | R16: =IF(AND(O16>=$B$9,O15<$B$9),A16,"")
A17: 5 | B17: =A17/12 -> 0.41666667 | C17: =Declarations!$C$20+(Declarations!$C$4-Declarations!$C$20)*EXP(-Declarations!$D$20*$B17)+IF(Declarations!$E$20=0,0,Declarations!$E$20*($B17/Declarations!$F$20)*EXP(1-$B17/Declarations!$F$20))+IF($B17>=T_sale,Declarations!$G$20,0) -> 88.753794 | D17: =Declarations!$C$21+(Declarations!$C$7-Declarations!$C$21)*EXP(-Declarations!$D$21*$B17)+IF(Declarations!$E$21=0,0,Declarations!$E$21*($B17/Declarations!$F$21)*EXP(1-$B17/Declarations!$F$21))+IF($B17>=T_sale,Declarations!$G$21,0) -> 48.577748 | E17: =Declarations!$C$22+(Declarations!$C$8-Declarations!$C$22)*EXP(-Declarations!$D$22*$B17)+IF(Declarations!$E$22=0,0,Declarations!$E$22*($B17/Declarations!$F$22)*EXP(1-$B17/Declarations!$F$22))+IF($B17>=T_sale,Declarations!$G$22,0) -> 66.980873 | F17: =Declarations!$C$23+(Declarations!$C$10-Declarations!$C$23)*EXP(-Declarations!$D$23*$B17)+IF(Declarations!$E$23=0,0,Declarations!$E$23*($B17/Declarations!$F$23)*EXP(1-$B17/Declarations!$F$23))+IF($B17>=T_sale,Declarations!$G$23,0) -> 71.341821 | G17: =Declarations!$C$24+(Declarations!$C$4-Declarations!$C$24)*EXP(-Declarations!$D$24*$B17)+IF(Declarations!$E$24=0,0,Declarations!$E$24*($B17/Declarations!$F$24)*EXP(1-$B17/Declarations!$F$24))+IF($B17>=T_sale,Declarations!$G$24,0) -> 100.47001 | H17: =Declarations!$C$25+(Declarations!$C$7-Declarations!$C$25)*EXP(-Declarations!$D$25*$B17)+IF(Declarations!$E$25=0,0,Declarations!$E$25*($B17/Declarations!$F$25)*EXP(1-$B17/Declarations!$F$25))+IF($B17>=T_sale,Declarations!$G$25,0) -> 40.703225 | I17: =Declarations!$C$26+(Declarations!$C$8-Declarations!$C$26)*EXP(-Declarations!$D$26*$B17)+IF(Declarations!$E$26=0,0,Declarations!$E$26*($B17/Declarations!$F$26)*EXP(1-$B17/Declarations!$F$26))+IF($B17>=T_sale,Declarations!$G$26,0) -> 71.512913 | J17: =Declarations!$C$27+(Declarations!$C$10-Declarations!$C$27)*EXP(-Declarations!$D$27*$B17)+IF(Declarations!$E$27=0,0,Declarations!$E$27*($B17/Declarations!$F$27)*EXP(1-$B17/Declarations!$F$27))+IF($B17>=T_sale,Declarations!$G$27,0) -> 62.914414 | K17: =Declarations!$C$28+(Declarations!$C$4-Declarations!$C$28)*EXP(-Declarations!$D$28*$B17)+IF(Declarations!$E$28=0,0,Declarations!$E$28*($B17/Declarations!$F$28)*EXP(1-$B17/Declarations!$F$28))+IF($B17>=T_sale,Declarations!$G$28,0) -> 101.02583 | L17: =Declarations!$C$29+(Declarations!$C$7-Declarations!$C$29)*EXP(-Declarations!$D$29*$B17)+IF(Declarations!$E$29=0,0,Declarations!$E$29*($B17/Declarations!$F$29)*EXP(1-$B17/Declarations!$F$29))+IF($B17>=T_sale,Declarations!$G$29,0) -> 40.360355 | M17: =Declarations!$C$30+(Declarations!$C$8-Declarations!$C$30)*EXP(-Declarations!$D$30*$B17)+IF(Declarations!$E$30=0,0,Declarations!$E$30*($B17/Declarations!$F$30)*EXP(1-$B17/Declarations!$F$30))+IF($B17>=T_sale,Declarations!$G$30,0) -> 72.769594 | N17: =Declarations!$C$31+(Declarations!$C$10-Declarations!$C$31)*EXP(-Declarations!$D$31*$B17)+IF(Declarations!$E$31=0,0,Declarations!$E$31*($B17/Declarations!$F$31)*EXP(1-$B17/Declarations!$F$31))+IF($B17>=T_sale,Declarations!$G$31,0) -> 64.352509 | O17: =W_L*C17+W_T*D17+W_E*E17+W_R*F17 -> 33.242648 | P17: =W_L*G17+W_T*H17+W_E*I17+W_R*J17 -> 37.442934 | Q17: =W_L*K17+W_T*L17+W_E*M17+W_R*N17 -> 37.450816 | R17: =IF(AND(O17>=$B$9,O16<$B$9),A17,"")
A18: 6 | B18: =A18/12 -> 0.5 | C18: =Declarations!$C$20+(Declarations!$C$4-Declarations!$C$20)*EXP(-Declarations!$D$20*$B18)+IF(Declarations!$E$20=0,0,Declarations!$E$20*($B18/Declarations!$F$20)*EXP(1-$B18/Declarations!$F$20))+IF($B18>=T_sale,Declarations!$G$20,0) -> 87.107516 | D18: =Declarations!$C$21+(Declarations!$C$7-Declarations!$C$21)*EXP(-Declarations!$D$21*$B18)+IF(Declarations!$E$21=0,0,Declarations!$E$21*($B18/Declarations!$F$21)*EXP(1-$B18/Declarations!$F$21))+IF($B18>=T_sale,Declarations!$G$21,0) -> 49.895831 | E18: =Declarations!$C$22+(Declarations!$C$8-Declarations!$C$22)*EXP(-Declarations!$D$22*$B18)+IF(Declarations!$E$22=0,0,Declarations!$E$22*($B18/Declarations!$F$22)*EXP(1-$B18/Declarations!$F$22))+IF($B18>=T_sale,Declarations!$G$22,0) -> 66.483993 | F18: =Declarations!$C$23+(Declarations!$C$10-Declarations!$C$23)*EXP(-Declarations!$D$23*$B18)+IF(Declarations!$E$23=0,0,Declarations!$E$23*($B18/Declarations!$F$23)*EXP(1-$B18/Declarations!$F$23))+IF($B18>=T_sale,Declarations!$G$23,0) -> 72.096844 | G18: =Declarations!$C$24+(Declarations!$C$4-Declarations!$C$24)*EXP(-Declarations!$D$24*$B18)+IF(Declarations!$E$24=0,0,Declarations!$E$24*($B18/Declarations!$F$24)*EXP(1-$B18/Declarations!$F$24))+IF($B18>=T_sale,Declarations!$G$24,0) -> 100.55717 | H18: =Declarations!$C$25+(Declarations!$C$7-Declarations!$C$25)*EXP(-Declarations!$D$25*$B18)+IF(Declarations!$E$25=0,0,Declarations!$E$25*($B18/Declarations!$F$25)*EXP(1-$B18/Declarations!$F$25))+IF($B18>=T_sale,Declarations!$G$25,0) -> 40.647491 | I18: =Declarations!$C$26+(Declarations!$C$8-Declarations!$C$26)*EXP(-Declarations!$D$26*$B18)+IF(Declarations!$E$26=0,0,Declarations!$E$26*($B18/Declarations!$F$26)*EXP(1-$B18/Declarations!$F$26))+IF($B18>=T_sale,Declarations!$G$26,0) -> 71.604451 | J18: =Declarations!$C$27+(Declarations!$C$10-Declarations!$C$27)*EXP(-Declarations!$D$27*$B18)+IF(Declarations!$E$27=0,0,Declarations!$E$27*($B18/Declarations!$F$27)*EXP(1-$B18/Declarations!$F$27))+IF($B18>=T_sale,Declarations!$G$27,0) -> 62.715656 | K18: =Declarations!$C$28+(Declarations!$C$4-Declarations!$C$28)*EXP(-Declarations!$D$28*$B18)+IF(Declarations!$E$28=0,0,Declarations!$E$28*($B18/Declarations!$F$28)*EXP(1-$B18/Declarations!$F$28))+IF($B18>=T_sale,Declarations!$G$28,0) -> 101.2089 | L18: =Declarations!$C$29+(Declarations!$C$7-Declarations!$C$29)*EXP(-Declarations!$D$29*$B18)+IF(Declarations!$E$29=0,0,Declarations!$E$29*($B18/Declarations!$F$29)*EXP(1-$B18/Declarations!$F$29))+IF($B18>=T_sale,Declarations!$G$29,0) -> 40.238699 | M18: =Declarations!$C$30+(Declarations!$C$8-Declarations!$C$30)*EXP(-Declarations!$D$30*$B18)+IF(Declarations!$E$30=0,0,Declarations!$E$30*($B18/Declarations!$F$30)*EXP(1-$B18/Declarations!$F$30))+IF($B18>=T_sale,Declarations!$G$30,0) -> 73.073454 | N18: =Declarations!$C$31+(Declarations!$C$10-Declarations!$C$31)*EXP(-Declarations!$D$31*$B18)+IF(Declarations!$E$31=0,0,Declarations!$E$31*($B18/Declarations!$F$31)*EXP(1-$B18/Declarations!$F$31))+IF($B18>=T_sale,Declarations!$G$31,0) -> 64.417876 | O18: =W_L*C18+W_T*D18+W_E*E18+W_R*F18 -> 32.847624 | P18: =W_L*G18+W_T*H18+W_E*I18+W_R*J18 -> 37.523363 | Q18: =W_L*K18+W_T*L18+W_E*M18+W_R*N18 -> 37.525795 | R18: =IF(AND(O18>=$B$9,O17<$B$9),A18,"")
A19: 7 | B19: =A19/12 -> 0.58333333 | C19: =Declarations!$C$20+(Declarations!$C$4-Declarations!$C$20)*EXP(-Declarations!$D$20*$B19)+IF(Declarations!$E$20=0,0,Declarations!$E$20*($B19/Declarations!$F$20)*EXP(1-$B19/Declarations!$F$20))+IF($B19>=T_sale,Declarations!$G$20,0) -> 85.632816 | D19: =Declarations!$C$21+(Declarations!$C$7-Declarations!$C$21)*EXP(-Declarations!$D$21*$B19)+IF(Declarations!$E$21=0,0,Declarations!$E$21*($B19/Declarations!$F$21)*EXP(1-$B19/Declarations!$F$21))+IF($B19>=T_sale,Declarations!$G$21,0) -> 51.154866 | E19: =Declarations!$C$22+(Declarations!$C$8-Declarations!$C$22)*EXP(-Declarations!$D$22*$B19)+IF(Declarations!$E$22=0,0,Declarations!$E$22*($B19/Declarations!$F$22)*EXP(1-$B19/Declarations!$F$22))+IF($B19>=T_sale,Declarations!$G$22,0) -> 66.069224 | F19: =Declarations!$C$23+(Declarations!$C$10-Declarations!$C$23)*EXP(-Declarations!$D$23*$B19)+IF(Declarations!$E$23=0,0,Declarations!$E$23*($B19/Declarations!$F$23)*EXP(1-$B19/Declarations!$F$23))+IF($B19>=T_sale,Declarations!$G$23,0) -> 72.671956 | G19: =Declarations!$C$24+(Declarations!$C$4-Declarations!$C$24)*EXP(-Declarations!$D$24*$B19)+IF(Declarations!$E$24=0,0,Declarations!$E$24*($B19/Declarations!$F$24)*EXP(1-$B19/Declarations!$F$24))+IF($B19>=T_sale,Declarations!$G$24,0) -> 100.64217 | H19: =Declarations!$C$25+(Declarations!$C$7-Declarations!$C$25)*EXP(-Declarations!$D$25*$B19)+IF(Declarations!$E$25=0,0,Declarations!$E$25*($B19/Declarations!$F$25)*EXP(1-$B19/Declarations!$F$25))+IF($B19>=T_sale,Declarations!$G$25,0) -> 40.592905 | I19: =Declarations!$C$26+(Declarations!$C$8-Declarations!$C$26)*EXP(-Declarations!$D$26*$B19)+IF(Declarations!$E$26=0,0,Declarations!$E$26*($B19/Declarations!$F$26)*EXP(1-$B19/Declarations!$F$26))+IF($B19>=T_sale,Declarations!$G$26,0) -> 71.692621 | J19: =Declarations!$C$27+(Declarations!$C$10-Declarations!$C$27)*EXP(-Declarations!$D$27*$B19)+IF(Declarations!$E$27=0,0,Declarations!$E$27*($B19/Declarations!$F$27)*EXP(1-$B19/Declarations!$F$27))+IF($B19>=T_sale,Declarations!$G$27,0) -> 62.522612 | K19: =Declarations!$C$28+(Declarations!$C$4-Declarations!$C$28)*EXP(-Declarations!$D$28*$B19)+IF(Declarations!$E$28=0,0,Declarations!$E$28*($B19/Declarations!$F$28)*EXP(1-$B19/Declarations!$F$28))+IF($B19>=T_sale,Declarations!$G$28,0) -> 101.38524 | L19: =Declarations!$C$29+(Declarations!$C$7-Declarations!$C$29)*EXP(-Declarations!$D$29*$B19)+IF(Declarations!$E$29=0,0,Declarations!$E$29*($B19/Declarations!$F$29)*EXP(1-$B19/Declarations!$F$29))+IF($B19>=T_sale,Declarations!$G$29,0) -> 40.119054 | M19: =Declarations!$C$30+(Declarations!$C$8-Declarations!$C$30)*EXP(-Declarations!$D$30*$B19)+IF(Declarations!$E$30=0,0,Declarations!$E$30*($B19/Declarations!$F$30)*EXP(1-$B19/Declarations!$F$30))+IF($B19>=T_sale,Declarations!$G$30,0) -> 73.362495 | N19: =Declarations!$C$31+(Declarations!$C$10-Declarations!$C$31)*EXP(-Declarations!$D$31*$B19)+IF(Declarations!$E$31=0,0,Declarations!$E$31*($B19/Declarations!$F$31)*EXP(1-$B19/Declarations!$F$31))+IF($B19>=T_sale,Declarations!$G$31,0) -> 64.481629 | O19: =W_L*C19+W_T*D19+W_E*E19+W_R*F19 -> 32.546237 | P19: =W_L*G19+W_T*H19+W_E*I19+W_R*J19 -> 37.601272 | Q19: =W_L*K19+W_T*L19+W_E*M19+W_R*N19 -> 37.596291 | R19: =IF(AND(O19>=$B$9,O18<$B$9),A19,"")
A20: 8 | B20: =A20/12 -> 0.66666667 | C20: =Declarations!$C$20+(Declarations!$C$4-Declarations!$C$20)*EXP(-Declarations!$D$20*$B20)+IF(Declarations!$E$20=0,0,Declarations!$E$20*($B20/Declarations!$F$20)*EXP(1-$B20/Declarations!$F$20))+IF($B20>=T_sale,Declarations!$G$20,0) -> 84.318474 | D20: =Declarations!$C$21+(Declarations!$C$7-Declarations!$C$21)*EXP(-Declarations!$D$21*$B20)+IF(Declarations!$E$21=0,0,Declarations!$E$21*($B20/Declarations!$F$21)*EXP(1-$B20/Declarations!$F$21))+IF($B20>=T_sale,Declarations!$G$21,0) -> 52.357497 | E20: =Declarations!$C$22+(Declarations!$C$8-Declarations!$C$22)*EXP(-Declarations!$D$22*$B20)+IF(Declarations!$E$22=0,0,Declarations!$E$22*($B20/Declarations!$F$22)*EXP(1-$B20/Declarations!$F$22))+IF($B20>=T_sale,Declarations!$G$22,0) -> 65.729176 | F20: =Declarations!$C$23+(Declarations!$C$10-Declarations!$C$23)*EXP(-Declarations!$D$23*$B20)+IF(Declarations!$E$23=0,0,Declarations!$E$23*($B20/Declarations!$F$23)*EXP(1-$B20/Declarations!$F$23))+IF($B20>=T_sale,Declarations!$G$23,0) -> 73.087473 | G20: =Declarations!$C$24+(Declarations!$C$4-Declarations!$C$24)*EXP(-Declarations!$D$24*$B20)+IF(Declarations!$E$24=0,0,Declarations!$E$24*($B20/Declarations!$F$24)*EXP(1-$B20/Declarations!$F$24))+IF($B20>=T_sale,Declarations!$G$24,0) -> 100.72508 | H20: =Declarations!$C$25+(Declarations!$C$7-Declarations!$C$25)*EXP(-Declarations!$D$25*$B20)+IF(Declarations!$E$25=0,0,Declarations!$E$25*($B20/Declarations!$F$25)*EXP(1-$B20/Declarations!$F$25))+IF($B20>=T_sale,Declarations!$G$25,0) -> 40.539445 | I20: =Declarations!$C$26+(Declarations!$C$8-Declarations!$C$26)*EXP(-Declarations!$D$26*$B20)+IF(Declarations!$E$26=0,0,Declarations!$E$26*($B20/Declarations!$F$26)*EXP(1-$B20/Declarations!$F$26))+IF($B20>=T_sale,Declarations!$G$26,0) -> 71.777545 | J20: =Declarations!$C$27+(Declarations!$C$10-Declarations!$C$27)*EXP(-Declarations!$D$27*$B20)+IF(Declarations!$E$27=0,0,Declarations!$E$27*($B20/Declarations!$F$27)*EXP(1-$B20/Declarations!$F$27))+IF($B20>=T_sale,Declarations!$G$27,0) -> 62.335117 | K20: =Declarations!$C$28+(Declarations!$C$4-Declarations!$C$28)*EXP(-Declarations!$D$28*$B20)+IF(Declarations!$E$28=0,0,Declarations!$E$28*($B20/Declarations!$F$28)*EXP(1-$B20/Declarations!$F$28))+IF($B20>=T_sale,Declarations!$G$28,0) -> 101.55509 | L20: =Declarations!$C$29+(Declarations!$C$7-Declarations!$C$29)*EXP(-Declarations!$D$29*$B20)+IF(Declarations!$E$29=0,0,Declarations!$E$29*($B20/Declarations!$F$29)*EXP(1-$B20/Declarations!$F$29))+IF($B20>=T_sale,Declarations!$G$29,0) -> 40.001387 | M20: =Declarations!$C$30+(Declarations!$C$8-Declarations!$C$30)*EXP(-Declarations!$D$30*$B20)+IF(Declarations!$E$30=0,0,Declarations!$E$30*($B20/Declarations!$F$30)*EXP(1-$B20/Declarations!$F$30))+IF($B20>=T_sale,Declarations!$G$30,0) -> 73.63744 | N20: =Declarations!$C$31+(Declarations!$C$10-Declarations!$C$31)*EXP(-Declarations!$D$31*$B20)+IF(Declarations!$E$31=0,0,Declarations!$E$31*($B20/Declarations!$F$31)*EXP(1-$B20/Declarations!$F$31))+IF($B20>=T_sale,Declarations!$G$31,0) -> 64.543808 | O20: =W_L*C20+W_T*D20+W_E*E20+W_R*F20 -> 32.329418 | P20: =W_L*G20+W_T*H20+W_E*I20+W_R*J20 -> 37.676738 | Q20: =W_L*K20+W_T*L20+W_E*M20+W_R*N20 -> 37.662527 | R20: =IF(AND(O20>=$B$9,O19<$B$9),A20,"")
A21: 9 | B21: =A21/12 -> 0.75 | C21: =Declarations!$C$20+(Declarations!$C$4-Declarations!$C$20)*EXP(-Declarations!$D$20*$B21)+IF(Declarations!$E$20=0,0,Declarations!$E$20*($B21/Declarations!$F$20)*EXP(1-$B21/Declarations!$F$20))+IF($B21>=T_sale,Declarations!$G$20,0) -> 83.153901 | D21: =Declarations!$C$21+(Declarations!$C$7-Declarations!$C$21)*EXP(-Declarations!$D$21*$B21)+IF(Declarations!$E$21=0,0,Declarations!$E$21*($B21/Declarations!$F$21)*EXP(1-$B21/Declarations!$F$21))+IF($B21>=T_sale,Declarations!$G$21,0) -> 53.506252 | E21: =Declarations!$C$22+(Declarations!$C$8-Declarations!$C$22)*EXP(-Declarations!$D$22*$B21)+IF(Declarations!$E$22=0,0,Declarations!$E$22*($B21/Declarations!$F$22)*EXP(1-$B21/Declarations!$F$22))+IF($B21>=T_sale,Declarations!$G$22,0) -> 65.457019 | F21: =Declarations!$C$23+(Declarations!$C$10-Declarations!$C$23)*EXP(-Declarations!$D$23*$B21)+IF(Declarations!$E$23=0,0,Declarations!$E$23*($B21/Declarations!$F$23)*EXP(1-$B21/Declarations!$F$23))+IF($B21>=T_sale,Declarations!$G$23,0) -> 73.361812 | G21: =Declarations!$C$24+(Declarations!$C$4-Declarations!$C$24)*EXP(-Declarations!$D$24*$B21)+IF(Declarations!$E$24=0,0,Declarations!$E$24*($B21/Declarations!$F$24)*EXP(1-$B21/Declarations!$F$24))+IF($B21>=T_sale,Declarations!$G$24,0) -> 100.80594 | H21: =Declarations!$C$25+(Declarations!$C$7-Declarations!$C$25)*EXP(-Declarations!$D$25*$B21)+IF(Declarations!$E$25=0,0,Declarations!$E$25*($B21/Declarations!$F$25)*EXP(1-$B21/Declarations!$F$25))+IF($B21>=T_sale,Declarations!$G$25,0) -> 40.487087 | I21: =Declarations!$C$26+(Declarations!$C$8-Declarations!$C$26)*EXP(-Declarations!$D$26*$B21)+IF(Declarations!$E$26=0,0,Declarations!$E$26*($B21/Declarations!$F$26)*EXP(1-$B21/Declarations!$F$26))+IF($B21>=T_sale,Declarations!$G$26,0) -> 71.859344 | J21: =Declarations!$C$27+(Declarations!$C$10-Declarations!$C$27)*EXP(-Declarations!$D$27*$B21)+IF(Declarations!$E$27=0,0,Declarations!$E$27*($B21/Declarations!$F$27)*EXP(1-$B21/Declarations!$F$27))+IF($B21>=T_sale,Declarations!$G$27,0) -> 62.153011 | K21: =Declarations!$C$28+(Declarations!$C$4-Declarations!$C$28)*EXP(-Declarations!$D$28*$B21)+IF(Declarations!$E$28=0,0,Declarations!$E$28*($B21/Declarations!$F$28)*EXP(1-$B21/Declarations!$F$28))+IF($B21>=T_sale,Declarations!$G$28,0) -> 101.71869 | L21: =Declarations!$C$29+(Declarations!$C$7-Declarations!$C$29)*EXP(-Declarations!$D$29*$B21)+IF(Declarations!$E$29=0,0,Declarations!$E$29*($B21/Declarations!$F$29)*EXP(1-$B21/Declarations!$F$29))+IF($B21>=T_sale,Declarations!$G$29,0) -> 39.885664 | M21: =Declarations!$C$30+(Declarations!$C$8-Declarations!$C$30)*EXP(-Declarations!$D$30*$B21)+IF(Declarations!$E$30=0,0,Declarations!$E$30*($B21/Declarations!$F$30)*EXP(1-$B21/Declarations!$F$30))+IF($B21>=T_sale,Declarations!$G$30,0) -> 73.898975 | N21: =Declarations!$C$31+(Declarations!$C$10-Declarations!$C$31)*EXP(-Declarations!$D$31*$B21)+IF(Declarations!$E$31=0,0,Declarations!$E$31*($B21/Declarations!$F$31)*EXP(1-$B21/Declarations!$F$31))+IF($B21>=T_sale,Declarations!$G$31,0) -> 64.604451 | O21: =W_L*C21+W_T*D21+W_E*E21+W_R*F21 -> 32.18884 | P21: =W_L*G21+W_T*H21+W_E*I21+W_R*J21 -> 37.749839 | Q21: =W_L*K21+W_T*L21+W_E*M21+W_R*N21 -> 37.724719 | R21: =IF(AND(O21>=$B$9,O20<$B$9),A21,"")
A22: 10 | B22: =A22/12 -> 0.83333333 | C22: =Declarations!$C$20+(Declarations!$C$4-Declarations!$C$20)*EXP(-Declarations!$D$20*$B22)+IF(Declarations!$E$20=0,0,Declarations!$E$20*($B22/Declarations!$F$20)*EXP(1-$B22/Declarations!$F$20))+IF($B22>=T_sale,Declarations!$G$20,0) -> 82.129102 | D22: =Declarations!$C$21+(Declarations!$C$7-Declarations!$C$21)*EXP(-Declarations!$D$21*$B22)+IF(Declarations!$E$21=0,0,Declarations!$E$21*($B22/Declarations!$F$21)*EXP(1-$B22/Declarations!$F$21))+IF($B22>=T_sale,Declarations!$G$21,0) -> 54.603543 | E22: =Declarations!$C$22+(Declarations!$C$8-Declarations!$C$22)*EXP(-Declarations!$D$22*$B22)+IF(Declarations!$E$22=0,0,Declarations!$E$22*($B22/Declarations!$F$22)*EXP(1-$B22/Declarations!$F$22))+IF($B22>=T_sale,Declarations!$G$22,0) -> 65.246439 | F22: =Declarations!$C$23+(Declarations!$C$10-Declarations!$C$23)*EXP(-Declarations!$D$23*$B22)+IF(Declarations!$E$23=0,0,Declarations!$E$23*($B22/Declarations!$F$23)*EXP(1-$B22/Declarations!$F$23))+IF($B22>=T_sale,Declarations!$G$23,0) -> 73.511646 | G22: =Declarations!$C$24+(Declarations!$C$4-Declarations!$C$24)*EXP(-Declarations!$D$24*$B22)+IF(Declarations!$E$24=0,0,Declarations!$E$24*($B22/Declarations!$F$24)*EXP(1-$B22/Declarations!$F$24))+IF($B22>=T_sale,Declarations!$G$24,0) -> 100.8848 | H22: =Declarations!$C$25+(Declarations!$C$7-Declarations!$C$25)*EXP(-Declarations!$D$25*$B22)+IF(Declarations!$E$25=0,0,Declarations!$E$25*($B22/Declarations!$F$25)*EXP(1-$B22/Declarations!$F$25))+IF($B22>=T_sale,Declarations!$G$25,0) -> 40.435809 | I22: =Declarations!$C$26+(Declarations!$C$8-Declarations!$C$26)*EXP(-Declarations!$D$26*$B22)+IF(Declarations!$E$26=0,0,Declarations!$E$26*($B22/Declarations!$F$26)*EXP(1-$B22/Declarations!$F$26))+IF($B22>=T_sale,Declarations!$G$26,0) -> 71.938132 | J22: =Declarations!$C$27+(Declarations!$C$10-Declarations!$C$27)*EXP(-Declarations!$D$27*$B22)+IF(Declarations!$E$27=0,0,Declarations!$E$27*($B22/Declarations!$F$27)*EXP(1-$B22/Declarations!$F$27))+IF($B22>=T_sale,Declarations!$G$27,0) -> 61.97614 | K22: =Declarations!$C$28+(Declarations!$C$4-Declarations!$C$28)*EXP(-Declarations!$D$28*$B22)+IF(Declarations!$E$28=0,0,Declarations!$E$28*($B22/Declarations!$F$28)*EXP(1-$B22/Declarations!$F$28))+IF($B22>=T_sale,Declarations!$G$28,0) -> 101.87626 | L22: =Declarations!$C$29+(Declarations!$C$7-Declarations!$C$29)*EXP(-Declarations!$D$29*$B22)+IF(Declarations!$E$29=0,0,Declarations!$E$29*($B22/Declarations!$F$29)*EXP(1-$B22/Declarations!$F$29))+IF($B22>=T_sale,Declarations!$G$29,0) -> 39.771854 | M22: =Declarations!$C$30+(Declarations!$C$8-Declarations!$C$30)*EXP(-Declarations!$D$30*$B22)+IF(Declarations!$E$30=0,0,Declarations!$E$30*($B22/Declarations!$F$30)*EXP(1-$B22/Declarations!$F$30))+IF($B22>=T_sale,Declarations!$G$30,0) -> 74.147755 | N22: =Declarations!$C$31+(Declarations!$C$10-Declarations!$C$31)*EXP(-Declarations!$D$31*$B22)+IF(Declarations!$E$31=0,0,Declarations!$E$31*($B22/Declarations!$F$31)*EXP(1-$B22/Declarations!$F$31))+IF($B22>=T_sale,Declarations!$G$31,0) -> 64.663598 | O22: =W_L*C22+W_T*D22+W_E*E22+W_R*F22 -> 32.116859 | P22: =W_L*G22+W_T*H22+W_E*I22+W_R*J22 -> 37.82065 | Q22: =W_L*K22+W_T*L22+W_E*M22+W_R*N22 -> 37.783069 | R22: =IF(AND(O22>=$B$9,O21<$B$9),A22,"")
A23: 11 | B23: =A23/12 -> 0.91666667 | C23: =Declarations!$C$20+(Declarations!$C$4-Declarations!$C$20)*EXP(-Declarations!$D$20*$B23)+IF(Declarations!$E$20=0,0,Declarations!$E$20*($B23/Declarations!$F$20)*EXP(1-$B23/Declarations!$F$20))+IF($B23>=T_sale,Declarations!$G$20,0) -> 81.234648 | D23: =Declarations!$C$21+(Declarations!$C$7-Declarations!$C$21)*EXP(-Declarations!$D$21*$B23)+IF(Declarations!$E$21=0,0,Declarations!$E$21*($B23/Declarations!$F$21)*EXP(1-$B23/Declarations!$F$21))+IF($B23>=T_sale,Declarations!$G$21,0) -> 55.651678 | E23: =Declarations!$C$22+(Declarations!$C$8-Declarations!$C$22)*EXP(-Declarations!$D$22*$B23)+IF(Declarations!$E$22=0,0,Declarations!$E$22*($B23/Declarations!$F$22)*EXP(1-$B23/Declarations!$F$22))+IF($B23>=T_sale,Declarations!$G$22,0) -> 65.091607 | F23: =Declarations!$C$23+(Declarations!$C$10-Declarations!$C$23)*EXP(-Declarations!$D$23*$B23)+IF(Declarations!$E$23=0,0,Declarations!$E$23*($B23/Declarations!$F$23)*EXP(1-$B23/Declarations!$F$23))+IF($B23>=T_sale,Declarations!$G$23,0) -> 73.552064 | G23: =Declarations!$C$24+(Declarations!$C$4-Declarations!$C$24)*EXP(-Declarations!$D$24*$B23)+IF(Declarations!$E$24=0,0,Declarations!$E$24*($B23/Declarations!$F$24)*EXP(1-$B23/Declarations!$F$24))+IF($B23>=T_sale,Declarations!$G$24,0) -> 100.96171 | H23: =Declarations!$C$25+(Declarations!$C$7-Declarations!$C$25)*EXP(-Declarations!$D$25*$B23)+IF(Declarations!$E$25=0,0,Declarations!$E$25*($B23/Declarations!$F$25)*EXP(1-$B23/Declarations!$F$25))+IF($B23>=T_sale,Declarations!$G$25,0) -> 40.385588 | I23: =Declarations!$C$26+(Declarations!$C$8-Declarations!$C$26)*EXP(-Declarations!$D$26*$B23)+IF(Declarations!$E$26=0,0,Declarations!$E$26*($B23/Declarations!$F$26)*EXP(1-$B23/Declarations!$F$26))+IF($B23>=T_sale,Declarations!$G$26,0) -> 72.01402 | J23: =Declarations!$C$27+(Declarations!$C$10-Declarations!$C$27)*EXP(-Declarations!$D$27*$B23)+IF(Declarations!$E$27=0,0,Declarations!$E$27*($B23/Declarations!$F$27)*EXP(1-$B23/Declarations!$F$27))+IF($B23>=T_sale,Declarations!$G$27,0) -> 61.804353 | K23: =Declarations!$C$28+(Declarations!$C$4-Declarations!$C$28)*EXP(-Declarations!$D$28*$B23)+IF(Declarations!$E$28=0,0,Declarations!$E$28*($B23/Declarations!$F$28)*EXP(1-$B23/Declarations!$F$28))+IF($B23>=T_sale,Declarations!$G$28,0) -> 102.02804 | L23: =Declarations!$C$29+(Declarations!$C$7-Declarations!$C$29)*EXP(-Declarations!$D$29*$B23)+IF(Declarations!$E$29=0,0,Declarations!$E$29*($B23/Declarations!$F$29)*EXP(1-$B23/Declarations!$F$29))+IF($B23>=T_sale,Declarations!$G$29,0) -> 39.659925 | M23: =Declarations!$C$30+(Declarations!$C$8-Declarations!$C$30)*EXP(-Declarations!$D$30*$B23)+IF(Declarations!$E$30=0,0,Declarations!$E$30*($B23/Declarations!$F$30)*EXP(1-$B23/Declarations!$F$30))+IF($B23>=T_sale,Declarations!$G$30,0) -> 74.384402 | N23: =Declarations!$C$31+(Declarations!$C$10-Declarations!$C$31)*EXP(-Declarations!$D$31*$B23)+IF(Declarations!$E$31=0,0,Declarations!$E$31*($B23/Declarations!$F$31)*EXP(1-$B23/Declarations!$F$31))+IF($B23>=T_sale,Declarations!$G$31,0) -> 64.721284 | O23: =W_L*C23+W_T*D23+W_E*E23+W_R*F23 -> 32.106467 | P23: =W_L*G23+W_T*H23+W_E*I23+W_R*J23 -> 37.889242 | Q23: =W_L*K23+W_T*L23+W_E*M23+W_R*N23 -> 37.837771 | R23: =IF(AND(O23>=$B$9,O22<$B$9),A23,"")
A24: 12 | B24: =A24/12 -> 1 | C24: =Declarations!$C$20+(Declarations!$C$4-Declarations!$C$20)*EXP(-Declarations!$D$20*$B24)+IF(Declarations!$E$20=0,0,Declarations!$E$20*($B24/Declarations!$F$20)*EXP(1-$B24/Declarations!$F$20))+IF($B24>=T_sale,Declarations!$G$20,0) -> 80.461645 | D24: =Declarations!$C$21+(Declarations!$C$7-Declarations!$C$21)*EXP(-Declarations!$D$21*$B24)+IF(Declarations!$E$21=0,0,Declarations!$E$21*($B24/Declarations!$F$21)*EXP(1-$B24/Declarations!$F$21))+IF($B24>=T_sale,Declarations!$G$21,0) -> 56.652857 | E24: =Declarations!$C$22+(Declarations!$C$8-Declarations!$C$22)*EXP(-Declarations!$D$22*$B24)+IF(Declarations!$E$22=0,0,Declarations!$E$22*($B24/Declarations!$F$22)*EXP(1-$B24/Declarations!$F$22))+IF($B24>=T_sale,Declarations!$G$22,0) -> 64.987141 | F24: =Declarations!$C$23+(Declarations!$C$10-Declarations!$C$23)*EXP(-Declarations!$D$23*$B24)+IF(Declarations!$E$23=0,0,Declarations!$E$23*($B24/Declarations!$F$23)*EXP(1-$B24/Declarations!$F$23))+IF($B24>=T_sale,Declarations!$G$23,0) -> 73.496699 | G24: =Declarations!$C$24+(Declarations!$C$4-Declarations!$C$24)*EXP(-Declarations!$D$24*$B24)+IF(Declarations!$E$24=0,0,Declarations!$E$24*($B24/Declarations!$F$24)*EXP(1-$B24/Declarations!$F$24))+IF($B24>=T_sale,Declarations!$G$24,0) -> 119.03673 | H24: =Declarations!$C$25+(Declarations!$C$7-Declarations!$C$25)*EXP(-Declarations!$D$25*$B24)+IF(Declarations!$E$25=0,0,Declarations!$E$25*($B24/Declarations!$F$25)*EXP(1-$B24/Declarations!$F$25))+IF($B24>=T_sale,Declarations!$G$25,0) -> 40.336402 | I24: =Declarations!$C$26+(Declarations!$C$8-Declarations!$C$26)*EXP(-Declarations!$D$26*$B24)+IF(Declarations!$E$26=0,0,Declarations!$E$26*($B24/Declarations!$F$26)*EXP(1-$B24/Declarations!$F$26))+IF($B24>=T_sale,Declarations!$G$26,0) -> 72.087116 | J24: =Declarations!$C$27+(Declarations!$C$10-Declarations!$C$27)*EXP(-Declarations!$D$27*$B24)+IF(Declarations!$E$27=0,0,Declarations!$E$27*($B24/Declarations!$F$27)*EXP(1-$B24/Declarations!$F$27))+IF($B24>=T_sale,Declarations!$G$27,0) -> 53.637505 | K24: =Declarations!$C$28+(Declarations!$C$4-Declarations!$C$28)*EXP(-Declarations!$D$28*$B24)+IF(Declarations!$E$28=0,0,Declarations!$E$28*($B24/Declarations!$F$28)*EXP(1-$B24/Declarations!$F$28))+IF($B24>=T_sale,Declarations!$G$28,0) -> 102.17423 | L24: =Declarations!$C$29+(Declarations!$C$7-Declarations!$C$29)*EXP(-Declarations!$D$29*$B24)+IF(Declarations!$E$29=0,0,Declarations!$E$29*($B24/Declarations!$F$29)*EXP(1-$B24/Declarations!$F$29))+IF($B24>=T_sale,Declarations!$G$29,0) -> 39.549846 | M24: =Declarations!$C$30+(Declarations!$C$8-Declarations!$C$30)*EXP(-Declarations!$D$30*$B24)+IF(Declarations!$E$30=0,0,Declarations!$E$30*($B24/Declarations!$F$30)*EXP(1-$B24/Declarations!$F$30))+IF($B24>=T_sale,Declarations!$G$30,0) -> 74.609507 | N24: =Declarations!$C$31+(Declarations!$C$10-Declarations!$C$31)*EXP(-Declarations!$D$31*$B24)+IF(Declarations!$E$31=0,0,Declarations!$E$31*($B24/Declarations!$F$31)*EXP(1-$B24/Declarations!$F$31))+IF($B24>=T_sale,Declarations!$G$31,0) -> 64.777545 | O24: =W_L*C24+W_T*D24+W_E*E24+W_R*F24 -> 32.151236 | P24: =W_L*G24+W_T*H24+W_E*I24+W_R*J24 -> 44.455685 | Q24: =W_L*K24+W_T*L24+W_E*M24+W_R*N24 -> 37.88901 | R24: =IF(AND(O24>=$B$9,O23<$B$9),A24,"")
... A72: 60 | B72: =A72/12 -> 5 | C72: =Declarations!$C$20+(Declarations!$C$4-Declarations!$C$20)*EXP(-Declarations!$D$20*$B72)+IF(Declarations!$E$20=0,0,Declarations!$E$20*($B72/Declarations!$F$20)*EXP(1-$B72/Declarations!$F$20))+IF($B72>=T_sale,Declarations!$G$20,0) -> 94.295601 | D72: =Declarations!$C$21+(Declarations!$C$7-Declarations!$C$21)*EXP(-Declarations!$D$21*$B72)+IF(Declarations!$E$21=0,0,Declarations!$E$21*($B72/Declarations!$F$21)*EXP(1-$B72/Declarations!$F$21))+IF($B72>=T_sale,Declarations!$G$21,0) -> 75.634669 | E72: =Declarations!$C$22+(Declarations!$C$8-Declarations!$C$22)*EXP(-Declarations!$D$22*$B72)+IF(Declarations!$E$22=0,0,Declarations!$E$22*($B72/Declarations!$F$22)*EXP(1-$B72/Declarations!$F$22))+IF($B72>=T_sale,Declarations!$G$22,0) -> 73.598331 | F72: =Declarations!$C$23+(Declarations!$C$10-Declarations!$C$23)*EXP(-Declarations!$D$23*$B72)+IF(Declarations!$E$23=0,0,Declarations!$E$23*($B72/Declarations!$F$23)*EXP(1-$B72/Declarations!$F$23))+IF($B72>=T_sale,Declarations!$G$23,0) -> 55.21775 | G72: =Declarations!$C$24+(Declarations!$C$4-Declarations!$C$24)*EXP(-Declarations!$D$24*$B72)+IF(Declarations!$E$24=0,0,Declarations!$E$24*($B72/Declarations!$F$24)*EXP(1-$B72/Declarations!$F$24))+IF($B72>=T_sale,Declarations!$G$24,0) -> 121.10748 | H72: =Declarations!$C$25+(Declarations!$C$7-Declarations!$C$25)*EXP(-Declarations!$D$25*$B72)+IF(Declarations!$E$25=0,0,Declarations!$E$25*($B72/Declarations!$F$25)*EXP(1-$B72/Declarations!$F$25))+IF($B72>=T_sale,Declarations!$G$25,0) -> 38.859514 | I72: =Declarations!$C$26+(Declarations!$C$8-Declarations!$C$26)*EXP(-Declarations!$D$26*$B72)+IF(Declarations!$E$26=0,0,Declarations!$E$26*($B72/Declarations!$F$26)*EXP(1-$B72/Declarations!$F$26))+IF($B72>=T_sale,Declarations!$G$26,0) -> 73.683802 | J72: =Declarations!$C$27+(Declarations!$C$10-Declarations!$C$27)*EXP(-Declarations!$D$27*$B72)+IF(Declarations!$E$27=0,0,Declarations!$E$27*($B72/Declarations!$F$27)*EXP(1-$B72/Declarations!$F$27))+IF($B72>=T_sale,Declarations!$G$27,0) -> 49.390192 | K72: =Declarations!$C$28+(Declarations!$C$4-Declarations!$C$28)*EXP(-Declarations!$D$28*$B72)+IF(Declarations!$E$28=0,0,Declarations!$E$28*($B72/Declarations!$F$28)*EXP(1-$B72/Declarations!$F$28))+IF($B72>=T_sale,Declarations!$G$28,0) -> 105.3676 | L72: =Declarations!$C$29+(Declarations!$C$7-Declarations!$C$29)*EXP(-Declarations!$D$29*$B72)+IF(Declarations!$E$29=0,0,Declarations!$E$29*($B72/Declarations!$F$29)*EXP(1-$B72/Declarations!$F$29))+IF($B72>=T_sale,Declarations!$G$29,0) -> 35.943036 | M72: =Declarations!$C$30+(Declarations!$C$8-Declarations!$C$30)*EXP(-Declarations!$D$30*$B72)+IF(Declarations!$E$30=0,0,Declarations!$E$30*($B72/Declarations!$F$30)*EXP(1-$B72/Declarations!$F$30))+IF($B72>=T_sale,Declarations!$G$30,0) -> 78.601703 | N72: =Declarations!$C$31+(Declarations!$C$10-Declarations!$C$31)*EXP(-Declarations!$D$31*$B72)+IF(Declarations!$E$31=0,0,Declarations!$E$31*($B72/Declarations!$F$31)*EXP(1-$B72/Declarations!$F$31))+IF($B72>=T_sale,Declarations!$G$31,0) -> 66.33061 | O72: =W_L*C72+W_T*D72+W_E*E72+W_R*F72 -> 47.077713 | P72: =W_L*G72+W_T*H72+W_E*I72+W_R*J72 -> 46.065151 | Q72: =W_L*K72+W_T*L72+W_E*M72+W_R*N72 -> 38.395434 | R72: =IF(AND(O72>=$B$9,O71<$B$9),A72,"")

Sheet Compare
A1: Compare paths, not just endpoints (AXIOM Lab 1.1, step 3; Worked Example 1.1, Step 5; Figure 1.3)
A3: Quantity | B3: Value | C3: Reading
A4: Digital liquidity: lowest monthly reading | B4: =MIN(Paths!$C$12:$C$72) -> 77.733933 | C4: Figure 1.3: low point
A5: Its month | B5: =INDEX(Paths!$A$12:$A$72,MATCH(B4,Paths!$C$12:$C$72,0)) -> 21 | C5: Worked Example 1.1, Step 5: month 21
A6: Lowest on a 0.01-year grid (rows 33-83) | B6: =MIN(B33:B83) -> 77.728787 | C6: Online Appendix 1.B.4: 77.73
A7: Its time (years) | B7: =INDEX(A33:A83,MATCH(B6,B33:B83,0)) -> 1.71 | C7: about 1.71 years
A8: Below today (points) | B8: =Liq_today-B6 -> 22.271213 | C8: 22.3 points
A9: Below today (share) | B9: =B8/Liq_today -> 0.22271213 | C9: 22 percent
A10: Below today ($ million) | B10: =B8*USD_pt -> 138.08152 | C10: about $138 million
A11: Restructuring: jump when the sale closes (points) | B11: =Declarations!G24 -> 18 | C11: Online Appendix 1.B.4
A12: Its value ($ million) | B12: =B11*USD_pt -> 111.6 | C12: about $112 million
A13: Restructuring liquidity in month 11 | B13: =Paths!G23 -> 100.96171 | C13: before the sale
A14: Restructuring liquidity in month 12 | B14: =Paths!G24 -> 119.03673 | C14: the sale has closed
A15: Digital strategic risk: highest monthly reading | B15: =MAX(Paths!$F$12:$F$72) -> 73.552064 | C15: the peak
A16: Its month | B16: =INDEX(Paths!$A$12:$A$72,MATCH(B15,Paths!$F$12:$F$72,0)) -> 11 | C16: month 11
A17: Margin to the ceiling (points) | B17: =Risk_ceiling-B15 -> 1.4479365 | C17: Table 1.5: 1.4 points, inside the +/-6 band
A18: Digital score: lowest | B18: =MIN(Paths!$O$12:$O$72) -> 32.106467
A19: Its month | B19: =INDEX(Paths!$A$12:$A$72,MATCH(B18,Paths!$O$12:$O$72,0)) -> 11
A20: Months with the digital score below today's | B20: =COUNTIF(Paths!$O$13:$O$72,"<"&Paths!$B$9) -> 28
A21: First month the digital score is back at today's | B21: =MIN(Paths!$R$13:$R$72) -> 29 | C21: Section 1.5.4: month 29
A23: Annual review | B23: Month | C23: Digital | D23: Restructuring | E23: Turnaround | F23: Digital's rank | G23: Digital last
A24: Year 1 | B24: 12 | C24: =INDEX(Paths!$O$12:$O$72,B24+1) -> 32.151236 | D24: =INDEX(Paths!$P$12:$P$72,B24+1) -> 44.455685 | E24: =INDEX(Paths!$Q$12:$Q$72,B24+1) -> 37.88901 | F24: =1+(D24>C24)+(E24>C24) -> 3 | G24: =IF(F24=3,1,0) -> 1
A25: Year 2 | B25: 24 | C25: =INDEX(Paths!$O$12:$O$72,B25+1) -> 35.274521 | D25: =INDEX(Paths!$P$12:$P$72,B25+1) -> 45.107989 | E25: =INDEX(Paths!$Q$12:$Q$72,B25+1) -> 38.290006 | F25: =1+(D25>C25)+(E25>C25) -> 3 | G25: =IF(F25=3,1,0) -> 1
A26: Year 3 | B26: 36 | C26: =INDEX(Paths!$O$12:$O$72,B26+1) -> 39.88373 | D26: =INDEX(Paths!$P$12:$P$72,B26+1) -> 45.5534 | E26: =INDEX(Paths!$Q$12:$Q$72,B26+1) -> 38.433092 | F26: =1+(D26>C26)+(E26>C26) -> 2 | G26: =IF(F26=3,1,0) -> 0
A27: Year 4 | B27: 48 | C27: =INDEX(Paths!$O$12:$O$72,B27+1) -> 43.961208 | D27: =INDEX(Paths!$P$12:$P$72,B27+1) -> 45.857547 | E27: =INDEX(Paths!$Q$12:$Q$72,B27+1) -> 38.445169 | F27: =1+(D27>C27)+(E27>C27) -> 2 | G27: =IF(F27=3,1,0) -> 0
A28: Year 5 | B28: 60 | C28: =INDEX(Paths!$O$12:$O$72,B28+1) -> 47.077713 | D28: =INDEX(Paths!$P$12:$P$72,B28+1) -> 46.065151 | E28: =INDEX(Paths!$Q$12:$Q$72,B28+1) -> 38.395434 | F28: =1+(D28>C28)+(E28>C28) -> 1 | G28: =IF(F28=3,1,0) -> 0
A29: Annual reviews that rank digital last | G29: =SUM(G24:G28) -> 2
A30: Section 1.5.4: digital stays below today's score until month 29, so annual reviews rank it last for two years.
A32: t (years) | B32: Digital liquidity
A33: 1.5 | B33: =Declarations!$C$20+(Declarations!$C$4-Declarations!$C$20)*EXP(-Declarations!$D$20*$A33)+IF(Declarations!$E$20=0,0,Declarations!$E$20*($A33/Declarations!$F$20)*EXP(1-$A33/Declarations!$F$20))+IF($A33>=T_sale,Declarations!$G$20,0) -> 77.936802
A34: 1.51 | B34: =Declarations!$C$20+(Declarations!$C$4-Declarations!$C$20)*EXP(-Declarations!$D$20*$A34)+IF(Declarations!$E$20=0,0,Declarations!$E$20*($A34/Declarations!$F$20)*EXP(1-$A34/Declarations!$F$20))+IF($A34>=T_sale,Declarations!$G$20,0) -> 77.917223
A35: 1.52 | B35: =Declarations!$C$20+(Declarations!$C$4-Declarations!$C$20)*EXP(-Declarations!$D$20*$A35)+IF(Declarations!$E$20=0,0,Declarations!$E$20*($A35/Declarations!$F$20)*EXP(1-$A35/Declarations!$F$20))+IF($A35>=T_sale,Declarations!$G$20,0) -> 77.898671
A36: 1.53 | B36: =Declarations!$C$20+(Declarations!$C$4-Declarations!$C$20)*EXP(-Declarations!$D$20*$A36)+IF(Declarations!$E$20=0,0,Declarations!$E$20*($A36/Declarations!$F$20)*EXP(1-$A36/Declarations!$F$20))+IF($A36>=T_sale,Declarations!$G$20,0) -> 77.881136
A37: 1.54 | B37: =Declarations!$C$20+(Declarations!$C$4-Declarations!$C$20)*EXP(-Declarations!$D$20*$A37)+IF(Declarations!$E$20=0,0,Declarations!$E$20*($A37/Declarations!$F$20)*EXP(1-$A37/Declarations!$F$20))+IF($A37>=T_sale,Declarations!$G$20,0) -> 77.864608
A38: 1.55 | B38: =Declarations!$C$20+(Declarations!$C$4-Declarations!$C$20)*EXP(-Declarations!$D$20*$A38)+IF(Declarations!$E$20=0,0,Declarations!$E$20*($A38/Declarations!$F$20)*EXP(1-$A38/Declarations!$F$20))+IF($A38>=T_sale,Declarations!$G$20,0) -> 77.849079
A39: 1.56 | B39: =Declarations!$C$20+(Declarations!$C$4-Declarations!$C$20)*EXP(-Declarations!$D$20*$A39)+IF(Declarations!$E$20=0,0,Declarations!$E$20*($A39/Declarations!$F$20)*EXP(1-$A39/Declarations!$F$20))+IF($A39>=T_sale,Declarations!$G$20,0) -> 77.834537
A40: 1.57 | B40: =Declarations!$C$20+(Declarations!$C$4-Declarations!$C$20)*EXP(-Declarations!$D$20*$A40)+IF(Declarations!$E$20=0,0,Declarations!$E$20*($A40/Declarations!$F$20)*EXP(1-$A40/Declarations!$F$20))+IF($A40>=T_sale,Declarations!$G$20,0) -> 77.820975
A41: 1.58 | B41: =Declarations!$C$20+(Declarations!$C$4-Declarations!$C$20)*EXP(-Declarations!$D$20*$A41)+IF(Declarations!$E$20=0,0,Declarations!$E$20*($A41/Declarations!$F$20)*EXP(1-$A41/Declarations!$F$20))+IF($A41>=T_sale,Declarations!$G$20,0) -> 77.808383
A42: 1.59 | B42: =Declarations!$C$20+(Declarations!$C$4-Declarations!$C$20)*EXP(-Declarations!$D$20*$A42)+IF(Declarations!$E$20=0,0,Declarations!$E$20*($A42/Declarations!$F$20)*EXP(1-$A42/Declarations!$F$20))+IF($A42>=T_sale,Declarations!$G$20,0) -> 77.79675
A43: 1.6 | B43: =Declarations!$C$20+(Declarations!$C$4-Declarations!$C$20)*EXP(-Declarations!$D$20*$A43)+IF(Declarations!$E$20=0,0,Declarations!$E$20*($A43/Declarations!$F$20)*EXP(1-$A43/Declarations!$F$20))+IF($A43>=T_sale,Declarations!$G$20,0) -> 77.786069
A44: 1.61 | B44: =Declarations!$C$20+(Declarations!$C$4-Declarations!$C$20)*EXP(-Declarations!$D$20*$A44)+IF(Declarations!$E$20=0,0,Declarations!$E$20*($A44/Declarations!$F$20)*EXP(1-$A44/Declarations!$F$20))+IF($A44>=T_sale,Declarations!$G$20,0) -> 77.77633
... A83: 2 | B83: =Declarations!$C$20+(Declarations!$C$4-Declarations!$C$20)*EXP(-Declarations!$D$20*$A83)+IF(Declarations!$E$20=0,0,Declarations!$E$20*($A83/Declarations!$F$20)*EXP(1-$A83/Declarations!$F$20))+IF($A83>=T_sale,Declarations!$G$20,0) -> 78.040976

Sheet Uncertainty
A1: Add uncertainty: the digital program's liquidity under the book's declared uncertainty (AXIOM Lab 1.1, step 4; Volume I, Worked Example 8.1)
A2: The plan is Chapter 1's digital liquidity path read quarterly in $ million. The 100,000-path simulation runs in the notebook with the book's seed 8; its results are engine values (green).
A4: Quarter | B4: t (years) | C4: Plan (index) | D4: Plan ($ million) | E4: Above the floor | F4: Phased build (index) | G4: Phased build ($ million) | I4: Quantity | J4: Value | K4: Reading
A5: 0 | B5: =A5/4 -> 0 | C5: =Declarations!$C$20+(Declarations!$C$4-Declarations!$C$20)*EXP(-Declarations!$D$20*$B5)+IF(Declarations!$E$20=0,0,Declarations!$E$20*($B5/Declarations!$F$20)*EXP(1-$B5/Declarations!$F$20))+IF($B5>=T_sale,Declarations!$G$20,0) -> 100 | D5: =C5*USD_pt -> 620 | E5: =D5-Floor_liq -> 270 | F5: =Declarations!$C$20+(Declarations!$C$4-Declarations!$C$20)*EXP(-Declarations!$D$20*$B5)+IF((-Depth_ph)=0,0,(-Depth_ph)*($B5/Declarations!$F$20)*EXP(1-$B5/Declarations!$F$20))+IF($B5>=T_sale,Declarations!$G$20,0) -> 100 | G5: =F5*USD_pt -> 620 | I5: Plan trough ($ million) | J5: =MIN(D5:D17) -> 481.95038 | K5: Section 1.5.10: $482 million
A6: 1 | B6: =A6/4 -> 0.25 | C6: =Declarations!$C$20+(Declarations!$C$4-Declarations!$C$20)*EXP(-Declarations!$D$20*$B6)+IF(Declarations!$E$20=0,0,Declarations!$E$20*($B6/Declarations!$F$20)*EXP(1-$B6/Declarations!$F$20))+IF($B6>=T_sale,Declarations!$G$20,0) -> 92.60931 | D6: =C6*USD_pt -> 574.17772 | E6: =D6-Floor_liq -> 224.17772 | F6: =Declarations!$C$20+(Declarations!$C$4-Declarations!$C$20)*EXP(-Declarations!$D$20*$B6)+IF((-Depth_ph)=0,0,(-Depth_ph)*($B6/Declarations!$F$20)*EXP(1-$B6/Declarations!$F$20))+IF($B6>=T_sale,Declarations!$G$20,0) -> 95.008185 | G6: =F6*USD_pt -> 589.05075 | I6: Its quarter | J6: =INDEX(A5:A17,MATCH(J5,D5:D17,0)) -> 7 | K6: quarter 7 = month 21
A7: 2 | B7: =A7/4 -> 0.5 | C7: =Declarations!$C$20+(Declarations!$C$4-Declarations!$C$20)*EXP(-Declarations!$D$20*$B7)+IF(Declarations!$E$20=0,0,Declarations!$E$20*($B7/Declarations!$F$20)*EXP(1-$B7/Declarations!$F$20))+IF($B7>=T_sale,Declarations!$G$20,0) -> 87.107516 | D7: =C7*USD_pt -> 540.0666 | E7: =D7-Floor_liq -> 190.0666 | F7: =Declarations!$C$20+(Declarations!$C$4-Declarations!$C$20)*EXP(-Declarations!$D$20*$B7)+IF((-Depth_ph)=0,0,(-Depth_ph)*($B7/Declarations!$F$20)*EXP(1-$B7/Declarations!$F$20))+IF($B7>=T_sale,Declarations!$G$20,0) -> 91.341516 | G7: =F7*USD_pt -> 566.3174 | I7: Above the floor ($ million) | J7: =J5-Floor_liq -> 131.95038 | K7: Table 1.4: $132 million
A8: 3 | B8: =A8/4 -> 0.75 | C8: =Declarations!$C$20+(Declarations!$C$4-Declarations!$C$20)*EXP(-Declarations!$D$20*$B8)+IF(Declarations!$E$20=0,0,Declarations!$E$20*($B8/Declarations!$F$20)*EXP(1-$B8/Declarations!$F$20))+IF($B8>=T_sale,Declarations!$G$20,0) -> 83.153901 | D8: =C8*USD_pt -> 515.55419 | E8: =D8-Floor_liq -> 165.55419 | F8: =Declarations!$C$20+(Declarations!$C$4-Declarations!$C$20)*EXP(-Declarations!$D$20*$B8)+IF((-Depth_ph)=0,0,(-Depth_ph)*($B8/Declarations!$F$20)*EXP(1-$B8/Declarations!$F$20))+IF($B8>=T_sale,Declarations!$G$20,0) -> 88.758639 | G8: =F8*USD_pt -> 550.30356 | I8: The program's draw ($ million) | J8: =D5-J5 -> 138.04962 | K8: Section 1.5.4: $138 million
A9: 4 | B9: =A9/4 -> 1 | C9: =Declarations!$C$20+(Declarations!$C$4-Declarations!$C$20)*EXP(-Declarations!$D$20*$B9)+IF(Declarations!$E$20=0,0,Declarations!$E$20*($B9/Declarations!$F$20)*EXP(1-$B9/Declarations!$F$20))+IF($B9>=T_sale,Declarations!$G$20,0) -> 80.461645 | D9: =C9*USD_pt -> 498.8622 | E9: =D9-Floor_liq -> 148.8622 | F9: =Declarations!$C$20+(Declarations!$C$4-Declarations!$C$20)*EXP(-Declarations!$D$20*$B9)+IF((-Depth_ph)=0,0,(-Depth_ph)*($B9/Declarations!$F$20)*EXP(1-$B9/Declarations!$F$20))+IF($B9>=T_sale,Declarations!$G$20,0) -> 87.05653 | G9: =F9*USD_pt -> 539.75049 | I9: Phased build's trough ($ million) | J9: =MIN(G5:G17) -> 530.97392 | K9: Worked Example 8.1: $531 million
A10: 5 | B10: =A10/4 -> 1.25 | C10: =Declarations!$C$20+(Declarations!$C$4-Declarations!$C$20)*EXP(-Declarations!$D$20*$B10)+IF(Declarations!$E$20=0,0,Declarations!$E$20*($B10/Declarations!$F$20)*EXP(1-$B10/Declarations!$F$20))+IF($B10>=T_sale,Declarations!$G$20,0) -> 78.789868 | D10: =C10*USD_pt -> 488.49718 | E10: =D10-Floor_liq -> 138.49718 | F10: =Declarations!$C$20+(Declarations!$C$4-Declarations!$C$20)*EXP(-Declarations!$D$20*$B10)+IF((-Depth_ph)=0,0,(-Depth_ph)*($B10/Declarations!$F$20)*EXP(1-$B10/Declarations!$F$20))+IF($B10>=T_sale,Declarations!$G$20,0) -> 86.064825 | G10: =F10*USD_pt -> 533.60192 | I10: Long-run sd of the surprises ($ million) | J10: =SD_w/SQRT(1-Carry_q^2) -> 62.5 | K10: Worked Example 8.1, Step 2
A11: 6 | B11: =A11/4 -> 1.5 | C11: =Declarations!$C$20+(Declarations!$C$4-Declarations!$C$20)*EXP(-Declarations!$D$20*$B11)+IF(Declarations!$E$20=0,0,Declarations!$E$20*($B11/Declarations!$F$20)*EXP(1-$B11/Declarations!$F$20))+IF($B11>=T_sale,Declarations!$G$20,0) -> 77.936802 | D11: =C11*USD_pt -> 483.20817 | E11: =D11-Floor_liq -> 133.20817 | F11: =Declarations!$C$20+(Declarations!$C$4-Declarations!$C$20)*EXP(-Declarations!$D$20*$B11)+IF((-Depth_ph)=0,0,(-Depth_ph)*($B11/Declarations!$F$20)*EXP(1-$B11/Declarations!$F$20))+IF($B11>=T_sale,Declarations!$G$20,0) -> 85.640954 | G11: =F11*USD_pt -> 530.97392 | I11: Headroom at the trough, in long-run sds | J11: =J7/J10 -> 2.1112061
A12: 7 | B12: =A12/4 -> 1.75 | C12: =Declarations!$C$20+(Declarations!$C$4-Declarations!$C$20)*EXP(-Declarations!$D$20*$B12)+IF(Declarations!$E$20=0,0,Declarations!$E$20*($B12/Declarations!$F$20)*EXP(1-$B12/Declarations!$F$20))+IF($B12>=T_sale,Declarations!$G$20,0) -> 77.733933 | D12: =C12*USD_pt -> 481.95038 | E12: =D12-Floor_liq -> 131.95038 | F12: =Declarations!$C$20+(Declarations!$C$4-Declarations!$C$20)*EXP(-Declarations!$D$20*$B12)+IF((-Depth_ph)=0,0,(-Depth_ph)*($B12/Declarations!$F$20)*EXP(1-$B12/Declarations!$F$20))+IF($B12>=T_sale,Declarations!$G$20,0) -> 85.665972 | G12: =F12*USD_pt -> 531.12903 | I12: Closures' plan line ($ million a year) | J12: =Lam_cl*J_mean -> 12
A13: 8 | B13: =A13/4 -> 2 | C13: =Declarations!$C$20+(Declarations!$C$4-Declarations!$C$20)*EXP(-Declarations!$D$20*$B13)+IF(Declarations!$E$20=0,0,Declarations!$E$20*($B13/Declarations!$F$20)*EXP(1-$B13/Declarations!$F$20))+IF($B13>=T_sale,Declarations!$G$20,0) -> 78.040976 | D13: =C13*USD_pt -> 483.85405 | E13: =D13-Floor_liq -> 133.85405 | F13: =Declarations!$C$20+(Declarations!$C$4-Declarations!$C$20)*EXP(-Declarations!$D$20*$B13)+IF((-Depth_ph)=0,0,(-Depth_ph)*($B13/Declarations!$F$20)*EXP(1-$B13/Declarations!$F$20))+IF($B13>=T_sale,Declarations!$G$20,0) -> 86.040976 | G13: =F13*USD_pt -> 533.45405 | I13: P(at least one closure in the program) | J13: =1-EXP(-Lam_cl*Years_prog) -> 0.25918178
A14: 9 | B14: =A14/4 -> 2.25 | C14: =Declarations!$C$20+(Declarations!$C$4-Declarations!$C$20)*EXP(-Declarations!$D$20*$B14)+IF(Declarations!$E$20=0,0,Declarations!$E$20*($B14/Declarations!$F$20)*EXP(1-$B14/Declarations!$F$20))+IF($B14>=T_sale,Declarations!$G$20,0) -> 78.741578 | D14: =C14*USD_pt -> 488.19778 | E14: =D14-Floor_liq -> 138.19778 | F14: =Declarations!$C$20+(Declarations!$C$4-Declarations!$C$20)*EXP(-Declarations!$D$20*$B14)+IF((-Depth_ph)=0,0,(-Depth_ph)*($B14/Declarations!$F$20)*EXP(1-$B14/Declarations!$F$20))+IF($B14>=T_sale,Declarations!$G$20,0) -> 86.68405 | G14: =F14*USD_pt -> 537.44111 | I14: Closure size: gamma shape | J14: =(J_mean/J_sd)^2 -> 5.76
A15: 10 | B15: =A15/4 -> 2.5 | C15: =Declarations!$C$20+(Declarations!$C$4-Declarations!$C$20)*EXP(-Declarations!$D$20*$B15)+IF(Declarations!$E$20=0,0,Declarations!$E$20*($B15/Declarations!$F$20)*EXP(1-$B15/Declarations!$F$20))+IF($B15>=T_sale,Declarations!$G$20,0) -> 79.739628 | D15: =C15*USD_pt -> 494.3857 | E15: =D15-Floor_liq -> 144.3857 | F15: =Declarations!$C$20+(Declarations!$C$4-Declarations!$C$20)*EXP(-Declarations!$D$20*$B15)+IF((-Depth_ph)=0,0,(-Depth_ph)*($B15/Declarations!$F$20)*EXP(1-$B15/Declarations!$F$20))+IF($B15>=T_sale,Declarations!$G$20,0) -> 87.527636 | G15: =F15*USD_pt -> 542.67134 | I15: Closure size: gamma scale ($ million) | J15: =J_sd^2/J_mean -> 20.833333
A16: 11 | B16: =A16/4 -> 2.75 | C16: =Declarations!$C$20+(Declarations!$C$4-Declarations!$C$20)*EXP(-Declarations!$D$20*$B16)+IF(Declarations!$E$20=0,0,Declarations!$E$20*($B16/Declarations!$F$20)*EXP(1-$B16/Declarations!$F$20))+IF($B16>=T_sale,Declarations!$G$20,0) -> 80.956121 | D16: =C16*USD_pt -> 501.92795 | E16: =D16-Floor_liq -> 151.92795 | F16: =Declarations!$C$20+(Declarations!$C$4-Declarations!$C$20)*EXP(-Declarations!$D$20*$B16)+IF((-Depth_ph)=0,0,(-Depth_ph)*($B16/Declarations!$F$20)*EXP(1-$B16/Declarations!$F$20))+IF($B16>=T_sale,Declarations!$G$20,0) -> 88.516303 | G16: =F16*USD_pt -> 548.80108 | I16: A bad closure: 90th percentile ($ million) | J16: =GAMMAINV(0.9,J14,J15) -> 186.86698 | K16: Section 1.5.4: $187 million
A17: 12 | B17: =A17/4 -> 3 | C17: =Declarations!$C$20+(Declarations!$C$4-Declarations!$C$20)*EXP(-Declarations!$D$20*$B17)+IF(Declarations!$E$20=0,0,Declarations!$E$20*($B17/Declarations!$F$20)*EXP(1-$B17/Declarations!$F$20))+IF($B17>=T_sale,Declarations!$G$20,0) -> 82.326459 | D17: =C17*USD_pt -> 510.42405 | E17: =D17-Floor_liq -> 160.42405 | F17: =Declarations!$C$20+(Declarations!$C$4-Declarations!$C$20)*EXP(-Declarations!$D$20*$B17)+IF((-Depth_ph)=0,0,(-Depth_ph)*($B17/Declarations!$F$20)*EXP(1-$B17/Declarations!$F$20))+IF($B17>=T_sale,Declarations!$G$20,0) -> 89.604827 | G17: =F17*USD_pt -> 555.54993 | I17: Cash above the floor today ($ million) | J17: =Liq_usd-Floor_liq -> 270 | K17: $270 million
I18: The draw plus a bad closure ($ million) | J18: =J8+J16 -> 324.91659 | K18: Section 1.5.4: $325 million
I19: Left over (negative: the same cash promised twice) | J19: =J17-J18 -> -54.916594
I21: Simulation (engine, seed 8: the book's draws) | J21: Plan trough | K21: Breach odds | L21: s.e. | M21: Worst 5% of troughs | N21: Below the floor | O21: Printed in the book
I22: plan as drawn | J22: 481.95038 | K22: 0.24622 | L22: 0.0013623352 | M22: 166.32781 | N22: =Floor_liq-M22 -> 183.67219 | O22: 24.6% (Section 1.5.3)
I23: standby line ($100m) | J23: 481.95038 | K23: 0.12374 | L23: 0.0010412896 | M23: 285.55156 | N23: =Floor_liq-M23 -> 64.448441 | O23: 12.4% (Worked Example 8.1)
I24: phased build | J24: 530.97392 | K24: 0.13068 | L24: 0.0010658459 | M24: 213.37745 | N24: =Floor_liq-M24 -> 136.62255 | O24: 13.1% (Worked Example 8.1)
I25: line and phased build | J25: 530.97392 | K25: 0.03003 | L25: 0.00053970547 | M25: 332.46785 | N25: =Floor_liq-M25 -> 17.532146 | O25: 3.0% (Section 1.5.3); $18 million below (Section 1.5.4)
I27: Fan at quarter 7: 10th percentile ($ million) | J27: 356.91554
I28: Fan at quarter 7: 90th percentile ($ million) | J28: 555.96342
I29: Width of the band holding 80 percent of paths | J29: =J28-J27 -> 199.04788
I31: Drawn, as in the book, with seed 8 (Volume II, Online Appendix 1.B.4: "Volume I's Chapter 8 model, random seed 8"). A fresh stream with the lab's seed 26101 differs only by sampling error.

Sheet Scorecard
A1: Build your own score: every weighting ties different companies (AXIOM Lab 1.1, step 5; Worked Example 1.1, Steps 3-4; Online Appendix 1.B.2)
A3: Year 5 | B3: Digital | C3: Restructuring | D3: Turnaround | E3: CFO's weight | F3: Digital's advantage
A4: liquidity | B4: =Paths!C5 -> 94.295601 | C4: =Paths!D5 -> 121.10748 | D4: =Paths!E5 -> 105.3676 | E4: =W_L -> 0.25 | F4: =SIGN(E4)*(B4-C4) -> -26.811878 | G4: Digital's advantage: digital less restructuring, sign reversed for strategic risk (lower is better).
A5: technology platform | B5: =Paths!C6 -> 75.634669 | C5: =Paths!D6 -> 38.859514 | D5: =Paths!E6 -> 35.943036 | E5: =W_T -> 0.25 | F5: =SIGN(E5)*(B5-C5) -> 36.775155
A6: operational efficiency | B6: =Paths!C7 -> 73.598331 | C6: =Paths!D7 -> 73.683802 | D6: =Paths!E7 -> 78.601703 | E6: =W_E -> 0.25 | F6: =SIGN(E6)*(B6-C6) -> -0.085471354
A7: strategic risk | B7: =Paths!C8 -> 55.21775 | C7: =Paths!D8 -> 49.390192 | D7: =Paths!E8 -> 66.33061 | E7: =W_R -> -0.25 | F7: =SIGN(E7)*(B7-C7) -> -5.827558
A8: Score | B8: =SUMPRODUCT($E$4:$E$7,B4:B7) -> 47.077713 | C8: =SUMPRODUCT($E$4:$E$7,C4:C7) -> 46.065151 | D8: =SUMPRODUCT($E$4:$E$7,D4:D7) -> 38.395434
A10: Digital's lead over restructuring (points) | B10: =B8-C8 -> 1.0125619 | C10: Section 1.5.4: 1.01
A11: Liquidity points that tie them (Step 3) | B11: =B10/E4 -> 4.0502475 | C11: Online Appendix 1.B.2: 4.05
A12: Their value ($ million) | B12: =B11*USD_pt -> 25.111534 | C12: about $25 million
A13: Score-matched restructured liquidity | B13: =C4+B11 -> 125.15773 | C13: Step 3: 125.2
A14: Its score | B14: =E4*B13+E5*C5+E6*C6+E7*C7 -> 47.077713 | C14: equal to digital's: the board should be indifferent
A15: Weight points moved from technology to liquidity that tie | B15: =B10/(0.01*(F5-F4)) -> 1.5924031 | C15: Table 1.4: 1.6
A16: ... from technology to efficiency | B16: =B10/(0.01*(F5-F6)) -> 2.7470013
A17: ... from technology to strategic risk | B17: =B10/(0.01*(F5-F7)) -> 2.3767545
A19: Your weighting | B19: w liquidity | C19: w technology | D19: w efficiency | E19: w strategic risk | F19: Digital | G19: Restructuring | H19: Turnaround | I19: Leader | J19: Runner-up | K19: Extra liquidity for the runner-up | L19: Leader's score | M19: Runner-up's score with it
A20: CFO | B20: =W_L -> 0.25 | C20: =W_T -> 0.25 | D20: =W_E -> 0.25 | E20: =W_R -> -0.25 | F20: =$B20*B$4+$C20*B$5+$D20*B$6+$E20*B$7 -> 47.077713 | G20: =$B20*C$4+$C20*C$5+$D20*C$6+$E20*C$7 -> 46.065151 | H20: =$B20*D$4+$C20*D$5+$D20*D$6+$E20*D$7 -> 38.395434 | I20: =INDEX($F$19:$H$19,MATCH(MAX(F20:H20),F20:H20,0)) -> Digital | J20: =INDEX($F$19:$H$19,MATCH(LARGE(F20:H20,2),F20:H20,0)) -> Restructuring | K20: =(MAX(F20:H20)-LARGE(F20:H20,2))/B20 -> 4.0502475 | L20: =MAX(F20:H20) -> 47.077713 | M20: =B20*(INDEX($B$4:$D$4,MATCH(J20,$B$3:$D$3,0))+K20)+C20*INDEX($B$5:$D$5,MATCH(J20,$B$3:$D$3,0))+D20*INDEX($B$6:$D$6,MATCH(J20,$B$3:$D$3,0))+E20*INDEX($B$7:$D$7,MATCH(J20,$B$3:$D$3,0)) -> 47.077713
A21: liquidity first | B21: 0.4 | C21: 0.2 | D21: 0.2 | E21: -0.2 | F21: =$B21*B$4+$C21*B$5+$D21*B$6+$E21*B$7 -> 56.521291 | G21: =$B21*C$4+$C21*C$5+$D21*C$6+$E21*C$7 -> 61.073617 | H21: =$B21*D$4+$C21*D$5+$D21*D$6+$E21*D$7 -> 51.789868 | I21: =INDEX($F$19:$H$19,MATCH(MAX(F21:H21),F21:H21,0)) -> Restructuring | J21: =INDEX($F$19:$H$19,MATCH(LARGE(F21:H21,2),F21:H21,0)) -> Digital | K21: =(MAX(F21:H21)-LARGE(F21:H21,2))/B21 -> 11.380815 | L21: =MAX(F21:H21) -> 61.073617 | M21: =B21*(INDEX($B$4:$D$4,MATCH(J21,$B$3:$D$3,0))+K21)+C21*INDEX($B$5:$D$5,MATCH(J21,$B$3:$D$3,0))+D21*INDEX($B$6:$D$6,MATCH(J21,$B$3:$D$3,0))+E21*INDEX($B$7:$D$7,MATCH(J21,$B$3:$D$3,0)) -> 61.073617
A22: technology first | B22: 0.2 | C22: 0.4 | D22: 0.2 | E22: -0.2 | F22: =$B22*B$4+$C22*B$5+$D22*B$6+$E22*B$7 -> 52.789104 | G22: =$B22*C$4+$C22*C$5+$D22*C$6+$E22*C$7 -> 44.624024 | H22: =$B22*D$4+$C22*D$5+$D22*D$6+$E22*D$7 -> 37.904954 | I22: =INDEX($F$19:$H$19,MATCH(MAX(F22:H22),F22:H22,0)) -> Digital | J22: =INDEX($F$19:$H$19,MATCH(LARGE(F22:H22,2),F22:H22,0)) -> Restructuring | K22: =(MAX(F22:H22)-LARGE(F22:H22,2))/B22 -> 40.825402 | L22: =MAX(F22:H22) -> 52.789104 | M22: =B22*(INDEX($B$4:$D$4,MATCH(J22,$B$3:$D$3,0))+K22)+C22*INDEX($B$5:$D$5,MATCH(J22,$B$3:$D$3,0))+D22*INDEX($B$6:$D$6,MATCH(J22,$B$3:$D$3,0))+E22*INDEX($B$7:$D$7,MATCH(J22,$B$3:$D$3,0)) -> 52.789104
A23: risk first | B23: 0.2 | C23: 0.2 | D23: 0.2 | E23: -0.4 | F23: =$B23*B$4+$C23*B$5+$D23*B$6+$E23*B$7 -> 26.61862 | G23: =$B23*C$4+$C23*C$5+$D23*C$6+$E23*C$7 -> 26.974083 | H23: =$B23*D$4+$C23*D$5+$D23*D$6+$E23*D$7 -> 17.450225 | I23: =INDEX($F$19:$H$19,MATCH(MAX(F23:H23),F23:H23,0)) -> Restructuring | J23: =INDEX($F$19:$H$19,MATCH(LARGE(F23:H23,2),F23:H23,0)) -> Digital | K23: =(MAX(F23:H23)-LARGE(F23:H23,2))/B23 -> 1.7773105 | L23: =MAX(F23:H23) -> 26.974083 | M23: =B23*(INDEX($B$4:$D$4,MATCH(J23,$B$3:$D$3,0))+K23)+C23*INDEX($B$5:$D$5,MATCH(J23,$B$3:$D$3,0))+D23*INDEX($B$6:$D$6,MATCH(J23,$B$3:$D$3,0))+E23*INDEX($B$7:$D$7,MATCH(J23,$B$3:$D$3,0)) -> 26.974083
A24: Change any weight: the runner-up, raised by the extra liquidity, always scores exactly the leader's score. No weighting avoids ties (Proposition 1.2).
A26: Result 1.B.2: moves that leave the CFO's score unchanged | B26: d liquidity | C26: d technology | D26: d efficiency | E26: d strategic risk | F26: w . d | G26: Digital, Year 5, moved 10 points along d: score
A27: direction 1 | B27: 1 | C27: -1 | D27: 0 | E27: 0 | F27: =$E$4*B27+$E$5*C27+$E$6*D27+$E$7*E27 -> 0 | G27: =$E$4*($B$4+10*B27)+$E$5*($B$5+10*C27)+$E$6*($B$6+10*D27)+$E$7*($B$7+10*E27) -> 47.077713
A28: direction 2 | B28: 1 | C28: 0 | D28: -1 | E28: 0 | F28: =$E$4*B28+$E$5*C28+$E$6*D28+$E$7*E28 -> 0 | G28: =$E$4*($B$4+10*B28)+$E$5*($B$5+10*C28)+$E$6*($B$6+10*D28)+$E$7*($B$7+10*E28) -> 47.077713
A29: direction 3 | B29: 1 | C29: 0 | D29: 0 | E29: 1 | F29: =$E$4*B29+$E$5*C29+$E$6*D29+$E$7*E29 -> 0 | G29: =$E$4*($B$4+10*B29)+$E$5*($B$5+10*C29)+$E$6*($B$6+10*D29)+$E$7*($B$7+10*E29) -> 47.077713
A30: Three independent directions with w . d = 0: the CFO's tie set through any state is a three-dimensional family of different companies with one score.

Sheet Reference_Values
A1: Checkpoint | B1: Engine value | C1: Meaning (where in the book)
A2: Today's score | B2: 37 | C2: Worked Example 1.1, Step 1: 37.0
A3: Table 1.9: digital liquidity | B3: 94.295601 | C3: Table 1.9, Year 5: 94.3
A4: Table 1.9: digital technology | B4: 75.634669 | C4: Table 1.9, Year 5: 75.6
A5: Table 1.9: digital efficiency | B5: 73.598331 | C5: Table 1.9, Year 5: 73.6
A6: Table 1.9: digital strategic risk | B6: 55.21775 | C6: Table 1.9, Year 5: 55.2
A7: Table 1.9: restructuring liquidity | B7: 121.10748 | C7: Table 1.9, Year 5: 121.1
A8: Table 1.9: restructuring technology | B8: 38.859514 | C8: Table 1.9, Year 5: 38.9
A9: Table 1.9: restructuring efficiency | B9: 73.683802 | C9: Table 1.9, Year 5: 73.7
A10: Table 1.9: restructuring strategic risk | B10: 49.390192 | C10: Table 1.9, Year 5: 49.4
A11: Table 1.9: turnaround liquidity | B11: 105.3676 | C11: Table 1.9, Year 5: 105.4
A12: Table 1.9: turnaround technology | B12: 35.943036 | C12: Table 1.9, Year 5: 35.9
A13: Table 1.9: turnaround efficiency | B13: 78.601703 | C13: Table 1.9, Year 5: 78.6
... A49: Tie under 'risk first': the tied score | B49: 26.974083 | C49: the runner-up's readings, with the extra liquidity, score the leader's score

Sheet Checks
A1: Checkpoint | B1: Workbook formula value | C1: Engine value | D1: |diff| | E1: Tolerance | F1: Status
A2: Today's score | B2: =Dashboard!E17 -> 37 | C2: =Reference_Values!B2 -> 37 | D2: =ABS(B2-C2) -> 0 | E2: 1e-09 | F2: =IF(D2<=E2,"PASS","FAIL") -> PASS
A3: Table 1.9: digital liquidity | B3: =Paths!C5 -> 94.295601 | C3: =Reference_Values!B3 -> 94.295601 | D3: =ABS(B3-C3) -> 0 | E3: 1e-09 | F3: =IF(D3<=E3,"PASS","FAIL") -> PASS
A4: Table 1.9: digital technology | B4: =Paths!C6 -> 75.634669 | C4: =Reference_Values!B4 -> 75.634669 | D4: =ABS(B4-C4) -> 0 | E4: 1e-09 | F4: =IF(D4<=E4,"PASS","FAIL") -> PASS
A5: Table 1.9: digital efficiency | B5: =Paths!C7 -> 73.598331 | C5: =Reference_Values!B5 -> 73.598331 | D5: =ABS(B5-C5) -> 0 | E5: 1e-09 | F5: =IF(D5<=E5,"PASS","FAIL") -> PASS
A6: Table 1.9: digital strategic risk | B6: =Paths!C8 -> 55.21775 | C6: =Reference_Values!B6 -> 55.21775 | D6: =ABS(B6-C6) -> 0 | E6: 1e-09 | F6: =IF(D6<=E6,"PASS","FAIL") -> PASS
A7: Table 1.9: restructuring liquidity | B7: =Paths!D5 -> 121.10748 | C7: =Reference_Values!B7 -> 121.10748 | D7: =ABS(B7-C7) -> 0 | E7: 1e-09 | F7: =IF(D7<=E7,"PASS","FAIL") -> PASS
A8: Table 1.9: restructuring technology | B8: =Paths!D6 -> 38.859514 | C8: =Reference_Values!B8 -> 38.859514 | D8: =ABS(B8-C8) -> 0 | E8: 1e-09 | F8: =IF(D8<=E8,"PASS","FAIL") -> PASS
A9: Table 1.9: restructuring efficiency | B9: =Paths!D7 -> 73.683802 | C9: =Reference_Values!B9 -> 73.683802 | D9: =ABS(B9-C9) -> 0 | E9: 1e-09 | F9: =IF(D9<=E9,"PASS","FAIL") -> PASS
A10: Table 1.9: restructuring strategic risk | B10: =Paths!D8 -> 49.390192 | C10: =Reference_Values!B10 -> 49.390192 | D10: =ABS(B10-C10) -> 0 | E10: 1e-09 | F10: =IF(D10<=E10,"PASS","FAIL") -> PASS
A11: Table 1.9: turnaround liquidity | B11: =Paths!E5 -> 105.3676 | C11: =Reference_Values!B11 -> 105.3676 | D11: =ABS(B11-C11) -> 0 | E11: 1e-09 | F11: =IF(D11<=E11,"PASS","FAIL") -> PASS
A12: Table 1.9: turnaround technology | B12: =Paths!E6 -> 35.943036 | C12: =Reference_Values!B12 -> 35.943036 | D12: =ABS(B12-C12) -> 0 | E12: 1e-09 | F12: =IF(D12<=E12,"PASS","FAIL") -> PASS
A13: Table 1.9: turnaround efficiency | B13: =Paths!E7 -> 78.601703 | C13: =Reference_Values!B13 -> 78.601703 | D13: =ABS(B13-C13) -> 0 | E13: 1e-09 | F13: =IF(D13<=E13,"PASS","FAIL") -> PASS
A14: Table 1.9: turnaround strategic risk | B14: =Paths!E8 -> 66.33061 | C14: =Reference_Values!B14 -> 66.33061 | D14: =ABS(B14-C14) -> 0 | E14: 1e-09 | F14: =IF(D14<=E14,"PASS","FAIL") -> PASS
A15: Year-5 score: digital | B15: =Paths!C9 -> 47.077713 | C15: =Reference_Values!B15 -> 47.077713 | D15: =ABS(B15-C15) -> 0 | E15: 1e-09 | F15: =IF(D15<=E15,"PASS","FAIL") -> PASS
A16: Year-5 score: restructuring | B16: =Paths!D9 -> 46.065151 | C16: =Reference_Values!B16 -> 46.065151 | D16: =ABS(B16-C16) -> 0 | E16: 1e-09 | F16: =IF(D16<=E16,"PASS","FAIL") -> PASS
A17: Year-5 score: turnaround | B17: =Paths!E9 -> 38.395434 | C17: =Reference_Values!B17 -> 38.395434 | D17: =ABS(B17-C17) -> 0 | E17: 1e-09 | F17: =IF(D17<=E17,"PASS","FAIL") -> PASS
A18: Digital low point (monthly) | B18: =Compare!B4 -> 77.733933 | C18: =Reference_Values!B18 -> 77.733933 | D18: =ABS(B18-C18) -> 0 | E18: 1e-09 | F18: =IF(D18<=E18,"PASS","FAIL") -> PASS
A19: Month of the low point | B19: =Compare!B5 -> 21 | C19: =Reference_Values!B19 -> 21 | D19: =ABS(B19-C19) -> 0 | E19: 0 | F19: =IF(D19<=E19,"PASS","FAIL") -> PASS
A20: Low point on a 0.01-year grid | B20: =Compare!B6 -> 77.728787 | C20: =Reference_Values!B20 -> 77.728787 | D20: =ABS(B20-C20) -> 0 | E20: 1e-09 | F20: =IF(D20<=E20,"PASS","FAIL") -> PASS
A21: Time of the low point (years) | B21: =Compare!B7 -> 1.71 | C21: =Reference_Values!B21 -> 1.71 | D21: =ABS(B21-C21) -> 0 | E21: 1e-09 | F21: =IF(D21<=E21,"PASS","FAIL") -> PASS
A22: Low point below today ($ million) | B22: =Compare!B10 -> 138.08152 | C22: =Reference_Values!B22 -> 138.08206 | D22: =ABS(B22-C22) -> 0.0005382238 | E22: 0.001 | F22: =IF(D22<=E22,"PASS","FAIL") -> PASS
A23: Sale-date jump ($ million) | B23: =Compare!B12 -> 111.6 | C23: =Reference_Values!B23 -> 111.6 | D23: =ABS(B23-C23) -> 0 | E23: 1e-09 | F23: =IF(D23<=E23,"PASS","FAIL") -> PASS
A24: Risk-ceiling margin at the digital peak (monthly) | B24: =Compare!B17 -> 1.4479365 | C24: =Reference_Values!B24 -> 1.4479365 | D24: =ABS(B24-C24) -> 0 | E24: 1e-09 | F24: =IF(D24<=E24,"PASS","FAIL") -> PASS
A25: First month the digital score is back at today's | B25: =Compare!B21 -> 29 | C25: =Reference_Values!B25 -> 29 | D25: =ABS(B25-C25) -> 0 | E25: 0 | F25: =IF(D25<=E25,"PASS","FAIL") -> PASS
A26: Annual reviews ranking digital last | B26: =Compare!G29 -> 2 | C26: =Reference_Values!B26 -> 2 | D26: =ABS(B26-C26) -> 0 | E26: 0 | F26: =IF(D26<=E26,"PASS","FAIL") -> PASS
A27: Plan trough ($ million) | B27: =Uncertainty!J5 -> 481.95038 | C27: =Reference_Values!B27 -> 481.95038 | D27: =ABS(B27-C27) -> 0 | E27: 1e-06 | F27: =IF(D27<=E27,"PASS","FAIL") -> PASS
A28: Trough above the floor ($ million) | B28: =Uncertainty!J7 -> 131.95038 | C28: =Reference_Values!B28 -> 131.95038 | D28: =ABS(B28-C28) -> 0 | E28: 1e-06 | F28: =IF(D28<=E28,"PASS","FAIL") -> PASS
A29: The program's draw ($ million) | B29: =Uncertainty!J8 -> 138.04962 | C29: =Reference_Values!B29 -> 138.04962 | D29: =ABS(B29-C29) -> 0 | E29: 1e-06 | F29: =IF(D29<=E29,"PASS","FAIL") -> PASS
A30: Phased build's trough ($ million) | B30: =Uncertainty!J9 -> 530.97392 | C30: =Reference_Values!B30 -> 530.97392 | D30: =ABS(B30-C30) -> 0 | E30: 1e-06 | F30: =IF(D30<=E30,"PASS","FAIL") -> PASS
A31: Long-run sd of the surprises ($ million) | B31: =Uncertainty!J10 -> 62.5 | C31: =Reference_Values!B31 -> 62.5 | D31: =ABS(B31-C31) -> 0 | E31: 1e-09 | F31: =IF(D31<=E31,"PASS","FAIL") -> PASS
A32: P(at least one closure in three years) | B32: =Uncertainty!J13 -> 0.25918178 | C32: =Reference_Values!B32 -> 0.25918178 | D32: =ABS(B32-C32) -> 0 | E32: 1e-09 | F32: =IF(D32<=E32,"PASS","FAIL") -> PASS
A33: A bad closure: 90th percentile ($ million) | B33: =Uncertainty!J16 -> 186.86698 | C33: =Reference_Values!B33 -> 186.86698 | D33: =ABS(B33-C33) -> 0 | E33: 0.0001 | F33: =IF(D33<=E33,"PASS","FAIL") -> PASS
A34: Draw plus a bad closure ($ million) | B34: =Uncertainty!J18 -> 324.91659 | C34: =Reference_Values!B34 -> 324.91659 | D34: =ABS(B34-C34) -> 0 | E34: 0.0001 | F34: =IF(D34<=E34,"PASS","FAIL") -> PASS
A35: Worst 5% of troughs below the floor, both levers | B35: =Uncertainty!N25 -> 17.532146 | C35: =Reference_Values!B35 -> 17.532146 | D35: =ABS(B35-C35) -> 0 | E35: 1e-09 | F35: =IF(D35<=E35,"PASS","FAIL") -> PASS
A36: Digital's lead over restructuring (points) | B36: =Scorecard!B10 -> 1.0125619 | C36: =Reference_Values!B36 -> 1.0125619 | D36: =ABS(B36-C36) -> 0 | E36: 1e-09 | F36: =IF(D36<=E36,"PASS","FAIL") -> PASS
A37: Liquidity points that tie the scores | B37: =Scorecard!B11 -> 4.0502475 | C37: =Reference_Values!B37 -> 4.0502475 | D37: =ABS(B37-C37) -> 0 | E37: 1e-09 | F37: =IF(D37<=E37,"PASS","FAIL") -> PASS
A38: Their value ($ million) | B38: =Scorecard!B12 -> 25.111534 | C38: =Reference_Values!B38 -> 25.111534 | D38: =ABS(B38-C38) -> 0 | E38: 1e-09 | F38: =IF(D38<=E38,"PASS","FAIL") -> PASS
A39: Score-matched restructured liquidity | B39: =Scorecard!B13 -> 125.15773 | C39: =Reference_Values!B39 -> 125.15773 | D39: =ABS(B39-C39) -> 0 | E39: 1e-09 | F39: =IF(D39<=E39,"PASS","FAIL") -> PASS
A40: Its score | B40: =Scorecard!B14 -> 47.077713 | C40: =Reference_Values!B40 -> 47.077713 | D40: =ABS(B40-C40) -> 0 | E40: 1e-09 | F40: =IF(D40<=E40,"PASS","FAIL") -> PASS
A41: Weight points to liquidity that tie | B41: =Scorecard!B15 -> 1.5924031 | C41: =Reference_Values!B41 -> 1.5924031 | D41: =ABS(B41-C41) -> 0 | E41: 1e-09 | F41: =IF(D41<=E41,"PASS","FAIL") -> PASS
A42: Weight points to efficiency that tie | B42: =Scorecard!B16 -> 2.7470013 | C42: =Reference_Values!B42 -> 2.7470013 | D42: =ABS(B42-C42) -> 0 | E42: 1e-09 | F42: =IF(D42<=E42,"PASS","FAIL") -> PASS
A43: Weight points to strategic risk that tie | B43: =Scorecard!B17 -> 2.3767545 | C43: =Reference_Values!B43 -> 2.3767545 | D43: =ABS(B43-C43) -> 0 | E43: 1e-09 | F43: =IF(D43<=E43,"PASS","FAIL") -> PASS
A44: Tie under 'liquidity first': extra liquidity | B44: =Scorecard!K21 -> 11.380815 | C44: =Reference_Values!B44 -> 11.380815 | D44: =ABS(B44-C44) -> 0 | E44: 1e-09 | F44: =IF(D44<=E44,"PASS","FAIL") -> PASS
A45: Tie under 'liquidity first': the tied score | B45: =Scorecard!M21 -> 61.073617 | C45: =Reference_Values!B45 -> 61.073617 | D45: =ABS(B45-C45) -> 0 | E45: 1e-09 | F45: =IF(D45<=E45,"PASS","FAIL") -> PASS
A46: Tie under 'technology first': extra liquidity | B46: =Scorecard!K22 -> 40.825402 | C46: =Reference_Values!B46 -> 40.825402 | D46: =ABS(B46-C46) -> 0 | E46: 1e-09 | F46: =IF(D46<=E46,"PASS","FAIL") -> PASS
A47: Tie under 'technology first': the tied score | B47: =Scorecard!M22 -> 52.789104 | C47: =Reference_Values!B47 -> 52.789104 | D47: =ABS(B47-C47) -> 0 | E47: 1e-09 | F47: =IF(D47<=E47,"PASS","FAIL") -> PASS
A48: Tie under 'risk first': extra liquidity | B48: =Scorecard!K23 -> 1.7773105 | C48: =Reference_Values!B48 -> 1.7773105 | D48: =ABS(B48-C48) -> 3.5749181e-14 | E48: 1e-09 | F48: =IF(D48<=E48,"PASS","FAIL") -> PASS
A49: Tie under 'risk first': the tied score | B49: =Scorecard!M23 -> 26.974083 | C49: =Reference_Values!B49 -> 26.974083 | D49: =ABS(B49-C49) -> 0 | E49: 1e-09 | F49: =IF(D49<=E49,"PASS","FAIL") -> PASS
A51: All checkpoints | F51: =IF(COUNTIF(F2:F49,"PASS")=48,"ALL PASS","CHECK") -> ALL PASS
