Workbook

Sheet README
B1: DCT Laboratory — Vol II, Ch 2: The General Enterprise Optimization Problem Revisited
B2: Seed 26202 · Companion to DCT_V2_Ch02_Lab.ipynb and AXIOM Lab 2.2 (module AXIOM-02). Money in $ million, undiscounted.
B4: Worked Example 2.1, Can Meridian Automate and Pay Out at Once?, with the book's declarations.
B5: Declarations: the automation program of Volume I, Worked Example 6.1, the two pledges, the board's two conditions, and the five commitments with their owners and codes.
B6: Instance: the instance card (Table 2.6), the decision-variable editor, which refuses savings as a decision, and the phantom lever: six-round savings carried into a three-round plan.
B7: JointPlan: one forward pass of the joint plan, which dies in year 3, the COO's plan with all savings kept, and the reachable sets of Theorem 2.3(iii).
B8: Schedules: all 64 schedules of rounds, run forward with no payout and with the half payout.
B9: DiagnoseClash: the deletion filter in both orders, every minimal infeasible set, and the groups of commitments whose removal restores feasibility (Theorem 2.3).
B10: Repairs: the largest payout share with six rounds, the most rounds with the half payout, both pledges without the board's conditions, Online Appendix 2.B.4 year by year, and Table 2.7.
B11: Optimizer: the plan for each credit beyond year 6, the thresholds 2.9, 10.7, 25.4 and 53.9 years, the Mayer rewrite and restatements that change nothing (Theorem 2.1).
B12: StandardForm: one schedule's linear program as emitted for a solver, and the price of its end condition in millions and in billions.
B13: Quantifiers: Table 2.4, one commitment under four quantifiers, and the price of the board's appetite. True odds come from the notebook's engine (Volume I's Chapter 8 model, 100,000 paths, seed 8).
... B20: Cross-sheet link: green.

Sheet Declarations
A1: Declarations (Worked Example 2.1, the situation). Money in $ million; amounts undiscounted.
A3: Quantity | B3: Value | C3: Source
A4: Cost of an automation round | B4: 120 | C4: Volume I, Worked Example 6.1
A5: Efficiency ceiling | B5: 85 | C5: A round closes half the gap to 85
A6: Share of the gap a round closes | B6: 0.5
A7: Savings a year per efficiency point above today's | B7: 10 | C7: $10 million a year a point
A8: Efficiency today | B8: 71
A9: Liquidity today | B9: 620
A10: Workforce capability today | B10: 58
A11: Capability a round adds | B11: 1 | C11: Each round raises capability by one point
A12: Capability a round needs | B12: 55 | C12: The admissible-decision block (HR)
A13: The board's liquidity floor | B13: 350 | C13: After paying for a round and at every year end
A14: Liquidity a round needs to start | B14: =Floor_liq+Round_cost -> 470 | C14: So that the floor holds after paying for it: $470 million
A15: The board's end condition: liquidity at the end of year 6 | B15: =Liq_start -> 470 | C15: The $470 million another round would need
A16: The CFO's pledge: share of each year's savings paid out | B16: 0.5 | C16: Half of each year's savings
A18: Commitment | B18: Code | C18: Owner | D18: What it requires
A19: floor | B19: 1 | C19: the board | D19: liquidity of at least $350 million after paying for a round and at every year end
A20: capability | B20: 2 | C20: HR | D20: capability of at least 55 when a round starts
A21: six rounds | B21: 4 | C21: the COO | D21: a round every year for six years
A22: half payout | B22: 8 | C22: the CFO | D22: half of each year's savings paid out
A23: end condition | B23: 16 | C23: the board | D23: at least $470 million at the end of year 6
A25: A set of commitments is written as the sum of its codes: {floor, six rounds, half payout} = 1 + 4 + 8 = 13. A schedule of rounds is written as the years of its rounds: years 1, 2 and 4 = 124.

Sheet Instance
A1: Build the instance: the card, the decision-variable editor, a phantom lever (Table 2.6; Proposition 2.2; AXIOM Lab 2.2, step 1)
A3: Block | B3: Meridian's declaration | C3: Owner
A4: Decisions | B4: round in year k, z_k in {0, 1}; payout p_k >= 0 | C4: COO; CFO
A5: Dynamics | B5: each round closes half the efficiency gap to 85 and adds a point of capability; savings $10 million per point above 71; liquidity q_k = q_k-1 - 120 z_k + S_k - p_k | C5: COO; treasury
A6: Admissible decisions | B6: a round needs capability of at least 55 | C6: HR
A7: Path commitments | B7: liquidity of at least $350 million after paying for a round and at year end; a round every year; half of each year's savings paid out | C7: board; COO; CFO
A8: Start and end | B8: $620 million, efficiency 71, capability 58; at least $470 million at the end of year 6 | C8: treasury; board
A9: Uncertainty | B9: none declared (Volume I's point estimates) | C9: --
A11: Quantity | B11: Declared as (decision or induced) | C11: Computed by the dynamics? | D11: How the dynamics compute it | E11: The decision-variable editor
A12: Round in year k, z_k | B12: decision | C12: no | E12: =IF(B12="decision",IF(C12="yes","REFUSED: induced by the dynamics; a lever on it would be a phantom lever","accepted as a decision"),IF(C12="yes","induced: computed by the dynamics","REFUSED: nothing computes it, so it must be declared a decision")) -> accepted as a decision
A13: Payout in year k, p_k | B13: decision | C13: no | E13: =IF(B13="decision",IF(C13="yes","REFUSED: induced by the dynamics; a lever on it would be a phantom lever","accepted as a decision"),IF(C13="yes","induced: computed by the dynamics","REFUSED: nothing computes it, so it must be declared a decision")) -> accepted as a decision
A14: Efficiency e_k | B14: induced | C14: yes | D14: e_k = e_k-1 + z_k (85 - e_k-1) / 2 | E14: =IF(B14="decision",IF(C14="yes","REFUSED: induced by the dynamics; a lever on it would be a phantom lever","accepted as a decision"),IF(C14="yes","induced: computed by the dynamics","REFUSED: nothing computes it, so it must be declared a decision")) -> induced: computed by the dynamics
A15: Capability w_k | B15: induced | C15: yes | D15: w_k = w_k-1 + z_k | E15: =IF(B15="decision",IF(C15="yes","REFUSED: induced by the dynamics; a lever on it would be a phantom lever","accepted as a decision"),IF(C15="yes","induced: computed by the dynamics","REFUSED: nothing computes it, so it must be declared a decision")) -> induced: computed by the dynamics
A16: Savings S_k | B16: decision | C16: yes | D16: S_k = 10 (e_k - 71) | E16: =IF(B16="decision",IF(C16="yes","REFUSED: induced by the dynamics; a lever on it would be a phantom lever","accepted as a decision"),IF(C16="yes","induced: computed by the dynamics","REFUSED: nothing computes it, so it must be declared a decision")) -> REFUSED: induced by the dynamics; a lever on it would be a phantom lever
A17: Liquidity q_k | B17: induced | C17: yes | D17: q_k = q_k-1 - 120 z_k + S_k - p_k | E17: =IF(B17="decision",IF(C17="yes","REFUSED: induced by the dynamics; a lever on it would be a phantom lever","accepted as a decision"),IF(C17="yes","induced: computed by the dynamics","REFUSED: nothing computes it, so it must be declared a decision")) -> induced: computed by the dynamics
A18: Entries the editor refuses | B18: =COUNTIF(E12:E17,"REFUSED*") -> 1
A19: AXIOM Lab 2.2, step 1: savings are entered as a decision (B16) and refused. Declare them induced and the editor accepts the card.
A21: A phantom lever: savings are induced by the rounds (Proposition 2.2)
A22: Plan | B22: Row | C22: Year 1 | D22: Year 2 | E22: Year 3 | F22: Year 4 | G22: Year 5 | H22: Year 6 | I22: Six years
A23: Six rounds (the CFO's spreadsheet) | B23: round (1 = yes) | C23: 1 | D23: 1 | E23: 1 | F23: 1 | G23: 1 | H23: 1
B24: efficiency | C24: =IF(C23=1,Eff_0+Gap_closed*(Eff_ceiling-Eff_0),Eff_0) -> 78 | D24: =IF(D23=1,C24+Gap_closed*(Eff_ceiling-C24),C24) -> 81.5 | E24: =IF(E23=1,D24+Gap_closed*(Eff_ceiling-D24),D24) -> 83.25 | F24: =IF(F23=1,E24+Gap_closed*(Eff_ceiling-E24),E24) -> 84.125 | G24: =IF(G23=1,F24+Gap_closed*(Eff_ceiling-F24),F24) -> 84.5625 | H24: =IF(H23=1,G24+Gap_closed*(Eff_ceiling-G24),G24) -> 84.78125
B25: savings | C25: =Sav_point*(C24-Eff_0) -> 70 | D25: =Sav_point*(D24-Eff_0) -> 105 | E25: =Sav_point*(E24-Eff_0) -> 122.5 | F25: =Sav_point*(F24-Eff_0) -> 131.25 | G25: =Sav_point*(G24-Eff_0) -> 135.625 | H25: =Sav_point*(H24-Eff_0) -> 137.8125 | I25: =SUM(C25:H25) -> 702.1875
A27: Rounds in years 1, 2 and 4 | B27: round (1 = yes) | C27: 1 | D27: 1 | E27: 0 | F27: 1 | G27: 0 | H27: 0
B28: efficiency | C28: =IF(C27=1,Eff_0+Gap_closed*(Eff_ceiling-Eff_0),Eff_0) -> 78 | D28: =IF(D27=1,C28+Gap_closed*(Eff_ceiling-C28),C28) -> 81.5 | E28: =IF(E27=1,D28+Gap_closed*(Eff_ceiling-D28),D28) -> 81.5 | F28: =IF(F27=1,E28+Gap_closed*(Eff_ceiling-E28),E28) -> 83.25 | G28: =IF(G27=1,F28+Gap_closed*(Eff_ceiling-F28),F28) -> 83.25 | H28: =IF(H27=1,G28+Gap_closed*(Eff_ceiling-G28),G28) -> 83.25
B29: savings | C29: =Sav_point*(C28-Eff_0) -> 70 | D29: =Sav_point*(D28-Eff_0) -> 105 | E29: =Sav_point*(E28-Eff_0) -> 105 | F29: =Sav_point*(F28-Eff_0) -> 122.5 | G29: =Sav_point*(G28-Eff_0) -> 122.5 | H29: =Sav_point*(H28-Eff_0) -> 122.5 | I29: =SUM(C29:H29) -> 647.5
A31: Six-round savings over six years (the spreadsheet's) | B31: =I25 -> 702.1875
A32: Savings of rounds in years 1, 2 and 4 | B32: =I29 -> 647.5
A33: Carried into the three-round plan, the spreadsheet overstates its savings by | B33: =B31-B32 -> 54.6875
A34: A plan's savings must be computed from its own rounds, never carried over from another plan: a lever on savings is a lever the company does not have.

Sheet JointPlan
A1: Check the joint plan by simulation (Worked Example 2.1, Step 2; Theorem 2.3(iii); AXIOM Lab 2.2, step 2)
A2: One forward pass of the declared dynamics under the plan. The rounds are the COO's pledge; change them, or the share paid out, and the pass recomputes.
A4: The joint plan: a round every year, half of each year's savings paid out
A5: Year | B5: Round (1 = yes) | C5: Liquidity at the start | D5: After paying for the round | E5: Capability before the round | F5: Efficiency | G5: Savings | H5: Paid out | I5: Liquidity at year end | J5: Floor kept? | K5: Capability kept? | M5: Reading | N5: Value
A6: 1 | B6: 1 | C6: =Liq_0 -> 620 | D6: =C6-Round_cost*B6 -> 500 | E6: =Cap_0 -> 58 | F6: =IF(B6=1,Eff_0+Gap_closed*(Eff_ceiling-Eff_0),Eff_0) -> 78 | G6: =Sav_point*(F6-Eff_0) -> 70 | H6: =Pledge_share*G6 -> 35 | I6: =D6+G6-H6 -> 535 | J6: =IF(AND(OR(B6=0,D6>=Floor_liq-0.000000001),I6>=Floor_liq-0.000000001),"yes","no") -> yes | K6: =IF(OR(B6=0,E6>=Cap_min),"yes","no") -> yes | M6: Liquidity at the end of year 1 | N6: =I6 -> 535
A7: 2 | B7: 1 | C7: =I6 -> 535 | D7: =C7-Round_cost*B7 -> 415 | E7: =E6+Cap_step*B6 -> 59 | F7: =IF(B7=1,F6+Gap_closed*(Eff_ceiling-F6),F6) -> 81.5 | G7: =Sav_point*(F7-Eff_0) -> 105 | H7: =Pledge_share*G7 -> 52.5 | I7: =D7+G7-H7 -> 467.5 | J7: =IF(AND(OR(B7=0,D7>=Floor_liq-0.000000001),I7>=Floor_liq-0.000000001),"yes","no") -> yes | K7: =IF(OR(B7=0,E7>=Cap_min),"yes","no") -> yes | M7: Liquidity at the end of year 2 | N7: =I7 -> 467.5
A8: 3 | B8: 1 | C8: =I7 -> 467.5 | D8: =C8-Round_cost*B8 -> 347.5 | E8: =E7+Cap_step*B7 -> 60 | F8: =IF(B8=1,F7+Gap_closed*(Eff_ceiling-F7),F7) -> 83.25 | G8: =Sav_point*(F8-Eff_0) -> 122.5 | H8: =Pledge_share*G8 -> 61.25 | I8: =D8+G8-H8 -> 408.75 | J8: =IF(AND(OR(B8=0,D8>=Floor_liq-0.000000001),I8>=Floor_liq-0.000000001),"yes","no") -> no | K8: =IF(OR(B8=0,E8>=Cap_min),"yes","no") -> yes | M8: Liquidity after paying for round 3 | N8: =D8 -> 347.5
A9: 4 | B9: 1 | C9: =I8 -> 408.75 | D9: =C9-Round_cost*B9 -> 288.75 | E9: =E8+Cap_step*B8 -> 61 | F9: =IF(B9=1,F8+Gap_closed*(Eff_ceiling-F8),F8) -> 84.125 | G9: =Sav_point*(F9-Eff_0) -> 131.25 | H9: =Pledge_share*G9 -> 65.625 | I9: =D9+G9-H9 -> 354.375 | J9: =IF(AND(OR(B9=0,D9>=Floor_liq-0.000000001),I9>=Floor_liq-0.000000001),"yes","no") -> no | K9: =IF(OR(B9=0,E9>=Cap_min),"yes","no") -> yes | M9: The joint plan dies in year (the first year the floor breaks) | N9: =IF(COUNTIF(J6:J11,"no")=0,0,MATCH("no",J6:J11,0)) -> 3
A10: 5 | B10: 1 | C10: =I9 -> 354.375 | D10: =C10-Round_cost*B10 -> 234.375 | E10: =E9+Cap_step*B9 -> 62 | F10: =IF(B10=1,F9+Gap_closed*(Eff_ceiling-F9),F9) -> 84.5625 | G10: =Sav_point*(F10-Eff_0) -> 135.625 | H10: =Pledge_share*G10 -> 67.8125 | I10: =D10+G10-H10 -> 302.1875 | J10: =IF(AND(OR(B10=0,D10>=Floor_liq-0.000000001),I10>=Floor_liq-0.000000001),"yes","no") -> no | K10: =IF(OR(B10=0,E10>=Cap_min),"yes","no") -> yes | M10: By the end of year 2 the payouts have taken | N10: =SUM(H6:H7) -> 87.5
A11: 6 | B11: 1 | C11: =I10 -> 302.1875 | D11: =C11-Round_cost*B11 -> 182.1875 | E11: =E10+Cap_step*B10 -> 63 | F11: =IF(B11=1,F10+Gap_closed*(Eff_ceiling-F10),F10) -> 84.78125 | G11: =Sav_point*(F11-Eff_0) -> 137.8125 | H11: =Pledge_share*G11 -> 68.90625 | I11: =D11+G11-H11 -> 251.09375 | J11: =IF(AND(OR(B11=0,D11>=Floor_liq-0.000000001),I11>=Floor_liq-0.000000001),"yes","no") -> no | K11: =IF(OR(B11=0,E11>=Cap_min),"yes","no") -> yes | M11: Round 3 misses the liquidity it needs by | N11: =Liq_start-I7 -> 2.5
A12: Round 3 cannot start, so the joint plan dies in year 3. The later rows run both pledges on regardless: that is repair (c), which gives up the floor and the end condition. | M12: The COO's plan with savings kept: liquidity at the end of year 6 | N12: =I21 -> 602.1875
M13: ... its first year breaking the floor (0 = none) | N13: =IF(COUNTIF(J16:J21,"no")=0,0,MATCH("no",J16:J21,0)) -> 0
A14: The COO's plan with all savings kept | M14: ... the end condition kept? | N14: =IF(I21>=End_liq,"yes","no") -> yes
A15: Year | B15: Round (1 = yes) | C15: Liquidity at the start | D15: After paying for the round | E15: Capability before the round | F15: Efficiency | G15: Savings | H15: Paid out | I15: Liquidity at year end | J15: Floor kept? | K15: Capability kept?
A16: 1 | B16: 1 | C16: =Liq_0 -> 620 | D16: =C16-Round_cost*B16 -> 500 | E16: =Cap_0 -> 58 | F16: =IF(B16=1,Eff_0+Gap_closed*(Eff_ceiling-Eff_0),Eff_0) -> 78 | G16: =Sav_point*(F16-Eff_0) -> 70 | H16: =0*G16 -> 0 | I16: =D16+G16-H16 -> 570 | J16: =IF(AND(OR(B16=0,D16>=Floor_liq-0.000000001),I16>=Floor_liq-0.000000001),"yes","no") -> yes | K16: =IF(OR(B16=0,E16>=Cap_min),"yes","no") -> yes
A17: 2 | B17: 1 | C17: =I16 -> 570 | D17: =C17-Round_cost*B17 -> 450 | E17: =E16+Cap_step*B16 -> 59 | F17: =IF(B17=1,F16+Gap_closed*(Eff_ceiling-F16),F16) -> 81.5 | G17: =Sav_point*(F17-Eff_0) -> 105 | H17: =0*G17 -> 0 | I17: =D17+G17-H17 -> 555 | J17: =IF(AND(OR(B17=0,D17>=Floor_liq-0.000000001),I17>=Floor_liq-0.000000001),"yes","no") -> yes | K17: =IF(OR(B17=0,E17>=Cap_min),"yes","no") -> yes
A18: 3 | B18: 1 | C18: =I17 -> 555 | D18: =C18-Round_cost*B18 -> 435 | E18: =E17+Cap_step*B17 -> 60 | F18: =IF(B18=1,F17+Gap_closed*(Eff_ceiling-F17),F17) -> 83.25 | G18: =Sav_point*(F18-Eff_0) -> 122.5 | H18: =0*G18 -> 0 | I18: =D18+G18-H18 -> 557.5 | J18: =IF(AND(OR(B18=0,D18>=Floor_liq-0.000000001),I18>=Floor_liq-0.000000001),"yes","no") -> yes | K18: =IF(OR(B18=0,E18>=Cap_min),"yes","no") -> yes
A19: 4 | B19: 1 | C19: =I18 -> 557.5 | D19: =C19-Round_cost*B19 -> 437.5 | E19: =E18+Cap_step*B18 -> 61 | F19: =IF(B19=1,F18+Gap_closed*(Eff_ceiling-F18),F18) -> 84.125 | G19: =Sav_point*(F19-Eff_0) -> 131.25 | H19: =0*G19 -> 0 | I19: =D19+G19-H19 -> 568.75 | J19: =IF(AND(OR(B19=0,D19>=Floor_liq-0.000000001),I19>=Floor_liq-0.000000001),"yes","no") -> yes | K19: =IF(OR(B19=0,E19>=Cap_min),"yes","no") -> yes
A20: 5 | B20: 1 | C20: =I19 -> 568.75 | D20: =C20-Round_cost*B20 -> 448.75 | E20: =E19+Cap_step*B19 -> 62 | F20: =IF(B20=1,F19+Gap_closed*(Eff_ceiling-F19),F19) -> 84.5625 | G20: =Sav_point*(F20-Eff_0) -> 135.625 | H20: =0*G20 -> 0 | I20: =D20+G20-H20 -> 584.375 | J20: =IF(AND(OR(B20=0,D20>=Floor_liq-0.000000001),I20>=Floor_liq-0.000000001),"yes","no") -> yes | K20: =IF(OR(B20=0,E20>=Cap_min),"yes","no") -> yes
A21: 6 | B21: 1 | C21: =I20 -> 584.375 | D21: =C21-Round_cost*B21 -> 464.375 | E21: =E20+Cap_step*B20 -> 63 | F21: =IF(B21=1,F20+Gap_closed*(Eff_ceiling-F20),F20) -> 84.78125 | G21: =Sav_point*(F21-Eff_0) -> 137.8125 | H21: =0*G21 -> 0 | I21: =D21+G21-H21 -> 602.1875 | J21: =IF(AND(OR(B21=0,D21>=Floor_liq-0.000000001),I21>=Floor_liq-0.000000001),"yes","no") -> yes | K21: =IF(OR(B21=0,E21>=Cap_min),"yes","no") -> yes
A25: Theorem 2.3(iii): the year-end liquidity some plan can reach under six rounds and at least half paid out, keeping every commitment so far: all five commitments in force
A26: Floor in force (1 = yes) | D26: 1 | E26: End condition in force (1 = yes) | H26: 1
A27: Year | B27: Efficiency | C27: Savings | D27: Lowest level that can start the round | E27: Highest level at the start | F27: Round can start? (1 = yes) | G27: Lowest year-end level | H27: Highest year-end level | I27: Set not empty? (1 = yes)
A28: 0 | B28: =Eff_0 -> 71 | G28: =Liq_0 -> 620 | H28: =Liq_0 -> 620 | I28: 1
A29: 1 | B29: =B28+Gap_closed*(Eff_ceiling-B28) -> 78 | C29: =Sav_point*(B29-Eff_0) -> 70 | D29: =IF($D$26=1,MAX(G28,Liq_start),G28) -> 620 | E29: =H28 -> 620 | F29: =IF(AND(I28=1,D29<=E29),1,0) -> 1 | G29: =IF($D$26=1,Floor_liq,-1000000000) -> 350 | H29: =E29-Round_cost+(1-Pledge_share)*C29 -> 535 | I29: =IF(AND(F29=1,G29<=H29),1,0) -> 1
A30: 2 | B30: =B29+Gap_closed*(Eff_ceiling-B29) -> 81.5 | C30: =Sav_point*(B30-Eff_0) -> 105 | D30: =IF($D$26=1,MAX(G29,Liq_start),G29) -> 470 | E30: =H29 -> 535 | F30: =IF(AND(I29=1,D30<=E30),1,0) -> 1 | G30: =IF($D$26=1,Floor_liq,-1000000000) -> 350 | H30: =E30-Round_cost+(1-Pledge_share)*C30 -> 467.5 | I30: =IF(AND(F30=1,G30<=H30),1,0) -> 1
A31: 3 | B31: =B30+Gap_closed*(Eff_ceiling-B30) -> 83.25 | C31: =Sav_point*(B31-Eff_0) -> 122.5 | D31: =IF($D$26=1,MAX(G30,Liq_start),G30) -> 470 | E31: =H30 -> 467.5 | F31: =IF(AND(I30=1,D31<=E31),1,0) -> 0 | G31: =IF($D$26=1,Floor_liq,-1000000000) -> 350 | H31: =E31-Round_cost+(1-Pledge_share)*C31 -> 408.75 | I31: =IF(AND(F31=1,G31<=H31),1,0) -> 0
A32: 4 | B32: =B31+Gap_closed*(Eff_ceiling-B31) -> 84.125 | C32: =Sav_point*(B32-Eff_0) -> 131.25 | D32: =IF($D$26=1,MAX(G31,Liq_start),G31) -> 470 | E32: =H31 -> 408.75 | F32: =IF(AND(I31=1,D32<=E32),1,0) -> 0 | G32: =IF($D$26=1,Floor_liq,-1000000000) -> 350 | H32: =E32-Round_cost+(1-Pledge_share)*C32 -> 354.375 | I32: =IF(AND(F32=1,G32<=H32),1,0) -> 0
A33: 5 | B33: =B32+Gap_closed*(Eff_ceiling-B32) -> 84.5625 | C33: =Sav_point*(B33-Eff_0) -> 135.625 | D33: =IF($D$26=1,MAX(G32,Liq_start),G32) -> 470 | E33: =H32 -> 354.375 | F33: =IF(AND(I32=1,D33<=E33),1,0) -> 0 | G33: =IF($D$26=1,Floor_liq,-1000000000) -> 350 | H33: =E33-Round_cost+(1-Pledge_share)*C33 -> 302.1875 | I33: =IF(AND(F33=1,G33<=H33),1,0) -> 0
A34: 6 | B34: =B33+Gap_closed*(Eff_ceiling-B33) -> 84.78125 | C34: =Sav_point*(B34-Eff_0) -> 137.8125 | D34: =IF($D$26=1,MAX(G33,Liq_start),G33) -> 470 | E34: =H33 -> 302.1875 | F34: =IF(AND(I33=1,D34<=E34),1,0) -> 0 | G34: =IF($H$26=1,MAX(IF($D$26=1,Floor_liq,-1000000000),End_liq),IF($D$26=1,Floor_liq,-1000000000)) -> 470 | H34: =E34-Round_cost+(1-Pledge_share)*C34 -> 251.09375 | I34: =IF(AND(F34=1,G34<=H34),1,0) -> 0
A35: The first year whose set is empty: the plan dies (grey: no plan reaches these years keeping every commitment) | I35: =IF(COUNTIF(I29:I34,0)=0,0,MATCH(0,I29:I34,0)) -> 3
A37: Theorem 2.3(iii): the year-end liquidity some plan can reach under six rounds and at least half paid out, keeping every commitment so far: the floor dropped (the pledges and the end condition)
A38: Floor in force (1 = yes) | D38: 0 | E38: End condition in force (1 = yes) | H38: 1
A39: Year | B39: Efficiency | C39: Savings | D39: Lowest level that can start the round | E39: Highest level at the start | F39: Round can start? (1 = yes) | G39: Lowest year-end level | H39: Highest year-end level | I39: Set not empty? (1 = yes)
A40: 0 | B40: =Eff_0 -> 71 | G40: =Liq_0 -> 620 | H40: =Liq_0 -> 620 | I40: 1
A41: 1 | B41: =B40+Gap_closed*(Eff_ceiling-B40) -> 78 | C41: =Sav_point*(B41-Eff_0) -> 70 | D41: =IF($D$38=1,MAX(G40,Liq_start),G40) -> 620 | E41: =H40 -> 620 | F41: =IF(AND(I40=1,D41<=E41),1,0) -> 1 | G41: =IF($D$38=1,Floor_liq,-1000000000) -> -1000000000 | H41: =E41-Round_cost+(1-Pledge_share)*C41 -> 535 | I41: =IF(AND(F41=1,G41<=H41),1,0) -> 1
A42: 2 | B42: =B41+Gap_closed*(Eff_ceiling-B41) -> 81.5 | C42: =Sav_point*(B42-Eff_0) -> 105 | D42: =IF($D$38=1,MAX(G41,Liq_start),G41) -> -1000000000 | E42: =H41 -> 535 | F42: =IF(AND(I41=1,D42<=E42),1,0) -> 1 | G42: =IF($D$38=1,Floor_liq,-1000000000) -> -1000000000 | H42: =E42-Round_cost+(1-Pledge_share)*C42 -> 467.5 | I42: =IF(AND(F42=1,G42<=H42),1,0) -> 1
A43: 3 | B43: =B42+Gap_closed*(Eff_ceiling-B42) -> 83.25 | C43: =Sav_point*(B43-Eff_0) -> 122.5 | D43: =IF($D$38=1,MAX(G42,Liq_start),G42) -> -1000000000 | E43: =H42 -> 467.5 | F43: =IF(AND(I42=1,D43<=E43),1,0) -> 1 | G43: =IF($D$38=1,Floor_liq,-1000000000) -> -1000000000 | H43: =E43-Round_cost+(1-Pledge_share)*C43 -> 408.75 | I43: =IF(AND(F43=1,G43<=H43),1,0) -> 1
A44: 4 | B44: =B43+Gap_closed*(Eff_ceiling-B43) -> 84.125 | C44: =Sav_point*(B44-Eff_0) -> 131.25 | D44: =IF($D$38=1,MAX(G43,Liq_start),G43) -> -1000000000 | E44: =H43 -> 408.75 | F44: =IF(AND(I43=1,D44<=E44),1,0) -> 1 | G44: =IF($D$38=1,Floor_liq,-1000000000) -> -1000000000 | H44: =E44-Round_cost+(1-Pledge_share)*C44 -> 354.375 | I44: =IF(AND(F44=1,G44<=H44),1,0) -> 1
A45: 5 | B45: =B44+Gap_closed*(Eff_ceiling-B44) -> 84.5625 | C45: =Sav_point*(B45-Eff_0) -> 135.625 | D45: =IF($D$38=1,MAX(G44,Liq_start),G44) -> -1000000000 | E45: =H44 -> 354.375 | F45: =IF(AND(I44=1,D45<=E45),1,0) -> 1 | G45: =IF($D$38=1,Floor_liq,-1000000000) -> -1000000000 | H45: =E45-Round_cost+(1-Pledge_share)*C45 -> 302.1875 | I45: =IF(AND(F45=1,G45<=H45),1,0) -> 1
A46: 6 | B46: =B45+Gap_closed*(Eff_ceiling-B45) -> 84.78125 | C46: =Sav_point*(B46-Eff_0) -> 137.8125 | D46: =IF($D$38=1,MAX(G45,Liq_start),G45) -> -1000000000 | E46: =H45 -> 302.1875 | F46: =IF(AND(I45=1,D46<=E46),1,0) -> 1 | G46: =IF($H$38=1,MAX(IF($D$38=1,Floor_liq,-1000000000),End_liq),IF($D$38=1,Floor_liq,-1000000000)) -> 470 | H46: =E46-Round_cost+(1-Pledge_share)*C46 -> 251.09375 | I46: =IF(AND(F46=1,G46<=H46),1,0) -> 0
A47: The first year whose set is empty: the plan dies (grey: no plan reaches these years keeping every commitment) | I47: =IF(COUNTIF(I41:I46,0)=0,0,MATCH(0,I41:I46,0)) -> 6

Sheet Schedules
A1: The 64 schedules of rounds, each run forward with no payout and with the half payout
A2: Row by row: the rounds (z_k = 1 in a round year), efficiency, savings, liquidity, and whether the board's conditions hold. The DiagnoseClash, Repairs and Optimizer sheets read this table.
A4: credit (years): | BG4: 0 | BH4: 5 | BI4: 10 | BJ4: 20 | BK4: 40 | BL4: 60
A5: Schedule | B5: z1 | C5: z2 | D5: z3 | E5: z4 | F5: z5 | G5: z6 | H5: Rounds | I5: Years of the rounds | J5: Efficiency, year 1 | K5: Efficiency, year 2 | L5: Efficiency, year 3 | M5: Efficiency, year 4 | N5: Efficiency, year 5 | O5: Efficiency, year 6 | P5: Savings, year 1 | Q5: Savings, year 2 | R5: Savings, year 3 | S5: Savings, year 4 | T5: Savings, year 5 | U5: Savings, year 6 | V5: Savings over six years | W5: Capability kept (1 = yes) | X5: Year-end liquidity 1, no payout | Y5: Year-end liquidity 2, no payout | Z5: Year-end liquidity 3, no payout | AA5: Year-end liquidity 4, no payout | AB5: Year-end liquidity 5, no payout | AC5: Year-end liquidity 6, no payout | AD5: After paying for round 1, no payout | AE5: After paying for round 2, no payout | AF5: After paying for round 3, no payout | AG5: After paying for round 4, no payout | AH5: After paying for round 5, no payout | AI5: After paying for round 6, no payout | AJ5: Floor kept, no payout | AK5: End condition kept, no payout | AL5: Board's conditions kept, no payout | AM5: Year-end liquidity 1, half paid out | AN5: Year-end liquidity 2, half paid out | AO5: Year-end liquidity 3, half paid out | AP5: Year-end liquidity 4, half paid out | AQ5: Year-end liquidity 5, half paid out | AR5: Year-end liquidity 6, half paid out | AS5: After paying for round 1, half paid out | AT5: After paying for round 2, half paid out | AU5: After paying for round 3, half paid out | AV5: After paying for round 4, half paid out | AW5: After paying for round 5, half paid out | AX5: After paying for round 6, half paid out | AY5: Floor kept, half paid out | AZ5: End condition kept, half paid out | BA5: Board's conditions kept, half paid out | BB5: Paid out under the half payout | BC5: Rank for repair (b): rounds, then paid out | BD5: Year-6 savings | BE5: Payouts + year-6 liquidity: the no-payout year-6 liquidity | BF5: Best six-year payout, the board's conditions kept | BG5: Value, credit 0 years | BH5: Value, credit 5 years | BI5: Value, credit 10 years | BJ5: Value, credit 20 years | BK5: Value, credit 40 years | BL5: Value, credit 60 years | BM5: Rounds in years 1 to n? (1 = yes) | BN5: Value in $ thousands (credit 0) | BO5: Value + 100 (credit 0) | BP5: ln(value) (credit 0)
A6: 0 | B6: =MOD(INT($A6/32),2) -> 0 | C6: =MOD(INT($A6/16),2) -> 0 | D6: =MOD(INT($A6/8),2) -> 0 | E6: =MOD(INT($A6/4),2) -> 0 | F6: =MOD(INT($A6/2),2) -> 0 | G6: =MOD(INT($A6/1),2) -> 0 | H6: =SUM(B6:G6) -> 0 | I6: =IF(H6=0,0,VALUE(IF(B6=1,"1","")&IF(C6=1,"2","")&IF(D6=1,"3","")&IF(E6=1,"4","")&IF(F6=1,"5","")&IF(G6=1,"6",""))) -> 0 | J6: =IF(B6=1,Eff_0+Gap_closed*(Eff_ceiling-Eff_0),Eff_0) -> 71 | K6: =IF(C6=1,J6+Gap_closed*(Eff_ceiling-J6),J6) -> 71 | L6: =IF(D6=1,K6+Gap_closed*(Eff_ceiling-K6),K6) -> 71 | M6: =IF(E6=1,L6+Gap_closed*(Eff_ceiling-L6),L6) -> 71 | N6: =IF(F6=1,M6+Gap_closed*(Eff_ceiling-M6),M6) -> 71 | O6: =IF(G6=1,N6+Gap_closed*(Eff_ceiling-N6),N6) -> 71 | P6: =Sav_point*(J6-Eff_0) -> 0 | Q6: =Sav_point*(K6-Eff_0) -> 0 | R6: =Sav_point*(L6-Eff_0) -> 0 | S6: =Sav_point*(M6-Eff_0) -> 0 | T6: =Sav_point*(N6-Eff_0) -> 0 | U6: =Sav_point*(O6-Eff_0) -> 0 | V6: =SUM(P6:U6) -> 0 | W6: =IF(AND(H6>0,Cap_0<Cap_min),0,1) -> 1 | X6: =Liq_0-Round_cost*B6+1*P6 -> 620 | Y6: =X6-Round_cost*C6+1*Q6 -> 620 | Z6: =Y6-Round_cost*D6+1*R6 -> 620 | AA6: =Z6-Round_cost*E6+1*S6 -> 620 | AB6: =AA6-Round_cost*F6+1*T6 -> 620 | AC6: =AB6-Round_cost*G6+1*U6 -> 620 | AD6: =IF(B6=1,Liq_0-Round_cost,1000000000) -> 1000000000 | AE6: =IF(C6=1,X6-Round_cost,1000000000) -> 1000000000 | AF6: =IF(D6=1,Y6-Round_cost,1000000000) -> 1000000000 | AG6: =IF(E6=1,Z6-Round_cost,1000000000) -> 1000000000 | AH6: =IF(F6=1,AA6-Round_cost,1000000000) -> 1000000000 | AI6: =IF(G6=1,AB6-Round_cost,1000000000) -> 1000000000 | AJ6: =IF(AND(MIN(X6:AC6)>=Floor_liq-0.000000001,MIN(AD6:AI6)>=Floor_liq-0.000000001),1,0) -> 1 | AK6: =IF(AC6>=End_liq-0.000000001,1,0) -> 1 | AL6: =AJ6*AK6*W6 -> 1 | AM6: =Liq_0-Round_cost*B6+(1-Pledge_share)*P6 -> 620 | AN6: =AM6-Round_cost*C6+(1-Pledge_share)*Q6 -> 620 | AO6: =AN6-Round_cost*D6+(1-Pledge_share)*R6 -> 620 | AP6: =AO6-Round_cost*E6+(1-Pledge_share)*S6 -> 620 | AQ6: =AP6-Round_cost*F6+(1-Pledge_share)*T6 -> 620 | AR6: =AQ6-Round_cost*G6+(1-Pledge_share)*U6 -> 620 | AS6: =IF(B6=1,Liq_0-Round_cost,1000000000) -> 1000000000 | AT6: =IF(C6=1,AM6-Round_cost,1000000000) -> 1000000000 | AU6: =IF(D6=1,AN6-Round_cost,1000000000) -> 1000000000 | AV6: =IF(E6=1,AO6-Round_cost,1000000000) -> 1000000000 | AW6: =IF(F6=1,AP6-Round_cost,1000000000) -> 1000000000 | AX6: =IF(G6=1,AQ6-Round_cost,1000000000) -> 1000000000 | AY6: =IF(AND(MIN(AM6:AR6)>=Floor_liq-0.000000001,MIN(AS6:AX6)>=Floor_liq-0.000000001),1,0) -> 1 | AZ6: =IF(AR6>=End_liq-0.000000001,1,0) -> 1 | BA6: =AY6*AZ6*W6 -> 1 | BB6: =Pledge_share*V6 -> 0 | BC6: =IF(BA6=1,H6*10000+BB6,-1) -> 0 | BD6: =U6 -> 0 | BE6: =AC6 -> 620 | BF6: =IF(AL6=1,AC6-End_liq,-1000000000) -> 150 | BG6: =IF(AL6=1,BF6+BG$4*BD6,-1000000000) -> 150 | BH6: =IF(AL6=1,BF6+BH$4*BD6,-1000000000) -> 150 | BI6: =IF(AL6=1,BF6+BI$4*BD6,-1000000000) -> 150 | BJ6: =IF(AL6=1,BF6+BJ$4*BD6,-1000000000) -> 150 | BK6: =IF(AL6=1,BF6+BK$4*BD6,-1000000000) -> 150 | BL6: =IF(AL6=1,BF6+BL$4*BD6,-1000000000) -> 150 | BM6: =IF(H6=0,1,IF(I6=VALUE(LEFT("123456",H6)),1,0)) -> 1 | BN6: =IF(BG6>0,1000*BG6,-1000000000000) -> 150000 | BO6: =IF(BG6>0,BG6+100,-1000000000) -> 250 | BP6: =IF(BG6>0,LN(BG6),-1000000000) -> 5.0106353
A7: 1 | B7: =MOD(INT($A7/32),2) -> 0 | C7: =MOD(INT($A7/16),2) -> 0 | D7: =MOD(INT($A7/8),2) -> 0 | E7: =MOD(INT($A7/4),2) -> 0 | F7: =MOD(INT($A7/2),2) -> 0 | G7: =MOD(INT($A7/1),2) -> 1 | H7: =SUM(B7:G7) -> 1 | I7: =IF(H7=0,0,VALUE(IF(B7=1,"1","")&IF(C7=1,"2","")&IF(D7=1,"3","")&IF(E7=1,"4","")&IF(F7=1,"5","")&IF(G7=1,"6",""))) -> 6 | J7: =IF(B7=1,Eff_0+Gap_closed*(Eff_ceiling-Eff_0),Eff_0) -> 71 | K7: =IF(C7=1,J7+Gap_closed*(Eff_ceiling-J7),J7) -> 71 | L7: =IF(D7=1,K7+Gap_closed*(Eff_ceiling-K7),K7) -> 71 | M7: =IF(E7=1,L7+Gap_closed*(Eff_ceiling-L7),L7) -> 71 | N7: =IF(F7=1,M7+Gap_closed*(Eff_ceiling-M7),M7) -> 71 | O7: =IF(G7=1,N7+Gap_closed*(Eff_ceiling-N7),N7) -> 78 | P7: =Sav_point*(J7-Eff_0) -> 0 | Q7: =Sav_point*(K7-Eff_0) -> 0 | R7: =Sav_point*(L7-Eff_0) -> 0 | S7: =Sav_point*(M7-Eff_0) -> 0 | T7: =Sav_point*(N7-Eff_0) -> 0 | U7: =Sav_point*(O7-Eff_0) -> 70 | V7: =SUM(P7:U7) -> 70 | W7: =IF(AND(H7>0,Cap_0<Cap_min),0,1) -> 1 | X7: =Liq_0-Round_cost*B7+1*P7 -> 620 | Y7: =X7-Round_cost*C7+1*Q7 -> 620 | Z7: =Y7-Round_cost*D7+1*R7 -> 620 | AA7: =Z7-Round_cost*E7+1*S7 -> 620 | AB7: =AA7-Round_cost*F7+1*T7 -> 620 | AC7: =AB7-Round_cost*G7+1*U7 -> 570 | AD7: =IF(B7=1,Liq_0-Round_cost,1000000000) -> 1000000000 | AE7: =IF(C7=1,X7-Round_cost,1000000000) -> 1000000000 | AF7: =IF(D7=1,Y7-Round_cost,1000000000) -> 1000000000 | AG7: =IF(E7=1,Z7-Round_cost,1000000000) -> 1000000000 | AH7: =IF(F7=1,AA7-Round_cost,1000000000) -> 1000000000 | AI7: =IF(G7=1,AB7-Round_cost,1000000000) -> 500 | AJ7: =IF(AND(MIN(X7:AC7)>=Floor_liq-0.000000001,MIN(AD7:AI7)>=Floor_liq-0.000000001),1,0) -> 1 | AK7: =IF(AC7>=End_liq-0.000000001,1,0) -> 1 | AL7: =AJ7*AK7*W7 -> 1 | AM7: =Liq_0-Round_cost*B7+(1-Pledge_share)*P7 -> 620 | AN7: =AM7-Round_cost*C7+(1-Pledge_share)*Q7 -> 620 | AO7: =AN7-Round_cost*D7+(1-Pledge_share)*R7 -> 620 | AP7: =AO7-Round_cost*E7+(1-Pledge_share)*S7 -> 620 | AQ7: =AP7-Round_cost*F7+(1-Pledge_share)*T7 -> 620 | AR7: =AQ7-Round_cost*G7+(1-Pledge_share)*U7 -> 535 | AS7: =IF(B7=1,Liq_0-Round_cost,1000000000) -> 1000000000 | AT7: =IF(C7=1,AM7-Round_cost,1000000000) -> 1000000000 | AU7: =IF(D7=1,AN7-Round_cost,1000000000) -> 1000000000 | AV7: =IF(E7=1,AO7-Round_cost,1000000000) -> 1000000000 | AW7: =IF(F7=1,AP7-Round_cost,1000000000) -> 1000000000 | AX7: =IF(G7=1,AQ7-Round_cost,1000000000) -> 500 | AY7: =IF(AND(MIN(AM7:AR7)>=Floor_liq-0.000000001,MIN(AS7:AX7)>=Floor_liq-0.000000001),1,0) -> 1 | AZ7: =IF(AR7>=End_liq-0.000000001,1,0) -> 1 | BA7: =AY7*AZ7*W7 -> 1 | BB7: =Pledge_share*V7 -> 35 | BC7: =IF(BA7=1,H7*10000+BB7,-1) -> 10035 | BD7: =U7 -> 70 | BE7: =AC7 -> 570 | BF7: =IF(AL7=1,AC7-End_liq,-1000000000) -> 100 | BG7: =IF(AL7=1,BF7+BG$4*BD7,-1000000000) -> 100 | BH7: =IF(AL7=1,BF7+BH$4*BD7,-1000000000) -> 450 | BI7: =IF(AL7=1,BF7+BI$4*BD7,-1000000000) -> 800 | BJ7: =IF(AL7=1,BF7+BJ$4*BD7,-1000000000) -> 1500 | BK7: =IF(AL7=1,BF7+BK$4*BD7,-1000000000) -> 2900 | BL7: =IF(AL7=1,BF7+BL$4*BD7,-1000000000) -> 4300 | BM7: =IF(H7=0,1,IF(I7=VALUE(LEFT("123456",H7)),1,0)) -> 0 | BN7: =IF(BG7>0,1000*BG7,-1000000000000) -> 100000 | BO7: =IF(BG7>0,BG7+100,-1000000000) -> 200 | BP7: =IF(BG7>0,LN(BG7),-1000000000) -> 4.6051702
A8: 2 | B8: =MOD(INT($A8/32),2) -> 0 | C8: =MOD(INT($A8/16),2) -> 0 | D8: =MOD(INT($A8/8),2) -> 0 | E8: =MOD(INT($A8/4),2) -> 0 | F8: =MOD(INT($A8/2),2) -> 1 | G8: =MOD(INT($A8/1),2) -> 0 | H8: =SUM(B8:G8) -> 1 | I8: =IF(H8=0,0,VALUE(IF(B8=1,"1","")&IF(C8=1,"2","")&IF(D8=1,"3","")&IF(E8=1,"4","")&IF(F8=1,"5","")&IF(G8=1,"6",""))) -> 5 | J8: =IF(B8=1,Eff_0+Gap_closed*(Eff_ceiling-Eff_0),Eff_0) -> 71 | K8: =IF(C8=1,J8+Gap_closed*(Eff_ceiling-J8),J8) -> 71 | L8: =IF(D8=1,K8+Gap_closed*(Eff_ceiling-K8),K8) -> 71 | M8: =IF(E8=1,L8+Gap_closed*(Eff_ceiling-L8),L8) -> 71 | N8: =IF(F8=1,M8+Gap_closed*(Eff_ceiling-M8),M8) -> 78 | O8: =IF(G8=1,N8+Gap_closed*(Eff_ceiling-N8),N8) -> 78 | P8: =Sav_point*(J8-Eff_0) -> 0 | Q8: =Sav_point*(K8-Eff_0) -> 0 | R8: =Sav_point*(L8-Eff_0) -> 0 | S8: =Sav_point*(M8-Eff_0) -> 0 | T8: =Sav_point*(N8-Eff_0) -> 70 | U8: =Sav_point*(O8-Eff_0) -> 70 | V8: =SUM(P8:U8) -> 140 | W8: =IF(AND(H8>0,Cap_0<Cap_min),0,1) -> 1 | X8: =Liq_0-Round_cost*B8+1*P8 -> 620 | Y8: =X8-Round_cost*C8+1*Q8 -> 620 | Z8: =Y8-Round_cost*D8+1*R8 -> 620 | AA8: =Z8-Round_cost*E8+1*S8 -> 620 | AB8: =AA8-Round_cost*F8+1*T8 -> 570 | AC8: =AB8-Round_cost*G8+1*U8 -> 640 | AD8: =IF(B8=1,Liq_0-Round_cost,1000000000) -> 1000000000 | AE8: =IF(C8=1,X8-Round_cost,1000000000) -> 1000000000 | AF8: =IF(D8=1,Y8-Round_cost,1000000000) -> 1000000000 | AG8: =IF(E8=1,Z8-Round_cost,1000000000) -> 1000000000 | AH8: =IF(F8=1,AA8-Round_cost,1000000000) -> 500 | AI8: =IF(G8=1,AB8-Round_cost,1000000000) -> 1000000000 | AJ8: =IF(AND(MIN(X8:AC8)>=Floor_liq-0.000000001,MIN(AD8:AI8)>=Floor_liq-0.000000001),1,0) -> 1 | AK8: =IF(AC8>=End_liq-0.000000001,1,0) -> 1 | AL8: =AJ8*AK8*W8 -> 1 | AM8: =Liq_0-Round_cost*B8+(1-Pledge_share)*P8 -> 620 | AN8: =AM8-Round_cost*C8+(1-Pledge_share)*Q8 -> 620 | AO8: =AN8-Round_cost*D8+(1-Pledge_share)*R8 -> 620 | AP8: =AO8-Round_cost*E8+(1-Pledge_share)*S8 -> 620 | AQ8: =AP8-Round_cost*F8+(1-Pledge_share)*T8 -> 535 | AR8: =AQ8-Round_cost*G8+(1-Pledge_share)*U8 -> 570 | AS8: =IF(B8=1,Liq_0-Round_cost,1000000000) -> 1000000000 | AT8: =IF(C8=1,AM8-Round_cost,1000000000) -> 1000000000 | AU8: =IF(D8=1,AN8-Round_cost,1000000000) -> 1000000000 | AV8: =IF(E8=1,AO8-Round_cost,1000000000) -> 1000000000 | AW8: =IF(F8=1,AP8-Round_cost,1000000000) -> 500 | AX8: =IF(G8=1,AQ8-Round_cost,1000000000) -> 1000000000 | AY8: =IF(AND(MIN(AM8:AR8)>=Floor_liq-0.000000001,MIN(AS8:AX8)>=Floor_liq-0.000000001),1,0) -> 1 | AZ8: =IF(AR8>=End_liq-0.000000001,1,0) -> 1 | BA8: =AY8*AZ8*W8 -> 1 | BB8: =Pledge_share*V8 -> 70 | BC8: =IF(BA8=1,H8*10000+BB8,-1) -> 10070 | BD8: =U8 -> 70 | BE8: =AC8 -> 640 | BF8: =IF(AL8=1,AC8-End_liq,-1000000000) -> 170 | BG8: =IF(AL8=1,BF8+BG$4*BD8,-1000000000) -> 170 | BH8: =IF(AL8=1,BF8+BH$4*BD8,-1000000000) -> 520 | BI8: =IF(AL8=1,BF8+BI$4*BD8,-1000000000) -> 870 | BJ8: =IF(AL8=1,BF8+BJ$4*BD8,-1000000000) -> 1570 | BK8: =IF(AL8=1,BF8+BK$4*BD8,-1000000000) -> 2970 | BL8: =IF(AL8=1,BF8+BL$4*BD8,-1000000000) -> 4370 | BM8: =IF(H8=0,1,IF(I8=VALUE(LEFT("123456",H8)),1,0)) -> 0 | BN8: =IF(BG8>0,1000*BG8,-1000000000000) -> 170000 | BO8: =IF(BG8>0,BG8+100,-1000000000) -> 270 | BP8: =IF(BG8>0,LN(BG8),-1000000000) -> 5.1357984
A9: 3 | B9: =MOD(INT($A9/32),2) -> 0 | C9: =MOD(INT($A9/16),2) -> 0 | D9: =MOD(INT($A9/8),2) -> 0 | E9: =MOD(INT($A9/4),2) -> 0 | F9: =MOD(INT($A9/2),2) -> 1 | G9: =MOD(INT($A9/1),2) -> 1 | H9: =SUM(B9:G9) -> 2 | I9: =IF(H9=0,0,VALUE(IF(B9=1,"1","")&IF(C9=1,"2","")&IF(D9=1,"3","")&IF(E9=1,"4","")&IF(F9=1,"5","")&IF(G9=1,"6",""))) -> 56 | J9: =IF(B9=1,Eff_0+Gap_closed*(Eff_ceiling-Eff_0),Eff_0) -> 71 | K9: =IF(C9=1,J9+Gap_closed*(Eff_ceiling-J9),J9) -> 71 | L9: =IF(D9=1,K9+Gap_closed*(Eff_ceiling-K9),K9) -> 71 | M9: =IF(E9=1,L9+Gap_closed*(Eff_ceiling-L9),L9) -> 71 | N9: =IF(F9=1,M9+Gap_closed*(Eff_ceiling-M9),M9) -> 78 | O9: =IF(G9=1,N9+Gap_closed*(Eff_ceiling-N9),N9) -> 81.5 | P9: =Sav_point*(J9-Eff_0) -> 0 | Q9: =Sav_point*(K9-Eff_0) -> 0 | R9: =Sav_point*(L9-Eff_0) -> 0 | S9: =Sav_point*(M9-Eff_0) -> 0 | T9: =Sav_point*(N9-Eff_0) -> 70 | U9: =Sav_point*(O9-Eff_0) -> 105 | V9: =SUM(P9:U9) -> 175 | W9: =IF(AND(H9>0,Cap_0<Cap_min),0,1) -> 1 | X9: =Liq_0-Round_cost*B9+1*P9 -> 620 | Y9: =X9-Round_cost*C9+1*Q9 -> 620 | Z9: =Y9-Round_cost*D9+1*R9 -> 620 | AA9: =Z9-Round_cost*E9+1*S9 -> 620 | AB9: =AA9-Round_cost*F9+1*T9 -> 570 | AC9: =AB9-Round_cost*G9+1*U9 -> 555 | AD9: =IF(B9=1,Liq_0-Round_cost,1000000000) -> 1000000000 | AE9: =IF(C9=1,X9-Round_cost,1000000000) -> 1000000000 | AF9: =IF(D9=1,Y9-Round_cost,1000000000) -> 1000000000 | AG9: =IF(E9=1,Z9-Round_cost,1000000000) -> 1000000000 | AH9: =IF(F9=1,AA9-Round_cost,1000000000) -> 500 | AI9: =IF(G9=1,AB9-Round_cost,1000000000) -> 450 | AJ9: =IF(AND(MIN(X9:AC9)>=Floor_liq-0.000000001,MIN(AD9:AI9)>=Floor_liq-0.000000001),1,0) -> 1 | AK9: =IF(AC9>=End_liq-0.000000001,1,0) -> 1 | AL9: =AJ9*AK9*W9 -> 1 | AM9: =Liq_0-Round_cost*B9+(1-Pledge_share)*P9 -> 620 | AN9: =AM9-Round_cost*C9+(1-Pledge_share)*Q9 -> 620 | AO9: =AN9-Round_cost*D9+(1-Pledge_share)*R9 -> 620 | AP9: =AO9-Round_cost*E9+(1-Pledge_share)*S9 -> 620 | AQ9: =AP9-Round_cost*F9+(1-Pledge_share)*T9 -> 535 | AR9: =AQ9-Round_cost*G9+(1-Pledge_share)*U9 -> 467.5 | AS9: =IF(B9=1,Liq_0-Round_cost,1000000000) -> 1000000000 | AT9: =IF(C9=1,AM9-Round_cost,1000000000) -> 1000000000 | AU9: =IF(D9=1,AN9-Round_cost,1000000000) -> 1000000000 | AV9: =IF(E9=1,AO9-Round_cost,1000000000) -> 1000000000 | AW9: =IF(F9=1,AP9-Round_cost,1000000000) -> 500 | AX9: =IF(G9=1,AQ9-Round_cost,1000000000) -> 415 | AY9: =IF(AND(MIN(AM9:AR9)>=Floor_liq-0.000000001,MIN(AS9:AX9)>=Floor_liq-0.000000001),1,0) -> 1 | AZ9: =IF(AR9>=End_liq-0.000000001,1,0) -> 0 | BA9: =AY9*AZ9*W9 -> 0 | BB9: =Pledge_share*V9 -> 87.5 | BC9: =IF(BA9=1,H9*10000+BB9,-1) -> -1 | BD9: =U9 -> 105 | BE9: =AC9 -> 555 | BF9: =IF(AL9=1,AC9-End_liq,-1000000000) -> 85 | BG9: =IF(AL9=1,BF9+BG$4*BD9,-1000000000) -> 85 | BH9: =IF(AL9=1,BF9+BH$4*BD9,-1000000000) -> 610 | BI9: =IF(AL9=1,BF9+BI$4*BD9,-1000000000) -> 1135 | BJ9: =IF(AL9=1,BF9+BJ$4*BD9,-1000000000) -> 2185 | BK9: =IF(AL9=1,BF9+BK$4*BD9,-1000000000) -> 4285 | BL9: =IF(AL9=1,BF9+BL$4*BD9,-1000000000) -> 6385 | BM9: =IF(H9=0,1,IF(I9=VALUE(LEFT("123456",H9)),1,0)) -> 0 | BN9: =IF(BG9>0,1000*BG9,-1000000000000) -> 85000 | BO9: =IF(BG9>0,BG9+100,-1000000000) -> 185 | BP9: =IF(BG9>0,LN(BG9),-1000000000) -> 4.4426513
A10: 4 | B10: =MOD(INT($A10/32),2) -> 0 | C10: =MOD(INT($A10/16),2) -> 0 | D10: =MOD(INT($A10/8),2) -> 0 | E10: =MOD(INT($A10/4),2) -> 1 | F10: =MOD(INT($A10/2),2) -> 0 | G10: =MOD(INT($A10/1),2) -> 0 | H10: =SUM(B10:G10) -> 1 | I10: =IF(H10=0,0,VALUE(IF(B10=1,"1","")&IF(C10=1,"2","")&IF(D10=1,"3","")&IF(E10=1,"4","")&IF(F10=1,"5","")&IF(G10=1,"6",""))) -> 4 | J10: =IF(B10=1,Eff_0+Gap_closed*(Eff_ceiling-Eff_0),Eff_0) -> 71 | K10: =IF(C10=1,J10+Gap_closed*(Eff_ceiling-J10),J10) -> 71 | L10: =IF(D10=1,K10+Gap_closed*(Eff_ceiling-K10),K10) -> 71 | M10: =IF(E10=1,L10+Gap_closed*(Eff_ceiling-L10),L10) -> 78 | N10: =IF(F10=1,M10+Gap_closed*(Eff_ceiling-M10),M10) -> 78 | O10: =IF(G10=1,N10+Gap_closed*(Eff_ceiling-N10),N10) -> 78 | P10: =Sav_point*(J10-Eff_0) -> 0 | Q10: =Sav_point*(K10-Eff_0) -> 0 | R10: =Sav_point*(L10-Eff_0) -> 0 | S10: =Sav_point*(M10-Eff_0) -> 70 | T10: =Sav_point*(N10-Eff_0) -> 70 | U10: =Sav_point*(O10-Eff_0) -> 70 | V10: =SUM(P10:U10) -> 210 | W10: =IF(AND(H10>0,Cap_0<Cap_min),0,1) -> 1 | X10: =Liq_0-Round_cost*B10+1*P10 -> 620 | Y10: =X10-Round_cost*C10+1*Q10 -> 620 | Z10: =Y10-Round_cost*D10+1*R10 -> 620 | AA10: =Z10-Round_cost*E10+1*S10 -> 570 | AB10: =AA10-Round_cost*F10+1*T10 -> 640 | AC10: =AB10-Round_cost*G10+1*U10 -> 710 | AD10: =IF(B10=1,Liq_0-Round_cost,1000000000) -> 1000000000 | AE10: =IF(C10=1,X10-Round_cost,1000000000) -> 1000000000 | AF10: =IF(D10=1,Y10-Round_cost,1000000000) -> 1000000000 | AG10: =IF(E10=1,Z10-Round_cost,1000000000) -> 500 | AH10: =IF(F10=1,AA10-Round_cost,1000000000) -> 1000000000 | AI10: =IF(G10=1,AB10-Round_cost,1000000000) -> 1000000000 | AJ10: =IF(AND(MIN(X10:AC10)>=Floor_liq-0.000000001,MIN(AD10:AI10)>=Floor_liq-0.000000001),1,0) -> 1 | AK10: =IF(AC10>=End_liq-0.000000001,1,0) -> 1 | AL10: =AJ10*AK10*W10 -> 1 | AM10: =Liq_0-Round_cost*B10+(1-Pledge_share)*P10 -> 620 | AN10: =AM10-Round_cost*C10+(1-Pledge_share)*Q10 -> 620 | AO10: =AN10-Round_cost*D10+(1-Pledge_share)*R10 -> 620 | AP10: =AO10-Round_cost*E10+(1-Pledge_share)*S10 -> 535 | AQ10: =AP10-Round_cost*F10+(1-Pledge_share)*T10 -> 570 | AR10: =AQ10-Round_cost*G10+(1-Pledge_share)*U10 -> 605 | AS10: =IF(B10=1,Liq_0-Round_cost,1000000000) -> 1000000000 | AT10: =IF(C10=1,AM10-Round_cost,1000000000) -> 1000000000 | AU10: =IF(D10=1,AN10-Round_cost,1000000000) -> 1000000000 | AV10: =IF(E10=1,AO10-Round_cost,1000000000) -> 500 | AW10: =IF(F10=1,AP10-Round_cost,1000000000) -> 1000000000 | AX10: =IF(G10=1,AQ10-Round_cost,1000000000) -> 1000000000 | AY10: =IF(AND(MIN(AM10:AR10)>=Floor_liq-0.000000001,MIN(AS10:AX10)>=Floor_liq-0.000000001),1,0) -> 1 | AZ10: =IF(AR10>=End_liq-0.000000001,1,0) -> 1 | BA10: =AY10*AZ10*W10 -> 1 | BB10: =Pledge_share*V10 -> 105 | BC10: =IF(BA10=1,H10*10000+BB10,-1) -> 10105 | BD10: =U10 -> 70 | BE10: =AC10 -> 710 | BF10: =IF(AL10=1,AC10-End_liq,-1000000000) -> 240 | BG10: =IF(AL10=1,BF10+BG$4*BD10,-1000000000) -> 240 | BH10: =IF(AL10=1,BF10+BH$4*BD10,-1000000000) -> 590 | BI10: =IF(AL10=1,BF10+BI$4*BD10,-1000000000) -> 940 | BJ10: =IF(AL10=1,BF10+BJ$4*BD10,-1000000000) -> 1640 | BK10: =IF(AL10=1,BF10+BK$4*BD10,-1000000000) -> 3040 | BL10: =IF(AL10=1,BF10+BL$4*BD10,-1000000000) -> 4440 | BM10: =IF(H10=0,1,IF(I10=VALUE(LEFT("123456",H10)),1,0)) -> 0 | BN10: =IF(BG10>0,1000*BG10,-1000000000000) -> 240000 | BO10: =IF(BG10>0,BG10+100,-1000000000) -> 340 | BP10: =IF(BG10>0,LN(BG10),-1000000000) -> 5.4806389
A11: 5 | B11: =MOD(INT($A11/32),2) -> 0 | C11: =MOD(INT($A11/16),2) -> 0 | D11: =MOD(INT($A11/8),2) -> 0 | E11: =MOD(INT($A11/4),2) -> 1 | F11: =MOD(INT($A11/2),2) -> 0 | G11: =MOD(INT($A11/1),2) -> 1 | H11: =SUM(B11:G11) -> 2 | I11: =IF(H11=0,0,VALUE(IF(B11=1,"1","")&IF(C11=1,"2","")&IF(D11=1,"3","")&IF(E11=1,"4","")&IF(F11=1,"5","")&IF(G11=1,"6",""))) -> 46 | J11: =IF(B11=1,Eff_0+Gap_closed*(Eff_ceiling-Eff_0),Eff_0) -> 71 | K11: =IF(C11=1,J11+Gap_closed*(Eff_ceiling-J11),J11) -> 71 | L11: =IF(D11=1,K11+Gap_closed*(Eff_ceiling-K11),K11) -> 71 | M11: =IF(E11=1,L11+Gap_closed*(Eff_ceiling-L11),L11) -> 78 | N11: =IF(F11=1,M11+Gap_closed*(Eff_ceiling-M11),M11) -> 78 | O11: =IF(G11=1,N11+Gap_closed*(Eff_ceiling-N11),N11) -> 81.5 | P11: =Sav_point*(J11-Eff_0) -> 0 | Q11: =Sav_point*(K11-Eff_0) -> 0 | R11: =Sav_point*(L11-Eff_0) -> 0 | S11: =Sav_point*(M11-Eff_0) -> 70 | T11: =Sav_point*(N11-Eff_0) -> 70 | U11: =Sav_point*(O11-Eff_0) -> 105 | V11: =SUM(P11:U11) -> 245 | W11: =IF(AND(H11>0,Cap_0<Cap_min),0,1) -> 1 | X11: =Liq_0-Round_cost*B11+1*P11 -> 620 | Y11: =X11-Round_cost*C11+1*Q11 -> 620 | Z11: =Y11-Round_cost*D11+1*R11 -> 620 | AA11: =Z11-Round_cost*E11+1*S11 -> 570 | AB11: =AA11-Round_cost*F11+1*T11 -> 640 | AC11: =AB11-Round_cost*G11+1*U11 -> 625 | AD11: =IF(B11=1,Liq_0-Round_cost,1000000000) -> 1000000000 | AE11: =IF(C11=1,X11-Round_cost,1000000000) -> 1000000000 | AF11: =IF(D11=1,Y11-Round_cost,1000000000) -> 1000000000 | AG11: =IF(E11=1,Z11-Round_cost,1000000000) -> 500 | AH11: =IF(F11=1,AA11-Round_cost,1000000000) -> 1000000000 | AI11: =IF(G11=1,AB11-Round_cost,1000000000) -> 520 | AJ11: =IF(AND(MIN(X11:AC11)>=Floor_liq-0.000000001,MIN(AD11:AI11)>=Floor_liq-0.000000001),1,0) -> 1 | AK11: =IF(AC11>=End_liq-0.000000001,1,0) -> 1 | AL11: =AJ11*AK11*W11 -> 1 | AM11: =Liq_0-Round_cost*B11+(1-Pledge_share)*P11 -> 620 | AN11: =AM11-Round_cost*C11+(1-Pledge_share)*Q11 -> 620 | AO11: =AN11-Round_cost*D11+(1-Pledge_share)*R11 -> 620 | AP11: =AO11-Round_cost*E11+(1-Pledge_share)*S11 -> 535 | AQ11: =AP11-Round_cost*F11+(1-Pledge_share)*T11 -> 570 | AR11: =AQ11-Round_cost*G11+(1-Pledge_share)*U11 -> 502.5 | AS11: =IF(B11=1,Liq_0-Round_cost,1000000000) -> 1000000000 | AT11: =IF(C11=1,AM11-Round_cost,1000000000) -> 1000000000 | AU11: =IF(D11=1,AN11-Round_cost,1000000000) -> 1000000000 | AV11: =IF(E11=1,AO11-Round_cost,1000000000) -> 500 | AW11: =IF(F11=1,AP11-Round_cost,1000000000) -> 1000000000 | AX11: =IF(G11=1,AQ11-Round_cost,1000000000) -> 450 | AY11: =IF(AND(MIN(AM11:AR11)>=Floor_liq-0.000000001,MIN(AS11:AX11)>=Floor_liq-0.000000001),1,0) -> 1 | AZ11: =IF(AR11>=End_liq-0.000000001,1,0) -> 1 | BA11: =AY11*AZ11*W11 -> 1 | BB11: =Pledge_share*V11 -> 122.5 | BC11: =IF(BA11=1,H11*10000+BB11,-1) -> 20122.5 | BD11: =U11 -> 105 | BE11: =AC11 -> 625 | BF11: =IF(AL11=1,AC11-End_liq,-1000000000) -> 155 | BG11: =IF(AL11=1,BF11+BG$4*BD11,-1000000000) -> 155 | BH11: =IF(AL11=1,BF11+BH$4*BD11,-1000000000) -> 680 | BI11: =IF(AL11=1,BF11+BI$4*BD11,-1000000000) -> 1205 | BJ11: =IF(AL11=1,BF11+BJ$4*BD11,-1000000000) -> 2255 | BK11: =IF(AL11=1,BF11+BK$4*BD11,-1000000000) -> 4355 | BL11: =IF(AL11=1,BF11+BL$4*BD11,-1000000000) -> 6455 | BM11: =IF(H11=0,1,IF(I11=VALUE(LEFT("123456",H11)),1,0)) -> 0 | BN11: =IF(BG11>0,1000*BG11,-1000000000000) -> 155000 | BO11: =IF(BG11>0,BG11+100,-1000000000) -> 255 | BP11: =IF(BG11>0,LN(BG11),-1000000000) -> 5.0434251
A12: 6 | B12: =MOD(INT($A12/32),2) -> 0 | C12: =MOD(INT($A12/16),2) -> 0 | D12: =MOD(INT($A12/8),2) -> 0 | E12: =MOD(INT($A12/4),2) -> 1 | F12: =MOD(INT($A12/2),2) -> 1 | G12: =MOD(INT($A12/1),2) -> 0 | H12: =SUM(B12:G12) -> 2 | I12: =IF(H12=0,0,VALUE(IF(B12=1,"1","")&IF(C12=1,"2","")&IF(D12=1,"3","")&IF(E12=1,"4","")&IF(F12=1,"5","")&IF(G12=1,"6",""))) -> 45 | J12: =IF(B12=1,Eff_0+Gap_closed*(Eff_ceiling-Eff_0),Eff_0) -> 71 | K12: =IF(C12=1,J12+Gap_closed*(Eff_ceiling-J12),J12) -> 71 | L12: =IF(D12=1,K12+Gap_closed*(Eff_ceiling-K12),K12) -> 71 | M12: =IF(E12=1,L12+Gap_closed*(Eff_ceiling-L12),L12) -> 78 | N12: =IF(F12=1,M12+Gap_closed*(Eff_ceiling-M12),M12) -> 81.5 | O12: =IF(G12=1,N12+Gap_closed*(Eff_ceiling-N12),N12) -> 81.5 | P12: =Sav_point*(J12-Eff_0) -> 0 | Q12: =Sav_point*(K12-Eff_0) -> 0 | R12: =Sav_point*(L12-Eff_0) -> 0 | S12: =Sav_point*(M12-Eff_0) -> 70 | T12: =Sav_point*(N12-Eff_0) -> 105 | U12: =Sav_point*(O12-Eff_0) -> 105 | V12: =SUM(P12:U12) -> 280 | W12: =IF(AND(H12>0,Cap_0<Cap_min),0,1) -> 1 | X12: =Liq_0-Round_cost*B12+1*P12 -> 620 | Y12: =X12-Round_cost*C12+1*Q12 -> 620 | Z12: =Y12-Round_cost*D12+1*R12 -> 620 | AA12: =Z12-Round_cost*E12+1*S12 -> 570 | AB12: =AA12-Round_cost*F12+1*T12 -> 555 | AC12: =AB12-Round_cost*G12+1*U12 -> 660 | AD12: =IF(B12=1,Liq_0-Round_cost,1000000000) -> 1000000000 | AE12: =IF(C12=1,X12-Round_cost,1000000000) -> 1000000000 | AF12: =IF(D12=1,Y12-Round_cost,1000000000) -> 1000000000 | AG12: =IF(E12=1,Z12-Round_cost,1000000000) -> 500 | AH12: =IF(F12=1,AA12-Round_cost,1000000000) -> 450 | AI12: =IF(G12=1,AB12-Round_cost,1000000000) -> 1000000000 | AJ12: =IF(AND(MIN(X12:AC12)>=Floor_liq-0.000000001,MIN(AD12:AI12)>=Floor_liq-0.000000001),1,0) -> 1 | AK12: =IF(AC12>=End_liq-0.000000001,1,0) -> 1 | AL12: =AJ12*AK12*W12 -> 1 | AM12: =Liq_0-Round_cost*B12+(1-Pledge_share)*P12 -> 620 | AN12: =AM12-Round_cost*C12+(1-Pledge_share)*Q12 -> 620 | AO12: =AN12-Round_cost*D12+(1-Pledge_share)*R12 -> 620 | AP12: =AO12-Round_cost*E12+(1-Pledge_share)*S12 -> 535 | AQ12: =AP12-Round_cost*F12+(1-Pledge_share)*T12 -> 467.5 | AR12: =AQ12-Round_cost*G12+(1-Pledge_share)*U12 -> 520 | AS12: =IF(B12=1,Liq_0-Round_cost,1000000000) -> 1000000000 | AT12: =IF(C12=1,AM12-Round_cost,1000000000) -> 1000000000 | AU12: =IF(D12=1,AN12-Round_cost,1000000000) -> 1000000000 | AV12: =IF(E12=1,AO12-Round_cost,1000000000) -> 500 | AW12: =IF(F12=1,AP12-Round_cost,1000000000) -> 415 | AX12: =IF(G12=1,AQ12-Round_cost,1000000000) -> 1000000000 | AY12: =IF(AND(MIN(AM12:AR12)>=Floor_liq-0.000000001,MIN(AS12:AX12)>=Floor_liq-0.000000001),1,0) -> 1 | AZ12: =IF(AR12>=End_liq-0.000000001,1,0) -> 1 | BA12: =AY12*AZ12*W12 -> 1 | BB12: =Pledge_share*V12 -> 140 | BC12: =IF(BA12=1,H12*10000+BB12,-1) -> 20140 | BD12: =U12 -> 105 | BE12: =AC12 -> 660 | BF12: =IF(AL12=1,AC12-End_liq,-1000000000) -> 190 | BG12: =IF(AL12=1,BF12+BG$4*BD12,-1000000000) -> 190 | BH12: =IF(AL12=1,BF12+BH$4*BD12,-1000000000) -> 715 | BI12: =IF(AL12=1,BF12+BI$4*BD12,-1000000000) -> 1240 | BJ12: =IF(AL12=1,BF12+BJ$4*BD12,-1000000000) -> 2290 | BK12: =IF(AL12=1,BF12+BK$4*BD12,-1000000000) -> 4390 | BL12: =IF(AL12=1,BF12+BL$4*BD12,-1000000000) -> 6490 | BM12: =IF(H12=0,1,IF(I12=VALUE(LEFT("123456",H12)),1,0)) -> 0 | BN12: =IF(BG12>0,1000*BG12,-1000000000000) -> 190000 | BO12: =IF(BG12>0,BG12+100,-1000000000) -> 290 | BP12: =IF(BG12>0,LN(BG12),-1000000000) -> 5.2470241
A13: 7 | B13: =MOD(INT($A13/32),2) -> 0 | C13: =MOD(INT($A13/16),2) -> 0 | D13: =MOD(INT($A13/8),2) -> 0 | E13: =MOD(INT($A13/4),2) -> 1 | F13: =MOD(INT($A13/2),2) -> 1 | G13: =MOD(INT($A13/1),2) -> 1 | H13: =SUM(B13:G13) -> 3 | I13: =IF(H13=0,0,VALUE(IF(B13=1,"1","")&IF(C13=1,"2","")&IF(D13=1,"3","")&IF(E13=1,"4","")&IF(F13=1,"5","")&IF(G13=1,"6",""))) -> 456 | J13: =IF(B13=1,Eff_0+Gap_closed*(Eff_ceiling-Eff_0),Eff_0) -> 71 | K13: =IF(C13=1,J13+Gap_closed*(Eff_ceiling-J13),J13) -> 71 | L13: =IF(D13=1,K13+Gap_closed*(Eff_ceiling-K13),K13) -> 71 | M13: =IF(E13=1,L13+Gap_closed*(Eff_ceiling-L13),L13) -> 78 | N13: =IF(F13=1,M13+Gap_closed*(Eff_ceiling-M13),M13) -> 81.5 | O13: =IF(G13=1,N13+Gap_closed*(Eff_ceiling-N13),N13) -> 83.25 | P13: =Sav_point*(J13-Eff_0) -> 0 | Q13: =Sav_point*(K13-Eff_0) -> 0 | R13: =Sav_point*(L13-Eff_0) -> 0 | S13: =Sav_point*(M13-Eff_0) -> 70 | T13: =Sav_point*(N13-Eff_0) -> 105 | U13: =Sav_point*(O13-Eff_0) -> 122.5 | V13: =SUM(P13:U13) -> 297.5 | W13: =IF(AND(H13>0,Cap_0<Cap_min),0,1) -> 1 | X13: =Liq_0-Round_cost*B13+1*P13 -> 620 | Y13: =X13-Round_cost*C13+1*Q13 -> 620 | Z13: =Y13-Round_cost*D13+1*R13 -> 620 | AA13: =Z13-Round_cost*E13+1*S13 -> 570 | AB13: =AA13-Round_cost*F13+1*T13 -> 555 | AC13: =AB13-Round_cost*G13+1*U13 -> 557.5 | AD13: =IF(B13=1,Liq_0-Round_cost,1000000000) -> 1000000000 | AE13: =IF(C13=1,X13-Round_cost,1000000000) -> 1000000000 | AF13: =IF(D13=1,Y13-Round_cost,1000000000) -> 1000000000 | AG13: =IF(E13=1,Z13-Round_cost,1000000000) -> 500 | AH13: =IF(F13=1,AA13-Round_cost,1000000000) -> 450 | AI13: =IF(G13=1,AB13-Round_cost,1000000000) -> 435 | AJ13: =IF(AND(MIN(X13:AC13)>=Floor_liq-0.000000001,MIN(AD13:AI13)>=Floor_liq-0.000000001),1,0) -> 1 | AK13: =IF(AC13>=End_liq-0.000000001,1,0) -> 1 | AL13: =AJ13*AK13*W13 -> 1 | AM13: =Liq_0-Round_cost*B13+(1-Pledge_share)*P13 -> 620 | AN13: =AM13-Round_cost*C13+(1-Pledge_share)*Q13 -> 620 | AO13: =AN13-Round_cost*D13+(1-Pledge_share)*R13 -> 620 | AP13: =AO13-Round_cost*E13+(1-Pledge_share)*S13 -> 535 | AQ13: =AP13-Round_cost*F13+(1-Pledge_share)*T13 -> 467.5 | AR13: =AQ13-Round_cost*G13+(1-Pledge_share)*U13 -> 408.75 | AS13: =IF(B13=1,Liq_0-Round_cost,1000000000) -> 1000000000 | AT13: =IF(C13=1,AM13-Round_cost,1000000000) -> 1000000000 | AU13: =IF(D13=1,AN13-Round_cost,1000000000) -> 1000000000 | AV13: =IF(E13=1,AO13-Round_cost,1000000000) -> 500 | AW13: =IF(F13=1,AP13-Round_cost,1000000000) -> 415 | AX13: =IF(G13=1,AQ13-Round_cost,1000000000) -> 347.5 | AY13: =IF(AND(MIN(AM13:AR13)>=Floor_liq-0.000000001,MIN(AS13:AX13)>=Floor_liq-0.000000001),1,0) -> 0 | AZ13: =IF(AR13>=End_liq-0.000000001,1,0) -> 0 | BA13: =AY13*AZ13*W13 -> 0 | BB13: =Pledge_share*V13 -> 148.75 | BC13: =IF(BA13=1,H13*10000+BB13,-1) -> -1 | BD13: =U13 -> 122.5 | BE13: =AC13 -> 557.5 | BF13: =IF(AL13=1,AC13-End_liq,-1000000000) -> 87.5 | BG13: =IF(AL13=1,BF13+BG$4*BD13,-1000000000) -> 87.5 | BH13: =IF(AL13=1,BF13+BH$4*BD13,-1000000000) -> 700 | BI13: =IF(AL13=1,BF13+BI$4*BD13,-1000000000) -> 1312.5 | BJ13: =IF(AL13=1,BF13+BJ$4*BD13,-1000000000) -> 2537.5 | BK13: =IF(AL13=1,BF13+BK$4*BD13,-1000000000) -> 4987.5 | BL13: =IF(AL13=1,BF13+BL$4*BD13,-1000000000) -> 7437.5 | BM13: =IF(H13=0,1,IF(I13=VALUE(LEFT("123456",H13)),1,0)) -> 0 | BN13: =IF(BG13>0,1000*BG13,-1000000000000) -> 87500 | BO13: =IF(BG13>0,BG13+100,-1000000000) -> 187.5 | BP13: =IF(BG13>0,LN(BG13),-1000000000) -> 4.4716388
A14: 8 | B14: =MOD(INT($A14/32),2) -> 0 | C14: =MOD(INT($A14/16),2) -> 0 | D14: =MOD(INT($A14/8),2) -> 1 | E14: =MOD(INT($A14/4),2) -> 0 | F14: =MOD(INT($A14/2),2) -> 0 | G14: =MOD(INT($A14/1),2) -> 0 | H14: =SUM(B14:G14) -> 1 | I14: =IF(H14=0,0,VALUE(IF(B14=1,"1","")&IF(C14=1,"2","")&IF(D14=1,"3","")&IF(E14=1,"4","")&IF(F14=1,"5","")&IF(G14=1,"6",""))) -> 3 | J14: =IF(B14=1,Eff_0+Gap_closed*(Eff_ceiling-Eff_0),Eff_0) -> 71 | K14: =IF(C14=1,J14+Gap_closed*(Eff_ceiling-J14),J14) -> 71 | L14: =IF(D14=1,K14+Gap_closed*(Eff_ceiling-K14),K14) -> 78 | M14: =IF(E14=1,L14+Gap_closed*(Eff_ceiling-L14),L14) -> 78 | N14: =IF(F14=1,M14+Gap_closed*(Eff_ceiling-M14),M14) -> 78 | O14: =IF(G14=1,N14+Gap_closed*(Eff_ceiling-N14),N14) -> 78 | P14: =Sav_point*(J14-Eff_0) -> 0 | Q14: =Sav_point*(K14-Eff_0) -> 0 | R14: =Sav_point*(L14-Eff_0) -> 70 | S14: =Sav_point*(M14-Eff_0) -> 70 | T14: =Sav_point*(N14-Eff_0) -> 70 | U14: =Sav_point*(O14-Eff_0) -> 70 | V14: =SUM(P14:U14) -> 280 | W14: =IF(AND(H14>0,Cap_0<Cap_min),0,1) -> 1 | X14: =Liq_0-Round_cost*B14+1*P14 -> 620 | Y14: =X14-Round_cost*C14+1*Q14 -> 620 | Z14: =Y14-Round_cost*D14+1*R14 -> 570 | AA14: =Z14-Round_cost*E14+1*S14 -> 640 | AB14: =AA14-Round_cost*F14+1*T14 -> 710 | AC14: =AB14-Round_cost*G14+1*U14 -> 780 | AD14: =IF(B14=1,Liq_0-Round_cost,1000000000) -> 1000000000 | AE14: =IF(C14=1,X14-Round_cost,1000000000) -> 1000000000 | AF14: =IF(D14=1,Y14-Round_cost,1000000000) -> 500 | AG14: =IF(E14=1,Z14-Round_cost,1000000000) -> 1000000000 | AH14: =IF(F14=1,AA14-Round_cost,1000000000) -> 1000000000 | AI14: =IF(G14=1,AB14-Round_cost,1000000000) -> 1000000000 | AJ14: =IF(AND(MIN(X14:AC14)>=Floor_liq-0.000000001,MIN(AD14:AI14)>=Floor_liq-0.000000001),1,0) -> 1 | AK14: =IF(AC14>=End_liq-0.000000001,1,0) -> 1 | AL14: =AJ14*AK14*W14 -> 1 | AM14: =Liq_0-Round_cost*B14+(1-Pledge_share)*P14 -> 620 | AN14: =AM14-Round_cost*C14+(1-Pledge_share)*Q14 -> 620 | AO14: =AN14-Round_cost*D14+(1-Pledge_share)*R14 -> 535 | AP14: =AO14-Round_cost*E14+(1-Pledge_share)*S14 -> 570 | AQ14: =AP14-Round_cost*F14+(1-Pledge_share)*T14 -> 605 | AR14: =AQ14-Round_cost*G14+(1-Pledge_share)*U14 -> 640 | AS14: =IF(B14=1,Liq_0-Round_cost,1000000000) -> 1000000000 | AT14: =IF(C14=1,AM14-Round_cost,1000000000) -> 1000000000 | AU14: =IF(D14=1,AN14-Round_cost,1000000000) -> 500 | AV14: =IF(E14=1,AO14-Round_cost,1000000000) -> 1000000000 | AW14: =IF(F14=1,AP14-Round_cost,1000000000) -> 1000000000 | AX14: =IF(G14=1,AQ14-Round_cost,1000000000) -> 1000000000 | AY14: =IF(AND(MIN(AM14:AR14)>=Floor_liq-0.000000001,MIN(AS14:AX14)>=Floor_liq-0.000000001),1,0) -> 1 | AZ14: =IF(AR14>=End_liq-0.000000001,1,0) -> 1 | BA14: =AY14*AZ14*W14 -> 1 | BB14: =Pledge_share*V14 -> 140 | BC14: =IF(BA14=1,H14*10000+BB14,-1) -> 10140 | BD14: =U14 -> 70 | BE14: =AC14 -> 780 | BF14: =IF(AL14=1,AC14-End_liq,-1000000000) -> 310 | BG14: =IF(AL14=1,BF14+BG$4*BD14,-1000000000) -> 310 | BH14: =IF(AL14=1,BF14+BH$4*BD14,-1000000000) -> 660 | BI14: =IF(AL14=1,BF14+BI$4*BD14,-1000000000) -> 1010 | BJ14: =IF(AL14=1,BF14+BJ$4*BD14,-1000000000) -> 1710 | BK14: =IF(AL14=1,BF14+BK$4*BD14,-1000000000) -> 3110 | BL14: =IF(AL14=1,BF14+BL$4*BD14,-1000000000) -> 4510 | BM14: =IF(H14=0,1,IF(I14=VALUE(LEFT("123456",H14)),1,0)) -> 0 | BN14: =IF(BG14>0,1000*BG14,-1000000000000) -> 310000 | BO14: =IF(BG14>0,BG14+100,-1000000000) -> 410 | BP14: =IF(BG14>0,LN(BG14),-1000000000) -> 5.7365723
A15: 9 | B15: =MOD(INT($A15/32),2) -> 0 | C15: =MOD(INT($A15/16),2) -> 0 | D15: =MOD(INT($A15/8),2) -> 1 | E15: =MOD(INT($A15/4),2) -> 0 | F15: =MOD(INT($A15/2),2) -> 0 | G15: =MOD(INT($A15/1),2) -> 1 | H15: =SUM(B15:G15) -> 2 | I15: =IF(H15=0,0,VALUE(IF(B15=1,"1","")&IF(C15=1,"2","")&IF(D15=1,"3","")&IF(E15=1,"4","")&IF(F15=1,"5","")&IF(G15=1,"6",""))) -> 36 | J15: =IF(B15=1,Eff_0+Gap_closed*(Eff_ceiling-Eff_0),Eff_0) -> 71 | K15: =IF(C15=1,J15+Gap_closed*(Eff_ceiling-J15),J15) -> 71 | L15: =IF(D15=1,K15+Gap_closed*(Eff_ceiling-K15),K15) -> 78 | M15: =IF(E15=1,L15+Gap_closed*(Eff_ceiling-L15),L15) -> 78 | N15: =IF(F15=1,M15+Gap_closed*(Eff_ceiling-M15),M15) -> 78 | O15: =IF(G15=1,N15+Gap_closed*(Eff_ceiling-N15),N15) -> 81.5 | P15: =Sav_point*(J15-Eff_0) -> 0 | Q15: =Sav_point*(K15-Eff_0) -> 0 | R15: =Sav_point*(L15-Eff_0) -> 70 | S15: =Sav_point*(M15-Eff_0) -> 70 | T15: =Sav_point*(N15-Eff_0) -> 70 | U15: =Sav_point*(O15-Eff_0) -> 105 | V15: =SUM(P15:U15) -> 315 | W15: =IF(AND(H15>0,Cap_0<Cap_min),0,1) -> 1 | X15: =Liq_0-Round_cost*B15+1*P15 -> 620 | Y15: =X15-Round_cost*C15+1*Q15 -> 620 | Z15: =Y15-Round_cost*D15+1*R15 -> 570 | AA15: =Z15-Round_cost*E15+1*S15 -> 640 | AB15: =AA15-Round_cost*F15+1*T15 -> 710 | AC15: =AB15-Round_cost*G15+1*U15 -> 695 | AD15: =IF(B15=1,Liq_0-Round_cost,1000000000) -> 1000000000 | AE15: =IF(C15=1,X15-Round_cost,1000000000) -> 1000000000 | AF15: =IF(D15=1,Y15-Round_cost,1000000000) -> 500 | AG15: =IF(E15=1,Z15-Round_cost,1000000000) -> 1000000000 | AH15: =IF(F15=1,AA15-Round_cost,1000000000) -> 1000000000 | AI15: =IF(G15=1,AB15-Round_cost,1000000000) -> 590 | AJ15: =IF(AND(MIN(X15:AC15)>=Floor_liq-0.000000001,MIN(AD15:AI15)>=Floor_liq-0.000000001),1,0) -> 1 | AK15: =IF(AC15>=End_liq-0.000000001,1,0) -> 1 | AL15: =AJ15*AK15*W15 -> 1 | AM15: =Liq_0-Round_cost*B15+(1-Pledge_share)*P15 -> 620 | AN15: =AM15-Round_cost*C15+(1-Pledge_share)*Q15 -> 620 | AO15: =AN15-Round_cost*D15+(1-Pledge_share)*R15 -> 535 | AP15: =AO15-Round_cost*E15+(1-Pledge_share)*S15 -> 570 | AQ15: =AP15-Round_cost*F15+(1-Pledge_share)*T15 -> 605 | AR15: =AQ15-Round_cost*G15+(1-Pledge_share)*U15 -> 537.5 | AS15: =IF(B15=1,Liq_0-Round_cost,1000000000) -> 1000000000 | AT15: =IF(C15=1,AM15-Round_cost,1000000000) -> 1000000000 | AU15: =IF(D15=1,AN15-Round_cost,1000000000) -> 500 | AV15: =IF(E15=1,AO15-Round_cost,1000000000) -> 1000000000 | AW15: =IF(F15=1,AP15-Round_cost,1000000000) -> 1000000000 | AX15: =IF(G15=1,AQ15-Round_cost,1000000000) -> 485 | AY15: =IF(AND(MIN(AM15:AR15)>=Floor_liq-0.000000001,MIN(AS15:AX15)>=Floor_liq-0.000000001),1,0) -> 1 | AZ15: =IF(AR15>=End_liq-0.000000001,1,0) -> 1 | BA15: =AY15*AZ15*W15 -> 1 | BB15: =Pledge_share*V15 -> 157.5 | BC15: =IF(BA15=1,H15*10000+BB15,-1) -> 20157.5 | BD15: =U15 -> 105 | BE15: =AC15 -> 695 | BF15: =IF(AL15=1,AC15-End_liq,-1000000000) -> 225 | BG15: =IF(AL15=1,BF15+BG$4*BD15,-1000000000) -> 225 | BH15: =IF(AL15=1,BF15+BH$4*BD15,-1000000000) -> 750 | BI15: =IF(AL15=1,BF15+BI$4*BD15,-1000000000) -> 1275 | BJ15: =IF(AL15=1,BF15+BJ$4*BD15,-1000000000) -> 2325 | BK15: =IF(AL15=1,BF15+BK$4*BD15,-1000000000) -> 4425 | BL15: =IF(AL15=1,BF15+BL$4*BD15,-1000000000) -> 6525 | BM15: =IF(H15=0,1,IF(I15=VALUE(LEFT("123456",H15)),1,0)) -> 0 | BN15: =IF(BG15>0,1000*BG15,-1000000000000) -> 225000 | BO15: =IF(BG15>0,BG15+100,-1000000000) -> 325 | BP15: =IF(BG15>0,LN(BG15),-1000000000) -> 5.4161004
A16: 10 | B16: =MOD(INT($A16/32),2) -> 0 | C16: =MOD(INT($A16/16),2) -> 0 | D16: =MOD(INT($A16/8),2) -> 1 | E16: =MOD(INT($A16/4),2) -> 0 | F16: =MOD(INT($A16/2),2) -> 1 | G16: =MOD(INT($A16/1),2) -> 0 | H16: =SUM(B16:G16) -> 2 | I16: =IF(H16=0,0,VALUE(IF(B16=1,"1","")&IF(C16=1,"2","")&IF(D16=1,"3","")&IF(E16=1,"4","")&IF(F16=1,"5","")&IF(G16=1,"6",""))) -> 35 | J16: =IF(B16=1,Eff_0+Gap_closed*(Eff_ceiling-Eff_0),Eff_0) -> 71 | K16: =IF(C16=1,J16+Gap_closed*(Eff_ceiling-J16),J16) -> 71 | L16: =IF(D16=1,K16+Gap_closed*(Eff_ceiling-K16),K16) -> 78 | M16: =IF(E16=1,L16+Gap_closed*(Eff_ceiling-L16),L16) -> 78 | N16: =IF(F16=1,M16+Gap_closed*(Eff_ceiling-M16),M16) -> 81.5 | O16: =IF(G16=1,N16+Gap_closed*(Eff_ceiling-N16),N16) -> 81.5 | P16: =Sav_point*(J16-Eff_0) -> 0 | Q16: =Sav_point*(K16-Eff_0) -> 0 | R16: =Sav_point*(L16-Eff_0) -> 70 | S16: =Sav_point*(M16-Eff_0) -> 70 | T16: =Sav_point*(N16-Eff_0) -> 105 | U16: =Sav_point*(O16-Eff_0) -> 105 | V16: =SUM(P16:U16) -> 350 | W16: =IF(AND(H16>0,Cap_0<Cap_min),0,1) -> 1 | X16: =Liq_0-Round_cost*B16+1*P16 -> 620 | Y16: =X16-Round_cost*C16+1*Q16 -> 620 | Z16: =Y16-Round_cost*D16+1*R16 -> 570 | AA16: =Z16-Round_cost*E16+1*S16 -> 640 | AB16: =AA16-Round_cost*F16+1*T16 -> 625 | AC16: =AB16-Round_cost*G16+1*U16 -> 730 | AD16: =IF(B16=1,Liq_0-Round_cost,1000000000) -> 1000000000 | AE16: =IF(C16=1,X16-Round_cost,1000000000) -> 1000000000 | AF16: =IF(D16=1,Y16-Round_cost,1000000000) -> 500 | AG16: =IF(E16=1,Z16-Round_cost,1000000000) -> 1000000000 | AH16: =IF(F16=1,AA16-Round_cost,1000000000) -> 520 | AI16: =IF(G16=1,AB16-Round_cost,1000000000) -> 1000000000 | AJ16: =IF(AND(MIN(X16:AC16)>=Floor_liq-0.000000001,MIN(AD16:AI16)>=Floor_liq-0.000000001),1,0) -> 1 | AK16: =IF(AC16>=End_liq-0.000000001,1,0) -> 1 | AL16: =AJ16*AK16*W16 -> 1 | AM16: =Liq_0-Round_cost*B16+(1-Pledge_share)*P16 -> 620 | AN16: =AM16-Round_cost*C16+(1-Pledge_share)*Q16 -> 620 | AO16: =AN16-Round_cost*D16+(1-Pledge_share)*R16 -> 535 | AP16: =AO16-Round_cost*E16+(1-Pledge_share)*S16 -> 570 | AQ16: =AP16-Round_cost*F16+(1-Pledge_share)*T16 -> 502.5 | AR16: =AQ16-Round_cost*G16+(1-Pledge_share)*U16 -> 555 | AS16: =IF(B16=1,Liq_0-Round_cost,1000000000) -> 1000000000 | AT16: =IF(C16=1,AM16-Round_cost,1000000000) -> 1000000000 | AU16: =IF(D16=1,AN16-Round_cost,1000000000) -> 500 | AV16: =IF(E16=1,AO16-Round_cost,1000000000) -> 1000000000 | AW16: =IF(F16=1,AP16-Round_cost,1000000000) -> 450 | AX16: =IF(G16=1,AQ16-Round_cost,1000000000) -> 1000000000 | AY16: =IF(AND(MIN(AM16:AR16)>=Floor_liq-0.000000001,MIN(AS16:AX16)>=Floor_liq-0.000000001),1,0) -> 1 | AZ16: =IF(AR16>=End_liq-0.000000001,1,0) -> 1 | BA16: =AY16*AZ16*W16 -> 1 | BB16: =Pledge_share*V16 -> 175 | BC16: =IF(BA16=1,H16*10000+BB16,-1) -> 20175 | BD16: =U16 -> 105 | BE16: =AC16 -> 730 | BF16: =IF(AL16=1,AC16-End_liq,-1000000000) -> 260 | BG16: =IF(AL16=1,BF16+BG$4*BD16,-1000000000) -> 260 | BH16: =IF(AL16=1,BF16+BH$4*BD16,-1000000000) -> 785 | BI16: =IF(AL16=1,BF16+BI$4*BD16,-1000000000) -> 1310 | BJ16: =IF(AL16=1,BF16+BJ$4*BD16,-1000000000) -> 2360 | BK16: =IF(AL16=1,BF16+BK$4*BD16,-1000000000) -> 4460 | BL16: =IF(AL16=1,BF16+BL$4*BD16,-1000000000) -> 6560 | BM16: =IF(H16=0,1,IF(I16=VALUE(LEFT("123456",H16)),1,0)) -> 0 | BN16: =IF(BG16>0,1000*BG16,-1000000000000) -> 260000 | BO16: =IF(BG16>0,BG16+100,-1000000000) -> 360 | BP16: =IF(BG16>0,LN(BG16),-1000000000) -> 5.5606816
A17: 11 | B17: =MOD(INT($A17/32),2) -> 0 | C17: =MOD(INT($A17/16),2) -> 0 | D17: =MOD(INT($A17/8),2) -> 1 | E17: =MOD(INT($A17/4),2) -> 0 | F17: =MOD(INT($A17/2),2) -> 1 | G17: =MOD(INT($A17/1),2) -> 1 | H17: =SUM(B17:G17) -> 3 | I17: =IF(H17=0,0,VALUE(IF(B17=1,"1","")&IF(C17=1,"2","")&IF(D17=1,"3","")&IF(E17=1,"4","")&IF(F17=1,"5","")&IF(G17=1,"6",""))) -> 356 | J17: =IF(B17=1,Eff_0+Gap_closed*(Eff_ceiling-Eff_0),Eff_0) -> 71 | K17: =IF(C17=1,J17+Gap_closed*(Eff_ceiling-J17),J17) -> 71 | L17: =IF(D17=1,K17+Gap_closed*(Eff_ceiling-K17),K17) -> 78 | M17: =IF(E17=1,L17+Gap_closed*(Eff_ceiling-L17),L17) -> 78 | N17: =IF(F17=1,M17+Gap_closed*(Eff_ceiling-M17),M17) -> 81.5 | O17: =IF(G17=1,N17+Gap_closed*(Eff_ceiling-N17),N17) -> 83.25 | P17: =Sav_point*(J17-Eff_0) -> 0 | Q17: =Sav_point*(K17-Eff_0) -> 0 | R17: =Sav_point*(L17-Eff_0) -> 70 | S17: =Sav_point*(M17-Eff_0) -> 70 | T17: =Sav_point*(N17-Eff_0) -> 105 | U17: =Sav_point*(O17-Eff_0) -> 122.5 | V17: =SUM(P17:U17) -> 367.5 | W17: =IF(AND(H17>0,Cap_0<Cap_min),0,1) -> 1 | X17: =Liq_0-Round_cost*B17+1*P17 -> 620 | Y17: =X17-Round_cost*C17+1*Q17 -> 620 | Z17: =Y17-Round_cost*D17+1*R17 -> 570 | AA17: =Z17-Round_cost*E17+1*S17 -> 640 | AB17: =AA17-Round_cost*F17+1*T17 -> 625 | AC17: =AB17-Round_cost*G17+1*U17 -> 627.5 | AD17: =IF(B17=1,Liq_0-Round_cost,1000000000) -> 1000000000 | AE17: =IF(C17=1,X17-Round_cost,1000000000) -> 1000000000 | AF17: =IF(D17=1,Y17-Round_cost,1000000000) -> 500 | AG17: =IF(E17=1,Z17-Round_cost,1000000000) -> 1000000000 | AH17: =IF(F17=1,AA17-Round_cost,1000000000) -> 520 | AI17: =IF(G17=1,AB17-Round_cost,1000000000) -> 505 | AJ17: =IF(AND(MIN(X17:AC17)>=Floor_liq-0.000000001,MIN(AD17:AI17)>=Floor_liq-0.000000001),1,0) -> 1 | AK17: =IF(AC17>=End_liq-0.000000001,1,0) -> 1 | AL17: =AJ17*AK17*W17 -> 1 | AM17: =Liq_0-Round_cost*B17+(1-Pledge_share)*P17 -> 620 | AN17: =AM17-Round_cost*C17+(1-Pledge_share)*Q17 -> 620 | AO17: =AN17-Round_cost*D17+(1-Pledge_share)*R17 -> 535 | AP17: =AO17-Round_cost*E17+(1-Pledge_share)*S17 -> 570 | AQ17: =AP17-Round_cost*F17+(1-Pledge_share)*T17 -> 502.5 | AR17: =AQ17-Round_cost*G17+(1-Pledge_share)*U17 -> 443.75 | AS17: =IF(B17=1,Liq_0-Round_cost,1000000000) -> 1000000000 | AT17: =IF(C17=1,AM17-Round_cost,1000000000) -> 1000000000 | AU17: =IF(D17=1,AN17-Round_cost,1000000000) -> 500 | AV17: =IF(E17=1,AO17-Round_cost,1000000000) -> 1000000000 | AW17: =IF(F17=1,AP17-Round_cost,1000000000) -> 450 | AX17: =IF(G17=1,AQ17-Round_cost,1000000000) -> 382.5 | AY17: =IF(AND(MIN(AM17:AR17)>=Floor_liq-0.000000001,MIN(AS17:AX17)>=Floor_liq-0.000000001),1,0) -> 1 | AZ17: =IF(AR17>=End_liq-0.000000001,1,0) -> 0 | BA17: =AY17*AZ17*W17 -> 0 | BB17: =Pledge_share*V17 -> 183.75 | BC17: =IF(BA17=1,H17*10000+BB17,-1) -> -1 | BD17: =U17 -> 122.5 | BE17: =AC17 -> 627.5 | BF17: =IF(AL17=1,AC17-End_liq,-1000000000) -> 157.5 | BG17: =IF(AL17=1,BF17+BG$4*BD17,-1000000000) -> 157.5 | BH17: =IF(AL17=1,BF17+BH$4*BD17,-1000000000) -> 770 | BI17: =IF(AL17=1,BF17+BI$4*BD17,-1000000000) -> 1382.5 | BJ17: =IF(AL17=1,BF17+BJ$4*BD17,-1000000000) -> 2607.5 | BK17: =IF(AL17=1,BF17+BK$4*BD17,-1000000000) -> 5057.5 | BL17: =IF(AL17=1,BF17+BL$4*BD17,-1000000000) -> 7507.5 | BM17: =IF(H17=0,1,IF(I17=VALUE(LEFT("123456",H17)),1,0)) -> 0 | BN17: =IF(BG17>0,1000*BG17,-1000000000000) -> 157500 | BO17: =IF(BG17>0,BG17+100,-1000000000) -> 257.5 | BP17: =IF(BG17>0,LN(BG17),-1000000000) -> 5.0594255
... A69: 63 | B69: =MOD(INT($A69/32),2) -> 1 | C69: =MOD(INT($A69/16),2) -> 1 | D69: =MOD(INT($A69/8),2) -> 1 | E69: =MOD(INT($A69/4),2) -> 1 | F69: =MOD(INT($A69/2),2) -> 1 | G69: =MOD(INT($A69/1),2) -> 1 | H69: =SUM(B69:G69) -> 6 | I69: =IF(H69=0,0,VALUE(IF(B69=1,"1","")&IF(C69=1,"2","")&IF(D69=1,"3","")&IF(E69=1,"4","")&IF(F69=1,"5","")&IF(G69=1,"6",""))) -> 123456 | J69: =IF(B69=1,Eff_0+Gap_closed*(Eff_ceiling-Eff_0),Eff_0) -> 78 | K69: =IF(C69=1,J69+Gap_closed*(Eff_ceiling-J69),J69) -> 81.5 | L69: =IF(D69=1,K69+Gap_closed*(Eff_ceiling-K69),K69) -> 83.25 | M69: =IF(E69=1,L69+Gap_closed*(Eff_ceiling-L69),L69) -> 84.125 | N69: =IF(F69=1,M69+Gap_closed*(Eff_ceiling-M69),M69) -> 84.5625 | O69: =IF(G69=1,N69+Gap_closed*(Eff_ceiling-N69),N69) -> 84.78125 | P69: =Sav_point*(J69-Eff_0) -> 70 | Q69: =Sav_point*(K69-Eff_0) -> 105 | R69: =Sav_point*(L69-Eff_0) -> 122.5 | S69: =Sav_point*(M69-Eff_0) -> 131.25 | T69: =Sav_point*(N69-Eff_0) -> 135.625 | U69: =Sav_point*(O69-Eff_0) -> 137.8125 | V69: =SUM(P69:U69) -> 702.1875 | W69: =IF(AND(H69>0,Cap_0<Cap_min),0,1) -> 1 | X69: =Liq_0-Round_cost*B69+1*P69 -> 570 | Y69: =X69-Round_cost*C69+1*Q69 -> 555 | Z69: =Y69-Round_cost*D69+1*R69 -> 557.5 | AA69: =Z69-Round_cost*E69+1*S69 -> 568.75 | AB69: =AA69-Round_cost*F69+1*T69 -> 584.375 | AC69: =AB69-Round_cost*G69+1*U69 -> 602.1875 | AD69: =IF(B69=1,Liq_0-Round_cost,1000000000) -> 500 | AE69: =IF(C69=1,X69-Round_cost,1000000000) -> 450 | AF69: =IF(D69=1,Y69-Round_cost,1000000000) -> 435 | AG69: =IF(E69=1,Z69-Round_cost,1000000000) -> 437.5 | AH69: =IF(F69=1,AA69-Round_cost,1000000000) -> 448.75 | AI69: =IF(G69=1,AB69-Round_cost,1000000000) -> 464.375 | AJ69: =IF(AND(MIN(X69:AC69)>=Floor_liq-0.000000001,MIN(AD69:AI69)>=Floor_liq-0.000000001),1,0) -> 1 | AK69: =IF(AC69>=End_liq-0.000000001,1,0) -> 1 | AL69: =AJ69*AK69*W69 -> 1 | AM69: =Liq_0-Round_cost*B69+(1-Pledge_share)*P69 -> 535 | AN69: =AM69-Round_cost*C69+(1-Pledge_share)*Q69 -> 467.5 | AO69: =AN69-Round_cost*D69+(1-Pledge_share)*R69 -> 408.75 | AP69: =AO69-Round_cost*E69+(1-Pledge_share)*S69 -> 354.375 | AQ69: =AP69-Round_cost*F69+(1-Pledge_share)*T69 -> 302.1875 | AR69: =AQ69-Round_cost*G69+(1-Pledge_share)*U69 -> 251.09375 | AS69: =IF(B69=1,Liq_0-Round_cost,1000000000) -> 500 | AT69: =IF(C69=1,AM69-Round_cost,1000000000) -> 415 | AU69: =IF(D69=1,AN69-Round_cost,1000000000) -> 347.5 | AV69: =IF(E69=1,AO69-Round_cost,1000000000) -> 288.75 | AW69: =IF(F69=1,AP69-Round_cost,1000000000) -> 234.375 | AX69: =IF(G69=1,AQ69-Round_cost,1000000000) -> 182.1875 | AY69: =IF(AND(MIN(AM69:AR69)>=Floor_liq-0.000000001,MIN(AS69:AX69)>=Floor_liq-0.000000001),1,0) -> 0 | AZ69: =IF(AR69>=End_liq-0.000000001,1,0) -> 0 | BA69: =AY69*AZ69*W69 -> 0 | BB69: =Pledge_share*V69 -> 351.09375 | BC69: =IF(BA69=1,H69*10000+BB69,-1) -> -1 | BD69: =U69 -> 137.8125 | BE69: =AC69 -> 602.1875 | BF69: =IF(AL69=1,AC69-End_liq,-1000000000) -> 132.1875 | BG69: =IF(AL69=1,BF69+BG$4*BD69,-1000000000) -> 132.1875 | BH69: =IF(AL69=1,BF69+BH$4*BD69,-1000000000) -> 821.25 | BI69: =IF(AL69=1,BF69+BI$4*BD69,-1000000000) -> 1510.3125 | BJ69: =IF(AL69=1,BF69+BJ$4*BD69,-1000000000) -> 2888.4375 | BK69: =IF(AL69=1,BF69+BK$4*BD69,-1000000000) -> 5644.6875 | BL69: =IF(AL69=1,BF69+BL$4*BD69,-1000000000) -> 8400.9375 | BM69: =IF(H69=0,1,IF(I69=VALUE(LEFT("123456",H69)),1,0)) -> 1 | BN69: =IF(BG69>0,1000*BG69,-1000000000000) -> 132187.5 | BO69: =IF(BG69>0,BG69+100,-1000000000) -> 232.1875 | BP69: =IF(BG69>0,LN(BG69),-1000000000) -> 4.8842214

Sheet DiagnoseClash
A1: Diagnose: the deletion filter, every minimal clash, and the repairs that break them (Theorem 2.3(i)-(ii); Worked Example 2.1, Step 3; AXIOM Lab 2.2, step 3)
A2: A set of commitments is feasible when some schedule keeps all of them, with the least payout they allow. Flags: 1 = in the set. Codes: floor 1, capability 2, six rounds 4, half payout 8, end condition 16.
A4: Deletion filter: the board's conditions first (one feasibility check per commitment)
A5: Step | B5: Commitment tried | C5: Its code | D5: In the set: floor | E5: In the set: capability | F5: In the set: six rounds | G5: In the set: half payout | H5: In the set: end condition | I5: Without it: floor | J5: Without it: capability | K5: Without it: six rounds | L5: Without it: half payout | M5: Without it: end condition | N5: Schedules keeping the rest | O5: The rest can hold? | P5: Verdict | Q5: After: floor | R5: After: capability | S5: After: six rounds | T5: After: half payout | U5: After: end condition
A6: 1 | B6: end condition | C6: =INDEX(Declarations!$B$19:$B$23,MATCH(B6,Declarations!$A$19:$A$23,0)) -> 16 | D6: 1 | E6: 1 | F6: 1 | G6: 1 | H6: 1 | I6: =D6*IF($C6=1,0,1) -> 1 | J6: =E6*IF($C6=2,0,1) -> 1 | K6: =F6*IF($C6=4,0,1) -> 1 | L6: =G6*IF($C6=8,0,1) -> 1 | M6: =H6*IF($C6=16,0,1) -> 0 | N6: =SUMPRODUCT((1-K6+K6*(Sch_rounds=6))*(1-I6*(1-(L6*Sch_floor5+(1-L6)*Sch_floor0)))*(1-J6*(1-Sch_cap))*(1-M6*(1-(L6*Sch_end5+(1-L6)*Sch_end0)))) -> 0 | O6: =IF(N6>0,1,0) -> 0 | P6: =IF(O6=1,"keep it: without it the rest can hold","drop it: the rest still clash") -> drop it: the rest still clash | Q6: =IF(O6=1,D6,I6) -> 1 | R6: =IF(O6=1,E6,J6) -> 1 | S6: =IF(O6=1,F6,K6) -> 1 | T6: =IF(O6=1,G6,L6) -> 1 | U6: =IF(O6=1,H6,M6) -> 0
A7: 2 | B7: floor | C7: =INDEX(Declarations!$B$19:$B$23,MATCH(B7,Declarations!$A$19:$A$23,0)) -> 1 | D7: =Q6 -> 1 | E7: =R6 -> 1 | F7: =S6 -> 1 | G7: =T6 -> 1 | H7: =U6 -> 0 | I7: =D7*IF($C7=1,0,1) -> 0 | J7: =E7*IF($C7=2,0,1) -> 1 | K7: =F7*IF($C7=4,0,1) -> 1 | L7: =G7*IF($C7=8,0,1) -> 1 | M7: =H7*IF($C7=16,0,1) -> 0 | N7: =SUMPRODUCT((1-K7+K7*(Sch_rounds=6))*(1-I7*(1-(L7*Sch_floor5+(1-L7)*Sch_floor0)))*(1-J7*(1-Sch_cap))*(1-M7*(1-(L7*Sch_end5+(1-L7)*Sch_end0)))) -> 1 | O7: =IF(N7>0,1,0) -> 1 | P7: =IF(O7=1,"keep it: without it the rest can hold","drop it: the rest still clash") -> keep it: without it the rest can hold | Q7: =IF(O7=1,D7,I7) -> 1 | R7: =IF(O7=1,E7,J7) -> 1 | S7: =IF(O7=1,F7,K7) -> 1 | T7: =IF(O7=1,G7,L7) -> 1 | U7: =IF(O7=1,H7,M7) -> 0
A8: 3 | B8: capability | C8: =INDEX(Declarations!$B$19:$B$23,MATCH(B8,Declarations!$A$19:$A$23,0)) -> 2 | D8: =Q7 -> 1 | E8: =R7 -> 1 | F8: =S7 -> 1 | G8: =T7 -> 1 | H8: =U7 -> 0 | I8: =D8*IF($C8=1,0,1) -> 1 | J8: =E8*IF($C8=2,0,1) -> 0 | K8: =F8*IF($C8=4,0,1) -> 1 | L8: =G8*IF($C8=8,0,1) -> 1 | M8: =H8*IF($C8=16,0,1) -> 0 | N8: =SUMPRODUCT((1-K8+K8*(Sch_rounds=6))*(1-I8*(1-(L8*Sch_floor5+(1-L8)*Sch_floor0)))*(1-J8*(1-Sch_cap))*(1-M8*(1-(L8*Sch_end5+(1-L8)*Sch_end0)))) -> 0 | O8: =IF(N8>0,1,0) -> 0 | P8: =IF(O8=1,"keep it: without it the rest can hold","drop it: the rest still clash") -> drop it: the rest still clash | Q8: =IF(O8=1,D8,I8) -> 1 | R8: =IF(O8=1,E8,J8) -> 0 | S8: =IF(O8=1,F8,K8) -> 1 | T8: =IF(O8=1,G8,L8) -> 1 | U8: =IF(O8=1,H8,M8) -> 0
A9: 4 | B9: six rounds | C9: =INDEX(Declarations!$B$19:$B$23,MATCH(B9,Declarations!$A$19:$A$23,0)) -> 4 | D9: =Q8 -> 1 | E9: =R8 -> 0 | F9: =S8 -> 1 | G9: =T8 -> 1 | H9: =U8 -> 0 | I9: =D9*IF($C9=1,0,1) -> 1 | J9: =E9*IF($C9=2,0,1) -> 0 | K9: =F9*IF($C9=4,0,1) -> 0 | L9: =G9*IF($C9=8,0,1) -> 1 | M9: =H9*IF($C9=16,0,1) -> 0 | N9: =SUMPRODUCT((1-K9+K9*(Sch_rounds=6))*(1-I9*(1-(L9*Sch_floor5+(1-L9)*Sch_floor0)))*(1-J9*(1-Sch_cap))*(1-M9*(1-(L9*Sch_end5+(1-L9)*Sch_end0)))) -> 43 | O9: =IF(N9>0,1,0) -> 1 | P9: =IF(O9=1,"keep it: without it the rest can hold","drop it: the rest still clash") -> keep it: without it the rest can hold | Q9: =IF(O9=1,D9,I9) -> 1 | R9: =IF(O9=1,E9,J9) -> 0 | S9: =IF(O9=1,F9,K9) -> 1 | T9: =IF(O9=1,G9,L9) -> 1 | U9: =IF(O9=1,H9,M9) -> 0
A10: 5 | B10: half payout | C10: =INDEX(Declarations!$B$19:$B$23,MATCH(B10,Declarations!$A$19:$A$23,0)) -> 8 | D10: =Q9 -> 1 | E10: =R9 -> 0 | F10: =S9 -> 1 | G10: =T9 -> 1 | H10: =U9 -> 0 | I10: =D10*IF($C10=1,0,1) -> 1 | J10: =E10*IF($C10=2,0,1) -> 0 | K10: =F10*IF($C10=4,0,1) -> 1 | L10: =G10*IF($C10=8,0,1) -> 0 | M10: =H10*IF($C10=16,0,1) -> 0 | N10: =SUMPRODUCT((1-K10+K10*(Sch_rounds=6))*(1-I10*(1-(L10*Sch_floor5+(1-L10)*Sch_floor0)))*(1-J10*(1-Sch_cap))*(1-M10*(1-(L10*Sch_end5+(1-L10)*Sch_end0)))) -> 1 | O10: =IF(N10>0,1,0) -> 1 | P10: =IF(O10=1,"keep it: without it the rest can hold","drop it: the rest still clash") -> keep it: without it the rest can hold | Q10: =IF(O10=1,D10,I10) -> 1 | R10: =IF(O10=1,E10,J10) -> 0 | S10: =IF(O10=1,F10,K10) -> 1 | T10: =IF(O10=1,G10,L10) -> 1 | U10: =IF(O10=1,H10,M10) -> 0
A11: The clash it names | D11: =MID(IF(Q10=1,", floor","")&IF(R10=1,", capability","")&IF(S10=1,", six rounds","")&IF(T10=1,", half payout","")&IF(U10=1,", end condition",""),3,200) -> floor, six rounds, half payout | N11: Code | O11: =1*Q10+2*R10+4*S10+8*T10+16*U10 -> 13
A14: Deletion filter: the pledges first (one feasibility check per commitment)
A15: Step | B15: Commitment tried | C15: Its code | D15: In the set: floor | E15: In the set: capability | F15: In the set: six rounds | G15: In the set: half payout | H15: In the set: end condition | I15: Without it: floor | J15: Without it: capability | K15: Without it: six rounds | L15: Without it: half payout | M15: Without it: end condition | N15: Schedules keeping the rest | O15: The rest can hold? | P15: Verdict | Q15: After: floor | R15: After: capability | S15: After: six rounds | T15: After: half payout | U15: After: end condition
A16: 1 | B16: six rounds | C16: =INDEX(Declarations!$B$19:$B$23,MATCH(B16,Declarations!$A$19:$A$23,0)) -> 4 | D16: 1 | E16: 1 | F16: 1 | G16: 1 | H16: 1 | I16: =D16*IF($C16=1,0,1) -> 1 | J16: =E16*IF($C16=2,0,1) -> 1 | K16: =F16*IF($C16=4,0,1) -> 0 | L16: =G16*IF($C16=8,0,1) -> 1 | M16: =H16*IF($C16=16,0,1) -> 1 | N16: =SUMPRODUCT((1-K16+K16*(Sch_rounds=6))*(1-I16*(1-(L16*Sch_floor5+(1-L16)*Sch_floor0)))*(1-J16*(1-Sch_cap))*(1-M16*(1-(L16*Sch_end5+(1-L16)*Sch_end0)))) -> 35 | O16: =IF(N16>0,1,0) -> 1 | P16: =IF(O16=1,"keep it: without it the rest can hold","drop it: the rest still clash") -> keep it: without it the rest can hold | Q16: =IF(O16=1,D16,I16) -> 1 | R16: =IF(O16=1,E16,J16) -> 1 | S16: =IF(O16=1,F16,K16) -> 1 | T16: =IF(O16=1,G16,L16) -> 1 | U16: =IF(O16=1,H16,M16) -> 1
A17: 2 | B17: half payout | C17: =INDEX(Declarations!$B$19:$B$23,MATCH(B17,Declarations!$A$19:$A$23,0)) -> 8 | D17: =Q16 -> 1 | E17: =R16 -> 1 | F17: =S16 -> 1 | G17: =T16 -> 1 | H17: =U16 -> 1 | I17: =D17*IF($C17=1,0,1) -> 1 | J17: =E17*IF($C17=2,0,1) -> 1 | K17: =F17*IF($C17=4,0,1) -> 1 | L17: =G17*IF($C17=8,0,1) -> 0 | M17: =H17*IF($C17=16,0,1) -> 1 | N17: =SUMPRODUCT((1-K17+K17*(Sch_rounds=6))*(1-I17*(1-(L17*Sch_floor5+(1-L17)*Sch_floor0)))*(1-J17*(1-Sch_cap))*(1-M17*(1-(L17*Sch_end5+(1-L17)*Sch_end0)))) -> 1 | O17: =IF(N17>0,1,0) -> 1 | P17: =IF(O17=1,"keep it: without it the rest can hold","drop it: the rest still clash") -> keep it: without it the rest can hold | Q17: =IF(O17=1,D17,I17) -> 1 | R17: =IF(O17=1,E17,J17) -> 1 | S17: =IF(O17=1,F17,K17) -> 1 | T17: =IF(O17=1,G17,L17) -> 1 | U17: =IF(O17=1,H17,M17) -> 1
A18: 3 | B18: capability | C18: =INDEX(Declarations!$B$19:$B$23,MATCH(B18,Declarations!$A$19:$A$23,0)) -> 2 | D18: =Q17 -> 1 | E18: =R17 -> 1 | F18: =S17 -> 1 | G18: =T17 -> 1 | H18: =U17 -> 1 | I18: =D18*IF($C18=1,0,1) -> 1 | J18: =E18*IF($C18=2,0,1) -> 0 | K18: =F18*IF($C18=4,0,1) -> 1 | L18: =G18*IF($C18=8,0,1) -> 1 | M18: =H18*IF($C18=16,0,1) -> 1 | N18: =SUMPRODUCT((1-K18+K18*(Sch_rounds=6))*(1-I18*(1-(L18*Sch_floor5+(1-L18)*Sch_floor0)))*(1-J18*(1-Sch_cap))*(1-M18*(1-(L18*Sch_end5+(1-L18)*Sch_end0)))) -> 0 | O18: =IF(N18>0,1,0) -> 0 | P18: =IF(O18=1,"keep it: without it the rest can hold","drop it: the rest still clash") -> drop it: the rest still clash | Q18: =IF(O18=1,D18,I18) -> 1 | R18: =IF(O18=1,E18,J18) -> 0 | S18: =IF(O18=1,F18,K18) -> 1 | T18: =IF(O18=1,G18,L18) -> 1 | U18: =IF(O18=1,H18,M18) -> 1
A19: 4 | B19: floor | C19: =INDEX(Declarations!$B$19:$B$23,MATCH(B19,Declarations!$A$19:$A$23,0)) -> 1 | D19: =Q18 -> 1 | E19: =R18 -> 0 | F19: =S18 -> 1 | G19: =T18 -> 1 | H19: =U18 -> 1 | I19: =D19*IF($C19=1,0,1) -> 0 | J19: =E19*IF($C19=2,0,1) -> 0 | K19: =F19*IF($C19=4,0,1) -> 1 | L19: =G19*IF($C19=8,0,1) -> 1 | M19: =H19*IF($C19=16,0,1) -> 1 | N19: =SUMPRODUCT((1-K19+K19*(Sch_rounds=6))*(1-I19*(1-(L19*Sch_floor5+(1-L19)*Sch_floor0)))*(1-J19*(1-Sch_cap))*(1-M19*(1-(L19*Sch_end5+(1-L19)*Sch_end0)))) -> 0 | O19: =IF(N19>0,1,0) -> 0 | P19: =IF(O19=1,"keep it: without it the rest can hold","drop it: the rest still clash") -> drop it: the rest still clash | Q19: =IF(O19=1,D19,I19) -> 0 | R19: =IF(O19=1,E19,J19) -> 0 | S19: =IF(O19=1,F19,K19) -> 1 | T19: =IF(O19=1,G19,L19) -> 1 | U19: =IF(O19=1,H19,M19) -> 1
A20: 5 | B20: end condition | C20: =INDEX(Declarations!$B$19:$B$23,MATCH(B20,Declarations!$A$19:$A$23,0)) -> 16 | D20: =Q19 -> 0 | E20: =R19 -> 0 | F20: =S19 -> 1 | G20: =T19 -> 1 | H20: =U19 -> 1 | I20: =D20*IF($C20=1,0,1) -> 0 | J20: =E20*IF($C20=2,0,1) -> 0 | K20: =F20*IF($C20=4,0,1) -> 1 | L20: =G20*IF($C20=8,0,1) -> 1 | M20: =H20*IF($C20=16,0,1) -> 0 | N20: =SUMPRODUCT((1-K20+K20*(Sch_rounds=6))*(1-I20*(1-(L20*Sch_floor5+(1-L20)*Sch_floor0)))*(1-J20*(1-Sch_cap))*(1-M20*(1-(L20*Sch_end5+(1-L20)*Sch_end0)))) -> 1 | O20: =IF(N20>0,1,0) -> 1 | P20: =IF(O20=1,"keep it: without it the rest can hold","drop it: the rest still clash") -> keep it: without it the rest can hold | Q20: =IF(O20=1,D20,I20) -> 0 | R20: =IF(O20=1,E20,J20) -> 0 | S20: =IF(O20=1,F20,K20) -> 1 | T20: =IF(O20=1,G20,L20) -> 1 | U20: =IF(O20=1,H20,M20) -> 1
A21: The clash it names | D21: =MID(IF(Q20=1,", floor","")&IF(R20=1,", capability","")&IF(S20=1,", six rounds","")&IF(T20=1,", half payout","")&IF(U20=1,", end condition",""),3,200) -> six rounds, half payout, end condition | N21: Code | O21: =1*Q20+2*R20+4*S20+8*T20+16*U20 -> 28
A24: Every nonempty set of commitments: feasible? minimal infeasible?
A25: Code | B25: Members | C25: floor | D25: capability | E25: six rounds | F25: half payout | G25: end condition | H25: Schedules keeping all | I25: Feasible (1 = yes) | J25: Without floor: feasible | K25: Without capability: feasible | L25: Without six rounds: feasible | M25: Without half payout: feasible | N25: Without end condition: feasible | O25: Minimal infeasible (1 = yes)
A26: 1 | B26: =MID(IF(C26=1,", floor","")&IF(D26=1,", capability","")&IF(E26=1,", six rounds","")&IF(F26=1,", half payout","")&IF(G26=1,", end condition",""),3,200) -> floor | C26: =MOD(INT($A26/1),2) -> 1 | D26: =MOD(INT($A26/2),2) -> 0 | E26: =MOD(INT($A26/4),2) -> 0 | F26: =MOD(INT($A26/8),2) -> 0 | G26: =MOD(INT($A26/16),2) -> 0 | H26: =SUMPRODUCT((1-E26+E26*(Sch_rounds=6))*(1-C26*(1-(F26*Sch_floor5+(1-F26)*Sch_floor0)))*(1-D26*(1-Sch_cap))*(1-G26*(1-(F26*Sch_end5+(1-F26)*Sch_end0)))) -> 64 | I26: =IF(H26>0,1,0) -> 1 | J26: =IF(C26=0,1,IF($A26-1=0,1,INDEX($I$26:$I$56,$A26-1))) -> 1 | K26: =IF(D26=0,1,IF($A26-2=0,1,INDEX($I$26:$I$56,$A26-2))) -> 1 | L26: =IF(E26=0,1,IF($A26-4=0,1,INDEX($I$26:$I$56,$A26-4))) -> 1 | M26: =IF(F26=0,1,IF($A26-8=0,1,INDEX($I$26:$I$56,$A26-8))) -> 1 | N26: =IF(G26=0,1,IF($A26-16=0,1,INDEX($I$26:$I$56,$A26-16))) -> 1 | O26: =IF(AND(I26=0,J26*K26*L26*M26*N26=1),1,0) -> 0
A27: 2 | B27: =MID(IF(C27=1,", floor","")&IF(D27=1,", capability","")&IF(E27=1,", six rounds","")&IF(F27=1,", half payout","")&IF(G27=1,", end condition",""),3,200) -> capability | C27: =MOD(INT($A27/1),2) -> 0 | D27: =MOD(INT($A27/2),2) -> 1 | E27: =MOD(INT($A27/4),2) -> 0 | F27: =MOD(INT($A27/8),2) -> 0 | G27: =MOD(INT($A27/16),2) -> 0 | H27: =SUMPRODUCT((1-E27+E27*(Sch_rounds=6))*(1-C27*(1-(F27*Sch_floor5+(1-F27)*Sch_floor0)))*(1-D27*(1-Sch_cap))*(1-G27*(1-(F27*Sch_end5+(1-F27)*Sch_end0)))) -> 64 | I27: =IF(H27>0,1,0) -> 1 | J27: =IF(C27=0,1,IF($A27-1=0,1,INDEX($I$26:$I$56,$A27-1))) -> 1 | K27: =IF(D27=0,1,IF($A27-2=0,1,INDEX($I$26:$I$56,$A27-2))) -> 1 | L27: =IF(E27=0,1,IF($A27-4=0,1,INDEX($I$26:$I$56,$A27-4))) -> 1 | M27: =IF(F27=0,1,IF($A27-8=0,1,INDEX($I$26:$I$56,$A27-8))) -> 1 | N27: =IF(G27=0,1,IF($A27-16=0,1,INDEX($I$26:$I$56,$A27-16))) -> 1 | O27: =IF(AND(I27=0,J27*K27*L27*M27*N27=1),1,0) -> 0
A28: 3 | B28: =MID(IF(C28=1,", floor","")&IF(D28=1,", capability","")&IF(E28=1,", six rounds","")&IF(F28=1,", half payout","")&IF(G28=1,", end condition",""),3,200) -> floor, capability | C28: =MOD(INT($A28/1),2) -> 1 | D28: =MOD(INT($A28/2),2) -> 1 | E28: =MOD(INT($A28/4),2) -> 0 | F28: =MOD(INT($A28/8),2) -> 0 | G28: =MOD(INT($A28/16),2) -> 0 | H28: =SUMPRODUCT((1-E28+E28*(Sch_rounds=6))*(1-C28*(1-(F28*Sch_floor5+(1-F28)*Sch_floor0)))*(1-D28*(1-Sch_cap))*(1-G28*(1-(F28*Sch_end5+(1-F28)*Sch_end0)))) -> 64 | I28: =IF(H28>0,1,0) -> 1 | J28: =IF(C28=0,1,IF($A28-1=0,1,INDEX($I$26:$I$56,$A28-1))) -> 1 | K28: =IF(D28=0,1,IF($A28-2=0,1,INDEX($I$26:$I$56,$A28-2))) -> 1 | L28: =IF(E28=0,1,IF($A28-4=0,1,INDEX($I$26:$I$56,$A28-4))) -> 1 | M28: =IF(F28=0,1,IF($A28-8=0,1,INDEX($I$26:$I$56,$A28-8))) -> 1 | N28: =IF(G28=0,1,IF($A28-16=0,1,INDEX($I$26:$I$56,$A28-16))) -> 1 | O28: =IF(AND(I28=0,J28*K28*L28*M28*N28=1),1,0) -> 0
A29: 4 | B29: =MID(IF(C29=1,", floor","")&IF(D29=1,", capability","")&IF(E29=1,", six rounds","")&IF(F29=1,", half payout","")&IF(G29=1,", end condition",""),3,200) -> six rounds | C29: =MOD(INT($A29/1),2) -> 0 | D29: =MOD(INT($A29/2),2) -> 0 | E29: =MOD(INT($A29/4),2) -> 1 | F29: =MOD(INT($A29/8),2) -> 0 | G29: =MOD(INT($A29/16),2) -> 0 | H29: =SUMPRODUCT((1-E29+E29*(Sch_rounds=6))*(1-C29*(1-(F29*Sch_floor5+(1-F29)*Sch_floor0)))*(1-D29*(1-Sch_cap))*(1-G29*(1-(F29*Sch_end5+(1-F29)*Sch_end0)))) -> 1 | I29: =IF(H29>0,1,0) -> 1 | J29: =IF(C29=0,1,IF($A29-1=0,1,INDEX($I$26:$I$56,$A29-1))) -> 1 | K29: =IF(D29=0,1,IF($A29-2=0,1,INDEX($I$26:$I$56,$A29-2))) -> 1 | L29: =IF(E29=0,1,IF($A29-4=0,1,INDEX($I$26:$I$56,$A29-4))) -> 1 | M29: =IF(F29=0,1,IF($A29-8=0,1,INDEX($I$26:$I$56,$A29-8))) -> 1 | N29: =IF(G29=0,1,IF($A29-16=0,1,INDEX($I$26:$I$56,$A29-16))) -> 1 | O29: =IF(AND(I29=0,J29*K29*L29*M29*N29=1),1,0) -> 0
A30: 5 | B30: =MID(IF(C30=1,", floor","")&IF(D30=1,", capability","")&IF(E30=1,", six rounds","")&IF(F30=1,", half payout","")&IF(G30=1,", end condition",""),3,200) -> floor, six rounds | C30: =MOD(INT($A30/1),2) -> 1 | D30: =MOD(INT($A30/2),2) -> 0 | E30: =MOD(INT($A30/4),2) -> 1 | F30: =MOD(INT($A30/8),2) -> 0 | G30: =MOD(INT($A30/16),2) -> 0 | H30: =SUMPRODUCT((1-E30+E30*(Sch_rounds=6))*(1-C30*(1-(F30*Sch_floor5+(1-F30)*Sch_floor0)))*(1-D30*(1-Sch_cap))*(1-G30*(1-(F30*Sch_end5+(1-F30)*Sch_end0)))) -> 1 | I30: =IF(H30>0,1,0) -> 1 | J30: =IF(C30=0,1,IF($A30-1=0,1,INDEX($I$26:$I$56,$A30-1))) -> 1 | K30: =IF(D30=0,1,IF($A30-2=0,1,INDEX($I$26:$I$56,$A30-2))) -> 1 | L30: =IF(E30=0,1,IF($A30-4=0,1,INDEX($I$26:$I$56,$A30-4))) -> 1 | M30: =IF(F30=0,1,IF($A30-8=0,1,INDEX($I$26:$I$56,$A30-8))) -> 1 | N30: =IF(G30=0,1,IF($A30-16=0,1,INDEX($I$26:$I$56,$A30-16))) -> 1 | O30: =IF(AND(I30=0,J30*K30*L30*M30*N30=1),1,0) -> 0
A31: 6 | B31: =MID(IF(C31=1,", floor","")&IF(D31=1,", capability","")&IF(E31=1,", six rounds","")&IF(F31=1,", half payout","")&IF(G31=1,", end condition",""),3,200) -> capability, six rounds | C31: =MOD(INT($A31/1),2) -> 0 | D31: =MOD(INT($A31/2),2) -> 1 | E31: =MOD(INT($A31/4),2) -> 1 | F31: =MOD(INT($A31/8),2) -> 0 | G31: =MOD(INT($A31/16),2) -> 0 | H31: =SUMPRODUCT((1-E31+E31*(Sch_rounds=6))*(1-C31*(1-(F31*Sch_floor5+(1-F31)*Sch_floor0)))*(1-D31*(1-Sch_cap))*(1-G31*(1-(F31*Sch_end5+(1-F31)*Sch_end0)))) -> 1 | I31: =IF(H31>0,1,0) -> 1 | J31: =IF(C31=0,1,IF($A31-1=0,1,INDEX($I$26:$I$56,$A31-1))) -> 1 | K31: =IF(D31=0,1,IF($A31-2=0,1,INDEX($I$26:$I$56,$A31-2))) -> 1 | L31: =IF(E31=0,1,IF($A31-4=0,1,INDEX($I$26:$I$56,$A31-4))) -> 1 | M31: =IF(F31=0,1,IF($A31-8=0,1,INDEX($I$26:$I$56,$A31-8))) -> 1 | N31: =IF(G31=0,1,IF($A31-16=0,1,INDEX($I$26:$I$56,$A31-16))) -> 1 | O31: =IF(AND(I31=0,J31*K31*L31*M31*N31=1),1,0) -> 0
A32: 7 | B32: =MID(IF(C32=1,", floor","")&IF(D32=1,", capability","")&IF(E32=1,", six rounds","")&IF(F32=1,", half payout","")&IF(G32=1,", end condition",""),3,200) -> floor, capability, six rounds | C32: =MOD(INT($A32/1),2) -> 1 | D32: =MOD(INT($A32/2),2) -> 1 | E32: =MOD(INT($A32/4),2) -> 1 | F32: =MOD(INT($A32/8),2) -> 0 | G32: =MOD(INT($A32/16),2) -> 0 | H32: =SUMPRODUCT((1-E32+E32*(Sch_rounds=6))*(1-C32*(1-(F32*Sch_floor5+(1-F32)*Sch_floor0)))*(1-D32*(1-Sch_cap))*(1-G32*(1-(F32*Sch_end5+(1-F32)*Sch_end0)))) -> 1 | I32: =IF(H32>0,1,0) -> 1 | J32: =IF(C32=0,1,IF($A32-1=0,1,INDEX($I$26:$I$56,$A32-1))) -> 1 | K32: =IF(D32=0,1,IF($A32-2=0,1,INDEX($I$26:$I$56,$A32-2))) -> 1 | L32: =IF(E32=0,1,IF($A32-4=0,1,INDEX($I$26:$I$56,$A32-4))) -> 1 | M32: =IF(F32=0,1,IF($A32-8=0,1,INDEX($I$26:$I$56,$A32-8))) -> 1 | N32: =IF(G32=0,1,IF($A32-16=0,1,INDEX($I$26:$I$56,$A32-16))) -> 1 | O32: =IF(AND(I32=0,J32*K32*L32*M32*N32=1),1,0) -> 0
A33: 8 | B33: =MID(IF(C33=1,", floor","")&IF(D33=1,", capability","")&IF(E33=1,", six rounds","")&IF(F33=1,", half payout","")&IF(G33=1,", end condition",""),3,200) -> half payout | C33: =MOD(INT($A33/1),2) -> 0 | D33: =MOD(INT($A33/2),2) -> 0 | E33: =MOD(INT($A33/4),2) -> 0 | F33: =MOD(INT($A33/8),2) -> 1 | G33: =MOD(INT($A33/16),2) -> 0 | H33: =SUMPRODUCT((1-E33+E33*(Sch_rounds=6))*(1-C33*(1-(F33*Sch_floor5+(1-F33)*Sch_floor0)))*(1-D33*(1-Sch_cap))*(1-G33*(1-(F33*Sch_end5+(1-F33)*Sch_end0)))) -> 64 | I33: =IF(H33>0,1,0) -> 1 | J33: =IF(C33=0,1,IF($A33-1=0,1,INDEX($I$26:$I$56,$A33-1))) -> 1 | K33: =IF(D33=0,1,IF($A33-2=0,1,INDEX($I$26:$I$56,$A33-2))) -> 1 | L33: =IF(E33=0,1,IF($A33-4=0,1,INDEX($I$26:$I$56,$A33-4))) -> 1 | M33: =IF(F33=0,1,IF($A33-8=0,1,INDEX($I$26:$I$56,$A33-8))) -> 1 | N33: =IF(G33=0,1,IF($A33-16=0,1,INDEX($I$26:$I$56,$A33-16))) -> 1 | O33: =IF(AND(I33=0,J33*K33*L33*M33*N33=1),1,0) -> 0
A34: 9 | B34: =MID(IF(C34=1,", floor","")&IF(D34=1,", capability","")&IF(E34=1,", six rounds","")&IF(F34=1,", half payout","")&IF(G34=1,", end condition",""),3,200) -> floor, half payout | C34: =MOD(INT($A34/1),2) -> 1 | D34: =MOD(INT($A34/2),2) -> 0 | E34: =MOD(INT($A34/4),2) -> 0 | F34: =MOD(INT($A34/8),2) -> 1 | G34: =MOD(INT($A34/16),2) -> 0 | H34: =SUMPRODUCT((1-E34+E34*(Sch_rounds=6))*(1-C34*(1-(F34*Sch_floor5+(1-F34)*Sch_floor0)))*(1-D34*(1-Sch_cap))*(1-G34*(1-(F34*Sch_end5+(1-F34)*Sch_end0)))) -> 43 | I34: =IF(H34>0,1,0) -> 1 | J34: =IF(C34=0,1,IF($A34-1=0,1,INDEX($I$26:$I$56,$A34-1))) -> 1 | K34: =IF(D34=0,1,IF($A34-2=0,1,INDEX($I$26:$I$56,$A34-2))) -> 1 | L34: =IF(E34=0,1,IF($A34-4=0,1,INDEX($I$26:$I$56,$A34-4))) -> 1 | M34: =IF(F34=0,1,IF($A34-8=0,1,INDEX($I$26:$I$56,$A34-8))) -> 1 | N34: =IF(G34=0,1,IF($A34-16=0,1,INDEX($I$26:$I$56,$A34-16))) -> 1 | O34: =IF(AND(I34=0,J34*K34*L34*M34*N34=1),1,0) -> 0
A35: 10 | B35: =MID(IF(C35=1,", floor","")&IF(D35=1,", capability","")&IF(E35=1,", six rounds","")&IF(F35=1,", half payout","")&IF(G35=1,", end condition",""),3,200) -> capability, half payout | C35: =MOD(INT($A35/1),2) -> 0 | D35: =MOD(INT($A35/2),2) -> 1 | E35: =MOD(INT($A35/4),2) -> 0 | F35: =MOD(INT($A35/8),2) -> 1 | G35: =MOD(INT($A35/16),2) -> 0 | H35: =SUMPRODUCT((1-E35+E35*(Sch_rounds=6))*(1-C35*(1-(F35*Sch_floor5+(1-F35)*Sch_floor0)))*(1-D35*(1-Sch_cap))*(1-G35*(1-(F35*Sch_end5+(1-F35)*Sch_end0)))) -> 64 | I35: =IF(H35>0,1,0) -> 1 | J35: =IF(C35=0,1,IF($A35-1=0,1,INDEX($I$26:$I$56,$A35-1))) -> 1 | K35: =IF(D35=0,1,IF($A35-2=0,1,INDEX($I$26:$I$56,$A35-2))) -> 1 | L35: =IF(E35=0,1,IF($A35-4=0,1,INDEX($I$26:$I$56,$A35-4))) -> 1 | M35: =IF(F35=0,1,IF($A35-8=0,1,INDEX($I$26:$I$56,$A35-8))) -> 1 | N35: =IF(G35=0,1,IF($A35-16=0,1,INDEX($I$26:$I$56,$A35-16))) -> 1 | O35: =IF(AND(I35=0,J35*K35*L35*M35*N35=1),1,0) -> 0
A36: 11 | B36: =MID(IF(C36=1,", floor","")&IF(D36=1,", capability","")&IF(E36=1,", six rounds","")&IF(F36=1,", half payout","")&IF(G36=1,", end condition",""),3,200) -> floor, capability, half payout | C36: =MOD(INT($A36/1),2) -> 1 | D36: =MOD(INT($A36/2),2) -> 1 | E36: =MOD(INT($A36/4),2) -> 0 | F36: =MOD(INT($A36/8),2) -> 1 | G36: =MOD(INT($A36/16),2) -> 0 | H36: =SUMPRODUCT((1-E36+E36*(Sch_rounds=6))*(1-C36*(1-(F36*Sch_floor5+(1-F36)*Sch_floor0)))*(1-D36*(1-Sch_cap))*(1-G36*(1-(F36*Sch_end5+(1-F36)*Sch_end0)))) -> 43 | I36: =IF(H36>0,1,0) -> 1 | J36: =IF(C36=0,1,IF($A36-1=0,1,INDEX($I$26:$I$56,$A36-1))) -> 1 | K36: =IF(D36=0,1,IF($A36-2=0,1,INDEX($I$26:$I$56,$A36-2))) -> 1 | L36: =IF(E36=0,1,IF($A36-4=0,1,INDEX($I$26:$I$56,$A36-4))) -> 1 | M36: =IF(F36=0,1,IF($A36-8=0,1,INDEX($I$26:$I$56,$A36-8))) -> 1 | N36: =IF(G36=0,1,IF($A36-16=0,1,INDEX($I$26:$I$56,$A36-16))) -> 1 | O36: =IF(AND(I36=0,J36*K36*L36*M36*N36=1),1,0) -> 0
A37: 12 | B37: =MID(IF(C37=1,", floor","")&IF(D37=1,", capability","")&IF(E37=1,", six rounds","")&IF(F37=1,", half payout","")&IF(G37=1,", end condition",""),3,200) -> six rounds, half payout | C37: =MOD(INT($A37/1),2) -> 0 | D37: =MOD(INT($A37/2),2) -> 0 | E37: =MOD(INT($A37/4),2) -> 1 | F37: =MOD(INT($A37/8),2) -> 1 | G37: =MOD(INT($A37/16),2) -> 0 | H37: =SUMPRODUCT((1-E37+E37*(Sch_rounds=6))*(1-C37*(1-(F37*Sch_floor5+(1-F37)*Sch_floor0)))*(1-D37*(1-Sch_cap))*(1-G37*(1-(F37*Sch_end5+(1-F37)*Sch_end0)))) -> 1 | I37: =IF(H37>0,1,0) -> 1 | J37: =IF(C37=0,1,IF($A37-1=0,1,INDEX($I$26:$I$56,$A37-1))) -> 1 | K37: =IF(D37=0,1,IF($A37-2=0,1,INDEX($I$26:$I$56,$A37-2))) -> 1 | L37: =IF(E37=0,1,IF($A37-4=0,1,INDEX($I$26:$I$56,$A37-4))) -> 1 | M37: =IF(F37=0,1,IF($A37-8=0,1,INDEX($I$26:$I$56,$A37-8))) -> 1 | N37: =IF(G37=0,1,IF($A37-16=0,1,INDEX($I$26:$I$56,$A37-16))) -> 1 | O37: =IF(AND(I37=0,J37*K37*L37*M37*N37=1),1,0) -> 0
... A56: 31 | B56: =MID(IF(C56=1,", floor","")&IF(D56=1,", capability","")&IF(E56=1,", six rounds","")&IF(F56=1,", half payout","")&IF(G56=1,", end condition",""),3,200) -> floor, capability, six rounds, half payout, end condition | C56: =MOD(INT($A56/1),2) -> 1 | D56: =MOD(INT($A56/2),2) -> 1 | E56: =MOD(INT($A56/4),2) -> 1 | F56: =MOD(INT($A56/8),2) -> 1 | G56: =MOD(INT($A56/16),2) -> 1 | H56: =SUMPRODUCT((1-E56+E56*(Sch_rounds=6))*(1-C56*(1-(F56*Sch_floor5+(1-F56)*Sch_floor0)))*(1-D56*(1-Sch_cap))*(1-G56*(1-(F56*Sch_end5+(1-F56)*Sch_end0)))) -> 0 | I56: =IF(H56>0,1,0) -> 0 | J56: =IF(C56=0,1,IF($A56-1=0,1,INDEX($I$26:$I$56,$A56-1))) -> 0 | K56: =IF(D56=0,1,IF($A56-2=0,1,INDEX($I$26:$I$56,$A56-2))) -> 0 | L56: =IF(E56=0,1,IF($A56-4=0,1,INDEX($I$26:$I$56,$A56-4))) -> 1 | M56: =IF(F56=0,1,IF($A56-8=0,1,INDEX($I$26:$I$56,$A56-8))) -> 1 | N56: =IF(G56=0,1,IF($A56-16=0,1,INDEX($I$26:$I$56,$A56-16))) -> 0 | O56: =IF(AND(I56=0,J56*K56*L56*M56*N56=1),1,0) -> 0
A58: Minimal infeasible sets | I58: =SUM(O26:O56) -> 2
A59: The first, by code | B59: =INDEX(B26:B56,I59) -> floor, six rounds, half payout | I59: =_xlfn.MINIFS(A26:A56,O26:O56,1) -> 13 | J59: =MOD(INT($I59/1),2) -> 1 | K59: =MOD(INT($I59/2),2) -> 0 | L59: =MOD(INT($I59/4),2) -> 1 | M59: =MOD(INT($I59/8),2) -> 1 | N59: =MOD(INT($I59/16),2) -> 0
A60: The second, by code | B60: =INDEX(B26:B56,I60) -> six rounds, half payout, end condition | I60: =_xlfn.MAXIFS(A26:A56,O26:O56,1) -> 28 | J60: =MOD(INT($I60/1),2) -> 0 | K60: =MOD(INT($I60/2),2) -> 0 | L60: =MOD(INT($I60/4),2) -> 1 | M60: =MOD(INT($I60/8),2) -> 1 | N60: =MOD(INT($I60/16),2) -> 1
A62: Theorem 2.3(ii): drop a group of commitments; the rest can hold exactly when the group meets every minimal clash
A63: Code dropped | B63: Dropped | C63: floor | D63: capability | E63: six rounds | F63: half payout | G63: end condition | H63: The rest can hold (1 = yes) | I63: Meets clash 1 | J63: Meets clash 2 | K63: Meets both | L63: Agrees (1 = yes) | M63: Without dropping floor: holds | N63: Without dropping capability: holds | O63: Without dropping six rounds: holds | P63: Without dropping half payout: holds | Q63: Without dropping end condition: holds | R63: Smallest repair (1 = yes)
A64: 0 | B64: =IF(A64=0,"nothing",MID(IF(C64=1,", floor","")&IF(D64=1,", capability","")&IF(E64=1,", six rounds","")&IF(F64=1,", half payout","")&IF(G64=1,", end condition",""),3,200)) -> nothing | C64: =MOD(INT($A64/1),2) -> 0 | D64: =MOD(INT($A64/2),2) -> 0 | E64: =MOD(INT($A64/4),2) -> 0 | F64: =MOD(INT($A64/8),2) -> 0 | G64: =MOD(INT($A64/16),2) -> 0 | H64: =IF(31-A64=0,1,INDEX($I$26:$I$56,31-A64)) -> 0 | I64: =IF(SUMPRODUCT(C64:G64,$J$59:$N$59)>0,1,0) -> 0 | J64: =IF(SUMPRODUCT(C64:G64,$J$60:$N$60)>0,1,0) -> 0 | K64: =I64*J64 -> 0 | L64: =IF(H64=K64,1,0) -> 1 | M64: =IF(C64=0,0,INDEX($H$64:$H$95,$A64-1+1)) -> 0 | N64: =IF(D64=0,0,INDEX($H$64:$H$95,$A64-2+1)) -> 0 | O64: =IF(E64=0,0,INDEX($H$64:$H$95,$A64-4+1)) -> 0 | P64: =IF(F64=0,0,INDEX($H$64:$H$95,$A64-8+1)) -> 0 | Q64: =IF(G64=0,0,INDEX($H$64:$H$95,$A64-16+1)) -> 0 | R64: =IF(AND(H64=1,SUM(M64:Q64)=0),1,0) -> 0
A65: 1 | B65: =IF(A65=0,"nothing",MID(IF(C65=1,", floor","")&IF(D65=1,", capability","")&IF(E65=1,", six rounds","")&IF(F65=1,", half payout","")&IF(G65=1,", end condition",""),3,200)) -> floor | C65: =MOD(INT($A65/1),2) -> 1 | D65: =MOD(INT($A65/2),2) -> 0 | E65: =MOD(INT($A65/4),2) -> 0 | F65: =MOD(INT($A65/8),2) -> 0 | G65: =MOD(INT($A65/16),2) -> 0 | H65: =IF(31-A65=0,1,INDEX($I$26:$I$56,31-A65)) -> 0 | I65: =IF(SUMPRODUCT(C65:G65,$J$59:$N$59)>0,1,0) -> 1 | J65: =IF(SUMPRODUCT(C65:G65,$J$60:$N$60)>0,1,0) -> 0 | K65: =I65*J65 -> 0 | L65: =IF(H65=K65,1,0) -> 1 | M65: =IF(C65=0,0,INDEX($H$64:$H$95,$A65-1+1)) -> 0 | N65: =IF(D65=0,0,INDEX($H$64:$H$95,$A65-2+1)) -> 0 | O65: =IF(E65=0,0,INDEX($H$64:$H$95,$A65-4+1)) -> 0 | P65: =IF(F65=0,0,INDEX($H$64:$H$95,$A65-8+1)) -> 0 | Q65: =IF(G65=0,0,INDEX($H$64:$H$95,$A65-16+1)) -> 0 | R65: =IF(AND(H65=1,SUM(M65:Q65)=0),1,0) -> 0
A66: 2 | B66: =IF(A66=0,"nothing",MID(IF(C66=1,", floor","")&IF(D66=1,", capability","")&IF(E66=1,", six rounds","")&IF(F66=1,", half payout","")&IF(G66=1,", end condition",""),3,200)) -> capability | C66: =MOD(INT($A66/1),2) -> 0 | D66: =MOD(INT($A66/2),2) -> 1 | E66: =MOD(INT($A66/4),2) -> 0 | F66: =MOD(INT($A66/8),2) -> 0 | G66: =MOD(INT($A66/16),2) -> 0 | H66: =IF(31-A66=0,1,INDEX($I$26:$I$56,31-A66)) -> 0 | I66: =IF(SUMPRODUCT(C66:G66,$J$59:$N$59)>0,1,0) -> 0 | J66: =IF(SUMPRODUCT(C66:G66,$J$60:$N$60)>0,1,0) -> 0 | K66: =I66*J66 -> 0 | L66: =IF(H66=K66,1,0) -> 1 | M66: =IF(C66=0,0,INDEX($H$64:$H$95,$A66-1+1)) -> 0 | N66: =IF(D66=0,0,INDEX($H$64:$H$95,$A66-2+1)) -> 0 | O66: =IF(E66=0,0,INDEX($H$64:$H$95,$A66-4+1)) -> 0 | P66: =IF(F66=0,0,INDEX($H$64:$H$95,$A66-8+1)) -> 0 | Q66: =IF(G66=0,0,INDEX($H$64:$H$95,$A66-16+1)) -> 0 | R66: =IF(AND(H66=1,SUM(M66:Q66)=0),1,0) -> 0
A67: 3 | B67: =IF(A67=0,"nothing",MID(IF(C67=1,", floor","")&IF(D67=1,", capability","")&IF(E67=1,", six rounds","")&IF(F67=1,", half payout","")&IF(G67=1,", end condition",""),3,200)) -> floor, capability | C67: =MOD(INT($A67/1),2) -> 1 | D67: =MOD(INT($A67/2),2) -> 1 | E67: =MOD(INT($A67/4),2) -> 0 | F67: =MOD(INT($A67/8),2) -> 0 | G67: =MOD(INT($A67/16),2) -> 0 | H67: =IF(31-A67=0,1,INDEX($I$26:$I$56,31-A67)) -> 0 | I67: =IF(SUMPRODUCT(C67:G67,$J$59:$N$59)>0,1,0) -> 1 | J67: =IF(SUMPRODUCT(C67:G67,$J$60:$N$60)>0,1,0) -> 0 | K67: =I67*J67 -> 0 | L67: =IF(H67=K67,1,0) -> 1 | M67: =IF(C67=0,0,INDEX($H$64:$H$95,$A67-1+1)) -> 0 | N67: =IF(D67=0,0,INDEX($H$64:$H$95,$A67-2+1)) -> 0 | O67: =IF(E67=0,0,INDEX($H$64:$H$95,$A67-4+1)) -> 0 | P67: =IF(F67=0,0,INDEX($H$64:$H$95,$A67-8+1)) -> 0 | Q67: =IF(G67=0,0,INDEX($H$64:$H$95,$A67-16+1)) -> 0 | R67: =IF(AND(H67=1,SUM(M67:Q67)=0),1,0) -> 0
A68: 4 | B68: =IF(A68=0,"nothing",MID(IF(C68=1,", floor","")&IF(D68=1,", capability","")&IF(E68=1,", six rounds","")&IF(F68=1,", half payout","")&IF(G68=1,", end condition",""),3,200)) -> six rounds | C68: =MOD(INT($A68/1),2) -> 0 | D68: =MOD(INT($A68/2),2) -> 0 | E68: =MOD(INT($A68/4),2) -> 1 | F68: =MOD(INT($A68/8),2) -> 0 | G68: =MOD(INT($A68/16),2) -> 0 | H68: =IF(31-A68=0,1,INDEX($I$26:$I$56,31-A68)) -> 1 | I68: =IF(SUMPRODUCT(C68:G68,$J$59:$N$59)>0,1,0) -> 1 | J68: =IF(SUMPRODUCT(C68:G68,$J$60:$N$60)>0,1,0) -> 1 | K68: =I68*J68 -> 1 | L68: =IF(H68=K68,1,0) -> 1 | M68: =IF(C68=0,0,INDEX($H$64:$H$95,$A68-1+1)) -> 0 | N68: =IF(D68=0,0,INDEX($H$64:$H$95,$A68-2+1)) -> 0 | O68: =IF(E68=0,0,INDEX($H$64:$H$95,$A68-4+1)) -> 0 | P68: =IF(F68=0,0,INDEX($H$64:$H$95,$A68-8+1)) -> 0 | Q68: =IF(G68=0,0,INDEX($H$64:$H$95,$A68-16+1)) -> 0 | R68: =IF(AND(H68=1,SUM(M68:Q68)=0),1,0) -> 1
A69: 5 | B69: =IF(A69=0,"nothing",MID(IF(C69=1,", floor","")&IF(D69=1,", capability","")&IF(E69=1,", six rounds","")&IF(F69=1,", half payout","")&IF(G69=1,", end condition",""),3,200)) -> floor, six rounds | C69: =MOD(INT($A69/1),2) -> 1 | D69: =MOD(INT($A69/2),2) -> 0 | E69: =MOD(INT($A69/4),2) -> 1 | F69: =MOD(INT($A69/8),2) -> 0 | G69: =MOD(INT($A69/16),2) -> 0 | H69: =IF(31-A69=0,1,INDEX($I$26:$I$56,31-A69)) -> 1 | I69: =IF(SUMPRODUCT(C69:G69,$J$59:$N$59)>0,1,0) -> 1 | J69: =IF(SUMPRODUCT(C69:G69,$J$60:$N$60)>0,1,0) -> 1 | K69: =I69*J69 -> 1 | L69: =IF(H69=K69,1,0) -> 1 | M69: =IF(C69=0,0,INDEX($H$64:$H$95,$A69-1+1)) -> 1 | N69: =IF(D69=0,0,INDEX($H$64:$H$95,$A69-2+1)) -> 0 | O69: =IF(E69=0,0,INDEX($H$64:$H$95,$A69-4+1)) -> 0 | P69: =IF(F69=0,0,INDEX($H$64:$H$95,$A69-8+1)) -> 0 | Q69: =IF(G69=0,0,INDEX($H$64:$H$95,$A69-16+1)) -> 0 | R69: =IF(AND(H69=1,SUM(M69:Q69)=0),1,0) -> 0
A70: 6 | B70: =IF(A70=0,"nothing",MID(IF(C70=1,", floor","")&IF(D70=1,", capability","")&IF(E70=1,", six rounds","")&IF(F70=1,", half payout","")&IF(G70=1,", end condition",""),3,200)) -> capability, six rounds | C70: =MOD(INT($A70/1),2) -> 0 | D70: =MOD(INT($A70/2),2) -> 1 | E70: =MOD(INT($A70/4),2) -> 1 | F70: =MOD(INT($A70/8),2) -> 0 | G70: =MOD(INT($A70/16),2) -> 0 | H70: =IF(31-A70=0,1,INDEX($I$26:$I$56,31-A70)) -> 1 | I70: =IF(SUMPRODUCT(C70:G70,$J$59:$N$59)>0,1,0) -> 1 | J70: =IF(SUMPRODUCT(C70:G70,$J$60:$N$60)>0,1,0) -> 1 | K70: =I70*J70 -> 1 | L70: =IF(H70=K70,1,0) -> 1 | M70: =IF(C70=0,0,INDEX($H$64:$H$95,$A70-1+1)) -> 0 | N70: =IF(D70=0,0,INDEX($H$64:$H$95,$A70-2+1)) -> 1 | O70: =IF(E70=0,0,INDEX($H$64:$H$95,$A70-4+1)) -> 0 | P70: =IF(F70=0,0,INDEX($H$64:$H$95,$A70-8+1)) -> 0 | Q70: =IF(G70=0,0,INDEX($H$64:$H$95,$A70-16+1)) -> 0 | R70: =IF(AND(H70=1,SUM(M70:Q70)=0),1,0) -> 0
A71: 7 | B71: =IF(A71=0,"nothing",MID(IF(C71=1,", floor","")&IF(D71=1,", capability","")&IF(E71=1,", six rounds","")&IF(F71=1,", half payout","")&IF(G71=1,", end condition",""),3,200)) -> floor, capability, six rounds | C71: =MOD(INT($A71/1),2) -> 1 | D71: =MOD(INT($A71/2),2) -> 1 | E71: =MOD(INT($A71/4),2) -> 1 | F71: =MOD(INT($A71/8),2) -> 0 | G71: =MOD(INT($A71/16),2) -> 0 | H71: =IF(31-A71=0,1,INDEX($I$26:$I$56,31-A71)) -> 1 | I71: =IF(SUMPRODUCT(C71:G71,$J$59:$N$59)>0,1,0) -> 1 | J71: =IF(SUMPRODUCT(C71:G71,$J$60:$N$60)>0,1,0) -> 1 | K71: =I71*J71 -> 1 | L71: =IF(H71=K71,1,0) -> 1 | M71: =IF(C71=0,0,INDEX($H$64:$H$95,$A71-1+1)) -> 1 | N71: =IF(D71=0,0,INDEX($H$64:$H$95,$A71-2+1)) -> 1 | O71: =IF(E71=0,0,INDEX($H$64:$H$95,$A71-4+1)) -> 0 | P71: =IF(F71=0,0,INDEX($H$64:$H$95,$A71-8+1)) -> 0 | Q71: =IF(G71=0,0,INDEX($H$64:$H$95,$A71-16+1)) -> 0 | R71: =IF(AND(H71=1,SUM(M71:Q71)=0),1,0) -> 0
A72: 8 | B72: =IF(A72=0,"nothing",MID(IF(C72=1,", floor","")&IF(D72=1,", capability","")&IF(E72=1,", six rounds","")&IF(F72=1,", half payout","")&IF(G72=1,", end condition",""),3,200)) -> half payout | C72: =MOD(INT($A72/1),2) -> 0 | D72: =MOD(INT($A72/2),2) -> 0 | E72: =MOD(INT($A72/4),2) -> 0 | F72: =MOD(INT($A72/8),2) -> 1 | G72: =MOD(INT($A72/16),2) -> 0 | H72: =IF(31-A72=0,1,INDEX($I$26:$I$56,31-A72)) -> 1 | I72: =IF(SUMPRODUCT(C72:G72,$J$59:$N$59)>0,1,0) -> 1 | J72: =IF(SUMPRODUCT(C72:G72,$J$60:$N$60)>0,1,0) -> 1 | K72: =I72*J72 -> 1 | L72: =IF(H72=K72,1,0) -> 1 | M72: =IF(C72=0,0,INDEX($H$64:$H$95,$A72-1+1)) -> 0 | N72: =IF(D72=0,0,INDEX($H$64:$H$95,$A72-2+1)) -> 0 | O72: =IF(E72=0,0,INDEX($H$64:$H$95,$A72-4+1)) -> 0 | P72: =IF(F72=0,0,INDEX($H$64:$H$95,$A72-8+1)) -> 0 | Q72: =IF(G72=0,0,INDEX($H$64:$H$95,$A72-16+1)) -> 0 | R72: =IF(AND(H72=1,SUM(M72:Q72)=0),1,0) -> 1
A73: 9 | B73: =IF(A73=0,"nothing",MID(IF(C73=1,", floor","")&IF(D73=1,", capability","")&IF(E73=1,", six rounds","")&IF(F73=1,", half payout","")&IF(G73=1,", end condition",""),3,200)) -> floor, half payout | C73: =MOD(INT($A73/1),2) -> 1 | D73: =MOD(INT($A73/2),2) -> 0 | E73: =MOD(INT($A73/4),2) -> 0 | F73: =MOD(INT($A73/8),2) -> 1 | G73: =MOD(INT($A73/16),2) -> 0 | H73: =IF(31-A73=0,1,INDEX($I$26:$I$56,31-A73)) -> 1 | I73: =IF(SUMPRODUCT(C73:G73,$J$59:$N$59)>0,1,0) -> 1 | J73: =IF(SUMPRODUCT(C73:G73,$J$60:$N$60)>0,1,0) -> 1 | K73: =I73*J73 -> 1 | L73: =IF(H73=K73,1,0) -> 1 | M73: =IF(C73=0,0,INDEX($H$64:$H$95,$A73-1+1)) -> 1 | N73: =IF(D73=0,0,INDEX($H$64:$H$95,$A73-2+1)) -> 0 | O73: =IF(E73=0,0,INDEX($H$64:$H$95,$A73-4+1)) -> 0 | P73: =IF(F73=0,0,INDEX($H$64:$H$95,$A73-8+1)) -> 0 | Q73: =IF(G73=0,0,INDEX($H$64:$H$95,$A73-16+1)) -> 0 | R73: =IF(AND(H73=1,SUM(M73:Q73)=0),1,0) -> 0
A74: 10 | B74: =IF(A74=0,"nothing",MID(IF(C74=1,", floor","")&IF(D74=1,", capability","")&IF(E74=1,", six rounds","")&IF(F74=1,", half payout","")&IF(G74=1,", end condition",""),3,200)) -> capability, half payout | C74: =MOD(INT($A74/1),2) -> 0 | D74: =MOD(INT($A74/2),2) -> 1 | E74: =MOD(INT($A74/4),2) -> 0 | F74: =MOD(INT($A74/8),2) -> 1 | G74: =MOD(INT($A74/16),2) -> 0 | H74: =IF(31-A74=0,1,INDEX($I$26:$I$56,31-A74)) -> 1 | I74: =IF(SUMPRODUCT(C74:G74,$J$59:$N$59)>0,1,0) -> 1 | J74: =IF(SUMPRODUCT(C74:G74,$J$60:$N$60)>0,1,0) -> 1 | K74: =I74*J74 -> 1 | L74: =IF(H74=K74,1,0) -> 1 | M74: =IF(C74=0,0,INDEX($H$64:$H$95,$A74-1+1)) -> 0 | N74: =IF(D74=0,0,INDEX($H$64:$H$95,$A74-2+1)) -> 1 | O74: =IF(E74=0,0,INDEX($H$64:$H$95,$A74-4+1)) -> 0 | P74: =IF(F74=0,0,INDEX($H$64:$H$95,$A74-8+1)) -> 0 | Q74: =IF(G74=0,0,INDEX($H$64:$H$95,$A74-16+1)) -> 0 | R74: =IF(AND(H74=1,SUM(M74:Q74)=0),1,0) -> 0
A75: 11 | B75: =IF(A75=0,"nothing",MID(IF(C75=1,", floor","")&IF(D75=1,", capability","")&IF(E75=1,", six rounds","")&IF(F75=1,", half payout","")&IF(G75=1,", end condition",""),3,200)) -> floor, capability, half payout | C75: =MOD(INT($A75/1),2) -> 1 | D75: =MOD(INT($A75/2),2) -> 1 | E75: =MOD(INT($A75/4),2) -> 0 | F75: =MOD(INT($A75/8),2) -> 1 | G75: =MOD(INT($A75/16),2) -> 0 | H75: =IF(31-A75=0,1,INDEX($I$26:$I$56,31-A75)) -> 1 | I75: =IF(SUMPRODUCT(C75:G75,$J$59:$N$59)>0,1,0) -> 1 | J75: =IF(SUMPRODUCT(C75:G75,$J$60:$N$60)>0,1,0) -> 1 | K75: =I75*J75 -> 1 | L75: =IF(H75=K75,1,0) -> 1 | M75: =IF(C75=0,0,INDEX($H$64:$H$95,$A75-1+1)) -> 1 | N75: =IF(D75=0,0,INDEX($H$64:$H$95,$A75-2+1)) -> 1 | O75: =IF(E75=0,0,INDEX($H$64:$H$95,$A75-4+1)) -> 0 | P75: =IF(F75=0,0,INDEX($H$64:$H$95,$A75-8+1)) -> 0 | Q75: =IF(G75=0,0,INDEX($H$64:$H$95,$A75-16+1)) -> 0 | R75: =IF(AND(H75=1,SUM(M75:Q75)=0),1,0) -> 0
... A95: 31 | B95: =IF(A95=0,"nothing",MID(IF(C95=1,", floor","")&IF(D95=1,", capability","")&IF(E95=1,", six rounds","")&IF(F95=1,", half payout","")&IF(G95=1,", end condition",""),3,200)) -> floor, capability, six rounds, half payout, end condition | C95: =MOD(INT($A95/1),2) -> 1 | D95: =MOD(INT($A95/2),2) -> 1 | E95: =MOD(INT($A95/4),2) -> 1 | F95: =MOD(INT($A95/8),2) -> 1 | G95: =MOD(INT($A95/16),2) -> 1 | H95: =IF(31-A95=0,1,INDEX($I$26:$I$56,31-A95)) -> 1 | I95: =IF(SUMPRODUCT(C95:G95,$J$59:$N$59)>0,1,0) -> 1 | J95: =IF(SUMPRODUCT(C95:G95,$J$60:$N$60)>0,1,0) -> 1 | K95: =I95*J95 -> 1 | L95: =IF(H95=K95,1,0) -> 1 | M95: =IF(C95=0,0,INDEX($H$64:$H$95,$A95-1+1)) -> 1 | N95: =IF(D95=0,0,INDEX($H$64:$H$95,$A95-2+1)) -> 1 | O95: =IF(E95=0,0,INDEX($H$64:$H$95,$A95-4+1)) -> 1 | P95: =IF(F95=0,0,INDEX($H$64:$H$95,$A95-8+1)) -> 1 | Q95: =IF(G95=0,0,INDEX($H$64:$H$95,$A95-16+1)) -> 1 | R95: =IF(AND(H95=1,SUM(M95:Q95)=0),1,0) -> 0
A97: Groups on which Theorem 2.3(ii) holds | H97: =SUM(L64:L95) -> 32
A98: Smallest repairs | H98: =SUM(R64:R95) -> 3
A99: Drop the floor alone: the rest can hold? (1 = yes) | H99: =H65 -> 0
A100: The three smallest repairs (R = 1): give up the six rounds, give up the half payout, or give up both the floor and the end condition. Dropping the floor alone leaves {six rounds, half payout, end condition}.

Sheet Repairs
A1: Price the repairs: (a) pay out less, (b) fewer rounds, (c) both pledges, and Table 2.7 (Worked Example 2.1, Step 4; Online Appendix 2.B.4; AXIOM Lab 2.2, step 4)
A4: (a) Six rounds with no payout: what each commitment leaves for a constant payout share
A5: Year | B5: Round (1 = yes) | C5: Liquidity at the start | D5: After paying for the round | E5: Capability before the round | F5: Efficiency | G5: Savings | H5: Paid out | I5: Liquidity at year end | J5: Floor kept? | K5: Capability kept? | L5: Savings to date | M5: Cap from the floor at the round start | N5: Cap from the floor at the year end | P5: The largest constant payout share | Q5: Value
A6: 1 | B6: 1 | C6: =Liq_0 -> 620 | D6: =C6-Round_cost*B6 -> 500 | E6: =Cap_0 -> 58 | F6: =IF(B6=1,Eff_0+Gap_closed*(Eff_ceiling-Eff_0),Eff_0) -> 78 | G6: =Sav_point*(F6-Eff_0) -> 70 | H6: =0*G6 -> 0 | I6: =D6+G6-H6 -> 570 | J6: =IF(AND(OR(B6=0,D6>=Floor_liq-0.000000001),I6>=Floor_liq-0.000000001),"yes","no") -> yes | K6: =IF(OR(B6=0,E6>=Cap_min),"yes","no") -> yes | L6: =SUM(G$6:G6) -> 70 | M6: =IF(AND(B6=1,A6>1),(D6-Floor_liq)/L5,"") | N6: =(I6-Floor_liq)/L6 -> 3.1428571 | P6: Cap from the end condition | Q6: =(I11-End_liq)/L11 -> 0.188251
A7: 2 | B7: 1 | C7: =I6 -> 570 | D7: =C7-Round_cost*B7 -> 450 | E7: =E6+Cap_step*B6 -> 59 | F7: =IF(B7=1,F6+Gap_closed*(Eff_ceiling-F6),F6) -> 81.5 | G7: =Sav_point*(F7-Eff_0) -> 105 | H7: =0*G7 -> 0 | I7: =D7+G7-H7 -> 555 | J7: =IF(AND(OR(B7=0,D7>=Floor_liq-0.000000001),I7>=Floor_liq-0.000000001),"yes","no") -> yes | K7: =IF(OR(B7=0,E7>=Cap_min),"yes","no") -> yes | L7: =SUM(G$6:G7) -> 175 | M7: =IF(AND(B7=1,A7>1),(D7-Floor_liq)/L6,"") -> 1.4285714 | N7: =(I7-Floor_liq)/L7 -> 1.1714286 | P7: Tightest cap from the floor at a round start | Q7: =MIN(M6:M11) -> 0.20265781
A8: 3 | B8: 1 | C8: =I7 -> 555 | D8: =C8-Round_cost*B8 -> 435 | E8: =E7+Cap_step*B7 -> 60 | F8: =IF(B8=1,F7+Gap_closed*(Eff_ceiling-F7),F7) -> 83.25 | G8: =Sav_point*(F8-Eff_0) -> 122.5 | H8: =0*G8 -> 0 | I8: =D8+G8-H8 -> 557.5 | J8: =IF(AND(OR(B8=0,D8>=Floor_liq-0.000000001),I8>=Floor_liq-0.000000001),"yes","no") -> yes | K8: =IF(OR(B8=0,E8>=Cap_min),"yes","no") -> yes | L8: =SUM(G$6:G8) -> 297.5 | M8: =IF(AND(B8=1,A8>1),(D8-Floor_liq)/L7,"") -> 0.48571429 | N8: =(I8-Floor_liq)/L8 -> 0.69747899 | P8: Tightest cap from the floor at a year end | Q8: =MIN(N6:N11) -> 0.35914553
A9: 4 | B9: 1 | C9: =I8 -> 557.5 | D9: =C9-Round_cost*B9 -> 437.5 | E9: =E8+Cap_step*B8 -> 61 | F9: =IF(B9=1,F8+Gap_closed*(Eff_ceiling-F8),F8) -> 84.125 | G9: =Sav_point*(F9-Eff_0) -> 131.25 | H9: =0*G9 -> 0 | I9: =D9+G9-H9 -> 568.75 | J9: =IF(AND(OR(B9=0,D9>=Floor_liq-0.000000001),I9>=Floor_liq-0.000000001),"yes","no") -> yes | K9: =IF(OR(B9=0,E9>=Cap_min),"yes","no") -> yes | L9: =SUM(G$6:G9) -> 428.75 | M9: =IF(AND(B9=1,A9>1),(D9-Floor_liq)/L8,"") -> 0.29411765 | N9: =(I9-Floor_liq)/L9 -> 0.51020408 | P9: Largest share the board's conditions allow | Q9: =MIN(Q6:Q8) -> 0.188251
A10: 5 | B10: 1 | C10: =I9 -> 568.75 | D10: =C10-Round_cost*B10 -> 448.75 | E10: =E9+Cap_step*B9 -> 62 | F10: =IF(B10=1,F9+Gap_closed*(Eff_ceiling-F9),F9) -> 84.5625 | G10: =Sav_point*(F10-Eff_0) -> 135.625 | H10: =0*G10 -> 0 | I10: =D10+G10-H10 -> 584.375 | J10: =IF(AND(OR(B10=0,D10>=Floor_liq-0.000000001),I10>=Floor_liq-0.000000001),"yes","no") -> yes | K10: =IF(OR(B10=0,E10>=Cap_min),"yes","no") -> yes | L10: =SUM(G$6:G10) -> 564.375 | M10: =IF(AND(B10=1,A10>1),(D10-Floor_liq)/L9,"") -> 0.2303207 | N10: =(I10-Floor_liq)/L10 -> 0.41528239 | P10: Set by | Q10: =IF(Q9=Q6,"the end condition",IF(Q9=Q7,"the floor at a round start","the floor at a year end")) -> the end condition
A11: 6 | B11: 1 | C11: =I10 -> 584.375 | D11: =C11-Round_cost*B11 -> 464.375 | E11: =E10+Cap_step*B10 -> 63 | F11: =IF(B11=1,F10+Gap_closed*(Eff_ceiling-F10),F10) -> 84.78125 | G11: =Sav_point*(F11-Eff_0) -> 137.8125 | H11: =0*G11 -> 0 | I11: =D11+G11-H11 -> 602.1875 | J11: =IF(AND(OR(B11=0,D11>=Floor_liq-0.000000001),I11>=Floor_liq-0.000000001),"yes","no") -> yes | K11: =IF(OR(B11=0,E11>=Cap_min),"yes","no") -> yes | L11: =SUM(G$6:G11) -> 702.1875 | M11: =IF(AND(B11=1,A11>1),(D11-Floor_liq)/L10,"") -> 0.20265781 | N11: =(I11-Floor_liq)/L11 -> 0.35914553 | P11: The round-6 start alone would allow | Q11: =M11 -> 0.20265781
A14: (a) Six rounds, the largest share paid out
A15: Year | B15: Round (1 = yes) | C15: Liquidity at the start | D15: After paying for the round | E15: Capability before the round | F15: Efficiency | G15: Savings | H15: Paid out | I15: Liquidity at year end | J15: Floor kept? | K15: Capability kept?
A16: 1 | B16: 1 | C16: =Liq_0 -> 620 | D16: =C16-Round_cost*B16 -> 500 | E16: =Cap_0 -> 58 | F16: =IF(B16=1,Eff_0+Gap_closed*(Eff_ceiling-Eff_0),Eff_0) -> 78 | G16: =Sav_point*(F16-Eff_0) -> 70 | H16: =$Q$9*G16 -> 13.17757 | I16: =D16+G16-H16 -> 556.82243 | J16: =IF(AND(OR(B16=0,D16>=Floor_liq-0.000000001),I16>=Floor_liq-0.000000001),"yes","no") -> yes | K16: =IF(OR(B16=0,E16>=Cap_min),"yes","no") -> yes | P16: Paid out over six years | Q16: =SUM(H16:H21) -> 132.1875
A17: 2 | B17: 1 | C17: =I16 -> 556.82243 | D17: =C17-Round_cost*B17 -> 436.82243 | E17: =E16+Cap_step*B16 -> 59 | F17: =IF(B17=1,F16+Gap_closed*(Eff_ceiling-F16),F16) -> 81.5 | G17: =Sav_point*(F17-Eff_0) -> 105 | H17: =$Q$9*G17 -> 19.766355 | I17: =D17+G17-H17 -> 522.05607 | J17: =IF(AND(OR(B17=0,D17>=Floor_liq-0.000000001),I17>=Floor_liq-0.000000001),"yes","no") -> yes | K17: =IF(OR(B17=0,E17>=Cap_min),"yes","no") -> yes | P17: Efficiency in year 6 | Q17: =F21 -> 84.78125
A18: 3 | B18: 1 | C18: =I17 -> 522.05607 | D18: =C18-Round_cost*B18 -> 402.05607 | E18: =E17+Cap_step*B17 -> 60 | F18: =IF(B18=1,F17+Gap_closed*(Eff_ceiling-F17),F17) -> 83.25 | G18: =Sav_point*(F18-Eff_0) -> 122.5 | H18: =$Q$9*G18 -> 23.060748 | I18: =D18+G18-H18 -> 501.49533 | J18: =IF(AND(OR(B18=0,D18>=Floor_liq-0.000000001),I18>=Floor_liq-0.000000001),"yes","no") -> yes | K18: =IF(OR(B18=0,E18>=Cap_min),"yes","no") -> yes | P18: Liquidity at the end of year 6 | Q18: =I21 -> 470
A19: 4 | B19: 1 | C19: =I18 -> 501.49533 | D19: =C19-Round_cost*B19 -> 381.49533 | E19: =E18+Cap_step*B18 -> 61 | F19: =IF(B19=1,F18+Gap_closed*(Eff_ceiling-F18),F18) -> 84.125 | G19: =Sav_point*(F19-Eff_0) -> 131.25 | H19: =$Q$9*G19 -> 24.707944 | I19: =D19+G19-H19 -> 488.03738 | J19: =IF(AND(OR(B19=0,D19>=Floor_liq-0.000000001),I19>=Floor_liq-0.000000001),"yes","no") -> yes | K19: =IF(OR(B19=0,E19>=Cap_min),"yes","no") -> yes | P19: Every year keeps the floor? | Q19: =IF(COUNTIF(J16:J21,"no")=0,"yes","no") -> yes
A20: 5 | B20: 1 | C20: =I19 -> 488.03738 | D20: =C20-Round_cost*B20 -> 368.03738 | E20: =E19+Cap_step*B19 -> 62 | F20: =IF(B20=1,F19+Gap_closed*(Eff_ceiling-F19),F19) -> 84.5625 | G20: =Sav_point*(F20-Eff_0) -> 135.625 | H20: =$Q$9*G20 -> 25.531542 | I20: =D20+G20-H20 -> 478.13084 | J20: =IF(AND(OR(B20=0,D20>=Floor_liq-0.000000001),I20>=Floor_liq-0.000000001),"yes","no") -> yes | K20: =IF(OR(B20=0,E20>=Cap_min),"yes","no") -> yes
A21: 6 | B21: 1 | C21: =I20 -> 478.13084 | D21: =C21-Round_cost*B21 -> 358.13084 | E21: =E20+Cap_step*B20 -> 63 | F21: =IF(B21=1,F20+Gap_closed*(Eff_ceiling-F20),F20) -> 84.78125 | G21: =Sav_point*(F21-Eff_0) -> 137.8125 | H21: =$Q$9*G21 -> 25.943341 | I21: =D21+G21-H21 -> 470 | J21: =IF(AND(OR(B21=0,D21>=Floor_liq-0.000000001),I21>=Floor_liq-0.000000001),"yes","no") -> yes | K21: =IF(OR(B21=0,E21>=Cap_min),"yes","no") -> yes
P23: (b) The half payout kept
A24: (b) Rounds where the half payout allows the most (read from the Schedules sheet) | P24: Schedules that keep the board's conditions | Q24: =SUM(Sch_ok5) -> 35
A25: Year | B25: Round (1 = yes) | C25: Liquidity at the start | D25: After paying for the round | E25: Capability before the round | F25: Efficiency | G25: Savings | H25: Paid out | I25: Liquidity at year end | J25: Floor kept? | K25: Capability kept? | P25: The most rounds among them | Q25: =_xlfn.MAXIFS(Sch_rounds,Sch_ok5,1) -> 3
A26: 1 | B26: =INDEX(Schedules!$B$6:$B$69,$Q$26) -> 1 | C26: =Liq_0 -> 620 | D26: =C26-Round_cost*B26 -> 500 | E26: =Cap_0 -> 58 | F26: =IF(B26=1,Eff_0+Gap_closed*(Eff_ceiling-Eff_0),Eff_0) -> 78 | G26: =Sav_point*(F26-Eff_0) -> 70 | H26: =Pledge_share*G26 -> 35 | I26: =D26+G26-H26 -> 535 | J26: =IF(AND(OR(B26=0,D26>=Floor_liq-0.000000001),I26>=Floor_liq-0.000000001),"yes","no") -> yes | K26: =IF(OR(B26=0,E26>=Cap_min),"yes","no") -> yes | P26: Row of the best (most rounds, then most paid out) | Q26: =MATCH(MAX(Sch_key),Sch_key,0) -> 53
A27: 2 | B27: =INDEX(Schedules!$C$6:$C$69,$Q$26) -> 1 | C27: =I26 -> 535 | D27: =C27-Round_cost*B27 -> 415 | E27: =E26+Cap_step*B26 -> 59 | F27: =IF(B27=1,F26+Gap_closed*(Eff_ceiling-F26),F26) -> 81.5 | G27: =Sav_point*(F27-Eff_0) -> 105 | H27: =Pledge_share*G27 -> 52.5 | I27: =D27+G27-H27 -> 467.5 | J27: =IF(AND(OR(B27=0,D27>=Floor_liq-0.000000001),I27>=Floor_liq-0.000000001),"yes","no") -> yes | K27: =IF(OR(B27=0,E27>=Cap_min),"yes","no") -> yes | P27: Years of its rounds | Q27: =INDEX(Sch_years,Q26) -> 124
A28: 3 | B28: =INDEX(Schedules!$D$6:$D$69,$Q$26) -> 0 | C28: =I27 -> 467.5 | D28: =C28-Round_cost*B28 -> 467.5 | E28: =E27+Cap_step*B27 -> 60 | F28: =IF(B28=1,F27+Gap_closed*(Eff_ceiling-F27),F27) -> 81.5 | G28: =Sav_point*(F28-Eff_0) -> 105 | H28: =Pledge_share*G28 -> 52.5 | I28: =D28+G28-H28 -> 520 | J28: =IF(AND(OR(B28=0,D28>=Floor_liq-0.000000001),I28>=Floor_liq-0.000000001),"yes","no") -> yes | K28: =IF(OR(B28=0,E28>=Cap_min),"yes","no") -> yes | P28: Paid out over six years | Q28: =INDEX(Sch_pay5,Q26) -> 323.75
A29: 4 | B29: =INDEX(Schedules!$E$6:$E$69,$Q$26) -> 1 | C29: =I28 -> 520 | D29: =C29-Round_cost*B29 -> 400 | E29: =E28+Cap_step*B28 -> 60 | F29: =IF(B29=1,F28+Gap_closed*(Eff_ceiling-F28),F28) -> 83.25 | G29: =Sav_point*(F29-Eff_0) -> 122.5 | H29: =Pledge_share*G29 -> 61.25 | I29: =D29+G29-H29 -> 461.25 | J29: =IF(AND(OR(B29=0,D29>=Floor_liq-0.000000001),I29>=Floor_liq-0.000000001),"yes","no") -> yes | K29: =IF(OR(B29=0,E29>=Cap_min),"yes","no") -> yes
A30: 5 | B30: =INDEX(Schedules!$F$6:$F$69,$Q$26) -> 0 | C30: =I29 -> 461.25 | D30: =C30-Round_cost*B30 -> 461.25 | E30: =E29+Cap_step*B29 -> 61 | F30: =IF(B30=1,F29+Gap_closed*(Eff_ceiling-F29),F29) -> 83.25 | G30: =Sav_point*(F30-Eff_0) -> 122.5 | H30: =Pledge_share*G30 -> 61.25 | I30: =D30+G30-H30 -> 522.5 | J30: =IF(AND(OR(B30=0,D30>=Floor_liq-0.000000001),I30>=Floor_liq-0.000000001),"yes","no") -> yes | K30: =IF(OR(B30=0,E30>=Cap_min),"yes","no") -> yes | P30: Efficiency in year 6 | Q30: =F31 -> 83.25
A31: 6 | B31: =INDEX(Schedules!$G$6:$G$69,$Q$26) -> 0 | C31: =I30 -> 522.5 | D31: =C31-Round_cost*B31 -> 522.5 | E31: =E30+Cap_step*B30 -> 61 | F31: =IF(B31=1,F30+Gap_closed*(Eff_ceiling-F30),F30) -> 83.25 | G31: =Sav_point*(F31-Eff_0) -> 122.5 | H31: =Pledge_share*G31 -> 61.25 | I31: =D31+G31-H31 -> 583.75 | J31: =IF(AND(OR(B31=0,D31>=Floor_liq-0.000000001),I31>=Floor_liq-0.000000001),"yes","no") -> yes | K31: =IF(OR(B31=0,E31>=Cap_min),"yes","no") -> yes | P31: Liquidity at the end of year 6 | Q31: =I31 -> 583.75
P32: Paid out (recomputed here) | Q32: =SUM(H26:H31) -> 323.75
A34: (b) with a round added in year 3
A35: Year | B35: Round (1 = yes) | C35: Liquidity at the start | D35: After paying for the round | E35: Capability before the round | F35: Efficiency | G35: Savings | H35: Paid out | I35: Liquidity at year end | J35: Floor kept? | K35: Capability kept?
A36: 1 | B36: =B26 -> 1 | C36: =Liq_0 -> 620 | D36: =C36-Round_cost*B36 -> 500 | E36: =Cap_0 -> 58 | F36: =IF(B36=1,Eff_0+Gap_closed*(Eff_ceiling-Eff_0),Eff_0) -> 78 | G36: =Sav_point*(F36-Eff_0) -> 70 | H36: =Pledge_share*G36 -> 35 | I36: =D36+G36-H36 -> 535 | J36: =IF(AND(OR(B36=0,D36>=Floor_liq-0.000000001),I36>=Floor_liq-0.000000001),"yes","no") -> yes | K36: =IF(OR(B36=0,E36>=Cap_min),"yes","no") -> yes | P36: First year the floor breaks (0 = none) | Q36: =IF(COUNTIF(J36:J41,"no")=0,0,MATCH("no",J36:J41,0)) -> 3
A37: 2 | B37: =B27 -> 1 | C37: =I36 -> 535 | D37: =C37-Round_cost*B37 -> 415 | E37: =E36+Cap_step*B36 -> 59 | F37: =IF(B37=1,F36+Gap_closed*(Eff_ceiling-F36),F36) -> 81.5 | G37: =Sav_point*(F37-Eff_0) -> 105 | H37: =Pledge_share*G37 -> 52.5 | I37: =D37+G37-H37 -> 467.5 | J37: =IF(AND(OR(B37=0,D37>=Floor_liq-0.000000001),I37>=Floor_liq-0.000000001),"yes","no") -> yes | K37: =IF(OR(B37=0,E37>=Cap_min),"yes","no") -> yes | P37: Liquidity after paying for the year-3 round | Q37: =D38 -> 347.5
A38: 3 | B38: =1 -> 1 | C38: =I37 -> 467.5 | D38: =C38-Round_cost*B38 -> 347.5 | E38: =E37+Cap_step*B37 -> 60 | F38: =IF(B38=1,F37+Gap_closed*(Eff_ceiling-F37),F37) -> 83.25 | G38: =Sav_point*(F38-Eff_0) -> 122.5 | H38: =Pledge_share*G38 -> 61.25 | I38: =D38+G38-H38 -> 408.75 | J38: =IF(AND(OR(B38=0,D38>=Floor_liq-0.000000001),I38>=Floor_liq-0.000000001),"yes","no") -> no | K38: =IF(OR(B38=0,E38>=Cap_min),"yes","no") -> yes | P38: Liquidity at the end of year 6 | Q38: =I41 -> 485.625
A39: 4 | B39: =B29 -> 1 | C39: =I38 -> 408.75 | D39: =C39-Round_cost*B39 -> 288.75 | E39: =E38+Cap_step*B38 -> 61 | F39: =IF(B39=1,F38+Gap_closed*(Eff_ceiling-F38),F38) -> 84.125 | G39: =Sav_point*(F39-Eff_0) -> 131.25 | H39: =Pledge_share*G39 -> 65.625 | I39: =D39+G39-H39 -> 354.375 | J39: =IF(AND(OR(B39=0,D39>=Floor_liq-0.000000001),I39>=Floor_liq-0.000000001),"yes","no") -> no | K39: =IF(OR(B39=0,E39>=Cap_min),"yes","no") -> yes | P39: End condition kept? | Q39: =IF(I41>=End_liq-0.000000001,"yes","no") -> yes
A40: 5 | B40: =B30 -> 0 | C40: =I39 -> 354.375 | D40: =C40-Round_cost*B40 -> 354.375 | E40: =E39+Cap_step*B39 -> 62 | F40: =IF(B40=1,F39+Gap_closed*(Eff_ceiling-F39),F39) -> 84.125 | G40: =Sav_point*(F40-Eff_0) -> 131.25 | H40: =Pledge_share*G40 -> 65.625 | I40: =D40+G40-H40 -> 420 | J40: =IF(AND(OR(B40=0,D40>=Floor_liq-0.000000001),I40>=Floor_liq-0.000000001),"yes","no") -> yes | K40: =IF(OR(B40=0,E40>=Cap_min),"yes","no") -> yes
A41: 6 | B41: =B31 -> 0 | C41: =I40 -> 420 | D41: =C41-Round_cost*B41 -> 420 | E41: =E40+Cap_step*B40 -> 62 | F41: =IF(B41=1,F40+Gap_closed*(Eff_ceiling-F40),F40) -> 84.125 | G41: =Sav_point*(F41-Eff_0) -> 131.25 | H41: =Pledge_share*G41 -> 65.625 | I41: =D41+G41-H41 -> 485.625 | J41: =IF(AND(OR(B41=0,D41>=Floor_liq-0.000000001),I41>=Floor_liq-0.000000001),"yes","no") -> yes | K41: =IF(OR(B41=0,E41>=Cap_min),"yes","no") -> yes
A44: (b) with a round added in year 5
A45: Year | B45: Round (1 = yes) | C45: Liquidity at the start | D45: After paying for the round | E45: Capability before the round | F45: Efficiency | G45: Savings | H45: Paid out | I45: Liquidity at year end | J45: Floor kept? | K45: Capability kept?
A46: 1 | B46: =B26 -> 1 | C46: =Liq_0 -> 620 | D46: =C46-Round_cost*B46 -> 500 | E46: =Cap_0 -> 58 | F46: =IF(B46=1,Eff_0+Gap_closed*(Eff_ceiling-Eff_0),Eff_0) -> 78 | G46: =Sav_point*(F46-Eff_0) -> 70 | H46: =Pledge_share*G46 -> 35 | I46: =D46+G46-H46 -> 535 | J46: =IF(AND(OR(B46=0,D46>=Floor_liq-0.000000001),I46>=Floor_liq-0.000000001),"yes","no") -> yes | K46: =IF(OR(B46=0,E46>=Cap_min),"yes","no") -> yes | P46: First year the floor breaks (0 = none) | Q46: =IF(COUNTIF(J46:J51,"no")=0,0,MATCH("no",J46:J51,0)) -> 5
A47: 2 | B47: =B27 -> 1 | C47: =I46 -> 535 | D47: =C47-Round_cost*B47 -> 415 | E47: =E46+Cap_step*B46 -> 59 | F47: =IF(B47=1,F46+Gap_closed*(Eff_ceiling-F46),F46) -> 81.5 | G47: =Sav_point*(F47-Eff_0) -> 105 | H47: =Pledge_share*G47 -> 52.5 | I47: =D47+G47-H47 -> 467.5 | J47: =IF(AND(OR(B47=0,D47>=Floor_liq-0.000000001),I47>=Floor_liq-0.000000001),"yes","no") -> yes | K47: =IF(OR(B47=0,E47>=Cap_min),"yes","no") -> yes | P47: Liquidity after paying for the year-5 round | Q47: =D50 -> 341.25
A48: 3 | B48: =B28 -> 0 | C48: =I47 -> 467.5 | D48: =C48-Round_cost*B48 -> 467.5 | E48: =E47+Cap_step*B47 -> 60 | F48: =IF(B48=1,F47+Gap_closed*(Eff_ceiling-F47),F47) -> 81.5 | G48: =Sav_point*(F48-Eff_0) -> 105 | H48: =Pledge_share*G48 -> 52.5 | I48: =D48+G48-H48 -> 520 | J48: =IF(AND(OR(B48=0,D48>=Floor_liq-0.000000001),I48>=Floor_liq-0.000000001),"yes","no") -> yes | K48: =IF(OR(B48=0,E48>=Cap_min),"yes","no") -> yes | P48: Liquidity at the end of year 6 | Q48: =I51 -> 472.5
A49: 4 | B49: =B29 -> 1 | C49: =I48 -> 520 | D49: =C49-Round_cost*B49 -> 400 | E49: =E48+Cap_step*B48 -> 60 | F49: =IF(B49=1,F48+Gap_closed*(Eff_ceiling-F48),F48) -> 83.25 | G49: =Sav_point*(F49-Eff_0) -> 122.5 | H49: =Pledge_share*G49 -> 61.25 | I49: =D49+G49-H49 -> 461.25 | J49: =IF(AND(OR(B49=0,D49>=Floor_liq-0.000000001),I49>=Floor_liq-0.000000001),"yes","no") -> yes | K49: =IF(OR(B49=0,E49>=Cap_min),"yes","no") -> yes | P49: End condition kept? | Q49: =IF(I51>=End_liq-0.000000001,"yes","no") -> yes
A50: 5 | B50: =1 -> 1 | C50: =I49 -> 461.25 | D50: =C50-Round_cost*B50 -> 341.25 | E50: =E49+Cap_step*B49 -> 61 | F50: =IF(B50=1,F49+Gap_closed*(Eff_ceiling-F49),F49) -> 84.125 | G50: =Sav_point*(F50-Eff_0) -> 131.25 | H50: =Pledge_share*G50 -> 65.625 | I50: =D50+G50-H50 -> 406.875 | J50: =IF(AND(OR(B50=0,D50>=Floor_liq-0.000000001),I50>=Floor_liq-0.000000001),"yes","no") -> no | K50: =IF(OR(B50=0,E50>=Cap_min),"yes","no") -> yes
A51: 6 | B51: =B31 -> 0 | C51: =I50 -> 406.875 | D51: =C51-Round_cost*B51 -> 406.875 | E51: =E50+Cap_step*B50 -> 62 | F51: =IF(B51=1,F50+Gap_closed*(Eff_ceiling-F50),F50) -> 84.125 | G51: =Sav_point*(F51-Eff_0) -> 131.25 | H51: =Pledge_share*G51 -> 65.625 | I51: =D51+G51-H51 -> 472.5 | J51: =IF(AND(OR(B51=0,D51>=Floor_liq-0.000000001),I51>=Floor_liq-0.000000001),"yes","no") -> yes | K51: =IF(OR(B51=0,E51>=Cap_min),"yes","no") -> yes
A54: (b) with a round added in year 6
A55: Year | B55: Round (1 = yes) | C55: Liquidity at the start | D55: After paying for the round | E55: Capability before the round | F55: Efficiency | G55: Savings | H55: Paid out | I55: Liquidity at year end | J55: Floor kept? | K55: Capability kept?
A56: 1 | B56: =B26 -> 1 | C56: =Liq_0 -> 620 | D56: =C56-Round_cost*B56 -> 500 | E56: =Cap_0 -> 58 | F56: =IF(B56=1,Eff_0+Gap_closed*(Eff_ceiling-Eff_0),Eff_0) -> 78 | G56: =Sav_point*(F56-Eff_0) -> 70 | H56: =Pledge_share*G56 -> 35 | I56: =D56+G56-H56 -> 535 | J56: =IF(AND(OR(B56=0,D56>=Floor_liq-0.000000001),I56>=Floor_liq-0.000000001),"yes","no") -> yes | K56: =IF(OR(B56=0,E56>=Cap_min),"yes","no") -> yes | P56: First year the floor breaks (0 = none) | Q56: =IF(COUNTIF(J56:J61,"no")=0,0,MATCH("no",J56:J61,0)) -> 0
A57: 2 | B57: =B27 -> 1 | C57: =I56 -> 535 | D57: =C57-Round_cost*B57 -> 415 | E57: =E56+Cap_step*B56 -> 59 | F57: =IF(B57=1,F56+Gap_closed*(Eff_ceiling-F56),F56) -> 81.5 | G57: =Sav_point*(F57-Eff_0) -> 105 | H57: =Pledge_share*G57 -> 52.5 | I57: =D57+G57-H57 -> 467.5 | J57: =IF(AND(OR(B57=0,D57>=Floor_liq-0.000000001),I57>=Floor_liq-0.000000001),"yes","no") -> yes | K57: =IF(OR(B57=0,E57>=Cap_min),"yes","no") -> yes | P57: Liquidity after paying for the year-6 round | Q57: =D61 -> 402.5
A58: 3 | B58: =B28 -> 0 | C58: =I57 -> 467.5 | D58: =C58-Round_cost*B58 -> 467.5 | E58: =E57+Cap_step*B57 -> 60 | F58: =IF(B58=1,F57+Gap_closed*(Eff_ceiling-F57),F57) -> 81.5 | G58: =Sav_point*(F58-Eff_0) -> 105 | H58: =Pledge_share*G58 -> 52.5 | I58: =D58+G58-H58 -> 520 | J58: =IF(AND(OR(B58=0,D58>=Floor_liq-0.000000001),I58>=Floor_liq-0.000000001),"yes","no") -> yes | K58: =IF(OR(B58=0,E58>=Cap_min),"yes","no") -> yes | P58: Liquidity at the end of year 6 | Q58: =I61 -> 468.125
A59: 4 | B59: =B29 -> 1 | C59: =I58 -> 520 | D59: =C59-Round_cost*B59 -> 400 | E59: =E58+Cap_step*B58 -> 60 | F59: =IF(B59=1,F58+Gap_closed*(Eff_ceiling-F58),F58) -> 83.25 | G59: =Sav_point*(F59-Eff_0) -> 122.5 | H59: =Pledge_share*G59 -> 61.25 | I59: =D59+G59-H59 -> 461.25 | J59: =IF(AND(OR(B59=0,D59>=Floor_liq-0.000000001),I59>=Floor_liq-0.000000001),"yes","no") -> yes | K59: =IF(OR(B59=0,E59>=Cap_min),"yes","no") -> yes | P59: End condition kept? | Q59: =IF(I61>=End_liq-0.000000001,"yes","no") -> no
A60: 5 | B60: =B30 -> 0 | C60: =I59 -> 461.25 | D60: =C60-Round_cost*B60 -> 461.25 | E60: =E59+Cap_step*B59 -> 61 | F60: =IF(B60=1,F59+Gap_closed*(Eff_ceiling-F59),F59) -> 83.25 | G60: =Sav_point*(F60-Eff_0) -> 122.5 | H60: =Pledge_share*G60 -> 61.25 | I60: =D60+G60-H60 -> 522.5 | J60: =IF(AND(OR(B60=0,D60>=Floor_liq-0.000000001),I60>=Floor_liq-0.000000001),"yes","no") -> yes | K60: =IF(OR(B60=0,E60>=Cap_min),"yes","no") -> yes
A61: 6 | B61: =1 -> 1 | C61: =I60 -> 522.5 | D61: =C61-Round_cost*B61 -> 402.5 | E61: =E60+Cap_step*B60 -> 61 | F61: =IF(B61=1,F60+Gap_closed*(Eff_ceiling-F60),F60) -> 84.125 | G61: =Sav_point*(F61-Eff_0) -> 131.25 | H61: =Pledge_share*G61 -> 65.625 | I61: =D61+G61-H61 -> 468.125 | J61: =IF(AND(OR(B61=0,D61>=Floor_liq-0.000000001),I61>=Floor_liq-0.000000001),"yes","no") -> yes | K61: =IF(OR(B61=0,E61>=Cap_min),"yes","no") -> yes
A64: (c) Both pledges kept, the floor and the end condition given up
A65: Year | B65: Round (1 = yes) | C65: Liquidity at the start | D65: After paying for the round | E65: Capability before the round | F65: Efficiency | G65: Savings | H65: Paid out | I65: Liquidity at year end | J65: Floor kept? | K65: Capability kept?
A66: 1 | B66: 1 | C66: =Liq_0 -> 620 | D66: =C66-Round_cost*B66 -> 500 | E66: =Cap_0 -> 58 | F66: =IF(B66=1,Eff_0+Gap_closed*(Eff_ceiling-Eff_0),Eff_0) -> 78 | G66: =Sav_point*(F66-Eff_0) -> 70 | H66: =Pledge_share*G66 -> 35 | I66: =D66+G66-H66 -> 535 | J66: =IF(AND(OR(B66=0,D66>=Floor_liq-0.000000001),I66>=Floor_liq-0.000000001),"yes","no") -> yes | K66: =IF(OR(B66=0,E66>=Cap_min),"yes","no") -> yes | P66: Lowest liquidity after paying for a round | Q66: =MIN(D66:D71) -> 182.1875
A67: 2 | B67: 1 | C67: =I66 -> 535 | D67: =C67-Round_cost*B67 -> 415 | E67: =E66+Cap_step*B66 -> 59 | F67: =IF(B67=1,F66+Gap_closed*(Eff_ceiling-F66),F66) -> 81.5 | G67: =Sav_point*(F67-Eff_0) -> 105 | H67: =Pledge_share*G67 -> 52.5 | I67: =D67+G67-H67 -> 467.5 | J67: =IF(AND(OR(B67=0,D67>=Floor_liq-0.000000001),I67>=Floor_liq-0.000000001),"yes","no") -> yes | K67: =IF(OR(B67=0,E67>=Cap_min),"yes","no") -> yes | P67: Paid out over six years | Q67: =SUM(H66:H71) -> 351.09375
A68: 3 | B68: 1 | C68: =I67 -> 467.5 | D68: =C68-Round_cost*B68 -> 347.5 | E68: =E67+Cap_step*B67 -> 60 | F68: =IF(B68=1,F67+Gap_closed*(Eff_ceiling-F67),F67) -> 83.25 | G68: =Sav_point*(F68-Eff_0) -> 122.5 | H68: =Pledge_share*G68 -> 61.25 | I68: =D68+G68-H68 -> 408.75 | J68: =IF(AND(OR(B68=0,D68>=Floor_liq-0.000000001),I68>=Floor_liq-0.000000001),"yes","no") -> no | K68: =IF(OR(B68=0,E68>=Cap_min),"yes","no") -> yes | P68: Liquidity at the end of year 6 | Q68: =I71 -> 251.09375
A69: 4 | B69: 1 | C69: =I68 -> 408.75 | D69: =C69-Round_cost*B69 -> 288.75 | E69: =E68+Cap_step*B68 -> 61 | F69: =IF(B69=1,F68+Gap_closed*(Eff_ceiling-F68),F68) -> 84.125 | G69: =Sav_point*(F69-Eff_0) -> 131.25 | H69: =Pledge_share*G69 -> 65.625 | I69: =D69+G69-H69 -> 354.375 | J69: =IF(AND(OR(B69=0,D69>=Floor_liq-0.000000001),I69>=Floor_liq-0.000000001),"yes","no") -> no | K69: =IF(OR(B69=0,E69>=Cap_min),"yes","no") -> yes
A70: 5 | B70: 1 | C70: =I69 -> 354.375 | D70: =C70-Round_cost*B70 -> 234.375 | E70: =E69+Cap_step*B69 -> 62 | F70: =IF(B70=1,F69+Gap_closed*(Eff_ceiling-F69),F69) -> 84.5625 | G70: =Sav_point*(F70-Eff_0) -> 135.625 | H70: =Pledge_share*G70 -> 67.8125 | I70: =D70+G70-H70 -> 302.1875 | J70: =IF(AND(OR(B70=0,D70>=Floor_liq-0.000000001),I70>=Floor_liq-0.000000001),"yes","no") -> no | K70: =IF(OR(B70=0,E70>=Cap_min),"yes","no") -> yes
A71: 6 | B71: 1 | C71: =I70 -> 302.1875 | D71: =C71-Round_cost*B71 -> 182.1875 | E71: =E70+Cap_step*B70 -> 63 | F71: =IF(B71=1,F70+Gap_closed*(Eff_ceiling-F70),F70) -> 84.78125 | G71: =Sav_point*(F71-Eff_0) -> 137.8125 | H71: =Pledge_share*G71 -> 68.90625 | I71: =D71+G71-H71 -> 251.09375 | J71: =IF(AND(OR(B71=0,D71>=Floor_liq-0.000000001),I71>=Floor_liq-0.000000001),"yes","no") -> no | K71: =IF(OR(B71=0,E71>=Cap_min),"yes","no") -> yes
A74: Online Appendix 2.B.4, year by year
A75: Row | C75: Year 1 | D75: Year 2 | E75: Year 3 | F75: Year 4 | G75: Year 5 | H75: Year 6
A76: (a) efficiency | C76: =F16 -> 78 | D76: =F17 -> 81.5 | E76: =F18 -> 83.25 | F76: =F19 -> 84.125 | G76: =F20 -> 84.5625 | H76: =F21 -> 84.78125
A77: (a) savings | C77: =G16 -> 70 | D77: =G17 -> 105 | E77: =G18 -> 122.5 | F77: =G19 -> 131.25 | G77: =G20 -> 135.625 | H77: =G21 -> 137.8125
A78: (a) paid out | C78: =H16 -> 13.17757 | D78: =H17 -> 19.766355 | E78: =H18 -> 23.060748 | F78: =H19 -> 24.707944 | G78: =H20 -> 25.531542 | H78: =H21 -> 25.943341
A79: (a) liquidity | C79: =I16 -> 556.82243 | D79: =I17 -> 522.05607 | E79: =I18 -> 501.49533 | F79: =I19 -> 488.03738 | G79: =I20 -> 478.13084 | H79: =I21 -> 470
A80: (b) round (1 = yes) | C80: =B26 -> 1 | D80: =B27 -> 1 | E80: =B28 -> 0 | F80: =B29 -> 1 | G80: =B30 -> 0 | H80: =B31 -> 0
A81: (b) savings | C81: =G26 -> 70 | D81: =G27 -> 105 | E81: =G28 -> 105 | F81: =G29 -> 122.5 | G81: =G30 -> 122.5 | H81: =G31 -> 122.5
A82: (b) liquidity | C82: =I26 -> 535 | D82: =I27 -> 467.5 | E82: =I28 -> 520 | F82: =I29 -> 461.25 | G82: =I30 -> 522.5 | H82: =I31 -> 583.75
A83: (c) liquidity | C83: =I66 -> 535 | D83: =I67 -> 467.5 | E83: =I68 -> 408.75 | F83: =I69 -> 354.375 | G83: =I70 -> 302.1875 | H83: =I71 -> 251.09375
A86: Table 2.7: the joint plan, the three repairs, and the optimizer's plans when both pledges are dropped (six-year totals, undiscounted)
A87: Plan | C87: Rounds | D87: Paid out | E87: Efficiency, year 6 | F87: Liquidity, year 6 | G87: Gives up
A88: joint plan | C88: ="two, then blocked" -> two, then blocked | D88: -- | E88: -- | F88: -- | G88: ="dies in year "&JointPlan!N9 -> dies in year 3
A89: (a) pay out less | C89: ="six" -> six | D89: =Q16 -> 132.1875 | E89: =Q17 -> 84.78125 | F89: =Q18 -> 470 | G89: ="half payout" -> half payout
A90: (b) fewer rounds | C90: ="years "&MID(IF(B26=1,", 1","")&IF(B27=1,", 2","")&IF(B28=1,", 3","")&IF(B29=1,", 4","")&IF(B30=1,", 5","")&IF(B31=1,", 6",""),3,50) -> years 1, 2, 4 | D90: =Q28 -> 323.75 | E90: =Q30 -> 83.25 | F90: =Q31 -> 583.75 | G90: ="six rounds" -> six rounds
A91: (c) both pledges | C91: ="six" -> six | D91: =Q67 -> 351.09375 | E91: =F71 -> 84.78125 | F91: =Q68 -> 251.09375 | G91: ="floor and end" -> floor and end
A92: optimizer, no credit | C92: =IF(Optimizer!I5=1,"years 1–"&Optimizer!G5,Optimizer!D5) -> years 1–2 | D92: =Optimizer!E5 -> 505 | E92: =Optimizer!H5 -> 81.5 | F92: =End_liq -> 470 | G92: ="both pledges" -> both pledges
A93: optimizer, ten years' credit | C93: =IF(Optimizer!I7=1,"years 1–"&Optimizer!G7,Optimizer!D7) -> years 1–3 | D93: =Optimizer!E7 -> 455 | E93: =Optimizer!H7 -> 83.25 | F93: =End_liq -> 470 | G93: ="both pledges" -> both pledges

Sheet Optimizer
A1: Reweight: let the optimizer choose, under a terminal credit (Worked Example 2.1, Step 5; Figure 2.3(b); Theorem 2.1; AXIOM Lab 2.2, step 5)
A2: Both pledges dropped; the floor, capability and the end condition kept. Objective: the six-year payout plus M years of year-6 savings. Each schedule's best payout is its no-payout year-6 liquidity less $470 million.
A4: Credit M (years) | B4: Best value | C4: Its row | D4: Years of the rounds | E4: Best six-year payout | F4: Year-6 savings | G4: Rounds | H4: Efficiency, year 6 | I4: Rounds in years 1 to n?
A5: =Schedules!BG4 -> 0 | B5: =MAX(Sch_v0) -> 505 | C5: =MATCH(B5,Sch_v0,0) -> 49 | D5: =INDEX(Sch_years,C5) -> 12 | E5: =INDEX(Sch_best,C5) -> 505 | F5: =INDEX(Sch_s6,C5) -> 105 | G5: =INDEX(Sch_rounds,C5) -> 2 | H5: =INDEX(Sch_eff6,C5) -> 81.5 | I5: =INDEX(Sch_early,C5) -> 1
A6: =Schedules!BH4 -> 5 | B6: =MAX(Sch_v5) -> 1067.5 | C6: =MATCH(B6,Sch_v5,0) -> 57 | D6: =INDEX(Sch_years,C6) -> 123 | E6: =INDEX(Sch_best,C6) -> 455 | F6: =INDEX(Sch_s6,C6) -> 122.5 | G6: =INDEX(Sch_rounds,C6) -> 3 | H6: =INDEX(Sch_eff6,C6) -> 83.25 | I6: =INDEX(Sch_early,C6) -> 1
A7: =Schedules!BI4 -> 10 | B7: =MAX(Sch_v10) -> 1680 | C7: =MATCH(B7,Sch_v10,0) -> 57 | D7: =INDEX(Sch_years,C7) -> 123 | E7: =INDEX(Sch_best,C7) -> 455 | F7: =INDEX(Sch_s6,C7) -> 122.5 | G7: =INDEX(Sch_rounds,C7) -> 3 | H7: =INDEX(Sch_eff6,C7) -> 83.25 | I7: =INDEX(Sch_early,C7) -> 1
A8: =Schedules!BJ4 -> 20 | B8: =MAX(Sch_v20) -> 2986.25 | C8: =MATCH(B8,Sch_v20,0) -> 61 | D8: =INDEX(Sch_years,C8) -> 1234 | E8: =INDEX(Sch_best,C8) -> 361.25 | F8: =INDEX(Sch_s6,C8) -> 131.25 | G8: =INDEX(Sch_rounds,C8) -> 4 | H8: =INDEX(Sch_eff6,C8) -> 84.125 | I8: =INDEX(Sch_early,C8) -> 1
A9: =Schedules!BK4 -> 40 | B9: =MAX(Sch_v40) -> 5675 | C9: =MATCH(B9,Sch_v40,0) -> 63 | D9: =INDEX(Sch_years,C9) -> 12345 | E9: =INDEX(Sch_best,C9) -> 250 | F9: =INDEX(Sch_s6,C9) -> 135.625 | G9: =INDEX(Sch_rounds,C9) -> 5 | H9: =INDEX(Sch_eff6,C9) -> 84.5625 | I9: =INDEX(Sch_early,C9) -> 1
A10: =Schedules!BL4 -> 60 | B10: =MAX(Sch_v60) -> 8400.9375 | C10: =MATCH(B10,Sch_v60,0) -> 64 | D10: =INDEX(Sch_years,C10) -> 123456 | E10: =INDEX(Sch_best,C10) -> 132.1875 | F10: =INDEX(Sch_s6,C10) -> 137.8125 | G10: =INDEX(Sch_rounds,C10) -> 6 | H10: =INDEX(Sch_eff6,C10) -> 84.78125 | I10: =INDEX(Sch_early,C10) -> 1
A12: Credits at which the best of all 64 schedules runs its rounds in years 1 to n | I12: =SUM(I5:I10) -> 6
A14: Rounds n (years 1 to n) | B14: Its row | C14: Payouts + year-6 liquidity | D14: Year-6 savings | E14: Best six-year payout | F14: Credit for one more round: fall in cash / rise in savings | K14: Rounds | L14: First credit on the 0.5-year grid that buys them
A15: 0 | B15: =64-2^(6-A15)+1 -> 1 | C15: =INDEX(Sch_net,B15) -> 620 | D15: =INDEX(Sch_s6,B15) -> 0 | E15: =C15-End_liq -> 150 | F15: =(C15-C16)/(D16-D15) -> -4.2857143 | K15: 3 | L15: =_xlfn.MINIFS($A$28:$A$148,$I$28:$I$148,K15) -> 3
A16: 1 | B16: =64-2^(6-A16)+1 -> 33 | C16: =INDEX(Sch_net,B16) -> 920 | D16: =INDEX(Sch_s6,B16) -> 70 | E16: =C16-End_liq -> 450 | F16: =(C16-C17)/(D17-D16) -> -1.5714286 | K16: 4 | L16: =_xlfn.MINIFS($A$28:$A$148,$I$28:$I$148,K16) -> 11
A17: 2 | B17: =64-2^(6-A17)+1 -> 49 | C17: =INDEX(Sch_net,B17) -> 975 | D17: =INDEX(Sch_s6,B17) -> 105 | E17: =C17-End_liq -> 505 | F17: =(C17-C18)/(D18-D17) -> 2.8571429 | K17: 5 | L17: =_xlfn.MINIFS($A$28:$A$148,$I$28:$I$148,K17) -> 25.5
A18: 3 | B18: =64-2^(6-A18)+1 -> 57 | C18: =INDEX(Sch_net,B18) -> 925 | D18: =INDEX(Sch_s6,B18) -> 122.5 | E18: =C18-End_liq -> 455 | F18: =(C18-C19)/(D19-D18) -> 10.714286 | K18: 6 | L18: =_xlfn.MINIFS($A$28:$A$148,$I$28:$I$148,K18) -> 54
A19: 4 | B19: =64-2^(6-A19)+1 -> 61 | C19: =INDEX(Sch_net,B19) -> 831.25 | D19: =INDEX(Sch_s6,B19) -> 131.25 | E19: =C19-End_liq -> 361.25 | F19: =(C19-C20)/(D20-D19) -> 25.428571
A20: 5 | B20: =64-2^(6-A20)+1 -> 63 | C20: =INDEX(Sch_net,B20) -> 720 | D20: =INDEX(Sch_s6,B20) -> 135.625 | E20: =C20-End_liq -> 250 | F20: =(C20-C21)/(D21-D20) -> 53.857143
A21: 6 | B21: =64-2^(6-A21)+1 -> 64 | C21: =INDEX(Sch_net,B21) -> 602.1875 | D21: =INDEX(Sch_s6,B21) -> 137.8125 | E21: =C21-End_liq -> 132.1875 | K21: Mayer form (Theorem 2.1(i)) | L21: Credit 0 | M21: Credit 10
K22: Row of the optimizer's schedule | L22: =C5 -> 49 | M22: =C7 -> 57
A23: Rounds 3 to 6 would cost | E23: =4*Round_cost -> 480 | K23: Payout in year 1 | L23: 0 | M23: 0
A24: and return, inside the six years, savings of | E24: =INDEX(Sch_savings,64)-INDEX(Sch_savings,49) -> 107.1875 | K24: Payout in year 2 | L24: 0 | M24: 0
K25: Payout in year 3 | L25: 0 | M25: 0
K26: Payout in year 4 | L26: 0 | M26: 0
A27: Credit M (years) | B27: Value, 0 rounds | C27: Value, 1 rounds | D27: Value, 2 rounds | E27: Value, 3 rounds | F27: Value, 4 rounds | G27: Value, 5 rounds | H27: Value, 6 rounds | I27: Rounds chosen | K27: Payout in year 5 | L27: 0 | M27: 0
A28: 0 | B28: =$E$15+$A28*$D$15 -> 150 | C28: =$E$16+$A28*$D$16 -> 450 | D28: =$E$17+$A28*$D$17 -> 505 | E28: =$E$18+$A28*$D$18 -> 455 | F28: =$E$19+$A28*$D$19 -> 361.25 | G28: =$E$20+$A28*$D$20 -> 250 | H28: =$E$21+$A28*$D$21 -> 132.1875 | I28: =MATCH(MAX(B28:H28),B28:H28,0)-1 -> 2 | K28: Payout in year 6 (everything above $470m) | L28: =E5 -> 505 | M28: =E7 -> 455
A29: =A28+0.5 -> 0.5 | B29: =$E$15+$A29*$D$15 -> 150 | C29: =$E$16+$A29*$D$16 -> 485 | D29: =$E$17+$A29*$D$17 -> 557.5 | E29: =$E$18+$A29*$D$18 -> 516.25 | F29: =$E$19+$A29*$D$19 -> 426.875 | G29: =$E$20+$A29*$D$20 -> 317.8125 | H29: =$E$21+$A29*$D$21 -> 201.09375 | I29: =MATCH(MAX(B29:H29),B29:H29,0)-1 -> 2 | K29: Accumulator a_1 = a_0 + p_1 | L29: =0+L23 -> 0 | M29: =0+M23 -> 0
A30: =A29+0.5 -> 1 | B30: =$E$15+$A30*$D$15 -> 150 | C30: =$E$16+$A30*$D$16 -> 520 | D30: =$E$17+$A30*$D$17 -> 610 | E30: =$E$18+$A30*$D$18 -> 577.5 | F30: =$E$19+$A30*$D$19 -> 492.5 | G30: =$E$20+$A30*$D$20 -> 385.625 | H30: =$E$21+$A30*$D$21 -> 270 | I30: =MATCH(MAX(B30:H30),B30:H30,0)-1 -> 2 | K30: Accumulator a_2 = a_1 + p_2 | L30: =L29+L24 -> 0 | M30: =M29+M24 -> 0
A31: =A30+0.5 -> 1.5 | B31: =$E$15+$A31*$D$15 -> 150 | C31: =$E$16+$A31*$D$16 -> 555 | D31: =$E$17+$A31*$D$17 -> 662.5 | E31: =$E$18+$A31*$D$18 -> 638.75 | F31: =$E$19+$A31*$D$19 -> 558.125 | G31: =$E$20+$A31*$D$20 -> 453.4375 | H31: =$E$21+$A31*$D$21 -> 338.90625 | I31: =MATCH(MAX(B31:H31),B31:H31,0)-1 -> 2 | K31: Accumulator a_3 = a_2 + p_3 | L31: =L30+L25 -> 0 | M31: =M30+M25 -> 0
A32: =A31+0.5 -> 2 | B32: =$E$15+$A32*$D$15 -> 150 | C32: =$E$16+$A32*$D$16 -> 590 | D32: =$E$17+$A32*$D$17 -> 715 | E32: =$E$18+$A32*$D$18 -> 700 | F32: =$E$19+$A32*$D$19 -> 623.75 | G32: =$E$20+$A32*$D$20 -> 521.25 | H32: =$E$21+$A32*$D$21 -> 407.8125 | I32: =MATCH(MAX(B32:H32),B32:H32,0)-1 -> 2 | K32: Accumulator a_4 = a_3 + p_4 | L32: =L31+L26 -> 0 | M32: =M31+M26 -> 0
A33: =A32+0.5 -> 2.5 | B33: =$E$15+$A33*$D$15 -> 150 | C33: =$E$16+$A33*$D$16 -> 625 | D33: =$E$17+$A33*$D$17 -> 767.5 | E33: =$E$18+$A33*$D$18 -> 761.25 | F33: =$E$19+$A33*$D$19 -> 689.375 | G33: =$E$20+$A33*$D$20 -> 589.0625 | H33: =$E$21+$A33*$D$21 -> 476.71875 | I33: =MATCH(MAX(B33:H33),B33:H33,0)-1 -> 2 | K33: Accumulator a_5 = a_4 + p_5 | L33: =L32+L27 -> 0 | M33: =M32+M27 -> 0
A34: =A33+0.5 -> 3 | B34: =$E$15+$A34*$D$15 -> 150 | C34: =$E$16+$A34*$D$16 -> 660 | D34: =$E$17+$A34*$D$17 -> 820 | E34: =$E$18+$A34*$D$18 -> 822.5 | F34: =$E$19+$A34*$D$19 -> 755 | G34: =$E$20+$A34*$D$20 -> 656.875 | H34: =$E$21+$A34*$D$21 -> 545.625 | I34: =MATCH(MAX(B34:H34),B34:H34,0)-1 -> 3 | K34: Accumulator a_6 = a_5 + p_6 | L34: =L33+L28 -> 505 | M34: =M33+M28 -> 455
A35: =A34+0.5 -> 3.5 | B35: =$E$15+$A35*$D$15 -> 150 | C35: =$E$16+$A35*$D$16 -> 695 | D35: =$E$17+$A35*$D$17 -> 872.5 | E35: =$E$18+$A35*$D$18 -> 883.75 | F35: =$E$19+$A35*$D$19 -> 820.625 | G35: =$E$20+$A35*$D$20 -> 724.6875 | H35: =$E$21+$A35*$D$21 -> 614.53125 | I35: =MATCH(MAX(B35:H35),B35:H35,0)-1 -> 3 | K35: Running (Bolza) value: payouts + M x year-6 savings | L35: =SUM(L23:L28)+A5*F5 -> 505 | M35: =SUM(M23:M28)+A7*F7 -> 1680
A36: =A35+0.5 -> 4 | B36: =$E$15+$A36*$D$15 -> 150 | C36: =$E$16+$A36*$D$16 -> 730 | D36: =$E$17+$A36*$D$17 -> 925 | E36: =$E$18+$A36*$D$18 -> 945 | F36: =$E$19+$A36*$D$19 -> 886.25 | G36: =$E$20+$A36*$D$20 -> 792.5 | H36: =$E$21+$A36*$D$21 -> 683.4375 | I36: =MATCH(MAX(B36:H36),B36:H36,0)-1 -> 3 | K36: Mayer value: a_6 + M x year-6 savings | L36: =L34+A5*F5 -> 505 | M36: =M34+A7*F7 -> 1680
A37: =A36+0.5 -> 4.5 | B37: =$E$15+$A37*$D$15 -> 150 | C37: =$E$16+$A37*$D$16 -> 765 | D37: =$E$17+$A37*$D$17 -> 977.5 | E37: =$E$18+$A37*$D$18 -> 1006.25 | F37: =$E$19+$A37*$D$19 -> 951.875 | G37: =$E$20+$A37*$D$20 -> 860.3125 | H37: =$E$21+$A37*$D$21 -> 752.34375 | I37: =MATCH(MAX(B37:H37),B37:H37,0)-1 -> 3 | K37: Difference | L37: =L35-L36 -> 0 | M37: =M35-M36 -> 0
A38: =A37+0.5 -> 5 | B38: =$E$15+$A38*$D$15 -> 150 | C38: =$E$16+$A38*$D$16 -> 800 | D38: =$E$17+$A38*$D$17 -> 1030 | E38: =$E$18+$A38*$D$18 -> 1067.5 | F38: =$E$19+$A38*$D$19 -> 1017.5 | G38: =$E$20+$A38*$D$20 -> 928.125 | H38: =$E$21+$A38*$D$21 -> 821.25 | I38: =MATCH(MAX(B38:H38),B38:H38,0)-1 -> 3 | K38: Year-6 liquidity under these payouts | L38: =INDEX(Schedules!$AC$6:$AC$69,L22)-L34 -> 470 | M38: =INDEX(Schedules!$AC$6:$AC$69,M22)-M34 -> 470
A39: =A38+0.5 -> 5.5 | B39: =$E$15+$A39*$D$15 -> 150 | C39: =$E$16+$A39*$D$16 -> 835 | D39: =$E$17+$A39*$D$17 -> 1082.5 | E39: =$E$18+$A39*$D$18 -> 1128.75 | F39: =$E$19+$A39*$D$19 -> 1083.125 | G39: =$E$20+$A39*$D$20 -> 995.9375 | H39: =$E$21+$A39*$D$21 -> 890.15625 | I39: =MATCH(MAX(B39:H39),B39:H39,0)-1 -> 3
A40: =A39+0.5 -> 6 | B40: =$E$15+$A40*$D$15 -> 150 | C40: =$E$16+$A40*$D$16 -> 870 | D40: =$E$17+$A40*$D$17 -> 1135 | E40: =$E$18+$A40*$D$18 -> 1190 | F40: =$E$19+$A40*$D$19 -> 1148.75 | G40: =$E$20+$A40*$D$20 -> 1063.75 | H40: =$E$21+$A40*$D$21 -> 959.0625 | I40: =MATCH(MAX(B40:H40),B40:H40,0)-1 -> 3 | K40: Theorem 2.1(iii) at a credit of 0: the same objective restated | L40: Best schedule (years)
A41: =A40+0.5 -> 6.5 | B41: =$E$15+$A41*$D$15 -> 150 | C41: =$E$16+$A41*$D$16 -> 905 | D41: =$E$17+$A41*$D$17 -> 1187.5 | E41: =$E$18+$A41*$D$18 -> 1251.25 | F41: =$E$19+$A41*$D$19 -> 1214.375 | G41: =$E$20+$A41*$D$20 -> 1131.5625 | H41: =$E$21+$A41*$D$21 -> 1027.9688 | I41: =MATCH(MAX(B41:H41),B41:H41,0)-1 -> 3 | K41: The six-year payout in $ million | L41: =INDEX(Sch_years,MATCH(MAX(Sch_v0),Sch_v0,0)) -> 12
A42: =A41+0.5 -> 7 | B42: =$E$15+$A42*$D$15 -> 150 | C42: =$E$16+$A42*$D$16 -> 940 | D42: =$E$17+$A42*$D$17 -> 1240 | E42: =$E$18+$A42*$D$18 -> 1312.5 | F42: =$E$19+$A42*$D$19 -> 1280 | G42: =$E$20+$A42*$D$20 -> 1199.375 | H42: =$E$21+$A42*$D$21 -> 1096.875 | I42: =MATCH(MAX(B42:H42),B42:H42,0)-1 -> 3 | K42: In $ thousands | L42: =INDEX(Sch_years,MATCH(MAX(Sch_t1000),Sch_t1000,0)) -> 12
A43: =A42+0.5 -> 7.5 | B43: =$E$15+$A43*$D$15 -> 150 | C43: =$E$16+$A43*$D$16 -> 975 | D43: =$E$17+$A43*$D$17 -> 1292.5 | E43: =$E$18+$A43*$D$18 -> 1373.75 | F43: =$E$19+$A43*$D$19 -> 1345.625 | G43: =$E$20+$A43*$D$20 -> 1267.1875 | H43: =$E$21+$A43*$D$21 -> 1165.7812 | I43: =MATCH(MAX(B43:H43),B43:H43,0)-1 -> 3 | K43: Plus a constant of 100 | L43: =INDEX(Sch_years,MATCH(MAX(Sch_tplus),Sch_tplus,0)) -> 12
A44: =A43+0.5 -> 8 | B44: =$E$15+$A44*$D$15 -> 150 | C44: =$E$16+$A44*$D$16 -> 1010 | D44: =$E$17+$A44*$D$17 -> 1345 | E44: =$E$18+$A44*$D$18 -> 1435 | F44: =$E$19+$A44*$D$19 -> 1411.25 | G44: =$E$20+$A44*$D$20 -> 1335 | H44: =$E$21+$A44*$D$21 -> 1234.6875 | I44: =MATCH(MAX(B44:H44),B44:H44,0)-1 -> 3 | K44: Its logarithm | L44: =INDEX(Sch_years,MATCH(MAX(Sch_tlog),Sch_tlog,0)) -> 12
A45: =A44+0.5 -> 8.5 | B45: =$E$15+$A45*$D$15 -> 150 | C45: =$E$16+$A45*$D$16 -> 1045 | D45: =$E$17+$A45*$D$17 -> 1397.5 | E45: =$E$18+$A45*$D$18 -> 1496.25 | F45: =$E$19+$A45*$D$19 -> 1476.875 | G45: =$E$20+$A45*$D$20 -> 1402.8125 | H45: =$E$21+$A45*$D$21 -> 1303.5938 | I45: =MATCH(MAX(B45:H45),B45:H45,0)-1 -> 3 | K45: Restatements that change the plan | L45: =SUMPRODUCT(--(L41:L44<>L41)) -> 0
A46: =A45+0.5 -> 9 | B46: =$E$15+$A46*$D$15 -> 150 | C46: =$E$16+$A46*$D$16 -> 1080 | D46: =$E$17+$A46*$D$17 -> 1450 | E46: =$E$18+$A46*$D$18 -> 1557.5 | F46: =$E$19+$A46*$D$19 -> 1542.5 | G46: =$E$20+$A46*$D$20 -> 1470.625 | H46: =$E$21+$A46*$D$21 -> 1372.5 | I46: =MATCH(MAX(B46:H46),B46:H46,0)-1 -> 3 | K46: Theorem 2.1(iv): a ten-year credit changes it to | L46: =D7 -> 123
A47: =A46+0.5 -> 9.5 | B47: =$E$15+$A47*$D$15 -> 150 | C47: =$E$16+$A47*$D$16 -> 1115 | D47: =$E$17+$A47*$D$17 -> 1502.5 | E47: =$E$18+$A47*$D$18 -> 1618.75 | F47: =$E$19+$A47*$D$19 -> 1608.125 | G47: =$E$20+$A47*$D$20 -> 1538.4375 | H47: =$E$21+$A47*$D$21 -> 1441.4062 | I47: =MATCH(MAX(B47:H47),B47:H47,0)-1 -> 3
A48: =A47+0.5 -> 10 | B48: =$E$15+$A48*$D$15 -> 150 | C48: =$E$16+$A48*$D$16 -> 1150 | D48: =$E$17+$A48*$D$17 -> 1555 | E48: =$E$18+$A48*$D$18 -> 1680 | F48: =$E$19+$A48*$D$19 -> 1673.75 | G48: =$E$20+$A48*$D$20 -> 1606.25 | H48: =$E$21+$A48*$D$21 -> 1510.3125 | I48: =MATCH(MAX(B48:H48),B48:H48,0)-1 -> 3
A49: =A48+0.5 -> 10.5 | B49: =$E$15+$A49*$D$15 -> 150 | C49: =$E$16+$A49*$D$16 -> 1185 | D49: =$E$17+$A49*$D$17 -> 1607.5 | E49: =$E$18+$A49*$D$18 -> 1741.25 | F49: =$E$19+$A49*$D$19 -> 1739.375 | G49: =$E$20+$A49*$D$20 -> 1674.0625 | H49: =$E$21+$A49*$D$21 -> 1579.2188 | I49: =MATCH(MAX(B49:H49),B49:H49,0)-1 -> 3
A50: =A49+0.5 -> 11 | B50: =$E$15+$A50*$D$15 -> 150 | C50: =$E$16+$A50*$D$16 -> 1220 | D50: =$E$17+$A50*$D$17 -> 1660 | E50: =$E$18+$A50*$D$18 -> 1802.5 | F50: =$E$19+$A50*$D$19 -> 1805 | G50: =$E$20+$A50*$D$20 -> 1741.875 | H50: =$E$21+$A50*$D$21 -> 1648.125 | I50: =MATCH(MAX(B50:H50),B50:H50,0)-1 -> 4
A51: =A50+0.5 -> 11.5 | B51: =$E$15+$A51*$D$15 -> 150 | C51: =$E$16+$A51*$D$16 -> 1255 | D51: =$E$17+$A51*$D$17 -> 1712.5 | E51: =$E$18+$A51*$D$18 -> 1863.75 | F51: =$E$19+$A51*$D$19 -> 1870.625 | G51: =$E$20+$A51*$D$20 -> 1809.6875 | H51: =$E$21+$A51*$D$21 -> 1717.0312 | I51: =MATCH(MAX(B51:H51),B51:H51,0)-1 -> 4
A52: =A51+0.5 -> 12 | B52: =$E$15+$A52*$D$15 -> 150 | C52: =$E$16+$A52*$D$16 -> 1290 | D52: =$E$17+$A52*$D$17 -> 1765 | E52: =$E$18+$A52*$D$18 -> 1925 | F52: =$E$19+$A52*$D$19 -> 1936.25 | G52: =$E$20+$A52*$D$20 -> 1877.5 | H52: =$E$21+$A52*$D$21 -> 1785.9375 | I52: =MATCH(MAX(B52:H52),B52:H52,0)-1 -> 4
A53: =A52+0.5 -> 12.5 | B53: =$E$15+$A53*$D$15 -> 150 | C53: =$E$16+$A53*$D$16 -> 1325 | D53: =$E$17+$A53*$D$17 -> 1817.5 | E53: =$E$18+$A53*$D$18 -> 1986.25 | F53: =$E$19+$A53*$D$19 -> 2001.875 | G53: =$E$20+$A53*$D$20 -> 1945.3125 | H53: =$E$21+$A53*$D$21 -> 1854.8438 | I53: =MATCH(MAX(B53:H53),B53:H53,0)-1 -> 4
A54: =A53+0.5 -> 13 | B54: =$E$15+$A54*$D$15 -> 150 | C54: =$E$16+$A54*$D$16 -> 1360 | D54: =$E$17+$A54*$D$17 -> 1870 | E54: =$E$18+$A54*$D$18 -> 2047.5 | F54: =$E$19+$A54*$D$19 -> 2067.5 | G54: =$E$20+$A54*$D$20 -> 2013.125 | H54: =$E$21+$A54*$D$21 -> 1923.75 | I54: =MATCH(MAX(B54:H54),B54:H54,0)-1 -> 4
A55: =A54+0.5 -> 13.5 | B55: =$E$15+$A55*$D$15 -> 150 | C55: =$E$16+$A55*$D$16 -> 1395 | D55: =$E$17+$A55*$D$17 -> 1922.5 | E55: =$E$18+$A55*$D$18 -> 2108.75 | F55: =$E$19+$A55*$D$19 -> 2133.125 | G55: =$E$20+$A55*$D$20 -> 2080.9375 | H55: =$E$21+$A55*$D$21 -> 1992.6562 | I55: =MATCH(MAX(B55:H55),B55:H55,0)-1 -> 4
A56: =A55+0.5 -> 14 | B56: =$E$15+$A56*$D$15 -> 150 | C56: =$E$16+$A56*$D$16 -> 1430 | D56: =$E$17+$A56*$D$17 -> 1975 | E56: =$E$18+$A56*$D$18 -> 2170 | F56: =$E$19+$A56*$D$19 -> 2198.75 | G56: =$E$20+$A56*$D$20 -> 2148.75 | H56: =$E$21+$A56*$D$21 -> 2061.5625 | I56: =MATCH(MAX(B56:H56),B56:H56,0)-1 -> 4
A57: =A56+0.5 -> 14.5 | B57: =$E$15+$A57*$D$15 -> 150 | C57: =$E$16+$A57*$D$16 -> 1465 | D57: =$E$17+$A57*$D$17 -> 2027.5 | E57: =$E$18+$A57*$D$18 -> 2231.25 | F57: =$E$19+$A57*$D$19 -> 2264.375 | G57: =$E$20+$A57*$D$20 -> 2216.5625 | H57: =$E$21+$A57*$D$21 -> 2130.4688 | I57: =MATCH(MAX(B57:H57),B57:H57,0)-1 -> 4
A58: =A57+0.5 -> 15 | B58: =$E$15+$A58*$D$15 -> 150 | C58: =$E$16+$A58*$D$16 -> 1500 | D58: =$E$17+$A58*$D$17 -> 2080 | E58: =$E$18+$A58*$D$18 -> 2292.5 | F58: =$E$19+$A58*$D$19 -> 2330 | G58: =$E$20+$A58*$D$20 -> 2284.375 | H58: =$E$21+$A58*$D$21 -> 2199.375 | I58: =MATCH(MAX(B58:H58),B58:H58,0)-1 -> 4
... A148: =A147+0.5 -> 60 | B148: =$E$15+$A148*$D$15 -> 150 | C148: =$E$16+$A148*$D$16 -> 4650 | D148: =$E$17+$A148*$D$17 -> 6805 | E148: =$E$18+$A148*$D$18 -> 7805 | F148: =$E$19+$A148*$D$19 -> 8236.25 | G148: =$E$20+$A148*$D$20 -> 8387.5 | H148: =$E$21+$A148*$D$21 -> 8400.9375 | I148: =MATCH(MAX(B148:H148),B148:H148,0)-1 -> 6

Sheet StandardForm
A1: Export the instance in standard form: one schedule's linear program, and the price of its end condition (Worked Example 2.1, Step 6; Section 2.7; Online Appendix Example 2.B.1)
A2: With the rounds fixed, liquidity is linear in the payouts p1 ... p6 and every commitment is a linear inequality. Emitted form: minimize -(p1 + ... + p6) subject to A p <= b, p >= 0. Change the rounds (blue) to export another schedule.
A4: The schedule, run with no payout
A5: Year | B5: Round (1 = yes) | C5: Liquidity at the start | D5: After paying for the round | E5: Capability before the round | F5: Efficiency | G5: Savings | H5: Paid out | I5: Liquidity at year end | J5: Floor kept? | K5: Capability kept?
A6: 1 | B6: 1 | C6: =Liq_0 -> 620 | D6: =C6-Round_cost*B6 -> 500 | E6: =Cap_0 -> 58 | F6: =IF(B6=1,Eff_0+Gap_closed*(Eff_ceiling-Eff_0),Eff_0) -> 78 | G6: =Sav_point*(F6-Eff_0) -> 70 | H6: =0*G6 -> 0 | I6: =D6+G6-H6 -> 570 | J6: =IF(AND(OR(B6=0,D6>=Floor_liq-0.000000001),I6>=Floor_liq-0.000000001),"yes","no") -> yes | K6: =IF(OR(B6=0,E6>=Cap_min),"yes","no") -> yes
A7: 2 | B7: 1 | C7: =I6 -> 570 | D7: =C7-Round_cost*B7 -> 450 | E7: =E6+Cap_step*B6 -> 59 | F7: =IF(B7=1,F6+Gap_closed*(Eff_ceiling-F6),F6) -> 81.5 | G7: =Sav_point*(F7-Eff_0) -> 105 | H7: =0*G7 -> 0 | I7: =D7+G7-H7 -> 555 | J7: =IF(AND(OR(B7=0,D7>=Floor_liq-0.000000001),I7>=Floor_liq-0.000000001),"yes","no") -> yes | K7: =IF(OR(B7=0,E7>=Cap_min),"yes","no") -> yes
A8: 3 | B8: 0 | C8: =I7 -> 555 | D8: =C8-Round_cost*B8 -> 555 | E8: =E7+Cap_step*B7 -> 60 | F8: =IF(B8=1,F7+Gap_closed*(Eff_ceiling-F7),F7) -> 81.5 | G8: =Sav_point*(F8-Eff_0) -> 105 | H8: =0*G8 -> 0 | I8: =D8+G8-H8 -> 660 | J8: =IF(AND(OR(B8=0,D8>=Floor_liq-0.000000001),I8>=Floor_liq-0.000000001),"yes","no") -> yes | K8: =IF(OR(B8=0,E8>=Cap_min),"yes","no") -> yes
A9: 4 | B9: 0 | C9: =I8 -> 660 | D9: =C9-Round_cost*B9 -> 660 | E9: =E8+Cap_step*B8 -> 60 | F9: =IF(B9=1,F8+Gap_closed*(Eff_ceiling-F8),F8) -> 81.5 | G9: =Sav_point*(F9-Eff_0) -> 105 | H9: =0*G9 -> 0 | I9: =D9+G9-H9 -> 765 | J9: =IF(AND(OR(B9=0,D9>=Floor_liq-0.000000001),I9>=Floor_liq-0.000000001),"yes","no") -> yes | K9: =IF(OR(B9=0,E9>=Cap_min),"yes","no") -> yes
A10: 5 | B10: 0 | C10: =I9 -> 765 | D10: =C10-Round_cost*B10 -> 765 | E10: =E9+Cap_step*B9 -> 60 | F10: =IF(B10=1,F9+Gap_closed*(Eff_ceiling-F9),F9) -> 81.5 | G10: =Sav_point*(F10-Eff_0) -> 105 | H10: =0*G10 -> 0 | I10: =D10+G10-H10 -> 870 | J10: =IF(AND(OR(B10=0,D10>=Floor_liq-0.000000001),I10>=Floor_liq-0.000000001),"yes","no") -> yes | K10: =IF(OR(B10=0,E10>=Cap_min),"yes","no") -> yes
A11: 6 | B11: 0 | C11: =I10 -> 870 | D11: =C11-Round_cost*B11 -> 870 | E11: =E10+Cap_step*B10 -> 60 | F11: =IF(B11=1,F10+Gap_closed*(Eff_ceiling-F10),F10) -> 81.5 | G11: =Sav_point*(F11-Eff_0) -> 105 | H11: =0*G11 -> 0 | I11: =D11+G11-H11 -> 975 | J11: =IF(AND(OR(B11=0,D11>=Floor_liq-0.000000001),I11>=Floor_liq-0.000000001),"yes","no") -> yes | K11: =IF(OR(B11=0,E11>=Cap_min),"yes","no") -> yes
M13: End condition written in units of (1 = $ million, 0.001 = $ billion): | Q13: 1
A14: Constraint | B14: In force (1 = yes) | C14: p1 | D14: p2 | E14: p3 | F14: p4 | G14: p5 | H14: p6 | I14: <= | J14: b, as written | K14: b if in force
A15: floor at the round-1 start | B15: =B6 -> 1 | C15: 0 | D15: 0 | E15: 0 | F15: 0 | G15: 0 | H15: 0 | I15: <= | J15: =D6-Floor_liq -> 150 | K15: =IF(B15=1,J15/IF(A15="end condition",$Q$13,1),1000000000) -> 150
A16: floor at the round-2 start | B16: =B7 -> 1 | C16: 1 | D16: 0 | E16: 0 | F16: 0 | G16: 0 | H16: 0 | I16: <= | J16: =D7-Floor_liq -> 100 | K16: =IF(B16=1,J16/IF(A16="end condition",$Q$13,1),1000000000) -> 100
A17: floor at the round-3 start | B17: =B8 -> 0 | C17: 1 | D17: 1 | E17: 0 | F17: 0 | G17: 0 | H17: 0 | I17: <= | J17: =D8-Floor_liq -> 205 | K17: =IF(B17=1,J17/IF(A17="end condition",$Q$13,1),1000000000) -> 1000000000
A18: floor at the round-4 start | B18: =B9 -> 0 | C18: 1 | D18: 1 | E18: 1 | F18: 0 | G18: 0 | H18: 0 | I18: <= | J18: =D9-Floor_liq -> 310 | K18: =IF(B18=1,J18/IF(A18="end condition",$Q$13,1),1000000000) -> 1000000000
A19: floor at the round-5 start | B19: =B10 -> 0 | C19: 1 | D19: 1 | E19: 1 | F19: 1 | G19: 0 | H19: 0 | I19: <= | J19: =D10-Floor_liq -> 415 | K19: =IF(B19=1,J19/IF(A19="end condition",$Q$13,1),1000000000) -> 1000000000
A20: floor at the round-6 start | B20: =B11 -> 0 | C20: 1 | D20: 1 | E20: 1 | F20: 1 | G20: 1 | H20: 0 | I20: <= | J20: =D11-Floor_liq -> 520 | K20: =IF(B20=1,J20/IF(A20="end condition",$Q$13,1),1000000000) -> 1000000000
A21: floor at the end of year 1 | B21: =1 -> 1 | C21: 1 | D21: 0 | E21: 0 | F21: 0 | G21: 0 | H21: 0 | I21: <= | J21: =I6-Floor_liq -> 220 | K21: =IF(B21=1,J21/IF(A21="end condition",$Q$13,1),1000000000) -> 220
A22: floor at the end of year 2 | B22: =1 -> 1 | C22: 1 | D22: 1 | E22: 0 | F22: 0 | G22: 0 | H22: 0 | I22: <= | J22: =I7-Floor_liq -> 205 | K22: =IF(B22=1,J22/IF(A22="end condition",$Q$13,1),1000000000) -> 205
A23: floor at the end of year 3 | B23: =1 -> 1 | C23: 1 | D23: 1 | E23: 1 | F23: 0 | G23: 0 | H23: 0 | I23: <= | J23: =I8-Floor_liq -> 310 | K23: =IF(B23=1,J23/IF(A23="end condition",$Q$13,1),1000000000) -> 310
A24: floor at the end of year 4 | B24: =1 -> 1 | C24: 1 | D24: 1 | E24: 1 | F24: 1 | G24: 0 | H24: 0 | I24: <= | J24: =I9-Floor_liq -> 415 | K24: =IF(B24=1,J24/IF(A24="end condition",$Q$13,1),1000000000) -> 415
A25: floor at the end of year 5 | B25: =1 -> 1 | C25: 1 | D25: 1 | E25: 1 | F25: 1 | G25: 1 | H25: 0 | I25: <= | J25: =I10-Floor_liq -> 520 | K25: =IF(B25=1,J25/IF(A25="end condition",$Q$13,1),1000000000) -> 520
A26: floor at the end of year 6 | B26: =1 -> 1 | C26: 1 | D26: 1 | E26: 1 | F26: 1 | G26: 1 | H26: 1 | I26: <= | J26: =I11-Floor_liq -> 625 | K26: =IF(B26=1,J26/IF(A26="end condition",$Q$13,1),1000000000) -> 625
A27: end condition | B27: =1 -> 1 | C27: =$Q$13 -> 1 | D27: =$Q$13 -> 1 | E27: =$Q$13 -> 1 | F27: =$Q$13 -> 1 | G27: =$Q$13 -> 1 | H27: =$Q$13 -> 1 | I27: <= | J27: =$Q$13*(I11-End_liq) -> 505 | K27: =IF(B27=1,J27/IF(A27="end condition",$Q$13,1),1000000000) -> 505
A30: Feasible: every constraint in force has b >= 0 (no payout can rescue a round-1 start) | B30: =IF(MIN(K15:K27)>=0,"yes","no") -> yes
A31: Best six-year payout: the smallest b among the constraints on all six payouts | B31: =IF(B30="yes",MIN(K26,K27),"infeasible") -> 505
A32: Binding constraint | B32: =IF(B30="yes",IF(K27<=K26,"end condition","floor at the end of year 6"),"") -> end condition
A33: End condition written in $ million: best payout if its b rises by 0.001 | B33: =MIN(K26,(I11-End_liq)+0.001) -> 505.001
A34: ... its price: the rise in the best payout per unit of b, in $ million | B34: =(B33-B31)/0.001 -> 1
A35: End condition written in $ billion: best payout if its b rises by 0.001 | B35: =MIN(K26,1000*((I11-End_liq)/1000+0.001)) -> 506
A36: ... its price per unit of b, in $ billion: the same commitment, 1,000 times the price | B36: =(B35-B31)/0.001 -> 1000
A37: Scaling a commitment by g > 0 divides its multiplier by g and changes no decision (Online Appendix Example 2.B.1): a price must be read in the units of the commitment as written.

Sheet Quantifiers
A1: One commitment, four quantifiers: the board's liquidity floor during the digital program (Table 2.4; Proposition 2.3; Theorem 2.4(iii))
A2: Volume I's Chapter 8 model and Worked Example 15.1's levers. True odds (green) are counted by the notebook's engine on the book's 100,000 paths (seed 8); costs, the stress-set line and the price of the appetite are formulas.
A3: Declaration | B3: Value | C3: Source
A4: Plan index the program's liquidity relaxes to (today = 100) | B4: 112 | C4: Volume I's digital program
A5: Relaxation rate a year | B5: 0.35
A6: Depth of the plan's trough (index points) | B6: 28 | C6: Low point in quarter 7
A7: Years to the trough's deepest point | B7: 2
A8: Liquidity per index point | B8: =Liq_0/100 -> 6.2 | C8: $6.2 million
A9: Funding-window closure: mean size | B9: 120 | C9: 0.10 a year, never recovered
A10: Funding-window closure: standard deviation | B10: 50 | C10: Gamma-distributed sizes
A11: Standby line fees over the program, per $ of line | B11: 0.03 | C11: About 1 percent a year for three years
A12: Value of a quarter of delay | B12: 8 | C12: Digital Solutions' contribution
A13: Depth cut by a quarter of delay (index points) | B13: 4 | C13: Phasing: depth 28 - 4 phi
A15: Quarter | B15: Years | C15: Planned liquidity ($ million)
A16: 0 | B16: =A16/4 -> 0 | C16: =$B$8*($B$4-($B$4-100)*EXP(-$B$5*B16)-$B$6*(B16/$B$7)*EXP(1-B16/$B$7)) -> 620
A17: 1 | B17: =A17/4 -> 0.25 | C17: =$B$8*($B$4-($B$4-100)*EXP(-$B$5*B17)-$B$6*(B17/$B$7)*EXP(1-B17/$B$7)) -> 574.17772
A18: 2 | B18: =A18/4 -> 0.5 | C18: =$B$8*($B$4-($B$4-100)*EXP(-$B$5*B18)-$B$6*(B18/$B$7)*EXP(1-B18/$B$7)) -> 540.0666
A19: 3 | B19: =A19/4 -> 0.75 | C19: =$B$8*($B$4-($B$4-100)*EXP(-$B$5*B19)-$B$6*(B19/$B$7)*EXP(1-B19/$B$7)) -> 515.55419
A20: 4 | B20: =A20/4 -> 1 | C20: =$B$8*($B$4-($B$4-100)*EXP(-$B$5*B20)-$B$6*(B20/$B$7)*EXP(1-B20/$B$7)) -> 498.8622
A21: 5 | B21: =A21/4 -> 1.25 | C21: =$B$8*($B$4-($B$4-100)*EXP(-$B$5*B21)-$B$6*(B21/$B$7)*EXP(1-B21/$B$7)) -> 488.49718
A22: 6 | B22: =A22/4 -> 1.5 | C22: =$B$8*($B$4-($B$4-100)*EXP(-$B$5*B22)-$B$6*(B22/$B$7)*EXP(1-B22/$B$7)) -> 483.20817
A23: 7 | B23: =A23/4 -> 1.75 | C23: =$B$8*($B$4-($B$4-100)*EXP(-$B$5*B23)-$B$6*(B23/$B$7)*EXP(1-B23/$B$7)) -> 481.95038
A24: 8 | B24: =A24/4 -> 2 | C24: =$B$8*($B$4-($B$4-100)*EXP(-$B$5*B24)-$B$6*(B24/$B$7)*EXP(1-B24/$B$7)) -> 483.85405
A25: 9 | B25: =A25/4 -> 2.25 | C25: =$B$8*($B$4-($B$4-100)*EXP(-$B$5*B25)-$B$6*(B25/$B$7)*EXP(1-B25/$B$7)) -> 488.19778
A26: 10 | B26: =A26/4 -> 2.5 | C26: =$B$8*($B$4-($B$4-100)*EXP(-$B$5*B26)-$B$6*(B26/$B$7)*EXP(1-B26/$B$7)) -> 494.3857
A27: 11 | B27: =A27/4 -> 2.75 | C27: =$B$8*($B$4-($B$4-100)*EXP(-$B$5*B27)-$B$6*(B27/$B$7)*EXP(1-B27/$B$7)) -> 501.92795
A28: 12 | B28: =A28/4 -> 3 | C28: =$B$8*($B$4-($B$4-100)*EXP(-$B$5*B28)-$B$6*(B28/$B$7)*EXP(1-B28/$B$7)) -> 510.42405
A30: The program's deepest draw on the cash above the floor | B30: =Liq_0-MIN(C16:C28) -> 138.04962
A31: A 90th-percentile closure | B31: =GAMMAINV(0.9,(B9/B10)^2,B10^2/B9) -> 186.86698
A32: Cash above the floor | B32: =Liq_0-Floor_liq -> 270
A33: Stress set (Volume I's joint check): the least line, draw + (closure - line) <= cash above the floor | B33: =MAX(B31-(B32-B30),0) -> 54.916594
A34: Its cost | B34: =B11*B33 -> 1.6474978
A35: With probability at least 95%: the line (engine, Volume I's $5m grid) | B35: 170
A36: ... and the least delay that meets 5 percent with it, quarters (engine) | B36: 0.66757636
A37: ... in months | B37: =3*B36 -> 2.0027291
A38: ... its cost | B38: =B11*B35+B12*B36 -> 10.440611
A39: The average path's lowest point (engine) | B39: 459.94151
A40: Does the average path keep the floor? | B40: =IF(B39>=Floor_liq,"yes: no lever is needed","no") -> yes: no lever is needed
A42: Declared as | B42: Cheapest package | C42: Cost ($ million) | D42: True odds (engine)
A43: on the average path | B43: ="no lever" -> no lever | C43: =0 -> 0 | D43: 0.24622
A44: in every scenario of a stress set | B44: ="a $"&TEXT(B33,"0")&" million standby line" -> a $55 million standby line | C44: =B34 -> 1.6474978 | D44: 0.17403
A45: with probability at least 95% | B45: ="a $"&TEXT(B35,"0")&" million line and "&TEXT(B37,"0")&" months' delay" -> a $170 million line and 2 months' delay | C45: =B38 -> 10.440611 | D45: 0.05
A46: on every path | B46: ="none: the odds never fall below "&TEXT(D47,"0.000%") -> none: the odds never fall below 0.001% | C46: -- | D46: --
A47: Lowest odds found on every path ($400m or $1bn line, six or seven quarters of delay) | D47: 1e-05
A49: The price of the appetite (Theorem 2.4(iii)) | B49: Line ($m, engine) | C49: Delay (quarters, engine) | D49: Cost
A50: Cheapest package at 4.5 percent | B50: 165 | C50: 0.80481304 | D50: =$B$11*B50+$B$12*C50 -> 11.388504
A51: Cheapest package at 5.5 percent | B51: 165 | C51: 0.57893619 | D51: =$B$11*B51+$B$12*C51 -> 9.5814895
A52: Price of a percentage point of breach odds | D52: =(D50-D51)/(5.5-4.5) -> 1.8070148
A53: Implied cost of a breach: 100 points x the price | D53: =100*D52 -> 180.70148
A55: Proposition 2.3(iv): holds with stated probability, fails on the average path | B55: Value | C55: Probability
A56: x1 when w = 1 | B56: 1 | C56: 0.96
A57: x1 when w = -30 | B57: -30 | C57: 0.04
A58: Probability that x1 >= 0 | B58: =SUMIF(B56:B57,">=0",C56:C57) -> 0.96
A59: Holds with probability at least 95%? | B59: =IF(B58>=0.95,"yes","no") -> yes
A60: x1 on the average path, E[x1] | B60: =SUMPRODUCT(B56:B57,C56:C57) -> -0.24
A61: Holds on the average path? | B61: =IF(B60>=0,"yes","no") -> no

Sheet Reference_Values
A1: Checkpoint | B1: Engine value | C1: Meaning (where in the book)
A2: Editor: entries refused (savings as a decision) | B2: 1 | C2: AXIOM Lab 2.2, step 1: the editor refuses an induced quantity
A3: Six-round savings in the CFO's spreadsheet | B3: 702.1875 | C3: Worked Example 2.1, Step 1: $702 million
A4: Savings of rounds in years 1, 2 and 4 | B4: 647.5 | C4: $647.5 million
A5: The phantom lever overstates them by | B5: 54.6875 | C5: LOS Guidance 2.2: $55 million
A6: Joint plan: liquidity at the end of year 1 | B6: 535 | C6: Step 2: $535 million
A7: Joint plan: liquidity at the end of year 2 | B7: 467.5 | C7: $467.5 million
A8: Joint plan: liquidity after paying for round 3 | B8: 347.5 | C8: $347.5 million
A9: The joint plan dies in year | B9: 3 | C9: Year 3
A10: COO's plan with savings kept: liquidity, year 6 | B10: 602.1875 | C10: Online Appendix 2.B.4: 602.2
A11: Reachable sets: first empty year | B11: 3 | C11: Theorem 2.3(iii): year 3
A12: Reachable sets, floor dropped: first empty year | B12: 6 | C12: The end condition fails in year 6
A13: Reachable sets: the most liquidity at the end of year 2 | B13: 467.5 | C13: $467.5 million
... A67: Proposition 2.3(iv): x1 on the average path | B67: -0.24 | C67: Online Appendix 2.B: -0.24

Sheet Checks
A1: Checkpoint | B1: Workbook formula value | C1: Engine value | D1: |diff| | E1: Tolerance | F1: Status
A2: Editor: entries refused (savings as a decision) | B2: =Instance!B18 -> 1 | C2: =Reference_Values!B2 -> 1 | D2: =ABS(B2-C2) -> 0 | E2: 0 | F2: =IF(D2<=E2,"PASS","FAIL") -> PASS
A3: Six-round savings in the CFO's spreadsheet | B3: =Instance!B31 -> 702.1875 | C3: =Reference_Values!B3 -> 702.1875 | D3: =ABS(B3-C3) -> 0 | E3: 1e-09 | F3: =IF(D3<=E3,"PASS","FAIL") -> PASS
A4: Savings of rounds in years 1, 2 and 4 | B4: =Instance!B32 -> 647.5 | C4: =Reference_Values!B4 -> 647.5 | D4: =ABS(B4-C4) -> 0 | E4: 1e-09 | F4: =IF(D4<=E4,"PASS","FAIL") -> PASS
A5: The phantom lever overstates them by | B5: =Instance!B33 -> 54.6875 | C5: =Reference_Values!B5 -> 54.6875 | D5: =ABS(B5-C5) -> 0 | E5: 1e-09 | F5: =IF(D5<=E5,"PASS","FAIL") -> PASS
A6: Joint plan: liquidity at the end of year 1 | B6: =JointPlan!N6 -> 535 | C6: =Reference_Values!B6 -> 535 | D6: =ABS(B6-C6) -> 0 | E6: 1e-09 | F6: =IF(D6<=E6,"PASS","FAIL") -> PASS
A7: Joint plan: liquidity at the end of year 2 | B7: =JointPlan!N7 -> 467.5 | C7: =Reference_Values!B7 -> 467.5 | D7: =ABS(B7-C7) -> 0 | E7: 1e-09 | F7: =IF(D7<=E7,"PASS","FAIL") -> PASS
A8: Joint plan: liquidity after paying for round 3 | B8: =JointPlan!N8 -> 347.5 | C8: =Reference_Values!B8 -> 347.5 | D8: =ABS(B8-C8) -> 0 | E8: 1e-09 | F8: =IF(D8<=E8,"PASS","FAIL") -> PASS
A9: The joint plan dies in year | B9: =JointPlan!N9 -> 3 | C9: =Reference_Values!B9 -> 3 | D9: =ABS(B9-C9) -> 0 | E9: 0 | F9: =IF(D9<=E9,"PASS","FAIL") -> PASS
A10: COO's plan with savings kept: liquidity, year 6 | B10: =JointPlan!N12 -> 602.1875 | C10: =Reference_Values!B10 -> 602.1875 | D10: =ABS(B10-C10) -> 0 | E10: 1e-09 | F10: =IF(D10<=E10,"PASS","FAIL") -> PASS
A11: Reachable sets: first empty year | B11: =JointPlan!I35 -> 3 | C11: =Reference_Values!B11 -> 3 | D11: =ABS(B11-C11) -> 0 | E11: 0 | F11: =IF(D11<=E11,"PASS","FAIL") -> PASS
A12: Reachable sets, floor dropped: first empty year | B12: =JointPlan!I47 -> 6 | C12: =Reference_Values!B12 -> 6 | D12: =ABS(B12-C12) -> 0 | E12: 0 | F12: =IF(D12<=E12,"PASS","FAIL") -> PASS
A13: Reachable sets: the most liquidity at the end of year 2 | B13: =JointPlan!H30 -> 467.5 | C13: =Reference_Values!B13 -> 467.5 | D13: =ABS(B13-C13) -> 0 | E13: 1e-09 | F13: =IF(D13<=E13,"PASS","FAIL") -> PASS
A14: Deletion filter, board first: code of the clash | B14: =DiagnoseClash!O11 -> 13 | C14: =Reference_Values!B14 -> 13 | D14: =ABS(B14-C14) -> 0 | E14: 0 | F14: =IF(D14<=E14,"PASS","FAIL") -> PASS
A15: Deletion filter, pledges first: code of the clash | B15: =DiagnoseClash!O21 -> 28 | C15: =Reference_Values!B15 -> 28 | D15: =ABS(B15-C15) -> 0 | E15: 0 | F15: =IF(D15<=E15,"PASS","FAIL") -> PASS
A16: Minimal infeasible sets | B16: =DiagnoseClash!I58 -> 2 | C16: =Reference_Values!B16 -> 2 | D16: =ABS(B16-C16) -> 0 | E16: 0 | F16: =IF(D16<=E16,"PASS","FAIL") -> PASS
A17: Groups to drop on which Theorem 2.3(ii) holds | B17: =DiagnoseClash!H97 -> 32 | C17: =Reference_Values!B17 -> 32 | D17: =ABS(B17-C17) -> 0 | E17: 0 | F17: =IF(D17<=E17,"PASS","FAIL") -> PASS
A18: Smallest repairs | B18: =DiagnoseClash!H98 -> 3 | C18: =Reference_Values!B18 -> 3 | D18: =ABS(B18-C18) -> 0 | E18: 0 | F18: =IF(D18<=E18,"PASS","FAIL") -> PASS
A19: Drop the floor alone: the rest can hold (1 = yes) | B19: =DiagnoseClash!H99 -> 0 | C19: =Reference_Values!B19 -> 0 | D19: =ABS(B19-C19) -> 0 | E19: 0 | F19: =IF(D19<=E19,"PASS","FAIL") -> PASS
A20: (a) largest constant payout share | B20: =Repairs!Q9 -> 0.188251 | C20: =Reference_Values!B20 -> 0.188251 | D20: =ABS(B20-C20) -> 0 | E20: 1e-09 | F20: =IF(D20<=E20,"PASS","FAIL") -> PASS
A21: (a) the round-6 start alone would allow | B21: =Repairs!Q11 -> 0.20265781 | C21: =Reference_Values!B21 -> 0.20265781 | D21: =ABS(B21-C21) -> 0 | E21: 1e-09 | F21: =IF(D21<=E21,"PASS","FAIL") -> PASS
A22: (a) paid out over six years | B22: =Repairs!Q16 -> 132.1875 | C22: =Reference_Values!B22 -> 132.1875 | D22: =ABS(B22-C22) -> 0 | E22: 1e-06 | F22: =IF(D22<=E22,"PASS","FAIL") -> PASS
A23: (a) efficiency in year 6 | B23: =Repairs!Q17 -> 84.78125 | C23: =Reference_Values!B23 -> 84.78125 | D23: =ABS(B23-C23) -> 0 | E23: 1e-09 | F23: =IF(D23<=E23,"PASS","FAIL") -> PASS
A24: (a) liquidity at the end of year 6 | B24: =Repairs!Q18 -> 470 | C24: =Reference_Values!B24 -> 470 | D24: =ABS(B24-C24) -> 0 | E24: 1e-06 | F24: =IF(D24<=E24,"PASS","FAIL") -> PASS
A25: (a) paid out in year 1 | B25: =Repairs!H16 -> 13.17757 | C25: =Reference_Values!B25 -> 13.17757 | D25: =ABS(B25-C25) -> 0 | E25: 1e-06 | F25: =IF(D25<=E25,"PASS","FAIL") -> PASS
A26: (a) liquidity at the end of year 4 | B26: =Repairs!I19 -> 488.03738 | C26: =Reference_Values!B26 -> 488.03738 | D26: =ABS(B26-C26) -> 0 | E26: 1e-06 | F26: =IF(D26<=E26,"PASS","FAIL") -> PASS
A27: (b) schedules keeping the board's conditions | B27: =Repairs!Q24 -> 35 | C27: =Reference_Values!B27 -> 35 | D27: =ABS(B27-C27) -> 0 | E27: 0 | F27: =IF(D27<=E27,"PASS","FAIL") -> PASS
A28: (b) years of the rounds | B28: =Repairs!Q27 -> 124 | C28: =Reference_Values!B28 -> 124 | D28: =ABS(B28-C28) -> 0 | E28: 0 | F28: =IF(D28<=E28,"PASS","FAIL") -> PASS
A29: (b) paid out over six years | B29: =Repairs!Q28 -> 323.75 | C29: =Reference_Values!B29 -> 323.75 | D29: =ABS(B29-C29) -> 0 | E29: 1e-09 | F29: =IF(D29<=E29,"PASS","FAIL") -> PASS
A30: (b) efficiency in year 6 | B30: =Repairs!Q30 -> 83.25 | C30: =Reference_Values!B30 -> 83.25 | D30: =ABS(B30-C30) -> 0 | E30: 1e-09 | F30: =IF(D30<=E30,"PASS","FAIL") -> PASS
A31: (b) liquidity at the end of year 6 | B31: =Repairs!Q31 -> 583.75 | C31: =Reference_Values!B31 -> 583.75 | D31: =ABS(B31-C31) -> 0 | E31: 1e-09 | F31: =IF(D31<=E31,"PASS","FAIL") -> PASS
A32: (b) liquidity at the end of year 4 | B32: =Repairs!I29 -> 461.25 | C32: =Reference_Values!B32 -> 461.25 | D32: =ABS(B32-C32) -> 0 | E32: 1e-09 | F32: =IF(D32<=E32,"PASS","FAIL") -> PASS
A33: (b) + a year-3 round: after paying for it | B33: =Repairs!Q37 -> 347.5 | C33: =Reference_Values!B33 -> 347.5 | D33: =ABS(B33-C33) -> 0 | E33: 1e-09 | F33: =IF(D33<=E33,"PASS","FAIL") -> PASS
A34: (b) + a year-5 round: after paying for it | B34: =Repairs!Q47 -> 341.25 | C34: =Reference_Values!B34 -> 341.25 | D34: =ABS(B34-C34) -> 0 | E34: 1e-09 | F34: =IF(D34<=E34,"PASS","FAIL") -> PASS
A35: (b) + a year-6 round: liquidity, year 6 | B35: =Repairs!Q58 -> 468.125 | C35: =Reference_Values!B35 -> 468.125 | D35: =ABS(B35-C35) -> 0 | E35: 1e-09 | F35: =IF(D35<=E35,"PASS","FAIL") -> PASS
A36: (c) paid out over six years | B36: =Repairs!Q67 -> 351.09375 | C36: =Reference_Values!B36 -> 351.09375 | D36: =ABS(B36-C36) -> 0 | E36: 1e-09 | F36: =IF(D36<=E36,"PASS","FAIL") -> PASS
A37: (c) lowest liquidity after paying for a round | B37: =Repairs!Q66 -> 182.1875 | C37: =Reference_Values!B37 -> 182.1875 | D37: =ABS(B37-C37) -> 0 | E37: 1e-09 | F37: =IF(D37<=E37,"PASS","FAIL") -> PASS
A38: (c) liquidity at the end of year 3 | B38: =Repairs!I68 -> 408.75 | C38: =Reference_Values!B38 -> 408.75 | D38: =ABS(B38-C38) -> 0 | E38: 1e-09 | F38: =IF(D38<=E38,"PASS","FAIL") -> PASS
A39: (c) liquidity at the end of year 6 | B39: =Repairs!Q68 -> 251.09375 | C39: =Reference_Values!B39 -> 251.09375 | D39: =ABS(B39-C39) -> 0 | E39: 1e-09 | F39: =IF(D39<=E39,"PASS","FAIL") -> PASS
A40: Optimizer, no credit: years of the rounds | B40: =Optimizer!D5 -> 12 | C40: =Reference_Values!B40 -> 12 | D40: =ABS(B40-C40) -> 0 | E40: 0 | F40: =IF(D40<=E40,"PASS","FAIL") -> PASS
A41: Optimizer, no credit: paid out | B41: =Optimizer!E5 -> 505 | C41: =Reference_Values!B41 -> 505 | D41: =ABS(B41-C41) -> 0 | E41: 1e-06 | F41: =IF(D41<=E41,"PASS","FAIL") -> PASS
A42: Optimizer, ten years' credit: years of the rounds | B42: =Optimizer!D7 -> 123 | C42: =Reference_Values!B42 -> 123 | D42: =ABS(B42-C42) -> 0 | E42: 0 | F42: =IF(D42<=E42,"PASS","FAIL") -> PASS
A43: Optimizer, ten years' credit: paid out | B43: =Optimizer!E7 -> 455 | C43: =Reference_Values!B43 -> 455 | D43: =ABS(B43-C43) -> 0 | E43: 1e-06 | F43: =IF(D43<=E43,"PASS","FAIL") -> PASS
A44: Six credits: the best of 64 runs early rounds | B44: =Optimizer!I12 -> 6 | C44: =Reference_Values!B44 -> 6 | D44: =ABS(B44-C44) -> 0 | E44: 0 | F44: =IF(D44<=E44,"PASS","FAIL") -> PASS
A45: Credit for a third round | B45: =Optimizer!F17 -> 2.8571429 | C45: =Reference_Values!B45 -> 2.8571429 | D45: =ABS(B45-C45) -> 0 | E45: 1e-09 | F45: =IF(D45<=E45,"PASS","FAIL") -> PASS
A46: Credit for a fourth round | B46: =Optimizer!F18 -> 10.714286 | C46: =Reference_Values!B46 -> 10.714286 | D46: =ABS(B46-C46) -> 0 | E46: 1e-09 | F46: =IF(D46<=E46,"PASS","FAIL") -> PASS
A47: Credit for a fifth round | B47: =Optimizer!F19 -> 25.428571 | C47: =Reference_Values!B47 -> 25.428571 | D47: =ABS(B47-C47) -> 0 | E47: 1e-09 | F47: =IF(D47<=E47,"PASS","FAIL") -> PASS
A48: Credit for the sixth round | B48: =Optimizer!F20 -> 53.857143 | C48: =Reference_Values!B48 -> 53.857143 | D48: =ABS(B48-C48) -> 0 | E48: 1e-09 | F48: =IF(D48<=E48,"PASS","FAIL") -> PASS
A49: First credit on the 0.5-year grid buying 3 rounds | B49: =Optimizer!L15 -> 3 | C49: =Reference_Values!B49 -> 3 | D49: =ABS(B49-C49) -> 0 | E49: 0 | F49: =IF(D49<=E49,"PASS","FAIL") -> PASS
A50: First credit on the 0.5-year grid buying 6 rounds | B50: =Optimizer!L18 -> 54 | C50: =Reference_Values!B50 -> 54 | D50: =ABS(B50-C50) -> 0 | E50: 0 | F50: =IF(D50<=E50,"PASS","FAIL") -> PASS
A51: Rounds 3 to 6: savings inside the six years | B51: =Optimizer!E24 -> 107.1875 | C51: =Reference_Values!B51 -> 107.1875 | D51: =ABS(B51-C51) -> 0 | E51: 1e-09 | F51: =IF(D51<=E51,"PASS","FAIL") -> PASS
A52: Six early rounds: payouts + year-6 liquidity | B52: =Optimizer!C21 -> 602.1875 | C52: =Reference_Values!B52 -> 602.1875 | D52: =ABS(B52-C52) -> 0 | E52: 1e-09 | F52: =IF(D52<=E52,"PASS","FAIL") -> PASS
A53: Mayer form less running form, credit 0 | B53: =Optimizer!L37 -> 0 | C53: =Reference_Values!B53 -> 0 | D53: =ABS(B53-C53) -> 0 | E53: 1e-09 | F53: =IF(D53<=E53,"PASS","FAIL") -> PASS
A54: Mayer form less running form, credit 10 | B54: =Optimizer!M37 -> 0 | C54: =Reference_Values!B54 -> 0 | D54: =ABS(B54-C54) -> 0 | E54: 1e-09 | F54: =IF(D54<=E54,"PASS","FAIL") -> PASS
A55: Restatements that change the plan | B55: =Optimizer!L45 -> 0 | C55: =Reference_Values!B55 -> 0 | D55: =ABS(B55-C55) -> 0 | E55: 0 | F55: =IF(D55<=E55,"PASS","FAIL") -> PASS
A56: Standard form: best six-year payout | B56: =StandardForm!B31 -> 505 | C56: =Reference_Values!B56 -> 505 | D56: =ABS(B56-C56) -> 0 | E56: 1e-06 | F56: =IF(D56<=E56,"PASS","FAIL") -> PASS
A57: Price of the end condition per $1 million | B57: =StandardForm!B34 -> 1 | C57: =Reference_Values!B57 -> 1 | D57: =ABS(B57-C57) -> 2.3646862e-11 | E57: 1e-06 | F57: =IF(D57<=E57,"PASS","FAIL") -> PASS
A58: Price of the end condition per $1 billion | B58: =StandardForm!B36 -> 1000 | C58: =Reference_Values!B58 -> 1000 | D58: =ABS(B58-C58) -> 0 | E58: 0.001 | F58: =IF(D58<=E58,"PASS","FAIL") -> PASS
A59: The program's deepest draw | B59: =Quantifiers!B30 -> 138.04962 | C59: =Reference_Values!B59 -> 138.04962 | D59: =ABS(B59-C59) -> 0 | E59: 1e-06 | F59: =IF(D59<=E59,"PASS","FAIL") -> PASS
A60: A 90th-percentile closure | B60: =Quantifiers!B31 -> 186.86698 | C60: =Reference_Values!B60 -> 186.86698 | D60: =ABS(B60-C60) -> 0 | E60: 1e-06 | F60: =IF(D60<=E60,"PASS","FAIL") -> PASS
A61: Stress set: the least standby line | B61: =Quantifiers!B33 -> 54.916594 | C61: =Reference_Values!B61 -> 54.916594 | D61: =ABS(B61-C61) -> 0 | E61: 1e-06 | F61: =IF(D61<=E61,"PASS","FAIL") -> PASS
A62: Stress set: its cost | B62: =Quantifiers!B34 -> 1.6474978 | C62: =Reference_Values!B62 -> 1.6474978 | D62: =ABS(B62-C62) -> 0 | E62: 1e-06 | F62: =IF(D62<=E62,"PASS","FAIL") -> PASS
A63: 95 percent: delay in months | B63: =Quantifiers!B37 -> 2.0027291 | C63: =Reference_Values!B63 -> 2.0027291 | D63: =ABS(B63-C63) -> 0 | E63: 1e-09 | F63: =IF(D63<=E63,"PASS","FAIL") -> PASS
A64: 95 percent: cost | B64: =Quantifiers!B38 -> 10.440611 | C64: =Reference_Values!B64 -> 10.440611 | D64: =ABS(B64-C64) -> 0 | E64: 1e-06 | F64: =IF(D64<=E64,"PASS","FAIL") -> PASS
A65: Price of the appetite, per percentage point | B65: =Quantifiers!D52 -> 1.8070148 | C65: =Reference_Values!B65 -> 1.8070148 | D65: =ABS(B65-C65) -> 0 | E65: 1e-06 | F65: =IF(D65<=E65,"PASS","FAIL") -> PASS
A66: Implied cost of a breach | B66: =Quantifiers!D53 -> 180.70148 | C66: =Reference_Values!B66 -> 180.70148 | D66: =ABS(B66-C66) -> 0 | E66: 0.0001 | F66: =IF(D66<=E66,"PASS","FAIL") -> PASS
A67: Proposition 2.3(iv): x1 on the average path | B67: =Quantifiers!B60 -> -0.24 | C67: =Reference_Values!B67 -> -0.24 | D67: =ABS(B67-C67) -> 0 | E67: 1e-09 | F67: =IF(D67<=E67,"PASS","FAIL") -> PASS
A69: All checkpoints | F69: =IF(COUNTIF(F2:F67,"PASS")=66,"ALL PASS","CHECK") -> ALL PASS
