Workbook

Sheet README
B1: DCT Laboratory — Vol II, Ch 1: Introduction to Enterprise Optimization
B2: Seed 26201 · Companion to DCT_V2_Ch01_Lab.ipynb and AXIOM Lab 2.1 (module AXIOM-01). Money in $ million.
B4: Worked Example 1.1, Can Meridian Sign Volume I's Answer?, with the book's declarations.
B5: Declarations: the inputs of Step 1 and Meridian's state. CanonicalForm: the formulation assistant, which refuses when a term has no declared price or owner.
B6: Gates: the four readiness gates of Theorem 1.5, Volume I's joint check from the plan's path, and the minimal infeasible set when the standby line is removed.
B7: Continuous: the cheapest package along the 5 percent curve, at $8m, $4m and $16m a quarter of delay.
B8: LumpyGrid: the 63 packages of $50 million tranches and whole quarters, the cheapest feasible one and the two roundings. FinerLines: Table 1.3 and the least line for each number of quarters.
B9: Reweight: rescaling changes no rank; reweighting moves the continuous answer, not the lumpy one.
B10: Commitments: the covenant, the capability floor and the joint check added to the appetite. ErrorBars: the sampling error of every breach odds, and fresh paths drawn with the lab's seed.
B11: TwoChannelBudget: Online Appendix Example 1.B.2, a budget of 100 between two channels, and its price.
B12: Breach odds come from the notebook's engine (Volume I's Chapter 8 model on the book's 100,000 paths); everything else is a formula.
B13: Reference_Values and Checks: the engine's numbers and a PASS/FAIL comparison with this workbook's formulas.
... B19: Cross-sheet link: green.

Sheet Declarations
A1: Declarations (Worked Example 1.1, Step 1). Money in $ million.
A3: Quantity | B3: Value | C3: Source
A4: Standby line fees a year, share of the line | B4: 0.01 | C4: About 1 percent a year (treasury)
A5: Length of the digital program (years) | B5: 3 | C5: Three years, twelve quarters
A6: Line fees over the program, per $ of line | B6: =B4*B5 -> 0.03 | C6: A line of l costs 0.03 l
A7: Value of a quarter of delay | B7: 8 | C7: Digital Solutions' contribution (the transformation office)
A8: The board's appetite: largest breach odds | B8: 0.05 | C8: At most a 5 percent chance of breaching the floor
A9: Line tranche | B9: 50 | C9: The bank writes committed lines in tranches of $50 million
A10: Largest line | B10: 400 | C10: The box: 0 <= l <= 400
A11: Longest delay (quarters) | B11: 6 | C11: The box: 0 <= phi <= 6; the program office plans whole quarters
A12: Simulated paths | B12: 100000 | C12: Volume I's Chapter 8 model (seed 8): the engine's breach odds
A13: Liquidity today | B13: 620 | C13: Meridian's liquidity, $620 million
A14: Liquidity index today | B14: 100 | C14: Volume I's plan is written as an index, today = 100
A15: Liquidity per index point | B15: =B13/B14 -> 6.2 | C15: $6.2 million
A16: The board's floor | B16: 350 | C16: Liquidity must stay above $350 million
A17: Cash above the floor | B17: =B13-B16 -> 270 | C17: $270 million
A18: Index the plan relaxes to | B18: 112 | C18: Volume I's digital-program plan
A19: Relaxation rate of the plan, a year | B19: 0.35
A20: Depth of the plan's trough (index points) | B20: 28 | C20: Low point in quarter 7
A21: Years to the trough's deepest point | B21: 2
A22: Depth cut by a quarter of delay | B22: 4 | C22: Phasing: depth 28 - 4 phi
A23: Funding-window closure: mean size | B23: 120 | C23: Closures 0.10 a year, never recovered
A24: Funding-window closure: standard deviation | B24: 50 | C24: Gamma-distributed sizes
A25: A 90th-percentile closure | B25: =GAMMAINV(0.9,(B23/B24)^2,B24^2/B23) -> 186.86698 | C25: The cash buffer of Volume I's joint check
A26: Revenue | B26: 4200
A27: EBITDA margin | B27: 0.118
A28: EBITDA | B28: =B26*B27 -> 495.6
A29: Net leverage today (net debt / EBITDA) | B29: 3.4
A30: Net debt | B30: =B29*B28 -> 1685.04
A31: Covenant: net leverage at most | B31: 4.5 | C31: The loan covenant
A32: Workforce capability | B32: 58 | C32: Stays at 58 through the digital program
A33: Capability floor of the digital build | B33: 55
A34: Strength of each of the core's four two-way links | B34: 0.4 | C34: The feedback core (Volume I)
A35: Tax rate (any rate leaves every package in place) | B35: 0.25 | C35: For the after-tax view
A37: Meridian's state (Volume I, Chapter 3) | B37: Reading
A38: Liquidity ($ million) | B38: 620
A39: Net leverage (net debt / EBITDA) | B39: 3.4
A40: Workforce capability | B40: 58
A41: Technology platform | B41: 41
A42: Operational efficiency | B42: 71
A43: ROIC | B43: 0.083
A44: Strategic risk | B44: 64
A45: Market share | B45: 0.19
A47: The breach odds on the other sheets come from the notebook's engine: Volume I's Chapter 8 model on the book's 100,000 paths. Everything else is a formula of these declarations.

Sheet CanonicalForm
A1: Formulate: the canonical form (Equation 1.1; Worked Example 1.1, Step 1; AXIOM Lab 2.1, step 1)
A2: The formulation assistant emits the canonical form only when every term has a declared price or limit and an owner (Proposition 1.1). Delete the delay's owner (E6) or price (F6) and watch it refuse.
A4: Term | B4: Symbol | C4: Unit | D4: Range | E4: Owner | F4: Price or limit | G4: Declared?
A5: Standby line | B5: l | C5: $ million | D5: ="0 to "&Line_max -> 0 to 400 | E5: treasury | F5: =Fee -> 0.03 | G5: =IF(AND(LEN(E5)>0,LEN(F5)>0),"yes","no") -> yes
A6: Delay of the build | B6: phi | C6: quarters | D6: ="0 to "&Delay_max -> 0 to 6 | E6: transformation office | F6: =Vq -> 8 | G6: =IF(AND(LEN(E6)>0,LEN(F6)>0),"yes","no") -> yes
A7: The board's appetite | B7: P | C7: breach odds | D7: ="at most "&TEXT(Appetite,"0%") -> at most 5% | E7: the board | F7: =Appetite -> 0.05 | G7: =IF(AND(LEN(E7)>0,LEN(F7)>0),"yes","no") -> yes
A8: State map | B8: x = f(l, phi) | E8: Volume I, Chapter 8 | F8: 100,000 paths | G8: yes
A10: The assistant's verdict | B10: =IF(COUNTIF(G5:G7,"no")>0,"Refuses: a term has no declared price or owner (Proposition 1.1)","Emits the canonical form below") -> Emits the canonical form below
B12: =IF(LEFT($B$10,5)="Emits","maximize -("&F5&" l + "&F6&" phi) the package's cost in $ million, with its sign reversed","") -> maximize -(0.03 l + 8 phi) the package's cost in $ million, with its sign reversed
B13: =IF(LEFT($B$10,5)="Emits","over 0 <= l <= "&Line_max&" ($ million, "&E5&"), 0 <= phi <= "&Delay_max&" (quarters, "&E6&")","") -> over 0 <= l <= 400 ($ million, treasury), 0 <= phi <= 6 (quarters, transformation office)
B14: =IF(LEFT($B$10,5)="Emits","subject to x = f(l, phi): Volume I's Chapter 8 liquidity model, "&TEXT(Paths_N,"#,##0")&" paths","") -> subject to x = f(l, phi): Volume I's Chapter 8 liquidity model, 100,000 paths
B15: =IF(LEFT($B$10,5)="Emits"," P(liquidity below "&Floor_liq&" in some quarter) - "&F7&" <= 0 ("&E7&")","") -> P(liquidity below 350 in some quarter) - 0.05 <= 0 (the board)

Sheet Gates
A1: Run the gates (Theorem 1.5; Worked Example 1.1, Step 2; AXIOM Lab 2.1, step 2)
A3: Volume I's package: line ($ million) | B3: =Continuous!H6 -> 170
A4: Delay (quarters): the least that meets the appetite with that line | B4: =Continuous!H7 -> 0.66757636
A5: Depth of the trough with that delay | B5: =Depth0-Depth_q*B4 -> 25.329695
A7: Gate | B7: Test | C7: Value | D7: Limit | E7: Verdict
A8: (R1) declaration completeness | B8: Every term declared, with a price and an owner (CanonicalForm) | E8: =IF(LEFT(CanonicalForm!B10,5)="Emits","pass","FAIL") -> pass
A9: (R2) unified consistency | B9: Draw + closure buffer within the cash above the floor ($ million) | C9: =B16 -> 138.50134 | D9: =Pool -> 270 | E9: =IF(C9<=D9,"pass","FAIL") -> pass
A10: (R3) analytical panel | B10: Feedback core's spectral radius within the board's rule: halve within a year | C10: =SQRT(8*(Link^2+Link^2))/2 -> 0.8 | D10: =0.5^(1/4) -> 0.84089642 | E10: =IF(C10<=D10,"pass","FAIL") -> pass
A11: (R4) feasibility over the horizon | B11: Breach odds within the appetite (engine) | C11: =Continuous!H17 -> 0.05 | D11: =Appetite -> 0.05 | E11: =IF(AND(C11<=D11,C12<=D12),"pass","FAIL") -> pass
B12: Leverage with the line fully drawn, within the covenant | C12: =(Net_debt+B3)/Ebitda -> 3.7430186 | D12: =Covenant -> 4.5
A13: Four two-way links of strength e, and no Digital-Industrial link, give a spectral radius of sqrt(8(e^2 + e^2))/2 = 2e = 0.80 (Section 1.1).
A15: (R2) Volume I's joint check with the package
A16: Claims: deepest draw + closure buffer | B16: =B17+B18 -> 138.50134
A17: Deepest draw on the cash above the floor | B17: =Liq0-MIN(E32:E44) -> 121.63437
A18: Cash buffer for a 90th-percentile closure, net of the line | B18: =MAX(P90-B3,0) -> 16.866976
A20: The line removed from the decision inventory
A21: Claims: the draw and a full closure buffer | B21: =B17+P90 -> 308.50134
A22: Verdict | B22: =IF(B21<=Pool,"(R2) passes","(R2) fails") -> (R2) fails
A23: Minimal infeasible set: drop one commitment | B23: Owner | C23: Claims left | D23: Room | E23: The rest can hold?
A24: Program draw | B24: the transformation office | C24: =P90 -> 186.86698 | D24: =Pool -> 270 | E24: =IF(ISNUMBER(D24),IF(C24<=D24,"yes","no"),"yes") -> yes
A25: Closure buffer | B25: treasury | C25: =B17 -> 121.63437 | D25: =Pool -> 270 | E25: =IF(ISNUMBER(D25),IF(C25<=D25,"yes","no"),"yes") -> yes
A26: Floor | B26: the board | C26: =B21 -> 308.50134 | D26: no limit | E26: =IF(ISNUMBER(D26),IF(C26<=D26,"yes","no"),"yes") -> yes
A27: Named: every commitment whose removal lets the rest hold | C27: =IF(COUNTIF(E24:E26,"yes")=3,"program draw, closure buffer, floor","check") -> program draw, closure buffer, floor
A28: Volume I's declaration before its levers: claims | B28: =Liq0-MIN(F32:F44)+P90 -> 324.91659
A29: Short of the room by | B29: =B28-Pool -> 54.916594
A31: Quarter | B31: Years | C31: Plan without the trough | D31: Trough per point of depth | E31: Plan with the package's delay | F31: Plan as first declared (depth 28)
A32: 0 | B32: =A32/4 -> 0 | C32: =Per_point*(Plan_target-(Plan_target-Index0)*EXP(-Plan_rate*B32)) -> 620 | D32: =Per_point*(B32/Trough_tau)*EXP(1-B32/Trough_tau) -> 0 | E32: =C32-$B$5*D32 -> 620 | F32: =C32-Depth0*D32 -> 620
A33: 1 | B33: =A33/4 -> 0.25 | C33: =Per_point*(Plan_target-(Plan_target-Index0)*EXP(-Plan_rate*B33)) -> 626.23332 | D33: =Per_point*(B33/Trough_tau)*EXP(1-B33/Trough_tau) -> 1.8591284 | E33: =C33-$B$5*D33 -> 579.14216 | F33: =C33-Depth0*D33 -> 574.17772
A34: 2 | B34: =A34/4 -> 0.5 | C34: =Per_point*(Plan_target-(Plan_target-Index0)*EXP(-Plan_rate*B34)) -> 631.9444 | D34: =Per_point*(B34/Trough_tau)*EXP(1-B34/Trough_tau) -> 3.28135 | E34: =C34-$B$5*D34 -> 548.8288 | F34: =C34-Depth0*D34 -> 540.0666
A35: 3 | B35: =A35/4 -> 0.75 | C35: =Per_point*(Plan_target-(Plan_target-Index0)*EXP(-Plan_rate*B35)) -> 637.177 | D35: =Per_point*(B35/Trough_tau)*EXP(1-B35/Trough_tau) -> 4.3436719 | E35: =C35-$B$5*D35 -> 527.15312 | F35: =C35-Depth0*D35 -> 515.55419
A36: 4 | B36: =A36/4 -> 1 | C36: =Per_point*(Plan_target-(Plan_target-Index0)*EXP(-Plan_rate*B36)) -> 641.97121 | D36: =Per_point*(B36/Trough_tau)*EXP(1-B36/Trough_tau) -> 5.1110359 | E36: =C36-$B$5*D36 -> 512.51023 | F36: =C36-Depth0*D36 -> 498.8622
A37: 5 | B37: =A37/4 -> 1.25 | C37: =Per_point*(Plan_target-(Plan_target-Index0)*EXP(-Plan_rate*B37)) -> 646.36375 | D37: =Per_point*(B37/Trough_tau)*EXP(1-B37/Trough_tau) -> 5.6380917 | E37: =C37-$B$5*D37 -> 503.55261 | F37: =C37-Depth0*D37 -> 488.49718
A38: 6 | B38: =A38/4 -> 1.5 | C38: =Per_point*(Plan_target-(Plan_target-Index0)*EXP(-Plan_rate*B38)) -> 650.38828 | D38: =Per_point*(B38/Trough_tau)*EXP(1-B38/Trough_tau) -> 5.9707182 | E38: =C38-$B$5*D38 -> 499.15181 | F38: =C38-Depth0*D38 -> 483.20817
A39: 7 | B39: =A39/4 -> 1.75 | C39: =Per_point*(Plan_target-(Plan_target-Index0)*EXP(-Plan_rate*B39)) -> 654.07563 | D39: =Per_point*(B39/Trough_tau)*EXP(1-B39/Trough_tau) -> 6.1473304 | E39: =C39-$B$5*D39 -> 498.36563 | F39: =C39-Depth0*D39 -> 481.95038
A40: 8 | B40: =A40/4 -> 2 | C40: =Per_point*(Plan_target-(Plan_target-Index0)*EXP(-Plan_rate*B40)) -> 657.45405 | D40: =Per_point*(B40/Trough_tau)*EXP(1-B40/Trough_tau) -> 6.2 | E40: =C40-$B$5*D40 -> 500.40995 | F40: =C40-Depth0*D40 -> 483.85405
A41: 9 | B41: =A41/4 -> 2.25 | C41: =Per_point*(Plan_target-(Plan_target-Index0)*EXP(-Plan_rate*B41)) -> 660.54943 | D41: =Per_point*(B41/Trough_tau)*EXP(1-B41/Trough_tau) -> 6.1554159 | E41: =C41-$B$5*D41 -> 504.63462 | F41: =C41-Depth0*D41 -> 488.19778
A42: 10 | B42: =A42/4 -> 2.5 | C42: =Per_point*(Plan_target-(Plan_target-Index0)*EXP(-Plan_rate*B42)) -> 663.38547 | D42: =Per_point*(B42/Trough_tau)*EXP(1-B42/Trough_tau) -> 6.0357061 | E42: =C42-$B$5*D42 -> 510.50287 | F42: =C42-Depth0*D42 -> 494.3857
A43: 11 | B43: =A43/4 -> 2.75 | C43: =Per_point*(Plan_target-(Plan_target-Index0)*EXP(-Plan_rate*B43)) -> 665.9839 | D43: =Per_point*(B43/Trough_tau)*EXP(1-B43/Trough_tau) -> 5.8591411 | E43: =C43-$B$5*D43 -> 517.57364 | F43: =C43-Depth0*D43 -> 501.92795
A44: 12 | B44: =A44/4 -> 3 | C44: =Per_point*(Plan_target-(Plan_target-Index0)*EXP(-Plan_rate*B44)) -> 668.36463 | D44: =Per_point*(B44/Trough_tau)*EXP(1-B44/Trough_tau) -> 5.6407351 | E44: =C44-$B$5*D44 -> 525.48653 | F44: =C44-Depth0*D44 -> 510.42405

Sheet Continuous
A1: Solve with continuous levers (Theorem 1.2; Worked Example 1.1, Step 3)
A2: Column B is the engine's least delay that meets the appetite with each line on Volume I's $5 million grid: the 5 percent curve of Figure 1.4. The formulas price every point of the curve and find the cheapest.
B3: value of a quarter: | C3: =Vq -> 8 | D3: 4 | E3: 16
A4: Line ($ million) | B4: Least delay meeting the appetite (engine) | C4: Cost | D4: Cost | E4: Cost | G4: Best package | H4: At the declared value | I4: At $4m a quarter | J4: At $16m a quarter
A5: 0 | B5: 5.0946732 | C5: =Fee*$A5+C$3*$B5 -> 40.757385 | D5: =Fee*$A5+D$3*$B5 -> 20.378693 | E5: =Fee*$A5+E$3*$B5 -> 81.514771 | G5: Cheapest cost on the curve | H5: =MIN(C5:C85) -> 10.440611 | I5: =MIN(D5:D85) -> 7.5246248 | J5: =MIN(E5:E85) -> 15.512875
A6: =A5+5 -> 5 | B6: 4.8306695 | C6: =Fee*$A6+C$3*$B6 -> 38.795356 | D6: =Fee*$A6+D$3*$B6 -> 19.472678 | E6: =Fee*$A6+E$3*$B6 -> 77.440712 | G6: Its line ($ million) | H6: =INDEX($A$5:$A$85,MATCH(H5,C5:C85,0)) -> 170 | I6: =INDEX($A$5:$A$85,MATCH(I5,D5:D85,0)) -> 140 | J6: =INDEX($A$5:$A$85,MATCH(J5,E5:E85,0)) -> 195
A7: =A6+5 -> 10 | B7: 4.579809 | C7: =Fee*$A7+C$3*$B7 -> 36.938472 | D7: =Fee*$A7+D$3*$B7 -> 18.619236 | E7: =Fee*$A7+E$3*$B7 -> 73.576945 | G7: Its delay (quarters) | H7: =INDEX($B$5:$B$85,MATCH(H5,C5:C85,0)) -> 0.66757636 | I7: =INDEX($B$5:$B$85,MATCH(I5,D5:D85,0)) -> 0.8311562 | J7: =INDEX($B$5:$B$85,MATCH(J5,E5:E85,0)) -> 0.60392968
A8: =A7+5 -> 15 | B8: 4.3286508 | C8: =Fee*$A8+C$3*$B8 -> 35.079207 | D8: =Fee*$A8+D$3*$B8 -> 17.764603 | E8: =Fee*$A8+E$3*$B8 -> 69.708413 | G8: Its delay in months | H8: =3*H7 -> 2.0027291 | I8: =3*I7 -> 2.4934686 | J8: =3*J7 -> 1.8117891
A9: =A8+5 -> 20 | B9: 4.0686784 | C9: =Fee*$A9+C$3*$B9 -> 33.149427 | D9: =Fee*$A9+D$3*$B9 -> 16.874714 | E9: =Fee*$A9+E$3*$B9 -> 65.698854 | G9: Line fees | H9: =Fee*H6 -> 5.1 | I9: =Fee*I6 -> 4.2 | J9: =Fee*J6 -> 5.85
A10: =A9+5 -> 25 | B10: 3.8169899 | C10: =Fee*$A10+C$3*$B10 -> 31.28592 | D10: =Fee*$A10+D$3*$B10 -> 16.01796 | E10: =Fee*$A10+E$3*$B10 -> 61.821839 | G10: Cost of the delay | H10: =C3*H7 -> 5.3406109 | I10: =D3*I7 -> 3.3246248 | J10: =E3*J7 -> 9.6628749
A11: =A10+5 -> 30 | B11: 3.5787587 | C11: =Fee*$A11+C$3*$B11 -> 29.530069 | D11: =Fee*$A11+D$3*$B11 -> 15.215035 | E11: =Fee*$A11+E$3*$B11 -> 58.160139
A12: =A11+5 -> 35 | B12: 3.3470376 | C12: =Fee*$A12+C$3*$B12 -> 27.826301 | D12: =Fee*$A12+D$3*$B12 -> 14.43815 | E12: =Fee*$A12+E$3*$B12 -> 54.602602 | G12: Lines within $0.5 million of the best: from | H12: =_xlfn.MINIFS(A5:A85,C5:C85,"<="&(H5+0.5)) -> 140
A13: =A12+5 -> 40 | B13: 3.1066048 | C13: =Fee*$A13+C$3*$B13 -> 26.052838 | D13: =Fee*$A13+D$3*$B13 -> 13.626419 | E13: =Fee*$A13+E$3*$B13 -> 50.905677 | G13: to | H13: =_xlfn.MAXIFS(A5:A85,C5:C85,"<="&(H5+0.5)) -> 205
A14: =A13+5 -> 45 | B14: 2.9025087 | C14: =Fee*$A14+C$3*$B14 -> 24.57007 | D14: =Fee*$A14+D$3*$B14 -> 12.960035 | E14: =Fee*$A14+E$3*$B14 -> 47.79014 | G14: Delay alone: quarters (no line) | H14: =INDEX(B5:B85,MATCH(0,A5:A85,0)) -> 5.0946732
A15: =A14+5 -> 50 | B15: 2.7009762 | C15: =Fee*$A15+C$3*$B15 -> 23.107809 | D15: =Fee*$A15+D$3*$B15 -> 12.303905 | E15: =Fee*$A15+E$3*$B15 -> 44.715619 | G15: Delay alone: cost | H15: =Vq*H14 -> 40.757385
A16: =A15+5 -> 55 | B16: 2.5121212 | C16: =Fee*$A16+C$3*$B16 -> 21.74697 | D16: =Fee*$A16+D$3*$B16 -> 11.698485 | E16: =Fee*$A16+E$3*$B16 -> 41.84394 | G16: The line alone: lowest breach odds (engine, a $400m line) | H16: 0.08404
A17: =A16+5 -> 60 | B17: 2.3303361 | C17: =Fee*$A17+C$3*$B17 -> 20.442689 | D17: =Fee*$A17+D$3*$B17 -> 11.121344 | E17: =Fee*$A17+E$3*$B17 -> 39.085378 | G17: Breach odds of the best package (engine) | H17: 0.05
A18: =A17+5 -> 65 | B18: 2.1535969 | C18: =Fee*$A18+C$3*$B18 -> 19.178775 | D18: =Fee*$A18+D$3*$B18 -> 10.564388 | E18: =Fee*$A18+E$3*$B18 -> 36.407551 | G18: Reweighting moves the line by ($ million, $4m to $16m a quarter) | H18: =J6-I6 -> 55
A19: =A18+5 -> 70 | B19: 1.997326 | C19: =Fee*$A19+C$3*$B19 -> 18.078608 | D19: =Fee*$A19+D$3*$B19 -> 10.089304 | E19: =Fee*$A19+E$3*$B19 -> 34.057216
A20: =A19+5 -> 75 | B20: 1.8511258 | C20: =Fee*$A20+C$3*$B20 -> 17.059006 | D20: =Fee*$A20+D$3*$B20 -> 9.6545031 | E20: =Fee*$A20+E$3*$B20 -> 31.868012
A21: =A20+5 -> 80 | B21: 1.7187291 | C21: =Fee*$A21+C$3*$B21 -> 16.149832 | D21: =Fee*$A21+D$3*$B21 -> 9.2749162 | E21: =Fee*$A21+E$3*$B21 -> 29.899665
A22: =A21+5 -> 85 | B22: 1.5973554 | C22: =Fee*$A22+C$3*$B22 -> 15.328844 | D22: =Fee*$A22+D$3*$B22 -> 8.9394218 | E22: =Fee*$A22+E$3*$B22 -> 28.107687
A23: =A22+5 -> 90 | B23: 1.4819733 | C23: =Fee*$A23+C$3*$B23 -> 14.555787 | D23: =Fee*$A23+D$3*$B23 -> 8.6278933 | E23: =Fee*$A23+E$3*$B23 -> 26.411573
A24: =A23+5 -> 95 | B24: 1.3778721 | C24: =Fee*$A24+C$3*$B24 -> 13.872977 | D24: =Fee*$A24+D$3*$B24 -> 8.3614883 | E24: =Fee*$A24+E$3*$B24 -> 24.895953
A25: =A24+5 -> 100 | B25: 1.2871114 | C25: =Fee*$A25+C$3*$B25 -> 13.296891 | D25: =Fee*$A25+D$3*$B25 -> 8.1484455 | E25: =Fee*$A25+E$3*$B25 -> 23.593782
A26: =A25+5 -> 105 | B26: 1.2117094 | C26: =Fee*$A26+C$3*$B26 -> 12.843675 | D26: =Fee*$A26+D$3*$B26 -> 7.9968375 | E26: =Fee*$A26+E$3*$B26 -> 22.53735
A27: =A26+5 -> 110 | B27: 1.1254172 | C27: =Fee*$A27+C$3*$B27 -> 12.303337 | D27: =Fee*$A27+D$3*$B27 -> 7.8016687 | E27: =Fee*$A27+E$3*$B27 -> 21.306675
A28: =A27+5 -> 115 | B28: 1.0644007 | C28: =Fee*$A28+C$3*$B28 -> 11.965205 | D28: =Fee*$A28+D$3*$B28 -> 7.7076027 | E28: =Fee*$A28+E$3*$B28 -> 20.480411
A29: =A28+5 -> 120 | B29: 1.0037717 | C29: =Fee*$A29+C$3*$B29 -> 11.630174 | D29: =Fee*$A29+D$3*$B29 -> 7.6150869 | E29: =Fee*$A29+E$3*$B29 -> 19.660347
A30: =A29+5 -> 125 | B30: 0.95008855 | C30: =Fee*$A30+C$3*$B30 -> 11.350708 | D30: =Fee*$A30+D$3*$B30 -> 7.5503542 | E30: =Fee*$A30+E$3*$B30 -> 18.951417
... A85: =A84+5 -> 400 | B85: 0.55460771 | C85: =Fee*$A85+C$3*$B85 -> 16.436862 | D85: =Fee*$A85+D$3*$B85 -> 14.218431 | E85: =Fee*$A85+E$3*$B85 -> 20.873723

Sheet LumpyGrid
A1: Make the levers lumpy: 63 packages (Theorem 1.3; Worked Example 1.1, Step 4; AXIOM Lab 2.1, step 3)
A2: Every package of $50 million tranches (0 to 400) and whole quarters (0 to 6), with the engine's breach odds on the book's paths. Cost, feasibility, the cheapest feasible package and the roundings are formulas.
A4: Package | B4: Line ($ million) | C4: Delay (quarters) | D4: Breach odds (engine) | E4: Cost ($ million) | F4: Meets the appetite (1 = yes) | G4: Cheapest feasible (1 = yes) | I4: Summary | J4: Value
A5: 1 | B5: =Tranche*INT((A5-1)/7) -> 0 | C5: =MOD(A5-1,7) -> 0 | D5: 0.24622 | E5: =Fee*B5+Vq*C5 -> 0 | F5: =IF(D5<=Appetite,1,0) -> 0 | G5: =IF(AND(F5=1,ABS(E5-$J$7)<0.000000001),1,0) -> 0 | I5: Packages | J5: =COUNT(B5:B67) -> 63
A6: 2 | B6: =Tranche*INT((A6-1)/7) -> 0 | C6: =MOD(A6-1,7) -> 1 | D6: 0.17731 | E6: =Fee*B6+Vq*C6 -> 8 | F6: =IF(D6<=Appetite,1,0) -> 0 | G6: =IF(AND(F6=1,ABS(E6-$J$7)<0.000000001),1,0) -> 0 | I6: Packages that meet the appetite | J6: =SUM(F5:F67) -> 46
A7: 3 | B7: =Tranche*INT((A7-1)/7) -> 0 | C7: =MOD(A7-1,7) -> 2 | D7: 0.13068 | E7: =Fee*B7+Vq*C7 -> 16 | F7: =IF(D7<=Appetite,1,0) -> 0 | G7: =IF(AND(F7=1,ABS(E7-$J$7)<0.000000001),1,0) -> 0 | I7: Cheapest that meets it: cost | J7: =_xlfn.MINIFS(E5:E67,F5:F67,1) -> 12.5
A8: 4 | B8: =Tranche*INT((A8-1)/7) -> 0 | C8: =MOD(A8-1,7) -> 3 | D8: 0.09687 | E8: =Fee*B8+Vq*C8 -> 24 | F8: =IF(D8<=Appetite,1,0) -> 0 | G8: =IF(AND(F8=1,ABS(E8-$J$7)<0.000000001),1,0) -> 0 | I8: its line ($ million) | J8: =INDEX(B5:B67,MATCH(1,G5:G67,0)) -> 150
A9: 5 | B9: =Tranche*INT((A9-1)/7) -> 0 | C9: =MOD(A9-1,7) -> 4 | D9: 0.07118 | E9: =Fee*B9+Vq*C9 -> 32 | F9: =IF(D9<=Appetite,1,0) -> 0 | G9: =IF(AND(F9=1,ABS(E9-$J$7)<0.000000001),1,0) -> 0 | I9: its delay (quarters) | J9: =INDEX(C5:C67,MATCH(1,G5:G67,0)) -> 1
A10: 6 | B10: =Tranche*INT((A10-1)/7) -> 0 | C10: =MOD(A10-1,7) -> 5 | D10: 0.05167 | E10: =Fee*B10+Vq*C10 -> 40 | F10: =IF(D10<=Appetite,1,0) -> 0 | G10: =IF(AND(F10=1,ABS(E10-$J$7)<0.000000001),1,0) -> 0 | I10: its breach odds | J10: =INDEX(D5:D67,MATCH(1,G5:G67,0)) -> 0.04003
A11: 7 | B11: =Tranche*INT((A11-1)/7) -> 0 | C11: =MOD(A11-1,7) -> 6 | D11: 0.03668 | E11: =Fee*B11+Vq*C11 -> 48 | F11: =IF(D11<=Appetite,1,0) -> 1 | G11: =IF(AND(F11=1,ABS(E11-$J$7)<0.000000001),1,0) -> 0
A12: 8 | B12: =Tranche*INT((A12-1)/7) -> 50 | C12: =MOD(A12-1,7) -> 0 | D12: 0.18073 | E12: =Fee*B12+Vq*C12 -> 1.5 | F12: =IF(D12<=Appetite,1,0) -> 0 | G12: =IF(AND(F12=1,ABS(E12-$J$7)<0.000000001),1,0) -> 0 | I12: Continuous best: line | J12: =Continuous!H6 -> 170
A13: 9 | B13: =Tranche*INT((A13-1)/7) -> 50 | C13: =MOD(A13-1,7) -> 1 | D13: 0.11089 | E13: =Fee*B13+Vq*C13 -> 9.5 | F13: =IF(D13<=Appetite,1,0) -> 0 | G13: =IF(AND(F13=1,ABS(E13-$J$7)<0.000000001),1,0) -> 0 | I13: Continuous best: delay | J13: =Continuous!H7 -> 0.66757636
A14: 10 | B14: =Tranche*INT((A14-1)/7) -> 50 | C14: =MOD(A14-1,7) -> 2 | D14: 0.06903 | E14: =Fee*B14+Vq*C14 -> 17.5 | F14: =IF(D14<=Appetite,1,0) -> 0 | G14: =IF(AND(F14=1,ABS(E14-$J$7)<0.000000001),1,0) -> 0 | I14: Continuous best: cost | J14: =Continuous!H5 -> 10.440611
A15: 11 | B15: =Tranche*INT((A15-1)/7) -> 50 | C15: =MOD(A15-1,7) -> 3 | D15: 0.04392 | E15: =Fee*B15+Vq*C15 -> 25.5 | F15: =IF(D15<=Appetite,1,0) -> 1 | G15: =IF(AND(F15=1,ABS(E15-$J$7)<0.000000001),1,0) -> 0
A16: 12 | B16: =Tranche*INT((A16-1)/7) -> 50 | C16: =MOD(A16-1,7) -> 4 | D16: 0.02801 | E16: =Fee*B16+Vq*C16 -> 33.5 | F16: =IF(D16<=Appetite,1,0) -> 1 | G16: =IF(AND(F16=1,ABS(E16-$J$7)<0.000000001),1,0) -> 0 | I16: Rounded down: line | J16: =INT(J12/Tranche)*Tranche -> 150
A17: 13 | B17: =Tranche*INT((A17-1)/7) -> 50 | C17: =MOD(A17-1,7) -> 5 | D17: 0.01772 | E17: =Fee*B17+Vq*C17 -> 41.5 | F17: =IF(D17<=Appetite,1,0) -> 1 | G17: =IF(AND(F17=1,ABS(E17-$J$7)<0.000000001),1,0) -> 0 | I17: Rounded down: delay | J17: =INT(J13) -> 0
A18: 14 | B18: =Tranche*INT((A18-1)/7) -> 50 | C18: =MOD(A18-1,7) -> 6 | D18: 0.01098 | E18: =Fee*B18+Vq*C18 -> 49.5 | F18: =IF(D18<=Appetite,1,0) -> 1 | G18: =IF(AND(F18=1,ABS(E18-$J$7)<0.000000001),1,0) -> 0 | I18: Rounded down: breach odds | J18: =SUMIFS(D5:D67,B5:B67,J16,C5:C67,J17) -> 0.09587
A19: 15 | B19: =Tranche*INT((A19-1)/7) -> 100 | C19: =MOD(A19-1,7) -> 0 | D19: 0.12374 | E19: =Fee*B19+Vq*C19 -> 3 | F19: =IF(D19<=Appetite,1,0) -> 0 | G19: =IF(AND(F19=1,ABS(E19-$J$7)<0.000000001),1,0) -> 0 | I19: Rounded down: cost | J19: =Fee*J16+Vq*J17 -> 4.5
A20: 16 | B20: =Tranche*INT((A20-1)/7) -> 100 | C20: =MOD(A20-1,7) -> 1 | D20: 0.06165 | E20: =Fee*B20+Vq*C20 -> 11 | F20: =IF(D20<=Appetite,1,0) -> 0 | G20: =IF(AND(F20=1,ABS(E20-$J$7)<0.000000001),1,0) -> 0 | I20: Rounded down: meets the appetite? | J20: =IF(J18<=Appetite,"yes","no: it fails") -> no: it fails
A21: 17 | B21: =Tranche*INT((A21-1)/7) -> 100 | C21: =MOD(A21-1,7) -> 2 | D21: 0.03003 | E21: =Fee*B21+Vq*C21 -> 19 | F21: =IF(D21<=Appetite,1,0) -> 1 | G21: =IF(AND(F21=1,ABS(E21-$J$7)<0.000000001),1,0) -> 0
A22: 18 | B22: =Tranche*INT((A22-1)/7) -> 100 | C22: =MOD(A22-1,7) -> 3 | D22: 0.01517 | E22: =Fee*B22+Vq*C22 -> 27 | F22: =IF(D22<=Appetite,1,0) -> 1 | G22: =IF(AND(F22=1,ABS(E22-$J$7)<0.000000001),1,0) -> 0 | I22: Rounded up: line | J22: =-INT(-J12/Tranche)*Tranche -> 200
A23: 19 | B23: =Tranche*INT((A23-1)/7) -> 100 | C23: =MOD(A23-1,7) -> 4 | D23: 0.00778 | E23: =Fee*B23+Vq*C23 -> 35 | F23: =IF(D23<=Appetite,1,0) -> 1 | G23: =IF(AND(F23=1,ABS(E23-$J$7)<0.000000001),1,0) -> 0 | I23: Rounded up: delay | J23: =-INT(-J13) -> 1
A24: 20 | B24: =Tranche*INT((A24-1)/7) -> 100 | C24: =MOD(A24-1,7) -> 5 | D24: 0.00421 | E24: =Fee*B24+Vq*C24 -> 43 | F24: =IF(D24<=Appetite,1,0) -> 1 | G24: =IF(AND(F24=1,ABS(E24-$J$7)<0.000000001),1,0) -> 0 | I24: Rounded up: breach odds | J24: =SUMIFS(D5:D67,B5:B67,J22,C5:C67,J23) -> 0.03386
A25: 21 | B25: =Tranche*INT((A25-1)/7) -> 100 | C25: =MOD(A25-1,7) -> 6 | D25: 0.00233 | E25: =Fee*B25+Vq*C25 -> 51 | F25: =IF(D25<=Appetite,1,0) -> 1 | G25: =IF(AND(F25=1,ABS(E25-$J$7)<0.000000001),1,0) -> 0 | I25: Rounded up: cost | J25: =Fee*J22+Vq*J23 -> 14
A26: 22 | B26: =Tranche*INT((A26-1)/7) -> 150 | C26: =MOD(A26-1,7) -> 0 | D26: 0.09587 | E26: =Fee*B26+Vq*C26 -> 4.5 | F26: =IF(D26<=Appetite,1,0) -> 0 | G26: =IF(AND(F26=1,ABS(E26-$J$7)<0.000000001),1,0) -> 0 | I26: Rounded up: meets the appetite? | J26: =IF(J24<=Appetite,"yes","no: it fails") -> yes
A27: 23 | B27: =Tranche*INT((A27-1)/7) -> 150 | C27: =MOD(A27-1,7) -> 1 | D27: 0.04003 | E27: =Fee*B27+Vq*C27 -> 12.5 | F27: =IF(D27<=Appetite,1,0) -> 1 | G27: =IF(AND(F27=1,ABS(E27-$J$7)<0.000000001),1,0) -> 1
A28: 24 | B28: =Tranche*INT((A28-1)/7) -> 150 | C28: =MOD(A28-1,7) -> 2 | D28: 0.01548 | E28: =Fee*B28+Vq*C28 -> 20.5 | F28: =IF(D28<=Appetite,1,0) -> 1 | G28: =IF(AND(F28=1,ABS(E28-$J$7)<0.000000001),1,0) -> 0 | I28: The lumps cost (cheapest lumpy less the continuous floor) | J28: =J7-J14 -> 2.0593891
A29: 25 | B29: =Tranche*INT((A29-1)/7) -> 150 | C29: =MOD(A29-1,7) -> 3 | D29: 0.00574 | E29: =Fee*B29+Vq*C29 -> 28.5 | F29: =IF(D29<=Appetite,1,0) -> 1 | G29: =IF(AND(F29=1,ABS(E29-$J$7)<0.000000001),1,0) -> 0 | I29: as a share of the continuous cost | J29: =J28/J14 -> 0.19724795
A30: 26 | B30: =Tranche*INT((A30-1)/7) -> 150 | C30: =MOD(A30-1,7) -> 4 | D30: 0.00236 | E30: =Fee*B30+Vq*C30 -> 36.5 | F30: =IF(D30<=Appetite,1,0) -> 1 | G30: =IF(AND(F30=1,ABS(E30-$J$7)<0.000000001),1,0) -> 0
A31: 27 | B31: =Tranche*INT((A31-1)/7) -> 150 | C31: =MOD(A31-1,7) -> 5 | D31: 0.00096 | E31: =Fee*B31+Vq*C31 -> 44.5 | F31: =IF(D31<=Appetite,1,0) -> 1 | G31: =IF(AND(F31=1,ABS(E31-$J$7)<0.000000001),1,0) -> 0 | I31: Convexity: is the midpoint of the best and the rounded-up package a package? | J31: =IF(MOD((J8+J22)/2,Tranche)=0,"yes","no: the lattice is not convex") -> no: the lattice is not convex
A32: 28 | B32: =Tranche*INT((A32-1)/7) -> 150 | C32: =MOD(A32-1,7) -> 6 | D32: 0.00038 | E32: =Fee*B32+Vq*C32 -> 52.5 | F32: =IF(D32<=Appetite,1,0) -> 1 | G32: =IF(AND(F32=1,ABS(E32-$J$7)<0.000000001),1,0) -> 0 | I32: Forty yes-or-no choices: combinations | J32: =2^40 -> 1099511627776
A33: 29 | B33: =Tranche*INT((A33-1)/7) -> 200 | C33: =MOD(A33-1,7) -> 0 | D33: 0.08674 | E33: =Fee*B33+Vq*C33 -> 6 | F33: =IF(D33<=Appetite,1,0) -> 0 | G33: =IF(AND(F33=1,ABS(E33-$J$7)<0.000000001),1,0) -> 0
A34: 30 | B34: =Tranche*INT((A34-1)/7) -> 200 | C34: =MOD(A34-1,7) -> 1 | D34: 0.03386 | E34: =Fee*B34+Vq*C34 -> 14 | F34: =IF(D34<=Appetite,1,0) -> 1 | G34: =IF(AND(F34=1,ABS(E34-$J$7)<0.000000001),1,0) -> 0
A35: 31 | B35: =Tranche*INT((A35-1)/7) -> 200 | C35: =MOD(A35-1,7) -> 2 | D35: 0.01165 | E35: =Fee*B35+Vq*C35 -> 22 | F35: =IF(D35<=Appetite,1,0) -> 1 | G35: =IF(AND(F35=1,ABS(E35-$J$7)<0.000000001),1,0) -> 0
A36: 32 | B36: =Tranche*INT((A36-1)/7) -> 200 | C36: =MOD(A36-1,7) -> 3 | D36: 0.00348 | E36: =Fee*B36+Vq*C36 -> 30 | F36: =IF(D36<=Appetite,1,0) -> 1 | G36: =IF(AND(F36=1,ABS(E36-$J$7)<0.000000001),1,0) -> 0
A37: 33 | B37: =Tranche*INT((A37-1)/7) -> 200 | C37: =MOD(A37-1,7) -> 4 | D37: 0.00105 | E37: =Fee*B37+Vq*C37 -> 38 | F37: =IF(D37<=Appetite,1,0) -> 1 | G37: =IF(AND(F37=1,ABS(E37-$J$7)<0.000000001),1,0) -> 0
A38: 34 | B38: =Tranche*INT((A38-1)/7) -> 200 | C38: =MOD(A38-1,7) -> 5 | D38: 0.00031 | E38: =Fee*B38+Vq*C38 -> 46 | F38: =IF(D38<=Appetite,1,0) -> 1 | G38: =IF(AND(F38=1,ABS(E38-$J$7)<0.000000001),1,0) -> 0
A39: 35 | B39: =Tranche*INT((A39-1)/7) -> 200 | C39: =MOD(A39-1,7) -> 6 | D39: 7e-05 | E39: =Fee*B39+Vq*C39 -> 54 | F39: =IF(D39<=Appetite,1,0) -> 1 | G39: =IF(AND(F39=1,ABS(E39-$J$7)<0.000000001),1,0) -> 0
A40: 36 | B40: =Tranche*INT((A40-1)/7) -> 250 | C40: =MOD(A40-1,7) -> 0 | D40: 0.08461 | E40: =Fee*B40+Vq*C40 -> 7.5 | F40: =IF(D40<=Appetite,1,0) -> 0 | G40: =IF(AND(F40=1,ABS(E40-$J$7)<0.000000001),1,0) -> 0
A41: 37 | B41: =Tranche*INT((A41-1)/7) -> 250 | C41: =MOD(A41-1,7) -> 1 | D41: 0.03241 | E41: =Fee*B41+Vq*C41 -> 15.5 | F41: =IF(D41<=Appetite,1,0) -> 1 | G41: =IF(AND(F41=1,ABS(E41-$J$7)<0.000000001),1,0) -> 0
A42: 38 | B42: =Tranche*INT((A42-1)/7) -> 250 | C42: =MOD(A42-1,7) -> 2 | D42: 0.01068 | E42: =Fee*B42+Vq*C42 -> 23.5 | F42: =IF(D42<=Appetite,1,0) -> 1 | G42: =IF(AND(F42=1,ABS(E42-$J$7)<0.000000001),1,0) -> 0
A43: 39 | B43: =Tranche*INT((A43-1)/7) -> 250 | C43: =MOD(A43-1,7) -> 3 | D43: 0.00301 | E43: =Fee*B43+Vq*C43 -> 31.5 | F43: =IF(D43<=Appetite,1,0) -> 1 | G43: =IF(AND(F43=1,ABS(E43-$J$7)<0.000000001),1,0) -> 0
A44: 40 | B44: =Tranche*INT((A44-1)/7) -> 250 | C44: =MOD(A44-1,7) -> 4 | D44: 0.0008 | E44: =Fee*B44+Vq*C44 -> 39.5 | F44: =IF(D44<=Appetite,1,0) -> 1 | G44: =IF(AND(F44=1,ABS(E44-$J$7)<0.000000001),1,0) -> 0
... A67: 63 | B67: =Tranche*INT((A67-1)/7) -> 400 | C67: =MOD(A67-1,7) -> 6 | D67: 1e-05 | E67: =Fee*B67+Vq*C67 -> 60 | F67: =IF(D67<=Appetite,1,0) -> 1 | G67: =IF(AND(F67=1,ABS(E67-$J$7)<0.000000001),1,0) -> 0
A70: Breach odds by line (down) and quarters of delay (across); shaded where the package meets the appetite
A71: Line | B71: 0 | C71: 1 | D71: 2 | E71: 3 | F71: 4 | G71: 5 | H71: 6
A72: =Tranche*0 -> 0 | B72: =SUMIFS(D5:D67,B5:B67,$A72,C5:C67,B$71) -> 0.24622 | C72: =SUMIFS(D5:D67,B5:B67,$A72,C5:C67,C$71) -> 0.17731 | D72: =SUMIFS(D5:D67,B5:B67,$A72,C5:C67,D$71) -> 0.13068 | E72: =SUMIFS(D5:D67,B5:B67,$A72,C5:C67,E$71) -> 0.09687 | F72: =SUMIFS(D5:D67,B5:B67,$A72,C5:C67,F$71) -> 0.07118 | G72: =SUMIFS(D5:D67,B5:B67,$A72,C5:C67,G$71) -> 0.05167 | H72: =SUMIFS(D5:D67,B5:B67,$A72,C5:C67,H$71) -> 0.03668
A73: =Tranche*1 -> 50 | B73: =SUMIFS(D5:D67,B5:B67,$A73,C5:C67,B$71) -> 0.18073 | C73: =SUMIFS(D5:D67,B5:B67,$A73,C5:C67,C$71) -> 0.11089 | D73: =SUMIFS(D5:D67,B5:B67,$A73,C5:C67,D$71) -> 0.06903 | E73: =SUMIFS(D5:D67,B5:B67,$A73,C5:C67,E$71) -> 0.04392 | F73: =SUMIFS(D5:D67,B5:B67,$A73,C5:C67,F$71) -> 0.02801 | G73: =SUMIFS(D5:D67,B5:B67,$A73,C5:C67,G$71) -> 0.01772 | H73: =SUMIFS(D5:D67,B5:B67,$A73,C5:C67,H$71) -> 0.01098
A74: =Tranche*2 -> 100 | B74: =SUMIFS(D5:D67,B5:B67,$A74,C5:C67,B$71) -> 0.12374 | C74: =SUMIFS(D5:D67,B5:B67,$A74,C5:C67,C$71) -> 0.06165 | D74: =SUMIFS(D5:D67,B5:B67,$A74,C5:C67,D$71) -> 0.03003 | E74: =SUMIFS(D5:D67,B5:B67,$A74,C5:C67,E$71) -> 0.01517 | F74: =SUMIFS(D5:D67,B5:B67,$A74,C5:C67,F$71) -> 0.00778 | G74: =SUMIFS(D5:D67,B5:B67,$A74,C5:C67,G$71) -> 0.00421 | H74: =SUMIFS(D5:D67,B5:B67,$A74,C5:C67,H$71) -> 0.00233
A75: =Tranche*3 -> 150 | B75: =SUMIFS(D5:D67,B5:B67,$A75,C5:C67,B$71) -> 0.09587 | C75: =SUMIFS(D5:D67,B5:B67,$A75,C5:C67,C$71) -> 0.04003 | D75: =SUMIFS(D5:D67,B5:B67,$A75,C5:C67,D$71) -> 0.01548 | E75: =SUMIFS(D5:D67,B5:B67,$A75,C5:C67,E$71) -> 0.00574 | F75: =SUMIFS(D5:D67,B5:B67,$A75,C5:C67,F$71) -> 0.00236 | G75: =SUMIFS(D5:D67,B5:B67,$A75,C5:C67,G$71) -> 0.00096 | H75: =SUMIFS(D5:D67,B5:B67,$A75,C5:C67,H$71) -> 0.00038
A76: =Tranche*4 -> 200 | B76: =SUMIFS(D5:D67,B5:B67,$A76,C5:C67,B$71) -> 0.08674 | C76: =SUMIFS(D5:D67,B5:B67,$A76,C5:C67,C$71) -> 0.03386 | D76: =SUMIFS(D5:D67,B5:B67,$A76,C5:C67,D$71) -> 0.01165 | E76: =SUMIFS(D5:D67,B5:B67,$A76,C5:C67,E$71) -> 0.00348 | F76: =SUMIFS(D5:D67,B5:B67,$A76,C5:C67,F$71) -> 0.00105 | G76: =SUMIFS(D5:D67,B5:B67,$A76,C5:C67,G$71) -> 0.00031 | H76: =SUMIFS(D5:D67,B5:B67,$A76,C5:C67,H$71) -> 7e-05
A77: =Tranche*5 -> 250 | B77: =SUMIFS(D5:D67,B5:B67,$A77,C5:C67,B$71) -> 0.08461 | C77: =SUMIFS(D5:D67,B5:B67,$A77,C5:C67,C$71) -> 0.03241 | D77: =SUMIFS(D5:D67,B5:B67,$A77,C5:C67,D$71) -> 0.01068 | E77: =SUMIFS(D5:D67,B5:B67,$A77,C5:C67,E$71) -> 0.00301 | F77: =SUMIFS(D5:D67,B5:B67,$A77,C5:C67,F$71) -> 0.0008 | G77: =SUMIFS(D5:D67,B5:B67,$A77,C5:C67,G$71) -> 0.00018 | H77: =SUMIFS(D5:D67,B5:B67,$A77,C5:C67,H$71) -> 3e-05
A78: =Tranche*6 -> 300 | B78: =SUMIFS(D5:D67,B5:B67,$A78,C5:C67,B$71) -> 0.08414 | C78: =SUMIFS(D5:D67,B5:B67,$A78,C5:C67,C$71) -> 0.03214 | D78: =SUMIFS(D5:D67,B5:B67,$A78,C5:C67,D$71) -> 0.01049 | E78: =SUMIFS(D5:D67,B5:B67,$A78,C5:C67,E$71) -> 0.0029 | F78: =SUMIFS(D5:D67,B5:B67,$A78,C5:C67,F$71) -> 0.00077 | G78: =SUMIFS(D5:D67,B5:B67,$A78,C5:C67,G$71) -> 0.00017 | H78: =SUMIFS(D5:D67,B5:B67,$A78,C5:C67,H$71) -> 2e-05
A79: =Tranche*7 -> 350 | B79: =SUMIFS(D5:D67,B5:B67,$A79,C5:C67,B$71) -> 0.08406 | C79: =SUMIFS(D5:D67,B5:B67,$A79,C5:C67,C$71) -> 0.03207 | D79: =SUMIFS(D5:D67,B5:B67,$A79,C5:C67,D$71) -> 0.01047 | E79: =SUMIFS(D5:D67,B5:B67,$A79,C5:C67,E$71) -> 0.00289 | F79: =SUMIFS(D5:D67,B5:B67,$A79,C5:C67,F$71) -> 0.00076 | G79: =SUMIFS(D5:D67,B5:B67,$A79,C5:C67,G$71) -> 0.00016 | H79: =SUMIFS(D5:D67,B5:B67,$A79,C5:C67,H$71) -> 1e-05
A80: =Tranche*8 -> 400 | B80: =SUMIFS(D5:D67,B5:B67,$A80,C5:C67,B$71) -> 0.08404 | C80: =SUMIFS(D5:D67,B5:B67,$A80,C5:C67,C$71) -> 0.03206 | D80: =SUMIFS(D5:D67,B5:B67,$A80,C5:C67,D$71) -> 0.01046 | E80: =SUMIFS(D5:D67,B5:B67,$A80,C5:C67,E$71) -> 0.00288 | F80: =SUMIFS(D5:D67,B5:B67,$A80,C5:C67,F$71) -> 0.00075 | G80: =SUMIFS(D5:D67,B5:B67,$A80,C5:C67,G$71) -> 0.00016 | H80: =SUMIFS(D5:D67,B5:B67,$A80,C5:C67,H$71) -> 1e-05

Sheet FinerLines
A1: The least line for each whole number of quarters (Online Appendix 1.B.4) and Table 1.3
A2: Lines in $1 million steps and in $10 million tranches: the engine's least line meeting the appetite (and its odds). $50 million tranches: formulas on LumpyGrid. Costs at the declared prices.
A4: Delay (quarters) | B4: Line, $1m steps (engine) | C4: Odds (engine) | D4: Cost | E4: Line, $10m tranches (engine) | F4: Odds (engine) | G4: Cost | H4: Line, $50m tranches | I4: Odds | J4: Cost
A5: 0 | B5: none | D5: =IF(ISNUMBER(B5),Fee*B5+Vq*A5,"") | E5: none | G5: =IF(ISNUMBER(E5),Fee*E5+Vq*A5,"") | H5: =IF(COUNTIFS(LumpyGrid!$C$5:$C$67,A5,LumpyGrid!$F$5:$F$67,1)=0,"none",_xlfn.MINIFS(LumpyGrid!$B$5:$B$67,LumpyGrid!$C$5:$C$67,A5,LumpyGrid!$F$5:$F$67,1)) -> none | I5: =IF(ISNUMBER(H5),SUMIFS(LumpyGrid!$D$5:$D$67,LumpyGrid!$B$5:$B$67,H5,LumpyGrid!$C$5:$C$67,A5),"") | J5: =IF(ISNUMBER(H5),Fee*H5+Vq*A5,"")
A6: 1 | B6: 121 | C6: 0.04968 | D6: =IF(ISNUMBER(B6),Fee*B6+Vq*A6,"") -> 11.63 | E6: 130 | F6: 0.0463 | G6: =IF(ISNUMBER(E6),Fee*E6+Vq*A6,"") -> 11.9 | H6: =IF(COUNTIFS(LumpyGrid!$C$5:$C$67,A6,LumpyGrid!$F$5:$F$67,1)=0,"none",_xlfn.MINIFS(LumpyGrid!$B$5:$B$67,LumpyGrid!$C$5:$C$67,A6,LumpyGrid!$F$5:$F$67,1)) -> 150 | I6: =IF(ISNUMBER(H6),SUMIFS(LumpyGrid!$D$5:$D$67,LumpyGrid!$B$5:$B$67,H6,LumpyGrid!$C$5:$C$67,A6),"") -> 0.04003 | J6: =IF(ISNUMBER(H6),Fee*H6+Vq*A6,"") -> 12.5
A7: 2 | B7: 70 | C7: 0.04989 | D7: =IF(ISNUMBER(B7),Fee*B7+Vq*A7,"") -> 18.1 | E7: 70 | F7: 0.04989 | G7: =IF(ISNUMBER(E7),Fee*E7+Vq*A7,"") -> 18.1 | H7: =IF(COUNTIFS(LumpyGrid!$C$5:$C$67,A7,LumpyGrid!$F$5:$F$67,1)=0,"none",_xlfn.MINIFS(LumpyGrid!$B$5:$B$67,LumpyGrid!$C$5:$C$67,A7,LumpyGrid!$F$5:$F$67,1)) -> 100 | I7: =IF(ISNUMBER(H7),SUMIFS(LumpyGrid!$D$5:$D$67,LumpyGrid!$B$5:$B$67,H7,LumpyGrid!$C$5:$C$67,A7),"") -> 0.03003 | J7: =IF(ISNUMBER(H7),Fee*H7+Vq*A7,"") -> 19
A8: 3 | B8: 43 | C8: 0.04982 | D8: =IF(ISNUMBER(B8),Fee*B8+Vq*A8,"") -> 25.29 | E8: 50 | F8: 0.04392 | G8: =IF(ISNUMBER(E8),Fee*E8+Vq*A8,"") -> 25.5 | H8: =IF(COUNTIFS(LumpyGrid!$C$5:$C$67,A8,LumpyGrid!$F$5:$F$67,1)=0,"none",_xlfn.MINIFS(LumpyGrid!$B$5:$B$67,LumpyGrid!$C$5:$C$67,A8,LumpyGrid!$F$5:$F$67,1)) -> 50 | I8: =IF(ISNUMBER(H8),SUMIFS(LumpyGrid!$D$5:$D$67,LumpyGrid!$B$5:$B$67,H8,LumpyGrid!$C$5:$C$67,A8),"") -> 0.04392 | J8: =IF(ISNUMBER(H8),Fee*H8+Vq*A8,"") -> 25.5
A9: 4 | B9: 22 | C9: 0.04946 | D9: =IF(ISNUMBER(B9),Fee*B9+Vq*A9,"") -> 32.66 | E9: 30 | F9: 0.04262 | G9: =IF(ISNUMBER(E9),Fee*E9+Vq*A9,"") -> 32.9 | H9: =IF(COUNTIFS(LumpyGrid!$C$5:$C$67,A9,LumpyGrid!$F$5:$F$67,1)=0,"none",_xlfn.MINIFS(LumpyGrid!$B$5:$B$67,LumpyGrid!$C$5:$C$67,A9,LumpyGrid!$F$5:$F$67,1)) -> 50 | I9: =IF(ISNUMBER(H9),SUMIFS(LumpyGrid!$D$5:$D$67,LumpyGrid!$B$5:$B$67,H9,LumpyGrid!$C$5:$C$67,A9),"") -> 0.02801 | J9: =IF(ISNUMBER(H9),Fee*H9+Vq*A9,"") -> 33.5
A10: 5 | B10: 2 | C10: 0.04988 | D10: =IF(ISNUMBER(B10),Fee*B10+Vq*A10,"") -> 40.06 | E10: 10 | F10: 0.04311 | G10: =IF(ISNUMBER(E10),Fee*E10+Vq*A10,"") -> 40.3 | H10: =IF(COUNTIFS(LumpyGrid!$C$5:$C$67,A10,LumpyGrid!$F$5:$F$67,1)=0,"none",_xlfn.MINIFS(LumpyGrid!$B$5:$B$67,LumpyGrid!$C$5:$C$67,A10,LumpyGrid!$F$5:$F$67,1)) -> 50 | I10: =IF(ISNUMBER(H10),SUMIFS(LumpyGrid!$D$5:$D$67,LumpyGrid!$B$5:$B$67,H10,LumpyGrid!$C$5:$C$67,A10),"") -> 0.01772 | J10: =IF(ISNUMBER(H10),Fee*H10+Vq*A10,"") -> 41.5
A11: 6 | B11: 0 | C11: 0.03668 | D11: =IF(ISNUMBER(B11),Fee*B11+Vq*A11,"") -> 48 | E11: 0 | F11: 0.03668 | G11: =IF(ISNUMBER(E11),Fee*E11+Vq*A11,"") -> 48 | H11: =IF(COUNTIFS(LumpyGrid!$C$5:$C$67,A11,LumpyGrid!$F$5:$F$67,1)=0,"none",_xlfn.MINIFS(LumpyGrid!$B$5:$B$67,LumpyGrid!$C$5:$C$67,A11,LumpyGrid!$F$5:$F$67,1)) -> 0 | I11: =IF(ISNUMBER(H11),SUMIFS(LumpyGrid!$D$5:$D$67,LumpyGrid!$B$5:$B$67,H11,LumpyGrid!$C$5:$C$67,A11),"") -> 0.03668 | J11: =IF(ISNUMBER(H11),Fee*H11+Vq*A11,"") -> 48
A13: Table 1.3: package | B13: Line ($ million) | C13: Delay (quarters) | D13: Breach odds | E13: Cost ($ million)
A14: Continuous levers (Volume I) | B14: =Continuous!H6 -> 170 | C14: =Continuous!H7 -> 0.66757636 | D14: =Continuous!H17 -> 0.05 | E14: =Continuous!H5 -> 10.440611
A15: Whole quarters, line to the $1 million | B15: =INDEX(B5:B11,MATCH(MIN(D5:D11),D5:D11,0)) -> 121 | C15: =INDEX(A5:A11,MATCH(MIN(D5:D11),D5:D11,0)) -> 1 | D15: =INDEX(C5:C11,MATCH(MIN(D5:D11),D5:D11,0)) -> 0.04968 | E15: =MIN(D5:D11) -> 11.63
A16: Whole quarters, $10 million tranches | B16: =INDEX(E5:E11,MATCH(MIN(G5:G11),G5:G11,0)) -> 130 | C16: =INDEX(A5:A11,MATCH(MIN(G5:G11),G5:G11,0)) -> 1 | D16: =INDEX(F5:F11,MATCH(MIN(G5:G11),G5:G11,0)) -> 0.0463 | E16: =MIN(G5:G11) -> 11.9
A17: Whole quarters, $50 million tranches | B17: =INDEX(H5:H11,MATCH(MIN(J5:J11),J5:J11,0)) -> 150 | C17: =INDEX(A5:A11,MATCH(MIN(J5:J11),J5:J11,0)) -> 1 | D17: =INDEX(I5:I11,MATCH(MIN(J5:J11),J5:J11,0)) -> 0.04003 | E17: =MIN(J5:J11) -> 12.5
A18: Rounded down (fails the appetite) | B18: =LumpyGrid!J16 -> 150 | C18: =LumpyGrid!J17 -> 0 | D18: =LumpyGrid!J18 -> 0.09587 | E18: =LumpyGrid!J19 -> 4.5
A19: Rounded up | B19: =LumpyGrid!J22 -> 200 | C19: =LumpyGrid!J23 -> 1 | D19: =LumpyGrid!J24 -> 0.03386 | E19: =LumpyGrid!J25 -> 14
A21: The lumps cost: $50m tranches and whole quarters against the continuous floor | E21: =E17-E14 -> 2.0593891
A22: of which whole quarters | E22: =E15-E14 -> 1.1893891
A23: and then $50 million tranches | E23: =E17-E15 -> 0.87
A24: $10 million tranches would save | E24: =E17-E16 -> 0.6

Sheet Reweight
A1: Rescale, then reweight (Theorem 1.4; Worked Example 1.1, Step 5; AXIOM Lab 2.1, step 4)
A2: Rescaling (after tax, or in thousands of dollars) is a strictly increasing transformation: no package changes rank. Reweighting the value of a quarter of delay is a new objective.
M3: a quarter of delay worth: | N3: =Vq -> 8 | O3: 4 | P3: 16
A4: Line | B4: Delay | C4: Cost | D4: After tax | E4: In $ thousands | F4: Rank | G4: Rank after tax | H4: Rank in thousands | J4: Reweighting | K4: Value | L4: Quarters | M4: Line fees of the cheapest lumpy package | N4: Cost at the declared value | O4: Cost at $4m | P4: Cost at $16m | Q4: Fees saved per extra quarter
A5: =LumpyGrid!B5 -> 0 | B5: =LumpyGrid!C5 -> 0 | C5: =LumpyGrid!E5 -> 0 | D5: =(1-Tax)*C5 -> 0 | E5: =1000*C5 -> 0 | F5: =RANK(C5,$C$5:$C$67,1) -> 1 | G5: =RANK(D5,$D$5:$D$67,1) -> 1 | H5: =RANK(E5,$E$5:$E$67,1) -> 1 | J5: Packages whose rank changes after tax or in thousands | K5: =SUMPRODUCT(--(F5:F67<>G5:G67))+SUMPRODUCT(--(F5:F67<>H5:H67)) -> 0
A6: =LumpyGrid!B6 -> 0 | B6: =LumpyGrid!C6 -> 1 | C6: =LumpyGrid!E6 -> 8 | D6: =(1-Tax)*C6 -> 6 | E6: =1000*C6 -> 8000 | F6: =RANK(C6,$C$5:$C$67,1) -> 7 | G6: =RANK(D6,$D$5:$D$67,1) -> 7 | H6: =RANK(E6,$E$5:$E$67,1) -> 7 | L6: 1 | M6: =Fee*FinerLines!H6 -> 4.5 | N6: =M6+N$3*L6 -> 12.5 | O6: =M6+O$3*L6 -> 8.5 | P6: =M6+P$3*L6 -> 20.5
A7: =LumpyGrid!B7 -> 0 | B7: =LumpyGrid!C7 -> 2 | C7: =LumpyGrid!E7 -> 16 | D7: =(1-Tax)*C7 -> 12 | E7: =1000*C7 -> 16000 | F7: =RANK(C7,$C$5:$C$67,1) -> 16 | G7: =RANK(D7,$D$5:$D$67,1) -> 16 | H7: =RANK(E7,$E$5:$E$67,1) -> 16 | J7: Continuous best at $4m a quarter: line | K7: =Continuous!I6 -> 140 | L7: 2 | M7: =Fee*FinerLines!H7 -> 3 | N7: =M7+N$3*L7 -> 19 | O7: =M7+O$3*L7 -> 11 | P7: =M7+P$3*L7 -> 35 | Q7: =($M$6-M7)/(L7-1) -> 1.5
A8: =LumpyGrid!B8 -> 0 | B8: =LumpyGrid!C8 -> 3 | C8: =LumpyGrid!E8 -> 24 | D8: =(1-Tax)*C8 -> 18 | E8: =1000*C8 -> 24000 | F8: =RANK(C8,$C$5:$C$67,1) -> 25 | G8: =RANK(D8,$D$5:$D$67,1) -> 25 | H8: =RANK(E8,$E$5:$E$67,1) -> 25 | J8: delay (quarters) | K8: =Continuous!I7 -> 0.8311562 | L8: 3 | M8: =Fee*FinerLines!H8 -> 1.5 | N8: =M8+N$3*L8 -> 25.5 | O8: =M8+O$3*L8 -> 13.5 | P8: =M8+P$3*L8 -> 49.5 | Q8: =($M$6-M8)/(L8-1) -> 1.5
A9: =LumpyGrid!B9 -> 0 | B9: =LumpyGrid!C9 -> 4 | C9: =LumpyGrid!E9 -> 32 | D9: =(1-Tax)*C9 -> 24 | E9: =1000*C9 -> 32000 | F9: =RANK(C9,$C$5:$C$67,1) -> 34 | G9: =RANK(D9,$D$5:$D$67,1) -> 34 | H9: =RANK(E9,$E$5:$E$67,1) -> 34 | J9: cost | K9: =Continuous!I5 -> 7.5246248 | L9: 4 | M9: =Fee*FinerLines!H9 -> 1.5 | N9: =M9+N$3*L9 -> 33.5 | O9: =M9+O$3*L9 -> 17.5 | P9: =M9+P$3*L9 -> 65.5 | Q9: =($M$6-M9)/(L9-1) -> 1
A10: =LumpyGrid!B10 -> 0 | B10: =LumpyGrid!C10 -> 5 | C10: =LumpyGrid!E10 -> 40 | D10: =(1-Tax)*C10 -> 30 | E10: =1000*C10 -> 40000 | F10: =RANK(C10,$C$5:$C$67,1) -> 43 | G10: =RANK(D10,$D$5:$D$67,1) -> 43 | H10: =RANK(E10,$E$5:$E$67,1) -> 43 | J10: Continuous best at $16m a quarter: line | K10: =Continuous!J6 -> 195 | L10: 5 | M10: =Fee*FinerLines!H10 -> 1.5 | N10: =M10+N$3*L10 -> 41.5 | O10: =M10+O$3*L10 -> 21.5 | P10: =M10+P$3*L10 -> 81.5 | Q10: =($M$6-M10)/(L10-1) -> 0.75
A11: =LumpyGrid!B11 -> 0 | B11: =LumpyGrid!C11 -> 6 | C11: =LumpyGrid!E11 -> 48 | D11: =(1-Tax)*C11 -> 36 | E11: =1000*C11 -> 48000 | F11: =RANK(C11,$C$5:$C$67,1) -> 52 | G11: =RANK(D11,$D$5:$D$67,1) -> 52 | H11: =RANK(E11,$E$5:$E$67,1) -> 52 | J11: delay (quarters) | K11: =Continuous!J7 -> 0.60392968 | L11: 6 | M11: =Fee*FinerLines!H11 -> 0 | N11: =M11+N$3*L11 -> 48 | O11: =M11+O$3*L11 -> 24 | P11: =M11+P$3*L11 -> 96 | Q11: =($M$6-M11)/(L11-1) -> 0.9
A12: =LumpyGrid!B12 -> 50 | B12: =LumpyGrid!C12 -> 0 | C12: =LumpyGrid!E12 -> 1.5 | D12: =(1-Tax)*C12 -> 1.125 | E12: =1000*C12 -> 1500 | F12: =RANK(C12,$C$5:$C$67,1) -> 2 | G12: =RANK(D12,$D$5:$D$67,1) -> 2 | H12: =RANK(E12,$E$5:$E$67,1) -> 2 | J12: cost | K12: =Continuous!J5 -> 15.512875
A13: =LumpyGrid!B13 -> 50 | B13: =LumpyGrid!C13 -> 1 | C13: =LumpyGrid!E13 -> 9.5 | D13: =(1-Tax)*C13 -> 7.125 | E13: =1000*C13 -> 9500 | F13: =RANK(C13,$C$5:$C$67,1) -> 9 | G13: =RANK(D13,$D$5:$D$67,1) -> 9 | H13: =RANK(E13,$E$5:$E$67,1) -> 9 | J13: The board's number moves the line by | K13: =K10-K7 -> 55 | L13: Cheapest | N13: At the declared value | O13: At $4m | P13: At $16m
A14: =LumpyGrid!B14 -> 50 | B14: =LumpyGrid!C14 -> 2 | C14: =LumpyGrid!E14 -> 17.5 | D14: =(1-Tax)*C14 -> 13.125 | E14: =1000*C14 -> 17500 | F14: =RANK(C14,$C$5:$C$67,1) -> 18 | G14: =RANK(D14,$D$5:$D$67,1) -> 18 | H14: =RANK(E14,$E$5:$E$67,1) -> 18 | L14: cost | N14: =MIN(N6:N11) -> 12.5 | O14: =MIN(O6:O11) -> 8.5 | P14: =MIN(P6:P11) -> 20.5
A15: =LumpyGrid!B15 -> 50 | B15: =LumpyGrid!C15 -> 3 | C15: =LumpyGrid!E15 -> 25.5 | D15: =(1-Tax)*C15 -> 19.125 | E15: =1000*C15 -> 25500 | F15: =RANK(C15,$C$5:$C$67,1) -> 27 | G15: =RANK(D15,$D$5:$D$67,1) -> 27 | H15: =RANK(E15,$E$5:$E$67,1) -> 27 | J15: One quarter is the cheapest lumpy delay when v exceeds | K15: =MAX(Q7:Q11) -> 1.5 | L15: quarters | N15: =INDEX($L$6:$L$11,MATCH(N14,N6:N11,0)) -> 1 | O15: =INDEX($L$6:$L$11,MATCH(O14,O6:O11,0)) -> 1 | P15: =INDEX($L$6:$L$11,MATCH(P14,P6:P11,0)) -> 1
A16: =LumpyGrid!B16 -> 50 | B16: =LumpyGrid!C16 -> 4 | C16: =LumpyGrid!E16 -> 33.5 | D16: =(1-Tax)*C16 -> 25.125 | E16: =1000*C16 -> 33500 | F16: =RANK(C16,$C$5:$C$67,1) -> 36 | G16: =RANK(D16,$D$5:$D$67,1) -> 36 | H16: =RANK(E16,$E$5:$E$67,1) -> 36
A17: =LumpyGrid!B17 -> 50 | B17: =LumpyGrid!C17 -> 5 | C17: =LumpyGrid!E17 -> 41.5 | D17: =(1-Tax)*C17 -> 31.125 | E17: =1000*C17 -> 41500 | F17: =RANK(C17,$C$5:$C$67,1) -> 45 | G17: =RANK(D17,$D$5:$D$67,1) -> 45 | H17: =RANK(E17,$E$5:$E$67,1) -> 45 | J17: At $16m: nearest package to the continuous best, line | K17: =ROUND(K10/Tranche,0)*Tranche -> 200
A18: =LumpyGrid!B18 -> 50 | B18: =LumpyGrid!C18 -> 6 | C18: =LumpyGrid!E18 -> 49.5 | D18: =(1-Tax)*C18 -> 37.125 | E18: =1000*C18 -> 49500 | F18: =RANK(C18,$C$5:$C$67,1) -> 54 | G18: =RANK(D18,$D$5:$D$67,1) -> 54 | H18: =RANK(E18,$E$5:$E$67,1) -> 54 | J18: its delay | K18: =ROUND(K11,0) -> 1
A19: =LumpyGrid!B19 -> 100 | B19: =LumpyGrid!C19 -> 0 | C19: =LumpyGrid!E19 -> 3 | D19: =(1-Tax)*C19 -> 2.25 | E19: =1000*C19 -> 3000 | F19: =RANK(C19,$C$5:$C$67,1) -> 3 | G19: =RANK(D19,$D$5:$D$67,1) -> 3 | H19: =RANK(E19,$E$5:$E$67,1) -> 3 | J19: its cost at $16m | K19: =Fee*K17+P3*K18 -> 22
A20: =LumpyGrid!B20 -> 100 | B20: =LumpyGrid!C20 -> 1 | C20: =LumpyGrid!E20 -> 11 | D20: =(1-Tax)*C20 -> 8.25 | E20: =1000*C20 -> 11000 | F20: =RANK(C20,$C$5:$C$67,1) -> 11 | G20: =RANK(D20,$D$5:$D$67,1) -> 11 | H20: =RANK(E20,$E$5:$E$67,1) -> 11 | J20: The signed package at $16m | K20: =Fee*LumpyGrid!J8+P3*LumpyGrid!J9 -> 20.5
A21: =LumpyGrid!B21 -> 100 | B21: =LumpyGrid!C21 -> 2 | C21: =LumpyGrid!E21 -> 19 | D21: =(1-Tax)*C21 -> 14.25 | E21: =1000*C21 -> 19000 | F21: =RANK(C21,$C$5:$C$67,1) -> 20 | G21: =RANK(D21,$D$5:$D$67,1) -> 20 | H21: =RANK(E21,$E$5:$E$67,1) -> 20 | J21: The signed package at $4m | K21: =Fee*LumpyGrid!J8+O3*LumpyGrid!J9 -> 8.5
A22: =LumpyGrid!B22 -> 100 | B22: =LumpyGrid!C22 -> 3 | C22: =LumpyGrid!E22 -> 27 | D22: =(1-Tax)*C22 -> 20.25 | E22: =1000*C22 -> 27000 | F22: =RANK(C22,$C$5:$C$67,1) -> 29 | G22: =RANK(D22,$D$5:$D$67,1) -> 29 | H22: =RANK(E22,$E$5:$E$67,1) -> 29
A23: =LumpyGrid!B23 -> 100 | B23: =LumpyGrid!C23 -> 4 | C23: =LumpyGrid!E23 -> 35 | D23: =(1-Tax)*C23 -> 26.25 | E23: =1000*C23 -> 35000 | F23: =RANK(C23,$C$5:$C$67,1) -> 38 | G23: =RANK(D23,$D$5:$D$67,1) -> 38 | H23: =RANK(E23,$E$5:$E$67,1) -> 38
A24: =LumpyGrid!B24 -> 100 | B24: =LumpyGrid!C24 -> 5 | C24: =LumpyGrid!E24 -> 43 | D24: =(1-Tax)*C24 -> 32.25 | E24: =1000*C24 -> 43000 | F24: =RANK(C24,$C$5:$C$67,1) -> 47 | G24: =RANK(D24,$D$5:$D$67,1) -> 47 | H24: =RANK(E24,$E$5:$E$67,1) -> 47
A25: =LumpyGrid!B25 -> 100 | B25: =LumpyGrid!C25 -> 6 | C25: =LumpyGrid!E25 -> 51 | D25: =(1-Tax)*C25 -> 38.25 | E25: =1000*C25 -> 51000 | F25: =RANK(C25,$C$5:$C$67,1) -> 56 | G25: =RANK(D25,$D$5:$D$67,1) -> 56 | H25: =RANK(E25,$E$5:$E$67,1) -> 56
A26: =LumpyGrid!B26 -> 150 | B26: =LumpyGrid!C26 -> 0 | C26: =LumpyGrid!E26 -> 4.5 | D26: =(1-Tax)*C26 -> 3.375 | E26: =1000*C26 -> 4500 | F26: =RANK(C26,$C$5:$C$67,1) -> 4 | G26: =RANK(D26,$D$5:$D$67,1) -> 4 | H26: =RANK(E26,$E$5:$E$67,1) -> 4
A27: =LumpyGrid!B27 -> 150 | B27: =LumpyGrid!C27 -> 1 | C27: =LumpyGrid!E27 -> 12.5 | D27: =(1-Tax)*C27 -> 9.375 | E27: =1000*C27 -> 12500 | F27: =RANK(C27,$C$5:$C$67,1) -> 13 | G27: =RANK(D27,$D$5:$D$67,1) -> 13 | H27: =RANK(E27,$E$5:$E$67,1) -> 13
A28: =LumpyGrid!B28 -> 150 | B28: =LumpyGrid!C28 -> 2 | C28: =LumpyGrid!E28 -> 20.5 | D28: =(1-Tax)*C28 -> 15.375 | E28: =1000*C28 -> 20500 | F28: =RANK(C28,$C$5:$C$67,1) -> 22 | G28: =RANK(D28,$D$5:$D$67,1) -> 22 | H28: =RANK(E28,$E$5:$E$67,1) -> 22
A29: =LumpyGrid!B29 -> 150 | B29: =LumpyGrid!C29 -> 3 | C29: =LumpyGrid!E29 -> 28.5 | D29: =(1-Tax)*C29 -> 21.375 | E29: =1000*C29 -> 28500 | F29: =RANK(C29,$C$5:$C$67,1) -> 31 | G29: =RANK(D29,$D$5:$D$67,1) -> 31 | H29: =RANK(E29,$E$5:$E$67,1) -> 31
A30: =LumpyGrid!B30 -> 150 | B30: =LumpyGrid!C30 -> 4 | C30: =LumpyGrid!E30 -> 36.5 | D30: =(1-Tax)*C30 -> 27.375 | E30: =1000*C30 -> 36500 | F30: =RANK(C30,$C$5:$C$67,1) -> 40 | G30: =RANK(D30,$D$5:$D$67,1) -> 40 | H30: =RANK(E30,$E$5:$E$67,1) -> 40
A31: =LumpyGrid!B31 -> 150 | B31: =LumpyGrid!C31 -> 5 | C31: =LumpyGrid!E31 -> 44.5 | D31: =(1-Tax)*C31 -> 33.375 | E31: =1000*C31 -> 44500 | F31: =RANK(C31,$C$5:$C$67,1) -> 49 | G31: =RANK(D31,$D$5:$D$67,1) -> 49 | H31: =RANK(E31,$E$5:$E$67,1) -> 49
A32: =LumpyGrid!B32 -> 150 | B32: =LumpyGrid!C32 -> 6 | C32: =LumpyGrid!E32 -> 52.5 | D32: =(1-Tax)*C32 -> 39.375 | E32: =1000*C32 -> 52500 | F32: =RANK(C32,$C$5:$C$67,1) -> 58 | G32: =RANK(D32,$D$5:$D$67,1) -> 58 | H32: =RANK(E32,$E$5:$E$67,1) -> 58
A33: =LumpyGrid!B33 -> 200 | B33: =LumpyGrid!C33 -> 0 | C33: =LumpyGrid!E33 -> 6 | D33: =(1-Tax)*C33 -> 4.5 | E33: =1000*C33 -> 6000 | F33: =RANK(C33,$C$5:$C$67,1) -> 5 | G33: =RANK(D33,$D$5:$D$67,1) -> 5 | H33: =RANK(E33,$E$5:$E$67,1) -> 5
... A67: =LumpyGrid!B67 -> 400 | B67: =LumpyGrid!C67 -> 6 | C67: =LumpyGrid!E67 -> 60 | D67: =(1-Tax)*C67 -> 45 | E67: =1000*C67 -> 60000 | F67: =RANK(C67,$C$5:$C$67,1) -> 63 | G67: =RANK(D67,$D$5:$D$67,1) -> 63 | H67: =RANK(E67,$E$5:$E$67,1) -> 63

Sheet Commitments
A1: Add a commitment: feasibility is conjunction (Proposition 1.2; AXIOM Lab 2.1, step 5)
A2: Each package against each commitment (1 = met). Adding commitments can only shrink the feasible packages; the order in which they are listed changes nothing.
A4: Quarter | B4: Years | C4: Plan, 0 q of delay | D4: Plan, 1 q of delay | E4: Plan, 2 q of delay | F4: Plan, 3 q of delay | G4: Plan, 4 q of delay | H4: Plan, 5 q of delay | I4: Plan, 6 q of delay | K4: Commitments in force | L4: Feasible packages
A5: 0 | B5: =A5/4 -> 0 | C5: =Per_point*(Plan_target-(Plan_target-Index0)*EXP(-Plan_rate*$B5)-(Depth0-Depth_q*0)*($B5/Trough_tau)*EXP(1-$B5/Trough_tau)) -> 620 | D5: =Per_point*(Plan_target-(Plan_target-Index0)*EXP(-Plan_rate*$B5)-(Depth0-Depth_q*1)*($B5/Trough_tau)*EXP(1-$B5/Trough_tau)) -> 620 | E5: =Per_point*(Plan_target-(Plan_target-Index0)*EXP(-Plan_rate*$B5)-(Depth0-Depth_q*2)*($B5/Trough_tau)*EXP(1-$B5/Trough_tau)) -> 620 | F5: =Per_point*(Plan_target-(Plan_target-Index0)*EXP(-Plan_rate*$B5)-(Depth0-Depth_q*3)*($B5/Trough_tau)*EXP(1-$B5/Trough_tau)) -> 620 | G5: =Per_point*(Plan_target-(Plan_target-Index0)*EXP(-Plan_rate*$B5)-(Depth0-Depth_q*4)*($B5/Trough_tau)*EXP(1-$B5/Trough_tau)) -> 620 | H5: =Per_point*(Plan_target-(Plan_target-Index0)*EXP(-Plan_rate*$B5)-(Depth0-Depth_q*5)*($B5/Trough_tau)*EXP(1-$B5/Trough_tau)) -> 620 | I5: =Per_point*(Plan_target-(Plan_target-Index0)*EXP(-Plan_rate*$B5)-(Depth0-Depth_q*6)*($B5/Trough_tau)*EXP(1-$B5/Trough_tau)) -> 620 | K5: The board's appetite | L5: =SUM(C22:C84) -> 46
A6: 1 | B6: =A6/4 -> 0.25 | C6: =Per_point*(Plan_target-(Plan_target-Index0)*EXP(-Plan_rate*$B6)-(Depth0-Depth_q*0)*($B6/Trough_tau)*EXP(1-$B6/Trough_tau)) -> 574.17772 | D6: =Per_point*(Plan_target-(Plan_target-Index0)*EXP(-Plan_rate*$B6)-(Depth0-Depth_q*1)*($B6/Trough_tau)*EXP(1-$B6/Trough_tau)) -> 581.61424 | E6: =Per_point*(Plan_target-(Plan_target-Index0)*EXP(-Plan_rate*$B6)-(Depth0-Depth_q*2)*($B6/Trough_tau)*EXP(1-$B6/Trough_tau)) -> 589.05075 | F6: =Per_point*(Plan_target-(Plan_target-Index0)*EXP(-Plan_rate*$B6)-(Depth0-Depth_q*3)*($B6/Trough_tau)*EXP(1-$B6/Trough_tau)) -> 596.48726 | G6: =Per_point*(Plan_target-(Plan_target-Index0)*EXP(-Plan_rate*$B6)-(Depth0-Depth_q*4)*($B6/Trough_tau)*EXP(1-$B6/Trough_tau)) -> 603.92378 | H6: =Per_point*(Plan_target-(Plan_target-Index0)*EXP(-Plan_rate*$B6)-(Depth0-Depth_q*5)*($B6/Trough_tau)*EXP(1-$B6/Trough_tau)) -> 611.36029 | I6: =Per_point*(Plan_target-(Plan_target-Index0)*EXP(-Plan_rate*$B6)-(Depth0-Depth_q*6)*($B6/Trough_tau)*EXP(1-$B6/Trough_tau)) -> 618.7968 | K6: + the covenant with the line fully drawn | L6: =SUMPRODUCT(C22:C84,D22:D84) -> 46
A7: 2 | B7: =A7/4 -> 0.5 | C7: =Per_point*(Plan_target-(Plan_target-Index0)*EXP(-Plan_rate*$B7)-(Depth0-Depth_q*0)*($B7/Trough_tau)*EXP(1-$B7/Trough_tau)) -> 540.0666 | D7: =Per_point*(Plan_target-(Plan_target-Index0)*EXP(-Plan_rate*$B7)-(Depth0-Depth_q*1)*($B7/Trough_tau)*EXP(1-$B7/Trough_tau)) -> 553.192 | E7: =Per_point*(Plan_target-(Plan_target-Index0)*EXP(-Plan_rate*$B7)-(Depth0-Depth_q*2)*($B7/Trough_tau)*EXP(1-$B7/Trough_tau)) -> 566.3174 | F7: =Per_point*(Plan_target-(Plan_target-Index0)*EXP(-Plan_rate*$B7)-(Depth0-Depth_q*3)*($B7/Trough_tau)*EXP(1-$B7/Trough_tau)) -> 579.4428 | G7: =Per_point*(Plan_target-(Plan_target-Index0)*EXP(-Plan_rate*$B7)-(Depth0-Depth_q*4)*($B7/Trough_tau)*EXP(1-$B7/Trough_tau)) -> 592.5682 | H7: =Per_point*(Plan_target-(Plan_target-Index0)*EXP(-Plan_rate*$B7)-(Depth0-Depth_q*5)*($B7/Trough_tau)*EXP(1-$B7/Trough_tau)) -> 605.6936 | I7: =Per_point*(Plan_target-(Plan_target-Index0)*EXP(-Plan_rate*$B7)-(Depth0-Depth_q*6)*($B7/Trough_tau)*EXP(1-$B7/Trough_tau)) -> 618.819 | K7: + the capability floor of 55 | L7: =SUMPRODUCT(C22:C84,D22:D84,E22:E84) -> 46
A8: 3 | B8: =A8/4 -> 0.75 | C8: =Per_point*(Plan_target-(Plan_target-Index0)*EXP(-Plan_rate*$B8)-(Depth0-Depth_q*0)*($B8/Trough_tau)*EXP(1-$B8/Trough_tau)) -> 515.55419 | D8: =Per_point*(Plan_target-(Plan_target-Index0)*EXP(-Plan_rate*$B8)-(Depth0-Depth_q*1)*($B8/Trough_tau)*EXP(1-$B8/Trough_tau)) -> 532.92887 | E8: =Per_point*(Plan_target-(Plan_target-Index0)*EXP(-Plan_rate*$B8)-(Depth0-Depth_q*2)*($B8/Trough_tau)*EXP(1-$B8/Trough_tau)) -> 550.30356 | F8: =Per_point*(Plan_target-(Plan_target-Index0)*EXP(-Plan_rate*$B8)-(Depth0-Depth_q*3)*($B8/Trough_tau)*EXP(1-$B8/Trough_tau)) -> 567.67825 | G8: =Per_point*(Plan_target-(Plan_target-Index0)*EXP(-Plan_rate*$B8)-(Depth0-Depth_q*4)*($B8/Trough_tau)*EXP(1-$B8/Trough_tau)) -> 585.05294 | H8: =Per_point*(Plan_target-(Plan_target-Index0)*EXP(-Plan_rate*$B8)-(Depth0-Depth_q*5)*($B8/Trough_tau)*EXP(1-$B8/Trough_tau)) -> 602.42762 | I8: =Per_point*(Plan_target-(Plan_target-Index0)*EXP(-Plan_rate*$B8)-(Depth0-Depth_q*6)*($B8/Trough_tau)*EXP(1-$B8/Trough_tau)) -> 619.80231 | K8: + Volume I's joint check | L8: =SUM(G22:G84) -> 46
A9: 4 | B9: =A9/4 -> 1 | C9: =Per_point*(Plan_target-(Plan_target-Index0)*EXP(-Plan_rate*$B9)-(Depth0-Depth_q*0)*($B9/Trough_tau)*EXP(1-$B9/Trough_tau)) -> 498.8622 | D9: =Per_point*(Plan_target-(Plan_target-Index0)*EXP(-Plan_rate*$B9)-(Depth0-Depth_q*1)*($B9/Trough_tau)*EXP(1-$B9/Trough_tau)) -> 519.30634 | E9: =Per_point*(Plan_target-(Plan_target-Index0)*EXP(-Plan_rate*$B9)-(Depth0-Depth_q*2)*($B9/Trough_tau)*EXP(1-$B9/Trough_tau)) -> 539.75049 | F9: =Per_point*(Plan_target-(Plan_target-Index0)*EXP(-Plan_rate*$B9)-(Depth0-Depth_q*3)*($B9/Trough_tau)*EXP(1-$B9/Trough_tau)) -> 560.19463 | G9: =Per_point*(Plan_target-(Plan_target-Index0)*EXP(-Plan_rate*$B9)-(Depth0-Depth_q*4)*($B9/Trough_tau)*EXP(1-$B9/Trough_tau)) -> 580.63877 | H9: =Per_point*(Plan_target-(Plan_target-Index0)*EXP(-Plan_rate*$B9)-(Depth0-Depth_q*5)*($B9/Trough_tau)*EXP(1-$B9/Trough_tau)) -> 601.08292 | I9: =Per_point*(Plan_target-(Plan_target-Index0)*EXP(-Plan_rate*$B9)-(Depth0-Depth_q*6)*($B9/Trough_tau)*EXP(1-$B9/Trough_tau)) -> 621.52706 | K9: The same four, listed in the opposite order | L9: =SUMPRODUCT(F22:F84,E22:E84,D22:D84,C22:C84) -> 46
A10: 5 | B10: =A10/4 -> 1.25 | C10: =Per_point*(Plan_target-(Plan_target-Index0)*EXP(-Plan_rate*$B10)-(Depth0-Depth_q*0)*($B10/Trough_tau)*EXP(1-$B10/Trough_tau)) -> 488.49718 | D10: =Per_point*(Plan_target-(Plan_target-Index0)*EXP(-Plan_rate*$B10)-(Depth0-Depth_q*1)*($B10/Trough_tau)*EXP(1-$B10/Trough_tau)) -> 511.04955 | E10: =Per_point*(Plan_target-(Plan_target-Index0)*EXP(-Plan_rate*$B10)-(Depth0-Depth_q*2)*($B10/Trough_tau)*EXP(1-$B10/Trough_tau)) -> 533.60192 | F10: =Per_point*(Plan_target-(Plan_target-Index0)*EXP(-Plan_rate*$B10)-(Depth0-Depth_q*3)*($B10/Trough_tau)*EXP(1-$B10/Trough_tau)) -> 556.15428 | G10: =Per_point*(Plan_target-(Plan_target-Index0)*EXP(-Plan_rate*$B10)-(Depth0-Depth_q*4)*($B10/Trough_tau)*EXP(1-$B10/Trough_tau)) -> 578.70665 | H10: =Per_point*(Plan_target-(Plan_target-Index0)*EXP(-Plan_rate*$B10)-(Depth0-Depth_q*5)*($B10/Trough_tau)*EXP(1-$B10/Trough_tau)) -> 601.25902 | I10: =Per_point*(Plan_target-(Plan_target-Index0)*EXP(-Plan_rate*$B10)-(Depth0-Depth_q*6)*($B10/Trough_tau)*EXP(1-$B10/Trough_tau)) -> 623.81138
A11: 6 | B11: =A11/4 -> 1.5 | C11: =Per_point*(Plan_target-(Plan_target-Index0)*EXP(-Plan_rate*$B11)-(Depth0-Depth_q*0)*($B11/Trough_tau)*EXP(1-$B11/Trough_tau)) -> 483.20817 | D11: =Per_point*(Plan_target-(Plan_target-Index0)*EXP(-Plan_rate*$B11)-(Depth0-Depth_q*1)*($B11/Trough_tau)*EXP(1-$B11/Trough_tau)) -> 507.09104 | E11: =Per_point*(Plan_target-(Plan_target-Index0)*EXP(-Plan_rate*$B11)-(Depth0-Depth_q*2)*($B11/Trough_tau)*EXP(1-$B11/Trough_tau)) -> 530.97392 | F11: =Per_point*(Plan_target-(Plan_target-Index0)*EXP(-Plan_rate*$B11)-(Depth0-Depth_q*3)*($B11/Trough_tau)*EXP(1-$B11/Trough_tau)) -> 554.85679 | G11: =Per_point*(Plan_target-(Plan_target-Index0)*EXP(-Plan_rate*$B11)-(Depth0-Depth_q*4)*($B11/Trough_tau)*EXP(1-$B11/Trough_tau)) -> 578.73966 | H11: =Per_point*(Plan_target-(Plan_target-Index0)*EXP(-Plan_rate*$B11)-(Depth0-Depth_q*5)*($B11/Trough_tau)*EXP(1-$B11/Trough_tau)) -> 602.62254 | I11: =Per_point*(Plan_target-(Plan_target-Index0)*EXP(-Plan_rate*$B11)-(Depth0-Depth_q*6)*($B11/Trough_tau)*EXP(1-$B11/Trough_tau)) -> 626.50541 | K11: The covenant would bind only above a line of ($ million) | L11: =Covenant*Ebitda-Net_debt -> 545.16
A12: 7 | B12: =A12/4 -> 1.75 | C12: =Per_point*(Plan_target-(Plan_target-Index0)*EXP(-Plan_rate*$B12)-(Depth0-Depth_q*0)*($B12/Trough_tau)*EXP(1-$B12/Trough_tau)) -> 481.95038 | D12: =Per_point*(Plan_target-(Plan_target-Index0)*EXP(-Plan_rate*$B12)-(Depth0-Depth_q*1)*($B12/Trough_tau)*EXP(1-$B12/Trough_tau)) -> 506.5397 | E12: =Per_point*(Plan_target-(Plan_target-Index0)*EXP(-Plan_rate*$B12)-(Depth0-Depth_q*2)*($B12/Trough_tau)*EXP(1-$B12/Trough_tau)) -> 531.12903 | F12: =Per_point*(Plan_target-(Plan_target-Index0)*EXP(-Plan_rate*$B12)-(Depth0-Depth_q*3)*($B12/Trough_tau)*EXP(1-$B12/Trough_tau)) -> 555.71835 | G12: =Per_point*(Plan_target-(Plan_target-Index0)*EXP(-Plan_rate*$B12)-(Depth0-Depth_q*4)*($B12/Trough_tau)*EXP(1-$B12/Trough_tau)) -> 580.30767 | H12: =Per_point*(Plan_target-(Plan_target-Index0)*EXP(-Plan_rate*$B12)-(Depth0-Depth_q*5)*($B12/Trough_tau)*EXP(1-$B12/Trough_tau)) -> 604.89699 | I12: =Per_point*(Plan_target-(Plan_target-Index0)*EXP(-Plan_rate*$B12)-(Depth0-Depth_q*6)*($B12/Trough_tau)*EXP(1-$B12/Trough_tau)) -> 629.48631
A13: 8 | B13: =A13/4 -> 2 | C13: =Per_point*(Plan_target-(Plan_target-Index0)*EXP(-Plan_rate*$B13)-(Depth0-Depth_q*0)*($B13/Trough_tau)*EXP(1-$B13/Trough_tau)) -> 483.85405 | D13: =Per_point*(Plan_target-(Plan_target-Index0)*EXP(-Plan_rate*$B13)-(Depth0-Depth_q*1)*($B13/Trough_tau)*EXP(1-$B13/Trough_tau)) -> 508.65405 | E13: =Per_point*(Plan_target-(Plan_target-Index0)*EXP(-Plan_rate*$B13)-(Depth0-Depth_q*2)*($B13/Trough_tau)*EXP(1-$B13/Trough_tau)) -> 533.45405 | F13: =Per_point*(Plan_target-(Plan_target-Index0)*EXP(-Plan_rate*$B13)-(Depth0-Depth_q*3)*($B13/Trough_tau)*EXP(1-$B13/Trough_tau)) -> 558.25405 | G13: =Per_point*(Plan_target-(Plan_target-Index0)*EXP(-Plan_rate*$B13)-(Depth0-Depth_q*4)*($B13/Trough_tau)*EXP(1-$B13/Trough_tau)) -> 583.05405 | H13: =Per_point*(Plan_target-(Plan_target-Index0)*EXP(-Plan_rate*$B13)-(Depth0-Depth_q*5)*($B13/Trough_tau)*EXP(1-$B13/Trough_tau)) -> 607.85405 | I13: =Per_point*(Plan_target-(Plan_target-Index0)*EXP(-Plan_rate*$B13)-(Depth0-Depth_q*6)*($B13/Trough_tau)*EXP(1-$B13/Trough_tau)) -> 632.65405 | K13: The signed package, commitment by commitment | L13: Value
A14: 9 | B14: =A14/4 -> 2.25 | C14: =Per_point*(Plan_target-(Plan_target-Index0)*EXP(-Plan_rate*$B14)-(Depth0-Depth_q*0)*($B14/Trough_tau)*EXP(1-$B14/Trough_tau)) -> 488.19778 | D14: =Per_point*(Plan_target-(Plan_target-Index0)*EXP(-Plan_rate*$B14)-(Depth0-Depth_q*1)*($B14/Trough_tau)*EXP(1-$B14/Trough_tau)) -> 512.81944 | E14: =Per_point*(Plan_target-(Plan_target-Index0)*EXP(-Plan_rate*$B14)-(Depth0-Depth_q*2)*($B14/Trough_tau)*EXP(1-$B14/Trough_tau)) -> 537.44111 | F14: =Per_point*(Plan_target-(Plan_target-Index0)*EXP(-Plan_rate*$B14)-(Depth0-Depth_q*3)*($B14/Trough_tau)*EXP(1-$B14/Trough_tau)) -> 562.06277 | G14: =Per_point*(Plan_target-(Plan_target-Index0)*EXP(-Plan_rate*$B14)-(Depth0-Depth_q*4)*($B14/Trough_tau)*EXP(1-$B14/Trough_tau)) -> 586.68444 | H14: =Per_point*(Plan_target-(Plan_target-Index0)*EXP(-Plan_rate*$B14)-(Depth0-Depth_q*5)*($B14/Trough_tau)*EXP(1-$B14/Trough_tau)) -> 611.3061 | I14: =Per_point*(Plan_target-(Plan_target-Index0)*EXP(-Plan_rate*$B14)-(Depth0-Depth_q*6)*($B14/Trough_tau)*EXP(1-$B14/Trough_tau)) -> 635.92776 | K14: Line ($ million) | L14: =LumpyGrid!J8 -> 150
A15: 10 | B15: =A15/4 -> 2.5 | C15: =Per_point*(Plan_target-(Plan_target-Index0)*EXP(-Plan_rate*$B15)-(Depth0-Depth_q*0)*($B15/Trough_tau)*EXP(1-$B15/Trough_tau)) -> 494.3857 | D15: =Per_point*(Plan_target-(Plan_target-Index0)*EXP(-Plan_rate*$B15)-(Depth0-Depth_q*1)*($B15/Trough_tau)*EXP(1-$B15/Trough_tau)) -> 518.52852 | E15: =Per_point*(Plan_target-(Plan_target-Index0)*EXP(-Plan_rate*$B15)-(Depth0-Depth_q*2)*($B15/Trough_tau)*EXP(1-$B15/Trough_tau)) -> 542.67134 | F15: =Per_point*(Plan_target-(Plan_target-Index0)*EXP(-Plan_rate*$B15)-(Depth0-Depth_q*3)*($B15/Trough_tau)*EXP(1-$B15/Trough_tau)) -> 566.81417 | G15: =Per_point*(Plan_target-(Plan_target-Index0)*EXP(-Plan_rate*$B15)-(Depth0-Depth_q*4)*($B15/Trough_tau)*EXP(1-$B15/Trough_tau)) -> 590.95699 | H15: =Per_point*(Plan_target-(Plan_target-Index0)*EXP(-Plan_rate*$B15)-(Depth0-Depth_q*5)*($B15/Trough_tau)*EXP(1-$B15/Trough_tau)) -> 615.09982 | I15: =Per_point*(Plan_target-(Plan_target-Index0)*EXP(-Plan_rate*$B15)-(Depth0-Depth_q*6)*($B15/Trough_tau)*EXP(1-$B15/Trough_tau)) -> 639.24264 | K15: Delay (quarters) | L15: =LumpyGrid!J9 -> 1
A16: 11 | B16: =A16/4 -> 2.75 | C16: =Per_point*(Plan_target-(Plan_target-Index0)*EXP(-Plan_rate*$B16)-(Depth0-Depth_q*0)*($B16/Trough_tau)*EXP(1-$B16/Trough_tau)) -> 501.92795 | D16: =Per_point*(Plan_target-(Plan_target-Index0)*EXP(-Plan_rate*$B16)-(Depth0-Depth_q*1)*($B16/Trough_tau)*EXP(1-$B16/Trough_tau)) -> 525.36451 | E16: =Per_point*(Plan_target-(Plan_target-Index0)*EXP(-Plan_rate*$B16)-(Depth0-Depth_q*2)*($B16/Trough_tau)*EXP(1-$B16/Trough_tau)) -> 548.80108 | F16: =Per_point*(Plan_target-(Plan_target-Index0)*EXP(-Plan_rate*$B16)-(Depth0-Depth_q*3)*($B16/Trough_tau)*EXP(1-$B16/Trough_tau)) -> 572.23764 | G16: =Per_point*(Plan_target-(Plan_target-Index0)*EXP(-Plan_rate*$B16)-(Depth0-Depth_q*4)*($B16/Trough_tau)*EXP(1-$B16/Trough_tau)) -> 595.67421 | H16: =Per_point*(Plan_target-(Plan_target-Index0)*EXP(-Plan_rate*$B16)-(Depth0-Depth_q*5)*($B16/Trough_tau)*EXP(1-$B16/Trough_tau)) -> 619.11077 | I16: =Per_point*(Plan_target-(Plan_target-Index0)*EXP(-Plan_rate*$B16)-(Depth0-Depth_q*6)*($B16/Trough_tau)*EXP(1-$B16/Trough_tau)) -> 642.54733 | K16: Breach odds (engine) | L16: =LumpyGrid!J10 -> 0.04003
A17: 12 | B17: =A17/4 -> 3 | C17: =Per_point*(Plan_target-(Plan_target-Index0)*EXP(-Plan_rate*$B17)-(Depth0-Depth_q*0)*($B17/Trough_tau)*EXP(1-$B17/Trough_tau)) -> 510.42405 | D17: =Per_point*(Plan_target-(Plan_target-Index0)*EXP(-Plan_rate*$B17)-(Depth0-Depth_q*1)*($B17/Trough_tau)*EXP(1-$B17/Trough_tau)) -> 532.98699 | E17: =Per_point*(Plan_target-(Plan_target-Index0)*EXP(-Plan_rate*$B17)-(Depth0-Depth_q*2)*($B17/Trough_tau)*EXP(1-$B17/Trough_tau)) -> 555.54993 | F17: =Per_point*(Plan_target-(Plan_target-Index0)*EXP(-Plan_rate*$B17)-(Depth0-Depth_q*3)*($B17/Trough_tau)*EXP(1-$B17/Trough_tau)) -> 578.11287 | G17: =Per_point*(Plan_target-(Plan_target-Index0)*EXP(-Plan_rate*$B17)-(Depth0-Depth_q*4)*($B17/Trough_tau)*EXP(1-$B17/Trough_tau)) -> 600.67581 | H17: =Per_point*(Plan_target-(Plan_target-Index0)*EXP(-Plan_rate*$B17)-(Depth0-Depth_q*5)*($B17/Trough_tau)*EXP(1-$B17/Trough_tau)) -> 623.23875 | I17: =Per_point*(Plan_target-(Plan_target-Index0)*EXP(-Plan_rate*$B17)-(Depth0-Depth_q*6)*($B17/Trough_tau)*EXP(1-$B17/Trough_tau)) -> 645.80169 | K17: Margin to the appetite (points) | L17: =100*(Appetite-L16) -> 0.997
A18: Deepest draw | C18: =Liq0-MIN(C5:C17) -> 138.04962 | D18: =Liq0-MIN(D5:D17) -> 113.4603 | E18: =Liq0-MIN(E5:E17) -> 89.026083 | F18: =Liq0-MIN(F5:F17) -> 65.14321 | G18: =Liq0-MIN(G5:G17) -> 41.293351 | H18: =Liq0-MIN(H5:H17) -> 18.917081 | I18: =Liq0-MIN(I5:I17) -> 1.2031975 | K18: Leverage with the line fully drawn | L18: =(Net_debt+L14)/Ebitda -> 3.7026634
K19: Capability above its floor | L19: =Capability-Cap_floor -> 3
K20: Joint check: deepest draw | L20: =INDEX($C$18:$I$18,1,L15+1) -> 113.4603
A21: Line | B21: Delay | C21: Appetite (the board) | D21: Covenant, line fully drawn | E21: Capability floor | F21: Joint check | G21: All four | K21: Joint check: closure buffer net of the line | L21: =MAX(P90-L14,0) -> 36.866976
A22: =LumpyGrid!B5 -> 0 | B22: =LumpyGrid!C5 -> 0 | C22: =LumpyGrid!F5 -> 0 | D22: =IF((Net_debt+A22)/Ebitda<=Covenant,1,0) -> 1 | E22: =IF(Capability>=Cap_floor,1,0) -> 1 | F22: =IF(INDEX($C$18:$I$18,1,B22+1)+MAX(P90-A22,0)<=Pool,1,0) -> 0 | G22: =C22*D22*E22*F22 -> 0 | K22: Joint check: claims | L22: =L20+L21 -> 150.32727
A23: =LumpyGrid!B6 -> 0 | B23: =LumpyGrid!C6 -> 1 | C23: =LumpyGrid!F6 -> 0 | D23: =IF((Net_debt+A23)/Ebitda<=Covenant,1,0) -> 1 | E23: =IF(Capability>=Cap_floor,1,0) -> 1 | F23: =IF(INDEX($C$18:$I$18,1,B23+1)+MAX(P90-A23,0)<=Pool,1,0) -> 0 | G23: =C23*D23*E23*F23 -> 0 | K23: Cash above the floor unclaimed | L23: =Pool-L22 -> 119.67273
A24: =LumpyGrid!B7 -> 0 | B24: =LumpyGrid!C7 -> 2 | C24: =LumpyGrid!F7 -> 0 | D24: =IF((Net_debt+A24)/Ebitda<=Covenant,1,0) -> 1 | E24: =IF(Capability>=Cap_floor,1,0) -> 1 | F24: =IF(INDEX($C$18:$I$18,1,B24+1)+MAX(P90-A24,0)<=Pool,1,0) -> 0 | G24: =C24*D24*E24*F24 -> 0
A25: =LumpyGrid!B8 -> 0 | B25: =LumpyGrid!C8 -> 3 | C25: =LumpyGrid!F8 -> 0 | D25: =IF((Net_debt+A25)/Ebitda<=Covenant,1,0) -> 1 | E25: =IF(Capability>=Cap_floor,1,0) -> 1 | F25: =IF(INDEX($C$18:$I$18,1,B25+1)+MAX(P90-A25,0)<=Pool,1,0) -> 1 | G25: =C25*D25*E25*F25 -> 0
A26: =LumpyGrid!B9 -> 0 | B26: =LumpyGrid!C9 -> 4 | C26: =LumpyGrid!F9 -> 0 | D26: =IF((Net_debt+A26)/Ebitda<=Covenant,1,0) -> 1 | E26: =IF(Capability>=Cap_floor,1,0) -> 1 | F26: =IF(INDEX($C$18:$I$18,1,B26+1)+MAX(P90-A26,0)<=Pool,1,0) -> 1 | G26: =C26*D26*E26*F26 -> 0
A27: =LumpyGrid!B10 -> 0 | B27: =LumpyGrid!C10 -> 5 | C27: =LumpyGrid!F10 -> 0 | D27: =IF((Net_debt+A27)/Ebitda<=Covenant,1,0) -> 1 | E27: =IF(Capability>=Cap_floor,1,0) -> 1 | F27: =IF(INDEX($C$18:$I$18,1,B27+1)+MAX(P90-A27,0)<=Pool,1,0) -> 1 | G27: =C27*D27*E27*F27 -> 0
A28: =LumpyGrid!B11 -> 0 | B28: =LumpyGrid!C11 -> 6 | C28: =LumpyGrid!F11 -> 1 | D28: =IF((Net_debt+A28)/Ebitda<=Covenant,1,0) -> 1 | E28: =IF(Capability>=Cap_floor,1,0) -> 1 | F28: =IF(INDEX($C$18:$I$18,1,B28+1)+MAX(P90-A28,0)<=Pool,1,0) -> 1 | G28: =C28*D28*E28*F28 -> 1
A29: =LumpyGrid!B12 -> 50 | B29: =LumpyGrid!C12 -> 0 | C29: =LumpyGrid!F12 -> 0 | D29: =IF((Net_debt+A29)/Ebitda<=Covenant,1,0) -> 1 | E29: =IF(Capability>=Cap_floor,1,0) -> 1 | F29: =IF(INDEX($C$18:$I$18,1,B29+1)+MAX(P90-A29,0)<=Pool,1,0) -> 0 | G29: =C29*D29*E29*F29 -> 0
A30: =LumpyGrid!B13 -> 50 | B30: =LumpyGrid!C13 -> 1 | C30: =LumpyGrid!F13 -> 0 | D30: =IF((Net_debt+A30)/Ebitda<=Covenant,1,0) -> 1 | E30: =IF(Capability>=Cap_floor,1,0) -> 1 | F30: =IF(INDEX($C$18:$I$18,1,B30+1)+MAX(P90-A30,0)<=Pool,1,0) -> 1 | G30: =C30*D30*E30*F30 -> 0
A31: =LumpyGrid!B14 -> 50 | B31: =LumpyGrid!C14 -> 2 | C31: =LumpyGrid!F14 -> 0 | D31: =IF((Net_debt+A31)/Ebitda<=Covenant,1,0) -> 1 | E31: =IF(Capability>=Cap_floor,1,0) -> 1 | F31: =IF(INDEX($C$18:$I$18,1,B31+1)+MAX(P90-A31,0)<=Pool,1,0) -> 1 | G31: =C31*D31*E31*F31 -> 0
A32: =LumpyGrid!B15 -> 50 | B32: =LumpyGrid!C15 -> 3 | C32: =LumpyGrid!F15 -> 1 | D32: =IF((Net_debt+A32)/Ebitda<=Covenant,1,0) -> 1 | E32: =IF(Capability>=Cap_floor,1,0) -> 1 | F32: =IF(INDEX($C$18:$I$18,1,B32+1)+MAX(P90-A32,0)<=Pool,1,0) -> 1 | G32: =C32*D32*E32*F32 -> 1
A33: =LumpyGrid!B16 -> 50 | B33: =LumpyGrid!C16 -> 4 | C33: =LumpyGrid!F16 -> 1 | D33: =IF((Net_debt+A33)/Ebitda<=Covenant,1,0) -> 1 | E33: =IF(Capability>=Cap_floor,1,0) -> 1 | F33: =IF(INDEX($C$18:$I$18,1,B33+1)+MAX(P90-A33,0)<=Pool,1,0) -> 1 | G33: =C33*D33*E33*F33 -> 1
A34: =LumpyGrid!B17 -> 50 | B34: =LumpyGrid!C17 -> 5 | C34: =LumpyGrid!F17 -> 1 | D34: =IF((Net_debt+A34)/Ebitda<=Covenant,1,0) -> 1 | E34: =IF(Capability>=Cap_floor,1,0) -> 1 | F34: =IF(INDEX($C$18:$I$18,1,B34+1)+MAX(P90-A34,0)<=Pool,1,0) -> 1 | G34: =C34*D34*E34*F34 -> 1
A35: =LumpyGrid!B18 -> 50 | B35: =LumpyGrid!C18 -> 6 | C35: =LumpyGrid!F18 -> 1 | D35: =IF((Net_debt+A35)/Ebitda<=Covenant,1,0) -> 1 | E35: =IF(Capability>=Cap_floor,1,0) -> 1 | F35: =IF(INDEX($C$18:$I$18,1,B35+1)+MAX(P90-A35,0)<=Pool,1,0) -> 1 | G35: =C35*D35*E35*F35 -> 1
A36: =LumpyGrid!B19 -> 100 | B36: =LumpyGrid!C19 -> 0 | C36: =LumpyGrid!F19 -> 0 | D36: =IF((Net_debt+A36)/Ebitda<=Covenant,1,0) -> 1 | E36: =IF(Capability>=Cap_floor,1,0) -> 1 | F36: =IF(INDEX($C$18:$I$18,1,B36+1)+MAX(P90-A36,0)<=Pool,1,0) -> 1 | G36: =C36*D36*E36*F36 -> 0
A37: =LumpyGrid!B20 -> 100 | B37: =LumpyGrid!C20 -> 1 | C37: =LumpyGrid!F20 -> 0 | D37: =IF((Net_debt+A37)/Ebitda<=Covenant,1,0) -> 1 | E37: =IF(Capability>=Cap_floor,1,0) -> 1 | F37: =IF(INDEX($C$18:$I$18,1,B37+1)+MAX(P90-A37,0)<=Pool,1,0) -> 1 | G37: =C37*D37*E37*F37 -> 0
A38: =LumpyGrid!B21 -> 100 | B38: =LumpyGrid!C21 -> 2 | C38: =LumpyGrid!F21 -> 1 | D38: =IF((Net_debt+A38)/Ebitda<=Covenant,1,0) -> 1 | E38: =IF(Capability>=Cap_floor,1,0) -> 1 | F38: =IF(INDEX($C$18:$I$18,1,B38+1)+MAX(P90-A38,0)<=Pool,1,0) -> 1 | G38: =C38*D38*E38*F38 -> 1
A39: =LumpyGrid!B22 -> 100 | B39: =LumpyGrid!C22 -> 3 | C39: =LumpyGrid!F22 -> 1 | D39: =IF((Net_debt+A39)/Ebitda<=Covenant,1,0) -> 1 | E39: =IF(Capability>=Cap_floor,1,0) -> 1 | F39: =IF(INDEX($C$18:$I$18,1,B39+1)+MAX(P90-A39,0)<=Pool,1,0) -> 1 | G39: =C39*D39*E39*F39 -> 1
A40: =LumpyGrid!B23 -> 100 | B40: =LumpyGrid!C23 -> 4 | C40: =LumpyGrid!F23 -> 1 | D40: =IF((Net_debt+A40)/Ebitda<=Covenant,1,0) -> 1 | E40: =IF(Capability>=Cap_floor,1,0) -> 1 | F40: =IF(INDEX($C$18:$I$18,1,B40+1)+MAX(P90-A40,0)<=Pool,1,0) -> 1 | G40: =C40*D40*E40*F40 -> 1
A41: =LumpyGrid!B24 -> 100 | B41: =LumpyGrid!C24 -> 5 | C41: =LumpyGrid!F24 -> 1 | D41: =IF((Net_debt+A41)/Ebitda<=Covenant,1,0) -> 1 | E41: =IF(Capability>=Cap_floor,1,0) -> 1 | F41: =IF(INDEX($C$18:$I$18,1,B41+1)+MAX(P90-A41,0)<=Pool,1,0) -> 1 | G41: =C41*D41*E41*F41 -> 1
A42: =LumpyGrid!B25 -> 100 | B42: =LumpyGrid!C25 -> 6 | C42: =LumpyGrid!F25 -> 1 | D42: =IF((Net_debt+A42)/Ebitda<=Covenant,1,0) -> 1 | E42: =IF(Capability>=Cap_floor,1,0) -> 1 | F42: =IF(INDEX($C$18:$I$18,1,B42+1)+MAX(P90-A42,0)<=Pool,1,0) -> 1 | G42: =C42*D42*E42*F42 -> 1
A43: =LumpyGrid!B26 -> 150 | B43: =LumpyGrid!C26 -> 0 | C43: =LumpyGrid!F26 -> 0 | D43: =IF((Net_debt+A43)/Ebitda<=Covenant,1,0) -> 1 | E43: =IF(Capability>=Cap_floor,1,0) -> 1 | F43: =IF(INDEX($C$18:$I$18,1,B43+1)+MAX(P90-A43,0)<=Pool,1,0) -> 1 | G43: =C43*D43*E43*F43 -> 0
A44: =LumpyGrid!B27 -> 150 | B44: =LumpyGrid!C27 -> 1 | C44: =LumpyGrid!F27 -> 1 | D44: =IF((Net_debt+A44)/Ebitda<=Covenant,1,0) -> 1 | E44: =IF(Capability>=Cap_floor,1,0) -> 1 | F44: =IF(INDEX($C$18:$I$18,1,B44+1)+MAX(P90-A44,0)<=Pool,1,0) -> 1 | G44: =C44*D44*E44*F44 -> 1
A45: =LumpyGrid!B28 -> 150 | B45: =LumpyGrid!C28 -> 2 | C45: =LumpyGrid!F28 -> 1 | D45: =IF((Net_debt+A45)/Ebitda<=Covenant,1,0) -> 1 | E45: =IF(Capability>=Cap_floor,1,0) -> 1 | F45: =IF(INDEX($C$18:$I$18,1,B45+1)+MAX(P90-A45,0)<=Pool,1,0) -> 1 | G45: =C45*D45*E45*F45 -> 1
A46: =LumpyGrid!B29 -> 150 | B46: =LumpyGrid!C29 -> 3 | C46: =LumpyGrid!F29 -> 1 | D46: =IF((Net_debt+A46)/Ebitda<=Covenant,1,0) -> 1 | E46: =IF(Capability>=Cap_floor,1,0) -> 1 | F46: =IF(INDEX($C$18:$I$18,1,B46+1)+MAX(P90-A46,0)<=Pool,1,0) -> 1 | G46: =C46*D46*E46*F46 -> 1
A47: =LumpyGrid!B30 -> 150 | B47: =LumpyGrid!C30 -> 4 | C47: =LumpyGrid!F30 -> 1 | D47: =IF((Net_debt+A47)/Ebitda<=Covenant,1,0) -> 1 | E47: =IF(Capability>=Cap_floor,1,0) -> 1 | F47: =IF(INDEX($C$18:$I$18,1,B47+1)+MAX(P90-A47,0)<=Pool,1,0) -> 1 | G47: =C47*D47*E47*F47 -> 1
A48: =LumpyGrid!B31 -> 150 | B48: =LumpyGrid!C31 -> 5 | C48: =LumpyGrid!F31 -> 1 | D48: =IF((Net_debt+A48)/Ebitda<=Covenant,1,0) -> 1 | E48: =IF(Capability>=Cap_floor,1,0) -> 1 | F48: =IF(INDEX($C$18:$I$18,1,B48+1)+MAX(P90-A48,0)<=Pool,1,0) -> 1 | G48: =C48*D48*E48*F48 -> 1
A49: =LumpyGrid!B32 -> 150 | B49: =LumpyGrid!C32 -> 6 | C49: =LumpyGrid!F32 -> 1 | D49: =IF((Net_debt+A49)/Ebitda<=Covenant,1,0) -> 1 | E49: =IF(Capability>=Cap_floor,1,0) -> 1 | F49: =IF(INDEX($C$18:$I$18,1,B49+1)+MAX(P90-A49,0)<=Pool,1,0) -> 1 | G49: =C49*D49*E49*F49 -> 1
A50: =LumpyGrid!B33 -> 200 | B50: =LumpyGrid!C33 -> 0 | C50: =LumpyGrid!F33 -> 0 | D50: =IF((Net_debt+A50)/Ebitda<=Covenant,1,0) -> 1 | E50: =IF(Capability>=Cap_floor,1,0) -> 1 | F50: =IF(INDEX($C$18:$I$18,1,B50+1)+MAX(P90-A50,0)<=Pool,1,0) -> 1 | G50: =C50*D50*E50*F50 -> 0
A51: =LumpyGrid!B34 -> 200 | B51: =LumpyGrid!C34 -> 1 | C51: =LumpyGrid!F34 -> 1 | D51: =IF((Net_debt+A51)/Ebitda<=Covenant,1,0) -> 1 | E51: =IF(Capability>=Cap_floor,1,0) -> 1 | F51: =IF(INDEX($C$18:$I$18,1,B51+1)+MAX(P90-A51,0)<=Pool,1,0) -> 1 | G51: =C51*D51*E51*F51 -> 1
A52: =LumpyGrid!B35 -> 200 | B52: =LumpyGrid!C35 -> 2 | C52: =LumpyGrid!F35 -> 1 | D52: =IF((Net_debt+A52)/Ebitda<=Covenant,1,0) -> 1 | E52: =IF(Capability>=Cap_floor,1,0) -> 1 | F52: =IF(INDEX($C$18:$I$18,1,B52+1)+MAX(P90-A52,0)<=Pool,1,0) -> 1 | G52: =C52*D52*E52*F52 -> 1
A53: =LumpyGrid!B36 -> 200 | B53: =LumpyGrid!C36 -> 3 | C53: =LumpyGrid!F36 -> 1 | D53: =IF((Net_debt+A53)/Ebitda<=Covenant,1,0) -> 1 | E53: =IF(Capability>=Cap_floor,1,0) -> 1 | F53: =IF(INDEX($C$18:$I$18,1,B53+1)+MAX(P90-A53,0)<=Pool,1,0) -> 1 | G53: =C53*D53*E53*F53 -> 1
A54: =LumpyGrid!B37 -> 200 | B54: =LumpyGrid!C37 -> 4 | C54: =LumpyGrid!F37 -> 1 | D54: =IF((Net_debt+A54)/Ebitda<=Covenant,1,0) -> 1 | E54: =IF(Capability>=Cap_floor,1,0) -> 1 | F54: =IF(INDEX($C$18:$I$18,1,B54+1)+MAX(P90-A54,0)<=Pool,1,0) -> 1 | G54: =C54*D54*E54*F54 -> 1
A55: =LumpyGrid!B38 -> 200 | B55: =LumpyGrid!C38 -> 5 | C55: =LumpyGrid!F38 -> 1 | D55: =IF((Net_debt+A55)/Ebitda<=Covenant,1,0) -> 1 | E55: =IF(Capability>=Cap_floor,1,0) -> 1 | F55: =IF(INDEX($C$18:$I$18,1,B55+1)+MAX(P90-A55,0)<=Pool,1,0) -> 1 | G55: =C55*D55*E55*F55 -> 1
A56: =LumpyGrid!B39 -> 200 | B56: =LumpyGrid!C39 -> 6 | C56: =LumpyGrid!F39 -> 1 | D56: =IF((Net_debt+A56)/Ebitda<=Covenant,1,0) -> 1 | E56: =IF(Capability>=Cap_floor,1,0) -> 1 | F56: =IF(INDEX($C$18:$I$18,1,B56+1)+MAX(P90-A56,0)<=Pool,1,0) -> 1 | G56: =C56*D56*E56*F56 -> 1
A57: =LumpyGrid!B40 -> 250 | B57: =LumpyGrid!C40 -> 0 | C57: =LumpyGrid!F40 -> 0 | D57: =IF((Net_debt+A57)/Ebitda<=Covenant,1,0) -> 1 | E57: =IF(Capability>=Cap_floor,1,0) -> 1 | F57: =IF(INDEX($C$18:$I$18,1,B57+1)+MAX(P90-A57,0)<=Pool,1,0) -> 1 | G57: =C57*D57*E57*F57 -> 0
A58: =LumpyGrid!B41 -> 250 | B58: =LumpyGrid!C41 -> 1 | C58: =LumpyGrid!F41 -> 1 | D58: =IF((Net_debt+A58)/Ebitda<=Covenant,1,0) -> 1 | E58: =IF(Capability>=Cap_floor,1,0) -> 1 | F58: =IF(INDEX($C$18:$I$18,1,B58+1)+MAX(P90-A58,0)<=Pool,1,0) -> 1 | G58: =C58*D58*E58*F58 -> 1
A59: =LumpyGrid!B42 -> 250 | B59: =LumpyGrid!C42 -> 2 | C59: =LumpyGrid!F42 -> 1 | D59: =IF((Net_debt+A59)/Ebitda<=Covenant,1,0) -> 1 | E59: =IF(Capability>=Cap_floor,1,0) -> 1 | F59: =IF(INDEX($C$18:$I$18,1,B59+1)+MAX(P90-A59,0)<=Pool,1,0) -> 1 | G59: =C59*D59*E59*F59 -> 1
A60: =LumpyGrid!B43 -> 250 | B60: =LumpyGrid!C43 -> 3 | C60: =LumpyGrid!F43 -> 1 | D60: =IF((Net_debt+A60)/Ebitda<=Covenant,1,0) -> 1 | E60: =IF(Capability>=Cap_floor,1,0) -> 1 | F60: =IF(INDEX($C$18:$I$18,1,B60+1)+MAX(P90-A60,0)<=Pool,1,0) -> 1 | G60: =C60*D60*E60*F60 -> 1
A61: =LumpyGrid!B44 -> 250 | B61: =LumpyGrid!C44 -> 4 | C61: =LumpyGrid!F44 -> 1 | D61: =IF((Net_debt+A61)/Ebitda<=Covenant,1,0) -> 1 | E61: =IF(Capability>=Cap_floor,1,0) -> 1 | F61: =IF(INDEX($C$18:$I$18,1,B61+1)+MAX(P90-A61,0)<=Pool,1,0) -> 1 | G61: =C61*D61*E61*F61 -> 1
A62: =LumpyGrid!B45 -> 250 | B62: =LumpyGrid!C45 -> 5 | C62: =LumpyGrid!F45 -> 1 | D62: =IF((Net_debt+A62)/Ebitda<=Covenant,1,0) -> 1 | E62: =IF(Capability>=Cap_floor,1,0) -> 1 | F62: =IF(INDEX($C$18:$I$18,1,B62+1)+MAX(P90-A62,0)<=Pool,1,0) -> 1 | G62: =C62*D62*E62*F62 -> 1
A63: =LumpyGrid!B46 -> 250 | B63: =LumpyGrid!C46 -> 6 | C63: =LumpyGrid!F46 -> 1 | D63: =IF((Net_debt+A63)/Ebitda<=Covenant,1,0) -> 1 | E63: =IF(Capability>=Cap_floor,1,0) -> 1 | F63: =IF(INDEX($C$18:$I$18,1,B63+1)+MAX(P90-A63,0)<=Pool,1,0) -> 1 | G63: =C63*D63*E63*F63 -> 1
A64: =LumpyGrid!B47 -> 300 | B64: =LumpyGrid!C47 -> 0 | C64: =LumpyGrid!F47 -> 0 | D64: =IF((Net_debt+A64)/Ebitda<=Covenant,1,0) -> 1 | E64: =IF(Capability>=Cap_floor,1,0) -> 1 | F64: =IF(INDEX($C$18:$I$18,1,B64+1)+MAX(P90-A64,0)<=Pool,1,0) -> 1 | G64: =C64*D64*E64*F64 -> 0
A65: =LumpyGrid!B48 -> 300 | B65: =LumpyGrid!C48 -> 1 | C65: =LumpyGrid!F48 -> 1 | D65: =IF((Net_debt+A65)/Ebitda<=Covenant,1,0) -> 1 | E65: =IF(Capability>=Cap_floor,1,0) -> 1 | F65: =IF(INDEX($C$18:$I$18,1,B65+1)+MAX(P90-A65,0)<=Pool,1,0) -> 1 | G65: =C65*D65*E65*F65 -> 1
A66: =LumpyGrid!B49 -> 300 | B66: =LumpyGrid!C49 -> 2 | C66: =LumpyGrid!F49 -> 1 | D66: =IF((Net_debt+A66)/Ebitda<=Covenant,1,0) -> 1 | E66: =IF(Capability>=Cap_floor,1,0) -> 1 | F66: =IF(INDEX($C$18:$I$18,1,B66+1)+MAX(P90-A66,0)<=Pool,1,0) -> 1 | G66: =C66*D66*E66*F66 -> 1
A67: =LumpyGrid!B50 -> 300 | B67: =LumpyGrid!C50 -> 3 | C67: =LumpyGrid!F50 -> 1 | D67: =IF((Net_debt+A67)/Ebitda<=Covenant,1,0) -> 1 | E67: =IF(Capability>=Cap_floor,1,0) -> 1 | F67: =IF(INDEX($C$18:$I$18,1,B67+1)+MAX(P90-A67,0)<=Pool,1,0) -> 1 | G67: =C67*D67*E67*F67 -> 1
A68: =LumpyGrid!B51 -> 300 | B68: =LumpyGrid!C51 -> 4 | C68: =LumpyGrid!F51 -> 1 | D68: =IF((Net_debt+A68)/Ebitda<=Covenant,1,0) -> 1 | E68: =IF(Capability>=Cap_floor,1,0) -> 1 | F68: =IF(INDEX($C$18:$I$18,1,B68+1)+MAX(P90-A68,0)<=Pool,1,0) -> 1 | G68: =C68*D68*E68*F68 -> 1
A69: =LumpyGrid!B52 -> 300 | B69: =LumpyGrid!C52 -> 5 | C69: =LumpyGrid!F52 -> 1 | D69: =IF((Net_debt+A69)/Ebitda<=Covenant,1,0) -> 1 | E69: =IF(Capability>=Cap_floor,1,0) -> 1 | F69: =IF(INDEX($C$18:$I$18,1,B69+1)+MAX(P90-A69,0)<=Pool,1,0) -> 1 | G69: =C69*D69*E69*F69 -> 1
A70: =LumpyGrid!B53 -> 300 | B70: =LumpyGrid!C53 -> 6 | C70: =LumpyGrid!F53 -> 1 | D70: =IF((Net_debt+A70)/Ebitda<=Covenant,1,0) -> 1 | E70: =IF(Capability>=Cap_floor,1,0) -> 1 | F70: =IF(INDEX($C$18:$I$18,1,B70+1)+MAX(P90-A70,0)<=Pool,1,0) -> 1 | G70: =C70*D70*E70*F70 -> 1
A71: =LumpyGrid!B54 -> 350 | B71: =LumpyGrid!C54 -> 0 | C71: =LumpyGrid!F54 -> 0 | D71: =IF((Net_debt+A71)/Ebitda<=Covenant,1,0) -> 1 | E71: =IF(Capability>=Cap_floor,1,0) -> 1 | F71: =IF(INDEX($C$18:$I$18,1,B71+1)+MAX(P90-A71,0)<=Pool,1,0) -> 1 | G71: =C71*D71*E71*F71 -> 0
A72: =LumpyGrid!B55 -> 350 | B72: =LumpyGrid!C55 -> 1 | C72: =LumpyGrid!F55 -> 1 | D72: =IF((Net_debt+A72)/Ebitda<=Covenant,1,0) -> 1 | E72: =IF(Capability>=Cap_floor,1,0) -> 1 | F72: =IF(INDEX($C$18:$I$18,1,B72+1)+MAX(P90-A72,0)<=Pool,1,0) -> 1 | G72: =C72*D72*E72*F72 -> 1
A73: =LumpyGrid!B56 -> 350 | B73: =LumpyGrid!C56 -> 2 | C73: =LumpyGrid!F56 -> 1 | D73: =IF((Net_debt+A73)/Ebitda<=Covenant,1,0) -> 1 | E73: =IF(Capability>=Cap_floor,1,0) -> 1 | F73: =IF(INDEX($C$18:$I$18,1,B73+1)+MAX(P90-A73,0)<=Pool,1,0) -> 1 | G73: =C73*D73*E73*F73 -> 1
A74: =LumpyGrid!B57 -> 350 | B74: =LumpyGrid!C57 -> 3 | C74: =LumpyGrid!F57 -> 1 | D74: =IF((Net_debt+A74)/Ebitda<=Covenant,1,0) -> 1 | E74: =IF(Capability>=Cap_floor,1,0) -> 1 | F74: =IF(INDEX($C$18:$I$18,1,B74+1)+MAX(P90-A74,0)<=Pool,1,0) -> 1 | G74: =C74*D74*E74*F74 -> 1
A75: =LumpyGrid!B58 -> 350 | B75: =LumpyGrid!C58 -> 4 | C75: =LumpyGrid!F58 -> 1 | D75: =IF((Net_debt+A75)/Ebitda<=Covenant,1,0) -> 1 | E75: =IF(Capability>=Cap_floor,1,0) -> 1 | F75: =IF(INDEX($C$18:$I$18,1,B75+1)+MAX(P90-A75,0)<=Pool,1,0) -> 1 | G75: =C75*D75*E75*F75 -> 1
A76: =LumpyGrid!B59 -> 350 | B76: =LumpyGrid!C59 -> 5 | C76: =LumpyGrid!F59 -> 1 | D76: =IF((Net_debt+A76)/Ebitda<=Covenant,1,0) -> 1 | E76: =IF(Capability>=Cap_floor,1,0) -> 1 | F76: =IF(INDEX($C$18:$I$18,1,B76+1)+MAX(P90-A76,0)<=Pool,1,0) -> 1 | G76: =C76*D76*E76*F76 -> 1
A77: =LumpyGrid!B60 -> 350 | B77: =LumpyGrid!C60 -> 6 | C77: =LumpyGrid!F60 -> 1 | D77: =IF((Net_debt+A77)/Ebitda<=Covenant,1,0) -> 1 | E77: =IF(Capability>=Cap_floor,1,0) -> 1 | F77: =IF(INDEX($C$18:$I$18,1,B77+1)+MAX(P90-A77,0)<=Pool,1,0) -> 1 | G77: =C77*D77*E77*F77 -> 1
A78: =LumpyGrid!B61 -> 400 | B78: =LumpyGrid!C61 -> 0 | C78: =LumpyGrid!F61 -> 0 | D78: =IF((Net_debt+A78)/Ebitda<=Covenant,1,0) -> 1 | E78: =IF(Capability>=Cap_floor,1,0) -> 1 | F78: =IF(INDEX($C$18:$I$18,1,B78+1)+MAX(P90-A78,0)<=Pool,1,0) -> 1 | G78: =C78*D78*E78*F78 -> 0
A79: =LumpyGrid!B62 -> 400 | B79: =LumpyGrid!C62 -> 1 | C79: =LumpyGrid!F62 -> 1 | D79: =IF((Net_debt+A79)/Ebitda<=Covenant,1,0) -> 1 | E79: =IF(Capability>=Cap_floor,1,0) -> 1 | F79: =IF(INDEX($C$18:$I$18,1,B79+1)+MAX(P90-A79,0)<=Pool,1,0) -> 1 | G79: =C79*D79*E79*F79 -> 1
A80: =LumpyGrid!B63 -> 400 | B80: =LumpyGrid!C63 -> 2 | C80: =LumpyGrid!F63 -> 1 | D80: =IF((Net_debt+A80)/Ebitda<=Covenant,1,0) -> 1 | E80: =IF(Capability>=Cap_floor,1,0) -> 1 | F80: =IF(INDEX($C$18:$I$18,1,B80+1)+MAX(P90-A80,0)<=Pool,1,0) -> 1 | G80: =C80*D80*E80*F80 -> 1
A81: =LumpyGrid!B64 -> 400 | B81: =LumpyGrid!C64 -> 3 | C81: =LumpyGrid!F64 -> 1 | D81: =IF((Net_debt+A81)/Ebitda<=Covenant,1,0) -> 1 | E81: =IF(Capability>=Cap_floor,1,0) -> 1 | F81: =IF(INDEX($C$18:$I$18,1,B81+1)+MAX(P90-A81,0)<=Pool,1,0) -> 1 | G81: =C81*D81*E81*F81 -> 1
A82: =LumpyGrid!B65 -> 400 | B82: =LumpyGrid!C65 -> 4 | C82: =LumpyGrid!F65 -> 1 | D82: =IF((Net_debt+A82)/Ebitda<=Covenant,1,0) -> 1 | E82: =IF(Capability>=Cap_floor,1,0) -> 1 | F82: =IF(INDEX($C$18:$I$18,1,B82+1)+MAX(P90-A82,0)<=Pool,1,0) -> 1 | G82: =C82*D82*E82*F82 -> 1
A83: =LumpyGrid!B66 -> 400 | B83: =LumpyGrid!C66 -> 5 | C83: =LumpyGrid!F66 -> 1 | D83: =IF((Net_debt+A83)/Ebitda<=Covenant,1,0) -> 1 | E83: =IF(Capability>=Cap_floor,1,0) -> 1 | F83: =IF(INDEX($C$18:$I$18,1,B83+1)+MAX(P90-A83,0)<=Pool,1,0) -> 1 | G83: =C83*D83*E83*F83 -> 1
A84: =LumpyGrid!B67 -> 400 | B84: =LumpyGrid!C67 -> 6 | C84: =LumpyGrid!F67 -> 1 | D84: =IF((Net_debt+A84)/Ebitda<=Covenant,1,0) -> 1 | E84: =IF(Capability>=Cap_floor,1,0) -> 1 | F84: =IF(INDEX($C$18:$I$18,1,B84+1)+MAX(P90-A84,0)<=Pool,1,0) -> 1 | G84: =C84*D84*E84*F84 -> 1

Sheet ErrorBars
A1: Certify the answer: the sample's error (Definition 1.7; Online Appendix 1.B.4)
A2: Each breach odds estimated on N paths has standard error sqrt(p(1 - p)/N). The fresh paths are the same model drawn with the lab's seed, 26201.
A4: Paths | B4: =Paths_N -> 100000
A5: Standard error at 5 percent (points) | B5: =100*SQRT(Appetite*(1-Appetite)/Paths_N) -> 0.068920244
A6: The signed package's breach odds (engine) | B6: =LumpyGrid!J10 -> 0.04003
A7: Standard error at those odds (points) | B7: =100*SQRT(B6*(1-B6)/Paths_N) -> 0.061989998
A8: It clears the appetite by (points) | B8: =100*(Appetite-B6) -> 0.997
A9: ... in standard errors | B9: =B8/B7 -> 16.08324
A10: Rounded down: breach odds (engine) | B10: =LumpyGrid!J18 -> 0.09587
A11: Rounded down misses the appetite by (points) | B11: =100*(B10-Appetite) -> 4.587
A13: Package | B13: Line | C13: Delay | D13: Odds, the book's paths (engine) | E13: Odds, fresh paths (engine) | F13: Standard error, fresh | G13: Fresh against 5%, in standard errors
A14: continuous best | B14: 170 | C14: 0.66757636 | D14: 0.05 | E14: 0.05139 | F14: =SQRT(E14*(1-E14)/Paths_N) -> 0.00069820533 | G14: =(E14-Appetite)/F14 -> 1.9908184
A15: $121m, 1 quarter | B15: 121 | C15: 1 | D15: 0.04968 | E15: 0.05043 | F15: =SQRT(E15*(1-E15)/Paths_N) -> 0.000692003 | G15: =(E15-Appetite)/F15 -> 0.62138459
A16: $130m, 1 quarter | B16: 130 | C16: 1 | D16: 0.0463 | E16: 0.04695 | F16: =SQRT(E16*(1-E16)/Paths_N) -> 0.00066892225 | G16: =(E16-Appetite)/F16 -> -4.5595733
A17: $150m, 1 quarter | B17: 150 | C17: 1 | D17: 0.04003 | E17: 0.04124 | F17: =SQRT(E17*(1-E17)/Paths_N) -> 0.00062880253 | G17: =(E17-Appetite)/F17 -> -13.931242
A18: $200m, 1 quarter | B18: 200 | C18: 1 | D18: 0.03386 | E18: 0.03468 | F18: =SQRT(E18*(1-E18)/Paths_N) -> 0.00057859569 | G18: =(E18-Appetite)/F18 -> -26.477902
A19: $150m, no delay | B19: 150 | C19: 0 | D19: 0.09587 | E19: 0.09541 | F19: =SQRT(E19*(1-E19)/Paths_N) -> 0.00092901524 | G19: =(E19-Appetite)/F19 -> 48.879715

Sheet TwoChannelBudget
A1: A two-channel budget and its price (Online Appendix Example 1.B.2)
A2: Not about Meridian. Maximize a1 sqrt(x1) + a2 sqrt(x2) subject to x1 + x2 <= B: equal marginal returns at the optimum, and the multiplier is the price of the budget.
A4: Return on channel 1, a1 | B4: 3 | D4: x1 | E4: Value
A5: Return on channel 2, a2 | B5: 4 | D5: =$B$6*0/100 -> 0 | E5: =$B$4*SQRT(D5)+$B$5*SQRT($B$6-D5) -> 40
A6: Budget, B | B6: 100 | D6: =$B$6*1/100 -> 1 | E6: =$B$4*SQRT(D6)+$B$5*SQRT($B$6-D6) -> 42.799497
D7: =$B$6*2/100 -> 2 | E7: =$B$4*SQRT(D7)+$B$5*SQRT($B$6-D7) -> 43.84062
A8: x1* = B a1^2 / (a1^2 + a2^2) | B8: =B6*B4^2/(B4^2+B5^2) -> 36 | D8: =$B$6*3/100 -> 3 | E8: =$B$4*SQRT(D8)+$B$5*SQRT($B$6-D8) -> 44.591584
A9: x2* = B - x1* | B9: =B6-B8 -> 64 | D9: =$B$6*4/100 -> 4 | E9: =$B$4*SQRT(D9)+$B$5*SQRT($B$6-D9) -> 45.191836
A10: Value | B10: =B4*SQRT(B8)+B5*SQRT(B9) -> 50 | D10: =$B$6*5/100 -> 5 | E10: =$B$4*SQRT(D10)+$B$5*SQRT($B$6-D10) -> 45.695381
A11: Marginal return on channel 1 | B11: =B4/(2*SQRT(B8)) -> 0.25 | D11: =$B$6*6/100 -> 6 | E11: =$B$4*SQRT(D11)+$B$5*SQRT($B$6-D11) -> 46.129908
A12: Marginal return on channel 2 | B12: =B5/(2*SQRT(B9)) -> 0.25 | D12: =$B$6*7/100 -> 7 | E12: =$B$4*SQRT(D12)+$B$5*SQRT($B$6-D12) -> 46.511857
A13: The multiplier, lambda | B13: =B11 -> 0.25 | D13: =$B$6*8/100 -> 8 | E13: =$B$4*SQRT(D13)+$B$5*SQRT($B$6-D13) -> 46.851934
A14: Value of a budget B: sqrt(a1^2 + a2^2) sqrt(B) | B14: =SQRT(B4^2+B5^2)*SQRT(B6) -> 50 | D14: =$B$6*9/100 -> 9 | E14: =$B$4*SQRT(D14)+$B$5*SQRT($B$6-D14) -> 47.157568
A15: Its slope at B | B15: =SQRT(B4^2+B5^2)/(2*SQRT(B6)) -> 0.25 | D15: =$B$6*10/100 -> 10 | E15: =$B$4*SQRT(D15)+$B$5*SQRT($B$6-D15) -> 47.434165
A16: One more unit of budget is worth | B16: =SQRT(B4^2+B5^2)*(SQRT(B6+1)-SQRT(B6)) -> 0.24937811 | D16: =$B$6*11/100 -> 11 | E16: =$B$4*SQRT(D16)+$B$5*SQRT($B$6-D16) -> 47.685799
D17: =$B$6*12/100 -> 12 | E17: =$B$4*SQRT(D17)+$B$5*SQRT($B$6-D17) -> 47.915631
A18: A search along the budget line: best x1 | B18: =INDEX(D5:D105,MATCH(MAX(E5:E105),E5:E105,0)) -> 36 | D18: =$B$6*13/100 -> 13 | E18: =$B$4*SQRT(D18)+$B$5*SQRT($B$6-D18) -> 48.12617
A19: its value | B19: =MAX(E5:E105) -> 50 | D19: =$B$6*14/100 -> 14 | E19: =$B$4*SQRT(D19)+$B$5*SQRT($B$6-D19) -> 48.319446
D20: =$B$6*15/100 -> 15 | E20: =$B$4*SQRT(D20)+$B$5*SQRT($B$6-D20) -> 48.497128
D21: =$B$6*16/100 -> 16 | E21: =$B$4*SQRT(D21)+$B$5*SQRT($B$6-D21) -> 48.660606
D22: =$B$6*17/100 -> 17 | E22: =$B$4*SQRT(D22)+$B$5*SQRT($B$6-D22) -> 48.811051
D23: =$B$6*18/100 -> 18 | E23: =$B$4*SQRT(D23)+$B$5*SQRT($B$6-D23) -> 48.949463
D24: =$B$6*19/100 -> 19 | E24: =$B$4*SQRT(D24)+$B$5*SQRT($B$6-D24) -> 49.076697
D25: =$B$6*20/100 -> 20 | E25: =$B$4*SQRT(D25)+$B$5*SQRT($B$6-D25) -> 49.193496
D26: =$B$6*21/100 -> 21 | E26: =$B$4*SQRT(D26)+$B$5*SQRT($B$6-D26) -> 49.300505
D27: =$B$6*22/100 -> 22 | E27: =$B$4*SQRT(D27)+$B$5*SQRT($B$6-D27) -> 49.398291
D28: =$B$6*23/100 -> 23 | E28: =$B$4*SQRT(D28)+$B$5*SQRT($B$6-D28) -> 49.487352
D29: =$B$6*24/100 -> 24 | E29: =$B$4*SQRT(D29)+$B$5*SQRT($B$6-D29) -> 49.56813
D30: =$B$6*25/100 -> 25 | E30: =$B$4*SQRT(D30)+$B$5*SQRT($B$6-D30) -> 49.641016
D31: =$B$6*26/100 -> 26 | E31: =$B$4*SQRT(D31)+$B$5*SQRT($B$6-D31) -> 49.70636
D32: =$B$6*27/100 -> 27 | E32: =$B$4*SQRT(D32)+$B$5*SQRT($B$6-D32) -> 49.764472
D33: =$B$6*28/100 -> 28 | E33: =$B$4*SQRT(D33)+$B$5*SQRT($B$6-D33) -> 49.815633
D34: =$B$6*29/100 -> 29 | E34: =$B$4*SQRT(D34)+$B$5*SQRT($B$6-D34) -> 49.860094
D35: =$B$6*30/100 -> 30 | E35: =$B$4*SQRT(D35)+$B$5*SQRT($B$6-D35) -> 49.898078
D36: =$B$6*31/100 -> 31 | E36: =$B$4*SQRT(D36)+$B$5*SQRT($B$6-D36) -> 49.929789
D37: =$B$6*32/100 -> 32 | E37: =$B$4*SQRT(D37)+$B$5*SQRT($B$6-D37) -> 49.955408
D38: =$B$6*33/100 -> 33 | E38: =$B$4*SQRT(D38)+$B$5*SQRT($B$6-D38) -> 49.975099
D39: =$B$6*34/100 -> 34 | E39: =$B$4*SQRT(D39)+$B$5*SQRT($B$6-D39) -> 49.989009
D40: =$B$6*35/100 -> 35 | E40: =$B$4*SQRT(D40)+$B$5*SQRT($B$6-D40) -> 49.99727
D41: =$B$6*36/100 -> 36 | E41: =$B$4*SQRT(D41)+$B$5*SQRT($B$6-D41) -> 50
D42: =$B$6*37/100 -> 37 | E42: =$B$4*SQRT(D42)+$B$5*SQRT($B$6-D42) -> 49.997303
D43: =$B$6*38/100 -> 38 | E43: =$B$4*SQRT(D43)+$B$5*SQRT($B$6-D43) -> 49.989274
D44: =$B$6*39/100 -> 39 | E44: =$B$4*SQRT(D44)+$B$5*SQRT($B$6-D44) -> 49.975993
D45: =$B$6*40/100 -> 40 | E45: =$B$4*SQRT(D45)+$B$5*SQRT($B$6-D45) -> 49.957533
D46: =$B$6*41/100 -> 41 | E46: =$B$4*SQRT(D46)+$B$5*SQRT($B$6-D46) -> 49.933956
D47: =$B$6*42/100 -> 42 | E47: =$B$4*SQRT(D47)+$B$5*SQRT($B$6-D47) -> 49.905315
D48: =$B$6*43/100 -> 43 | E48: =$B$4*SQRT(D48)+$B$5*SQRT($B$6-D48) -> 49.871653
D49: =$B$6*44/100 -> 44 | E49: =$B$4*SQRT(D49)+$B$5*SQRT($B$6-D49) -> 49.833008
D50: =$B$6*45/100 -> 45 | E50: =$B$4*SQRT(D50)+$B$5*SQRT($B$6-D50) -> 49.789406
D51: =$B$6*46/100 -> 46 | E51: =$B$4*SQRT(D51)+$B$5*SQRT($B$6-D51) -> 49.740867
D52: =$B$6*47/100 -> 47 | E52: =$B$4*SQRT(D52)+$B$5*SQRT($B$6-D52) -> 49.687403
D53: =$B$6*48/100 -> 48 | E53: =$B$4*SQRT(D53)+$B$5*SQRT($B$6-D53) -> 49.62902
D54: =$B$6*49/100 -> 49 | E54: =$B$4*SQRT(D54)+$B$5*SQRT($B$6-D54) -> 49.565714
D55: =$B$6*50/100 -> 50 | E55: =$B$4*SQRT(D55)+$B$5*SQRT($B$6-D55) -> 49.497475
D56: =$B$6*51/100 -> 51 | E56: =$B$4*SQRT(D56)+$B$5*SQRT($B$6-D56) -> 49.424285
D57: =$B$6*52/100 -> 52 | E57: =$B$4*SQRT(D57)+$B$5*SQRT($B$6-D57) -> 49.346121
D58: =$B$6*53/100 -> 53 | E58: =$B$4*SQRT(D58)+$B$5*SQRT($B$6-D58) -> 49.262948
D59: =$B$6*54/100 -> 54 | E59: =$B$4*SQRT(D59)+$B$5*SQRT($B$6-D59) -> 49.174728
D60: =$B$6*55/100 -> 55 | E60: =$B$4*SQRT(D60)+$B$5*SQRT($B$6-D60) -> 49.081411
D61: =$B$6*56/100 -> 56 | E61: =$B$4*SQRT(D61)+$B$5*SQRT($B$6-D61) -> 48.982943
D62: =$B$6*57/100 -> 57 | E62: =$B$4*SQRT(D62)+$B$5*SQRT($B$6-D62) -> 48.879257
D63: =$B$6*58/100 -> 58 | E63: =$B$4*SQRT(D63)+$B$5*SQRT($B$6-D63) -> 48.770282
D64: =$B$6*59/100 -> 59 | E64: =$B$4*SQRT(D64)+$B$5*SQRT($B$6-D64) -> 48.655934
D65: =$B$6*60/100 -> 60 | E65: =$B$4*SQRT(D65)+$B$5*SQRT($B$6-D65) -> 48.536121
D66: =$B$6*61/100 -> 61 | E66: =$B$4*SQRT(D66)+$B$5*SQRT($B$6-D66) -> 48.410741
D67: =$B$6*62/100 -> 62 | E67: =$B$4*SQRT(D67)+$B$5*SQRT($B$6-D67) -> 48.27968
D68: =$B$6*63/100 -> 63 | E68: =$B$4*SQRT(D68)+$B$5*SQRT($B$6-D68) -> 48.142812
D69: =$B$6*64/100 -> 64 | E69: =$B$4*SQRT(D69)+$B$5*SQRT($B$6-D69) -> 48
D70: =$B$6*65/100 -> 65 | E70: =$B$4*SQRT(D70)+$B$5*SQRT($B$6-D70) -> 47.851092
D71: =$B$6*66/100 -> 66 | E71: =$B$4*SQRT(D71)+$B$5*SQRT($B$6-D71) -> 47.695923
D72: =$B$6*67/100 -> 67 | E72: =$B$4*SQRT(D72)+$B$5*SQRT($B$6-D72) -> 47.534309
D73: =$B$6*68/100 -> 68 | E73: =$B$4*SQRT(D73)+$B$5*SQRT($B$6-D73) -> 47.366051
D74: =$B$6*69/100 -> 69 | E74: =$B$4*SQRT(D74)+$B$5*SQRT($B$6-D74) -> 47.190929
D75: =$B$6*70/100 -> 70 | E75: =$B$4*SQRT(D75)+$B$5*SQRT($B$6-D75) -> 47.008703
D76: =$B$6*71/100 -> 71 | E76: =$B$4*SQRT(D76)+$B$5*SQRT($B$6-D76) -> 46.819109
D77: =$B$6*72/100 -> 72 | E77: =$B$4*SQRT(D77)+$B$5*SQRT($B$6-D77) -> 46.621855
D78: =$B$6*73/100 -> 73 | E78: =$B$4*SQRT(D78)+$B$5*SQRT($B$6-D78) -> 46.416621
D79: =$B$6*74/100 -> 74 | E79: =$B$4*SQRT(D79)+$B$5*SQRT($B$6-D79) -> 46.203054
D80: =$B$6*75/100 -> 75 | E80: =$B$4*SQRT(D80)+$B$5*SQRT($B$6-D80) -> 45.980762
D81: =$B$6*76/100 -> 76 | E81: =$B$4*SQRT(D81)+$B$5*SQRT($B$6-D81) -> 45.749312
D82: =$B$6*77/100 -> 77 | E82: =$B$4*SQRT(D82)+$B$5*SQRT($B$6-D82) -> 45.508219
D83: =$B$6*78/100 -> 78 | E83: =$B$4*SQRT(D83)+$B$5*SQRT($B$6-D83) -> 45.256946
D84: =$B$6*79/100 -> 79 | E84: =$B$4*SQRT(D84)+$B$5*SQRT($B$6-D84) -> 44.994886
D85: =$B$6*80/100 -> 80 | E85: =$B$4*SQRT(D85)+$B$5*SQRT($B$6-D85) -> 44.72136
D86: =$B$6*81/100 -> 81 | E86: =$B$4*SQRT(D86)+$B$5*SQRT($B$6-D86) -> 44.435596
D87: =$B$6*82/100 -> 82 | E87: =$B$4*SQRT(D87)+$B$5*SQRT($B$6-D87) -> 44.136718
D88: =$B$6*83/100 -> 83 | E88: =$B$4*SQRT(D88)+$B$5*SQRT($B$6-D88) -> 43.823723
D89: =$B$6*84/100 -> 84 | E89: =$B$4*SQRT(D89)+$B$5*SQRT($B$6-D89) -> 43.495454
D90: =$B$6*85/100 -> 85 | E90: =$B$4*SQRT(D90)+$B$5*SQRT($B$6-D90) -> 43.150567
D91: =$B$6*86/100 -> 86 | E91: =$B$4*SQRT(D91)+$B$5*SQRT($B$6-D91) -> 42.787485
D92: =$B$6*87/100 -> 87 | E92: =$B$4*SQRT(D92)+$B$5*SQRT($B$6-D92) -> 42.404342
D93: =$B$6*88/100 -> 88 | E93: =$B$4*SQRT(D93)+$B$5*SQRT($B$6-D93) -> 41.998901
D94: =$B$6*89/100 -> 89 | E94: =$B$4*SQRT(D94)+$B$5*SQRT($B$6-D94) -> 41.568443
D95: =$B$6*90/100 -> 90 | E95: =$B$4*SQRT(D95)+$B$5*SQRT($B$6-D95) -> 41.10961
D96: =$B$6*91/100 -> 91 | E96: =$B$4*SQRT(D96)+$B$5*SQRT($B$6-D96) -> 40.618176
D97: =$B$6*92/100 -> 92 | E97: =$B$4*SQRT(D97)+$B$5*SQRT($B$6-D97) -> 40.088698
D98: =$B$6*93/100 -> 93 | E98: =$B$4*SQRT(D98)+$B$5*SQRT($B$6-D98) -> 39.513958
D99: =$B$6*94/100 -> 94 | E99: =$B$4*SQRT(D99)+$B$5*SQRT($B$6-D99) -> 38.884038
D100: =$B$6*95/100 -> 95 | E100: =$B$4*SQRT(D100)+$B$5*SQRT($B$6-D100) -> 38.184655
D101: =$B$6*96/100 -> 96 | E101: =$B$4*SQRT(D101)+$B$5*SQRT($B$6-D101) -> 37.393877
...

Sheet Reference_Values
A1: Checkpoint | B1: Engine value | C1: Meaning (where in the book)
A2: Continuous best: line | B2: 170 | C2: Worked Example 1.1, Step 3: $170 million
A3: Continuous best: delay (quarters) | B3: 0.66757636 | C3: 0.67 quarters, two months
A4: Continuous best: cost | B4: 10.440611 | C4: $10.44 million
A5: Flat optimum: lines within $0.5m from | B5: 140 | C5: Volume I: $140m
A6: Flat optimum: to | B6: 205 | C6: Volume I: $205m
A7: Delay alone (quarters) | B7: 5.0946732 | C7: More than five quarters (5.09)
A8: $4m a quarter: continuous line | B8: 140 | C8: Worked Example 1.1, Step 5: $140 million
A9: $4m a quarter: continuous cost | B9: 7.5246248 | C9: $7.52 million
A10: $16m a quarter: continuous line | B10: 195 | C10: $195 million
A11: $16m a quarter: continuous delay | B11: 0.60392968 | C11: 0.60 quarters
A12: $16m a quarter: continuous cost | B12: 15.512875 | C12: $15.51 million
A13: The board's number moves the line by | B13: 55 | C13: What the board should take away: $55 million of line
... A54: Two-channel budget: search along the line | B54: 36 | C54: 36

Sheet Checks
A1: Checkpoint | B1: Workbook formula value | C1: Engine value | D1: |diff| | E1: Tolerance | F1: Status
A2: Continuous best: line | B2: =Continuous!H6 -> 170 | C2: =Reference_Values!B2 -> 170 | D2: =ABS(B2-C2) -> 0 | E2: 0 | F2: =IF(D2<=E2,"PASS","FAIL") -> PASS
A3: Continuous best: delay (quarters) | B3: =Continuous!H7 -> 0.66757636 | C3: =Reference_Values!B3 -> 0.66757636 | D3: =ABS(B3-C3) -> 0 | E3: 1e-09 | F3: =IF(D3<=E3,"PASS","FAIL") -> PASS
A4: Continuous best: cost | B4: =Continuous!H5 -> 10.440611 | C4: =Reference_Values!B4 -> 10.440611 | D4: =ABS(B4-C4) -> 0 | E4: 1e-09 | F4: =IF(D4<=E4,"PASS","FAIL") -> PASS
A5: Flat optimum: lines within $0.5m from | B5: =Continuous!H12 -> 140 | C5: =Reference_Values!B5 -> 140 | D5: =ABS(B5-C5) -> 0 | E5: 0 | F5: =IF(D5<=E5,"PASS","FAIL") -> PASS
A6: Flat optimum: to | B6: =Continuous!H13 -> 205 | C6: =Reference_Values!B6 -> 205 | D6: =ABS(B6-C6) -> 0 | E6: 0 | F6: =IF(D6<=E6,"PASS","FAIL") -> PASS
A7: Delay alone (quarters) | B7: =Continuous!H14 -> 5.0946732 | C7: =Reference_Values!B7 -> 5.0946732 | D7: =ABS(B7-C7) -> 0 | E7: 1e-09 | F7: =IF(D7<=E7,"PASS","FAIL") -> PASS
A8: $4m a quarter: continuous line | B8: =Continuous!I6 -> 140 | C8: =Reference_Values!B8 -> 140 | D8: =ABS(B8-C8) -> 0 | E8: 0 | F8: =IF(D8<=E8,"PASS","FAIL") -> PASS
A9: $4m a quarter: continuous cost | B9: =Continuous!I5 -> 7.5246248 | C9: =Reference_Values!B9 -> 7.5246248 | D9: =ABS(B9-C9) -> 0 | E9: 1e-09 | F9: =IF(D9<=E9,"PASS","FAIL") -> PASS
A10: $16m a quarter: continuous line | B10: =Continuous!J6 -> 195 | C10: =Reference_Values!B10 -> 195 | D10: =ABS(B10-C10) -> 0 | E10: 0 | F10: =IF(D10<=E10,"PASS","FAIL") -> PASS
A11: $16m a quarter: continuous delay | B11: =Continuous!J7 -> 0.60392968 | C11: =Reference_Values!B11 -> 0.60392968 | D11: =ABS(B11-C11) -> 0 | E11: 1e-09 | F11: =IF(D11<=E11,"PASS","FAIL") -> PASS
A12: $16m a quarter: continuous cost | B12: =Continuous!J5 -> 15.512875 | C12: =Reference_Values!B12 -> 15.512875 | D12: =ABS(B12-C12) -> 0 | E12: 1e-09 | F12: =IF(D12<=E12,"PASS","FAIL") -> PASS
A13: The board's number moves the line by | B13: =Continuous!H18 -> 55 | C13: =Reference_Values!B13 -> 55 | D13: =ABS(B13-C13) -> 0 | E13: 0 | F13: =IF(D13<=E13,"PASS","FAIL") -> PASS
A14: A 90th-percentile closure | B14: =P90 -> 186.86698 | C14: =Reference_Values!B14 -> 186.86698 | D14: =ABS(B14-C14) -> 0 | E14: 1e-06 | F14: =IF(D14<=E14,"PASS","FAIL") -> PASS
A15: (R2) joint check with the package | B15: =Gates!B16 -> 138.50134 | C15: =Reference_Values!B15 -> 138.50134 | D15: =ABS(B15-C15) -> 0 | E15: 1e-06 | F15: =IF(D15<=E15,"PASS","FAIL") -> PASS
A16: (R2) with the line removed | B16: =Gates!B21 -> 308.50134 | C16: =Reference_Values!B16 -> 308.50134 | D16: =ABS(B16-C16) -> 0 | E16: 1e-06 | F16: =IF(D16<=E16,"PASS","FAIL") -> PASS
A17: Volume I's declaration before its levers | B17: =Gates!B28 -> 324.91659 | C17: =Reference_Values!B17 -> 324.91659 | D17: =ABS(B17-C17) -> 0 | E17: 1e-06 | F17: =IF(D17<=E17,"PASS","FAIL") -> PASS
A18: (R3) spectral radius of the feedback core | B18: =Gates!C10 -> 0.8 | C18: =Reference_Values!B18 -> 0.8 | D18: =ABS(B18-C18) -> 0 | E18: 1e-09 | F18: =IF(D18<=E18,"PASS","FAIL") -> PASS
A19: (R4) leverage with Volume I's line fully drawn | B19: =Gates!C12 -> 3.7430186 | C19: =Reference_Values!B19 -> 3.7430186 | D19: =ABS(B19-C19) -> 0 | E19: 1e-09 | F19: =IF(D19<=E19,"PASS","FAIL") -> PASS
A20: Lumpy packages | B20: =LumpyGrid!J5 -> 63 | C20: =Reference_Values!B20 -> 63 | D20: =ABS(B20-C20) -> 0 | E20: 0 | F20: =IF(D20<=E20,"PASS","FAIL") -> PASS
A21: Lumpy packages meeting the appetite | B21: =LumpyGrid!J6 -> 46 | C21: =Reference_Values!B21 -> 46 | D21: =ABS(B21-C21) -> 0 | E21: 0 | F21: =IF(D21<=E21,"PASS","FAIL") -> PASS
A22: Best lumpy package: line | B22: =LumpyGrid!J8 -> 150 | C22: =Reference_Values!B22 -> 150 | D22: =ABS(B22-C22) -> 0 | E22: 0 | F22: =IF(D22<=E22,"PASS","FAIL") -> PASS
A23: Best lumpy package: delay | B23: =LumpyGrid!J9 -> 1 | C23: =Reference_Values!B23 -> 1 | D23: =ABS(B23-C23) -> 0 | E23: 0 | F23: =IF(D23<=E23,"PASS","FAIL") -> PASS
A24: Best lumpy package: cost | B24: =LumpyGrid!J7 -> 12.5 | C24: =Reference_Values!B24 -> 12.5 | D24: =ABS(B24-C24) -> 0 | E24: 1e-09 | F24: =IF(D24<=E24,"PASS","FAIL") -> PASS
A25: Rounded down: line | B25: =LumpyGrid!J16 -> 150 | C25: =Reference_Values!B25 -> 150 | D25: =ABS(B25-C25) -> 0 | E25: 0 | F25: =IF(D25<=E25,"PASS","FAIL") -> PASS
A26: Rounded down: breach odds | B26: =LumpyGrid!J18 -> 0.09587 | C26: =Reference_Values!B26 -> 0.09587 | D26: =ABS(B26-C26) -> 0 | E26: 1e-12 | F26: =IF(D26<=E26,"PASS","FAIL") -> PASS
A27: Rounded up: delay | B27: =LumpyGrid!J23 -> 1 | C27: =Reference_Values!B27 -> 1 | D27: =ABS(B27-C27) -> 0 | E27: 0 | F27: =IF(D27<=E27,"PASS","FAIL") -> PASS
A28: Rounded up: cost | B28: =LumpyGrid!J25 -> 14 | C28: =Reference_Values!B28 -> 14 | D28: =ABS(B28-C28) -> 0 | E28: 1e-09 | F28: =IF(D28<=E28,"PASS","FAIL") -> PASS
A29: Whole quarters, $1m steps: cost | B29: =FinerLines!E15 -> 11.63 | C29: =Reference_Values!B29 -> 11.63 | D29: =ABS(B29-C29) -> 0 | E29: 1e-09 | F29: =IF(D29<=E29,"PASS","FAIL") -> PASS
A30: $10m tranches: cost | B30: =FinerLines!E16 -> 11.9 | C30: =Reference_Values!B30 -> 11.9 | D30: =ABS(B30-C30) -> 0 | E30: 1e-09 | F30: =IF(D30<=E30,"PASS","FAIL") -> PASS
A31: The lumps cost | B31: =FinerLines!E21 -> 2.0593891 | C31: =Reference_Values!B31 -> 2.0593891 | D31: =ABS(B31-C31) -> 0 | E31: 1e-09 | F31: =IF(D31<=E31,"PASS","FAIL") -> PASS
A32: of which whole quarters | B32: =FinerLines!E22 -> 1.1893891 | C32: =Reference_Values!B32 -> 1.1893891 | D32: =ABS(B32-C32) -> 0 | E32: 1e-09 | F32: =IF(D32<=E32,"PASS","FAIL") -> PASS
A33: then $50m tranches | B33: =FinerLines!E23 -> 0.87 | C33: =Reference_Values!B33 -> 0.87 | D33: =ABS(B33-C33) -> 0 | E33: 1e-09 | F33: =IF(D33<=E33,"PASS","FAIL") -> PASS
A34: $10m tranches would save | B34: =FinerLines!E24 -> 0.6 | C34: =Reference_Values!B34 -> 0.6 | D34: =ABS(B34-C34) -> 0 | E34: 1e-09 | F34: =IF(D34<=E34,"PASS","FAIL") -> PASS
A35: Two quarters: least line in $1m steps | B35: =FinerLines!B7 -> 70 | C35: =Reference_Values!B35 -> 70 | D35: =ABS(B35-C35) -> 0 | E35: 0 | F35: =IF(D35<=E35,"PASS","FAIL") -> PASS
A36: Two quarters: $50m package cost | B36: =FinerLines!J7 -> 19 | C36: =Reference_Values!B36 -> 19 | D36: =ABS(B36-C36) -> 0 | E36: 1e-09 | F36: =IF(D36<=E36,"PASS","FAIL") -> PASS
A37: Packages whose rank changes when rescaled | B37: =Reweight!K5 -> 0 | C37: =Reference_Values!B37 -> 0 | D37: =ABS(B37-C37) -> 0 | E37: 0 | F37: =IF(D37<=E37,"PASS","FAIL") -> PASS
A38: The lumpy answer holds above (a quarter) | B38: =Reweight!K15 -> 1.5 | C38: =Reference_Values!B38 -> 1.5 | D38: =ABS(B38-C38) -> 0 | E38: 1e-09 | F38: =IF(D38<=E38,"PASS","FAIL") -> PASS
A39: $16m: the nearest package (200, 1) | B39: =Reweight!K19 -> 22 | C39: =Reference_Values!B39 -> 22 | D39: =ABS(B39-C39) -> 0 | E39: 1e-09 | F39: =IF(D39<=E39,"PASS","FAIL") -> PASS
A40: $16m: the signed package (150, 1) | B40: =Reweight!K20 -> 20.5 | C40: =Reference_Values!B40 -> 20.5 | D40: =ABS(B40-C40) -> 0 | E40: 1e-09 | F40: =IF(D40<=E40,"PASS","FAIL") -> PASS
A41: Feasible with all four commitments | B41: =Commitments!L8 -> 46 | C41: =Reference_Values!B41 -> 46 | D41: =ABS(B41-C41) -> 0 | E41: 0 | F41: =IF(D41<=E41,"PASS","FAIL") -> PASS
A42: The covenant binds above a line of | B42: =Commitments!L11 -> 545.16 | C42: =Reference_Values!B42 -> 545.16 | D42: =ABS(B42-C42) -> 0 | E42: 1e-06 | F42: =IF(D42<=E42,"PASS","FAIL") -> PASS
A43: Signed package: leverage, line fully drawn | B43: =Commitments!L18 -> 3.7026634 | C43: =Reference_Values!B43 -> 3.7026634 | D43: =ABS(B43-C43) -> 0 | E43: 1e-09 | F43: =IF(D43<=E43,"PASS","FAIL") -> PASS
A44: Signed package: joint-check claims | B44: =Commitments!L22 -> 150.32727 | C44: =Reference_Values!B44 -> 150.32727 | D44: =ABS(B44-C44) -> 0 | E44: 1e-06 | F44: =IF(D44<=E44,"PASS","FAIL") -> PASS
A45: Cash above the floor unclaimed | B45: =Commitments!L23 -> 119.67273 | C45: =Reference_Values!B45 -> 119.67273 | D45: =ABS(B45-C45) -> 0 | E45: 1e-06 | F45: =IF(D45<=E45,"PASS","FAIL") -> PASS
A46: Standard error near 5% (points) | B46: =ErrorBars!B5 -> 0.068920244 | C46: =Reference_Values!B46 -> 0.068920244 | D46: =ABS(B46-C46) -> 0 | E46: 1e-09 | F46: =IF(D46<=E46,"PASS","FAIL") -> PASS
A47: Standard error near 4% (points) | B47: =ErrorBars!B7 -> 0.061989998 | C47: =Reference_Values!B47 -> 0.061989998 | D47: =ABS(B47-C47) -> 0 | E47: 1e-09 | F47: =IF(D47<=E47,"PASS","FAIL") -> PASS
A48: Lumpy margin in standard errors | B48: =ErrorBars!B9 -> 16.08324 | C48: =Reference_Values!B48 -> 16.08324 | D48: =ABS(B48-C48) -> 0 | E48: 1e-06 | F48: =IF(D48<=E48,"PASS","FAIL") -> PASS
A49: Rounding down misses by (points) | B49: =ErrorBars!B11 -> 4.587 | C49: =Reference_Values!B49 -> 4.587 | D49: =ABS(B49-C49) -> 0 | E49: 1e-09 | F49: =IF(D49<=E49,"PASS","FAIL") -> PASS
A50: Two-channel budget: x1* | B50: =TwoChannelBudget!B8 -> 36 | C50: =Reference_Values!B50 -> 36 | D50: =ABS(B50-C50) -> 0 | E50: 1e-09 | F50: =IF(D50<=E50,"PASS","FAIL") -> PASS
A51: Two-channel budget: value | B51: =TwoChannelBudget!B10 -> 50 | C51: =Reference_Values!B51 -> 50 | D51: =ABS(B51-C51) -> 0 | E51: 1e-09 | F51: =IF(D51<=E51,"PASS","FAIL") -> PASS
A52: Two-channel budget: multiplier | B52: =TwoChannelBudget!B13 -> 0.25 | C52: =Reference_Values!B52 -> 0.25 | D52: =ABS(B52-C52) -> 0 | E52: 1e-09 | F52: =IF(D52<=E52,"PASS","FAIL") -> PASS
A53: Two-channel budget: slope of 5 sqrt(B) at 100 | B53: =TwoChannelBudget!B15 -> 0.25 | C53: =Reference_Values!B53 -> 0.25 | D53: =ABS(B53-C53) -> 0 | E53: 1e-09 | F53: =IF(D53<=E53,"PASS","FAIL") -> PASS
A54: Two-channel budget: search along the line | B54: =TwoChannelBudget!B18 -> 36 | C54: =Reference_Values!B54 -> 36 | D54: =ABS(B54-C54) -> 0 | E54: 0 | F54: =IF(D54<=E54,"PASS","FAIL") -> PASS
A56: All checkpoints | F56: =IF(COUNTIF(F2:F54,"PASS")=53,"ALL PASS","CHECK") -> ALL PASS
