Workbook

Sheet README
B1: DCT Laboratory — Vol I, Ch 14: Mathematical Analysis of the Unified Enterprise Transformation Architecture
B2: Seed 26114 · Companion to DCT_V1_Ch14_Lab.ipynb and AXIOM Lab 1.14 (module AXIOM-14). Money in $ million.
B4: Worked Example 14.1, Can Meridian Afford the New Link?, with the book's declarations, and the five steps of AXIOM Lab 1.14, How Close to the Edge Is Meridian?
B5: Declarations: the core register's ceiling, the stability bench's gains (edit them), the board's rule, and the runway of Section 14.6.
B6: Bench: the register M from e, t and h; its radius (Online Appendix 14.B.1, checked by MDETERM), clocks, Lyapunov bowl and echo; the settled deviation solved exactly, in closed form and by the sensitivity recursion (Theorems 14.3 and 14.4; lab step 1).
B7: Rebudget: Table 14.4, the three repairs and the frontier, and the echo of every register (Figure 14.3; Worked Example 14.1, Steps 3-4).
B8: Clocks: half-life and amplification against the spectral radius (Figure 14.1).
B9: Sensitivity: the multiplier walk by walk, the Perron-weighted identity, elasticity tables and the blow-up dial (Theorem 14.4; lab step 2).
B10: Perturbations: a state shock, a recalibration and the structural change (Definition 14.7; Worked Example 14.1, Step 5; lab step 3).
B11: Runway: the viability sets V_j and the kernel, the fastest-cuts path and the two repairs (Theorem 14.5(iii)-(iv); Figure 14.2; Online Appendix 14.B.2; lab step 4).
B12: Audit: Table 14.2's five tests, the complexity panel, the gain audit and three tripwires (Definition 14.11; Theorems 14.6(ii) and 14.7(iv); lab step 5).
B13: The fresh draws (seed 26114) and the viability iteration on a grid run in the notebook. Reference_Values and Checks: the notebook engine's numbers and a PASS/FAIL comparison with this workbook's formulas.
... B19: Cross-sheet link: green.

Sheet Declarations
A1: Declarations (Worked Example 14.1; Section 14.6). Money in $ million; gains are the share of a quarter's deviation passed on per link.
A3: Quantity | B3: Value | C3: Source
A4: Register ceiling per link | B4: 0.4 | C4: Section 12.7: no unit passes on more than 40 percent of a quarter's deviation to a linked unit
A5: Stability bench: engineering links, e | B5: 0.4 | C5: Today 0.40. Edit e, t and h to explore (AXIOM Lab 1.14, step 1); the Checks expect today's values
A6: Stability bench: treasury links, t | B6: 0.4 | C6: Today 0.40
A7: Stability bench: new Digital-Industrial Systems link, h | B7: 0 | C7: Today 0; the second phase of the digital program adds it, with a ceiling of 0.40
A8: The board's rule: half-life at most (quarters) | B8: 4 | C8: Any deviation must halve within a year
A9: The rule as a spectral radius, 0.5^(1/half-life) | B9: =0.5^(1/B8) -> 0.84089642 | C9: 2^(-1/4) = 0.8409 (Worked Example 14.1, Step 3)
A10: Shock, or permanent shortfall a quarter, at Digital ($ million) | B10: 10 | C10: Worked Example 14.1, Steps 1-2
A11: A company near the edge: spectral radius | B11: 0.95 | C11: Figure 14.1
A13: The runway (Section 14.6; a unit, not Meridian) | B13: Value | C13: Source
A14: Cash above the floor ($ million) | B14: 120 | C14: Section 14.6; Figure 14.2
A15: Burn a quarter ($ million) | B15: 50 | C15: Section 14.6
A16: Largest cut of the burn a quarter ($ million) | B16: 10 | C16: Commitments and notice periods
A17: Faster cuts: exit clauses allow ($ million a quarter) | B17: 15 | C17: The second repair
A18: Cuts in between ($ million a quarter) | B18: 12.5 | C18: Online Appendix 14.B.2: still too slow
A19: Feasible region: cash above the floor at most ($ million) | B19: 500 | C19: Appendix 14.A, proof of Theorem 14.5(iv)
A20: Feasible region: burn at most ($ million a quarter) | B20: 60 | C20: Appendix 14.A
A22: The core: Industrial Systems (IND), Digital (DIG), engineering (ENG) and treasury (TRS); IND and DIG are each wired both ways to ENG and TRS (Worked Example 9.1). With every link at its ceiling, deviations follow x' = M x each quarter (Chapter 12's echo).
A23: The runway: s' = s - r and r' = max(r - u, 0), with 0 <= u <= the largest cut; feasible while 0 <= s <= 500 and 0 <= r <= 60.

Sheet Bench
A1: Stability bench: the register, its radius, clocks and Lyapunov bowl (Theorem 14.3; Worked Example 14.1, Steps 1-2; AXIOM Lab 1.14, step 1)
A2: Edit the bench's gains e, t, h on Declarations. Entry (i, j) is the share of unit j's deviation that unit i receives in the next quarter.
A3: Register M (rows receive) | B3: IND | C3: DIG | D3: ENG | E3: TRS | G3: M - rho I | H3: IND | I3: DIG | J3: ENG | K3: TRS | M3: I - M | N3: IND | O3: DIG | P3: ENG | Q3: TRS
A4: Industrial Systems | B4: 0 | C4: =Bench_h -> 0 | D4: =Bench_e -> 0.4 | E4: =Bench_t -> 0.4 | G4: Industrial Systems | H4: =B4-$B$10 -> -0.8 | I4: =C4 -> 0 | J4: =D4 -> 0.4 | K4: =E4 -> 0.4 | M4: Industrial Systems | N4: =1-B4 -> 1 | O4: =-C4 -> 0 | P4: =-D4 -> -0.4 | Q4: =-E4 -> -0.4
A5: Digital | B5: =Bench_h -> 0 | C5: 0 | D5: =Bench_e -> 0.4 | E5: =Bench_t -> 0.4 | G5: Digital | H5: =B5 -> 0 | I5: =C5-$B$10 -> -0.8 | J5: =D5 -> 0.4 | K5: =E5 -> 0.4 | M5: Digital | N5: =-B5 -> 0 | O5: =1-C5 -> 1 | P5: =-D5 -> -0.4 | Q5: =-E5 -> -0.4
A6: Engineering | B6: =Bench_e -> 0.4 | C6: =Bench_e -> 0.4 | D6: 0 | E6: 0 | G6: Engineering | H6: =B6 -> 0.4 | I6: =C6 -> 0.4 | J6: =D6-$B$10 -> -0.8 | K6: =E6 -> 0 | M6: Engineering | N6: =-B6 -> -0.4 | O6: =-C6 -> -0.4 | P6: =1-D6 -> 1 | Q6: =-E6 -> 0
A7: Treasury | B7: =Bench_t -> 0.4 | C7: =Bench_t -> 0.4 | D7: 0 | E7: 0 | G7: Treasury | H7: =B7 -> 0.4 | I7: =C7 -> 0.4 | J7: =D7 -> 0 | K7: =E7-$B$10 -> -0.8 | M7: Treasury | N7: =-B7 -> -0.4 | O7: =-C7 -> -0.4 | P7: =-D7 -> 0 | Q7: =1-E7 -> 1
A8: Passes on (column sum) | B8: =SUM(B4:B7) -> 0.8 | C8: =SUM(C4:C7) -> 0.8 | D8: =SUM(D4:D7) -> 0.8 | E8: =SUM(E4:E7) -> 0.8
A9: Quantity | B9: Value | C9: Reading
A10: Spectral radius (closed form, Online Appendix 14.B.1) | B10: =(Bench_h+SQRT(Bench_h^2+8*(Bench_e^2+Bench_t^2)))/2 -> 0.8 | C10: Today 0.80; with the new link at 0.40, 1.0246
A11: It is an eigenvalue: det(M - rho I) | B11: =MDETERM(H4:K7) -> -1.7763568e-17 | C11: Zero
A12: Half-life (quarters) | B12: =IF(B10<1,LN(2)/LN(1/B10),"none") -> 3.1062837 | C12: ln 2 / ln(1/rho): 3.1 today
A13: Quarters to a tenth | B13: =IF(B10<1,LN(10)/LN(1/B10),"none") -> 10.318851 | C13: 10.3 today
A14: Amplification, 1/(1 - rho) | B14: =IF(B10<1,1/(1-B10),"none") -> 5 | C14: Theorem 14.4(iii): 5 today
A15: Margin to the edge, 1 - rho | B15: =1-B10 -> 0.2 | C15: The certificate's margin
A16: Margin to the board's rule, r* - rho | B16: =R_star-B10 -> 0.040896415 | C16: Negative: the rule fails
A17: Meets the board's rule? | B17: =IF(B10<=R_star+0.000000000001,"yes","no") -> yes
A18: Contraction constant: the largest row sum | B18: =MAX(SUM(B4:E4),SUM(B5:E5),SUM(B6:E6),SUM(B7:E7)) -> 0.8 | C18: Table 14.2: L < 1 is the strongest test
A19: Largest radius of 10,000 gains drawn within the ceilings (notebook) | B19: 0.63468786 | C19: Fresh draws, seed 26114. Theorem 14.3(ii): never above the register's radius
A21: M^2 | B21: IND | C21: DIG | D21: ENG | E21: TRS | G21: I - M^2 | H21: IND | I21: DIG | J21: ENG | K21: TRS | M21: P = (I - M^2)^-1 | N21: IND | O21: DIG | P21: ENG | Q21: TRS
A22: Industrial Systems | B22: =INDEX(MMULT($B$4:$E$7,$B$4:$E$7),1,1) -> 0.32 | C22: =INDEX(MMULT($B$4:$E$7,$B$4:$E$7),1,2) -> 0.32 | D22: =INDEX(MMULT($B$4:$E$7,$B$4:$E$7),1,3) -> 0 | E22: =INDEX(MMULT($B$4:$E$7,$B$4:$E$7),1,4) -> 0 | G22: Industrial Systems | H22: =1-B22 -> 0.68 | I22: =-C22 -> -0.32 | J22: =-D22 -> 0 | K22: =-E22 -> 0 | M22: Industrial Systems | N22: =INDEX(MINVERSE($H$22:$K$25),1,1) -> 1.8888889 | O22: =INDEX(MINVERSE($H$22:$K$25),1,2) -> 0.88888889 | P22: =INDEX(MINVERSE($H$22:$K$25),1,3) -> 0 | Q22: =INDEX(MINVERSE($H$22:$K$25),1,4) -> 0
A23: Digital | B23: =INDEX(MMULT($B$4:$E$7,$B$4:$E$7),2,1) -> 0.32 | C23: =INDEX(MMULT($B$4:$E$7,$B$4:$E$7),2,2) -> 0.32 | D23: =INDEX(MMULT($B$4:$E$7,$B$4:$E$7),2,3) -> 0 | E23: =INDEX(MMULT($B$4:$E$7,$B$4:$E$7),2,4) -> 0 | G23: Digital | H23: =-B23 -> -0.32 | I23: =1-C23 -> 0.68 | J23: =-D23 -> 0 | K23: =-E23 -> 0 | M23: Digital | N23: =INDEX(MINVERSE($H$22:$K$25),2,1) -> 0.88888889 | O23: =INDEX(MINVERSE($H$22:$K$25),2,2) -> 1.8888889 | P23: =INDEX(MINVERSE($H$22:$K$25),2,3) -> 0 | Q23: =INDEX(MINVERSE($H$22:$K$25),2,4) -> 0
A24: Engineering | B24: =INDEX(MMULT($B$4:$E$7,$B$4:$E$7),3,1) -> 0 | C24: =INDEX(MMULT($B$4:$E$7,$B$4:$E$7),3,2) -> 0 | D24: =INDEX(MMULT($B$4:$E$7,$B$4:$E$7),3,3) -> 0.32 | E24: =INDEX(MMULT($B$4:$E$7,$B$4:$E$7),3,4) -> 0.32 | G24: Engineering | H24: =-B24 -> 0 | I24: =-C24 -> 0 | J24: =1-D24 -> 0.68 | K24: =-E24 -> -0.32 | M24: Engineering | N24: =INDEX(MINVERSE($H$22:$K$25),3,1) -> 0 | O24: =INDEX(MINVERSE($H$22:$K$25),3,2) -> 0 | P24: =INDEX(MINVERSE($H$22:$K$25),3,3) -> 1.8888889 | Q24: =INDEX(MINVERSE($H$22:$K$25),3,4) -> 0.88888889
A25: Treasury | B25: =INDEX(MMULT($B$4:$E$7,$B$4:$E$7),4,1) -> 0 | C25: =INDEX(MMULT($B$4:$E$7,$B$4:$E$7),4,2) -> 0 | D25: =INDEX(MMULT($B$4:$E$7,$B$4:$E$7),4,3) -> 0.32 | E25: =INDEX(MMULT($B$4:$E$7,$B$4:$E$7),4,4) -> 0.32 | G25: Treasury | H25: =-B25 -> 0 | I25: =-C25 -> 0 | J25: =-D25 -> -0.32 | K25: =1-E25 -> 0.68 | M25: Treasury | N25: =INDEX(MINVERSE($H$22:$K$25),4,1) -> 0 | O25: =INDEX(MINVERSE($H$22:$K$25),4,2) -> 0 | P25: =INDEX(MINVERSE($H$22:$K$25),4,3) -> 0.88888889 | Q25: =INDEX(MINVERSE($H$22:$K$25),4,4) -> 1.8888889
A27: Leading minors of P (Sylvester) | B27: =N22 -> 1.8888889 | C27: =MDETERM(N22:O23) -> 2.7777778 | D27: =MDETERM(N22:P24) -> 5.2469136 | E27: =MDETERM(N22:Q25) -> 7.7160494
A28: P positive definite: a Lyapunov bowl | B28: =IF(AND(B27>0,C27>0,D27>0,E27>0),"yes","no") -> yes
A29: P's curvature along the Perron direction, 1/(1 - rho^2) | B29: =IF(B10<1,1/(1-B10^2),"none") -> 2.7777778
A30: For a symmetric register, P = (I - M^2)^-1 solves Lyapunov's equation M'PM - P = -I (Theorem 14.3(iv)); it is positive definite exactly when rho < 1, and then V(x) = x'Px falls every quarter.
A32: A permanent shortfall at Digital settles at (Theorem 14.4(ii)) | B32: IND | C32: DIG | D32: ENG | E32: TRS | F32: Core
A33: Exact: Shock x Digital's column of (I - M)^-1 | B33: =IF($B$10<1,Shock*INDEX(MINVERSE($N$4:$Q$7),1,2),"none") -> 8.8888889 | C33: =IF($B$10<1,Shock*INDEX(MINVERSE($N$4:$Q$7),2,2),"none") -> 18.888889 | D33: =IF($B$10<1,Shock*INDEX(MINVERSE($N$4:$Q$7),3,2),"none") -> 11.111111 | E33: =IF($B$10<1,Shock*INDEX(MINVERSE($N$4:$Q$7),4,2),"none") -> 11.111111 | F33: =IF($B$10<1,SUM(B33:E33),"no limit") -> 50
A34: Closed form by the Industrial Systems-Digital symmetry | B34: =IF($B$10<1,(Shock/(1-Bench_h-2*(Bench_e^2+Bench_t^2))-Shock/(1+Bench_h))/2,"none") -> 8.8888889 | C34: =IF($B$10<1,(Shock/(1-Bench_h-2*(Bench_e^2+Bench_t^2))+Shock/(1+Bench_h))/2,"none") -> 18.888889 | D34: =IF($B$10<1,Bench_e*Shock/(1-Bench_h-2*(Bench_e^2+Bench_t^2)),"none") -> 11.111111 | E34: =IF($B$10<1,Bench_t*Shock/(1-Bench_h-2*(Bench_e^2+Bench_t^2)),"none") -> 11.111111 | F34: =IF($B$10<1,SUM(B34:E34),"no limit") -> 50
A35: Direct: the shortfall at Digital itself | F35: =Shock -> 10
A36: Knock-on: the rest | F36: =IF($B$10<1,F33-F35,"no limit") -> 40
A37: Largest gap, exact against the closed form | F37: =IF($B$10<1,MAX(ABS(B33-B34),ABS(C33-C34),ABS(D33-D34),ABS(E33-E34)),0) -> 0
A38: Closed form: x_IND + x_DIG = Shock/(1 - h - 2(e^2 + t^2)) and x_DIG - x_IND = Shock/(1 + h).
A39: Quarter | B39: Echo: IND | C39: Echo: DIG | D39: Echo: ENG | E39: Echo: TRS | F39: Echo: core | G39: Ratio to the previous quarter | H39: Health index x'Px | I39: S_k: IND | J39: S_k: DIG | K39: S_k: ENG | L39: S_k: TRS | M39: S_k: core
A40: 0 | B40: 0 | C40: =Shock -> 10 | D40: 0 | E40: 0 | F40: =SUM(B40:E40) -> 10 | H40: =IF($B$28="yes",SUMPRODUCT(MMULT(B40:E40,$N$22:$Q$25),B40:E40),"") -> 188.88889 | I40: 0 | J40: 0 | K40: 0 | L40: 0 | M40: =SUM(I40:L40) -> 0
A41: 1 | B41: =SUMPRODUCT($B$4:$E$4,B40:E40) -> 0 | C41: =SUMPRODUCT($B$5:$E$5,B40:E40) -> 0 | D41: =SUMPRODUCT($B$6:$E$6,B40:E40) -> 4 | E41: =SUMPRODUCT($B$7:$E$7,B40:E40) -> 4 | F41: =SUM(B41:E41) -> 8 | G41: =IF(F40<>0,F41/F40,"") -> 0.8 | H41: =IF($B$28="yes",SUMPRODUCT(MMULT(B41:E41,$N$22:$Q$25),B41:E41),"") -> 88.888889 | I41: =SUMPRODUCT($B$4:$E$4,I40:L40) -> 0 | J41: =SUMPRODUCT($B$5:$E$5,I40:L40)+Shock -> 10 | K41: =SUMPRODUCT($B$6:$E$6,I40:L40) -> 0 | L41: =SUMPRODUCT($B$7:$E$7,I40:L40) -> 0 | M41: =SUM(I41:L41) -> 10
A42: 2 | B42: =SUMPRODUCT($B$4:$E$4,B41:E41) -> 3.2 | C42: =SUMPRODUCT($B$5:$E$5,B41:E41) -> 3.2 | D42: =SUMPRODUCT($B$6:$E$6,B41:E41) -> 0 | E42: =SUMPRODUCT($B$7:$E$7,B41:E41) -> 0 | F42: =SUM(B42:E42) -> 6.4 | G42: =IF(F41<>0,F42/F41,"") -> 0.8 | H42: =IF($B$28="yes",SUMPRODUCT(MMULT(B42:E42,$N$22:$Q$25),B42:E42),"") -> 56.888889 | I42: =SUMPRODUCT($B$4:$E$4,I41:L41) -> 0 | J42: =SUMPRODUCT($B$5:$E$5,I41:L41)+Shock -> 10 | K42: =SUMPRODUCT($B$6:$E$6,I41:L41) -> 4 | L42: =SUMPRODUCT($B$7:$E$7,I41:L41) -> 4 | M42: =SUM(I42:L42) -> 18
A43: 3 | B43: =SUMPRODUCT($B$4:$E$4,B42:E42) -> 0 | C43: =SUMPRODUCT($B$5:$E$5,B42:E42) -> 0 | D43: =SUMPRODUCT($B$6:$E$6,B42:E42) -> 2.56 | E43: =SUMPRODUCT($B$7:$E$7,B42:E42) -> 2.56 | F43: =SUM(B43:E43) -> 5.12 | G43: =IF(F42<>0,F43/F42,"") -> 0.8 | H43: =IF($B$28="yes",SUMPRODUCT(MMULT(B43:E43,$N$22:$Q$25),B43:E43),"") -> 36.408889 | I43: =SUMPRODUCT($B$4:$E$4,I42:L42) -> 3.2 | J43: =SUMPRODUCT($B$5:$E$5,I42:L42)+Shock -> 13.2 | K43: =SUMPRODUCT($B$6:$E$6,I42:L42) -> 4 | L43: =SUMPRODUCT($B$7:$E$7,I42:L42) -> 4 | M43: =SUM(I43:L43) -> 24.4
A44: 4 | B44: =SUMPRODUCT($B$4:$E$4,B43:E43) -> 2.048 | C44: =SUMPRODUCT($B$5:$E$5,B43:E43) -> 2.048 | D44: =SUMPRODUCT($B$6:$E$6,B43:E43) -> 0 | E44: =SUMPRODUCT($B$7:$E$7,B43:E43) -> 0 | F44: =SUM(B44:E44) -> 4.096 | G44: =IF(F43<>0,F44/F43,"") -> 0.8 | H44: =IF($B$28="yes",SUMPRODUCT(MMULT(B44:E44,$N$22:$Q$25),B44:E44),"") -> 23.301689 | I44: =SUMPRODUCT($B$4:$E$4,I43:L43) -> 3.2 | J44: =SUMPRODUCT($B$5:$E$5,I43:L43)+Shock -> 13.2 | K44: =SUMPRODUCT($B$6:$E$6,I43:L43) -> 6.56 | L44: =SUMPRODUCT($B$7:$E$7,I43:L43) -> 6.56 | M44: =SUM(I44:L44) -> 29.52
A45: 5 | B45: =SUMPRODUCT($B$4:$E$4,B44:E44) -> 0 | C45: =SUMPRODUCT($B$5:$E$5,B44:E44) -> 0 | D45: =SUMPRODUCT($B$6:$E$6,B44:E44) -> 1.6384 | E45: =SUMPRODUCT($B$7:$E$7,B44:E44) -> 1.6384 | F45: =SUM(B45:E45) -> 3.2768 | G45: =IF(F44<>0,F45/F44,"") -> 0.8 | H45: =IF($B$28="yes",SUMPRODUCT(MMULT(B45:E45,$N$22:$Q$25),B45:E45),"") -> 14.913081 | I45: =SUMPRODUCT($B$4:$E$4,I44:L44) -> 5.248 | J45: =SUMPRODUCT($B$5:$E$5,I44:L44)+Shock -> 15.248 | K45: =SUMPRODUCT($B$6:$E$6,I44:L44) -> 6.56 | L45: =SUMPRODUCT($B$7:$E$7,I44:L44) -> 6.56 | M45: =SUM(I45:L45) -> 33.616
A46: 6 | B46: =SUMPRODUCT($B$4:$E$4,B45:E45) -> 1.31072 | C46: =SUMPRODUCT($B$5:$E$5,B45:E45) -> 1.31072 | D46: =SUMPRODUCT($B$6:$E$6,B45:E45) -> 0 | E46: =SUMPRODUCT($B$7:$E$7,B45:E45) -> 0 | F46: =SUM(B46:E46) -> 2.62144 | G46: =IF(F45<>0,F46/F45,"") -> 0.8 | H46: =IF($B$28="yes",SUMPRODUCT(MMULT(B46:E46,$N$22:$Q$25),B46:E46),"") -> 9.5443718 | I46: =SUMPRODUCT($B$4:$E$4,I45:L45) -> 5.248 | J46: =SUMPRODUCT($B$5:$E$5,I45:L45)+Shock -> 15.248 | K46: =SUMPRODUCT($B$6:$E$6,I45:L45) -> 8.1984 | L46: =SUMPRODUCT($B$7:$E$7,I45:L45) -> 8.1984 | M46: =SUM(I46:L46) -> 36.8928
A47: 7 | B47: =SUMPRODUCT($B$4:$E$4,B46:E46) -> 0 | C47: =SUMPRODUCT($B$5:$E$5,B46:E46) -> 0 | D47: =SUMPRODUCT($B$6:$E$6,B46:E46) -> 1.048576 | E47: =SUMPRODUCT($B$7:$E$7,B46:E46) -> 1.048576 | F47: =SUM(B47:E47) -> 2.097152 | G47: =IF(F46<>0,F47/F46,"") -> 0.8 | H47: =IF($B$28="yes",SUMPRODUCT(MMULT(B47:E47,$N$22:$Q$25),B47:E47),"") -> 6.1083979 | I47: =SUMPRODUCT($B$4:$E$4,I46:L46) -> 6.55872 | J47: =SUMPRODUCT($B$5:$E$5,I46:L46)+Shock -> 16.55872 | K47: =SUMPRODUCT($B$6:$E$6,I46:L46) -> 8.1984 | L47: =SUMPRODUCT($B$7:$E$7,I46:L46) -> 8.1984 | M47: =SUM(I47:L47) -> 39.51424
A48: 8 | B48: =SUMPRODUCT($B$4:$E$4,B47:E47) -> 0.8388608 | C48: =SUMPRODUCT($B$5:$E$5,B47:E47) -> 0.8388608 | D48: =SUMPRODUCT($B$6:$E$6,B47:E47) -> 0 | E48: =SUMPRODUCT($B$7:$E$7,B47:E47) -> 0 | F48: =SUM(B48:E48) -> 1.6777216 | G48: =IF(F47<>0,F48/F47,"") -> 0.8 | H48: =IF($B$28="yes",SUMPRODUCT(MMULT(B48:E48,$N$22:$Q$25),B48:E48),"") -> 3.9093747 | I48: =SUMPRODUCT($B$4:$E$4,I47:L47) -> 6.55872 | J48: =SUMPRODUCT($B$5:$E$5,I47:L47)+Shock -> 16.55872 | K48: =SUMPRODUCT($B$6:$E$6,I47:L47) -> 9.246976 | L48: =SUMPRODUCT($B$7:$E$7,I47:L47) -> 9.246976 | M48: =SUM(I48:L48) -> 41.611392
A49: 9 | B49: =SUMPRODUCT($B$4:$E$4,B48:E48) -> 0 | C49: =SUMPRODUCT($B$5:$E$5,B48:E48) -> 0 | D49: =SUMPRODUCT($B$6:$E$6,B48:E48) -> 0.67108864 | E49: =SUMPRODUCT($B$7:$E$7,B48:E48) -> 0.67108864 | F49: =SUM(B49:E49) -> 1.3421773 | G49: =IF(F48<>0,F49/F48,"") -> 0.8 | H49: =IF($B$28="yes",SUMPRODUCT(MMULT(B49:E49,$N$22:$Q$25),B49:E49),"") -> 2.5019998 | I49: =SUMPRODUCT($B$4:$E$4,I48:L48) -> 7.3975808 | J49: =SUMPRODUCT($B$5:$E$5,I48:L48)+Shock -> 17.397581 | K49: =SUMPRODUCT($B$6:$E$6,I48:L48) -> 9.246976 | L49: =SUMPRODUCT($B$7:$E$7,I48:L48) -> 9.246976 | M49: =SUM(I49:L49) -> 43.289114
A50: 10 | B50: =SUMPRODUCT($B$4:$E$4,B49:E49) -> 0.53687091 | C50: =SUMPRODUCT($B$5:$E$5,B49:E49) -> 0.53687091 | D50: =SUMPRODUCT($B$6:$E$6,B49:E49) -> 0 | E50: =SUMPRODUCT($B$7:$E$7,B49:E49) -> 0 | F50: =SUM(B50:E50) -> 1.0737418 | G50: =IF(F49<>0,F50/F49,"") -> 0.8 | H50: =IF($B$28="yes",SUMPRODUCT(MMULT(B50:E50,$N$22:$Q$25),B50:E50),"") -> 1.6012799 | I50: =SUMPRODUCT($B$4:$E$4,I49:L49) -> 7.3975808 | J50: =SUMPRODUCT($B$5:$E$5,I49:L49)+Shock -> 17.397581 | K50: =SUMPRODUCT($B$6:$E$6,I49:L49) -> 9.9180646 | L50: =SUMPRODUCT($B$7:$E$7,I49:L49) -> 9.9180646 | M50: =SUM(I50:L50) -> 44.631291
A51: 11 | B51: =SUMPRODUCT($B$4:$E$4,B50:E50) -> 0 | C51: =SUMPRODUCT($B$5:$E$5,B50:E50) -> 0 | D51: =SUMPRODUCT($B$6:$E$6,B50:E50) -> 0.42949673 | E51: =SUMPRODUCT($B$7:$E$7,B50:E50) -> 0.42949673 | F51: =SUM(B51:E51) -> 0.85899346 | G51: =IF(F50<>0,F51/F50,"") -> 0.8 | H51: =IF($B$28="yes",SUMPRODUCT(MMULT(B51:E51,$N$22:$Q$25),B51:E51),"") -> 1.0248191 | I51: =SUMPRODUCT($B$4:$E$4,I50:L50) -> 7.9344517 | J51: =SUMPRODUCT($B$5:$E$5,I50:L50)+Shock -> 17.934452 | K51: =SUMPRODUCT($B$6:$E$6,I50:L50) -> 9.9180646 | L51: =SUMPRODUCT($B$7:$E$7,I50:L50) -> 9.9180646 | M51: =SUM(I51:L51) -> 45.705033
A52: 12 | B52: =SUMPRODUCT($B$4:$E$4,B51:E51) -> 0.34359738 | C52: =SUMPRODUCT($B$5:$E$5,B51:E51) -> 0.34359738 | D52: =SUMPRODUCT($B$6:$E$6,B51:E51) -> 0 | E52: =SUMPRODUCT($B$7:$E$7,B51:E51) -> 0 | F52: =SUM(B52:E52) -> 0.68719477 | G52: =IF(F51<>0,F52/F51,"") -> 0.8 | H52: =IF($B$28="yes",SUMPRODUCT(MMULT(B52:E52,$N$22:$Q$25),B52:E52),"") -> 0.65588423 | I52: =SUMPRODUCT($B$4:$E$4,I51:L51) -> 7.9344517 | J52: =SUMPRODUCT($B$5:$E$5,I51:L51)+Shock -> 17.934452 | K52: =SUMPRODUCT($B$6:$E$6,I51:L51) -> 10.347561 | L52: =SUMPRODUCT($B$7:$E$7,I51:L51) -> 10.347561 | M52: =SUM(I52:L52) -> 46.564026
... A140: 100 | B140: =SUMPRODUCT($B$4:$E$4,B139:E139) -> 1.018518e-09 | C140: =SUMPRODUCT($B$5:$E$5,B139:E139) -> 1.018518e-09 | D140: =SUMPRODUCT($B$6:$E$6,B139:E139) -> 0 | E140: =SUMPRODUCT($B$7:$E$7,B139:E139) -> 0 | F140: =SUM(B140:E140) -> 2.037036e-09 | G140: =IF(F139<>0,F140/F139,"") -> 0.8 | H140: =IF($B$28="yes",SUMPRODUCT(MMULT(B140:E140,$N$22:$Q$25),B140:E140),"") -> 5.7632161e-18 | I140: =SUMPRODUCT($B$4:$E$4,I139:L139) -> 8.8888889 | J140: =SUMPRODUCT($B$5:$E$5,I139:L139)+Shock -> 18.888889 | K140: =SUMPRODUCT($B$6:$E$6,I139:L139) -> 11.111111 | L140: =SUMPRODUCT($B$7:$E$7,I139:L139) -> 11.111111 | M140: =SUM(I140:L140) -> 50
A142: S_k follows the sensitivity recursion S_(k+1) = M S_k + B (Equation 14.4) and converges to the settled deviation when rho < 1 (Theorem 14.4(i)-(ii)).

Sheet Rebudget
A1: Re-budget under the board's rule: Table 14.4 and the frontier (Worked Example 14.1, Steps 3-4; Online Appendix 14.B.1; AXIOM Lab 1.14, step 1)
A2: rho = (h + sqrt(h^2 + 8(e^2 + t^2)))/2, and rho <= r* exactly when h r* + 2(e^2 + t^2) <= r*^2: one frontier prices every repair.
A3: Quantity | B3: Value | C3: Reading
A4: The board's rule as a spectral radius, r* | B4: =R_star -> 0.84089642 | C4: 2^(-1/4)
A5: Run the new link light: largest h with e = t at the ceiling | B5: =(R_star^2-2*(Ceiling^2+Ceiling^2))/R_star -> 0.079803862 | C5: 0.08 (Online Appendix 14.B.1: 0.080)
A6: Ring-fence treasury: largest t with h = e at the ceiling | B6: =SQRT((R_star^2-Ceiling*R_star)/2-Ceiling^2) -> 0.15929252 | C6: 0.16 (0.159)
A7: Trim every existing link: e = t with h at the ceiling | B7: =SQRT((R_star^2-Ceiling*R_star)/4) -> 0.30444549 | C7: 0.30 (0.304)
A8: The trim as a share of the ceiling | B8: =1-B7/Ceiling -> 0.23888629 | C8: About a quarter
A10: Table 14.4: register | B10: Eng. links e | C10: Treas. links t | D10: New link h | E10: rho (closed form) | F10: Frontier: h r* + 2(e^2+t^2) - r*^2 | G10: Half-life (quarters) | H10: Quarters to a tenth | I10: Amplification | J10: Passes on: IND, DIG | K10: Passes on: ENG | L10: Passes on: TRS | M10: S = x_IND + x_DIG | N10: x_DIG - x_IND | O10: Settled: IND | P10: Settled: DIG | Q10: Settled: ENG | R10: Settled: TRS | S10: Settled total ($ million a quarter) | T10: Meets the rule?
A11: Today | B11: =Ceiling -> 0.4 | C11: =Ceiling -> 0.4 | D11: 0 | E11: =(D11+SQRT(D11^2+8*(B11^2+C11^2)))/2 -> 0.8 | F11: =D11*R_star+2*(B11^2+C11^2)-R_star^2 -> -0.067106781 | G11: =IF(E11<1,LN(2)/LN(1/E11),"none") -> 3.1062837 | H11: =IF(E11<1,LN(10)/LN(1/E11),"none") -> 10.318851 | I11: =IF(E11<1,1/(1-E11),"none") -> 5 | J11: =B11+C11+D11 -> 0.8 | K11: =2*B11 -> 0.8 | L11: =2*C11 -> 0.8 | M11: =IF(E11<1,Shock/(1-D11-2*(B11^2+C11^2)),"none") -> 27.777778 | N11: =Shock/(1+D11) -> 10 | O11: =IF(E11<1,(M11-N11)/2,"none") -> 8.8888889 | P11: =IF(E11<1,(M11+N11)/2,"none") -> 18.888889 | Q11: =IF(E11<1,B11*M11,"none") -> 11.111111 | R11: =IF(E11<1,C11*M11,"none") -> 11.111111 | S11: =IF(E11<1,M11*(1+B11+C11),"no limit") -> 50 | T11: =IF(E11<=R_star+0.000000001,"yes","no") -> yes
A12: New link at the ceiling | B12: =Ceiling -> 0.4 | C12: =Ceiling -> 0.4 | D12: =Ceiling -> 0.4 | E12: =(D12+SQRT(D12^2+8*(B12^2+C12^2)))/2 -> 1.0246211 | F12: =D12*R_star+2*(B12^2+C12^2)-R_star^2 -> 0.26925178 | G12: =IF(E12<1,LN(2)/LN(1/E12),"none") -> none | H12: =IF(E12<1,LN(10)/LN(1/E12),"none") -> none | I12: =IF(E12<1,1/(1-E12),"none") -> none | J12: =B12+C12+D12 -> 1.2 | K12: =2*B12 -> 0.8 | L12: =2*C12 -> 0.8 | M12: =IF(E12<1,Shock/(1-D12-2*(B12^2+C12^2)),"none") -> none | N12: =Shock/(1+D12) -> 7.1428571 | O12: =IF(E12<1,(M12-N12)/2,"none") -> none | P12: =IF(E12<1,(M12+N12)/2,"none") -> none | Q12: =IF(E12<1,B12*M12,"none") -> none | R12: =IF(E12<1,C12*M12,"none") -> none | S12: =IF(E12<1,M12*(1+B12+C12),"no limit") -> no limit | T12: =IF(E12<=R_star+0.000000001,"yes","no") -> no
A13: Run the new link light | B13: =Ceiling -> 0.4 | C13: =Ceiling -> 0.4 | D13: =$B$5 -> 0.079803862 | E13: =(D13+SQRT(D13^2+8*(B13^2+C13^2)))/2 -> 0.84089642 | F13: =D13*R_star+2*(B13^2+C13^2)-R_star^2 -> 0 | G13: =IF(E13<1,LN(2)/LN(1/E13),"none") -> 4 | H13: =IF(E13<1,LN(10)/LN(1/E13),"none") -> 13.287712 | I13: =IF(E13<1,1/(1-E13),"none") -> 6.2852135 | J13: =B13+C13+D13 -> 0.87980386 | K13: =2*B13 -> 0.8 | L13: =2*C13 -> 0.8 | M13: =IF(E13<1,Shock/(1-D13-2*(B13^2+C13^2)),"none") -> 35.689286 | N13: =Shock/(1+D13) -> 9.2609411 | O13: =IF(E13<1,(M13-N13)/2,"none") -> 13.214172 | P13: =IF(E13<1,(M13+N13)/2,"none") -> 22.475113 | Q13: =IF(E13<1,B13*M13,"none") -> 14.275714 | R13: =IF(E13<1,C13*M13,"none") -> 14.275714 | S13: =IF(E13<1,M13*(1+B13+C13),"no limit") -> 64.240714 | T13: =IF(E13<=R_star+0.000000001,"yes","no") -> yes
A14: Ring-fence treasury | B14: =Ceiling -> 0.4 | C14: =$B$6 -> 0.15929252 | D14: =Ceiling -> 0.4 | E14: =(D14+SQRT(D14^2+8*(B14^2+C14^2)))/2 -> 0.84089642 | F14: =D14*R_star+2*(B14^2+C14^2)-R_star^2 -> 0 | G14: =IF(E14<1,LN(2)/LN(1/E14),"none") -> 4 | H14: =IF(E14<1,LN(10)/LN(1/E14),"none") -> 13.287712 | I14: =IF(E14<1,1/(1-E14),"none") -> 6.2852135 | J14: =B14+C14+D14 -> 0.95929252 | K14: =2*B14 -> 0.8 | L14: =2*C14 -> 0.31858504 | M14: =IF(E14<1,Shock/(1-D14-2*(B14^2+C14^2)),"none") -> 43.620162 | N14: =Shock/(1+D14) -> 7.1428571 | O14: =IF(E14<1,(M14-N14)/2,"none") -> 18.238652 | P14: =IF(E14<1,(M14+N14)/2,"none") -> 25.38151 | Q14: =IF(E14<1,B14*M14,"none") -> 17.448065 | R14: =IF(E14<1,C14*M14,"none") -> 6.9483656 | S14: =IF(E14<1,M14*(1+B14+C14),"no limit") -> 68.016592 | T14: =IF(E14<=R_star+0.000000001,"yes","no") -> yes
A15: Trim every existing link | B15: =$B$7 -> 0.30444549 | C15: =$B$7 -> 0.30444549 | D15: =Ceiling -> 0.4 | E15: =(D15+SQRT(D15^2+8*(B15^2+C15^2)))/2 -> 0.84089642 | F15: =D15*R_star+2*(B15^2+C15^2)-R_star^2 -> 0 | G15: =IF(E15<1,LN(2)/LN(1/E15),"none") -> 4 | H15: =IF(E15<1,LN(10)/LN(1/E15),"none") -> 13.287712 | I15: =IF(E15<1,1/(1-E15),"none") -> 6.2852135 | J15: =B15+C15+D15 -> 1.008891 | K15: =2*B15 -> 0.60889097 | L15: =2*C15 -> 0.60889097 | M15: =IF(E15<1,Shock/(1-D15-2*(B15^2+C15^2)),"none") -> 43.620162 | N15: =Shock/(1+D15) -> 7.1428571 | O15: =IF(E15<1,(M15-N15)/2,"none") -> 18.238652 | P15: =IF(E15<1,(M15+N15)/2,"none") -> 25.38151 | Q15: =IF(E15<1,B15*M15,"none") -> 13.279961 | R15: =IF(E15<1,C15*M15,"none") -> 13.279961 | S15: =IF(E15<1,M15*(1+B15+C15),"no limit") -> 70.180085 | T15: =IF(E15<=R_star+0.000000001,"yes","no") -> yes
A17: Settled: the deviation across the core each quarter for a permanent $10 million a quarter shortfall at Digital, solved by the Industrial Systems-Digital symmetry. Ring-fencing and trimming have the same radius (it sees e^2 + t^2 only); the trims spread the settled deviation to engineering and treasury.
A18: Ring-fence and trim: difference in radius | B18: =E14-E15 -> 0
A20: Treasury links t (engineering at the ceiling) | B20: Largest new link within the rule | C20: All four existing links at c | D20: Largest new link within the rule
A21: 0.4 | B21: =(R_star^2-2*(Ceiling^2+A21^2))/R_star -> 0.079803862 | C21: 0.4 | D21: =(R_star^2-4*C21^2)/R_star -> 0.079803862
A22: 0.35 | B22: =(R_star^2-2*(Ceiling^2+A22^2))/R_star -> 0.1689944 | C22: 0.35 | D22: =(R_star^2-4*C22^2)/R_star -> 0.25818493
A23: 0.3 | B23: =(R_star^2-2*(Ceiling^2+A23^2))/R_star -> 0.24629286 | C23: =$B$7 -> 0.30444549 | D23: =(R_star^2-4*C23^2)/R_star -> 0.4
A24: 0.25 | B24: =(R_star^2-2*(Ceiling^2+A24^2))/R_star -> 0.31169925 | C24: 0.3 | D24: =(R_star^2-4*C24^2)/R_star -> 0.41278185
A25: 0.2 | B25: =(R_star^2-2*(Ceiling^2+A25^2))/R_star -> 0.36521357 | C25: 0.25 | D25: =(R_star^2-4*C25^2)/R_star -> 0.54359464
A26: =$B$6 -> 0.15929252 | B26: =(R_star^2-2*(Ceiling^2+A26^2))/R_star -> 0.4 | C26: 0.2 | D26: =(R_star^2-4*C26^2)/R_star -> 0.65062328
A27: 0.15 | B27: =(R_star^2-2*(Ceiling^2+A27^2))/R_star -> 0.40683582 | C27: 0.15 | D27: =(R_star^2-4*C27^2)/R_star -> 0.73386777
A28: 0.1 | B28: =(R_star^2-2*(Ceiling^2+A28^2))/R_star -> 0.436566 | C28: 0.1 | D28: =(R_star^2-4*C28^2)/R_star -> 0.79332813
A29: 0.05 | B29: =(R_star^2-2*(Ceiling^2+A29^2))/R_star -> 0.4544041 | C29: 0.05 | D29: =(R_star^2-4*C29^2)/R_star -> 0.82900434
A30: 0 | B30: =(R_star^2-2*(Ceiling^2+A30^2))/R_star -> 0.46035014 | C30: 0 | D30: =(R_star^2-4*C30^2)/R_star -> 0.84089642
A34: Quarter | B34: Today: IND | C34: Today: DIG | D34: Today: ENG | E34: Today: TRS | F34: Today: core | G34: New link at the ceiling: IND | H34: New link at the ceiling: DIG | I34: New link at the ceiling: ENG | J34: New link at the ceiling: TRS | K34: New link at the ceiling: core | L34: Run the new link light: IND | M34: Run the new link light: DIG | N34: Run the new link light: ENG | O34: Run the new link light: TRS | P34: Run the new link light: core | Q34: Ring-fence treasury: IND | R34: Ring-fence treasury: DIG | S34: Ring-fence treasury: ENG | T34: Ring-fence treasury: TRS | U34: Ring-fence treasury: core | V34: Trim every existing link: IND | W34: Trim every existing link: DIG | X34: Trim every existing link: ENG | Y34: Trim every existing link: TRS | Z34: Trim every existing link: core
A35: 0 | B35: 0 | C35: =Shock -> 10 | D35: 0 | E35: 0 | F35: =SUM(B35:E35) -> 10 | G35: 0 | H35: =Shock -> 10 | I35: 0 | J35: 0 | K35: =SUM(G35:J35) -> 10 | L35: 0 | M35: =Shock -> 10 | N35: 0 | O35: 0 | P35: =SUM(L35:O35) -> 10 | Q35: 0 | R35: =Shock -> 10 | S35: 0 | T35: 0 | U35: =SUM(Q35:T35) -> 10 | V35: 0 | W35: =Shock -> 10 | X35: 0 | Y35: 0 | Z35: =SUM(V35:Y35) -> 10
A36: 1 | B36: =$D$11*C35+$B$11*D35+$C$11*E35 -> 0 | C36: =$D$11*B35+$B$11*D35+$C$11*E35 -> 0 | D36: =$B$11*(B35+C35) -> 4 | E36: =$C$11*(B35+C35) -> 4 | F36: =SUM(B36:E36) -> 8 | G36: =$D$12*H35+$B$12*I35+$C$12*J35 -> 4 | H36: =$D$12*G35+$B$12*I35+$C$12*J35 -> 0 | I36: =$B$12*(G35+H35) -> 4 | J36: =$C$12*(G35+H35) -> 4 | K36: =SUM(G36:J36) -> 12 | L36: =$D$13*M35+$B$13*N35+$C$13*O35 -> 0.79803862 | M36: =$D$13*L35+$B$13*N35+$C$13*O35 -> 0 | N36: =$B$13*(L35+M35) -> 4 | O36: =$C$13*(L35+M35) -> 4 | P36: =SUM(L36:O36) -> 8.7980386 | Q36: =$D$14*R35+$B$14*S35+$C$14*T35 -> 4 | R36: =$D$14*Q35+$B$14*S35+$C$14*T35 -> 0 | S36: =$B$14*(Q35+R35) -> 4 | T36: =$C$14*(Q35+R35) -> 1.5929252 | U36: =SUM(Q36:T36) -> 9.5929252 | V36: =$D$15*W35+$B$15*X35+$C$15*Y35 -> 4 | W36: =$D$15*V35+$B$15*X35+$C$15*Y35 -> 0 | X36: =$B$15*(V35+W35) -> 3.0444549 | Y36: =$C$15*(V35+W35) -> 3.0444549 | Z36: =SUM(V36:Y36) -> 10.08891
A37: 2 | B37: =$D$11*C36+$B$11*D36+$C$11*E36 -> 3.2 | C37: =$D$11*B36+$B$11*D36+$C$11*E36 -> 3.2 | D37: =$B$11*(B36+C36) -> 0 | E37: =$C$11*(B36+C36) -> 0 | F37: =SUM(B37:E37) -> 6.4 | G37: =$D$12*H36+$B$12*I36+$C$12*J36 -> 3.2 | H37: =$D$12*G36+$B$12*I36+$C$12*J36 -> 4.8 | I37: =$B$12*(G36+H36) -> 1.6 | J37: =$C$12*(G36+H36) -> 1.6 | K37: =SUM(G37:J37) -> 11.2 | L37: =$D$13*M36+$B$13*N36+$C$13*O36 -> 3.2 | M37: =$D$13*L36+$B$13*N36+$C$13*O36 -> 3.2636866 | N37: =$B$13*(L36+M36) -> 0.31921545 | O37: =$C$13*(L36+M36) -> 0.31921545 | P37: =SUM(L37:O37) -> 7.1021175 | Q37: =$D$14*R36+$B$14*S36+$C$14*T36 -> 1.8537411 | R37: =$D$14*Q36+$B$14*S36+$C$14*T36 -> 3.4537411 | S37: =$B$14*(Q36+R36) -> 1.6 | T37: =$C$14*(Q36+R36) -> 0.63717009 | U37: =SUM(Q37:T37) -> 7.5446522 | V37: =$D$15*W36+$B$15*X36+$C$15*Y36 -> 1.8537411 | W37: =$D$15*V36+$B$15*X36+$C$15*Y36 -> 3.4537411 | X37: =$B$15*(V36+W36) -> 1.2177819 | Y37: =$C$15*(V36+W36) -> 1.2177819 | Z37: =SUM(V37:Y37) -> 7.743046
A38: 3 | B38: =$D$11*C37+$B$11*D37+$C$11*E37 -> 0 | C38: =$D$11*B37+$B$11*D37+$C$11*E37 -> 0 | D38: =$B$11*(B37+C37) -> 2.56 | E38: =$C$11*(B37+C37) -> 2.56 | F38: =SUM(B38:E38) -> 5.12 | G38: =$D$12*H37+$B$12*I37+$C$12*J37 -> 3.2 | H38: =$D$12*G37+$B$12*I37+$C$12*J37 -> 2.56 | I38: =$B$12*(G37+H37) -> 3.2 | J38: =$C$12*(G37+H37) -> 3.2 | K38: =SUM(G38:J38) -> 12.16 | L38: =$D$13*M37+$B$13*N37+$C$13*O37 -> 0.51582715 | M38: =$D$13*L37+$B$13*N37+$C$13*O37 -> 0.51074471 | N38: =$B$13*(L37+M37) -> 2.5854746 | O38: =$C$13*(L37+M37) -> 2.5854746 | P38: =SUM(L38:O38) -> 6.1975211 | Q38: =$D$14*R37+$B$14*S37+$C$14*T37 -> 2.1229929 | R38: =$D$14*Q37+$B$14*S37+$C$14*T37 -> 1.4829929 | S38: =$B$14*(Q37+R37) -> 2.1229929 | T38: =$C$14*(Q37+R37) -> 0.84544222 | U38: =SUM(Q38:T38) -> 6.5744208 | V38: =$D$15*W37+$B$15*X37+$C$15*Y37 -> 2.1229929 | W38: =$D$15*V37+$B$15*X37+$C$15*Y37 -> 1.4829929 | X38: =$B$15*(V37+W37) -> 1.615839 | Y38: =$C$15*(V37+W37) -> 1.615839 | Z38: =SUM(V38:Y38) -> 6.8376637
A39: 4 | B39: =$D$11*C38+$B$11*D38+$C$11*E38 -> 2.048 | C39: =$D$11*B38+$B$11*D38+$C$11*E38 -> 2.048 | D39: =$B$11*(B38+C38) -> 0 | E39: =$C$11*(B38+C38) -> 0 | F39: =SUM(B39:E39) -> 4.096 | G39: =$D$12*H38+$B$12*I38+$C$12*J38 -> 3.584 | H39: =$D$12*G38+$B$12*I38+$C$12*J38 -> 3.84 | I39: =$B$12*(G38+H38) -> 2.304 | J39: =$C$12*(G38+H38) -> 2.304 | K39: =SUM(G39:J39) -> 12.032 | L39: =$D$13*M38+$B$13*N38+$C$13*O38 -> 2.1091391 | M39: =$D$13*L38+$B$13*N38+$C$13*O38 -> 2.1095447 | N39: =$B$13*(L38+M38) -> 0.41062875 | O39: =$C$13*(L38+M38) -> 0.41062875 | P39: =SUM(L39:O39) -> 5.0399413 | Q39: =$D$14*R38+$B$14*S38+$C$14*T38 -> 1.5770669 | R39: =$D$14*Q38+$B$14*S38+$C$14*T38 -> 1.8330669 | S39: =$B$14*(Q38+R38) -> 1.4423943 | T39: =$C$14*(Q38+R38) -> 0.57440656 | U39: =SUM(Q39:T39) -> 5.4269347 | V39: =$D$15*W38+$B$15*X38+$C$15*Y38 -> 1.5770669 | W39: =$D$15*V38+$B$15*X38+$C$15*Y38 -> 1.8330669 | X39: =$B$15*(V38+W38) -> 1.0978261 | Y39: =$C$15*(V38+W38) -> 1.0978261 | Z39: =SUM(V39:Y39) -> 5.605786
A40: 5 | B40: =$D$11*C39+$B$11*D39+$C$11*E39 -> 0 | C40: =$D$11*B39+$B$11*D39+$C$11*E39 -> 0 | D40: =$B$11*(B39+C39) -> 1.6384 | E40: =$C$11*(B39+C39) -> 1.6384 | F40: =SUM(B40:E40) -> 3.2768 | G40: =$D$12*H39+$B$12*I39+$C$12*J39 -> 3.3792 | H40: =$D$12*G39+$B$12*I39+$C$12*J39 -> 3.2768 | I40: =$B$12*(G39+H39) -> 2.9696 | J40: =$C$12*(G39+H39) -> 2.9696 | K40: =SUM(G40:J40) -> 12.5952 | L40: =$D$13*M39+$B$13*N39+$C$13*O39 -> 0.49685281 | M40: =$D$13*L39+$B$13*N39+$C$13*O39 -> 0.49682044 | N40: =$B$13*(L39+M39) -> 1.6874735 | O40: =$C$13*(L39+M39) -> 1.6874735 | P40: =SUM(L40:O40) -> 4.3686203 | Q40: =$D$14*R39+$B$14*S39+$C$14*T39 -> 1.4016831 | R40: =$D$14*Q39+$B$14*S39+$C$14*T39 -> 1.2992831 | S40: =$B$14*(Q39+R39) -> 1.3640535 | T40: =$C$14*(Q39+R39) -> 0.54320882 | U40: =SUM(Q40:T40) -> 4.6082286 | V40: =$D$15*W39+$B$15*X39+$C$15*Y39 -> 1.4016831 | W40: =$D$15*V39+$B$15*X39+$C$15*Y39 -> 1.2992831 | X40: =$B$15*(V39+W39) -> 1.0381998 | Y40: =$C$15*(V39+W39) -> 1.0381998 | Z40: =SUM(V40:Y40) -> 4.777366
A41: 6 | B41: =$D$11*C40+$B$11*D40+$C$11*E40 -> 1.31072 | C41: =$D$11*B40+$B$11*D40+$C$11*E40 -> 1.31072 | D41: =$B$11*(B40+C40) -> 0 | E41: =$C$11*(B40+C40) -> 0 | F41: =SUM(B41:E41) -> 2.62144 | G41: =$D$12*H40+$B$12*I40+$C$12*J40 -> 3.6864 | H41: =$D$12*G40+$B$12*I40+$C$12*J40 -> 3.72736 | I41: =$B$12*(G40+H40) -> 2.6624 | J41: =$C$12*(G40+H40) -> 2.6624 | K41: =SUM(G41:J41) -> 12.73856 | L41: =$D$13*M40+$B$13*N40+$C$13*O40 -> 1.389627 | M41: =$D$13*L40+$B$13*N40+$C$13*O40 -> 1.3896296 | N41: =$B$13*(L40+M40) -> 0.3974693 | O41: =$C$13*(L40+M40) -> 0.3974693 | P41: =SUM(L41:O41) -> 3.5741952 | Q41: =$D$14*R40+$B$14*S40+$C$14*T40 -> 1.1518638 | R41: =$D$14*Q40+$B$14*S40+$C$14*T40 -> 1.1928238 | S41: =$B$14*(Q40+R40) -> 1.0803865 | T41: =$C$14*(Q40+R40) -> 0.43024373 | U41: =SUM(Q41:T41) -> 3.8553178 | V41: =$D$15*W40+$B$15*X40+$C$15*Y40 -> 1.1518638 | W41: =$D$15*V40+$B$15*X40+$C$15*Y40 -> 1.1928238 | X41: =$B$15*(V40+W40) -> 0.822297 | Y41: =$C$15*(V40+W40) -> 0.822297 | Z41: =SUM(V41:Y41) -> 3.9892815
A42: 7 | B42: =$D$11*C41+$B$11*D41+$C$11*E41 -> 0 | C42: =$D$11*B41+$B$11*D41+$C$11*E41 -> 0 | D42: =$B$11*(B41+C41) -> 1.048576 | E42: =$C$11*(B41+C41) -> 1.048576 | F42: =SUM(B42:E42) -> 2.097152 | G42: =$D$12*H41+$B$12*I41+$C$12*J41 -> 3.620864 | H42: =$D$12*G41+$B$12*I41+$C$12*J41 -> 3.60448 | I42: =$B$12*(G41+H41) -> 2.965504 | J42: =$C$12*(G41+H41) -> 2.965504 | K42: =SUM(G42:J42) -> 13.156352 | L42: =$D$13*M41+$B$13*N41+$C$13*O41 -> 0.42887325 | M42: =$D$13*L41+$B$13*N41+$C$13*O41 -> 0.42887304 | N42: =$B$13*(L41+M41) -> 1.1117026 | O42: =$C$13*(L41+M41) -> 1.1117026 | P42: =SUM(L42:O42) -> 3.0811516 | Q42: =$D$14*R41+$B$14*S41+$C$14*T41 -> 0.97781873 | R42: =$D$14*Q41+$B$14*S41+$C$14*T41 -> 0.96143473 | S42: =$B$14*(Q41+R41) -> 0.93787502 | T42: =$C$14*(Q41+R41) -> 0.37349119 | U42: =SUM(Q42:T42) -> 3.2506197 | V42: =$D$15*W41+$B$15*X41+$C$15*Y41 -> 0.97781873 | W42: =$D$15*V41+$B$15*X41+$C$15*Y41 -> 0.96143473 | X42: =$B$15*(V41+W41) -> 0.71382954 | Y42: =$C$15*(V41+W41) -> 0.71382954 | Z42: =SUM(V42:Y42) -> 3.3669125
A43: 8 | B43: =$D$11*C42+$B$11*D42+$C$11*E42 -> 0.8388608 | C43: =$D$11*B42+$B$11*D42+$C$11*E42 -> 0.8388608 | D43: =$B$11*(B42+C42) -> 0 | E43: =$C$11*(B42+C42) -> 0 | F43: =SUM(B43:E43) -> 1.6777216 | G43: =$D$12*H42+$B$12*I42+$C$12*J42 -> 3.8141952 | H43: =$D$12*G42+$B$12*I42+$C$12*J42 -> 3.8207488 | I43: =$B$12*(G42+H42) -> 2.8901376 | J43: =$C$12*(G42+H42) -> 2.8901376 | K43: =SUM(G43:J43) -> 13.415219 | L43: =$D$13*M42+$B$13*N42+$C$13*O42 -> 0.92358784 | M43: =$D$13*L42+$B$13*N42+$C$13*O42 -> 0.92358785 | N43: =$B$13*(L42+M42) -> 0.34309852 | O43: =$C$13*(L42+M42) -> 0.34309852 | P43: =SUM(L43:O43) -> 2.5333727 | Q43: =$D$14*R42+$B$14*S42+$C$14*T42 -> 0.81921825 | R43: =$D$14*Q42+$B$14*S42+$C$14*T42 -> 0.82577185 | S43: =$B$14*(Q42+R42) -> 0.77570138 | T43: =$C$14*(Q42+R42) -> 0.30890857 | U43: =SUM(Q43:T43) -> 2.7296001 | V43: =$D$15*W42+$B$15*X42+$C$15*Y42 -> 0.81921825 | W43: =$D$15*V42+$B$15*X42+$C$15*Y42 -> 0.82577185 | X43: =$B$15*(V42+W42) -> 0.59039696 | Y43: =$C$15*(V42+W42) -> 0.59039696 | Z43: =SUM(V43:Y43) -> 2.825784
A44: 9 | B44: =$D$11*C43+$B$11*D43+$C$11*E43 -> 0 | C44: =$D$11*B43+$B$11*D43+$C$11*E43 -> 0 | D44: =$B$11*(B43+C43) -> 0.67108864 | E44: =$C$11*(B43+C43) -> 0.67108864 | F44: =SUM(B44:E44) -> 1.3421773 | G44: =$D$12*H43+$B$12*I43+$C$12*J43 -> 3.8404096 | H44: =$D$12*G43+$B$12*I43+$C$12*J43 -> 3.8377882 | I44: =$B$12*(G43+H43) -> 3.0539776 | J44: =$C$12*(G43+H43) -> 3.0539776 | K44: =SUM(G44:J44) -> 13.786153 | L44: =$D$13*M43+$B$13*N43+$C$13*O43 -> 0.34818469 | M44: =$D$13*L43+$B$13*N43+$C$13*O43 -> 0.34818469 | N44: =$B$13*(L43+M43) -> 0.73887027 | O44: =$C$13*(L43+M43) -> 0.73887027 | P44: =SUM(L44:O44) -> 2.1741099 | Q44: =$D$14*R43+$B$14*S43+$C$14*T43 -> 0.68979612 | R44: =$D$14*Q43+$B$14*S43+$C$14*T43 -> 0.68717468 | S44: =$B$14*(Q43+R43) -> 0.65799604 | T44: =$C$14*(Q43+R43) -> 0.26203462 | U44: =SUM(Q44:T44) -> 2.2970015 | V44: =$D$15*W43+$B$15*X43+$C$15*Y43 -> 0.68979612 | W44: =$D$15*V43+$B$15*X43+$C$15*Y43 -> 0.68717468 | X44: =$B$15*(V43+W43) -> 0.50080981 | Y44: =$C$15*(V43+W43) -> 0.50080981 | Z44: =SUM(V44:Y44) -> 2.3785904
A45: 10 | B45: =$D$11*C44+$B$11*D44+$C$11*E44 -> 0.53687091 | C45: =$D$11*B44+$B$11*D44+$C$11*E44 -> 0.53687091 | D45: =$B$11*(B44+C44) -> 0 | E45: =$C$11*(B44+C44) -> 0 | F45: =SUM(B45:E45) -> 1.0737418 | G45: =$D$12*H44+$B$12*I44+$C$12*J44 -> 3.9782973 | H45: =$D$12*G44+$B$12*I44+$C$12*J44 -> 3.9793459 | I45: =$B$12*(G44+H44) -> 3.0712791 | J45: =$C$12*(G44+H44) -> 3.0712791 | K45: =SUM(G45:J45) -> 14.100201 | L45: =$D$13*M44+$B$13*N44+$C$13*O44 -> 0.6188827 | M45: =$D$13*L44+$B$13*N44+$C$13*O44 -> 0.6188827 | N45: =$B$13*(L44+M44) -> 0.27854775 | O45: =$C$13*(L44+M44) -> 0.27854775 | P45: =SUM(L45:O45) -> 1.7948609 | Q45: =$D$14*R44+$B$14*S44+$C$14*T44 -> 0.57980844 | R45: =$D$14*Q44+$B$14*S44+$C$14*T44 -> 0.58085702 | S45: =$B$14*(Q44+R44) -> 0.55078832 | T45: =$C$14*(Q44+R44) -> 0.21934115 | U45: =SUM(Q45:T45) -> 1.9307949 | V45: =$D$15*W44+$B$15*X44+$C$15*Y44 -> 0.57980844 | W45: =$D$15*V44+$B$15*X44+$C$15*Y44 -> 0.58085702 | X45: =$B$15*(V44+W44) -> 0.41921254 | Y45: =$C$15*(V44+W44) -> 0.41921254 | Z45: =SUM(V45:Y45) -> 1.9990906
A46: 11 | B46: =$D$11*C45+$B$11*D45+$C$11*E45 -> 0 | C46: =$D$11*B45+$B$11*D45+$C$11*E45 -> 0 | D46: =$B$11*(B45+C45) -> 0.42949673 | E46: =$C$11*(B45+C45) -> 0.42949673 | F46: =SUM(B46:E46) -> 0.85899346 | G46: =$D$12*H45+$B$12*I45+$C$12*J45 -> 4.0487617 | H46: =$D$12*G45+$B$12*I45+$C$12*J45 -> 4.0483422 | I46: =$B$12*(G45+H45) -> 3.1830573 | J46: =$C$12*(G45+H45) -> 3.1830573 | K46: =SUM(G46:J46) -> 14.463218 | L46: =$D$13*M45+$B$13*N45+$C$13*O45 -> 0.27222743 | M46: =$D$13*L45+$B$13*N45+$C$13*O45 -> 0.27222743 | N46: =$B$13*(L45+M45) -> 0.49510616 | O46: =$C$13*(L45+M45) -> 0.49510616 | P46: =SUM(L46:O46) -> 1.5346672 | Q46: =$D$14*R45+$B$14*S45+$C$14*T45 -> 0.48759754 | R46: =$D$14*Q45+$B$14*S45+$C$14*T45 -> 0.48717811 | S46: =$B$14*(Q45+R45) -> 0.46426619 | T46: =$C$14*(Q45+R45) -> 0.18488533 | U46: =SUM(Q46:T46) -> 1.6239272 | V46: =$D$15*W45+$B$15*X45+$C$15*Y45 -> 0.48759754 | W46: =$D$15*V45+$B$15*X45+$C$15*Y45 -> 0.48717811 | X46: =$B$15*(V45+W45) -> 0.35335936 | Y46: =$C$15*(V45+W45) -> 0.35335936 | Z46: =SUM(V46:Y46) -> 1.6814944
A47: 12 | B47: =$D$11*C46+$B$11*D46+$C$11*E46 -> 0.34359738 | C47: =$D$11*B46+$B$11*D46+$C$11*E46 -> 0.34359738 | D47: =$B$11*(B46+C46) -> 0 | E47: =$C$11*(B46+C46) -> 0 | F47: =SUM(B47:E47) -> 0.68719477 | G47: =$D$12*H46+$B$12*I46+$C$12*J46 -> 4.1657827 | H47: =$D$12*G46+$B$12*I46+$C$12*J46 -> 4.1659505 | I47: =$B$12*(G46+H46) -> 3.2388415 | J47: =$C$12*(G46+H46) -> 3.2388415 | K47: =SUM(G47:J47) -> 14.809416 | L47: =$D$13*M46+$B$13*N46+$C$13*O46 -> 0.41780973 | M47: =$D$13*L46+$B$13*N46+$C$13*O46 -> 0.41780973 | N47: =$B$13*(L46+M46) -> 0.21778194 | O47: =$C$13*(L46+M46) -> 0.21778194 | P47: =SUM(L47:O47) -> 1.2711833 | Q47: =$D$14*R46+$B$14*S46+$C$14*T46 -> 0.41002857 | R47: =$D$14*Q46+$B$14*S46+$C$14*T46 -> 0.41019634 | S47: =$B$14*(Q46+R46) -> 0.38991026 | T47: =$C$14*(Q46+R46) -> 0.15527447 | U47: =SUM(Q47:T47) -> 1.3654096 | V47: =$D$15*W46+$B$15*X46+$C$15*Y46 -> 0.41002857 | W47: =$D$15*V46+$B$15*X46+$C$15*Y46 -> 0.41019634 | X47: =$B$15*(V46+W46) -> 0.29676605 | Y47: =$C$15*(V46+W46) -> 0.29676605 | Z47: =SUM(V47:Y47) -> 1.413757

Sheet Clocks
A1: One gap, two clocks: half-life and amplification (Figure 14.1; Theorems 14.3(i) and 14.4(iii))
A3: Marked | B3: rho | C3: Half-life (quarters) | D3: Quarters to a tenth | E3: Amplification 1/(1 - rho)
A4: Meridian's core today | B4: =Rebudget!E11 -> 0.8 | C4: =LN(2)/LN(1/B4) -> 3.1062837 | D4: =LN(10)/LN(1/B4) -> 10.318851 | E4: =1/(1-B4) -> 5
A5: The board's limit | B5: =R_star -> 0.84089642 | C5: =LN(2)/LN(1/B5) -> 4 | D5: =LN(10)/LN(1/B5) -> 13.287712 | E5: =1/(1-B5) -> 6.2852135
A6: A company near the edge | B6: =Edge_rho -> 0.95 | C6: =LN(2)/LN(1/B6) -> 13.513407 | D6: =LN(10)/LN(1/B6) -> 44.890567 | E6: =1/(1-B6) -> 20
B8: rho | C8: Half-life (quarters) | D8: Quarters to a tenth | E8: Amplification 1/(1 - rho)
B9: 0.3 | C9: =LN(2)/LN(1/B9) -> 0.57571664 | D9: =LN(10)/LN(1/B9) -> 1.9124893 | E9: =1/(1-B9) -> 1.4285714
B10: 0.31 | C10: =LN(2)/LN(1/B10) -> 0.59183509 | D10: =LN(10)/LN(1/B10) -> 1.9660336 | E10: =1/(1-B10) -> 1.4492754
B11: 0.32 | C11: =LN(2)/LN(1/B11) -> 0.60832572 | D11: =LN(10)/LN(1/B11) -> 2.0208143 | E11: =1/(1-B11) -> 1.4705882
B12: 0.33 | C12: =LN(2)/LN(1/B12) -> 0.6252102 | D12: =LN(10)/LN(1/B12) -> 2.0769033 | E12: =1/(1-B12) -> 1.4925373
B13: 0.34 | C13: =LN(2)/LN(1/B13) -> 0.6425111 | D13: =LN(10)/LN(1/B13) -> 2.1343757 | E13: =1/(1-B13) -> 1.5151515
B14: 0.35 | C14: =LN(2)/LN(1/B14) -> 0.66025202 | D14: =LN(10)/LN(1/B14) -> 2.1933097 | E14: =1/(1-B14) -> 1.5384615
B15: 0.36 | C15: =LN(2)/LN(1/B15) -> 0.67845772 | D15: =LN(10)/LN(1/B15) -> 2.2537878 | E15: =1/(1-B15) -> 1.5625
B16: 0.37 | C16: =LN(2)/LN(1/B16) -> 0.69715423 | D16: =LN(10)/LN(1/B16) -> 2.3158962 | E16: =1/(1-B16) -> 1.5873016
B17: 0.38 | C17: =LN(2)/LN(1/B17) -> 0.71636898 | D17: =LN(10)/LN(1/B17) -> 2.3797262 | E17: =1/(1-B17) -> 1.6129032
B18: 0.39 | C18: =LN(2)/LN(1/B18) -> 0.73613094 | D18: =LN(10)/LN(1/B18) -> 2.4453741 | E18: =1/(1-B18) -> 1.6393443
B19: 0.4 | C19: =LN(2)/LN(1/B19) -> 0.7564708 | D19: =LN(10)/LN(1/B19) -> 2.5129416 | E19: =1/(1-B19) -> 1.6666667
B20: 0.41 | C20: =LN(2)/LN(1/B20) -> 0.77742109 | D20: =LN(10)/LN(1/B20) -> 2.582537 | E20: =1/(1-B20) -> 1.6949153
... B78: 0.99 | C78: =LN(2)/LN(1/B78) -> 68.967564 | D78: =LN(10)/LN(1/B78) -> 229.10529 | E78: =1/(1-B78) -> 100
A80: A company that keeps a share rho of every deviation each quarter has a half-life of ln 2 / ln(1/rho) and amplifies a permanent change 1/(1 - rho) times: the gap that slows recovery amplifies every recalibration.

Sheet Sensitivity
A1: Sensitivity explorer: walks, the Perron identity, elasticities and the blow-up dial (Theorem 14.4(ii)-(iii); Worked Example 14.1, Step 4; AXIOM Lab 1.14, step 2)
A2: Today's register at its ceilings. (I - M)^-1 B = B + MB + M^2 B + ...: walks of n links carry the shortfall at Digital to the other units.
A4: Walks of n links | B4: IND | C4: DIG | D4: ENG | E4: TRS | F4: Core | G4: Cumulative: IND | H4: Cumulative: DIG | I4: Cumulative: ENG | J4: Cumulative: TRS | K4: Cumulative: core
A5: 0 | B5: 0 | C5: =Shock -> 10 | D5: 0 | E5: 0 | F5: =SUM(B5:E5) -> 10 | G5: =B5 -> 0 | H5: =C5 -> 10 | I5: =D5 -> 0 | J5: =E5 -> 0 | K5: =F5 -> 10
A6: 1 | B6: =0*C5+Ceiling*D5+Ceiling*E5 -> 0 | C6: =0*B5+Ceiling*D5+Ceiling*E5 -> 0 | D6: =Ceiling*(B5+C5) -> 4 | E6: =Ceiling*(B5+C5) -> 4 | F6: =SUM(B6:E6) -> 8 | G6: =G5+B6 -> 0 | H6: =H5+C6 -> 10 | I6: =I5+D6 -> 4 | J6: =J5+E6 -> 4 | K6: =K5+F6 -> 18
A7: 2 | B7: =0*C6+Ceiling*D6+Ceiling*E6 -> 3.2 | C7: =0*B6+Ceiling*D6+Ceiling*E6 -> 3.2 | D7: =Ceiling*(B6+C6) -> 0 | E7: =Ceiling*(B6+C6) -> 0 | F7: =SUM(B7:E7) -> 6.4 | G7: =G6+B7 -> 3.2 | H7: =H6+C7 -> 13.2 | I7: =I6+D7 -> 4 | J7: =J6+E7 -> 4 | K7: =K6+F7 -> 24.4
A8: 3 | B8: =0*C7+Ceiling*D7+Ceiling*E7 -> 0 | C8: =0*B7+Ceiling*D7+Ceiling*E7 -> 0 | D8: =Ceiling*(B7+C7) -> 2.56 | E8: =Ceiling*(B7+C7) -> 2.56 | F8: =SUM(B8:E8) -> 5.12 | G8: =G7+B8 -> 3.2 | H8: =H7+C8 -> 13.2 | I8: =I7+D8 -> 6.56 | J8: =J7+E8 -> 6.56 | K8: =K7+F8 -> 29.52
A9: 4 | B9: =0*C8+Ceiling*D8+Ceiling*E8 -> 2.048 | C9: =0*B8+Ceiling*D8+Ceiling*E8 -> 2.048 | D9: =Ceiling*(B8+C8) -> 0 | E9: =Ceiling*(B8+C8) -> 0 | F9: =SUM(B9:E9) -> 4.096 | G9: =G8+B9 -> 5.248 | H9: =H8+C9 -> 15.248 | I9: =I8+D9 -> 6.56 | J9: =J8+E9 -> 6.56 | K9: =K8+F9 -> 33.616
A10: 5 | B10: =0*C9+Ceiling*D9+Ceiling*E9 -> 0 | C10: =0*B9+Ceiling*D9+Ceiling*E9 -> 0 | D10: =Ceiling*(B9+C9) -> 1.6384 | E10: =Ceiling*(B9+C9) -> 1.6384 | F10: =SUM(B10:E10) -> 3.2768 | G10: =G9+B10 -> 5.248 | H10: =H9+C10 -> 15.248 | I10: =I9+D10 -> 8.1984 | J10: =J9+E10 -> 8.1984 | K10: =K9+F10 -> 36.8928
A11: 6 | B11: =0*C10+Ceiling*D10+Ceiling*E10 -> 1.31072 | C11: =0*B10+Ceiling*D10+Ceiling*E10 -> 1.31072 | D11: =Ceiling*(B10+C10) -> 0 | E11: =Ceiling*(B10+C10) -> 0 | F11: =SUM(B11:E11) -> 2.62144 | G11: =G10+B11 -> 6.55872 | H11: =H10+C11 -> 16.55872 | I11: =I10+D11 -> 8.1984 | J11: =J10+E11 -> 8.1984 | K11: =K10+F11 -> 39.51424
A12: 7 | B12: =0*C11+Ceiling*D11+Ceiling*E11 -> 0 | C12: =0*B11+Ceiling*D11+Ceiling*E11 -> 0 | D12: =Ceiling*(B11+C11) -> 1.048576 | E12: =Ceiling*(B11+C11) -> 1.048576 | F12: =SUM(B12:E12) -> 2.097152 | G12: =G11+B12 -> 6.55872 | H12: =H11+C12 -> 16.55872 | I12: =I11+D12 -> 9.246976 | J12: =J11+E12 -> 9.246976 | K12: =K11+F12 -> 41.611392
A13: 8 | B13: =0*C12+Ceiling*D12+Ceiling*E12 -> 0.8388608 | C13: =0*B12+Ceiling*D12+Ceiling*E12 -> 0.8388608 | D13: =Ceiling*(B12+C12) -> 0 | E13: =Ceiling*(B12+C12) -> 0 | F13: =SUM(B13:E13) -> 1.6777216 | G13: =G12+B13 -> 7.3975808 | H13: =H12+C13 -> 17.397581 | I13: =I12+D13 -> 9.246976 | J13: =J12+E13 -> 9.246976 | K13: =K12+F13 -> 43.289114
A14: 9 | B14: =0*C13+Ceiling*D13+Ceiling*E13 -> 0 | C14: =0*B13+Ceiling*D13+Ceiling*E13 -> 0 | D14: =Ceiling*(B13+C13) -> 0.67108864 | E14: =Ceiling*(B13+C13) -> 0.67108864 | F14: =SUM(B14:E14) -> 1.3421773 | G14: =G13+B14 -> 7.3975808 | H14: =H13+C14 -> 17.397581 | I14: =I13+D14 -> 9.9180646 | J14: =J13+E14 -> 9.9180646 | K14: =K13+F14 -> 44.631291
A15: 10 | B15: =0*C14+Ceiling*D14+Ceiling*E14 -> 0.53687091 | C15: =0*B14+Ceiling*D14+Ceiling*E14 -> 0.53687091 | D15: =Ceiling*(B14+C14) -> 0 | E15: =Ceiling*(B14+C14) -> 0 | F15: =SUM(B15:E15) -> 1.0737418 | G15: =G14+B15 -> 7.9344517 | H15: =H14+C15 -> 17.934452 | I15: =I14+D15 -> 9.9180646 | J15: =J14+E15 -> 9.9180646 | K15: =K14+F15 -> 45.705033
A16: 11 | B16: =0*C15+Ceiling*D15+Ceiling*E15 -> 0 | C16: =0*B15+Ceiling*D15+Ceiling*E15 -> 0 | D16: =Ceiling*(B15+C15) -> 0.42949673 | E16: =Ceiling*(B15+C15) -> 0.42949673 | F16: =SUM(B16:E16) -> 0.85899346 | G16: =G15+B16 -> 7.9344517 | H16: =H15+C16 -> 17.934452 | I16: =I15+D16 -> 10.347561 | J16: =J15+E16 -> 10.347561 | K16: =K15+F16 -> 46.564026
A17: 12 | B17: =0*C16+Ceiling*D16+Ceiling*E16 -> 0.34359738 | C17: =0*B16+Ceiling*D16+Ceiling*E16 -> 0.34359738 | D17: =Ceiling*(B16+C16) -> 0 | E17: =Ceiling*(B16+C16) -> 0 | F17: =SUM(B17:E17) -> 0.68719477 | G17: =G16+B17 -> 8.2780491 | H17: =H16+C17 -> 18.278049 | I17: =I16+D17 -> 10.347561 | J17: =J16+E17 -> 10.347561 | K17: =K16+F17 -> 47.251221
... A45: 40 | B45: =0*C44+Ceiling*D44+Ceiling*E44 -> 0.000664614 | C45: =0*B44+Ceiling*D44+Ceiling*E44 -> 0.000664614 | D45: =Ceiling*(B44+C44) -> 0 | E45: =Ceiling*(B44+C44) -> 0 | F45: =SUM(B45:E45) -> 0.001329228 | G45: =G44+B45 -> 8.8877074 | H45: =H44+C45 -> 18.887707 | I45: =I44+D45 -> 11.109634 | J45: =J44+E45 -> 11.109634 | K45: =K44+F45 -> 49.994683
A47: Settled (Rebudget, today) | G47: =Rebudget!O11 -> 8.8888889 | H47: =Rebudget!P11 -> 18.888889 | I47: =Rebudget!Q11 -> 11.111111 | J47: =Rebudget!R11 -> 11.111111 | K47: =Rebudget!S11 -> 50
A48: Direct effect (walks of no links) and knock-on | B48: =F5 -> 10 | C48: =K47-F5 -> 40
A50: Repair at the rule's limit | B50: rho | C50: Perron weight IND | D50: DIG | E50: ENG | F50: TRS | G50: Perron-weighted settled | H50: Shock / (1 - rho) | I50: Plain settled total
A51: =Rebudget!A13 -> Run the new link light | B51: =Rebudget!E13 -> 0.84089642 | C51: 1 | D51: 1 | E51: =2*Rebudget!B13/B51 -> 0.95136569 | F51: =2*Rebudget!C13/B51 -> 0.95136569 | G51: =SUMPRODUCT(C51:F51,Rebudget!O13:R13) -> 62.852135 | H51: =Shock/(1-B51) -> 62.852135 | I51: =Rebudget!S13 -> 64.240714
A52: =Rebudget!A14 -> Ring-fence treasury | B52: =Rebudget!E14 -> 0.84089642 | C52: 1 | D52: 1 | E52: =2*Rebudget!B14/B52 -> 0.95136569 | F52: =2*Rebudget!C14/B52 -> 0.3788636 | G52: =SUMPRODUCT(C52:F52,Rebudget!O14:R14) -> 62.852135 | H52: =Shock/(1-B52) -> 62.852135 | I52: =Rebudget!S14 -> 68.016592
A53: =Rebudget!A15 -> Trim every existing link | B53: =Rebudget!E15 -> 0.84089642 | C53: 1 | D53: 1 | E53: =2*Rebudget!B15/B53 -> 0.72409748 | F53: =2*Rebudget!C15/B53 -> 0.72409748 | G53: =SUMPRODUCT(C53:F53,Rebudget!O15:R15) -> 62.852135 | H53: =Shock/(1-B53) -> 62.852135 | I53: =Rebudget!S15 -> 70.180085
A54: Perron weights (1, 1, 2e/rho, 2t/rho) solve w'M = rho w' for the symmetric core; the Perron-weighted response is exactly the Perron-weighted direct effect over 1 - rho (Theorem 14.4(iii)).
A57: Elasticities, today (percent per percent) | B57: Engineering links e | C57: Treasury links t | D57: New link h
A58: Industrial Systems | B58: =$B$65/(($B$69-$B$70)/2)*($B$71-0)/2 -> 2.7777778 | C58: =$B$66/(($B$69-$B$70)/2)*($B$72-0)/2 -> 2.7777778 | D58: =$B$67/(($B$69-$B$70)/2)*($B$73-$B$74)/2 -> 0
A59: Digital | B59: =$B$65/(($B$69+$B$70)/2)*($B$71+0)/2 -> 1.3071895 | C59: =$B$66/(($B$69+$B$70)/2)*($B$72+0)/2 -> 1.3071895 | D59: =$B$67/(($B$69+$B$70)/2)*($B$73+$B$74)/2 -> 0
A60: Engineering | B60: =$B$65/($B$65*$B$69)*($B$69+$B$65*$B$71) -> 2.7777778 | C60: =$B$66/($B$65*$B$69)*($B$65*$B$72) -> 1.7777778 | D60: =$B$67/($B$65*$B$69)*($B$65*$B$73) -> 0
A61: Treasury | B61: =$B$65/($B$66*$B$69)*($B$66*$B$71) -> 1.7777778 | C61: =$B$66/($B$66*$B$69)*($B$69+$B$66*$B$72) -> 2.7777778 | D61: =$B$67/($B$66*$B$69)*($B$66*$B$73) -> 0
A62: Core total | B62: =$B$65/($B$69*(1+$B$65+$B$66))*($B$71*(1+$B$65+$B$66)+$B$69) -> 2 | C62: =$B$66/($B$69*(1+$B$65+$B$66))*($B$72*(1+$B$65+$B$66)+$B$69) -> 2 | D62: =$B$67/($B$69*(1+$B$65+$B$66))*($B$73*(1+$B$65+$B$66)) -> 0
A63: Spectral radius | B63: =$B$65/$B$76*4*$B$65/$B$75 -> 0.5 | C63: =$B$66/$B$76*4*$B$66/$B$75 -> 0.5 | D63: =$B$67/$B$76*0.5*(1+$B$67/$B$75) -> 0
A64: Sum of the radius's elasticities (it is homogeneous in the gains) | B64: =SUM(B63:D63) -> 1
A65: e | B65: =Rebudget!B11 -> 0.4
A66: t | B66: =Rebudget!C11 -> 0.4
A67: h | B67: =Rebudget!D11 -> 0
A68: D = 1 - h - 2(e^2 + t^2) | B68: =1-B67-2*(B65^2+B66^2) -> 0.36
A69: S = Shock / D | B69: =Shock/B68 -> 27.777778
A70: Delta = Shock / (1 + h) | B70: =Shock/(1+B67) -> 10
A71: dS/de = 4eS/D | B71: =4*B65*B69/B68 -> 123.45679
A72: dS/dt = 4tS/D | B72: =4*B66*B69/B68 -> 123.45679
A73: dS/dh = S/D | B73: =B69/B68 -> 77.160494
A74: dDelta/dh = -Delta/(1 + h) | B74: =-B70/(1+B67) -> -10
A75: Q = sqrt(h^2 + 8(e^2 + t^2)) | B75: =SQRT(B67^2+8*(B65^2+B66^2)) -> 1.6
A76: rho = (h + Q)/2 | B76: =(B67+B75)/2 -> 0.8
A79: Elasticities, trim every existing link (percent per percent) | B79: Engineering links e | C79: Treasury links t | D79: New link h
A80: Industrial Systems | B80: =$B$87/(($B$91-$B$92)/2)*($B$93-0)/2 -> 1.933886 | C80: =$B$88/(($B$91-$B$92)/2)*($B$94-0)/2 -> 1.933886 | D80: =$B$89/(($B$91-$B$92)/2)*($B$95-$B$96)/2 -> 2.1424159
A81: Digital | B81: =$B$87/(($B$91+$B$92)/2)*($B$93+0)/2 -> 1.3896524 | C81: =$B$88/(($B$91+$B$92)/2)*($B$94+0)/2 -> 1.3896524 | D81: =$B$89/(($B$91+$B$92)/2)*($B$95+$B$96)/2 -> 1.4590922
A82: Engineering | B82: =$B$87/($B$87*$B$91)*($B$91+$B$87*$B$93) -> 2.6172097 | C82: =$B$88/($B$87*$B$91)*($B$87*$B$94) -> 1.6172097 | D82: =$B$89/($B$87*$B$91)*($B$87*$B$95) -> 1.7448065
A83: Treasury | B83: =$B$87/($B$88*$B$91)*($B$88*$B$93) -> 1.6172097 | C83: =$B$88/($B$88*$B$91)*($B$91+$B$88*$B$94) -> 2.6172097 | D83: =$B$89/($B$88*$B$91)*($B$88*$B$95) -> 1.7448065
A84: Core total | B84: =$B$87/($B$91*(1+$B$87+$B$88))*($B$93*(1+$B$87+$B$88)+$B$91) -> 1.8064366 | C84: =$B$88/($B$91*(1+$B$87+$B$88))*($B$94*(1+$B$87+$B$88)+$B$91) -> 1.8064366 | D84: =$B$89/($B$91*(1+$B$87+$B$88))*($B$95*(1+$B$87+$B$88)) -> 1.7448065
A85: Spectral radius | B85: =$B$87/$B$98*4*$B$87/$B$97 -> 0.34396855 | C85: =$B$88/$B$98*4*$B$88/$B$97 -> 0.34396855 | D85: =$B$89/$B$98*0.5*(1+$B$89/$B$97) -> 0.31206291
A86: Sum of the radius's elasticities (it is homogeneous in the gains) | B86: =SUM(B85:D85) -> 1
A87: e | B87: =Rebudget!B15 -> 0.30444549
A88: t | B88: =Rebudget!C15 -> 0.30444549
A89: h | B89: =Rebudget!D15 -> 0.4
A90: D = 1 - h - 2(e^2 + t^2) | B90: =1-B89-2*(B87^2+B88^2) -> 0.22925178
A91: S = Shock / D | B91: =Shock/B90 -> 43.620162
A92: Delta = Shock / (1 + h) | B92: =Shock/(1+B89) -> 7.1428571
A93: dS/de = 4eS/D | B93: =4*B87*B91/B90 -> 231.70963
A94: dS/dt = 4tS/D | B94: =4*B88*B91/B90 -> 231.70963
A95: dS/dh = S/D | B95: =B91/B90 -> 190.27185
A96: dDelta/dh = -Delta/(1 + h) | B96: =-B92/(1+B89) -> -5.1020408
A97: Q = sqrt(h^2 + 8(e^2 + t^2)) | B97: =SQRT(B89^2+8*(B87^2+B88^2)) -> 1.2817928
A98: rho = (h + Q)/2 | B98: =(B89+B97)/2 -> 0.84089642
A102: The blow-up dial: today's gains times c | B102: rho | C102: c = rho / today's rho | D102: Amplification | E102: Half-life (quarters) | F102: Settled total | G102: Settled at Digital
A103: today | B103: 0.8 | C103: =B103/Rebudget!$E$11 -> 1 | D103: =1/(1-B103) -> 5 | E103: =LN(2)/LN(1/B103) -> 3.1062837 | F103: =Shock/(1-4*(Ceiling*C103)^2)*(1+2*Ceiling*C103) -> 50 | G103: =(Shock/(1-4*(Ceiling*C103)^2)+Shock)/2 -> 18.888889
A104: the board's limit | B104: =R_star -> 0.84089642 | C104: =B104/Rebudget!$E$11 -> 1.0511205 | D104: =1/(1-B104) -> 6.2852135 | E104: =LN(2)/LN(1/B104) -> 4 | F104: =Shock/(1-4*(Ceiling*C104)^2)*(1+2*Ceiling*C104) -> 62.852135 | G104: =(Shock/(1-4*(Ceiling*C104)^2)+Shock)/2 -> 22.071068
B105: 0.9 | C105: =B105/Rebudget!$E$11 -> 1.125 | D105: =1/(1-B105) -> 10 | E105: =LN(2)/LN(1/B105) -> 6.5788135 | F105: =Shock/(1-4*(Ceiling*C105)^2)*(1+2*Ceiling*C105) -> 100 | G105: =(Shock/(1-4*(Ceiling*C105)^2)+Shock)/2 -> 31.315789
A106: near the edge | B106: 0.95 | C106: =B106/Rebudget!$E$11 -> 1.1875 | D106: =1/(1-B106) -> 20 | E106: =LN(2)/LN(1/B106) -> 13.513407 | F106: =Shock/(1-4*(Ceiling*C106)^2)*(1+2*Ceiling*C106) -> 200 | G106: =(Shock/(1-4*(Ceiling*C106)^2)+Shock)/2 -> 56.282051
B107: 0.97 | C107: =B107/Rebudget!$E$11 -> 1.2125 | D107: =1/(1-B107) -> 33.333333 | E107: =LN(2)/LN(1/B107) -> 22.756573 | F107: =Shock/(1-4*(Ceiling*C107)^2)*(1+2*Ceiling*C107) -> 333.33333 | G107: =(Shock/(1-4*(Ceiling*C107)^2)+Shock)/2 -> 89.602369
B108: 0.99 | C108: =B108/Rebudget!$E$11 -> 1.2375 | D108: =1/(1-B108) -> 100 | E108: =LN(2)/LN(1/B108) -> 68.967564 | F108: =Shock/(1-4*(Ceiling*C108)^2)*(1+2*Ceiling*C108) -> 1000 | G108: =(Shock/(1-4*(Ceiling*C108)^2)+Shock)/2 -> 256.25628

Sheet Perturbations
A1: Perturbation simulator: a state shock, a recalibration, a structural change (Definition 14.7; Theorem 14.4(i); Worked Example 14.1, Step 5; AXIOM Lab 1.14, step 3)
A2: Today's register at its ceilings. State: the echo of a one-off shock. Parametric: S_(k+1) = M S_k + B. Structural: the new link, which today's model has no parameter for.
V3: A recalibration and a tangent | W3: Value
A4: Quarter | B4: Echo of 2 x Shock: core | C4: Echo of Shock: core (Rebudget) | D4: Ratio | E4: S_k: IND | F4: S_k: DIG | G4: S_k: ENG | H4: S_k: TRS | I4: S_k: core | J4: New link: IND | K4: DIG | L4: ENG | M4: TRS | N4: New link: core | O4: Cumulative: today | P4: Cumulative: new link | Q4: Shock x2: IND | R4: DIG | S4: ENG | T4: TRS | V4: Engineering links today, e0 | W4: =Ceiling -> 0.4
A5: 0 | B5: =SUM(Q5:T5) -> 20 | C5: =Rebudget!F35 -> 10 | D5: =B5/C5 -> 2 | E5: 0 | F5: 0 | G5: 0 | H5: 0 | I5: =SUM(E5:H5) -> 0 | J5: 0 | K5: =Shock -> 10 | L5: 0 | M5: 0 | N5: =SUM(J5:M5) -> 10 | O5: =(Q5+R5+S5+T5)/2 -> 10 | P5: =N5 -> 10 | Q5: 0 | R5: =2*Shock -> 20 | S5: 0 | T5: 0 | V5: Recalibrated engineering links, e1 | W5: 0.39
A6: 1 | B6: =SUM(Q6:T6) -> 16 | C6: =Rebudget!F36 -> 8 | D6: =B6/C6 -> 2 | E6: =0*F5+Ceiling*G5+Ceiling*H5 -> 0 | F6: =0*E5+Ceiling*G5+Ceiling*H5+Shock -> 10 | G6: =Ceiling*(E5+F5) -> 0 | H6: =Ceiling*(E5+F5) -> 0 | I6: =SUM(E6:H6) -> 10 | J6: =Ceiling*K5+Ceiling*L5+Ceiling*M5 -> 4 | K6: =Ceiling*J5+Ceiling*L5+Ceiling*M5 -> 0 | L6: =Ceiling*(J5+K5) -> 4 | M6: =Ceiling*(J5+K5) -> 4 | N6: =SUM(J6:M6) -> 12 | O6: =O5+(Q6+R6+S6+T6)/2 -> 18 | P6: =P5+N6 -> 22 | Q6: =0*R5+Ceiling*S5+Ceiling*T5 -> 0 | R6: =0*Q5+Ceiling*S5+Ceiling*T5 -> 0 | S6: =Ceiling*(Q5+R5) -> 8 | T6: =Ceiling*(Q5+R5) -> 8 | V6: Treasury links, t | W6: =Ceiling -> 0.4
A7: 2 | B7: =SUM(Q7:T7) -> 12.8 | C7: =Rebudget!F37 -> 6.4 | D7: =B7/C7 -> 2 | E7: =0*F6+Ceiling*G6+Ceiling*H6 -> 0 | F7: =0*E6+Ceiling*G6+Ceiling*H6+Shock -> 10 | G7: =Ceiling*(E6+F6) -> 4 | H7: =Ceiling*(E6+F6) -> 4 | I7: =SUM(E7:H7) -> 18 | J7: =Ceiling*K6+Ceiling*L6+Ceiling*M6 -> 3.2 | K7: =Ceiling*J6+Ceiling*L6+Ceiling*M6 -> 4.8 | L7: =Ceiling*(J6+K6) -> 1.6 | M7: =Ceiling*(J6+K6) -> 1.6 | N7: =SUM(J7:M7) -> 11.2 | O7: =O6+(Q7+R7+S7+T7)/2 -> 24.4 | P7: =P6+N7 -> 33.2 | Q7: =0*R6+Ceiling*S6+Ceiling*T6 -> 6.4 | R7: =0*Q6+Ceiling*S6+Ceiling*T6 -> 6.4 | S7: =Ceiling*(Q6+R6) -> 0 | T7: =Ceiling*(Q6+R6) -> 0 | V7: Q0 = sqrt(8(e0^2 + t^2)) | W7: =SQRT(8*(W4^2+W6^2)) -> 1.6
A8: 3 | B8: =SUM(Q8:T8) -> 10.24 | C8: =Rebudget!F38 -> 5.12 | D8: =B8/C8 -> 2 | E8: =0*F7+Ceiling*G7+Ceiling*H7 -> 3.2 | F8: =0*E7+Ceiling*G7+Ceiling*H7+Shock -> 13.2 | G8: =Ceiling*(E7+F7) -> 4 | H8: =Ceiling*(E7+F7) -> 4 | I8: =SUM(E8:H8) -> 24.4 | J8: =Ceiling*K7+Ceiling*L7+Ceiling*M7 -> 3.2 | K8: =Ceiling*J7+Ceiling*L7+Ceiling*M7 -> 2.56 | L8: =Ceiling*(J7+K7) -> 3.2 | M8: =Ceiling*(J7+K7) -> 3.2 | N8: =SUM(J8:M8) -> 12.16 | O8: =O7+(Q8+R8+S8+T8)/2 -> 29.52 | P8: =P7+N8 -> 45.36 | Q8: =0*R7+Ceiling*S7+Ceiling*T7 -> 0 | R8: =0*Q7+Ceiling*S7+Ceiling*T7 -> 0 | S8: =Ceiling*(Q7+R7) -> 5.12 | T8: =Ceiling*(Q7+R7) -> 5.12 | V8: rho(e0) | W8: =W7/2 -> 0.8
A9: 4 | B9: =SUM(Q9:T9) -> 8.192 | C9: =Rebudget!F39 -> 4.096 | D9: =B9/C9 -> 2 | E9: =0*F8+Ceiling*G8+Ceiling*H8 -> 3.2 | F9: =0*E8+Ceiling*G8+Ceiling*H8+Shock -> 13.2 | G9: =Ceiling*(E8+F8) -> 6.56 | H9: =Ceiling*(E8+F8) -> 6.56 | I9: =SUM(E9:H9) -> 29.52 | J9: =Ceiling*K8+Ceiling*L8+Ceiling*M8 -> 3.584 | K9: =Ceiling*J8+Ceiling*L8+Ceiling*M8 -> 3.84 | L9: =Ceiling*(J8+K8) -> 2.304 | M9: =Ceiling*(J8+K8) -> 2.304 | N9: =SUM(J9:M9) -> 12.032 | O9: =O8+(Q9+R9+S9+T9)/2 -> 33.616 | P9: =P8+N9 -> 57.392 | Q9: =0*R8+Ceiling*S8+Ceiling*T8 -> 4.096 | R9: =0*Q8+Ceiling*S8+Ceiling*T8 -> 4.096 | S9: =Ceiling*(Q8+R8) -> 0 | T9: =Ceiling*(Q8+R8) -> 0 | V9: d rho / d e = 4 e0 / Q0 | W9: =4*W4/W7 -> 1
A10: 5 | B10: =SUM(Q10:T10) -> 6.5536 | C10: =Rebudget!F40 -> 3.2768 | D10: =B10/C10 -> 2 | E10: =0*F9+Ceiling*G9+Ceiling*H9 -> 5.248 | F10: =0*E9+Ceiling*G9+Ceiling*H9+Shock -> 15.248 | G10: =Ceiling*(E9+F9) -> 6.56 | H10: =Ceiling*(E9+F9) -> 6.56 | I10: =SUM(E10:H10) -> 33.616 | J10: =Ceiling*K9+Ceiling*L9+Ceiling*M9 -> 3.3792 | K10: =Ceiling*J9+Ceiling*L9+Ceiling*M9 -> 3.2768 | L10: =Ceiling*(J9+K9) -> 2.9696 | M10: =Ceiling*(J9+K9) -> 2.9696 | N10: =SUM(J10:M10) -> 12.5952 | O10: =O9+(Q10+R10+S10+T10)/2 -> 36.8928 | P10: =P9+N10 -> 69.9872 | Q10: =0*R9+Ceiling*S9+Ceiling*T9 -> 0 | R10: =0*Q9+Ceiling*S9+Ceiling*T9 -> 0 | S10: =Ceiling*(Q9+R9) -> 3.2768 | T10: =Ceiling*(Q9+R9) -> 3.2768 | V10: Settled total T(e0) = S (1 + e + t), S = Shock/(1 - 2(e^2 + t^2)) | W10: =Shock/(1-2*(W4^2+W6^2))*(1+W4+W6) -> 50
A11: 6 | B11: =SUM(Q11:T11) -> 5.24288 | C11: =Rebudget!F41 -> 2.62144 | D11: =B11/C11 -> 2 | E11: =0*F10+Ceiling*G10+Ceiling*H10 -> 5.248 | F11: =0*E10+Ceiling*G10+Ceiling*H10+Shock -> 15.248 | G11: =Ceiling*(E10+F10) -> 8.1984 | H11: =Ceiling*(E10+F10) -> 8.1984 | I11: =SUM(E11:H11) -> 36.8928 | J11: =Ceiling*K10+Ceiling*L10+Ceiling*M10 -> 3.6864 | K11: =Ceiling*J10+Ceiling*L10+Ceiling*M10 -> 3.72736 | L11: =Ceiling*(J10+K10) -> 2.6624 | M11: =Ceiling*(J10+K10) -> 2.6624 | N11: =SUM(J11:M11) -> 12.73856 | O11: =O10+(Q11+R11+S11+T11)/2 -> 39.51424 | P11: =P10+N11 -> 82.72576 | Q11: =0*R10+Ceiling*S10+Ceiling*T10 -> 2.62144 | R11: =0*Q10+Ceiling*S10+Ceiling*T10 -> 2.62144 | S11: =Ceiling*(Q10+R10) -> 0 | T11: =Ceiling*(Q10+R10) -> 0 | V11: dT/de = (4 e S / D)(1 + e + t) + S | W11: =4*W4*(Shock/(1-2*(W4^2+W6^2)))/(1-2*(W4^2+W6^2))*(1+W4+W6)+Shock/(1-2*(W4^2+W6^2)) -> 250
A12: 7 | B12: =SUM(Q12:T12) -> 4.194304 | C12: =Rebudget!F42 -> 2.097152 | D12: =B12/C12 -> 2 | E12: =0*F11+Ceiling*G11+Ceiling*H11 -> 6.55872 | F12: =0*E11+Ceiling*G11+Ceiling*H11+Shock -> 16.55872 | G12: =Ceiling*(E11+F11) -> 8.1984 | H12: =Ceiling*(E11+F11) -> 8.1984 | I12: =SUM(E12:H12) -> 39.51424 | J12: =Ceiling*K11+Ceiling*L11+Ceiling*M11 -> 3.620864 | K12: =Ceiling*J11+Ceiling*L11+Ceiling*M11 -> 3.60448 | L12: =Ceiling*(J11+K11) -> 2.965504 | M12: =Ceiling*(J11+K11) -> 2.965504 | N12: =SUM(J12:M12) -> 13.156352 | O12: =O11+(Q12+R12+S12+T12)/2 -> 41.611392 | P12: =P11+N12 -> 95.882112 | Q12: =0*R11+Ceiling*S11+Ceiling*T11 -> 0 | R12: =0*Q11+Ceiling*S11+Ceiling*T11 -> 0 | S12: =Ceiling*(Q11+R11) -> 2.097152 | T12: =Ceiling*(Q11+R11) -> 2.097152 | V12: First order: rho(e1) | W12: =W8+(W5-W4)*W9 -> 0.79
A13: 8 | B13: =SUM(Q13:T13) -> 3.3554432 | C13: =Rebudget!F43 -> 1.6777216 | D13: =B13/C13 -> 2 | E13: =0*F12+Ceiling*G12+Ceiling*H12 -> 6.55872 | F13: =0*E12+Ceiling*G12+Ceiling*H12+Shock -> 16.55872 | G13: =Ceiling*(E12+F12) -> 9.246976 | H13: =Ceiling*(E12+F12) -> 9.246976 | I13: =SUM(E13:H13) -> 41.611392 | J13: =Ceiling*K12+Ceiling*L12+Ceiling*M12 -> 3.8141952 | K13: =Ceiling*J12+Ceiling*L12+Ceiling*M12 -> 3.8207488 | L13: =Ceiling*(J12+K12) -> 2.8901376 | M13: =Ceiling*(J12+K12) -> 2.8901376 | N13: =SUM(J13:M13) -> 13.415219 | O13: =O12+(Q13+R13+S13+T13)/2 -> 43.289114 | P13: =P12+N13 -> 109.29733 | Q13: =0*R12+Ceiling*S12+Ceiling*T12 -> 1.6777216 | R13: =0*Q12+Ceiling*S12+Ceiling*T12 -> 1.6777216 | S13: =Ceiling*(Q12+R12) -> 0 | T13: =Ceiling*(Q12+R12) -> 0 | V13: Re-analysis: rho(e1) | W13: =SQRT(2*(W5^2+W6^2)) -> 0.79006329
A14: 9 | B14: =SUM(Q14:T14) -> 2.6843546 | C14: =Rebudget!F44 -> 1.3421773 | D14: =B14/C14 -> 2 | E14: =0*F13+Ceiling*G13+Ceiling*H13 -> 7.3975808 | F14: =0*E13+Ceiling*G13+Ceiling*H13+Shock -> 17.397581 | G14: =Ceiling*(E13+F13) -> 9.246976 | H14: =Ceiling*(E13+F13) -> 9.246976 | I14: =SUM(E14:H14) -> 43.289114 | J14: =Ceiling*K13+Ceiling*L13+Ceiling*M13 -> 3.8404096 | K14: =Ceiling*J13+Ceiling*L13+Ceiling*M13 -> 3.8377882 | L14: =Ceiling*(J13+K13) -> 3.0539776 | M14: =Ceiling*(J13+K13) -> 3.0539776 | N14: =SUM(J14:M14) -> 13.786153 | O14: =O13+(Q14+R14+S14+T14)/2 -> 44.631291 | P14: =P13+N14 -> 123.08348 | Q14: =0*R13+Ceiling*S13+Ceiling*T13 -> 0 | R14: =0*Q13+Ceiling*S13+Ceiling*T13 -> 0 | S14: =Ceiling*(Q13+R13) -> 1.3421773 | T14: =Ceiling*(Q13+R13) -> 1.3421773 | V14: First order: T(e1) | W14: =W10+(W5-W4)*W11 -> 47.5
A15: 10 | B15: =SUM(Q15:T15) -> 2.1474836 | C15: =Rebudget!F45 -> 1.0737418 | D15: =B15/C15 -> 2 | E15: =0*F14+Ceiling*G14+Ceiling*H14 -> 7.3975808 | F15: =0*E14+Ceiling*G14+Ceiling*H14+Shock -> 17.397581 | G15: =Ceiling*(E14+F14) -> 9.9180646 | H15: =Ceiling*(E14+F14) -> 9.9180646 | I15: =SUM(E15:H15) -> 44.631291 | J15: =Ceiling*K14+Ceiling*L14+Ceiling*M14 -> 3.9782973 | K15: =Ceiling*J14+Ceiling*L14+Ceiling*M14 -> 3.9793459 | L15: =Ceiling*(J14+K14) -> 3.0712791 | M15: =Ceiling*(J14+K14) -> 3.0712791 | N15: =SUM(J15:M15) -> 14.100201 | O15: =O14+(Q15+R15+S15+T15)/2 -> 45.705033 | P15: =P14+N15 -> 137.18369 | Q15: =0*R14+Ceiling*S14+Ceiling*T14 -> 1.0737418 | R15: =0*Q14+Ceiling*S14+Ceiling*T14 -> 1.0737418 | S15: =Ceiling*(Q14+R14) -> 0 | T15: =Ceiling*(Q14+R14) -> 0 | V15: Re-analysis: T(e1) | W15: =Shock/(1-2*(W5^2+W6^2))*(1+W5+W6) -> 47.631719
A16: 11 | B16: =SUM(Q16:T16) -> 1.7179869 | C16: =Rebudget!F46 -> 0.85899346 | D16: =B16/C16 -> 2 | E16: =0*F15+Ceiling*G15+Ceiling*H15 -> 7.9344517 | F16: =0*E15+Ceiling*G15+Ceiling*H15+Shock -> 17.934452 | G16: =Ceiling*(E15+F15) -> 9.9180646 | H16: =Ceiling*(E15+F15) -> 9.9180646 | I16: =SUM(E16:H16) -> 45.705033 | J16: =Ceiling*K15+Ceiling*L15+Ceiling*M15 -> 4.0487617 | K16: =Ceiling*J15+Ceiling*L15+Ceiling*M15 -> 4.0483422 | L16: =Ceiling*(J15+K15) -> 3.1830573 | M16: =Ceiling*(J15+K15) -> 3.1830573 | N16: =SUM(J16:M16) -> 14.463218 | O16: =O15+(Q16+R16+S16+T16)/2 -> 46.564026 | P16: =P15+N16 -> 151.6469 | Q16: =0*R15+Ceiling*S15+Ceiling*T15 -> 0 | R16: =0*Q15+Ceiling*S15+Ceiling*T15 -> 0 | S16: =Ceiling*(Q15+R15) -> 0.85899346 | T16: =Ceiling*(Q15+R15) -> 0.85899346 | V16: The new link: d rho / d h at h = 0, (1 + h/Q)/2 | W16: =0.5 -> 0.5
A17: 12 | B17: =SUM(Q17:T17) -> 1.3743895 | C17: =Rebudget!F47 -> 0.68719477 | D17: =B17/C17 -> 2 | E17: =0*F16+Ceiling*G16+Ceiling*H16 -> 7.9344517 | F17: =0*E16+Ceiling*G16+Ceiling*H16+Shock -> 17.934452 | G17: =Ceiling*(E16+F16) -> 10.347561 | H17: =Ceiling*(E16+F16) -> 10.347561 | I17: =SUM(E17:H17) -> 46.564026 | J17: =Ceiling*K16+Ceiling*L16+Ceiling*M16 -> 4.1657827 | K17: =Ceiling*J16+Ceiling*L16+Ceiling*M16 -> 4.1659505 | L17: =Ceiling*(J16+K16) -> 3.2388415 | M17: =Ceiling*(J16+K16) -> 3.2388415 | N17: =SUM(J17:M17) -> 14.809416 | O17: =O16+(Q17+R17+S17+T17)/2 -> 47.251221 | P17: =P16+N17 -> 166.45632 | Q17: =0*R16+Ceiling*S16+Ceiling*T16 -> 0.68719477 | R17: =0*Q16+Ceiling*S16+Ceiling*T16 -> 0.68719477 | S17: =Ceiling*(Q16+R16) -> 0 | T17: =Ceiling*(Q16+R16) -> 0 | V17: Tangent at h = 0: rho at the ceiling | W17: =W8+Ceiling*W16 -> 1
A18: 13 | B18: =SUM(Q18:T18) -> 1.0995116 | E18: =0*F17+Ceiling*G17+Ceiling*H17 -> 8.2780491 | F18: =0*E17+Ceiling*G17+Ceiling*H17+Shock -> 18.278049 | G18: =Ceiling*(E17+F17) -> 10.347561 | H18: =Ceiling*(E17+F17) -> 10.347561 | I18: =SUM(E18:H18) -> 47.251221 | J18: =Ceiling*K17+Ceiling*L17+Ceiling*M17 -> 4.2574534 | K18: =Ceiling*J17+Ceiling*L17+Ceiling*M17 -> 4.2573863 | L18: =Ceiling*(J17+K17) -> 3.3326933 | M18: =Ceiling*(J17+K17) -> 3.3326933 | N18: =SUM(J18:M18) -> 15.180226 | O18: =O17+(Q18+R18+S18+T18)/2 -> 47.800977 | P18: =P17+N18 -> 181.63655 | Q18: =0*R17+Ceiling*S17+Ceiling*T17 -> 0 | R18: =0*Q17+Ceiling*S17+Ceiling*T17 -> 0 | S18: =Ceiling*(Q17+R17) -> 0.54975581 | T18: =Ceiling*(Q17+R17) -> 0.54975581 | V18: d T / d h at h = 0: (S / D)(1 + e + t) | W18: =(Shock/(1-2*(W4^2+W6^2)))/(1-2*(W4^2+W6^2))*(1+W4+W6) -> 138.88889
A19: 14 | B19: =SUM(Q19:T19) -> 0.8796093 | E19: =0*F18+Ceiling*G18+Ceiling*H18 -> 8.2780491 | F19: =0*E18+Ceiling*G18+Ceiling*H18+Shock -> 18.278049 | G19: =Ceiling*(E18+F18) -> 10.622439 | H19: =Ceiling*(E18+F18) -> 10.622439 | I19: =SUM(E19:H19) -> 47.800977 | J19: =Ceiling*K18+Ceiling*L18+Ceiling*M18 -> 4.3691092 | K19: =Ceiling*J18+Ceiling*L18+Ceiling*M18 -> 4.369136 | L19: =Ceiling*(J18+K18) -> 3.4059359 | M19: =Ceiling*(J18+K18) -> 3.4059359 | N19: =SUM(J19:M19) -> 15.550117 | O19: =O18+(Q19+R19+S19+T19)/2 -> 48.240781 | P19: =P18+N19 -> 197.18666 | Q19: =0*R18+Ceiling*S18+Ceiling*T18 -> 0.43980465 | R19: =0*Q18+Ceiling*S18+Ceiling*T18 -> 0.43980465 | S19: =Ceiling*(Q18+R18) -> 0 | T19: =Ceiling*(Q18+R18) -> 0 | V19: Tangent at h = 0: settled total at the ceiling | W19: =W10+Ceiling*W18 -> 105.55556
A20: 15 | B20: =SUM(Q20:T20) -> 0.70368744 | E20: =0*F19+Ceiling*G19+Ceiling*H19 -> 8.4979514 | F20: =0*E19+Ceiling*G19+Ceiling*H19+Shock -> 18.497951 | G20: =Ceiling*(E19+F19) -> 10.622439 | H20: =Ceiling*(E19+F19) -> 10.622439 | I20: =SUM(E20:H20) -> 48.240781 | J20: =Ceiling*K19+Ceiling*L19+Ceiling*M19 -> 4.4724031 | K20: =Ceiling*J19+Ceiling*L19+Ceiling*M19 -> 4.4723924 | L20: =Ceiling*(J19+K19) -> 3.4952981 | M20: =Ceiling*(J19+K19) -> 3.4952981 | N20: =SUM(J20:M20) -> 15.935392 | O20: =O19+(Q20+R20+S20+T20)/2 -> 48.592625 | P20: =P19+N20 -> 213.12206 | Q20: =0*R19+Ceiling*S19+Ceiling*T19 -> 0 | R20: =0*Q19+Ceiling*S19+Ceiling*T19 -> 0 | S20: =Ceiling*(Q19+R19) -> 0.35184372 | T20: =Ceiling*(Q19+R19) -> 0.35184372 | V20: Re-analysis: rho with the new link | W20: =Rebudget!E12 -> 1.0246211
A21: 16 | B21: =SUM(Q21:T21) -> 0.56294995 | E21: =0*F20+Ceiling*G20+Ceiling*H20 -> 8.4979514 | F21: =0*E20+Ceiling*G20+Ceiling*H20+Shock -> 18.497951 | G21: =Ceiling*(E20+F20) -> 10.798361 | H21: =Ceiling*(E20+F20) -> 10.798361 | I21: =SUM(E21:H21) -> 48.592625 | J21: =Ceiling*K20+Ceiling*L20+Ceiling*M20 -> 4.5851954 | K21: =Ceiling*J20+Ceiling*L20+Ceiling*M20 -> 4.5851997 | L21: =Ceiling*(J20+K20) -> 3.5779182 | M21: =Ceiling*(J20+K20) -> 3.5779182 | N21: =SUM(J21:M21) -> 16.326232 | O21: =O20+(Q21+R21+S21+T21)/2 -> 48.8741 | P21: =P20+N21 -> 229.44829 | Q21: =0*R20+Ceiling*S20+Ceiling*T20 -> 0.28147498 | R21: =0*Q20+Ceiling*S20+Ceiling*T20 -> 0.28147498 | S21: =Ceiling*(Q20+R20) -> 0 | T21: =Ceiling*(Q20+R20) -> 0 | V21: Re-analysis: settled total with the new link | W21: =Rebudget!S12 -> no limit
A22: 17 | B22: =SUM(Q22:T22) -> 0.45035996 | E22: =0*F21+Ceiling*G21+Ceiling*H21 -> 8.6386889 | F22: =0*E21+Ceiling*G21+Ceiling*H21+Shock -> 18.638689 | G22: =Ceiling*(E21+F21) -> 10.798361 | H22: =Ceiling*(E21+F21) -> 10.798361 | I22: =SUM(E22:H22) -> 48.8741 | J22: =Ceiling*K21+Ceiling*L21+Ceiling*M21 -> 4.6964145 | K22: =Ceiling*J21+Ceiling*L21+Ceiling*M21 -> 4.6964127 | L22: =Ceiling*(J21+K21) -> 3.6681581 | M22: =Ceiling*(J21+K21) -> 3.6681581 | N22: =SUM(J22:M22) -> 16.729143 | O22: =O21+(Q22+R22+S22+T22)/2 -> 49.09928 | P22: =P21+N22 -> 246.17743 | Q22: =0*R21+Ceiling*S21+Ceiling*T21 -> 0 | R22: =0*Q21+Ceiling*S21+Ceiling*T21 -> 0 | S22: =Ceiling*(Q21+R21) -> 0.22517998 | T22: =Ceiling*(Q21+R21) -> 0.22517998
A23: 18 | B23: =SUM(Q23:T23) -> 0.36028797 | E23: =0*F22+Ceiling*G22+Ceiling*H22 -> 8.6386889 | F23: =0*E22+Ceiling*G22+Ceiling*H22+Shock -> 18.638689 | G23: =Ceiling*(E22+F22) -> 10.910951 | H23: =Ceiling*(E22+F22) -> 10.910951 | I23: =SUM(E23:H23) -> 49.09928 | J23: =Ceiling*K22+Ceiling*L22+Ceiling*M22 -> 4.8130915 | K23: =Ceiling*J22+Ceiling*L22+Ceiling*M22 -> 4.8130922 | L23: =Ceiling*(J22+K22) -> 3.7571309 | M23: =Ceiling*(J22+K22) -> 3.7571309 | N23: =SUM(J23:M23) -> 17.140446 | O23: =O22+(Q23+R23+S23+T23)/2 -> 49.279424 | P23: =P22+N23 -> 263.31788 | Q23: =0*R22+Ceiling*S22+Ceiling*T22 -> 0.18014399 | R23: =0*Q22+Ceiling*S22+Ceiling*T22 -> 0.18014399 | S23: =Ceiling*(Q22+R22) -> 0 | T23: =Ceiling*(Q22+R22) -> 0 | V23: A structural change is not small: even with the link written in as a parameter, which is already the re-analysis, the tangent misreads it.
A24: 19 | B24: =SUM(Q24:T24) -> 0.28823038 | E24: =0*F23+Ceiling*G23+Ceiling*H23 -> 8.7287609 | F24: =0*E23+Ceiling*G23+Ceiling*H23+Shock -> 18.728761 | G24: =Ceiling*(E23+F23) -> 10.910951 | H24: =Ceiling*(E23+F23) -> 10.910951 | I24: =SUM(E24:H24) -> 49.279424 | J24: =Ceiling*K23+Ceiling*L23+Ceiling*M23 -> 4.9309416 | K24: =Ceiling*J23+Ceiling*L23+Ceiling*M23 -> 4.9309413 | L24: =Ceiling*(J23+K23) -> 3.8504735 | M24: =Ceiling*(J23+K23) -> 3.8504735 | N24: =SUM(J24:M24) -> 17.56283 | O24: =O23+(Q24+R24+S24+T24)/2 -> 49.423539 | P24: =P23+N24 -> 280.88071 | Q24: =0*R23+Ceiling*S23+Ceiling*T23 -> 0 | R24: =0*Q23+Ceiling*S23+Ceiling*T23 -> 0 | S24: =Ceiling*(Q23+R23) -> 0.14411519 | T24: =Ceiling*(Q23+R23) -> 0.14411519
A25: 20 | B25: =SUM(Q25:T25) -> 0.2305843 | E25: =0*F24+Ceiling*G24+Ceiling*H24 -> 8.7287609 | F25: =0*E24+Ceiling*G24+Ceiling*H24+Shock -> 18.728761 | G25: =Ceiling*(E24+F24) -> 10.983009 | H25: =Ceiling*(E24+F24) -> 10.983009 | I25: =SUM(E25:H25) -> 49.423539 | J25: =Ceiling*K24+Ceiling*L24+Ceiling*M24 -> 5.0527553 | K25: =Ceiling*J24+Ceiling*L24+Ceiling*M24 -> 5.0527554 | L25: =Ceiling*(J24+K24) -> 3.9447532 | M25: =Ceiling*(J24+K24) -> 3.9447532 | N25: =SUM(J25:M25) -> 17.995017 | O25: =O24+(Q25+R25+S25+T25)/2 -> 49.538831 | P25: =P24+N25 -> 298.87572 | Q25: =0*R24+Ceiling*S24+Ceiling*T24 -> 0.11529215 | R25: =0*Q24+Ceiling*S24+Ceiling*T24 -> 0.11529215 | S25: =Ceiling*(Q24+R24) -> 0 | T25: =Ceiling*(Q24+R24) -> 0
A26: 21 | B26: =SUM(Q26:T26) -> 0.18446744 | E26: =0*F25+Ceiling*G25+Ceiling*H25 -> 8.786407 | F26: =0*E25+Ceiling*G25+Ceiling*H25+Shock -> 18.786407 | G26: =Ceiling*(E25+F25) -> 10.983009 | H26: =Ceiling*(E25+F25) -> 10.983009 | I26: =SUM(E26:H26) -> 49.538831 | J26: =Ceiling*K25+Ceiling*L25+Ceiling*M25 -> 5.1769047 | K26: =Ceiling*J25+Ceiling*L25+Ceiling*M25 -> 5.1769047 | L26: =Ceiling*(J25+K25) -> 4.0422043 | M26: =Ceiling*(J25+K25) -> 4.0422043 | N26: =SUM(J26:M26) -> 18.438218 | O26: =O25+(Q26+R26+S26+T26)/2 -> 49.631065 | P26: =P25+N26 -> 317.31394 | Q26: =0*R25+Ceiling*S25+Ceiling*T25 -> 0 | R26: =0*Q25+Ceiling*S25+Ceiling*T25 -> 0 | S26: =Ceiling*(Q25+R25) -> 0.09223372 | T26: =Ceiling*(Q25+R25) -> 0.09223372
A27: 22 | B27: =SUM(Q27:T27) -> 0.14757395 | E27: =0*F26+Ceiling*G26+Ceiling*H26 -> 8.786407 | F27: =0*E26+Ceiling*G26+Ceiling*H26+Shock -> 18.786407 | G27: =Ceiling*(E26+F26) -> 11.029126 | H27: =Ceiling*(E26+F26) -> 11.029126 | I27: =SUM(E27:H27) -> 49.631065 | J27: =Ceiling*K26+Ceiling*L26+Ceiling*M26 -> 5.3045253 | K27: =Ceiling*J26+Ceiling*L26+Ceiling*M26 -> 5.3045253 | L27: =Ceiling*(J26+K26) -> 4.1415237 | M27: =Ceiling*(J26+K26) -> 4.1415237 | N27: =SUM(J27:M27) -> 18.892098 | O27: =O26+(Q27+R27+S27+T27)/2 -> 49.704852 | P27: =P26+N27 -> 336.20604 | Q27: =0*R26+Ceiling*S26+Ceiling*T26 -> 0.073786976 | R27: =0*Q26+Ceiling*S26+Ceiling*T26 -> 0.073786976 | S27: =Ceiling*(Q26+R26) -> 0 | T27: =Ceiling*(Q26+R26) -> 0
A28: 23 | B28: =SUM(Q28:T28) -> 0.11805916 | E28: =0*F27+Ceiling*G27+Ceiling*H27 -> 8.8233005 | F28: =0*E27+Ceiling*G27+Ceiling*H27+Shock -> 18.8233 | G28: =Ceiling*(E27+F27) -> 11.029126 | H28: =Ceiling*(E27+F27) -> 11.029126 | I28: =SUM(E28:H28) -> 49.704852 | J28: =Ceiling*K27+Ceiling*L27+Ceiling*M27 -> 5.4350291 | K28: =Ceiling*J27+Ceiling*L27+Ceiling*M27 -> 5.4350291 | L28: =Ceiling*(J27+K27) -> 4.2436203 | M28: =Ceiling*(J27+K27) -> 4.2436203 | N28: =SUM(J28:M28) -> 19.357299 | O28: =O27+(Q28+R28+S28+T28)/2 -> 49.763882 | P28: =P27+N28 -> 355.56334 | Q28: =0*R27+Ceiling*S27+Ceiling*T27 -> 0 | R28: =0*Q27+Ceiling*S27+Ceiling*T27 -> 0 | S28: =Ceiling*(Q27+R27) -> 0.059029581 | T28: =Ceiling*(Q27+R27) -> 0.059029581
A29: 24 | B29: =SUM(Q29:T29) -> 0.09444733 | E29: =0*F28+Ceiling*G28+Ceiling*H28 -> 8.8233005 | F29: =0*E28+Ceiling*G28+Ceiling*H28+Shock -> 18.8233 | G29: =Ceiling*(E28+F28) -> 11.05864 | H29: =Ceiling*(E28+F28) -> 11.05864 | I29: =SUM(E29:H29) -> 49.763882 | J29: =Ceiling*K28+Ceiling*L28+Ceiling*M28 -> 5.5689079 | K29: =Ceiling*J28+Ceiling*L28+Ceiling*M28 -> 5.5689079 | L29: =Ceiling*(J28+K28) -> 4.3480233 | M29: =Ceiling*(J28+K28) -> 4.3480233 | N29: =SUM(J29:M29) -> 19.833862 | O29: =O28+(Q29+R29+S29+T29)/2 -> 49.811105 | P29: =P28+N29 -> 375.3972 | Q29: =0*R28+Ceiling*S28+Ceiling*T28 -> 0.047223665 | R29: =0*Q28+Ceiling*S28+Ceiling*T28 -> 0.047223665 | S29: =Ceiling*(Q28+R28) -> 0 | T29: =Ceiling*(Q28+R28) -> 0
A30: 25 | B30: =SUM(Q30:T30) -> 0.075557864 | E30: =0*F29+Ceiling*G29+Ceiling*H29 -> 8.8469123 | F30: =0*E29+Ceiling*G29+Ceiling*H29+Shock -> 18.846912 | G30: =Ceiling*(E29+F29) -> 11.05864 | H30: =Ceiling*(E29+F29) -> 11.05864 | I30: =SUM(E30:H30) -> 49.811105 | J30: =Ceiling*K29+Ceiling*L29+Ceiling*M29 -> 5.7059818 | K30: =Ceiling*J29+Ceiling*L29+Ceiling*M29 -> 5.7059818 | L30: =Ceiling*(J29+K29) -> 4.4551263 | M30: =Ceiling*(J29+K29) -> 4.4551263 | N30: =SUM(J30:M30) -> 20.322216 | O30: =O29+(Q30+R30+S30+T30)/2 -> 49.848884 | P30: =P29+N30 -> 395.71942 | Q30: =0*R29+Ceiling*S29+Ceiling*T29 -> 0 | R30: =0*Q29+Ceiling*S29+Ceiling*T29 -> 0 | S30: =Ceiling*(Q29+R29) -> 0.037778932 | T30: =Ceiling*(Q29+R29) -> 0.037778932
A31: 26 | B31: =SUM(Q31:T31) -> 0.060446291 | E31: =0*F30+Ceiling*G30+Ceiling*H30 -> 8.8469123 | F31: =0*E30+Ceiling*G30+Ceiling*H30+Shock -> 18.846912 | G31: =Ceiling*(E30+F30) -> 11.07753 | H31: =Ceiling*(E30+F30) -> 11.07753 | I31: =SUM(E31:H31) -> 49.848884 | J31: =Ceiling*K30+Ceiling*L30+Ceiling*M30 -> 5.8464937 | K31: =Ceiling*J30+Ceiling*L30+Ceiling*M30 -> 5.8464937 | L31: =Ceiling*(J30+K30) -> 4.5647854 | M31: =Ceiling*(J30+K30) -> 4.5647854 | N31: =SUM(J31:M31) -> 20.822558 | O31: =O30+(Q31+R31+S31+T31)/2 -> 49.879107 | P31: =P30+N31 -> 416.54197 | Q31: =0*R30+Ceiling*S30+Ceiling*T30 -> 0.030223145 | R31: =0*Q30+Ceiling*S30+Ceiling*T30 -> 0.030223145 | S31: =Ceiling*(Q30+R30) -> 0 | T31: =Ceiling*(Q30+R30) -> 0
A32: 27 | B32: =SUM(Q32:T32) -> 0.048357033 | E32: =0*F31+Ceiling*G31+Ceiling*H31 -> 8.8620239 | F32: =0*E31+Ceiling*G31+Ceiling*H31+Shock -> 18.862024 | G32: =Ceiling*(E31+F31) -> 11.07753 | H32: =Ceiling*(E31+F31) -> 11.07753 | I32: =SUM(E32:H32) -> 49.879107 | J32: =Ceiling*K31+Ceiling*L31+Ceiling*M31 -> 5.9904258 | K32: =Ceiling*J31+Ceiling*L31+Ceiling*M31 -> 5.9904258 | L32: =Ceiling*(J31+K31) -> 4.677195 | M32: =Ceiling*(J31+K31) -> 4.677195 | N32: =SUM(J32:M32) -> 21.335242 | O32: =O31+(Q32+R32+S32+T32)/2 -> 49.903286 | P32: =P31+N32 -> 437.87722 | Q32: =0*R31+Ceiling*S31+Ceiling*T31 -> 0 | R32: =0*Q31+Ceiling*S31+Ceiling*T31 -> 0 | S32: =Ceiling*(Q31+R31) -> 0.024178516 | T32: =Ceiling*(Q31+R31) -> 0.024178516
A33: 28 | B33: =SUM(Q33:T33) -> 0.038685626 | E33: =0*F32+Ceiling*G32+Ceiling*H32 -> 8.8620239 | F33: =0*E32+Ceiling*G32+Ceiling*H32+Shock -> 18.862024 | G33: =Ceiling*(E32+F32) -> 11.089619 | H33: =Ceiling*(E32+F32) -> 11.089619 | I33: =SUM(E33:H33) -> 49.903286 | J33: =Ceiling*K32+Ceiling*L32+Ceiling*M32 -> 6.1379263 | K33: =Ceiling*J32+Ceiling*L32+Ceiling*M32 -> 6.1379263 | L33: =Ceiling*(J32+K32) -> 4.7923407 | M33: =Ceiling*(J32+K32) -> 4.7923407 | N33: =SUM(J33:M33) -> 21.860534 | O33: =O32+(Q33+R33+S33+T33)/2 -> 49.922629 | P33: =P32+N33 -> 459.73775 | Q33: =0*R32+Ceiling*S32+Ceiling*T32 -> 0.019342813 | R33: =0*Q32+Ceiling*S32+Ceiling*T32 -> 0.019342813 | S33: =Ceiling*(Q32+R32) -> 0 | T33: =Ceiling*(Q32+R32) -> 0
A34: 29 | B34: =SUM(Q34:T34) -> 0.030948501 | E34: =0*F33+Ceiling*G33+Ceiling*H33 -> 8.8716953 | F34: =0*E33+Ceiling*G33+Ceiling*H33+Shock -> 18.871695 | G34: =Ceiling*(E33+F33) -> 11.089619 | H34: =Ceiling*(E33+F33) -> 11.089619 | I34: =SUM(E34:H34) -> 49.922629 | J34: =Ceiling*K33+Ceiling*L33+Ceiling*M33 -> 6.2890431 | K34: =Ceiling*J33+Ceiling*L33+Ceiling*M33 -> 6.2890431 | L34: =Ceiling*(J33+K33) -> 4.9103411 | M34: =Ceiling*(J33+K33) -> 4.9103411 | N34: =SUM(J34:M34) -> 22.398768 | O34: =O33+(Q34+R34+S34+T34)/2 -> 49.938103 | P34: =P33+N34 -> 482.13652 | Q34: =0*R33+Ceiling*S33+Ceiling*T33 -> 0 | R34: =0*Q33+Ceiling*S33+Ceiling*T33 -> 0 | S34: =Ceiling*(Q33+R33) -> 0.01547425 | T34: =Ceiling*(Q33+R33) -> 0.01547425
A35: 30 | B35: =SUM(Q35:T35) -> 0.024758801 | E35: =0*F34+Ceiling*G34+Ceiling*H34 -> 8.8716953 | F35: =0*E34+Ceiling*G34+Ceiling*H34+Shock -> 18.871695 | G35: =Ceiling*(E34+F34) -> 11.097356 | H35: =Ceiling*(E34+F34) -> 11.097356 | I35: =SUM(E35:H35) -> 49.938103 | J35: =Ceiling*K34+Ceiling*L34+Ceiling*M34 -> 6.4438901 | K35: =Ceiling*J34+Ceiling*L34+Ceiling*M34 -> 6.4438901 | L35: =Ceiling*(J34+K34) -> 5.0312345 | M35: =Ceiling*(J34+K34) -> 5.0312345 | N35: =SUM(J35:M35) -> 22.950249 | O35: =O34+(Q35+R35+S35+T35)/2 -> 49.950482 | P35: =P34+N35 -> 505.08677 | Q35: =0*R34+Ceiling*S34+Ceiling*T34 -> 0.0123794 | R35: =0*Q34+Ceiling*S34+Ceiling*T34 -> 0.0123794 | S35: =Ceiling*(Q34+R34) -> 0 | T35: =Ceiling*(Q34+R34) -> 0
... A45: 40 | B45: =SUM(Q45:T45) -> 0.002658456 | E45: =0*F44+Ceiling*G44+Ceiling*H44 -> 8.8870427 | F45: =0*E44+Ceiling*G44+Ceiling*H44+Shock -> 18.887043 | G45: =Ceiling*(E44+F44) -> 11.109634 | H45: =Ceiling*(E44+F44) -> 11.109634 | I45: =SUM(E45:H45) -> 49.993354 | J45: =Ceiling*K44+Ceiling*L44+Ceiling*M44 -> 8.2182829 | K45: =Ceiling*J44+Ceiling*L44+Ceiling*M44 -> 8.2182829 | L45: =Ceiling*(J44+K44) -> 6.4166414 | M45: =Ceiling*(J44+K44) -> 6.4166414 | N45: =SUM(J45:M45) -> 29.269848 | O45: =O44+(Q45+R45+S45+T45)/2 -> 49.994683 | P45: =P44+N45 -> 768.0802 | Q45: =0*R44+Ceiling*S44+Ceiling*T44 -> 0.001329228 | R45: =0*Q44+Ceiling*S44+Ceiling*T44 -> 0.001329228 | S45: =Ceiling*(Q44+R44) -> 0 | T45: =Ceiling*(Q44+R44) -> 0

Sheet Runway
A1: Feasible-region visualizer: the runway's viability sets and its kernel (Theorem 14.5(iii)-(iv); Figure 14.2; Online Appendix 14.B.2; AXIOM Lab 1.14, step 4)
A2: V_j = {s >= N_j(r)}, N_j(r) = r + (r - b) + ... + (r - (j - 1)b), positive terms only: the cash that j quarters of burn consume at the fastest cuts. The kernel's edge N(r) is the cash needed to stop the burn.
A3: Quarter | B3: Cash above the floor | C3: Burn | D3: Cut (fastest) | E3: Feasible? | F3: No cuts: cash | G3: No cuts: feasible?
A4: 0 | B4: =Cash_now -> 120 | C4: =Burn_now -> 50 | D4: =MIN(Cut_b,C4) -> 10 | E4: =IF(AND(B4>=0,B4<=S_max,C4>=0,C4<=R_max),"yes","no") -> yes | F4: =Cash_now -> 120 | G4: =IF(AND(F4>=0,F4<=S_max),"yes","no") -> yes
A5: 1 | B5: =B4-C4 -> 70 | C5: =C4-D4 -> 40 | D5: =MIN(Cut_b,C5) -> 10 | E5: =IF(AND(B5>=0,B5<=S_max,C5>=0,C5<=R_max),"yes","no") -> yes | F5: =F4-Burn_now -> 70 | G5: =IF(AND(F5>=0,F5<=S_max),"yes","no") -> yes
A6: 2 | B6: =B5-C5 -> 30 | C6: =C5-D5 -> 30 | D6: =MIN(Cut_b,C6) -> 10 | E6: =IF(AND(B6>=0,B6<=S_max,C6>=0,C6<=R_max),"yes","no") -> yes | F6: =F5-Burn_now -> 20 | G6: =IF(AND(F6>=0,F6<=S_max),"yes","no") -> yes
A7: 3 | B7: =B6-C6 -> 0 | C7: =C6-D6 -> 20 | D7: =MIN(Cut_b,C7) -> 10 | E7: =IF(AND(B7>=0,B7<=S_max,C7>=0,C7<=R_max),"yes","no") -> yes | F7: =F6-Burn_now -> -30 | G7: =IF(AND(F7>=0,F7<=S_max),"yes","no") -> no
A8: 4 | B8: =B7-C7 -> -20 | C8: =C7-D7 -> 10 | D8: =MIN(Cut_b,C8) -> 10 | E8: =IF(AND(B8>=0,B8<=S_max,C8>=0,C8<=R_max),"yes","no") -> no | F8: =F7-Burn_now -> -80 | G8: =IF(AND(F8>=0,F8<=S_max),"yes","no") -> no
A9: 5 | B9: =B8-C8 -> -30 | C9: =C8-D8 -> 0 | D9: =MIN(Cut_b,C9) -> 0 | E9: =IF(AND(B9>=0,B9<=S_max,C9>=0,C9<=R_max),"yes","no") -> no | F9: =F8-Burn_now -> -130 | G9: =IF(AND(F9>=0,F9<=S_max),"yes","no") -> no
A10: 6 | B10: =B9-C9 -> -30 | C10: =C9-D9 -> 0 | D10: =MIN(Cut_b,C10) -> 0 | E10: =IF(AND(B10>=0,B10<=S_max,C10>=0,C10<=R_max),"yes","no") -> no | F10: =F9-Burn_now -> -180 | G10: =IF(AND(F10>=0,F10<=S_max),"yes","no") -> no
A12: First quarter out of cash, fastest cuts | B12: =MATCH("no",E4:E10,0)-1 -> 4
A13: First quarter out of cash, no cuts | B13: =MATCH("no",G4:G10,0)-1 -> 3
A16: Burn r | B16: N_1(r) | C16: N_2(r) | D16: N_3(r) | E16: N_4(r) | F16: N_5(r) | G16: N_6(r) | H16: N_7(r) | I16: N_8(r) | J16: N_9(r) | K16: N_10(r) | L16: Kernel edge N(r) | M16: r(r + b)/(2b), r a multiple of b
A17: 0 | B17: =MAX($A17-0*Cut_b,0) -> 0 | C17: =B17+MAX($A17-1*Cut_b,0) -> 0 | D17: =C17+MAX($A17-2*Cut_b,0) -> 0 | E17: =D17+MAX($A17-3*Cut_b,0) -> 0 | F17: =E17+MAX($A17-4*Cut_b,0) -> 0 | G17: =F17+MAX($A17-5*Cut_b,0) -> 0 | H17: =G17+MAX($A17-6*Cut_b,0) -> 0 | I17: =H17+MAX($A17-7*Cut_b,0) -> 0 | J17: =I17+MAX($A17-8*Cut_b,0) -> 0 | K17: =J17+MAX($A17-9*Cut_b,0) -> 0 | L17: =K17 -> 0 | M17: =IF(MOD($A17,Cut_b)=0,$A17*($A17+Cut_b)/(2*Cut_b),"") -> 0
A18: 5 | B18: =MAX($A18-0*Cut_b,0) -> 5 | C18: =B18+MAX($A18-1*Cut_b,0) -> 5 | D18: =C18+MAX($A18-2*Cut_b,0) -> 5 | E18: =D18+MAX($A18-3*Cut_b,0) -> 5 | F18: =E18+MAX($A18-4*Cut_b,0) -> 5 | G18: =F18+MAX($A18-5*Cut_b,0) -> 5 | H18: =G18+MAX($A18-6*Cut_b,0) -> 5 | I18: =H18+MAX($A18-7*Cut_b,0) -> 5 | J18: =I18+MAX($A18-8*Cut_b,0) -> 5 | K18: =J18+MAX($A18-9*Cut_b,0) -> 5 | L18: =K18 -> 5 | M18: =IF(MOD($A18,Cut_b)=0,$A18*($A18+Cut_b)/(2*Cut_b),"")
A19: 10 | B19: =MAX($A19-0*Cut_b,0) -> 10 | C19: =B19+MAX($A19-1*Cut_b,0) -> 10 | D19: =C19+MAX($A19-2*Cut_b,0) -> 10 | E19: =D19+MAX($A19-3*Cut_b,0) -> 10 | F19: =E19+MAX($A19-4*Cut_b,0) -> 10 | G19: =F19+MAX($A19-5*Cut_b,0) -> 10 | H19: =G19+MAX($A19-6*Cut_b,0) -> 10 | I19: =H19+MAX($A19-7*Cut_b,0) -> 10 | J19: =I19+MAX($A19-8*Cut_b,0) -> 10 | K19: =J19+MAX($A19-9*Cut_b,0) -> 10 | L19: =K19 -> 10 | M19: =IF(MOD($A19,Cut_b)=0,$A19*($A19+Cut_b)/(2*Cut_b),"") -> 10
A20: 15 | B20: =MAX($A20-0*Cut_b,0) -> 15 | C20: =B20+MAX($A20-1*Cut_b,0) -> 20 | D20: =C20+MAX($A20-2*Cut_b,0) -> 20 | E20: =D20+MAX($A20-3*Cut_b,0) -> 20 | F20: =E20+MAX($A20-4*Cut_b,0) -> 20 | G20: =F20+MAX($A20-5*Cut_b,0) -> 20 | H20: =G20+MAX($A20-6*Cut_b,0) -> 20 | I20: =H20+MAX($A20-7*Cut_b,0) -> 20 | J20: =I20+MAX($A20-8*Cut_b,0) -> 20 | K20: =J20+MAX($A20-9*Cut_b,0) -> 20 | L20: =K20 -> 20 | M20: =IF(MOD($A20,Cut_b)=0,$A20*($A20+Cut_b)/(2*Cut_b),"")
A21: 20 | B21: =MAX($A21-0*Cut_b,0) -> 20 | C21: =B21+MAX($A21-1*Cut_b,0) -> 30 | D21: =C21+MAX($A21-2*Cut_b,0) -> 30 | E21: =D21+MAX($A21-3*Cut_b,0) -> 30 | F21: =E21+MAX($A21-4*Cut_b,0) -> 30 | G21: =F21+MAX($A21-5*Cut_b,0) -> 30 | H21: =G21+MAX($A21-6*Cut_b,0) -> 30 | I21: =H21+MAX($A21-7*Cut_b,0) -> 30 | J21: =I21+MAX($A21-8*Cut_b,0) -> 30 | K21: =J21+MAX($A21-9*Cut_b,0) -> 30 | L21: =K21 -> 30 | M21: =IF(MOD($A21,Cut_b)=0,$A21*($A21+Cut_b)/(2*Cut_b),"") -> 30
A22: 25 | B22: =MAX($A22-0*Cut_b,0) -> 25 | C22: =B22+MAX($A22-1*Cut_b,0) -> 40 | D22: =C22+MAX($A22-2*Cut_b,0) -> 45 | E22: =D22+MAX($A22-3*Cut_b,0) -> 45 | F22: =E22+MAX($A22-4*Cut_b,0) -> 45 | G22: =F22+MAX($A22-5*Cut_b,0) -> 45 | H22: =G22+MAX($A22-6*Cut_b,0) -> 45 | I22: =H22+MAX($A22-7*Cut_b,0) -> 45 | J22: =I22+MAX($A22-8*Cut_b,0) -> 45 | K22: =J22+MAX($A22-9*Cut_b,0) -> 45 | L22: =K22 -> 45 | M22: =IF(MOD($A22,Cut_b)=0,$A22*($A22+Cut_b)/(2*Cut_b),"")
A23: 30 | B23: =MAX($A23-0*Cut_b,0) -> 30 | C23: =B23+MAX($A23-1*Cut_b,0) -> 50 | D23: =C23+MAX($A23-2*Cut_b,0) -> 60 | E23: =D23+MAX($A23-3*Cut_b,0) -> 60 | F23: =E23+MAX($A23-4*Cut_b,0) -> 60 | G23: =F23+MAX($A23-5*Cut_b,0) -> 60 | H23: =G23+MAX($A23-6*Cut_b,0) -> 60 | I23: =H23+MAX($A23-7*Cut_b,0) -> 60 | J23: =I23+MAX($A23-8*Cut_b,0) -> 60 | K23: =J23+MAX($A23-9*Cut_b,0) -> 60 | L23: =K23 -> 60 | M23: =IF(MOD($A23,Cut_b)=0,$A23*($A23+Cut_b)/(2*Cut_b),"") -> 60
A24: 35 | B24: =MAX($A24-0*Cut_b,0) -> 35 | C24: =B24+MAX($A24-1*Cut_b,0) -> 60 | D24: =C24+MAX($A24-2*Cut_b,0) -> 75 | E24: =D24+MAX($A24-3*Cut_b,0) -> 80 | F24: =E24+MAX($A24-4*Cut_b,0) -> 80 | G24: =F24+MAX($A24-5*Cut_b,0) -> 80 | H24: =G24+MAX($A24-6*Cut_b,0) -> 80 | I24: =H24+MAX($A24-7*Cut_b,0) -> 80 | J24: =I24+MAX($A24-8*Cut_b,0) -> 80 | K24: =J24+MAX($A24-9*Cut_b,0) -> 80 | L24: =K24 -> 80 | M24: =IF(MOD($A24,Cut_b)=0,$A24*($A24+Cut_b)/(2*Cut_b),"")
A25: 40 | B25: =MAX($A25-0*Cut_b,0) -> 40 | C25: =B25+MAX($A25-1*Cut_b,0) -> 70 | D25: =C25+MAX($A25-2*Cut_b,0) -> 90 | E25: =D25+MAX($A25-3*Cut_b,0) -> 100 | F25: =E25+MAX($A25-4*Cut_b,0) -> 100 | G25: =F25+MAX($A25-5*Cut_b,0) -> 100 | H25: =G25+MAX($A25-6*Cut_b,0) -> 100 | I25: =H25+MAX($A25-7*Cut_b,0) -> 100 | J25: =I25+MAX($A25-8*Cut_b,0) -> 100 | K25: =J25+MAX($A25-9*Cut_b,0) -> 100 | L25: =K25 -> 100 | M25: =IF(MOD($A25,Cut_b)=0,$A25*($A25+Cut_b)/(2*Cut_b),"") -> 100
A26: 45 | B26: =MAX($A26-0*Cut_b,0) -> 45 | C26: =B26+MAX($A26-1*Cut_b,0) -> 80 | D26: =C26+MAX($A26-2*Cut_b,0) -> 105 | E26: =D26+MAX($A26-3*Cut_b,0) -> 120 | F26: =E26+MAX($A26-4*Cut_b,0) -> 125 | G26: =F26+MAX($A26-5*Cut_b,0) -> 125 | H26: =G26+MAX($A26-6*Cut_b,0) -> 125 | I26: =H26+MAX($A26-7*Cut_b,0) -> 125 | J26: =I26+MAX($A26-8*Cut_b,0) -> 125 | K26: =J26+MAX($A26-9*Cut_b,0) -> 125 | L26: =K26 -> 125 | M26: =IF(MOD($A26,Cut_b)=0,$A26*($A26+Cut_b)/(2*Cut_b),"")
A27: 50 | B27: =MAX($A27-0*Cut_b,0) -> 50 | C27: =B27+MAX($A27-1*Cut_b,0) -> 90 | D27: =C27+MAX($A27-2*Cut_b,0) -> 120 | E27: =D27+MAX($A27-3*Cut_b,0) -> 140 | F27: =E27+MAX($A27-4*Cut_b,0) -> 150 | G27: =F27+MAX($A27-5*Cut_b,0) -> 150 | H27: =G27+MAX($A27-6*Cut_b,0) -> 150 | I27: =H27+MAX($A27-7*Cut_b,0) -> 150 | J27: =I27+MAX($A27-8*Cut_b,0) -> 150 | K27: =J27+MAX($A27-9*Cut_b,0) -> 150 | L27: =K27 -> 150 | M27: =IF(MOD($A27,Cut_b)=0,$A27*($A27+Cut_b)/(2*Cut_b),"") -> 150
A28: 55 | B28: =MAX($A28-0*Cut_b,0) -> 55 | C28: =B28+MAX($A28-1*Cut_b,0) -> 100 | D28: =C28+MAX($A28-2*Cut_b,0) -> 135 | E28: =D28+MAX($A28-3*Cut_b,0) -> 160 | F28: =E28+MAX($A28-4*Cut_b,0) -> 175 | G28: =F28+MAX($A28-5*Cut_b,0) -> 180 | H28: =G28+MAX($A28-6*Cut_b,0) -> 180 | I28: =H28+MAX($A28-7*Cut_b,0) -> 180 | J28: =I28+MAX($A28-8*Cut_b,0) -> 180 | K28: =J28+MAX($A28-9*Cut_b,0) -> 180 | L28: =K28 -> 180 | M28: =IF(MOD($A28,Cut_b)=0,$A28*($A28+Cut_b)/(2*Cut_b),"")
A29: 60 | B29: =MAX($A29-0*Cut_b,0) -> 60 | C29: =B29+MAX($A29-1*Cut_b,0) -> 110 | D29: =C29+MAX($A29-2*Cut_b,0) -> 150 | E29: =D29+MAX($A29-3*Cut_b,0) -> 180 | F29: =E29+MAX($A29-4*Cut_b,0) -> 200 | G29: =F29+MAX($A29-5*Cut_b,0) -> 210 | H29: =G29+MAX($A29-6*Cut_b,0) -> 210 | I29: =H29+MAX($A29-7*Cut_b,0) -> 210 | J29: =I29+MAX($A29-8*Cut_b,0) -> 210 | K29: =J29+MAX($A29-9*Cut_b,0) -> 210 | L29: =K29 -> 210 | M29: =IF(MOD($A29,Cut_b)=0,$A29*($A29+Cut_b)/(2*Cut_b),"") -> 210
A32: The start: cash and burn | B32: Quarter 0 | C32: Quarter 1 | D32: Quarter 2 | E32: Quarter 3 | F32: Quarter 4 | G32: Quarter 5 | H32: Quarter 6 | I32: Quarter 7 | J32: Quarter 8 | K32: Quarter 9 | L32: Quarter 10
A33: Quarter i | B33: 0 | C33: 1 | D33: 2 | E33: 3 | F33: 4 | G33: 5 | H33: 6 | I33: 7 | J33: 8 | K33: 9 | L33: 10
A34: Burn in quarter i, cutting as fast as allowed | B34: =MAX(Burn_now-B$33*Cut_b,0) -> 50 | C34: =MAX(Burn_now-C$33*Cut_b,0) -> 40 | D34: =MAX(Burn_now-D$33*Cut_b,0) -> 30 | E34: =MAX(Burn_now-E$33*Cut_b,0) -> 20 | F34: =MAX(Burn_now-F$33*Cut_b,0) -> 10 | G34: =MAX(Burn_now-G$33*Cut_b,0) -> 0 | H34: =MAX(Burn_now-H$33*Cut_b,0) -> 0 | I34: =MAX(Burn_now-I$33*Cut_b,0) -> 0 | ... L34: =MAX(Burn_now-L$33*Cut_b,0) -> 0
A35: N_(i+1): cash to stay admissible i + 1 quarters | B35: =SUM($B34:B34) -> 50 | C35: =SUM($B34:C34) -> 90 | D35: =SUM($B34:D34) -> 120 | E35: =SUM($B34:E34) -> 140 | F35: =SUM($B34:F34) -> 150 | G35: =SUM($B34:G34) -> 150 | H35: =SUM($B34:H34) -> 150 | I35: =SUM($B34:I34) -> 150 | ... L35: =SUM($B34:L34) -> 150
A36: Burn in quarter i with faster cuts | B36: =MAX(Burn_now-B$33*Cut_fast,0) -> 50 | C36: =MAX(Burn_now-C$33*Cut_fast,0) -> 35 | D36: =MAX(Burn_now-D$33*Cut_fast,0) -> 20 | E36: =MAX(Burn_now-E$33*Cut_fast,0) -> 5 | F36: =MAX(Burn_now-F$33*Cut_fast,0) -> 0 | G36: =MAX(Burn_now-G$33*Cut_fast,0) -> 0 | H36: =MAX(Burn_now-H$33*Cut_fast,0) -> 0 | I36: =MAX(Burn_now-I$33*Cut_fast,0) -> 0 | ... L36: =MAX(Burn_now-L$33*Cut_fast,0) -> 0
A37: Burn in quarter i with cuts in between | B37: =MAX(Burn_now-B$33*Cut_mid,0) -> 50 | C37: =MAX(Burn_now-C$33*Cut_mid,0) -> 37.5 | D37: =MAX(Burn_now-D$33*Cut_mid,0) -> 25 | E37: =MAX(Burn_now-E$33*Cut_mid,0) -> 12.5 | F37: =MAX(Burn_now-F$33*Cut_mid,0) -> 0 | G37: =MAX(Burn_now-G$33*Cut_mid,0) -> 0 | H37: =MAX(Burn_now-H$33*Cut_mid,0) -> 0 | I37: =MAX(Burn_now-I$33*Cut_mid,0) -> 0 | ... L37: =MAX(Burn_now-L$33*Cut_mid,0) -> 0
A39: Reading | B39: Value | C39: In the book
A40: Quarters the start stays admissible (the V_j containing it) | B40: =IF(COUNTIF(B35:L35,"<="&Cash_now)=11,"forever",COUNTIF(B35:L35,"<="&Cash_now)) -> 3 | C40: Online Appendix 14.B.2: in V_3, not in V_4
A41: Cash needed to stop the burn: the kernel's edge N(r) | B41: =L35 -> 150 | C41: 50 + 40 + 30 + 20 + 10 = 150
A42: Repair by cash: more cash needed | B42: =B41-Cash_now -> 30 | C42: $30 million
A43: Repair by faster cuts: cash needed | B43: =SUM(B36:L36) -> 110 | C43: 50 + 35 + 20 + 5 = 110: enough
A44: Cuts in between: cash needed | B44: =SUM(B37:L37) -> 125 | C44: 125: not enough

Sheet Audit
A1: Diagnostics dashboard: Table 14.2's tests, the complexity panel, the gain audit and three tripwires (Definition 14.11; Theorems 14.6(ii) and 14.7(iv); AXIOM Lab 1.14, step 5)
A3: Register (at its ceilings) | B3: e | C3: t | D3: h | E3: Spectral rho | F3: Block sizes: divisions | G3: Divisions <- center | H3: Center <- divisions | I3: Block small-gain rho | J3: Eigenvalue 2 | K3: Eigenvalue 3 | L3: Eigenvalue 4 | M3: Smallest eigenvalue of P | N3: Contraction L | O3: Spectral < 1 | P3: Blocks < 1 | Q3: Lyapunov P > 0 | R3: Contraction L < 1 | S3: Meets the rule
A4: =Rebudget!A11 -> Today | B4: =Rebudget!B11 -> 0.4 | C4: =Rebudget!C11 -> 0.4 | D4: =Rebudget!D11 -> 0 | E4: =Rebudget!E11 -> 0.8 | F4: =D4 -> 0 | G4: =B4+C4 -> 0.8 | H4: =2*MAX(B4,C4) -> 0.8 | I4: =(F4+SQRT(F4^2+4*G4*H4))/2 -> 0.8 | J4: =(D4-SQRT(D4^2+8*(B4^2+C4^2)))/2 -> -0.8 | K4: =-D4 -> 0 | L4: 0 | M4: =MIN(1/(1-E4^2),1/(1-J4^2),1/(1-K4^2),1/(1-L4^2)) -> 1 | N4: =MAX(B4+C4+D4,2*B4,2*C4) -> 0.8 | O4: =IF(E4<1,"pass","fail") -> pass | P4: =IF(I4<1,"pass","fail") -> pass | Q4: =IF(M4>0,"pass","fail") -> pass | R4: =IF(N4<1,"pass","fail") -> pass | S4: =IF(E4<=R_star+0.000000001,"yes","no") -> yes
A5: =Rebudget!A12 -> New link at the ceiling | B5: =Rebudget!B12 -> 0.4 | C5: =Rebudget!C12 -> 0.4 | D5: =Rebudget!D12 -> 0.4 | E5: =Rebudget!E12 -> 1.0246211 | F5: =D5 -> 0.4 | G5: =B5+C5 -> 0.8 | H5: =2*MAX(B5,C5) -> 0.8 | I5: =(F5+SQRT(F5^2+4*G5*H5))/2 -> 1.0246211 | J5: =(D5-SQRT(D5^2+8*(B5^2+C5^2)))/2 -> -0.62462113 | K5: =-D5 -> -0.4 | L5: 0 | M5: =MIN(1/(1-E5^2),1/(1-J5^2),1/(1-K5^2),1/(1-L5^2)) -> -20.060804 | N5: =MAX(B5+C5+D5,2*B5,2*C5) -> 1.2 | O5: =IF(E5<1,"pass","fail") -> fail | P5: =IF(I5<1,"pass","fail") -> fail | Q5: =IF(M5>0,"pass","fail") -> fail | R5: =IF(N5<1,"pass","fail") -> fail | S5: =IF(E5<=R_star+0.000000001,"yes","no") -> no
A6: =Rebudget!A13 -> Run the new link light | B6: =Rebudget!B13 -> 0.4 | C6: =Rebudget!C13 -> 0.4 | D6: =Rebudget!D13 -> 0.079803862 | E6: =Rebudget!E13 -> 0.84089642 | F6: =D6 -> 0.079803862 | G6: =B6+C6 -> 0.8 | H6: =2*MAX(B6,C6) -> 0.8 | I6: =(F6+SQRT(F6^2+4*G6*H6))/2 -> 0.84089642 | J6: =(D6-SQRT(D6^2+8*(B6^2+C6^2)))/2 -> -0.76109255 | K6: =-D6 -> -0.079803862 | L6: 0 | M6: =MIN(1/(1-E6^2),1/(1-J6^2),1/(1-K6^2),1/(1-L6^2)) -> 1 | N6: =MAX(B6+C6+D6,2*B6,2*C6) -> 0.87980386 | O6: =IF(E6<1,"pass","fail") -> pass | P6: =IF(I6<1,"pass","fail") -> pass | Q6: =IF(M6>0,"pass","fail") -> pass | R6: =IF(N6<1,"pass","fail") -> pass | S6: =IF(E6<=R_star+0.000000001,"yes","no") -> yes
A7: =Rebudget!A14 -> Ring-fence treasury | B7: =Rebudget!B14 -> 0.4 | C7: =Rebudget!C14 -> 0.15929252 | D7: =Rebudget!D14 -> 0.4 | E7: =Rebudget!E14 -> 0.84089642 | F7: =D7 -> 0.4 | G7: =B7+C7 -> 0.55929252 | H7: =2*MAX(B7,C7) -> 0.8 | I7: =(F7+SQRT(F7^2+4*G7*H7))/2 -> 0.89816475 | J7: =(D7-SQRT(D7^2+8*(B7^2+C7^2)))/2 -> -0.44089642 | K7: =-D7 -> -0.4 | L7: 0 | M7: =MIN(1/(1-E7^2),1/(1-J7^2),1/(1-K7^2),1/(1-L7^2)) -> 1 | N7: =MAX(B7+C7+D7,2*B7,2*C7) -> 0.95929252 | O7: =IF(E7<1,"pass","fail") -> pass | P7: =IF(I7<1,"pass","fail") -> pass | Q7: =IF(M7>0,"pass","fail") -> pass | R7: =IF(N7<1,"pass","fail") -> pass | S7: =IF(E7<=R_star+0.000000001,"yes","no") -> yes
A8: =Rebudget!A15 -> Trim every existing link | B8: =Rebudget!B15 -> 0.30444549 | C8: =Rebudget!C15 -> 0.30444549 | D8: =Rebudget!D15 -> 0.4 | E8: =Rebudget!E15 -> 0.84089642 | F8: =D8 -> 0.4 | G8: =B8+C8 -> 0.60889097 | H8: =2*MAX(B8,C8) -> 0.60889097 | I8: =(F8+SQRT(F8^2+4*G8*H8))/2 -> 0.84089642 | J8: =(D8-SQRT(D8^2+8*(B8^2+C8^2)))/2 -> -0.44089642 | K8: =-D8 -> -0.4 | L8: 0 | M8: =MIN(1/(1-E8^2),1/(1-J8^2),1/(1-K8^2),1/(1-L8^2)) -> 1 | N8: =MAX(B8+C8+D8,2*B8,2*C8) -> 1.008891 | O8: =IF(E8<1,"pass","fail") -> pass | P8: =IF(I8<1,"pass","fail") -> pass | Q8: =IF(M8>0,"pass","fail") -> pass | R8: =IF(N8<1,"pass","fail") -> fail | S8: =IF(E8<=R_star+0.000000001,"yes","no") -> yes
A9: Block sizes on Chapter 9's two layers, the divisions (IND, DIG) and the corporate center (ENG, TRS): the most one unit receives from a layer. Eigenvalues of the symmetric register: rho, (h - Q)/2, -h and 0; P = (I - M^2)^-1 has eigenvalues 1/(1 - lambda^2).
A11: Complexity panel (Definition 14.11) | B11: State dimension n | C11: Channels (nonzero entries) | D11: Of the 12 possible | E11: Spectral gap 1 - rho | F11: Conditioning 1/(1 - rho) | G11: Clocks
A12: =Rebudget!A11 -> Today | B12: 4 | C12: =8+2*(Rebudget!D11>0) -> 8 | D12: =C12/12 -> 0.66666667 | E12: =IF(Rebudget!E11<1,1-Rebudget!E11,"none") -> 0.2 | F12: =IF(Rebudget!E11<1,1/(1-Rebudget!E11),"none") -> 5 | G12: one, quarterly
A13: =Rebudget!A12 -> New link at the ceiling | B13: 4 | C13: =8+2*(Rebudget!D12>0) -> 10 | D13: =C13/12 -> 0.83333333 | E13: =IF(Rebudget!E12<1,1-Rebudget!E12,"none") -> none | F13: =IF(Rebudget!E12<1,1/(1-Rebudget!E12),"none") -> none | G13: one, quarterly
A14: =Rebudget!A13 -> Run the new link light | B14: 4 | C14: =8+2*(Rebudget!D13>0) -> 10 | D14: =C14/12 -> 0.83333333 | E14: =IF(Rebudget!E13<1,1-Rebudget!E13,"none") -> 0.15910358 | F14: =IF(Rebudget!E13<1,1/(1-Rebudget!E13),"none") -> 6.2852135 | G14: one, quarterly
A15: =Rebudget!A14 -> Ring-fence treasury | B15: 4 | C15: =8+2*(Rebudget!D14>0) -> 10 | D15: =C15/12 -> 0.83333333 | E15: =IF(Rebudget!E14<1,1-Rebudget!E14,"none") -> 0.15910358 | F15: =IF(Rebudget!E14<1,1/(1-Rebudget!E14),"none") -> 6.2852135 | G15: one, quarterly
A16: =Rebudget!A15 -> Trim every existing link | B16: 4 | C16: =8+2*(Rebudget!D15>0) -> 10 | D16: =C16/12 -> 0.83333333 | E16: =IF(Rebudget!E15<1,1-Rebudget!E15,"none") -> 0.15910358 | F16: =IF(Rebudget!E15<1,1/(1-Rebudget!E15),"none") -> 6.2852135 | G16: one, quarterly
A19: Gain audit: channel (sender -> receiver) | B19: Family | C19: Ceiling: today's register | D19: Ceiling: re-budgeted register | E19: Measured: link on, trims made | F19: Measured: link on, no trims | G19: No trims vs today's register | H19: Trims made vs re-budget | I19: No trims vs re-budget
A20: DIG -> IND | B20: new link | C20: =0 -> 0 | D20: =Ceiling -> 0.4 | E20: =Ceiling -> 0.4 | F20: =Ceiling -> 0.4 | G20: =IF(F20>C20+0.000000001,"exceeds","within") -> exceeds | H20: =IF(E20>D20+0.000000001,"exceeds","within") -> within | I20: =IF(F20>D20+0.000000001,"exceeds","within") -> within
A21: ENG -> IND | B21: engineering link | C21: =Ceiling -> 0.4 | D21: =Rebudget!$B$7 -> 0.30444549 | E21: =Rebudget!$B$7 -> 0.30444549 | F21: =Ceiling -> 0.4 | G21: =IF(F21>C21+0.000000001,"exceeds","within") -> within | H21: =IF(E21>D21+0.000000001,"exceeds","within") -> within | I21: =IF(F21>D21+0.000000001,"exceeds","within") -> exceeds
A22: TRS -> IND | B22: treasury link | C22: =Ceiling -> 0.4 | D22: =Rebudget!$B$7 -> 0.30444549 | E22: =Rebudget!$B$7 -> 0.30444549 | F22: =Ceiling -> 0.4 | G22: =IF(F22>C22+0.000000001,"exceeds","within") -> within | H22: =IF(E22>D22+0.000000001,"exceeds","within") -> within | I22: =IF(F22>D22+0.000000001,"exceeds","within") -> exceeds
A23: IND -> DIG | B23: new link | C23: =0 -> 0 | D23: =Ceiling -> 0.4 | E23: =Ceiling -> 0.4 | F23: =Ceiling -> 0.4 | G23: =IF(F23>C23+0.000000001,"exceeds","within") -> exceeds | H23: =IF(E23>D23+0.000000001,"exceeds","within") -> within | I23: =IF(F23>D23+0.000000001,"exceeds","within") -> within
A24: ENG -> DIG | B24: engineering link | C24: =Ceiling -> 0.4 | D24: =Rebudget!$B$7 -> 0.30444549 | E24: =Rebudget!$B$7 -> 0.30444549 | F24: =Ceiling -> 0.4 | G24: =IF(F24>C24+0.000000001,"exceeds","within") -> within | H24: =IF(E24>D24+0.000000001,"exceeds","within") -> within | I24: =IF(F24>D24+0.000000001,"exceeds","within") -> exceeds
A25: TRS -> DIG | B25: treasury link | C25: =Ceiling -> 0.4 | D25: =Rebudget!$B$7 -> 0.30444549 | E25: =Rebudget!$B$7 -> 0.30444549 | F25: =Ceiling -> 0.4 | G25: =IF(F25>C25+0.000000001,"exceeds","within") -> within | H25: =IF(E25>D25+0.000000001,"exceeds","within") -> within | I25: =IF(F25>D25+0.000000001,"exceeds","within") -> exceeds
A26: IND -> ENG | B26: engineering link | C26: =Ceiling -> 0.4 | D26: =Rebudget!$B$7 -> 0.30444549 | E26: =Rebudget!$B$7 -> 0.30444549 | F26: =Ceiling -> 0.4 | G26: =IF(F26>C26+0.000000001,"exceeds","within") -> within | H26: =IF(E26>D26+0.000000001,"exceeds","within") -> within | I26: =IF(F26>D26+0.000000001,"exceeds","within") -> exceeds
A27: DIG -> ENG | B27: engineering link | C27: =Ceiling -> 0.4 | D27: =Rebudget!$B$7 -> 0.30444549 | E27: =Rebudget!$B$7 -> 0.30444549 | F27: =Ceiling -> 0.4 | G27: =IF(F27>C27+0.000000001,"exceeds","within") -> within | H27: =IF(E27>D27+0.000000001,"exceeds","within") -> within | I27: =IF(F27>D27+0.000000001,"exceeds","within") -> exceeds
A28: TRS -> ENG | B28: none | C28: =0 -> 0 | D28: =0 -> 0 | E28: =0 -> 0 | F28: =0 -> 0 | G28: =IF(F28>C28+0.000000001,"exceeds","within") -> within | H28: =IF(E28>D28+0.000000001,"exceeds","within") -> within | I28: =IF(F28>D28+0.000000001,"exceeds","within") -> within
A29: IND -> TRS | B29: treasury link | C29: =Ceiling -> 0.4 | D29: =Rebudget!$B$7 -> 0.30444549 | E29: =Rebudget!$B$7 -> 0.30444549 | F29: =Ceiling -> 0.4 | G29: =IF(F29>C29+0.000000001,"exceeds","within") -> within | H29: =IF(E29>D29+0.000000001,"exceeds","within") -> within | I29: =IF(F29>D29+0.000000001,"exceeds","within") -> exceeds
A30: DIG -> TRS | B30: treasury link | C30: =Ceiling -> 0.4 | D30: =Rebudget!$B$7 -> 0.30444549 | E30: =Rebudget!$B$7 -> 0.30444549 | F30: =Ceiling -> 0.4 | G30: =IF(F30>C30+0.000000001,"exceeds","within") -> within | H30: =IF(E30>D30+0.000000001,"exceeds","within") -> within | I30: =IF(F30>D30+0.000000001,"exceeds","within") -> exceeds
A31: ENG -> TRS | B31: none | C31: =0 -> 0 | D31: =0 -> 0 | E31: =0 -> 0 | F31: =0 -> 0 | G31: =IF(F31>C31+0.000000001,"exceeds","within") -> within | H31: =IF(E31>D31+0.000000001,"exceeds","within") -> within | I31: =IF(F31>D31+0.000000001,"exceeds","within") -> within
A32: Violations | G32: =COUNTIF(G20:G31,"exceeds") -> 2 | H32: =COUNTIF(H20:H31,"exceeds") -> 0 | I32: =COUNTIF(I20:I31,"exceeds") -> 8
A33: Radius the register promises / radius of the measured gains | G33: =Rebudget!E11 -> 0.8 | H33: =Rebudget!E15 -> 0.84089642 | I33: =Rebudget!E12 -> 1.0246211
A34: Theorem 14.6(ii): a violation is attributed to the channel that exceeds its ceiling, and the stability certificate is suspended until the register is re-certified. The book declares no measured record; the measured gains are three states Worked Example 14.1 describes.
A36: Tripwire: the runway's cash identity s' = s - r | B36: Quarter 0 | C36: 1 | D36: 2 | E36: 3 | F36: 4 | G36: 5 | H36: Violations | I36: With a breach | J36: Verdict
A37: Burn at the fastest cuts | B37: =Burn_now -> 50 | C37: =MAX(B37-Cut_b,0) -> 40 | D37: =MAX(C37-Cut_b,0) -> 30 | E37: =MAX(D37-Cut_b,0) -> 20 | F37: =MAX(E37-Cut_b,0) -> 10 | G37: =MAX(F37-Cut_b,0) -> 0
A38: Correct books: cash | B38: =Cash_now -> 120 | C38: =B38-B37 -> 70 | D38: =C38-C37 -> 30 | E38: =D38-D37 -> 0 | F38: =E38-E37 -> -20 | G38: =F38-F37 -> -30 | H38: =SUMPRODUCT(--(ABS(B39:F39)>0.000000001)) -> 0 | I38: =SUMPRODUCT((ABS(B39:F39)>0.000000001)*(B40:F40<0)) -> 0 | J38: =IF(H38=0,"identity holds",IF(I38=H38,"arrives with a breach: an inadmissible state",IF(H38=1,"a one-quarter jump: an implementation error","a steady drift: a mis-declared map"))) -> identity holds
A39: Correct books: residual s' - (s - r) | B39: =C38-(B38-B37) -> 0 | C39: =D38-(C38-C37) -> 0 | D39: =E38-(D38-D37) -> 0 | E39: =F38-(E38-E37) -> 0 | F39: =G38-(F38-F37) -> 0
A40: Correct books: s - r, the identity's next cash | B40: =B38-B37 -> 70 | C40: =C38-C37 -> 30 | D40: =D38-D37 -> 0 | E40: =E38-E37 -> -20 | F40: =F38-F37 -> -30
A41: Quarter 1's burn not posted: cash | B41: =Cash_now -> 120 | C41: =B41-B37 -> 70 | D41: =C41 -> 70 | E41: =D41-D37 -> 40 | F41: =E41-E37 -> 20 | G41: =F41-F37 -> 10 | H41: =SUMPRODUCT(--(ABS(B42:F42)>0.000000001)) -> 1 | I41: =SUMPRODUCT((ABS(B42:F42)>0.000000001)*(B43:F43<0)) -> 0 | J41: =IF(H41=0,"identity holds",IF(I41=H41,"arrives with a breach: an inadmissible state",IF(H41=1,"a one-quarter jump: an implementation error","a steady drift: a mis-declared map"))) -> a one-quarter jump: an implementation error
A42: Quarter 1's burn not posted: residual s' - (s - r) | B42: =C41-(B41-B37) -> 0 | C42: =D41-(C41-C37) -> 40 | D42: =E41-(D41-D37) -> 0 | E42: =F41-(E41-E37) -> 0 | F42: =G41-(F41-F37) -> 0
A43: Quarter 1's burn not posted: s - r, the identity's next cash | B43: =B41-B37 -> 70 | C43: =C41-C37 -> 30 | D43: =D41-D37 -> 40 | E43: =E41-E37 -> 20 | F43: =F41-F37 -> 10
A44: Cuts booked in the quarter they are decided: cash | B44: =Cash_now -> 120 | C44: =B44-C37 -> 80 | D44: =C44-D37 -> 50 | E44: =D44-E37 -> 30 | F44: =E44-F37 -> 20 | G44: =F44-G37 -> 20 | H44: =SUMPRODUCT(--(ABS(B45:F45)>0.000000001)) -> 5 | I44: =SUMPRODUCT((ABS(B45:F45)>0.000000001)*(B46:F46<0)) -> 0 | J44: =IF(H44=0,"identity holds",IF(I44=H44,"arrives with a breach: an inadmissible state",IF(H44=1,"a one-quarter jump: an implementation error","a steady drift: a mis-declared map"))) -> a steady drift: a mis-declared map
A45: Cuts booked in the quarter they are decided: residual s' - (s - r) | B45: =C44-(B44-B37) -> 10 | C45: =D44-(C44-C37) -> 10 | D45: =E44-(D44-D37) -> 10 | E45: =F44-(E44-E37) -> 10 | F45: =G44-(F44-F37) -> 10
A46: Cuts booked in the quarter they are decided: s - r, the identity's next cash | B46: =B44-B37 -> 70 | C46: =C44-C37 -> 40 | D46: =D44-D37 -> 20 | E46: =E44-E37 -> 10 | F46: =F44-F37 -> 10
A47: Cash never allowed below the floor: cash | B47: =Cash_now -> 120 | C47: =MAX(B47-B37,0) -> 70 | D47: =MAX(C47-C37,0) -> 30 | E47: =MAX(D47-D37,0) -> 0 | F47: =MAX(E47-E37,0) -> 0 | G47: =MAX(F47-F37,0) -> 0 | H47: =SUMPRODUCT(--(ABS(B48:F48)>0.000000001)) -> 2 | I47: =SUMPRODUCT((ABS(B48:F48)>0.000000001)*(B49:F49<0)) -> 2 | J47: =IF(H47=0,"identity holds",IF(I47=H47,"arrives with a breach: an inadmissible state",IF(H47=1,"a one-quarter jump: an implementation error","a steady drift: a mis-declared map"))) -> arrives with a breach: an inadmissible state
A48: Cash never allowed below the floor: residual s' - (s - r) | B48: =C47-(B47-B37) -> 0 | C48: =D47-(C47-C37) -> 0 | D48: =E47-(D47-D37) -> 0 | E48: =F47-(E47-E37) -> 20 | F48: =G47-(F47-F37) -> 10
A49: Cash never allowed below the floor: s - r, the identity's next cash | B49: =B47-B37 -> 70 | C49: =C47-C37 -> 30 | D49: =D47-D37 -> 0 | E49: =E47-E37 -> -20 | F49: =F47-F37 -> -10
A51: Theorem 14.7(iv) and Section 14.7: a jump suggests an implementation error, a steady drift a mis-declared map, and a violation that arrives with a constraint breach an inadmissible state.

Sheet Reference_Values
A1: Checkpoint | B1: Engine value | C1: Meaning (where in the book)
A2: Today: pass-on per unit | B2: 0.8 | C2: Worked Example 14.1, Step 1: 0.80
A3: Today: spectral radius | B3: 0.8 | C3: Step 1: 0.80
A4: Closed-form radius is an eigenvalue (det) | B4: -5.1159077e-17 | C4: Online Appendix 14.B.1
A5: Today: half-life, quarters | B5: 3.1062837 | C5: Step 1: 3.1 (Online Appendix 14.B.3: 3.11)
A6: Today: quarters to a tenth | B6: 10.318851 | C6: Online Appendix 14.B.3: 10.3
A7: Today: amplification | B7: 5 | C7: Step 1: 5
A8: Today: Lyapunov bowl, steepest curvature | B8: 2.7777778 | C8: Theorem 14.3(iv): 1/(1 - 0.64)
A9: Today: health index after the shock, quarter 0 | B9: 188.88889 | C9: Theorem 14.3(iv)
A10: Today: settled at Industrial Systems | B10: 8.8888889 | C10: Step 1: $9 million
A11: Today: settled at Digital | B11: 18.888889 | C11: Step 1: $19 million
A12: Today: settled at engineering | B12: 11.111111 | C12: Step 1: $11 million
A13: Today: settled at treasury | B13: 11.111111 | C13: Step 1: $11 million
... A72: Tripwire: early cuts, total residual | B72: 50 | C72: A steady drift

Sheet Checks
A1: Checkpoint | B1: Workbook formula value | C1: Engine value | D1: |diff| | E1: Tolerance | F1: Status
A2: Today: pass-on per unit | B2: =MAX(Bench!B8:E8) -> 0.8 | C2: =Reference_Values!B2 -> 0.8 | D2: =ABS(B2-C2) -> 0 | E2: 1e-09 | F2: =IF(D2<=E2,"PASS","FAIL") -> PASS
A3: Today: spectral radius | B3: =Bench!B10 -> 0.8 | C3: =Reference_Values!B3 -> 0.8 | D3: =ABS(B3-C3) -> 0 | E3: 1e-09 | F3: =IF(D3<=E3,"PASS","FAIL") -> PASS
A4: Closed-form radius is an eigenvalue (det) | B4: =Bench!B11 -> -1.7763568e-17 | C4: =Reference_Values!B4 -> -5.1159077e-17 | D4: =ABS(B4-C4) -> 3.3395509e-17 | E4: 1e-09 | F4: =IF(D4<=E4,"PASS","FAIL") -> PASS
A5: Today: half-life, quarters | B5: =Bench!B12 -> 3.1062837 | C5: =Reference_Values!B5 -> 3.1062837 | D5: =ABS(B5-C5) -> 0 | E5: 1e-09 | F5: =IF(D5<=E5,"PASS","FAIL") -> PASS
A6: Today: quarters to a tenth | B6: =Bench!B13 -> 10.318851 | C6: =Reference_Values!B6 -> 10.318851 | D6: =ABS(B6-C6) -> 0 | E6: 1e-09 | F6: =IF(D6<=E6,"PASS","FAIL") -> PASS
A7: Today: amplification | B7: =Bench!B14 -> 5 | C7: =Reference_Values!B7 -> 5 | D7: =ABS(B7-C7) -> 0 | E7: 1e-09 | F7: =IF(D7<=E7,"PASS","FAIL") -> PASS
A8: Today: Lyapunov bowl, steepest curvature | B8: =Bench!B29 -> 2.7777778 | C8: =Reference_Values!B8 -> 2.7777778 | D8: =ABS(B8-C8) -> 0 | E8: 1e-09 | F8: =IF(D8<=E8,"PASS","FAIL") -> PASS
A9: Today: health index after the shock, quarter 0 | B9: =Bench!H40 -> 188.88889 | C9: =Reference_Values!B9 -> 188.88889 | D9: =ABS(B9-C9) -> 0 | E9: 1e-06 | F9: =IF(D9<=E9,"PASS","FAIL") -> PASS
A10: Today: settled at Industrial Systems | B10: =Bench!B33 -> 8.8888889 | C10: =Reference_Values!B10 -> 8.8888889 | D10: =ABS(B10-C10) -> 0 | E10: 1e-09 | F10: =IF(D10<=E10,"PASS","FAIL") -> PASS
A11: Today: settled at Digital | B11: =Bench!C33 -> 18.888889 | C11: =Reference_Values!B11 -> 18.888889 | D11: =ABS(B11-C11) -> 0 | E11: 1e-09 | F11: =IF(D11<=E11,"PASS","FAIL") -> PASS
A12: Today: settled at engineering | B12: =Bench!D33 -> 11.111111 | C12: =Reference_Values!B12 -> 11.111111 | D12: =ABS(B12-C12) -> 0 | E12: 1e-09 | F12: =IF(D12<=E12,"PASS","FAIL") -> PASS
A13: Today: settled at treasury | B13: =Bench!E33 -> 11.111111 | C13: =Reference_Values!B13 -> 11.111111 | D13: =ABS(B13-C13) -> 0 | E13: 1e-09 | F13: =IF(D13<=E13,"PASS","FAIL") -> PASS
A14: Today: settled total | B14: =Bench!F33 -> 50 | C14: =Reference_Values!B14 -> 50 | D14: =ABS(B14-C14) -> 0 | E14: 1e-09 | F14: =IF(D14<=E14,"PASS","FAIL") -> PASS
A15: Today: knock-on | B15: =Bench!F36 -> 40 | C15: =Reference_Values!B15 -> 40 | D15: =ABS(B15-C15) -> 0 | E15: 1e-09 | F15: =IF(D15<=E15,"PASS","FAIL") -> PASS
A16: Exact against closed form: largest gap | B16: =Bench!F37 -> 0 | C16: =Reference_Values!B16 -> 1.7763568e-15 | D16: =ABS(B16-C16) -> 1.7763568e-15 | E16: 1e-09 | F16: =IF(D16<=E16,"PASS","FAIL") -> PASS
A17: Sensitivity recursion after 100 quarters, core | B17: =Bench!M140 -> 50 | C17: =Reference_Values!B17 -> 50 | D17: =ABS(B17-C17) -> 0 | E17: 1e-09 | F17: =IF(D17<=E17,"PASS","FAIL") -> PASS
A18: Today: echo in quarter 3 | B18: =Rebudget!F38 -> 5.12 | C18: =Reference_Values!B18 -> 5.12 | D18: =ABS(B18-C18) -> 0 | E18: 1e-09 | F18: =IF(D18<=E18,"PASS","FAIL") -> PASS
A19: Today: echo in quarter 12 | B19: =Rebudget!F47 -> 0.68719477 | C19: =Reference_Values!B19 -> 0.68719477 | D19: =ABS(B19-C19) -> 0 | E19: 1e-09 | F19: =IF(D19<=E19,"PASS","FAIL") -> PASS
A20: New link: pass-on of IND and DIG | B20: =Rebudget!J12 -> 1.2 | C20: =Reference_Values!B20 -> 1.2 | D20: =ABS(B20-C20) -> 0 | E20: 1e-09 | F20: =IF(D20<=E20,"PASS","FAIL") -> PASS
A21: New link: spectral radius | B21: =Rebudget!E12 -> 1.0246211 | C21: =Reference_Values!B21 -> 1.0246211 | D21: =ABS(B21-C21) -> 0 | E21: 1e-09 | F21: =IF(D21<=E21,"PASS","FAIL") -> PASS
A22: New link: smallest eigenvalue of P | B22: =Audit!M5 -> -20.060804 | C22: =Reference_Values!B22 -> -20.060804 | D22: =ABS(B22-C22) -> 0 | E22: 1e-06 | F22: =IF(D22<=E22,"PASS","FAIL") -> PASS
A23: New link: echo in quarter 1 | B23: =Rebudget!K36 -> 12 | C23: =Reference_Values!B23 -> 12 | D23: =ABS(B23-C23) -> 0 | E23: 1e-09 | F23: =IF(D23<=E23,"PASS","FAIL") -> PASS
A24: New link: echo in quarter 3 | B24: =Rebudget!K38 -> 12.16 | C24: =Reference_Values!B24 -> 12.16 | D24: =ABS(B24-C24) -> 0 | E24: 1e-09 | F24: =IF(D24<=E24,"PASS","FAIL") -> PASS
A25: New link: echo after three years | B25: =Rebudget!K47 -> 14.809416 | C25: =Reference_Values!B25 -> 14.809416 | D25: =ABS(B25-C25) -> 0 | E25: 1e-09 | F25: =IF(D25<=E25,"PASS","FAIL") -> PASS
A26: The board's rule as a spectral radius | B26: =R_star -> 0.84089642 | C26: =Reference_Values!B26 -> 0.84089642 | D26: =ABS(B26-C26) -> 0 | E26: 1e-09 | F26: =IF(D26<=E26,"PASS","FAIL") -> PASS
A27: Run the new link light: h | B27: =Rebudget!B5 -> 0.079803862 | C27: =Reference_Values!B27 -> 0.079803862 | D27: =ABS(B27-C27) -> 0 | E27: 1e-09 | F27: =IF(D27<=E27,"PASS","FAIL") -> PASS
A28: Ring-fence treasury: t | B28: =Rebudget!B6 -> 0.15929252 | C28: =Reference_Values!B28 -> 0.15929252 | D28: =ABS(B28-C28) -> 0 | E28: 1e-09 | F28: =IF(D28<=E28,"PASS","FAIL") -> PASS
A29: Trim every existing link: e = t | B29: =Rebudget!B7 -> 0.30444549 | C29: =Reference_Values!B29 -> 0.30444549 | D29: =ABS(B29-C29) -> 0 | E29: 1e-09 | F29: =IF(D29<=E29,"PASS","FAIL") -> PASS
A30: At the limit: half-life | B30: =Rebudget!G15 -> 4 | C30: =Reference_Values!B30 -> 4 | D30: =ABS(B30-C30) -> 0 | E30: 1e-09 | F30: =IF(D30<=E30,"PASS","FAIL") -> PASS
A31: At the limit: quarters to a tenth | B31: =Rebudget!H15 -> 13.287712 | C31: =Reference_Values!B31 -> 13.287712 | D31: =ABS(B31-C31) -> 0 | E31: 1e-09 | F31: =IF(D31<=E31,"PASS","FAIL") -> PASS
A32: At the limit: amplification | B32: =Rebudget!I15 -> 6.2852135 | C32: =Reference_Values!B32 -> 6.2852135 | D32: =ABS(B32-C32) -> 0 | E32: 1e-09 | F32: =IF(D32<=E32,"PASS","FAIL") -> PASS
A33: Run the new link light: settled total | B33: =Rebudget!S13 -> 64.240714 | C33: =Reference_Values!B33 -> 64.240714 | D33: =ABS(B33-C33) -> 0 | E33: 1e-09 | F33: =IF(D33<=E33,"PASS","FAIL") -> PASS
A34: Ring-fence treasury: settled total | B34: =Rebudget!S14 -> 68.016592 | C34: =Reference_Values!B34 -> 68.016592 | D34: =ABS(B34-C34) -> 0 | E34: 1e-09 | F34: =IF(D34<=E34,"PASS","FAIL") -> PASS
A35: Trim every existing link: settled total | B35: =Rebudget!S15 -> 70.180085 | C35: =Reference_Values!B35 -> 70.180085 | D35: =ABS(B35-C35) -> 0 | E35: 1e-09 | F35: =IF(D35<=E35,"PASS","FAIL") -> PASS
A36: Ring-fence: settled at Digital (= trim's) | B36: =Rebudget!P14 -> 25.38151 | C36: =Reference_Values!B36 -> 25.38151 | D36: =ABS(B36-C36) -> 0 | E36: 1e-09 | F36: =IF(D36<=E36,"PASS","FAIL") -> PASS
A37: Trim: echo in quarter 1 | B37: =Rebudget!Z36 -> 10.08891 | C37: =Reference_Values!B37 -> 10.08891 | D37: =ABS(B37-C37) -> 0 | E37: 1e-09 | F37: =IF(D37<=E37,"PASS","FAIL") -> PASS
A38: Trim: echo in quarter 12 | B38: =Rebudget!Z47 -> 1.413757 | C38: =Reference_Values!B38 -> 1.413757 | D38: =ABS(B38-C38) -> 0 | E38: 1e-09 | F38: =IF(D38<=E38,"PASS","FAIL") -> PASS
A39: Frontier: new link with treasury links at 0 | B39: =Rebudget!B30 -> 0.46035014 | C39: =Reference_Values!B39 -> 0.46035014 | D39: =ABS(B39-C39) -> 0 | E39: 1e-09 | F39: =IF(D39<=E39,"PASS","FAIL") -> PASS
A40: Near the edge, 0.95: half-life | B40: =Clocks!C6 -> 13.513407 | C40: =Reference_Values!B40 -> 13.513407 | D40: =ABS(B40-C40) -> 0 | E40: 1e-09 | F40: =IF(D40<=E40,"PASS","FAIL") -> PASS
A41: Near the edge, 0.95: amplification | B41: =Clocks!E6 -> 20 | C41: =Reference_Values!B41 -> 20 | D41: =ABS(B41-C41) -> 0 | E41: 1e-09 | F41: =IF(D41<=E41,"PASS","FAIL") -> PASS
A42: Walks of up to 40 links: cumulative core | B42: =Sensitivity!K45 -> 49.994683 | C42: =Reference_Values!B42 -> 49.994683 | D42: =ABS(B42-C42) -> 0 | E42: 1e-09 | F42: =IF(D42<=E42,"PASS","FAIL") -> PASS
A43: Trim: Perron-weighted settled | B43: =Sensitivity!G53 -> 62.852135 | C43: =Reference_Values!B43 -> 62.852135 | D43: =ABS(B43-C43) -> 0 | E43: 1e-09 | F43: =IF(D43<=E43,"PASS","FAIL") -> PASS
A44: Today: elasticity of the settled total to e | B44: =Sensitivity!B62 -> 2 | C44: =Reference_Values!B44 -> 2 | D44: =ABS(B44-C44) -> 4.5075055e-11 | E44: 1e-06 | F44: =IF(D44<=E44,"PASS","FAIL") -> PASS
A45: Trim: elasticity of the radius to h | B45: =Sensitivity!D85 -> 0.31206291 | C45: =Reference_Values!B45 -> 0.31206291 | D45: =ABS(B45-C45) -> 4.4687587e-12 | E45: 1e-06 | F45: =IF(D45<=E45,"PASS","FAIL") -> PASS
A46: Trim: elasticities of the radius sum to 1 | B46: =Sensitivity!B86 -> 1 | C46: =Reference_Values!B46 -> 1 | D46: =ABS(B46-C46) -> 8.3279494e-11 | E46: 1e-06 | F46: =IF(D46<=E46,"PASS","FAIL") -> PASS
A47: Blow-up dial at 0.99: settled total | B47: =Sensitivity!F108 -> 1000 | C47: =Reference_Values!B47 -> 1000 | D47: =ABS(B47-C47) -> 2.1714186e-11 | E47: 1e-06 | F47: =IF(D47<=E47,"PASS","FAIL") -> PASS
A48: State shock: echo linear in its size (ratio) | B48: =MIN(Perturbations!D5:D17) -> 2 | C48: =Reference_Values!B48 -> 2 | D48: =ABS(B48-C48) -> 0 | E48: 1e-09 | F48: =IF(D48<=E48,"PASS","FAIL") -> PASS
A49: Parametric: S_k after 40 quarters, core | B49: =Perturbations!I45 -> 49.993354 | C49: =Reference_Values!B49 -> 49.993354 | D49: =ABS(B49-C49) -> 0 | E49: 1e-09 | F49: =IF(D49<=E49,"PASS","FAIL") -> PASS
A50: Recalibration 0.40 -> 0.39: first-order total | B50: =Perturbations!W14 -> 47.5 | C50: =Reference_Values!B50 -> 47.5 | D50: =ABS(B50-C50) -> 4.7450044e-11 | E50: 1e-06 | F50: =IF(D50<=E50,"PASS","FAIL") -> PASS
A51: Recalibration 0.40 -> 0.39: re-analysis total | B51: =Perturbations!W15 -> 47.631719 | C51: =Reference_Values!B51 -> 47.631719 | D51: =ABS(B51-C51) -> 0 | E51: 1e-09 | F51: =IF(D51<=E51,"PASS","FAIL") -> PASS
A52: New link: tangent at h = 0, settled total | B52: =Perturbations!W19 -> 105.55556 | C52: =Reference_Values!B52 -> 105.55556 | D52: =ABS(B52-C52) -> 1.9452813e-09 | E52: 1e-06 | F52: =IF(D52<=E52,"PASS","FAIL") -> PASS
A53: New link: cumulative echo after 12 quarters | B53: =Perturbations!P17 -> 166.45632 | C53: =Reference_Values!B53 -> 166.45632 | D53: =ABS(B53-C53) -> 0 | E53: 1e-09 | F53: =IF(D53<=E53,"PASS","FAIL") -> PASS
A54: Runway: cash after one quarter | B54: =Runway!B5 -> 70 | C54: =Reference_Values!B54 -> 70 | D54: =ABS(B54-C54) -> 0 | E54: 1e-09 | F54: =IF(D54<=E54,"PASS","FAIL") -> PASS
A55: Runway: cash in quarter 4, fastest cuts | B55: =Runway!B8 -> -20 | C55: =Reference_Values!B55 -> -20 | D55: =ABS(B55-C55) -> 0 | E55: 1e-09 | F55: =IF(D55<=E55,"PASS","FAIL") -> PASS
A56: Runway: first quarter out of cash | B56: =Runway!B12 -> 4 | C56: =Reference_Values!B56 -> 4 | D56: =ABS(B56-C56) -> 0 | E56: 0 | F56: =IF(D56<=E56,"PASS","FAIL") -> PASS
A57: Runway: N_3(50) | B57: =Runway!D27 -> 120 | C57: =Reference_Values!B57 -> 120 | D57: =ABS(B57-C57) -> 0 | E57: 1e-09 | F57: =IF(D57<=E57,"PASS","FAIL") -> PASS
A58: Runway: N_4(50) | B58: =Runway!E27 -> 140 | C58: =Reference_Values!B58 -> 140 | D58: =ABS(B58-C58) -> 0 | E58: 1e-09 | F58: =IF(D58<=E58,"PASS","FAIL") -> PASS
A59: Runway: quarters admissible from (120, 50) | B59: =Runway!B40 -> 3 | C59: =Reference_Values!B59 -> 3 | D59: =ABS(B59-C59) -> 0 | E59: 0 | F59: =IF(D59<=E59,"PASS","FAIL") -> PASS
A60: Runway: cash needed to stop | B60: =Runway!B41 -> 150 | C60: =Reference_Values!B60 -> 150 | D60: =ABS(B60-C60) -> 0 | E60: 1e-09 | F60: =IF(D60<=E60,"PASS","FAIL") -> PASS
A61: Runway: repair by cash | B61: =Runway!B42 -> 30 | C61: =Reference_Values!B61 -> 30 | D61: =ABS(B61-C61) -> 0 | E61: 1e-09 | F61: =IF(D61<=E61,"PASS","FAIL") -> PASS
A62: Runway: need with cuts of 15 | B62: =Runway!B43 -> 110 | C62: =Reference_Values!B62 -> 110 | D62: =ABS(B62-C62) -> 0 | E62: 1e-09 | F62: =IF(D62<=E62,"PASS","FAIL") -> PASS
A63: Runway: need with cuts of 12.5 | B63: =Runway!B44 -> 125 | C63: =Reference_Values!B63 -> 125 | D63: =ABS(B63-C63) -> 0 | E63: 1e-09 | F63: =IF(D63<=E63,"PASS","FAIL") -> PASS
A64: Runway: no cuts, cash after two quarters | B64: =Runway!F6 -> 20 | C64: =Reference_Values!B64 -> 20 | D64: =ABS(B64-C64) -> 0 | E64: 1e-09 | F64: =IF(D64<=E64,"PASS","FAIL") -> PASS
A65: Runway: no cuts, first quarter out of cash | B65: =Runway!B13 -> 3 | C65: =Reference_Values!B65 -> 3 | D65: =ABS(B65-C65) -> 0 | E65: 0 | F65: =IF(D65<=E65,"PASS","FAIL") -> PASS
A66: Tests: block small gain, ring-fenced register | B66: =Audit!I7 -> 0.89816475 | C66: =Reference_Values!B66 -> 0.89816475 | D66: =ABS(B66-C66) -> 0 | E66: 1e-06 | F66: =IF(D66<=E66,"PASS","FAIL") -> PASS
A67: Tests: contraction constant, trimmed register | B67: =Audit!N8 -> 1.008891 | C67: =Reference_Values!B67 -> 1.008891 | D67: =ABS(B67-C67) -> 0 | E67: 1e-09 | F67: =IF(D67<=E67,"PASS","FAIL") -> PASS
A68: Gain audit: link on vs today's register | B68: =Audit!G32 -> 2 | C68: =Reference_Values!B68 -> 2 | D68: =ABS(B68-C68) -> 0 | E68: 0 | F68: =IF(D68<=E68,"PASS","FAIL") -> PASS
A69: Gain audit: trims made vs re-budget | B69: =Audit!H32 -> 0 | C69: =Reference_Values!B69 -> 0 | D69: =ABS(B69-C69) -> 0 | E69: 0 | F69: =IF(D69<=E69,"PASS","FAIL") -> PASS
A70: Gain audit: no trims vs re-budget | B70: =Audit!I32 -> 8 | C70: =Reference_Values!B70 -> 8 | D70: =ABS(B70-C70) -> 0 | E70: 0 | F70: =IF(D70<=E70,"PASS","FAIL") -> PASS
A71: Tripwire: floored cash, residual in quarter 3 | B71: =Audit!E48 -> 20 | C71: =Reference_Values!B71 -> 20 | D71: =ABS(B71-C71) -> 0 | E71: 1e-09 | F71: =IF(D71<=E71,"PASS","FAIL") -> PASS
A72: Tripwire: early cuts, total residual | B72: =SUM(Audit!B45:F45) -> 50 | C72: =Reference_Values!B72 -> 50 | D72: =ABS(B72-C72) -> 0 | E72: 1e-09 | F72: =IF(D72<=E72,"PASS","FAIL") -> PASS
A74: All checkpoints | F74: =IF(COUNTIF(F2:F72,"PASS")=71,"ALL PASS","CHECK") -> ALL PASS
