Workbook

Sheet README
B1: DCT Laboratory — Vol II, Ch 14: Artificial Intelligence for Enterprise Optimization
B2: Seed 26214 · Companion to DCT_V2_Ch14_Lab.ipynb and AXIOM Lab 2.14 (module AXIOM-14). Money in $ million.
B4: Worked Example 14.1, Should Meridian Let an Agent Learn Its Hiring Rule?, with the book's declarations: Chapter 7's law and costs on the agent's quarter-point grid; the AI team's agent (tabular Q-learning, one random decision in ten, step 1/(1 + (1 - beta) n), untried decisions at zero); the board's guardrail; the audit committee's certification. Seeds as in Online Appendix Remark 14.B.1.
B5: Declarations: the costs, the discount, the swings and the record, the grid, the new declarations, the seeds.
B6: Grid: the 2,113 admissible decisions and the 1,152 inside the guardrail, by formula (AXIOM Lab 2.14, step 1).
B7: BestRule: one Bellman step on the engine's values of the best rule at all 201 levels: decision values, best hires, the residual, planned capability, the guardrail check; the rule's cost from 58 and its shape.
B8: Rules: Volume I's rule and the worst rules, by formula against the engine; their costs and excess.
B9: Certify: the ten learned rules' breaches of the guardrail at every capability (Step 6).
B10: QLearning: step sizes, Equation 14.2 for one trial, every agent's excess cost and the summaries, Theorem 14.1(ii)'s bound, and the greedy learners (Steps 2-3; Figure 14.1).
B11: Bandit: thirteen target rules, the regret decomposition, Theorem 14.2(iii)'s bound and the optimistic rule's index (Step 3; Figure 14.2(a)).
B12: Swings and Practice: simulators learned from records of swings and from a record kept under Volume I's rule, with Theorem 14.3's bounds, LINEST and the collinearity of hiring and capability (Step 4; Figure 14.3).
B13: Company: learning on the company with and without the guardrail (Step 5; Figure 14.2(b)). Table14_3: the Worked Example's table, linked to the sheets. Examples: the appendices' small examples.
... B21: Cross-sheet link: green.

Sheet Declarations
A1: Declarations (Worked Example 14.1, Step 1; Chapter 7's law and costs; the agent's grid; Online Appendix Remark 14.B.1). Money in $ million; capability in points.
A3: Quantity | B3: Value | C3: Source
A4: Discount rate a year | B4: 0.1 | C4: The board's 10 percent
A5: Discount factor a quarter, beta | B5: =(1+B4)^(-1/4) -> 0.97645409 | C5: beta = 1.1^(-1/4)
A6: Effective horizon 1/(1 - beta), quarters | B6: =1/(1-B5) -> 42.47022 | C6: 42 quarters (Section 14.2)
A7: Capability kept each quarter, alpha | B7: 0.975 | C7: Chapter 7
A8: Cost of a point hired and trained, k | B8: 4 | C8: $4 million a point
A9: Hiring cap a quarter (points) | B9: 2.5
A10: Capability floor | B10: 55
A11: Cost of a point-quarter short, p | B11: 1.6 | C11: $1.6 million (Chapter 7)
A12: Lowest capability on the agent's grid | B12: 30
A13: Highest capability on the grid | B13: 80
A14: Grid step (points) | B14: 0.25 | C14: The engineering office counts quarter-points
A15: Levels | B15: =ROUND((B13-B12)/B14,0)+1 -> 201 | C15: 201
A16: Hire step (points) | B16: 0.25 | C16: Human resources hires in quarter-points
A17: Hires a quarter may take | B17: =ROUND(B9/B16,0)+1 -> 11 | C17: 0, 0.25, ..., 2.5
A18: Starting capability | B18: 58 | C18: Every rule is priced from 58
A19: Chance of a random decision | B19: 0.1 | C19: One time in ten
A20: Untried decisions start at | B20: 0 | C20: The software's default
A21: Chapter 7's best rule, cost from 58 (0.05-point grid) | B21: 230.755 | C21: Worked Example 7.1
A22: Range of a quarter's value, rbar = k x cap + p x (floor - lowest) | B22: =B8*B9+B11*(B10-B12) -> 50 | C22: From -50 (capability 30, hiring at the cap) to 0
A24: Swing w (points lost) | B24: Chance | C24: The record: count (40 quarters) | D24: The record: frequency | E24: Grid steps, w / step
A25: 1.5 | B25: 0.05 | C25: 2 | D25: =C25/SUM($C$25:$C$29) -> 0.05 | E25: =ROUND(A25/$B$14,0) -> 6
A26: 0.75 | B26: 0.2 | C26: 8 | D26: =C26/SUM($C$25:$C$29) -> 0.2 | E26: =ROUND(A26/$B$14,0) -> 3
A27: 0 | B27: 0.5 | C27: 20 | D27: =C27/SUM($C$25:$C$29) -> 0.5 | E27: =ROUND(A27/$B$14,0) -> 0
A28: -0.75 | B28: 0.2 | C28: 8 | D28: =C28/SUM($C$25:$C$29) -> 0.2 | E28: =ROUND(A28/$B$14,0) -> -3
A29: -1.5 | B29: 0.05 | C29: 2 | D29: =C29/SUM($C$25:$C$29) -> 0.05 | E29: =ROUND(A29/$B$14,0) -> -6
A30: Total | B30: =SUM(B25:B29) -> 1 | C30: =SUM(C25:C29) -> 40
A31: Mean swing | B31: =SUMPRODUCT(A25:A29,B25:B29) -> 0
A32: Standard deviation of a swing | B32: =SQRT(SUMPRODUCT(A25:A29,A25:A29,B25:B29)-B31^2) -> 0.67082039
A33: c' = 0.975c + h - w; the next capability is placed on the grid by unbiased rounding: the upper neighbour with chance equal to its fractional position (Chapter 7's interpolation).
A35: New declarations (Chapter 14)
A36: The agent: tabular Q-learning (Equation 14.2), one random admissible decision in ten, step size 1/(1 + (1 - beta) n) after n trials of a pair, untried decisions at zero, ties to the smallest hire; it knows the costs and the discount, not the law of the swings.
A37: The board's guardrail: never plan below 55 unless hiring at the cap.
A38: The audit committee: adopt a learned rule only after exact evaluation under the declared model, with the guardrail checked at every capability.
A40: Seeds (Online Appendix Remark 14.B.1)
A41: Q-learning in the simulator: the first million quarters | B41: 1400 | C41: 25 agents
A42: the declared-step agents' second million | B42: 1401 | C42: 10 agents
A43: Greedy learners | B43: 1403 | C43: 20 agents, 100,000 quarters
A44: Bandit: pools of simulated decades | B44: 1407 | C44: 50,000 decades a target
A45: Bandit: runs | B45: 1408 | C45: 100 runs of 20,000 trials
A46: Learning on the company | B46: 1411 | C46: 400 companies, with and without the guardrail
A47: Records of swings: 914000 + 1000 n + r | B47: 914000 | C47: n = 12, 40, 120; r = 0, ..., 199
A48: Records kept under Volume I's rule: 1414000 + r | B48: 1414000 | C48: r = 0, ..., 199
A49: The lab's seed (new draws only) | B49: 26214 | C49: The optimizer's curse (notebook, Panel 6)

Sheet Grid
A1: The agent's grid: admissible decisions and the board's guardrail (Worked Example 14.1, Step 1; Definition 14.2; AXIOM Lab 2.14, step 1)
A2: A hire h at capability c is admissible when 0.975c + h - w stays within [30, 80] for every swing w; it is inside the guardrail when it plans at least 55, or hires at the cap where no admissible hire plans 55.
B3: hire h: | C3: =0*Step_h -> 0 | D3: =1*Step_h -> 0.25 | E3: =2*Step_h -> 0.5 | F3: =3*Step_h -> 0.75 | G3: =4*Step_h -> 1 | H3: =5*Step_h -> 1.25 | I3: =6*Step_h -> 1.5 | J3: =7*Step_h -> 1.75 | K3: =8*Step_h -> 2 | L3: =9*Step_h -> 2.25 | M3: =10*Step_h -> 2.5 | N3: =C3 -> 0 | O3: =D3 -> 0.25 | P3: =E3 -> 0.5 | Q3: =F3 -> 0.75 | R3: =G3 -> 1 | S3: =H3 -> 1.25 | T3: =I3 -> 1.5 | U3: =J3 -> 1.75 | ... X3: =M3 -> 2.5 | AD3: Summary | AE3: Value
A4: Capability c | B4: Can plan 55 (1 = yes) | C4: Admissible, h = 0 | D4: Admissible, h = 0.25 | E4: Admissible, h = 0.5 | F4: Admissible, h = 0.75 | G4: Admissible, h = 1 | H4: Admissible, h = 1.25 | I4: Admissible, h = 1.5 | J4: Admissible, h = 1.75 | K4: Admissible, h = 2 | L4: Admissible, h = 2.25 | M4: Admissible, h = 2.5 | N4: Guarded, h = 0 | O4: Guarded, h = 0.25 | P4: Guarded, h = 0.5 | Q4: Guarded, h = 0.75 | R4: Guarded, h = 1 | S4: Guarded, h = 1.25 | T4: Guarded, h = 1.5 | U4: Guarded, h = 1.75 | V4: Guarded, h = 2 | W4: Guarded, h = 2.25 | X4: Guarded, h = 2.5 | Y4: Admissible hires | Z4: Guarded hires | AA4: Lowest admissible hire | AB4: Highest guarded hire | AD4: Admissible decisions | AE4: =SUM(Y5:Y205) -> 2113 | AF4: 2,113
A5: =Lo_c -> 30 | B5: =IF(SUMPRODUCT((Alpha_keep*$A5+$C$3:$M$3>=Floor_c-0.000000001)*(C5:M5))>0,1,0) -> 0 | C5: =IF(AND(Alpha_keep*$A5+C$3-MAX(Loss_w)>=Lo_c-0.000000001,Alpha_keep*$A5+C$3-MIN(Loss_w)<=Hi_c+0.000000001),1,0) -> 0 | D5: =IF(AND(Alpha_keep*$A5+D$3-MAX(Loss_w)>=Lo_c-0.000000001,Alpha_keep*$A5+D$3-MIN(Loss_w)<=Hi_c+0.000000001),1,0) -> 0 | E5: =IF(AND(Alpha_keep*$A5+E$3-MAX(Loss_w)>=Lo_c-0.000000001,Alpha_keep*$A5+E$3-MIN(Loss_w)<=Hi_c+0.000000001),1,0) -> 0 | F5: =IF(AND(Alpha_keep*$A5+F$3-MAX(Loss_w)>=Lo_c-0.000000001,Alpha_keep*$A5+F$3-MIN(Loss_w)<=Hi_c+0.000000001),1,0) -> 0 | G5: =IF(AND(Alpha_keep*$A5+G$3-MAX(Loss_w)>=Lo_c-0.000000001,Alpha_keep*$A5+G$3-MIN(Loss_w)<=Hi_c+0.000000001),1,0) -> 0 | H5: =IF(AND(Alpha_keep*$A5+H$3-MAX(Loss_w)>=Lo_c-0.000000001,Alpha_keep*$A5+H$3-MIN(Loss_w)<=Hi_c+0.000000001),1,0) -> 0 | I5: =IF(AND(Alpha_keep*$A5+I$3-MAX(Loss_w)>=Lo_c-0.000000001,Alpha_keep*$A5+I$3-MIN(Loss_w)<=Hi_c+0.000000001),1,0) -> 0 | J5: =IF(AND(Alpha_keep*$A5+J$3-MAX(Loss_w)>=Lo_c-0.000000001,Alpha_keep*$A5+J$3-MIN(Loss_w)<=Hi_c+0.000000001),1,0) -> 0 | ... M5: =IF(AND(Alpha_keep*$A5+M$3-MAX(Loss_w)>=Lo_c-0.000000001,Alpha_keep*$A5+M$3-MIN(Loss_w)<=Hi_c+0.000000001),1,0) -> 1 | N5: =IF(C5=1,IF(OR(Alpha_keep*$A5+N$3>=Floor_c-0.000000001,AND($B5=0,N$3>=Cap_h-0.000000001)),1,0),0) -> 0 | O5: =IF(D5=1,IF(OR(Alpha_keep*$A5+O$3>=Floor_c-0.000000001,AND($B5=0,O$3>=Cap_h-0.000000001)),1,0),0) -> 0 | P5: =IF(E5=1,IF(OR(Alpha_keep*$A5+P$3>=Floor_c-0.000000001,AND($B5=0,P$3>=Cap_h-0.000000001)),1,0),0) -> 0 | Q5: =IF(F5=1,IF(OR(Alpha_keep*$A5+Q$3>=Floor_c-0.000000001,AND($B5=0,Q$3>=Cap_h-0.000000001)),1,0),0) -> 0 | R5: =IF(G5=1,IF(OR(Alpha_keep*$A5+R$3>=Floor_c-0.000000001,AND($B5=0,R$3>=Cap_h-0.000000001)),1,0),0) -> 0 | S5: =IF(H5=1,IF(OR(Alpha_keep*$A5+S$3>=Floor_c-0.000000001,AND($B5=0,S$3>=Cap_h-0.000000001)),1,0),0) -> 0 | T5: =IF(I5=1,IF(OR(Alpha_keep*$A5+T$3>=Floor_c-0.000000001,AND($B5=0,T$3>=Cap_h-0.000000001)),1,0),0) -> 0 | U5: =IF(J5=1,IF(OR(Alpha_keep*$A5+U$3>=Floor_c-0.000000001,AND($B5=0,U$3>=Cap_h-0.000000001)),1,0),0) -> 0 | ... X5: =IF(M5=1,IF(OR(Alpha_keep*$A5+X$3>=Floor_c-0.000000001,AND($B5=0,X$3>=Cap_h-0.000000001)),1,0),0) -> 1 | Y5: =SUM(C5:M5) -> 2 | Z5: =SUM(N5:X5) -> 1 | AA5: =INDEX($C$3:$M$3,MATCH(1,C5:M5,0)) -> 2.25 | AB5: =INDEX($N$3:$X$3,MATCH(1,N5:X5,0))+(Z5-1)*Step_h -> 2.5 | AD5: Decisions inside the guardrail | AE5: =SUM(Z5:Z205) -> 1152 | AF5: 1,152
A6: =A5+Step_c -> 30.25 | B6: =IF(SUMPRODUCT((Alpha_keep*$A6+$C$3:$M$3>=Floor_c-0.000000001)*(C6:M6))>0,1,0) -> 0 | C6: =IF(AND(Alpha_keep*$A6+C$3-MAX(Loss_w)>=Lo_c-0.000000001,Alpha_keep*$A6+C$3-MIN(Loss_w)<=Hi_c+0.000000001),1,0) -> 0 | D6: =IF(AND(Alpha_keep*$A6+D$3-MAX(Loss_w)>=Lo_c-0.000000001,Alpha_keep*$A6+D$3-MIN(Loss_w)<=Hi_c+0.000000001),1,0) -> 0 | E6: =IF(AND(Alpha_keep*$A6+E$3-MAX(Loss_w)>=Lo_c-0.000000001,Alpha_keep*$A6+E$3-MIN(Loss_w)<=Hi_c+0.000000001),1,0) -> 0 | F6: =IF(AND(Alpha_keep*$A6+F$3-MAX(Loss_w)>=Lo_c-0.000000001,Alpha_keep*$A6+F$3-MIN(Loss_w)<=Hi_c+0.000000001),1,0) -> 0 | G6: =IF(AND(Alpha_keep*$A6+G$3-MAX(Loss_w)>=Lo_c-0.000000001,Alpha_keep*$A6+G$3-MIN(Loss_w)<=Hi_c+0.000000001),1,0) -> 0 | H6: =IF(AND(Alpha_keep*$A6+H$3-MAX(Loss_w)>=Lo_c-0.000000001,Alpha_keep*$A6+H$3-MIN(Loss_w)<=Hi_c+0.000000001),1,0) -> 0 | I6: =IF(AND(Alpha_keep*$A6+I$3-MAX(Loss_w)>=Lo_c-0.000000001,Alpha_keep*$A6+I$3-MIN(Loss_w)<=Hi_c+0.000000001),1,0) -> 0 | J6: =IF(AND(Alpha_keep*$A6+J$3-MAX(Loss_w)>=Lo_c-0.000000001,Alpha_keep*$A6+J$3-MIN(Loss_w)<=Hi_c+0.000000001),1,0) -> 0 | ... M6: =IF(AND(Alpha_keep*$A6+M$3-MAX(Loss_w)>=Lo_c-0.000000001,Alpha_keep*$A6+M$3-MIN(Loss_w)<=Hi_c+0.000000001),1,0) -> 1 | N6: =IF(C6=1,IF(OR(Alpha_keep*$A6+N$3>=Floor_c-0.000000001,AND($B6=0,N$3>=Cap_h-0.000000001)),1,0),0) -> 0 | O6: =IF(D6=1,IF(OR(Alpha_keep*$A6+O$3>=Floor_c-0.000000001,AND($B6=0,O$3>=Cap_h-0.000000001)),1,0),0) -> 0 | P6: =IF(E6=1,IF(OR(Alpha_keep*$A6+P$3>=Floor_c-0.000000001,AND($B6=0,P$3>=Cap_h-0.000000001)),1,0),0) -> 0 | Q6: =IF(F6=1,IF(OR(Alpha_keep*$A6+Q$3>=Floor_c-0.000000001,AND($B6=0,Q$3>=Cap_h-0.000000001)),1,0),0) -> 0 | R6: =IF(G6=1,IF(OR(Alpha_keep*$A6+R$3>=Floor_c-0.000000001,AND($B6=0,R$3>=Cap_h-0.000000001)),1,0),0) -> 0 | S6: =IF(H6=1,IF(OR(Alpha_keep*$A6+S$3>=Floor_c-0.000000001,AND($B6=0,S$3>=Cap_h-0.000000001)),1,0),0) -> 0 | T6: =IF(I6=1,IF(OR(Alpha_keep*$A6+T$3>=Floor_c-0.000000001,AND($B6=0,T$3>=Cap_h-0.000000001)),1,0),0) -> 0 | U6: =IF(J6=1,IF(OR(Alpha_keep*$A6+U$3>=Floor_c-0.000000001,AND($B6=0,U$3>=Cap_h-0.000000001)),1,0),0) -> 0 | ... X6: =IF(M6=1,IF(OR(Alpha_keep*$A6+X$3>=Floor_c-0.000000001,AND($B6=0,X$3>=Cap_h-0.000000001)),1,0),0) -> 1 | Y6: =SUM(C6:M6) -> 2 | Z6: =SUM(N6:X6) -> 1 | AA6: =INDEX($C$3:$M$3,MATCH(1,C6:M6,0)) -> 2.25 | AB6: =INDEX($N$3:$X$3,MATCH(1,N6:X6,0))+(Z6-1)*Step_h -> 2.5 | AD6: Levels that cannot plan 55 | AE6: =COUNTIF(B5:B205,0) -> 96 | AF6: There the guardrail asks for the cap
A7: =A6+Step_c -> 30.5 | B7: =IF(SUMPRODUCT((Alpha_keep*$A7+$C$3:$M$3>=Floor_c-0.000000001)*(C7:M7))>0,1,0) -> 0 | C7: =IF(AND(Alpha_keep*$A7+C$3-MAX(Loss_w)>=Lo_c-0.000000001,Alpha_keep*$A7+C$3-MIN(Loss_w)<=Hi_c+0.000000001),1,0) -> 0 | D7: =IF(AND(Alpha_keep*$A7+D$3-MAX(Loss_w)>=Lo_c-0.000000001,Alpha_keep*$A7+D$3-MIN(Loss_w)<=Hi_c+0.000000001),1,0) -> 0 | E7: =IF(AND(Alpha_keep*$A7+E$3-MAX(Loss_w)>=Lo_c-0.000000001,Alpha_keep*$A7+E$3-MIN(Loss_w)<=Hi_c+0.000000001),1,0) -> 0 | F7: =IF(AND(Alpha_keep*$A7+F$3-MAX(Loss_w)>=Lo_c-0.000000001,Alpha_keep*$A7+F$3-MIN(Loss_w)<=Hi_c+0.000000001),1,0) -> 0 | G7: =IF(AND(Alpha_keep*$A7+G$3-MAX(Loss_w)>=Lo_c-0.000000001,Alpha_keep*$A7+G$3-MIN(Loss_w)<=Hi_c+0.000000001),1,0) -> 0 | H7: =IF(AND(Alpha_keep*$A7+H$3-MAX(Loss_w)>=Lo_c-0.000000001,Alpha_keep*$A7+H$3-MIN(Loss_w)<=Hi_c+0.000000001),1,0) -> 0 | I7: =IF(AND(Alpha_keep*$A7+I$3-MAX(Loss_w)>=Lo_c-0.000000001,Alpha_keep*$A7+I$3-MIN(Loss_w)<=Hi_c+0.000000001),1,0) -> 0 | J7: =IF(AND(Alpha_keep*$A7+J$3-MAX(Loss_w)>=Lo_c-0.000000001,Alpha_keep*$A7+J$3-MIN(Loss_w)<=Hi_c+0.000000001),1,0) -> 0 | ... M7: =IF(AND(Alpha_keep*$A7+M$3-MAX(Loss_w)>=Lo_c-0.000000001,Alpha_keep*$A7+M$3-MIN(Loss_w)<=Hi_c+0.000000001),1,0) -> 1 | N7: =IF(C7=1,IF(OR(Alpha_keep*$A7+N$3>=Floor_c-0.000000001,AND($B7=0,N$3>=Cap_h-0.000000001)),1,0),0) -> 0 | O7: =IF(D7=1,IF(OR(Alpha_keep*$A7+O$3>=Floor_c-0.000000001,AND($B7=0,O$3>=Cap_h-0.000000001)),1,0),0) -> 0 | P7: =IF(E7=1,IF(OR(Alpha_keep*$A7+P$3>=Floor_c-0.000000001,AND($B7=0,P$3>=Cap_h-0.000000001)),1,0),0) -> 0 | Q7: =IF(F7=1,IF(OR(Alpha_keep*$A7+Q$3>=Floor_c-0.000000001,AND($B7=0,Q$3>=Cap_h-0.000000001)),1,0),0) -> 0 | R7: =IF(G7=1,IF(OR(Alpha_keep*$A7+R$3>=Floor_c-0.000000001,AND($B7=0,R$3>=Cap_h-0.000000001)),1,0),0) -> 0 | S7: =IF(H7=1,IF(OR(Alpha_keep*$A7+S$3>=Floor_c-0.000000001,AND($B7=0,S$3>=Cap_h-0.000000001)),1,0),0) -> 0 | T7: =IF(I7=1,IF(OR(Alpha_keep*$A7+T$3>=Floor_c-0.000000001,AND($B7=0,T$3>=Cap_h-0.000000001)),1,0),0) -> 0 | U7: =IF(J7=1,IF(OR(Alpha_keep*$A7+U$3>=Floor_c-0.000000001,AND($B7=0,U$3>=Cap_h-0.000000001)),1,0),0) -> 0 | ... X7: =IF(M7=1,IF(OR(Alpha_keep*$A7+X$3>=Floor_c-0.000000001,AND($B7=0,X$3>=Cap_h-0.000000001)),1,0),0) -> 1 | Y7: =SUM(C7:M7) -> 3 | Z7: =SUM(N7:X7) -> 1 | AA7: =INDEX($C$3:$M$3,MATCH(1,C7:M7,0)) -> 2 | AB7: =INDEX($N$3:$X$3,MATCH(1,N7:X7,0))+(Z7-1)*Step_h -> 2.5 | AD7: the highest of them | AE7: =_xlfn.MAXIFS($A$5:$A$205,B5:B205,0) -> 53.75
A8: =A7+Step_c -> 30.75 | B8: =IF(SUMPRODUCT((Alpha_keep*$A8+$C$3:$M$3>=Floor_c-0.000000001)*(C8:M8))>0,1,0) -> 0 | C8: =IF(AND(Alpha_keep*$A8+C$3-MAX(Loss_w)>=Lo_c-0.000000001,Alpha_keep*$A8+C$3-MIN(Loss_w)<=Hi_c+0.000000001),1,0) -> 0 | D8: =IF(AND(Alpha_keep*$A8+D$3-MAX(Loss_w)>=Lo_c-0.000000001,Alpha_keep*$A8+D$3-MIN(Loss_w)<=Hi_c+0.000000001),1,0) -> 0 | E8: =IF(AND(Alpha_keep*$A8+E$3-MAX(Loss_w)>=Lo_c-0.000000001,Alpha_keep*$A8+E$3-MIN(Loss_w)<=Hi_c+0.000000001),1,0) -> 0 | F8: =IF(AND(Alpha_keep*$A8+F$3-MAX(Loss_w)>=Lo_c-0.000000001,Alpha_keep*$A8+F$3-MIN(Loss_w)<=Hi_c+0.000000001),1,0) -> 0 | G8: =IF(AND(Alpha_keep*$A8+G$3-MAX(Loss_w)>=Lo_c-0.000000001,Alpha_keep*$A8+G$3-MIN(Loss_w)<=Hi_c+0.000000001),1,0) -> 0 | H8: =IF(AND(Alpha_keep*$A8+H$3-MAX(Loss_w)>=Lo_c-0.000000001,Alpha_keep*$A8+H$3-MIN(Loss_w)<=Hi_c+0.000000001),1,0) -> 0 | I8: =IF(AND(Alpha_keep*$A8+I$3-MAX(Loss_w)>=Lo_c-0.000000001,Alpha_keep*$A8+I$3-MIN(Loss_w)<=Hi_c+0.000000001),1,0) -> 0 | J8: =IF(AND(Alpha_keep*$A8+J$3-MAX(Loss_w)>=Lo_c-0.000000001,Alpha_keep*$A8+J$3-MIN(Loss_w)<=Hi_c+0.000000001),1,0) -> 1 | ... M8: =IF(AND(Alpha_keep*$A8+M$3-MAX(Loss_w)>=Lo_c-0.000000001,Alpha_keep*$A8+M$3-MIN(Loss_w)<=Hi_c+0.000000001),1,0) -> 1 | N8: =IF(C8=1,IF(OR(Alpha_keep*$A8+N$3>=Floor_c-0.000000001,AND($B8=0,N$3>=Cap_h-0.000000001)),1,0),0) -> 0 | O8: =IF(D8=1,IF(OR(Alpha_keep*$A8+O$3>=Floor_c-0.000000001,AND($B8=0,O$3>=Cap_h-0.000000001)),1,0),0) -> 0 | P8: =IF(E8=1,IF(OR(Alpha_keep*$A8+P$3>=Floor_c-0.000000001,AND($B8=0,P$3>=Cap_h-0.000000001)),1,0),0) -> 0 | Q8: =IF(F8=1,IF(OR(Alpha_keep*$A8+Q$3>=Floor_c-0.000000001,AND($B8=0,Q$3>=Cap_h-0.000000001)),1,0),0) -> 0 | R8: =IF(G8=1,IF(OR(Alpha_keep*$A8+R$3>=Floor_c-0.000000001,AND($B8=0,R$3>=Cap_h-0.000000001)),1,0),0) -> 0 | S8: =IF(H8=1,IF(OR(Alpha_keep*$A8+S$3>=Floor_c-0.000000001,AND($B8=0,S$3>=Cap_h-0.000000001)),1,0),0) -> 0 | T8: =IF(I8=1,IF(OR(Alpha_keep*$A8+T$3>=Floor_c-0.000000001,AND($B8=0,T$3>=Cap_h-0.000000001)),1,0),0) -> 0 | U8: =IF(J8=1,IF(OR(Alpha_keep*$A8+U$3>=Floor_c-0.000000001,AND($B8=0,U$3>=Cap_h-0.000000001)),1,0),0) -> 0 | ... X8: =IF(M8=1,IF(OR(Alpha_keep*$A8+X$3>=Floor_c-0.000000001,AND($B8=0,X$3>=Cap_h-0.000000001)),1,0),0) -> 1 | Y8: =SUM(C8:M8) -> 4 | Z8: =SUM(N8:X8) -> 1 | AA8: =INDEX($C$3:$M$3,MATCH(1,C8:M8,0)) -> 1.75 | AB8: =INDEX($N$3:$X$3,MATCH(1,N8:X8,0))+(Z8-1)*Step_h -> 2.5
A9: =A8+Step_c -> 31 | B9: =IF(SUMPRODUCT((Alpha_keep*$A9+$C$3:$M$3>=Floor_c-0.000000001)*(C9:M9))>0,1,0) -> 0 | C9: =IF(AND(Alpha_keep*$A9+C$3-MAX(Loss_w)>=Lo_c-0.000000001,Alpha_keep*$A9+C$3-MIN(Loss_w)<=Hi_c+0.000000001),1,0) -> 0 | D9: =IF(AND(Alpha_keep*$A9+D$3-MAX(Loss_w)>=Lo_c-0.000000001,Alpha_keep*$A9+D$3-MIN(Loss_w)<=Hi_c+0.000000001),1,0) -> 0 | E9: =IF(AND(Alpha_keep*$A9+E$3-MAX(Loss_w)>=Lo_c-0.000000001,Alpha_keep*$A9+E$3-MIN(Loss_w)<=Hi_c+0.000000001),1,0) -> 0 | F9: =IF(AND(Alpha_keep*$A9+F$3-MAX(Loss_w)>=Lo_c-0.000000001,Alpha_keep*$A9+F$3-MIN(Loss_w)<=Hi_c+0.000000001),1,0) -> 0 | G9: =IF(AND(Alpha_keep*$A9+G$3-MAX(Loss_w)>=Lo_c-0.000000001,Alpha_keep*$A9+G$3-MIN(Loss_w)<=Hi_c+0.000000001),1,0) -> 0 | H9: =IF(AND(Alpha_keep*$A9+H$3-MAX(Loss_w)>=Lo_c-0.000000001,Alpha_keep*$A9+H$3-MIN(Loss_w)<=Hi_c+0.000000001),1,0) -> 0 | I9: =IF(AND(Alpha_keep*$A9+I$3-MAX(Loss_w)>=Lo_c-0.000000001,Alpha_keep*$A9+I$3-MIN(Loss_w)<=Hi_c+0.000000001),1,0) -> 1 | J9: =IF(AND(Alpha_keep*$A9+J$3-MAX(Loss_w)>=Lo_c-0.000000001,Alpha_keep*$A9+J$3-MIN(Loss_w)<=Hi_c+0.000000001),1,0) -> 1 | ... M9: =IF(AND(Alpha_keep*$A9+M$3-MAX(Loss_w)>=Lo_c-0.000000001,Alpha_keep*$A9+M$3-MIN(Loss_w)<=Hi_c+0.000000001),1,0) -> 1 | N9: =IF(C9=1,IF(OR(Alpha_keep*$A9+N$3>=Floor_c-0.000000001,AND($B9=0,N$3>=Cap_h-0.000000001)),1,0),0) -> 0 | O9: =IF(D9=1,IF(OR(Alpha_keep*$A9+O$3>=Floor_c-0.000000001,AND($B9=0,O$3>=Cap_h-0.000000001)),1,0),0) -> 0 | P9: =IF(E9=1,IF(OR(Alpha_keep*$A9+P$3>=Floor_c-0.000000001,AND($B9=0,P$3>=Cap_h-0.000000001)),1,0),0) -> 0 | Q9: =IF(F9=1,IF(OR(Alpha_keep*$A9+Q$3>=Floor_c-0.000000001,AND($B9=0,Q$3>=Cap_h-0.000000001)),1,0),0) -> 0 | R9: =IF(G9=1,IF(OR(Alpha_keep*$A9+R$3>=Floor_c-0.000000001,AND($B9=0,R$3>=Cap_h-0.000000001)),1,0),0) -> 0 | S9: =IF(H9=1,IF(OR(Alpha_keep*$A9+S$3>=Floor_c-0.000000001,AND($B9=0,S$3>=Cap_h-0.000000001)),1,0),0) -> 0 | T9: =IF(I9=1,IF(OR(Alpha_keep*$A9+T$3>=Floor_c-0.000000001,AND($B9=0,T$3>=Cap_h-0.000000001)),1,0),0) -> 0 | U9: =IF(J9=1,IF(OR(Alpha_keep*$A9+U$3>=Floor_c-0.000000001,AND($B9=0,U$3>=Cap_h-0.000000001)),1,0),0) -> 0 | ... X9: =IF(M9=1,IF(OR(Alpha_keep*$A9+X$3>=Floor_c-0.000000001,AND($B9=0,X$3>=Cap_h-0.000000001)),1,0),0) -> 1 | Y9: =SUM(C9:M9) -> 5 | Z9: =SUM(N9:X9) -> 1 | AA9: =INDEX($C$3:$M$3,MATCH(1,C9:M9,0)) -> 1.5 | AB9: =INDEX($N$3:$X$3,MATCH(1,N9:X9,0))+(Z9-1)*Step_h -> 2.5 | AD9: Admissible hires form a run of quarter-points, and the guarded ones end at the highest admissible hire: the highest guarded hire is the lowest guarded hire plus the run's length.
A10: =A9+Step_c -> 31.25 | B10: =IF(SUMPRODUCT((Alpha_keep*$A10+$C$3:$M$3>=Floor_c-0.000000001)*(C10:M10))>0,1,0) -> 0 | C10: =IF(AND(Alpha_keep*$A10+C$3-MAX(Loss_w)>=Lo_c-0.000000001,Alpha_keep*$A10+C$3-MIN(Loss_w)<=Hi_c+0.000000001),1,0) -> 0 | D10: =IF(AND(Alpha_keep*$A10+D$3-MAX(Loss_w)>=Lo_c-0.000000001,Alpha_keep*$A10+D$3-MIN(Loss_w)<=Hi_c+0.000000001),1,0) -> 0 | E10: =IF(AND(Alpha_keep*$A10+E$3-MAX(Loss_w)>=Lo_c-0.000000001,Alpha_keep*$A10+E$3-MIN(Loss_w)<=Hi_c+0.000000001),1,0) -> 0 | F10: =IF(AND(Alpha_keep*$A10+F$3-MAX(Loss_w)>=Lo_c-0.000000001,Alpha_keep*$A10+F$3-MIN(Loss_w)<=Hi_c+0.000000001),1,0) -> 0 | G10: =IF(AND(Alpha_keep*$A10+G$3-MAX(Loss_w)>=Lo_c-0.000000001,Alpha_keep*$A10+G$3-MIN(Loss_w)<=Hi_c+0.000000001),1,0) -> 0 | H10: =IF(AND(Alpha_keep*$A10+H$3-MAX(Loss_w)>=Lo_c-0.000000001,Alpha_keep*$A10+H$3-MIN(Loss_w)<=Hi_c+0.000000001),1,0) -> 1 | I10: =IF(AND(Alpha_keep*$A10+I$3-MAX(Loss_w)>=Lo_c-0.000000001,Alpha_keep*$A10+I$3-MIN(Loss_w)<=Hi_c+0.000000001),1,0) -> 1 | J10: =IF(AND(Alpha_keep*$A10+J$3-MAX(Loss_w)>=Lo_c-0.000000001,Alpha_keep*$A10+J$3-MIN(Loss_w)<=Hi_c+0.000000001),1,0) -> 1 | ... M10: =IF(AND(Alpha_keep*$A10+M$3-MAX(Loss_w)>=Lo_c-0.000000001,Alpha_keep*$A10+M$3-MIN(Loss_w)<=Hi_c+0.000000001),1,0) -> 1 | N10: =IF(C10=1,IF(OR(Alpha_keep*$A10+N$3>=Floor_c-0.000000001,AND($B10=0,N$3>=Cap_h-0.000000001)),1,0),0) -> 0 | O10: =IF(D10=1,IF(OR(Alpha_keep*$A10+O$3>=Floor_c-0.000000001,AND($B10=0,O$3>=Cap_h-0.000000001)),1,0),0) -> 0 | P10: =IF(E10=1,IF(OR(Alpha_keep*$A10+P$3>=Floor_c-0.000000001,AND($B10=0,P$3>=Cap_h-0.000000001)),1,0),0) -> 0 | Q10: =IF(F10=1,IF(OR(Alpha_keep*$A10+Q$3>=Floor_c-0.000000001,AND($B10=0,Q$3>=Cap_h-0.000000001)),1,0),0) -> 0 | R10: =IF(G10=1,IF(OR(Alpha_keep*$A10+R$3>=Floor_c-0.000000001,AND($B10=0,R$3>=Cap_h-0.000000001)),1,0),0) -> 0 | S10: =IF(H10=1,IF(OR(Alpha_keep*$A10+S$3>=Floor_c-0.000000001,AND($B10=0,S$3>=Cap_h-0.000000001)),1,0),0) -> 0 | T10: =IF(I10=1,IF(OR(Alpha_keep*$A10+T$3>=Floor_c-0.000000001,AND($B10=0,T$3>=Cap_h-0.000000001)),1,0),0) -> 0 | U10: =IF(J10=1,IF(OR(Alpha_keep*$A10+U$3>=Floor_c-0.000000001,AND($B10=0,U$3>=Cap_h-0.000000001)),1,0),0) -> 0 | ... X10: =IF(M10=1,IF(OR(Alpha_keep*$A10+X$3>=Floor_c-0.000000001,AND($B10=0,X$3>=Cap_h-0.000000001)),1,0),0) -> 1 | Y10: =SUM(C10:M10) -> 6 | Z10: =SUM(N10:X10) -> 1 | AA10: =INDEX($C$3:$M$3,MATCH(1,C10:M10,0)) -> 1.25 | AB10: =INDEX($N$3:$X$3,MATCH(1,N10:X10,0))+(Z10-1)*Step_h -> 2.5
A11: =A10+Step_c -> 31.5 | B11: =IF(SUMPRODUCT((Alpha_keep*$A11+$C$3:$M$3>=Floor_c-0.000000001)*(C11:M11))>0,1,0) -> 0 | C11: =IF(AND(Alpha_keep*$A11+C$3-MAX(Loss_w)>=Lo_c-0.000000001,Alpha_keep*$A11+C$3-MIN(Loss_w)<=Hi_c+0.000000001),1,0) -> 0 | D11: =IF(AND(Alpha_keep*$A11+D$3-MAX(Loss_w)>=Lo_c-0.000000001,Alpha_keep*$A11+D$3-MIN(Loss_w)<=Hi_c+0.000000001),1,0) -> 0 | E11: =IF(AND(Alpha_keep*$A11+E$3-MAX(Loss_w)>=Lo_c-0.000000001,Alpha_keep*$A11+E$3-MIN(Loss_w)<=Hi_c+0.000000001),1,0) -> 0 | F11: =IF(AND(Alpha_keep*$A11+F$3-MAX(Loss_w)>=Lo_c-0.000000001,Alpha_keep*$A11+F$3-MIN(Loss_w)<=Hi_c+0.000000001),1,0) -> 0 | G11: =IF(AND(Alpha_keep*$A11+G$3-MAX(Loss_w)>=Lo_c-0.000000001,Alpha_keep*$A11+G$3-MIN(Loss_w)<=Hi_c+0.000000001),1,0) -> 1 | H11: =IF(AND(Alpha_keep*$A11+H$3-MAX(Loss_w)>=Lo_c-0.000000001,Alpha_keep*$A11+H$3-MIN(Loss_w)<=Hi_c+0.000000001),1,0) -> 1 | I11: =IF(AND(Alpha_keep*$A11+I$3-MAX(Loss_w)>=Lo_c-0.000000001,Alpha_keep*$A11+I$3-MIN(Loss_w)<=Hi_c+0.000000001),1,0) -> 1 | J11: =IF(AND(Alpha_keep*$A11+J$3-MAX(Loss_w)>=Lo_c-0.000000001,Alpha_keep*$A11+J$3-MIN(Loss_w)<=Hi_c+0.000000001),1,0) -> 1 | ... M11: =IF(AND(Alpha_keep*$A11+M$3-MAX(Loss_w)>=Lo_c-0.000000001,Alpha_keep*$A11+M$3-MIN(Loss_w)<=Hi_c+0.000000001),1,0) -> 1 | N11: =IF(C11=1,IF(OR(Alpha_keep*$A11+N$3>=Floor_c-0.000000001,AND($B11=0,N$3>=Cap_h-0.000000001)),1,0),0) -> 0 | O11: =IF(D11=1,IF(OR(Alpha_keep*$A11+O$3>=Floor_c-0.000000001,AND($B11=0,O$3>=Cap_h-0.000000001)),1,0),0) -> 0 | P11: =IF(E11=1,IF(OR(Alpha_keep*$A11+P$3>=Floor_c-0.000000001,AND($B11=0,P$3>=Cap_h-0.000000001)),1,0),0) -> 0 | Q11: =IF(F11=1,IF(OR(Alpha_keep*$A11+Q$3>=Floor_c-0.000000001,AND($B11=0,Q$3>=Cap_h-0.000000001)),1,0),0) -> 0 | R11: =IF(G11=1,IF(OR(Alpha_keep*$A11+R$3>=Floor_c-0.000000001,AND($B11=0,R$3>=Cap_h-0.000000001)),1,0),0) -> 0 | S11: =IF(H11=1,IF(OR(Alpha_keep*$A11+S$3>=Floor_c-0.000000001,AND($B11=0,S$3>=Cap_h-0.000000001)),1,0),0) -> 0 | T11: =IF(I11=1,IF(OR(Alpha_keep*$A11+T$3>=Floor_c-0.000000001,AND($B11=0,T$3>=Cap_h-0.000000001)),1,0),0) -> 0 | U11: =IF(J11=1,IF(OR(Alpha_keep*$A11+U$3>=Floor_c-0.000000001,AND($B11=0,U$3>=Cap_h-0.000000001)),1,0),0) -> 0 | ... X11: =IF(M11=1,IF(OR(Alpha_keep*$A11+X$3>=Floor_c-0.000000001,AND($B11=0,X$3>=Cap_h-0.000000001)),1,0),0) -> 1 | Y11: =SUM(C11:M11) -> 7 | Z11: =SUM(N11:X11) -> 1 | AA11: =INDEX($C$3:$M$3,MATCH(1,C11:M11,0)) -> 1 | AB11: =INDEX($N$3:$X$3,MATCH(1,N11:X11,0))+(Z11-1)*Step_h -> 2.5
A12: =A11+Step_c -> 31.75 | B12: =IF(SUMPRODUCT((Alpha_keep*$A12+$C$3:$M$3>=Floor_c-0.000000001)*(C12:M12))>0,1,0) -> 0 | C12: =IF(AND(Alpha_keep*$A12+C$3-MAX(Loss_w)>=Lo_c-0.000000001,Alpha_keep*$A12+C$3-MIN(Loss_w)<=Hi_c+0.000000001),1,0) -> 0 | D12: =IF(AND(Alpha_keep*$A12+D$3-MAX(Loss_w)>=Lo_c-0.000000001,Alpha_keep*$A12+D$3-MIN(Loss_w)<=Hi_c+0.000000001),1,0) -> 0 | E12: =IF(AND(Alpha_keep*$A12+E$3-MAX(Loss_w)>=Lo_c-0.000000001,Alpha_keep*$A12+E$3-MIN(Loss_w)<=Hi_c+0.000000001),1,0) -> 0 | F12: =IF(AND(Alpha_keep*$A12+F$3-MAX(Loss_w)>=Lo_c-0.000000001,Alpha_keep*$A12+F$3-MIN(Loss_w)<=Hi_c+0.000000001),1,0) -> 1 | G12: =IF(AND(Alpha_keep*$A12+G$3-MAX(Loss_w)>=Lo_c-0.000000001,Alpha_keep*$A12+G$3-MIN(Loss_w)<=Hi_c+0.000000001),1,0) -> 1 | H12: =IF(AND(Alpha_keep*$A12+H$3-MAX(Loss_w)>=Lo_c-0.000000001,Alpha_keep*$A12+H$3-MIN(Loss_w)<=Hi_c+0.000000001),1,0) -> 1 | I12: =IF(AND(Alpha_keep*$A12+I$3-MAX(Loss_w)>=Lo_c-0.000000001,Alpha_keep*$A12+I$3-MIN(Loss_w)<=Hi_c+0.000000001),1,0) -> 1 | J12: =IF(AND(Alpha_keep*$A12+J$3-MAX(Loss_w)>=Lo_c-0.000000001,Alpha_keep*$A12+J$3-MIN(Loss_w)<=Hi_c+0.000000001),1,0) -> 1 | ... M12: =IF(AND(Alpha_keep*$A12+M$3-MAX(Loss_w)>=Lo_c-0.000000001,Alpha_keep*$A12+M$3-MIN(Loss_w)<=Hi_c+0.000000001),1,0) -> 1 | N12: =IF(C12=1,IF(OR(Alpha_keep*$A12+N$3>=Floor_c-0.000000001,AND($B12=0,N$3>=Cap_h-0.000000001)),1,0),0) -> 0 | O12: =IF(D12=1,IF(OR(Alpha_keep*$A12+O$3>=Floor_c-0.000000001,AND($B12=0,O$3>=Cap_h-0.000000001)),1,0),0) -> 0 | P12: =IF(E12=1,IF(OR(Alpha_keep*$A12+P$3>=Floor_c-0.000000001,AND($B12=0,P$3>=Cap_h-0.000000001)),1,0),0) -> 0 | Q12: =IF(F12=1,IF(OR(Alpha_keep*$A12+Q$3>=Floor_c-0.000000001,AND($B12=0,Q$3>=Cap_h-0.000000001)),1,0),0) -> 0 | R12: =IF(G12=1,IF(OR(Alpha_keep*$A12+R$3>=Floor_c-0.000000001,AND($B12=0,R$3>=Cap_h-0.000000001)),1,0),0) -> 0 | S12: =IF(H12=1,IF(OR(Alpha_keep*$A12+S$3>=Floor_c-0.000000001,AND($B12=0,S$3>=Cap_h-0.000000001)),1,0),0) -> 0 | T12: =IF(I12=1,IF(OR(Alpha_keep*$A12+T$3>=Floor_c-0.000000001,AND($B12=0,T$3>=Cap_h-0.000000001)),1,0),0) -> 0 | U12: =IF(J12=1,IF(OR(Alpha_keep*$A12+U$3>=Floor_c-0.000000001,AND($B12=0,U$3>=Cap_h-0.000000001)),1,0),0) -> 0 | ... X12: =IF(M12=1,IF(OR(Alpha_keep*$A12+X$3>=Floor_c-0.000000001,AND($B12=0,X$3>=Cap_h-0.000000001)),1,0),0) -> 1 | Y12: =SUM(C12:M12) -> 8 | Z12: =SUM(N12:X12) -> 1 | AA12: =INDEX($C$3:$M$3,MATCH(1,C12:M12,0)) -> 0.75 | AB12: =INDEX($N$3:$X$3,MATCH(1,N12:X12,0))+(Z12-1)*Step_h -> 2.5
A13: =A12+Step_c -> 32 | B13: =IF(SUMPRODUCT((Alpha_keep*$A13+$C$3:$M$3>=Floor_c-0.000000001)*(C13:M13))>0,1,0) -> 0 | C13: =IF(AND(Alpha_keep*$A13+C$3-MAX(Loss_w)>=Lo_c-0.000000001,Alpha_keep*$A13+C$3-MIN(Loss_w)<=Hi_c+0.000000001),1,0) -> 0 | D13: =IF(AND(Alpha_keep*$A13+D$3-MAX(Loss_w)>=Lo_c-0.000000001,Alpha_keep*$A13+D$3-MIN(Loss_w)<=Hi_c+0.000000001),1,0) -> 0 | E13: =IF(AND(Alpha_keep*$A13+E$3-MAX(Loss_w)>=Lo_c-0.000000001,Alpha_keep*$A13+E$3-MIN(Loss_w)<=Hi_c+0.000000001),1,0) -> 1 | F13: =IF(AND(Alpha_keep*$A13+F$3-MAX(Loss_w)>=Lo_c-0.000000001,Alpha_keep*$A13+F$3-MIN(Loss_w)<=Hi_c+0.000000001),1,0) -> 1 | G13: =IF(AND(Alpha_keep*$A13+G$3-MAX(Loss_w)>=Lo_c-0.000000001,Alpha_keep*$A13+G$3-MIN(Loss_w)<=Hi_c+0.000000001),1,0) -> 1 | H13: =IF(AND(Alpha_keep*$A13+H$3-MAX(Loss_w)>=Lo_c-0.000000001,Alpha_keep*$A13+H$3-MIN(Loss_w)<=Hi_c+0.000000001),1,0) -> 1 | I13: =IF(AND(Alpha_keep*$A13+I$3-MAX(Loss_w)>=Lo_c-0.000000001,Alpha_keep*$A13+I$3-MIN(Loss_w)<=Hi_c+0.000000001),1,0) -> 1 | J13: =IF(AND(Alpha_keep*$A13+J$3-MAX(Loss_w)>=Lo_c-0.000000001,Alpha_keep*$A13+J$3-MIN(Loss_w)<=Hi_c+0.000000001),1,0) -> 1 | ... M13: =IF(AND(Alpha_keep*$A13+M$3-MAX(Loss_w)>=Lo_c-0.000000001,Alpha_keep*$A13+M$3-MIN(Loss_w)<=Hi_c+0.000000001),1,0) -> 1 | N13: =IF(C13=1,IF(OR(Alpha_keep*$A13+N$3>=Floor_c-0.000000001,AND($B13=0,N$3>=Cap_h-0.000000001)),1,0),0) -> 0 | O13: =IF(D13=1,IF(OR(Alpha_keep*$A13+O$3>=Floor_c-0.000000001,AND($B13=0,O$3>=Cap_h-0.000000001)),1,0),0) -> 0 | P13: =IF(E13=1,IF(OR(Alpha_keep*$A13+P$3>=Floor_c-0.000000001,AND($B13=0,P$3>=Cap_h-0.000000001)),1,0),0) -> 0 | Q13: =IF(F13=1,IF(OR(Alpha_keep*$A13+Q$3>=Floor_c-0.000000001,AND($B13=0,Q$3>=Cap_h-0.000000001)),1,0),0) -> 0 | R13: =IF(G13=1,IF(OR(Alpha_keep*$A13+R$3>=Floor_c-0.000000001,AND($B13=0,R$3>=Cap_h-0.000000001)),1,0),0) -> 0 | S13: =IF(H13=1,IF(OR(Alpha_keep*$A13+S$3>=Floor_c-0.000000001,AND($B13=0,S$3>=Cap_h-0.000000001)),1,0),0) -> 0 | T13: =IF(I13=1,IF(OR(Alpha_keep*$A13+T$3>=Floor_c-0.000000001,AND($B13=0,T$3>=Cap_h-0.000000001)),1,0),0) -> 0 | U13: =IF(J13=1,IF(OR(Alpha_keep*$A13+U$3>=Floor_c-0.000000001,AND($B13=0,U$3>=Cap_h-0.000000001)),1,0),0) -> 0 | ... X13: =IF(M13=1,IF(OR(Alpha_keep*$A13+X$3>=Floor_c-0.000000001,AND($B13=0,X$3>=Cap_h-0.000000001)),1,0),0) -> 1 | Y13: =SUM(C13:M13) -> 9 | Z13: =SUM(N13:X13) -> 1 | AA13: =INDEX($C$3:$M$3,MATCH(1,C13:M13,0)) -> 0.5 | AB13: =INDEX($N$3:$X$3,MATCH(1,N13:X13,0))+(Z13-1)*Step_h -> 2.5
A14: =A13+Step_c -> 32.25 | B14: =IF(SUMPRODUCT((Alpha_keep*$A14+$C$3:$M$3>=Floor_c-0.000000001)*(C14:M14))>0,1,0) -> 0 | C14: =IF(AND(Alpha_keep*$A14+C$3-MAX(Loss_w)>=Lo_c-0.000000001,Alpha_keep*$A14+C$3-MIN(Loss_w)<=Hi_c+0.000000001),1,0) -> 0 | D14: =IF(AND(Alpha_keep*$A14+D$3-MAX(Loss_w)>=Lo_c-0.000000001,Alpha_keep*$A14+D$3-MIN(Loss_w)<=Hi_c+0.000000001),1,0) -> 1 | E14: =IF(AND(Alpha_keep*$A14+E$3-MAX(Loss_w)>=Lo_c-0.000000001,Alpha_keep*$A14+E$3-MIN(Loss_w)<=Hi_c+0.000000001),1,0) -> 1 | F14: =IF(AND(Alpha_keep*$A14+F$3-MAX(Loss_w)>=Lo_c-0.000000001,Alpha_keep*$A14+F$3-MIN(Loss_w)<=Hi_c+0.000000001),1,0) -> 1 | G14: =IF(AND(Alpha_keep*$A14+G$3-MAX(Loss_w)>=Lo_c-0.000000001,Alpha_keep*$A14+G$3-MIN(Loss_w)<=Hi_c+0.000000001),1,0) -> 1 | H14: =IF(AND(Alpha_keep*$A14+H$3-MAX(Loss_w)>=Lo_c-0.000000001,Alpha_keep*$A14+H$3-MIN(Loss_w)<=Hi_c+0.000000001),1,0) -> 1 | I14: =IF(AND(Alpha_keep*$A14+I$3-MAX(Loss_w)>=Lo_c-0.000000001,Alpha_keep*$A14+I$3-MIN(Loss_w)<=Hi_c+0.000000001),1,0) -> 1 | J14: =IF(AND(Alpha_keep*$A14+J$3-MAX(Loss_w)>=Lo_c-0.000000001,Alpha_keep*$A14+J$3-MIN(Loss_w)<=Hi_c+0.000000001),1,0) -> 1 | ... M14: =IF(AND(Alpha_keep*$A14+M$3-MAX(Loss_w)>=Lo_c-0.000000001,Alpha_keep*$A14+M$3-MIN(Loss_w)<=Hi_c+0.000000001),1,0) -> 1 | N14: =IF(C14=1,IF(OR(Alpha_keep*$A14+N$3>=Floor_c-0.000000001,AND($B14=0,N$3>=Cap_h-0.000000001)),1,0),0) -> 0 | O14: =IF(D14=1,IF(OR(Alpha_keep*$A14+O$3>=Floor_c-0.000000001,AND($B14=0,O$3>=Cap_h-0.000000001)),1,0),0) -> 0 | P14: =IF(E14=1,IF(OR(Alpha_keep*$A14+P$3>=Floor_c-0.000000001,AND($B14=0,P$3>=Cap_h-0.000000001)),1,0),0) -> 0 | Q14: =IF(F14=1,IF(OR(Alpha_keep*$A14+Q$3>=Floor_c-0.000000001,AND($B14=0,Q$3>=Cap_h-0.000000001)),1,0),0) -> 0 | R14: =IF(G14=1,IF(OR(Alpha_keep*$A14+R$3>=Floor_c-0.000000001,AND($B14=0,R$3>=Cap_h-0.000000001)),1,0),0) -> 0 | S14: =IF(H14=1,IF(OR(Alpha_keep*$A14+S$3>=Floor_c-0.000000001,AND($B14=0,S$3>=Cap_h-0.000000001)),1,0),0) -> 0 | T14: =IF(I14=1,IF(OR(Alpha_keep*$A14+T$3>=Floor_c-0.000000001,AND($B14=0,T$3>=Cap_h-0.000000001)),1,0),0) -> 0 | U14: =IF(J14=1,IF(OR(Alpha_keep*$A14+U$3>=Floor_c-0.000000001,AND($B14=0,U$3>=Cap_h-0.000000001)),1,0),0) -> 0 | ... X14: =IF(M14=1,IF(OR(Alpha_keep*$A14+X$3>=Floor_c-0.000000001,AND($B14=0,X$3>=Cap_h-0.000000001)),1,0),0) -> 1 | Y14: =SUM(C14:M14) -> 10 | Z14: =SUM(N14:X14) -> 1 | AA14: =INDEX($C$3:$M$3,MATCH(1,C14:M14,0)) -> 0.25 | AB14: =INDEX($N$3:$X$3,MATCH(1,N14:X14,0))+(Z14-1)*Step_h -> 2.5
A15: =A14+Step_c -> 32.5 | B15: =IF(SUMPRODUCT((Alpha_keep*$A15+$C$3:$M$3>=Floor_c-0.000000001)*(C15:M15))>0,1,0) -> 0 | C15: =IF(AND(Alpha_keep*$A15+C$3-MAX(Loss_w)>=Lo_c-0.000000001,Alpha_keep*$A15+C$3-MIN(Loss_w)<=Hi_c+0.000000001),1,0) -> 1 | D15: =IF(AND(Alpha_keep*$A15+D$3-MAX(Loss_w)>=Lo_c-0.000000001,Alpha_keep*$A15+D$3-MIN(Loss_w)<=Hi_c+0.000000001),1,0) -> 1 | E15: =IF(AND(Alpha_keep*$A15+E$3-MAX(Loss_w)>=Lo_c-0.000000001,Alpha_keep*$A15+E$3-MIN(Loss_w)<=Hi_c+0.000000001),1,0) -> 1 | F15: =IF(AND(Alpha_keep*$A15+F$3-MAX(Loss_w)>=Lo_c-0.000000001,Alpha_keep*$A15+F$3-MIN(Loss_w)<=Hi_c+0.000000001),1,0) -> 1 | G15: =IF(AND(Alpha_keep*$A15+G$3-MAX(Loss_w)>=Lo_c-0.000000001,Alpha_keep*$A15+G$3-MIN(Loss_w)<=Hi_c+0.000000001),1,0) -> 1 | H15: =IF(AND(Alpha_keep*$A15+H$3-MAX(Loss_w)>=Lo_c-0.000000001,Alpha_keep*$A15+H$3-MIN(Loss_w)<=Hi_c+0.000000001),1,0) -> 1 | I15: =IF(AND(Alpha_keep*$A15+I$3-MAX(Loss_w)>=Lo_c-0.000000001,Alpha_keep*$A15+I$3-MIN(Loss_w)<=Hi_c+0.000000001),1,0) -> 1 | J15: =IF(AND(Alpha_keep*$A15+J$3-MAX(Loss_w)>=Lo_c-0.000000001,Alpha_keep*$A15+J$3-MIN(Loss_w)<=Hi_c+0.000000001),1,0) -> 1 | ... M15: =IF(AND(Alpha_keep*$A15+M$3-MAX(Loss_w)>=Lo_c-0.000000001,Alpha_keep*$A15+M$3-MIN(Loss_w)<=Hi_c+0.000000001),1,0) -> 1 | N15: =IF(C15=1,IF(OR(Alpha_keep*$A15+N$3>=Floor_c-0.000000001,AND($B15=0,N$3>=Cap_h-0.000000001)),1,0),0) -> 0 | O15: =IF(D15=1,IF(OR(Alpha_keep*$A15+O$3>=Floor_c-0.000000001,AND($B15=0,O$3>=Cap_h-0.000000001)),1,0),0) -> 0 | P15: =IF(E15=1,IF(OR(Alpha_keep*$A15+P$3>=Floor_c-0.000000001,AND($B15=0,P$3>=Cap_h-0.000000001)),1,0),0) -> 0 | Q15: =IF(F15=1,IF(OR(Alpha_keep*$A15+Q$3>=Floor_c-0.000000001,AND($B15=0,Q$3>=Cap_h-0.000000001)),1,0),0) -> 0 | R15: =IF(G15=1,IF(OR(Alpha_keep*$A15+R$3>=Floor_c-0.000000001,AND($B15=0,R$3>=Cap_h-0.000000001)),1,0),0) -> 0 | S15: =IF(H15=1,IF(OR(Alpha_keep*$A15+S$3>=Floor_c-0.000000001,AND($B15=0,S$3>=Cap_h-0.000000001)),1,0),0) -> 0 | T15: =IF(I15=1,IF(OR(Alpha_keep*$A15+T$3>=Floor_c-0.000000001,AND($B15=0,T$3>=Cap_h-0.000000001)),1,0),0) -> 0 | U15: =IF(J15=1,IF(OR(Alpha_keep*$A15+U$3>=Floor_c-0.000000001,AND($B15=0,U$3>=Cap_h-0.000000001)),1,0),0) -> 0 | ... X15: =IF(M15=1,IF(OR(Alpha_keep*$A15+X$3>=Floor_c-0.000000001,AND($B15=0,X$3>=Cap_h-0.000000001)),1,0),0) -> 1 | Y15: =SUM(C15:M15) -> 11 | Z15: =SUM(N15:X15) -> 1 | AA15: =INDEX($C$3:$M$3,MATCH(1,C15:M15,0)) -> 0 | AB15: =INDEX($N$3:$X$3,MATCH(1,N15:X15,0))+(Z15-1)*Step_h -> 2.5
A16: =A15+Step_c -> 32.75 | B16: =IF(SUMPRODUCT((Alpha_keep*$A16+$C$3:$M$3>=Floor_c-0.000000001)*(C16:M16))>0,1,0) -> 0 | C16: =IF(AND(Alpha_keep*$A16+C$3-MAX(Loss_w)>=Lo_c-0.000000001,Alpha_keep*$A16+C$3-MIN(Loss_w)<=Hi_c+0.000000001),1,0) -> 1 | D16: =IF(AND(Alpha_keep*$A16+D$3-MAX(Loss_w)>=Lo_c-0.000000001,Alpha_keep*$A16+D$3-MIN(Loss_w)<=Hi_c+0.000000001),1,0) -> 1 | E16: =IF(AND(Alpha_keep*$A16+E$3-MAX(Loss_w)>=Lo_c-0.000000001,Alpha_keep*$A16+E$3-MIN(Loss_w)<=Hi_c+0.000000001),1,0) -> 1 | F16: =IF(AND(Alpha_keep*$A16+F$3-MAX(Loss_w)>=Lo_c-0.000000001,Alpha_keep*$A16+F$3-MIN(Loss_w)<=Hi_c+0.000000001),1,0) -> 1 | G16: =IF(AND(Alpha_keep*$A16+G$3-MAX(Loss_w)>=Lo_c-0.000000001,Alpha_keep*$A16+G$3-MIN(Loss_w)<=Hi_c+0.000000001),1,0) -> 1 | H16: =IF(AND(Alpha_keep*$A16+H$3-MAX(Loss_w)>=Lo_c-0.000000001,Alpha_keep*$A16+H$3-MIN(Loss_w)<=Hi_c+0.000000001),1,0) -> 1 | I16: =IF(AND(Alpha_keep*$A16+I$3-MAX(Loss_w)>=Lo_c-0.000000001,Alpha_keep*$A16+I$3-MIN(Loss_w)<=Hi_c+0.000000001),1,0) -> 1 | J16: =IF(AND(Alpha_keep*$A16+J$3-MAX(Loss_w)>=Lo_c-0.000000001,Alpha_keep*$A16+J$3-MIN(Loss_w)<=Hi_c+0.000000001),1,0) -> 1 | ... M16: =IF(AND(Alpha_keep*$A16+M$3-MAX(Loss_w)>=Lo_c-0.000000001,Alpha_keep*$A16+M$3-MIN(Loss_w)<=Hi_c+0.000000001),1,0) -> 1 | N16: =IF(C16=1,IF(OR(Alpha_keep*$A16+N$3>=Floor_c-0.000000001,AND($B16=0,N$3>=Cap_h-0.000000001)),1,0),0) -> 0 | O16: =IF(D16=1,IF(OR(Alpha_keep*$A16+O$3>=Floor_c-0.000000001,AND($B16=0,O$3>=Cap_h-0.000000001)),1,0),0) -> 0 | P16: =IF(E16=1,IF(OR(Alpha_keep*$A16+P$3>=Floor_c-0.000000001,AND($B16=0,P$3>=Cap_h-0.000000001)),1,0),0) -> 0 | Q16: =IF(F16=1,IF(OR(Alpha_keep*$A16+Q$3>=Floor_c-0.000000001,AND($B16=0,Q$3>=Cap_h-0.000000001)),1,0),0) -> 0 | R16: =IF(G16=1,IF(OR(Alpha_keep*$A16+R$3>=Floor_c-0.000000001,AND($B16=0,R$3>=Cap_h-0.000000001)),1,0),0) -> 0 | S16: =IF(H16=1,IF(OR(Alpha_keep*$A16+S$3>=Floor_c-0.000000001,AND($B16=0,S$3>=Cap_h-0.000000001)),1,0),0) -> 0 | T16: =IF(I16=1,IF(OR(Alpha_keep*$A16+T$3>=Floor_c-0.000000001,AND($B16=0,T$3>=Cap_h-0.000000001)),1,0),0) -> 0 | U16: =IF(J16=1,IF(OR(Alpha_keep*$A16+U$3>=Floor_c-0.000000001,AND($B16=0,U$3>=Cap_h-0.000000001)),1,0),0) -> 0 | ... X16: =IF(M16=1,IF(OR(Alpha_keep*$A16+X$3>=Floor_c-0.000000001,AND($B16=0,X$3>=Cap_h-0.000000001)),1,0),0) -> 1 | Y16: =SUM(C16:M16) -> 11 | Z16: =SUM(N16:X16) -> 1 | AA16: =INDEX($C$3:$M$3,MATCH(1,C16:M16,0)) -> 0 | AB16: =INDEX($N$3:$X$3,MATCH(1,N16:X16,0))+(Z16-1)*Step_h -> 2.5
A17: =A16+Step_c -> 33 | B17: =IF(SUMPRODUCT((Alpha_keep*$A17+$C$3:$M$3>=Floor_c-0.000000001)*(C17:M17))>0,1,0) -> 0 | C17: =IF(AND(Alpha_keep*$A17+C$3-MAX(Loss_w)>=Lo_c-0.000000001,Alpha_keep*$A17+C$3-MIN(Loss_w)<=Hi_c+0.000000001),1,0) -> 1 | D17: =IF(AND(Alpha_keep*$A17+D$3-MAX(Loss_w)>=Lo_c-0.000000001,Alpha_keep*$A17+D$3-MIN(Loss_w)<=Hi_c+0.000000001),1,0) -> 1 | E17: =IF(AND(Alpha_keep*$A17+E$3-MAX(Loss_w)>=Lo_c-0.000000001,Alpha_keep*$A17+E$3-MIN(Loss_w)<=Hi_c+0.000000001),1,0) -> 1 | F17: =IF(AND(Alpha_keep*$A17+F$3-MAX(Loss_w)>=Lo_c-0.000000001,Alpha_keep*$A17+F$3-MIN(Loss_w)<=Hi_c+0.000000001),1,0) -> 1 | G17: =IF(AND(Alpha_keep*$A17+G$3-MAX(Loss_w)>=Lo_c-0.000000001,Alpha_keep*$A17+G$3-MIN(Loss_w)<=Hi_c+0.000000001),1,0) -> 1 | H17: =IF(AND(Alpha_keep*$A17+H$3-MAX(Loss_w)>=Lo_c-0.000000001,Alpha_keep*$A17+H$3-MIN(Loss_w)<=Hi_c+0.000000001),1,0) -> 1 | I17: =IF(AND(Alpha_keep*$A17+I$3-MAX(Loss_w)>=Lo_c-0.000000001,Alpha_keep*$A17+I$3-MIN(Loss_w)<=Hi_c+0.000000001),1,0) -> 1 | J17: =IF(AND(Alpha_keep*$A17+J$3-MAX(Loss_w)>=Lo_c-0.000000001,Alpha_keep*$A17+J$3-MIN(Loss_w)<=Hi_c+0.000000001),1,0) -> 1 | ... M17: =IF(AND(Alpha_keep*$A17+M$3-MAX(Loss_w)>=Lo_c-0.000000001,Alpha_keep*$A17+M$3-MIN(Loss_w)<=Hi_c+0.000000001),1,0) -> 1 | N17: =IF(C17=1,IF(OR(Alpha_keep*$A17+N$3>=Floor_c-0.000000001,AND($B17=0,N$3>=Cap_h-0.000000001)),1,0),0) -> 0 | O17: =IF(D17=1,IF(OR(Alpha_keep*$A17+O$3>=Floor_c-0.000000001,AND($B17=0,O$3>=Cap_h-0.000000001)),1,0),0) -> 0 | P17: =IF(E17=1,IF(OR(Alpha_keep*$A17+P$3>=Floor_c-0.000000001,AND($B17=0,P$3>=Cap_h-0.000000001)),1,0),0) -> 0 | Q17: =IF(F17=1,IF(OR(Alpha_keep*$A17+Q$3>=Floor_c-0.000000001,AND($B17=0,Q$3>=Cap_h-0.000000001)),1,0),0) -> 0 | R17: =IF(G17=1,IF(OR(Alpha_keep*$A17+R$3>=Floor_c-0.000000001,AND($B17=0,R$3>=Cap_h-0.000000001)),1,0),0) -> 0 | S17: =IF(H17=1,IF(OR(Alpha_keep*$A17+S$3>=Floor_c-0.000000001,AND($B17=0,S$3>=Cap_h-0.000000001)),1,0),0) -> 0 | T17: =IF(I17=1,IF(OR(Alpha_keep*$A17+T$3>=Floor_c-0.000000001,AND($B17=0,T$3>=Cap_h-0.000000001)),1,0),0) -> 0 | U17: =IF(J17=1,IF(OR(Alpha_keep*$A17+U$3>=Floor_c-0.000000001,AND($B17=0,U$3>=Cap_h-0.000000001)),1,0),0) -> 0 | ... X17: =IF(M17=1,IF(OR(Alpha_keep*$A17+X$3>=Floor_c-0.000000001,AND($B17=0,X$3>=Cap_h-0.000000001)),1,0),0) -> 1 | Y17: =SUM(C17:M17) -> 11 | Z17: =SUM(N17:X17) -> 1 | AA17: =INDEX($C$3:$M$3,MATCH(1,C17:M17,0)) -> 0 | AB17: =INDEX($N$3:$X$3,MATCH(1,N17:X17,0))+(Z17-1)*Step_h -> 2.5
A18: =A17+Step_c -> 33.25 | B18: =IF(SUMPRODUCT((Alpha_keep*$A18+$C$3:$M$3>=Floor_c-0.000000001)*(C18:M18))>0,1,0) -> 0 | C18: =IF(AND(Alpha_keep*$A18+C$3-MAX(Loss_w)>=Lo_c-0.000000001,Alpha_keep*$A18+C$3-MIN(Loss_w)<=Hi_c+0.000000001),1,0) -> 1 | D18: =IF(AND(Alpha_keep*$A18+D$3-MAX(Loss_w)>=Lo_c-0.000000001,Alpha_keep*$A18+D$3-MIN(Loss_w)<=Hi_c+0.000000001),1,0) -> 1 | E18: =IF(AND(Alpha_keep*$A18+E$3-MAX(Loss_w)>=Lo_c-0.000000001,Alpha_keep*$A18+E$3-MIN(Loss_w)<=Hi_c+0.000000001),1,0) -> 1 | F18: =IF(AND(Alpha_keep*$A18+F$3-MAX(Loss_w)>=Lo_c-0.000000001,Alpha_keep*$A18+F$3-MIN(Loss_w)<=Hi_c+0.000000001),1,0) -> 1 | G18: =IF(AND(Alpha_keep*$A18+G$3-MAX(Loss_w)>=Lo_c-0.000000001,Alpha_keep*$A18+G$3-MIN(Loss_w)<=Hi_c+0.000000001),1,0) -> 1 | H18: =IF(AND(Alpha_keep*$A18+H$3-MAX(Loss_w)>=Lo_c-0.000000001,Alpha_keep*$A18+H$3-MIN(Loss_w)<=Hi_c+0.000000001),1,0) -> 1 | I18: =IF(AND(Alpha_keep*$A18+I$3-MAX(Loss_w)>=Lo_c-0.000000001,Alpha_keep*$A18+I$3-MIN(Loss_w)<=Hi_c+0.000000001),1,0) -> 1 | J18: =IF(AND(Alpha_keep*$A18+J$3-MAX(Loss_w)>=Lo_c-0.000000001,Alpha_keep*$A18+J$3-MIN(Loss_w)<=Hi_c+0.000000001),1,0) -> 1 | ... M18: =IF(AND(Alpha_keep*$A18+M$3-MAX(Loss_w)>=Lo_c-0.000000001,Alpha_keep*$A18+M$3-MIN(Loss_w)<=Hi_c+0.000000001),1,0) -> 1 | N18: =IF(C18=1,IF(OR(Alpha_keep*$A18+N$3>=Floor_c-0.000000001,AND($B18=0,N$3>=Cap_h-0.000000001)),1,0),0) -> 0 | O18: =IF(D18=1,IF(OR(Alpha_keep*$A18+O$3>=Floor_c-0.000000001,AND($B18=0,O$3>=Cap_h-0.000000001)),1,0),0) -> 0 | P18: =IF(E18=1,IF(OR(Alpha_keep*$A18+P$3>=Floor_c-0.000000001,AND($B18=0,P$3>=Cap_h-0.000000001)),1,0),0) -> 0 | Q18: =IF(F18=1,IF(OR(Alpha_keep*$A18+Q$3>=Floor_c-0.000000001,AND($B18=0,Q$3>=Cap_h-0.000000001)),1,0),0) -> 0 | R18: =IF(G18=1,IF(OR(Alpha_keep*$A18+R$3>=Floor_c-0.000000001,AND($B18=0,R$3>=Cap_h-0.000000001)),1,0),0) -> 0 | S18: =IF(H18=1,IF(OR(Alpha_keep*$A18+S$3>=Floor_c-0.000000001,AND($B18=0,S$3>=Cap_h-0.000000001)),1,0),0) -> 0 | T18: =IF(I18=1,IF(OR(Alpha_keep*$A18+T$3>=Floor_c-0.000000001,AND($B18=0,T$3>=Cap_h-0.000000001)),1,0),0) -> 0 | U18: =IF(J18=1,IF(OR(Alpha_keep*$A18+U$3>=Floor_c-0.000000001,AND($B18=0,U$3>=Cap_h-0.000000001)),1,0),0) -> 0 | ... X18: =IF(M18=1,IF(OR(Alpha_keep*$A18+X$3>=Floor_c-0.000000001,AND($B18=0,X$3>=Cap_h-0.000000001)),1,0),0) -> 1 | Y18: =SUM(C18:M18) -> 11 | Z18: =SUM(N18:X18) -> 1 | AA18: =INDEX($C$3:$M$3,MATCH(1,C18:M18,0)) -> 0 | AB18: =INDEX($N$3:$X$3,MATCH(1,N18:X18,0))+(Z18-1)*Step_h -> 2.5
A19: =A18+Step_c -> 33.5 | B19: =IF(SUMPRODUCT((Alpha_keep*$A19+$C$3:$M$3>=Floor_c-0.000000001)*(C19:M19))>0,1,0) -> 0 | C19: =IF(AND(Alpha_keep*$A19+C$3-MAX(Loss_w)>=Lo_c-0.000000001,Alpha_keep*$A19+C$3-MIN(Loss_w)<=Hi_c+0.000000001),1,0) -> 1 | D19: =IF(AND(Alpha_keep*$A19+D$3-MAX(Loss_w)>=Lo_c-0.000000001,Alpha_keep*$A19+D$3-MIN(Loss_w)<=Hi_c+0.000000001),1,0) -> 1 | E19: =IF(AND(Alpha_keep*$A19+E$3-MAX(Loss_w)>=Lo_c-0.000000001,Alpha_keep*$A19+E$3-MIN(Loss_w)<=Hi_c+0.000000001),1,0) -> 1 | F19: =IF(AND(Alpha_keep*$A19+F$3-MAX(Loss_w)>=Lo_c-0.000000001,Alpha_keep*$A19+F$3-MIN(Loss_w)<=Hi_c+0.000000001),1,0) -> 1 | G19: =IF(AND(Alpha_keep*$A19+G$3-MAX(Loss_w)>=Lo_c-0.000000001,Alpha_keep*$A19+G$3-MIN(Loss_w)<=Hi_c+0.000000001),1,0) -> 1 | H19: =IF(AND(Alpha_keep*$A19+H$3-MAX(Loss_w)>=Lo_c-0.000000001,Alpha_keep*$A19+H$3-MIN(Loss_w)<=Hi_c+0.000000001),1,0) -> 1 | I19: =IF(AND(Alpha_keep*$A19+I$3-MAX(Loss_w)>=Lo_c-0.000000001,Alpha_keep*$A19+I$3-MIN(Loss_w)<=Hi_c+0.000000001),1,0) -> 1 | J19: =IF(AND(Alpha_keep*$A19+J$3-MAX(Loss_w)>=Lo_c-0.000000001,Alpha_keep*$A19+J$3-MIN(Loss_w)<=Hi_c+0.000000001),1,0) -> 1 | ... M19: =IF(AND(Alpha_keep*$A19+M$3-MAX(Loss_w)>=Lo_c-0.000000001,Alpha_keep*$A19+M$3-MIN(Loss_w)<=Hi_c+0.000000001),1,0) -> 1 | N19: =IF(C19=1,IF(OR(Alpha_keep*$A19+N$3>=Floor_c-0.000000001,AND($B19=0,N$3>=Cap_h-0.000000001)),1,0),0) -> 0 | O19: =IF(D19=1,IF(OR(Alpha_keep*$A19+O$3>=Floor_c-0.000000001,AND($B19=0,O$3>=Cap_h-0.000000001)),1,0),0) -> 0 | P19: =IF(E19=1,IF(OR(Alpha_keep*$A19+P$3>=Floor_c-0.000000001,AND($B19=0,P$3>=Cap_h-0.000000001)),1,0),0) -> 0 | Q19: =IF(F19=1,IF(OR(Alpha_keep*$A19+Q$3>=Floor_c-0.000000001,AND($B19=0,Q$3>=Cap_h-0.000000001)),1,0),0) -> 0 | R19: =IF(G19=1,IF(OR(Alpha_keep*$A19+R$3>=Floor_c-0.000000001,AND($B19=0,R$3>=Cap_h-0.000000001)),1,0),0) -> 0 | S19: =IF(H19=1,IF(OR(Alpha_keep*$A19+S$3>=Floor_c-0.000000001,AND($B19=0,S$3>=Cap_h-0.000000001)),1,0),0) -> 0 | T19: =IF(I19=1,IF(OR(Alpha_keep*$A19+T$3>=Floor_c-0.000000001,AND($B19=0,T$3>=Cap_h-0.000000001)),1,0),0) -> 0 | U19: =IF(J19=1,IF(OR(Alpha_keep*$A19+U$3>=Floor_c-0.000000001,AND($B19=0,U$3>=Cap_h-0.000000001)),1,0),0) -> 0 | ... X19: =IF(M19=1,IF(OR(Alpha_keep*$A19+X$3>=Floor_c-0.000000001,AND($B19=0,X$3>=Cap_h-0.000000001)),1,0),0) -> 1 | Y19: =SUM(C19:M19) -> 11 | Z19: =SUM(N19:X19) -> 1 | AA19: =INDEX($C$3:$M$3,MATCH(1,C19:M19,0)) -> 0 | AB19: =INDEX($N$3:$X$3,MATCH(1,N19:X19,0))+(Z19-1)*Step_h -> 2.5
A20: =A19+Step_c -> 33.75 | B20: =IF(SUMPRODUCT((Alpha_keep*$A20+$C$3:$M$3>=Floor_c-0.000000001)*(C20:M20))>0,1,0) -> 0 | C20: =IF(AND(Alpha_keep*$A20+C$3-MAX(Loss_w)>=Lo_c-0.000000001,Alpha_keep*$A20+C$3-MIN(Loss_w)<=Hi_c+0.000000001),1,0) -> 1 | D20: =IF(AND(Alpha_keep*$A20+D$3-MAX(Loss_w)>=Lo_c-0.000000001,Alpha_keep*$A20+D$3-MIN(Loss_w)<=Hi_c+0.000000001),1,0) -> 1 | E20: =IF(AND(Alpha_keep*$A20+E$3-MAX(Loss_w)>=Lo_c-0.000000001,Alpha_keep*$A20+E$3-MIN(Loss_w)<=Hi_c+0.000000001),1,0) -> 1 | F20: =IF(AND(Alpha_keep*$A20+F$3-MAX(Loss_w)>=Lo_c-0.000000001,Alpha_keep*$A20+F$3-MIN(Loss_w)<=Hi_c+0.000000001),1,0) -> 1 | G20: =IF(AND(Alpha_keep*$A20+G$3-MAX(Loss_w)>=Lo_c-0.000000001,Alpha_keep*$A20+G$3-MIN(Loss_w)<=Hi_c+0.000000001),1,0) -> 1 | H20: =IF(AND(Alpha_keep*$A20+H$3-MAX(Loss_w)>=Lo_c-0.000000001,Alpha_keep*$A20+H$3-MIN(Loss_w)<=Hi_c+0.000000001),1,0) -> 1 | I20: =IF(AND(Alpha_keep*$A20+I$3-MAX(Loss_w)>=Lo_c-0.000000001,Alpha_keep*$A20+I$3-MIN(Loss_w)<=Hi_c+0.000000001),1,0) -> 1 | J20: =IF(AND(Alpha_keep*$A20+J$3-MAX(Loss_w)>=Lo_c-0.000000001,Alpha_keep*$A20+J$3-MIN(Loss_w)<=Hi_c+0.000000001),1,0) -> 1 | ... M20: =IF(AND(Alpha_keep*$A20+M$3-MAX(Loss_w)>=Lo_c-0.000000001,Alpha_keep*$A20+M$3-MIN(Loss_w)<=Hi_c+0.000000001),1,0) -> 1 | N20: =IF(C20=1,IF(OR(Alpha_keep*$A20+N$3>=Floor_c-0.000000001,AND($B20=0,N$3>=Cap_h-0.000000001)),1,0),0) -> 0 | O20: =IF(D20=1,IF(OR(Alpha_keep*$A20+O$3>=Floor_c-0.000000001,AND($B20=0,O$3>=Cap_h-0.000000001)),1,0),0) -> 0 | P20: =IF(E20=1,IF(OR(Alpha_keep*$A20+P$3>=Floor_c-0.000000001,AND($B20=0,P$3>=Cap_h-0.000000001)),1,0),0) -> 0 | Q20: =IF(F20=1,IF(OR(Alpha_keep*$A20+Q$3>=Floor_c-0.000000001,AND($B20=0,Q$3>=Cap_h-0.000000001)),1,0),0) -> 0 | R20: =IF(G20=1,IF(OR(Alpha_keep*$A20+R$3>=Floor_c-0.000000001,AND($B20=0,R$3>=Cap_h-0.000000001)),1,0),0) -> 0 | S20: =IF(H20=1,IF(OR(Alpha_keep*$A20+S$3>=Floor_c-0.000000001,AND($B20=0,S$3>=Cap_h-0.000000001)),1,0),0) -> 0 | T20: =IF(I20=1,IF(OR(Alpha_keep*$A20+T$3>=Floor_c-0.000000001,AND($B20=0,T$3>=Cap_h-0.000000001)),1,0),0) -> 0 | U20: =IF(J20=1,IF(OR(Alpha_keep*$A20+U$3>=Floor_c-0.000000001,AND($B20=0,U$3>=Cap_h-0.000000001)),1,0),0) -> 0 | ... X20: =IF(M20=1,IF(OR(Alpha_keep*$A20+X$3>=Floor_c-0.000000001,AND($B20=0,X$3>=Cap_h-0.000000001)),1,0),0) -> 1 | Y20: =SUM(C20:M20) -> 11 | Z20: =SUM(N20:X20) -> 1 | AA20: =INDEX($C$3:$M$3,MATCH(1,C20:M20,0)) -> 0 | AB20: =INDEX($N$3:$X$3,MATCH(1,N20:X20,0))+(Z20-1)*Step_h -> 2.5
A21: =A20+Step_c -> 34 | B21: =IF(SUMPRODUCT((Alpha_keep*$A21+$C$3:$M$3>=Floor_c-0.000000001)*(C21:M21))>0,1,0) -> 0 | C21: =IF(AND(Alpha_keep*$A21+C$3-MAX(Loss_w)>=Lo_c-0.000000001,Alpha_keep*$A21+C$3-MIN(Loss_w)<=Hi_c+0.000000001),1,0) -> 1 | D21: =IF(AND(Alpha_keep*$A21+D$3-MAX(Loss_w)>=Lo_c-0.000000001,Alpha_keep*$A21+D$3-MIN(Loss_w)<=Hi_c+0.000000001),1,0) -> 1 | E21: =IF(AND(Alpha_keep*$A21+E$3-MAX(Loss_w)>=Lo_c-0.000000001,Alpha_keep*$A21+E$3-MIN(Loss_w)<=Hi_c+0.000000001),1,0) -> 1 | F21: =IF(AND(Alpha_keep*$A21+F$3-MAX(Loss_w)>=Lo_c-0.000000001,Alpha_keep*$A21+F$3-MIN(Loss_w)<=Hi_c+0.000000001),1,0) -> 1 | G21: =IF(AND(Alpha_keep*$A21+G$3-MAX(Loss_w)>=Lo_c-0.000000001,Alpha_keep*$A21+G$3-MIN(Loss_w)<=Hi_c+0.000000001),1,0) -> 1 | H21: =IF(AND(Alpha_keep*$A21+H$3-MAX(Loss_w)>=Lo_c-0.000000001,Alpha_keep*$A21+H$3-MIN(Loss_w)<=Hi_c+0.000000001),1,0) -> 1 | I21: =IF(AND(Alpha_keep*$A21+I$3-MAX(Loss_w)>=Lo_c-0.000000001,Alpha_keep*$A21+I$3-MIN(Loss_w)<=Hi_c+0.000000001),1,0) -> 1 | J21: =IF(AND(Alpha_keep*$A21+J$3-MAX(Loss_w)>=Lo_c-0.000000001,Alpha_keep*$A21+J$3-MIN(Loss_w)<=Hi_c+0.000000001),1,0) -> 1 | ... M21: =IF(AND(Alpha_keep*$A21+M$3-MAX(Loss_w)>=Lo_c-0.000000001,Alpha_keep*$A21+M$3-MIN(Loss_w)<=Hi_c+0.000000001),1,0) -> 1 | N21: =IF(C21=1,IF(OR(Alpha_keep*$A21+N$3>=Floor_c-0.000000001,AND($B21=0,N$3>=Cap_h-0.000000001)),1,0),0) -> 0 | O21: =IF(D21=1,IF(OR(Alpha_keep*$A21+O$3>=Floor_c-0.000000001,AND($B21=0,O$3>=Cap_h-0.000000001)),1,0),0) -> 0 | P21: =IF(E21=1,IF(OR(Alpha_keep*$A21+P$3>=Floor_c-0.000000001,AND($B21=0,P$3>=Cap_h-0.000000001)),1,0),0) -> 0 | Q21: =IF(F21=1,IF(OR(Alpha_keep*$A21+Q$3>=Floor_c-0.000000001,AND($B21=0,Q$3>=Cap_h-0.000000001)),1,0),0) -> 0 | R21: =IF(G21=1,IF(OR(Alpha_keep*$A21+R$3>=Floor_c-0.000000001,AND($B21=0,R$3>=Cap_h-0.000000001)),1,0),0) -> 0 | S21: =IF(H21=1,IF(OR(Alpha_keep*$A21+S$3>=Floor_c-0.000000001,AND($B21=0,S$3>=Cap_h-0.000000001)),1,0),0) -> 0 | T21: =IF(I21=1,IF(OR(Alpha_keep*$A21+T$3>=Floor_c-0.000000001,AND($B21=0,T$3>=Cap_h-0.000000001)),1,0),0) -> 0 | U21: =IF(J21=1,IF(OR(Alpha_keep*$A21+U$3>=Floor_c-0.000000001,AND($B21=0,U$3>=Cap_h-0.000000001)),1,0),0) -> 0 | ... X21: =IF(M21=1,IF(OR(Alpha_keep*$A21+X$3>=Floor_c-0.000000001,AND($B21=0,X$3>=Cap_h-0.000000001)),1,0),0) -> 1 | Y21: =SUM(C21:M21) -> 11 | Z21: =SUM(N21:X21) -> 1 | AA21: =INDEX($C$3:$M$3,MATCH(1,C21:M21,0)) -> 0 | AB21: =INDEX($N$3:$X$3,MATCH(1,N21:X21,0))+(Z21-1)*Step_h -> 2.5
... A205: =A204+Step_c -> 80 | B205: =IF(SUMPRODUCT((Alpha_keep*$A205+$C$3:$M$3>=Floor_c-0.000000001)*(C205:M205))>0,1,0) -> 1 | C205: =IF(AND(Alpha_keep*$A205+C$3-MAX(Loss_w)>=Lo_c-0.000000001,Alpha_keep*$A205+C$3-MIN(Loss_w)<=Hi_c+0.000000001),1,0) -> 1 | D205: =IF(AND(Alpha_keep*$A205+D$3-MAX(Loss_w)>=Lo_c-0.000000001,Alpha_keep*$A205+D$3-MIN(Loss_w)<=Hi_c+0.000000001),1,0) -> 1 | E205: =IF(AND(Alpha_keep*$A205+E$3-MAX(Loss_w)>=Lo_c-0.000000001,Alpha_keep*$A205+E$3-MIN(Loss_w)<=Hi_c+0.000000001),1,0) -> 1 | F205: =IF(AND(Alpha_keep*$A205+F$3-MAX(Loss_w)>=Lo_c-0.000000001,Alpha_keep*$A205+F$3-MIN(Loss_w)<=Hi_c+0.000000001),1,0) -> 0 | G205: =IF(AND(Alpha_keep*$A205+G$3-MAX(Loss_w)>=Lo_c-0.000000001,Alpha_keep*$A205+G$3-MIN(Loss_w)<=Hi_c+0.000000001),1,0) -> 0 | H205: =IF(AND(Alpha_keep*$A205+H$3-MAX(Loss_w)>=Lo_c-0.000000001,Alpha_keep*$A205+H$3-MIN(Loss_w)<=Hi_c+0.000000001),1,0) -> 0 | I205: =IF(AND(Alpha_keep*$A205+I$3-MAX(Loss_w)>=Lo_c-0.000000001,Alpha_keep*$A205+I$3-MIN(Loss_w)<=Hi_c+0.000000001),1,0) -> 0 | J205: =IF(AND(Alpha_keep*$A205+J$3-MAX(Loss_w)>=Lo_c-0.000000001,Alpha_keep*$A205+J$3-MIN(Loss_w)<=Hi_c+0.000000001),1,0) -> 0 | ... M205: =IF(AND(Alpha_keep*$A205+M$3-MAX(Loss_w)>=Lo_c-0.000000001,Alpha_keep*$A205+M$3-MIN(Loss_w)<=Hi_c+0.000000001),1,0) -> 0 | N205: =IF(C205=1,IF(OR(Alpha_keep*$A205+N$3>=Floor_c-0.000000001,AND($B205=0,N$3>=Cap_h-0.000000001)),1,0),0) -> 1 | O205: =IF(D205=1,IF(OR(Alpha_keep*$A205+O$3>=Floor_c-0.000000001,AND($B205=0,O$3>=Cap_h-0.000000001)),1,0),0) -> 1 | P205: =IF(E205=1,IF(OR(Alpha_keep*$A205+P$3>=Floor_c-0.000000001,AND($B205=0,P$3>=Cap_h-0.000000001)),1,0),0) -> 1 | Q205: =IF(F205=1,IF(OR(Alpha_keep*$A205+Q$3>=Floor_c-0.000000001,AND($B205=0,Q$3>=Cap_h-0.000000001)),1,0),0) -> 0 | R205: =IF(G205=1,IF(OR(Alpha_keep*$A205+R$3>=Floor_c-0.000000001,AND($B205=0,R$3>=Cap_h-0.000000001)),1,0),0) -> 0 | S205: =IF(H205=1,IF(OR(Alpha_keep*$A205+S$3>=Floor_c-0.000000001,AND($B205=0,S$3>=Cap_h-0.000000001)),1,0),0) -> 0 | T205: =IF(I205=1,IF(OR(Alpha_keep*$A205+T$3>=Floor_c-0.000000001,AND($B205=0,T$3>=Cap_h-0.000000001)),1,0),0) -> 0 | U205: =IF(J205=1,IF(OR(Alpha_keep*$A205+U$3>=Floor_c-0.000000001,AND($B205=0,U$3>=Cap_h-0.000000001)),1,0),0) -> 0 | ... X205: =IF(M205=1,IF(OR(Alpha_keep*$A205+X$3>=Floor_c-0.000000001,AND($B205=0,X$3>=Cap_h-0.000000001)),1,0),0) -> 0 | Y205: =SUM(C205:M205) -> 3 | Z205: =SUM(N205:X205) -> 3 | AA205: =INDEX($C$3:$M$3,MATCH(1,C205:M205,0)) -> 0 | AB205: =INDEX($N$3:$X$3,MATCH(1,N205:X205,0))+(Z205-1)*Step_h -> 0.5

Sheet BestRule
A1: One Bellman step on the best rule's values: decision values, best decisions, the residual and the guardrail (Definition 14.1; Equation 14.1; Proposition 14.2(ii); Worked Example 14.1, Step 1; AXIOM Lab 2.14, step 1)
A2: Column B is the engine's values of the best rule (policy iteration, exact). G = the sum of p_w V(node - w/step) at each node; Q(c, h) = -k h - p (55 - c)^+ + beta [(1 - t) G(j) + t G(j + 1)] where 0.975c + h = 30 + (j + t) x step: the value of deciding h at c and acting best afterwards. A residual near zero certifies the values, and the best decisions are the rule.
D3: hire h: | E3: =Grid!C3 -> 0 | F3: =Grid!D3 -> 0.25 | G3: =Grid!E3 -> 0.5 | H3: =Grid!F3 -> 0.75 | I3: =Grid!G3 -> 1 | J3: =Grid!H3 -> 1.25 | K3: =Grid!I3 -> 1.5 | L3: =Grid!J3 -> 1.75 | ... O3: =Grid!M3 -> 2.5 | Z3: The best rule on the agent's grid | AA3: Value | AB3: Book
A4: c | B4: V*(c) (engine) | C4: Node | D4: G at the node | E4: Q(c, 0) | F4: Q(c, 0.25) | G4: Q(c, 0.5) | H4: Q(c, 0.75) | I4: Q(c, 1) | J4: Q(c, 1.25) | K4: Q(c, 1.5) | L4: Q(c, 1.75) | M4: Q(c, 2) | N4: Q(c, 2.25) | O4: Q(c, 2.5) | P4: Best value, max Q | Q4: Best hire (formula) | R4: Engine's hire | S4: Same (1 = yes) | T4: |max Q - V*| | U4: Planned 0.975c + h | V4: In the guardrail (1 = yes) | W4: Long-run share (engine) | Z4: Cost from 58: minus the best value at 58 | AA4: =-INDEX(P5:P205,MATCH(Start_c,$A$5:$A$205,0)) -> 231.1784 | AB4: 231.18
A5: =Grid!A5 -> 30 | B5: -611.53872 | C5: 0 | D5: =IF(AND($C5>=6,$C5<=194),Declarations!$B$25*INDEX($B$5:$B$205,$C5+1-Declarations!$E$25)+Declarations!$B$26*INDEX($B$5:$B$205,$C5+1-Declarations!$E$26)+Declarations!$B$27*INDEX($B$5:$B$205,$C5+1-Declarations!$E$27)+Declarations!$B$28*INDEX($B$5:$B$205,$C5+1-Declarations!$E$28)+Declarations!$B$29*INDEX($B$5:$B$205,$C5+1-Declarations!$E$29),"") | E5: =IF(Grid!C5=1,-Cost_k*E$3-Short_p*MAX(0,Floor_c-$A5)+Beta_q*((1-(((Alpha_keep*$A5+E$3-Lo_c)/Step_c)-MAX(6,MIN(INT(((Alpha_keep*$A5+E$3-Lo_c)/Step_c)+0.00000001),193))))*INDEX($D$5:$D$205,MAX(6,MIN(INT(((Alpha_keep*$A5+E$3-Lo_c)/Step_c)+0.00000001),193))+1)+(((Alpha_keep*$A5+E$3-Lo_c)/Step_c)-MAX(6,MIN(INT(((Alpha_keep*$A5+E$3-Lo_c)/Step_c)+0.00000001),193)))*INDEX($D$5:$D$205,MAX(6,MIN(INT(((Alpha_keep*$A5+E$3-Lo_c)/Step_c)+0.00000001),193))+2)),"") | F5: =IF(Grid!D5=1,-Cost_k*F$3-Short_p*MAX(0,Floor_c-$A5)+Beta_q*((1-(((Alpha_keep*$A5+F$3-Lo_c)/Step_c)-MAX(6,MIN(INT(((Alpha_keep*$A5+F$3-Lo_c)/Step_c)+0.00000001),193))))*INDEX($D$5:$D$205,MAX(6,MIN(INT(((Alpha_keep*$A5+F$3-Lo_c)/Step_c)+0.00000001),193))+1)+(((Alpha_keep*$A5+F$3-Lo_c)/Step_c)-MAX(6,MIN(INT(((Alpha_keep*$A5+F$3-Lo_c)/Step_c)+0.00000001),193)))*INDEX($D$5:$D$205,MAX(6,MIN(INT(((Alpha_keep*$A5+F$3-Lo_c)/Step_c)+0.00000001),193))+2)),"") | G5: =IF(Grid!E5=1,-Cost_k*G$3-Short_p*MAX(0,Floor_c-$A5)+Beta_q*((1-(((Alpha_keep*$A5+G$3-Lo_c)/Step_c)-MAX(6,MIN(INT(((Alpha_keep*$A5+G$3-Lo_c)/Step_c)+0.00000001),193))))*INDEX($D$5:$D$205,MAX(6,MIN(INT(((Alpha_keep*$A5+G$3-Lo_c)/Step_c)+0.00000001),193))+1)+(((Alpha_keep*$A5+G$3-Lo_c)/Step_c)-MAX(6,MIN(INT(((Alpha_keep*$A5+G$3-Lo_c)/Step_c)+0.00000001),193)))*INDEX($D$5:$D$205,MAX(6,MIN(INT(((Alpha_keep*$A5+G$3-Lo_c)/Step_c)+0.00000001),193))+2)),"") | H5: =IF(Grid!F5=1,-Cost_k*H$3-Short_p*MAX(0,Floor_c-$A5)+Beta_q*((1-(((Alpha_keep*$A5+H$3-Lo_c)/Step_c)-MAX(6,MIN(INT(((Alpha_keep*$A5+H$3-Lo_c)/Step_c)+0.00000001),193))))*INDEX($D$5:$D$205,MAX(6,MIN(INT(((Alpha_keep*$A5+H$3-Lo_c)/Step_c)+0.00000001),193))+1)+(((Alpha_keep*$A5+H$3-Lo_c)/Step_c)-MAX(6,MIN(INT(((Alpha_keep*$A5+H$3-Lo_c)/Step_c)+0.00000001),193)))*INDEX($D$5:$D$205,MAX(6,MIN(INT(((Alpha_keep*$A5+H$3-Lo_c)/Step_c)+0.00000001),193))+2)),"") | I5: =IF(Grid!G5=1,-Cost_k*I$3-Short_p*MAX(0,Floor_c-$A5)+Beta_q*((1-(((Alpha_keep*$A5+I$3-Lo_c)/Step_c)-MAX(6,MIN(INT(((Alpha_keep*$A5+I$3-Lo_c)/Step_c)+0.00000001),193))))*INDEX($D$5:$D$205,MAX(6,MIN(INT(((Alpha_keep*$A5+I$3-Lo_c)/Step_c)+0.00000001),193))+1)+(((Alpha_keep*$A5+I$3-Lo_c)/Step_c)-MAX(6,MIN(INT(((Alpha_keep*$A5+I$3-Lo_c)/Step_c)+0.00000001),193)))*INDEX($D$5:$D$205,MAX(6,MIN(INT(((Alpha_keep*$A5+I$3-Lo_c)/Step_c)+0.00000001),193))+2)),"") | J5: =IF(Grid!H5=1,-Cost_k*J$3-Short_p*MAX(0,Floor_c-$A5)+Beta_q*((1-(((Alpha_keep*$A5+J$3-Lo_c)/Step_c)-MAX(6,MIN(INT(((Alpha_keep*$A5+J$3-Lo_c)/Step_c)+0.00000001),193))))*INDEX($D$5:$D$205,MAX(6,MIN(INT(((Alpha_keep*$A5+J$3-Lo_c)/Step_c)+0.00000001),193))+1)+(((Alpha_keep*$A5+J$3-Lo_c)/Step_c)-MAX(6,MIN(INT(((Alpha_keep*$A5+J$3-Lo_c)/Step_c)+0.00000001),193)))*INDEX($D$5:$D$205,MAX(6,MIN(INT(((Alpha_keep*$A5+J$3-Lo_c)/Step_c)+0.00000001),193))+2)),"") | K5: =IF(Grid!I5=1,-Cost_k*K$3-Short_p*MAX(0,Floor_c-$A5)+Beta_q*((1-(((Alpha_keep*$A5+K$3-Lo_c)/Step_c)-MAX(6,MIN(INT(((Alpha_keep*$A5+K$3-Lo_c)/Step_c)+0.00000001),193))))*INDEX($D$5:$D$205,MAX(6,MIN(INT(((Alpha_keep*$A5+K$3-Lo_c)/Step_c)+0.00000001),193))+1)+(((Alpha_keep*$A5+K$3-Lo_c)/Step_c)-MAX(6,MIN(INT(((Alpha_keep*$A5+K$3-Lo_c)/Step_c)+0.00000001),193)))*INDEX($D$5:$D$205,MAX(6,MIN(INT(((Alpha_keep*$A5+K$3-Lo_c)/Step_c)+0.00000001),193))+2)),"") | L5: =IF(Grid!J5=1,-Cost_k*L$3-Short_p*MAX(0,Floor_c-$A5)+Beta_q*((1-(((Alpha_keep*$A5+L$3-Lo_c)/Step_c)-MAX(6,MIN(INT(((Alpha_keep*$A5+L$3-Lo_c)/Step_c)+0.00000001),193))))*INDEX($D$5:$D$205,MAX(6,MIN(INT(((Alpha_keep*$A5+L$3-Lo_c)/Step_c)+0.00000001),193))+1)+(((Alpha_keep*$A5+L$3-Lo_c)/Step_c)-MAX(6,MIN(INT(((Alpha_keep*$A5+L$3-Lo_c)/Step_c)+0.00000001),193)))*INDEX($D$5:$D$205,MAX(6,MIN(INT(((Alpha_keep*$A5+L$3-Lo_c)/Step_c)+0.00000001),193))+2)),"") | ... O5: =IF(Grid!M5=1,-Cost_k*O$3-Short_p*MAX(0,Floor_c-$A5)+Beta_q*((1-(((Alpha_keep*$A5+O$3-Lo_c)/Step_c)-MAX(6,MIN(INT(((Alpha_keep*$A5+O$3-Lo_c)/Step_c)+0.00000001),193))))*INDEX($D$5:$D$205,MAX(6,MIN(INT(((Alpha_keep*$A5+O$3-Lo_c)/Step_c)+0.00000001),193))+1)+(((Alpha_keep*$A5+O$3-Lo_c)/Step_c)-MAX(6,MIN(INT(((Alpha_keep*$A5+O$3-Lo_c)/Step_c)+0.00000001),193)))*INDEX($D$5:$D$205,MAX(6,MIN(INT(((Alpha_keep*$A5+O$3-Lo_c)/Step_c)+0.00000001),193))+2)),"") -> -611.53872 | P5: =MAX(E5:O5) -> -611.53872 | Q5: =INDEX($E$3:$O$3,MATCH(P5,E5:O5,0)) -> 2.5 | R5: 2.5 | S5: =IF(ABS(Q5-R5)<0.000000001,1,0) -> 1 | T5: =ABS(P5-B5) -> 0 | U5: =Alpha_keep*A5+Q5 -> 31.75 | V5: =INDEX(GuardBlock,1,ROUND(Q5/Step_h,0)+1) -> 1 | W5: 0 | Z5: Above Chapter 7's 230.755 (hires in quarter-points) | AA5: =AA4-Ch7_cost -> 0.4233985 | AB5: 0.42
A6: =Grid!A6 -> 30.25 | B6: -606.25398 | C6: 1 | D6: =IF(AND($C6>=6,$C6<=194),Declarations!$B$25*INDEX($B$5:$B$205,$C6+1-Declarations!$E$25)+Declarations!$B$26*INDEX($B$5:$B$205,$C6+1-Declarations!$E$26)+Declarations!$B$27*INDEX($B$5:$B$205,$C6+1-Declarations!$E$27)+Declarations!$B$28*INDEX($B$5:$B$205,$C6+1-Declarations!$E$28)+Declarations!$B$29*INDEX($B$5:$B$205,$C6+1-Declarations!$E$29),"") | E6: =IF(Grid!C6=1,-Cost_k*E$3-Short_p*MAX(0,Floor_c-$A6)+Beta_q*((1-(((Alpha_keep*$A6+E$3-Lo_c)/Step_c)-MAX(6,MIN(INT(((Alpha_keep*$A6+E$3-Lo_c)/Step_c)+0.00000001),193))))*INDEX($D$5:$D$205,MAX(6,MIN(INT(((Alpha_keep*$A6+E$3-Lo_c)/Step_c)+0.00000001),193))+1)+(((Alpha_keep*$A6+E$3-Lo_c)/Step_c)-MAX(6,MIN(INT(((Alpha_keep*$A6+E$3-Lo_c)/Step_c)+0.00000001),193)))*INDEX($D$5:$D$205,MAX(6,MIN(INT(((Alpha_keep*$A6+E$3-Lo_c)/Step_c)+0.00000001),193))+2)),"") | F6: =IF(Grid!D6=1,-Cost_k*F$3-Short_p*MAX(0,Floor_c-$A6)+Beta_q*((1-(((Alpha_keep*$A6+F$3-Lo_c)/Step_c)-MAX(6,MIN(INT(((Alpha_keep*$A6+F$3-Lo_c)/Step_c)+0.00000001),193))))*INDEX($D$5:$D$205,MAX(6,MIN(INT(((Alpha_keep*$A6+F$3-Lo_c)/Step_c)+0.00000001),193))+1)+(((Alpha_keep*$A6+F$3-Lo_c)/Step_c)-MAX(6,MIN(INT(((Alpha_keep*$A6+F$3-Lo_c)/Step_c)+0.00000001),193)))*INDEX($D$5:$D$205,MAX(6,MIN(INT(((Alpha_keep*$A6+F$3-Lo_c)/Step_c)+0.00000001),193))+2)),"") | G6: =IF(Grid!E6=1,-Cost_k*G$3-Short_p*MAX(0,Floor_c-$A6)+Beta_q*((1-(((Alpha_keep*$A6+G$3-Lo_c)/Step_c)-MAX(6,MIN(INT(((Alpha_keep*$A6+G$3-Lo_c)/Step_c)+0.00000001),193))))*INDEX($D$5:$D$205,MAX(6,MIN(INT(((Alpha_keep*$A6+G$3-Lo_c)/Step_c)+0.00000001),193))+1)+(((Alpha_keep*$A6+G$3-Lo_c)/Step_c)-MAX(6,MIN(INT(((Alpha_keep*$A6+G$3-Lo_c)/Step_c)+0.00000001),193)))*INDEX($D$5:$D$205,MAX(6,MIN(INT(((Alpha_keep*$A6+G$3-Lo_c)/Step_c)+0.00000001),193))+2)),"") | H6: =IF(Grid!F6=1,-Cost_k*H$3-Short_p*MAX(0,Floor_c-$A6)+Beta_q*((1-(((Alpha_keep*$A6+H$3-Lo_c)/Step_c)-MAX(6,MIN(INT(((Alpha_keep*$A6+H$3-Lo_c)/Step_c)+0.00000001),193))))*INDEX($D$5:$D$205,MAX(6,MIN(INT(((Alpha_keep*$A6+H$3-Lo_c)/Step_c)+0.00000001),193))+1)+(((Alpha_keep*$A6+H$3-Lo_c)/Step_c)-MAX(6,MIN(INT(((Alpha_keep*$A6+H$3-Lo_c)/Step_c)+0.00000001),193)))*INDEX($D$5:$D$205,MAX(6,MIN(INT(((Alpha_keep*$A6+H$3-Lo_c)/Step_c)+0.00000001),193))+2)),"") | I6: =IF(Grid!G6=1,-Cost_k*I$3-Short_p*MAX(0,Floor_c-$A6)+Beta_q*((1-(((Alpha_keep*$A6+I$3-Lo_c)/Step_c)-MAX(6,MIN(INT(((Alpha_keep*$A6+I$3-Lo_c)/Step_c)+0.00000001),193))))*INDEX($D$5:$D$205,MAX(6,MIN(INT(((Alpha_keep*$A6+I$3-Lo_c)/Step_c)+0.00000001),193))+1)+(((Alpha_keep*$A6+I$3-Lo_c)/Step_c)-MAX(6,MIN(INT(((Alpha_keep*$A6+I$3-Lo_c)/Step_c)+0.00000001),193)))*INDEX($D$5:$D$205,MAX(6,MIN(INT(((Alpha_keep*$A6+I$3-Lo_c)/Step_c)+0.00000001),193))+2)),"") | J6: =IF(Grid!H6=1,-Cost_k*J$3-Short_p*MAX(0,Floor_c-$A6)+Beta_q*((1-(((Alpha_keep*$A6+J$3-Lo_c)/Step_c)-MAX(6,MIN(INT(((Alpha_keep*$A6+J$3-Lo_c)/Step_c)+0.00000001),193))))*INDEX($D$5:$D$205,MAX(6,MIN(INT(((Alpha_keep*$A6+J$3-Lo_c)/Step_c)+0.00000001),193))+1)+(((Alpha_keep*$A6+J$3-Lo_c)/Step_c)-MAX(6,MIN(INT(((Alpha_keep*$A6+J$3-Lo_c)/Step_c)+0.00000001),193)))*INDEX($D$5:$D$205,MAX(6,MIN(INT(((Alpha_keep*$A6+J$3-Lo_c)/Step_c)+0.00000001),193))+2)),"") | K6: =IF(Grid!I6=1,-Cost_k*K$3-Short_p*MAX(0,Floor_c-$A6)+Beta_q*((1-(((Alpha_keep*$A6+K$3-Lo_c)/Step_c)-MAX(6,MIN(INT(((Alpha_keep*$A6+K$3-Lo_c)/Step_c)+0.00000001),193))))*INDEX($D$5:$D$205,MAX(6,MIN(INT(((Alpha_keep*$A6+K$3-Lo_c)/Step_c)+0.00000001),193))+1)+(((Alpha_keep*$A6+K$3-Lo_c)/Step_c)-MAX(6,MIN(INT(((Alpha_keep*$A6+K$3-Lo_c)/Step_c)+0.00000001),193)))*INDEX($D$5:$D$205,MAX(6,MIN(INT(((Alpha_keep*$A6+K$3-Lo_c)/Step_c)+0.00000001),193))+2)),"") | L6: =IF(Grid!J6=1,-Cost_k*L$3-Short_p*MAX(0,Floor_c-$A6)+Beta_q*((1-(((Alpha_keep*$A6+L$3-Lo_c)/Step_c)-MAX(6,MIN(INT(((Alpha_keep*$A6+L$3-Lo_c)/Step_c)+0.00000001),193))))*INDEX($D$5:$D$205,MAX(6,MIN(INT(((Alpha_keep*$A6+L$3-Lo_c)/Step_c)+0.00000001),193))+1)+(((Alpha_keep*$A6+L$3-Lo_c)/Step_c)-MAX(6,MIN(INT(((Alpha_keep*$A6+L$3-Lo_c)/Step_c)+0.00000001),193)))*INDEX($D$5:$D$205,MAX(6,MIN(INT(((Alpha_keep*$A6+L$3-Lo_c)/Step_c)+0.00000001),193))+2)),"") | ... O6: =IF(Grid!M6=1,-Cost_k*O$3-Short_p*MAX(0,Floor_c-$A6)+Beta_q*((1-(((Alpha_keep*$A6+O$3-Lo_c)/Step_c)-MAX(6,MIN(INT(((Alpha_keep*$A6+O$3-Lo_c)/Step_c)+0.00000001),193))))*INDEX($D$5:$D$205,MAX(6,MIN(INT(((Alpha_keep*$A6+O$3-Lo_c)/Step_c)+0.00000001),193))+1)+(((Alpha_keep*$A6+O$3-Lo_c)/Step_c)-MAX(6,MIN(INT(((Alpha_keep*$A6+O$3-Lo_c)/Step_c)+0.00000001),193)))*INDEX($D$5:$D$205,MAX(6,MIN(INT(((Alpha_keep*$A6+O$3-Lo_c)/Step_c)+0.00000001),193))+2)),"") -> -606.25398 | P6: =MAX(E6:O6) -> -606.25398 | Q6: =INDEX($E$3:$O$3,MATCH(P6,E6:O6,0)) -> 2.5 | R6: 2.5 | S6: =IF(ABS(Q6-R6)<0.000000001,1,0) -> 1 | T6: =ABS(P6-B6) -> 0 | U6: =Alpha_keep*A6+Q6 -> 31.99375 | V6: =INDEX(GuardBlock,2,ROUND(Q6/Step_h,0)+1) -> 1 | W6: 0 | Z6: Largest Bellman residual at the 201 levels | AA6: =MAX(T5:T205) -> 0 | AB6: Values within residual/(1 - beta) of the best
A7: =Grid!A7 -> 30.5 | B7: -600.99042 | C7: 2 | D7: =IF(AND($C7>=6,$C7<=194),Declarations!$B$25*INDEX($B$5:$B$205,$C7+1-Declarations!$E$25)+Declarations!$B$26*INDEX($B$5:$B$205,$C7+1-Declarations!$E$26)+Declarations!$B$27*INDEX($B$5:$B$205,$C7+1-Declarations!$E$27)+Declarations!$B$28*INDEX($B$5:$B$205,$C7+1-Declarations!$E$28)+Declarations!$B$29*INDEX($B$5:$B$205,$C7+1-Declarations!$E$29),"") | E7: =IF(Grid!C7=1,-Cost_k*E$3-Short_p*MAX(0,Floor_c-$A7)+Beta_q*((1-(((Alpha_keep*$A7+E$3-Lo_c)/Step_c)-MAX(6,MIN(INT(((Alpha_keep*$A7+E$3-Lo_c)/Step_c)+0.00000001),193))))*INDEX($D$5:$D$205,MAX(6,MIN(INT(((Alpha_keep*$A7+E$3-Lo_c)/Step_c)+0.00000001),193))+1)+(((Alpha_keep*$A7+E$3-Lo_c)/Step_c)-MAX(6,MIN(INT(((Alpha_keep*$A7+E$3-Lo_c)/Step_c)+0.00000001),193)))*INDEX($D$5:$D$205,MAX(6,MIN(INT(((Alpha_keep*$A7+E$3-Lo_c)/Step_c)+0.00000001),193))+2)),"") | F7: =IF(Grid!D7=1,-Cost_k*F$3-Short_p*MAX(0,Floor_c-$A7)+Beta_q*((1-(((Alpha_keep*$A7+F$3-Lo_c)/Step_c)-MAX(6,MIN(INT(((Alpha_keep*$A7+F$3-Lo_c)/Step_c)+0.00000001),193))))*INDEX($D$5:$D$205,MAX(6,MIN(INT(((Alpha_keep*$A7+F$3-Lo_c)/Step_c)+0.00000001),193))+1)+(((Alpha_keep*$A7+F$3-Lo_c)/Step_c)-MAX(6,MIN(INT(((Alpha_keep*$A7+F$3-Lo_c)/Step_c)+0.00000001),193)))*INDEX($D$5:$D$205,MAX(6,MIN(INT(((Alpha_keep*$A7+F$3-Lo_c)/Step_c)+0.00000001),193))+2)),"") | G7: =IF(Grid!E7=1,-Cost_k*G$3-Short_p*MAX(0,Floor_c-$A7)+Beta_q*((1-(((Alpha_keep*$A7+G$3-Lo_c)/Step_c)-MAX(6,MIN(INT(((Alpha_keep*$A7+G$3-Lo_c)/Step_c)+0.00000001),193))))*INDEX($D$5:$D$205,MAX(6,MIN(INT(((Alpha_keep*$A7+G$3-Lo_c)/Step_c)+0.00000001),193))+1)+(((Alpha_keep*$A7+G$3-Lo_c)/Step_c)-MAX(6,MIN(INT(((Alpha_keep*$A7+G$3-Lo_c)/Step_c)+0.00000001),193)))*INDEX($D$5:$D$205,MAX(6,MIN(INT(((Alpha_keep*$A7+G$3-Lo_c)/Step_c)+0.00000001),193))+2)),"") | H7: =IF(Grid!F7=1,-Cost_k*H$3-Short_p*MAX(0,Floor_c-$A7)+Beta_q*((1-(((Alpha_keep*$A7+H$3-Lo_c)/Step_c)-MAX(6,MIN(INT(((Alpha_keep*$A7+H$3-Lo_c)/Step_c)+0.00000001),193))))*INDEX($D$5:$D$205,MAX(6,MIN(INT(((Alpha_keep*$A7+H$3-Lo_c)/Step_c)+0.00000001),193))+1)+(((Alpha_keep*$A7+H$3-Lo_c)/Step_c)-MAX(6,MIN(INT(((Alpha_keep*$A7+H$3-Lo_c)/Step_c)+0.00000001),193)))*INDEX($D$5:$D$205,MAX(6,MIN(INT(((Alpha_keep*$A7+H$3-Lo_c)/Step_c)+0.00000001),193))+2)),"") | I7: =IF(Grid!G7=1,-Cost_k*I$3-Short_p*MAX(0,Floor_c-$A7)+Beta_q*((1-(((Alpha_keep*$A7+I$3-Lo_c)/Step_c)-MAX(6,MIN(INT(((Alpha_keep*$A7+I$3-Lo_c)/Step_c)+0.00000001),193))))*INDEX($D$5:$D$205,MAX(6,MIN(INT(((Alpha_keep*$A7+I$3-Lo_c)/Step_c)+0.00000001),193))+1)+(((Alpha_keep*$A7+I$3-Lo_c)/Step_c)-MAX(6,MIN(INT(((Alpha_keep*$A7+I$3-Lo_c)/Step_c)+0.00000001),193)))*INDEX($D$5:$D$205,MAX(6,MIN(INT(((Alpha_keep*$A7+I$3-Lo_c)/Step_c)+0.00000001),193))+2)),"") | J7: =IF(Grid!H7=1,-Cost_k*J$3-Short_p*MAX(0,Floor_c-$A7)+Beta_q*((1-(((Alpha_keep*$A7+J$3-Lo_c)/Step_c)-MAX(6,MIN(INT(((Alpha_keep*$A7+J$3-Lo_c)/Step_c)+0.00000001),193))))*INDEX($D$5:$D$205,MAX(6,MIN(INT(((Alpha_keep*$A7+J$3-Lo_c)/Step_c)+0.00000001),193))+1)+(((Alpha_keep*$A7+J$3-Lo_c)/Step_c)-MAX(6,MIN(INT(((Alpha_keep*$A7+J$3-Lo_c)/Step_c)+0.00000001),193)))*INDEX($D$5:$D$205,MAX(6,MIN(INT(((Alpha_keep*$A7+J$3-Lo_c)/Step_c)+0.00000001),193))+2)),"") | K7: =IF(Grid!I7=1,-Cost_k*K$3-Short_p*MAX(0,Floor_c-$A7)+Beta_q*((1-(((Alpha_keep*$A7+K$3-Lo_c)/Step_c)-MAX(6,MIN(INT(((Alpha_keep*$A7+K$3-Lo_c)/Step_c)+0.00000001),193))))*INDEX($D$5:$D$205,MAX(6,MIN(INT(((Alpha_keep*$A7+K$3-Lo_c)/Step_c)+0.00000001),193))+1)+(((Alpha_keep*$A7+K$3-Lo_c)/Step_c)-MAX(6,MIN(INT(((Alpha_keep*$A7+K$3-Lo_c)/Step_c)+0.00000001),193)))*INDEX($D$5:$D$205,MAX(6,MIN(INT(((Alpha_keep*$A7+K$3-Lo_c)/Step_c)+0.00000001),193))+2)),"") | L7: =IF(Grid!J7=1,-Cost_k*L$3-Short_p*MAX(0,Floor_c-$A7)+Beta_q*((1-(((Alpha_keep*$A7+L$3-Lo_c)/Step_c)-MAX(6,MIN(INT(((Alpha_keep*$A7+L$3-Lo_c)/Step_c)+0.00000001),193))))*INDEX($D$5:$D$205,MAX(6,MIN(INT(((Alpha_keep*$A7+L$3-Lo_c)/Step_c)+0.00000001),193))+1)+(((Alpha_keep*$A7+L$3-Lo_c)/Step_c)-MAX(6,MIN(INT(((Alpha_keep*$A7+L$3-Lo_c)/Step_c)+0.00000001),193)))*INDEX($D$5:$D$205,MAX(6,MIN(INT(((Alpha_keep*$A7+L$3-Lo_c)/Step_c)+0.00000001),193))+2)),"") | ... O7: =IF(Grid!M7=1,-Cost_k*O$3-Short_p*MAX(0,Floor_c-$A7)+Beta_q*((1-(((Alpha_keep*$A7+O$3-Lo_c)/Step_c)-MAX(6,MIN(INT(((Alpha_keep*$A7+O$3-Lo_c)/Step_c)+0.00000001),193))))*INDEX($D$5:$D$205,MAX(6,MIN(INT(((Alpha_keep*$A7+O$3-Lo_c)/Step_c)+0.00000001),193))+1)+(((Alpha_keep*$A7+O$3-Lo_c)/Step_c)-MAX(6,MIN(INT(((Alpha_keep*$A7+O$3-Lo_c)/Step_c)+0.00000001),193)))*INDEX($D$5:$D$205,MAX(6,MIN(INT(((Alpha_keep*$A7+O$3-Lo_c)/Step_c)+0.00000001),193))+2)),"") -> -600.99042 | P7: =MAX(E7:O7) -> -600.99042 | Q7: =INDEX($E$3:$O$3,MATCH(P7,E7:O7,0)) -> 2.5 | R7: 2.5 | S7: =IF(ABS(Q7-R7)<0.000000001,1,0) -> 1 | T7: =ABS(P7-B7) -> 0 | U7: =Alpha_keep*A7+Q7 -> 32.2375 | V7: =INDEX(GuardBlock,3,ROUND(Q7/Step_h,0)+1) -> 1 | W7: 0 | Z7: Levels where the formulas' best hire is the engine's | AA7: =SUM(S5:S205) -> 201 | AB7: 201
A8: =Grid!A8 -> 30.75 | B8: -595.74826 | C8: 3 | D8: =IF(AND($C8>=6,$C8<=194),Declarations!$B$25*INDEX($B$5:$B$205,$C8+1-Declarations!$E$25)+Declarations!$B$26*INDEX($B$5:$B$205,$C8+1-Declarations!$E$26)+Declarations!$B$27*INDEX($B$5:$B$205,$C8+1-Declarations!$E$27)+Declarations!$B$28*INDEX($B$5:$B$205,$C8+1-Declarations!$E$28)+Declarations!$B$29*INDEX($B$5:$B$205,$C8+1-Declarations!$E$29),"") | E8: =IF(Grid!C8=1,-Cost_k*E$3-Short_p*MAX(0,Floor_c-$A8)+Beta_q*((1-(((Alpha_keep*$A8+E$3-Lo_c)/Step_c)-MAX(6,MIN(INT(((Alpha_keep*$A8+E$3-Lo_c)/Step_c)+0.00000001),193))))*INDEX($D$5:$D$205,MAX(6,MIN(INT(((Alpha_keep*$A8+E$3-Lo_c)/Step_c)+0.00000001),193))+1)+(((Alpha_keep*$A8+E$3-Lo_c)/Step_c)-MAX(6,MIN(INT(((Alpha_keep*$A8+E$3-Lo_c)/Step_c)+0.00000001),193)))*INDEX($D$5:$D$205,MAX(6,MIN(INT(((Alpha_keep*$A8+E$3-Lo_c)/Step_c)+0.00000001),193))+2)),"") | F8: =IF(Grid!D8=1,-Cost_k*F$3-Short_p*MAX(0,Floor_c-$A8)+Beta_q*((1-(((Alpha_keep*$A8+F$3-Lo_c)/Step_c)-MAX(6,MIN(INT(((Alpha_keep*$A8+F$3-Lo_c)/Step_c)+0.00000001),193))))*INDEX($D$5:$D$205,MAX(6,MIN(INT(((Alpha_keep*$A8+F$3-Lo_c)/Step_c)+0.00000001),193))+1)+(((Alpha_keep*$A8+F$3-Lo_c)/Step_c)-MAX(6,MIN(INT(((Alpha_keep*$A8+F$3-Lo_c)/Step_c)+0.00000001),193)))*INDEX($D$5:$D$205,MAX(6,MIN(INT(((Alpha_keep*$A8+F$3-Lo_c)/Step_c)+0.00000001),193))+2)),"") | G8: =IF(Grid!E8=1,-Cost_k*G$3-Short_p*MAX(0,Floor_c-$A8)+Beta_q*((1-(((Alpha_keep*$A8+G$3-Lo_c)/Step_c)-MAX(6,MIN(INT(((Alpha_keep*$A8+G$3-Lo_c)/Step_c)+0.00000001),193))))*INDEX($D$5:$D$205,MAX(6,MIN(INT(((Alpha_keep*$A8+G$3-Lo_c)/Step_c)+0.00000001),193))+1)+(((Alpha_keep*$A8+G$3-Lo_c)/Step_c)-MAX(6,MIN(INT(((Alpha_keep*$A8+G$3-Lo_c)/Step_c)+0.00000001),193)))*INDEX($D$5:$D$205,MAX(6,MIN(INT(((Alpha_keep*$A8+G$3-Lo_c)/Step_c)+0.00000001),193))+2)),"") | H8: =IF(Grid!F8=1,-Cost_k*H$3-Short_p*MAX(0,Floor_c-$A8)+Beta_q*((1-(((Alpha_keep*$A8+H$3-Lo_c)/Step_c)-MAX(6,MIN(INT(((Alpha_keep*$A8+H$3-Lo_c)/Step_c)+0.00000001),193))))*INDEX($D$5:$D$205,MAX(6,MIN(INT(((Alpha_keep*$A8+H$3-Lo_c)/Step_c)+0.00000001),193))+1)+(((Alpha_keep*$A8+H$3-Lo_c)/Step_c)-MAX(6,MIN(INT(((Alpha_keep*$A8+H$3-Lo_c)/Step_c)+0.00000001),193)))*INDEX($D$5:$D$205,MAX(6,MIN(INT(((Alpha_keep*$A8+H$3-Lo_c)/Step_c)+0.00000001),193))+2)),"") | I8: =IF(Grid!G8=1,-Cost_k*I$3-Short_p*MAX(0,Floor_c-$A8)+Beta_q*((1-(((Alpha_keep*$A8+I$3-Lo_c)/Step_c)-MAX(6,MIN(INT(((Alpha_keep*$A8+I$3-Lo_c)/Step_c)+0.00000001),193))))*INDEX($D$5:$D$205,MAX(6,MIN(INT(((Alpha_keep*$A8+I$3-Lo_c)/Step_c)+0.00000001),193))+1)+(((Alpha_keep*$A8+I$3-Lo_c)/Step_c)-MAX(6,MIN(INT(((Alpha_keep*$A8+I$3-Lo_c)/Step_c)+0.00000001),193)))*INDEX($D$5:$D$205,MAX(6,MIN(INT(((Alpha_keep*$A8+I$3-Lo_c)/Step_c)+0.00000001),193))+2)),"") | J8: =IF(Grid!H8=1,-Cost_k*J$3-Short_p*MAX(0,Floor_c-$A8)+Beta_q*((1-(((Alpha_keep*$A8+J$3-Lo_c)/Step_c)-MAX(6,MIN(INT(((Alpha_keep*$A8+J$3-Lo_c)/Step_c)+0.00000001),193))))*INDEX($D$5:$D$205,MAX(6,MIN(INT(((Alpha_keep*$A8+J$3-Lo_c)/Step_c)+0.00000001),193))+1)+(((Alpha_keep*$A8+J$3-Lo_c)/Step_c)-MAX(6,MIN(INT(((Alpha_keep*$A8+J$3-Lo_c)/Step_c)+0.00000001),193)))*INDEX($D$5:$D$205,MAX(6,MIN(INT(((Alpha_keep*$A8+J$3-Lo_c)/Step_c)+0.00000001),193))+2)),"") | K8: =IF(Grid!I8=1,-Cost_k*K$3-Short_p*MAX(0,Floor_c-$A8)+Beta_q*((1-(((Alpha_keep*$A8+K$3-Lo_c)/Step_c)-MAX(6,MIN(INT(((Alpha_keep*$A8+K$3-Lo_c)/Step_c)+0.00000001),193))))*INDEX($D$5:$D$205,MAX(6,MIN(INT(((Alpha_keep*$A8+K$3-Lo_c)/Step_c)+0.00000001),193))+1)+(((Alpha_keep*$A8+K$3-Lo_c)/Step_c)-MAX(6,MIN(INT(((Alpha_keep*$A8+K$3-Lo_c)/Step_c)+0.00000001),193)))*INDEX($D$5:$D$205,MAX(6,MIN(INT(((Alpha_keep*$A8+K$3-Lo_c)/Step_c)+0.00000001),193))+2)),"") | L8: =IF(Grid!J8=1,-Cost_k*L$3-Short_p*MAX(0,Floor_c-$A8)+Beta_q*((1-(((Alpha_keep*$A8+L$3-Lo_c)/Step_c)-MAX(6,MIN(INT(((Alpha_keep*$A8+L$3-Lo_c)/Step_c)+0.00000001),193))))*INDEX($D$5:$D$205,MAX(6,MIN(INT(((Alpha_keep*$A8+L$3-Lo_c)/Step_c)+0.00000001),193))+1)+(((Alpha_keep*$A8+L$3-Lo_c)/Step_c)-MAX(6,MIN(INT(((Alpha_keep*$A8+L$3-Lo_c)/Step_c)+0.00000001),193)))*INDEX($D$5:$D$205,MAX(6,MIN(INT(((Alpha_keep*$A8+L$3-Lo_c)/Step_c)+0.00000001),193))+2)),"") -> -607.71613 | ... O8: =IF(Grid!M8=1,-Cost_k*O$3-Short_p*MAX(0,Floor_c-$A8)+Beta_q*((1-(((Alpha_keep*$A8+O$3-Lo_c)/Step_c)-MAX(6,MIN(INT(((Alpha_keep*$A8+O$3-Lo_c)/Step_c)+0.00000001),193))))*INDEX($D$5:$D$205,MAX(6,MIN(INT(((Alpha_keep*$A8+O$3-Lo_c)/Step_c)+0.00000001),193))+1)+(((Alpha_keep*$A8+O$3-Lo_c)/Step_c)-MAX(6,MIN(INT(((Alpha_keep*$A8+O$3-Lo_c)/Step_c)+0.00000001),193)))*INDEX($D$5:$D$205,MAX(6,MIN(INT(((Alpha_keep*$A8+O$3-Lo_c)/Step_c)+0.00000001),193))+2)),"") -> -595.74826 | P8: =MAX(E8:O8) -> -595.74826 | Q8: =INDEX($E$3:$O$3,MATCH(P8,E8:O8,0)) -> 2.5 | R8: 2.5 | S8: =IF(ABS(Q8-R8)<0.000000001,1,0) -> 1 | T8: =ABS(P8-B8) -> 0 | U8: =Alpha_keep*A8+Q8 -> 32.48125 | V8: =INDEX(GuardBlock,4,ROUND(Q8/Step_h,0)+1) -> 1 | W8: 0 | Z8: Hires at the cap at and below | AA8: =_xlfn.MAXIFS($A$5:$A$205,Q5:Q205,Cap_h) -> 54.75 | AB8: 54.75
A9: =Grid!A9 -> 31 | B9: -590.52772 | C9: 4 | D9: =IF(AND($C9>=6,$C9<=194),Declarations!$B$25*INDEX($B$5:$B$205,$C9+1-Declarations!$E$25)+Declarations!$B$26*INDEX($B$5:$B$205,$C9+1-Declarations!$E$26)+Declarations!$B$27*INDEX($B$5:$B$205,$C9+1-Declarations!$E$27)+Declarations!$B$28*INDEX($B$5:$B$205,$C9+1-Declarations!$E$28)+Declarations!$B$29*INDEX($B$5:$B$205,$C9+1-Declarations!$E$29),"") | E9: =IF(Grid!C9=1,-Cost_k*E$3-Short_p*MAX(0,Floor_c-$A9)+Beta_q*((1-(((Alpha_keep*$A9+E$3-Lo_c)/Step_c)-MAX(6,MIN(INT(((Alpha_keep*$A9+E$3-Lo_c)/Step_c)+0.00000001),193))))*INDEX($D$5:$D$205,MAX(6,MIN(INT(((Alpha_keep*$A9+E$3-Lo_c)/Step_c)+0.00000001),193))+1)+(((Alpha_keep*$A9+E$3-Lo_c)/Step_c)-MAX(6,MIN(INT(((Alpha_keep*$A9+E$3-Lo_c)/Step_c)+0.00000001),193)))*INDEX($D$5:$D$205,MAX(6,MIN(INT(((Alpha_keep*$A9+E$3-Lo_c)/Step_c)+0.00000001),193))+2)),"") | F9: =IF(Grid!D9=1,-Cost_k*F$3-Short_p*MAX(0,Floor_c-$A9)+Beta_q*((1-(((Alpha_keep*$A9+F$3-Lo_c)/Step_c)-MAX(6,MIN(INT(((Alpha_keep*$A9+F$3-Lo_c)/Step_c)+0.00000001),193))))*INDEX($D$5:$D$205,MAX(6,MIN(INT(((Alpha_keep*$A9+F$3-Lo_c)/Step_c)+0.00000001),193))+1)+(((Alpha_keep*$A9+F$3-Lo_c)/Step_c)-MAX(6,MIN(INT(((Alpha_keep*$A9+F$3-Lo_c)/Step_c)+0.00000001),193)))*INDEX($D$5:$D$205,MAX(6,MIN(INT(((Alpha_keep*$A9+F$3-Lo_c)/Step_c)+0.00000001),193))+2)),"") | G9: =IF(Grid!E9=1,-Cost_k*G$3-Short_p*MAX(0,Floor_c-$A9)+Beta_q*((1-(((Alpha_keep*$A9+G$3-Lo_c)/Step_c)-MAX(6,MIN(INT(((Alpha_keep*$A9+G$3-Lo_c)/Step_c)+0.00000001),193))))*INDEX($D$5:$D$205,MAX(6,MIN(INT(((Alpha_keep*$A9+G$3-Lo_c)/Step_c)+0.00000001),193))+1)+(((Alpha_keep*$A9+G$3-Lo_c)/Step_c)-MAX(6,MIN(INT(((Alpha_keep*$A9+G$3-Lo_c)/Step_c)+0.00000001),193)))*INDEX($D$5:$D$205,MAX(6,MIN(INT(((Alpha_keep*$A9+G$3-Lo_c)/Step_c)+0.00000001),193))+2)),"") | H9: =IF(Grid!F9=1,-Cost_k*H$3-Short_p*MAX(0,Floor_c-$A9)+Beta_q*((1-(((Alpha_keep*$A9+H$3-Lo_c)/Step_c)-MAX(6,MIN(INT(((Alpha_keep*$A9+H$3-Lo_c)/Step_c)+0.00000001),193))))*INDEX($D$5:$D$205,MAX(6,MIN(INT(((Alpha_keep*$A9+H$3-Lo_c)/Step_c)+0.00000001),193))+1)+(((Alpha_keep*$A9+H$3-Lo_c)/Step_c)-MAX(6,MIN(INT(((Alpha_keep*$A9+H$3-Lo_c)/Step_c)+0.00000001),193)))*INDEX($D$5:$D$205,MAX(6,MIN(INT(((Alpha_keep*$A9+H$3-Lo_c)/Step_c)+0.00000001),193))+2)),"") | I9: =IF(Grid!G9=1,-Cost_k*I$3-Short_p*MAX(0,Floor_c-$A9)+Beta_q*((1-(((Alpha_keep*$A9+I$3-Lo_c)/Step_c)-MAX(6,MIN(INT(((Alpha_keep*$A9+I$3-Lo_c)/Step_c)+0.00000001),193))))*INDEX($D$5:$D$205,MAX(6,MIN(INT(((Alpha_keep*$A9+I$3-Lo_c)/Step_c)+0.00000001),193))+1)+(((Alpha_keep*$A9+I$3-Lo_c)/Step_c)-MAX(6,MIN(INT(((Alpha_keep*$A9+I$3-Lo_c)/Step_c)+0.00000001),193)))*INDEX($D$5:$D$205,MAX(6,MIN(INT(((Alpha_keep*$A9+I$3-Lo_c)/Step_c)+0.00000001),193))+2)),"") | J9: =IF(Grid!H9=1,-Cost_k*J$3-Short_p*MAX(0,Floor_c-$A9)+Beta_q*((1-(((Alpha_keep*$A9+J$3-Lo_c)/Step_c)-MAX(6,MIN(INT(((Alpha_keep*$A9+J$3-Lo_c)/Step_c)+0.00000001),193))))*INDEX($D$5:$D$205,MAX(6,MIN(INT(((Alpha_keep*$A9+J$3-Lo_c)/Step_c)+0.00000001),193))+1)+(((Alpha_keep*$A9+J$3-Lo_c)/Step_c)-MAX(6,MIN(INT(((Alpha_keep*$A9+J$3-Lo_c)/Step_c)+0.00000001),193)))*INDEX($D$5:$D$205,MAX(6,MIN(INT(((Alpha_keep*$A9+J$3-Lo_c)/Step_c)+0.00000001),193))+2)),"") | K9: =IF(Grid!I9=1,-Cost_k*K$3-Short_p*MAX(0,Floor_c-$A9)+Beta_q*((1-(((Alpha_keep*$A9+K$3-Lo_c)/Step_c)-MAX(6,MIN(INT(((Alpha_keep*$A9+K$3-Lo_c)/Step_c)+0.00000001),193))))*INDEX($D$5:$D$205,MAX(6,MIN(INT(((Alpha_keep*$A9+K$3-Lo_c)/Step_c)+0.00000001),193))+1)+(((Alpha_keep*$A9+K$3-Lo_c)/Step_c)-MAX(6,MIN(INT(((Alpha_keep*$A9+K$3-Lo_c)/Step_c)+0.00000001),193)))*INDEX($D$5:$D$205,MAX(6,MIN(INT(((Alpha_keep*$A9+K$3-Lo_c)/Step_c)+0.00000001),193))+2)),"") -> -606.44193 | L9: =IF(Grid!J9=1,-Cost_k*L$3-Short_p*MAX(0,Floor_c-$A9)+Beta_q*((1-(((Alpha_keep*$A9+L$3-Lo_c)/Step_c)-MAX(6,MIN(INT(((Alpha_keep*$A9+L$3-Lo_c)/Step_c)+0.00000001),193))))*INDEX($D$5:$D$205,MAX(6,MIN(INT(((Alpha_keep*$A9+L$3-Lo_c)/Step_c)+0.00000001),193))+1)+(((Alpha_keep*$A9+L$3-Lo_c)/Step_c)-MAX(6,MIN(INT(((Alpha_keep*$A9+L$3-Lo_c)/Step_c)+0.00000001),193)))*INDEX($D$5:$D$205,MAX(6,MIN(INT(((Alpha_keep*$A9+L$3-Lo_c)/Step_c)+0.00000001),193))+2)),"") -> -602.42973 | ... O9: =IF(Grid!M9=1,-Cost_k*O$3-Short_p*MAX(0,Floor_c-$A9)+Beta_q*((1-(((Alpha_keep*$A9+O$3-Lo_c)/Step_c)-MAX(6,MIN(INT(((Alpha_keep*$A9+O$3-Lo_c)/Step_c)+0.00000001),193))))*INDEX($D$5:$D$205,MAX(6,MIN(INT(((Alpha_keep*$A9+O$3-Lo_c)/Step_c)+0.00000001),193))+1)+(((Alpha_keep*$A9+O$3-Lo_c)/Step_c)-MAX(6,MIN(INT(((Alpha_keep*$A9+O$3-Lo_c)/Step_c)+0.00000001),193)))*INDEX($D$5:$D$205,MAX(6,MIN(INT(((Alpha_keep*$A9+O$3-Lo_c)/Step_c)+0.00000001),193))+2)),"") -> -590.52772 | P9: =MAX(E9:O9) -> -590.52772 | Q9: =INDEX($E$3:$O$3,MATCH(P9,E9:O9,0)) -> 2.5 | R9: 2.5 | S9: =IF(ABS(Q9-R9)<0.000000001,1,0) -> 1 | T9: =ABS(P9-B9) -> 0 | U9: =Alpha_keep*A9+Q9 -> 32.725 | V9: =INDEX(GuardBlock,5,ROUND(Q9/Step_h,0)+1) -> 1 | W9: 0 | Z9: Hires nothing at and above | AA9: =_xlfn.MINIFS($A$5:$A$205,Q5:Q205,0) -> 57.25 | AB9: 57.25
A10: =Grid!A10 -> 31.25 | B10: -585.32905 | C10: 5 | D10: =IF(AND($C10>=6,$C10<=194),Declarations!$B$25*INDEX($B$5:$B$205,$C10+1-Declarations!$E$25)+Declarations!$B$26*INDEX($B$5:$B$205,$C10+1-Declarations!$E$26)+Declarations!$B$27*INDEX($B$5:$B$205,$C10+1-Declarations!$E$27)+Declarations!$B$28*INDEX($B$5:$B$205,$C10+1-Declarations!$E$28)+Declarations!$B$29*INDEX($B$5:$B$205,$C10+1-Declarations!$E$29),"") | E10: =IF(Grid!C10=1,-Cost_k*E$3-Short_p*MAX(0,Floor_c-$A10)+Beta_q*((1-(((Alpha_keep*$A10+E$3-Lo_c)/Step_c)-MAX(6,MIN(INT(((Alpha_keep*$A10+E$3-Lo_c)/Step_c)+0.00000001),193))))*INDEX($D$5:$D$205,MAX(6,MIN(INT(((Alpha_keep*$A10+E$3-Lo_c)/Step_c)+0.00000001),193))+1)+(((Alpha_keep*$A10+E$3-Lo_c)/Step_c)-MAX(6,MIN(INT(((Alpha_keep*$A10+E$3-Lo_c)/Step_c)+0.00000001),193)))*INDEX($D$5:$D$205,MAX(6,MIN(INT(((Alpha_keep*$A10+E$3-Lo_c)/Step_c)+0.00000001),193))+2)),"") | F10: =IF(Grid!D10=1,-Cost_k*F$3-Short_p*MAX(0,Floor_c-$A10)+Beta_q*((1-(((Alpha_keep*$A10+F$3-Lo_c)/Step_c)-MAX(6,MIN(INT(((Alpha_keep*$A10+F$3-Lo_c)/Step_c)+0.00000001),193))))*INDEX($D$5:$D$205,MAX(6,MIN(INT(((Alpha_keep*$A10+F$3-Lo_c)/Step_c)+0.00000001),193))+1)+(((Alpha_keep*$A10+F$3-Lo_c)/Step_c)-MAX(6,MIN(INT(((Alpha_keep*$A10+F$3-Lo_c)/Step_c)+0.00000001),193)))*INDEX($D$5:$D$205,MAX(6,MIN(INT(((Alpha_keep*$A10+F$3-Lo_c)/Step_c)+0.00000001),193))+2)),"") | G10: =IF(Grid!E10=1,-Cost_k*G$3-Short_p*MAX(0,Floor_c-$A10)+Beta_q*((1-(((Alpha_keep*$A10+G$3-Lo_c)/Step_c)-MAX(6,MIN(INT(((Alpha_keep*$A10+G$3-Lo_c)/Step_c)+0.00000001),193))))*INDEX($D$5:$D$205,MAX(6,MIN(INT(((Alpha_keep*$A10+G$3-Lo_c)/Step_c)+0.00000001),193))+1)+(((Alpha_keep*$A10+G$3-Lo_c)/Step_c)-MAX(6,MIN(INT(((Alpha_keep*$A10+G$3-Lo_c)/Step_c)+0.00000001),193)))*INDEX($D$5:$D$205,MAX(6,MIN(INT(((Alpha_keep*$A10+G$3-Lo_c)/Step_c)+0.00000001),193))+2)),"") | H10: =IF(Grid!F10=1,-Cost_k*H$3-Short_p*MAX(0,Floor_c-$A10)+Beta_q*((1-(((Alpha_keep*$A10+H$3-Lo_c)/Step_c)-MAX(6,MIN(INT(((Alpha_keep*$A10+H$3-Lo_c)/Step_c)+0.00000001),193))))*INDEX($D$5:$D$205,MAX(6,MIN(INT(((Alpha_keep*$A10+H$3-Lo_c)/Step_c)+0.00000001),193))+1)+(((Alpha_keep*$A10+H$3-Lo_c)/Step_c)-MAX(6,MIN(INT(((Alpha_keep*$A10+H$3-Lo_c)/Step_c)+0.00000001),193)))*INDEX($D$5:$D$205,MAX(6,MIN(INT(((Alpha_keep*$A10+H$3-Lo_c)/Step_c)+0.00000001),193))+2)),"") | I10: =IF(Grid!G10=1,-Cost_k*I$3-Short_p*MAX(0,Floor_c-$A10)+Beta_q*((1-(((Alpha_keep*$A10+I$3-Lo_c)/Step_c)-MAX(6,MIN(INT(((Alpha_keep*$A10+I$3-Lo_c)/Step_c)+0.00000001),193))))*INDEX($D$5:$D$205,MAX(6,MIN(INT(((Alpha_keep*$A10+I$3-Lo_c)/Step_c)+0.00000001),193))+1)+(((Alpha_keep*$A10+I$3-Lo_c)/Step_c)-MAX(6,MIN(INT(((Alpha_keep*$A10+I$3-Lo_c)/Step_c)+0.00000001),193)))*INDEX($D$5:$D$205,MAX(6,MIN(INT(((Alpha_keep*$A10+I$3-Lo_c)/Step_c)+0.00000001),193))+2)),"") | J10: =IF(Grid!H10=1,-Cost_k*J$3-Short_p*MAX(0,Floor_c-$A10)+Beta_q*((1-(((Alpha_keep*$A10+J$3-Lo_c)/Step_c)-MAX(6,MIN(INT(((Alpha_keep*$A10+J$3-Lo_c)/Step_c)+0.00000001),193))))*INDEX($D$5:$D$205,MAX(6,MIN(INT(((Alpha_keep*$A10+J$3-Lo_c)/Step_c)+0.00000001),193))+1)+(((Alpha_keep*$A10+J$3-Lo_c)/Step_c)-MAX(6,MIN(INT(((Alpha_keep*$A10+J$3-Lo_c)/Step_c)+0.00000001),193)))*INDEX($D$5:$D$205,MAX(6,MIN(INT(((Alpha_keep*$A10+J$3-Lo_c)/Step_c)+0.00000001),193))+2)),"") -> -605.16773 | K10: =IF(Grid!I10=1,-Cost_k*K$3-Short_p*MAX(0,Floor_c-$A10)+Beta_q*((1-(((Alpha_keep*$A10+K$3-Lo_c)/Step_c)-MAX(6,MIN(INT(((Alpha_keep*$A10+K$3-Lo_c)/Step_c)+0.00000001),193))))*INDEX($D$5:$D$205,MAX(6,MIN(INT(((Alpha_keep*$A10+K$3-Lo_c)/Step_c)+0.00000001),193))+1)+(((Alpha_keep*$A10+K$3-Lo_c)/Step_c)-MAX(6,MIN(INT(((Alpha_keep*$A10+K$3-Lo_c)/Step_c)+0.00000001),193)))*INDEX($D$5:$D$205,MAX(6,MIN(INT(((Alpha_keep*$A10+K$3-Lo_c)/Step_c)+0.00000001),193))+2)),"") -> -601.15498 | L10: =IF(Grid!J10=1,-Cost_k*L$3-Short_p*MAX(0,Floor_c-$A10)+Beta_q*((1-(((Alpha_keep*$A10+L$3-Lo_c)/Step_c)-MAX(6,MIN(INT(((Alpha_keep*$A10+L$3-Lo_c)/Step_c)+0.00000001),193))))*INDEX($D$5:$D$205,MAX(6,MIN(INT(((Alpha_keep*$A10+L$3-Lo_c)/Step_c)+0.00000001),193))+1)+(((Alpha_keep*$A10+L$3-Lo_c)/Step_c)-MAX(6,MIN(INT(((Alpha_keep*$A10+L$3-Lo_c)/Step_c)+0.00000001),193)))*INDEX($D$5:$D$205,MAX(6,MIN(INT(((Alpha_keep*$A10+L$3-Lo_c)/Step_c)+0.00000001),193))+2)),"") -> -597.1645 | ... O10: =IF(Grid!M10=1,-Cost_k*O$3-Short_p*MAX(0,Floor_c-$A10)+Beta_q*((1-(((Alpha_keep*$A10+O$3-Lo_c)/Step_c)-MAX(6,MIN(INT(((Alpha_keep*$A10+O$3-Lo_c)/Step_c)+0.00000001),193))))*INDEX($D$5:$D$205,MAX(6,MIN(INT(((Alpha_keep*$A10+O$3-Lo_c)/Step_c)+0.00000001),193))+1)+(((Alpha_keep*$A10+O$3-Lo_c)/Step_c)-MAX(6,MIN(INT(((Alpha_keep*$A10+O$3-Lo_c)/Step_c)+0.00000001),193)))*INDEX($D$5:$D$205,MAX(6,MIN(INT(((Alpha_keep*$A10+O$3-Lo_c)/Step_c)+0.00000001),193))+2)),"") -> -585.32905 | P10: =MAX(E10:O10) -> -585.32905 | Q10: =INDEX($E$3:$O$3,MATCH(P10,E10:O10,0)) -> 2.5 | R10: 2.5 | S10: =IF(ABS(Q10-R10)<0.000000001,1,0) -> 1 | T10: =ABS(P10-B10) -> 0 | U10: =Alpha_keep*A10+Q10 -> 32.96875 | V10: =INDEX(GuardBlock,6,ROUND(Q10/Step_h,0)+1) -> 1 | W10: 0 | Z10: Where it hires below the cap, it plans from | AA10: =_xlfn.MINIFS(U5:U205,Q5:Q205,">0",Q5:Q205,"<"&Cap_h) -> 55.825 | AB10: 55.825
A11: =Grid!A11 -> 31.5 | B11: -580.15247 | C11: 6 | D11: =IF(AND($C11>=6,$C11<=194),Declarations!$B$25*INDEX($B$5:$B$205,$C11+1-Declarations!$E$25)+Declarations!$B$26*INDEX($B$5:$B$205,$C11+1-Declarations!$E$26)+Declarations!$B$27*INDEX($B$5:$B$205,$C11+1-Declarations!$E$27)+Declarations!$B$28*INDEX($B$5:$B$205,$C11+1-Declarations!$E$28)+Declarations!$B$29*INDEX($B$5:$B$205,$C11+1-Declarations!$E$29),"") -> -580.23289 | E11: =IF(Grid!C11=1,-Cost_k*E$3-Short_p*MAX(0,Floor_c-$A11)+Beta_q*((1-(((Alpha_keep*$A11+E$3-Lo_c)/Step_c)-MAX(6,MIN(INT(((Alpha_keep*$A11+E$3-Lo_c)/Step_c)+0.00000001),193))))*INDEX($D$5:$D$205,MAX(6,MIN(INT(((Alpha_keep*$A11+E$3-Lo_c)/Step_c)+0.00000001),193))+1)+(((Alpha_keep*$A11+E$3-Lo_c)/Step_c)-MAX(6,MIN(INT(((Alpha_keep*$A11+E$3-Lo_c)/Step_c)+0.00000001),193)))*INDEX($D$5:$D$205,MAX(6,MIN(INT(((Alpha_keep*$A11+E$3-Lo_c)/Step_c)+0.00000001),193))+2)),"") | F11: =IF(Grid!D11=1,-Cost_k*F$3-Short_p*MAX(0,Floor_c-$A11)+Beta_q*((1-(((Alpha_keep*$A11+F$3-Lo_c)/Step_c)-MAX(6,MIN(INT(((Alpha_keep*$A11+F$3-Lo_c)/Step_c)+0.00000001),193))))*INDEX($D$5:$D$205,MAX(6,MIN(INT(((Alpha_keep*$A11+F$3-Lo_c)/Step_c)+0.00000001),193))+1)+(((Alpha_keep*$A11+F$3-Lo_c)/Step_c)-MAX(6,MIN(INT(((Alpha_keep*$A11+F$3-Lo_c)/Step_c)+0.00000001),193)))*INDEX($D$5:$D$205,MAX(6,MIN(INT(((Alpha_keep*$A11+F$3-Lo_c)/Step_c)+0.00000001),193))+2)),"") | G11: =IF(Grid!E11=1,-Cost_k*G$3-Short_p*MAX(0,Floor_c-$A11)+Beta_q*((1-(((Alpha_keep*$A11+G$3-Lo_c)/Step_c)-MAX(6,MIN(INT(((Alpha_keep*$A11+G$3-Lo_c)/Step_c)+0.00000001),193))))*INDEX($D$5:$D$205,MAX(6,MIN(INT(((Alpha_keep*$A11+G$3-Lo_c)/Step_c)+0.00000001),193))+1)+(((Alpha_keep*$A11+G$3-Lo_c)/Step_c)-MAX(6,MIN(INT(((Alpha_keep*$A11+G$3-Lo_c)/Step_c)+0.00000001),193)))*INDEX($D$5:$D$205,MAX(6,MIN(INT(((Alpha_keep*$A11+G$3-Lo_c)/Step_c)+0.00000001),193))+2)),"") | H11: =IF(Grid!F11=1,-Cost_k*H$3-Short_p*MAX(0,Floor_c-$A11)+Beta_q*((1-(((Alpha_keep*$A11+H$3-Lo_c)/Step_c)-MAX(6,MIN(INT(((Alpha_keep*$A11+H$3-Lo_c)/Step_c)+0.00000001),193))))*INDEX($D$5:$D$205,MAX(6,MIN(INT(((Alpha_keep*$A11+H$3-Lo_c)/Step_c)+0.00000001),193))+1)+(((Alpha_keep*$A11+H$3-Lo_c)/Step_c)-MAX(6,MIN(INT(((Alpha_keep*$A11+H$3-Lo_c)/Step_c)+0.00000001),193)))*INDEX($D$5:$D$205,MAX(6,MIN(INT(((Alpha_keep*$A11+H$3-Lo_c)/Step_c)+0.00000001),193))+2)),"") | I11: =IF(Grid!G11=1,-Cost_k*I$3-Short_p*MAX(0,Floor_c-$A11)+Beta_q*((1-(((Alpha_keep*$A11+I$3-Lo_c)/Step_c)-MAX(6,MIN(INT(((Alpha_keep*$A11+I$3-Lo_c)/Step_c)+0.00000001),193))))*INDEX($D$5:$D$205,MAX(6,MIN(INT(((Alpha_keep*$A11+I$3-Lo_c)/Step_c)+0.00000001),193))+1)+(((Alpha_keep*$A11+I$3-Lo_c)/Step_c)-MAX(6,MIN(INT(((Alpha_keep*$A11+I$3-Lo_c)/Step_c)+0.00000001),193)))*INDEX($D$5:$D$205,MAX(6,MIN(INT(((Alpha_keep*$A11+I$3-Lo_c)/Step_c)+0.00000001),193))+2)),"") -> -603.89353 | J11: =IF(Grid!H11=1,-Cost_k*J$3-Short_p*MAX(0,Floor_c-$A11)+Beta_q*((1-(((Alpha_keep*$A11+J$3-Lo_c)/Step_c)-MAX(6,MIN(INT(((Alpha_keep*$A11+J$3-Lo_c)/Step_c)+0.00000001),193))))*INDEX($D$5:$D$205,MAX(6,MIN(INT(((Alpha_keep*$A11+J$3-Lo_c)/Step_c)+0.00000001),193))+1)+(((Alpha_keep*$A11+J$3-Lo_c)/Step_c)-MAX(6,MIN(INT(((Alpha_keep*$A11+J$3-Lo_c)/Step_c)+0.00000001),193)))*INDEX($D$5:$D$205,MAX(6,MIN(INT(((Alpha_keep*$A11+J$3-Lo_c)/Step_c)+0.00000001),193))+2)),"") -> -599.88023 | K11: =IF(Grid!I11=1,-Cost_k*K$3-Short_p*MAX(0,Floor_c-$A11)+Beta_q*((1-(((Alpha_keep*$A11+K$3-Lo_c)/Step_c)-MAX(6,MIN(INT(((Alpha_keep*$A11+K$3-Lo_c)/Step_c)+0.00000001),193))))*INDEX($D$5:$D$205,MAX(6,MIN(INT(((Alpha_keep*$A11+K$3-Lo_c)/Step_c)+0.00000001),193))+1)+(((Alpha_keep*$A11+K$3-Lo_c)/Step_c)-MAX(6,MIN(INT(((Alpha_keep*$A11+K$3-Lo_c)/Step_c)+0.00000001),193)))*INDEX($D$5:$D$205,MAX(6,MIN(INT(((Alpha_keep*$A11+K$3-Lo_c)/Step_c)+0.00000001),193))+2)),"") -> -595.88919 | L11: =IF(Grid!J11=1,-Cost_k*L$3-Short_p*MAX(0,Floor_c-$A11)+Beta_q*((1-(((Alpha_keep*$A11+L$3-Lo_c)/Step_c)-MAX(6,MIN(INT(((Alpha_keep*$A11+L$3-Lo_c)/Step_c)+0.00000001),193))))*INDEX($D$5:$D$205,MAX(6,MIN(INT(((Alpha_keep*$A11+L$3-Lo_c)/Step_c)+0.00000001),193))+1)+(((Alpha_keep*$A11+L$3-Lo_c)/Step_c)-MAX(6,MIN(INT(((Alpha_keep*$A11+L$3-Lo_c)/Step_c)+0.00000001),193)))*INDEX($D$5:$D$205,MAX(6,MIN(INT(((Alpha_keep*$A11+L$3-Lo_c)/Step_c)+0.00000001),193))+2)),"") -> -591.92065 | ... O11: =IF(Grid!M11=1,-Cost_k*O$3-Short_p*MAX(0,Floor_c-$A11)+Beta_q*((1-(((Alpha_keep*$A11+O$3-Lo_c)/Step_c)-MAX(6,MIN(INT(((Alpha_keep*$A11+O$3-Lo_c)/Step_c)+0.00000001),193))))*INDEX($D$5:$D$205,MAX(6,MIN(INT(((Alpha_keep*$A11+O$3-Lo_c)/Step_c)+0.00000001),193))+1)+(((Alpha_keep*$A11+O$3-Lo_c)/Step_c)-MAX(6,MIN(INT(((Alpha_keep*$A11+O$3-Lo_c)/Step_c)+0.00000001),193)))*INDEX($D$5:$D$205,MAX(6,MIN(INT(((Alpha_keep*$A11+O$3-Lo_c)/Step_c)+0.00000001),193))+2)),"") -> -580.15247 | P11: =MAX(E11:O11) -> -580.15247 | Q11: =INDEX($E$3:$O$3,MATCH(P11,E11:O11,0)) -> 2.5 | R11: 2.5 | S11: =IF(ABS(Q11-R11)<0.000000001,1,0) -> 1 | T11: =ABS(P11-B11) -> 0 | U11: =Alpha_keep*A11+Q11 -> 33.2125 | V11: =INDEX(GuardBlock,7,ROUND(Q11/Step_h,0)+1) -> 1 | W11: 0 | Z11: to | AA11: =_xlfn.MAXIFS(U5:U205,Q5:Q205,">0",Q5:Q205,"<"&Cap_h) -> 55.875 | AB11: 55.875
A12: =Grid!A12 -> 31.75 | B12: -574.99821 | C12: 7 | D12: =IF(AND($C12>=6,$C12<=194),Declarations!$B$25*INDEX($B$5:$B$205,$C12+1-Declarations!$E$25)+Declarations!$B$26*INDEX($B$5:$B$205,$C12+1-Declarations!$E$26)+Declarations!$B$27*INDEX($B$5:$B$205,$C12+1-Declarations!$E$27)+Declarations!$B$28*INDEX($B$5:$B$205,$C12+1-Declarations!$E$28)+Declarations!$B$29*INDEX($B$5:$B$205,$C12+1-Declarations!$E$29),"") -> -575.07949 | E12: =IF(Grid!C12=1,-Cost_k*E$3-Short_p*MAX(0,Floor_c-$A12)+Beta_q*((1-(((Alpha_keep*$A12+E$3-Lo_c)/Step_c)-MAX(6,MIN(INT(((Alpha_keep*$A12+E$3-Lo_c)/Step_c)+0.00000001),193))))*INDEX($D$5:$D$205,MAX(6,MIN(INT(((Alpha_keep*$A12+E$3-Lo_c)/Step_c)+0.00000001),193))+1)+(((Alpha_keep*$A12+E$3-Lo_c)/Step_c)-MAX(6,MIN(INT(((Alpha_keep*$A12+E$3-Lo_c)/Step_c)+0.00000001),193)))*INDEX($D$5:$D$205,MAX(6,MIN(INT(((Alpha_keep*$A12+E$3-Lo_c)/Step_c)+0.00000001),193))+2)),"") | F12: =IF(Grid!D12=1,-Cost_k*F$3-Short_p*MAX(0,Floor_c-$A12)+Beta_q*((1-(((Alpha_keep*$A12+F$3-Lo_c)/Step_c)-MAX(6,MIN(INT(((Alpha_keep*$A12+F$3-Lo_c)/Step_c)+0.00000001),193))))*INDEX($D$5:$D$205,MAX(6,MIN(INT(((Alpha_keep*$A12+F$3-Lo_c)/Step_c)+0.00000001),193))+1)+(((Alpha_keep*$A12+F$3-Lo_c)/Step_c)-MAX(6,MIN(INT(((Alpha_keep*$A12+F$3-Lo_c)/Step_c)+0.00000001),193)))*INDEX($D$5:$D$205,MAX(6,MIN(INT(((Alpha_keep*$A12+F$3-Lo_c)/Step_c)+0.00000001),193))+2)),"") | G12: =IF(Grid!E12=1,-Cost_k*G$3-Short_p*MAX(0,Floor_c-$A12)+Beta_q*((1-(((Alpha_keep*$A12+G$3-Lo_c)/Step_c)-MAX(6,MIN(INT(((Alpha_keep*$A12+G$3-Lo_c)/Step_c)+0.00000001),193))))*INDEX($D$5:$D$205,MAX(6,MIN(INT(((Alpha_keep*$A12+G$3-Lo_c)/Step_c)+0.00000001),193))+1)+(((Alpha_keep*$A12+G$3-Lo_c)/Step_c)-MAX(6,MIN(INT(((Alpha_keep*$A12+G$3-Lo_c)/Step_c)+0.00000001),193)))*INDEX($D$5:$D$205,MAX(6,MIN(INT(((Alpha_keep*$A12+G$3-Lo_c)/Step_c)+0.00000001),193))+2)),"") | H12: =IF(Grid!F12=1,-Cost_k*H$3-Short_p*MAX(0,Floor_c-$A12)+Beta_q*((1-(((Alpha_keep*$A12+H$3-Lo_c)/Step_c)-MAX(6,MIN(INT(((Alpha_keep*$A12+H$3-Lo_c)/Step_c)+0.00000001),193))))*INDEX($D$5:$D$205,MAX(6,MIN(INT(((Alpha_keep*$A12+H$3-Lo_c)/Step_c)+0.00000001),193))+1)+(((Alpha_keep*$A12+H$3-Lo_c)/Step_c)-MAX(6,MIN(INT(((Alpha_keep*$A12+H$3-Lo_c)/Step_c)+0.00000001),193)))*INDEX($D$5:$D$205,MAX(6,MIN(INT(((Alpha_keep*$A12+H$3-Lo_c)/Step_c)+0.00000001),193))+2)),"") -> -602.61933 | I12: =IF(Grid!G12=1,-Cost_k*I$3-Short_p*MAX(0,Floor_c-$A12)+Beta_q*((1-(((Alpha_keep*$A12+I$3-Lo_c)/Step_c)-MAX(6,MIN(INT(((Alpha_keep*$A12+I$3-Lo_c)/Step_c)+0.00000001),193))))*INDEX($D$5:$D$205,MAX(6,MIN(INT(((Alpha_keep*$A12+I$3-Lo_c)/Step_c)+0.00000001),193))+1)+(((Alpha_keep*$A12+I$3-Lo_c)/Step_c)-MAX(6,MIN(INT(((Alpha_keep*$A12+I$3-Lo_c)/Step_c)+0.00000001),193)))*INDEX($D$5:$D$205,MAX(6,MIN(INT(((Alpha_keep*$A12+I$3-Lo_c)/Step_c)+0.00000001),193))+2)),"") -> -598.60548 | J12: =IF(Grid!H12=1,-Cost_k*J$3-Short_p*MAX(0,Floor_c-$A12)+Beta_q*((1-(((Alpha_keep*$A12+J$3-Lo_c)/Step_c)-MAX(6,MIN(INT(((Alpha_keep*$A12+J$3-Lo_c)/Step_c)+0.00000001),193))))*INDEX($D$5:$D$205,MAX(6,MIN(INT(((Alpha_keep*$A12+J$3-Lo_c)/Step_c)+0.00000001),193))+1)+(((Alpha_keep*$A12+J$3-Lo_c)/Step_c)-MAX(6,MIN(INT(((Alpha_keep*$A12+J$3-Lo_c)/Step_c)+0.00000001),193)))*INDEX($D$5:$D$205,MAX(6,MIN(INT(((Alpha_keep*$A12+J$3-Lo_c)/Step_c)+0.00000001),193))+2)),"") -> -594.61389 | K12: =IF(Grid!I12=1,-Cost_k*K$3-Short_p*MAX(0,Floor_c-$A12)+Beta_q*((1-(((Alpha_keep*$A12+K$3-Lo_c)/Step_c)-MAX(6,MIN(INT(((Alpha_keep*$A12+K$3-Lo_c)/Step_c)+0.00000001),193))))*INDEX($D$5:$D$205,MAX(6,MIN(INT(((Alpha_keep*$A12+K$3-Lo_c)/Step_c)+0.00000001),193))+1)+(((Alpha_keep*$A12+K$3-Lo_c)/Step_c)-MAX(6,MIN(INT(((Alpha_keep*$A12+K$3-Lo_c)/Step_c)+0.00000001),193)))*INDEX($D$5:$D$205,MAX(6,MIN(INT(((Alpha_keep*$A12+K$3-Lo_c)/Step_c)+0.00000001),193))+2)),"") -> -590.64478 | L12: =IF(Grid!J12=1,-Cost_k*L$3-Short_p*MAX(0,Floor_c-$A12)+Beta_q*((1-(((Alpha_keep*$A12+L$3-Lo_c)/Step_c)-MAX(6,MIN(INT(((Alpha_keep*$A12+L$3-Lo_c)/Step_c)+0.00000001),193))))*INDEX($D$5:$D$205,MAX(6,MIN(INT(((Alpha_keep*$A12+L$3-Lo_c)/Step_c)+0.00000001),193))+1)+(((Alpha_keep*$A12+L$3-Lo_c)/Step_c)-MAX(6,MIN(INT(((Alpha_keep*$A12+L$3-Lo_c)/Step_c)+0.00000001),193)))*INDEX($D$5:$D$205,MAX(6,MIN(INT(((Alpha_keep*$A12+L$3-Lo_c)/Step_c)+0.00000001),193))+2)),"") -> -586.6984 | ... O12: =IF(Grid!M12=1,-Cost_k*O$3-Short_p*MAX(0,Floor_c-$A12)+Beta_q*((1-(((Alpha_keep*$A12+O$3-Lo_c)/Step_c)-MAX(6,MIN(INT(((Alpha_keep*$A12+O$3-Lo_c)/Step_c)+0.00000001),193))))*INDEX($D$5:$D$205,MAX(6,MIN(INT(((Alpha_keep*$A12+O$3-Lo_c)/Step_c)+0.00000001),193))+1)+(((Alpha_keep*$A12+O$3-Lo_c)/Step_c)-MAX(6,MIN(INT(((Alpha_keep*$A12+O$3-Lo_c)/Step_c)+0.00000001),193)))*INDEX($D$5:$D$205,MAX(6,MIN(INT(((Alpha_keep*$A12+O$3-Lo_c)/Step_c)+0.00000001),193))+2)),"") -> -574.99821 | P12: =MAX(E12:O12) -> -574.99821 | Q12: =INDEX($E$3:$O$3,MATCH(P12,E12:O12,0)) -> 2.5 | R12: 2.5 | S12: =IF(ABS(Q12-R12)<0.000000001,1,0) -> 1 | T12: =ABS(P12-B12) -> 0 | U12: =Alpha_keep*A12+Q12 -> 33.45625 | V12: =INDEX(GuardBlock,8,ROUND(Q12/Step_h,0)+1) -> 1 | W12: 0 | Z12: Levels where the best rule is inside the guardrail | AA12: =SUM(V5:V205) -> 201 | AB12: 201
A13: =Grid!A13 -> 32 | B13: -569.86653 | C13: 8 | D13: =IF(AND($C13>=6,$C13<=194),Declarations!$B$25*INDEX($B$5:$B$205,$C13+1-Declarations!$E$25)+Declarations!$B$26*INDEX($B$5:$B$205,$C13+1-Declarations!$E$26)+Declarations!$B$27*INDEX($B$5:$B$205,$C13+1-Declarations!$E$27)+Declarations!$B$28*INDEX($B$5:$B$205,$C13+1-Declarations!$E$28)+Declarations!$B$29*INDEX($B$5:$B$205,$C13+1-Declarations!$E$29),"") -> -569.94869 | E13: =IF(Grid!C13=1,-Cost_k*E$3-Short_p*MAX(0,Floor_c-$A13)+Beta_q*((1-(((Alpha_keep*$A13+E$3-Lo_c)/Step_c)-MAX(6,MIN(INT(((Alpha_keep*$A13+E$3-Lo_c)/Step_c)+0.00000001),193))))*INDEX($D$5:$D$205,MAX(6,MIN(INT(((Alpha_keep*$A13+E$3-Lo_c)/Step_c)+0.00000001),193))+1)+(((Alpha_keep*$A13+E$3-Lo_c)/Step_c)-MAX(6,MIN(INT(((Alpha_keep*$A13+E$3-Lo_c)/Step_c)+0.00000001),193)))*INDEX($D$5:$D$205,MAX(6,MIN(INT(((Alpha_keep*$A13+E$3-Lo_c)/Step_c)+0.00000001),193))+2)),"") | F13: =IF(Grid!D13=1,-Cost_k*F$3-Short_p*MAX(0,Floor_c-$A13)+Beta_q*((1-(((Alpha_keep*$A13+F$3-Lo_c)/Step_c)-MAX(6,MIN(INT(((Alpha_keep*$A13+F$3-Lo_c)/Step_c)+0.00000001),193))))*INDEX($D$5:$D$205,MAX(6,MIN(INT(((Alpha_keep*$A13+F$3-Lo_c)/Step_c)+0.00000001),193))+1)+(((Alpha_keep*$A13+F$3-Lo_c)/Step_c)-MAX(6,MIN(INT(((Alpha_keep*$A13+F$3-Lo_c)/Step_c)+0.00000001),193)))*INDEX($D$5:$D$205,MAX(6,MIN(INT(((Alpha_keep*$A13+F$3-Lo_c)/Step_c)+0.00000001),193))+2)),"") | G13: =IF(Grid!E13=1,-Cost_k*G$3-Short_p*MAX(0,Floor_c-$A13)+Beta_q*((1-(((Alpha_keep*$A13+G$3-Lo_c)/Step_c)-MAX(6,MIN(INT(((Alpha_keep*$A13+G$3-Lo_c)/Step_c)+0.00000001),193))))*INDEX($D$5:$D$205,MAX(6,MIN(INT(((Alpha_keep*$A13+G$3-Lo_c)/Step_c)+0.00000001),193))+1)+(((Alpha_keep*$A13+G$3-Lo_c)/Step_c)-MAX(6,MIN(INT(((Alpha_keep*$A13+G$3-Lo_c)/Step_c)+0.00000001),193)))*INDEX($D$5:$D$205,MAX(6,MIN(INT(((Alpha_keep*$A13+G$3-Lo_c)/Step_c)+0.00000001),193))+2)),"") -> -601.34513 | H13: =IF(Grid!F13=1,-Cost_k*H$3-Short_p*MAX(0,Floor_c-$A13)+Beta_q*((1-(((Alpha_keep*$A13+H$3-Lo_c)/Step_c)-MAX(6,MIN(INT(((Alpha_keep*$A13+H$3-Lo_c)/Step_c)+0.00000001),193))))*INDEX($D$5:$D$205,MAX(6,MIN(INT(((Alpha_keep*$A13+H$3-Lo_c)/Step_c)+0.00000001),193))+1)+(((Alpha_keep*$A13+H$3-Lo_c)/Step_c)-MAX(6,MIN(INT(((Alpha_keep*$A13+H$3-Lo_c)/Step_c)+0.00000001),193)))*INDEX($D$5:$D$205,MAX(6,MIN(INT(((Alpha_keep*$A13+H$3-Lo_c)/Step_c)+0.00000001),193))+2)),"") -> -597.33073 | I13: =IF(Grid!G13=1,-Cost_k*I$3-Short_p*MAX(0,Floor_c-$A13)+Beta_q*((1-(((Alpha_keep*$A13+I$3-Lo_c)/Step_c)-MAX(6,MIN(INT(((Alpha_keep*$A13+I$3-Lo_c)/Step_c)+0.00000001),193))))*INDEX($D$5:$D$205,MAX(6,MIN(INT(((Alpha_keep*$A13+I$3-Lo_c)/Step_c)+0.00000001),193))+1)+(((Alpha_keep*$A13+I$3-Lo_c)/Step_c)-MAX(6,MIN(INT(((Alpha_keep*$A13+I$3-Lo_c)/Step_c)+0.00000001),193)))*INDEX($D$5:$D$205,MAX(6,MIN(INT(((Alpha_keep*$A13+I$3-Lo_c)/Step_c)+0.00000001),193))+2)),"") -> -593.33858 | J13: =IF(Grid!H13=1,-Cost_k*J$3-Short_p*MAX(0,Floor_c-$A13)+Beta_q*((1-(((Alpha_keep*$A13+J$3-Lo_c)/Step_c)-MAX(6,MIN(INT(((Alpha_keep*$A13+J$3-Lo_c)/Step_c)+0.00000001),193))))*INDEX($D$5:$D$205,MAX(6,MIN(INT(((Alpha_keep*$A13+J$3-Lo_c)/Step_c)+0.00000001),193))+1)+(((Alpha_keep*$A13+J$3-Lo_c)/Step_c)-MAX(6,MIN(INT(((Alpha_keep*$A13+J$3-Lo_c)/Step_c)+0.00000001),193)))*INDEX($D$5:$D$205,MAX(6,MIN(INT(((Alpha_keep*$A13+J$3-Lo_c)/Step_c)+0.00000001),193))+2)),"") -> -589.36891 | K13: =IF(Grid!I13=1,-Cost_k*K$3-Short_p*MAX(0,Floor_c-$A13)+Beta_q*((1-(((Alpha_keep*$A13+K$3-Lo_c)/Step_c)-MAX(6,MIN(INT(((Alpha_keep*$A13+K$3-Lo_c)/Step_c)+0.00000001),193))))*INDEX($D$5:$D$205,MAX(6,MIN(INT(((Alpha_keep*$A13+K$3-Lo_c)/Step_c)+0.00000001),193))+1)+(((Alpha_keep*$A13+K$3-Lo_c)/Step_c)-MAX(6,MIN(INT(((Alpha_keep*$A13+K$3-Lo_c)/Step_c)+0.00000001),193)))*INDEX($D$5:$D$205,MAX(6,MIN(INT(((Alpha_keep*$A13+K$3-Lo_c)/Step_c)+0.00000001),193))+2)),"") -> -585.42196 | L13: =IF(Grid!J13=1,-Cost_k*L$3-Short_p*MAX(0,Floor_c-$A13)+Beta_q*((1-(((Alpha_keep*$A13+L$3-Lo_c)/Step_c)-MAX(6,MIN(INT(((Alpha_keep*$A13+L$3-Lo_c)/Step_c)+0.00000001),193))))*INDEX($D$5:$D$205,MAX(6,MIN(INT(((Alpha_keep*$A13+L$3-Lo_c)/Step_c)+0.00000001),193))+1)+(((Alpha_keep*$A13+L$3-Lo_c)/Step_c)-MAX(6,MIN(INT(((Alpha_keep*$A13+L$3-Lo_c)/Step_c)+0.00000001),193)))*INDEX($D$5:$D$205,MAX(6,MIN(INT(((Alpha_keep*$A13+L$3-Lo_c)/Step_c)+0.00000001),193))+2)),"") -> -581.498 | ... O13: =IF(Grid!M13=1,-Cost_k*O$3-Short_p*MAX(0,Floor_c-$A13)+Beta_q*((1-(((Alpha_keep*$A13+O$3-Lo_c)/Step_c)-MAX(6,MIN(INT(((Alpha_keep*$A13+O$3-Lo_c)/Step_c)+0.00000001),193))))*INDEX($D$5:$D$205,MAX(6,MIN(INT(((Alpha_keep*$A13+O$3-Lo_c)/Step_c)+0.00000001),193))+1)+(((Alpha_keep*$A13+O$3-Lo_c)/Step_c)-MAX(6,MIN(INT(((Alpha_keep*$A13+O$3-Lo_c)/Step_c)+0.00000001),193)))*INDEX($D$5:$D$205,MAX(6,MIN(INT(((Alpha_keep*$A13+O$3-Lo_c)/Step_c)+0.00000001),193))+2)),"") -> -569.86653 | P13: =MAX(E13:O13) -> -569.86653 | Q13: =INDEX($E$3:$O$3,MATCH(P13,E13:O13,0)) -> 2.5 | R13: 2.5 | S13: =IF(ABS(Q13-R13)<0.000000001,1,0) -> 1 | T13: =ABS(P13-B13) -> 0 | U13: =Alpha_keep*A13+Q13 -> 33.7 | V13: =INDEX(GuardBlock,9,ROUND(Q13/Step_h,0)+1) -> 1 | W13: 0 | Z13: Long-run share of quarters below the floor | AA13: =SUMPRODUCT(W5:W205,--($A$5:$A$205<Floor_c-0.000000001)) -> 0.058199363 | AB13: 5.82 percent
A14: =Grid!A14 -> 32.25 | B14: -564.75768 | C14: 9 | D14: =IF(AND($C14>=6,$C14<=194),Declarations!$B$25*INDEX($B$5:$B$205,$C14+1-Declarations!$E$25)+Declarations!$B$26*INDEX($B$5:$B$205,$C14+1-Declarations!$E$26)+Declarations!$B$27*INDEX($B$5:$B$205,$C14+1-Declarations!$E$27)+Declarations!$B$28*INDEX($B$5:$B$205,$C14+1-Declarations!$E$28)+Declarations!$B$29*INDEX($B$5:$B$205,$C14+1-Declarations!$E$29),"") -> -564.84073 | E14: =IF(Grid!C14=1,-Cost_k*E$3-Short_p*MAX(0,Floor_c-$A14)+Beta_q*((1-(((Alpha_keep*$A14+E$3-Lo_c)/Step_c)-MAX(6,MIN(INT(((Alpha_keep*$A14+E$3-Lo_c)/Step_c)+0.00000001),193))))*INDEX($D$5:$D$205,MAX(6,MIN(INT(((Alpha_keep*$A14+E$3-Lo_c)/Step_c)+0.00000001),193))+1)+(((Alpha_keep*$A14+E$3-Lo_c)/Step_c)-MAX(6,MIN(INT(((Alpha_keep*$A14+E$3-Lo_c)/Step_c)+0.00000001),193)))*INDEX($D$5:$D$205,MAX(6,MIN(INT(((Alpha_keep*$A14+E$3-Lo_c)/Step_c)+0.00000001),193))+2)),"") | F14: =IF(Grid!D14=1,-Cost_k*F$3-Short_p*MAX(0,Floor_c-$A14)+Beta_q*((1-(((Alpha_keep*$A14+F$3-Lo_c)/Step_c)-MAX(6,MIN(INT(((Alpha_keep*$A14+F$3-Lo_c)/Step_c)+0.00000001),193))))*INDEX($D$5:$D$205,MAX(6,MIN(INT(((Alpha_keep*$A14+F$3-Lo_c)/Step_c)+0.00000001),193))+1)+(((Alpha_keep*$A14+F$3-Lo_c)/Step_c)-MAX(6,MIN(INT(((Alpha_keep*$A14+F$3-Lo_c)/Step_c)+0.00000001),193)))*INDEX($D$5:$D$205,MAX(6,MIN(INT(((Alpha_keep*$A14+F$3-Lo_c)/Step_c)+0.00000001),193))+2)),"") -> -600.07093 | G14: =IF(Grid!E14=1,-Cost_k*G$3-Short_p*MAX(0,Floor_c-$A14)+Beta_q*((1-(((Alpha_keep*$A14+G$3-Lo_c)/Step_c)-MAX(6,MIN(INT(((Alpha_keep*$A14+G$3-Lo_c)/Step_c)+0.00000001),193))))*INDEX($D$5:$D$205,MAX(6,MIN(INT(((Alpha_keep*$A14+G$3-Lo_c)/Step_c)+0.00000001),193))+1)+(((Alpha_keep*$A14+G$3-Lo_c)/Step_c)-MAX(6,MIN(INT(((Alpha_keep*$A14+G$3-Lo_c)/Step_c)+0.00000001),193)))*INDEX($D$5:$D$205,MAX(6,MIN(INT(((Alpha_keep*$A14+G$3-Lo_c)/Step_c)+0.00000001),193))+2)),"") -> -596.05598 | H14: =IF(Grid!F14=1,-Cost_k*H$3-Short_p*MAX(0,Floor_c-$A14)+Beta_q*((1-(((Alpha_keep*$A14+H$3-Lo_c)/Step_c)-MAX(6,MIN(INT(((Alpha_keep*$A14+H$3-Lo_c)/Step_c)+0.00000001),193))))*INDEX($D$5:$D$205,MAX(6,MIN(INT(((Alpha_keep*$A14+H$3-Lo_c)/Step_c)+0.00000001),193))+1)+(((Alpha_keep*$A14+H$3-Lo_c)/Step_c)-MAX(6,MIN(INT(((Alpha_keep*$A14+H$3-Lo_c)/Step_c)+0.00000001),193)))*INDEX($D$5:$D$205,MAX(6,MIN(INT(((Alpha_keep*$A14+H$3-Lo_c)/Step_c)+0.00000001),193))+2)),"") -> -592.06327 | I14: =IF(Grid!G14=1,-Cost_k*I$3-Short_p*MAX(0,Floor_c-$A14)+Beta_q*((1-(((Alpha_keep*$A14+I$3-Lo_c)/Step_c)-MAX(6,MIN(INT(((Alpha_keep*$A14+I$3-Lo_c)/Step_c)+0.00000001),193))))*INDEX($D$5:$D$205,MAX(6,MIN(INT(((Alpha_keep*$A14+I$3-Lo_c)/Step_c)+0.00000001),193))+1)+(((Alpha_keep*$A14+I$3-Lo_c)/Step_c)-MAX(6,MIN(INT(((Alpha_keep*$A14+I$3-Lo_c)/Step_c)+0.00000001),193)))*INDEX($D$5:$D$205,MAX(6,MIN(INT(((Alpha_keep*$A14+I$3-Lo_c)/Step_c)+0.00000001),193))+2)),"") -> -588.09304 | J14: =IF(Grid!H14=1,-Cost_k*J$3-Short_p*MAX(0,Floor_c-$A14)+Beta_q*((1-(((Alpha_keep*$A14+J$3-Lo_c)/Step_c)-MAX(6,MIN(INT(((Alpha_keep*$A14+J$3-Lo_c)/Step_c)+0.00000001),193))))*INDEX($D$5:$D$205,MAX(6,MIN(INT(((Alpha_keep*$A14+J$3-Lo_c)/Step_c)+0.00000001),193))+1)+(((Alpha_keep*$A14+J$3-Lo_c)/Step_c)-MAX(6,MIN(INT(((Alpha_keep*$A14+J$3-Lo_c)/Step_c)+0.00000001),193)))*INDEX($D$5:$D$205,MAX(6,MIN(INT(((Alpha_keep*$A14+J$3-Lo_c)/Step_c)+0.00000001),193))+2)),"") -> -584.14552 | K14: =IF(Grid!I14=1,-Cost_k*K$3-Short_p*MAX(0,Floor_c-$A14)+Beta_q*((1-(((Alpha_keep*$A14+K$3-Lo_c)/Step_c)-MAX(6,MIN(INT(((Alpha_keep*$A14+K$3-Lo_c)/Step_c)+0.00000001),193))))*INDEX($D$5:$D$205,MAX(6,MIN(INT(((Alpha_keep*$A14+K$3-Lo_c)/Step_c)+0.00000001),193))+1)+(((Alpha_keep*$A14+K$3-Lo_c)/Step_c)-MAX(6,MIN(INT(((Alpha_keep*$A14+K$3-Lo_c)/Step_c)+0.00000001),193)))*INDEX($D$5:$D$205,MAX(6,MIN(INT(((Alpha_keep*$A14+K$3-Lo_c)/Step_c)+0.00000001),193))+2)),"") -> -580.22098 | L14: =IF(Grid!J14=1,-Cost_k*L$3-Short_p*MAX(0,Floor_c-$A14)+Beta_q*((1-(((Alpha_keep*$A14+L$3-Lo_c)/Step_c)-MAX(6,MIN(INT(((Alpha_keep*$A14+L$3-Lo_c)/Step_c)+0.00000001),193))))*INDEX($D$5:$D$205,MAX(6,MIN(INT(((Alpha_keep*$A14+L$3-Lo_c)/Step_c)+0.00000001),193))+1)+(((Alpha_keep*$A14+L$3-Lo_c)/Step_c)-MAX(6,MIN(INT(((Alpha_keep*$A14+L$3-Lo_c)/Step_c)+0.00000001),193)))*INDEX($D$5:$D$205,MAX(6,MIN(INT(((Alpha_keep*$A14+L$3-Lo_c)/Step_c)+0.00000001),193))+2)),"") -> -576.31968 | ... O14: =IF(Grid!M14=1,-Cost_k*O$3-Short_p*MAX(0,Floor_c-$A14)+Beta_q*((1-(((Alpha_keep*$A14+O$3-Lo_c)/Step_c)-MAX(6,MIN(INT(((Alpha_keep*$A14+O$3-Lo_c)/Step_c)+0.00000001),193))))*INDEX($D$5:$D$205,MAX(6,MIN(INT(((Alpha_keep*$A14+O$3-Lo_c)/Step_c)+0.00000001),193))+1)+(((Alpha_keep*$A14+O$3-Lo_c)/Step_c)-MAX(6,MIN(INT(((Alpha_keep*$A14+O$3-Lo_c)/Step_c)+0.00000001),193)))*INDEX($D$5:$D$205,MAX(6,MIN(INT(((Alpha_keep*$A14+O$3-Lo_c)/Step_c)+0.00000001),193))+2)),"") -> -564.75768 | P14: =MAX(E14:O14) -> -564.75768 | Q14: =INDEX($E$3:$O$3,MATCH(P14,E14:O14,0)) -> 2.5 | R14: 2.5 | S14: =IF(ABS(Q14-R14)<0.000000001,1,0) -> 1 | T14: =ABS(P14-B14) -> 0 | U14: =Alpha_keep*A14+Q14 -> 33.94375 | V14: =INDEX(GuardBlock,10,ROUND(Q14/Step_h,0)+1) -> 1 | W14: 0 | Z14: Long-run mean capability | AA14: =SUMPRODUCT(W5:W205,$A$5:$A$205) -> 55.837743
A15: =Grid!A15 -> 32.5 | B15: -559.67188 | C15: 10 | D15: =IF(AND($C15>=6,$C15<=194),Declarations!$B$25*INDEX($B$5:$B$205,$C15+1-Declarations!$E$25)+Declarations!$B$26*INDEX($B$5:$B$205,$C15+1-Declarations!$E$26)+Declarations!$B$27*INDEX($B$5:$B$205,$C15+1-Declarations!$E$27)+Declarations!$B$28*INDEX($B$5:$B$205,$C15+1-Declarations!$E$28)+Declarations!$B$29*INDEX($B$5:$B$205,$C15+1-Declarations!$E$29),"") -> -559.75584 | E15: =IF(Grid!C15=1,-Cost_k*E$3-Short_p*MAX(0,Floor_c-$A15)+Beta_q*((1-(((Alpha_keep*$A15+E$3-Lo_c)/Step_c)-MAX(6,MIN(INT(((Alpha_keep*$A15+E$3-Lo_c)/Step_c)+0.00000001),193))))*INDEX($D$5:$D$205,MAX(6,MIN(INT(((Alpha_keep*$A15+E$3-Lo_c)/Step_c)+0.00000001),193))+1)+(((Alpha_keep*$A15+E$3-Lo_c)/Step_c)-MAX(6,MIN(INT(((Alpha_keep*$A15+E$3-Lo_c)/Step_c)+0.00000001),193)))*INDEX($D$5:$D$205,MAX(6,MIN(INT(((Alpha_keep*$A15+E$3-Lo_c)/Step_c)+0.00000001),193))+2)),"") -> -598.79674 | F15: =IF(Grid!D15=1,-Cost_k*F$3-Short_p*MAX(0,Floor_c-$A15)+Beta_q*((1-(((Alpha_keep*$A15+F$3-Lo_c)/Step_c)-MAX(6,MIN(INT(((Alpha_keep*$A15+F$3-Lo_c)/Step_c)+0.00000001),193))))*INDEX($D$5:$D$205,MAX(6,MIN(INT(((Alpha_keep*$A15+F$3-Lo_c)/Step_c)+0.00000001),193))+1)+(((Alpha_keep*$A15+F$3-Lo_c)/Step_c)-MAX(6,MIN(INT(((Alpha_keep*$A15+F$3-Lo_c)/Step_c)+0.00000001),193)))*INDEX($D$5:$D$205,MAX(6,MIN(INT(((Alpha_keep*$A15+F$3-Lo_c)/Step_c)+0.00000001),193))+2)),"") -> -594.78123 | G15: =IF(Grid!E15=1,-Cost_k*G$3-Short_p*MAX(0,Floor_c-$A15)+Beta_q*((1-(((Alpha_keep*$A15+G$3-Lo_c)/Step_c)-MAX(6,MIN(INT(((Alpha_keep*$A15+G$3-Lo_c)/Step_c)+0.00000001),193))))*INDEX($D$5:$D$205,MAX(6,MIN(INT(((Alpha_keep*$A15+G$3-Lo_c)/Step_c)+0.00000001),193))+1)+(((Alpha_keep*$A15+G$3-Lo_c)/Step_c)-MAX(6,MIN(INT(((Alpha_keep*$A15+G$3-Lo_c)/Step_c)+0.00000001),193)))*INDEX($D$5:$D$205,MAX(6,MIN(INT(((Alpha_keep*$A15+G$3-Lo_c)/Step_c)+0.00000001),193))+2)),"") -> -590.78796 | H15: =IF(Grid!F15=1,-Cost_k*H$3-Short_p*MAX(0,Floor_c-$A15)+Beta_q*((1-(((Alpha_keep*$A15+H$3-Lo_c)/Step_c)-MAX(6,MIN(INT(((Alpha_keep*$A15+H$3-Lo_c)/Step_c)+0.00000001),193))))*INDEX($D$5:$D$205,MAX(6,MIN(INT(((Alpha_keep*$A15+H$3-Lo_c)/Step_c)+0.00000001),193))+1)+(((Alpha_keep*$A15+H$3-Lo_c)/Step_c)-MAX(6,MIN(INT(((Alpha_keep*$A15+H$3-Lo_c)/Step_c)+0.00000001),193)))*INDEX($D$5:$D$205,MAX(6,MIN(INT(((Alpha_keep*$A15+H$3-Lo_c)/Step_c)+0.00000001),193))+2)),"") -> -586.81717 | I15: =IF(Grid!G15=1,-Cost_k*I$3-Short_p*MAX(0,Floor_c-$A15)+Beta_q*((1-(((Alpha_keep*$A15+I$3-Lo_c)/Step_c)-MAX(6,MIN(INT(((Alpha_keep*$A15+I$3-Lo_c)/Step_c)+0.00000001),193))))*INDEX($D$5:$D$205,MAX(6,MIN(INT(((Alpha_keep*$A15+I$3-Lo_c)/Step_c)+0.00000001),193))+1)+(((Alpha_keep*$A15+I$3-Lo_c)/Step_c)-MAX(6,MIN(INT(((Alpha_keep*$A15+I$3-Lo_c)/Step_c)+0.00000001),193)))*INDEX($D$5:$D$205,MAX(6,MIN(INT(((Alpha_keep*$A15+I$3-Lo_c)/Step_c)+0.00000001),193))+2)),"") -> -582.86908 | J15: =IF(Grid!H15=1,-Cost_k*J$3-Short_p*MAX(0,Floor_c-$A15)+Beta_q*((1-(((Alpha_keep*$A15+J$3-Lo_c)/Step_c)-MAX(6,MIN(INT(((Alpha_keep*$A15+J$3-Lo_c)/Step_c)+0.00000001),193))))*INDEX($D$5:$D$205,MAX(6,MIN(INT(((Alpha_keep*$A15+J$3-Lo_c)/Step_c)+0.00000001),193))+1)+(((Alpha_keep*$A15+J$3-Lo_c)/Step_c)-MAX(6,MIN(INT(((Alpha_keep*$A15+J$3-Lo_c)/Step_c)+0.00000001),193)))*INDEX($D$5:$D$205,MAX(6,MIN(INT(((Alpha_keep*$A15+J$3-Lo_c)/Step_c)+0.00000001),193))+2)),"") -> -578.94396 | K15: =IF(Grid!I15=1,-Cost_k*K$3-Short_p*MAX(0,Floor_c-$A15)+Beta_q*((1-(((Alpha_keep*$A15+K$3-Lo_c)/Step_c)-MAX(6,MIN(INT(((Alpha_keep*$A15+K$3-Lo_c)/Step_c)+0.00000001),193))))*INDEX($D$5:$D$205,MAX(6,MIN(INT(((Alpha_keep*$A15+K$3-Lo_c)/Step_c)+0.00000001),193))+1)+(((Alpha_keep*$A15+K$3-Lo_c)/Step_c)-MAX(6,MIN(INT(((Alpha_keep*$A15+K$3-Lo_c)/Step_c)+0.00000001),193)))*INDEX($D$5:$D$205,MAX(6,MIN(INT(((Alpha_keep*$A15+K$3-Lo_c)/Step_c)+0.00000001),193))+2)),"") -> -575.04208 | L15: =IF(Grid!J15=1,-Cost_k*L$3-Short_p*MAX(0,Floor_c-$A15)+Beta_q*((1-(((Alpha_keep*$A15+L$3-Lo_c)/Step_c)-MAX(6,MIN(INT(((Alpha_keep*$A15+L$3-Lo_c)/Step_c)+0.00000001),193))))*INDEX($D$5:$D$205,MAX(6,MIN(INT(((Alpha_keep*$A15+L$3-Lo_c)/Step_c)+0.00000001),193))+1)+(((Alpha_keep*$A15+L$3-Lo_c)/Step_c)-MAX(6,MIN(INT(((Alpha_keep*$A15+L$3-Lo_c)/Step_c)+0.00000001),193)))*INDEX($D$5:$D$205,MAX(6,MIN(INT(((Alpha_keep*$A15+L$3-Lo_c)/Step_c)+0.00000001),193))+2)),"") -> -571.16365 | ... O15: =IF(Grid!M15=1,-Cost_k*O$3-Short_p*MAX(0,Floor_c-$A15)+Beta_q*((1-(((Alpha_keep*$A15+O$3-Lo_c)/Step_c)-MAX(6,MIN(INT(((Alpha_keep*$A15+O$3-Lo_c)/Step_c)+0.00000001),193))))*INDEX($D$5:$D$205,MAX(6,MIN(INT(((Alpha_keep*$A15+O$3-Lo_c)/Step_c)+0.00000001),193))+1)+(((Alpha_keep*$A15+O$3-Lo_c)/Step_c)-MAX(6,MIN(INT(((Alpha_keep*$A15+O$3-Lo_c)/Step_c)+0.00000001),193)))*INDEX($D$5:$D$205,MAX(6,MIN(INT(((Alpha_keep*$A15+O$3-Lo_c)/Step_c)+0.00000001),193))+2)),"") -> -559.67188 | P15: =MAX(E15:O15) -> -559.67188 | Q15: =INDEX($E$3:$O$3,MATCH(P15,E15:O15,0)) -> 2.5 | R15: 2.5 | S15: =IF(ABS(Q15-R15)<0.000000001,1,0) -> 1 | T15: =ABS(P15-B15) -> 0 | U15: =Alpha_keep*A15+Q15 -> 34.1875 | V15: =INDEX(GuardBlock,11,ROUND(Q15/Step_h,0)+1) -> 1 | W15: 0 | Z15: Expected capability after one quarter from 58 | AA15: =Alpha_keep*Start_c+INDEX(Q5:Q205,MATCH(Start_c,$A$5:$A$205,0))-Mean_w -> 56.55 | AB15: 56.55 (Online Appendix Example 14.B.2)
A16: =Grid!A16 -> 32.75 | B16: -554.60937 | C16: 11 | D16: =IF(AND($C16>=6,$C16<=194),Declarations!$B$25*INDEX($B$5:$B$205,$C16+1-Declarations!$E$25)+Declarations!$B$26*INDEX($B$5:$B$205,$C16+1-Declarations!$E$26)+Declarations!$B$27*INDEX($B$5:$B$205,$C16+1-Declarations!$E$27)+Declarations!$B$28*INDEX($B$5:$B$205,$C16+1-Declarations!$E$28)+Declarations!$B$29*INDEX($B$5:$B$205,$C16+1-Declarations!$E$29),"") -> -554.69426 | E16: =IF(Grid!C16=1,-Cost_k*E$3-Short_p*MAX(0,Floor_c-$A16)+Beta_q*((1-(((Alpha_keep*$A16+E$3-Lo_c)/Step_c)-MAX(6,MIN(INT(((Alpha_keep*$A16+E$3-Lo_c)/Step_c)+0.00000001),193))))*INDEX($D$5:$D$205,MAX(6,MIN(INT(((Alpha_keep*$A16+E$3-Lo_c)/Step_c)+0.00000001),193))+1)+(((Alpha_keep*$A16+E$3-Lo_c)/Step_c)-MAX(6,MIN(INT(((Alpha_keep*$A16+E$3-Lo_c)/Step_c)+0.00000001),193)))*INDEX($D$5:$D$205,MAX(6,MIN(INT(((Alpha_keep*$A16+E$3-Lo_c)/Step_c)+0.00000001),193))+2)),"") -> -593.50648 | F16: =IF(Grid!D16=1,-Cost_k*F$3-Short_p*MAX(0,Floor_c-$A16)+Beta_q*((1-(((Alpha_keep*$A16+F$3-Lo_c)/Step_c)-MAX(6,MIN(INT(((Alpha_keep*$A16+F$3-Lo_c)/Step_c)+0.00000001),193))))*INDEX($D$5:$D$205,MAX(6,MIN(INT(((Alpha_keep*$A16+F$3-Lo_c)/Step_c)+0.00000001),193))+1)+(((Alpha_keep*$A16+F$3-Lo_c)/Step_c)-MAX(6,MIN(INT(((Alpha_keep*$A16+F$3-Lo_c)/Step_c)+0.00000001),193)))*INDEX($D$5:$D$205,MAX(6,MIN(INT(((Alpha_keep*$A16+F$3-Lo_c)/Step_c)+0.00000001),193))+2)),"") -> -589.51265 | G16: =IF(Grid!E16=1,-Cost_k*G$3-Short_p*MAX(0,Floor_c-$A16)+Beta_q*((1-(((Alpha_keep*$A16+G$3-Lo_c)/Step_c)-MAX(6,MIN(INT(((Alpha_keep*$A16+G$3-Lo_c)/Step_c)+0.00000001),193))))*INDEX($D$5:$D$205,MAX(6,MIN(INT(((Alpha_keep*$A16+G$3-Lo_c)/Step_c)+0.00000001),193))+1)+(((Alpha_keep*$A16+G$3-Lo_c)/Step_c)-MAX(6,MIN(INT(((Alpha_keep*$A16+G$3-Lo_c)/Step_c)+0.00000001),193)))*INDEX($D$5:$D$205,MAX(6,MIN(INT(((Alpha_keep*$A16+G$3-Lo_c)/Step_c)+0.00000001),193))+2)),"") -> -585.5413 | H16: =IF(Grid!F16=1,-Cost_k*H$3-Short_p*MAX(0,Floor_c-$A16)+Beta_q*((1-(((Alpha_keep*$A16+H$3-Lo_c)/Step_c)-MAX(6,MIN(INT(((Alpha_keep*$A16+H$3-Lo_c)/Step_c)+0.00000001),193))))*INDEX($D$5:$D$205,MAX(6,MIN(INT(((Alpha_keep*$A16+H$3-Lo_c)/Step_c)+0.00000001),193))+1)+(((Alpha_keep*$A16+H$3-Lo_c)/Step_c)-MAX(6,MIN(INT(((Alpha_keep*$A16+H$3-Lo_c)/Step_c)+0.00000001),193)))*INDEX($D$5:$D$205,MAX(6,MIN(INT(((Alpha_keep*$A16+H$3-Lo_c)/Step_c)+0.00000001),193))+2)),"") -> -581.59264 | I16: =IF(Grid!G16=1,-Cost_k*I$3-Short_p*MAX(0,Floor_c-$A16)+Beta_q*((1-(((Alpha_keep*$A16+I$3-Lo_c)/Step_c)-MAX(6,MIN(INT(((Alpha_keep*$A16+I$3-Lo_c)/Step_c)+0.00000001),193))))*INDEX($D$5:$D$205,MAX(6,MIN(INT(((Alpha_keep*$A16+I$3-Lo_c)/Step_c)+0.00000001),193))+1)+(((Alpha_keep*$A16+I$3-Lo_c)/Step_c)-MAX(6,MIN(INT(((Alpha_keep*$A16+I$3-Lo_c)/Step_c)+0.00000001),193)))*INDEX($D$5:$D$205,MAX(6,MIN(INT(((Alpha_keep*$A16+I$3-Lo_c)/Step_c)+0.00000001),193))+2)),"") -> -577.66695 | J16: =IF(Grid!H16=1,-Cost_k*J$3-Short_p*MAX(0,Floor_c-$A16)+Beta_q*((1-(((Alpha_keep*$A16+J$3-Lo_c)/Step_c)-MAX(6,MIN(INT(((Alpha_keep*$A16+J$3-Lo_c)/Step_c)+0.00000001),193))))*INDEX($D$5:$D$205,MAX(6,MIN(INT(((Alpha_keep*$A16+J$3-Lo_c)/Step_c)+0.00000001),193))+1)+(((Alpha_keep*$A16+J$3-Lo_c)/Step_c)-MAX(6,MIN(INT(((Alpha_keep*$A16+J$3-Lo_c)/Step_c)+0.00000001),193)))*INDEX($D$5:$D$205,MAX(6,MIN(INT(((Alpha_keep*$A16+J$3-Lo_c)/Step_c)+0.00000001),193))+2)),"") -> -573.76448 | K16: =IF(Grid!I16=1,-Cost_k*K$3-Short_p*MAX(0,Floor_c-$A16)+Beta_q*((1-(((Alpha_keep*$A16+K$3-Lo_c)/Step_c)-MAX(6,MIN(INT(((Alpha_keep*$A16+K$3-Lo_c)/Step_c)+0.00000001),193))))*INDEX($D$5:$D$205,MAX(6,MIN(INT(((Alpha_keep*$A16+K$3-Lo_c)/Step_c)+0.00000001),193))+1)+(((Alpha_keep*$A16+K$3-Lo_c)/Step_c)-MAX(6,MIN(INT(((Alpha_keep*$A16+K$3-Lo_c)/Step_c)+0.00000001),193)))*INDEX($D$5:$D$205,MAX(6,MIN(INT(((Alpha_keep*$A16+K$3-Lo_c)/Step_c)+0.00000001),193))+2)),"") -> -569.88547 | L16: =IF(Grid!J16=1,-Cost_k*L$3-Short_p*MAX(0,Floor_c-$A16)+Beta_q*((1-(((Alpha_keep*$A16+L$3-Lo_c)/Step_c)-MAX(6,MIN(INT(((Alpha_keep*$A16+L$3-Lo_c)/Step_c)+0.00000001),193))))*INDEX($D$5:$D$205,MAX(6,MIN(INT(((Alpha_keep*$A16+L$3-Lo_c)/Step_c)+0.00000001),193))+1)+(((Alpha_keep*$A16+L$3-Lo_c)/Step_c)-MAX(6,MIN(INT(((Alpha_keep*$A16+L$3-Lo_c)/Step_c)+0.00000001),193)))*INDEX($D$5:$D$205,MAX(6,MIN(INT(((Alpha_keep*$A16+L$3-Lo_c)/Step_c)+0.00000001),193))+2)),"") -> -566.03018 | ... O16: =IF(Grid!M16=1,-Cost_k*O$3-Short_p*MAX(0,Floor_c-$A16)+Beta_q*((1-(((Alpha_keep*$A16+O$3-Lo_c)/Step_c)-MAX(6,MIN(INT(((Alpha_keep*$A16+O$3-Lo_c)/Step_c)+0.00000001),193))))*INDEX($D$5:$D$205,MAX(6,MIN(INT(((Alpha_keep*$A16+O$3-Lo_c)/Step_c)+0.00000001),193))+1)+(((Alpha_keep*$A16+O$3-Lo_c)/Step_c)-MAX(6,MIN(INT(((Alpha_keep*$A16+O$3-Lo_c)/Step_c)+0.00000001),193)))*INDEX($D$5:$D$205,MAX(6,MIN(INT(((Alpha_keep*$A16+O$3-Lo_c)/Step_c)+0.00000001),193))+2)),"") -> -554.60937 | P16: =MAX(E16:O16) -> -554.60937 | Q16: =INDEX($E$3:$O$3,MATCH(P16,E16:O16,0)) -> 2.5 | R16: 2.5 | S16: =IF(ABS(Q16-R16)<0.000000001,1,0) -> 1 | T16: =ABS(P16-B16) -> 0 | U16: =Alpha_keep*A16+Q16 -> 34.43125 | V16: =INDEX(GuardBlock,12,ROUND(Q16/Step_h,0)+1) -> 1 | W16: 0
A17: =Grid!A17 -> 33 | B17: -549.57047 | C17: 12 | D17: =IF(AND($C17>=6,$C17<=194),Declarations!$B$25*INDEX($B$5:$B$205,$C17+1-Declarations!$E$25)+Declarations!$B$26*INDEX($B$5:$B$205,$C17+1-Declarations!$E$26)+Declarations!$B$27*INDEX($B$5:$B$205,$C17+1-Declarations!$E$27)+Declarations!$B$28*INDEX($B$5:$B$205,$C17+1-Declarations!$E$28)+Declarations!$B$29*INDEX($B$5:$B$205,$C17+1-Declarations!$E$29),"") -> -549.65629 | E17: =IF(Grid!C17=1,-Cost_k*E$3-Short_p*MAX(0,Floor_c-$A17)+Beta_q*((1-(((Alpha_keep*$A17+E$3-Lo_c)/Step_c)-MAX(6,MIN(INT(((Alpha_keep*$A17+E$3-Lo_c)/Step_c)+0.00000001),193))))*INDEX($D$5:$D$205,MAX(6,MIN(INT(((Alpha_keep*$A17+E$3-Lo_c)/Step_c)+0.00000001),193))+1)+(((Alpha_keep*$A17+E$3-Lo_c)/Step_c)-MAX(6,MIN(INT(((Alpha_keep*$A17+E$3-Lo_c)/Step_c)+0.00000001),193)))*INDEX($D$5:$D$205,MAX(6,MIN(INT(((Alpha_keep*$A17+E$3-Lo_c)/Step_c)+0.00000001),193))+2)),"") -> -588.23735 | F17: =IF(Grid!D17=1,-Cost_k*F$3-Short_p*MAX(0,Floor_c-$A17)+Beta_q*((1-(((Alpha_keep*$A17+F$3-Lo_c)/Step_c)-MAX(6,MIN(INT(((Alpha_keep*$A17+F$3-Lo_c)/Step_c)+0.00000001),193))))*INDEX($D$5:$D$205,MAX(6,MIN(INT(((Alpha_keep*$A17+F$3-Lo_c)/Step_c)+0.00000001),193))+1)+(((Alpha_keep*$A17+F$3-Lo_c)/Step_c)-MAX(6,MIN(INT(((Alpha_keep*$A17+F$3-Lo_c)/Step_c)+0.00000001),193)))*INDEX($D$5:$D$205,MAX(6,MIN(INT(((Alpha_keep*$A17+F$3-Lo_c)/Step_c)+0.00000001),193))+2)),"") -> -584.26542 | G17: =IF(Grid!E17=1,-Cost_k*G$3-Short_p*MAX(0,Floor_c-$A17)+Beta_q*((1-(((Alpha_keep*$A17+G$3-Lo_c)/Step_c)-MAX(6,MIN(INT(((Alpha_keep*$A17+G$3-Lo_c)/Step_c)+0.00000001),193))))*INDEX($D$5:$D$205,MAX(6,MIN(INT(((Alpha_keep*$A17+G$3-Lo_c)/Step_c)+0.00000001),193))+1)+(((Alpha_keep*$A17+G$3-Lo_c)/Step_c)-MAX(6,MIN(INT(((Alpha_keep*$A17+G$3-Lo_c)/Step_c)+0.00000001),193)))*INDEX($D$5:$D$205,MAX(6,MIN(INT(((Alpha_keep*$A17+G$3-Lo_c)/Step_c)+0.00000001),193))+2)),"") -> -580.3162 | H17: =IF(Grid!F17=1,-Cost_k*H$3-Short_p*MAX(0,Floor_c-$A17)+Beta_q*((1-(((Alpha_keep*$A17+H$3-Lo_c)/Step_c)-MAX(6,MIN(INT(((Alpha_keep*$A17+H$3-Lo_c)/Step_c)+0.00000001),193))))*INDEX($D$5:$D$205,MAX(6,MIN(INT(((Alpha_keep*$A17+H$3-Lo_c)/Step_c)+0.00000001),193))+1)+(((Alpha_keep*$A17+H$3-Lo_c)/Step_c)-MAX(6,MIN(INT(((Alpha_keep*$A17+H$3-Lo_c)/Step_c)+0.00000001),193)))*INDEX($D$5:$D$205,MAX(6,MIN(INT(((Alpha_keep*$A17+H$3-Lo_c)/Step_c)+0.00000001),193))+2)),"") -> -576.38993 | I17: =IF(Grid!G17=1,-Cost_k*I$3-Short_p*MAX(0,Floor_c-$A17)+Beta_q*((1-(((Alpha_keep*$A17+I$3-Lo_c)/Step_c)-MAX(6,MIN(INT(((Alpha_keep*$A17+I$3-Lo_c)/Step_c)+0.00000001),193))))*INDEX($D$5:$D$205,MAX(6,MIN(INT(((Alpha_keep*$A17+I$3-Lo_c)/Step_c)+0.00000001),193))+1)+(((Alpha_keep*$A17+I$3-Lo_c)/Step_c)-MAX(6,MIN(INT(((Alpha_keep*$A17+I$3-Lo_c)/Step_c)+0.00000001),193)))*INDEX($D$5:$D$205,MAX(6,MIN(INT(((Alpha_keep*$A17+I$3-Lo_c)/Step_c)+0.00000001),193))+2)),"") -> -572.48688 | J17: =IF(Grid!H17=1,-Cost_k*J$3-Short_p*MAX(0,Floor_c-$A17)+Beta_q*((1-(((Alpha_keep*$A17+J$3-Lo_c)/Step_c)-MAX(6,MIN(INT(((Alpha_keep*$A17+J$3-Lo_c)/Step_c)+0.00000001),193))))*INDEX($D$5:$D$205,MAX(6,MIN(INT(((Alpha_keep*$A17+J$3-Lo_c)/Step_c)+0.00000001),193))+1)+(((Alpha_keep*$A17+J$3-Lo_c)/Step_c)-MAX(6,MIN(INT(((Alpha_keep*$A17+J$3-Lo_c)/Step_c)+0.00000001),193)))*INDEX($D$5:$D$205,MAX(6,MIN(INT(((Alpha_keep*$A17+J$3-Lo_c)/Step_c)+0.00000001),193))+2)),"") -> -568.60728 | K17: =IF(Grid!I17=1,-Cost_k*K$3-Short_p*MAX(0,Floor_c-$A17)+Beta_q*((1-(((Alpha_keep*$A17+K$3-Lo_c)/Step_c)-MAX(6,MIN(INT(((Alpha_keep*$A17+K$3-Lo_c)/Step_c)+0.00000001),193))))*INDEX($D$5:$D$205,MAX(6,MIN(INT(((Alpha_keep*$A17+K$3-Lo_c)/Step_c)+0.00000001),193))+1)+(((Alpha_keep*$A17+K$3-Lo_c)/Step_c)-MAX(6,MIN(INT(((Alpha_keep*$A17+K$3-Lo_c)/Step_c)+0.00000001),193)))*INDEX($D$5:$D$205,MAX(6,MIN(INT(((Alpha_keep*$A17+K$3-Lo_c)/Step_c)+0.00000001),193))+2)),"") -> -564.7514 | L17: =IF(Grid!J17=1,-Cost_k*L$3-Short_p*MAX(0,Floor_c-$A17)+Beta_q*((1-(((Alpha_keep*$A17+L$3-Lo_c)/Step_c)-MAX(6,MIN(INT(((Alpha_keep*$A17+L$3-Lo_c)/Step_c)+0.00000001),193))))*INDEX($D$5:$D$205,MAX(6,MIN(INT(((Alpha_keep*$A17+L$3-Lo_c)/Step_c)+0.00000001),193))+1)+(((Alpha_keep*$A17+L$3-Lo_c)/Step_c)-MAX(6,MIN(INT(((Alpha_keep*$A17+L$3-Lo_c)/Step_c)+0.00000001),193)))*INDEX($D$5:$D$205,MAX(6,MIN(INT(((Alpha_keep*$A17+L$3-Lo_c)/Step_c)+0.00000001),193))+2)),"") -> -560.91953 | ... O17: =IF(Grid!M17=1,-Cost_k*O$3-Short_p*MAX(0,Floor_c-$A17)+Beta_q*((1-(((Alpha_keep*$A17+O$3-Lo_c)/Step_c)-MAX(6,MIN(INT(((Alpha_keep*$A17+O$3-Lo_c)/Step_c)+0.00000001),193))))*INDEX($D$5:$D$205,MAX(6,MIN(INT(((Alpha_keep*$A17+O$3-Lo_c)/Step_c)+0.00000001),193))+1)+(((Alpha_keep*$A17+O$3-Lo_c)/Step_c)-MAX(6,MIN(INT(((Alpha_keep*$A17+O$3-Lo_c)/Step_c)+0.00000001),193)))*INDEX($D$5:$D$205,MAX(6,MIN(INT(((Alpha_keep*$A17+O$3-Lo_c)/Step_c)+0.00000001),193))+2)),"") -> -549.57047 | P17: =MAX(E17:O17) -> -549.57047 | Q17: =INDEX($E$3:$O$3,MATCH(P17,E17:O17,0)) -> 2.5 | R17: 2.5 | S17: =IF(ABS(Q17-R17)<0.000000001,1,0) -> 1 | T17: =ABS(P17-B17) -> 0 | U17: =Alpha_keep*A17+Q17 -> 34.675 | V17: =INDEX(GuardBlock,13,ROUND(Q17/Step_h,0)+1) -> 1 | W17: 0
A18: =Grid!A18 -> 33.25 | B18: -544.5554 | C18: 13 | D18: =IF(AND($C18>=6,$C18<=194),Declarations!$B$25*INDEX($B$5:$B$205,$C18+1-Declarations!$E$25)+Declarations!$B$26*INDEX($B$5:$B$205,$C18+1-Declarations!$E$26)+Declarations!$B$27*INDEX($B$5:$B$205,$C18+1-Declarations!$E$27)+Declarations!$B$28*INDEX($B$5:$B$205,$C18+1-Declarations!$E$28)+Declarations!$B$29*INDEX($B$5:$B$205,$C18+1-Declarations!$E$29),"") -> -544.64216 | E18: =IF(Grid!C18=1,-Cost_k*E$3-Short_p*MAX(0,Floor_c-$A18)+Beta_q*((1-(((Alpha_keep*$A18+E$3-Lo_c)/Step_c)-MAX(6,MIN(INT(((Alpha_keep*$A18+E$3-Lo_c)/Step_c)+0.00000001),193))))*INDEX($D$5:$D$205,MAX(6,MIN(INT(((Alpha_keep*$A18+E$3-Lo_c)/Step_c)+0.00000001),193))+1)+(((Alpha_keep*$A18+E$3-Lo_c)/Step_c)-MAX(6,MIN(INT(((Alpha_keep*$A18+E$3-Lo_c)/Step_c)+0.00000001),193)))*INDEX($D$5:$D$205,MAX(6,MIN(INT(((Alpha_keep*$A18+E$3-Lo_c)/Step_c)+0.00000001),193))+2)),"") -> -582.98955 | F18: =IF(Grid!D18=1,-Cost_k*F$3-Short_p*MAX(0,Floor_c-$A18)+Beta_q*((1-(((Alpha_keep*$A18+F$3-Lo_c)/Step_c)-MAX(6,MIN(INT(((Alpha_keep*$A18+F$3-Lo_c)/Step_c)+0.00000001),193))))*INDEX($D$5:$D$205,MAX(6,MIN(INT(((Alpha_keep*$A18+F$3-Lo_c)/Step_c)+0.00000001),193))+1)+(((Alpha_keep*$A18+F$3-Lo_c)/Step_c)-MAX(6,MIN(INT(((Alpha_keep*$A18+F$3-Lo_c)/Step_c)+0.00000001),193)))*INDEX($D$5:$D$205,MAX(6,MIN(INT(((Alpha_keep*$A18+F$3-Lo_c)/Step_c)+0.00000001),193))+2)),"") -> -579.03976 | G18: =IF(Grid!E18=1,-Cost_k*G$3-Short_p*MAX(0,Floor_c-$A18)+Beta_q*((1-(((Alpha_keep*$A18+G$3-Lo_c)/Step_c)-MAX(6,MIN(INT(((Alpha_keep*$A18+G$3-Lo_c)/Step_c)+0.00000001),193))))*INDEX($D$5:$D$205,MAX(6,MIN(INT(((Alpha_keep*$A18+G$3-Lo_c)/Step_c)+0.00000001),193))+1)+(((Alpha_keep*$A18+G$3-Lo_c)/Step_c)-MAX(6,MIN(INT(((Alpha_keep*$A18+G$3-Lo_c)/Step_c)+0.00000001),193)))*INDEX($D$5:$D$205,MAX(6,MIN(INT(((Alpha_keep*$A18+G$3-Lo_c)/Step_c)+0.00000001),193))+2)),"") -> -575.11292 | H18: =IF(Grid!F18=1,-Cost_k*H$3-Short_p*MAX(0,Floor_c-$A18)+Beta_q*((1-(((Alpha_keep*$A18+H$3-Lo_c)/Step_c)-MAX(6,MIN(INT(((Alpha_keep*$A18+H$3-Lo_c)/Step_c)+0.00000001),193))))*INDEX($D$5:$D$205,MAX(6,MIN(INT(((Alpha_keep*$A18+H$3-Lo_c)/Step_c)+0.00000001),193))+1)+(((Alpha_keep*$A18+H$3-Lo_c)/Step_c)-MAX(6,MIN(INT(((Alpha_keep*$A18+H$3-Lo_c)/Step_c)+0.00000001),193)))*INDEX($D$5:$D$205,MAX(6,MIN(INT(((Alpha_keep*$A18+H$3-Lo_c)/Step_c)+0.00000001),193))+2)),"") -> -571.20929 | I18: =IF(Grid!G18=1,-Cost_k*I$3-Short_p*MAX(0,Floor_c-$A18)+Beta_q*((1-(((Alpha_keep*$A18+I$3-Lo_c)/Step_c)-MAX(6,MIN(INT(((Alpha_keep*$A18+I$3-Lo_c)/Step_c)+0.00000001),193))))*INDEX($D$5:$D$205,MAX(6,MIN(INT(((Alpha_keep*$A18+I$3-Lo_c)/Step_c)+0.00000001),193))+1)+(((Alpha_keep*$A18+I$3-Lo_c)/Step_c)-MAX(6,MIN(INT(((Alpha_keep*$A18+I$3-Lo_c)/Step_c)+0.00000001),193)))*INDEX($D$5:$D$205,MAX(6,MIN(INT(((Alpha_keep*$A18+I$3-Lo_c)/Step_c)+0.00000001),193))+2)),"") -> -567.32909 | J18: =IF(Grid!H18=1,-Cost_k*J$3-Short_p*MAX(0,Floor_c-$A18)+Beta_q*((1-(((Alpha_keep*$A18+J$3-Lo_c)/Step_c)-MAX(6,MIN(INT(((Alpha_keep*$A18+J$3-Lo_c)/Step_c)+0.00000001),193))))*INDEX($D$5:$D$205,MAX(6,MIN(INT(((Alpha_keep*$A18+J$3-Lo_c)/Step_c)+0.00000001),193))+1)+(((Alpha_keep*$A18+J$3-Lo_c)/Step_c)-MAX(6,MIN(INT(((Alpha_keep*$A18+J$3-Lo_c)/Step_c)+0.00000001),193)))*INDEX($D$5:$D$205,MAX(6,MIN(INT(((Alpha_keep*$A18+J$3-Lo_c)/Step_c)+0.00000001),193))+2)),"") -> -563.47262 | K18: =IF(Grid!I18=1,-Cost_k*K$3-Short_p*MAX(0,Floor_c-$A18)+Beta_q*((1-(((Alpha_keep*$A18+K$3-Lo_c)/Step_c)-MAX(6,MIN(INT(((Alpha_keep*$A18+K$3-Lo_c)/Step_c)+0.00000001),193))))*INDEX($D$5:$D$205,MAX(6,MIN(INT(((Alpha_keep*$A18+K$3-Lo_c)/Step_c)+0.00000001),193))+1)+(((Alpha_keep*$A18+K$3-Lo_c)/Step_c)-MAX(6,MIN(INT(((Alpha_keep*$A18+K$3-Lo_c)/Step_c)+0.00000001),193)))*INDEX($D$5:$D$205,MAX(6,MIN(INT(((Alpha_keep*$A18+K$3-Lo_c)/Step_c)+0.00000001),193))+2)),"") -> -559.64014 | L18: =IF(Grid!J18=1,-Cost_k*L$3-Short_p*MAX(0,Floor_c-$A18)+Beta_q*((1-(((Alpha_keep*$A18+L$3-Lo_c)/Step_c)-MAX(6,MIN(INT(((Alpha_keep*$A18+L$3-Lo_c)/Step_c)+0.00000001),193))))*INDEX($D$5:$D$205,MAX(6,MIN(INT(((Alpha_keep*$A18+L$3-Lo_c)/Step_c)+0.00000001),193))+1)+(((Alpha_keep*$A18+L$3-Lo_c)/Step_c)-MAX(6,MIN(INT(((Alpha_keep*$A18+L$3-Lo_c)/Step_c)+0.00000001),193)))*INDEX($D$5:$D$205,MAX(6,MIN(INT(((Alpha_keep*$A18+L$3-Lo_c)/Step_c)+0.00000001),193))+2)),"") -> -555.8319 | ... O18: =IF(Grid!M18=1,-Cost_k*O$3-Short_p*MAX(0,Floor_c-$A18)+Beta_q*((1-(((Alpha_keep*$A18+O$3-Lo_c)/Step_c)-MAX(6,MIN(INT(((Alpha_keep*$A18+O$3-Lo_c)/Step_c)+0.00000001),193))))*INDEX($D$5:$D$205,MAX(6,MIN(INT(((Alpha_keep*$A18+O$3-Lo_c)/Step_c)+0.00000001),193))+1)+(((Alpha_keep*$A18+O$3-Lo_c)/Step_c)-MAX(6,MIN(INT(((Alpha_keep*$A18+O$3-Lo_c)/Step_c)+0.00000001),193)))*INDEX($D$5:$D$205,MAX(6,MIN(INT(((Alpha_keep*$A18+O$3-Lo_c)/Step_c)+0.00000001),193))+2)),"") -> -544.5554 | P18: =MAX(E18:O18) -> -544.5554 | Q18: =INDEX($E$3:$O$3,MATCH(P18,E18:O18,0)) -> 2.5 | R18: 2.5 | S18: =IF(ABS(Q18-R18)<0.000000001,1,0) -> 1 | T18: =ABS(P18-B18) -> 0 | U18: =Alpha_keep*A18+Q18 -> 34.91875 | V18: =INDEX(GuardBlock,14,ROUND(Q18/Step_h,0)+1) -> 1 | W18: 0
A19: =Grid!A19 -> 33.5 | B19: -539.56439 | C19: 14 | D19: =IF(AND($C19>=6,$C19<=194),Declarations!$B$25*INDEX($B$5:$B$205,$C19+1-Declarations!$E$25)+Declarations!$B$26*INDEX($B$5:$B$205,$C19+1-Declarations!$E$26)+Declarations!$B$27*INDEX($B$5:$B$205,$C19+1-Declarations!$E$27)+Declarations!$B$28*INDEX($B$5:$B$205,$C19+1-Declarations!$E$28)+Declarations!$B$29*INDEX($B$5:$B$205,$C19+1-Declarations!$E$29),"") -> -539.65212 | E19: =IF(Grid!C19=1,-Cost_k*E$3-Short_p*MAX(0,Floor_c-$A19)+Beta_q*((1-(((Alpha_keep*$A19+E$3-Lo_c)/Step_c)-MAX(6,MIN(INT(((Alpha_keep*$A19+E$3-Lo_c)/Step_c)+0.00000001),193))))*INDEX($D$5:$D$205,MAX(6,MIN(INT(((Alpha_keep*$A19+E$3-Lo_c)/Step_c)+0.00000001),193))+1)+(((Alpha_keep*$A19+E$3-Lo_c)/Step_c)-MAX(6,MIN(INT(((Alpha_keep*$A19+E$3-Lo_c)/Step_c)+0.00000001),193)))*INDEX($D$5:$D$205,MAX(6,MIN(INT(((Alpha_keep*$A19+E$3-Lo_c)/Step_c)+0.00000001),193))+2)),"") -> -577.76332 | F19: =IF(Grid!D19=1,-Cost_k*F$3-Short_p*MAX(0,Floor_c-$A19)+Beta_q*((1-(((Alpha_keep*$A19+F$3-Lo_c)/Step_c)-MAX(6,MIN(INT(((Alpha_keep*$A19+F$3-Lo_c)/Step_c)+0.00000001),193))))*INDEX($D$5:$D$205,MAX(6,MIN(INT(((Alpha_keep*$A19+F$3-Lo_c)/Step_c)+0.00000001),193))+1)+(((Alpha_keep*$A19+F$3-Lo_c)/Step_c)-MAX(6,MIN(INT(((Alpha_keep*$A19+F$3-Lo_c)/Step_c)+0.00000001),193)))*INDEX($D$5:$D$205,MAX(6,MIN(INT(((Alpha_keep*$A19+F$3-Lo_c)/Step_c)+0.00000001),193))+2)),"") -> -573.8359 | G19: =IF(Grid!E19=1,-Cost_k*G$3-Short_p*MAX(0,Floor_c-$A19)+Beta_q*((1-(((Alpha_keep*$A19+G$3-Lo_c)/Step_c)-MAX(6,MIN(INT(((Alpha_keep*$A19+G$3-Lo_c)/Step_c)+0.00000001),193))))*INDEX($D$5:$D$205,MAX(6,MIN(INT(((Alpha_keep*$A19+G$3-Lo_c)/Step_c)+0.00000001),193))+1)+(((Alpha_keep*$A19+G$3-Lo_c)/Step_c)-MAX(6,MIN(INT(((Alpha_keep*$A19+G$3-Lo_c)/Step_c)+0.00000001),193)))*INDEX($D$5:$D$205,MAX(6,MIN(INT(((Alpha_keep*$A19+G$3-Lo_c)/Step_c)+0.00000001),193))+2)),"") -> -569.93169 | H19: =IF(Grid!F19=1,-Cost_k*H$3-Short_p*MAX(0,Floor_c-$A19)+Beta_q*((1-(((Alpha_keep*$A19+H$3-Lo_c)/Step_c)-MAX(6,MIN(INT(((Alpha_keep*$A19+H$3-Lo_c)/Step_c)+0.00000001),193))))*INDEX($D$5:$D$205,MAX(6,MIN(INT(((Alpha_keep*$A19+H$3-Lo_c)/Step_c)+0.00000001),193))+1)+(((Alpha_keep*$A19+H$3-Lo_c)/Step_c)-MAX(6,MIN(INT(((Alpha_keep*$A19+H$3-Lo_c)/Step_c)+0.00000001),193)))*INDEX($D$5:$D$205,MAX(6,MIN(INT(((Alpha_keep*$A19+H$3-Lo_c)/Step_c)+0.00000001),193))+2)),"") -> -566.05091 | I19: =IF(Grid!G19=1,-Cost_k*I$3-Short_p*MAX(0,Floor_c-$A19)+Beta_q*((1-(((Alpha_keep*$A19+I$3-Lo_c)/Step_c)-MAX(6,MIN(INT(((Alpha_keep*$A19+I$3-Lo_c)/Step_c)+0.00000001),193))))*INDEX($D$5:$D$205,MAX(6,MIN(INT(((Alpha_keep*$A19+I$3-Lo_c)/Step_c)+0.00000001),193))+1)+(((Alpha_keep*$A19+I$3-Lo_c)/Step_c)-MAX(6,MIN(INT(((Alpha_keep*$A19+I$3-Lo_c)/Step_c)+0.00000001),193)))*INDEX($D$5:$D$205,MAX(6,MIN(INT(((Alpha_keep*$A19+I$3-Lo_c)/Step_c)+0.00000001),193))+2)),"") -> -562.19384 | J19: =IF(Grid!H19=1,-Cost_k*J$3-Short_p*MAX(0,Floor_c-$A19)+Beta_q*((1-(((Alpha_keep*$A19+J$3-Lo_c)/Step_c)-MAX(6,MIN(INT(((Alpha_keep*$A19+J$3-Lo_c)/Step_c)+0.00000001),193))))*INDEX($D$5:$D$205,MAX(6,MIN(INT(((Alpha_keep*$A19+J$3-Lo_c)/Step_c)+0.00000001),193))+1)+(((Alpha_keep*$A19+J$3-Lo_c)/Step_c)-MAX(6,MIN(INT(((Alpha_keep*$A19+J$3-Lo_c)/Step_c)+0.00000001),193)))*INDEX($D$5:$D$205,MAX(6,MIN(INT(((Alpha_keep*$A19+J$3-Lo_c)/Step_c)+0.00000001),193))+2)),"") -> -558.36076 | K19: =IF(Grid!I19=1,-Cost_k*K$3-Short_p*MAX(0,Floor_c-$A19)+Beta_q*((1-(((Alpha_keep*$A19+K$3-Lo_c)/Step_c)-MAX(6,MIN(INT(((Alpha_keep*$A19+K$3-Lo_c)/Step_c)+0.00000001),193))))*INDEX($D$5:$D$205,MAX(6,MIN(INT(((Alpha_keep*$A19+K$3-Lo_c)/Step_c)+0.00000001),193))+1)+(((Alpha_keep*$A19+K$3-Lo_c)/Step_c)-MAX(6,MIN(INT(((Alpha_keep*$A19+K$3-Lo_c)/Step_c)+0.00000001),193)))*INDEX($D$5:$D$205,MAX(6,MIN(INT(((Alpha_keep*$A19+K$3-Lo_c)/Step_c)+0.00000001),193))+2)),"") -> -554.55191 | L19: =IF(Grid!J19=1,-Cost_k*L$3-Short_p*MAX(0,Floor_c-$A19)+Beta_q*((1-(((Alpha_keep*$A19+L$3-Lo_c)/Step_c)-MAX(6,MIN(INT(((Alpha_keep*$A19+L$3-Lo_c)/Step_c)+0.00000001),193))))*INDEX($D$5:$D$205,MAX(6,MIN(INT(((Alpha_keep*$A19+L$3-Lo_c)/Step_c)+0.00000001),193))+1)+(((Alpha_keep*$A19+L$3-Lo_c)/Step_c)-MAX(6,MIN(INT(((Alpha_keep*$A19+L$3-Lo_c)/Step_c)+0.00000001),193)))*INDEX($D$5:$D$205,MAX(6,MIN(INT(((Alpha_keep*$A19+L$3-Lo_c)/Step_c)+0.00000001),193))+2)),"") -> -550.76756 | ... O19: =IF(Grid!M19=1,-Cost_k*O$3-Short_p*MAX(0,Floor_c-$A19)+Beta_q*((1-(((Alpha_keep*$A19+O$3-Lo_c)/Step_c)-MAX(6,MIN(INT(((Alpha_keep*$A19+O$3-Lo_c)/Step_c)+0.00000001),193))))*INDEX($D$5:$D$205,MAX(6,MIN(INT(((Alpha_keep*$A19+O$3-Lo_c)/Step_c)+0.00000001),193))+1)+(((Alpha_keep*$A19+O$3-Lo_c)/Step_c)-MAX(6,MIN(INT(((Alpha_keep*$A19+O$3-Lo_c)/Step_c)+0.00000001),193)))*INDEX($D$5:$D$205,MAX(6,MIN(INT(((Alpha_keep*$A19+O$3-Lo_c)/Step_c)+0.00000001),193))+2)),"") -> -539.56439 | P19: =MAX(E19:O19) -> -539.56439 | Q19: =INDEX($E$3:$O$3,MATCH(P19,E19:O19,0)) -> 2.5 | R19: 2.5 | S19: =IF(ABS(Q19-R19)<0.000000001,1,0) -> 1 | T19: =ABS(P19-B19) -> 0 | U19: =Alpha_keep*A19+Q19 -> 35.1625 | V19: =INDEX(GuardBlock,15,ROUND(Q19/Step_h,0)+1) -> 1 | W19: 0
A20: =Grid!A20 -> 33.75 | B20: -534.59776 | C20: 15 | D20: =IF(AND($C20>=6,$C20<=194),Declarations!$B$25*INDEX($B$5:$B$205,$C20+1-Declarations!$E$25)+Declarations!$B$26*INDEX($B$5:$B$205,$C20+1-Declarations!$E$26)+Declarations!$B$27*INDEX($B$5:$B$205,$C20+1-Declarations!$E$27)+Declarations!$B$28*INDEX($B$5:$B$205,$C20+1-Declarations!$E$28)+Declarations!$B$29*INDEX($B$5:$B$205,$C20+1-Declarations!$E$29),"") -> -534.68646 | E20: =IF(Grid!C20=1,-Cost_k*E$3-Short_p*MAX(0,Floor_c-$A20)+Beta_q*((1-(((Alpha_keep*$A20+E$3-Lo_c)/Step_c)-MAX(6,MIN(INT(((Alpha_keep*$A20+E$3-Lo_c)/Step_c)+0.00000001),193))))*INDEX($D$5:$D$205,MAX(6,MIN(INT(((Alpha_keep*$A20+E$3-Lo_c)/Step_c)+0.00000001),193))+1)+(((Alpha_keep*$A20+E$3-Lo_c)/Step_c)-MAX(6,MIN(INT(((Alpha_keep*$A20+E$3-Lo_c)/Step_c)+0.00000001),193)))*INDEX($D$5:$D$205,MAX(6,MIN(INT(((Alpha_keep*$A20+E$3-Lo_c)/Step_c)+0.00000001),193))+2)),"") -> -572.55888 | F20: =IF(Grid!D20=1,-Cost_k*F$3-Short_p*MAX(0,Floor_c-$A20)+Beta_q*((1-(((Alpha_keep*$A20+F$3-Lo_c)/Step_c)-MAX(6,MIN(INT(((Alpha_keep*$A20+F$3-Lo_c)/Step_c)+0.00000001),193))))*INDEX($D$5:$D$205,MAX(6,MIN(INT(((Alpha_keep*$A20+F$3-Lo_c)/Step_c)+0.00000001),193))+1)+(((Alpha_keep*$A20+F$3-Lo_c)/Step_c)-MAX(6,MIN(INT(((Alpha_keep*$A20+F$3-Lo_c)/Step_c)+0.00000001),193)))*INDEX($D$5:$D$205,MAX(6,MIN(INT(((Alpha_keep*$A20+F$3-Lo_c)/Step_c)+0.00000001),193))+2)),"") -> -568.65409 | G20: =IF(Grid!E20=1,-Cost_k*G$3-Short_p*MAX(0,Floor_c-$A20)+Beta_q*((1-(((Alpha_keep*$A20+G$3-Lo_c)/Step_c)-MAX(6,MIN(INT(((Alpha_keep*$A20+G$3-Lo_c)/Step_c)+0.00000001),193))))*INDEX($D$5:$D$205,MAX(6,MIN(INT(((Alpha_keep*$A20+G$3-Lo_c)/Step_c)+0.00000001),193))+1)+(((Alpha_keep*$A20+G$3-Lo_c)/Step_c)-MAX(6,MIN(INT(((Alpha_keep*$A20+G$3-Lo_c)/Step_c)+0.00000001),193)))*INDEX($D$5:$D$205,MAX(6,MIN(INT(((Alpha_keep*$A20+G$3-Lo_c)/Step_c)+0.00000001),193))+2)),"") -> -564.77272 | H20: =IF(Grid!F20=1,-Cost_k*H$3-Short_p*MAX(0,Floor_c-$A20)+Beta_q*((1-(((Alpha_keep*$A20+H$3-Lo_c)/Step_c)-MAX(6,MIN(INT(((Alpha_keep*$A20+H$3-Lo_c)/Step_c)+0.00000001),193))))*INDEX($D$5:$D$205,MAX(6,MIN(INT(((Alpha_keep*$A20+H$3-Lo_c)/Step_c)+0.00000001),193))+1)+(((Alpha_keep*$A20+H$3-Lo_c)/Step_c)-MAX(6,MIN(INT(((Alpha_keep*$A20+H$3-Lo_c)/Step_c)+0.00000001),193)))*INDEX($D$5:$D$205,MAX(6,MIN(INT(((Alpha_keep*$A20+H$3-Lo_c)/Step_c)+0.00000001),193))+2)),"") -> -560.91506 | I20: =IF(Grid!G20=1,-Cost_k*I$3-Short_p*MAX(0,Floor_c-$A20)+Beta_q*((1-(((Alpha_keep*$A20+I$3-Lo_c)/Step_c)-MAX(6,MIN(INT(((Alpha_keep*$A20+I$3-Lo_c)/Step_c)+0.00000001),193))))*INDEX($D$5:$D$205,MAX(6,MIN(INT(((Alpha_keep*$A20+I$3-Lo_c)/Step_c)+0.00000001),193))+1)+(((Alpha_keep*$A20+I$3-Lo_c)/Step_c)-MAX(6,MIN(INT(((Alpha_keep*$A20+I$3-Lo_c)/Step_c)+0.00000001),193)))*INDEX($D$5:$D$205,MAX(6,MIN(INT(((Alpha_keep*$A20+I$3-Lo_c)/Step_c)+0.00000001),193))+2)),"") -> -557.08137 | J20: =IF(Grid!H20=1,-Cost_k*J$3-Short_p*MAX(0,Floor_c-$A20)+Beta_q*((1-(((Alpha_keep*$A20+J$3-Lo_c)/Step_c)-MAX(6,MIN(INT(((Alpha_keep*$A20+J$3-Lo_c)/Step_c)+0.00000001),193))))*INDEX($D$5:$D$205,MAX(6,MIN(INT(((Alpha_keep*$A20+J$3-Lo_c)/Step_c)+0.00000001),193))+1)+(((Alpha_keep*$A20+J$3-Lo_c)/Step_c)-MAX(6,MIN(INT(((Alpha_keep*$A20+J$3-Lo_c)/Step_c)+0.00000001),193)))*INDEX($D$5:$D$205,MAX(6,MIN(INT(((Alpha_keep*$A20+J$3-Lo_c)/Step_c)+0.00000001),193))+2)),"") -> -553.27192 | K20: =IF(Grid!I20=1,-Cost_k*K$3-Short_p*MAX(0,Floor_c-$A20)+Beta_q*((1-(((Alpha_keep*$A20+K$3-Lo_c)/Step_c)-MAX(6,MIN(INT(((Alpha_keep*$A20+K$3-Lo_c)/Step_c)+0.00000001),193))))*INDEX($D$5:$D$205,MAX(6,MIN(INT(((Alpha_keep*$A20+K$3-Lo_c)/Step_c)+0.00000001),193))+1)+(((Alpha_keep*$A20+K$3-Lo_c)/Step_c)-MAX(6,MIN(INT(((Alpha_keep*$A20+K$3-Lo_c)/Step_c)+0.00000001),193)))*INDEX($D$5:$D$205,MAX(6,MIN(INT(((Alpha_keep*$A20+K$3-Lo_c)/Step_c)+0.00000001),193))+2)),"") -> -549.48695 | L20: =IF(Grid!J20=1,-Cost_k*L$3-Short_p*MAX(0,Floor_c-$A20)+Beta_q*((1-(((Alpha_keep*$A20+L$3-Lo_c)/Step_c)-MAX(6,MIN(INT(((Alpha_keep*$A20+L$3-Lo_c)/Step_c)+0.00000001),193))))*INDEX($D$5:$D$205,MAX(6,MIN(INT(((Alpha_keep*$A20+L$3-Lo_c)/Step_c)+0.00000001),193))+1)+(((Alpha_keep*$A20+L$3-Lo_c)/Step_c)-MAX(6,MIN(INT(((Alpha_keep*$A20+L$3-Lo_c)/Step_c)+0.00000001),193)))*INDEX($D$5:$D$205,MAX(6,MIN(INT(((Alpha_keep*$A20+L$3-Lo_c)/Step_c)+0.00000001),193))+2)),"") -> -545.72678 | ... O20: =IF(Grid!M20=1,-Cost_k*O$3-Short_p*MAX(0,Floor_c-$A20)+Beta_q*((1-(((Alpha_keep*$A20+O$3-Lo_c)/Step_c)-MAX(6,MIN(INT(((Alpha_keep*$A20+O$3-Lo_c)/Step_c)+0.00000001),193))))*INDEX($D$5:$D$205,MAX(6,MIN(INT(((Alpha_keep*$A20+O$3-Lo_c)/Step_c)+0.00000001),193))+1)+(((Alpha_keep*$A20+O$3-Lo_c)/Step_c)-MAX(6,MIN(INT(((Alpha_keep*$A20+O$3-Lo_c)/Step_c)+0.00000001),193)))*INDEX($D$5:$D$205,MAX(6,MIN(INT(((Alpha_keep*$A20+O$3-Lo_c)/Step_c)+0.00000001),193))+2)),"") -> -534.59776 | P20: =MAX(E20:O20) -> -534.59776 | Q20: =INDEX($E$3:$O$3,MATCH(P20,E20:O20,0)) -> 2.5 | R20: 2.5 | S20: =IF(ABS(Q20-R20)<0.000000001,1,0) -> 1 | T20: =ABS(P20-B20) -> 0 | U20: =Alpha_keep*A20+Q20 -> 35.40625 | V20: =INDEX(GuardBlock,16,ROUND(Q20/Step_h,0)+1) -> 1 | W20: 0
A21: =Grid!A21 -> 34 | B21: -529.65579 | C21: 16 | D21: =IF(AND($C21>=6,$C21<=194),Declarations!$B$25*INDEX($B$5:$B$205,$C21+1-Declarations!$E$25)+Declarations!$B$26*INDEX($B$5:$B$205,$C21+1-Declarations!$E$26)+Declarations!$B$27*INDEX($B$5:$B$205,$C21+1-Declarations!$E$27)+Declarations!$B$28*INDEX($B$5:$B$205,$C21+1-Declarations!$E$28)+Declarations!$B$29*INDEX($B$5:$B$205,$C21+1-Declarations!$E$29),"") -> -529.74547 | E21: =IF(Grid!C21=1,-Cost_k*E$3-Short_p*MAX(0,Floor_c-$A21)+Beta_q*((1-(((Alpha_keep*$A21+E$3-Lo_c)/Step_c)-MAX(6,MIN(INT(((Alpha_keep*$A21+E$3-Lo_c)/Step_c)+0.00000001),193))))*INDEX($D$5:$D$205,MAX(6,MIN(INT(((Alpha_keep*$A21+E$3-Lo_c)/Step_c)+0.00000001),193))+1)+(((Alpha_keep*$A21+E$3-Lo_c)/Step_c)-MAX(6,MIN(INT(((Alpha_keep*$A21+E$3-Lo_c)/Step_c)+0.00000001),193)))*INDEX($D$5:$D$205,MAX(6,MIN(INT(((Alpha_keep*$A21+E$3-Lo_c)/Step_c)+0.00000001),193))+2)),"") -> -567.37649 | F21: =IF(Grid!D21=1,-Cost_k*F$3-Short_p*MAX(0,Floor_c-$A21)+Beta_q*((1-(((Alpha_keep*$A21+F$3-Lo_c)/Step_c)-MAX(6,MIN(INT(((Alpha_keep*$A21+F$3-Lo_c)/Step_c)+0.00000001),193))))*INDEX($D$5:$D$205,MAX(6,MIN(INT(((Alpha_keep*$A21+F$3-Lo_c)/Step_c)+0.00000001),193))+1)+(((Alpha_keep*$A21+F$3-Lo_c)/Step_c)-MAX(6,MIN(INT(((Alpha_keep*$A21+F$3-Lo_c)/Step_c)+0.00000001),193)))*INDEX($D$5:$D$205,MAX(6,MIN(INT(((Alpha_keep*$A21+F$3-Lo_c)/Step_c)+0.00000001),193))+2)),"") -> -563.49454 | G21: =IF(Grid!E21=1,-Cost_k*G$3-Short_p*MAX(0,Floor_c-$A21)+Beta_q*((1-(((Alpha_keep*$A21+G$3-Lo_c)/Step_c)-MAX(6,MIN(INT(((Alpha_keep*$A21+G$3-Lo_c)/Step_c)+0.00000001),193))))*INDEX($D$5:$D$205,MAX(6,MIN(INT(((Alpha_keep*$A21+G$3-Lo_c)/Step_c)+0.00000001),193))+1)+(((Alpha_keep*$A21+G$3-Lo_c)/Step_c)-MAX(6,MIN(INT(((Alpha_keep*$A21+G$3-Lo_c)/Step_c)+0.00000001),193)))*INDEX($D$5:$D$205,MAX(6,MIN(INT(((Alpha_keep*$A21+G$3-Lo_c)/Step_c)+0.00000001),193))+2)),"") -> -559.63627 | H21: =IF(Grid!F21=1,-Cost_k*H$3-Short_p*MAX(0,Floor_c-$A21)+Beta_q*((1-(((Alpha_keep*$A21+H$3-Lo_c)/Step_c)-MAX(6,MIN(INT(((Alpha_keep*$A21+H$3-Lo_c)/Step_c)+0.00000001),193))))*INDEX($D$5:$D$205,MAX(6,MIN(INT(((Alpha_keep*$A21+H$3-Lo_c)/Step_c)+0.00000001),193))+1)+(((Alpha_keep*$A21+H$3-Lo_c)/Step_c)-MAX(6,MIN(INT(((Alpha_keep*$A21+H$3-Lo_c)/Step_c)+0.00000001),193)))*INDEX($D$5:$D$205,MAX(6,MIN(INT(((Alpha_keep*$A21+H$3-Lo_c)/Step_c)+0.00000001),193))+2)),"") -> -555.80199 | I21: =IF(Grid!G21=1,-Cost_k*I$3-Short_p*MAX(0,Floor_c-$A21)+Beta_q*((1-(((Alpha_keep*$A21+I$3-Lo_c)/Step_c)-MAX(6,MIN(INT(((Alpha_keep*$A21+I$3-Lo_c)/Step_c)+0.00000001),193))))*INDEX($D$5:$D$205,MAX(6,MIN(INT(((Alpha_keep*$A21+I$3-Lo_c)/Step_c)+0.00000001),193))+1)+(((Alpha_keep*$A21+I$3-Lo_c)/Step_c)-MAX(6,MIN(INT(((Alpha_keep*$A21+I$3-Lo_c)/Step_c)+0.00000001),193)))*INDEX($D$5:$D$205,MAX(6,MIN(INT(((Alpha_keep*$A21+I$3-Lo_c)/Step_c)+0.00000001),193))+2)),"") -> -551.99193 | J21: =IF(Grid!H21=1,-Cost_k*J$3-Short_p*MAX(0,Floor_c-$A21)+Beta_q*((1-(((Alpha_keep*$A21+J$3-Lo_c)/Step_c)-MAX(6,MIN(INT(((Alpha_keep*$A21+J$3-Lo_c)/Step_c)+0.00000001),193))))*INDEX($D$5:$D$205,MAX(6,MIN(INT(((Alpha_keep*$A21+J$3-Lo_c)/Step_c)+0.00000001),193))+1)+(((Alpha_keep*$A21+J$3-Lo_c)/Step_c)-MAX(6,MIN(INT(((Alpha_keep*$A21+J$3-Lo_c)/Step_c)+0.00000001),193)))*INDEX($D$5:$D$205,MAX(6,MIN(INT(((Alpha_keep*$A21+J$3-Lo_c)/Step_c)+0.00000001),193))+2)),"") -> -548.20634 | K21: =IF(Grid!I21=1,-Cost_k*K$3-Short_p*MAX(0,Floor_c-$A21)+Beta_q*((1-(((Alpha_keep*$A21+K$3-Lo_c)/Step_c)-MAX(6,MIN(INT(((Alpha_keep*$A21+K$3-Lo_c)/Step_c)+0.00000001),193))))*INDEX($D$5:$D$205,MAX(6,MIN(INT(((Alpha_keep*$A21+K$3-Lo_c)/Step_c)+0.00000001),193))+1)+(((Alpha_keep*$A21+K$3-Lo_c)/Step_c)-MAX(6,MIN(INT(((Alpha_keep*$A21+K$3-Lo_c)/Step_c)+0.00000001),193)))*INDEX($D$5:$D$205,MAX(6,MIN(INT(((Alpha_keep*$A21+K$3-Lo_c)/Step_c)+0.00000001),193))+2)),"") -> -544.44555 | L21: =IF(Grid!J21=1,-Cost_k*L$3-Short_p*MAX(0,Floor_c-$A21)+Beta_q*((1-(((Alpha_keep*$A21+L$3-Lo_c)/Step_c)-MAX(6,MIN(INT(((Alpha_keep*$A21+L$3-Lo_c)/Step_c)+0.00000001),193))))*INDEX($D$5:$D$205,MAX(6,MIN(INT(((Alpha_keep*$A21+L$3-Lo_c)/Step_c)+0.00000001),193))+1)+(((Alpha_keep*$A21+L$3-Lo_c)/Step_c)-MAX(6,MIN(INT(((Alpha_keep*$A21+L$3-Lo_c)/Step_c)+0.00000001),193)))*INDEX($D$5:$D$205,MAX(6,MIN(INT(((Alpha_keep*$A21+L$3-Lo_c)/Step_c)+0.00000001),193))+2)),"") -> -540.70983 | ... O21: =IF(Grid!M21=1,-Cost_k*O$3-Short_p*MAX(0,Floor_c-$A21)+Beta_q*((1-(((Alpha_keep*$A21+O$3-Lo_c)/Step_c)-MAX(6,MIN(INT(((Alpha_keep*$A21+O$3-Lo_c)/Step_c)+0.00000001),193))))*INDEX($D$5:$D$205,MAX(6,MIN(INT(((Alpha_keep*$A21+O$3-Lo_c)/Step_c)+0.00000001),193))+1)+(((Alpha_keep*$A21+O$3-Lo_c)/Step_c)-MAX(6,MIN(INT(((Alpha_keep*$A21+O$3-Lo_c)/Step_c)+0.00000001),193)))*INDEX($D$5:$D$205,MAX(6,MIN(INT(((Alpha_keep*$A21+O$3-Lo_c)/Step_c)+0.00000001),193))+2)),"") -> -529.65579 | P21: =MAX(E21:O21) -> -529.65579 | Q21: =INDEX($E$3:$O$3,MATCH(P21,E21:O21,0)) -> 2.5 | R21: 2.5 | S21: =IF(ABS(Q21-R21)<0.000000001,1,0) -> 1 | T21: =ABS(P21-B21) -> 0 | U21: =Alpha_keep*A21+Q21 -> 35.65 | V21: =INDEX(GuardBlock,17,ROUND(Q21/Step_h,0)+1) -> 1 | W21: 0
A22: =Grid!A22 -> 34.25 | B22: -524.73868 | C22: 17 | D22: =IF(AND($C22>=6,$C22<=194),Declarations!$B$25*INDEX($B$5:$B$205,$C22+1-Declarations!$E$25)+Declarations!$B$26*INDEX($B$5:$B$205,$C22+1-Declarations!$E$26)+Declarations!$B$27*INDEX($B$5:$B$205,$C22+1-Declarations!$E$27)+Declarations!$B$28*INDEX($B$5:$B$205,$C22+1-Declarations!$E$28)+Declarations!$B$29*INDEX($B$5:$B$205,$C22+1-Declarations!$E$29),"") -> -524.82938 | E22: =IF(Grid!C22=1,-Cost_k*E$3-Short_p*MAX(0,Floor_c-$A22)+Beta_q*((1-(((Alpha_keep*$A22+E$3-Lo_c)/Step_c)-MAX(6,MIN(INT(((Alpha_keep*$A22+E$3-Lo_c)/Step_c)+0.00000001),193))))*INDEX($D$5:$D$205,MAX(6,MIN(INT(((Alpha_keep*$A22+E$3-Lo_c)/Step_c)+0.00000001),193))+1)+(((Alpha_keep*$A22+E$3-Lo_c)/Step_c)-MAX(6,MIN(INT(((Alpha_keep*$A22+E$3-Lo_c)/Step_c)+0.00000001),193)))*INDEX($D$5:$D$205,MAX(6,MIN(INT(((Alpha_keep*$A22+E$3-Lo_c)/Step_c)+0.00000001),193))+2)),"") -> -562.21635 | F22: =IF(Grid!D22=1,-Cost_k*F$3-Short_p*MAX(0,Floor_c-$A22)+Beta_q*((1-(((Alpha_keep*$A22+F$3-Lo_c)/Step_c)-MAX(6,MIN(INT(((Alpha_keep*$A22+F$3-Lo_c)/Step_c)+0.00000001),193))))*INDEX($D$5:$D$205,MAX(6,MIN(INT(((Alpha_keep*$A22+F$3-Lo_c)/Step_c)+0.00000001),193))+1)+(((Alpha_keep*$A22+F$3-Lo_c)/Step_c)-MAX(6,MIN(INT(((Alpha_keep*$A22+F$3-Lo_c)/Step_c)+0.00000001),193)))*INDEX($D$5:$D$205,MAX(6,MIN(INT(((Alpha_keep*$A22+F$3-Lo_c)/Step_c)+0.00000001),193))+2)),"") -> -558.35749 | G22: =IF(Grid!E22=1,-Cost_k*G$3-Short_p*MAX(0,Floor_c-$A22)+Beta_q*((1-(((Alpha_keep*$A22+G$3-Lo_c)/Step_c)-MAX(6,MIN(INT(((Alpha_keep*$A22+G$3-Lo_c)/Step_c)+0.00000001),193))))*INDEX($D$5:$D$205,MAX(6,MIN(INT(((Alpha_keep*$A22+G$3-Lo_c)/Step_c)+0.00000001),193))+1)+(((Alpha_keep*$A22+G$3-Lo_c)/Step_c)-MAX(6,MIN(INT(((Alpha_keep*$A22+G$3-Lo_c)/Step_c)+0.00000001),193)))*INDEX($D$5:$D$205,MAX(6,MIN(INT(((Alpha_keep*$A22+G$3-Lo_c)/Step_c)+0.00000001),193))+2)),"") -> -554.52261 | H22: =IF(Grid!F22=1,-Cost_k*H$3-Short_p*MAX(0,Floor_c-$A22)+Beta_q*((1-(((Alpha_keep*$A22+H$3-Lo_c)/Step_c)-MAX(6,MIN(INT(((Alpha_keep*$A22+H$3-Lo_c)/Step_c)+0.00000001),193))))*INDEX($D$5:$D$205,MAX(6,MIN(INT(((Alpha_keep*$A22+H$3-Lo_c)/Step_c)+0.00000001),193))+1)+(((Alpha_keep*$A22+H$3-Lo_c)/Step_c)-MAX(6,MIN(INT(((Alpha_keep*$A22+H$3-Lo_c)/Step_c)+0.00000001),193)))*INDEX($D$5:$D$205,MAX(6,MIN(INT(((Alpha_keep*$A22+H$3-Lo_c)/Step_c)+0.00000001),193))+2)),"") -> -550.71194 | I22: =IF(Grid!G22=1,-Cost_k*I$3-Short_p*MAX(0,Floor_c-$A22)+Beta_q*((1-(((Alpha_keep*$A22+I$3-Lo_c)/Step_c)-MAX(6,MIN(INT(((Alpha_keep*$A22+I$3-Lo_c)/Step_c)+0.00000001),193))))*INDEX($D$5:$D$205,MAX(6,MIN(INT(((Alpha_keep*$A22+I$3-Lo_c)/Step_c)+0.00000001),193))+1)+(((Alpha_keep*$A22+I$3-Lo_c)/Step_c)-MAX(6,MIN(INT(((Alpha_keep*$A22+I$3-Lo_c)/Step_c)+0.00000001),193)))*INDEX($D$5:$D$205,MAX(6,MIN(INT(((Alpha_keep*$A22+I$3-Lo_c)/Step_c)+0.00000001),193))+2)),"") -> -546.92574 | J22: =IF(Grid!H22=1,-Cost_k*J$3-Short_p*MAX(0,Floor_c-$A22)+Beta_q*((1-(((Alpha_keep*$A22+J$3-Lo_c)/Step_c)-MAX(6,MIN(INT(((Alpha_keep*$A22+J$3-Lo_c)/Step_c)+0.00000001),193))))*INDEX($D$5:$D$205,MAX(6,MIN(INT(((Alpha_keep*$A22+J$3-Lo_c)/Step_c)+0.00000001),193))+1)+(((Alpha_keep*$A22+J$3-Lo_c)/Step_c)-MAX(6,MIN(INT(((Alpha_keep*$A22+J$3-Lo_c)/Step_c)+0.00000001),193)))*INDEX($D$5:$D$205,MAX(6,MIN(INT(((Alpha_keep*$A22+J$3-Lo_c)/Step_c)+0.00000001),193))+2)),"") -> -543.16432 | K22: =IF(Grid!I22=1,-Cost_k*K$3-Short_p*MAX(0,Floor_c-$A22)+Beta_q*((1-(((Alpha_keep*$A22+K$3-Lo_c)/Step_c)-MAX(6,MIN(INT(((Alpha_keep*$A22+K$3-Lo_c)/Step_c)+0.00000001),193))))*INDEX($D$5:$D$205,MAX(6,MIN(INT(((Alpha_keep*$A22+K$3-Lo_c)/Step_c)+0.00000001),193))+1)+(((Alpha_keep*$A22+K$3-Lo_c)/Step_c)-MAX(6,MIN(INT(((Alpha_keep*$A22+K$3-Lo_c)/Step_c)+0.00000001),193)))*INDEX($D$5:$D$205,MAX(6,MIN(INT(((Alpha_keep*$A22+K$3-Lo_c)/Step_c)+0.00000001),193))+2)),"") -> -539.42797 | L22: =IF(Grid!J22=1,-Cost_k*L$3-Short_p*MAX(0,Floor_c-$A22)+Beta_q*((1-(((Alpha_keep*$A22+L$3-Lo_c)/Step_c)-MAX(6,MIN(INT(((Alpha_keep*$A22+L$3-Lo_c)/Step_c)+0.00000001),193))))*INDEX($D$5:$D$205,MAX(6,MIN(INT(((Alpha_keep*$A22+L$3-Lo_c)/Step_c)+0.00000001),193))+1)+(((Alpha_keep*$A22+L$3-Lo_c)/Step_c)-MAX(6,MIN(INT(((Alpha_keep*$A22+L$3-Lo_c)/Step_c)+0.00000001),193)))*INDEX($D$5:$D$205,MAX(6,MIN(INT(((Alpha_keep*$A22+L$3-Lo_c)/Step_c)+0.00000001),193))+2)),"") -> -535.71691 | ... O22: =IF(Grid!M22=1,-Cost_k*O$3-Short_p*MAX(0,Floor_c-$A22)+Beta_q*((1-(((Alpha_keep*$A22+O$3-Lo_c)/Step_c)-MAX(6,MIN(INT(((Alpha_keep*$A22+O$3-Lo_c)/Step_c)+0.00000001),193))))*INDEX($D$5:$D$205,MAX(6,MIN(INT(((Alpha_keep*$A22+O$3-Lo_c)/Step_c)+0.00000001),193))+1)+(((Alpha_keep*$A22+O$3-Lo_c)/Step_c)-MAX(6,MIN(INT(((Alpha_keep*$A22+O$3-Lo_c)/Step_c)+0.00000001),193)))*INDEX($D$5:$D$205,MAX(6,MIN(INT(((Alpha_keep*$A22+O$3-Lo_c)/Step_c)+0.00000001),193))+2)),"") -> -524.73868 | P22: =MAX(E22:O22) -> -524.73868 | Q22: =INDEX($E$3:$O$3,MATCH(P22,E22:O22,0)) -> 2.5 | R22: 2.5 | S22: =IF(ABS(Q22-R22)<0.000000001,1,0) -> 1 | T22: =ABS(P22-B22) -> 0 | U22: =Alpha_keep*A22+Q22 -> 35.89375 | V22: =INDEX(GuardBlock,18,ROUND(Q22/Step_h,0)+1) -> 1 | W22: 0
A23: =Grid!A23 -> 34.5 | B23: -519.84675 | C23: 18 | D23: =IF(AND($C23>=6,$C23<=194),Declarations!$B$25*INDEX($B$5:$B$205,$C23+1-Declarations!$E$25)+Declarations!$B$26*INDEX($B$5:$B$205,$C23+1-Declarations!$E$26)+Declarations!$B$27*INDEX($B$5:$B$205,$C23+1-Declarations!$E$27)+Declarations!$B$28*INDEX($B$5:$B$205,$C23+1-Declarations!$E$28)+Declarations!$B$29*INDEX($B$5:$B$205,$C23+1-Declarations!$E$29),"") -> -519.93847 | E23: =IF(Grid!C23=1,-Cost_k*E$3-Short_p*MAX(0,Floor_c-$A23)+Beta_q*((1-(((Alpha_keep*$A23+E$3-Lo_c)/Step_c)-MAX(6,MIN(INT(((Alpha_keep*$A23+E$3-Lo_c)/Step_c)+0.00000001),193))))*INDEX($D$5:$D$205,MAX(6,MIN(INT(((Alpha_keep*$A23+E$3-Lo_c)/Step_c)+0.00000001),193))+1)+(((Alpha_keep*$A23+E$3-Lo_c)/Step_c)-MAX(6,MIN(INT(((Alpha_keep*$A23+E$3-Lo_c)/Step_c)+0.00000001),193)))*INDEX($D$5:$D$205,MAX(6,MIN(INT(((Alpha_keep*$A23+E$3-Lo_c)/Step_c)+0.00000001),193))+2)),"") -> -557.07871 | F23: =IF(Grid!D23=1,-Cost_k*F$3-Short_p*MAX(0,Floor_c-$A23)+Beta_q*((1-(((Alpha_keep*$A23+F$3-Lo_c)/Step_c)-MAX(6,MIN(INT(((Alpha_keep*$A23+F$3-Lo_c)/Step_c)+0.00000001),193))))*INDEX($D$5:$D$205,MAX(6,MIN(INT(((Alpha_keep*$A23+F$3-Lo_c)/Step_c)+0.00000001),193))+1)+(((Alpha_keep*$A23+F$3-Lo_c)/Step_c)-MAX(6,MIN(INT(((Alpha_keep*$A23+F$3-Lo_c)/Step_c)+0.00000001),193)))*INDEX($D$5:$D$205,MAX(6,MIN(INT(((Alpha_keep*$A23+F$3-Lo_c)/Step_c)+0.00000001),193))+2)),"") -> -553.24322 | G23: =IF(Grid!E23=1,-Cost_k*G$3-Short_p*MAX(0,Floor_c-$A23)+Beta_q*((1-(((Alpha_keep*$A23+G$3-Lo_c)/Step_c)-MAX(6,MIN(INT(((Alpha_keep*$A23+G$3-Lo_c)/Step_c)+0.00000001),193))))*INDEX($D$5:$D$205,MAX(6,MIN(INT(((Alpha_keep*$A23+G$3-Lo_c)/Step_c)+0.00000001),193))+1)+(((Alpha_keep*$A23+G$3-Lo_c)/Step_c)-MAX(6,MIN(INT(((Alpha_keep*$A23+G$3-Lo_c)/Step_c)+0.00000001),193)))*INDEX($D$5:$D$205,MAX(6,MIN(INT(((Alpha_keep*$A23+G$3-Lo_c)/Step_c)+0.00000001),193))+2)),"") -> -549.43194 | H23: =IF(Grid!F23=1,-Cost_k*H$3-Short_p*MAX(0,Floor_c-$A23)+Beta_q*((1-(((Alpha_keep*$A23+H$3-Lo_c)/Step_c)-MAX(6,MIN(INT(((Alpha_keep*$A23+H$3-Lo_c)/Step_c)+0.00000001),193))))*INDEX($D$5:$D$205,MAX(6,MIN(INT(((Alpha_keep*$A23+H$3-Lo_c)/Step_c)+0.00000001),193))+1)+(((Alpha_keep*$A23+H$3-Lo_c)/Step_c)-MAX(6,MIN(INT(((Alpha_keep*$A23+H$3-Lo_c)/Step_c)+0.00000001),193)))*INDEX($D$5:$D$205,MAX(6,MIN(INT(((Alpha_keep*$A23+H$3-Lo_c)/Step_c)+0.00000001),193))+2)),"") -> -545.64513 | I23: =IF(Grid!G23=1,-Cost_k*I$3-Short_p*MAX(0,Floor_c-$A23)+Beta_q*((1-(((Alpha_keep*$A23+I$3-Lo_c)/Step_c)-MAX(6,MIN(INT(((Alpha_keep*$A23+I$3-Lo_c)/Step_c)+0.00000001),193))))*INDEX($D$5:$D$205,MAX(6,MIN(INT(((Alpha_keep*$A23+I$3-Lo_c)/Step_c)+0.00000001),193))+1)+(((Alpha_keep*$A23+I$3-Lo_c)/Step_c)-MAX(6,MIN(INT(((Alpha_keep*$A23+I$3-Lo_c)/Step_c)+0.00000001),193)))*INDEX($D$5:$D$205,MAX(6,MIN(INT(((Alpha_keep*$A23+I$3-Lo_c)/Step_c)+0.00000001),193))+2)),"") -> -541.8831 | J23: =IF(Grid!H23=1,-Cost_k*J$3-Short_p*MAX(0,Floor_c-$A23)+Beta_q*((1-(((Alpha_keep*$A23+J$3-Lo_c)/Step_c)-MAX(6,MIN(INT(((Alpha_keep*$A23+J$3-Lo_c)/Step_c)+0.00000001),193))))*INDEX($D$5:$D$205,MAX(6,MIN(INT(((Alpha_keep*$A23+J$3-Lo_c)/Step_c)+0.00000001),193))+1)+(((Alpha_keep*$A23+J$3-Lo_c)/Step_c)-MAX(6,MIN(INT(((Alpha_keep*$A23+J$3-Lo_c)/Step_c)+0.00000001),193)))*INDEX($D$5:$D$205,MAX(6,MIN(INT(((Alpha_keep*$A23+J$3-Lo_c)/Step_c)+0.00000001),193))+2)),"") -> -538.14611 | K23: =IF(Grid!I23=1,-Cost_k*K$3-Short_p*MAX(0,Floor_c-$A23)+Beta_q*((1-(((Alpha_keep*$A23+K$3-Lo_c)/Step_c)-MAX(6,MIN(INT(((Alpha_keep*$A23+K$3-Lo_c)/Step_c)+0.00000001),193))))*INDEX($D$5:$D$205,MAX(6,MIN(INT(((Alpha_keep*$A23+K$3-Lo_c)/Step_c)+0.00000001),193))+1)+(((Alpha_keep*$A23+K$3-Lo_c)/Step_c)-MAX(6,MIN(INT(((Alpha_keep*$A23+K$3-Lo_c)/Step_c)+0.00000001),193)))*INDEX($D$5:$D$205,MAX(6,MIN(INT(((Alpha_keep*$A23+K$3-Lo_c)/Step_c)+0.00000001),193))+2)),"") -> -534.43442 | L23: =IF(Grid!J23=1,-Cost_k*L$3-Short_p*MAX(0,Floor_c-$A23)+Beta_q*((1-(((Alpha_keep*$A23+L$3-Lo_c)/Step_c)-MAX(6,MIN(INT(((Alpha_keep*$A23+L$3-Lo_c)/Step_c)+0.00000001),193))))*INDEX($D$5:$D$205,MAX(6,MIN(INT(((Alpha_keep*$A23+L$3-Lo_c)/Step_c)+0.00000001),193))+1)+(((Alpha_keep*$A23+L$3-Lo_c)/Step_c)-MAX(6,MIN(INT(((Alpha_keep*$A23+L$3-Lo_c)/Step_c)+0.00000001),193)))*INDEX($D$5:$D$205,MAX(6,MIN(INT(((Alpha_keep*$A23+L$3-Lo_c)/Step_c)+0.00000001),193))+2)),"") -> -530.74834 | ... O23: =IF(Grid!M23=1,-Cost_k*O$3-Short_p*MAX(0,Floor_c-$A23)+Beta_q*((1-(((Alpha_keep*$A23+O$3-Lo_c)/Step_c)-MAX(6,MIN(INT(((Alpha_keep*$A23+O$3-Lo_c)/Step_c)+0.00000001),193))))*INDEX($D$5:$D$205,MAX(6,MIN(INT(((Alpha_keep*$A23+O$3-Lo_c)/Step_c)+0.00000001),193))+1)+(((Alpha_keep*$A23+O$3-Lo_c)/Step_c)-MAX(6,MIN(INT(((Alpha_keep*$A23+O$3-Lo_c)/Step_c)+0.00000001),193)))*INDEX($D$5:$D$205,MAX(6,MIN(INT(((Alpha_keep*$A23+O$3-Lo_c)/Step_c)+0.00000001),193))+2)),"") -> -519.84675 | P23: =MAX(E23:O23) -> -519.84675 | Q23: =INDEX($E$3:$O$3,MATCH(P23,E23:O23,0)) -> 2.5 | R23: 2.5 | S23: =IF(ABS(Q23-R23)<0.000000001,1,0) -> 1 | T23: =ABS(P23-B23) -> 0 | U23: =Alpha_keep*A23+Q23 -> 36.1375 | V23: =INDEX(GuardBlock,19,ROUND(Q23/Step_h,0)+1) -> 1 | W23: 0
A24: =Grid!A24 -> 34.75 | B24: -514.98034 | C24: 19 | D24: =IF(AND($C24>=6,$C24<=194),Declarations!$B$25*INDEX($B$5:$B$205,$C24+1-Declarations!$E$25)+Declarations!$B$26*INDEX($B$5:$B$205,$C24+1-Declarations!$E$26)+Declarations!$B$27*INDEX($B$5:$B$205,$C24+1-Declarations!$E$27)+Declarations!$B$28*INDEX($B$5:$B$205,$C24+1-Declarations!$E$28)+Declarations!$B$29*INDEX($B$5:$B$205,$C24+1-Declarations!$E$29),"") -> -515.07309 | E24: =IF(Grid!C24=1,-Cost_k*E$3-Short_p*MAX(0,Floor_c-$A24)+Beta_q*((1-(((Alpha_keep*$A24+E$3-Lo_c)/Step_c)-MAX(6,MIN(INT(((Alpha_keep*$A24+E$3-Lo_c)/Step_c)+0.00000001),193))))*INDEX($D$5:$D$205,MAX(6,MIN(INT(((Alpha_keep*$A24+E$3-Lo_c)/Step_c)+0.00000001),193))+1)+(((Alpha_keep*$A24+E$3-Lo_c)/Step_c)-MAX(6,MIN(INT(((Alpha_keep*$A24+E$3-Lo_c)/Step_c)+0.00000001),193)))*INDEX($D$5:$D$205,MAX(6,MIN(INT(((Alpha_keep*$A24+E$3-Lo_c)/Step_c)+0.00000001),193))+2)),"") -> -551.96384 | F24: =IF(Grid!D24=1,-Cost_k*F$3-Short_p*MAX(0,Floor_c-$A24)+Beta_q*((1-(((Alpha_keep*$A24+F$3-Lo_c)/Step_c)-MAX(6,MIN(INT(((Alpha_keep*$A24+F$3-Lo_c)/Step_c)+0.00000001),193))))*INDEX($D$5:$D$205,MAX(6,MIN(INT(((Alpha_keep*$A24+F$3-Lo_c)/Step_c)+0.00000001),193))+1)+(((Alpha_keep*$A24+F$3-Lo_c)/Step_c)-MAX(6,MIN(INT(((Alpha_keep*$A24+F$3-Lo_c)/Step_c)+0.00000001),193)))*INDEX($D$5:$D$205,MAX(6,MIN(INT(((Alpha_keep*$A24+F$3-Lo_c)/Step_c)+0.00000001),193))+2)),"") -> -548.15195 | G24: =IF(Grid!E24=1,-Cost_k*G$3-Short_p*MAX(0,Floor_c-$A24)+Beta_q*((1-(((Alpha_keep*$A24+G$3-Lo_c)/Step_c)-MAX(6,MIN(INT(((Alpha_keep*$A24+G$3-Lo_c)/Step_c)+0.00000001),193))))*INDEX($D$5:$D$205,MAX(6,MIN(INT(((Alpha_keep*$A24+G$3-Lo_c)/Step_c)+0.00000001),193))+1)+(((Alpha_keep*$A24+G$3-Lo_c)/Step_c)-MAX(6,MIN(INT(((Alpha_keep*$A24+G$3-Lo_c)/Step_c)+0.00000001),193)))*INDEX($D$5:$D$205,MAX(6,MIN(INT(((Alpha_keep*$A24+G$3-Lo_c)/Step_c)+0.00000001),193))+2)),"") -> -544.36452 | H24: =IF(Grid!F24=1,-Cost_k*H$3-Short_p*MAX(0,Floor_c-$A24)+Beta_q*((1-(((Alpha_keep*$A24+H$3-Lo_c)/Step_c)-MAX(6,MIN(INT(((Alpha_keep*$A24+H$3-Lo_c)/Step_c)+0.00000001),193))))*INDEX($D$5:$D$205,MAX(6,MIN(INT(((Alpha_keep*$A24+H$3-Lo_c)/Step_c)+0.00000001),193))+1)+(((Alpha_keep*$A24+H$3-Lo_c)/Step_c)-MAX(6,MIN(INT(((Alpha_keep*$A24+H$3-Lo_c)/Step_c)+0.00000001),193)))*INDEX($D$5:$D$205,MAX(6,MIN(INT(((Alpha_keep*$A24+H$3-Lo_c)/Step_c)+0.00000001),193))+2)),"") -> -540.60187 | I24: =IF(Grid!G24=1,-Cost_k*I$3-Short_p*MAX(0,Floor_c-$A24)+Beta_q*((1-(((Alpha_keep*$A24+I$3-Lo_c)/Step_c)-MAX(6,MIN(INT(((Alpha_keep*$A24+I$3-Lo_c)/Step_c)+0.00000001),193))))*INDEX($D$5:$D$205,MAX(6,MIN(INT(((Alpha_keep*$A24+I$3-Lo_c)/Step_c)+0.00000001),193))+1)+(((Alpha_keep*$A24+I$3-Lo_c)/Step_c)-MAX(6,MIN(INT(((Alpha_keep*$A24+I$3-Lo_c)/Step_c)+0.00000001),193)))*INDEX($D$5:$D$205,MAX(6,MIN(INT(((Alpha_keep*$A24+I$3-Lo_c)/Step_c)+0.00000001),193))+2)),"") -> -536.86425 | J24: =IF(Grid!H24=1,-Cost_k*J$3-Short_p*MAX(0,Floor_c-$A24)+Beta_q*((1-(((Alpha_keep*$A24+J$3-Lo_c)/Step_c)-MAX(6,MIN(INT(((Alpha_keep*$A24+J$3-Lo_c)/Step_c)+0.00000001),193))))*INDEX($D$5:$D$205,MAX(6,MIN(INT(((Alpha_keep*$A24+J$3-Lo_c)/Step_c)+0.00000001),193))+1)+(((Alpha_keep*$A24+J$3-Lo_c)/Step_c)-MAX(6,MIN(INT(((Alpha_keep*$A24+J$3-Lo_c)/Step_c)+0.00000001),193)))*INDEX($D$5:$D$205,MAX(6,MIN(INT(((Alpha_keep*$A24+J$3-Lo_c)/Step_c)+0.00000001),193))+2)),"") -> -533.15192 | K24: =IF(Grid!I24=1,-Cost_k*K$3-Short_p*MAX(0,Floor_c-$A24)+Beta_q*((1-(((Alpha_keep*$A24+K$3-Lo_c)/Step_c)-MAX(6,MIN(INT(((Alpha_keep*$A24+K$3-Lo_c)/Step_c)+0.00000001),193))))*INDEX($D$5:$D$205,MAX(6,MIN(INT(((Alpha_keep*$A24+K$3-Lo_c)/Step_c)+0.00000001),193))+1)+(((Alpha_keep*$A24+K$3-Lo_c)/Step_c)-MAX(6,MIN(INT(((Alpha_keep*$A24+K$3-Lo_c)/Step_c)+0.00000001),193)))*INDEX($D$5:$D$205,MAX(6,MIN(INT(((Alpha_keep*$A24+K$3-Lo_c)/Step_c)+0.00000001),193))+2)),"") -> -529.46521 | L24: =IF(Grid!J24=1,-Cost_k*L$3-Short_p*MAX(0,Floor_c-$A24)+Beta_q*((1-(((Alpha_keep*$A24+L$3-Lo_c)/Step_c)-MAX(6,MIN(INT(((Alpha_keep*$A24+L$3-Lo_c)/Step_c)+0.00000001),193))))*INDEX($D$5:$D$205,MAX(6,MIN(INT(((Alpha_keep*$A24+L$3-Lo_c)/Step_c)+0.00000001),193))+1)+(((Alpha_keep*$A24+L$3-Lo_c)/Step_c)-MAX(6,MIN(INT(((Alpha_keep*$A24+L$3-Lo_c)/Step_c)+0.00000001),193)))*INDEX($D$5:$D$205,MAX(6,MIN(INT(((Alpha_keep*$A24+L$3-Lo_c)/Step_c)+0.00000001),193))+2)),"") -> -525.80442 | ... O24: =IF(Grid!M24=1,-Cost_k*O$3-Short_p*MAX(0,Floor_c-$A24)+Beta_q*((1-(((Alpha_keep*$A24+O$3-Lo_c)/Step_c)-MAX(6,MIN(INT(((Alpha_keep*$A24+O$3-Lo_c)/Step_c)+0.00000001),193))))*INDEX($D$5:$D$205,MAX(6,MIN(INT(((Alpha_keep*$A24+O$3-Lo_c)/Step_c)+0.00000001),193))+1)+(((Alpha_keep*$A24+O$3-Lo_c)/Step_c)-MAX(6,MIN(INT(((Alpha_keep*$A24+O$3-Lo_c)/Step_c)+0.00000001),193)))*INDEX($D$5:$D$205,MAX(6,MIN(INT(((Alpha_keep*$A24+O$3-Lo_c)/Step_c)+0.00000001),193))+2)),"") -> -514.98034 | P24: =MAX(E24:O24) -> -514.98034 | Q24: =INDEX($E$3:$O$3,MATCH(P24,E24:O24,0)) -> 2.5 | R24: 2.5 | S24: =IF(ABS(Q24-R24)<0.000000001,1,0) -> 1 | T24: =ABS(P24-B24) -> 0 | U24: =Alpha_keep*A24+Q24 -> 36.38125 | V24: =INDEX(GuardBlock,20,ROUND(Q24/Step_h,0)+1) -> 1 | W24: 0
A25: =Grid!A25 -> 35 | B25: -510.13967 | C25: 20 | D25: =IF(AND($C25>=6,$C25<=194),Declarations!$B$25*INDEX($B$5:$B$205,$C25+1-Declarations!$E$25)+Declarations!$B$26*INDEX($B$5:$B$205,$C25+1-Declarations!$E$26)+Declarations!$B$27*INDEX($B$5:$B$205,$C25+1-Declarations!$E$27)+Declarations!$B$28*INDEX($B$5:$B$205,$C25+1-Declarations!$E$28)+Declarations!$B$29*INDEX($B$5:$B$205,$C25+1-Declarations!$E$29),"") -> -510.23347 | E25: =IF(Grid!C25=1,-Cost_k*E$3-Short_p*MAX(0,Floor_c-$A25)+Beta_q*((1-(((Alpha_keep*$A25+E$3-Lo_c)/Step_c)-MAX(6,MIN(INT(((Alpha_keep*$A25+E$3-Lo_c)/Step_c)+0.00000001),193))))*INDEX($D$5:$D$205,MAX(6,MIN(INT(((Alpha_keep*$A25+E$3-Lo_c)/Step_c)+0.00000001),193))+1)+(((Alpha_keep*$A25+E$3-Lo_c)/Step_c)-MAX(6,MIN(INT(((Alpha_keep*$A25+E$3-Lo_c)/Step_c)+0.00000001),193)))*INDEX($D$5:$D$205,MAX(6,MIN(INT(((Alpha_keep*$A25+E$3-Lo_c)/Step_c)+0.00000001),193))+2)),"") -> -546.87196 | F25: =IF(Grid!D25=1,-Cost_k*F$3-Short_p*MAX(0,Floor_c-$A25)+Beta_q*((1-(((Alpha_keep*$A25+F$3-Lo_c)/Step_c)-MAX(6,MIN(INT(((Alpha_keep*$A25+F$3-Lo_c)/Step_c)+0.00000001),193))))*INDEX($D$5:$D$205,MAX(6,MIN(INT(((Alpha_keep*$A25+F$3-Lo_c)/Step_c)+0.00000001),193))+1)+(((Alpha_keep*$A25+F$3-Lo_c)/Step_c)-MAX(6,MIN(INT(((Alpha_keep*$A25+F$3-Lo_c)/Step_c)+0.00000001),193)))*INDEX($D$5:$D$205,MAX(6,MIN(INT(((Alpha_keep*$A25+F$3-Lo_c)/Step_c)+0.00000001),193))+2)),"") -> -543.08392 | G25: =IF(Grid!E25=1,-Cost_k*G$3-Short_p*MAX(0,Floor_c-$A25)+Beta_q*((1-(((Alpha_keep*$A25+G$3-Lo_c)/Step_c)-MAX(6,MIN(INT(((Alpha_keep*$A25+G$3-Lo_c)/Step_c)+0.00000001),193))))*INDEX($D$5:$D$205,MAX(6,MIN(INT(((Alpha_keep*$A25+G$3-Lo_c)/Step_c)+0.00000001),193))+1)+(((Alpha_keep*$A25+G$3-Lo_c)/Step_c)-MAX(6,MIN(INT(((Alpha_keep*$A25+G$3-Lo_c)/Step_c)+0.00000001),193)))*INDEX($D$5:$D$205,MAX(6,MIN(INT(((Alpha_keep*$A25+G$3-Lo_c)/Step_c)+0.00000001),193))+2)),"") -> -539.32064 | H25: =IF(Grid!F25=1,-Cost_k*H$3-Short_p*MAX(0,Floor_c-$A25)+Beta_q*((1-(((Alpha_keep*$A25+H$3-Lo_c)/Step_c)-MAX(6,MIN(INT(((Alpha_keep*$A25+H$3-Lo_c)/Step_c)+0.00000001),193))))*INDEX($D$5:$D$205,MAX(6,MIN(INT(((Alpha_keep*$A25+H$3-Lo_c)/Step_c)+0.00000001),193))+1)+(((Alpha_keep*$A25+H$3-Lo_c)/Step_c)-MAX(6,MIN(INT(((Alpha_keep*$A25+H$3-Lo_c)/Step_c)+0.00000001),193)))*INDEX($D$5:$D$205,MAX(6,MIN(INT(((Alpha_keep*$A25+H$3-Lo_c)/Step_c)+0.00000001),193))+2)),"") -> -535.58239 | I25: =IF(Grid!G25=1,-Cost_k*I$3-Short_p*MAX(0,Floor_c-$A25)+Beta_q*((1-(((Alpha_keep*$A25+I$3-Lo_c)/Step_c)-MAX(6,MIN(INT(((Alpha_keep*$A25+I$3-Lo_c)/Step_c)+0.00000001),193))))*INDEX($D$5:$D$205,MAX(6,MIN(INT(((Alpha_keep*$A25+I$3-Lo_c)/Step_c)+0.00000001),193))+1)+(((Alpha_keep*$A25+I$3-Lo_c)/Step_c)-MAX(6,MIN(INT(((Alpha_keep*$A25+I$3-Lo_c)/Step_c)+0.00000001),193)))*INDEX($D$5:$D$205,MAX(6,MIN(INT(((Alpha_keep*$A25+I$3-Lo_c)/Step_c)+0.00000001),193))+2)),"") -> -531.86943 | J25: =IF(Grid!H25=1,-Cost_k*J$3-Short_p*MAX(0,Floor_c-$A25)+Beta_q*((1-(((Alpha_keep*$A25+J$3-Lo_c)/Step_c)-MAX(6,MIN(INT(((Alpha_keep*$A25+J$3-Lo_c)/Step_c)+0.00000001),193))))*INDEX($D$5:$D$205,MAX(6,MIN(INT(((Alpha_keep*$A25+J$3-Lo_c)/Step_c)+0.00000001),193))+1)+(((Alpha_keep*$A25+J$3-Lo_c)/Step_c)-MAX(6,MIN(INT(((Alpha_keep*$A25+J$3-Lo_c)/Step_c)+0.00000001),193)))*INDEX($D$5:$D$205,MAX(6,MIN(INT(((Alpha_keep*$A25+J$3-Lo_c)/Step_c)+0.00000001),193))+2)),"") -> -528.18207 | K25: =IF(Grid!I25=1,-Cost_k*K$3-Short_p*MAX(0,Floor_c-$A25)+Beta_q*((1-(((Alpha_keep*$A25+K$3-Lo_c)/Step_c)-MAX(6,MIN(INT(((Alpha_keep*$A25+K$3-Lo_c)/Step_c)+0.00000001),193))))*INDEX($D$5:$D$205,MAX(6,MIN(INT(((Alpha_keep*$A25+K$3-Lo_c)/Step_c)+0.00000001),193))+1)+(((Alpha_keep*$A25+K$3-Lo_c)/Step_c)-MAX(6,MIN(INT(((Alpha_keep*$A25+K$3-Lo_c)/Step_c)+0.00000001),193)))*INDEX($D$5:$D$205,MAX(6,MIN(INT(((Alpha_keep*$A25+K$3-Lo_c)/Step_c)+0.00000001),193))+2)),"") -> -524.52063 | L25: =IF(Grid!J25=1,-Cost_k*L$3-Short_p*MAX(0,Floor_c-$A25)+Beta_q*((1-(((Alpha_keep*$A25+L$3-Lo_c)/Step_c)-MAX(6,MIN(INT(((Alpha_keep*$A25+L$3-Lo_c)/Step_c)+0.00000001),193))))*INDEX($D$5:$D$205,MAX(6,MIN(INT(((Alpha_keep*$A25+L$3-Lo_c)/Step_c)+0.00000001),193))+1)+(((Alpha_keep*$A25+L$3-Lo_c)/Step_c)-MAX(6,MIN(INT(((Alpha_keep*$A25+L$3-Lo_c)/Step_c)+0.00000001),193)))*INDEX($D$5:$D$205,MAX(6,MIN(INT(((Alpha_keep*$A25+L$3-Lo_c)/Step_c)+0.00000001),193))+2)),"") -> -520.88534 | ... O25: =IF(Grid!M25=1,-Cost_k*O$3-Short_p*MAX(0,Floor_c-$A25)+Beta_q*((1-(((Alpha_keep*$A25+O$3-Lo_c)/Step_c)-MAX(6,MIN(INT(((Alpha_keep*$A25+O$3-Lo_c)/Step_c)+0.00000001),193))))*INDEX($D$5:$D$205,MAX(6,MIN(INT(((Alpha_keep*$A25+O$3-Lo_c)/Step_c)+0.00000001),193))+1)+(((Alpha_keep*$A25+O$3-Lo_c)/Step_c)-MAX(6,MIN(INT(((Alpha_keep*$A25+O$3-Lo_c)/Step_c)+0.00000001),193)))*INDEX($D$5:$D$205,MAX(6,MIN(INT(((Alpha_keep*$A25+O$3-Lo_c)/Step_c)+0.00000001),193))+2)),"") -> -510.13967 | P25: =MAX(E25:O25) -> -510.13967 | Q25: =INDEX($E$3:$O$3,MATCH(P25,E25:O25,0)) -> 2.5 | R25: 2.5 | S25: =IF(ABS(Q25-R25)<0.000000001,1,0) -> 1 | T25: =ABS(P25-B25) -> 0 | U25: =Alpha_keep*A25+Q25 -> 36.625 | V25: =INDEX(GuardBlock,21,ROUND(Q25/Step_h,0)+1) -> 1 | W25: 0
A26: =Grid!A26 -> 35.25 | B26: -505.32499 | C26: 21 | D26: =IF(AND($C26>=6,$C26<=194),Declarations!$B$25*INDEX($B$5:$B$205,$C26+1-Declarations!$E$25)+Declarations!$B$26*INDEX($B$5:$B$205,$C26+1-Declarations!$E$26)+Declarations!$B$27*INDEX($B$5:$B$205,$C26+1-Declarations!$E$27)+Declarations!$B$28*INDEX($B$5:$B$205,$C26+1-Declarations!$E$28)+Declarations!$B$29*INDEX($B$5:$B$205,$C26+1-Declarations!$E$29),"") -> -505.41987 | E26: =IF(Grid!C26=1,-Cost_k*E$3-Short_p*MAX(0,Floor_c-$A26)+Beta_q*((1-(((Alpha_keep*$A26+E$3-Lo_c)/Step_c)-MAX(6,MIN(INT(((Alpha_keep*$A26+E$3-Lo_c)/Step_c)+0.00000001),193))))*INDEX($D$5:$D$205,MAX(6,MIN(INT(((Alpha_keep*$A26+E$3-Lo_c)/Step_c)+0.00000001),193))+1)+(((Alpha_keep*$A26+E$3-Lo_c)/Step_c)-MAX(6,MIN(INT(((Alpha_keep*$A26+E$3-Lo_c)/Step_c)+0.00000001),193)))*INDEX($D$5:$D$205,MAX(6,MIN(INT(((Alpha_keep*$A26+E$3-Lo_c)/Step_c)+0.00000001),193))+2)),"") -> -541.80331 | F26: =IF(Grid!D26=1,-Cost_k*F$3-Short_p*MAX(0,Floor_c-$A26)+Beta_q*((1-(((Alpha_keep*$A26+F$3-Lo_c)/Step_c)-MAX(6,MIN(INT(((Alpha_keep*$A26+F$3-Lo_c)/Step_c)+0.00000001),193))))*INDEX($D$5:$D$205,MAX(6,MIN(INT(((Alpha_keep*$A26+F$3-Lo_c)/Step_c)+0.00000001),193))+1)+(((Alpha_keep*$A26+F$3-Lo_c)/Step_c)-MAX(6,MIN(INT(((Alpha_keep*$A26+F$3-Lo_c)/Step_c)+0.00000001),193)))*INDEX($D$5:$D$205,MAX(6,MIN(INT(((Alpha_keep*$A26+F$3-Lo_c)/Step_c)+0.00000001),193))+2)),"") -> -538.03941 | G26: =IF(Grid!E26=1,-Cost_k*G$3-Short_p*MAX(0,Floor_c-$A26)+Beta_q*((1-(((Alpha_keep*$A26+G$3-Lo_c)/Step_c)-MAX(6,MIN(INT(((Alpha_keep*$A26+G$3-Lo_c)/Step_c)+0.00000001),193))))*INDEX($D$5:$D$205,MAX(6,MIN(INT(((Alpha_keep*$A26+G$3-Lo_c)/Step_c)+0.00000001),193))+1)+(((Alpha_keep*$A26+G$3-Lo_c)/Step_c)-MAX(6,MIN(INT(((Alpha_keep*$A26+G$3-Lo_c)/Step_c)+0.00000001),193)))*INDEX($D$5:$D$205,MAX(6,MIN(INT(((Alpha_keep*$A26+G$3-Lo_c)/Step_c)+0.00000001),193))+2)),"") -> -534.30054 | H26: =IF(Grid!F26=1,-Cost_k*H$3-Short_p*MAX(0,Floor_c-$A26)+Beta_q*((1-(((Alpha_keep*$A26+H$3-Lo_c)/Step_c)-MAX(6,MIN(INT(((Alpha_keep*$A26+H$3-Lo_c)/Step_c)+0.00000001),193))))*INDEX($D$5:$D$205,MAX(6,MIN(INT(((Alpha_keep*$A26+H$3-Lo_c)/Step_c)+0.00000001),193))+1)+(((Alpha_keep*$A26+H$3-Lo_c)/Step_c)-MAX(6,MIN(INT(((Alpha_keep*$A26+H$3-Lo_c)/Step_c)+0.00000001),193)))*INDEX($D$5:$D$205,MAX(6,MIN(INT(((Alpha_keep*$A26+H$3-Lo_c)/Step_c)+0.00000001),193))+2)),"") -> -530.58694 | I26: =IF(Grid!G26=1,-Cost_k*I$3-Short_p*MAX(0,Floor_c-$A26)+Beta_q*((1-(((Alpha_keep*$A26+I$3-Lo_c)/Step_c)-MAX(6,MIN(INT(((Alpha_keep*$A26+I$3-Lo_c)/Step_c)+0.00000001),193))))*INDEX($D$5:$D$205,MAX(6,MIN(INT(((Alpha_keep*$A26+I$3-Lo_c)/Step_c)+0.00000001),193))+1)+(((Alpha_keep*$A26+I$3-Lo_c)/Step_c)-MAX(6,MIN(INT(((Alpha_keep*$A26+I$3-Lo_c)/Step_c)+0.00000001),193)))*INDEX($D$5:$D$205,MAX(6,MIN(INT(((Alpha_keep*$A26+I$3-Lo_c)/Step_c)+0.00000001),193))+2)),"") -> -526.89893 | J26: =IF(Grid!H26=1,-Cost_k*J$3-Short_p*MAX(0,Floor_c-$A26)+Beta_q*((1-(((Alpha_keep*$A26+J$3-Lo_c)/Step_c)-MAX(6,MIN(INT(((Alpha_keep*$A26+J$3-Lo_c)/Step_c)+0.00000001),193))))*INDEX($D$5:$D$205,MAX(6,MIN(INT(((Alpha_keep*$A26+J$3-Lo_c)/Step_c)+0.00000001),193))+1)+(((Alpha_keep*$A26+J$3-Lo_c)/Step_c)-MAX(6,MIN(INT(((Alpha_keep*$A26+J$3-Lo_c)/Step_c)+0.00000001),193)))*INDEX($D$5:$D$205,MAX(6,MIN(INT(((Alpha_keep*$A26+J$3-Lo_c)/Step_c)+0.00000001),193))+2)),"") -> -523.23684 | K26: =IF(Grid!I26=1,-Cost_k*K$3-Short_p*MAX(0,Floor_c-$A26)+Beta_q*((1-(((Alpha_keep*$A26+K$3-Lo_c)/Step_c)-MAX(6,MIN(INT(((Alpha_keep*$A26+K$3-Lo_c)/Step_c)+0.00000001),193))))*INDEX($D$5:$D$205,MAX(6,MIN(INT(((Alpha_keep*$A26+K$3-Lo_c)/Step_c)+0.00000001),193))+1)+(((Alpha_keep*$A26+K$3-Lo_c)/Step_c)-MAX(6,MIN(INT(((Alpha_keep*$A26+K$3-Lo_c)/Step_c)+0.00000001),193)))*INDEX($D$5:$D$205,MAX(6,MIN(INT(((Alpha_keep*$A26+K$3-Lo_c)/Step_c)+0.00000001),193))+2)),"") -> -519.6009 | L26: =IF(Grid!J26=1,-Cost_k*L$3-Short_p*MAX(0,Floor_c-$A26)+Beta_q*((1-(((Alpha_keep*$A26+L$3-Lo_c)/Step_c)-MAX(6,MIN(INT(((Alpha_keep*$A26+L$3-Lo_c)/Step_c)+0.00000001),193))))*INDEX($D$5:$D$205,MAX(6,MIN(INT(((Alpha_keep*$A26+L$3-Lo_c)/Step_c)+0.00000001),193))+1)+(((Alpha_keep*$A26+L$3-Lo_c)/Step_c)-MAX(6,MIN(INT(((Alpha_keep*$A26+L$3-Lo_c)/Step_c)+0.00000001),193)))*INDEX($D$5:$D$205,MAX(6,MIN(INT(((Alpha_keep*$A26+L$3-Lo_c)/Step_c)+0.00000001),193))+2)),"") -> -515.99141 | ... O26: =IF(Grid!M26=1,-Cost_k*O$3-Short_p*MAX(0,Floor_c-$A26)+Beta_q*((1-(((Alpha_keep*$A26+O$3-Lo_c)/Step_c)-MAX(6,MIN(INT(((Alpha_keep*$A26+O$3-Lo_c)/Step_c)+0.00000001),193))))*INDEX($D$5:$D$205,MAX(6,MIN(INT(((Alpha_keep*$A26+O$3-Lo_c)/Step_c)+0.00000001),193))+1)+(((Alpha_keep*$A26+O$3-Lo_c)/Step_c)-MAX(6,MIN(INT(((Alpha_keep*$A26+O$3-Lo_c)/Step_c)+0.00000001),193)))*INDEX($D$5:$D$205,MAX(6,MIN(INT(((Alpha_keep*$A26+O$3-Lo_c)/Step_c)+0.00000001),193))+2)),"") -> -505.32499 | P26: =MAX(E26:O26) -> -505.32499 | Q26: =INDEX($E$3:$O$3,MATCH(P26,E26:O26,0)) -> 2.5 | R26: 2.5 | S26: =IF(ABS(Q26-R26)<0.000000001,1,0) -> 1 | T26: =ABS(P26-B26) -> 0 | U26: =Alpha_keep*A26+Q26 -> 36.86875 | V26: =INDEX(GuardBlock,22,ROUND(Q26/Step_h,0)+1) -> 1 | W26: 0
A27: =Grid!A27 -> 35.5 | B27: -500.53673 | C27: 22 | D27: =IF(AND($C27>=6,$C27<=194),Declarations!$B$25*INDEX($B$5:$B$205,$C27+1-Declarations!$E$25)+Declarations!$B$26*INDEX($B$5:$B$205,$C27+1-Declarations!$E$26)+Declarations!$B$27*INDEX($B$5:$B$205,$C27+1-Declarations!$E$27)+Declarations!$B$28*INDEX($B$5:$B$205,$C27+1-Declarations!$E$28)+Declarations!$B$29*INDEX($B$5:$B$205,$C27+1-Declarations!$E$29),"") -> -500.63269 | E27: =IF(Grid!C27=1,-Cost_k*E$3-Short_p*MAX(0,Floor_c-$A27)+Beta_q*((1-(((Alpha_keep*$A27+E$3-Lo_c)/Step_c)-MAX(6,MIN(INT(((Alpha_keep*$A27+E$3-Lo_c)/Step_c)+0.00000001),193))))*INDEX($D$5:$D$205,MAX(6,MIN(INT(((Alpha_keep*$A27+E$3-Lo_c)/Step_c)+0.00000001),193))+1)+(((Alpha_keep*$A27+E$3-Lo_c)/Step_c)-MAX(6,MIN(INT(((Alpha_keep*$A27+E$3-Lo_c)/Step_c)+0.00000001),193)))*INDEX($D$5:$D$205,MAX(6,MIN(INT(((Alpha_keep*$A27+E$3-Lo_c)/Step_c)+0.00000001),193))+2)),"") -> -536.75818 | F27: =IF(Grid!D27=1,-Cost_k*F$3-Short_p*MAX(0,Floor_c-$A27)+Beta_q*((1-(((Alpha_keep*$A27+F$3-Lo_c)/Step_c)-MAX(6,MIN(INT(((Alpha_keep*$A27+F$3-Lo_c)/Step_c)+0.00000001),193))))*INDEX($D$5:$D$205,MAX(6,MIN(INT(((Alpha_keep*$A27+F$3-Lo_c)/Step_c)+0.00000001),193))+1)+(((Alpha_keep*$A27+F$3-Lo_c)/Step_c)-MAX(6,MIN(INT(((Alpha_keep*$A27+F$3-Lo_c)/Step_c)+0.00000001),193)))*INDEX($D$5:$D$205,MAX(6,MIN(INT(((Alpha_keep*$A27+F$3-Lo_c)/Step_c)+0.00000001),193))+2)),"") -> -533.01868 | G27: =IF(Grid!E27=1,-Cost_k*G$3-Short_p*MAX(0,Floor_c-$A27)+Beta_q*((1-(((Alpha_keep*$A27+G$3-Lo_c)/Step_c)-MAX(6,MIN(INT(((Alpha_keep*$A27+G$3-Lo_c)/Step_c)+0.00000001),193))))*INDEX($D$5:$D$205,MAX(6,MIN(INT(((Alpha_keep*$A27+G$3-Lo_c)/Step_c)+0.00000001),193))+1)+(((Alpha_keep*$A27+G$3-Lo_c)/Step_c)-MAX(6,MIN(INT(((Alpha_keep*$A27+G$3-Lo_c)/Step_c)+0.00000001),193)))*INDEX($D$5:$D$205,MAX(6,MIN(INT(((Alpha_keep*$A27+G$3-Lo_c)/Step_c)+0.00000001),193))+2)),"") -> -529.30444 | H27: =IF(Grid!F27=1,-Cost_k*H$3-Short_p*MAX(0,Floor_c-$A27)+Beta_q*((1-(((Alpha_keep*$A27+H$3-Lo_c)/Step_c)-MAX(6,MIN(INT(((Alpha_keep*$A27+H$3-Lo_c)/Step_c)+0.00000001),193))))*INDEX($D$5:$D$205,MAX(6,MIN(INT(((Alpha_keep*$A27+H$3-Lo_c)/Step_c)+0.00000001),193))+1)+(((Alpha_keep*$A27+H$3-Lo_c)/Step_c)-MAX(6,MIN(INT(((Alpha_keep*$A27+H$3-Lo_c)/Step_c)+0.00000001),193)))*INDEX($D$5:$D$205,MAX(6,MIN(INT(((Alpha_keep*$A27+H$3-Lo_c)/Step_c)+0.00000001),193))+2)),"") -> -525.61579 | I27: =IF(Grid!G27=1,-Cost_k*I$3-Short_p*MAX(0,Floor_c-$A27)+Beta_q*((1-(((Alpha_keep*$A27+I$3-Lo_c)/Step_c)-MAX(6,MIN(INT(((Alpha_keep*$A27+I$3-Lo_c)/Step_c)+0.00000001),193))))*INDEX($D$5:$D$205,MAX(6,MIN(INT(((Alpha_keep*$A27+I$3-Lo_c)/Step_c)+0.00000001),193))+1)+(((Alpha_keep*$A27+I$3-Lo_c)/Step_c)-MAX(6,MIN(INT(((Alpha_keep*$A27+I$3-Lo_c)/Step_c)+0.00000001),193)))*INDEX($D$5:$D$205,MAX(6,MIN(INT(((Alpha_keep*$A27+I$3-Lo_c)/Step_c)+0.00000001),193))+2)),"") -> -521.95305 | J27: =IF(Grid!H27=1,-Cost_k*J$3-Short_p*MAX(0,Floor_c-$A27)+Beta_q*((1-(((Alpha_keep*$A27+J$3-Lo_c)/Step_c)-MAX(6,MIN(INT(((Alpha_keep*$A27+J$3-Lo_c)/Step_c)+0.00000001),193))))*INDEX($D$5:$D$205,MAX(6,MIN(INT(((Alpha_keep*$A27+J$3-Lo_c)/Step_c)+0.00000001),193))+1)+(((Alpha_keep*$A27+J$3-Lo_c)/Step_c)-MAX(6,MIN(INT(((Alpha_keep*$A27+J$3-Lo_c)/Step_c)+0.00000001),193)))*INDEX($D$5:$D$205,MAX(6,MIN(INT(((Alpha_keep*$A27+J$3-Lo_c)/Step_c)+0.00000001),193))+2)),"") -> -518.31645 | K27: =IF(Grid!I27=1,-Cost_k*K$3-Short_p*MAX(0,Floor_c-$A27)+Beta_q*((1-(((Alpha_keep*$A27+K$3-Lo_c)/Step_c)-MAX(6,MIN(INT(((Alpha_keep*$A27+K$3-Lo_c)/Step_c)+0.00000001),193))))*INDEX($D$5:$D$205,MAX(6,MIN(INT(((Alpha_keep*$A27+K$3-Lo_c)/Step_c)+0.00000001),193))+1)+(((Alpha_keep*$A27+K$3-Lo_c)/Step_c)-MAX(6,MIN(INT(((Alpha_keep*$A27+K$3-Lo_c)/Step_c)+0.00000001),193)))*INDEX($D$5:$D$205,MAX(6,MIN(INT(((Alpha_keep*$A27+K$3-Lo_c)/Step_c)+0.00000001),193))+2)),"") -> -514.7063 | L27: =IF(Grid!J27=1,-Cost_k*L$3-Short_p*MAX(0,Floor_c-$A27)+Beta_q*((1-(((Alpha_keep*$A27+L$3-Lo_c)/Step_c)-MAX(6,MIN(INT(((Alpha_keep*$A27+L$3-Lo_c)/Step_c)+0.00000001),193))))*INDEX($D$5:$D$205,MAX(6,MIN(INT(((Alpha_keep*$A27+L$3-Lo_c)/Step_c)+0.00000001),193))+1)+(((Alpha_keep*$A27+L$3-Lo_c)/Step_c)-MAX(6,MIN(INT(((Alpha_keep*$A27+L$3-Lo_c)/Step_c)+0.00000001),193)))*INDEX($D$5:$D$205,MAX(6,MIN(INT(((Alpha_keep*$A27+L$3-Lo_c)/Step_c)+0.00000001),193))+2)),"") -> -511.12298 | ... O27: =IF(Grid!M27=1,-Cost_k*O$3-Short_p*MAX(0,Floor_c-$A27)+Beta_q*((1-(((Alpha_keep*$A27+O$3-Lo_c)/Step_c)-MAX(6,MIN(INT(((Alpha_keep*$A27+O$3-Lo_c)/Step_c)+0.00000001),193))))*INDEX($D$5:$D$205,MAX(6,MIN(INT(((Alpha_keep*$A27+O$3-Lo_c)/Step_c)+0.00000001),193))+1)+(((Alpha_keep*$A27+O$3-Lo_c)/Step_c)-MAX(6,MIN(INT(((Alpha_keep*$A27+O$3-Lo_c)/Step_c)+0.00000001),193)))*INDEX($D$5:$D$205,MAX(6,MIN(INT(((Alpha_keep*$A27+O$3-Lo_c)/Step_c)+0.00000001),193))+2)),"") -> -500.53673 | P27: =MAX(E27:O27) -> -500.53673 | Q27: =INDEX($E$3:$O$3,MATCH(P27,E27:O27,0)) -> 2.5 | R27: 2.5 | S27: =IF(ABS(Q27-R27)<0.000000001,1,0) -> 1 | T27: =ABS(P27-B27) -> 0 | U27: =Alpha_keep*A27+Q27 -> 37.1125 | V27: =INDEX(GuardBlock,23,ROUND(Q27/Step_h,0)+1) -> 1 | W27: 0
A28: =Grid!A28 -> 35.75 | B28: -495.77512 | C28: 23 | D28: =IF(AND($C28>=6,$C28<=194),Declarations!$B$25*INDEX($B$5:$B$205,$C28+1-Declarations!$E$25)+Declarations!$B$26*INDEX($B$5:$B$205,$C28+1-Declarations!$E$26)+Declarations!$B$27*INDEX($B$5:$B$205,$C28+1-Declarations!$E$27)+Declarations!$B$28*INDEX($B$5:$B$205,$C28+1-Declarations!$E$28)+Declarations!$B$29*INDEX($B$5:$B$205,$C28+1-Declarations!$E$29),"") -> -495.87218 | E28: =IF(Grid!C28=1,-Cost_k*E$3-Short_p*MAX(0,Floor_c-$A28)+Beta_q*((1-(((Alpha_keep*$A28+E$3-Lo_c)/Step_c)-MAX(6,MIN(INT(((Alpha_keep*$A28+E$3-Lo_c)/Step_c)+0.00000001),193))))*INDEX($D$5:$D$205,MAX(6,MIN(INT(((Alpha_keep*$A28+E$3-Lo_c)/Step_c)+0.00000001),193))+1)+(((Alpha_keep*$A28+E$3-Lo_c)/Step_c)-MAX(6,MIN(INT(((Alpha_keep*$A28+E$3-Lo_c)/Step_c)+0.00000001),193)))*INDEX($D$5:$D$205,MAX(6,MIN(INT(((Alpha_keep*$A28+E$3-Lo_c)/Step_c)+0.00000001),193))+2)),"") -> -531.73682 | F28: =IF(Grid!D28=1,-Cost_k*F$3-Short_p*MAX(0,Floor_c-$A28)+Beta_q*((1-(((Alpha_keep*$A28+F$3-Lo_c)/Step_c)-MAX(6,MIN(INT(((Alpha_keep*$A28+F$3-Lo_c)/Step_c)+0.00000001),193))))*INDEX($D$5:$D$205,MAX(6,MIN(INT(((Alpha_keep*$A28+F$3-Lo_c)/Step_c)+0.00000001),193))+1)+(((Alpha_keep*$A28+F$3-Lo_c)/Step_c)-MAX(6,MIN(INT(((Alpha_keep*$A28+F$3-Lo_c)/Step_c)+0.00000001),193)))*INDEX($D$5:$D$205,MAX(6,MIN(INT(((Alpha_keep*$A28+F$3-Lo_c)/Step_c)+0.00000001),193))+2)),"") -> -528.02195 | G28: =IF(Grid!E28=1,-Cost_k*G$3-Short_p*MAX(0,Floor_c-$A28)+Beta_q*((1-(((Alpha_keep*$A28+G$3-Lo_c)/Step_c)-MAX(6,MIN(INT(((Alpha_keep*$A28+G$3-Lo_c)/Step_c)+0.00000001),193))))*INDEX($D$5:$D$205,MAX(6,MIN(INT(((Alpha_keep*$A28+G$3-Lo_c)/Step_c)+0.00000001),193))+1)+(((Alpha_keep*$A28+G$3-Lo_c)/Step_c)-MAX(6,MIN(INT(((Alpha_keep*$A28+G$3-Lo_c)/Step_c)+0.00000001),193)))*INDEX($D$5:$D$205,MAX(6,MIN(INT(((Alpha_keep*$A28+G$3-Lo_c)/Step_c)+0.00000001),193))+2)),"") -> -524.33265 | H28: =IF(Grid!F28=1,-Cost_k*H$3-Short_p*MAX(0,Floor_c-$A28)+Beta_q*((1-(((Alpha_keep*$A28+H$3-Lo_c)/Step_c)-MAX(6,MIN(INT(((Alpha_keep*$A28+H$3-Lo_c)/Step_c)+0.00000001),193))))*INDEX($D$5:$D$205,MAX(6,MIN(INT(((Alpha_keep*$A28+H$3-Lo_c)/Step_c)+0.00000001),193))+1)+(((Alpha_keep*$A28+H$3-Lo_c)/Step_c)-MAX(6,MIN(INT(((Alpha_keep*$A28+H$3-Lo_c)/Step_c)+0.00000001),193)))*INDEX($D$5:$D$205,MAX(6,MIN(INT(((Alpha_keep*$A28+H$3-Lo_c)/Step_c)+0.00000001),193))+2)),"") -> -520.66926 | I28: =IF(Grid!G28=1,-Cost_k*I$3-Short_p*MAX(0,Floor_c-$A28)+Beta_q*((1-(((Alpha_keep*$A28+I$3-Lo_c)/Step_c)-MAX(6,MIN(INT(((Alpha_keep*$A28+I$3-Lo_c)/Step_c)+0.00000001),193))))*INDEX($D$5:$D$205,MAX(6,MIN(INT(((Alpha_keep*$A28+I$3-Lo_c)/Step_c)+0.00000001),193))+1)+(((Alpha_keep*$A28+I$3-Lo_c)/Step_c)-MAX(6,MIN(INT(((Alpha_keep*$A28+I$3-Lo_c)/Step_c)+0.00000001),193)))*INDEX($D$5:$D$205,MAX(6,MIN(INT(((Alpha_keep*$A28+I$3-Lo_c)/Step_c)+0.00000001),193))+2)),"") -> -517.032 | J28: =IF(Grid!H28=1,-Cost_k*J$3-Short_p*MAX(0,Floor_c-$A28)+Beta_q*((1-(((Alpha_keep*$A28+J$3-Lo_c)/Step_c)-MAX(6,MIN(INT(((Alpha_keep*$A28+J$3-Lo_c)/Step_c)+0.00000001),193))))*INDEX($D$5:$D$205,MAX(6,MIN(INT(((Alpha_keep*$A28+J$3-Lo_c)/Step_c)+0.00000001),193))+1)+(((Alpha_keep*$A28+J$3-Lo_c)/Step_c)-MAX(6,MIN(INT(((Alpha_keep*$A28+J$3-Lo_c)/Step_c)+0.00000001),193)))*INDEX($D$5:$D$205,MAX(6,MIN(INT(((Alpha_keep*$A28+J$3-Lo_c)/Step_c)+0.00000001),193))+2)),"") -> -513.42119 | K28: =IF(Grid!I28=1,-Cost_k*K$3-Short_p*MAX(0,Floor_c-$A28)+Beta_q*((1-(((Alpha_keep*$A28+K$3-Lo_c)/Step_c)-MAX(6,MIN(INT(((Alpha_keep*$A28+K$3-Lo_c)/Step_c)+0.00000001),193))))*INDEX($D$5:$D$205,MAX(6,MIN(INT(((Alpha_keep*$A28+K$3-Lo_c)/Step_c)+0.00000001),193))+1)+(((Alpha_keep*$A28+K$3-Lo_c)/Step_c)-MAX(6,MIN(INT(((Alpha_keep*$A28+K$3-Lo_c)/Step_c)+0.00000001),193)))*INDEX($D$5:$D$205,MAX(6,MIN(INT(((Alpha_keep*$A28+K$3-Lo_c)/Step_c)+0.00000001),193))+2)),"") -> -509.83719 | L28: =IF(Grid!J28=1,-Cost_k*L$3-Short_p*MAX(0,Floor_c-$A28)+Beta_q*((1-(((Alpha_keep*$A28+L$3-Lo_c)/Step_c)-MAX(6,MIN(INT(((Alpha_keep*$A28+L$3-Lo_c)/Step_c)+0.00000001),193))))*INDEX($D$5:$D$205,MAX(6,MIN(INT(((Alpha_keep*$A28+L$3-Lo_c)/Step_c)+0.00000001),193))+1)+(((Alpha_keep*$A28+L$3-Lo_c)/Step_c)-MAX(6,MIN(INT(((Alpha_keep*$A28+L$3-Lo_c)/Step_c)+0.00000001),193)))*INDEX($D$5:$D$205,MAX(6,MIN(INT(((Alpha_keep*$A28+L$3-Lo_c)/Step_c)+0.00000001),193))+2)),"") -> -506.28026 | ... O28: =IF(Grid!M28=1,-Cost_k*O$3-Short_p*MAX(0,Floor_c-$A28)+Beta_q*((1-(((Alpha_keep*$A28+O$3-Lo_c)/Step_c)-MAX(6,MIN(INT(((Alpha_keep*$A28+O$3-Lo_c)/Step_c)+0.00000001),193))))*INDEX($D$5:$D$205,MAX(6,MIN(INT(((Alpha_keep*$A28+O$3-Lo_c)/Step_c)+0.00000001),193))+1)+(((Alpha_keep*$A28+O$3-Lo_c)/Step_c)-MAX(6,MIN(INT(((Alpha_keep*$A28+O$3-Lo_c)/Step_c)+0.00000001),193)))*INDEX($D$5:$D$205,MAX(6,MIN(INT(((Alpha_keep*$A28+O$3-Lo_c)/Step_c)+0.00000001),193))+2)),"") -> -495.77512 | P28: =MAX(E28:O28) -> -495.77512 | Q28: =INDEX($E$3:$O$3,MATCH(P28,E28:O28,0)) -> 2.5 | R28: 2.5 | S28: =IF(ABS(Q28-R28)<0.000000001,1,0) -> 1 | T28: =ABS(P28-B28) -> 0 | U28: =Alpha_keep*A28+Q28 -> 37.35625 | V28: =INDEX(GuardBlock,24,ROUND(Q28/Step_h,0)+1) -> 1 | W28: 0
A29: =Grid!A29 -> 36 | B29: -491.04039 | C29: 24 | D29: =IF(AND($C29>=6,$C29<=194),Declarations!$B$25*INDEX($B$5:$B$205,$C29+1-Declarations!$E$25)+Declarations!$B$26*INDEX($B$5:$B$205,$C29+1-Declarations!$E$26)+Declarations!$B$27*INDEX($B$5:$B$205,$C29+1-Declarations!$E$27)+Declarations!$B$28*INDEX($B$5:$B$205,$C29+1-Declarations!$E$28)+Declarations!$B$29*INDEX($B$5:$B$205,$C29+1-Declarations!$E$29),"") -> -491.13857 | E29: =IF(Grid!C29=1,-Cost_k*E$3-Short_p*MAX(0,Floor_c-$A29)+Beta_q*((1-(((Alpha_keep*$A29+E$3-Lo_c)/Step_c)-MAX(6,MIN(INT(((Alpha_keep*$A29+E$3-Lo_c)/Step_c)+0.00000001),193))))*INDEX($D$5:$D$205,MAX(6,MIN(INT(((Alpha_keep*$A29+E$3-Lo_c)/Step_c)+0.00000001),193))+1)+(((Alpha_keep*$A29+E$3-Lo_c)/Step_c)-MAX(6,MIN(INT(((Alpha_keep*$A29+E$3-Lo_c)/Step_c)+0.00000001),193)))*INDEX($D$5:$D$205,MAX(6,MIN(INT(((Alpha_keep*$A29+E$3-Lo_c)/Step_c)+0.00000001),193))+2)),"") -> -526.73946 | F29: =IF(Grid!D29=1,-Cost_k*F$3-Short_p*MAX(0,Floor_c-$A29)+Beta_q*((1-(((Alpha_keep*$A29+F$3-Lo_c)/Step_c)-MAX(6,MIN(INT(((Alpha_keep*$A29+F$3-Lo_c)/Step_c)+0.00000001),193))))*INDEX($D$5:$D$205,MAX(6,MIN(INT(((Alpha_keep*$A29+F$3-Lo_c)/Step_c)+0.00000001),193))+1)+(((Alpha_keep*$A29+F$3-Lo_c)/Step_c)-MAX(6,MIN(INT(((Alpha_keep*$A29+F$3-Lo_c)/Step_c)+0.00000001),193)))*INDEX($D$5:$D$205,MAX(6,MIN(INT(((Alpha_keep*$A29+F$3-Lo_c)/Step_c)+0.00000001),193))+2)),"") -> -523.04951 | G29: =IF(Grid!E29=1,-Cost_k*G$3-Short_p*MAX(0,Floor_c-$A29)+Beta_q*((1-(((Alpha_keep*$A29+G$3-Lo_c)/Step_c)-MAX(6,MIN(INT(((Alpha_keep*$A29+G$3-Lo_c)/Step_c)+0.00000001),193))))*INDEX($D$5:$D$205,MAX(6,MIN(INT(((Alpha_keep*$A29+G$3-Lo_c)/Step_c)+0.00000001),193))+1)+(((Alpha_keep*$A29+G$3-Lo_c)/Step_c)-MAX(6,MIN(INT(((Alpha_keep*$A29+G$3-Lo_c)/Step_c)+0.00000001),193)))*INDEX($D$5:$D$205,MAX(6,MIN(INT(((Alpha_keep*$A29+G$3-Lo_c)/Step_c)+0.00000001),193))+2)),"") -> -519.38547 | H29: =IF(Grid!F29=1,-Cost_k*H$3-Short_p*MAX(0,Floor_c-$A29)+Beta_q*((1-(((Alpha_keep*$A29+H$3-Lo_c)/Step_c)-MAX(6,MIN(INT(((Alpha_keep*$A29+H$3-Lo_c)/Step_c)+0.00000001),193))))*INDEX($D$5:$D$205,MAX(6,MIN(INT(((Alpha_keep*$A29+H$3-Lo_c)/Step_c)+0.00000001),193))+1)+(((Alpha_keep*$A29+H$3-Lo_c)/Step_c)-MAX(6,MIN(INT(((Alpha_keep*$A29+H$3-Lo_c)/Step_c)+0.00000001),193)))*INDEX($D$5:$D$205,MAX(6,MIN(INT(((Alpha_keep*$A29+H$3-Lo_c)/Step_c)+0.00000001),193))+2)),"") -> -515.74756 | I29: =IF(Grid!G29=1,-Cost_k*I$3-Short_p*MAX(0,Floor_c-$A29)+Beta_q*((1-(((Alpha_keep*$A29+I$3-Lo_c)/Step_c)-MAX(6,MIN(INT(((Alpha_keep*$A29+I$3-Lo_c)/Step_c)+0.00000001),193))))*INDEX($D$5:$D$205,MAX(6,MIN(INT(((Alpha_keep*$A29+I$3-Lo_c)/Step_c)+0.00000001),193))+1)+(((Alpha_keep*$A29+I$3-Lo_c)/Step_c)-MAX(6,MIN(INT(((Alpha_keep*$A29+I$3-Lo_c)/Step_c)+0.00000001),193)))*INDEX($D$5:$D$205,MAX(6,MIN(INT(((Alpha_keep*$A29+I$3-Lo_c)/Step_c)+0.00000001),193))+2)),"") -> -512.13607 | J29: =IF(Grid!H29=1,-Cost_k*J$3-Short_p*MAX(0,Floor_c-$A29)+Beta_q*((1-(((Alpha_keep*$A29+J$3-Lo_c)/Step_c)-MAX(6,MIN(INT(((Alpha_keep*$A29+J$3-Lo_c)/Step_c)+0.00000001),193))))*INDEX($D$5:$D$205,MAX(6,MIN(INT(((Alpha_keep*$A29+J$3-Lo_c)/Step_c)+0.00000001),193))+1)+(((Alpha_keep*$A29+J$3-Lo_c)/Step_c)-MAX(6,MIN(INT(((Alpha_keep*$A29+J$3-Lo_c)/Step_c)+0.00000001),193)))*INDEX($D$5:$D$205,MAX(6,MIN(INT(((Alpha_keep*$A29+J$3-Lo_c)/Step_c)+0.00000001),193))+2)),"") -> -508.5514 | K29: =IF(Grid!I29=1,-Cost_k*K$3-Short_p*MAX(0,Floor_c-$A29)+Beta_q*((1-(((Alpha_keep*$A29+K$3-Lo_c)/Step_c)-MAX(6,MIN(INT(((Alpha_keep*$A29+K$3-Lo_c)/Step_c)+0.00000001),193))))*INDEX($D$5:$D$205,MAX(6,MIN(INT(((Alpha_keep*$A29+K$3-Lo_c)/Step_c)+0.00000001),193))+1)+(((Alpha_keep*$A29+K$3-Lo_c)/Step_c)-MAX(6,MIN(INT(((Alpha_keep*$A29+K$3-Lo_c)/Step_c)+0.00000001),193)))*INDEX($D$5:$D$205,MAX(6,MIN(INT(((Alpha_keep*$A29+K$3-Lo_c)/Step_c)+0.00000001),193))+2)),"") -> -504.9938 | L29: =IF(Grid!J29=1,-Cost_k*L$3-Short_p*MAX(0,Floor_c-$A29)+Beta_q*((1-(((Alpha_keep*$A29+L$3-Lo_c)/Step_c)-MAX(6,MIN(INT(((Alpha_keep*$A29+L$3-Lo_c)/Step_c)+0.00000001),193))))*INDEX($D$5:$D$205,MAX(6,MIN(INT(((Alpha_keep*$A29+L$3-Lo_c)/Step_c)+0.00000001),193))+1)+(((Alpha_keep*$A29+L$3-Lo_c)/Step_c)-MAX(6,MIN(INT(((Alpha_keep*$A29+L$3-Lo_c)/Step_c)+0.00000001),193)))*INDEX($D$5:$D$205,MAX(6,MIN(INT(((Alpha_keep*$A29+L$3-Lo_c)/Step_c)+0.00000001),193))+2)),"") -> -501.46352 | ... O29: =IF(Grid!M29=1,-Cost_k*O$3-Short_p*MAX(0,Floor_c-$A29)+Beta_q*((1-(((Alpha_keep*$A29+O$3-Lo_c)/Step_c)-MAX(6,MIN(INT(((Alpha_keep*$A29+O$3-Lo_c)/Step_c)+0.00000001),193))))*INDEX($D$5:$D$205,MAX(6,MIN(INT(((Alpha_keep*$A29+O$3-Lo_c)/Step_c)+0.00000001),193))+1)+(((Alpha_keep*$A29+O$3-Lo_c)/Step_c)-MAX(6,MIN(INT(((Alpha_keep*$A29+O$3-Lo_c)/Step_c)+0.00000001),193)))*INDEX($D$5:$D$205,MAX(6,MIN(INT(((Alpha_keep*$A29+O$3-Lo_c)/Step_c)+0.00000001),193))+2)),"") -> -491.04039 | P29: =MAX(E29:O29) -> -491.04039 | Q29: =INDEX($E$3:$O$3,MATCH(P29,E29:O29,0)) -> 2.5 | R29: 2.5 | S29: =IF(ABS(Q29-R29)<0.000000001,1,0) -> 1 | T29: =ABS(P29-B29) -> 0 | U29: =Alpha_keep*A29+Q29 -> 37.6 | V29: =INDEX(GuardBlock,25,ROUND(Q29/Step_h,0)+1) -> 1 | W29: 0
A30: =Grid!A30 -> 36.25 | B30: -486.33296 | C30: 25 | D30: =IF(AND($C30>=6,$C30<=194),Declarations!$B$25*INDEX($B$5:$B$205,$C30+1-Declarations!$E$25)+Declarations!$B$26*INDEX($B$5:$B$205,$C30+1-Declarations!$E$26)+Declarations!$B$27*INDEX($B$5:$B$205,$C30+1-Declarations!$E$27)+Declarations!$B$28*INDEX($B$5:$B$205,$C30+1-Declarations!$E$28)+Declarations!$B$29*INDEX($B$5:$B$205,$C30+1-Declarations!$E$29),"") -> -486.43228 | E30: =IF(Grid!C30=1,-Cost_k*E$3-Short_p*MAX(0,Floor_c-$A30)+Beta_q*((1-(((Alpha_keep*$A30+E$3-Lo_c)/Step_c)-MAX(6,MIN(INT(((Alpha_keep*$A30+E$3-Lo_c)/Step_c)+0.00000001),193))))*INDEX($D$5:$D$205,MAX(6,MIN(INT(((Alpha_keep*$A30+E$3-Lo_c)/Step_c)+0.00000001),193))+1)+(((Alpha_keep*$A30+E$3-Lo_c)/Step_c)-MAX(6,MIN(INT(((Alpha_keep*$A30+E$3-Lo_c)/Step_c)+0.00000001),193)))*INDEX($D$5:$D$205,MAX(6,MIN(INT(((Alpha_keep*$A30+E$3-Lo_c)/Step_c)+0.00000001),193))+2)),"") -> -521.76638 | F30: =IF(Grid!D30=1,-Cost_k*F$3-Short_p*MAX(0,Floor_c-$A30)+Beta_q*((1-(((Alpha_keep*$A30+F$3-Lo_c)/Step_c)-MAX(6,MIN(INT(((Alpha_keep*$A30+F$3-Lo_c)/Step_c)+0.00000001),193))))*INDEX($D$5:$D$205,MAX(6,MIN(INT(((Alpha_keep*$A30+F$3-Lo_c)/Step_c)+0.00000001),193))+1)+(((Alpha_keep*$A30+F$3-Lo_c)/Step_c)-MAX(6,MIN(INT(((Alpha_keep*$A30+F$3-Lo_c)/Step_c)+0.00000001),193)))*INDEX($D$5:$D$205,MAX(6,MIN(INT(((Alpha_keep*$A30+F$3-Lo_c)/Step_c)+0.00000001),193))+2)),"") -> -518.10168 | G30: =IF(Grid!E30=1,-Cost_k*G$3-Short_p*MAX(0,Floor_c-$A30)+Beta_q*((1-(((Alpha_keep*$A30+G$3-Lo_c)/Step_c)-MAX(6,MIN(INT(((Alpha_keep*$A30+G$3-Lo_c)/Step_c)+0.00000001),193))))*INDEX($D$5:$D$205,MAX(6,MIN(INT(((Alpha_keep*$A30+G$3-Lo_c)/Step_c)+0.00000001),193))+1)+(((Alpha_keep*$A30+G$3-Lo_c)/Step_c)-MAX(6,MIN(INT(((Alpha_keep*$A30+G$3-Lo_c)/Step_c)+0.00000001),193)))*INDEX($D$5:$D$205,MAX(6,MIN(INT(((Alpha_keep*$A30+G$3-Lo_c)/Step_c)+0.00000001),193))+2)),"") -> -514.46311 | H30: =IF(Grid!F30=1,-Cost_k*H$3-Short_p*MAX(0,Floor_c-$A30)+Beta_q*((1-(((Alpha_keep*$A30+H$3-Lo_c)/Step_c)-MAX(6,MIN(INT(((Alpha_keep*$A30+H$3-Lo_c)/Step_c)+0.00000001),193))))*INDEX($D$5:$D$205,MAX(6,MIN(INT(((Alpha_keep*$A30+H$3-Lo_c)/Step_c)+0.00000001),193))+1)+(((Alpha_keep*$A30+H$3-Lo_c)/Step_c)-MAX(6,MIN(INT(((Alpha_keep*$A30+H$3-Lo_c)/Step_c)+0.00000001),193)))*INDEX($D$5:$D$205,MAX(6,MIN(INT(((Alpha_keep*$A30+H$3-Lo_c)/Step_c)+0.00000001),193))+2)),"") -> -510.85096 | I30: =IF(Grid!G30=1,-Cost_k*I$3-Short_p*MAX(0,Floor_c-$A30)+Beta_q*((1-(((Alpha_keep*$A30+I$3-Lo_c)/Step_c)-MAX(6,MIN(INT(((Alpha_keep*$A30+I$3-Lo_c)/Step_c)+0.00000001),193))))*INDEX($D$5:$D$205,MAX(6,MIN(INT(((Alpha_keep*$A30+I$3-Lo_c)/Step_c)+0.00000001),193))+1)+(((Alpha_keep*$A30+I$3-Lo_c)/Step_c)-MAX(6,MIN(INT(((Alpha_keep*$A30+I$3-Lo_c)/Step_c)+0.00000001),193)))*INDEX($D$5:$D$205,MAX(6,MIN(INT(((Alpha_keep*$A30+I$3-Lo_c)/Step_c)+0.00000001),193))+2)),"") -> -507.26561 | J30: =IF(Grid!H30=1,-Cost_k*J$3-Short_p*MAX(0,Floor_c-$A30)+Beta_q*((1-(((Alpha_keep*$A30+J$3-Lo_c)/Step_c)-MAX(6,MIN(INT(((Alpha_keep*$A30+J$3-Lo_c)/Step_c)+0.00000001),193))))*INDEX($D$5:$D$205,MAX(6,MIN(INT(((Alpha_keep*$A30+J$3-Lo_c)/Step_c)+0.00000001),193))+1)+(((Alpha_keep*$A30+J$3-Lo_c)/Step_c)-MAX(6,MIN(INT(((Alpha_keep*$A30+J$3-Lo_c)/Step_c)+0.00000001),193)))*INDEX($D$5:$D$205,MAX(6,MIN(INT(((Alpha_keep*$A30+J$3-Lo_c)/Step_c)+0.00000001),193))+2)),"") -> -503.70733 | K30: =IF(Grid!I30=1,-Cost_k*K$3-Short_p*MAX(0,Floor_c-$A30)+Beta_q*((1-(((Alpha_keep*$A30+K$3-Lo_c)/Step_c)-MAX(6,MIN(INT(((Alpha_keep*$A30+K$3-Lo_c)/Step_c)+0.00000001),193))))*INDEX($D$5:$D$205,MAX(6,MIN(INT(((Alpha_keep*$A30+K$3-Lo_c)/Step_c)+0.00000001),193))+1)+(((Alpha_keep*$A30+K$3-Lo_c)/Step_c)-MAX(6,MIN(INT(((Alpha_keep*$A30+K$3-Lo_c)/Step_c)+0.00000001),193)))*INDEX($D$5:$D$205,MAX(6,MIN(INT(((Alpha_keep*$A30+K$3-Lo_c)/Step_c)+0.00000001),193))+2)),"") -> -500.17637 | L30: =IF(Grid!J30=1,-Cost_k*L$3-Short_p*MAX(0,Floor_c-$A30)+Beta_q*((1-(((Alpha_keep*$A30+L$3-Lo_c)/Step_c)-MAX(6,MIN(INT(((Alpha_keep*$A30+L$3-Lo_c)/Step_c)+0.00000001),193))))*INDEX($D$5:$D$205,MAX(6,MIN(INT(((Alpha_keep*$A30+L$3-Lo_c)/Step_c)+0.00000001),193))+1)+(((Alpha_keep*$A30+L$3-Lo_c)/Step_c)-MAX(6,MIN(INT(((Alpha_keep*$A30+L$3-Lo_c)/Step_c)+0.00000001),193)))*INDEX($D$5:$D$205,MAX(6,MIN(INT(((Alpha_keep*$A30+L$3-Lo_c)/Step_c)+0.00000001),193))+2)),"") -> -496.67316 | ... O30: =IF(Grid!M30=1,-Cost_k*O$3-Short_p*MAX(0,Floor_c-$A30)+Beta_q*((1-(((Alpha_keep*$A30+O$3-Lo_c)/Step_c)-MAX(6,MIN(INT(((Alpha_keep*$A30+O$3-Lo_c)/Step_c)+0.00000001),193))))*INDEX($D$5:$D$205,MAX(6,MIN(INT(((Alpha_keep*$A30+O$3-Lo_c)/Step_c)+0.00000001),193))+1)+(((Alpha_keep*$A30+O$3-Lo_c)/Step_c)-MAX(6,MIN(INT(((Alpha_keep*$A30+O$3-Lo_c)/Step_c)+0.00000001),193)))*INDEX($D$5:$D$205,MAX(6,MIN(INT(((Alpha_keep*$A30+O$3-Lo_c)/Step_c)+0.00000001),193))+2)),"") -> -486.33296 | P30: =MAX(E30:O30) -> -486.33296 | Q30: =INDEX($E$3:$O$3,MATCH(P30,E30:O30,0)) -> 2.5 | R30: 2.5 | S30: =IF(ABS(Q30-R30)<0.000000001,1,0) -> 1 | T30: =ABS(P30-B30) -> 0 | U30: =Alpha_keep*A30+Q30 -> 37.84375 | V30: =INDEX(GuardBlock,26,ROUND(Q30/Step_h,0)+1) -> 1 | W30: 0
A31: =Grid!A31 -> 36.5 | B31: -481.65318 | C31: 26 | D31: =IF(AND($C31>=6,$C31<=194),Declarations!$B$25*INDEX($B$5:$B$205,$C31+1-Declarations!$E$25)+Declarations!$B$26*INDEX($B$5:$B$205,$C31+1-Declarations!$E$26)+Declarations!$B$27*INDEX($B$5:$B$205,$C31+1-Declarations!$E$27)+Declarations!$B$28*INDEX($B$5:$B$205,$C31+1-Declarations!$E$28)+Declarations!$B$29*INDEX($B$5:$B$205,$C31+1-Declarations!$E$29),"") -> -481.75365 | E31: =IF(Grid!C31=1,-Cost_k*E$3-Short_p*MAX(0,Floor_c-$A31)+Beta_q*((1-(((Alpha_keep*$A31+E$3-Lo_c)/Step_c)-MAX(6,MIN(INT(((Alpha_keep*$A31+E$3-Lo_c)/Step_c)+0.00000001),193))))*INDEX($D$5:$D$205,MAX(6,MIN(INT(((Alpha_keep*$A31+E$3-Lo_c)/Step_c)+0.00000001),193))+1)+(((Alpha_keep*$A31+E$3-Lo_c)/Step_c)-MAX(6,MIN(INT(((Alpha_keep*$A31+E$3-Lo_c)/Step_c)+0.00000001),193)))*INDEX($D$5:$D$205,MAX(6,MIN(INT(((Alpha_keep*$A31+E$3-Lo_c)/Step_c)+0.00000001),193))+2)),"") -> -516.81789 | F31: =IF(Grid!D31=1,-Cost_k*F$3-Short_p*MAX(0,Floor_c-$A31)+Beta_q*((1-(((Alpha_keep*$A31+F$3-Lo_c)/Step_c)-MAX(6,MIN(INT(((Alpha_keep*$A31+F$3-Lo_c)/Step_c)+0.00000001),193))))*INDEX($D$5:$D$205,MAX(6,MIN(INT(((Alpha_keep*$A31+F$3-Lo_c)/Step_c)+0.00000001),193))+1)+(((Alpha_keep*$A31+F$3-Lo_c)/Step_c)-MAX(6,MIN(INT(((Alpha_keep*$A31+F$3-Lo_c)/Step_c)+0.00000001),193)))*INDEX($D$5:$D$205,MAX(6,MIN(INT(((Alpha_keep*$A31+F$3-Lo_c)/Step_c)+0.00000001),193))+2)),"") -> -513.17867 | G31: =IF(Grid!E31=1,-Cost_k*G$3-Short_p*MAX(0,Floor_c-$A31)+Beta_q*((1-(((Alpha_keep*$A31+G$3-Lo_c)/Step_c)-MAX(6,MIN(INT(((Alpha_keep*$A31+G$3-Lo_c)/Step_c)+0.00000001),193))))*INDEX($D$5:$D$205,MAX(6,MIN(INT(((Alpha_keep*$A31+G$3-Lo_c)/Step_c)+0.00000001),193))+1)+(((Alpha_keep*$A31+G$3-Lo_c)/Step_c)-MAX(6,MIN(INT(((Alpha_keep*$A31+G$3-Lo_c)/Step_c)+0.00000001),193)))*INDEX($D$5:$D$205,MAX(6,MIN(INT(((Alpha_keep*$A31+G$3-Lo_c)/Step_c)+0.00000001),193))+2)),"") -> -509.56585 | H31: =IF(Grid!F31=1,-Cost_k*H$3-Short_p*MAX(0,Floor_c-$A31)+Beta_q*((1-(((Alpha_keep*$A31+H$3-Lo_c)/Step_c)-MAX(6,MIN(INT(((Alpha_keep*$A31+H$3-Lo_c)/Step_c)+0.00000001),193))))*INDEX($D$5:$D$205,MAX(6,MIN(INT(((Alpha_keep*$A31+H$3-Lo_c)/Step_c)+0.00000001),193))+1)+(((Alpha_keep*$A31+H$3-Lo_c)/Step_c)-MAX(6,MIN(INT(((Alpha_keep*$A31+H$3-Lo_c)/Step_c)+0.00000001),193)))*INDEX($D$5:$D$205,MAX(6,MIN(INT(((Alpha_keep*$A31+H$3-Lo_c)/Step_c)+0.00000001),193))+2)),"") -> -505.97982 | I31: =IF(Grid!G31=1,-Cost_k*I$3-Short_p*MAX(0,Floor_c-$A31)+Beta_q*((1-(((Alpha_keep*$A31+I$3-Lo_c)/Step_c)-MAX(6,MIN(INT(((Alpha_keep*$A31+I$3-Lo_c)/Step_c)+0.00000001),193))))*INDEX($D$5:$D$205,MAX(6,MIN(INT(((Alpha_keep*$A31+I$3-Lo_c)/Step_c)+0.00000001),193))+1)+(((Alpha_keep*$A31+I$3-Lo_c)/Step_c)-MAX(6,MIN(INT(((Alpha_keep*$A31+I$3-Lo_c)/Step_c)+0.00000001),193)))*INDEX($D$5:$D$205,MAX(6,MIN(INT(((Alpha_keep*$A31+I$3-Lo_c)/Step_c)+0.00000001),193))+2)),"") -> -502.42086 | J31: =IF(Grid!H31=1,-Cost_k*J$3-Short_p*MAX(0,Floor_c-$A31)+Beta_q*((1-(((Alpha_keep*$A31+J$3-Lo_c)/Step_c)-MAX(6,MIN(INT(((Alpha_keep*$A31+J$3-Lo_c)/Step_c)+0.00000001),193))))*INDEX($D$5:$D$205,MAX(6,MIN(INT(((Alpha_keep*$A31+J$3-Lo_c)/Step_c)+0.00000001),193))+1)+(((Alpha_keep*$A31+J$3-Lo_c)/Step_c)-MAX(6,MIN(INT(((Alpha_keep*$A31+J$3-Lo_c)/Step_c)+0.00000001),193)))*INDEX($D$5:$D$205,MAX(6,MIN(INT(((Alpha_keep*$A31+J$3-Lo_c)/Step_c)+0.00000001),193))+2)),"") -> -498.88921 | K31: =IF(Grid!I31=1,-Cost_k*K$3-Short_p*MAX(0,Floor_c-$A31)+Beta_q*((1-(((Alpha_keep*$A31+K$3-Lo_c)/Step_c)-MAX(6,MIN(INT(((Alpha_keep*$A31+K$3-Lo_c)/Step_c)+0.00000001),193))))*INDEX($D$5:$D$205,MAX(6,MIN(INT(((Alpha_keep*$A31+K$3-Lo_c)/Step_c)+0.00000001),193))+1)+(((Alpha_keep*$A31+K$3-Lo_c)/Step_c)-MAX(6,MIN(INT(((Alpha_keep*$A31+K$3-Lo_c)/Step_c)+0.00000001),193)))*INDEX($D$5:$D$205,MAX(6,MIN(INT(((Alpha_keep*$A31+K$3-Lo_c)/Step_c)+0.00000001),193))+2)),"") -> -495.3853 | L31: =IF(Grid!J31=1,-Cost_k*L$3-Short_p*MAX(0,Floor_c-$A31)+Beta_q*((1-(((Alpha_keep*$A31+L$3-Lo_c)/Step_c)-MAX(6,MIN(INT(((Alpha_keep*$A31+L$3-Lo_c)/Step_c)+0.00000001),193))))*INDEX($D$5:$D$205,MAX(6,MIN(INT(((Alpha_keep*$A31+L$3-Lo_c)/Step_c)+0.00000001),193))+1)+(((Alpha_keep*$A31+L$3-Lo_c)/Step_c)-MAX(6,MIN(INT(((Alpha_keep*$A31+L$3-Lo_c)/Step_c)+0.00000001),193)))*INDEX($D$5:$D$205,MAX(6,MIN(INT(((Alpha_keep*$A31+L$3-Lo_c)/Step_c)+0.00000001),193))+2)),"") -> -491.90944 | ... O31: =IF(Grid!M31=1,-Cost_k*O$3-Short_p*MAX(0,Floor_c-$A31)+Beta_q*((1-(((Alpha_keep*$A31+O$3-Lo_c)/Step_c)-MAX(6,MIN(INT(((Alpha_keep*$A31+O$3-Lo_c)/Step_c)+0.00000001),193))))*INDEX($D$5:$D$205,MAX(6,MIN(INT(((Alpha_keep*$A31+O$3-Lo_c)/Step_c)+0.00000001),193))+1)+(((Alpha_keep*$A31+O$3-Lo_c)/Step_c)-MAX(6,MIN(INT(((Alpha_keep*$A31+O$3-Lo_c)/Step_c)+0.00000001),193)))*INDEX($D$5:$D$205,MAX(6,MIN(INT(((Alpha_keep*$A31+O$3-Lo_c)/Step_c)+0.00000001),193))+2)),"") -> -481.65318 | P31: =MAX(E31:O31) -> -481.65318 | Q31: =INDEX($E$3:$O$3,MATCH(P31,E31:O31,0)) -> 2.5 | R31: 2.5 | S31: =IF(ABS(Q31-R31)<0.000000001,1,0) -> 1 | T31: =ABS(P31-B31) -> 0 | U31: =Alpha_keep*A31+Q31 -> 38.0875 | V31: =INDEX(GuardBlock,27,ROUND(Q31/Step_h,0)+1) -> 1 | W31: 0
A32: =Grid!A32 -> 36.75 | B32: -477.00118 | C32: 27 | D32: =IF(AND($C32>=6,$C32<=194),Declarations!$B$25*INDEX($B$5:$B$205,$C32+1-Declarations!$E$25)+Declarations!$B$26*INDEX($B$5:$B$205,$C32+1-Declarations!$E$26)+Declarations!$B$27*INDEX($B$5:$B$205,$C32+1-Declarations!$E$27)+Declarations!$B$28*INDEX($B$5:$B$205,$C32+1-Declarations!$E$28)+Declarations!$B$29*INDEX($B$5:$B$205,$C32+1-Declarations!$E$29),"") -> -477.10283 | E32: =IF(Grid!C32=1,-Cost_k*E$3-Short_p*MAX(0,Floor_c-$A32)+Beta_q*((1-(((Alpha_keep*$A32+E$3-Lo_c)/Step_c)-MAX(6,MIN(INT(((Alpha_keep*$A32+E$3-Lo_c)/Step_c)+0.00000001),193))))*INDEX($D$5:$D$205,MAX(6,MIN(INT(((Alpha_keep*$A32+E$3-Lo_c)/Step_c)+0.00000001),193))+1)+(((Alpha_keep*$A32+E$3-Lo_c)/Step_c)-MAX(6,MIN(INT(((Alpha_keep*$A32+E$3-Lo_c)/Step_c)+0.00000001),193)))*INDEX($D$5:$D$205,MAX(6,MIN(INT(((Alpha_keep*$A32+E$3-Lo_c)/Step_c)+0.00000001),193))+2)),"") -> -511.89422 | F32: =IF(Grid!D32=1,-Cost_k*F$3-Short_p*MAX(0,Floor_c-$A32)+Beta_q*((1-(((Alpha_keep*$A32+F$3-Lo_c)/Step_c)-MAX(6,MIN(INT(((Alpha_keep*$A32+F$3-Lo_c)/Step_c)+0.00000001),193))))*INDEX($D$5:$D$205,MAX(6,MIN(INT(((Alpha_keep*$A32+F$3-Lo_c)/Step_c)+0.00000001),193))+1)+(((Alpha_keep*$A32+F$3-Lo_c)/Step_c)-MAX(6,MIN(INT(((Alpha_keep*$A32+F$3-Lo_c)/Step_c)+0.00000001),193)))*INDEX($D$5:$D$205,MAX(6,MIN(INT(((Alpha_keep*$A32+F$3-Lo_c)/Step_c)+0.00000001),193))+2)),"") -> -508.28073 | G32: =IF(Grid!E32=1,-Cost_k*G$3-Short_p*MAX(0,Floor_c-$A32)+Beta_q*((1-(((Alpha_keep*$A32+G$3-Lo_c)/Step_c)-MAX(6,MIN(INT(((Alpha_keep*$A32+G$3-Lo_c)/Step_c)+0.00000001),193))))*INDEX($D$5:$D$205,MAX(6,MIN(INT(((Alpha_keep*$A32+G$3-Lo_c)/Step_c)+0.00000001),193))+1)+(((Alpha_keep*$A32+G$3-Lo_c)/Step_c)-MAX(6,MIN(INT(((Alpha_keep*$A32+G$3-Lo_c)/Step_c)+0.00000001),193)))*INDEX($D$5:$D$205,MAX(6,MIN(INT(((Alpha_keep*$A32+G$3-Lo_c)/Step_c)+0.00000001),193))+2)),"") -> -504.69404 | H32: =IF(Grid!F32=1,-Cost_k*H$3-Short_p*MAX(0,Floor_c-$A32)+Beta_q*((1-(((Alpha_keep*$A32+H$3-Lo_c)/Step_c)-MAX(6,MIN(INT(((Alpha_keep*$A32+H$3-Lo_c)/Step_c)+0.00000001),193))))*INDEX($D$5:$D$205,MAX(6,MIN(INT(((Alpha_keep*$A32+H$3-Lo_c)/Step_c)+0.00000001),193))+1)+(((Alpha_keep*$A32+H$3-Lo_c)/Step_c)-MAX(6,MIN(INT(((Alpha_keep*$A32+H$3-Lo_c)/Step_c)+0.00000001),193)))*INDEX($D$5:$D$205,MAX(6,MIN(INT(((Alpha_keep*$A32+H$3-Lo_c)/Step_c)+0.00000001),193))+2)),"") -> -501.13439 | I32: =IF(Grid!G32=1,-Cost_k*I$3-Short_p*MAX(0,Floor_c-$A32)+Beta_q*((1-(((Alpha_keep*$A32+I$3-Lo_c)/Step_c)-MAX(6,MIN(INT(((Alpha_keep*$A32+I$3-Lo_c)/Step_c)+0.00000001),193))))*INDEX($D$5:$D$205,MAX(6,MIN(INT(((Alpha_keep*$A32+I$3-Lo_c)/Step_c)+0.00000001),193))+1)+(((Alpha_keep*$A32+I$3-Lo_c)/Step_c)-MAX(6,MIN(INT(((Alpha_keep*$A32+I$3-Lo_c)/Step_c)+0.00000001),193)))*INDEX($D$5:$D$205,MAX(6,MIN(INT(((Alpha_keep*$A32+I$3-Lo_c)/Step_c)+0.00000001),193))+2)),"") -> -497.60205 | J32: =IF(Grid!H32=1,-Cost_k*J$3-Short_p*MAX(0,Floor_c-$A32)+Beta_q*((1-(((Alpha_keep*$A32+J$3-Lo_c)/Step_c)-MAX(6,MIN(INT(((Alpha_keep*$A32+J$3-Lo_c)/Step_c)+0.00000001),193))))*INDEX($D$5:$D$205,MAX(6,MIN(INT(((Alpha_keep*$A32+J$3-Lo_c)/Step_c)+0.00000001),193))+1)+(((Alpha_keep*$A32+J$3-Lo_c)/Step_c)-MAX(6,MIN(INT(((Alpha_keep*$A32+J$3-Lo_c)/Step_c)+0.00000001),193)))*INDEX($D$5:$D$205,MAX(6,MIN(INT(((Alpha_keep*$A32+J$3-Lo_c)/Step_c)+0.00000001),193))+2)),"") -> -494.09744 | K32: =IF(Grid!I32=1,-Cost_k*K$3-Short_p*MAX(0,Floor_c-$A32)+Beta_q*((1-(((Alpha_keep*$A32+K$3-Lo_c)/Step_c)-MAX(6,MIN(INT(((Alpha_keep*$A32+K$3-Lo_c)/Step_c)+0.00000001),193))))*INDEX($D$5:$D$205,MAX(6,MIN(INT(((Alpha_keep*$A32+K$3-Lo_c)/Step_c)+0.00000001),193))+1)+(((Alpha_keep*$A32+K$3-Lo_c)/Step_c)-MAX(6,MIN(INT(((Alpha_keep*$A32+K$3-Lo_c)/Step_c)+0.00000001),193)))*INDEX($D$5:$D$205,MAX(6,MIN(INT(((Alpha_keep*$A32+K$3-Lo_c)/Step_c)+0.00000001),193))+2)),"") -> -490.62088 | L32: =IF(Grid!J32=1,-Cost_k*L$3-Short_p*MAX(0,Floor_c-$A32)+Beta_q*((1-(((Alpha_keep*$A32+L$3-Lo_c)/Step_c)-MAX(6,MIN(INT(((Alpha_keep*$A32+L$3-Lo_c)/Step_c)+0.00000001),193))))*INDEX($D$5:$D$205,MAX(6,MIN(INT(((Alpha_keep*$A32+L$3-Lo_c)/Step_c)+0.00000001),193))+1)+(((Alpha_keep*$A32+L$3-Lo_c)/Step_c)-MAX(6,MIN(INT(((Alpha_keep*$A32+L$3-Lo_c)/Step_c)+0.00000001),193)))*INDEX($D$5:$D$205,MAX(6,MIN(INT(((Alpha_keep*$A32+L$3-Lo_c)/Step_c)+0.00000001),193))+2)),"") -> -487.17257 | ... O32: =IF(Grid!M32=1,-Cost_k*O$3-Short_p*MAX(0,Floor_c-$A32)+Beta_q*((1-(((Alpha_keep*$A32+O$3-Lo_c)/Step_c)-MAX(6,MIN(INT(((Alpha_keep*$A32+O$3-Lo_c)/Step_c)+0.00000001),193))))*INDEX($D$5:$D$205,MAX(6,MIN(INT(((Alpha_keep*$A32+O$3-Lo_c)/Step_c)+0.00000001),193))+1)+(((Alpha_keep*$A32+O$3-Lo_c)/Step_c)-MAX(6,MIN(INT(((Alpha_keep*$A32+O$3-Lo_c)/Step_c)+0.00000001),193)))*INDEX($D$5:$D$205,MAX(6,MIN(INT(((Alpha_keep*$A32+O$3-Lo_c)/Step_c)+0.00000001),193))+2)),"") -> -477.00118 | P32: =MAX(E32:O32) -> -477.00118 | Q32: =INDEX($E$3:$O$3,MATCH(P32,E32:O32,0)) -> 2.5 | R32: 2.5 | S32: =IF(ABS(Q32-R32)<0.000000001,1,0) -> 1 | T32: =ABS(P32-B32) -> 0 | U32: =Alpha_keep*A32+Q32 -> 38.33125 | V32: =INDEX(GuardBlock,28,ROUND(Q32/Step_h,0)+1) -> 1 | W32: 0
A33: =Grid!A33 -> 37 | B33: -472.37743 | C33: 28 | D33: =IF(AND($C33>=6,$C33<=194),Declarations!$B$25*INDEX($B$5:$B$205,$C33+1-Declarations!$E$25)+Declarations!$B$26*INDEX($B$5:$B$205,$C33+1-Declarations!$E$26)+Declarations!$B$27*INDEX($B$5:$B$205,$C33+1-Declarations!$E$27)+Declarations!$B$28*INDEX($B$5:$B$205,$C33+1-Declarations!$E$28)+Declarations!$B$29*INDEX($B$5:$B$205,$C33+1-Declarations!$E$29),"") -> -472.48027 | E33: =IF(Grid!C33=1,-Cost_k*E$3-Short_p*MAX(0,Floor_c-$A33)+Beta_q*((1-(((Alpha_keep*$A33+E$3-Lo_c)/Step_c)-MAX(6,MIN(INT(((Alpha_keep*$A33+E$3-Lo_c)/Step_c)+0.00000001),193))))*INDEX($D$5:$D$205,MAX(6,MIN(INT(((Alpha_keep*$A33+E$3-Lo_c)/Step_c)+0.00000001),193))+1)+(((Alpha_keep*$A33+E$3-Lo_c)/Step_c)-MAX(6,MIN(INT(((Alpha_keep*$A33+E$3-Lo_c)/Step_c)+0.00000001),193)))*INDEX($D$5:$D$205,MAX(6,MIN(INT(((Alpha_keep*$A33+E$3-Lo_c)/Step_c)+0.00000001),193))+2)),"") -> -506.99562 | F33: =IF(Grid!D33=1,-Cost_k*F$3-Short_p*MAX(0,Floor_c-$A33)+Beta_q*((1-(((Alpha_keep*$A33+F$3-Lo_c)/Step_c)-MAX(6,MIN(INT(((Alpha_keep*$A33+F$3-Lo_c)/Step_c)+0.00000001),193))))*INDEX($D$5:$D$205,MAX(6,MIN(INT(((Alpha_keep*$A33+F$3-Lo_c)/Step_c)+0.00000001),193))+1)+(((Alpha_keep*$A33+F$3-Lo_c)/Step_c)-MAX(6,MIN(INT(((Alpha_keep*$A33+F$3-Lo_c)/Step_c)+0.00000001),193)))*INDEX($D$5:$D$205,MAX(6,MIN(INT(((Alpha_keep*$A33+F$3-Lo_c)/Step_c)+0.00000001),193))+2)),"") -> -503.40825 | G33: =IF(Grid!E33=1,-Cost_k*G$3-Short_p*MAX(0,Floor_c-$A33)+Beta_q*((1-(((Alpha_keep*$A33+G$3-Lo_c)/Step_c)-MAX(6,MIN(INT(((Alpha_keep*$A33+G$3-Lo_c)/Step_c)+0.00000001),193))))*INDEX($D$5:$D$205,MAX(6,MIN(INT(((Alpha_keep*$A33+G$3-Lo_c)/Step_c)+0.00000001),193))+1)+(((Alpha_keep*$A33+G$3-Lo_c)/Step_c)-MAX(6,MIN(INT(((Alpha_keep*$A33+G$3-Lo_c)/Step_c)+0.00000001),193)))*INDEX($D$5:$D$205,MAX(6,MIN(INT(((Alpha_keep*$A33+G$3-Lo_c)/Step_c)+0.00000001),193))+2)),"") -> -499.84793 | H33: =IF(Grid!F33=1,-Cost_k*H$3-Short_p*MAX(0,Floor_c-$A33)+Beta_q*((1-(((Alpha_keep*$A33+H$3-Lo_c)/Step_c)-MAX(6,MIN(INT(((Alpha_keep*$A33+H$3-Lo_c)/Step_c)+0.00000001),193))))*INDEX($D$5:$D$205,MAX(6,MIN(INT(((Alpha_keep*$A33+H$3-Lo_c)/Step_c)+0.00000001),193))+1)+(((Alpha_keep*$A33+H$3-Lo_c)/Step_c)-MAX(6,MIN(INT(((Alpha_keep*$A33+H$3-Lo_c)/Step_c)+0.00000001),193)))*INDEX($D$5:$D$205,MAX(6,MIN(INT(((Alpha_keep*$A33+H$3-Lo_c)/Step_c)+0.00000001),193))+2)),"") -> -496.31489 | I33: =IF(Grid!G33=1,-Cost_k*I$3-Short_p*MAX(0,Floor_c-$A33)+Beta_q*((1-(((Alpha_keep*$A33+I$3-Lo_c)/Step_c)-MAX(6,MIN(INT(((Alpha_keep*$A33+I$3-Lo_c)/Step_c)+0.00000001),193))))*INDEX($D$5:$D$205,MAX(6,MIN(INT(((Alpha_keep*$A33+I$3-Lo_c)/Step_c)+0.00000001),193))+1)+(((Alpha_keep*$A33+I$3-Lo_c)/Step_c)-MAX(6,MIN(INT(((Alpha_keep*$A33+I$3-Lo_c)/Step_c)+0.00000001),193)))*INDEX($D$5:$D$205,MAX(6,MIN(INT(((Alpha_keep*$A33+I$3-Lo_c)/Step_c)+0.00000001),193))+2)),"") -> -492.80958 | J33: =IF(Grid!H33=1,-Cost_k*J$3-Short_p*MAX(0,Floor_c-$A33)+Beta_q*((1-(((Alpha_keep*$A33+J$3-Lo_c)/Step_c)-MAX(6,MIN(INT(((Alpha_keep*$A33+J$3-Lo_c)/Step_c)+0.00000001),193))))*INDEX($D$5:$D$205,MAX(6,MIN(INT(((Alpha_keep*$A33+J$3-Lo_c)/Step_c)+0.00000001),193))+1)+(((Alpha_keep*$A33+J$3-Lo_c)/Step_c)-MAX(6,MIN(INT(((Alpha_keep*$A33+J$3-Lo_c)/Step_c)+0.00000001),193)))*INDEX($D$5:$D$205,MAX(6,MIN(INT(((Alpha_keep*$A33+J$3-Lo_c)/Step_c)+0.00000001),193))+2)),"") -> -489.33232 | K33: =IF(Grid!I33=1,-Cost_k*K$3-Short_p*MAX(0,Floor_c-$A33)+Beta_q*((1-(((Alpha_keep*$A33+K$3-Lo_c)/Step_c)-MAX(6,MIN(INT(((Alpha_keep*$A33+K$3-Lo_c)/Step_c)+0.00000001),193))))*INDEX($D$5:$D$205,MAX(6,MIN(INT(((Alpha_keep*$A33+K$3-Lo_c)/Step_c)+0.00000001),193))+1)+(((Alpha_keep*$A33+K$3-Lo_c)/Step_c)-MAX(6,MIN(INT(((Alpha_keep*$A33+K$3-Lo_c)/Step_c)+0.00000001),193)))*INDEX($D$5:$D$205,MAX(6,MIN(INT(((Alpha_keep*$A33+K$3-Lo_c)/Step_c)+0.00000001),193))+2)),"") -> -485.88329 | L33: =IF(Grid!J33=1,-Cost_k*L$3-Short_p*MAX(0,Floor_c-$A33)+Beta_q*((1-(((Alpha_keep*$A33+L$3-Lo_c)/Step_c)-MAX(6,MIN(INT(((Alpha_keep*$A33+L$3-Lo_c)/Step_c)+0.00000001),193))))*INDEX($D$5:$D$205,MAX(6,MIN(INT(((Alpha_keep*$A33+L$3-Lo_c)/Step_c)+0.00000001),193))+1)+(((Alpha_keep*$A33+L$3-Lo_c)/Step_c)-MAX(6,MIN(INT(((Alpha_keep*$A33+L$3-Lo_c)/Step_c)+0.00000001),193)))*INDEX($D$5:$D$205,MAX(6,MIN(INT(((Alpha_keep*$A33+L$3-Lo_c)/Step_c)+0.00000001),193))+2)),"") -> -482.46296 | ... O33: =IF(Grid!M33=1,-Cost_k*O$3-Short_p*MAX(0,Floor_c-$A33)+Beta_q*((1-(((Alpha_keep*$A33+O$3-Lo_c)/Step_c)-MAX(6,MIN(INT(((Alpha_keep*$A33+O$3-Lo_c)/Step_c)+0.00000001),193))))*INDEX($D$5:$D$205,MAX(6,MIN(INT(((Alpha_keep*$A33+O$3-Lo_c)/Step_c)+0.00000001),193))+1)+(((Alpha_keep*$A33+O$3-Lo_c)/Step_c)-MAX(6,MIN(INT(((Alpha_keep*$A33+O$3-Lo_c)/Step_c)+0.00000001),193)))*INDEX($D$5:$D$205,MAX(6,MIN(INT(((Alpha_keep*$A33+O$3-Lo_c)/Step_c)+0.00000001),193))+2)),"") -> -472.37743 | P33: =MAX(E33:O33) -> -472.37743 | Q33: =INDEX($E$3:$O$3,MATCH(P33,E33:O33,0)) -> 2.5 | R33: 2.5 | S33: =IF(ABS(Q33-R33)<0.000000001,1,0) -> 1 | T33: =ABS(P33-B33) -> 0 | U33: =Alpha_keep*A33+Q33 -> 38.575 | V33: =INDEX(GuardBlock,29,ROUND(Q33/Step_h,0)+1) -> 1 | W33: 0
