Workbook

Sheet README
B1: DCT Laboratory — Vol I, Ch 8: Stochastic Enterprise Dynamics
B2: Seed 26108 · Companion to DCT_V1_Ch08_Lab.ipynb and AXIOM Lab 1.8 (module AXIOM-08). Money in $ million.
B4: Worked Example 8.1, Will the Digital Program Breach the Floor?, with the book's declarations, and the five steps of AXIOM Lab 1.8, Putting Odds on Meridian's Plan.
B5: Declarations: the plan, the two channels of uncertainty and the levers of Worked Example 8.1; Section 8.6's revenue deviation and Section 8.7's regulatory interventions.
B6: Plan: the plan quarter by quarter, the deviation's volatility budget, the closures' plan line and the mean path (Steps 1-2).
B7: Fan: the revenue fan's exact law, the volatility budget, the persistence sweep, and the two-reading Lyapunov equation (Theorems 8.2-8.3; Online Appendix 8.B.3-8.B.4; lab step 1).
B8: Compose: the program office's chain and the revenue fans compose (Chapman-Kolmogorov; Online Appendix 8.B.2; lab step 2).
B9: Events: the plan line and the risk line of an event risk, and memorylessness (Theorem 8.4; Figure 8.3; lab step 3).
B10: Averages: linear, convex and concave cases of the flaw of averages, and Proposition 8.5 (Theorem 8.5; Online Appendix 8.B.7; lab step 4).
B11: Odds: Table 8.5 from the book's 100,000 paths (seed 8), the reading of Step 4 and the decomposition of Online Appendix 8.B.6.
B12: Bench and Draws: 2,000 of the book's own paths rebuilt by formula from their draws: every scenario of Table 8.5 and the error bar as the paths accumulate, live under your declarations (lab step 5).
B13: ErrorBars: Section 8.9's error bars and the paths a precision needs (Online Appendix 8.B.5).
... B20: Cross-sheet link: green.

Sheet Declarations
A1: Declarations (Worked Example 8.1, Step 1; Sections 8.6 and 8.7). Money in $ million.
A3: Quantity | B3: Value | C3: Source
A4: Liquidity index today (Chapter 1) | B4: 100 | C4: Chapter 1's digital path; 100 = $620 million
A5: $ million per index point | B5: 6.2 | C5: Chapter 1: index 100 = $0.62 billion
A6: Index the plan relaxes toward | B6: 112 | C6: Chapter 1's digital option
A7: Relaxation rate a year | B7: 0.35
A8: Depth of the program's cash draw (index points) | B8: 28 | C8: the draw D (t/tau) e^(1 - t/tau)
A9: Years to the deepest draw, tau | B9: 2
A10: Liquidity today ($ million) | B10: =Idx_today*Usd_point -> 620 | C10: $620 million
A11: Board floor ($ million) | B11: 350 | C11: Table 5.4
A12: Board risk appetite: largest chance of breaching the floor | B12: 0.05 | C12: Worked Example 8.1: 5 percent during the program
A13: Program horizon (quarters) | B13: 12 | C13: three years
A14: Deviation carried into the next quarter, a | B14: 0.6 | C14: Step 1: 60 percent of a surprise
A15: Surprise a quarter: standard deviation | B15: 50 | C15: Step 1: execution and market deviation
A16: Funding-window closures a year, lambda | B16: 0.1 | C16: Step 1: about once a decade
A17: Closure size: mean | B17: 120 | C17: not recovered within the program
A18: Closure size: standard deviation | B18: 50
A19: Closure size: gamma shape, (mean / sd)^2 | B19: =(Close_mean/Close_sd)^2 -> 5.76 | C19: the book's engine draws gamma sizes with this mean and sd
A20: Closure size: gamma scale, sd^2 / mean | B20: =Close_sd^2/Close_mean -> 20.833333
A21: Standby line: most it replaces of any closure | B21: 100 | C21: Step 5
A22: Phased build: depth of the cash draw | B22: 20 | C22: Step 5: deepest draw $49 million smaller
A23: Paths simulated | B23: 100000 | C23: Step 3
A25: Section 8.6: Industrial Systems' quarterly revenue deviation from plan
A26: Persistence of the revenue deviation, a | B26: 0.7 | C26: R' = 0.7 R + w
A27: Revenue shock: standard deviation | B27: 15
A28: Deviation after a strong quarter, R0 | B28: 30 | C28: Figure 8.1
A29: Covenant test: shortfall below plan | B29: 45
A31: Section 8.7: regulatory interventions
A32: Regulatory interventions a year, lambda | B32: 0.15 | C32: about once every 6.7 years
A33: Intervention cost: mean | B33: 40
A34: Intervention cost: standard deviation | B34: 30
A36: Liquidity by quarter: L_k = plan_k + E_k - (closures to date), with E_k = a E_k-1 + w_k and closures arriving at lambda/4 a quarter. The plan is Chapter 1's digital index: target + (today - target) e^(-rate t) - depth (t/tau) e^(1 - t/tau), in $ million.

Sheet Plan
A1: Declare and size each channel: the plan, the deviation's budget, the closures' plan line (Worked Example 8.1, Steps 1-2)
A4: Quarter | B4: Years | C4: Plan index | D4: Plan ($ million) | E4: Phased index | F4: Phased plan | G4: Headroom above the floor | H4: Deviation sd (Theorem 8.3(i)) | I4: Headroom in sd | J4: Expected closures to date | K4: Mean path (Theorem 8.4(iii))
A5: 0 | B5: =A5/4 -> 0 | C5: =Idx_target+(Idx_today-Idx_target)*EXP(-Relax_rate*B5)-Draw_depth*(B5/Draw_tau)*EXP(1-B5/Draw_tau) -> 100 | D5: =Usd_point*C5 -> 620 | E5: =Idx_target+(Idx_today-Idx_target)*EXP(-Relax_rate*B5)-Depth_phased*(B5/Draw_tau)*EXP(1-B5/Draw_tau) -> 100 | F5: =Usd_point*E5 -> 620 | G5: =D5-Floor_L -> 270 | H5: =Shock_sd*SQRT((1-Persist_a^(2*A5))/(1-Persist_a^2)) -> 0 | J5: =Lam_c/4*A5*Close_mean -> 0 | K5: =D5-J5 -> 620
A6: 1 | B6: =A6/4 -> 0.25 | C6: =Idx_target+(Idx_today-Idx_target)*EXP(-Relax_rate*B6)-Draw_depth*(B6/Draw_tau)*EXP(1-B6/Draw_tau) -> 92.60931 | D6: =Usd_point*C6 -> 574.17772 | E6: =Idx_target+(Idx_today-Idx_target)*EXP(-Relax_rate*B6)-Depth_phased*(B6/Draw_tau)*EXP(1-B6/Draw_tau) -> 95.008185 | F6: =Usd_point*E6 -> 589.05075 | G6: =D6-Floor_L -> 224.17772 | H6: =Shock_sd*SQRT((1-Persist_a^(2*A6))/(1-Persist_a^2)) -> 50 | I6: =G6/H6 -> 4.4835544 | J6: =Lam_c/4*A6*Close_mean -> 3 | K6: =D6-J6 -> 571.17772
A7: 2 | B7: =A7/4 -> 0.5 | C7: =Idx_target+(Idx_today-Idx_target)*EXP(-Relax_rate*B7)-Draw_depth*(B7/Draw_tau)*EXP(1-B7/Draw_tau) -> 87.107516 | D7: =Usd_point*C7 -> 540.0666 | E7: =Idx_target+(Idx_today-Idx_target)*EXP(-Relax_rate*B7)-Depth_phased*(B7/Draw_tau)*EXP(1-B7/Draw_tau) -> 91.341516 | F7: =Usd_point*E7 -> 566.3174 | G7: =D7-Floor_L -> 190.0666 | H7: =Shock_sd*SQRT((1-Persist_a^(2*A7))/(1-Persist_a^2)) -> 58.309519 | I7: =G7/H7 -> 3.2596152 | J7: =Lam_c/4*A7*Close_mean -> 6 | K7: =D7-J7 -> 534.0666
A8: 3 | B8: =A8/4 -> 0.75 | C8: =Idx_target+(Idx_today-Idx_target)*EXP(-Relax_rate*B8)-Draw_depth*(B8/Draw_tau)*EXP(1-B8/Draw_tau) -> 83.153901 | D8: =Usd_point*C8 -> 515.55419 | E8: =Idx_target+(Idx_today-Idx_target)*EXP(-Relax_rate*B8)-Depth_phased*(B8/Draw_tau)*EXP(1-B8/Draw_tau) -> 88.758639 | F8: =Usd_point*E8 -> 550.30356 | G8: =D8-Floor_L -> 165.55419 | H8: =Shock_sd*SQRT((1-Persist_a^(2*A8))/(1-Persist_a^2)) -> 61.024585 | I8: =G8/H8 -> 2.7129097 | J8: =Lam_c/4*A8*Close_mean -> 9 | K8: =D8-J8 -> 506.55419
A9: 4 | B9: =A9/4 -> 1 | C9: =Idx_target+(Idx_today-Idx_target)*EXP(-Relax_rate*B9)-Draw_depth*(B9/Draw_tau)*EXP(1-B9/Draw_tau) -> 80.461645 | D9: =Usd_point*C9 -> 498.8622 | E9: =Idx_target+(Idx_today-Idx_target)*EXP(-Relax_rate*B9)-Depth_phased*(B9/Draw_tau)*EXP(1-B9/Draw_tau) -> 87.05653 | F9: =Usd_point*E9 -> 539.75049 | G9: =D9-Floor_L -> 148.8622 | H9: =Shock_sd*SQRT((1-Persist_a^(2*A9))/(1-Persist_a^2)) -> 61.972897 | I9: =G9/H9 -> 2.4020533 | J9: =Lam_c/4*A9*Close_mean -> 12 | K9: =D9-J9 -> 486.8622
A10: 5 | B10: =A10/4 -> 1.25 | C10: =Idx_target+(Idx_today-Idx_target)*EXP(-Relax_rate*B10)-Draw_depth*(B10/Draw_tau)*EXP(1-B10/Draw_tau) -> 78.789868 | D10: =Usd_point*C10 -> 488.49718 | E10: =Idx_target+(Idx_today-Idx_target)*EXP(-Relax_rate*B10)-Depth_phased*(B10/Draw_tau)*EXP(1-B10/Draw_tau) -> 86.064825 | F10: =Usd_point*E10 -> 533.60192 | G10: =D10-Floor_L -> 138.49718 | H10: =Shock_sd*SQRT((1-Persist_a^(2*A10))/(1-Persist_a^2)) -> 62.310757 | I10: =G10/H10 -> 2.222685 | J10: =Lam_c/4*A10*Close_mean -> 15 | K10: =D10-J10 -> 473.49718
A11: 6 | B11: =A11/4 -> 1.5 | C11: =Idx_target+(Idx_today-Idx_target)*EXP(-Relax_rate*B11)-Draw_depth*(B11/Draw_tau)*EXP(1-B11/Draw_tau) -> 77.936802 | D11: =Usd_point*C11 -> 483.20817 | E11: =Idx_target+(Idx_today-Idx_target)*EXP(-Relax_rate*B11)-Depth_phased*(B11/Draw_tau)*EXP(1-B11/Draw_tau) -> 85.640954 | F11: =Usd_point*E11 -> 530.97392 | G11: =D11-Floor_L -> 133.20817 | H11: =Shock_sd*SQRT((1-Persist_a^(2*A11))/(1-Persist_a^2)) -> 62.431938 | I11: =G11/H11 -> 2.1336543 | J11: =Lam_c/4*A11*Close_mean -> 18 | K11: =D11-J11 -> 465.20817
A12: 7 | B12: =A12/4 -> 1.75 | C12: =Idx_target+(Idx_today-Idx_target)*EXP(-Relax_rate*B12)-Draw_depth*(B12/Draw_tau)*EXP(1-B12/Draw_tau) -> 77.733933 | D12: =Usd_point*C12 -> 481.95038 | E12: =Idx_target+(Idx_today-Idx_target)*EXP(-Relax_rate*B12)-Depth_phased*(B12/Draw_tau)*EXP(1-B12/Draw_tau) -> 85.665972 | F12: =Usd_point*E12 -> 531.12903 | G12: =D12-Floor_L -> 131.95038 | H12: =Shock_sd*SQRT((1-Persist_a^(2*A12))/(1-Persist_a^2)) -> 62.475506 | I12: =G12/H12 -> 2.1120338 | J12: =Lam_c/4*A12*Close_mean -> 21 | K12: =D12-J12 -> 460.95038
A13: 8 | B13: =A13/4 -> 2 | C13: =Idx_target+(Idx_today-Idx_target)*EXP(-Relax_rate*B13)-Draw_depth*(B13/Draw_tau)*EXP(1-B13/Draw_tau) -> 78.040976 | D13: =Usd_point*C13 -> 483.85405 | E13: =Idx_target+(Idx_today-Idx_target)*EXP(-Relax_rate*B13)-Depth_phased*(B13/Draw_tau)*EXP(1-B13/Draw_tau) -> 86.040976 | F13: =Usd_point*E13 -> 533.45405 | G13: =D13-Floor_L -> 133.85405 | H13: =Shock_sd*SQRT((1-Persist_a^(2*A13))/(1-Persist_a^2)) -> 62.491183 | I13: =G13/H13 -> 2.141967 | J13: =Lam_c/4*A13*Close_mean -> 24 | K13: =D13-J13 -> 459.85405
A14: 9 | B14: =A14/4 -> 2.25 | C14: =Idx_target+(Idx_today-Idx_target)*EXP(-Relax_rate*B14)-Draw_depth*(B14/Draw_tau)*EXP(1-B14/Draw_tau) -> 78.741578 | D14: =Usd_point*C14 -> 488.19778 | E14: =Idx_target+(Idx_today-Idx_target)*EXP(-Relax_rate*B14)-Depth_phased*(B14/Draw_tau)*EXP(1-B14/Draw_tau) -> 86.68405 | F14: =Usd_point*E14 -> 537.44111 | G14: =D14-Floor_L -> 138.19778 | H14: =Shock_sd*SQRT((1-Persist_a^(2*A14))/(1-Persist_a^2)) -> 62.496826 | I14: =G14/H14 -> 2.2112768 | J14: =Lam_c/4*A14*Close_mean -> 27 | K14: =D14-J14 -> 461.19778
A15: 10 | B15: =A15/4 -> 2.5 | C15: =Idx_target+(Idx_today-Idx_target)*EXP(-Relax_rate*B15)-Draw_depth*(B15/Draw_tau)*EXP(1-B15/Draw_tau) -> 79.739628 | D15: =Usd_point*C15 -> 494.3857 | E15: =Idx_target+(Idx_today-Idx_target)*EXP(-Relax_rate*B15)-Depth_phased*(B15/Draw_tau)*EXP(1-B15/Draw_tau) -> 87.527636 | F15: =Usd_point*E15 -> 542.67134 | G15: =D15-Floor_L -> 144.3857 | H15: =Shock_sd*SQRT((1-Persist_a^(2*A15))/(1-Persist_a^2)) -> 62.498857 | I15: =G15/H15 -> 2.3102134 | J15: =Lam_c/4*A15*Close_mean -> 30 | K15: =D15-J15 -> 464.3857
A16: 11 | B16: =A16/4 -> 2.75 | C16: =Idx_target+(Idx_today-Idx_target)*EXP(-Relax_rate*B16)-Draw_depth*(B16/Draw_tau)*EXP(1-B16/Draw_tau) -> 80.956121 | D16: =Usd_point*C16 -> 501.92795 | E16: =Idx_target+(Idx_today-Idx_target)*EXP(-Relax_rate*B16)-Depth_phased*(B16/Draw_tau)*EXP(1-B16/Draw_tau) -> 88.516303 | F16: =Usd_point*E16 -> 548.80108 | G16: =D16-Floor_L -> 151.92795 | H16: =Shock_sd*SQRT((1-Persist_a^(2*A16))/(1-Persist_a^2)) -> 62.499589 | I16: =G16/H16 -> 2.4308632 | J16: =Lam_c/4*A16*Close_mean -> 33 | K16: =D16-J16 -> 468.92795
A17: 12 | B17: =A17/4 -> 3 | C17: =Idx_target+(Idx_today-Idx_target)*EXP(-Relax_rate*B17)-Draw_depth*(B17/Draw_tau)*EXP(1-B17/Draw_tau) -> 82.326459 | D17: =Usd_point*C17 -> 510.42405 | E17: =Idx_target+(Idx_today-Idx_target)*EXP(-Relax_rate*B17)-Depth_phased*(B17/Draw_tau)*EXP(1-B17/Draw_tau) -> 89.604827 | F17: =Usd_point*E17 -> 555.54993 | G17: =D17-Floor_L -> 160.42405 | H17: =Shock_sd*SQRT((1-Persist_a^(2*A17))/(1-Persist_a^2)) -> 62.499852 | I17: =G17/H17 -> 2.5667908 | J17: =Lam_c/4*A17*Close_mean -> 36 | K17: =D17-J17 -> 474.42405
A19: Steps 1-2 | B19: Value | C19: Reading
A20: Plan: trough ($ million) | B20: =MIN($D$5:$D$17) -> 481.95038 | C20: Step 1: $482 million
A21: Plan: quarter of the trough | B21: =MATCH(B20,$D$5:$D$17,0)-1 -> 7 | C21: quarter 7
A22: Plan: liquidity at the end of year 3 | B22: =D17 -> 510.42405 | C22: $510 million
A23: Headroom above the floor at the trough | B23: =B20-Floor_L -> 131.95038 | C23: $132 million
A24: Deviation's volatility budget, sd / sqrt(1 - a^2) | B24: =Shock_sd/SQRT(1-Persist_a^2) -> 62.5 | C24: Step 2: $62.5 million (Theorem 8.3(ii))
A25: Headroom at the trough in standard deviations | B25: =B23/B24 -> 2.1112061 | C25: only 2.1 standard deviations
A26: One quarter at the trough, deviation alone: Phi(-headroom / budget) | B26: =NORMSDIST(-B25) -> 0.0173773 | C26: a path has twelve quarters, and a second channel
A27: Closures: plan line, lambda E[J] ($ million a year) | B27: =Lam_c*Close_mean -> 12 | C27: Step 2: $12 million a year (Theorem 8.4(ii))
A28: Closures: risk line, lambda E[J^2] (variance a year) | B28: =Lam_c*(Close_mean^2+Close_sd^2) -> 1690
A29: Closures: chance of at least one in three years, 1 - e^(-3 lambda) | B29: =1-EXP(-Lam_c*Horizon_q/4) -> 0.25918178 | C29: Step 2: 26 percent
A30: Closures: chance of one by quarter 7 | B30: =1-EXP(-Lam_c*B21/4) -> 0.16054298
A31: Mean path: its trough (plan less the closures' plan line) | B31: =MIN($K$5:$K$17) -> 459.85405 | C31: Step 4: $460 million
A32: Mean path: quarter of its trough | B32: =MATCH(B31,$K$5:$K$17,0)-1 -> 8
A33: Phased build: trough | B33: =MIN($F$5:$F$17) -> 530.97392 | C33: Step 5: $531 million
A34: Deepest cash draw, plan as drawn | B34: =Liq_today-B20 -> 138.04962
A35: Deepest cash draw, phased build | B35: =Liq_today-B33 -> 89.026083
A36: Phasing makes the deepest draw smaller by | B36: =B34-B35 -> 49.023535 | C36: Step 5: $49 million

Sheet Fan
A1: Watch the fan form: Industrial Systems' revenue deviation (Theorems 8.2-8.3; Figures 8.1-8.2; Online Appendix 8.B.3-8.B.4; AXIOM Lab 1.8, step 1)
A3: The volatility budget | B3: Value | C3: Reading | J3: The saturator: persistence a | K3: Long-run sd | L3: Long-run chance of the shortfall | M3: sd after 40 quarters
A4: Long-run variance, sd^2 / (1 - a^2) | B4: =Rev_sd^2/(1-Rev_a^2) -> 441.17647 | C4: about 441 | J4: 0 | K4: =IF(J4<1,Rev_sd/SQRT(1-J4^2),"none") -> 15 | L4: =IF(J4<1,NORMSDIST(-Rev_cov/K4),"none") -> 0.001349898 | M4: =Rev_sd*SQRT(IF(J4<1,(1-J4^80)/(1-J4^2),40)) -> 15
A5: Volatility budget: the long-run standard deviation | B5: =SQRT(B4) -> 21.004201 | C5: $21 million, not $15 million | J5: 0.35 | K5: =IF(J5<1,Rev_sd/SQRT(1-J5^2),"none") -> 16.012815 | L5: =IF(J5<1,NORMSDIST(-Rev_cov/K5),"none") -> 0.0024751585 | M5: =Rev_sd*SQRT(IF(J5<1,(1-J5^80)/(1-J5^2),40)) -> 16.012815
A6: Persistence inflates the shock by 1 / sqrt(1 - a^2) | B6: =1/SQRT(1-Rev_a^2) -> 1.4002801 | C6: 1.40 | J6: 0.5 | K6: =IF(J6<1,Rev_sd/SQRT(1-J6^2),"none") -> 17.320508 | L6: =IF(J6<1,NORMSDIST(-Rev_cov/K6),"none") -> 0.0046873842 | M6: =Rev_sd*SQRT(IF(J6<1,(1-J6^80)/(1-J6^2),40)) -> 17.320508
A7: Long-run chance a quarter of a shortfall of 45 or more, Phi(-45/21) | B7: =NORMSDIST(-Rev_cov/B5) -> 0.016079507 | C7: 1.6 percent | J7: 0.7 | K7: =IF(J7<1,Rev_sd/SQRT(1-J7^2),"none") -> 21.004201 | L7: =IF(J7<1,NORMSDIST(-Rev_cov/K7),"none") -> 0.016079507 | M7: =Rev_sd*SQRT(IF(J7<1,(1-J7^80)/(1-J7^2),40)) -> 21.004201
A8: The same chance if persistence were ignored, Phi(-45/15) | B8: =NORMSDIST(-Rev_cov/Rev_sd) -> 0.001349898 | C8: 0.13 percent | J8: 0.9 | K8: =IF(J8<1,Rev_sd/SQRT(1-J8^2),"none") -> 34.41236 | L8: =IF(J8<1,NORMSDIST(-Rev_cov/K8),"none") -> 0.095492685 | M8: =Rev_sd*SQRT(IF(J8<1,(1-J8^80)/(1-J8^2),40)) -> 34.408601
A9: Halved persistence, a | B9: 0.35 | C9: Online Appendix 8.B.4 | J9: 0.95 | K9: =IF(J9<1,Rev_sd/SQRT(1-J9^2),"none") -> 48.038446 | L9: =IF(J9<1,NORMSDIST(-Rev_cov/K9),"none") -> 0.17444366 | M9: =Rev_sd*SQRT(IF(J9<1,(1-J9^80)/(1-J9^2),40)) -> 47.640108
A10: Its volatility budget | B10: =Rev_sd/SQRT(1-B9^2) -> 16.012815 | C10: $16.0 million | J10: 0.99 | K10: =IF(J10<1,Rev_sd/SQRT(1-J10^2),"none") -> 106.33218 | L10: =IF(J10<1,NORMSDIST(-Rev_cov/K10),"none") -> 0.33607391 | M10: =Rev_sd*SQRT(IF(J10<1,(1-J10^80)/(1-J10^2),40)) -> 79.035415
A11: Its chance of the shortfall a quarter | B11: =NORMSDIST(-Rev_cov/B10) -> 0.0024751585 | C11: 0.25 percent | J11: 1 | K11: =IF(J11<1,Rev_sd/SQRT(1-J11^2),"none") -> none | L11: =IF(J11<1,NORMSDIST(-Rev_cov/K11),"none") -> none | M11: =Rev_sd*SQRT(IF(J11<1,(1-J11^80)/(1-J11^2),40)) -> 94.86833
A12: How many times smaller | B12: =B7/B11 -> 6.4963546 | C12: sixfold, with no change in the market | J12: As a reaches one the band stops settling: with no restoring force it widens like 15 sqrt(k).
A14: Theorem 8.3(i): the law stays normal; its mean and variance follow exact recursions. From +30 the fan drifts back toward plan and widens until it settles (Figure 8.1); with a = 1 it never settles (Figure 8.2).
A15: Quarter k | B15: Mean, a^k R0 | C15: Variance, a^2 var + sd^2 | D15: Standard deviation | E15: Band: mean - 2 sd | F15: Band: mean + 2 sd | G15: Closed form of the variance | H15: No restoring force (a = 1): sd x sqrt(k) | J15: Online Appendix 8.B.3: two readings | K15: Value
A16: 0 | B16: =Rev_R0*Rev_a^A16 -> 30 | C16: 0 | D16: =SQRT(C16) -> 0 | E16: =B16-2*D16 -> 30 | F16: =B16+2*D16 -> 30 | G16: =Rev_sd^2*(1-Rev_a^(2*A16))/(1-Rev_a^2) -> 0 | H16: =Rev_sd*SQRT(A16) -> 0 | J16: a11 | K16: 0.8
A17: 1 | B17: =Rev_R0*Rev_a^A17 -> 21 | C17: =Rev_a^2*C16+Rev_sd^2 -> 225 | D17: =SQRT(C17) -> 15 | E17: =B17-2*D17 -> -9 | F17: =B17+2*D17 -> 51 | G17: =Rev_sd^2*(1-Rev_a^(2*A17))/(1-Rev_a^2) -> 225 | H17: =Rev_sd*SQRT(A17) -> 15 | J17: a12 | K17: 0.2
A18: 2 | B18: =Rev_R0*Rev_a^A18 -> 14.7 | C18: =Rev_a^2*C17+Rev_sd^2 -> 335.25 | D18: =SQRT(C18) -> 18.309833 | E18: =B18-2*D18 -> -21.919667 | F18: =B18+2*D18 -> 51.319667 | G18: =Rev_sd^2*(1-Rev_a^(2*A18))/(1-Rev_a^2) -> 335.25 | H18: =Rev_sd*SQRT(A18) -> 21.213203 | J18: a21 | K18: 0
A19: 3 | B19: =Rev_R0*Rev_a^A19 -> 10.29 | C19: =Rev_a^2*C18+Rev_sd^2 -> 389.2725 | D19: =SQRT(C19) -> 19.72999 | E19: =B19-2*D19 -> -29.16998 | F19: =B19+2*D19 -> 49.74998 | G19: =Rev_sd^2*(1-Rev_a^(2*A19))/(1-Rev_a^2) -> 389.2725 | H19: =Rev_sd*SQRT(A19) -> 25.980762 | J19: a22 | K19: 0.6
A20: 4 | B20: =Rev_R0*Rev_a^A20 -> 7.203 | C20: =Rev_a^2*C19+Rev_sd^2 -> 415.74352 | D20: =SQRT(C20) -> 20.38979 | E20: =B20-2*D20 -> -33.576579 | F20: =B20+2*D20 -> 47.982579 | G20: =Rev_sd^2*(1-Rev_a^(2*A20))/(1-Rev_a^2) -> 415.74352 | H20: =Rev_sd*SQRT(A20) -> 30 | J20: s11 | K20: 0.04
A21: 5 | B21: =Rev_R0*Rev_a^A21 -> 5.0421 | C21: =Rev_a^2*C20+Rev_sd^2 -> 428.71433 | D21: =SQRT(C21) -> 20.705418 | E21: =B21-2*D21 -> -36.368736 | F21: =B21+2*D21 -> 46.452936 | G21: =Rev_sd^2*(1-Rev_a^(2*A21))/(1-Rev_a^2) -> 428.71433 | H21: =Rev_sd*SQRT(A21) -> 33.54102 | J21: s22 | K21: 0.01
A22: 6 | B22: =Rev_R0*Rev_a^A22 -> 3.52947 | C22: =Rev_a^2*C21+Rev_sd^2 -> 435.07002 | D22: =SQRT(C22) -> 20.858332 | E22: =B22-2*D22 -> -38.187194 | F22: =B22+2*D22 -> 45.246134 | G22: =Rev_sd^2*(1-Rev_a^(2*A22))/(1-Rev_a^2) -> 435.07002 | H22: =Rev_sd*SQRT(A22) -> 36.742346 | J22: Closed form: sigma_22 = s22 / (1 - a22^2) | K22: =K21/(1-K19^2) -> 0.015625
A23: 7 | B23: =Rev_R0*Rev_a^A23 -> 2.470629 | C23: =Rev_a^2*C22+Rev_sd^2 -> 438.18431 | D23: =SQRT(C23) -> 20.932852 | E23: =B23-2*D23 -> -39.395076 | F23: =B23+2*D23 -> 44.336334 | G23: =Rev_sd^2*(1-Rev_a^(2*A23))/(1-Rev_a^2) -> 438.18431 | H23: =Rev_sd*SQRT(A23) -> 39.68627 | J23: Closed form: sigma_12 = a12 a22 sigma_22 / (1 - a11 a22) | K23: =K17*K19*K22/(1-K16*K19) -> 0.0036057692
A24: 8 | B24: =Rev_R0*Rev_a^A24 -> 1.7294403 | C24: =Rev_a^2*C23+Rev_sd^2 -> 439.71031 | D24: =SQRT(C24) -> 20.969271 | E24: =B24-2*D24 -> -40.209101 | F24: =B24+2*D24 -> 43.667982 | G24: =Rev_sd^2*(1-Rev_a^(2*A24))/(1-Rev_a^2) -> 439.71031 | H24: =Rev_sd*SQRT(A24) -> 42.426407 | J24: Closed form: sigma_11 = (2 a11 a12 sigma_12 + a12^2 sigma_22 + s11) / (1 - a11^2) | K24: =(2*K16*K17*K23+K17^2*K22+K20)/(1-K16^2) -> 0.11605235
A25: 9 | B25: =Rev_R0*Rev_a^A25 -> 1.2106082 | C25: =Rev_a^2*C24+Rev_sd^2 -> 440.45805 | D25: =SQRT(C25) -> 20.987093 | E25: =B25-2*D25 -> -40.763577 | F25: =B25+2*D25 -> 43.184793 | G25: =Rev_sd^2*(1-Rev_a^(2*A25))/(1-Rev_a^2) -> 440.45805 | H25: =Rev_sd*SQRT(A25) -> 45 | J25: Long-run sd of the first reading | K25: =SQRT(K24) -> 0.34066457
A26: 10 | B26: =Rev_R0*Rev_a^A26 -> 0.84742575 | C26: =Rev_a^2*C25+Rev_sd^2 -> 440.82445 | D26: =SQRT(C26) -> 20.99582 | E26: =B26-2*D26 -> -41.144214 | F26: =B26+2*D26 -> 42.839065 | G26: =Rev_sd^2*(1-Rev_a^(2*A26))/(1-Rev_a^2) -> 440.82445 | H26: =Rev_sd*SQRT(A26) -> 47.434165 | J26: Long-run sd of the second reading | K26: =SQRT(K22) -> 0.125
A27: 11 | B27: =Rev_R0*Rev_a^A27 -> 0.59319802 | C27: =Rev_a^2*C26+Rev_sd^2 -> 441.00398 | D27: =SQRT(C27) -> 21.000095 | E27: =B27-2*D27 -> -41.406991 | F27: =B27+2*D27 -> 42.593387 | G27: =Rev_sd^2*(1-Rev_a^(2*A27))/(1-Rev_a^2) -> 441.00398 | H27: =Rev_sd*SQRT(A27) -> 49.749372 | J27: The iteration below after 60 periods: sigma_11 | K27: =L90 -> 0.11605235
A28: 12 | B28: =Rev_R0*Rev_a^A28 -> 0.41523862 | C28: =Rev_a^2*C27+Rev_sd^2 -> 441.09195 | D28: =SQRT(C28) -> 21.002189 | E28: =B28-2*D28 -> -41.58914 | F28: =B28+2*D28 -> 42.419617 | G28: =Rev_sd^2*(1-Rev_a^(2*A28))/(1-Rev_a^2) -> 441.09195 | H28: =Rev_sd*SQRT(A28) -> 51.961524 | J28: Largest gap between the iteration and the closed form | K28: =MAX(ABS(L90-K24),ABS(M90-K23),ABS(N90-K22)) -> 3.2615577e-13
A29: 13 | B29: =Rev_R0*Rev_a^A29 -> 0.29066703 | C29: =Rev_a^2*C28+Rev_sd^2 -> 441.13506 | D29: =SQRT(C29) -> 21.003215 | E29: =B29-2*D29 -> -41.715764 | F29: =B29+2*D29 -> 42.297098 | G29: =Rev_sd^2*(1-Rev_a^(2*A29))/(1-Rev_a^2) -> 441.13506 | H29: =Rev_sd*SQRT(A29) -> 54.083269 | K29: Period | L29: sigma_11 | M29: sigma_12 | N29: sigma_22
A30: 14 | B30: =Rev_R0*Rev_a^A30 -> 0.20346692 | C30: =Rev_a^2*C29+Rev_sd^2 -> 441.15618 | D30: =SQRT(C30) -> 21.003718 | E30: =B30-2*D30 -> -41.803969 | F30: =B30+2*D30 -> 42.210903 | G30: =Rev_sd^2*(1-Rev_a^(2*A30))/(1-Rev_a^2) -> 441.15618 | H30: =Rev_sd*SQRT(A30) -> 56.124861 | K30: 0 | L30: 0 | M30: 0 | N30: 0
A31: 15 | B31: =Rev_R0*Rev_a^A31 -> 0.14242685 | C31: =Rev_a^2*C30+Rev_sd^2 -> 441.16653 | D31: =SQRT(C31) -> 21.003965 | E31: =B31-2*D31 -> -41.865502 | F31: =B31+2*D31 -> 42.150356 | G31: =Rev_sd^2*(1-Rev_a^(2*A31))/(1-Rev_a^2) -> 441.16653 | H31: =Rev_sd*SQRT(A31) -> 58.09475 | K31: 1 | L31: =$K$16^2*L30+2*$K$16*$K$17*M30+$K$17^2*N30+$K$20 -> 0.04 | M31: =$K$16*$K$18*L30+($K$16*$K$19+$K$17*$K$18)*M30+$K$17*$K$19*N30 -> 0 | N31: =$K$18^2*L30+2*$K$18*$K$19*M30+$K$19^2*N30+$K$21 -> 0.01
A32: 16 | B32: =Rev_R0*Rev_a^A32 -> 0.099698792 | C32: =Rev_a^2*C31+Rev_sd^2 -> 441.1716 | D32: =SQRT(C32) -> 21.004085 | E32: =B32-2*D32 -> -41.908472 | F32: =B32+2*D32 -> 42.107869 | G32: =Rev_sd^2*(1-Rev_a^(2*A32))/(1-Rev_a^2) -> 441.1716 | H32: =Rev_sd*SQRT(A32) -> 60 | K32: 2 | L32: =$K$16^2*L31+2*$K$16*$K$17*M31+$K$17^2*N31+$K$20 -> 0.066 | M32: =$K$16*$K$18*L31+($K$16*$K$19+$K$17*$K$18)*M31+$K$17*$K$19*N31 -> 0.0012 | N32: =$K$18^2*L31+2*$K$18*$K$19*M31+$K$19^2*N31+$K$21 -> 0.0136
A33: 17 | B33: =Rev_R0*Rev_a^A33 -> 0.069789154 | C33: =Rev_a^2*C32+Rev_sd^2 -> 441.17408 | D33: =SQRT(C33) -> 21.004144 | E33: =B33-2*D33 -> -41.9385 | F33: =B33+2*D33 -> 42.078078 | G33: =Rev_sd^2*(1-Rev_a^(2*A33))/(1-Rev_a^2) -> 441.17408 | H33: =Rev_sd*SQRT(A33) -> 61.846584 | K33: 3 | L33: =$K$16^2*L32+2*$K$16*$K$17*M32+$K$17^2*N32+$K$20 -> 0.083168 | M33: =$K$16*$K$18*L32+($K$16*$K$19+$K$17*$K$18)*M32+$K$17*$K$19*N32 -> 0.002208 | N33: =$K$18^2*L32+2*$K$18*$K$19*M32+$K$19^2*N32+$K$21 -> 0.014896
A34: 18 | B34: =Rev_R0*Rev_a^A34 -> 0.048852408 | C34: =Rev_a^2*C33+Rev_sd^2 -> 441.1753 | D34: =SQRT(C34) -> 21.004173 | E34: =B34-2*D34 -> -41.959494 | F34: =B34+2*D34 -> 42.057199 | G34: =Rev_sd^2*(1-Rev_a^(2*A34))/(1-Rev_a^2) -> 441.1753 | H34: =Rev_sd*SQRT(A34) -> 63.63961 | K34: 4 | L34: =$K$16^2*L33+2*$K$16*$K$17*M33+$K$17^2*N33+$K$20 -> 0.09452992 | M34: =$K$16*$K$18*L33+($K$16*$K$19+$K$17*$K$18)*M33+$K$17*$K$19*N33 -> 0.00284736 | N34: =$K$18^2*L33+2*$K$18*$K$19*M33+$K$19^2*N33+$K$21 -> 0.01536256
A35: 19 | B35: =Rev_R0*Rev_a^A35 -> 0.034196686 | C35: =Rev_a^2*C34+Rev_sd^2 -> 441.1759 | D35: =SQRT(C35) -> 21.004188 | E35: =B35-2*D35 -> -41.974179 | F35: =B35+2*D35 -> 42.042572 | G35: =Rev_sd^2*(1-Rev_a^(2*A35))/(1-Rev_a^2) -> 441.1759 | H35: =Rev_sd*SQRT(A35) -> 65.383484 | K35: 5 | L35: =$K$16^2*L34+2*$K$16*$K$17*M34+$K$17^2*N34+$K$20 -> 0.10202481 | M35: =$K$16*$K$18*L34+($K$16*$K$19+$K$17*$K$18)*M34+$K$17*$K$19*N34 -> 0.00321024 | N35: =$K$18^2*L34+2*$K$18*$K$19*M34+$K$19^2*N34+$K$21 -> 0.015530522
A36: 20 | B36: =Rev_R0*Rev_a^A36 -> 0.02393768 | C36: =Rev_a^2*C35+Rev_sd^2 -> 441.17619 | D36: =SQRT(C36) -> 21.004195 | E36: =B36-2*D36 -> -41.984451 | F36: =B36+2*D36 -> 42.032327 | G36: =Rev_sd^2*(1-Rev_a^(2*A36))/(1-Rev_a^2) -> 441.17619 | H36: =Rev_sd*SQRT(A36) -> 67.082039 | K36: 6 | L36: =$K$16^2*L35+2*$K$16*$K$17*M35+$K$17^2*N35+$K$20 -> 0.10694437 | M36: =$K$16*$K$18*L35+($K$16*$K$19+$K$17*$K$18)*M35+$K$17*$K$19*N35 -> 0.0034045778 | N36: =$K$18^2*L35+2*$K$18*$K$19*M35+$K$19^2*N35+$K$21 -> 0.015590988
A37: 21 | B37: =Rev_R0*Rev_a^A37 -> 0.016756376 | C37: =Rev_a^2*C36+Rev_sd^2 -> 441.17633 | D37: =SQRT(C37) -> 21.004198 | E37: =B37-2*D37 -> -41.99164 | F37: =B37+2*D37 -> 42.025152 | G37: =Rev_sd^2*(1-Rev_a^(2*A37))/(1-Rev_a^2) -> 441.17633 | H37: =Rev_sd*SQRT(A37) -> 68.738635 | K37: 7 | L37: =$K$16^2*L36+2*$K$16*$K$17*M36+$K$17^2*N36+$K$20 -> 0.1101575 | M37: =$K$16*$K$18*L36+($K$16*$K$19+$K$17*$K$18)*M36+$K$17*$K$19*N36 -> 0.0035051159 | N37: =$K$18^2*L36+2*$K$18*$K$19*M36+$K$19^2*N36+$K$21 -> 0.015612756
A38: 22 | B38: =Rev_R0*Rev_a^A38 -> 0.011729463 | C38: =Rev_a^2*C37+Rev_sd^2 -> 441.1764 | D38: =SQRT(C38) -> 21.0042 | E38: =B38-2*D38 -> -41.99667 | F38: =B38+2*D38 -> 42.020129 | G38: =Rev_sd^2*(1-Rev_a^(2*A38))/(1-Rev_a^2) -> 441.1764 | H38: =Rev_sd*SQRT(A38) -> 70.356236 | K38: 8 | L38: =$K$16^2*L37+2*$K$16*$K$17*M37+$K$17^2*N37+$K$20 -> 0.11224695 | M38: =$K$16*$K$18*L37+($K$16*$K$19+$K$17*$K$18)*M37+$K$17*$K$19*N37 -> 0.0035559863 | N38: =$K$18^2*L37+2*$K$18*$K$19*M37+$K$19^2*N37+$K$21 -> 0.015620592
A39: 23 | B39: =Rev_R0*Rev_a^A39 -> 0.0082106242 | C39: =Rev_a^2*C38+Rev_sd^2 -> 441.17644 | D39: =SQRT(C39) -> 21.0042 | E39: =B39-2*D39 -> -42.00019 | F39: =B39+2*D39 -> 42.016612 | G39: =Rev_sd^2*(1-Rev_a^(2*A39))/(1-Rev_a^2) -> 441.17644 | H39: =Rev_sd*SQRT(A39) -> 71.937473 | K39: 9 | L39: =$K$16^2*L38+2*$K$16*$K$17*M38+$K$17^2*N38+$K$20 -> 0.11360079 | M39: =$K$16*$K$18*L38+($K$16*$K$19+$K$17*$K$18)*M38+$K$17*$K$19*N38 -> 0.0035813445 | N39: =$K$18^2*L38+2*$K$18*$K$19*M38+$K$19^2*N38+$K$21 -> 0.015623413
A40: 24 | B40: =Rev_R0*Rev_a^A40 -> 0.0057474369 | C40: =Rev_a^2*C39+Rev_sd^2 -> 441.17645 | D40: =SQRT(C40) -> 21.004201 | E40: =B40-2*D40 -> -42.002654 | F40: =B40+2*D40 -> 42.014149 | G40: =Rev_sd^2*(1-Rev_a^(2*A40))/(1-Rev_a^2) -> 441.17645 | H40: =Rev_sd*SQRT(A40) -> 73.484692 | K40: 10 | L40: =$K$16^2*L39+2*$K$16*$K$17*M39+$K$17^2*N39+$K$20 -> 0.11447547 | M40: =$K$16*$K$18*L39+($K$16*$K$19+$K$17*$K$18)*M39+$K$17*$K$19*N39 -> 0.0035938549 | N40: =$K$18^2*L39+2*$K$18*$K$19*M39+$K$19^2*N39+$K$21 -> 0.015624429
A41: 25 | B41: =Rev_R0*Rev_a^A41 -> 0.0040232059 | C41: =Rev_a^2*C40+Rev_sd^2 -> 441.17646 | D41: =SQRT(C41) -> 21.004201 | E41: =B41-2*D41 -> -42.004379 | F41: =B41+2*D41 -> 42.012425 | G41: =Rev_sd^2*(1-Rev_a^(2*A41))/(1-Rev_a^2) -> 441.17646 | H41: =Rev_sd*SQRT(A41) -> 75 | K41: 11 | L41: =$K$16^2*L40+2*$K$16*$K$17*M40+$K$17^2*N40+$K$20 -> 0.11503931 | M41: =$K$16*$K$18*L40+($K$16*$K$19+$K$17*$K$18)*M40+$K$17*$K$19*N40 -> 0.0035999818 | N41: =$K$18^2*L40+2*$K$18*$K$19*M40+$K$19^2*N40+$K$21 -> 0.015624794
A42: 26 | B42: =Rev_R0*Rev_a^A42 -> 0.0028162441 | C42: =Rev_a^2*C41+Rev_sd^2 -> 441.17647 | D42: =SQRT(C42) -> 21.004201 | E42: =B42-2*D42 -> -42.005586 | F42: =B42+2*D42 -> 42.011219 | G42: =Rev_sd^2*(1-Rev_a^(2*A42))/(1-Rev_a^2) -> 441.17647 | H42: =Rev_sd*SQRT(A42) -> 76.485293 | K42: 12 | L42: =$K$16^2*L41+2*$K$16*$K$17*M41+$K$17^2*N41+$K$20 -> 0.11540215 | M42: =$K$16*$K$18*L41+($K$16*$K$19+$K$17*$K$18)*M41+$K$17*$K$19*N41 -> 0.0036029666 | N42: =$K$18^2*L41+2*$K$18*$K$19*M41+$K$19^2*N41+$K$21 -> 0.015624926
... A56: 40 | B56: =Rev_R0*Rev_a^A56 -> 1.9100417e-05 | C56: =Rev_a^2*C55+Rev_sd^2 -> 441.17647 | D56: =SQRT(C56) -> 21.004201 | E56: =B56-2*D56 -> -42.008383 | F56: =B56+2*D56 -> 42.008422 | G56: =Rev_sd^2*(1-Rev_a^(2*A56))/(1-Rev_a^2) -> 441.17647 | H56: =Rev_sd*SQRT(A56) -> 94.86833 | K56: 26 | L56: =$K$16^2*L55+2*$K$16*$K$17*M55+$K$17^2*N55+$K$20 -> 0.11605108 | M56: =$K$16*$K$18*L55+($K$16*$K$19+$K$17*$K$18)*M55+$K$17*$K$19*N55 -> 0.0036057691 | N56: =$K$18^2*L55+2*$K$18*$K$19*M55+$K$19^2*N55+$K$21 -> 0.015625
K57: 27 | L57: =$K$16^2*L56+2*$K$16*$K$17*M56+$K$17^2*N56+$K$20 -> 0.11605154 | M57: =$K$16*$K$18*L56+($K$16*$K$19+$K$17*$K$18)*M56+$K$17*$K$19*N56 -> 0.0036057692 | N57: =$K$18^2*L56+2*$K$18*$K$19*M56+$K$19^2*N56+$K$21 -> 0.015625
K58: 28 | L58: =$K$16^2*L57+2*$K$16*$K$17*M57+$K$17^2*N57+$K$20 -> 0.11605183 | M58: =$K$16*$K$18*L57+($K$16*$K$19+$K$17*$K$18)*M57+$K$17*$K$19*N57 -> 0.0036057692 | N58: =$K$18^2*L57+2*$K$18*$K$19*M57+$K$19^2*N57+$K$21 -> 0.015625
K59: 29 | L59: =$K$16^2*L58+2*$K$16*$K$17*M58+$K$17^2*N58+$K$20 -> 0.11605202 | M59: =$K$16*$K$18*L58+($K$16*$K$19+$K$17*$K$18)*M58+$K$17*$K$19*N58 -> 0.0036057692 | N59: =$K$18^2*L58+2*$K$18*$K$19*M58+$K$19^2*N58+$K$21 -> 0.015625
K60: 30 | L60: =$K$16^2*L59+2*$K$16*$K$17*M59+$K$17^2*N59+$K$20 -> 0.11605214 | M60: =$K$16*$K$18*L59+($K$16*$K$19+$K$17*$K$18)*M59+$K$17*$K$19*N59 -> 0.0036057692 | N60: =$K$18^2*L59+2*$K$18*$K$19*M59+$K$19^2*N59+$K$21 -> 0.015625
K61: 31 | L61: =$K$16^2*L60+2*$K$16*$K$17*M60+$K$17^2*N60+$K$20 -> 0.11605221 | M61: =$K$16*$K$18*L60+($K$16*$K$19+$K$17*$K$18)*M60+$K$17*$K$19*N60 -> 0.0036057692 | N61: =$K$18^2*L60+2*$K$18*$K$19*M60+$K$19^2*N60+$K$21 -> 0.015625
K62: 32 | L62: =$K$16^2*L61+2*$K$16*$K$17*M61+$K$17^2*N61+$K$20 -> 0.11605226 | M62: =$K$16*$K$18*L61+($K$16*$K$19+$K$17*$K$18)*M61+$K$17*$K$19*N61 -> 0.0036057692 | N62: =$K$18^2*L61+2*$K$18*$K$19*M61+$K$19^2*N61+$K$21 -> 0.015625
K63: 33 | L63: =$K$16^2*L62+2*$K$16*$K$17*M62+$K$17^2*N62+$K$20 -> 0.11605229 | M63: =$K$16*$K$18*L62+($K$16*$K$19+$K$17*$K$18)*M62+$K$17*$K$19*N62 -> 0.0036057692 | N63: =$K$18^2*L62+2*$K$18*$K$19*M62+$K$19^2*N62+$K$21 -> 0.015625
K64: 34 | L64: =$K$16^2*L63+2*$K$16*$K$17*M63+$K$17^2*N63+$K$20 -> 0.11605231 | M64: =$K$16*$K$18*L63+($K$16*$K$19+$K$17*$K$18)*M63+$K$17*$K$19*N63 -> 0.0036057692 | N64: =$K$18^2*L63+2*$K$18*$K$19*M63+$K$19^2*N63+$K$21 -> 0.015625
K65: 35 | L65: =$K$16^2*L64+2*$K$16*$K$17*M64+$K$17^2*N64+$K$20 -> 0.11605233 | M65: =$K$16*$K$18*L64+($K$16*$K$19+$K$17*$K$18)*M64+$K$17*$K$19*N64 -> 0.0036057692 | N65: =$K$18^2*L64+2*$K$18*$K$19*M64+$K$19^2*N64+$K$21 -> 0.015625
K66: 36 | L66: =$K$16^2*L65+2*$K$16*$K$17*M65+$K$17^2*N65+$K$20 -> 0.11605234 | M66: =$K$16*$K$18*L65+($K$16*$K$19+$K$17*$K$18)*M65+$K$17*$K$19*N65 -> 0.0036057692 | N66: =$K$18^2*L65+2*$K$18*$K$19*M65+$K$19^2*N65+$K$21 -> 0.015625
K67: 37 | L67: =$K$16^2*L66+2*$K$16*$K$17*M66+$K$17^2*N66+$K$20 -> 0.11605234 | M67: =$K$16*$K$18*L66+($K$16*$K$19+$K$17*$K$18)*M66+$K$17*$K$19*N66 -> 0.0036057692 | N67: =$K$18^2*L66+2*$K$18*$K$19*M66+$K$19^2*N66+$K$21 -> 0.015625
K68: 38 | L68: =$K$16^2*L67+2*$K$16*$K$17*M67+$K$17^2*N67+$K$20 -> 0.11605234 | M68: =$K$16*$K$18*L67+($K$16*$K$19+$K$17*$K$18)*M67+$K$17*$K$19*N67 -> 0.0036057692 | N68: =$K$18^2*L67+2*$K$18*$K$19*M67+$K$19^2*N67+$K$21 -> 0.015625
... K90: 60 | L90: =$K$16^2*L89+2*$K$16*$K$17*M89+$K$17^2*N89+$K$20 -> 0.11605235 | M90: =$K$16*$K$18*L89+($K$16*$K$19+$K$17*$K$18)*M89+$K$17*$K$19*N89 -> 0.0036057692 | N90: =$K$18^2*L89+2*$K$18*$K$19*M89+$K$19^2*N89+$K$21 -> 0.015625

Sheet Compose
A1: Check the multi-year view: Chapman-Kolmogorov (Theorem 8.2(ii); Online Appendix 8.B.2; AXIOM Lab 1.8, step 2)
A2: The program office classifies each quarter as on plan or off plan. Multi-quarter odds must pass through every intermediate state: P^(j+k) = P^j P^k.
A4: One quarter, P | B4: to on plan | C4: to off plan | F4: Revenue fans compose (Section 8.6's deviation) | G4: Value | H4: Reading
A5: from on plan | B5: 0.9 | C5: =1-B5 -> 0.1 | F5: One-year fan: the mean's factor, a^4 | G5: =Rev_a^4 -> 0.2401
A6: from off plan | B6: 0.3 | C6: =1-B6 -> 0.7 | F6: One-year fan: variance, sd^2 (1 - a^8) / (1 - a^2) | G6: =Rev_sd^2*(1-Rev_a^8)/(1-Rev_a^2) -> 415.74352
F7: One-year fan: standard deviation | G7: =SQRT(G6) -> 20.38979
A8: Two quarters, P^2 = P P | B8: to on plan | C8: to off plan | F8: Three one-year fans compounded: the mean's factor | G8: =G5^3 -> 0.013841287
A9: from on plan | B9: =B5*B5+C5*B6 -> 0.84 | C9: =B5*C5+C5*C6 -> 0.16 | F9: Three one-year fans compounded: variance, v (1 + a^8 + a^16) | G9: =G6*(1+G5^2+G5^4) -> 441.09195
A10: from off plan | B10: =B6*B5+C6*B6 -> 0.48 | C10: =B6*C5+C6*C6 -> 0.52 | F10: The three-year fan directly: the mean's factor, a^12 | G10: =Rev_a^12 -> 0.013841287
F11: The three-year fan directly: variance, sd^2 (1 - a^24) / (1 - a^2) | G11: =Rev_sd^2*(1-Rev_a^24)/(1-Rev_a^2) -> 441.09195
A12: Three quarters, P^3 = P^2 P | B12: to on plan | C12: to off plan | F12: Gap between compounded and direct variance | G12: =ABS(G9-G11) -> 0 | H12: they compose
A13: from on plan | B13: =B9*B5+C9*B6 -> 0.804 | C13: =B9*C5+C9*C6 -> 0.196 | F13: A three-year fan stretched by the square-root law, sqrt(3) x one-year sd | G13: =SQRT(3)*G7 -> 35.316152 | H13: not this model's: it ignores the restoring force
A14: from off plan | B14: =B10*B5+C10*B6 -> 0.588 | C14: =B10*C5+C10*C6 -> 0.412 | F14: The model's three-year sd | G14: =SQRT(G11) -> 21.002189
A16: Three quarters, P P^2 | B16: to on plan | C16: to off plan
A17: from on plan | B17: =B5*B9+C5*B10 -> 0.804 | C17: =B5*C9+C5*C10 -> 0.196
A18: from off plan | B18: =B6*B9+C6*B10 -> 0.588 | C18: =B6*C9+C6*C10 -> 0.412
A20: Chapman-Kolmogorov: largest gap between P^2 P and P P^2 | B20: =MAX(ABS(B13-B17),ABS(C13-C17),ABS(B14-B18),ABS(C14-C18)) -> 0 | C20: they compose
A21: Off plan three quarters after being on plan | B21: =C13 -> 0.196 | C21: 19.6 percent
A22: A planning pack's three-quarter figure | B22: 0.3 | C22: Online Appendix 8.B.2
A23: Is the pack consistent with its own one-quarter view? | B23: =IF(ABS(B22-B21)<0.0005,"yes","no: the one-quarter view implies "&TEXT(B21,"0.0%")) -> no: the one-quarter view implies 19.6%
A24: Long-run share of quarters on plan, P(off to on) / (P(on to off) + P(off to on)) | B24: =B6/(C5+B6) -> 0.75 | C24: 0.75
A25: Average on-plan spell (quarters), 1 / P(on to off) | B25: =1/C5 -> 10 | C25: 10 quarters
A26: Average off-plan spell (quarters), 1 / P(off to on) | B26: =1/B6 -> 3.3333333 | C26: 3.3 quarters
A28: Quarter k, from on plan | B28: On plan | C28: Off plan
A29: 0 | B29: 1 | C29: 0
A30: 1 | B30: =B29*$B$5+C29*$B$6 -> 0.9 | C30: =B29*$C$5+C29*$C$6 -> 0.1
A31: 2 | B31: =B30*$B$5+C30*$B$6 -> 0.84 | C31: =B30*$C$5+C30*$C$6 -> 0.16
A32: 3 | B32: =B31*$B$5+C31*$B$6 -> 0.804 | C32: =B31*$C$5+C31*$C$6 -> 0.196
A33: 4 | B33: =B32*$B$5+C32*$B$6 -> 0.7824 | C33: =B32*$C$5+C32*$C$6 -> 0.2176
A34: 5 | B34: =B33*$B$5+C33*$B$6 -> 0.76944 | C34: =B33*$C$5+C33*$C$6 -> 0.23056
A35: 6 | B35: =B34*$B$5+C34*$B$6 -> 0.761664 | C35: =B34*$C$5+C34*$C$6 -> 0.238336
A36: 7 | B36: =B35*$B$5+C35*$B$6 -> 0.7569984 | C36: =B35*$C$5+C35*$C$6 -> 0.2430016
A37: 8 | B37: =B36*$B$5+C36*$B$6 -> 0.75419904 | C37: =B36*$C$5+C36*$C$6 -> 0.24580096
A38: 9 | B38: =B37*$B$5+C37*$B$6 -> 0.75251942 | C38: =B37*$C$5+C37*$C$6 -> 0.24748058
A39: 10 | B39: =B38*$B$5+C38*$B$6 -> 0.75151165 | C39: =B38*$C$5+C38*$C$6 -> 0.24848835
A40: 11 | B40: =B39*$B$5+C39*$B$6 -> 0.75090699 | C40: =B39*$C$5+C39*$C$6 -> 0.24909301
A41: 12 | B41: =B40*$B$5+C40*$B$6 -> 0.7505442 | C41: =B40*$C$5+C40*$C$6 -> 0.2494558

Sheet Events
A1: Price an event risk: two ledger lines (Theorem 8.4; Figure 8.3; AXIOM Lab 1.8, step 3)
A3: Regulatory interventions (Section 8.7) | B3: Value | C3: Reading
A4: E[J^2] = mean^2 + sd^2 | B4: =Reg_mean^2+Reg_sd^2 -> 2500 | C4: 2,500
A5: Plan line, lambda E[J] ($ million a year) | B5: =Reg_lam*Reg_mean -> 6 | C5: $6 million a year, quiet years included
A6: Risk line, lambda E[J^2] (variance a year) | B6: =Reg_lam*B4 -> 375 | C6: 375 a year
A7: Standard deviation over one year | B7: =SQRT(B6) -> 19.364917 | C7: about $19 million
A8: Standard deviation over five years | B8: =SQRT(5*B6) -> 43.30127 | C8: about $43 million
A9: Mean wait between interventions (years) | B9: =1/Reg_lam -> 6.6666667 | C9: about 6.7 years
A10: Chance of an intervention next year, 1 - e^(-lambda) | B10: =1-EXP(-Reg_lam) -> 0.13929202 | C10: 14 percent
A11: After five quiet years: 1 - P(quiet six years) / P(quiet five years) | B11: =1-EXP(-6*Reg_lam)/EXP(-5*Reg_lam) -> 0.13929202 | C11: the same: an event is never due (Theorem 8.4(i))
A12: Chance of at least one in five years | B12: =1-EXP(-5*Reg_lam) -> 0.52763345
A13: Half the frequency, twice the size: plan line | B13: =(Reg_lam/2)*(2*Reg_mean) -> 6 | C13: unchanged
A14: Half the frequency, twice the size: variance a year | B14: =(Reg_lam/2)*4*B4 -> 750 | C14: doubled
A15: Cost law: gamma shape, (mean / sd)^2 | B15: =(Reg_mean/Reg_sd)^2 -> 1.7777778
A16: Cost law: gamma scale, sd^2 / mean | B16: =Reg_sd^2/Reg_mean -> 22.5
A18: Funding-window closures (Worked Example 8.1, Step 2) | B18: Value | C18: Reading
A19: Plan line, lambda E[J] ($ million a year) | B19: =Lam_c*Close_mean -> 12 | C19: $12 million a year
A20: Risk line, lambda E[J^2] (variance a year) | B20: =Lam_c*(Close_mean^2+Close_sd^2) -> 1690
A21: Standard deviation over one year | B21: =SQRT(B20) -> 41.10961
A22: Chance of at least one closure in three years | B22: =1-EXP(-Lam_c*Horizon_q/4) -> 0.25918178 | C22: 26 percent
A25: Years | B25: Plan line | C25: Standard deviation | D25: Risk band: low | E25: Risk band: high
A26: 0 | B26: =Reg_lam*Reg_mean*A26 -> 0 | C26: =SQRT($B$6*A26) -> 0 | D26: =MAX(B26-2*C26,0) -> 0 | E26: =B26+2*C26 -> 0
A27: 0.5 | B27: =Reg_lam*Reg_mean*A27 -> 3 | C27: =SQRT($B$6*A27) -> 13.693064 | D27: =MAX(B27-2*C27,0) -> 0 | E27: =B27+2*C27 -> 30.386128
A28: 1 | B28: =Reg_lam*Reg_mean*A28 -> 6 | C28: =SQRT($B$6*A28) -> 19.364917 | D28: =MAX(B28-2*C28,0) -> 0 | E28: =B28+2*C28 -> 44.729833
A29: 1.5 | B29: =Reg_lam*Reg_mean*A29 -> 9 | C29: =SQRT($B$6*A29) -> 23.717082 | D29: =MAX(B29-2*C29,0) -> 0 | E29: =B29+2*C29 -> 56.434165
A30: 2 | B30: =Reg_lam*Reg_mean*A30 -> 12 | C30: =SQRT($B$6*A30) -> 27.386128 | D30: =MAX(B30-2*C30,0) -> 0 | E30: =B30+2*C30 -> 66.772256
A31: 2.5 | B31: =Reg_lam*Reg_mean*A31 -> 15 | C31: =SQRT($B$6*A31) -> 30.618622 | D31: =MAX(B31-2*C31,0) -> 0 | E31: =B31+2*C31 -> 76.237244
A32: 3 | B32: =Reg_lam*Reg_mean*A32 -> 18 | C32: =SQRT($B$6*A32) -> 33.54102 | D32: =MAX(B32-2*C32,0) -> 0 | E32: =B32+2*C32 -> 85.082039
A33: 3.5 | B33: =Reg_lam*Reg_mean*A33 -> 21 | C33: =SQRT($B$6*A33) -> 36.228442 | D33: =MAX(B33-2*C33,0) -> 0 | E33: =B33+2*C33 -> 93.456884
A34: 4 | B34: =Reg_lam*Reg_mean*A34 -> 24 | C34: =SQRT($B$6*A34) -> 38.729833 | D34: =MAX(B34-2*C34,0) -> 0 | E34: =B34+2*C34 -> 101.45967
A35: 4.5 | B35: =Reg_lam*Reg_mean*A35 -> 27 | C35: =SQRT($B$6*A35) -> 41.079192 | D35: =MAX(B35-2*C35,0) -> 0 | E35: =B35+2*C35 -> 109.15838
A36: 5 | B36: =Reg_lam*Reg_mean*A36 -> 30 | C36: =SQRT($B$6*A36) -> 43.30127 | D36: =MAX(B36-2*C36,0) -> 0 | E36: =B36+2*C36 -> 116.60254
A37: 5.5 | B37: =Reg_lam*Reg_mean*A37 -> 33 | C37: =SQRT($B$6*A37) -> 45.414755 | D37: =MAX(B37-2*C37,0) -> 0 | E37: =B37+2*C37 -> 123.82951
... A46: 10 | B46: =Reg_lam*Reg_mean*A46 -> 60 | C46: =SQRT($B$6*A46) -> 61.237244 | D46: =MAX(B46-2*C46,0) -> 0 | E46: =B46+2*C46 -> 182.47449
A48: Figure 8.3: the plan line accrues through quiet years and eventful ones alike; the risk band widens with the square root of time.

Sheet Averages
A1: Feel the flaw of averages (Theorem 8.5; Proposition 8.5; Online Appendix 8.B.7; AXIOM Lab 1.8, step 4)
A3: Linear: Worked Example 4.1's Unit A (Table 4.5) | B3: Legacy | C3: Software | D3: Total
A4: year 0 | B4: 400 | C4: 100 | D4: =B4+C4 -> 500 | F4: legacy engineers stay legacy | G4: 0.92
A5: year 1 | B5: =$G$4*B4 -> 368 | C5: =$G$6*C4+$G$5*B4 -> 108 | D5: =B5+C5 -> 476 | F5: legacy engineers retrained into software | G5: 0.03
A6: year 2 | B6: =$G$4*B5 -> 338.56 | C6: =$G$6*C5+$G$5*B5 -> 114.72 | D6: =B6+C6 -> 453.28 | F6: software engineers stay | G6: 0.96
A7: year 3 | B7: =$G$4*B6 -> 311.4752 | C7: =$G$6*C6+$G$5*B6 -> 120.288 | D7: =B7+C7 -> 431.7632
A8: year 4 | B8: =$G$4*B7 -> 286.55718 | C8: =$G$6*C7+$G$5*B7 -> 124.82074 | D8: =B8+C8 -> 411.37792
A9: year 5 | B9: =$G$4*B8 -> 263.63261 | C9: =$G$6*C8+$G$5*B8 -> 128.42462 | D9: =B9+C9 -> 392.05723
A10: Theorem 8.5(i): with random attrition restored, the mean workforce follows this roll-up exactly.
A12: Convex: Online Appendix 8.B.7's start-up | B12: Value | C12: Reading
A13: Growth near zero, r (a year) | B13: 0.9
A14: Demand volatility, sigma (a year) | B14: 0.6
A16: Years t | B16: Mean factor, e^(r t) | C16: Median factor, e^((r - sigma^2/2) t) | D16: Mean less median | E16: Paths below the mean, Phi(sigma sqrt(t) / 2)
A17: 1 | B17: =EXP($B$13*A17) -> 2.4596031 | C17: =EXP(($B$13-$B$14^2/2)*A17) -> 2.0544332 | D17: =B17-C17 -> 0.4051699 | E17: =NORMSDIST($B$14*SQRT(A17)/2) -> 0.61791142
A18: 2 | B18: =EXP($B$13*A18) -> 6.0496475 | C18: =EXP(($B$13-$B$14^2/2)*A18) -> 4.2206958 | D18: =B18-C18 -> 1.8289516 | E18: =NORMSDIST($B$14*SQRT(A18)/2) -> 0.66431338
A20: Bend the function: sigma | B20: Mean factor, one year | C20: Median factor | D20: Mean less median | E20: Paths below the mean
A21: 0 | B21: =EXP($B$13) -> 2.4596031 | C21: =EXP($B$13-A21^2/2) -> 2.4596031 | D21: =B21-C21 -> 0 | E21: =NORMSDIST(A21/2) -> 0.5
A22: 0.2 | B22: =EXP($B$13) -> 2.4596031 | C22: =EXP($B$13-A22^2/2) -> 2.4108997 | D22: =B22-C22 -> 0.048703405 | E22: =NORMSDIST(A22/2) -> 0.53982784
A23: 0.4 | B23: =EXP($B$13) -> 2.4596031 | C23: =EXP($B$13-A23^2/2) -> 2.2704998 | D23: =B23-C23 -> 0.18910327 | E23: =NORMSDIST(A23/2) -> 0.57925971
A24: 0.6 | B24: =EXP($B$13) -> 2.4596031 | C24: =EXP($B$13-A24^2/2) -> 2.0544332 | D24: =B24-C24 -> 0.4051699 | E24: =NORMSDIST(A24/2) -> 0.61791142
A25: 0.8 | B25: =EXP($B$13) -> 2.4596031 | C25: =EXP($B$13-A25^2/2) -> 1.7860384 | D25: =B25-C25 -> 0.67356468 | E25: =NORMSDIST(A25/2) -> 0.65542174
A26: The exponential is convex: the average of the outcomes runs ahead of the outcome at average inputs (the median), and the gap widens as the function bends; with no spread it closes (Proposition 8.3).
A28: Concave: Worked Example 8.1's trough | B28: Value | C28: Reading
A29: The plan's trough (Plan sheet) | B29: =Plan!B20 -> 481.95038 | C29: $482 million
A30: The mean path's trough (Plan sheet) | B30: =Plan!B31 -> 459.85405 | C30: $460 million
A31: The average of the path troughs (engine: the book's 100,000 paths, seed 8) | B31: 383.83151 | C31: $384 million
A32: The average trough lies below the plan's by | B32: =B29-B31 -> 98.11887 | C32: almost $100 million
A33: and below the mean path's trough by (Jensen: the low point is concave) | B33: =B30-B31 -> 76.022541
A35: Proposition 8.5: inherited spread | B35: Sensitivity L | C35: Steps | D35: Spread multiplied by up to L^(2k)
A36: three expansive steps | B36: 1.2 | C36: 3 | D36: =B36^(2*C36) -> 2.985984
A37: three consolidating steps | B37: 0.8 | C37: 3 | D37: =B37^(2*C37) -> 0.262144

Sheet Odds
A1: Read the answer and test the levers: Table 8.5 on the book's 100,000 paths (Worked Example 8.1, Steps 3-5; Online Appendix 8.B.6)
A2: Breach probabilities are engine values: the book's 100,000 paths, drawn with seed 8. Standard errors, troughs, the appetite test and the decomposition are formulas.
A4: Scenario (Table 8.5) | B4: Plan trough ($ million) | C4: Breach probability (engine, seed 8) | D4: Standard error, sqrt(p (1 - p) / N) | E4: Within the 5% appetite? | F4: Share of the plan's risk
A5: Plan as drawn, both channels | B5: =Plan!B20 -> 481.95038 | C5: 0.24622 | D5: =SQRT(C5*(1-C5)/N_paths) -> 0.0013623352 | E5: =IF(C5<=Appetite_p,"yes","no") -> no | F5: =C5/$C$5 -> 1
A6: Execution and market deviation only | B6: =Plan!B20 -> 481.95038 | C6: 0.08403 | D6: =SQRT(C6*(1-C6)/N_paths) -> 0.00087731955 | E6: =IF(C6<=Appetite_p,"yes","no") -> no | F6: =C6/$C$5 -> 0.34128016
A7: Funding-window events only | B7: =Plan!B20 -> 481.95038 | C7: 0.10619 | D7: =SQRT(C7*(1-C7)/N_paths) -> 0.00097423654 | E7: =IF(C7<=Appetite_p,"yes","no") -> no | F7: =C7/$C$5 -> 0.43128097
A8: Standby line (up to $100 million per closure) | B8: =Plan!B20 -> 481.95038 | C8: 0.12374 | D8: =SQRT(C8*(1-C8)/N_paths) -> 0.0010412896 | E8: =IF(C8<=Appetite_p,"yes","no") -> no | F8: =C8/$C$5 -> 0.50255869
A9: Phased build | B9: =Plan!B33 -> 530.97392 | C9: 0.13068 | D9: =SQRT(C9*(1-C9)/N_paths) -> 0.0010658459 | E9: =IF(C9<=Appetite_p,"yes","no") -> no | F9: =C9/$C$5 -> 0.53074486
A10: Standby line and phased build | B10: =Plan!B33 -> 530.97392 | C10: 0.03003 | D10: =SQRT(C10*(1-C10)/N_paths) -> 0.00053970547 | E10: =IF(C10<=Appetite_p,"yes","no") -> yes | F10: =C10/$C$5 -> 0.1219641
A12: Smallest standard error in the table | B12: =MIN(D5:D10) -> 0.00053970547 | C12: 0.05 percentage points
A13: Largest standard error in the table | B13: =MAX(D5:D10) -> 0.0013623352 | C13: 0.14 percentage points
A14: The two channels compound: together less the sum of each alone | B14: =C5-(C6+C7) -> 0.056 | C14: 8.4 + 10.6 < 24.6
A16: Read the answer (Step 4) | B16: Value | C16: Reading
A17: Planned trough (Plan sheet) | B17: =Plan!B20 -> 481.95038 | C17: $482 million
A18: The mean path's trough, exact (Plan sheet) | B18: =Plan!B31 -> 459.85405 | C18: $460 million
A19: The mean path's trough, simulated (engine, seed 8) | B19: 459.94151
A20: The average of the path troughs (engine, seed 8) | B20: 383.83151 | C20: $384 million
A21: The median path trough (engine, seed 8) | B21: 399.00265
A22: The average trough's shortfall from the plan's | B22: =B17-B20 -> 98.11887 | C22: almost $100 million
A24: Where the risk comes from (Online Appendix 8.B.6) | B24: Value | C24: Reading
A25: Paths with at least one closure (engine, seed 8) | B25: 0.25912 | C25: 25.9 percent
A26: Breach probability on those paths (engine) | B26: 0.70901513 | C26: 70.9 percent
A27: Breach probability on the others (engine) | B27: 0.08435914 | C27: 8.4 percent
A28: Total probability, pe p1 + (1 - pe) p0 | B28: =B25*B26+(1-B25)*B27 -> 0.24622 | C28: 0.246
A29: Share of breaches on paths with a closure, pe p1 / total | B29: =B25*B26/B28 -> 0.74616197 | C29: three in four
A30: Variance of the breach indicator, p (1 - p) | B30: =B28*(1-B28) -> 0.18559571 | C30: 0.186
A31: Within the two scenarios, pe p1 (1 - p1) + (1 - pe) p0 (1 - p0) | B31: =B25*B26*(1-B26)+(1-B25)*B27*(1-B27) -> 0.11068729 | C31: 0.111
A32: Between them, pe p1^2 + (1 - pe) p0^2 - p^2 | B32: =B25*B26^2+(1-B25)*B27^2-B28^2 -> 0.074908417 | C32: 0.075
A33: Share of the uncertainty that is whether a window closes | B33: =B32/B30 -> 0.40361071 | C33: 40 percent
A34: Check: within + between - total (Theorem 8.5(iii)) | B34: =B31+B32-B30 -> 0 | C34: zero

Sheet ErrorBars
A1: Vary the number of paths: the Monte Carlo error bar (Section 8.9; Online Appendix 8.B.5; AXIOM Lab 1.8, step 5)
A2: Estimates are engine values. The book's engine draws Section 8.9's three runs from their own streams, seeds 100 + N, and the worked example's 100,000 paths with seed 8.
A4: Paths N | B4: Seed (the book's engine) | C4: Estimate (engine) | D4: Standard error, sqrt(p (1 - p) / N) | E4: As printed
A5: 100 | B5: 200 | C5: 0.25 | D5: =SQRT(C5*(1-C5)/A5) -> 0.04330127 | E5: 25.0 ± 4.3
A6: 1000 | B6: 1100 | C6: 0.252 | D6: =SQRT(C6*(1-C6)/A6) -> 0.013729385 | E6: 25.2 ± 1.4
A7: 10000 | B7: 10100 | C7: 0.2449 | D7: =SQRT(C7*(1-C7)/A7) -> 0.0043002789 | E7: 24.5 ± 0.4
A8: 100000 | B8: 8 | C8: 0.24622 | D8: =SQRT(C8*(1-C8)/A8) -> 0.0013623352 | E8: 24.6, standard error 0.14
A10: Paths needed for a given error bar (Online Appendix 8.B.5) | B10: Value | C10: Reading
A11: Target standard error (one standard error, as a probability) | B11: 0.001 | C11: ±0.1 percentage point
A12: Paths needed near 5 percent, p (1 - p) / h^2 | B12: =0.05*0.95/B11^2 -> 47500 | C12: 47,500
A13: Paths needed near 25 percent | B13: =0.25*0.75/B11^2 -> 187500 | C13: 187,500
A14: One more decimal digit near 25 percent (h ten times smaller) | B14: =0.25*0.75/(B11/10)^2 -> 18750000 | C14: a hundredfold more paths

Sheet Draws
A1: The book's draws for the first 2,000 of its 100,000 paths (seed 8; engine values)
A2: z: the standard-normal surprises, quarter by quarter (the surprise is Shock_sd x z). Closure sizes ($ million) sit in the quarter they occur; a second column holds a second closure in the same quarter.
A4: Path | B4: z, q1 | C4: z, q2 | D4: z, q3 | E4: z, q4 | F4: z, q5 | G4: z, q6 | H4: z, q7 | I4: z, q8 | J4: z, q9 | K4: z, q10 | L4: z, q11 | M4: z, q12 | N4: Closure, q1 | O4: Closure, q2 | P4: Closure, q3 | Q4: Closure, q4 | R4: Closure, q5 | S4: Closure, q6 | T4: Closure, q7 | U4: Closure, q8 | V4: Closure, q9 | W4: Closure, q10 | X4: Closure, q11 | Y4: Closure, q12 | Z4: Second closure, q1 | AA4: Second closure, q2 | AB4: Second closure, q3 | AC4: Second closure, q4 | AD4: Second closure, q5 | AE4: Second closure, q6 | AF4: Second closure, q7 | AG4: Second closure, q8 | AH4: Second closure, q9 | AI4: Second closure, q10 | AJ4: Second closure, q11 | AK4: Second closure, q12
A5: 1 | B5: -1.7382664 | C5: -0.82354848 | D5: -0.260355 | E5: 0.58003543 | F5: 0.39911725 | G5: 2.2397873 | H5: -1.6917165 | I5: 0.29064117 | J5: -0.25269694 | K5: -0.0038833029 | L5: -0.3314423 | M5: 0.19350898 | V5: 116.26108
A6: 2 | B6: -1.3366428 | C6: -0.37969574 | D6: 0.68583911 | E6: 0.094085308 | F6: -0.054433325 | G6: 0.24535199 | H6: 1.2694226 | I6: 1.7533354 | J6: -0.98926548 | K6: -0.109239 | L6: 0.0017784229 | M6: 1.8297928
A7: 3 | B7: -1.3611067 | C7: -0.47413661 | D7: -0.87410914 | E7: 0.88459358 | F7: 0.42193529 | G7: -0.097711412 | H7: 2.0083556 | I7: -0.93889505 | J7: 0.21739186 | K7: -0.62781602 | L7: 0.66395739 | M7: 0.48929768 | W7: 88.73281
A8: 4 | B8: -0.35161713 | C8: -0.62123296 | D8: -1.1304902 | E8: 0.47792809 | F8: 1.0791084 | G8: -0.540004 | H8: 0.1843355 | I8: -0.36632148 | J8: 0.57479984 | K8: 0.94028261 | L8: -0.49384752 | M8: -0.058988741 | N8: 242.21484 | S8: 191.90951
A9: 5 | B9: -2.3125816 | C9: -0.87614562 | D9: 0.93472852 | E9: -0.91880822 | F9: -1.3538016 | G9: 1.0648268 | H9: -0.93036908 | I9: -0.81867701 | J9: -0.055544515 | K9: -0.33018557 | L9: -0.69210995 | M9: 0.27694639 | W9: 121.3002
A10: 6 | B10: -0.1888972 | C10: -0.82533463 | D10: 0.30435955 | E10: -1.0721117 | F10: 0.66908494 | G10: 0.66902029 | H10: 1.1400032 | I10: 0.77146776 | J10: -0.16495414 | K10: -0.15968186 | L10: 0.87990375 | M10: 0.070628452
A11: 7 | B11: -0.95722923 | C11: -1.0672263 | D11: 0.2747212 | E11: 0.21965761 | F11: -0.30603106 | G11: 0.2047837 | H11: -1.1257261 | I11: 0.22742389 | J11: -0.48652824 | K11: 0.79164028 | L11: 1.2303926 | M11: 0.63443749
A12: 8 | B12: 0.89360018 | C12: 1.5250506 | D12: -0.68604652 | E12: -0.87387587 | F12: -0.3056738 | G12: 0.12389298 | H12: -2.2931936 | I12: -0.39625968 | J12: -1.8088382 | K12: 0.16336043 | L12: 0.044452162 | M12: -0.4224667
A13: 9 | B13: 0.95684724 | C13: 1.5077485 | D13: 0.3038741 | E13: -0.5135625 | F13: -1.0482989 | G13: 0.99306082 | H13: -1.1221842 | I13: 0.12935058 | J13: -2.138555 | K13: -0.43363242 | L13: -1.2567893 | M13: 0.066334075
A14: 10 | B14: 1.3922582 | C14: -1.3722239 | D14: -1.3042378 | E14: -0.10477064 | F14: 1.0991665 | G14: 0.63781842 | H14: -0.67154445 | I14: 0.25731684 | J14: -0.68029507 | K14: 0.59353547 | L14: -0.22170183 | M14: 0.24815753
A15: 11 | B15: 0.76747011 | C15: -0.077507253 | D15: 1.0386132 | E15: -0.32818491 | F15: -0.58810705 | G15: 0.82239353 | H15: 0.086859798 | I15: -0.32775401 | J15: -1.0491233 | K15: 0.80530676 | L15: -0.585731 | M15: 0.17807018
A16: 12 | B16: -0.053029779 | C16: 0.38113762 | D16: 0.46539649 | E16: -0.26218292 | F16: 0.26255152 | G16: 1.2008831 | H16: 0.67385642 | I16: 0.45998436 | J16: 0.4114858 | K16: -0.26510618 | L16: -0.64598428 | M16: -1.3876461
A17: 13 | B17: 0.85979399 | C17: 0.66308316 | D17: -0.7522352 | E17: -0.84303665 | F17: 0.24448566 | G17: -0.18732032 | H17: -0.31006908 | I17: 0.67072159 | J17: -2.1103327 | K17: -1.0434403 | L17: 0.29247632 | M17: 0.69959199
A18: 14 | B18: 1.5054812 | C18: -0.43000558 | D18: 1.1410548 | E18: -1.1704546 | F18: -0.44465808 | G18: -0.38983784 | H18: 0.4719034 | I18: 0.97754161 | J18: -0.17388993 | K18: 1.755042 | L18: 0.32249052 | M18: 1.6437302
A19: 15 | B19: -0.65359453 | C19: 2.0188191 | D19: 1.0849329 | E19: 1.240262 | F19: -0.25307014 | G19: 0.48033246 | H19: -2.5271262 | I19: -0.4857648 | J19: -0.37904747 | K19: -0.094517476 | L19: -1.1994537 | M19: 0.84774565
A20: 16 | B20: 0.61035115 | C20: -0.32466212 | D20: 0.79434645 | E20: -0.40295322 | F20: 1.3729986 | G20: 0.88558477 | H20: -0.94336273 | I20: 2.0379258 | J20: -1.1897635 | K20: 0.78192832 | L20: 0.80578312 | M20: 0.3404807
A21: 17 | B21: -0.042673828 | C21: -0.5630373 | D21: -0.13080358 | E21: -0.35924693 | F21: -1.5251637 | G21: 0.36219806 | H21: 0.88436379 | I21: 0.3302539 | J21: 0.12722571 | K21: -0.26124176 | L21: 0.25097073 | M21: -1.7728565 | O21: 119.1164
A22: 18 | B22: 1.4400167 | C22: -1.0890433 | D22: 0.22779655 | E22: -0.22804724 | F22: -2.4002723 | G22: 0.50640216 | H22: -1.64674 | I22: 0.69228697 | J22: -0.9551003 | K22: -0.68057258 | L22: -0.79265371 | M22: -1.1080133
A23: 19 | B23: -0.83689502 | C23: -1.0016606 | D23: -1.3915319 | E23: -0.70471875 | F23: -0.27245839 | G23: -0.73536568 | H23: 0.48552357 | I23: 0.30292571 | J23: 0.74853127 | K23: -0.32809109 | L23: 1.3771913 | M23: 1.6131651
A24: 20 | B24: -0.30154661 | C24: -0.11306953 | D24: 1.5105408 | E24: -0.29865809 | F24: 0.54457046 | G24: 0.30640137 | H24: 0.22318232 | I24: -0.97404823 | J24: 0.43662899 | K24: -0.65568106 | L24: -0.74524536 | M24: 0.43836252
A25: 21 | B25: 0.36233859 | C25: 1.9546318 | D25: 0.70190004 | E25: 0.39762501 | F25: 0.22293001 | G25: 0.40561143 | H25: -0.1845148 | I25: -0.1606567 | J25: -0.27792924 | K25: 0.0035503185 | L25: -0.90803813 | M25: -1.2909422
A26: 22 | B26: 0.25811027 | C26: -0.05397466 | D26: 1.7459191 | E26: -0.48652664 | F26: 0.34512086 | G26: 0.62232344 | H26: 0.23298265 | I26: 1.0745317 | J26: -1.9230197 | K26: 1.0045463 | L26: -1.203042 | M26: -1.4001582 | O26: 157.21491
A27: 23 | B27: -1.639448 | C27: 0.36678993 | D27: -1.1217563 | E27: -1.1237523 | F27: 1.2377084 | G27: -0.9297783 | H27: -1.1205419 | I27: 0.77799023 | J27: 0.25830389 | K27: -1.4494293 | L27: 0.67129266 | M27: -0.24631105 | V27: 153.98212
A28: 24 | B28: 0.36015523 | C28: 0.85419272 | D28: 0.63797579 | E28: -1.6359479 | F28: 1.7179789 | G28: 0.61457506 | H28: 1.7040148 | I28: -1.1403921 | J28: 0.1039524 | K28: 0.27259031 | L28: -1.0154444 | M28: 0.45951136
A29: 25 | B29: -0.1184977 | C29: -1.3740505 | D29: 0.38244054 | E29: 1.8541291 | F29: 0.49033217 | G29: 2.3680212 | H29: -0.29925692 | I29: 0.6473022 | J29: 1.3048395 | K29: 1.5237408 | L29: 0.22880407 | M29: 1.4236186
A30: 26 | B30: -0.23974785 | C30: 0.84302651 | D30: -1.0076405 | E30: -0.2831061 | F30: -0.081591593 | G30: -0.60018208 | H30: -0.11625101 | I30: 0.29907574 | J30: 0.013173403 | K30: 0.53337239 | L30: 1.008456 | M30: 0.047877677
A31: 27 | B31: -0.15530166 | C31: 0.72121568 | D31: 1.1621103 | E31: -0.2607464 | F31: 1.0603844 | G31: -0.59688367 | H31: 0.20824279 | I31: 0.40997668 | J31: 3.1078846 | K31: -0.72604556 | L31: 1.3605644 | M31: -0.98204664
A32: 28 | B32: 0.21897171 | C32: -0.78340534 | D32: -0.79754202 | E32: -1.413726 | F32: 0.90146322 | G32: -0.62790777 | H32: 0.67381484 | I32: 0.26772388 | J32: -1.2986298 | K32: 0.25872484 | L32: -1.4566989 | M32: 0.30404282
A33: 29 | B33: -1.8163957 | C33: -0.31130444 | D33: 1.1071456 | E33: 0.64439487 | F33: -0.29172936 | G33: 1.166719 | H33: 0.16746234 | I33: 1.7995766 | J33: 0.38116882 | K33: -1.9143578 | L33: -0.87649229 | M33: 0.85689462
A34: 30 | B34: 1.5524666 | C34: 0.37600302 | D34: 0.28053956 | E34: 2.8309372 | F34: -0.65534255 | G34: -0.95454852 | H34: -1.5595603 | I34: 1.704306 | J34: 1.2067336 | K34: -2.6940877 | L34: -0.53945225 | M34: 2.7250905 | P34: 97.768573
A35: 31 | B35: -0.86144167 | C35: -1.036497 | D35: 1.7702363 | E35: -1.502233 | F35: -0.0066420739 | G35: 0.62314378 | H35: 0.70873886 | I35: -0.16780939 | J35: -0.77419047 | K35: 0.99190686 | L35: 1.2697079 | M35: -0.57828347
A36: 32 | B36: -2.2413679 | C36: -0.85749016 | D36: -0.65750104 | E36: -0.6456761 | F36: -0.65716711 | G36: -0.42925551 | H36: -0.79016307 | I36: 0.35268544 | J36: -1.2458507 | K36: -1.235833 | L36: 0.67753752 | M36: -0.21228045
A37: 33 | B37: -0.081974494 | C37: 1.3308017 | D37: -0.398613 | E37: -1.7936664 | F37: 0.13398024 | G37: -0.892404 | H37: -0.66361908 | I37: 0.43630047 | J37: -0.91677659 | K37: 0.20890049 | L37: 0.7887748 | M37: -1.0398757
A38: 34 | B38: 1.4574804 | C38: -0.72183961 | D38: -1.0042238 | E38: 2.2535116 | F38: 0.37766057 | G38: 0.694244 | H38: -0.21520048 | I38: 0.052689716 | J38: 1.591159 | K38: -0.25638344 | L38: -0.57244242 | M38: -1.4520774
A39: 35 | B39: -0.51860097 | C39: -0.73988894 | D39: -0.59120598 | E39: 0.35526562 | F39: -0.6556499 | G39: 0.035765795 | H39: -1.1056791 | I39: 0.61378888 | J39: 0.17885325 | K39: 0.15291506 | L39: -0.5592773 | M39: 1.0392428
A40: 36 | B40: 1.5512756 | C40: 1.0842411 | D40: 0.81950349 | E40: 0.34937313 | F40: -0.29416549 | G40: 0.05590571 | H40: 0.066272981 | I40: 1.4037748 | J40: 0.30564624 | K40: -0.061429556 | L40: 0.1069347 | M40: 0.56979732
A41: 37 | B41: 1.556942 | C41: -0.69835256 | D41: 0.52785454 | E41: -0.51916736 | F41: -0.94925876 | G41: -1.3446473 | H41: -1.0518601 | I41: -0.12100124 | J41: -0.048027386 | K41: -1.3482858 | L41: -1.0315833 | M41: -2.0022432
A42: 38 | B42: -0.86273192 | C42: -0.5394329 | D42: -0.82418592 | E42: -0.41559922 | F42: 1.2076274 | G42: 0.7780818 | H42: -0.71274104 | I42: -1.6287597 | J42: -0.92254563 | K42: 0.62017369 | L42: -0.14519074 | M42: -1.0028594
A43: 39 | B43: -2.4651208 | C43: 0.060149239 | D43: 0.28858531 | E43: -0.45538658 | F43: -1.1330538 | G43: -0.6899536 | H43: 0.03135831 | I43: -1.0344005 | J43: -1.2676741 | K43: 0.11260911 | L43: 0.36905007 | M43: -0.19451118
A44: 40 | B44: -1.2351828 | C44: 0.023585186 | D44: -2.2018796 | E44: -1.4789239 | F44: 0.3674302 | G44: -0.8703993 | H44: -0.67104417 | I44: 0.0001286746 | J44: 0.84219184 | K44: -0.54386481 | L44: 0.56667614 | M44: -0.79101743
A45: 41 | B45: 1.1874322 | C45: 0.88281379 | D45: 0.01796959 | E45: -0.53127304 | F45: 2.9430598 | G45: -1.4311907 | H45: 1.2083487 | I45: 1.087624 | J45: 1.8965211 | K45: 0.0082012121 | L45: -0.97989989 | M45: 1.4119141 | S45: 139.38562 | U45: 119.2138
A46: 42 | B46: -0.81677217 | C46: -2.0907035 | D46: 0.62270576 | E46: -1.1705308 | F46: -0.65947973 | G46: -0.25934105 | H46: 0.63445884 | I46: 1.2116 | J46: 1.6081959 | K46: -0.59156116 | L46: 1.1505521 | M46: -0.31544472
A47: 43 | B47: -1.5106775 | C47: 0.0093113878 | D47: 2.3247864 | E47: -0.66106904 | F47: 1.5615538 | G47: 2.0348556 | H47: 0.57821611 | I47: -0.91439779 | J47: 0.17217023 | K47: -0.54898239 | L47: 0.6445722 | M47: -1.2828804
A48: 44 | B48: -1.3376947 | C48: -1.4555619 | D48: -0.53593782 | E48: 0.98971588 | F48: -1.3453502 | G48: 0.049919809 | H48: -0.51837778 | I48: 0.83553695 | J48: 0.099017392 | K48: -0.10858556 | L48: 1.5820902 | M48: 0.65855184 | Y48: 136.32901
A49: 45 | B49: 0.00018014422 | C49: 0.60949208 | D49: 1.9190526 | E49: -0.40860097 | F49: -0.28980753 | G49: -0.13195136 | H49: 0.15490003 | I49: 0.46893966 | J49: 0.2465292 | K49: 0.97743107 | L49: -1.4125816 | M49: -0.11707616 | W49: 127.22723
A50: 46 | B50: -0.026108484 | C50: -1.4787067 | D50: 0.71064095 | E50: -0.93159083 | F50: 2.0076396 | G50: -0.078453912 | H50: 0.43000461 | I50: -0.23318198 | J50: 0.92694717 | K50: -1.6562025 | L50: 0.42091867 | M50: -0.28155858 | X50: 75.121107
A51: 47 | B51: 0.87204491 | C51: 0.51701759 | D51: -0.23340479 | E51: 0.67954077 | F51: 0.77530033 | G51: 0.56751766 | H51: 0.30585022 | I51: 0.4677179 | J51: -0.24323335 | K51: -0.17675626 | L51: 2.0855046 | M51: 0.40729983
A52: 48 | B52: 0.98904997 | C52: 0.3599403 | D52: -0.75793574 | E52: -0.40241956 | F52: 0.067735074 | G52: -1.3752485 | H52: 0.26743842 | I52: -0.68067497 | J52: 0.15943216 | K52: -0.19632697 | L52: -0.12545968 | M52: 1.0261307
A53: 49 | B53: -0.93224902 | C53: -0.63174187 | D53: -0.11684297 | E53: -0.41400782 | F53: 0.77284087 | G53: -0.52836129 | H53: -1.1794583 | I53: 0.093228345 | J53: 0.019781907 | K53: -1.0624306 | L53: 0.87797321 | M53: -0.067944089
A54: 50 | B54: -0.1567587 | C54: -1.8448785 | D54: 1.2848268 | E54: -1.2714546 | F54: -0.12479193 | G54: 0.17808627 | H54: -1.372218 | I54: 0.1764524 | J54: -0.39853104 | K54: -0.7197873 | L54: -0.51362599 | M54: -0.66832342
A55: 51 | B55: -1.1339346 | C55: 0.95481983 | D55: 0.83847545 | E55: -0.15760641 | F55: 0.084602372 | G55: -0.70588215 | H55: 0.79461285 | I55: -1.1101616 | J55: -0.048576773 | K55: -0.72981056 | L55: 1.1708301 | M55: -0.42130192 | R55: 53.533517
A56: 52 | B56: 0.071890672 | C56: -0.52114507 | D56: 1.0311476 | E56: 0.67543389 | F56: -0.20898599 | G56: 2.3604483 | H56: 0.40390753 | I56: -0.16344438 | J56: -0.22298361 | K56: 1.0213062 | L56: -0.76066541 | M56: -1.6595
A57: 53 | B57: -1.1506078 | C57: 1.4594855 | D57: 0.19024641 | E57: -0.95523556 | F57: 1.4531716 | G57: -0.22979047 | H57: 0.30168839 | I57: -0.19622004 | J57: -0.98708164 | K57: 0.92380714 | L57: 0.54762052 | M57: 0.025426228
A58: 54 | B58: -1.2002516 | C58: -0.98375442 | D58: -0.27684899 | E58: 0.40869911 | F58: 0.35636208 | G58: -1.0868919 | H58: -1.4909269 | I58: 0.5942603 | J58: -0.75135092 | K58: -0.25458511 | L58: 1.0409043 | M58: 0.92847257 | N58: 128.75104
A59: 55 | B59: 2.1234219 | C59: 0.59523665 | D59: 1.6041721 | E59: 0.92782397 | F59: 0.092423135 | G59: 1.2294751 | H59: 0.53647124 | I59: 1.1798288 | J59: -0.39966208 | K59: -0.61104934 | L59: -0.33935211 | M59: -0.70569515
A60: 56 | B60: 0.032388888 | C60: -1.7803583 | D60: -0.19909896 | E60: 0.2835039 | F60: 0.35852888 | G60: 0.6861692 | H60: -0.96545535 | I60: 0.12112824 | J60: -0.017374621 | K60: -0.24795632 | L60: 0.48346662 | M60: -0.56068167 | Y60: 89.632868
A61: 57 | B61: 0.64317861 | C61: 1.4270709 | D61: -0.39834491 | E61: 1.6136026 | F61: 0.32603241 | G61: 0.34552579 | H61: 1.0197399 | I61: 0.21498311 | J61: 0.14417076 | K61: 1.0538165 | L61: 1.1380838 | M61: 0.30455634
A62: 58 | B62: 2.5380984 | C62: -0.10409915 | D62: -0.38687579 | E62: 0.39528091 | F62: -1.1483588 | G62: 1.6516091 | H62: -1.2308583 | I62: -0.5008695 | J62: 0.53852116 | K62: -1.0947208 | L62: 2.201488 | M62: 0.48448454
A63: 59 | B63: 0.78583882 | C63: 0.60550935 | D63: 0.94350294 | E63: -0.29702871 | F63: 0.88240323 | G63: -1.9453244 | H63: -0.22983448 | I63: 2.086005 | J63: -1.9629227 | K63: -0.11397951 | L63: -0.3114787 | M63: -1.1071738
A64: 60 | B64: -0.1141426 | C64: 0.7801306 | D64: 1.472061 | E64: -1.0651437 | F64: 0.13502541 | G64: 0.13953385 | H64: -1.6405234 | I64: -0.37341488 | J64: -0.86450784 | K64: 0.29725218 | L64: 0.40212067 | M64: 0.079719638
A65: 61 | B65: 0.054589952 | C65: 0.66866793 | D65: -1.1621784 | E65: 0.070213587 | F65: -0.5655688 | G65: 0.80733637 | H65: 0.83011442 | I65: -0.40508819 | J65: -0.14047756 | K65: -0.82690553 | L65: -0.37219331 | M65: -0.46213984
A66: 62 | B66: -0.74449197 | C66: 0.98665153 | D66: -0.81398973 | E66: -0.53944748 | F66: -1.9843045 | G66: 0.28963205 | H66: 1.514568 | I66: -0.15555966 | J66: 1.9589611 | K66: -2.3940279 | L66: -1.5528675 | M66: 0.13141831 | R66: 44.218702
A67: 63 | B67: 1.0943384 | C67: 0.63181986 | D67: 0.68502877 | E67: -0.70231952 | F67: -1.2901379 | G67: -2.1140656 | H67: 0.054496192 | I67: -0.21478359 | J67: -0.37360022 | K67: -0.82466648 | L67: 1.1476001 | M67: -0.84305381
A68: 64 | B68: -0.33027869 | C68: -1.3370984 | D68: -0.81568707 | E68: -0.17420246 | F68: 1.3040059 | G68: 1.2304486 | H68: 1.2883653 | I68: -1.283242 | J68: 0.57757932 | K68: 1.5753067 | L68: 0.76434428 | M68: 0.32705304
A69: 65 | B69: 1.7627455 | C69: -0.36262856 | D69: -0.23258021 | E69: 1.2240566 | F69: 0.11025436 | G69: 1.5704096 | H69: 0.18925132 | I69: -0.049397124 | J69: -0.14864264 | K69: 1.2300383 | L69: -1.0364365 | M69: 0.20928196
A70: 66 | B70: -0.34475854 | C70: 1.2364893 | D70: -0.96228815 | E70: -1.5160969 | F70: -0.89938041 | G70: 1.9177445 | H70: 0.22889947 | I70: -0.7679718 | J70: 1.2190361 | K70: 1.5829069 | L70: -0.81382966 | M70: 0.053970183
A71: 67 | B71: -0.35362293 | C71: -1.2466974 | D71: -0.37634773 | E71: -1.8689362 | F71: 0.61667773 | G71: -1.1042378 | H71: -0.918762 | I71: -1.0504094 | J71: 1.0430198 | K71: -0.64365228 | L71: -0.67778104 | M71: -0.21520181
A72: 68 | B72: -0.4193774 | C72: 1.6896531 | D72: -0.61610017 | E72: 0.49822933 | F72: 2.1612873 | G72: 0.73713252 | H72: -0.31656034 | I72: -1.0651648 | J72: -0.86312227 | K72: -1.6501943 | L72: 1.1232873 | M72: 0.75777125 | T72: 73.523796
A73: 69 | B73: 0.62569388 | C73: 0.068725724 | D73: -0.021236596 | E73: -1.0550439 | F73: 0.4619021 | G73: -1.0044636 | H73: -0.39726199 | I73: -0.1400946 | J73: 0.15437549 | K73: 1.2909376 | L73: 0.51911257 | M73: 0.71533058
A74: 70 | B74: 0.18693607 | C74: -0.76639867 | D74: -0.68776044 | E74: 1.6591616 | F74: -0.048107836 | G74: -2.1090811 | H74: 2.2880688 | I74: -1.902488 | J74: 0.95073879 | K74: -0.52001816 | L74: -0.33436366 | M74: 0.62954673
A75: 71 | B75: 1.3714324 | C75: -0.25033042 | D75: 0.0048144259 | E75: 0.56945508 | F75: -0.7095146 | G75: -1.1855915 | H75: -0.011275129 | I75: 0.23222481 | J75: -0.60704758 | K75: -1.2668757 | L75: 0.64502728 | M75: 0.67053588 | P75: 104.37612
A76: 72 | B76: -0.55334962 | C76: -1.3666841 | D76: 1.2770645 | E76: 1.1927842 | F76: -0.17079101 | G76: 0.75673123 | H76: 1.4368233 | I76: -1.3009243 | J76: 0.54874074 | K76: 0.99279042 | L76: -0.25393303 | M76: 0.48359007 | Q76: 50.126291
A77: 73 | B77: 0.29023814 | C77: 0.66987432 | D77: 0.66609996 | E77: 1.7876816 | F77: -0.50442697 | G77: 0.64510722 | H77: -0.41314899 | I77: 2.2441239 | J77: -0.32347936 | K77: -1.1393615 | L77: -2.2665704 | M77: -0.036799658 | P77: 133.76321
A78: 74 | B78: 1.9379617 | C78: 1.3852012 | D78: 1.3333208 | E78: 1.0479164 | F78: -1.1803892 | G78: 0.718281 | H78: 0.30679833 | I78: 1.2103471 | J78: -0.46101944 | K78: 0.41257858 | L78: -0.36385949 | M78: -0.99696273
A79: 75 | B79: -0.24038169 | C79: 0.2676931 | D79: 0.043333906 | E79: -1.1200602 | F79: -1.2788752 | G79: -0.28307273 | H79: 0.47670132 | I79: -0.23874468 | J79: 0.37576384 | K79: 0.28996962 | L79: -0.39603293 | M79: 0.77397564
A80: 76 | B80: 0.53261279 | C80: -0.25442468 | D80: -0.79105155 | E80: -0.40963256 | F80: -0.98240712 | G80: 0.44032956 | H80: 0.26531505 | I80: -0.31600135 | J80: 0.71802015 | K80: 0.22598221 | L80: -0.13634644 | M80: -0.9640726
A81: 77 | B81: 1.5718822 | C81: 0.39975389 | D81: -0.98273877 | E81: 0.30668219 | F81: 0.30373767 | G81: 0.82292788 | H81: -1.2009504 | I81: -1.6518976 | J81: 1.5983878 | K81: 0.16937092 | L81: 1.7864823 | M81: -0.087170187
A82: 78 | B82: 0.55344578 | C82: -1.389944 | D82: 1.7434801 | E82: -0.30539868 | F82: 0.89101027 | G82: -1.9918154 | H82: 0.95006509 | I82: 0.38389369 | J82: 0.23427175 | K82: -0.11489607 | L82: -0.79070848 | M82: 0.51124942
A83: 79 | B83: -0.63450517 | C83: 0.64047838 | D83: -0.020269517 | E83: 1.6944646 | F83: -0.58788365 | G83: 1.5791623 | H83: 1.3045469 | I83: -0.42616683 | J83: -1.5076673 | K83: 0.28243716 | L83: -0.89243285 | M83: -1.1674067 | U83: 114.60536
A84: 80 | B84: -2.06235 | C84: -0.066145437 | D84: -0.53066166 | E84: 0.34865103 | F84: -0.33160378 | G84: -1.4149937 | H84: -2.1706268 | I84: 0.7610773 | J84: -0.38625984 | K84: -0.45418417 | L84: 0.6642711 | M84: 0.021051752
A85: 81 | B85: 2.3931636 | C85: -0.087724728 | D85: 0.94684773 | E85: -0.0031117784 | F85: -0.20908004 | G85: 0.53817509 | H85: 0.70209904 | I85: -1.1524435 | J85: -0.87451957 | K85: -0.69559519 | L85: 0.54100614 | M85: -0.79965592
A86: 82 | B86: 0.43031428 | C86: -2.7001757 | D86: -1.1995266 | E86: 0.79710111 | F86: 2.572189 | G86: 0.7510054 | H86: -1.2291044 | I86: 1.5326638 | J86: 0.21979194 | K86: 0.35619277 | L86: 0.60946766 | M86: -0.047630063
A87: 83 | B87: 1.2605289 | C87: 0.83310785 | D87: 0.0077192554 | E87: -2.276329 | F87: -1.7016955 | G87: -1.2153089 | H87: 0.58545832 | I87: 0.98128177 | J87: 0.68659866 | K87: 0.06294803 | L87: -0.6081888 | M87: 0.8265285
A88: 84 | B88: -0.47631355 | C88: 0.80150512 | D88: 0.76163184 | E88: 0.57638487 | F88: 0.93790853 | G88: 1.5461931 | H88: 0.73557619 | I88: 0.71212853 | J88: 0.32650409 | K88: 0.3395281 | L88: -1.1338504 | M88: 1.8605006 | R88: 224.86921
A89: 85 | B89: 1.8184817 | C89: -0.3834231 | D89: 1.0055265 | E89: -0.32452108 | F89: -0.37553544 | G89: 0.67177061 | H89: -0.72812955 | I89: 1.4042732 | J89: 0.25085418 | K89: -0.20951887 | L89: 0.78706151 | M89: -0.97774104
A90: 86 | B90: 0.51953936 | C90: -0.33386273 | D90: -0.35087001 | E90: 1.298512 | F90: 0.034630573 | G90: 0.043589492 | H90: -0.95095231 | I90: 0.15110038 | J90: -0.78268347 | K90: -1.0001266 | L90: 0.18937348 | M90: 0.94727339
A91: 87 | B91: 0.049797443 | C91: 0.5303514 | D91: -0.33689453 | E91: -0.045457819 | F91: -1.0940318 | G91: 1.0325204 | H91: 0.47319225 | I91: -1.389908 | J91: -1.1667173 | K91: -0.67883083 | L91: 0.47501592 | M91: -0.53089136
A92: 88 | B92: -0.90181719 | C92: -0.85112757 | D92: -1.1967225 | E92: 0.11909839 | F92: -0.63988065 | G92: 0.32504716 | H92: -1.4634088 | I92: 0.29124533 | J92: 0.22411048 | K92: 0.35491093 | L92: 0.89492654 | M92: 0.97165666
A93: 89 | B93: 0.36818472 | C93: -0.05805984 | D93: -1.3627939 | E93: -0.44448001 | F93: -0.29088831 | G93: 0.0065774862 | H93: -0.34890601 | I93: 0.83470276 | J93: 0.78385576 | K93: 1.2230502 | L93: -1.1526998 | M93: -0.55969745
A94: 90 | B94: -0.48653003 | C94: -0.72007252 | D94: 1.2140068 | E94: -0.0078713562 | F94: -0.56554252 | G94: 1.6216436 | H94: 0.67251968 | I94: 1.393367 | J94: -0.78695095 | K94: 0.4650067 | L94: 1.9672498 | M94: 0.31218169
A95: 91 | B95: -0.22276918 | C95: -1.0050741 | D95: 1.9725295 | E95: 1.5706195 | F95: -1.3292118 | G95: -1.1284808 | H95: -1.0750718 | I95: -0.49988088 | J95: -0.85132945 | K95: 1.3671698 | L95: -2.5818088 | M95: 1.1273259
A96: 92 | B96: -1.6225108 | C96: 1.3686171 | D96: -0.1870068 | E96: -0.7338353 | F96: -0.14575644 | G96: -0.68723381 | H96: 0.74708685 | I96: 0.96800941 | J96: 0.9773682 | K96: -0.20164276 | L96: 0.12835726 | M96: -1.5863616 | Y96: 99.002749
A97: 93 | B97: -0.49055393 | C97: -0.83099096 | D97: -0.91657569 | E97: -0.26984241 | F97: -1.1206921 | G97: -2.1688184 | H97: 1.2806092 | I97: -0.73521756 | J97: 0.44389881 | K97: -0.11080598 | L97: 1.3057226 | M97: 1.2984083
A98: 94 | B98: 0.15987903 | C98: -1.4334234 | D98: 0.20909064 | E98: -1.0194954 | F98: -1.7260939 | G98: -0.3548765 | H98: -0.91983968 | I98: -0.17971078 | J98: 1.6131689 | K98: -1.1239366 | L98: 0.30249182 | M98: -3.4716101
A99: 95 | B99: -1.2508062 | C99: 0.91008428 | D99: -0.52522767 | E99: 0.3774139 | F99: 0.93827899 | G99: -1.7176542 | H99: 0.42336829 | I99: 0.056615704 | J99: -0.73188772 | K99: -1.7055576 | L99: -0.31361062 | M99: 0.87592714 | T99: 232.31223
A100: 96 | B100: 0.07389651 | C100: -0.83582251 | D100: 2.5464221 | E100: 1.3147949 | F100: 0.81129252 | G100: 1.1092211 | H100: -1.7235796 | I100: -0.70199274 | J100: -0.44356056 | K100: -1.6701436 | L100: -1.5465421 | M100: 0.51646352
A101: 97 | B101: 0.66329388 | C101: 1.1119818 | D101: -1.4843255 | E101: 1.1040878 | F101: 2.0525022 | G101: 0.87428087 | H101: 1.0948244 | I101: 1.2436263 | J101: 1.0212262 | K101: -1.2877145 | L101: -0.014584965 | M101: 0.92750643
...

Sheet Bench
A1: Put odds on the program: 2,000 of the book's paths, rebuilt by formula (Worked Example 8.1, Steps 3-5; AXIOM Lab 1.8, step 5)
A2: Each row is one of the first 2,000 of the book's 100,000 paths (seed 8); its draws are on Draws. E_k = a E_k-1 + Shock_sd z_k; closures to date J_k, and net of the standby line; liquidity = plan + E + J. Change the floor, the persistence, the surprise, the line or the phasing on Declarations and every scenario recomputes.
A4: Scenario | B4: Breaches on these paths | C4: Breach probability | D4: Standard error | E4: The engine on the same paths | F4: The book's 100,000 paths (Table 8.5)
A5: Plan as drawn, both channels | B5: =COUNTIF($AL$26:$AL$2025,"<"&Floor_L) -> 521 | C5: =B5/2000 -> 0.2605 | D5: =SQRT(C5*(1-C5)/2000) -> 0.0098142689 | E5: 521 | F5: =Odds!C5 -> 0.24622
A6: Execution and market deviation only | B6: =COUNTIF($AM$26:$AM$2025,"<"&Floor_L) -> 180 | C6: =B6/2000 -> 0.09 | D6: =SQRT(C6*(1-C6)/2000) -> 0.0063992187 | E6: 180 | F6: =Odds!C6 -> 0.08403
A7: Funding-window events only | B7: =COUNTIF($AN$26:$AN$2025,"<"&Floor_L) -> 232 | C7: =B7/2000 -> 0.116 | D7: =SQRT(C7*(1-C7)/2000) -> 0.0071604469 | E7: 232 | F7: =Odds!C7 -> 0.10619
A8: Standby line (up to $100 million per closure) | B8: =COUNTIF($AO$26:$AO$2025,"<"&Floor_L) -> 267 | C8: =B8/2000 -> 0.1335 | D8: =SQRT(C8*(1-C8)/2000) -> 0.0076051874 | E8: 267 | F8: =Odds!C8 -> 0.12374
A9: Phased build | B9: =COUNTIF($AP$26:$AP$2025,"<"&Floor_L) -> 268 | C9: =B9/2000 -> 0.134 | D9: =SQRT(C9*(1-C9)/2000) -> 0.0076172173 | E9: 268 | F9: =Odds!C9 -> 0.13068
A10: Standby line and phased build | B10: =COUNTIF($AQ$26:$AQ$2025,"<"&Floor_L) -> 61 | C10: =B10/2000 -> 0.0305 | D10: =SQRT(C10*(1-C10)/2000) -> 0.0038451105 | E10: 61 | F10: =Odds!C10 -> 0.03003
A12: Paths with at least one closure | B12: =COUNTIF($AR$26:$AR$2025,1) -> 529 | C12: =B12/2000 -> 0.2645 | E12: 529
A13: Breaches on paths with a closure (plan as drawn) | B13: =COUNTIFS($AR$26:$AR$2025,1,$AL$26:$AL$2025,"<"&Floor_L) -> 380 | C13: =B13/B5 -> 0.7293666 | E13: 380
A15: Watch the error bar shrink: the first N paths | B15: Breaches | C15: Estimate | D15: Standard error | E15: The engine on the same paths | F15: 95% interval: low | G15: 95% interval: high
A16: 100 | B16: =COUNTIFS($A$26:$A$2025,"<="&A16,$AL$26:$AL$2025,"<"&Floor_L) -> 26 | C16: =B16/A16 -> 0.26 | D16: =SQRT(C16*(1-C16)/A16) -> 0.043863424 | E16: 26 | F16: =C16-1.96*D16 -> 0.17402769 | G16: =C16+1.96*D16 -> 0.34597231
A17: 250 | B17: =COUNTIFS($A$26:$A$2025,"<="&A17,$AL$26:$AL$2025,"<"&Floor_L) -> 70 | C17: =B17/A17 -> 0.28 | D17: =SQRT(C17*(1-C17)/A17) -> 0.028397183 | E17: 70 | F17: =C17-1.96*D17 -> 0.22434152 | G17: =C17+1.96*D17 -> 0.33565848
A18: 500 | B18: =COUNTIFS($A$26:$A$2025,"<="&A18,$AL$26:$AL$2025,"<"&Floor_L) -> 133 | C18: =B18/A18 -> 0.266 | D18: =SQRT(C18*(1-C18)/A18) -> 0.019760769 | E18: 133 | F18: =C18-1.96*D18 -> 0.22726889 | G18: =C18+1.96*D18 -> 0.30473111
A19: 1000 | B19: =COUNTIFS($A$26:$A$2025,"<="&A19,$AL$26:$AL$2025,"<"&Floor_L) -> 261 | C19: =B19/A19 -> 0.261 | D19: =SQRT(C19*(1-C19)/A19) -> 0.013888088 | E19: 261 | F19: =C19-1.96*D19 -> 0.23377935 | G19: =C19+1.96*D19 -> 0.28822065
A20: 2000 | B20: =COUNTIFS($A$26:$A$2025,"<="&A20,$AL$26:$AL$2025,"<"&Floor_L) -> 521 | C20: =B20/A20 -> 0.2605 | D20: =SQRT(C20*(1-C20)/A20) -> 0.0098142689 | E20: 521 | F20: =C20-1.96*D20 -> 0.24126403 | G20: =C20+1.96*D20 -> 0.27973597
A22: Plan, quarters 1-12 ($ million) | B22: =Plan!D6 -> 574.17772 | C22: =Plan!D7 -> 540.0666 | D22: =Plan!D8 -> 515.55419 | E22: =Plan!D9 -> 498.8622 | F22: =Plan!D10 -> 488.49718 | G22: =Plan!D11 -> 483.20817 | H22: =Plan!D12 -> 481.95038 | I22: =Plan!D13 -> 483.85405 | J22: =Plan!D14 -> 488.19778 | K22: =Plan!D15 -> 494.3857 | L22: =Plan!D16 -> 501.92795 | M22: =Plan!D17 -> 510.42405
A23: Phased plan, quarters 1-12 | B23: =Plan!F6 -> 589.05075 | C23: =Plan!F7 -> 566.3174 | D23: =Plan!F8 -> 550.30356 | E23: =Plan!F9 -> 539.75049 | F23: =Plan!F10 -> 533.60192 | G23: =Plan!F11 -> 530.97392 | H23: =Plan!F12 -> 531.12903 | I23: =Plan!F13 -> 533.45405 | J23: =Plan!F14 -> 537.44111 | K23: =Plan!F15 -> 542.67134 | L23: =Plan!F16 -> 548.80108 | M23: =Plan!F17 -> 555.54993
A25: Path | B25: E_1 | C25: E_2 | D25: E_3 | E25: E_4 | F25: E_5 | G25: E_6 | H25: E_7 | I25: E_8 | J25: E_9 | K25: E_10 | L25: E_11 | M25: E_12 | N25: J_1 | O25: J_2 | P25: J_3 | Q25: J_4 | R25: J_5 | S25: J_6 | T25: J_7 | U25: J_8 | V25: J_9 | W25: J_10 | X25: J_11 | Y25: J_12 | Z25: J_1, with the line | AA25: J_2, with the line | AB25: J_3, with the line | AC25: J_4, with the line | AD25: J_5, with the line | AE25: J_6, with the line | AF25: J_7, with the line | AG25: J_8, with the line | AH25: J_9, with the line | AI25: J_10, with the line | AJ25: J_11, with the line | AK25: J_12, with the line | AL25: Trough: both channels | AM25: Trough: deviation only | AN25: Trough: events only | AO25: Trough: standby line | AP25: Trough: phased build | AQ25: Trough: line and phasing | AR25: A closure?
A26: 1 | B26: =Shock_sd*Draws!B5 -> -86.91332 | C26: =Persist_a*B26+Shock_sd*Draws!C5 -> -93.325416 | D26: =Persist_a*C26+Shock_sd*Draws!D5 -> -69.013 | E26: =Persist_a*D26+Shock_sd*Draws!E5 -> -12.406028 | F26: =Persist_a*E26+Shock_sd*Draws!F5 -> 12.512245 | G26: =Persist_a*F26+Shock_sd*Draws!G5 -> 119.49671 | H26: =Persist_a*G26+Shock_sd*Draws!H5 -> -12.887798 | I26: =Persist_a*H26+Shock_sd*Draws!I5 -> 6.7993796 | J26: =Persist_a*I26+Shock_sd*Draws!J5 -> -8.555219 | ... M26: =Persist_a*L26+Shock_sd*Draws!M5 -> -2.1856466 | N26: =0-(Draws!N5+Draws!Z5) -> 0 | O26: =N26-(Draws!O5+Draws!AA5) -> 0 | P26: =O26-(Draws!P5+Draws!AB5) -> 0 | Q26: =P26-(Draws!Q5+Draws!AC5) -> 0 | R26: =Q26-(Draws!R5+Draws!AD5) -> 0 | S26: =R26-(Draws!S5+Draws!AE5) -> 0 | T26: =S26-(Draws!T5+Draws!AF5) -> 0 | U26: =T26-(Draws!U5+Draws!AG5) -> 0 | V26: =U26-(Draws!V5+Draws!AH5) -> -116.26108 | ... Y26: =X26-(Draws!Y5+Draws!AK5) -> -116.26108 | Z26: =0-(MAX(Draws!N5-Line_cap,0)+MAX(Draws!Z5-Line_cap,0)) -> 0 | AA26: =Z26-(MAX(Draws!O5-Line_cap,0)+MAX(Draws!AA5-Line_cap,0)) -> 0 | AB26: =AA26-(MAX(Draws!P5-Line_cap,0)+MAX(Draws!AB5-Line_cap,0)) -> 0 | AC26: =AB26-(MAX(Draws!Q5-Line_cap,0)+MAX(Draws!AC5-Line_cap,0)) -> 0 | AD26: =AC26-(MAX(Draws!R5-Line_cap,0)+MAX(Draws!AD5-Line_cap,0)) -> 0 | AE26: =AD26-(MAX(Draws!S5-Line_cap,0)+MAX(Draws!AE5-Line_cap,0)) -> 0 | AF26: =AE26-(MAX(Draws!T5-Line_cap,0)+MAX(Draws!AF5-Line_cap,0)) -> 0 | AG26: =AF26-(MAX(Draws!U5-Line_cap,0)+MAX(Draws!AG5-Line_cap,0)) -> 0 | AH26: =AG26-(MAX(Draws!V5-Line_cap,0)+MAX(Draws!AH5-Line_cap,0)) -> -16.261078 | ... AK26: =AJ26-(MAX(Draws!Y5-Line_cap,0)+MAX(Draws!AK5-Line_cap,0)) -> -16.261078 | AL26: =SUMPRODUCT(MIN($B$22:$M$22+B26:M26+N26:Y26)) -> 363.38148 | AM26: =SUMPRODUCT(MIN($B$22:$M$22+B26:M26)) -> 446.54119 | AN26: =SUMPRODUCT(MIN($B$22:$M$22+N26:Y26)) -> 371.9367 | AO26: =SUMPRODUCT(MIN($B$22:$M$22+B26:M26+Z26:AK26)) -> 446.54119 | AP26: =SUMPRODUCT(MIN($B$23:$M$23+B26:M26+N26:Y26)) -> 412.62481 | AQ26: =SUMPRODUCT(MIN($B$23:$M$23+B26:M26+Z26:AK26)) -> 472.99198 | AR26: =IF(Y26<0,1,0) -> 1
A27: 2 | B27: =Shock_sd*Draws!B6 -> -66.83214 | C27: =Persist_a*B27+Shock_sd*Draws!C6 -> -59.084071 | D27: =Persist_a*C27+Shock_sd*Draws!D6 -> -1.1584868 | E27: =Persist_a*D27+Shock_sd*Draws!E6 -> 4.0091734 | F27: =Persist_a*E27+Shock_sd*Draws!F6 -> -0.31616224 | G27: =Persist_a*F27+Shock_sd*Draws!G6 -> 12.077902 | H27: =Persist_a*G27+Shock_sd*Draws!H6 -> 70.717873 | I27: =Persist_a*H27+Shock_sd*Draws!I6 -> 130.09749 | J27: =Persist_a*I27+Shock_sd*Draws!J6 -> 28.595221 | ... M27: =Persist_a*L27+Shock_sd*Draws!M6 -> 95.753257 | N27: =0-(Draws!N6+Draws!Z6) -> 0 | O27: =N27-(Draws!O6+Draws!AA6) -> 0 | P27: =O27-(Draws!P6+Draws!AB6) -> 0 | Q27: =P27-(Draws!Q6+Draws!AC6) -> 0 | R27: =Q27-(Draws!R6+Draws!AD6) -> 0 | S27: =R27-(Draws!S6+Draws!AE6) -> 0 | T27: =S27-(Draws!T6+Draws!AF6) -> 0 | U27: =T27-(Draws!U6+Draws!AG6) -> 0 | V27: =U27-(Draws!V6+Draws!AH6) -> 0 | ... Y27: =X27-(Draws!Y6+Draws!AK6) -> 0 | Z27: =0-(MAX(Draws!N6-Line_cap,0)+MAX(Draws!Z6-Line_cap,0)) -> 0 | AA27: =Z27-(MAX(Draws!O6-Line_cap,0)+MAX(Draws!AA6-Line_cap,0)) -> 0 | AB27: =AA27-(MAX(Draws!P6-Line_cap,0)+MAX(Draws!AB6-Line_cap,0)) -> 0 | AC27: =AB27-(MAX(Draws!Q6-Line_cap,0)+MAX(Draws!AC6-Line_cap,0)) -> 0 | AD27: =AC27-(MAX(Draws!R6-Line_cap,0)+MAX(Draws!AD6-Line_cap,0)) -> 0 | AE27: =AD27-(MAX(Draws!S6-Line_cap,0)+MAX(Draws!AE6-Line_cap,0)) -> 0 | AF27: =AE27-(MAX(Draws!T6-Line_cap,0)+MAX(Draws!AF6-Line_cap,0)) -> 0 | AG27: =AF27-(MAX(Draws!U6-Line_cap,0)+MAX(Draws!AG6-Line_cap,0)) -> 0 | AH27: =AG27-(MAX(Draws!V6-Line_cap,0)+MAX(Draws!AH6-Line_cap,0)) -> 0 | ... AK27: =AJ27-(MAX(Draws!Y6-Line_cap,0)+MAX(Draws!AK6-Line_cap,0)) -> 0 | AL27: =SUMPRODUCT(MIN($B$22:$M$22+B27:M27+N27:Y27)) -> 480.98253 | AM27: =SUMPRODUCT(MIN($B$22:$M$22+B27:M27)) -> 480.98253 | AN27: =SUMPRODUCT(MIN($B$22:$M$22+N27:Y27)) -> 481.95038 | AO27: =SUMPRODUCT(MIN($B$22:$M$22+B27:M27+Z27:AK27)) -> 480.98253 | AP27: =SUMPRODUCT(MIN($B$23:$M$23+B27:M27+N27:Y27)) -> 507.23333 | AQ27: =SUMPRODUCT(MIN($B$23:$M$23+B27:M27+Z27:AK27)) -> 507.23333 | AR27: =IF(Y27<0,1,0) -> 0
A28: 3 | B28: =Shock_sd*Draws!B7 -> -68.055335 | C28: =Persist_a*B28+Shock_sd*Draws!C7 -> -64.540032 | D28: =Persist_a*C28+Shock_sd*Draws!D7 -> -82.429476 | E28: =Persist_a*D28+Shock_sd*Draws!E7 -> -5.2280065 | F28: =Persist_a*E28+Shock_sd*Draws!F7 -> 17.95996 | G28: =Persist_a*F28+Shock_sd*Draws!G7 -> 5.8904056 | H28: =Persist_a*G28+Shock_sd*Draws!H7 -> 103.95202 | I28: =Persist_a*H28+Shock_sd*Draws!I7 -> 15.42646 | J28: =Persist_a*I28+Shock_sd*Draws!J7 -> 20.125469 | ... M28: =Persist_a*L28+Shock_sd*Draws!M7 -> 37.430019 | N28: =0-(Draws!N7+Draws!Z7) -> 0 | O28: =N28-(Draws!O7+Draws!AA7) -> 0 | P28: =O28-(Draws!P7+Draws!AB7) -> 0 | Q28: =P28-(Draws!Q7+Draws!AC7) -> 0 | R28: =Q28-(Draws!R7+Draws!AD7) -> 0 | S28: =R28-(Draws!S7+Draws!AE7) -> 0 | T28: =S28-(Draws!T7+Draws!AF7) -> 0 | U28: =T28-(Draws!U7+Draws!AG7) -> 0 | V28: =U28-(Draws!V7+Draws!AH7) -> 0 | ... Y28: =X28-(Draws!Y7+Draws!AK7) -> -88.73281 | Z28: =0-(MAX(Draws!N7-Line_cap,0)+MAX(Draws!Z7-Line_cap,0)) -> 0 | AA28: =Z28-(MAX(Draws!O7-Line_cap,0)+MAX(Draws!AA7-Line_cap,0)) -> 0 | AB28: =AA28-(MAX(Draws!P7-Line_cap,0)+MAX(Draws!AB7-Line_cap,0)) -> 0 | AC28: =AB28-(MAX(Draws!Q7-Line_cap,0)+MAX(Draws!AC7-Line_cap,0)) -> 0 | AD28: =AC28-(MAX(Draws!R7-Line_cap,0)+MAX(Draws!AD7-Line_cap,0)) -> 0 | AE28: =AD28-(MAX(Draws!S7-Line_cap,0)+MAX(Draws!AE7-Line_cap,0)) -> 0 | AF28: =AE28-(MAX(Draws!T7-Line_cap,0)+MAX(Draws!AF7-Line_cap,0)) -> 0 | AG28: =AF28-(MAX(Draws!U7-Line_cap,0)+MAX(Draws!AG7-Line_cap,0)) -> 0 | AH28: =AG28-(MAX(Draws!V7-Line_cap,0)+MAX(Draws!AH7-Line_cap,0)) -> 0 | ... AK28: =AJ28-(MAX(Draws!Y7-Line_cap,0)+MAX(Draws!AK7-Line_cap,0)) -> 0 | AL28: =SUMPRODUCT(MIN($B$22:$M$22+B28:M28+N28:Y28)) -> 386.33737 | AM28: =SUMPRODUCT(MIN($B$22:$M$22+B28:M28)) -> 433.12471 | AN28: =SUMPRODUCT(MIN($B$22:$M$22+N28:Y28)) -> 405.65289 | AO28: =SUMPRODUCT(MIN($B$22:$M$22+B28:M28+Z28:AK28)) -> 433.12471 | AP28: =SUMPRODUCT(MIN($B$23:$M$23+B28:M28+N28:Y28)) -> 434.62301 | AQ28: =SUMPRODUCT(MIN($B$23:$M$23+B28:M28+Z28:AK28)) -> 467.87409 | AR28: =IF(Y28<0,1,0) -> 1
A29: 4 | B29: =Shock_sd*Draws!B8 -> -17.580857 | C29: =Persist_a*B29+Shock_sd*Draws!C8 -> -41.610162 | D29: =Persist_a*C29+Shock_sd*Draws!D8 -> -81.490607 | E29: =Persist_a*D29+Shock_sd*Draws!E8 -> -24.997959 | F29: =Persist_a*E29+Shock_sd*Draws!F8 -> 38.956642 | G29: =Persist_a*F29+Shock_sd*Draws!G8 -> -3.6262148 | H29: =Persist_a*G29+Shock_sd*Draws!H8 -> 7.0410461 | I29: =Persist_a*H29+Shock_sd*Draws!I8 -> -14.091446 | J29: =Persist_a*I29+Shock_sd*Draws!J8 -> 20.285124 | ... M29: =Persist_a*L29+Shock_sd*Draws!M8 -> 3.541811 | N29: =0-(Draws!N8+Draws!Z8) -> -242.21484 | O29: =N29-(Draws!O8+Draws!AA8) -> -242.21484 | P29: =O29-(Draws!P8+Draws!AB8) -> -242.21484 | Q29: =P29-(Draws!Q8+Draws!AC8) -> -242.21484 | R29: =Q29-(Draws!R8+Draws!AD8) -> -242.21484 | S29: =R29-(Draws!S8+Draws!AE8) -> -434.12435 | T29: =S29-(Draws!T8+Draws!AF8) -> -434.12435 | U29: =T29-(Draws!U8+Draws!AG8) -> -434.12435 | V29: =U29-(Draws!V8+Draws!AH8) -> -434.12435 | ... Y29: =X29-(Draws!Y8+Draws!AK8) -> -434.12435 | Z29: =0-(MAX(Draws!N8-Line_cap,0)+MAX(Draws!Z8-Line_cap,0)) -> -142.21484 | AA29: =Z29-(MAX(Draws!O8-Line_cap,0)+MAX(Draws!AA8-Line_cap,0)) -> -142.21484 | AB29: =AA29-(MAX(Draws!P8-Line_cap,0)+MAX(Draws!AB8-Line_cap,0)) -> -142.21484 | AC29: =AB29-(MAX(Draws!Q8-Line_cap,0)+MAX(Draws!AC8-Line_cap,0)) -> -142.21484 | AD29: =AC29-(MAX(Draws!R8-Line_cap,0)+MAX(Draws!AD8-Line_cap,0)) -> -142.21484 | AE29: =AD29-(MAX(Draws!S8-Line_cap,0)+MAX(Draws!AE8-Line_cap,0)) -> -234.12435 | AF29: =AE29-(MAX(Draws!T8-Line_cap,0)+MAX(Draws!AF8-Line_cap,0)) -> -234.12435 | AG29: =AF29-(MAX(Draws!U8-Line_cap,0)+MAX(Draws!AG8-Line_cap,0)) -> -234.12435 | AH29: =AG29-(MAX(Draws!V8-Line_cap,0)+MAX(Draws!AH8-Line_cap,0)) -> -234.12435 | ... AK29: =AJ29-(MAX(Draws!Y8-Line_cap,0)+MAX(Draws!AK8-Line_cap,0)) -> -234.12435 | AL29: =SUMPRODUCT(MIN($B$22:$M$22+B29:M29+N29:Y29)) -> 35.638259 | AM29: =SUMPRODUCT(MIN($B$22:$M$22+B29:M29)) -> 434.06358 | AN29: =SUMPRODUCT(MIN($B$22:$M$22+N29:Y29)) -> 47.826034 | AO29: =SUMPRODUCT(MIN($B$22:$M$22+B29:M29+Z29:AK29)) -> 235.63826 | AP29: =SUMPRODUCT(MIN($B$23:$M$23+B29:M29+N29:Y29)) -> 85.238259 | AQ29: =SUMPRODUCT(MIN($B$23:$M$23+B29:M29+Z29:AK29)) -> 285.23826 | AR29: =IF(Y29<0,1,0) -> 1
A30: 5 | B30: =Shock_sd*Draws!B9 -> -115.62908 | C30: =Persist_a*B30+Shock_sd*Draws!C9 -> -113.18473 | D30: =Persist_a*C30+Shock_sd*Draws!D9 -> -21.174411 | E30: =Persist_a*D30+Shock_sd*Draws!E9 -> -58.645058 | F30: =Persist_a*E30+Shock_sd*Draws!F9 -> -102.87712 | G30: =Persist_a*F30+Shock_sd*Draws!G9 -> -8.4849293 | H30: =Persist_a*G30+Shock_sd*Draws!H9 -> -51.609412 | I30: =Persist_a*H30+Shock_sd*Draws!I9 -> -71.899497 | J30: =Persist_a*I30+Shock_sd*Draws!J9 -> -45.916924 | ... M30: =Persist_a*L30+Shock_sd*Draws!M9 -> -22.777375 | N30: =0-(Draws!N9+Draws!Z9) -> 0 | O30: =N30-(Draws!O9+Draws!AA9) -> 0 | P30: =O30-(Draws!P9+Draws!AB9) -> 0 | Q30: =P30-(Draws!Q9+Draws!AC9) -> 0 | R30: =Q30-(Draws!R9+Draws!AD9) -> 0 | S30: =R30-(Draws!S9+Draws!AE9) -> 0 | T30: =S30-(Draws!T9+Draws!AF9) -> 0 | U30: =T30-(Draws!U9+Draws!AG9) -> 0 | V30: =U30-(Draws!V9+Draws!AH9) -> 0 | ... Y30: =X30-(Draws!Y9+Draws!AK9) -> -121.3002 | Z30: =0-(MAX(Draws!N9-Line_cap,0)+MAX(Draws!Z9-Line_cap,0)) -> 0 | AA30: =Z30-(MAX(Draws!O9-Line_cap,0)+MAX(Draws!AA9-Line_cap,0)) -> 0 | AB30: =AA30-(MAX(Draws!P9-Line_cap,0)+MAX(Draws!AB9-Line_cap,0)) -> 0 | AC30: =AB30-(MAX(Draws!Q9-Line_cap,0)+MAX(Draws!AC9-Line_cap,0)) -> 0 | AD30: =AC30-(MAX(Draws!R9-Line_cap,0)+MAX(Draws!AD9-Line_cap,0)) -> 0 | AE30: =AD30-(MAX(Draws!S9-Line_cap,0)+MAX(Draws!AE9-Line_cap,0)) -> 0 | AF30: =AE30-(MAX(Draws!T9-Line_cap,0)+MAX(Draws!AF9-Line_cap,0)) -> 0 | AG30: =AF30-(MAX(Draws!U9-Line_cap,0)+MAX(Draws!AG9-Line_cap,0)) -> 0 | AH30: =AG30-(MAX(Draws!V9-Line_cap,0)+MAX(Draws!AH9-Line_cap,0)) -> 0 | ... AK30: =AJ30-(MAX(Draws!Y9-Line_cap,0)+MAX(Draws!AK9-Line_cap,0)) -> -21.300201 | AL30: =SUMPRODUCT(MIN($B$22:$M$22+B30:M30+N30:Y30)) -> 319.58659 | AM30: =SUMPRODUCT(MIN($B$22:$M$22+B30:M30)) -> 385.62006 | AN30: =SUMPRODUCT(MIN($B$22:$M$22+N30:Y30)) -> 373.0855 | AO30: =SUMPRODUCT(MIN($B$22:$M$22+B30:M30+Z30:AK30)) -> 385.62006 | AP30: =SUMPRODUCT(MIN($B$23:$M$23+B30:M30+N30:Y30)) -> 366.45972 | AQ30: =SUMPRODUCT(MIN($B$23:$M$23+B30:M30+Z30:AK30)) -> 430.7248 | AR30: =IF(Y30<0,1,0) -> 1
A31: 6 | B31: =Shock_sd*Draws!B10 -> -9.4448598 | C31: =Persist_a*B31+Shock_sd*Draws!C10 -> -46.933648 | D31: =Persist_a*C31+Shock_sd*Draws!D10 -> -12.942211 | E31: =Persist_a*D31+Shock_sd*Draws!E10 -> -61.370912 | F31: =Persist_a*E31+Shock_sd*Draws!F10 -> -3.3683002 | G31: =Persist_a*F31+Shock_sd*Draws!G10 -> 31.430034 | H31: =Persist_a*G31+Shock_sd*Draws!H10 -> 75.858178 | I31: =Persist_a*H31+Shock_sd*Draws!I10 -> 84.088295 | J31: =Persist_a*I31+Shock_sd*Draws!J10 -> 42.20527 | ... M31: =Persist_a*L31+Shock_sd*Draws!M10 -> 36.1706 | N31: =0-(Draws!N10+Draws!Z10) -> 0 | O31: =N31-(Draws!O10+Draws!AA10) -> 0 | P31: =O31-(Draws!P10+Draws!AB10) -> 0 | Q31: =P31-(Draws!Q10+Draws!AC10) -> 0 | R31: =Q31-(Draws!R10+Draws!AD10) -> 0 | S31: =R31-(Draws!S10+Draws!AE10) -> 0 | T31: =S31-(Draws!T10+Draws!AF10) -> 0 | U31: =T31-(Draws!U10+Draws!AG10) -> 0 | V31: =U31-(Draws!V10+Draws!AH10) -> 0 | ... Y31: =X31-(Draws!Y10+Draws!AK10) -> 0 | Z31: =0-(MAX(Draws!N10-Line_cap,0)+MAX(Draws!Z10-Line_cap,0)) -> 0 | AA31: =Z31-(MAX(Draws!O10-Line_cap,0)+MAX(Draws!AA10-Line_cap,0)) -> 0 | AB31: =AA31-(MAX(Draws!P10-Line_cap,0)+MAX(Draws!AB10-Line_cap,0)) -> 0 | AC31: =AB31-(MAX(Draws!Q10-Line_cap,0)+MAX(Draws!AC10-Line_cap,0)) -> 0 | AD31: =AC31-(MAX(Draws!R10-Line_cap,0)+MAX(Draws!AD10-Line_cap,0)) -> 0 | AE31: =AD31-(MAX(Draws!S10-Line_cap,0)+MAX(Draws!AE10-Line_cap,0)) -> 0 | AF31: =AE31-(MAX(Draws!T10-Line_cap,0)+MAX(Draws!AF10-Line_cap,0)) -> 0 | AG31: =AF31-(MAX(Draws!U10-Line_cap,0)+MAX(Draws!AG10-Line_cap,0)) -> 0 | AH31: =AG31-(MAX(Draws!V10-Line_cap,0)+MAX(Draws!AH10-Line_cap,0)) -> 0 | ... AK31: =AJ31-(MAX(Draws!Y10-Line_cap,0)+MAX(Draws!AK10-Line_cap,0)) -> 0 | AL31: =SUMPRODUCT(MIN($B$22:$M$22+B31:M31+N31:Y31)) -> 437.49129 | AM31: =SUMPRODUCT(MIN($B$22:$M$22+B31:M31)) -> 437.49129 | AN31: =SUMPRODUCT(MIN($B$22:$M$22+N31:Y31)) -> 481.95038 | AO31: =SUMPRODUCT(MIN($B$22:$M$22+B31:M31+Z31:AK31)) -> 437.49129 | AP31: =SUMPRODUCT(MIN($B$23:$M$23+B31:M31+N31:Y31)) -> 478.37958 | AQ31: =SUMPRODUCT(MIN($B$23:$M$23+B31:M31+Z31:AK31)) -> 478.37958 | AR31: =IF(Y31<0,1,0) -> 0
A32: 7 | B32: =Shock_sd*Draws!B11 -> -47.861461 | C32: =Persist_a*B32+Shock_sd*Draws!C11 -> -82.078192 | D32: =Persist_a*C32+Shock_sd*Draws!D11 -> -35.510855 | E32: =Persist_a*D32+Shock_sd*Draws!E11 -> -10.323632 | F32: =Persist_a*E32+Shock_sd*Draws!F11 -> -21.495733 | G32: =Persist_a*F32+Shock_sd*Draws!G11 -> -2.6582547 | H32: =Persist_a*G32+Shock_sd*Draws!H11 -> -57.881259 | I32: =Persist_a*H32+Shock_sd*Draws!I11 -> -23.357561 | J32: =Persist_a*I32+Shock_sd*Draws!J11 -> -38.340948 | ... M32: =Persist_a*L32+Shock_sd*Draws!M11 -> 74.601533 | N32: =0-(Draws!N11+Draws!Z11) -> 0 | O32: =N32-(Draws!O11+Draws!AA11) -> 0 | P32: =O32-(Draws!P11+Draws!AB11) -> 0 | Q32: =P32-(Draws!Q11+Draws!AC11) -> 0 | R32: =Q32-(Draws!R11+Draws!AD11) -> 0 | S32: =R32-(Draws!S11+Draws!AE11) -> 0 | T32: =S32-(Draws!T11+Draws!AF11) -> 0 | U32: =T32-(Draws!U11+Draws!AG11) -> 0 | V32: =U32-(Draws!V11+Draws!AH11) -> 0 | ... Y32: =X32-(Draws!Y11+Draws!AK11) -> 0 | Z32: =0-(MAX(Draws!N11-Line_cap,0)+MAX(Draws!Z11-Line_cap,0)) -> 0 | AA32: =Z32-(MAX(Draws!O11-Line_cap,0)+MAX(Draws!AA11-Line_cap,0)) -> 0 | AB32: =AA32-(MAX(Draws!P11-Line_cap,0)+MAX(Draws!AB11-Line_cap,0)) -> 0 | AC32: =AB32-(MAX(Draws!Q11-Line_cap,0)+MAX(Draws!AC11-Line_cap,0)) -> 0 | AD32: =AC32-(MAX(Draws!R11-Line_cap,0)+MAX(Draws!AD11-Line_cap,0)) -> 0 | AE32: =AD32-(MAX(Draws!S11-Line_cap,0)+MAX(Draws!AE11-Line_cap,0)) -> 0 | AF32: =AE32-(MAX(Draws!T11-Line_cap,0)+MAX(Draws!AF11-Line_cap,0)) -> 0 | AG32: =AF32-(MAX(Draws!U11-Line_cap,0)+MAX(Draws!AG11-Line_cap,0)) -> 0 | AH32: =AG32-(MAX(Draws!V11-Line_cap,0)+MAX(Draws!AH11-Line_cap,0)) -> 0 | ... AK32: =AJ32-(MAX(Draws!Y11-Line_cap,0)+MAX(Draws!AK11-Line_cap,0)) -> 0 | AL32: =SUMPRODUCT(MIN($B$22:$M$22+B32:M32+N32:Y32)) -> 424.06912 | AM32: =SUMPRODUCT(MIN($B$22:$M$22+B32:M32)) -> 424.06912 | AN32: =SUMPRODUCT(MIN($B$22:$M$22+N32:Y32)) -> 481.95038 | AO32: =SUMPRODUCT(MIN($B$22:$M$22+B32:M32+Z32:AK32)) -> 424.06912 | AP32: =SUMPRODUCT(MIN($B$23:$M$23+B32:M32+N32:Y32)) -> 473.24777 | AQ32: =SUMPRODUCT(MIN($B$23:$M$23+B32:M32+Z32:AK32)) -> 473.24777 | AR32: =IF(Y32<0,1,0) -> 0
A33: 8 | B33: =Shock_sd*Draws!B12 -> 44.680009 | C33: =Persist_a*B33+Shock_sd*Draws!C12 -> 103.06053 | D33: =Persist_a*C33+Shock_sd*Draws!D12 -> 27.533994 | E33: =Persist_a*D33+Shock_sd*Draws!E12 -> -27.173397 | F33: =Persist_a*E33+Shock_sd*Draws!F12 -> -31.587728 | G33: =Persist_a*F33+Shock_sd*Draws!G12 -> -12.757988 | H33: =Persist_a*G33+Shock_sd*Draws!H12 -> -122.31447 | I33: =Persist_a*H33+Shock_sd*Draws!I12 -> -93.201666 | J33: =Persist_a*I33+Shock_sd*Draws!J12 -> -146.36291 | ... M33: =Persist_a*L33+Shock_sd*Draws!M12 -> -48.463671 | N33: =0-(Draws!N12+Draws!Z12) -> 0 | O33: =N33-(Draws!O12+Draws!AA12) -> 0 | P33: =O33-(Draws!P12+Draws!AB12) -> 0 | Q33: =P33-(Draws!Q12+Draws!AC12) -> 0 | R33: =Q33-(Draws!R12+Draws!AD12) -> 0 | S33: =R33-(Draws!S12+Draws!AE12) -> 0 | T33: =S33-(Draws!T12+Draws!AF12) -> 0 | U33: =T33-(Draws!U12+Draws!AG12) -> 0 | V33: =U33-(Draws!V12+Draws!AH12) -> 0 | ... Y33: =X33-(Draws!Y12+Draws!AK12) -> 0 | Z33: =0-(MAX(Draws!N12-Line_cap,0)+MAX(Draws!Z12-Line_cap,0)) -> 0 | AA33: =Z33-(MAX(Draws!O12-Line_cap,0)+MAX(Draws!AA12-Line_cap,0)) -> 0 | AB33: =AA33-(MAX(Draws!P12-Line_cap,0)+MAX(Draws!AB12-Line_cap,0)) -> 0 | AC33: =AB33-(MAX(Draws!Q12-Line_cap,0)+MAX(Draws!AC12-Line_cap,0)) -> 0 | AD33: =AC33-(MAX(Draws!R12-Line_cap,0)+MAX(Draws!AD12-Line_cap,0)) -> 0 | AE33: =AD33-(MAX(Draws!S12-Line_cap,0)+MAX(Draws!AE12-Line_cap,0)) -> 0 | AF33: =AE33-(MAX(Draws!T12-Line_cap,0)+MAX(Draws!AF12-Line_cap,0)) -> 0 | AG33: =AF33-(MAX(Draws!U12-Line_cap,0)+MAX(Draws!AG12-Line_cap,0)) -> 0 | AH33: =AG33-(MAX(Draws!V12-Line_cap,0)+MAX(Draws!AH12-Line_cap,0)) -> 0 | ... AK33: =AJ33-(MAX(Draws!Y12-Line_cap,0)+MAX(Draws!AK12-Line_cap,0)) -> 0 | AL33: =SUMPRODUCT(MIN($B$22:$M$22+B33:M33+N33:Y33)) -> 341.83487 | AM33: =SUMPRODUCT(MIN($B$22:$M$22+B33:M33)) -> 341.83487 | AN33: =SUMPRODUCT(MIN($B$22:$M$22+N33:Y33)) -> 481.95038 | AO33: =SUMPRODUCT(MIN($B$22:$M$22+B33:M33+Z33:AK33)) -> 341.83487 | AP33: =SUMPRODUCT(MIN($B$23:$M$23+B33:M33+N33:Y33)) -> 391.0782 | AQ33: =SUMPRODUCT(MIN($B$23:$M$23+B33:M33+Z33:AK33)) -> 391.0782 | AR33: =IF(Y33<0,1,0) -> 0
A34: 9 | B34: =Shock_sd*Draws!B13 -> 47.842362 | C34: =Persist_a*B34+Shock_sd*Draws!C13 -> 104.09284 | D34: =Persist_a*C34+Shock_sd*Draws!D13 -> 77.649409 | E34: =Persist_a*D34+Shock_sd*Draws!E13 -> 20.911521 | F34: =Persist_a*E34+Shock_sd*Draws!F13 -> -39.868031 | G34: =Persist_a*F34+Shock_sd*Draws!G13 -> 25.732222 | H34: =Persist_a*G34+Shock_sd*Draws!H13 -> -40.669877 | I34: =Persist_a*H34+Shock_sd*Draws!I13 -> -17.934397 | J34: =Persist_a*I34+Shock_sd*Draws!J13 -> -117.68839 | ... M34: =Persist_a*L34+Shock_sd*Draws!M13 -> -67.613051 | N34: =0-(Draws!N13+Draws!Z13) -> 0 | O34: =N34-(Draws!O13+Draws!AA13) -> 0 | P34: =O34-(Draws!P13+Draws!AB13) -> 0 | Q34: =P34-(Draws!Q13+Draws!AC13) -> 0 | R34: =Q34-(Draws!R13+Draws!AD13) -> 0 | S34: =R34-(Draws!S13+Draws!AE13) -> 0 | T34: =S34-(Draws!T13+Draws!AF13) -> 0 | U34: =T34-(Draws!U13+Draws!AG13) -> 0 | V34: =U34-(Draws!V13+Draws!AH13) -> 0 | ... Y34: =X34-(Draws!Y13+Draws!AK13) -> 0 | Z34: =0-(MAX(Draws!N13-Line_cap,0)+MAX(Draws!Z13-Line_cap,0)) -> 0 | AA34: =Z34-(MAX(Draws!O13-Line_cap,0)+MAX(Draws!AA13-Line_cap,0)) -> 0 | AB34: =AA34-(MAX(Draws!P13-Line_cap,0)+MAX(Draws!AB13-Line_cap,0)) -> 0 | AC34: =AB34-(MAX(Draws!Q13-Line_cap,0)+MAX(Draws!AC13-Line_cap,0)) -> 0 | AD34: =AC34-(MAX(Draws!R13-Line_cap,0)+MAX(Draws!AD13-Line_cap,0)) -> 0 | AE34: =AD34-(MAX(Draws!S13-Line_cap,0)+MAX(Draws!AE13-Line_cap,0)) -> 0 | AF34: =AE34-(MAX(Draws!T13-Line_cap,0)+MAX(Draws!AF13-Line_cap,0)) -> 0 | AG34: =AF34-(MAX(Draws!U13-Line_cap,0)+MAX(Draws!AG13-Line_cap,0)) -> 0 | AH34: =AG34-(MAX(Draws!V13-Line_cap,0)+MAX(Draws!AH13-Line_cap,0)) -> 0 | ... AK34: =AJ34-(MAX(Draws!Y13-Line_cap,0)+MAX(Draws!AK13-Line_cap,0)) -> 0 | AL34: =SUMPRODUCT(MIN($B$22:$M$22+B34:M34+N34:Y34)) -> 370.50939 | AM34: =SUMPRODUCT(MIN($B$22:$M$22+B34:M34)) -> 370.50939 | AN34: =SUMPRODUCT(MIN($B$22:$M$22+N34:Y34)) -> 481.95038 | AO34: =SUMPRODUCT(MIN($B$22:$M$22+B34:M34+Z34:AK34)) -> 370.50939 | AP34: =SUMPRODUCT(MIN($B$23:$M$23+B34:M34+N34:Y34)) -> 419.75272 | AQ34: =SUMPRODUCT(MIN($B$23:$M$23+B34:M34+Z34:AK34)) -> 419.75272 | AR34: =IF(Y34<0,1,0) -> 0
A35: 10 | B35: =Shock_sd*Draws!B14 -> 69.612911 | C35: =Persist_a*B35+Shock_sd*Draws!C14 -> -26.843448 | D35: =Persist_a*C35+Shock_sd*Draws!D14 -> -81.317958 | E35: =Persist_a*D35+Shock_sd*Draws!E14 -> -54.029307 | F35: =Persist_a*E35+Shock_sd*Draws!F14 -> 22.540743 | G35: =Persist_a*F35+Shock_sd*Draws!G14 -> 45.415367 | H35: =Persist_a*G35+Shock_sd*Draws!H14 -> -6.3280026 | I35: =Persist_a*H35+Shock_sd*Draws!I14 -> 9.0690403 | J35: =Persist_a*I35+Shock_sd*Draws!J14 -> -28.573329 | ... M35: =Persist_a*L35+Shock_sd*Draws!M14 -> 10.268621 | N35: =0-(Draws!N14+Draws!Z14) -> 0 | O35: =N35-(Draws!O14+Draws!AA14) -> 0 | P35: =O35-(Draws!P14+Draws!AB14) -> 0 | Q35: =P35-(Draws!Q14+Draws!AC14) -> 0 | R35: =Q35-(Draws!R14+Draws!AD14) -> 0 | S35: =R35-(Draws!S14+Draws!AE14) -> 0 | T35: =S35-(Draws!T14+Draws!AF14) -> 0 | U35: =T35-(Draws!U14+Draws!AG14) -> 0 | V35: =U35-(Draws!V14+Draws!AH14) -> 0 | ... Y35: =X35-(Draws!Y14+Draws!AK14) -> 0 | Z35: =0-(MAX(Draws!N14-Line_cap,0)+MAX(Draws!Z14-Line_cap,0)) -> 0 | AA35: =Z35-(MAX(Draws!O14-Line_cap,0)+MAX(Draws!AA14-Line_cap,0)) -> 0 | AB35: =AA35-(MAX(Draws!P14-Line_cap,0)+MAX(Draws!AB14-Line_cap,0)) -> 0 | AC35: =AB35-(MAX(Draws!Q14-Line_cap,0)+MAX(Draws!AC14-Line_cap,0)) -> 0 | AD35: =AC35-(MAX(Draws!R14-Line_cap,0)+MAX(Draws!AD14-Line_cap,0)) -> 0 | AE35: =AD35-(MAX(Draws!S14-Line_cap,0)+MAX(Draws!AE14-Line_cap,0)) -> 0 | AF35: =AE35-(MAX(Draws!T14-Line_cap,0)+MAX(Draws!AF14-Line_cap,0)) -> 0 | AG35: =AF35-(MAX(Draws!U14-Line_cap,0)+MAX(Draws!AG14-Line_cap,0)) -> 0 | AH35: =AG35-(MAX(Draws!V14-Line_cap,0)+MAX(Draws!AH14-Line_cap,0)) -> 0 | ... AK35: =AJ35-(MAX(Draws!Y14-Line_cap,0)+MAX(Draws!AK14-Line_cap,0)) -> 0 | AL35: =SUMPRODUCT(MIN($B$22:$M$22+B35:M35+N35:Y35)) -> 434.23623 | AM35: =SUMPRODUCT(MIN($B$22:$M$22+B35:M35)) -> 434.23623 | AN35: =SUMPRODUCT(MIN($B$22:$M$22+N35:Y35)) -> 481.95038 | AO35: =SUMPRODUCT(MIN($B$22:$M$22+B35:M35+Z35:AK35)) -> 434.23623 | AP35: =SUMPRODUCT(MIN($B$23:$M$23+B35:M35+N35:Y35)) -> 468.9856 | AQ35: =SUMPRODUCT(MIN($B$23:$M$23+B35:M35+Z35:AK35)) -> 468.9856 | AR35: =IF(Y35<0,1,0) -> 0
A36: 11 | B36: =Shock_sd*Draws!B15 -> 38.373506 | C36: =Persist_a*B36+Shock_sd*Draws!C15 -> 19.148741 | D36: =Persist_a*C36+Shock_sd*Draws!D15 -> 63.419905 | E36: =Persist_a*D36+Shock_sd*Draws!E15 -> 21.642698 | F36: =Persist_a*E36+Shock_sd*Draws!F15 -> -16.419734 | G36: =Persist_a*F36+Shock_sd*Draws!G15 -> 31.267836 | H36: =Persist_a*G36+Shock_sd*Draws!H15 -> 23.103692 | I36: =Persist_a*H36+Shock_sd*Draws!I15 -> -2.5254858 | J36: =Persist_a*I36+Shock_sd*Draws!J15 -> -53.971458 | ... M36: =Persist_a*L36+Shock_sd*Draws!M15 -> -5.8307341 | N36: =0-(Draws!N15+Draws!Z15) -> 0 | O36: =N36-(Draws!O15+Draws!AA15) -> 0 | P36: =O36-(Draws!P15+Draws!AB15) -> 0 | Q36: =P36-(Draws!Q15+Draws!AC15) -> 0 | R36: =Q36-(Draws!R15+Draws!AD15) -> 0 | S36: =R36-(Draws!S15+Draws!AE15) -> 0 | T36: =S36-(Draws!T15+Draws!AF15) -> 0 | U36: =T36-(Draws!U15+Draws!AG15) -> 0 | V36: =U36-(Draws!V15+Draws!AH15) -> 0 | ... Y36: =X36-(Draws!Y15+Draws!AK15) -> 0 | Z36: =0-(MAX(Draws!N15-Line_cap,0)+MAX(Draws!Z15-Line_cap,0)) -> 0 | AA36: =Z36-(MAX(Draws!O15-Line_cap,0)+MAX(Draws!AA15-Line_cap,0)) -> 0 | AB36: =AA36-(MAX(Draws!P15-Line_cap,0)+MAX(Draws!AB15-Line_cap,0)) -> 0 | AC36: =AB36-(MAX(Draws!Q15-Line_cap,0)+MAX(Draws!AC15-Line_cap,0)) -> 0 | AD36: =AC36-(MAX(Draws!R15-Line_cap,0)+MAX(Draws!AD15-Line_cap,0)) -> 0 | AE36: =AD36-(MAX(Draws!S15-Line_cap,0)+MAX(Draws!AE15-Line_cap,0)) -> 0 | AF36: =AE36-(MAX(Draws!T15-Line_cap,0)+MAX(Draws!AF15-Line_cap,0)) -> 0 | AG36: =AF36-(MAX(Draws!U15-Line_cap,0)+MAX(Draws!AG15-Line_cap,0)) -> 0 | AH36: =AG36-(MAX(Draws!V15-Line_cap,0)+MAX(Draws!AH15-Line_cap,0)) -> 0 | ... AK36: =AJ36-(MAX(Draws!Y15-Line_cap,0)+MAX(Draws!AK15-Line_cap,0)) -> 0 | AL36: =SUMPRODUCT(MIN($B$22:$M$22+B36:M36+N36:Y36)) -> 434.22632 | AM36: =SUMPRODUCT(MIN($B$22:$M$22+B36:M36)) -> 434.22632 | AN36: =SUMPRODUCT(MIN($B$22:$M$22+N36:Y36)) -> 481.95038 | AO36: =SUMPRODUCT(MIN($B$22:$M$22+B36:M36+Z36:AK36)) -> 434.22632 | AP36: =SUMPRODUCT(MIN($B$23:$M$23+B36:M36+N36:Y36)) -> 483.46965 | AQ36: =SUMPRODUCT(MIN($B$23:$M$23+B36:M36+Z36:AK36)) -> 483.46965 | AR36: =IF(Y36<0,1,0) -> 0
A37: 12 | B37: =Shock_sd*Draws!B16 -> -2.6514889 | C37: =Persist_a*B37+Shock_sd*Draws!C16 -> 17.465988 | D37: =Persist_a*C37+Shock_sd*Draws!D16 -> 33.749417 | E37: =Persist_a*D37+Shock_sd*Draws!E16 -> 7.1405043 | F37: =Persist_a*E37+Shock_sd*Draws!F16 -> 17.411878 | G37: =Persist_a*F37+Shock_sd*Draws!G16 -> 70.491282 | H37: =Persist_a*G37+Shock_sd*Draws!H16 -> 75.98759 | I37: =Persist_a*H37+Shock_sd*Draws!I16 -> 68.591773 | J37: =Persist_a*I37+Shock_sd*Draws!J16 -> 61.729353 | ... M37: =Persist_a*L37+Shock_sd*Draws!M16 -> -80.200206 | N37: =0-(Draws!N16+Draws!Z16) -> 0 | O37: =N37-(Draws!O16+Draws!AA16) -> 0 | P37: =O37-(Draws!P16+Draws!AB16) -> 0 | Q37: =P37-(Draws!Q16+Draws!AC16) -> 0 | R37: =Q37-(Draws!R16+Draws!AD16) -> 0 | S37: =R37-(Draws!S16+Draws!AE16) -> 0 | T37: =S37-(Draws!T16+Draws!AF16) -> 0 | U37: =T37-(Draws!U16+Draws!AG16) -> 0 | V37: =U37-(Draws!V16+Draws!AH16) -> 0 | ... Y37: =X37-(Draws!Y16+Draws!AK16) -> 0 | Z37: =0-(MAX(Draws!N16-Line_cap,0)+MAX(Draws!Z16-Line_cap,0)) -> 0 | AA37: =Z37-(MAX(Draws!O16-Line_cap,0)+MAX(Draws!AA16-Line_cap,0)) -> 0 | AB37: =AA37-(MAX(Draws!P16-Line_cap,0)+MAX(Draws!AB16-Line_cap,0)) -> 0 | AC37: =AB37-(MAX(Draws!Q16-Line_cap,0)+MAX(Draws!AC16-Line_cap,0)) -> 0 | AD37: =AC37-(MAX(Draws!R16-Line_cap,0)+MAX(Draws!AD16-Line_cap,0)) -> 0 | AE37: =AD37-(MAX(Draws!S16-Line_cap,0)+MAX(Draws!AE16-Line_cap,0)) -> 0 | AF37: =AE37-(MAX(Draws!T16-Line_cap,0)+MAX(Draws!AF16-Line_cap,0)) -> 0 | AG37: =AF37-(MAX(Draws!U16-Line_cap,0)+MAX(Draws!AG16-Line_cap,0)) -> 0 | AH37: =AG37-(MAX(Draws!V16-Line_cap,0)+MAX(Draws!AH16-Line_cap,0)) -> 0 | ... AK37: =AJ37-(MAX(Draws!Y16-Line_cap,0)+MAX(Draws!AK16-Line_cap,0)) -> 0 | AL37: =SUMPRODUCT(MIN($B$22:$M$22+B37:M37+N37:Y37)) -> 430.22384 | AM37: =SUMPRODUCT(MIN($B$22:$M$22+B37:M37)) -> 430.22384 | AN37: =SUMPRODUCT(MIN($B$22:$M$22+N37:Y37)) -> 481.95038 | AO37: =SUMPRODUCT(MIN($B$22:$M$22+B37:M37+Z37:AK37)) -> 430.22384 | AP37: =SUMPRODUCT(MIN($B$23:$M$23+B37:M37+N37:Y37)) -> 475.34972 | AQ37: =SUMPRODUCT(MIN($B$23:$M$23+B37:M37+Z37:AK37)) -> 475.34972 | AR37: =IF(Y37<0,1,0) -> 0
... A2025: 2000 | B2025: =Shock_sd*Draws!B2004 -> -13.755441 | C2025: =Persist_a*B2025+Shock_sd*Draws!C2004 -> -42.356691 | D2025: =Persist_a*C2025+Shock_sd*Draws!D2004 -> 92.740733 | E2025: =Persist_a*D2025+Shock_sd*Draws!E2004 -> 49.254601 | F2025: =Persist_a*E2025+Shock_sd*Draws!F2004 -> 100.4326 | G2025: =Persist_a*F2025+Shock_sd*Draws!G2004 -> 20.610288 | H2025: =Persist_a*G2025+Shock_sd*Draws!H2004 -> 3.7490601 | I2025: =Persist_a*H2025+Shock_sd*Draws!I2004 -> -56.463938 | J2025: =Persist_a*I2025+Shock_sd*Draws!J2004 -> -57.199449 | ... M2025: =Persist_a*L2025+Shock_sd*Draws!M2004 -> 45.907522 | N2025: =0-(Draws!N2004+Draws!Z2004) -> 0 | O2025: =N2025-(Draws!O2004+Draws!AA2004) -> 0 | P2025: =O2025-(Draws!P2004+Draws!AB2004) -> 0 | Q2025: =P2025-(Draws!Q2004+Draws!AC2004) -> -81.358555 | R2025: =Q2025-(Draws!R2004+Draws!AD2004) -> -81.358555 | S2025: =R2025-(Draws!S2004+Draws!AE2004) -> -81.358555 | T2025: =S2025-(Draws!T2004+Draws!AF2004) -> -81.358555 | U2025: =T2025-(Draws!U2004+Draws!AG2004) -> -81.358555 | V2025: =U2025-(Draws!V2004+Draws!AH2004) -> -81.358555 | ... Y2025: =X2025-(Draws!Y2004+Draws!AK2004) -> -81.358555 | Z2025: =0-(MAX(Draws!N2004-Line_cap,0)+MAX(Draws!Z2004-Line_cap,0)) -> 0 | AA2025: =Z2025-(MAX(Draws!O2004-Line_cap,0)+MAX(Draws!AA2004-Line_cap,0)) -> 0 | AB2025: =AA2025-(MAX(Draws!P2004-Line_cap,0)+MAX(Draws!AB2004-Line_cap,0)) -> 0 | AC2025: =AB2025-(MAX(Draws!Q2004-Line_cap,0)+MAX(Draws!AC2004-Line_cap,0)) -> 0 | AD2025: =AC2025-(MAX(Draws!R2004-Line_cap,0)+MAX(Draws!AD2004-Line_cap,0)) -> 0 | AE2025: =AD2025-(MAX(Draws!S2004-Line_cap,0)+MAX(Draws!AE2004-Line_cap,0)) -> 0 | AF2025: =AE2025-(MAX(Draws!T2004-Line_cap,0)+MAX(Draws!AF2004-Line_cap,0)) -> 0 | AG2025: =AF2025-(MAX(Draws!U2004-Line_cap,0)+MAX(Draws!AG2004-Line_cap,0)) -> 0 | AH2025: =AG2025-(MAX(Draws!V2004-Line_cap,0)+MAX(Draws!AH2004-Line_cap,0)) -> 0 | ... AK2025: =AJ2025-(MAX(Draws!Y2004-Line_cap,0)+MAX(Draws!AK2004-Line_cap,0)) -> 0 | AL2025: =SUMPRODUCT(MIN($B$22:$M$22+B2025:M2025+N2025:Y2025)) -> 346.03156 | AM2025: =SUMPRODUCT(MIN($B$22:$M$22+B2025:M2025)) -> 427.39012 | AN2025: =SUMPRODUCT(MIN($B$22:$M$22+N2025:Y2025)) -> 400.59183 | AO2025: =SUMPRODUCT(MIN($B$22:$M$22+B2025:M2025+Z2025:AK2025)) -> 427.39012 | AP2025: =SUMPRODUCT(MIN($B$23:$M$23+B2025:M2025+N2025:Y2025)) -> 395.63156 | AQ2025: =SUMPRODUCT(MIN($B$23:$M$23+B2025:M2025+Z2025:AK2025)) -> 476.99012 | AR2025: =IF(Y2025<0,1,0) -> 1

Sheet Reference_Values
A1: Checkpoint | B1: Engine value | C1: Meaning (where in the book)
A2: Revenue: long-run variance | B2: 441.17647 | C2: Section 8.6: about 441
A3: Revenue: volatility budget | B3: 21.004201 | C3: Section 8.6: $21 million
A4: Revenue: inflation from persistence | B4: 1.4002801 | C4: Section 8.6: 1.40
A5: Revenue: long-run chance of the $45m shortfall (%) | B5: 1.6079507 | C5: Section 8.6: 1.6 percent a quarter
A6: Revenue: the same, persistence ignored (%) | B6: 0.1349898 | C6: Section 8.6: 0.13 percent
A7: Revenue after 1 quarter: mean | B7: 21 | C7: Figure 8.1: mean 21
A8: Revenue after 1 quarter: sd | B8: 15 | C8: Figure 8.1: sd 15
A9: Revenue after 2 quarters: mean | B9: 14.7 | C9: Figure 8.1: mean 15
A10: Revenue after 2 quarters: sd | B10: 18.309833 | C10: Figure 8.1: sd 18
A11: Revenue after 4 quarters: mean | B11: 7.203 | C11: Figure 8.1: mean 7
A12: Revenue after 4 quarters: sd | B12: 20.38979 | C12: Figure 8.1: sd 20
A13: Halved persistence: budget | B13: 16.012815 | C13: Online Appendix 8.B.4: $16.0 million
... A82: Bench: path 1's trough, standby line and phased build | B82: 472.99198 | C82: a spot check of one path, quarter by quarter

Sheet Checks
A1: Checkpoint | B1: Workbook formula value | C1: Engine value | D1: |diff| | E1: Tolerance | F1: Status
A2: Revenue: long-run variance | B2: =Fan!B4 -> 441.17647 | C2: =Reference_Values!B2 -> 441.17647 | D2: =ABS(B2-C2) -> 0 | E2: 1e-09 | F2: =IF(D2<=E2,"PASS","FAIL") -> PASS
A3: Revenue: volatility budget | B3: =Fan!B5 -> 21.004201 | C3: =Reference_Values!B3 -> 21.004201 | D3: =ABS(B3-C3) -> 0 | E3: 1e-09 | F3: =IF(D3<=E3,"PASS","FAIL") -> PASS
A4: Revenue: inflation from persistence | B4: =Fan!B6 -> 1.4002801 | C4: =Reference_Values!B4 -> 1.4002801 | D4: =ABS(B4-C4) -> 0 | E4: 1e-09 | F4: =IF(D4<=E4,"PASS","FAIL") -> PASS
A5: Revenue: long-run chance of the $45m shortfall (%) | B5: =100*Fan!B7 -> 1.6079507 | C5: =Reference_Values!B5 -> 1.6079507 | D5: =ABS(B5-C5) -> 0 | E5: 1e-06 | F5: =IF(D5<=E5,"PASS","FAIL") -> PASS
A6: Revenue: the same, persistence ignored (%) | B6: =100*Fan!B8 -> 0.1349898 | C6: =Reference_Values!B6 -> 0.1349898 | D6: =ABS(B6-C6) -> 9.9920072e-16 | E6: 1e-06 | F6: =IF(D6<=E6,"PASS","FAIL") -> PASS
A7: Revenue after 1 quarter: mean | B7: =Fan!B17 -> 21 | C7: =Reference_Values!B7 -> 21 | D7: =ABS(B7-C7) -> 0 | E7: 1e-09 | F7: =IF(D7<=E7,"PASS","FAIL") -> PASS
A8: Revenue after 1 quarter: sd | B8: =Fan!D17 -> 15 | C8: =Reference_Values!B8 -> 15 | D8: =ABS(B8-C8) -> 0 | E8: 1e-09 | F8: =IF(D8<=E8,"PASS","FAIL") -> PASS
A9: Revenue after 2 quarters: mean | B9: =Fan!B18 -> 14.7 | C9: =Reference_Values!B9 -> 14.7 | D9: =ABS(B9-C9) -> 0 | E9: 1e-09 | F9: =IF(D9<=E9,"PASS","FAIL") -> PASS
A10: Revenue after 2 quarters: sd | B10: =Fan!D18 -> 18.309833 | C10: =Reference_Values!B10 -> 18.309833 | D10: =ABS(B10-C10) -> 0 | E10: 1e-09 | F10: =IF(D10<=E10,"PASS","FAIL") -> PASS
A11: Revenue after 4 quarters: mean | B11: =Fan!B20 -> 7.203 | C11: =Reference_Values!B11 -> 7.203 | D11: =ABS(B11-C11) -> 0 | E11: 1e-09 | F11: =IF(D11<=E11,"PASS","FAIL") -> PASS
A12: Revenue after 4 quarters: sd | B12: =Fan!D20 -> 20.38979 | C12: =Reference_Values!B12 -> 20.38979 | D12: =ABS(B12-C12) -> 0 | E12: 1e-09 | F12: =IF(D12<=E12,"PASS","FAIL") -> PASS
A13: Halved persistence: budget | B13: =Fan!B10 -> 16.012815 | C13: =Reference_Values!B13 -> 16.012815 | D13: =ABS(B13-C13) -> 0 | E13: 1e-09 | F13: =IF(D13<=E13,"PASS","FAIL") -> PASS
A14: Halved persistence: shortfall chance (%) | B14: =100*Fan!B11 -> 0.24751585 | C14: =Reference_Values!B14 -> 0.24751585 | D14: =ABS(B14-C14) -> 2.3037128e-15 | E14: 1e-06 | F14: =IF(D14<=E14,"PASS","FAIL") -> PASS
A15: Two readings: sigma_11 | B15: =Fan!K24 -> 0.11605235 | C15: =Reference_Values!B15 -> 0.11605235 | D15: =ABS(B15-C15) -> 0 | E15: 1e-09 | F15: =IF(D15<=E15,"PASS","FAIL") -> PASS
A16: Two readings: sigma_12 | B16: =Fan!K23 -> 0.0036057692 | C16: =Reference_Values!B16 -> 0.0036057692 | D16: =ABS(B16-C16) -> 0 | E16: 1e-09 | F16: =IF(D16<=E16,"PASS","FAIL") -> PASS
A17: Two readings: sigma_22 | B17: =Fan!K22 -> 0.015625 | C17: =Reference_Values!B17 -> 0.015625 | D17: =ABS(B17-C17) -> 0 | E17: 1e-09 | F17: =IF(D17<=E17,"PASS","FAIL") -> PASS
A18: Two readings: long-run sd of the first | B18: =Fan!K25 -> 0.34066457 | C18: =Reference_Values!B18 -> 0.34066457 | D18: =ABS(B18-C18) -> 0 | E18: 1e-09 | F18: =IF(D18<=E18,"PASS","FAIL") -> PASS
A19: Two readings: iteration agrees with the closed form | B19: =Fan!K28 -> 3.2615577e-13 | C19: =Reference_Values!B19 -> 0 | D19: =ABS(B19-C19) -> 3.2615577e-13 | E19: 1e-09 | F19: =IF(D19<=E19,"PASS","FAIL") -> PASS
A20: Chain: P^2 on plan to on plan | B20: =Compose!B9 -> 0.84 | C20: =Reference_Values!B20 -> 0.84 | D20: =ABS(B20-C20) -> 0 | E20: 1e-09 | F20: =IF(D20<=E20,"PASS","FAIL") -> PASS
A21: Chain: P^2 off plan to on plan | B21: =Compose!B10 -> 0.48 | C21: =Reference_Values!B21 -> 0.48 | D21: =ABS(B21-C21) -> 0 | E21: 1e-09 | F21: =IF(D21<=E21,"PASS","FAIL") -> PASS
A22: Chain: off plan three quarters after on plan | B22: =Compose!B21 -> 0.196 | C22: =Reference_Values!B22 -> 0.196 | D22: =ABS(B22-C22) -> 0 | E22: 1e-09 | F22: =IF(D22<=E22,"PASS","FAIL") -> PASS
A23: Chain: P^3 off plan to on plan | B23: =Compose!B14 -> 0.588 | C23: =Reference_Values!B23 -> 0.588 | D23: =ABS(B23-C23) -> 0 | E23: 1e-09 | F23: =IF(D23<=E23,"PASS","FAIL") -> PASS
A24: Chain: P^2 P and P P^2 agree | B24: =Compose!B20 -> 0 | C24: =Reference_Values!B24 -> 0 | D24: =ABS(B24-C24) -> 0 | E24: 1e-12 | F24: =IF(D24<=E24,"PASS","FAIL") -> PASS
A25: Chain: long-run share on plan | B25: =Compose!B24 -> 0.75 | C25: =Reference_Values!B25 -> 0.75 | D25: =ABS(B25-C25) -> 0 | E25: 1e-09 | F25: =IF(D25<=E25,"PASS","FAIL") -> PASS
A26: Chain: average off-plan spell | B26: =Compose!B26 -> 3.3333333 | C26: =Reference_Values!B26 -> 3.3333333 | D26: =ABS(B26-C26) -> 0 | E26: 1e-09 | F26: =IF(D26<=E26,"PASS","FAIL") -> PASS
A27: Revenue fans: compounded equals direct | B27: =Compose!G12 -> 0 | C27: =Reference_Values!B27 -> 0 | D27: =ABS(B27-C27) -> 0 | E27: 1e-09 | F27: =IF(D27<=E27,"PASS","FAIL") -> PASS
A28: Regulatory: E[J^2] | B28: =Events!B4 -> 2500 | C28: =Reference_Values!B28 -> 2500 | D28: =ABS(B28-C28) -> 0 | E28: 1e-09 | F28: =IF(D28<=E28,"PASS","FAIL") -> PASS
A29: Regulatory: plan line | B29: =Events!B5 -> 6 | C29: =Reference_Values!B29 -> 6 | D29: =ABS(B29-C29) -> 0 | E29: 1e-09 | F29: =IF(D29<=E29,"PASS","FAIL") -> PASS
A30: Regulatory: risk line | B30: =Events!B6 -> 375 | C30: =Reference_Values!B30 -> 375 | D30: =ABS(B30-C30) -> 0 | E30: 1e-09 | F30: =IF(D30<=E30,"PASS","FAIL") -> PASS
A31: Regulatory: sd over one year | B31: =Events!B7 -> 19.364917 | C31: =Reference_Values!B31 -> 19.364917 | D31: =ABS(B31-C31) -> 0 | E31: 1e-09 | F31: =IF(D31<=E31,"PASS","FAIL") -> PASS
A32: Regulatory: sd over five years | B32: =Events!B8 -> 43.30127 | C32: =Reference_Values!B32 -> 43.30127 | D32: =ABS(B32-C32) -> 0 | E32: 1e-09 | F32: =IF(D32<=E32,"PASS","FAIL") -> PASS
A33: Regulatory: mean wait (years) | B33: =Events!B9 -> 6.6666667 | C33: =Reference_Values!B33 -> 6.6666667 | D33: =ABS(B33-C33) -> 0 | E33: 1e-09 | F33: =IF(D33<=E33,"PASS","FAIL") -> PASS
A34: Regulatory: next year's chance (%) | B34: =100*Events!B10 -> 13.929202 | C34: =Reference_Values!B34 -> 13.929202 | D34: =ABS(B34-C34) -> 0 | E34: 1e-06 | F34: =IF(D34<=E34,"PASS","FAIL") -> PASS
A35: Regulatory: next year's chance after five quiet years (%) | B35: =100*Events!B11 -> 13.929202 | C35: =Reference_Values!B35 -> 13.929202 | D35: =ABS(B35-C35) -> 0 | E35: 1e-06 | F35: =IF(D35<=E35,"PASS","FAIL") -> PASS
A36: Half the frequency, twice the size: variance | B36: =Events!B14 -> 750 | C36: =Reference_Values!B36 -> 750 | D36: =ABS(B36-C36) -> 0 | E36: 1e-09 | F36: =IF(D36<=E36,"PASS","FAIL") -> PASS
A37: Start-up: mean factor after one year | B37: =Averages!B17 -> 2.4596031 | C37: =Reference_Values!B37 -> 2.4596031 | D37: =ABS(B37-C37) -> 0 | E37: 1e-09 | F37: =IF(D37<=E37,"PASS","FAIL") -> PASS
A38: Start-up: mean factor after two years | B38: =Averages!B18 -> 6.0496475 | C38: =Reference_Values!B38 -> 6.0496475 | D38: =ABS(B38-C38) -> 0 | E38: 1e-09 | F38: =IF(D38<=E38,"PASS","FAIL") -> PASS
A39: Start-up: median factor after one year | B39: =Averages!C17 -> 2.0544332 | C39: =Reference_Values!B39 -> 2.0544332 | D39: =ABS(B39-C39) -> 0 | E39: 1e-09 | F39: =IF(D39<=E39,"PASS","FAIL") -> PASS
A40: Start-up: median factor after two years | B40: =Averages!C18 -> 4.2206958 | C40: =Reference_Values!B40 -> 4.2206958 | D40: =ABS(B40-C40) -> 0 | E40: 1e-09 | F40: =IF(D40<=E40,"PASS","FAIL") -> PASS
A41: Start-up: paths below the mean after one year (%) | B41: =100*Averages!E17 -> 61.791142 | C41: =Reference_Values!B41 -> 61.791142 | D41: =ABS(B41-C41) -> 0 | E41: 1e-06 | F41: =IF(D41<=E41,"PASS","FAIL") -> PASS
A42: Start-up: paths below the mean after two years (%) | B42: =100*Averages!E18 -> 66.431338 | C42: =Reference_Values!B42 -> 66.431338 | D42: =ABS(B42-C42) -> 0 | E42: 1e-06 | F42: =IF(D42<=E42,"PASS","FAIL") -> PASS
A43: Unit A's expected total in year 5 | B43: =Averages!D9 -> 392.05723 | C43: =Reference_Values!B43 -> 392.05723 | D43: =ABS(B43-C43) -> 0 | E43: 1e-09 | F43: =IF(D43<=E43,"PASS","FAIL") -> PASS
A44: Three expansive steps: spread factor | B44: =Averages!D36 -> 2.985984 | C44: =Reference_Values!B44 -> 2.985984 | D44: =ABS(B44-C44) -> 0 | E44: 1e-09 | F44: =IF(D44<=E44,"PASS","FAIL") -> PASS
A45: Three consolidating steps: spread factor | B45: =Averages!D37 -> 0.262144 | C45: =Reference_Values!B45 -> 0.262144 | D45: =ABS(B45-C45) -> 0 | E45: 1e-09 | F45: =IF(D45<=E45,"PASS","FAIL") -> PASS
A46: Plan: liquidity today | B46: =Plan!D5 -> 620 | C46: =Reference_Values!B46 -> 620 | D46: =ABS(B46-C46) -> 0 | E46: 1e-09 | F46: =IF(D46<=E46,"PASS","FAIL") -> PASS
A47: Plan: trough | B47: =Plan!B20 -> 481.95038 | C47: =Reference_Values!B47 -> 481.95038 | D47: =ABS(B47-C47) -> 0 | E47: 1e-09 | F47: =IF(D47<=E47,"PASS","FAIL") -> PASS
A48: Plan: quarter of the trough | B48: =Plan!B21 -> 7 | C48: =Reference_Values!B48 -> 7 | D48: =ABS(B48-C48) -> 0 | E48: 0 | F48: =IF(D48<=E48,"PASS","FAIL") -> PASS
A49: Plan: end of year 3 | B49: =Plan!B22 -> 510.42405 | C49: =Reference_Values!B49 -> 510.42405 | D49: =ABS(B49-C49) -> 0 | E49: 1e-09 | F49: =IF(D49<=E49,"PASS","FAIL") -> PASS
A50: Plan: headroom above the floor | B50: =Plan!B23 -> 131.95038 | C50: =Reference_Values!B50 -> 131.95038 | D50: =ABS(B50-C50) -> 0 | E50: 1e-09 | F50: =IF(D50<=E50,"PASS","FAIL") -> PASS
A51: Deviation: volatility budget | B51: =Plan!B24 -> 62.5 | C51: =Reference_Values!B51 -> 62.5 | D51: =ABS(B51-C51) -> 0 | E51: 1e-09 | F51: =IF(D51<=E51,"PASS","FAIL") -> PASS
A52: Deviation: headroom in standard deviations | B52: =Plan!B25 -> 2.1112061 | C52: =Reference_Values!B52 -> 2.1112061 | D52: =ABS(B52-C52) -> 0 | E52: 1e-09 | F52: =IF(D52<=E52,"PASS","FAIL") -> PASS
A53: Closures: plan line | B53: =Plan!B27 -> 12 | C53: =Reference_Values!B53 -> 12 | D53: =ABS(B53-C53) -> 0 | E53: 1e-09 | F53: =IF(D53<=E53,"PASS","FAIL") -> PASS
A54: Closures: at least one in three years (%) | B54: =100*Plan!B29 -> 25.918178 | C54: =Reference_Values!B54 -> 25.918178 | D54: =ABS(B54-C54) -> 0 | E54: 1e-06 | F54: =IF(D54<=E54,"PASS","FAIL") -> PASS
A55: Breach probability: its standard error (points) | B55: =100*Odds!D5 -> 0.13623352 | C55: =Reference_Values!B55 -> 0.13623352 | D55: =ABS(B55-C55) -> 0 | E55: 1e-06 | F55: =IF(D55<=E55,"PASS","FAIL") -> PASS
A56: Mean path's trough, exact | B56: =Plan!B31 -> 459.85405 | C56: =Reference_Values!B56 -> 459.85405 | D56: =ABS(B56-C56) -> 0 | E56: 1e-09 | F56: =IF(D56<=E56,"PASS","FAIL") -> PASS
A57: Total probability | B57: =Odds!B28 -> 0.24622 | C57: =Reference_Values!B57 -> 0.24622 | D57: =ABS(B57-C57) -> 0 | E57: 1e-09 | F57: =IF(D57<=E57,"PASS","FAIL") -> PASS
A58: Breach-indicator variance | B58: =Odds!B30 -> 0.18559571 | C58: =Reference_Values!B58 -> 0.18559571 | D58: =ABS(B58-C58) -> 0 | E58: 1e-09 | F58: =IF(D58<=E58,"PASS","FAIL") -> PASS
A59: Variance within the scenarios | B59: =Odds!B31 -> 0.11068729 | C59: =Reference_Values!B59 -> 0.11068729 | D59: =ABS(B59-C59) -> 0 | E59: 1e-09 | F59: =IF(D59<=E59,"PASS","FAIL") -> PASS
A60: Variance between the scenarios | B60: =Odds!B32 -> 0.074908417 | C60: =Reference_Values!B60 -> 0.074908417 | D60: =ABS(B60-C60) -> 0 | E60: 1e-09 | F60: =IF(D60<=E60,"PASS","FAIL") -> PASS
A61: Share that is whether a window closes (%) | B61: =100*Odds!B33 -> 40.361071 | C61: =Reference_Values!B61 -> 40.361071 | D61: =ABS(B61-C61) -> 0 | E61: 1e-06 | F61: =IF(D61<=E61,"PASS","FAIL") -> PASS
A62: Breaches on paths with a closure (%) | B62: =100*Odds!B29 -> 74.616197 | C62: =Reference_Values!B62 -> 74.616197 | D62: =ABS(B62-C62) -> 0 | E62: 1e-06 | F62: =IF(D62<=E62,"PASS","FAIL") -> PASS
A63: Phased build: plan trough | B63: =Plan!B33 -> 530.97392 | C63: =Reference_Values!B63 -> 530.97392 | D63: =ABS(B63-C63) -> 0 | E63: 1e-09 | F63: =IF(D63<=E63,"PASS","FAIL") -> PASS
A64: Phased build: deepest draw smaller by | B64: =Plan!B36 -> 49.023535 | C64: =Reference_Values!B64 -> 49.023535 | D64: =ABS(B64-C64) -> 0 | E64: 1e-09 | F64: =IF(D64<=E64,"PASS","FAIL") -> PASS
A65: Table 8.5: smallest standard error (points) | B65: =100*Odds!B12 -> 0.053970547 | C65: =Reference_Values!B65 -> 0.053970547 | D65: =ABS(B65-C65) -> 0 | E65: 1e-06 | F65: =IF(D65<=E65,"PASS","FAIL") -> PASS
A66: 100 paths: standard error (points) | B66: =100*ErrorBars!D5 -> 4.330127 | C66: =Reference_Values!B66 -> 4.330127 | D66: =ABS(B66-C66) -> 0 | E66: 1e-06 | F66: =IF(D66<=E66,"PASS","FAIL") -> PASS
A67: 1,000 paths: standard error (points) | B67: =100*ErrorBars!D6 -> 1.3729385 | C67: =Reference_Values!B67 -> 1.3729385 | D67: =ABS(B67-C67) -> 0 | E67: 1e-06 | F67: =IF(D67<=E67,"PASS","FAIL") -> PASS
A68: 10,000 paths: standard error (points) | B68: =100*ErrorBars!D7 -> 0.43002789 | C68: =Reference_Values!B68 -> 0.43002789 | D68: =ABS(B68-C68) -> 0 | E68: 1e-06 | F68: =IF(D68<=E68,"PASS","FAIL") -> PASS
A69: Paths for ±0.1 point near 5% | B69: =ErrorBars!B12 -> 47500 | C69: =Reference_Values!B69 -> 47500 | D69: =ABS(B69-C69) -> 0 | E69: 1e-06 | F69: =IF(D69<=E69,"PASS","FAIL") -> PASS
A70: Paths for ±0.1 point near 25% | B70: =ErrorBars!B13 -> 187500 | C70: =Reference_Values!B70 -> 187500 | D70: =ABS(B70-C70) -> 0 | E70: 1e-06 | F70: =IF(D70<=E70,"PASS","FAIL") -> PASS
A71: Bench: breaches, plan as drawn, both channels | B71: =Bench!B5 -> 521 | C71: =Reference_Values!B71 -> 521 | D71: =ABS(B71-C71) -> 0 | E71: 0 | F71: =IF(D71<=E71,"PASS","FAIL") -> PASS
A72: Bench: breaches, execution and market deviation only | B72: =Bench!B6 -> 180 | C72: =Reference_Values!B72 -> 180 | D72: =ABS(B72-C72) -> 0 | E72: 0 | F72: =IF(D72<=E72,"PASS","FAIL") -> PASS
A73: Bench: breaches, funding-window events only | B73: =Bench!B7 -> 232 | C73: =Reference_Values!B73 -> 232 | D73: =ABS(B73-C73) -> 0 | E73: 0 | F73: =IF(D73<=E73,"PASS","FAIL") -> PASS
A74: Bench: breaches, standby line | B74: =Bench!B8 -> 267 | C74: =Reference_Values!B74 -> 267 | D74: =ABS(B74-C74) -> 0 | E74: 0 | F74: =IF(D74<=E74,"PASS","FAIL") -> PASS
A75: Bench: breaches, phased build | B75: =Bench!B9 -> 268 | C75: =Reference_Values!B75 -> 268 | D75: =ABS(B75-C75) -> 0 | E75: 0 | F75: =IF(D75<=E75,"PASS","FAIL") -> PASS
A76: Bench: breaches, standby line and phased build | B76: =Bench!B10 -> 61 | C76: =Reference_Values!B76 -> 61 | D76: =ABS(B76-C76) -> 0 | E76: 0 | F76: =IF(D76<=E76,"PASS","FAIL") -> PASS
A77: Bench: paths with a closure | B77: =Bench!B12 -> 529 | C77: =Reference_Values!B77 -> 529 | D77: =ABS(B77-C77) -> 0 | E77: 0 | F77: =IF(D77<=E77,"PASS","FAIL") -> PASS
A78: Bench: breaches on paths with a closure | B78: =Bench!B13 -> 380 | C78: =Reference_Values!B78 -> 380 | D78: =ABS(B78-C78) -> 0 | E78: 0 | F78: =IF(D78<=E78,"PASS","FAIL") -> PASS
A79: Bench: breaches among the first 100 paths | B79: =Bench!B16 -> 26 | C79: =Reference_Values!B79 -> 26 | D79: =ABS(B79-C79) -> 0 | E79: 0 | F79: =IF(D79<=E79,"PASS","FAIL") -> PASS
A80: Bench: breaches among the first 1,000 paths | B80: =Bench!B19 -> 261 | C80: =Reference_Values!B80 -> 261 | D80: =ABS(B80-C80) -> 0 | E80: 0 | F80: =IF(D80<=E80,"PASS","FAIL") -> PASS
A81: Bench: path 1's trough, plan as drawn, both channels | B81: =Bench!AL26 -> 363.38148 | C81: =Reference_Values!B81 -> 363.38148 | D81: =ABS(B81-C81) -> 0 | E81: 1e-06 | F81: =IF(D81<=E81,"PASS","FAIL") -> PASS
A82: Bench: path 1's trough, standby line and phased build | B82: =Bench!AQ26 -> 472.99198 | C82: =Reference_Values!B82 -> 472.99198 | D82: =ABS(B82-C82) -> 0 | E82: 1e-06 | F82: =IF(D82<=E82,"PASS","FAIL") -> PASS
A84: All checkpoints | F84: =IF(COUNTIF(F2:F82,"PASS")=81,"ALL PASS","CHECK") -> ALL PASS
