Workbook

Sheet README
B1: DCT Laboratory — Vol I, Ch 16: Synthesis, Future Directions, and Transition to Volume II
B2: Seed 26116 · Companion to DCT_V1_Ch16_Lab.ipynb and AXIOM Lab 1.16 (module AXIOM-16). Money in $ million.
B4: Worked Example 16.1, Is Meridian Ready to Optimize?, with the book's declarations, and the five steps of AXIOM Lab 1.16, Certifying Meridian for Volume II.
B5: Declarations: the digital program, its uncertainty, the levers' prices, the commitments, the readings' errors and the register.
B6: Framework: Table 16.1's evidence for the five limitations, and Theorem 16.2's instance (lab step 1).
B7: Scorecard: Chapter 1's model at year 5 and the CFO's scorecard on two scales, the gap (R1) leaves to the board.
B8: Quantiles: the one simulation output, from the book's 100,000 paths (seed 8): each line's critical depth at four appetites; the least delay and cost of every package, the 5 percent package and its price.
B9: R1_Inventory, R2_Consistency, R3_Panel, R4_Horizon: the four gates (Steps 1-4; lab step 2).
B10: DigitalTwin: the gain audit flags a drift (the scenario is this workbook's declaration, seed 26116) and Online Appendix 16.B.2's models within the ceilings (lab step 3).
B11: Certificate: Table 16.4, the grades, the work orders, and Appendix 16.A's runway (Step 5).
B12: Dependencies and Citations: Volume I's citation graph, Figure 16.2, the longest chains and what Theorem 16.4 rests on (lab step 4). Export: the certified instance in Volume II's canonical form (lab step 5).
B13: Reference_Values and Checks: the notebook engine's numbers and a PASS/FAIL comparison with this workbook's formulas.
... B19: Cross-sheet link: green.

Sheet Declarations
A1: Declarations (Worked Example 16.1; Worked Examples 8.1 and 15.1; Tables 5.2, 5.4 and 15.2). Money in $ million.
A3: Quantity | B3: Value | C3: Source | D3: Name
A4: Liquidity today | B4: 620 | C4: Table 5.4; Worked Example 8.1 | D4: Liq0
A5: The board's liquidity floor | B5: 350 | C5: Table 5.4 | D5: Floor_m
A6: Cash above the floor | B6: =B4-B5 -> 270 | C6: Chapter 13's joint check: 270 | D6: Pool
A7: Liquidity per index point | B7: 6.2 | C7: Chapter 1: index 100 = $620 million | D7: Usd_pt
A8: Chapter 1's liquidity target (index) | B8: 112 | C8: Online Appendix 1.B.4 | D8: Liq_target
A9: Relaxation toward the target, a year | B9: 0.35 | C9: Online Appendix 1.B.4 | D9: Relax
A10: Depth of the program's draw, as planned (index points) | B10: 28 | C10: Chapter 1's digital program | D10: Depth0
A11: Years to the deepest draw | B11: 2 | C11: Chapter 1's digital program | D11: Tau
A12: Depth cut by a quarter of delay (index points) | B12: 4 | C12: Chapter 8's phased build: depth 20 for two quarters of delay | D12: Depth_per_q
A13: Standby-line fees a year (share of the line) | B13: 0.01 | C13: Worked Example 15.1 | D13: Fee_year
A14: Program length (years) | B14: 3 | C14: Twelve quarters | D14: Years
A15: Fees over the program (share of the line) | B15: =B13*B14 -> 0.03 | C15: $3 million per $100 million | D15: Fee
A16: Value of a quarter of delay | B16: 8 | C16: The transformation office | D16: Vq
A17: The board's appetite: chance of a breach in some quarter | B17: 0.05 | C17: Chapter 8 | D17: Appetite
A18: Revenue | B18: 4200 | C18: Chapter 1 | D18: Revenue
A19: EBITDA margin | B19: 0.118 | C19: Chapter 1 | D19: Margin
A20: EBITDA | B20: =B18*B19 -> 495.6 | C20: $495.6 million | D20: Ebitda
A21: Net leverage today (net debt / EBITDA) | B21: 3.4 | C21: Table 5.4 | D21: Lev0
A22: Net debt | B22: =B21*B20 -> 1685.04 | C22: $1,685 million | D22: Net_debt
A23: Covenant: net leverage at most | B23: 4.5 | C23: Table 5.4; the CFO | D23: Covenant
A24: Workforce capability today | B24: 58 | C24: Table 5.2 | D24: Capability
A25: Capability floor for the digital build | B25: 55 | C25: HR and the CTO (Table 15.2) | D25: Cap_floor
A26: Strategic-risk ceiling | B26: 75 | C26: Table 5.4; the CRO and the board | D26: Risk_ceil
A27: Error of the leverage reading (share of the reading) | B27: 0.02 | C27: Table 5.2: audited accounts | D27: Band_lev
A28: Error of the capability reading (points) | B28: 5 | C28: Table 5.2: skills survey | D28: Band_cap
A29: Error of the strategic-risk reading (points) | B29: 6 | C29: Table 5.2: risk committee | D29: Band_risk
A30: Persistence of the execution and market deviation | B30: 0.6 | C30: Worked Example 8.1 | D30: A_e
A31: Surprise a quarter: standard deviation | B31: 50 | C31: Worked Example 8.1 | D31: Sd_w
A32: Funding-window closures a year | B32: 0.1 | C32: Worked Example 8.1 | D32: Lam
A33: Closure size: mean | B33: 120 | C33: Worked Example 8.1 | D33: J_mean
A34: Closure size: standard deviation | B34: 50 | C34: Worked Example 8.1 | D34: J_sd
A35: Gamma shape of a closure | B35: =(B33/B34)^2 -> 5.76 | C35: 5.76 | D35: G_shape
A36: Gamma scale of a closure | B36: =B34^2/B33 -> 20.833333 | C36: 20.83 | D36: G_scale
A37: Paths | B37: 100000 | C37: Worked Example 8.1 | D37: N_paths
A38: Random seed of the book's paths | B38: 8 | C38: Volume II, Online Appendix 1.B.4 | D38: Book_seed
A39: Chapter 8's package: line | B39: 100 | C39: Worked Example 8.1 | D39: Line8
A40: Chapter 8's package: delay (quarters) | B40: 2 | C40: the phased build | D40: Delay8
A41: Coupling register: ceiling of each core link | B41: 0.4 | C41: Chapter 14; the risk office | D41: Ceil_gain
A42: The board's rule: spectral radius at most 2^(-1/4) | B42: =2^(-1/4) -> 0.84089642 | C42: any deviation halves within a year | D42: Rule_rho
A43: Quarters in the program | B43: 12 | C43: the horizon | D43: Quarters
A45: Decisions: the standby line (the CFO's) and the delay in quarters (the transformation office's). Objective: minimize Fee x line + Vq x delay. Commitments: the appetite (board), the covenant (CFO), the capability floor (HR, CTO), the strategic-risk ceiling (CRO, board), the register (risk office).

Sheet Framework
A1: Walk the framework: Table 16.1's evidence, and Theorem 16.2's instance (AXIOM Lab 1.16, step 1; Sections 16.1-16.2)
A3: Limitation removed (Table 16.1) | B3: Meridian's evidence | C3: Reading
A4: L1 Fragmentation: the program's deepest draw | B4: =R2_Consistency!B19 -> 138.04962 | C4: $138 million
A5: L1 Fragmentation: the treasury's buffer | B5: =R2_Consistency!B20 -> 186.86698 | C5: $187 million, both on the $270 million
A6: L2 Snapshots: the average path's lowest point | B6: =R2_Consistency!B24 -> 459.85405 | C6: never breaches the floor
A7: L2 Snapshots: paths that breach the floor (engine, seed 8) | B7: 0.24622 | C7: 24.6 percent
A8: L3 One-number summaries: weight points that tie the leaders | B8: =Scorecard!B43 -> 1.5924031 | C8: 1.6 weight points; the scale flips the ranking
A9: L4 No state: a shock in the core halves in (quarters) | B9: =R3_Panel!B9 -> 3.1062837 | C9: 3.1 quarters
A10: L4 No state: one more link, spectral radius | B10: =R3_Panel!B26 -> 1.0246211 | C10: above 1: a shock would grow
A11: L5 No well-posed problem: the 5% appetite met for | B11: =Quantiles!B95 -> 10.440611 | C11: $10.4 million
A12: L5 No well-posed problem: a breach priced at | B12: =Quantiles!B102 -> 180.70148 | C12: about $180 million
A15: Theorem 16.2's instance (Worked Example 4.1) | B15: Legacy | C15: Software | D15: Total | E15: A year: legacy keeps 0.92 (5% leave, 3% retrain); software keeps 0.96 and gains 0.03 of legacy.
A16: Legacy kept a year | B16: 0.92
A17: Retrained into software a year | B17: 0.03
A18: Software kept a year | B18: 0.96
A20: Year | B20: Unit A legacy | C20: Unit A software | D20: Unit A total | E20: Unit B legacy | F20: Unit B software | G20: Unit B total | H20: Totals model
A21: 0 | B21: 400 | C21: 100 | D21: =B21+C21 -> 500 | E21: 100 | F21: 400 | G21: =E21+F21 -> 500 | H21: =D21 -> 500
A22: 1 | B22: =$B$16*B21 -> 368 | C22: =$B$18*C21+$B$17*B21 -> 108 | D22: =B22+C22 -> 476 | E22: =$B$16*E21 -> 92 | F22: =$B$18*F21+$B$17*E21 -> 387 | G22: =E22+F22 -> 479 | H22: =H21*$D$22/$D$21 -> 476
A23: 2 | B23: =$B$16*B22 -> 338.56 | C23: =$B$18*C22+$B$17*B22 -> 114.72 | D23: =B23+C23 -> 453.28 | E23: =$B$16*E22 -> 84.64 | F23: =$B$18*F22+$B$17*E22 -> 374.28 | G23: =E23+F23 -> 458.92 | H23: =H22*$D$22/$D$21 -> 453.152
A24: 3 | B24: =$B$16*B23 -> 311.4752 | C24: =$B$18*C23+$B$17*B23 -> 120.288 | D24: =B24+C24 -> 431.7632 | E24: =$B$16*E23 -> 77.8688 | F24: =$B$18*F23+$B$17*E23 -> 361.848 | G24: =E24+F24 -> 439.7168 | H24: =H23*$D$22/$D$21 -> 431.4007
A25: 4 | B25: =$B$16*B24 -> 286.55718 | C25: =$B$18*C24+$B$17*B24 -> 124.82074 | D25: =B25+C25 -> 411.37792 | E25: =$B$16*E24 -> 71.639296 | F25: =$B$18*F24+$B$17*E24 -> 349.71014 | G25: =E25+F25 -> 421.34944 | H25: =H24*$D$22/$D$21 -> 410.69347
A26: 5 | B26: =$B$16*B25 -> 263.63261 | C26: =$B$18*C25+$B$17*B25 -> 128.42462 | D26: =B26+C26 -> 392.05723 | E26: =$B$16*E25 -> 65.908152 | F26: =$B$18*F25+$B$17*E25 -> 337.87092 | G26: =E26+F26 -> 403.77907 | H26: =H25*$D$22/$D$21 -> 390.98018
A28: Unit A in year 5 | B28: =D26 -> 392.05723 | C28: 392
A29: Unit B in year 5 | B29: =G26 -> 403.77907 | C29: 404
A30: Engineers apart | B30: =B29-B28 -> 11.721838 | C30: Section 16.2: 12
A31: The totals model (calibrated on unit A's first year), both units | B31: =H26 -> 390.98018 | C31: 391
A32: Any answer from the declared total errs for one unit by at least | B32: =B30/2 -> 5.860919 | C32: Theorem 16.2(ii)

Sheet Scorecard
A1: The CFO's scorecard on two scales: the gap (R1) left for the board (Worked Example 16.1, Step 1; Chapter 11; Table 16.1, L3)
A2: Chapter 1's model (Online Appendix 1.B.4): value(t) = target + (today - target) e^(-rate t) + hump (t/peak) e^(1 - t/peak) + the jump at the sale (year 1). Readings: liquidity index L, technology T, efficiency E, strategic risk R (lower is better).
A4: Option | B4: Reading | C4: Today | D4: Target | E4: Rate a year | F4: Hump (signed) | G4: Hump peak (years) | H4: Jump at year 1 | I4: Value at the year | K4: Reading year | L4: 5
A5: Digital | B5: L | C5: 100 | D5: 112 | E5: 0.35 | F5: -28 | G5: 2 | H5: 0 | I5: =D5+(C5-D5)*EXP(-E5*$L$4)+IF(G5="",0,F5*($L$4/G5)*EXP(1-$L$4/G5))+H5*($L$4>=1) -> 94.295601
A6: Digital | B6: T | C6: 41 | D6: 78 | E6: 0.55 | F6: 0 | H6: 0 | I6: =D6+(C6-D6)*EXP(-E6*$L$4)+IF(G6="",0,F6*($L$4/G6)*EXP(1-$L$4/G6))+H6*($L$4>=1) -> 75.634669
A7: Digital | B7: E | C7: 71 | D7: 77 | E7: 0.5 | F7: -9 | G7: 1.5 | H7: 0 | I7: =D7+(C7-D7)*EXP(-E7*$L$4)+IF(G7="",0,F7*($L$4/G7)*EXP(1-$L$4/G7))+H7*($L$4>=1) -> 73.598331
A8: Digital | B8: R | C8: 64 | D8: 51 | E8: 0.4 | F8: 14 | G8: 1.2 | H8: 0 | I8: =D8+(C8-D8)*EXP(-E8*$L$4)+IF(G8="",0,F8*($L$4/G8)*EXP(1-$L$4/G8))+H8*($L$4>=1) -> 55.21775
A9: Restructuring | B9: L | C9: 100 | D9: 104 | E9: 0.3 | F9: 0 | H9: 18 | I9: =D9+(C9-D9)*EXP(-E9*$L$4)+IF(G9="",0,F9*($L$4/G9)*EXP(1-$L$4/G9))+H9*($L$4>=1) -> 121.10748
A10: Restructuring | B10: T | C10: 41 | D10: 38 | E10: 0.25 | F10: 0 | H10: 0 | I10: =D10+(C10-D10)*EXP(-E10*$L$4)+IF(G10="",0,F10*($L$4/G10)*EXP(1-$L$4/G10))+H10*($L$4>=1) -> 38.859514
A11: Restructuring | B11: E | C11: 71 | D11: 74 | E11: 0.45 | F11: 0 | H11: 0 | I11: =D11+(C11-D11)*EXP(-E11*$L$4)+IF(G11="",0,F11*($L$4/G11)*EXP(1-$L$4/G11))+H11*($L$4>=1) -> 73.683802
A12: Restructuring | B12: R | C12: 64 | D12: 56 | E12: 0.35 | F12: 0 | H12: -8 | I12: =D12+(C12-D12)*EXP(-E12*$L$4)+IF(G12="",0,F12*($L$4/G12)*EXP(1-$L$4/G12))+H12*($L$4>=1) -> 49.390192
A13: Turnaround | B13: L | C13: 100 | D13: 106 | E13: 0.45 | F13: 0 | H13: 0 | I13: =D13+(C13-D13)*EXP(-E13*$L$4)+IF(G13="",0,F13*($L$4/G13)*EXP(1-$L$4/G13))+H13*($L$4>=1) -> 105.3676
A14: Turnaround | B14: T | C14: 41 | D14: 33 | E14: 0.2 | F14: 0 | H14: 0 | I14: =D14+(C14-D14)*EXP(-E14*$L$4)+IF(G14="",0,F14*($L$4/G14)*EXP(1-$L$4/G14))+H14*($L$4>=1) -> 35.943036
A15: Turnaround | B15: E | C15: 71 | D15: 79 | E15: 0.6 | F15: 0 | H15: 0 | I15: =D15+(C15-D15)*EXP(-E15*$L$4)+IF(G15="",0,F15*($L$4/G15)*EXP(1-$L$4/G15))+H15*($L$4>=1) -> 78.601703
A16: Turnaround | B16: R | C16: 64 | D16: 67 | E16: 0.3 | F16: 0 | H16: 0 | I16: =D16+(C16-D16)*EXP(-E16*$L$4)+IF(G16="",0,F16*($L$4/G16)*EXP(1-$L$4/G16))+H16*($L$4>=1) -> 66.33061
A19: Year-5 readings | B19: L | C19: T | D19: E | E19: R | F19: CFO score (L + T + E - R)/4
A20: Sign (risk: lower is better) | B20: 1 | C20: 1 | D20: 1 | E20: -1
A21: Today | B21: =C5 -> 100 | C21: =C6 -> 41 | D21: =C7 -> 71 | E21: =C8 -> 64
A22: Digital | B22: =I5 -> 94.295601 | C22: =I6 -> 75.634669 | D22: =I7 -> 73.598331 | E22: =I8 -> 55.21775 | F22: =SUMPRODUCT(B22:E22,$B$20:$E$20)/4 -> 47.077713
A23: Restructuring | B23: =I9 -> 121.10748 | C23: =I10 -> 38.859514 | D23: =I11 -> 73.683802 | E23: =I12 -> 49.390192 | F23: =SUMPRODUCT(B23:E23,$B$20:$E$20)/4 -> 46.065151
A24: Turnaround | B24: =I13 -> 105.3676 | C24: =I14 -> 35.943036 | D24: =I15 -> 78.601703 | E24: =I16 -> 66.33061 | F24: =SUMPRODUCT(B24:E24,$B$20:$E$20)/4 -> 38.395434
A26: Best-to-worst scale (best 100, worst 0) | B26: L | C26: T | D26: E | E26: R | F26: Equal weights | G26: Rank
A27: Digital | B27: =100*(B22*B$20-MIN(B22*B$20,B23*B$20,B24*B$20))/(MAX(B22*B$20,B23*B$20,B24*B$20)-MIN(B22*B$20,B23*B$20,B24*B$20)) -> 0 | C27: =100*(C22*C$20-MIN(C22*C$20,C23*C$20,C24*C$20))/(MAX(C22*C$20,C23*C$20,C24*C$20)-MIN(C22*C$20,C23*C$20,C24*C$20)) -> 100 | D27: =100*(D22*D$20-MIN(D22*D$20,D23*D$20,D24*D$20))/(MAX(D22*D$20,D23*D$20,D24*D$20)-MIN(D22*D$20,D23*D$20,D24*D$20)) -> 0 | E27: =100*(E22*E$20-MIN(E22*E$20,E23*E$20,E24*E$20))/(MAX(E22*E$20,E23*E$20,E24*E$20)-MIN(E22*E$20,E23*E$20,E24*E$20)) -> 65.59968 | F27: =AVERAGE(B27:E27) -> 41.39992 | G27: =RANK(F27,$F$27:$F$29) -> 2
A28: Restructuring | B28: =100*(B23*B$20-MIN(B22*B$20,B23*B$20,B24*B$20))/(MAX(B22*B$20,B23*B$20,B24*B$20)-MIN(B22*B$20,B23*B$20,B24*B$20)) -> 100 | C28: =100*(C23*C$20-MIN(C22*C$20,C23*C$20,C24*C$20))/(MAX(C22*C$20,C23*C$20,C24*C$20)-MIN(C22*C$20,C23*C$20,C24*C$20)) -> 7.3478428 | D28: =100*(D23*D$20-MIN(D22*D$20,D23*D$20,D24*D$20))/(MAX(D22*D$20,D23*D$20,D24*D$20)-MIN(D22*D$20,D23*D$20,D24*D$20)) -> 1.7082749 | E28: =100*(E23*E$20-MIN(E22*E$20,E23*E$20,E24*E$20))/(MAX(E22*E$20,E23*E$20,E24*E$20)-MIN(E22*E$20,E23*E$20,E24*E$20)) -> 100 | F28: =AVERAGE(B28:E28) -> 52.264029 | G28: =RANK(F28,$F$27:$F$29) -> 1
A29: Turnaround | B29: =100*(B24*B$20-MIN(B22*B$20,B23*B$20,B24*B$20))/(MAX(B22*B$20,B23*B$20,B24*B$20)-MIN(B22*B$20,B23*B$20,B24*B$20)) -> 41.295143 | C29: =100*(C24*C$20-MIN(C22*C$20,C23*C$20,C24*C$20))/(MAX(C22*C$20,C23*C$20,C24*C$20)-MIN(C22*C$20,C23*C$20,C24*C$20)) -> 0 | D29: =100*(D24*D$20-MIN(D22*D$20,D23*D$20,D24*D$20))/(MAX(D22*D$20,D23*D$20,D24*D$20)-MIN(D22*D$20,D23*D$20,D24*D$20)) -> 100 | E29: =100*(E24*E$20-MIN(E22*E$20,E23*E$20,E24*E$20))/(MAX(E22*E$20,E23*E$20,E24*E$20)-MIN(E22*E$20,E23*E$20,E24*E$20)) -> 0 | F29: =AVERAGE(B29:E29) -> 35.323786 | G29: =RANK(F29,$F$27:$F$29) -> 3
A31: Percentage improvement on today | B31: L | C31: T | D31: E | E31: R | F31: Equal weights | G31: Rank
A32: Digital | B32: =100*(B22-B$21)/B$21*B$20 -> -5.7043985 | C32: =100*(C22-C$21)/C$21*C$20 -> 84.474803 | D32: =100*(D22-D$21)/D$21*D$20 -> 3.6596211 | E32: =100*(E22-E$21)/E$21*E$20 -> 13.722266 | F32: =AVERAGE(B32:E32) -> 24.038073 | G32: =RANK(F32,$F$32:$F$34) -> 1
A33: Restructuring | B33: =100*(B23-B$21)/B$21*B$20 -> 21.107479 | C33: =100*(C23-C$21)/C$21*C$20 -> -5.2206966 | D33: =100*(D23-D$21)/D$21*D$20 -> 3.7800033 | E33: =100*(E23-E$21)/E$21*E$20 -> 22.827826 | F33: =AVERAGE(B33:E33) -> 10.623653 | G33: =RANK(F33,$F$32:$F$34) -> 2
A34: Turnaround | B34: =100*(B24-B$21)/B$21*B$20 -> 5.3676047 | C34: =100*(C24-C$21)/C$21*C$20 -> -12.33406 | D34: =100*(D24-D$21)/D$21*D$20 -> 10.706625 | E34: =100*(E24-E$21)/E$21*E$20 -> -3.6415774 | F34: =AVERAGE(B34:E34) -> 0.024648044 | G34: =RANK(F34,$F$32:$F$34) -> 3
A36: First on the best-to-worst scale | B36: =INDEX($A$27:$A$29,MATCH(1,$G$27:$G$29,0)) -> Restructuring | C36: restructuring leads digital 52.3 to 41.4
A37: First on percentage improvement | B37: =INDEX($A$32:$A$34,MATCH(1,$G$32:$G$34,0)) -> Digital | C37: digital leads 24.0 to 10.6: the scale decides the ranking
A39: Digital less restructuring, signed: L | B39: =(B22-B23)*B20 -> -26.811878
A40: Digital less restructuring, signed: T | B40: =(C22-C23)*C20 -> 36.775155
A41: Digital less restructuring, signed: E | B41: =(D22-D23)*D20 -> -0.085471354
A42: Digital less restructuring, signed: R | B42: =(E22-E23)*E20 -> -5.827558
A43: Weight points moved from technology to liquidity that tie the two leaders | B43: =100*AVERAGE(B39:B42)/(B40-B39) -> 1.5924031 | C43: Table 16.1, L3: 1.6 weight points

Sheet R1_Inventory
A1: Declaration completeness, gate (R1): the inventory and its two gaps (Worked Example 16.1, Step 1; AXIOM Lab 1.16, steps 1-2)
A3: Reading (Table 5.2) | B3: Measured by | C3: Error
A4: liquidity | B4: treasury systems | C4: +/-1%
A5: net leverage | B5: audited accounts | C5: +/-2%
A6: workforce capability | B6: skills survey | C6: +/-5 points
A7: technology platform | B7: architecture audit | C7: +/-4 points
A8: operational efficiency | B8: cost benchmarking | C8: +/-3 points
A9: ROIC | B9: audited accounts | C9: +/-0.4 pp
A10: strategic risk | B10: risk committee | C10: +/-6 points
A11: market share | B11: industry data | C11: +/-0.8 pp
A13: Arrow from (Chapter 9) | B13: To | C13: Type | D13: Two-way?
A14: MKT | B14: IND | C14: demand | D14: =IF(COUNTIFS($A$14:$A$27,B14,$B$14:$B$27,A14)>0,1,0) -> 0
A15: MKT | B15: DIG | C15: demand | D15: =IF(COUNTIFS($A$14:$A$27,B15,$B$14:$B$27,A15)>0,1,0) -> 0
A16: MKT | B16: MAT | C16: demand | D16: =IF(COUNTIFS($A$14:$A$27,B16,$B$14:$B$27,A16)>0,1,0) -> 0
A17: IND | B17: TRS | C17: cash | D17: =IF(COUNTIFS($A$14:$A$27,B17,$B$14:$B$27,A17)>0,1,0) -> 1
A18: DIG | B18: TRS | C18: cash | D18: =IF(COUNTIFS($A$14:$A$27,B18,$B$14:$B$27,A18)>0,1,0) -> 1
A19: MAT | B19: TRS | C19: cash | D19: =IF(COUNTIFS($A$14:$A$27,B19,$B$14:$B$27,A19)>0,1,0) -> 0
A20: TRS | B20: IND | C20: funding | D20: =IF(COUNTIFS($A$14:$A$27,B20,$B$14:$B$27,A20)>0,1,0) -> 1
A21: TRS | B21: DIG | C21: funding | D21: =IF(COUNTIFS($A$14:$A$27,B21,$B$14:$B$27,A21)>0,1,0) -> 1
A22: ENG | B22: IND | C22: capability | D22: =IF(COUNTIFS($A$14:$A$27,B22,$B$14:$B$27,A22)>0,1,0) -> 1
A23: IND | B23: ENG | C23: capability | D23: =IF(COUNTIFS($A$14:$A$27,B23,$B$14:$B$27,A23)>0,1,0) -> 1
A24: ENG | B24: DIG | C24: capability | D24: =IF(COUNTIFS($A$14:$A$27,B24,$B$14:$B$27,A24)>0,1,0) -> 1
A25: DIG | B25: ENG | C25: capability | D25: =IF(COUNTIFS($A$14:$A$27,B25,$B$14:$B$27,A25)>0,1,0) -> 1
... A27: GOV | B27: DIG | C27: policy | D27: =IF(COUNTIFS($A$14:$A$27,B27,$B$14:$B$27,A27)>0,1,0) -> 0
A29: Standing commitment (Tables 5.4 and 15.2) | B29: Owner
A30: covenant: net leverage at most 4.5x | B30: CFO
A31: liquidity floor: $350 million | B31: board
A32: strategic-risk ceiling: 75 | B32: CRO, board
A33: plant capacity in Industrial Systems | B33: COO
A34: capability at least 55 for the digital build | B34: HR, CTO
A36: Element of the GEOP (Worked Example 15.1) | B36: Declared as
A37: horizon | B37: the program's 12 quarters
A38: decisions | B38: the standby line (CFO); the delay in quarters (transformation office)
A39: policy class | B39: a package committed today (open loop)
A40: environment | B40: Chapter 8's laws: 100,000 paths, seed 8
A41: objective | B41: the levers' cost: fees priced by the CFO, delay by the transformation office
A42: commitments | B42: the appetite (board); the covenant (CFO); the capability floor (HR, CTO)
A45: State readings declared, each with its office and error | B45: =COUNTA(A4:A11) -> 8 | C45: eight
A46: Components | B46: =SUMPRODUCT(1/COUNTIF(A14:B27,A14:B27)) -> 7 | C46: seven
A47: Typed arrows | B47: =COUNTA(A14:A27) -> 14 | C47: fourteen
A48: Two-way links (the feedback core's) | B48: =SUM(D14:D27)/2 -> 4 | C48: four, at a ceiling of 0.40
A49: Standing commitments | B49: =COUNTA(A30:A34) -> 5 | C49: five
A50: Elements of the GEOP, each declared | B50: =COUNTA(B37:B42) -> 6 | C50: six
A52: Gap 1, the levers' prices: Chapter 8's package at the declared prices | B52: =Quantiles!B96 -> 19 | C52: $19.0 million
A53: its odds on the book's paths (engine) | B53: =Quantiles!B4 -> 0.03003 | C53: 3.0 percent
A54: the cheapest package at those odds | B54: =Quantiles!B97 -> 14.668098 | C54: $14.7 million
A55: choosing on safety alone cost | B55: =Quantiles!B98 -> 4.3319019 | C55: $4.33 million
A57: Gap 2, the scorecard's scale: first on the best-to-worst scale | B57: =Scorecard!B36 -> Restructuring | C57: restructuring 52.3, digital 41.4
A58: first on percentage improvement | B58: =Scorecard!B37 -> Digital | C58: digital 24.0, restructuring 10.6
A59: the scale decides the ranking? | B59: =IF(B57<>B58,"yes: the board must declare it","no") -> yes: the board must declare it | C59: Proposition 16.1(i)
A61: (R1) after Chapter 8 | B61: fails: lever prices and the scorecard's scale undeclared
A62: (R1) now: the levers' prices declared? | B62: =IF(AND(Fee>0,Vq>0),"pass","fail") -> pass | C62: the scale is the board's to declare before any optimizer ranks the options

Sheet Quantiles
A1: The decision table from the book's 100,000 paths (seed 8): the least delay and cost of every package (Worked Example 15.1; Worked Example 16.1, Steps 1, 2 and 4)
A2: Engine values (green): for a line l, a path stays above the floor exactly when the draw's depth is at most its critical depth; sorted over the paths, the value at the appetite's quantile is the deepest draw that meets it. Delay = (28 - that depth)/4, cost = Fee x line + Vq x delay: formulas. Blank: no delay can meet it.
A3: Quantile index (paths allowed to breach) | B3: 3003 | E3: The first appetite is the odds of Chapter 8's package on the book's paths (engine). | H3: 5000 | K3: 5500
A4: Appetite | B4: 0.03003 | E4: 0.045 | H4: 0.05 | K4: 0.055
A5: Line ($ million) | B5: Critical depth | C5: Delay | D5: Cost | E5: Critical depth | F5: Delay | G5: Cost | H5: Critical depth | I5: Delay | J5: Cost | K5: Critical depth | L5: Delay | M5: Cost
A6: 0 | B6: 1.5474426 | C6: =IF(B6<0,"",(Depth0-MIN(Depth0,B6))/Depth_per_q) -> 6.6131394 | D6: =IF(C6="","",Fee*$A6+Vq*C6) -> 52.905115 | E6: 6.3852114 | F6: =IF(E6<0,"",(Depth0-MIN(Depth0,E6))/Depth_per_q) -> 5.4036971 | G6: =IF(F6="","",Fee*$A6+Vq*F6) -> 43.229577 | H6: 7.6213073 | I6: =IF(H6<0,"",(Depth0-MIN(Depth0,H6))/Depth_per_q) -> 5.0946732 | J6: =IF(I6="","",Fee*$A6+Vq*I6) -> 40.757385 | K6: 8.8090794 | L6: =IF(K6<0,"",(Depth0-MIN(Depth0,K6))/Depth_per_q) -> 4.7977301 | M6: =IF(L6="","",Fee*$A6+Vq*L6) -> 38.381841
A7: 5 | B7: 2.6936105 | C7: =IF(B7<0,"",(Depth0-MIN(Depth0,B7))/Depth_per_q) -> 6.3265974 | D7: =IF(C7="","",Fee*$A7+Vq*C7) -> 50.762779 | E7: 7.426928 | F7: =IF(E7<0,"",(Depth0-MIN(Depth0,E7))/Depth_per_q) -> 5.143268 | G7: =IF(F7="","",Fee*$A7+Vq*F7) -> 41.296144 | H7: 8.677322 | I7: =IF(H7<0,"",(Depth0-MIN(Depth0,H7))/Depth_per_q) -> 4.8306695 | J7: =IF(I7="","",Fee*$A7+Vq*I7) -> 38.795356 | K7: 9.8233242 | L7: =IF(K7<0,"",(Depth0-MIN(Depth0,K7))/Depth_per_q) -> 4.5441689 | M7: =IF(L7="","",Fee*$A7+Vq*L7) -> 36.503352
A8: 10 | B8: 3.8281618 | C8: =IF(B8<0,"",(Depth0-MIN(Depth0,B8))/Depth_per_q) -> 6.0429595 | D8: =IF(C8="","",Fee*$A8+Vq*C8) -> 48.643676 | E8: 8.4910737 | F8: =IF(E8<0,"",(Depth0-MIN(Depth0,E8))/Depth_per_q) -> 4.8772316 | G8: =IF(F8="","",Fee*$A8+Vq*F8) -> 39.317853 | H8: 9.6807638 | I8: =IF(H8<0,"",(Depth0-MIN(Depth0,H8))/Depth_per_q) -> 4.579809 | J8: =IF(I8="","",Fee*$A8+Vq*I8) -> 36.938472 | K8: 10.813042 | L8: =IF(K8<0,"",(Depth0-MIN(Depth0,K8))/Depth_per_q) -> 4.2967395 | M8: =IF(L8="","",Fee*$A8+Vq*L8) -> 34.673916
A9: 15 | B9: 5.0043178 | C9: =IF(B9<0,"",(Depth0-MIN(Depth0,B9))/Depth_per_q) -> 5.7489205 | D9: =IF(C9="","",Fee*$A9+Vq*C9) -> 46.441364 | E9: 9.5089735 | F9: =IF(E9<0,"",(Depth0-MIN(Depth0,E9))/Depth_per_q) -> 4.6227566 | G9: =IF(F9="","",Fee*$A9+Vq*F9) -> 37.432053 | H9: 10.685397 | I9: =IF(H9<0,"",(Depth0-MIN(Depth0,H9))/Depth_per_q) -> 4.3286508 | J9: =IF(I9="","",Fee*$A9+Vq*I9) -> 35.079207 | K9: 11.76437 | L9: =IF(K9<0,"",(Depth0-MIN(Depth0,K9))/Depth_per_q) -> 4.0589074 | M9: =IF(L9="","",Fee*$A9+Vq*L9) -> 32.92126
A10: 20 | B10: 6.1116362 | C10: =IF(B10<0,"",(Depth0-MIN(Depth0,B10))/Depth_per_q) -> 5.472091 | D10: =IF(C10="","",Fee*$A10+Vq*C10) -> 44.376728 | E10: 10.541698 | F10: =IF(E10<0,"",(Depth0-MIN(Depth0,E10))/Depth_per_q) -> 4.3645754 | G10: =IF(F10="","",Fee*$A10+Vq*F10) -> 35.516603 | H10: 11.725286 | I10: =IF(H10<0,"",(Depth0-MIN(Depth0,H10))/Depth_per_q) -> 4.0686784 | J10: =IF(I10="","",Fee*$A10+Vq*I10) -> 33.149427 | K10: 12.752734 | L10: =IF(K10<0,"",(Depth0-MIN(Depth0,K10))/Depth_per_q) -> 3.8118166 | M10: =IF(L10="","",Fee*$A10+Vq*L10) -> 31.094533
A11: 25 | B11: 7.2806758 | C11: =IF(B11<0,"",(Depth0-MIN(Depth0,B11))/Depth_per_q) -> 5.179831 | D11: =IF(C11="","",Fee*$A11+Vq*C11) -> 42.188648 | E11: 11.546097 | F11: =IF(E11<0,"",(Depth0-MIN(Depth0,E11))/Depth_per_q) -> 4.1134758 | G11: =IF(F11="","",Fee*$A11+Vq*F11) -> 33.657807 | H11: 12.73204 | I11: =IF(H11<0,"",(Depth0-MIN(Depth0,H11))/Depth_per_q) -> 3.8169899 | J11: =IF(I11="","",Fee*$A11+Vq*I11) -> 31.28592 | K11: 13.714837 | L11: =IF(K11<0,"",(Depth0-MIN(Depth0,K11))/Depth_per_q) -> 3.5712909 | M11: =IF(L11="","",Fee*$A11+Vq*L11) -> 29.320327
A12: 30 | B12: 8.3768794 | C12: =IF(B12<0,"",(Depth0-MIN(Depth0,B12))/Depth_per_q) -> 4.9057801 | D12: =IF(C12="","",Fee*$A12+Vq*C12) -> 40.146241 | E12: 12.538499 | F12: =IF(E12<0,"",(Depth0-MIN(Depth0,E12))/Depth_per_q) -> 3.8653752 | G12: =IF(F12="","",Fee*$A12+Vq*F12) -> 31.823002 | H12: 13.684965 | I12: =IF(H12<0,"",(Depth0-MIN(Depth0,H12))/Depth_per_q) -> 3.5787587 | J12: =IF(I12="","",Fee*$A12+Vq*I12) -> 29.530069 | K12: 14.682351 | L12: =IF(K12<0,"",(Depth0-MIN(Depth0,K12))/Depth_per_q) -> 3.3294124 | M12: =IF(L12="","",Fee*$A12+Vq*L12) -> 27.535299
A13: 35 | B13: 9.5542854 | C13: =IF(B13<0,"",(Depth0-MIN(Depth0,B13))/Depth_per_q) -> 4.6114286 | D13: =IF(C13="","",Fee*$A13+Vq*C13) -> 37.941429 | E13: 13.534125 | F13: =IF(E13<0,"",(Depth0-MIN(Depth0,E13))/Depth_per_q) -> 3.6164689 | G13: =IF(F13="","",Fee*$A13+Vq*F13) -> 29.981751 | H13: 14.61185 | I13: =IF(H13<0,"",(Depth0-MIN(Depth0,H13))/Depth_per_q) -> 3.3470376 | J13: =IF(I13="","",Fee*$A13+Vq*I13) -> 27.826301 | K13: 15.598537 | L13: =IF(K13<0,"",(Depth0-MIN(Depth0,K13))/Depth_per_q) -> 3.1003658 | M13: =IF(L13="","",Fee*$A13+Vq*L13) -> 25.852927
A14: 40 | B14: 10.620755 | C14: =IF(B14<0,"",(Depth0-MIN(Depth0,B14))/Depth_per_q) -> 4.3448112 | D14: =IF(C14="","",Fee*$A14+Vq*C14) -> 35.958489 | E14: 14.459524 | F14: =IF(E14<0,"",(Depth0-MIN(Depth0,E14))/Depth_per_q) -> 3.385119 | G14: =IF(F14="","",Fee*$A14+Vq*F14) -> 28.280952 | H14: 15.573581 | I14: =IF(H14<0,"",(Depth0-MIN(Depth0,H14))/Depth_per_q) -> 3.1066048 | J14: =IF(I14="","",Fee*$A14+Vq*I14) -> 26.052838 | K14: 16.429356 | L14: =IF(K14<0,"",(Depth0-MIN(Depth0,K14))/Depth_per_q) -> 2.8926609 | M14: =IF(L14="","",Fee*$A14+Vq*L14) -> 24.341287
A15: 45 | B15: 11.625358 | C15: =IF(B15<0,"",(Depth0-MIN(Depth0,B15))/Depth_per_q) -> 4.0936604 | D15: =IF(C15="","",Fee*$A15+Vq*C15) -> 34.099283 | E15: 15.335646 | F15: =IF(E15<0,"",(Depth0-MIN(Depth0,E15))/Depth_per_q) -> 3.1660885 | G15: =IF(F15="","",Fee*$A15+Vq*F15) -> 26.678708 | H15: 16.389965 | I15: =IF(H15<0,"",(Depth0-MIN(Depth0,H15))/Depth_per_q) -> 2.9025087 | J15: =IF(I15="","",Fee*$A15+Vq*I15) -> 24.57007 | K15: 17.253341 | L15: =IF(K15<0,"",(Depth0-MIN(Depth0,K15))/Depth_per_q) -> 2.6866647 | M15: =IF(L15="","",Fee*$A15+Vq*L15) -> 22.843318
A16: 50 | B16: 12.665393 | C16: =IF(B16<0,"",(Depth0-MIN(Depth0,B16))/Depth_per_q) -> 3.8336516 | D16: =IF(C16="","",Fee*$A16+Vq*C16) -> 32.169213 | E16: 16.222545 | F16: =IF(E16<0,"",(Depth0-MIN(Depth0,E16))/Depth_per_q) -> 2.9443637 | G16: =IF(F16="","",Fee*$A16+Vq*F16) -> 25.05491 | H16: 17.196095 | I16: =IF(H16<0,"",(Depth0-MIN(Depth0,H16))/Depth_per_q) -> 2.7009762 | J16: =IF(I16="","",Fee*$A16+Vq*I16) -> 23.107809 | K16: 18.001074 | L16: =IF(K16<0,"",(Depth0-MIN(Depth0,K16))/Depth_per_q) -> 2.4997315 | M16: =IF(L16="","",Fee*$A16+Vq*L16) -> 21.497852
A17: 55 | B17: 13.649299 | C17: =IF(B17<0,"",(Depth0-MIN(Depth0,B17))/Depth_per_q) -> 3.5876753 | D17: =IF(C17="","",Fee*$A17+Vq*C17) -> 30.351402 | E17: 17.056024 | F17: =IF(E17<0,"",(Depth0-MIN(Depth0,E17))/Depth_per_q) -> 2.7359939 | G17: =IF(F17="","",Fee*$A17+Vq*F17) -> 23.537951 | H17: 17.951515 | I17: =IF(H17<0,"",(Depth0-MIN(Depth0,H17))/Depth_per_q) -> 2.5121212 | J17: =IF(I17="","",Fee*$A17+Vq*I17) -> 21.74697 | K17: 18.705128 | L17: =IF(K17<0,"",(Depth0-MIN(Depth0,K17))/Depth_per_q) -> 2.323718 | M17: =IF(L17="","",Fee*$A17+Vq*L17) -> 20.239744
... A86: 400 | B86: 23.732449 | C86: =IF(B86<0,"",(Depth0-MIN(Depth0,B86))/Depth_per_q) -> 1.0668877 | D86: =IF(C86="","",Fee*$A86+Vq*C86) -> 20.535101 | E86: 25.351449 | F86: =IF(E86<0,"",(Depth0-MIN(Depth0,E86))/Depth_per_q) -> 0.66213765 | G86: =IF(F86="","",Fee*$A86+Vq*F86) -> 17.297101 | H86: 25.781569 | I86: =IF(H86<0,"",(Depth0-MIN(Depth0,H86))/Depth_per_q) -> 0.55460771 | J86: =IF(I86="","",Fee*$A86+Vq*I86) -> 16.436862 | K86: 26.163908 | L86: =IF(K86<0,"",(Depth0-MIN(Depth0,K86))/Depth_per_q) -> 0.459023 | M86: =IF(L86="","",Fee*$A86+Vq*L86) -> 15.672184
A88: Least cost at each appetite
A89: Least cost | D89: =MIN(D6:D86) -> 14.668098 | G89: =MIN(G6:G86) -> 11.388504 | J89: =MIN(J6:J86) -> 10.440611 | M89: =MIN(M6:M86) -> 9.5814895
A90: Its line | D90: =INDEX($A$6:$A$86,MATCH(D89,D6:D86,0)) -> 180 | G90: =INDEX($A$6:$A$86,MATCH(G89,G6:G86,0)) -> 165 | J90: =INDEX($A$6:$A$86,MATCH(J89,J6:J86,0)) -> 170 | M90: =INDEX($A$6:$A$86,MATCH(M89,M6:M86,0)) -> 165
A91: Its delay (quarters) | D91: =INDEX(C6:C86,MATCH(D89,D6:D86,0)) -> 1.1585123 | G91: =INDEX(F6:F86,MATCH(G89,G6:G86,0)) -> 0.80481304 | J91: =INDEX(I6:I86,MATCH(J89,J6:J86,0)) -> 0.66757636 | M91: =INDEX(L6:L86,MATCH(M89,M6:M86,0)) -> 0.57893619
A93: The 5% package: line | B93: =J90 -> 170 | C93: Worked Example 15.1: about $170 million
A94: The 5% package: delay (quarters) | B94: =J91 -> 0.66757636 | C94: 0.668: two months
A95: The 5% package: least cost | B95: =J89 -> 10.440611 | C95: Table 16.1, L5: $10.4 million
A96: Chapter 8's package at the declared prices | B96: =Fee*Line8+Vq*Delay8 -> 19 | C96: Step 1: $19.0 million
A97: The cheapest package at the same odds | B97: =D89 -> 14.668098 | C97: Step 1: $14.7 million (Online Appendix 16.B.3: 14.67)
A98: Choosing on safety alone cost | B98: =B96-B97 -> 4.3319019 | C98: Online Appendix 16.B.3: 4.33
A99: Least cost at 4.5% | B99: =G89 -> 11.388504
A100: Least cost at 5.5% | B100: =M89 -> 9.5814895
A101: The appetite's multiplier ($ million a point) | B101: =B99-B100 -> 1.8070148 | C101: Table 16.4: $1.8 million a point
A102: Implied cost of a breach, 100 x the multiplier | B102: =100*B101 -> 180.70148 | C102: Table 16.1, L5: about $180 million

Sheet R2_Consistency
A1: Unified consistency, gate (R2): the joint check, its minimal set and the repair (Worked Example 16.1, Step 2; Table 16.1, L1 and L2)
A2: Liquidity = $6.2 million x (Chapter 1's index less the draw D x s(t)), s(t) = (t/2) e^(1 - t/2). The average path is the plan less the closures' expected drain.
A4: Quarter | B4: Years t | C4: Index without the draw | D4: Draw shape s(t) | E4: Plan as drawn (D = 28) | F4: With the package's delay | G4: Expected closures so far | H4: The average path
A5: 0 | B5: =A5/4 -> 0 | C5: =Liq_target+(100-Liq_target)*EXP(-Relax*B5) -> 100 | D5: =(B5/Tau)*EXP(1-B5/Tau) -> 0 | E5: =Usd_pt*(C5-Depth0*D5) -> 620 | F5: =Usd_pt*(C5-$B$31*D5) -> 620 | G5: =Lam/4*A5*J_mean -> 0 | H5: =E5-G5 -> 620
A6: 1 | B6: =A6/4 -> 0.25 | C6: =Liq_target+(100-Liq_target)*EXP(-Relax*B6) -> 101.00537 | D6: =(B6/Tau)*EXP(1-B6/Tau) -> 0.29985941 | E6: =Usd_pt*(C6-Depth0*D6) -> 574.17772 | F6: =Usd_pt*(C6-$B$31*D6) -> 579.14216 | G6: =Lam/4*A6*J_mean -> 3 | H6: =E6-G6 -> 571.17772
A7: 2 | B7: =A7/4 -> 0.5 | C7: =Liq_target+(100-Liq_target)*EXP(-Relax*B7) -> 101.92652 | D7: =(B7/Tau)*EXP(1-B7/Tau) -> 0.52925 | E7: =Usd_pt*(C7-Depth0*D7) -> 540.0666 | F7: =Usd_pt*(C7-$B$31*D7) -> 548.8288 | G7: =Lam/4*A7*J_mean -> 6 | H7: =E7-G7 -> 534.0666
A8: 3 | B8: =A8/4 -> 0.75 | C8: =Liq_target+(100-Liq_target)*EXP(-Relax*B8) -> 102.77048 | D8: =(B8/Tau)*EXP(1-B8/Tau) -> 0.70059223 | E8: =Usd_pt*(C8-Depth0*D8) -> 515.55419 | F8: =Usd_pt*(C8-$B$31*D8) -> 527.15312 | G8: =Lam/4*A8*J_mean -> 9 | H8: =E8-G8 -> 506.55419
A9: 4 | B9: =A9/4 -> 1 | C9: =Liq_target+(100-Liq_target)*EXP(-Relax*B9) -> 103.54374 | D9: =(B9/Tau)*EXP(1-B9/Tau) -> 0.82436064 | E9: =Usd_pt*(C9-Depth0*D9) -> 498.8622 | F9: =Usd_pt*(C9-$B$31*D9) -> 512.51023 | G9: =Lam/4*A9*J_mean -> 12 | H9: =E9-G9 -> 486.8622
A10: 5 | B10: =A10/4 -> 1.25 | C10: =Liq_target+(100-Liq_target)*EXP(-Relax*B10) -> 104.25222 | D10: =(B10/Tau)*EXP(1-B10/Tau) -> 0.90936963 | E10: =Usd_pt*(C10-Depth0*D10) -> 488.49718 | F10: =Usd_pt*(C10-$B$31*D10) -> 503.55261 | G10: =Lam/4*A10*J_mean -> 15 | H10: =E10-G10 -> 473.49718
A11: 6 | B11: =A11/4 -> 1.5 | C11: =Liq_target+(100-Liq_target)*EXP(-Relax*B11) -> 104.90134 | D11: =(B11/Tau)*EXP(1-B11/Tau) -> 0.96301906 | E11: =Usd_pt*(C11-Depth0*D11) -> 483.20817 | F11: =Usd_pt*(C11-$B$31*D11) -> 499.15181 | G11: =Lam/4*A11*J_mean -> 18 | H11: =E11-G11 -> 465.20817
A12: 7 | B12: =A12/4 -> 1.75 | C12: =Liq_target+(100-Liq_target)*EXP(-Relax*B12) -> 105.49607 | D12: =(B12/Tau)*EXP(1-B12/Tau) -> 0.9915049 | E12: =Usd_pt*(C12-Depth0*D12) -> 481.95038 | F12: =Usd_pt*(C12-$B$31*D12) -> 498.36563 | G12: =Lam/4*A12*J_mean -> 21 | H12: =E12-G12 -> 460.95038
A13: 8 | B13: =A13/4 -> 2 | C13: =Liq_target+(100-Liq_target)*EXP(-Relax*B13) -> 106.04098 | D13: =(B13/Tau)*EXP(1-B13/Tau) -> 1 | E13: =Usd_pt*(C13-Depth0*D13) -> 483.85405 | F13: =Usd_pt*(C13-$B$31*D13) -> 500.40995 | G13: =Lam/4*A13*J_mean -> 24 | H13: =E13-G13 -> 459.85405
A14: 9 | B14: =A14/4 -> 2.25 | C14: =Liq_target+(100-Liq_target)*EXP(-Relax*B14) -> 106.54023 | D14: =(B14/Tau)*EXP(1-B14/Tau) -> 0.99280902 | E14: =Usd_pt*(C14-Depth0*D14) -> 488.19778 | F14: =Usd_pt*(C14-$B$31*D14) -> 504.63462 | G14: =Lam/4*A14*J_mean -> 27 | H14: =E14-G14 -> 461.19778
A15: 10 | B15: =A15/4 -> 2.5 | C15: =Liq_target+(100-Liq_target)*EXP(-Relax*B15) -> 106.99766 | D15: =(B15/Tau)*EXP(1-B15/Tau) -> 0.97350098 | E15: =Usd_pt*(C15-Depth0*D15) -> 494.3857 | F15: =Usd_pt*(C15-$B$31*D15) -> 510.50287 | G15: =Lam/4*A15*J_mean -> 30 | H15: =E15-G15 -> 464.3857
A16: 11 | B16: =A16/4 -> 2.75 | C16: =Liq_target+(100-Liq_target)*EXP(-Relax*B16) -> 107.41676 | D16: =(B16/Tau)*EXP(1-B16/Tau) -> 0.94502276 | E16: =Usd_pt*(C16-Depth0*D16) -> 501.92795 | F16: =Usd_pt*(C16-$B$31*D16) -> 517.57364 | G16: =Lam/4*A16*J_mean -> 33 | H16: =E16-G16 -> 468.92795
A17: 12 | B17: =A17/4 -> 3 | C17: =Liq_target+(100-Liq_target)*EXP(-Relax*B17) -> 107.80075 | D17: =(B17/Tau)*EXP(1-B17/Tau) -> 0.90979599 | E17: =Usd_pt*(C17-Depth0*D17) -> 510.42405 | F17: =Usd_pt*(C17-$B$31*D17) -> 525.48653 | G17: =Lam/4*A17*J_mean -> 36 | H17: =E17-G17 -> 474.42405
A19: The program's deepest draw (transformation office) | B19: =Liq0-MIN(E5:E17) -> 138.04962 | C19: Table 16.1, L1: $138 million
A20: Buffer for a 90th-percentile closure (treasury) | B20: =GAMMAINV(0.9,G_shape,G_scale) -> 186.86698 | C20: Table 16.1, L1: $187 million
A21: Each alone fits in the cash above the floor? | B21: =IF(AND(B19<=Pool,B20<=Pool),"yes: both sign-offs pass","no") -> yes: both sign-offs pass | C21: the bilateral checks
A22: Together: draw + buffer | B22: =B19+B20 -> 324.91659 | C22: Step 2: $325 million on $270 million
A23: Short by | B23: =B22-Pool -> 54.916594 | C23: Online Appendix 16.B.3: 54.9
A24: The average path's lowest point | B24: =MIN(H5:H17) -> 459.85405 | C24: Table 16.1, L2: $460 million, above the floor
A26: Without the draw: liquidity left after the buffer, against the floor | B26: =Liq0-B20 -> 433.13302
A27: Without the buffer: liquidity left after the draw, against the floor | B27: =Liq0-B19 -> 481.95038
A28: Without the floor: liquidity left after both claims, against zero | B28: =Liq0-B19-B20 -> 295.08341
A29: The minimal set {draw, buffer, floor}: every pair holds, all three fail? | B29: =IF(AND(B26>=Floor_m,B27>=Floor_m,B28>=0,B28<Floor_m),"yes: a minimal set","no") -> yes: a minimal set | C29: owners: transformation office, treasury, board
A31: Depth with the package's delay, 28 - 4 x delay | B31: =Depth0-Depth_per_q*Quantiles!B94 -> 25.329695 | C31: 25.33
A32: Deepest draw with the delay | B32: =Liq0-MIN(F5:F17) -> 121.63437 | C32: Step 2: $122 million
A33: Buffer the line leaves | B33: =MAX(B20-Quantiles!B93,0) -> 16.866976 | C33: Step 2: all but $17 million
A34: Draw + buffer now | B34: =B32+B33 -> 138.50134 | C34: Step 2: $139 million
A35: Unclaimed | B35: =Pool-B34 -> 131.49866 | C35: Step 2: $131 million
A36: The consistency certificate issues? | B36: =IF(B34<=Pool,"yes","no") -> yes | C36: (R2) passes

Sheet R3_Panel
A1: The analytical panel, gate (R3): the register, its certificate, the phase-two link and its repairs (Worked Example 16.1, Step 3; Theorem 16.5(ii); Section 16.5)
A2: Symmetric core: engineering links e, treasury links t, the phase-two Digital-Industrial Systems link h; every link two-way. Spectral radius (h + sqrt(h^2 + 8(e^2 + t^2)))/2 (Chapter 14).
A4: Engineering links e | B4: =Ceil_gain -> 0.4 | C4: 0.40
A5: Treasury links t | B5: =Ceil_gain -> 0.4 | C5: 0.40
A6: Phase-two link h (not in the register) | B6: 0 | C6: its ceiling is zero
A7: Spectral radius of the register | B7: =((B6)+SQRT((B6)^2+8*((B4)^2+(B5)^2)))/2 -> 0.8 | C7: Step 3: 0.80
A8: The board's rule | B8: =Rule_rho -> 0.84089642 | C8: 0.841
A9: Half-life (quarters) | B9: =LN(2)/LN(1/B7) -> 3.1062837 | C9: 3.1 quarters, inside the four-quarter rule
A10: Multiplier 1/(1 - spectral radius) | B10: =1/(1-B7) -> 5 | C10: 5
A11: The register passes the board's rule? | B11: =IF(B7<=B8,"yes","no") -> yes | C11: (R3) passes
A13: Passes on (column) to (row) | B13: IND | C13: DIG | D13: ENG | E13: TRS | H13: Quarter | I13: IND | J13: DIG | K13: ENG | L13: TRS | M13: Total echo
A14: IND | B14: 0 | C14: =$B$6 -> 0 | D14: =$B$4 -> 0.4 | E14: =$B$5 -> 0.4 | H14: 0 | I14: 0 | J14: 10 | K14: 0 | L14: 0 | M14: =SUM(I14:L14) -> 10
A15: DIG | B15: =$B$6 -> 0 | C15: 0 | D15: =$B$4 -> 0.4 | E15: =$B$5 -> 0.4 | H15: 1 | I15: =SUMPRODUCT($B$14:$E$14,I14:L14) -> 0 | J15: =SUMPRODUCT($B$15:$E$15,I14:L14) -> 0 | K15: =SUMPRODUCT($B$16:$E$16,I14:L14) -> 4 | L15: =SUMPRODUCT($B$17:$E$17,I14:L14) -> 4 | M15: =SUM(I15:L15) -> 8
A16: ENG | B16: =$B$4 -> 0.4 | C16: =$B$4 -> 0.4 | D16: 0 | E16: 0 | H16: 2 | I16: =SUMPRODUCT($B$14:$E$14,I15:L15) -> 3.2 | J16: =SUMPRODUCT($B$15:$E$15,I15:L15) -> 3.2 | K16: =SUMPRODUCT($B$16:$E$16,I15:L15) -> 0 | L16: =SUMPRODUCT($B$17:$E$17,I15:L15) -> 0 | M16: =SUM(I16:L16) -> 6.4
A17: TRS | B17: =$B$5 -> 0.4 | C17: =$B$5 -> 0.4 | D17: 0 | E17: 0 | H17: 3 | I17: =SUMPRODUCT($B$14:$E$14,I16:L16) -> 0 | J17: =SUMPRODUCT($B$15:$E$15,I16:L16) -> 0 | K17: =SUMPRODUCT($B$16:$E$16,I16:L16) -> 2.56 | L17: =SUMPRODUCT($B$17:$E$17,I16:L16) -> 2.56 | M17: =SUM(I17:L17) -> 5.12
H18: 4 | I18: =SUMPRODUCT($B$14:$E$14,I17:L17) -> 2.048 | J18: =SUMPRODUCT($B$15:$E$15,I17:L17) -> 2.048 | K18: =SUMPRODUCT($B$16:$E$16,I17:L17) -> 0 | L18: =SUMPRODUCT($B$17:$E$17,I17:L17) -> 0 | M18: =SUM(I18:L18) -> 4.096
A19: Echo of a $10 million shock at Digital: next quarter | B19: =M15 -> 8 | C19: $8 million | H19: 5 | I19: =SUMPRODUCT($B$14:$E$14,I18:L18) -> 0 | J19: =SUMPRODUCT($B$15:$E$15,I18:L18) -> 0 | K19: =SUMPRODUCT($B$16:$E$16,I18:L18) -> 1.6384 | L19: =SUMPRODUCT($B$17:$E$17,I18:L18) -> 1.6384 | M19: =SUM(I19:L19) -> 3.2768
A20: The quarter after | B20: =M16 -> 6.4 | C20: $6.4 million | H20: 6 | I20: =SUMPRODUCT($B$14:$E$14,I19:L19) -> 1.31072 | J20: =SUMPRODUCT($B$15:$E$15,I19:L19) -> 1.31072 | K20: =SUMPRODUCT($B$16:$E$16,I19:L19) -> 0 | L20: =SUMPRODUCT($B$17:$E$17,I19:L19) -> 0 | M20: =SUM(I20:L20) -> 2.62144
A21: The quarter after that | B21: =M17 -> 5.12 | C21: Online Appendix 16.B.2: 5.12 | H21: 7 | I21: =SUMPRODUCT($B$14:$E$14,I20:L20) -> 0 | J21: =SUMPRODUCT($B$15:$E$15,I20:L20) -> 0 | K21: =SUMPRODUCT($B$16:$E$16,I20:L20) -> 1.048576 | L21: =SUMPRODUCT($B$17:$E$17,I20:L20) -> 1.048576 | M21: =SUM(I21:L21) -> 2.097152
A22: In all, shock included (81 quarters) | B22: =SUM(M14:M94) -> 49.999999 | C22: $50 million | H22: 8 | I22: =SUMPRODUCT($B$14:$E$14,I21:L21) -> 0.8388608 | J22: =SUMPRODUCT($B$15:$E$15,I21:L21) -> 0.8388608 | K22: =SUMPRODUCT($B$16:$E$16,I21:L21) -> 0 | L22: =SUMPRODUCT($B$17:$E$17,I21:L21) -> 0 | M22: =SUM(I22:L22) -> 1.6777216
H23: 9 | I23: =SUMPRODUCT($B$14:$E$14,I22:L22) -> 0 | J23: =SUMPRODUCT($B$15:$E$15,I22:L22) -> 0 | K23: =SUMPRODUCT($B$16:$E$16,I22:L22) -> 0.67108864 | L23: =SUMPRODUCT($B$17:$E$17,I22:L22) -> 0.67108864 | M23: =SUM(I23:L23) -> 1.3421773
H24: 10 | I24: =SUMPRODUCT($B$14:$E$14,I23:L23) -> 0.53687091 | J24: =SUMPRODUCT($B$15:$E$15,I23:L23) -> 0.53687091 | K24: =SUMPRODUCT($B$16:$E$16,I23:L23) -> 0 | L24: =SUMPRODUCT($B$17:$E$17,I23:L23) -> 0 | M24: =SUM(I24:L24) -> 1.0737418
A25: Phase two: the new link declared at the ceiling | B25: =Ceil_gain -> 0.4 | H25: 11 | I25: =SUMPRODUCT($B$14:$E$14,I24:L24) -> 0 | J25: =SUMPRODUCT($B$15:$E$15,I24:L24) -> 0 | K25: =SUMPRODUCT($B$16:$E$16,I24:L24) -> 0.42949673 | L25: =SUMPRODUCT($B$17:$E$17,I24:L24) -> 0.42949673 | M25: =SUM(I25:L25) -> 0.85899346
A26: Spectral radius with the new link | B26: =((B25)+SQRT((B25)^2+8*((B4)^2+(B5)^2)))/2 -> 1.0246211 | C26: Step 3: 1.02 (Online Appendix 16.B.3: 1.025) | H26: 12 | I26: =SUMPRODUCT($B$14:$E$14,I25:L25) -> 0.34359738 | J26: =SUMPRODUCT($B$15:$E$15,I25:L25) -> 0.34359738 | K26: =SUMPRODUCT($B$16:$E$16,I25:L25) -> 0 | L26: =SUMPRODUCT($B$17:$E$17,I25:L25) -> 0 | M26: =SUM(I26:L26) -> 0.68719477
A27: Fails the board's rule and stability? | B27: =IF(AND(B26>Rule_rho,B26>=1),"yes: no certificate holds","no") -> yes: no certificate holds | H27: 13 | I27: =SUMPRODUCT($B$14:$E$14,I26:L26) -> 0 | J27: =SUMPRODUCT($B$15:$E$15,I26:L26) -> 0 | K27: =SUMPRODUCT($B$16:$E$16,I26:L26) -> 0.27487791 | L27: =SUMPRODUCT($B$17:$E$17,I26:L26) -> 0.27487791 | M27: =SUM(I27:L27) -> 0.54975581
H28: 14 | I28: =SUMPRODUCT($B$14:$E$14,I27:L27) -> 0.21990233 | J28: =SUMPRODUCT($B$15:$E$15,I27:L27) -> 0.21990233 | K28: =SUMPRODUCT($B$16:$E$16,I27:L27) -> 0 | L28: =SUMPRODUCT($B$17:$E$17,I27:L27) -> 0 | M28: =SUM(I28:L28) -> 0.43980465
A29: Repair: the new link at most | B29: =(Rule_rho^2-2*(B4^2+B5^2))/Rule_rho -> 0.079803862 | C29: Step 3: 0.08 | H29: 15 | I29: =SUMPRODUCT($B$14:$E$14,I28:L28) -> 0 | J29: =SUMPRODUCT($B$15:$E$15,I28:L28) -> 0 | K29: =SUMPRODUCT($B$16:$E$16,I28:L28) -> 0.17592186 | L29: =SUMPRODUCT($B$17:$E$17,I28:L28) -> 0.17592186 | M29: =SUM(I29:L29) -> 0.35184372
A30: its spectral radius | B30: =((B29)+SQRT((B29)^2+8*((B4)^2+(B5)^2)))/2 -> 0.84089642 | C30: equals the board's rule | H30: 16 | I30: =SUMPRODUCT($B$14:$E$14,I29:L29) -> 0.14073749 | J30: =SUMPRODUCT($B$15:$E$15,I29:L29) -> 0.14073749 | K30: =SUMPRODUCT($B$16:$E$16,I29:L29) -> 0 | L30: =SUMPRODUCT($B$17:$E$17,I29:L29) -> 0 | M30: =SUM(I30:L30) -> 0.28147498
A31: Repair: ring-fence the treasury links at | B31: =SQRT((Rule_rho^2-B25*Rule_rho)/2-B4^2) -> 0.15929252 | C31: Step 3: 0.16 | H31: 17 | I31: =SUMPRODUCT($B$14:$E$14,I30:L30) -> 0 | J31: =SUMPRODUCT($B$15:$E$15,I30:L30) -> 0 | K31: =SUMPRODUCT($B$16:$E$16,I30:L30) -> 0.11258999 | L31: =SUMPRODUCT($B$17:$E$17,I30:L30) -> 0.11258999 | M31: =SUM(I31:L31) -> 0.22517998
A32: its spectral radius | B32: =((B25)+SQRT((B25)^2+8*((B4)^2+(B31)^2)))/2 -> 0.84089642 | C32: equals the board's rule | H32: 18 | I32: =SUMPRODUCT($B$14:$E$14,I31:L31) -> 0.090071993 | J32: =SUMPRODUCT($B$15:$E$15,I31:L31) -> 0.090071993 | K32: =SUMPRODUCT($B$16:$E$16,I31:L31) -> 0 | L32: =SUMPRODUCT($B$17:$E$17,I31:L31) -> 0 | M32: =SUM(I32:L32) -> 0.18014399
A33: Repair: trim all four existing links to | B33: =SQRT((Rule_rho^2-B25*Rule_rho)/4) -> 0.30444549 | C33: Step 3: 0.30 | H33: 19 | I33: =SUMPRODUCT($B$14:$E$14,I32:L32) -> 0 | J33: =SUMPRODUCT($B$15:$E$15,I32:L32) -> 0 | K33: =SUMPRODUCT($B$16:$E$16,I32:L32) -> 0.072057594 | L33: =SUMPRODUCT($B$17:$E$17,I32:L32) -> 0.072057594 | M33: =SUM(I33:L33) -> 0.14411519
A34: its spectral radius | B34: =((B25)+SQRT((B25)^2+8*((B33)^2+(B33)^2)))/2 -> 0.84089642 | C34: equals the board's rule | H34: 20 | I34: =SUMPRODUCT($B$14:$E$14,I33:L33) -> 0.057646075 | J34: =SUMPRODUCT($B$15:$E$15,I33:L33) -> 0.057646075 | K34: =SUMPRODUCT($B$16:$E$16,I33:L33) -> 0 | L34: =SUMPRODUCT($B$17:$E$17,I33:L33) -> 0 | M34: =SUM(I34:L34) -> 0.11529215
H35: 21 | I35: =SUMPRODUCT($B$14:$E$14,I34:L34) -> 0 | J35: =SUMPRODUCT($B$15:$E$15,I34:L34) -> 0 | K35: =SUMPRODUCT($B$16:$E$16,I34:L34) -> 0.04611686 | L35: =SUMPRODUCT($B$17:$E$17,I34:L34) -> 0.04611686 | M35: =SUM(I35:L35) -> 0.09223372
A36: Phase two at the ceiling: the register | H36: 22 | I36: =SUMPRODUCT($B$14:$E$14,I35:L35) -> 0.036893488 | J36: =SUMPRODUCT($B$15:$E$15,I35:L35) -> 0.036893488 | K36: =SUMPRODUCT($B$16:$E$16,I35:L35) -> 0 | L36: =SUMPRODUCT($B$17:$E$17,I35:L35) -> 0 | M36: =SUM(I36:L36) -> 0.073786976
A37: Passes on (column) to (row) | B37: IND | C37: DIG | D37: ENG | E37: TRS | H37: 23 | I37: =SUMPRODUCT($B$14:$E$14,I36:L36) -> 0 | J37: =SUMPRODUCT($B$15:$E$15,I36:L36) -> 0 | K37: =SUMPRODUCT($B$16:$E$16,I36:L36) -> 0.029514791 | L37: =SUMPRODUCT($B$17:$E$17,I36:L36) -> 0.029514791 | M37: =SUM(I37:L37) -> 0.059029581
A38: IND | B38: 0 | C38: =$B$25 -> 0.4 | D38: =$B$4 -> 0.4 | E38: =$B$5 -> 0.4 | H38: 24 | I38: =SUMPRODUCT($B$14:$E$14,I37:L37) -> 0.023611832 | J38: =SUMPRODUCT($B$15:$E$15,I37:L37) -> 0.023611832 | K38: =SUMPRODUCT($B$16:$E$16,I37:L37) -> 0 | L38: =SUMPRODUCT($B$17:$E$17,I37:L37) -> 0 | M38: =SUM(I38:L38) -> 0.047223665
A39: DIG | B39: =$B$25 -> 0.4 | C39: 0 | D39: =$B$4 -> 0.4 | E39: =$B$5 -> 0.4 | H39: 25 | I39: =SUMPRODUCT($B$14:$E$14,I38:L38) -> 0 | J39: =SUMPRODUCT($B$15:$E$15,I38:L38) -> 0 | K39: =SUMPRODUCT($B$16:$E$16,I38:L38) -> 0.018889466 | L39: =SUMPRODUCT($B$17:$E$17,I38:L38) -> 0.018889466 | M39: =SUM(I39:L39) -> 0.037778932
A40: ENG | B40: =$B$4 -> 0.4 | C40: =$B$4 -> 0.4 | D40: 0 | E40: 0 | H40: 26 | I40: =SUMPRODUCT($B$14:$E$14,I39:L39) -> 0.015111573 | J40: =SUMPRODUCT($B$15:$E$15,I39:L39) -> 0.015111573 | K40: =SUMPRODUCT($B$16:$E$16,I39:L39) -> 0 | L40: =SUMPRODUCT($B$17:$E$17,I39:L39) -> 0 | M40: =SUM(I40:L40) -> 0.030223145
A41: TRS | B41: =$B$5 -> 0.4 | C41: =$B$5 -> 0.4 | D41: 0 | E41: 0 | H41: 27 | I41: =SUMPRODUCT($B$14:$E$14,I40:L40) -> 0 | J41: =SUMPRODUCT($B$15:$E$15,I40:L40) -> 0 | K41: =SUMPRODUCT($B$16:$E$16,I40:L40) -> 0.012089258 | L41: =SUMPRODUCT($B$17:$E$17,I40:L40) -> 0.012089258 | M41: =SUM(I41:L41) -> 0.024178516
H42: 28 | I42: =SUMPRODUCT($B$14:$E$14,I41:L41) -> 0.0096714066 | J42: =SUMPRODUCT($B$15:$E$15,I41:L41) -> 0.0096714066 | K42: =SUMPRODUCT($B$16:$E$16,I41:L41) -> 0 | L42: =SUMPRODUCT($B$17:$E$17,I41:L41) -> 0 | M42: =SUM(I42:L42) -> 0.019342813
A43: Quarter | B43: IND | C43: DIG | D43: ENG | E43: TRS | F43: Total echo | H43: 29 | I43: =SUMPRODUCT($B$14:$E$14,I42:L42) -> 0 | J43: =SUMPRODUCT($B$15:$E$15,I42:L42) -> 0 | K43: =SUMPRODUCT($B$16:$E$16,I42:L42) -> 0.0077371252 | L43: =SUMPRODUCT($B$17:$E$17,I42:L42) -> 0.0077371252 | M43: =SUM(I43:L43) -> 0.01547425
A44: 0 | B44: 0 | C44: 10 | D44: 0 | E44: 0 | F44: =SUM(B44:E44) -> 10 | H44: 30 | I44: =SUMPRODUCT($B$14:$E$14,I43:L43) -> 0.0061897002 | J44: =SUMPRODUCT($B$15:$E$15,I43:L43) -> 0.0061897002 | K44: =SUMPRODUCT($B$16:$E$16,I43:L43) -> 0 | L44: =SUMPRODUCT($B$17:$E$17,I43:L43) -> 0 | M44: =SUM(I44:L44) -> 0.0123794
A45: 1 | B45: =SUMPRODUCT($B$38:$E$38,B44:E44) -> 4 | C45: =SUMPRODUCT($B$39:$E$39,B44:E44) -> 0 | D45: =SUMPRODUCT($B$40:$E$40,B44:E44) -> 4 | E45: =SUMPRODUCT($B$41:$E$41,B44:E44) -> 4 | F45: =SUM(B45:E45) -> 12 | H45: 31 | I45: =SUMPRODUCT($B$14:$E$14,I44:L44) -> 0 | J45: =SUMPRODUCT($B$15:$E$15,I44:L44) -> 0 | K45: =SUMPRODUCT($B$16:$E$16,I44:L44) -> 0.0049517602 | L45: =SUMPRODUCT($B$17:$E$17,I44:L44) -> 0.0049517602 | M45: =SUM(I45:L45) -> 0.0099035203
A46: 2 | B46: =SUMPRODUCT($B$38:$E$38,B45:E45) -> 3.2 | C46: =SUMPRODUCT($B$39:$E$39,B45:E45) -> 4.8 | D46: =SUMPRODUCT($B$40:$E$40,B45:E45) -> 1.6 | E46: =SUMPRODUCT($B$41:$E$41,B45:E45) -> 1.6 | F46: =SUM(B46:E46) -> 11.2 | H46: 32 | I46: =SUMPRODUCT($B$14:$E$14,I45:L45) -> 0.0039614081 | J46: =SUMPRODUCT($B$15:$E$15,I45:L45) -> 0.0039614081 | K46: =SUMPRODUCT($B$16:$E$16,I45:L45) -> 0 | L46: =SUMPRODUCT($B$17:$E$17,I45:L45) -> 0 | M46: =SUM(I46:L46) -> 0.0079228163
A47: 3 | B47: =SUMPRODUCT($B$38:$E$38,B46:E46) -> 3.2 | C47: =SUMPRODUCT($B$39:$E$39,B46:E46) -> 2.56 | D47: =SUMPRODUCT($B$40:$E$40,B46:E46) -> 3.2 | E47: =SUMPRODUCT($B$41:$E$41,B46:E46) -> 3.2 | F47: =SUM(B47:E47) -> 12.16 | H47: 33 | I47: =SUMPRODUCT($B$14:$E$14,I46:L46) -> 0 | J47: =SUMPRODUCT($B$15:$E$15,I46:L46) -> 0 | K47: =SUMPRODUCT($B$16:$E$16,I46:L46) -> 0.0031691265 | L47: =SUMPRODUCT($B$17:$E$17,I46:L46) -> 0.0031691265 | M47: =SUM(I47:L47) -> 0.006338253
A48: 4 | B48: =SUMPRODUCT($B$38:$E$38,B47:E47) -> 3.584 | C48: =SUMPRODUCT($B$39:$E$39,B47:E47) -> 3.84 | D48: =SUMPRODUCT($B$40:$E$40,B47:E47) -> 2.304 | E48: =SUMPRODUCT($B$41:$E$41,B47:E47) -> 2.304 | F48: =SUM(B48:E48) -> 12.032 | H48: 34 | I48: =SUMPRODUCT($B$14:$E$14,I47:L47) -> 0.0025353012 | J48: =SUMPRODUCT($B$15:$E$15,I47:L47) -> 0.0025353012 | K48: =SUMPRODUCT($B$16:$E$16,I47:L47) -> 0 | L48: =SUMPRODUCT($B$17:$E$17,I47:L47) -> 0 | M48: =SUM(I48:L48) -> 0.0050706024
A49: 5 | B49: =SUMPRODUCT($B$38:$E$38,B48:E48) -> 3.3792 | C49: =SUMPRODUCT($B$39:$E$39,B48:E48) -> 3.2768 | D49: =SUMPRODUCT($B$40:$E$40,B48:E48) -> 2.9696 | E49: =SUMPRODUCT($B$41:$E$41,B48:E48) -> 2.9696 | F49: =SUM(B49:E49) -> 12.5952 | H49: 35 | I49: =SUMPRODUCT($B$14:$E$14,I48:L48) -> 0 | J49: =SUMPRODUCT($B$15:$E$15,I48:L48) -> 0 | K49: =SUMPRODUCT($B$16:$E$16,I48:L48) -> 0.002028241 | L49: =SUMPRODUCT($B$17:$E$17,I48:L48) -> 0.002028241 | M49: =SUM(I49:L49) -> 0.0040564819
A50: 6 | B50: =SUMPRODUCT($B$38:$E$38,B49:E49) -> 3.6864 | C50: =SUMPRODUCT($B$39:$E$39,B49:E49) -> 3.72736 | D50: =SUMPRODUCT($B$40:$E$40,B49:E49) -> 2.6624 | E50: =SUMPRODUCT($B$41:$E$41,B49:E49) -> 2.6624 | F50: =SUM(B50:E50) -> 12.73856 | H50: 36 | I50: =SUMPRODUCT($B$14:$E$14,I49:L49) -> 0.0016225928 | J50: =SUMPRODUCT($B$15:$E$15,I49:L49) -> 0.0016225928 | K50: =SUMPRODUCT($B$16:$E$16,I49:L49) -> 0 | L50: =SUMPRODUCT($B$17:$E$17,I49:L49) -> 0 | M50: =SUM(I50:L50) -> 0.0032451855
A51: 7 | B51: =SUMPRODUCT($B$38:$E$38,B50:E50) -> 3.620864 | C51: =SUMPRODUCT($B$39:$E$39,B50:E50) -> 3.60448 | D51: =SUMPRODUCT($B$40:$E$40,B50:E50) -> 2.965504 | E51: =SUMPRODUCT($B$41:$E$41,B50:E50) -> 2.965504 | F51: =SUM(B51:E51) -> 13.156352 | H51: 37 | I51: =SUMPRODUCT($B$14:$E$14,I50:L50) -> 0 | J51: =SUMPRODUCT($B$15:$E$15,I50:L50) -> 0 | K51: =SUMPRODUCT($B$16:$E$16,I50:L50) -> 0.0012980742 | L51: =SUMPRODUCT($B$17:$E$17,I50:L50) -> 0.0012980742 | M51: =SUM(I51:L51) -> 0.0025961484
A52: 8 | B52: =SUMPRODUCT($B$38:$E$38,B51:E51) -> 3.8141952 | C52: =SUMPRODUCT($B$39:$E$39,B51:E51) -> 3.8207488 | D52: =SUMPRODUCT($B$40:$E$40,B51:E51) -> 2.8901376 | E52: =SUMPRODUCT($B$41:$E$41,B51:E51) -> 2.8901376 | F52: =SUM(B52:E52) -> 13.415219 | H52: 38 | I52: =SUMPRODUCT($B$14:$E$14,I51:L51) -> 0.0010384594 | J52: =SUMPRODUCT($B$15:$E$15,I51:L51) -> 0.0010384594 | K52: =SUMPRODUCT($B$16:$E$16,I51:L51) -> 0 | L52: =SUMPRODUCT($B$17:$E$17,I51:L51) -> 0 | M52: =SUM(I52:L52) -> 0.0020769187
A53: 9 | B53: =SUMPRODUCT($B$38:$E$38,B52:E52) -> 3.8404096 | C53: =SUMPRODUCT($B$39:$E$39,B52:E52) -> 3.8377882 | D53: =SUMPRODUCT($B$40:$E$40,B52:E52) -> 3.0539776 | E53: =SUMPRODUCT($B$41:$E$41,B52:E52) -> 3.0539776 | F53: =SUM(B53:E53) -> 13.786153 | H53: 39 | I53: =SUMPRODUCT($B$14:$E$14,I52:L52) -> 0 | J53: =SUMPRODUCT($B$15:$E$15,I52:L52) -> 0 | K53: =SUMPRODUCT($B$16:$E$16,I52:L52) -> 0.0008307675 | L53: =SUMPRODUCT($B$17:$E$17,I52:L52) -> 0.0008307675 | M53: =SUM(I53:L53) -> 0.001661535
A54: 10 | B54: =SUMPRODUCT($B$38:$E$38,B53:E53) -> 3.9782973 | C54: =SUMPRODUCT($B$39:$E$39,B53:E53) -> 3.9793459 | D54: =SUMPRODUCT($B$40:$E$40,B53:E53) -> 3.0712791 | E54: =SUMPRODUCT($B$41:$E$41,B53:E53) -> 3.0712791 | F54: =SUM(B54:E54) -> 14.100201 | H54: 40 | I54: =SUMPRODUCT($B$14:$E$14,I53:L53) -> 0.000664614 | J54: =SUMPRODUCT($B$15:$E$15,I53:L53) -> 0.000664614 | K54: =SUMPRODUCT($B$16:$E$16,I53:L53) -> 0 | L54: =SUMPRODUCT($B$17:$E$17,I53:L53) -> 0 | M54: =SUM(I54:L54) -> 0.001329228
A55: 11 | B55: =SUMPRODUCT($B$38:$E$38,B54:E54) -> 4.0487617 | C55: =SUMPRODUCT($B$39:$E$39,B54:E54) -> 4.0483422 | D55: =SUMPRODUCT($B$40:$E$40,B54:E54) -> 3.1830573 | E55: =SUMPRODUCT($B$41:$E$41,B54:E54) -> 3.1830573 | F55: =SUM(B55:E55) -> 14.463218 | H55: 41 | I55: =SUMPRODUCT($B$14:$E$14,I54:L54) -> 0 | J55: =SUMPRODUCT($B$15:$E$15,I54:L54) -> 0 | K55: =SUMPRODUCT($B$16:$E$16,I54:L54) -> 0.0005316912 | L55: =SUMPRODUCT($B$17:$E$17,I54:L54) -> 0.0005316912 | M55: =SUM(I55:L55) -> 0.0010633824
A56: 12 | B56: =SUMPRODUCT($B$38:$E$38,B55:E55) -> 4.1657827 | C56: =SUMPRODUCT($B$39:$E$39,B55:E55) -> 4.1659505 | D56: =SUMPRODUCT($B$40:$E$40,B55:E55) -> 3.2388415 | E56: =SUMPRODUCT($B$41:$E$41,B55:E55) -> 3.2388415 | F56: =SUM(B56:E56) -> 14.809416 | H56: 42 | I56: =SUMPRODUCT($B$14:$E$14,I55:L55) -> 0.00042535296 | J56: =SUMPRODUCT($B$15:$E$15,I55:L55) -> 0.00042535296 | K56: =SUMPRODUCT($B$16:$E$16,I55:L55) -> 0 | L56: =SUMPRODUCT($B$17:$E$17,I55:L55) -> 0 | M56: =SUM(I56:L56) -> 0.00085070592
H57: 43 | I57: =SUMPRODUCT($B$14:$E$14,I56:L56) -> 0 | J57: =SUMPRODUCT($B$15:$E$15,I56:L56) -> 0 | K57: =SUMPRODUCT($B$16:$E$16,I56:L56) -> 0.00034028237 | L57: =SUMPRODUCT($B$17:$E$17,I56:L56) -> 0.00034028237 | M57: =SUM(I57:L57) -> 0.00068056473
H58: 44 | I58: =SUMPRODUCT($B$14:$E$14,I57:L57) -> 0.00027222589 | J58: =SUMPRODUCT($B$15:$E$15,I57:L57) -> 0.00027222589 | K58: =SUMPRODUCT($B$16:$E$16,I57:L57) -> 0 | L58: =SUMPRODUCT($B$17:$E$17,I57:L57) -> 0 | M58: =SUM(I58:L58) -> 0.00054445179
H59: 45 | I59: =SUMPRODUCT($B$14:$E$14,I58:L58) -> 0 | J59: =SUMPRODUCT($B$15:$E$15,I58:L58) -> 0 | K59: =SUMPRODUCT($B$16:$E$16,I58:L58) -> 0.00021778071 | L59: =SUMPRODUCT($B$17:$E$17,I58:L58) -> 0.00021778071 | M59: =SUM(I59:L59) -> 0.00043556143
H60: 46 | I60: =SUMPRODUCT($B$14:$E$14,I59:L59) -> 0.00017422457 | J60: =SUMPRODUCT($B$15:$E$15,I59:L59) -> 0.00017422457 | K60: =SUMPRODUCT($B$16:$E$16,I59:L59) -> 0 | L60: =SUMPRODUCT($B$17:$E$17,I59:L59) -> 0 | M60: =SUM(I60:L60) -> 0.00034844914
H61: 47 | I61: =SUMPRODUCT($B$14:$E$14,I60:L60) -> 0 | J61: =SUMPRODUCT($B$15:$E$15,I60:L60) -> 0 | K61: =SUMPRODUCT($B$16:$E$16,I60:L60) -> 0.00013937966 | L61: =SUMPRODUCT($B$17:$E$17,I60:L60) -> 0.00013937966 | M61: =SUM(I61:L61) -> 0.00027875931
H62: 48 | I62: =SUMPRODUCT($B$14:$E$14,I61:L61) -> 0.00011150373 | J62: =SUMPRODUCT($B$15:$E$15,I61:L61) -> 0.00011150373 | K62: =SUMPRODUCT($B$16:$E$16,I61:L61) -> 0 | L62: =SUMPRODUCT($B$17:$E$17,I61:L61) -> 0 | M62: =SUM(I62:L62) -> 0.00022300745
H63: 49 | I63: =SUMPRODUCT($B$14:$E$14,I62:L62) -> 0 | J63: =SUMPRODUCT($B$15:$E$15,I62:L62) -> 0 | K63: =SUMPRODUCT($B$16:$E$16,I62:L62) -> 8.9202981e-05 | L63: =SUMPRODUCT($B$17:$E$17,I62:L62) -> 8.9202981e-05 | M63: =SUM(I63:L63) -> 0.00017840596
H64: 50 | I64: =SUMPRODUCT($B$14:$E$14,I63:L63) -> 7.1362385e-05 | J64: =SUMPRODUCT($B$15:$E$15,I63:L63) -> 7.1362385e-05 | K64: =SUMPRODUCT($B$16:$E$16,I63:L63) -> 0 | L64: =SUMPRODUCT($B$17:$E$17,I63:L63) -> 0 | M64: =SUM(I64:L64) -> 0.00014272477
H65: 51 | I65: =SUMPRODUCT($B$14:$E$14,I64:L64) -> 0 | J65: =SUMPRODUCT($B$15:$E$15,I64:L64) -> 0 | K65: =SUMPRODUCT($B$16:$E$16,I64:L64) -> 5.7089908e-05 | L65: =SUMPRODUCT($B$17:$E$17,I64:L64) -> 5.7089908e-05 | M65: =SUM(I65:L65) -> 0.00011417982
H66: 52 | I66: =SUMPRODUCT($B$14:$E$14,I65:L65) -> 4.5671926e-05 | J66: =SUMPRODUCT($B$15:$E$15,I65:L65) -> 4.5671926e-05 | K66: =SUMPRODUCT($B$16:$E$16,I65:L65) -> 0 | L66: =SUMPRODUCT($B$17:$E$17,I65:L65) -> 0 | M66: =SUM(I66:L66) -> 9.1343852e-05
H67: 53 | I67: =SUMPRODUCT($B$14:$E$14,I66:L66) -> 0 | J67: =SUMPRODUCT($B$15:$E$15,I66:L66) -> 0 | K67: =SUMPRODUCT($B$16:$E$16,I66:L66) -> 3.6537541e-05 | L67: =SUMPRODUCT($B$17:$E$17,I66:L66) -> 3.6537541e-05 | M67: =SUM(I67:L67) -> 7.3075082e-05
H68: 54 | I68: =SUMPRODUCT($B$14:$E$14,I67:L67) -> 2.9230033e-05 | J68: =SUMPRODUCT($B$15:$E$15,I67:L67) -> 2.9230033e-05 | K68: =SUMPRODUCT($B$16:$E$16,I67:L67) -> 0 | L68: =SUMPRODUCT($B$17:$E$17,I67:L67) -> 0 | M68: =SUM(I68:L68) -> 5.8460065e-05
... H94: 80 | I94: =SUMPRODUCT($B$14:$E$14,I93:L93) -> 8.8342353e-08 | J94: =SUMPRODUCT($B$15:$E$15,I93:L93) -> 8.8342353e-08 | K94: =SUMPRODUCT($B$16:$E$16,I93:L93) -> 0 | L94: =SUMPRODUCT($B$17:$E$17,I93:L93) -> 0 | M94: =SUM(I94:L94) -> 1.7668471e-07

Sheet DigitalTwin
A1: The digital twin: the gain audit flags a drift; the register's certificates are void until re-certified (AXIOM Lab 1.16, step 3; Theorem 16.5(ii); Online Appendix 16.B.2)
A2: The book prints no numbers for the drift: the scenario is this workbook's declaration, not the book's. Readings are the notebook's draws (seed 26116, engine values): the true gain plus an error of +/-0.02 (two standard deviations). Thin pass: within the error of the ceiling; flag: above it by more than the error.
A4: Ceiling of each core link | B4: =Ceil_gain -> 0.4 | C4: the register
A5: Error of a gain reading (two standard deviations) | B5: 0.02 | C5: this workbook's declaration
A6: True gains at the start | B6: 0.36 | C6: this workbook's declaration
A7: The Digital-engineering link drifts up, a quarter | B7: 0.02 | C7: from quarter 4
C8: IND-ENG | D8: DIG-ENG | E8: IND-TRS | F8: DIG-TRS
A9: Quarter | B9: True DIG-ENG | C9: Reading IND-ENG | D9: Reading DIG-ENG | E9: Reading IND-TRS | F9: Reading DIG-TRS | G9: Verdict IND-ENG | H9: Verdict DIG-ENG | I9: Verdict IND-TRS | J9: Verdict DIG-TRS | K9: Any thin pass | L9: Any flag
A10: 0 | B10: =$B$6+$B$7*MAX(A10-3,0) -> 0.36 | C10: 0.36782347 | D10: 0.34584903 | E10: 0.37455668 | F10: 0.35877822 | G10: =IF(C10>$B$4+$B$5,"flag",IF(C10>$B$4-$B$5,"thin pass","passes")) -> passes | H10: =IF(D10>$B$4+$B$5,"flag",IF(D10>$B$4-$B$5,"thin pass","passes")) -> passes | I10: =IF(E10>$B$4+$B$5,"flag",IF(E10>$B$4-$B$5,"thin pass","passes")) -> passes | J10: =IF(F10>$B$4+$B$5,"flag",IF(F10>$B$4-$B$5,"thin pass","passes")) -> passes | K10: =IF(COUNTIF(G10:J10,"thin pass")+COUNTIF(G10:J10,"flag")>0,1,0) -> 0 | L10: =IF(COUNTIF(G10:J10,"flag")>0,1,0) -> 0
A11: 1 | B11: =$B$6+$B$7*MAX(A11-3,0) -> 0.36 | C11: 0.34625735 | D11: 0.37510457 | E11: 0.36700913 | F11: 0.36460843 | G11: =IF(C11>$B$4+$B$5,"flag",IF(C11>$B$4-$B$5,"thin pass","passes")) -> passes | H11: =IF(D11>$B$4+$B$5,"flag",IF(D11>$B$4-$B$5,"thin pass","passes")) -> passes | I11: =IF(E11>$B$4+$B$5,"flag",IF(E11>$B$4-$B$5,"thin pass","passes")) -> passes | J11: =IF(F11>$B$4+$B$5,"flag",IF(F11>$B$4-$B$5,"thin pass","passes")) -> passes | K11: =IF(COUNTIF(G11:J11,"thin pass")+COUNTIF(G11:J11,"flag")>0,1,0) -> 0 | L11: =IF(COUNTIF(G11:J11,"flag")>0,1,0) -> 0
A12: 2 | B12: =$B$6+$B$7*MAX(A12-3,0) -> 0.36 | C12: 0.36819159 | D12: 0.35779282 | E12: 0.3534175 | F12: 0.36501289 | G12: =IF(C12>$B$4+$B$5,"flag",IF(C12>$B$4-$B$5,"thin pass","passes")) -> passes | H12: =IF(D12>$B$4+$B$5,"flag",IF(D12>$B$4-$B$5,"thin pass","passes")) -> passes | I12: =IF(E12>$B$4+$B$5,"flag",IF(E12>$B$4-$B$5,"thin pass","passes")) -> passes | J12: =IF(F12>$B$4+$B$5,"flag",IF(F12>$B$4-$B$5,"thin pass","passes")) -> passes | K12: =IF(COUNTIF(G12:J12,"thin pass")+COUNTIF(G12:J12,"flag")>0,1,0) -> 0 | L12: =IF(COUNTIF(G12:J12,"flag")>0,1,0) -> 0
A13: 3 | B13: =$B$6+$B$7*MAX(A13-3,0) -> 0.36 | C13: 0.3596179 | D13: 0.36496064 | E13: 0.34966654 | F13: 0.37236685 | G13: =IF(C13>$B$4+$B$5,"flag",IF(C13>$B$4-$B$5,"thin pass","passes")) -> passes | H13: =IF(D13>$B$4+$B$5,"flag",IF(D13>$B$4-$B$5,"thin pass","passes")) -> passes | I13: =IF(E13>$B$4+$B$5,"flag",IF(E13>$B$4-$B$5,"thin pass","passes")) -> passes | J13: =IF(F13>$B$4+$B$5,"flag",IF(F13>$B$4-$B$5,"thin pass","passes")) -> passes | K13: =IF(COUNTIF(G13:J13,"thin pass")+COUNTIF(G13:J13,"flag")>0,1,0) -> 0 | L13: =IF(COUNTIF(G13:J13,"flag")>0,1,0) -> 0
A14: 4 | B14: =$B$6+$B$7*MAX(A14-3,0) -> 0.38 | C14: 0.37167697 | D14: 0.39671516 | E14: 0.35953103 | F14: 0.3572778 | G14: =IF(C14>$B$4+$B$5,"flag",IF(C14>$B$4-$B$5,"thin pass","passes")) -> passes | H14: =IF(D14>$B$4+$B$5,"flag",IF(D14>$B$4-$B$5,"thin pass","passes")) -> thin pass | I14: =IF(E14>$B$4+$B$5,"flag",IF(E14>$B$4-$B$5,"thin pass","passes")) -> passes | J14: =IF(F14>$B$4+$B$5,"flag",IF(F14>$B$4-$B$5,"thin pass","passes")) -> passes | K14: =IF(COUNTIF(G14:J14,"thin pass")+COUNTIF(G14:J14,"flag")>0,1,0) -> 1 | L14: =IF(COUNTIF(G14:J14,"flag")>0,1,0) -> 0
A15: 5 | B15: =$B$6+$B$7*MAX(A15-3,0) -> 0.4 | C15: 0.34200378 | D15: 0.39315064 | E15: 0.36227875 | F15: 0.3475844 | G15: =IF(C15>$B$4+$B$5,"flag",IF(C15>$B$4-$B$5,"thin pass","passes")) -> passes | H15: =IF(D15>$B$4+$B$5,"flag",IF(D15>$B$4-$B$5,"thin pass","passes")) -> thin pass | I15: =IF(E15>$B$4+$B$5,"flag",IF(E15>$B$4-$B$5,"thin pass","passes")) -> passes | J15: =IF(F15>$B$4+$B$5,"flag",IF(F15>$B$4-$B$5,"thin pass","passes")) -> passes | K15: =IF(COUNTIF(G15:J15,"thin pass")+COUNTIF(G15:J15,"flag")>0,1,0) -> 1 | L15: =IF(COUNTIF(G15:J15,"flag")>0,1,0) -> 0
A16: 6 | B16: =$B$6+$B$7*MAX(A16-3,0) -> 0.42 | C16: 0.38529759 | D16: 0.42670797 | E16: 0.37306062 | F16: 0.34401212 | G16: =IF(C16>$B$4+$B$5,"flag",IF(C16>$B$4-$B$5,"thin pass","passes")) -> thin pass | H16: =IF(D16>$B$4+$B$5,"flag",IF(D16>$B$4-$B$5,"thin pass","passes")) -> flag | I16: =IF(E16>$B$4+$B$5,"flag",IF(E16>$B$4-$B$5,"thin pass","passes")) -> passes | J16: =IF(F16>$B$4+$B$5,"flag",IF(F16>$B$4-$B$5,"thin pass","passes")) -> passes | K16: =IF(COUNTIF(G16:J16,"thin pass")+COUNTIF(G16:J16,"flag")>0,1,0) -> 1 | L16: =IF(COUNTIF(G16:J16,"flag")>0,1,0) -> 1
A17: 7 | B17: =$B$6+$B$7*MAX(A17-3,0) -> 0.44 | C17: 0.38236254 | D17: 0.43065241 | E17: 0.3825762 | F17: 0.36059186 | G17: =IF(C17>$B$4+$B$5,"flag",IF(C17>$B$4-$B$5,"thin pass","passes")) -> thin pass | H17: =IF(D17>$B$4+$B$5,"flag",IF(D17>$B$4-$B$5,"thin pass","passes")) -> flag | I17: =IF(E17>$B$4+$B$5,"flag",IF(E17>$B$4-$B$5,"thin pass","passes")) -> thin pass | J17: =IF(F17>$B$4+$B$5,"flag",IF(F17>$B$4-$B$5,"thin pass","passes")) -> passes | K17: =IF(COUNTIF(G17:J17,"thin pass")+COUNTIF(G17:J17,"flag")>0,1,0) -> 1 | L17: =IF(COUNTIF(G17:J17,"flag")>0,1,0) -> 1
A18: 8 | B18: =$B$6+$B$7*MAX(A18-3,0) -> 0.46 | C18: 0.36195419 | D18: 0.48124736 | E18: 0.36388778 | F18: 0.34779855 | G18: =IF(C18>$B$4+$B$5,"flag",IF(C18>$B$4-$B$5,"thin pass","passes")) -> passes | H18: =IF(D18>$B$4+$B$5,"flag",IF(D18>$B$4-$B$5,"thin pass","passes")) -> flag | I18: =IF(E18>$B$4+$B$5,"flag",IF(E18>$B$4-$B$5,"thin pass","passes")) -> passes | J18: =IF(F18>$B$4+$B$5,"flag",IF(F18>$B$4-$B$5,"thin pass","passes")) -> passes | K18: =IF(COUNTIF(G18:J18,"thin pass")+COUNTIF(G18:J18,"flag")>0,1,0) -> 1 | L18: =IF(COUNTIF(G18:J18,"flag")>0,1,0) -> 1
A19: 9 | B19: =$B$6+$B$7*MAX(A19-3,0) -> 0.48 | C19: 0.36102931 | D19: 0.49079489 | E19: 0.34426158 | F19: 0.36840115 | G19: =IF(C19>$B$4+$B$5,"flag",IF(C19>$B$4-$B$5,"thin pass","passes")) -> passes | H19: =IF(D19>$B$4+$B$5,"flag",IF(D19>$B$4-$B$5,"thin pass","passes")) -> flag | I19: =IF(E19>$B$4+$B$5,"flag",IF(E19>$B$4-$B$5,"thin pass","passes")) -> passes | J19: =IF(F19>$B$4+$B$5,"flag",IF(F19>$B$4-$B$5,"thin pass","passes")) -> passes | K19: =IF(COUNTIF(G19:J19,"thin pass")+COUNTIF(G19:J19,"flag")>0,1,0) -> 1 | L19: =IF(COUNTIF(G19:J19,"flag")>0,1,0) -> 1
A20: 10 | B20: =$B$6+$B$7*MAX(A20-3,0) -> 0.5 | C20: 0.36149446 | D20: 0.48423394 | E20: 0.37494588 | F20: 0.36305955 | G20: =IF(C20>$B$4+$B$5,"flag",IF(C20>$B$4-$B$5,"thin pass","passes")) -> passes | H20: =IF(D20>$B$4+$B$5,"flag",IF(D20>$B$4-$B$5,"thin pass","passes")) -> flag | I20: =IF(E20>$B$4+$B$5,"flag",IF(E20>$B$4-$B$5,"thin pass","passes")) -> passes | J20: =IF(F20>$B$4+$B$5,"flag",IF(F20>$B$4-$B$5,"thin pass","passes")) -> passes | K20: =IF(COUNTIF(G20:J20,"thin pass")+COUNTIF(G20:J20,"flag")>0,1,0) -> 1 | L20: =IF(COUNTIF(G20:J20,"flag")>0,1,0) -> 1
A21: 11 | B21: =$B$6+$B$7*MAX(A21-3,0) -> 0.52 | C21: 0.34285338 | D21: 0.51272715 | E21: 0.36065908 | F21: 0.36463784 | G21: =IF(C21>$B$4+$B$5,"flag",IF(C21>$B$4-$B$5,"thin pass","passes")) -> passes | H21: =IF(D21>$B$4+$B$5,"flag",IF(D21>$B$4-$B$5,"thin pass","passes")) -> flag | I21: =IF(E21>$B$4+$B$5,"flag",IF(E21>$B$4-$B$5,"thin pass","passes")) -> passes | J21: =IF(F21>$B$4+$B$5,"flag",IF(F21>$B$4-$B$5,"thin pass","passes")) -> passes | K21: =IF(COUNTIF(G21:J21,"thin pass")+COUNTIF(G21:J21,"flag")>0,1,0) -> 1 | L21: =IF(COUNTIF(G21:J21,"flag")>0,1,0) -> 1
A22: 12 | B22: =$B$6+$B$7*MAX(A22-3,0) -> 0.54 | C22: 0.36165972 | D22: 0.53570422 | E22: 0.35067436 | F22: 0.36026329 | G22: =IF(C22>$B$4+$B$5,"flag",IF(C22>$B$4-$B$5,"thin pass","passes")) -> passes | H22: =IF(D22>$B$4+$B$5,"flag",IF(D22>$B$4-$B$5,"thin pass","passes")) -> flag | I22: =IF(E22>$B$4+$B$5,"flag",IF(E22>$B$4-$B$5,"thin pass","passes")) -> passes | J22: =IF(F22>$B$4+$B$5,"flag",IF(F22>$B$4-$B$5,"thin pass","passes")) -> passes | K22: =IF(COUNTIF(G22:J22,"thin pass")+COUNTIF(G22:J22,"flag")>0,1,0) -> 1 | L22: =IF(COUNTIF(G22:J22,"flag")>0,1,0) -> 1
A25: First quarter with a thin pass | B25: =MATCH(1,K10:K22,0)-1 -> 4
A26: First quarter with a flag | B26: =MATCH(1,L10:L22,0)-1 -> 6 | C26: the gain audit fires
A27: The flagged link | B27: =INDEX($C$8:$F$8,MATCH("flag",INDEX($G$10:$J$22,B26+1,0),0)) -> DIG-ENG | C27: attribution: Digital Solutions and shared engineering
A28: Its reading | B28: =INDEX($C$10:$F$22,B26+1,MATCH(B27,$C$8:$F$8,0)) -> 0.42670797
A30: Re-certified register: e = t = the ceiling, DIG-ENG = the reading. B B^T: (1,1) | B30: =$B$4^2+$B$4^2 -> 0.32 | C30: the core is bipartite: the spectral radius is B's largest singular value
A31: (1,2) | B31: =$B$4*B28+$B$4^2 -> 0.33068319
A32: (2,2) | B32: =B28^2+$B$4^2 -> 0.34207969
A33: Spectral radius | B33: =SQRT((B30+B32+SQRT((B30-B32)^2+4*B31^2))/2) -> 0.81357684
A34: Half-life (quarters) | B34: =LN(2)/LN(1/B33) -> 3.3596563
A35: Multiplier | B35: =1/(1-B33) -> 5.3641402
A36: Within the board's rule? | B36: =IF(B33<=Rule_rho,"yes, with the ceiling re-declared","no") -> yes, with the ceiling re-declared
A38: Largest DIG-ENG gain the rule tolerates, others at the ceiling: a = t^2 - r*^2 | B38: =$B$4^2-Rule_rho^2 -> -0.54710678 | C38: (t^2 - L) g^2 - 2 e t^2 g + (e^2 + t^2 - L)(t^2 - L) - t^4 = 0, L = r*^2
A39: b = -2 e t^2 | B39: =-2*$B$4*$B$4^2 -> -0.128
A40: c | B40: =($B$4^2+$B$4^2-Rule_rho^2)*($B$4^2-Rule_rho^2)-$B$4^4 -> 0.18618875
A41: the gain | B41: =(-B39-SQRT(B39^2-4*B38*B40))/(2*B38) -> 0.47799938
A42: Quarter the true drift passes it | B42: =_xlfn.MINIFS($A$10:$A$22,$B$10:$B$22,">"&B41) -> 9 | C42: re-declaring is no longer enough: buy the link down
A44: Certificates the flag voids, all of which Theorem 16.5(ii) grants only within the ceilings: the spectral radius at most 0.80; the half-life at most 3.1 quarters; the multiplier at most 5; the echo of a $10 million shock at most $8m, $6.4m, ..., $50m; the sensitivity certificates of Chapter 14; gate (R3).
A46: Online Appendix 16.B.2: 10,000 models with |A| <= M | B46: Largest spectral radius | C46: Models above the register's radius | D46: Echoes above its bound
A47: seed 16, as in the book's engine | B47: 0.63481061 | C47: 0 | D47: 0
A48: seed 26116, fresh draws | B48: 0.64962795 | C48: 0 | D48: 0
A50: The register's bound 10 x 0.8^k, quarters 0 to 8 | B50: =10*R3_Panel!$B$7^0 -> 10 | C50: =10*R3_Panel!$B$7^1 -> 8 | D50: =10*R3_Panel!$B$7^2 -> 6.4 | E50: =10*R3_Panel!$B$7^3 -> 5.12 | F50: =10*R3_Panel!$B$7^4 -> 4.096 | G50: =10*R3_Panel!$B$7^5 -> 3.2768 | H50: =10*R3_Panel!$B$7^6 -> 2.62144 | I50: =10*R3_Panel!$B$7^7 -> 2.097152 | J50: =10*R3_Panel!$B$7^8 -> 1.6777216

Sheet R4_Horizon
A1: Feasibility with horizon honesty, gate (R4): each margin against the error of its reading (Worked Example 16.1, Step 4; Table 16.4)
A3: As first declared: no levers among the decisions | B3: Value | C3: Reading
A4: Breach odds, no levers (engine, seed 8) | B4: 0.24622 | C4: 24.6 percent
A5: Within the appetite? | B5: =IF(B4<=Appetite,"yes","no: (R4) fails") -> no: (R4) fails
A7: Quarter K | B7: Odds of a breach by quarter K (engine) | C7: Within the appetite?
A8: 1 | B8: 0.00215 | C8: =IF(B8<=Appetite,"yes","no") -> yes
A9: 2 | B9: 0.01028 | C9: =IF(B9<=Appetite,"yes","no") -> yes
A10: 3 | B10: 0.02676 | C10: =IF(B10<=Appetite,"yes","no") -> yes
A11: 4 | B11: 0.05112 | C11: =IF(B11<=Appetite,"yes","no") -> no
A12: 5 | B12: 0.08092 | C12: =IF(B12<=Appetite,"yes","no") -> no
A13: 6 | B13: 0.11297 | C13: =IF(B13<=Appetite,"yes","no") -> no
A14: 7 | B14: 0.1429 | C14: =IF(B14<=Appetite,"yes","no") -> no
A15: 8 | B15: 0.16928 | C15: =IF(B15<=Appetite,"yes","no") -> no
A16: 9 | B16: 0.19364 | C16: =IF(B16<=Appetite,"yes","no") -> no
A17: 10 | B17: 0.21387 | C17: =IF(B17<=Appetite,"yes","no") -> no
A18: 11 | B18: 0.2317 | C18: =IF(B18<=Appetite,"yes","no") -> no
A19: 12 | B19: 0.24622 | C19: =IF(B19<=Appetite,"yes","no") -> no
A20: The artifact: quarters for which the declaration honors the appetite | B20: =COUNTIF(B8:B19,"<="&Appetite) -> 3
A22: With the package | B22: Value | C22: Reading
A23: Breach odds with the package (engine, seed 8) | B23: 0.05 | C23: 5.0 percent: binds
A24: Simulation error, points | B24: =100*SQRT(B23*(1-B23)/N_paths) -> 0.068920244 | C24: 0.07 points
A25: Price of the appetite ($ million a point) | B25: =Quantiles!B101 -> 1.8070148 | C25: $1.8 million a point
A26: Net leverage with the line fully drawn | B26: =(Net_debt+Quantiles!B93)/Ebitda -> 3.7430186 | C26: 3.74x
A27: Covenant margin | B27: =Covenant-B26 -> 0.75698144 | C27: 0.76 below the limit
A28: Error of the leverage reading | B28: =Band_lev*B26 -> 0.074860371 | C28: Online Appendix 16.B.3: 0.075
A29: Margin in errors of the reading | B29: =B27/B28 -> 10.111911 | C29: ten times its band
A30: Capability margin | B30: =Capability-Cap_floor -> 3 | C30: 3 points against +/-5
A31: Strategic risk: peak on the plan | B31: =MAX(B46:B646) -> 73.552546 | C31: 73.6
A32: month of the peak | B32: =12*INDEX(A46:A646,MATCH(B31,B46:B646,0)) -> 10.9 | C32: month 11
A33: margin under the ceiling | B33: =Risk_ceil-B31 -> 1.4474538 | C33: 1.4 points against +/-6
A35: Fresh paths (certificate seed 26209): the same package's odds (engine) | B35: 0.04907 | C35: fitted to the book's paths, its odds move by about a standard error on new ones
A36: Fresh paths: the cheapest package's cost (engine) | B36: 10.276112 | C36: a statistical certificate carries its paths, its seed and its error
A38: Table 16.4, bottom: commitment | B38: Margin | C38: Error of the reading | D38: Grade
A39: leverage <= 4.5x | B39: =B27 -> 0.75698144 | C39: =B28 -> 0.074860371 | D39: =IF(ABS(B39)<0.000000001,"statistical: binds",IF(B39>=C39,"strong","weaker than the reading")) -> strong
A40: breach odds <= 5% | B40: =100*(Appetite-B23) -> 0 | C40: =B24 -> 0.068920244 | D40: =IF(ABS(B40)<0.000000001,"statistical: binds",IF(B40>=C40,"strong","weaker than the reading")) -> statistical: binds
A41: capability >= 55 | B41: =B30 -> 3 | C41: =Band_cap -> 5 | D41: =IF(ABS(B41)<0.000000001,"statistical: binds",IF(B41>=C41,"strong","weaker than the reading")) -> weaker than the reading
A42: strategic risk <= 75 | B42: =B33 -> 1.4474538 | C42: =Band_risk -> 6 | D42: =IF(ABS(B42)<0.000000001,"statistical: binds",IF(B42>=C42,"strong","weaker than the reading")) -> weaker than the reading
A45: Years t (a tenth of a month) | B45: Strategic risk on the digital plan
A46: =0/120 -> 0 | B46: =Risk_target+(Risk0-Risk_target)*EXP(-Risk_rate*A46)+Risk_hump*(A46/Risk_peak_t)*EXP(1-A46/Risk_peak_t) -> 64
A47: =1/120 -> 0.0083333333 | B47: =Risk_target+(Risk0-Risk_target)*EXP(-Risk_rate*A47)+Risk_hump*(A47/Risk_peak_t)*EXP(1-A47/Risk_peak_t) -> 64.219187
A48: =2/120 -> 0.016666667 | B48: =Risk_target+(Risk0-Risk_target)*EXP(-Risk_rate*A48)+Risk_hump*(A48/Risk_peak_t)*EXP(1-A48/Risk_peak_t) -> 64.434886
A49: =3/120 -> 0.025 | B49: =Risk_target+(Risk0-Risk_target)*EXP(-Risk_rate*A49)+Risk_hump*(A49/Risk_peak_t)*EXP(1-A49/Risk_peak_t) -> 64.647134
A50: =4/120 -> 0.033333333 | B50: =Risk_target+(Risk0-Risk_target)*EXP(-Risk_rate*A50)+Risk_hump*(A50/Risk_peak_t)*EXP(1-A50/Risk_peak_t) -> 64.855967
A51: =5/120 -> 0.041666667 | B51: =Risk_target+(Risk0-Risk_target)*EXP(-Risk_rate*A51)+Risk_hump*(A51/Risk_peak_t)*EXP(1-A51/Risk_peak_t) -> 65.061422
A52: =6/120 -> 0.05 | B52: =Risk_target+(Risk0-Risk_target)*EXP(-Risk_rate*A52)+Risk_hump*(A52/Risk_peak_t)*EXP(1-A52/Risk_peak_t) -> 65.263535
A53: =7/120 -> 0.058333333 | B53: =Risk_target+(Risk0-Risk_target)*EXP(-Risk_rate*A53)+Risk_hump*(A53/Risk_peak_t)*EXP(1-A53/Risk_peak_t) -> 65.462343
A54: =8/120 -> 0.066666667 | B54: =Risk_target+(Risk0-Risk_target)*EXP(-Risk_rate*A54)+Risk_hump*(A54/Risk_peak_t)*EXP(1-A54/Risk_peak_t) -> 65.65788
A55: =9/120 -> 0.075 | B55: =Risk_target+(Risk0-Risk_target)*EXP(-Risk_rate*A55)+Risk_hump*(A55/Risk_peak_t)*EXP(1-A55/Risk_peak_t) -> 65.850183
A56: =10/120 -> 0.083333333 | B56: =Risk_target+(Risk0-Risk_target)*EXP(-Risk_rate*A56)+Risk_hump*(A56/Risk_peak_t)*EXP(1-A56/Risk_peak_t) -> 66.039285
A57: =11/120 -> 0.091666667 | B57: =Risk_target+(Risk0-Risk_target)*EXP(-Risk_rate*A57)+Risk_hump*(A57/Risk_peak_t)*EXP(1-A57/Risk_peak_t) -> 66.225221
A58: =12/120 -> 0.1 | B58: =Risk_target+(Risk0-Risk_target)*EXP(-Risk_rate*A58)+Risk_hump*(A58/Risk_peak_t)*EXP(1-A58/Risk_peak_t) -> 66.408026
A59: =13/120 -> 0.10833333 | B59: =Risk_target+(Risk0-Risk_target)*EXP(-Risk_rate*A59)+Risk_hump*(A59/Risk_peak_t)*EXP(1-A59/Risk_peak_t) -> 66.587733
A60: =14/120 -> 0.11666667 | B60: =Risk_target+(Risk0-Risk_target)*EXP(-Risk_rate*A60)+Risk_hump*(A60/Risk_peak_t)*EXP(1-A60/Risk_peak_t) -> 66.764377
A61: =15/120 -> 0.125 | B61: =Risk_target+(Risk0-Risk_target)*EXP(-Risk_rate*A61)+Risk_hump*(A61/Risk_peak_t)*EXP(1-A61/Risk_peak_t) -> 66.937989
A62: =16/120 -> 0.13333333 | B62: =Risk_target+(Risk0-Risk_target)*EXP(-Risk_rate*A62)+Risk_hump*(A62/Risk_peak_t)*EXP(1-A62/Risk_peak_t) -> 67.108604
A63: =17/120 -> 0.14166667 | B63: =Risk_target+(Risk0-Risk_target)*EXP(-Risk_rate*A63)+Risk_hump*(A63/Risk_peak_t)*EXP(1-A63/Risk_peak_t) -> 67.276254
A64: =18/120 -> 0.15 | B64: =Risk_target+(Risk0-Risk_target)*EXP(-Risk_rate*A64)+Risk_hump*(A64/Risk_peak_t)*EXP(1-A64/Risk_peak_t) -> 67.440971
A65: =19/120 -> 0.15833333 | B65: =Risk_target+(Risk0-Risk_target)*EXP(-Risk_rate*A65)+Risk_hump*(A65/Risk_peak_t)*EXP(1-A65/Risk_peak_t) -> 67.602787
A66: =20/120 -> 0.16666667 | B66: =Risk_target+(Risk0-Risk_target)*EXP(-Risk_rate*A66)+Risk_hump*(A66/Risk_peak_t)*EXP(1-A66/Risk_peak_t) -> 67.761734
A67: =21/120 -> 0.175 | B67: =Risk_target+(Risk0-Risk_target)*EXP(-Risk_rate*A67)+Risk_hump*(A67/Risk_peak_t)*EXP(1-A67/Risk_peak_t) -> 67.917843
A68: =22/120 -> 0.18333333 | B68: =Risk_target+(Risk0-Risk_target)*EXP(-Risk_rate*A68)+Risk_hump*(A68/Risk_peak_t)*EXP(1-A68/Risk_peak_t) -> 68.071146
A69: =23/120 -> 0.19166667 | B69: =Risk_target+(Risk0-Risk_target)*EXP(-Risk_rate*A69)+Risk_hump*(A69/Risk_peak_t)*EXP(1-A69/Risk_peak_t) -> 68.221674
A70: =24/120 -> 0.2 | B70: =Risk_target+(Risk0-Risk_target)*EXP(-Risk_rate*A70)+Risk_hump*(A70/Risk_peak_t)*EXP(1-A70/Risk_peak_t) -> 68.369456
A71: =25/120 -> 0.20833333 | B71: =Risk_target+(Risk0-Risk_target)*EXP(-Risk_rate*A71)+Risk_hump*(A71/Risk_peak_t)*EXP(1-A71/Risk_peak_t) -> 68.514524
A72: =26/120 -> 0.21666667 | B72: =Risk_target+(Risk0-Risk_target)*EXP(-Risk_rate*A72)+Risk_hump*(A72/Risk_peak_t)*EXP(1-A72/Risk_peak_t) -> 68.656907
A73: =27/120 -> 0.225 | B73: =Risk_target+(Risk0-Risk_target)*EXP(-Risk_rate*A73)+Risk_hump*(A73/Risk_peak_t)*EXP(1-A73/Risk_peak_t) -> 68.796634
A74: =28/120 -> 0.23333333 | B74: =Risk_target+(Risk0-Risk_target)*EXP(-Risk_rate*A74)+Risk_hump*(A74/Risk_peak_t)*EXP(1-A74/Risk_peak_t) -> 68.933736
A75: =29/120 -> 0.24166667 | B75: =Risk_target+(Risk0-Risk_target)*EXP(-Risk_rate*A75)+Risk_hump*(A75/Risk_peak_t)*EXP(1-A75/Risk_peak_t) -> 69.068242
A76: =30/120 -> 0.25 | B76: =Risk_target+(Risk0-Risk_target)*EXP(-Risk_rate*A76)+Risk_hump*(A76/Risk_peak_t)*EXP(1-A76/Risk_peak_t) -> 69.200179
A77: =31/120 -> 0.25833333 | B77: =Risk_target+(Risk0-Risk_target)*EXP(-Risk_rate*A77)+Risk_hump*(A77/Risk_peak_t)*EXP(1-A77/Risk_peak_t) -> 69.329578
A78: =32/120 -> 0.26666667 | B78: =Risk_target+(Risk0-Risk_target)*EXP(-Risk_rate*A78)+Risk_hump*(A78/Risk_peak_t)*EXP(1-A78/Risk_peak_t) -> 69.456466
A79: =33/120 -> 0.275 | B79: =Risk_target+(Risk0-Risk_target)*EXP(-Risk_rate*A79)+Risk_hump*(A79/Risk_peak_t)*EXP(1-A79/Risk_peak_t) -> 69.580871
A80: =34/120 -> 0.28333333 | B80: =Risk_target+(Risk0-Risk_target)*EXP(-Risk_rate*A80)+Risk_hump*(A80/Risk_peak_t)*EXP(1-A80/Risk_peak_t) -> 69.702821
A81: =35/120 -> 0.29166667 | B81: =Risk_target+(Risk0-Risk_target)*EXP(-Risk_rate*A81)+Risk_hump*(A81/Risk_peak_t)*EXP(1-A81/Risk_peak_t) -> 69.822343
A82: =36/120 -> 0.3 | B82: =Risk_target+(Risk0-Risk_target)*EXP(-Risk_rate*A82)+Risk_hump*(A82/Risk_peak_t)*EXP(1-A82/Risk_peak_t) -> 69.939466
A83: =37/120 -> 0.30833333 | B83: =Risk_target+(Risk0-Risk_target)*EXP(-Risk_rate*A83)+Risk_hump*(A83/Risk_peak_t)*EXP(1-A83/Risk_peak_t) -> 70.054215
A84: =38/120 -> 0.31666667 | B84: =Risk_target+(Risk0-Risk_target)*EXP(-Risk_rate*A84)+Risk_hump*(A84/Risk_peak_t)*EXP(1-A84/Risk_peak_t) -> 70.166618
A85: =39/120 -> 0.325 | B85: =Risk_target+(Risk0-Risk_target)*EXP(-Risk_rate*A85)+Risk_hump*(A85/Risk_peak_t)*EXP(1-A85/Risk_peak_t) -> 70.276701
A86: =40/120 -> 0.33333333 | B86: =Risk_target+(Risk0-Risk_target)*EXP(-Risk_rate*A86)+Risk_hump*(A86/Risk_peak_t)*EXP(1-A86/Risk_peak_t) -> 70.38449
A87: =41/120 -> 0.34166667 | B87: =Risk_target+(Risk0-Risk_target)*EXP(-Risk_rate*A87)+Risk_hump*(A87/Risk_peak_t)*EXP(1-A87/Risk_peak_t) -> 70.490011
A88: =42/120 -> 0.35 | B88: =Risk_target+(Risk0-Risk_target)*EXP(-Risk_rate*A88)+Risk_hump*(A88/Risk_peak_t)*EXP(1-A88/Risk_peak_t) -> 70.59329
A89: =43/120 -> 0.35833333 | B89: =Risk_target+(Risk0-Risk_target)*EXP(-Risk_rate*A89)+Risk_hump*(A89/Risk_peak_t)*EXP(1-A89/Risk_peak_t) -> 70.694353
A90: =44/120 -> 0.36666667 | B90: =Risk_target+(Risk0-Risk_target)*EXP(-Risk_rate*A90)+Risk_hump*(A90/Risk_peak_t)*EXP(1-A90/Risk_peak_t) -> 70.793225
A91: =45/120 -> 0.375 | B91: =Risk_target+(Risk0-Risk_target)*EXP(-Risk_rate*A91)+Risk_hump*(A91/Risk_peak_t)*EXP(1-A91/Risk_peak_t) -> 70.88993
A92: =46/120 -> 0.38333333 | B92: =Risk_target+(Risk0-Risk_target)*EXP(-Risk_rate*A92)+Risk_hump*(A92/Risk_peak_t)*EXP(1-A92/Risk_peak_t) -> 70.984494
A93: =47/120 -> 0.39166667 | B93: =Risk_target+(Risk0-Risk_target)*EXP(-Risk_rate*A93)+Risk_hump*(A93/Risk_peak_t)*EXP(1-A93/Risk_peak_t) -> 71.076941
A94: =48/120 -> 0.4 | B94: =Risk_target+(Risk0-Risk_target)*EXP(-Risk_rate*A94)+Risk_hump*(A94/Risk_peak_t)*EXP(1-A94/Risk_peak_t) -> 71.167295
A95: =49/120 -> 0.40833333 | B95: =Risk_target+(Risk0-Risk_target)*EXP(-Risk_rate*A95)+Risk_hump*(A95/Risk_peak_t)*EXP(1-A95/Risk_peak_t) -> 71.25558
A96: =50/120 -> 0.41666667 | B96: =Risk_target+(Risk0-Risk_target)*EXP(-Risk_rate*A96)+Risk_hump*(A96/Risk_peak_t)*EXP(1-A96/Risk_peak_t) -> 71.341821
A97: =51/120 -> 0.425 | B97: =Risk_target+(Risk0-Risk_target)*EXP(-Risk_rate*A97)+Risk_hump*(A97/Risk_peak_t)*EXP(1-A97/Risk_peak_t) -> 71.42604
A98: =52/120 -> 0.43333333 | B98: =Risk_target+(Risk0-Risk_target)*EXP(-Risk_rate*A98)+Risk_hump*(A98/Risk_peak_t)*EXP(1-A98/Risk_peak_t) -> 71.508262
A99: =53/120 -> 0.44166667 | B99: =Risk_target+(Risk0-Risk_target)*EXP(-Risk_rate*A99)+Risk_hump*(A99/Risk_peak_t)*EXP(1-A99/Risk_peak_t) -> 71.588509
A100: =54/120 -> 0.45 | B100: =Risk_target+(Risk0-Risk_target)*EXP(-Risk_rate*A100)+Risk_hump*(A100/Risk_peak_t)*EXP(1-A100/Risk_peak_t) -> 71.666804
A101: =55/120 -> 0.45833333 | B101: =Risk_target+(Risk0-Risk_target)*EXP(-Risk_rate*A101)+Risk_hump*(A101/Risk_peak_t)*EXP(1-A101/Risk_peak_t) -> 71.74317
A102: =56/120 -> 0.46666667 | B102: =Risk_target+(Risk0-Risk_target)*EXP(-Risk_rate*A102)+Risk_hump*(A102/Risk_peak_t)*EXP(1-A102/Risk_peak_t) -> 71.81763
A103: =57/120 -> 0.475 | B103: =Risk_target+(Risk0-Risk_target)*EXP(-Risk_rate*A103)+Risk_hump*(A103/Risk_peak_t)*EXP(1-A103/Risk_peak_t) -> 71.890205
A104: =58/120 -> 0.48333333 | B104: =Risk_target+(Risk0-Risk_target)*EXP(-Risk_rate*A104)+Risk_hump*(A104/Risk_peak_t)*EXP(1-A104/Risk_peak_t) -> 71.960918
A105: =59/120 -> 0.49166667 | B105: =Risk_target+(Risk0-Risk_target)*EXP(-Risk_rate*A105)+Risk_hump*(A105/Risk_peak_t)*EXP(1-A105/Risk_peak_t) -> 72.02979
A106: =60/120 -> 0.5 | B106: =Risk_target+(Risk0-Risk_target)*EXP(-Risk_rate*A106)+Risk_hump*(A106/Risk_peak_t)*EXP(1-A106/Risk_peak_t) -> 72.096844
A107: =61/120 -> 0.50833333 | B107: =Risk_target+(Risk0-Risk_target)*EXP(-Risk_rate*A107)+Risk_hump*(A107/Risk_peak_t)*EXP(1-A107/Risk_peak_t) -> 72.1621
...

Sheet Certificate
A1: Issue the certificate: Table 16.4, the grades and the work orders; no gate implies the next (Worked Example 16.1, Step 5; Theorem 16.4; Appendix 16.A)
A3: Gate | B3: After Chapter 8 | C3: Now | D3: Verdict now | E3: Owners
A4: (R1) declaration | B4: lever prices and the scorecard's scale undeclared | C4: prices declared; the scale is the board's to declare | D4: =R1_Inventory!B62 -> pass | E4: CFO, transformation office, board
A5: (R2) consistency | B5: draw 138 + buffer 187 = 325 on 270 of cash | C5: 122 + 17 = 139; 131 unclaimed | D5: =IF(R2_Consistency!B36="yes","pass","fail") -> pass | E5: transformation office, treasury, board
A6: (R3) panel | B6: core certified: spectral radius 0.80 | C6: passes; a phase-two link at 0.40 would fail (1.02) | D6: =IF(AND(D5="pass",R3_Panel!B11="yes"),"pass","fail") -> pass | E6: risk office, Digital, Industrial Systems
A7: (R4) horizon | B7: breach odds 24.6% against 5% | C7: 5.0% with the $10.4 million package | D7: =IF(AND(D5="pass",R4_Horizon!B23<=Appetite),"pass","fail") -> pass | E7: board, CFO, transformation office
A9: Gates passing now | B9: =COUNTIF(D4:D7,"pass") -> 4 | C9: (R1)-(R4) pass
A10: GEOP-ready for the program as approved? | B10: =IF(B9=4,"yes","no") -> yes | C10: the four artifacts on file
A11: Passes thinner than their readings | B11: =COUNTIF(R4_Horizon!D39:D42,"weaker than the reading") -> 2 | C11: capability and strategic risk
A12: After Chapter 8 | B12: (R1), (R2) and (R4) failed; by Theorem 16.4(iii) a failure at (R2) is one at (R3)
A14: Work order | B14: Owner
A15: tighten the capability survey, or protect five points of margin | B15: human-resources and engineering offices
A16: narrow the band of the risk reading, or buy margin at the month-11 peak | B16: risk office; the plan
A17: declare the phase-two link and return to (R3) before it is optimized | B17: risk office, Digital, Industrial Systems
A19: Appendix 16.A: no gate implies the next, none can be dropped | B19: Value | C19: Reading
A20: (R2): the board's floor on cash | B20: 350 | C20: x >= 350
A21: (R2): the payout policy's cap on cash | B21: 300 | C21: x <= 300
A22: (R2): some cash level keeps both? | B22: =IF(B20<=B21,"yes","no: the region is empty; (R3), (R4) fail too") -> no: the region is empty; (R3), (R4) fail too
A23: (R4): Chapter 14's runway, cash above the floor | B23: 120
A24: (R4): burn a quarter | B24: 50
A25: (R4): largest cut a quarter | B25: 10
A27: Quarter | B27: Cash above the floor | C27: Burn, cut as fast as allowed
A28: 0 | B28: =B23 -> 120 | C28: =B24 -> 50
A29: 1 | B29: =B28-C28 -> 70 | C29: =MAX(C28-$B$25,0) -> 40
A30: 2 | B30: =B29-C29 -> 30 | C30: =MAX(C29-$B$25,0) -> 30
A31: 3 | B31: =B30-C30 -> 0 | C31: =MAX(C30-$B$25,0) -> 20
A32: 4 | B32: =B31-C31 -> -20 | C32: =MAX(C31-$B$25,0) -> 10
A34: Cash in quarter 4, at most | B34: =B32 -> -20 | C34: 120 - (50 + 40 + 30 + 20) = -20
A35: The artifact: quarters the commitments can be kept | B35: =COUNTIF(B29:B32,">=0") -> 3

Sheet Dependencies
A1: The dependency navigator: the longest chain below each result, and what Theorem 16.4 rests on (AXIOM Lab 1.16, step 4; Theorem 16.5(i); Online Appendix 16.B.1)
A2: Volume I's numbered results in an order where every cited result comes before the results citing it (column A); the matrix to the right has a 1 where the column's result cites the row's (engine data, read from the book's source by its citation script). Longest chain: 1 + the longest among the results cited.
K4: rests-on, by column: | L4: =$H$6 -> 0 | M4: =$H$7 -> 0 | N4: =$H$8 -> 0 | O4: =$H$9 -> 0 | P4: =$H$10 -> 0 | Q4: =$H$11 -> 1 | R4: =$H$12 -> 1 | S4: =$H$13 -> 0 | T4: =$H$14 -> 0 | U4: =$H$15 -> 0 | V4: =$H$16 -> 0 | W4: =$H$17 -> 1 | X4: =$H$18 -> 1 | Y4: =$H$19 -> 0 | Z4: =$H$20 -> 1 | AA4: =$H$21 -> 0 | AB4: =$H$22 -> 1 | AC4: =$H$23 -> 0 | AD4: =$H$24 -> 1 | AE4: =$H$25 -> 0 | AF4: =$H$26 -> 0 | AG4: =$H$27 -> 1 | AH4: =$H$28 -> 0 | AI4: =$H$29 -> 0 | AJ4: =$H$30 -> 0 | AK4: =$H$31 -> 1 | AL4: =$H$32 -> 0 | AM4: =$H$33 -> 1 | AN4: =$H$34 -> 1 | AO4: =$H$35 -> 1 | AP4: =$H$36 -> 1 | AQ4: =$H$37 -> 1 | AR4: =$H$38 -> 0 | AS4: =$H$39 -> 0 | AT4: =$H$40 -> 1 | AU4: =$H$41 -> 1 | AV4: =$H$42 -> 0 | AW4: =$H$43 -> 0 | AX4: =$H$44 -> 0 | AY4: =$H$45 -> 0 | AZ4: =$H$46 -> 0 | BA4: =$H$47 -> 0 | BB4: =$H$48 -> 0 | BC4: =$H$49 -> 1 | BD4: =$H$50 -> 1 | BE4: =$H$51 -> 1 | BF4: =$H$52 -> 1 | BG4: =$H$53 -> 1 | BH4: =$H$54 -> 1 | BI4: =$H$55 -> 1 | BJ4: =$H$56 -> 0 | BK4: =$H$57 -> 0 | BL4: =$H$58 -> 0 | BM4: =$H$59 -> 0 | BN4: =$H$60 -> 0 | BO4: =$H$61 -> 1 | BP4: =$H$62 -> 0 | BQ4: =$H$63 -> 1 | BR4: =$H$64 -> 1 | BS4: =$H$65 -> 0 | BT4: =$H$66 -> 0 | BU4: =$H$67 -> 0 | BV4: =$H$68 -> 1 | BW4: =$H$69 -> 0 | BX4: =$H$70 -> 0 | BY4: =$H$71 -> 0 | BZ4: =$H$72 -> 0 | CA4: =$H$73 -> 0 | CB4: =$H$74 -> 0 | CC4: =$H$75 -> 0 | CD4: =$H$76 -> 0 | CE4: =$H$77 -> 0 | CF4: =$H$78 -> 0 | CG4: =$H$79 -> 1 | CH4: =$H$80 -> 0 | CI4: =$H$81 -> 1 | CJ4: =$H$82 -> 1 | CK4: =$H$83 -> 1 | CL4: =$H$84 -> 0 | CM4: =$H$85 -> 0 | CN4: =$H$86 -> 0 | CO4: =$H$87 -> 0 | CP4: =$H$88 -> 0 | CQ4: =$H$89 -> 0 | CR4: =$H$90 -> 0 | CS4: =$H$91 -> 0 | CT4: =$H$92 -> 0 | CU4: =$H$93 -> 0 | CV4: =$H$94 -> 0 | CW4: =$H$95 -> 0 | CX4: =$H$96 -> 0 | CY4: =$H$97 -> 1 | CZ4: =$H$98 -> 0 | DA4: =$H$99 -> 0 | DB4: =$H$100 -> 1 | DC4: =$H$101 -> 0 | DD4: =$H$102 -> 1 | DE4: =$H$103 -> 0 | DF4: =$H$104 -> 1 | DG4: =$H$105 -> 1 | DH4: =$H$106 -> 1 | DI4: =$H$107 -> 0 | DJ4: =$H$108 -> 0 | DK4: =$H$109 -> 0 | DL4: =$H$110 -> 0 | DM4: =$H$111 -> 0 | DN4: =$H$112 -> 0 | DO4: =$H$113 -> 0 | DP4: =$H$114 -> 0 | DQ4: =$H$115 -> 0 | DR4: =$H$116 -> 0 | DS4: =$H$117 -> 0 | DT4: =$H$118 -> 0 | DU4: =$H$119 -> 0 | DV4: =$H$120 -> 0 | DW4: =$H$121 -> 1 | DX4: =$H$122 -> 1 | DY4: =$H$123 -> 1 | DZ4: =$H$124 -> 0 | EA4: =$H$125 -> 0 | EB4: =$H$126 -> 0 | EC4: =$H$127 -> 0 | ED4: =$H$128 -> 0 | EE4: =$H$129 -> 0 | EF4: =$H$130 -> 0 | EG4: =$H$131 -> 1 | EH4: =$H$132 -> 1 | EI4: =$H$133 -> 1 | EJ4: =$H$134 -> 0 | EK4: =$H$135 -> 0 | EL4: =$H$136 -> 0 | EM4: =$H$137 -> 0 | EN4: =$H$138 -> 0 | EO4: =$H$139 -> 0 | EP4: =$H$140 -> 1 | EQ4: =$H$141 -> 1 | ER4: =$H$142 -> 0 | ES4: =$H$143 -> 0 | ET4: =$H$144 -> 0 | EU4: =$H$145 -> 0 | EV4: =$H$146 -> 1 | EW4: =$H$147 -> 0 | EX4: =$H$148 -> 0 | EY4: =$H$149 -> 0 | EZ4: =$H$150 -> 0 | FA4: =$H$151 -> 1 | FB4: =$H$152 -> 0 | FC4: =$H$153 -> 0 | FD4: =$H$154 -> 0 | FE4: =$H$155 -> 0 | FF4: =$H$156 -> 0 | FG4: =$H$157 -> 0 | FH4: =$H$158 -> 0 | FI4: =$H$159 -> 1 | FJ4: =$H$160 -> 0 | FK4: =$H$161 -> 1 | FL4: =$H$162 -> 0 | FM4: =$H$163 -> 0 | FN4: =$H$164 -> 0 | FO4: =$H$165 -> 1 | FP4: =$H$166 -> 1 | FQ4: =$H$167 -> 0 | FR4: =$H$168 -> 0 | FS4: =$H$169 -> 0 | FT4: =$H$170 -> 0 | FU4: =$H$171 -> 0 | FV4: =$H$172 -> 0 | FW4: =$H$173 -> 1 | FX4: =$H$174 -> 1 | FY4: =$H$175 -> 0 | FZ4: =$H$176 -> 1 | GA4: =$H$177 -> 1 | GB4: =$H$178 -> 0 | GC4: =$H$179 -> 1 | GD4: =$H$180 -> 0 | GE4: =$H$181 -> 0 | GF4: =$H$182 -> 0 | GG4: =$H$183 -> 1 | GH4: =$H$184 -> 0 | GI4: =$H$185 -> 1 | GJ4: =$H$186 -> 1 | GK4: =$H$187 -> 0 | GL4: =$H$188 -> 0 | GM4: =$H$189 -> 1 | GN4: =$H$190 -> 0 | GO4: =$H$191 -> 1 | GP4: =$H$192 -> 1 | GQ4: =$H$193 -> 0 | GR4: =$H$194 -> 0 | GS4: =$H$195 -> 1 | GT4: =$H$196 -> 1 | GU4: =$H$197 -> 0 | GV4: =$H$198 -> 1 | GW4: =$H$199 -> 0 | GX4: =$H$200 -> 0 | GY4: =$H$201 -> 1 | GZ4: =$H$202 -> 1 | HA4: =$H$203 -> 0 | HB4: =$H$204 -> 1 | HC4: =$H$205 -> 1 | HD4: =$H$206 -> 1 | HE4: =$H$207 -> 0 | HF4: =$H$208 -> 0 | HG4: =$H$209 -> 0 | HH4: =$H$210 -> 0 | HI4: =$H$211 -> 1 | HJ4: =$H$212 -> 0 | HK4: =$H$213 -> 0 | HL4: =$H$214 -> 0 | HM4: =$H$215 -> 0 | HN4: =$H$216 -> 0
A5: Result | B5: Name | C5: Chapter | D5: Cites | E5: Cited by | F5: Longest chain below | G5: Chains that long | H5: Theorem 16.4 rests on it | L5: P1.1 | M5: P1.2 | N5: S1.B.1 | O5: S1.B.2 | P5: P2.1 | Q5: T2.1 | R5: P2.2 | S5: T2.2 | T5: P2.3 | U5: R2.B.1 | V5: C2.B.2 | W5: P3.1 | X5: T3.1 | Y5: P3.2 | Z5: T3.2 | AA5: P3.3 | AB5: T3.3 | AC5: R3.B.1 | AD5: T4.1 | AE5: P4.1 | AF5: P4.2 | AG5: T4.2 | AH5: P4.3 | AI5: T4.3 | AJ5: P4.B.1 | AK5: P5.1 | AL5: T5.1 | AM5: P5.2 | AN5: T5.2 | AO5: P5.3 | AP5: T5.4 | AQ5: T5.3 | AR5: P5.4 | AS5: P5.5 | AT5: T5.5 | AU5: E5.B.1 | AV5: E5.B.2 | AW5: R5.B.3 | AX5: E5.B.4 | AY5: R5.B.5 | AZ5: E5.B.6 | BA5: E5.B.7 | BB5: P6.1 | BC5: T6.1 | BD5: P6.2 | BE5: P6.3 | BF5: T6.3 | BG5: P6.4 | BH5: T6.2 | BI5: T6.4 | BJ5: P6.5 | BK5: T6.5 | BL5: E6.B.1 | BM5: R6.B.2 | BN5: R6.B.3 | BO5: T7.1 | BP5: P7.1 | BQ5: T7.2 | BR5: P7.2 | BS5: P7.3 | BT5: P7.4 | BU5: T7.3 | BV5: T7.4 | BW5: P7.5 | BX5: T7.5 | BY5: E7.B.1 | BZ5: E7.B.2 | CA5: E7.B.3 | CB5: E7.B.4 | CC5: L7.B.5 | CD5: P7.B.6 | CE5: E7.B.7 | CF5: R7.B.8 | CG5: L8.1 | CH5: P8.1 | CI5: T8.1 | CJ5: P8.2 | CK5: T8.2 | CL5: P8.3 | CM5: T8.3 | CN5: P8.4 | CO5: P8.5 | CP5: T8.5 | CQ5: T8.4 | CR5: E8.B.1 | CS5: E8.B.2 | CT5: E8.B.3 | CU5: R8.B.4 | CV5: E8.B.5 | CW5: E8.B.6 | CX5: E8.B.7 | CY5: T9.1 | CZ5: P9.1 | DA5: P9.2 | DB5: T9.2 | DC5: P9.3 | DD5: T9.3 | DE5: P9.4 | DF5: T9.4 | DG5: P9.5 | DH5: T9.5 | DI5: P9.6 | DJ5: E9.B.1 | DK5: P9.B.2 | DL5: P9.B.3 | DM5: P9.B.4 | DN5: E9.B.5 | DO5: P9.B.6 | DP5: E9.B.7 | DQ5: P10.1 | DR5: P10.2 | DS5: T10.2 | DT5: P10.3 | DU5: T10.3 | DV5: P10.4 | DW5: T10.4 | DX5: T10.5 | DY5: T10.1 | DZ5: P10.5 | EA5: P10.B.1 | EB5: P10.B.2 | EC5: E10.B.3 | ED5: E10.B.4 | EE5: P10.B.5 | EF5: E10.B.6 | EG5: P11.1 | EH5: T11.1 | EI5: T11.2 | EJ5: P11.3 | EK5: T11.3 | EL5: T11.5 | EM5: P11.B.1 | EN5: E11.B.2 | EO5: E11.B.3 | EP5: P11.B.4 | EQ5: T11.4 | ER5: P11.2 | ES5: E11.B.5 | ET5: E11.B.6 | EU5: P12.1 | EV5: T12.1 | EW5: P12.2 | EX5: T12.2 | EY5: T12.3 | EZ5: T12.4 | FA5: T12.5 | FB5: P12.B.1 | FC5: E12.B.2 | FD5: P12.B.3 | FE5: E12.B.4 | FF5: E12.B.5 | FG5: E12.B.6 | FH5: P13.1 | FI5: T13.1 | FJ5: P13.2 | FK5: T13.3 | FL5: P13.3 | FM5: P13.4 | FN5: P13.5 | FO5: T13.5 | FP5: T13.2 | FQ5: T13.4 | FR5: P13.B.1 | FS5: E13.B.2 | FT5: E13.B.3 | FU5: E13.B.4 | FV5: P14.2 | FW5: T14.2 | FX5: T14.3 | FY5: P14.4 | FZ5: T14.4 | GA5: P14.3 | GB5: P14.5 | GC5: T14.5 | GD5: T14.7 | GE5: T14.8 | GF5: P14.B.1 | GG5: E14.B.2 | GH5: P14.1 | GI5: T14.1 | GJ5: T14.6 | GK5: E14.B.3 | GL5: P15.1 | GM5: T15.1 | GN5: P15.2 | GO5: T15.3 | GP5: T15.2 | GQ5: P15.3 | GR5: P15.4 | GS5: P15.5 | GT5: T15.5 | GU5: P15.6 | GV5: T15.6 | GW5: P15.9 | GX5: E15.B.1 | GY5: E15.B.2 | GZ5: T15.4 | HA5: E15.B.3 | HB5: E15.B.4 | HC5: P15.7 | HD5: T15.7 | HE5: P15.8 | HF5: P16.1 | HG5: T16.2 | HH5: T16.3 | HI5: T16.4 | HJ5: E16.B.1 | HK5: T16.5 | HL5: E16.B.2 | HM5: E16.B.3 | HN5: T16.1
A6: P1.1 | B6: Proposition 1.1 | C6: =VALUE(MID(A6,2,FIND(".",A6)-2)) -> 1 | D6: =COUNTIF(L$6:L$216,1) -> 0 | E6: =COUNTIF($L6:$HN6,1) -> 0 | F6: 0 | G6: 1 | H6: =IF($A6="T16.4",1,IF(COUNTIFS(M6:HN6,1,M$4:HN$4,1)>0,1,0)) -> 0
A7: P1.2 | B7: Proposition 1.2 | C7: =VALUE(MID(A7,2,FIND(".",A7)-2)) -> 1 | D7: =COUNTIF(M$6:M$216,1) -> 0 | E7: =COUNTIF($L7:$HN7,1) -> 0 | F7: =IF(COUNTIF(M$6:M6,1)=0,0,1+_xlfn.MAXIFS($F$6:$F6,M$6:M6,1)) -> 0 | G7: =IF(F7=0,1,SUMIFS($G$6:$G6,M$6:M6,1,$F$6:$F6,F7-1)) -> 1 | H7: =IF($A7="T16.4",1,IF(COUNTIFS(N7:HN7,1,N$4:HN$4,1)>0,1,0)) -> 0
A8: S1.B.1 | B8: Result 1.B.1 | C8: =VALUE(MID(A8,2,FIND(".",A8)-2)) -> 1 | D8: =COUNTIF(N$6:N$216,1) -> 0 | E8: =COUNTIF($L8:$HN8,1) -> 0 | F8: =IF(COUNTIF(N$6:N7,1)=0,0,1+_xlfn.MAXIFS($F$6:$F7,N$6:N7,1)) -> 0 | G8: =IF(F8=0,1,SUMIFS($G$6:$G7,N$6:N7,1,$F$6:$F7,F8-1)) -> 1 | H8: =IF($A8="T16.4",1,IF(COUNTIFS(O8:HN8,1,O$4:HN$4,1)>0,1,0)) -> 0
A9: S1.B.2 | B9: Result 1.B.2 | C9: =VALUE(MID(A9,2,FIND(".",A9)-2)) -> 1 | D9: =COUNTIF(O$6:O$216,1) -> 0 | E9: =COUNTIF($L9:$HN9,1) -> 0 | F9: =IF(COUNTIF(O$6:O8,1)=0,0,1+_xlfn.MAXIFS($F$6:$F8,O$6:O8,1)) -> 0 | G9: =IF(F9=0,1,SUMIFS($G$6:$G8,O$6:O8,1,$F$6:$F8,F9-1)) -> 1 | H9: =IF($A9="T16.4",1,IF(COUNTIFS(P9:HN9,1,P$4:HN$4,1)>0,1,0)) -> 0
A10: P2.1 | B10: Proposition 2.1 | C10: =VALUE(MID(A10,2,FIND(".",A10)-2)) -> 2 | D10: =COUNTIF(P$6:P$216,1) -> 0 | E10: =COUNTIF($L10:$HN10,1) -> 0 | F10: =IF(COUNTIF(P$6:P9,1)=0,0,1+_xlfn.MAXIFS($F$6:$F9,P$6:P9,1)) -> 0 | G10: =IF(F10=0,1,SUMIFS($G$6:$G9,P$6:P9,1,$F$6:$F9,F10-1)) -> 1 | H10: =IF($A10="T16.4",1,IF(COUNTIFS(Q10:HN10,1,Q$4:HN$4,1)>0,1,0)) -> 0
A11: T2.1 | B11: Theorem 2.1 | C11: =VALUE(MID(A11,2,FIND(".",A11)-2)) -> 2 | D11: =COUNTIF(Q$6:Q$216,1) -> 0 | E11: =COUNTIF($L11:$HN11,1) -> 8 | F11: =IF(COUNTIF(Q$6:Q10,1)=0,0,1+_xlfn.MAXIFS($F$6:$F10,Q$6:Q10,1)) -> 0 | G11: =IF(F11=0,1,SUMIFS($G$6:$G10,Q$6:Q10,1,$F$6:$F10,F11-1)) -> 1 | H11: =IF($A11="T16.4",1,IF(COUNTIFS(R11:HN11,1,R$4:HN$4,1)>0,1,0)) -> 1 | R11: 1 | T11: 1 | AI11: 1 | AL11: 1 | AQ11: 1 | BO11: 1 | CI11: 1 | CY11: 1
A12: P2.2 | B12: Proposition 2.2 | C12: =VALUE(MID(A12,2,FIND(".",A12)-2)) -> 2 | D12: =COUNTIF(R$6:R$216,1) -> 1 | E12: =COUNTIF($L12:$HN12,1) -> 4 | F12: =IF(COUNTIF(R$6:R11,1)=0,0,1+_xlfn.MAXIFS($F$6:$F11,R$6:R11,1)) -> 1 | G12: =IF(F12=0,1,SUMIFS($G$6:$G11,R$6:R11,1,$F$6:$F11,F12-1)) -> 1 | H12: =IF($A12="T16.4",1,IF(COUNTIFS(S12:HN12,1,S$4:HN$4,1)>0,1,0)) -> 1 | U12: 1 | BC12: 1 | BW12: 1 | CI12: 1
A13: T2.2 | B13: Theorem 2.2 | C13: =VALUE(MID(A13,2,FIND(".",A13)-2)) -> 2 | D13: =COUNTIF(S$6:S$216,1) -> 0 | E13: =COUNTIF($L13:$HN13,1) -> 1 | F13: =IF(COUNTIF(S$6:S12,1)=0,0,1+_xlfn.MAXIFS($F$6:$F12,S$6:S12,1)) -> 0 | G13: =IF(F13=0,1,SUMIFS($G$6:$G12,S$6:S12,1,$F$6:$F12,F13-1)) -> 1 | H13: =IF($A13="T16.4",1,IF(COUNTIFS(T13:HN13,1,T$4:HN$4,1)>0,1,0)) -> 0 | V13: 1
A14: P2.3 | B14: Proposition 2.3 | C14: =VALUE(MID(A14,2,FIND(".",A14)-2)) -> 2 | D14: =COUNTIF(T$6:T$216,1) -> 1 | E14: =COUNTIF($L14:$HN14,1) -> 1 | F14: =IF(COUNTIF(T$6:T13,1)=0,0,1+_xlfn.MAXIFS($F$6:$F13,T$6:T13,1)) -> 1 | G14: =IF(F14=0,1,SUMIFS($G$6:$G13,T$6:T13,1,$F$6:$F13,F14-1)) -> 1 | H14: =IF($A14="T16.4",1,IF(COUNTIFS(U14:HN14,1,U$4:HN$4,1)>0,1,0)) -> 0 | CF14: 1
A15: R2.B.1 | B15: Remark 2.B.1 | C15: =VALUE(MID(A15,2,FIND(".",A15)-2)) -> 2 | D15: =COUNTIF(U$6:U$216,1) -> 1 | E15: =COUNTIF($L15:$HN15,1) -> 0 | F15: =IF(COUNTIF(U$6:U14,1)=0,0,1+_xlfn.MAXIFS($F$6:$F14,U$6:U14,1)) -> 2 | G15: =IF(F15=0,1,SUMIFS($G$6:$G14,U$6:U14,1,$F$6:$F14,F15-1)) -> 1 | H15: =IF($A15="T16.4",1,IF(COUNTIFS(V15:HN15,1,V$4:HN$4,1)>0,1,0)) -> 0
A16: C2.B.2 | B16: Corollary 2.B.2 | C16: =VALUE(MID(A16,2,FIND(".",A16)-2)) -> 2 | D16: =COUNTIF(V$6:V$216,1) -> 1 | E16: =COUNTIF($L16:$HN16,1) -> 0 | F16: =IF(COUNTIF(V$6:V15,1)=0,0,1+_xlfn.MAXIFS($F$6:$F15,V$6:V15,1)) -> 1 | G16: =IF(F16=0,1,SUMIFS($G$6:$G15,V$6:V15,1,$F$6:$F15,F16-1)) -> 1 | H16: =IF($A16="T16.4",1,IF(COUNTIFS(W16:HN16,1,W$4:HN$4,1)>0,1,0)) -> 0
A17: P3.1 | B17: Proposition 3.1 | C17: =VALUE(MID(A17,2,FIND(".",A17)-2)) -> 3 | D17: =COUNTIF(W$6:W$216,1) -> 0 | E17: =COUNTIF($L17:$HN17,1) -> 6 | F17: =IF(COUNTIF(W$6:W16,1)=0,0,1+_xlfn.MAXIFS($F$6:$F16,W$6:W16,1)) -> 0 | G17: =IF(F17=0,1,SUMIFS($G$6:$G16,W$6:W16,1,$F$6:$F16,F17-1)) -> 1 | H17: =IF($A17="T16.4",1,IF(COUNTIFS(X17:HN17,1,X$4:HN$4,1)>0,1,0)) -> 1 | Z17: 1 | AH17: 1 | AO17: 1 | BD17: 1 | BG17: 1 | BH17: 1
A18: T3.1 | B18: Theorem 3.1 | C18: =VALUE(MID(A18,2,FIND(".",A18)-2)) -> 3 | D18: =COUNTIF(X$6:X$216,1) -> 0 | E18: =COUNTIF($L18:$HN18,1) -> 2 | F18: =IF(COUNTIF(X$6:X17,1)=0,0,1+_xlfn.MAXIFS($F$6:$F17,X$6:X17,1)) -> 0 | G18: =IF(F18=0,1,SUMIFS($G$6:$G17,X$6:X17,1,$F$6:$F17,F18-1)) -> 1 | H18: =IF($A18="T16.4",1,IF(COUNTIFS(Y18:HN18,1,Y$4:HN$4,1)>0,1,0)) -> 1 | FX18: 1 | GJ18: 1
A19: P3.2 | B19: Proposition 3.2 | C19: =VALUE(MID(A19,2,FIND(".",A19)-2)) -> 3 | D19: =COUNTIF(Y$6:Y$216,1) -> 0 | E19: =COUNTIF($L19:$HN19,1) -> 0 | F19: =IF(COUNTIF(Y$6:Y18,1)=0,0,1+_xlfn.MAXIFS($F$6:$F18,Y$6:Y18,1)) -> 0 | G19: =IF(F19=0,1,SUMIFS($G$6:$G18,Y$6:Y18,1,$F$6:$F18,F19-1)) -> 1 | H19: =IF($A19="T16.4",1,IF(COUNTIFS(Z19:HN19,1,Z$4:HN$4,1)>0,1,0)) -> 0
A20: T3.2 | B20: Theorem 3.2 | C20: =VALUE(MID(A20,2,FIND(".",A20)-2)) -> 3 | D20: =COUNTIF(Z$6:Z$216,1) -> 1 | E20: =COUNTIF($L20:$HN20,1) -> 1 | F20: =IF(COUNTIF(Z$6:Z19,1)=0,0,1+_xlfn.MAXIFS($F$6:$F19,Z$6:Z19,1)) -> 1 | G20: =IF(F20=0,1,SUMIFS($G$6:$G19,Z$6:Z19,1,$F$6:$F19,F20-1)) -> 1 | H20: =IF($A20="T16.4",1,IF(COUNTIFS(AA20:HN20,1,AA$4:HN$4,1)>0,1,0)) -> 1 | BH20: 1
A21: P3.3 | B21: Proposition 3.3 | C21: =VALUE(MID(A21,2,FIND(".",A21)-2)) -> 3 | D21: =COUNTIF(AA$6:AA$216,1) -> 0 | E21: =COUNTIF($L21:$HN21,1) -> 0 | F21: =IF(COUNTIF(AA$6:AA20,1)=0,0,1+_xlfn.MAXIFS($F$6:$F20,AA$6:AA20,1)) -> 0 | G21: =IF(F21=0,1,SUMIFS($G$6:$G20,AA$6:AA20,1,$F$6:$F20,F21-1)) -> 1 | H21: =IF($A21="T16.4",1,IF(COUNTIFS(AB21:HN21,1,AB$4:HN$4,1)>0,1,0)) -> 0
A22: T3.3 | B22: Theorem 3.3 | C22: =VALUE(MID(A22,2,FIND(".",A22)-2)) -> 3 | D22: =COUNTIF(AB$6:AB$216,1) -> 0 | E22: =COUNTIF($L22:$HN22,1) -> 3 | F22: =IF(COUNTIF(AB$6:AB21,1)=0,0,1+_xlfn.MAXIFS($F$6:$F21,AB$6:AB21,1)) -> 0 | G22: =IF(F22=0,1,SUMIFS($G$6:$G21,AB$6:AB21,1,$F$6:$F21,F22-1)) -> 1 | H22: =IF($A22="T16.4",1,IF(COUNTIFS(AC22:HN22,1,AC$4:HN$4,1)>0,1,0)) -> 1 | AD22: 1 | AM22: 1 | AN22: 1
A23: R3.B.1 | B23: Remark 3.B.1 | C23: =VALUE(MID(A23,2,FIND(".",A23)-2)) -> 3 | D23: =COUNTIF(AC$6:AC$216,1) -> 0 | E23: =COUNTIF($L23:$HN23,1) -> 0 | F23: =IF(COUNTIF(AC$6:AC22,1)=0,0,1+_xlfn.MAXIFS($F$6:$F22,AC$6:AC22,1)) -> 0 | G23: =IF(F23=0,1,SUMIFS($G$6:$G22,AC$6:AC22,1,$F$6:$F22,F23-1)) -> 1 | H23: =IF($A23="T16.4",1,IF(COUNTIFS(AD23:HN23,1,AD$4:HN$4,1)>0,1,0)) -> 0
A24: T4.1 | B24: Theorem 4.1 | C24: =VALUE(MID(A24,2,FIND(".",A24)-2)) -> 4 | D24: =COUNTIF(AD$6:AD$216,1) -> 1 | E24: =COUNTIF($L24:$HN24,1) -> 3 | F24: =IF(COUNTIF(AD$6:AD23,1)=0,0,1+_xlfn.MAXIFS($F$6:$F23,AD$6:AD23,1)) -> 1 | G24: =IF(F24=0,1,SUMIFS($G$6:$G23,AD$6:AD23,1,$F$6:$F23,F24-1)) -> 1 | H24: =IF($A24="T16.4",1,IF(COUNTIFS(AE24:HN24,1,AE$4:HN$4,1)>0,1,0)) -> 1 | AE24: 1 | DH24: 1 | HG24: 1
A25: P4.1 | B25: Proposition 4.1 | C25: =VALUE(MID(A25,2,FIND(".",A25)-2)) -> 4 | D25: =COUNTIF(AE$6:AE$216,1) -> 1 | E25: =COUNTIF($L25:$HN25,1) -> 0 | F25: =IF(COUNTIF(AE$6:AE24,1)=0,0,1+_xlfn.MAXIFS($F$6:$F24,AE$6:AE24,1)) -> 2 | G25: =IF(F25=0,1,SUMIFS($G$6:$G24,AE$6:AE24,1,$F$6:$F24,F25-1)) -> 1 | H25: =IF($A25="T16.4",1,IF(COUNTIFS(AF25:HN25,1,AF$4:HN$4,1)>0,1,0)) -> 0
A26: P4.2 | B26: Proposition 4.2 | C26: =VALUE(MID(A26,2,FIND(".",A26)-2)) -> 4 | D26: =COUNTIF(AF$6:AF$216,1) -> 0 | E26: =COUNTIF($L26:$HN26,1) -> 0 | F26: =IF(COUNTIF(AF$6:AF25,1)=0,0,1+_xlfn.MAXIFS($F$6:$F25,AF$6:AF25,1)) -> 0 | G26: =IF(F26=0,1,SUMIFS($G$6:$G25,AF$6:AF25,1,$F$6:$F25,F26-1)) -> 1 | H26: =IF($A26="T16.4",1,IF(COUNTIFS(AG26:HN26,1,AG$4:HN$4,1)>0,1,0)) -> 0
A27: T4.2 | B27: Theorem 4.2 | C27: =VALUE(MID(A27,2,FIND(".",A27)-2)) -> 4 | D27: =COUNTIF(AG$6:AG$216,1) -> 0 | E27: =COUNTIF($L27:$HN27,1) -> 5 | F27: =IF(COUNTIF(AG$6:AG26,1)=0,0,1+_xlfn.MAXIFS($F$6:$F26,AG$6:AG26,1)) -> 0 | G27: =IF(F27=0,1,SUMIFS($G$6:$G26,AG$6:AG26,1,$F$6:$F26,F27-1)) -> 1 | H27: =IF($A27="T16.4",1,IF(COUNTIFS(AH27:HN27,1,AH$4:HN$4,1)>0,1,0)) -> 1 | DG27: 1 | DX27: 1 | EL27: 1 | FO27: 1 | FP27: 1
A28: P4.3 | B28: Proposition 4.3 | C28: =VALUE(MID(A28,2,FIND(".",A28)-2)) -> 4 | D28: =COUNTIF(AH$6:AH$216,1) -> 1 | E28: =COUNTIF($L28:$HN28,1) -> 0 | F28: =IF(COUNTIF(AH$6:AH27,1)=0,0,1+_xlfn.MAXIFS($F$6:$F27,AH$6:AH27,1)) -> 1 | G28: =IF(F28=0,1,SUMIFS($G$6:$G27,AH$6:AH27,1,$F$6:$F27,F28-1)) -> 1 | H28: =IF($A28="T16.4",1,IF(COUNTIFS(AI28:HN28,1,AI$4:HN$4,1)>0,1,0)) -> 0
A29: T4.3 | B29: Theorem 4.3 | C29: =VALUE(MID(A29,2,FIND(".",A29)-2)) -> 4 | D29: =COUNTIF(AI$6:AI$216,1) -> 1 | E29: =COUNTIF($L29:$HN29,1) -> 2 | F29: =IF(COUNTIF(AI$6:AI28,1)=0,0,1+_xlfn.MAXIFS($F$6:$F28,AI$6:AI28,1)) -> 1 | G29: =IF(F29=0,1,SUMIFS($G$6:$G28,AI$6:AI28,1,$F$6:$F28,F29-1)) -> 1 | H29: =IF($A29="T16.4",1,IF(COUNTIFS(AJ29:HN29,1,AJ$4:HN$4,1)>0,1,0)) -> 0 | CH29: 1 | HF29: 1
A30: P4.B.1 | B30: Proposition 4.B.1 | C30: =VALUE(MID(A30,2,FIND(".",A30)-2)) -> 4 | D30: =COUNTIF(AJ$6:AJ$216,1) -> 0 | E30: =COUNTIF($L30:$HN30,1) -> 0 | F30: =IF(COUNTIF(AJ$6:AJ29,1)=0,0,1+_xlfn.MAXIFS($F$6:$F29,AJ$6:AJ29,1)) -> 0 | G30: =IF(F30=0,1,SUMIFS($G$6:$G29,AJ$6:AJ29,1,$F$6:$F29,F30-1)) -> 1 | H30: =IF($A30="T16.4",1,IF(COUNTIFS(AK30:HN30,1,AK$4:HN$4,1)>0,1,0)) -> 0
A31: P5.1 | B31: Proposition 5.1 | C31: =VALUE(MID(A31,2,FIND(".",A31)-2)) -> 5 | D31: =COUNTIF(AK$6:AK$216,1) -> 0 | E31: =COUNTIF($L31:$HN31,1) -> 1 | F31: =IF(COUNTIF(AK$6:AK30,1)=0,0,1+_xlfn.MAXIFS($F$6:$F30,AK$6:AK30,1)) -> 0 | G31: =IF(F31=0,1,SUMIFS($G$6:$G30,AK$6:AK30,1,$F$6:$F30,F31-1)) -> 1 | H31: =IF($A31="T16.4",1,IF(COUNTIFS(AL31:HN31,1,AL$4:HN$4,1)>0,1,0)) -> 1 | AM31: 1
A32: T5.1 | B32: Theorem 5.1 | C32: =VALUE(MID(A32,2,FIND(".",A32)-2)) -> 5 | D32: =COUNTIF(AL$6:AL$216,1) -> 1 | E32: =COUNTIF($L32:$HN32,1) -> 0 | F32: =IF(COUNTIF(AL$6:AL31,1)=0,0,1+_xlfn.MAXIFS($F$6:$F31,AL$6:AL31,1)) -> 1 | G32: =IF(F32=0,1,SUMIFS($G$6:$G31,AL$6:AL31,1,$F$6:$F31,F32-1)) -> 1 | H32: =IF($A32="T16.4",1,IF(COUNTIFS(AM32:HN32,1,AM$4:HN$4,1)>0,1,0)) -> 0
A33: P5.2 | B33: Proposition 5.2 | C33: =VALUE(MID(A33,2,FIND(".",A33)-2)) -> 5 | D33: =COUNTIF(AM$6:AM$216,1) -> 2 | E33: =COUNTIF($L33:$HN33,1) -> 1 | F33: =IF(COUNTIF(AM$6:AM32,1)=0,0,1+_xlfn.MAXIFS($F$6:$F32,AM$6:AM32,1)) -> 1 | G33: =IF(F33=0,1,SUMIFS($G$6:$G32,AM$6:AM32,1,$F$6:$F32,F33-1)) -> 2 | H33: =IF($A33="T16.4",1,IF(COUNTIFS(AN33:HN33,1,AN$4:HN$4,1)>0,1,0)) -> 1 | AN33: 1
A34: T5.2 | B34: Theorem 5.2 | C34: =VALUE(MID(A34,2,FIND(".",A34)-2)) -> 5 | D34: =COUNTIF(AN$6:AN$216,1) -> 2 | E34: =COUNTIF($L34:$HN34,1) -> 1 | F34: =IF(COUNTIF(AN$6:AN33,1)=0,0,1+_xlfn.MAXIFS($F$6:$F33,AN$6:AN33,1)) -> 2 | G34: =IF(F34=0,1,SUMIFS($G$6:$G33,AN$6:AN33,1,$F$6:$F33,F34-1)) -> 2 | H34: =IF($A34="T16.4",1,IF(COUNTIFS(AO34:HN34,1,AO$4:HN$4,1)>0,1,0)) -> 1 | CI34: 1
A35: P5.3 | B35: Proposition 5.3 | C35: =VALUE(MID(A35,2,FIND(".",A35)-2)) -> 5 | D35: =COUNTIF(AO$6:AO$216,1) -> 1 | E35: =COUNTIF($L35:$HN35,1) -> 3 | F35: =IF(COUNTIF(AO$6:AO34,1)=0,0,1+_xlfn.MAXIFS($F$6:$F34,AO$6:AO34,1)) -> 1 | G35: =IF(F35=0,1,SUMIFS($G$6:$G34,AO$6:AO34,1,$F$6:$F34,F35-1)) -> 1 | H35: =IF($A35="T16.4",1,IF(COUNTIFS(AP35:HN35,1,AP$4:HN$4,1)>0,1,0)) -> 1 | AR35: 1 | BO35: 1 | BU35: 1
A36: T5.4 | B36: Theorem 5.4 | C36: =VALUE(MID(A36,2,FIND(".",A36)-2)) -> 5 | D36: =COUNTIF(AP$6:AP$216,1) -> 0 | E36: =COUNTIF($L36:$HN36,1) -> 10 | F36: =IF(COUNTIF(AP$6:AP35,1)=0,0,1+_xlfn.MAXIFS($F$6:$F35,AP$6:AP35,1)) -> 0 | G36: =IF(F36=0,1,SUMIFS($G$6:$G35,AP$6:AP35,1,$F$6:$F35,F36-1)) -> 1 | H36: =IF($A36="T16.4",1,IF(COUNTIFS(AQ36:HN36,1,AQ$4:HN$4,1)>0,1,0)) -> 1 | AQ36: 1 | AX36: 1 | AZ36: 1 | BA36: 1 | BK36: 1 | BL36: 1 | BO36: 1 | GE36: 1 | GI36: 1 | GZ36: 1
A37: T5.3 | B37: Theorem 5.3 | C37: =VALUE(MID(A37,2,FIND(".",A37)-2)) -> 5 | D37: =COUNTIF(AQ$6:AQ$216,1) -> 2 | E37: =COUNTIF($L37:$HN37,1) -> 6 | F37: =IF(COUNTIF(AQ$6:AQ36,1)=0,0,1+_xlfn.MAXIFS($F$6:$F36,AQ$6:AQ36,1)) -> 1 | G37: =IF(F37=0,1,SUMIFS($G$6:$G36,AQ$6:AQ36,1,$F$6:$F36,F37-1)) -> 2 | H37: =IF($A37="T16.4",1,IF(COUNTIFS(AR37:HN37,1,AR$4:HN$4,1)>0,1,0)) -> 1 | AR37: 1 | AU37: 1 | BO37: 1 | BT37: 1 | CI37: 1 | GI37: 1
A38: P5.4 | B38: Proposition 5.4 | C38: =VALUE(MID(A38,2,FIND(".",A38)-2)) -> 5 | D38: =COUNTIF(AR$6:AR$216,1) -> 2 | E38: =COUNTIF($L38:$HN38,1) -> 0 | F38: =IF(COUNTIF(AR$6:AR37,1)=0,0,1+_xlfn.MAXIFS($F$6:$F37,AR$6:AR37,1)) -> 2 | G38: =IF(F38=0,1,SUMIFS($G$6:$G37,AR$6:AR37,1,$F$6:$F37,F38-1)) -> 3 | H38: =IF($A38="T16.4",1,IF(COUNTIFS(AS38:HN38,1,AS$4:HN$4,1)>0,1,0)) -> 0
A39: P5.5 | B39: Proposition 5.5 | C39: =VALUE(MID(A39,2,FIND(".",A39)-2)) -> 5 | D39: =COUNTIF(AS$6:AS$216,1) -> 0 | E39: =COUNTIF($L39:$HN39,1) -> 0 | F39: =IF(COUNTIF(AS$6:AS38,1)=0,0,1+_xlfn.MAXIFS($F$6:$F38,AS$6:AS38,1)) -> 0 | G39: =IF(F39=0,1,SUMIFS($G$6:$G38,AS$6:AS38,1,$F$6:$F38,F39-1)) -> 1 | H39: =IF($A39="T16.4",1,IF(COUNTIFS(AT39:HN39,1,AT$4:HN$4,1)>0,1,0)) -> 0
A40: T5.5 | B40: Theorem 5.5 | C40: =VALUE(MID(A40,2,FIND(".",A40)-2)) -> 5 | D40: =COUNTIF(AT$6:AT$216,1) -> 0 | E40: =COUNTIF($L40:$HN40,1) -> 3 | F40: =IF(COUNTIF(AT$6:AT39,1)=0,0,1+_xlfn.MAXIFS($F$6:$F39,AT$6:AT39,1)) -> 0 | G40: =IF(F40=0,1,SUMIFS($G$6:$G39,AT$6:AT39,1,$F$6:$F39,F40-1)) -> 1 | H40: =IF($A40="T16.4",1,IF(COUNTIFS(AU40:HN40,1,AU$4:HN$4,1)>0,1,0)) -> 1 | BF40: 1 | GC40: 1 | GH40: 1
A41: E5.B.1 | B41: Example 5.B.1 | C41: =VALUE(MID(A41,2,FIND(".",A41)-2)) -> 5 | D41: =COUNTIF(AU$6:AU$216,1) -> 1 | E41: =COUNTIF($L41:$HN41,1) -> 1 | F41: =IF(COUNTIF(AU$6:AU40,1)=0,0,1+_xlfn.MAXIFS($F$6:$F40,AU$6:AU40,1)) -> 2 | G41: =IF(F41=0,1,SUMIFS($G$6:$G40,AU$6:AU40,1,$F$6:$F40,F41-1)) -> 2 | H41: =IF($A41="T16.4",1,IF(COUNTIFS(AV41:HN41,1,AV$4:HN$4,1)>0,1,0)) -> 1 | BO41: 1
A42: E5.B.2 | B42: Example 5.B.2 | C42: =VALUE(MID(A42,2,FIND(".",A42)-2)) -> 5 | D42: =COUNTIF(AV$6:AV$216,1) -> 0 | E42: =COUNTIF($L42:$HN42,1) -> 0 | F42: =IF(COUNTIF(AV$6:AV41,1)=0,0,1+_xlfn.MAXIFS($F$6:$F41,AV$6:AV41,1)) -> 0 | G42: =IF(F42=0,1,SUMIFS($G$6:$G41,AV$6:AV41,1,$F$6:$F41,F42-1)) -> 1 | H42: =IF($A42="T16.4",1,IF(COUNTIFS(AW42:HN42,1,AW$4:HN$4,1)>0,1,0)) -> 0
A43: R5.B.3 | B43: Remark 5.B.3 | C43: =VALUE(MID(A43,2,FIND(".",A43)-2)) -> 5 | D43: =COUNTIF(AW$6:AW$216,1) -> 0 | E43: =COUNTIF($L43:$HN43,1) -> 0 | F43: =IF(COUNTIF(AW$6:AW42,1)=0,0,1+_xlfn.MAXIFS($F$6:$F42,AW$6:AW42,1)) -> 0 | G43: =IF(F43=0,1,SUMIFS($G$6:$G42,AW$6:AW42,1,$F$6:$F42,F43-1)) -> 1 | H43: =IF($A43="T16.4",1,IF(COUNTIFS(AX43:HN43,1,AX$4:HN$4,1)>0,1,0)) -> 0
A44: E5.B.4 | B44: Example 5.B.4 | C44: =VALUE(MID(A44,2,FIND(".",A44)-2)) -> 5 | D44: =COUNTIF(AX$6:AX$216,1) -> 1 | E44: =COUNTIF($L44:$HN44,1) -> 1 | F44: =IF(COUNTIF(AX$6:AX43,1)=0,0,1+_xlfn.MAXIFS($F$6:$F43,AX$6:AX43,1)) -> 1 | G44: =IF(F44=0,1,SUMIFS($G$6:$G43,AX$6:AX43,1,$F$6:$F43,F44-1)) -> 1 | H44: =IF($A44="T16.4",1,IF(COUNTIFS(AY44:HN44,1,AY$4:HN$4,1)>0,1,0)) -> 0 | AY44: 1
A45: R5.B.5 | B45: Remark 5.B.5 | C45: =VALUE(MID(A45,2,FIND(".",A45)-2)) -> 5 | D45: =COUNTIF(AY$6:AY$216,1) -> 1 | E45: =COUNTIF($L45:$HN45,1) -> 0 | F45: =IF(COUNTIF(AY$6:AY44,1)=0,0,1+_xlfn.MAXIFS($F$6:$F44,AY$6:AY44,1)) -> 2 | G45: =IF(F45=0,1,SUMIFS($G$6:$G44,AY$6:AY44,1,$F$6:$F44,F45-1)) -> 1 | H45: =IF($A45="T16.4",1,IF(COUNTIFS(AZ45:HN45,1,AZ$4:HN$4,1)>0,1,0)) -> 0
A46: E5.B.6 | B46: Example 5.B.6 | C46: =VALUE(MID(A46,2,FIND(".",A46)-2)) -> 5 | D46: =COUNTIF(AZ$6:AZ$216,1) -> 1 | E46: =COUNTIF($L46:$HN46,1) -> 0 | F46: =IF(COUNTIF(AZ$6:AZ45,1)=0,0,1+_xlfn.MAXIFS($F$6:$F45,AZ$6:AZ45,1)) -> 1 | G46: =IF(F46=0,1,SUMIFS($G$6:$G45,AZ$6:AZ45,1,$F$6:$F45,F46-1)) -> 1 | H46: =IF($A46="T16.4",1,IF(COUNTIFS(BA46:HN46,1,BA$4:HN$4,1)>0,1,0)) -> 0
A47: E5.B.7 | B47: Example 5.B.7 | C47: =VALUE(MID(A47,2,FIND(".",A47)-2)) -> 5 | D47: =COUNTIF(BA$6:BA$216,1) -> 1 | E47: =COUNTIF($L47:$HN47,1) -> 0 | F47: =IF(COUNTIF(BA$6:BA46,1)=0,0,1+_xlfn.MAXIFS($F$6:$F46,BA$6:BA46,1)) -> 1 | G47: =IF(F47=0,1,SUMIFS($G$6:$G46,BA$6:BA46,1,$F$6:$F46,F47-1)) -> 1 | H47: =IF($A47="T16.4",1,IF(COUNTIFS(BB47:HN47,1,BB$4:HN$4,1)>0,1,0)) -> 0
A48: P6.1 | B48: Proposition 6.1 | C48: =VALUE(MID(A48,2,FIND(".",A48)-2)) -> 6 | D48: =COUNTIF(BB$6:BB$216,1) -> 0 | E48: =COUNTIF($L48:$HN48,1) -> 0 | F48: =IF(COUNTIF(BB$6:BB47,1)=0,0,1+_xlfn.MAXIFS($F$6:$F47,BB$6:BB47,1)) -> 0 | G48: =IF(F48=0,1,SUMIFS($G$6:$G47,BB$6:BB47,1,$F$6:$F47,F48-1)) -> 1 | H48: =IF($A48="T16.4",1,IF(COUNTIFS(BC48:HN48,1,BC$4:HN$4,1)>0,1,0)) -> 0
A49: T6.1 | B49: Theorem 6.1 | C49: =VALUE(MID(A49,2,FIND(".",A49)-2)) -> 6 | D49: =COUNTIF(BC$6:BC$216,1) -> 1 | E49: =COUNTIF($L49:$HN49,1) -> 2 | F49: =IF(COUNTIF(BC$6:BC48,1)=0,0,1+_xlfn.MAXIFS($F$6:$F48,BC$6:BC48,1)) -> 2 | G49: =IF(F49=0,1,SUMIFS($G$6:$G48,BC$6:BC48,1,$F$6:$F48,F49-1)) -> 1 | H49: =IF($A49="T16.4",1,IF(COUNTIFS(BD49:HN49,1,BD$4:HN$4,1)>0,1,0)) -> 1 | BL49: 1 | FI49: 1
A50: P6.2 | B50: Proposition 6.2 | C50: =VALUE(MID(A50,2,FIND(".",A50)-2)) -> 6 | D50: =COUNTIF(BD$6:BD$216,1) -> 1 | E50: =COUNTIF($L50:$HN50,1) -> 4 | F50: =IF(COUNTIF(BD$6:BD49,1)=0,0,1+_xlfn.MAXIFS($F$6:$F49,BD$6:BD49,1)) -> 1 | G50: =IF(F50=0,1,SUMIFS($G$6:$G49,BD$6:BD49,1,$F$6:$F49,F50-1)) -> 1 | H50: =IF($A50="T16.4",1,IF(COUNTIFS(BE50:HN50,1,BE$4:HN$4,1)>0,1,0)) -> 1 | BF50: 1 | BH50: 1 | BJ50: 1 | GI50: 1
A51: P6.3 | B51: Proposition 6.3 | C51: =VALUE(MID(A51,2,FIND(".",A51)-2)) -> 6 | D51: =COUNTIF(BE$6:BE$216,1) -> 0 | E51: =COUNTIF($L51:$HN51,1) -> 1 | F51: =IF(COUNTIF(BE$6:BE50,1)=0,0,1+_xlfn.MAXIFS($F$6:$F50,BE$6:BE50,1)) -> 0 | G51: =IF(F51=0,1,SUMIFS($G$6:$G50,BE$6:BE50,1,$F$6:$F50,F51-1)) -> 1 | H51: =IF($A51="T16.4",1,IF(COUNTIFS(BF51:HN51,1,BF$4:HN$4,1)>0,1,0)) -> 1 | BH51: 1
A52: T6.3 | B52: Theorem 6.3 | C52: =VALUE(MID(A52,2,FIND(".",A52)-2)) -> 6 | D52: =COUNTIF(BF$6:BF$216,1) -> 2 | E52: =COUNTIF($L52:$HN52,1) -> 1 | F52: =IF(COUNTIF(BF$6:BF51,1)=0,0,1+_xlfn.MAXIFS($F$6:$F51,BF$6:BF51,1)) -> 2 | G52: =IF(F52=0,1,SUMIFS($G$6:$G51,BF$6:BF51,1,$F$6:$F51,F52-1)) -> 1 | H52: =IF($A52="T16.4",1,IF(COUNTIFS(BG52:HN52,1,BG$4:HN$4,1)>0,1,0)) -> 1 | GC52: 1
A53: P6.4 | B53: Proposition 6.4 | C53: =VALUE(MID(A53,2,FIND(".",A53)-2)) -> 6 | D53: =COUNTIF(BG$6:BG$216,1) -> 1 | E53: =COUNTIF($L53:$HN53,1) -> 1 | F53: =IF(COUNTIF(BG$6:BG52,1)=0,0,1+_xlfn.MAXIFS($F$6:$F52,BG$6:BG52,1)) -> 1 | G53: =IF(F53=0,1,SUMIFS($G$6:$G52,BG$6:BG52,1,$F$6:$F52,F53-1)) -> 1 | H53: =IF($A53="T16.4",1,IF(COUNTIFS(BH53:HN53,1,BH$4:HN$4,1)>0,1,0)) -> 1 | BH53: 1
A54: T6.2 | B54: Theorem 6.2 | C54: =VALUE(MID(A54,2,FIND(".",A54)-2)) -> 6 | D54: =COUNTIF(BH$6:BH$216,1) -> 5 | E54: =COUNTIF($L54:$HN54,1) -> 4 | F54: =IF(COUNTIF(BH$6:BH53,1)=0,0,1+_xlfn.MAXIFS($F$6:$F53,BH$6:BH53,1)) -> 2 | G54: =IF(F54=0,1,SUMIFS($G$6:$G53,BH$6:BH53,1,$F$6:$F53,F54-1)) -> 3 | H54: =IF($A54="T16.4",1,IF(COUNTIFS(BI54:HN54,1,BI$4:HN$4,1)>0,1,0)) -> 1 | CO54: 1 | GH54: 1 | GJ54: 1 | GU54: 1
A55: T6.4 | B55: Theorem 6.4 | C55: =VALUE(MID(A55,2,FIND(".",A55)-2)) -> 6 | D55: =COUNTIF(BI$6:BI$216,1) -> 0 | E55: =COUNTIF($L55:$HN55,1) -> 3 | F55: =IF(COUNTIF(BI$6:BI54,1)=0,0,1+_xlfn.MAXIFS($F$6:$F54,BI$6:BI54,1)) -> 0 | G55: =IF(F55=0,1,SUMIFS($G$6:$G54,BI$6:BI54,1,$F$6:$F54,F55-1)) -> 1 | H55: =IF($A55="T16.4",1,IF(COUNTIFS(BJ55:HN55,1,BJ$4:HN$4,1)>0,1,0)) -> 1 | BN55: 1 | DT55: 1 | FI55: 1
A56: P6.5 | B56: Proposition 6.5 | C56: =VALUE(MID(A56,2,FIND(".",A56)-2)) -> 6 | D56: =COUNTIF(BJ$6:BJ$216,1) -> 1 | E56: =COUNTIF($L56:$HN56,1) -> 0 | F56: =IF(COUNTIF(BJ$6:BJ55,1)=0,0,1+_xlfn.MAXIFS($F$6:$F55,BJ$6:BJ55,1)) -> 2 | G56: =IF(F56=0,1,SUMIFS($G$6:$G55,BJ$6:BJ55,1,$F$6:$F55,F56-1)) -> 1 | H56: =IF($A56="T16.4",1,IF(COUNTIFS(BK56:HN56,1,BK$4:HN$4,1)>0,1,0)) -> 0
A57: T6.5 | B57: Theorem 6.5 | C57: =VALUE(MID(A57,2,FIND(".",A57)-2)) -> 6 | D57: =COUNTIF(BK$6:BK$216,1) -> 1 | E57: =COUNTIF($L57:$HN57,1) -> 0 | F57: =IF(COUNTIF(BK$6:BK56,1)=0,0,1+_xlfn.MAXIFS($F$6:$F56,BK$6:BK56,1)) -> 1 | G57: =IF(F57=0,1,SUMIFS($G$6:$G56,BK$6:BK56,1,$F$6:$F56,F57-1)) -> 1 | H57: =IF($A57="T16.4",1,IF(COUNTIFS(BL57:HN57,1,BL$4:HN$4,1)>0,1,0)) -> 0
A58: E6.B.1 | B58: Example 6.B.1 | C58: =VALUE(MID(A58,2,FIND(".",A58)-2)) -> 6 | D58: =COUNTIF(BL$6:BL$216,1) -> 2 | E58: =COUNTIF($L58:$HN58,1) -> 0 | F58: =IF(COUNTIF(BL$6:BL57,1)=0,0,1+_xlfn.MAXIFS($F$6:$F57,BL$6:BL57,1)) -> 3 | G58: =IF(F58=0,1,SUMIFS($G$6:$G57,BL$6:BL57,1,$F$6:$F57,F58-1)) -> 1 | H58: =IF($A58="T16.4",1,IF(COUNTIFS(BM58:HN58,1,BM$4:HN$4,1)>0,1,0)) -> 0
A59: R6.B.2 | B59: Remark 6.B.2 | C59: =VALUE(MID(A59,2,FIND(".",A59)-2)) -> 6 | D59: =COUNTIF(BM$6:BM$216,1) -> 0 | E59: =COUNTIF($L59:$HN59,1) -> 0 | F59: =IF(COUNTIF(BM$6:BM58,1)=0,0,1+_xlfn.MAXIFS($F$6:$F58,BM$6:BM58,1)) -> 0 | G59: =IF(F59=0,1,SUMIFS($G$6:$G58,BM$6:BM58,1,$F$6:$F58,F59-1)) -> 1 | H59: =IF($A59="T16.4",1,IF(COUNTIFS(BN59:HN59,1,BN$4:HN$4,1)>0,1,0)) -> 0
A60: R6.B.3 | B60: Remark 6.B.3 | C60: =VALUE(MID(A60,2,FIND(".",A60)-2)) -> 6 | D60: =COUNTIF(BN$6:BN$216,1) -> 1 | E60: =COUNTIF($L60:$HN60,1) -> 0 | F60: =IF(COUNTIF(BN$6:BN59,1)=0,0,1+_xlfn.MAXIFS($F$6:$F59,BN$6:BN59,1)) -> 1 | G60: =IF(F60=0,1,SUMIFS($G$6:$G59,BN$6:BN59,1,$F$6:$F59,F60-1)) -> 1 | H60: =IF($A60="T16.4",1,IF(COUNTIFS(BO60:HN60,1,BO$4:HN$4,1)>0,1,0)) -> 0
A61: T7.1 | B61: Theorem 7.1 | C61: =VALUE(MID(A61,2,FIND(".",A61)-2)) -> 7 | D61: =COUNTIF(BO$6:BO$216,1) -> 5 | E61: =COUNTIF($L61:$HN61,1) -> 7 | F61: =IF(COUNTIF(BO$6:BO60,1)=0,0,1+_xlfn.MAXIFS($F$6:$F60,BO$6:BO60,1)) -> 3 | G61: =IF(F61=0,1,SUMIFS($G$6:$G60,BO$6:BO60,1,$F$6:$F60,F61-1)) -> 2 | H61: =IF($A61="T16.4",1,IF(COUNTIFS(BP61:HN61,1,BP$4:HN$4,1)>0,1,0)) -> 1 | BP61: 1 | BQ61: 1 | BR61: 1 | BS61: 1 | BU61: 1 | EH61: 1 | FQ61: 1
A62: P7.1 | B62: Proposition 7.1 | C62: =VALUE(MID(A62,2,FIND(".",A62)-2)) -> 7 | D62: =COUNTIF(BP$6:BP$216,1) -> 1 | E62: =COUNTIF($L62:$HN62,1) -> 1 | F62: =IF(COUNTIF(BP$6:BP61,1)=0,0,1+_xlfn.MAXIFS($F$6:$F61,BP$6:BP61,1)) -> 4 | G62: =IF(F62=0,1,SUMIFS($G$6:$G61,BP$6:BP61,1,$F$6:$F61,F62-1)) -> 2 | H62: =IF($A62="T16.4",1,IF(COUNTIFS(BQ62:HN62,1,BQ$4:HN$4,1)>0,1,0)) -> 0 | BS62: 1
A63: T7.2 | B63: Theorem 7.2 | C63: =VALUE(MID(A63,2,FIND(".",A63)-2)) -> 7 | D63: =COUNTIF(BQ$6:BQ$216,1) -> 1 | E63: =COUNTIF($L63:$HN63,1) -> 3 | F63: =IF(COUNTIF(BQ$6:BQ62,1)=0,0,1+_xlfn.MAXIFS($F$6:$F62,BQ$6:BQ62,1)) -> 4 | G63: =IF(F63=0,1,SUMIFS($G$6:$G62,BQ$6:BQ62,1,$F$6:$F62,F63-1)) -> 2 | H63: =IF($A63="T16.4",1,IF(COUNTIFS(BR63:HN63,1,BR$4:HN$4,1)>0,1,0)) -> 1 | BR63: 1 | BZ63: 1 | DU63: 1
A64: P7.2 | B64: Proposition 7.2 | C64: =VALUE(MID(A64,2,FIND(".",A64)-2)) -> 7 | D64: =COUNTIF(BR$6:BR$216,1) -> 2 | E64: =COUNTIF($L64:$HN64,1) -> 3 | F64: =IF(COUNTIF(BR$6:BR63,1)=0,0,1+_xlfn.MAXIFS($F$6:$F63,BR$6:BR63,1)) -> 5 | G64: =IF(F64=0,1,SUMIFS($G$6:$G63,BR$6:BR63,1,$F$6:$F63,F64-1)) -> 2 | H64: =IF($A64="T16.4",1,IF(COUNTIFS(BS64:HN64,1,BS$4:HN$4,1)>0,1,0)) -> 1 | BT64: 1 | CB64: 1 | GM64: 1
A65: P7.3 | B65: Proposition 7.3 | C65: =VALUE(MID(A65,2,FIND(".",A65)-2)) -> 7 | D65: =COUNTIF(BS$6:BS$216,1) -> 2 | E65: =COUNTIF($L65:$HN65,1) -> 1 | F65: =IF(COUNTIF(BS$6:BS64,1)=0,0,1+_xlfn.MAXIFS($F$6:$F64,BS$6:BS64,1)) -> 5 | G65: =IF(F65=0,1,SUMIFS($G$6:$G64,BS$6:BS64,1,$F$6:$F64,F65-1)) -> 2 | H65: =IF($A65="T16.4",1,IF(COUNTIFS(BT65:HN65,1,BT$4:HN$4,1)>0,1,0)) -> 0 | BU65: 1
A66: P7.4 | B66: Proposition 7.4 | C66: =VALUE(MID(A66,2,FIND(".",A66)-2)) -> 7 | D66: =COUNTIF(BT$6:BT$216,1) -> 2 | E66: =COUNTIF($L66:$HN66,1) -> 1 | F66: =IF(COUNTIF(BT$6:BT65,1)=0,0,1+_xlfn.MAXIFS($F$6:$F65,BT$6:BT65,1)) -> 6 | G66: =IF(F66=0,1,SUMIFS($G$6:$G65,BT$6:BT65,1,$F$6:$F65,F66-1)) -> 2 | H66: =IF($A66="T16.4",1,IF(COUNTIFS(BU66:HN66,1,BU$4:HN$4,1)>0,1,0)) -> 0 | BU66: 1
A67: T7.3 | B67: Theorem 7.3 | C67: =VALUE(MID(A67,2,FIND(".",A67)-2)) -> 7 | D67: =COUNTIF(BU$6:BU$216,1) -> 4 | E67: =COUNTIF($L67:$HN67,1) -> 1 | F67: =IF(COUNTIF(BU$6:BU66,1)=0,0,1+_xlfn.MAXIFS($F$6:$F66,BU$6:BU66,1)) -> 7 | G67: =IF(F67=0,1,SUMIFS($G$6:$G66,BU$6:BU66,1,$F$6:$F66,F67-1)) -> 2 | H67: =IF($A67="T16.4",1,IF(COUNTIFS(BV67:HN67,1,BV$4:HN$4,1)>0,1,0)) -> 0 | EY67: 1
A68: T7.4 | B68: Theorem 7.4 | C68: =VALUE(MID(A68,2,FIND(".",A68)-2)) -> 7 | D68: =COUNTIF(BV$6:BV$216,1) -> 0 | E68: =COUNTIF($L68:$HN68,1) -> 6 | F68: =IF(COUNTIF(BV$6:BV67,1)=0,0,1+_xlfn.MAXIFS($F$6:$F67,BV$6:BV67,1)) -> 0 | G68: =IF(F68=0,1,SUMIFS($G$6:$G67,BV$6:BV67,1,$F$6:$F67,F68-1)) -> 1 | H68: =IF($A68="T16.4",1,IF(COUNTIFS(BW68:HN68,1,BW$4:HN$4,1)>0,1,0)) -> 1 | BX68: 1 | CD68: 1 | CM68: 1 | EY68: 1 | FA68: 1 | FX68: 1
A69: P7.5 | B69: Proposition 7.5 | C69: =VALUE(MID(A69,2,FIND(".",A69)-2)) -> 7 | D69: =COUNTIF(BW$6:BW$216,1) -> 1 | E69: =COUNTIF($L69:$HN69,1) -> 1 | F69: =IF(COUNTIF(BW$6:BW68,1)=0,0,1+_xlfn.MAXIFS($F$6:$F68,BW$6:BW68,1)) -> 2 | G69: =IF(F69=0,1,SUMIFS($G$6:$G68,BW$6:BW68,1,$F$6:$F68,F69-1)) -> 1 | H69: =IF($A69="T16.4",1,IF(COUNTIFS(BX69:HN69,1,BX$4:HN$4,1)>0,1,0)) -> 0 | BX69: 1
A70: T7.5 | B70: Theorem 7.5 | C70: =VALUE(MID(A70,2,FIND(".",A70)-2)) -> 7 | D70: =COUNTIF(BX$6:BX$216,1) -> 2 | E70: =COUNTIF($L70:$HN70,1) -> 2 | F70: =IF(COUNTIF(BX$6:BX69,1)=0,0,1+_xlfn.MAXIFS($F$6:$F69,BX$6:BX69,1)) -> 3 | G70: =IF(F70=0,1,SUMIFS($G$6:$G69,BX$6:BX69,1,$F$6:$F69,F70-1)) -> 1 | H70: =IF($A70="T16.4",1,IF(COUNTIFS(BY70:HN70,1,BY$4:HN$4,1)>0,1,0)) -> 0 | CD70: 1 | CE70: 1
A71: E7.B.1 | B71: Example 7.B.1 | C71: =VALUE(MID(A71,2,FIND(".",A71)-2)) -> 7 | D71: =COUNTIF(BY$6:BY$216,1) -> 0 | E71: =COUNTIF($L71:$HN71,1) -> 0 | F71: =IF(COUNTIF(BY$6:BY70,1)=0,0,1+_xlfn.MAXIFS($F$6:$F70,BY$6:BY70,1)) -> 0 | G71: =IF(F71=0,1,SUMIFS($G$6:$G70,BY$6:BY70,1,$F$6:$F70,F71-1)) -> 1 | H71: =IF($A71="T16.4",1,IF(COUNTIFS(BZ71:HN71,1,BZ$4:HN$4,1)>0,1,0)) -> 0
A72: E7.B.2 | B72: Example 7.B.2 | C72: =VALUE(MID(A72,2,FIND(".",A72)-2)) -> 7 | D72: =COUNTIF(BZ$6:BZ$216,1) -> 1 | E72: =COUNTIF($L72:$HN72,1) -> 0 | F72: =IF(COUNTIF(BZ$6:BZ71,1)=0,0,1+_xlfn.MAXIFS($F$6:$F71,BZ$6:BZ71,1)) -> 5 | G72: =IF(F72=0,1,SUMIFS($G$6:$G71,BZ$6:BZ71,1,$F$6:$F71,F72-1)) -> 2 | H72: =IF($A72="T16.4",1,IF(COUNTIFS(CA72:HN72,1,CA$4:HN$4,1)>0,1,0)) -> 0
A73: E7.B.3 | B73: Example 7.B.3 | C73: =VALUE(MID(A73,2,FIND(".",A73)-2)) -> 7 | D73: =COUNTIF(CA$6:CA$216,1) -> 0 | E73: =COUNTIF($L73:$HN73,1) -> 0 | F73: =IF(COUNTIF(CA$6:CA72,1)=0,0,1+_xlfn.MAXIFS($F$6:$F72,CA$6:CA72,1)) -> 0 | G73: =IF(F73=0,1,SUMIFS($G$6:$G72,CA$6:CA72,1,$F$6:$F72,F73-1)) -> 1 | H73: =IF($A73="T16.4",1,IF(COUNTIFS(CB73:HN73,1,CB$4:HN$4,1)>0,1,0)) -> 0
A74: E7.B.4 | B74: Example 7.B.4 | C74: =VALUE(MID(A74,2,FIND(".",A74)-2)) -> 7 | D74: =COUNTIF(CB$6:CB$216,1) -> 1 | E74: =COUNTIF($L74:$HN74,1) -> 0 | F74: =IF(COUNTIF(CB$6:CB73,1)=0,0,1+_xlfn.MAXIFS($F$6:$F73,CB$6:CB73,1)) -> 6 | G74: =IF(F74=0,1,SUMIFS($G$6:$G73,CB$6:CB73,1,$F$6:$F73,F74-1)) -> 2 | H74: =IF($A74="T16.4",1,IF(COUNTIFS(CC74:HN74,1,CC$4:HN$4,1)>0,1,0)) -> 0
A75: L7.B.5 | B75: Lemma 7.B.5 | C75: =VALUE(MID(A75,2,FIND(".",A75)-2)) -> 7 | D75: =COUNTIF(CC$6:CC$216,1) -> 0 | E75: =COUNTIF($L75:$HN75,1) -> 1 | F75: =IF(COUNTIF(CC$6:CC74,1)=0,0,1+_xlfn.MAXIFS($F$6:$F74,CC$6:CC74,1)) -> 0 | G75: =IF(F75=0,1,SUMIFS($G$6:$G74,CC$6:CC74,1,$F$6:$F74,F75-1)) -> 1 | H75: =IF($A75="T16.4",1,IF(COUNTIFS(CD75:HN75,1,CD$4:HN$4,1)>0,1,0)) -> 0 | CD75: 1
A76: P7.B.6 | B76: Proposition 7.B.6 | C76: =VALUE(MID(A76,2,FIND(".",A76)-2)) -> 7 | D76: =COUNTIF(CD$6:CD$216,1) -> 3 | E76: =COUNTIF($L76:$HN76,1) -> 0 | F76: =IF(COUNTIF(CD$6:CD75,1)=0,0,1+_xlfn.MAXIFS($F$6:$F75,CD$6:CD75,1)) -> 4 | G76: =IF(F76=0,1,SUMIFS($G$6:$G75,CD$6:CD75,1,$F$6:$F75,F76-1)) -> 1 | H76: =IF($A76="T16.4",1,IF(COUNTIFS(CE76:HN76,1,CE$4:HN$4,1)>0,1,0)) -> 0
A77: E7.B.7 | B77: Example 7.B.7 | C77: =VALUE(MID(A77,2,FIND(".",A77)-2)) -> 7 | D77: =COUNTIF(CE$6:CE$216,1) -> 1 | E77: =COUNTIF($L77:$HN77,1) -> 1 | F77: =IF(COUNTIF(CE$6:CE76,1)=0,0,1+_xlfn.MAXIFS($F$6:$F76,CE$6:CE76,1)) -> 4 | G77: =IF(F77=0,1,SUMIFS($G$6:$G76,CE$6:CE76,1,$F$6:$F76,F77-1)) -> 1 | H77: =IF($A77="T16.4",1,IF(COUNTIFS(CF77:HN77,1,CF$4:HN$4,1)>0,1,0)) -> 0 | CF77: 1
A78: R7.B.8 | B78: Remark 7.B.8 | C78: =VALUE(MID(A78,2,FIND(".",A78)-2)) -> 7 | D78: =COUNTIF(CF$6:CF$216,1) -> 2 | E78: =COUNTIF($L78:$HN78,1) -> 0 | F78: =IF(COUNTIF(CF$6:CF77,1)=0,0,1+_xlfn.MAXIFS($F$6:$F77,CF$6:CF77,1)) -> 5 | G78: =IF(F78=0,1,SUMIFS($G$6:$G77,CF$6:CF77,1,$F$6:$F77,F78-1)) -> 1 | H78: =IF($A78="T16.4",1,IF(COUNTIFS(CG78:HN78,1,CG$4:HN$4,1)>0,1,0)) -> 0
A79: L8.1 | B79: Lemma 8.1 | C79: =VALUE(MID(A79,2,FIND(".",A79)-2)) -> 8 | D79: =COUNTIF(CG$6:CG$216,1) -> 0 | E79: =COUNTIF($L79:$HN79,1) -> 1 | F79: =IF(COUNTIF(CG$6:CG78,1)=0,0,1+_xlfn.MAXIFS($F$6:$F78,CG$6:CG78,1)) -> 0 | G79: =IF(F79=0,1,SUMIFS($G$6:$G78,CG$6:CG78,1,$F$6:$F78,F79-1)) -> 1 | H79: =IF($A79="T16.4",1,IF(COUNTIFS(CH79:HN79,1,CH$4:HN$4,1)>0,1,0)) -> 1 | CI79: 1
A80: P8.1 | B80: Proposition 8.1 | C80: =VALUE(MID(A80,2,FIND(".",A80)-2)) -> 8 | D80: =COUNTIF(CH$6:CH$216,1) -> 1 | E80: =COUNTIF($L80:$HN80,1) -> 0 | F80: =IF(COUNTIF(CH$6:CH79,1)=0,0,1+_xlfn.MAXIFS($F$6:$F79,CH$6:CH79,1)) -> 2 | G80: =IF(F80=0,1,SUMIFS($G$6:$G79,CH$6:CH79,1,$F$6:$F79,F80-1)) -> 1 | H80: =IF($A80="T16.4",1,IF(COUNTIFS(CI80:HN80,1,CI$4:HN$4,1)>0,1,0)) -> 0
A81: T8.1 | B81: Theorem 8.1 | C81: =VALUE(MID(A81,2,FIND(".",A81)-2)) -> 8 | D81: =COUNTIF(CI$6:CI$216,1) -> 5 | E81: =COUNTIF($L81:$HN81,1) -> 7 | F81: =IF(COUNTIF(CI$6:CI80,1)=0,0,1+_xlfn.MAXIFS($F$6:$F80,CI$6:CI80,1)) -> 3 | G81: =IF(F81=0,1,SUMIFS($G$6:$G80,CI$6:CI80,1,$F$6:$F80,F81-1)) -> 2 | H81: =IF($A81="T16.4",1,IF(COUNTIFS(CJ81:HN81,1,CJ$4:HN$4,1)>0,1,0)) -> 1 | CJ81: 1 | CK81: 1 | CN81: 1 | EH81: 1 | FQ81: 1 | GI81: 1 | GN81: 1
A82: P8.2 | B82: Proposition 8.2 | C82: =VALUE(MID(A82,2,FIND(".",A82)-2)) -> 8 | D82: =COUNTIF(CJ$6:CJ$216,1) -> 1 | E82: =COUNTIF($L82:$HN82,1) -> 2 | F82: =IF(COUNTIF(CJ$6:CJ81,1)=0,0,1+_xlfn.MAXIFS($F$6:$F81,CJ$6:CJ81,1)) -> 4 | G82: =IF(F82=0,1,SUMIFS($G$6:$G81,CJ$6:CJ81,1,$F$6:$F81,F82-1)) -> 2 | H82: =IF($A82="T16.4",1,IF(COUNTIFS(CK82:HN82,1,CK$4:HN$4,1)>0,1,0)) -> 1 | EH82: 1 | EV82: 1
A83: T8.2 | B83: Theorem 8.2 | C83: =VALUE(MID(A83,2,FIND(".",A83)-2)) -> 8 | D83: =COUNTIF(CK$6:CK$216,1) -> 1 | E83: =COUNTIF($L83:$HN83,1) -> 6 | F83: =IF(COUNTIF(CK$6:CK82,1)=0,0,1+_xlfn.MAXIFS($F$6:$F82,CK$6:CK82,1)) -> 4 | G83: =IF(F83=0,1,SUMIFS($G$6:$G82,CK$6:CK82,1,$F$6:$F82,F83-1)) -> 2 | H83: =IF($A83="T16.4",1,IF(COUNTIFS(CL83:HN83,1,CL$4:HN$4,1)>0,1,0)) -> 1 | CS83: 1 | EJ83: 1 | FI83: 1 | FQ83: 1 | GI83: 1 | GN83: 1
A84: P8.3 | B84: Proposition 8.3 | C84: =VALUE(MID(A84,2,FIND(".",A84)-2)) -> 8 | D84: =COUNTIF(CL$6:CL$216,1) -> 0 | E84: =COUNTIF($L84:$HN84,1) -> 0 | F84: =IF(COUNTIF(CL$6:CL83,1)=0,0,1+_xlfn.MAXIFS($F$6:$F83,CL$6:CL83,1)) -> 0 | G84: =IF(F84=0,1,SUMIFS($G$6:$G83,CL$6:CL83,1,$F$6:$F83,F84-1)) -> 1 | H84: =IF($A84="T16.4",1,IF(COUNTIFS(CM84:HN84,1,CM$4:HN$4,1)>0,1,0)) -> 0
A85: T8.3 | B85: Theorem 8.3 | C85: =VALUE(MID(A85,2,FIND(".",A85)-2)) -> 8 | D85: =COUNTIF(CM$6:CM$216,1) -> 1 | E85: =COUNTIF($L85:$HN85,1) -> 5 | F85: =IF(COUNTIF(CM$6:CM84,1)=0,0,1+_xlfn.MAXIFS($F$6:$F84,CM$6:CM84,1)) -> 1 | G85: =IF(F85=0,1,SUMIFS($G$6:$G84,CM$6:CM84,1,$F$6:$F84,F85-1)) -> 1 | H85: =IF($A85="T16.4",1,IF(COUNTIFS(CN85:HN85,1,CN$4:HN$4,1)>0,1,0)) -> 0 | CR85: 1 | CT85: 1 | EY85: 1 | GD85: 1 | GE85: 1
A86: P8.4 | B86: Proposition 8.4 | C86: =VALUE(MID(A86,2,FIND(".",A86)-2)) -> 8 | D86: =COUNTIF(CN$6:CN$216,1) -> 1 | E86: =COUNTIF($L86:$HN86,1) -> 0 | F86: =IF(COUNTIF(CN$6:CN85,1)=0,0,1+_xlfn.MAXIFS($F$6:$F85,CN$6:CN85,1)) -> 4 | G86: =IF(F86=0,1,SUMIFS($G$6:$G85,CN$6:CN85,1,$F$6:$F85,F86-1)) -> 2 | H86: =IF($A86="T16.4",1,IF(COUNTIFS(CO86:HN86,1,CO$4:HN$4,1)>0,1,0)) -> 0
A87: P8.5 | B87: Proposition 8.5 | C87: =VALUE(MID(A87,2,FIND(".",A87)-2)) -> 8 | D87: =COUNTIF(CO$6:CO$216,1) -> 1 | E87: =COUNTIF($L87:$HN87,1) -> 0 | F87: =IF(COUNTIF(CO$6:CO86,1)=0,0,1+_xlfn.MAXIFS($F$6:$F86,CO$6:CO86,1)) -> 3 | G87: =IF(F87=0,1,SUMIFS($G$6:$G86,CO$6:CO86,1,$F$6:$F86,F87-1)) -> 3 | H87: =IF($A87="T16.4",1,IF(COUNTIFS(CP87:HN87,1,CP$4:HN$4,1)>0,1,0)) -> 0
A88: T8.5 | B88: Theorem 8.5 | C88: =VALUE(MID(A88,2,FIND(".",A88)-2)) -> 8 | D88: =COUNTIF(CP$6:CP$216,1) -> 0 | E88: =COUNTIF($L88:$HN88,1) -> 6 | F88: =IF(COUNTIF(CP$6:CP87,1)=0,0,1+_xlfn.MAXIFS($F$6:$F87,CP$6:CP87,1)) -> 0 | G88: =IF(F88=0,1,SUMIFS($G$6:$G87,CP$6:CP87,1,$F$6:$F87,F88-1)) -> 1 | H88: =IF($A88="T16.4",1,IF(COUNTIFS(CQ88:HN88,1,CQ$4:HN$4,1)>0,1,0)) -> 0 | CQ88: 1 | CW88: 1 | CX88: 1 | EJ88: 1 | FQ88: 1 | GE88: 1
A89: T8.4 | B89: Theorem 8.4 | C89: =VALUE(MID(A89,2,FIND(".",A89)-2)) -> 8 | D89: =COUNTIF(CQ$6:CQ$216,1) -> 1 | E89: =COUNTIF($L89:$HN89,1) -> 1 | F89: =IF(COUNTIF(CQ$6:CQ88,1)=0,0,1+_xlfn.MAXIFS($F$6:$F88,CQ$6:CQ88,1)) -> 1 | G89: =IF(F89=0,1,SUMIFS($G$6:$G88,CQ$6:CQ88,1,$F$6:$F88,F89-1)) -> 1 | H89: =IF($A89="T16.4",1,IF(COUNTIFS(CR89:HN89,1,CR$4:HN$4,1)>0,1,0)) -> 0 | EZ89: 1
A90: E8.B.1 | B90: Example 8.B.1 | C90: =VALUE(MID(A90,2,FIND(".",A90)-2)) -> 8 | D90: =COUNTIF(CR$6:CR$216,1) -> 1 | E90: =COUNTIF($L90:$HN90,1) -> 0 | F90: =IF(COUNTIF(CR$6:CR89,1)=0,0,1+_xlfn.MAXIFS($F$6:$F89,CR$6:CR89,1)) -> 2 | G90: =IF(F90=0,1,SUMIFS($G$6:$G89,CR$6:CR89,1,$F$6:$F89,F90-1)) -> 1 | H90: =IF($A90="T16.4",1,IF(COUNTIFS(CS90:HN90,1,CS$4:HN$4,1)>0,1,0)) -> 0
A91: E8.B.2 | B91: Example 8.B.2 | C91: =VALUE(MID(A91,2,FIND(".",A91)-2)) -> 8 | D91: =COUNTIF(CS$6:CS$216,1) -> 1 | E91: =COUNTIF($L91:$HN91,1) -> 0 | F91: =IF(COUNTIF(CS$6:CS90,1)=0,0,1+_xlfn.MAXIFS($F$6:$F90,CS$6:CS90,1)) -> 5 | G91: =IF(F91=0,1,SUMIFS($G$6:$G90,CS$6:CS90,1,$F$6:$F90,F91-1)) -> 2 | H91: =IF($A91="T16.4",1,IF(COUNTIFS(CT91:HN91,1,CT$4:HN$4,1)>0,1,0)) -> 0
A92: E8.B.3 | B92: Example 8.B.3 | C92: =VALUE(MID(A92,2,FIND(".",A92)-2)) -> 8 | D92: =COUNTIF(CT$6:CT$216,1) -> 1 | E92: =COUNTIF($L92:$HN92,1) -> 0 | F92: =IF(COUNTIF(CT$6:CT91,1)=0,0,1+_xlfn.MAXIFS($F$6:$F91,CT$6:CT91,1)) -> 2 | G92: =IF(F92=0,1,SUMIFS($G$6:$G91,CT$6:CT91,1,$F$6:$F91,F92-1)) -> 1 | H92: =IF($A92="T16.4",1,IF(COUNTIFS(CU92:HN92,1,CU$4:HN$4,1)>0,1,0)) -> 0
A93: R8.B.4 | B93: Remark 8.B.4 | C93: =VALUE(MID(A93,2,FIND(".",A93)-2)) -> 8 | D93: =COUNTIF(CU$6:CU$216,1) -> 0 | E93: =COUNTIF($L93:$HN93,1) -> 0 | F93: =IF(COUNTIF(CU$6:CU92,1)=0,0,1+_xlfn.MAXIFS($F$6:$F92,CU$6:CU92,1)) -> 0 | G93: =IF(F93=0,1,SUMIFS($G$6:$G92,CU$6:CU92,1,$F$6:$F92,F93-1)) -> 1 | H93: =IF($A93="T16.4",1,IF(COUNTIFS(CV93:HN93,1,CV$4:HN$4,1)>0,1,0)) -> 0
A94: E8.B.5 | B94: Example 8.B.5 | C94: =VALUE(MID(A94,2,FIND(".",A94)-2)) -> 8 | D94: =COUNTIF(CV$6:CV$216,1) -> 0 | E94: =COUNTIF($L94:$HN94,1) -> 0 | F94: =IF(COUNTIF(CV$6:CV93,1)=0,0,1+_xlfn.MAXIFS($F$6:$F93,CV$6:CV93,1)) -> 0 | G94: =IF(F94=0,1,SUMIFS($G$6:$G93,CV$6:CV93,1,$F$6:$F93,F94-1)) -> 1 | H94: =IF($A94="T16.4",1,IF(COUNTIFS(CW94:HN94,1,CW$4:HN$4,1)>0,1,0)) -> 0
A95: E8.B.6 | B95: Example 8.B.6 | C95: =VALUE(MID(A95,2,FIND(".",A95)-2)) -> 8 | D95: =COUNTIF(CW$6:CW$216,1) -> 1 | E95: =COUNTIF($L95:$HN95,1) -> 0 | F95: =IF(COUNTIF(CW$6:CW94,1)=0,0,1+_xlfn.MAXIFS($F$6:$F94,CW$6:CW94,1)) -> 1 | G95: =IF(F95=0,1,SUMIFS($G$6:$G94,CW$6:CW94,1,$F$6:$F94,F95-1)) -> 1 | H95: =IF($A95="T16.4",1,IF(COUNTIFS(CX95:HN95,1,CX$4:HN$4,1)>0,1,0)) -> 0
A96: E8.B.7 | B96: Example 8.B.7 | C96: =VALUE(MID(A96,2,FIND(".",A96)-2)) -> 8 | D96: =COUNTIF(CX$6:CX$216,1) -> 1 | E96: =COUNTIF($L96:$HN96,1) -> 0 | F96: =IF(COUNTIF(CX$6:CX95,1)=0,0,1+_xlfn.MAXIFS($F$6:$F95,CX$6:CX95,1)) -> 1 | G96: =IF(F96=0,1,SUMIFS($G$6:$G95,CX$6:CX95,1,$F$6:$F95,F96-1)) -> 1 | H96: =IF($A96="T16.4",1,IF(COUNTIFS(CY96:HN96,1,CY$4:HN$4,1)>0,1,0)) -> 0
A97: T9.1 | B97: Theorem 9.1 | C97: =VALUE(MID(A97,2,FIND(".",A97)-2)) -> 9 | D97: =COUNTIF(CY$6:CY$216,1) -> 1 | E97: =COUNTIF($L97:$HN97,1) -> 6 | F97: =IF(COUNTIF(CY$6:CY96,1)=0,0,1+_xlfn.MAXIFS($F$6:$F96,CY$6:CY96,1)) -> 1 | G97: =IF(F97=0,1,SUMIFS($G$6:$G96,CY$6:CY96,1,$F$6:$F96,F97-1)) -> 1 | H97: =IF($A97="T16.4",1,IF(COUNTIFS(CZ97:HN97,1,CZ$4:HN$4,1)>0,1,0)) -> 1 | CZ97: 1 | DA97: 1 | DG97: 1 | DS97: 1 | FI97: 1 | FP97: 1
A98: P9.1 | B98: Proposition 9.1 | C98: =VALUE(MID(A98,2,FIND(".",A98)-2)) -> 9 | D98: =COUNTIF(CZ$6:CZ$216,1) -> 1 | E98: =COUNTIF($L98:$HN98,1) -> 1 | F98: =IF(COUNTIF(CZ$6:CZ97,1)=0,0,1+_xlfn.MAXIFS($F$6:$F97,CZ$6:CZ97,1)) -> 2 | G98: =IF(F98=0,1,SUMIFS($G$6:$G97,CZ$6:CZ97,1,$F$6:$F97,F98-1)) -> 1 | H98: =IF($A98="T16.4",1,IF(COUNTIFS(DA98:HN98,1,DA$4:HN$4,1)>0,1,0)) -> 0 | FH98: 1
A99: P9.2 | B99: Proposition 9.2 | C99: =VALUE(MID(A99,2,FIND(".",A99)-2)) -> 9 | D99: =COUNTIF(DA$6:DA$216,1) -> 1 | E99: =COUNTIF($L99:$HN99,1) -> 0 | F99: =IF(COUNTIF(DA$6:DA98,1)=0,0,1+_xlfn.MAXIFS($F$6:$F98,DA$6:DA98,1)) -> 2 | G99: =IF(F99=0,1,SUMIFS($G$6:$G98,DA$6:DA98,1,$F$6:$F98,F99-1)) -> 1 | H99: =IF($A99="T16.4",1,IF(COUNTIFS(DB99:HN99,1,DB$4:HN$4,1)>0,1,0)) -> 0
A100: T9.2 | B100: Theorem 9.2 | C100: =VALUE(MID(A100,2,FIND(".",A100)-2)) -> 9 | D100: =COUNTIF(DB$6:DB$216,1) -> 0 | E100: =COUNTIF($L100:$HN100,1) -> 9 | F100: =IF(COUNTIF(DB$6:DB99,1)=0,0,1+_xlfn.MAXIFS($F$6:$F99,DB$6:DB99,1)) -> 0 | G100: =IF(F100=0,1,SUMIFS($G$6:$G99,DB$6:DB99,1,$F$6:$F99,F100-1)) -> 1 | H100: =IF($A100="T16.4",1,IF(COUNTIFS(DC100:HN100,1,DC$4:HN$4,1)>0,1,0)) -> 1 | DD100: 1 | DJ100: 1 | DK100: 1 | DS100: 1 | EK100: 1 | FA100: 1 | FI100: 1 | FJ100: 1 | GA100: 1
A101: P9.3 | B101: Proposition 9.3 | C101: =VALUE(MID(A101,2,FIND(".",A101)-2)) -> 9 | D101: =COUNTIF(DC$6:DC$216,1) -> 0 | E101: =COUNTIF($L101:$HN101,1) -> 1 | F101: =IF(COUNTIF(DC$6:DC100,1)=0,0,1+_xlfn.MAXIFS($F$6:$F100,DC$6:DC100,1)) -> 0 | G101: =IF(F101=0,1,SUMIFS($G$6:$G100,DC$6:DC100,1,$F$6:$F100,F101-1)) -> 1 | H101: =IF($A101="T16.4",1,IF(COUNTIFS(DD101:HN101,1,DD$4:HN$4,1)>0,1,0)) -> 0 | DE101: 1
...

Sheet Citations
A1: Who cites whom: Figure 16.2 and the checks of Theorem 16.5(i) (Online Appendix 16.B.1)
A2: Each citation as the book's script reads it (engine data), with the chapters and the positions of the two results in the Dependencies sheet's order. Nine pointers to illustrations are set aside (column K).
A4: Citing result | B4: Cited result | C4: Citing chapter | D4: Cited chapter | E4: Position citing | F4: Position cited | G4: In the matrix? | K4: Pointer set aside (citing > cited)
A5: P2.2 | B5: T2.1 | C5: =VALUE(MID(A5,2,FIND(".",A5)-2)) -> 2 | D5: =VALUE(MID(B5,2,FIND(".",B5)-2)) -> 2 | E5: =MATCH(A5,Dependencies!$A$6:$A$216,0) -> 7 | F5: =MATCH(B5,Dependencies!$A$6:$A$216,0) -> 6 | G5: =INDEX(Dependencies!$L$6:$HN$216,F5,E5) -> 1 | K5: T5.4>T5.3
A6: P2.3 | B6: T2.1 | C6: =VALUE(MID(A6,2,FIND(".",A6)-2)) -> 2 | D6: =VALUE(MID(B6,2,FIND(".",B6)-2)) -> 2 | E6: =MATCH(A6,Dependencies!$A$6:$A$216,0) -> 9 | F6: =MATCH(B6,Dependencies!$A$6:$A$216,0) -> 6 | G6: =INDEX(Dependencies!$L$6:$HN$216,F6,E6) -> 1 | K6: T7.1>P7.1
A7: R2.B.1 | B7: P2.2 | C7: =VALUE(MID(A7,2,FIND(".",A7)-2)) -> 2 | D7: =VALUE(MID(B7,2,FIND(".",B7)-2)) -> 2 | E7: =MATCH(A7,Dependencies!$A$6:$A$216,0) -> 10 | F7: =MATCH(B7,Dependencies!$A$6:$A$216,0) -> 7 | G7: =INDEX(Dependencies!$L$6:$HN$216,F7,E7) -> 1 | K7: T7.1>P7.4
A8: C2.B.2 | B8: T2.2 | C8: =VALUE(MID(A8,2,FIND(".",A8)-2)) -> 2 | D8: =VALUE(MID(B8,2,FIND(".",B8)-2)) -> 2 | E8: =MATCH(A8,Dependencies!$A$6:$A$216,0) -> 11 | F8: =MATCH(B8,Dependencies!$A$6:$A$216,0) -> 8 | G8: =INDEX(Dependencies!$L$6:$HN$216,F8,E8) -> 1 | K8: P7.2>E7.B.4
A9: T3.2 | B9: P3.1 | C9: =VALUE(MID(A9,2,FIND(".",A9)-2)) -> 3 | D9: =VALUE(MID(B9,2,FIND(".",B9)-2)) -> 3 | E9: =MATCH(A9,Dependencies!$A$6:$A$216,0) -> 15 | F9: =MATCH(B9,Dependencies!$A$6:$A$216,0) -> 12 | G9: =INDEX(Dependencies!$L$6:$HN$216,F9,E9) -> 1 | K9: T9.2>E9.B.1
A10: T4.1 | B10: T3.3 | C10: =VALUE(MID(A10,2,FIND(".",A10)-2)) -> 4 | D10: =VALUE(MID(B10,2,FIND(".",B10)-2)) -> 3 | E10: =MATCH(A10,Dependencies!$A$6:$A$216,0) -> 19 | F10: =MATCH(B10,Dependencies!$A$6:$A$216,0) -> 17 | G10: =INDEX(Dependencies!$L$6:$HN$216,F10,E10) -> 1 | K10: T14.5>E14.B.2
A11: P4.1 | B11: T4.1 | C11: =VALUE(MID(A11,2,FIND(".",A11)-2)) -> 4 | D11: =VALUE(MID(B11,2,FIND(".",B11)-2)) -> 4 | E11: =MATCH(A11,Dependencies!$A$6:$A$216,0) -> 20 | F11: =MATCH(B11,Dependencies!$A$6:$A$216,0) -> 19 | G11: =INDEX(Dependencies!$L$6:$HN$216,F11,E11) -> 1 | K11: P15.5>E15.B.1
A12: P4.3 | B12: P3.1 | C12: =VALUE(MID(A12,2,FIND(".",A12)-2)) -> 4 | D12: =VALUE(MID(B12,2,FIND(".",B12)-2)) -> 3 | E12: =MATCH(A12,Dependencies!$A$6:$A$216,0) -> 23 | F12: =MATCH(B12,Dependencies!$A$6:$A$216,0) -> 12 | G12: =INDEX(Dependencies!$L$6:$HN$216,F12,E12) -> 1 | K12: P15.9>E15.B.3
A13: T4.3 | B13: T2.1 | C13: =VALUE(MID(A13,2,FIND(".",A13)-2)) -> 4 | D13: =VALUE(MID(B13,2,FIND(".",B13)-2)) -> 2 | E13: =MATCH(A13,Dependencies!$A$6:$A$216,0) -> 24 | F13: =MATCH(B13,Dependencies!$A$6:$A$216,0) -> 6 | G13: =INDEX(Dependencies!$L$6:$HN$216,F13,E13) -> 1 | K13: T15.2>E15.B.4
A14: T5.1 | B14: T2.1 | C14: =VALUE(MID(A14,2,FIND(".",A14)-2)) -> 5 | D14: =VALUE(MID(B14,2,FIND(".",B14)-2)) -> 2 | E14: =MATCH(A14,Dependencies!$A$6:$A$216,0) -> 27 | F14: =MATCH(B14,Dependencies!$A$6:$A$216,0) -> 6 | G14: =INDEX(Dependencies!$L$6:$HN$216,F14,E14) -> 1
A15: P5.2 | B15: T3.3 | C15: =VALUE(MID(A15,2,FIND(".",A15)-2)) -> 5 | D15: =VALUE(MID(B15,2,FIND(".",B15)-2)) -> 3 | E15: =MATCH(A15,Dependencies!$A$6:$A$216,0) -> 28 | F15: =MATCH(B15,Dependencies!$A$6:$A$216,0) -> 17 | G15: =INDEX(Dependencies!$L$6:$HN$216,F15,E15) -> 1
A16: P5.2 | B16: P5.1 | C16: =VALUE(MID(A16,2,FIND(".",A16)-2)) -> 5 | D16: =VALUE(MID(B16,2,FIND(".",B16)-2)) -> 5 | E16: =MATCH(A16,Dependencies!$A$6:$A$216,0) -> 28 | F16: =MATCH(B16,Dependencies!$A$6:$A$216,0) -> 26 | G16: =INDEX(Dependencies!$L$6:$HN$216,F16,E16) -> 1 | K16: Figure 16.2: citing chapter (row), cited chapter (column) | L16: 1 | M16: 2 | N16: 3 | O16: 4 | P16: 5 | Q16: 6 | R16: 7 | S16: 8 | T16: 9 | U16: 10 | V16: 11 | W16: 12 | X16: 13 | Y16: 14 | Z16: 15 | AA16: 16 | AB16: Results
A17: T5.2 | B17: T3.3 | C17: =VALUE(MID(A17,2,FIND(".",A17)-2)) -> 5 | D17: =VALUE(MID(B17,2,FIND(".",B17)-2)) -> 3 | E17: =MATCH(A17,Dependencies!$A$6:$A$216,0) -> 29 | F17: =MATCH(B17,Dependencies!$A$6:$A$216,0) -> 17 | G17: =INDEX(Dependencies!$L$6:$HN$216,F17,E17) -> 1 | K17: 1 | L17: =COUNTIFS($C$5:$C$306,$K17,$D$5:$D$306,1) -> 0 | M17: =COUNTIFS($C$5:$C$306,$K17,$D$5:$D$306,2) -> 0 | N17: =COUNTIFS($C$5:$C$306,$K17,$D$5:$D$306,3) -> 0 | O17: =COUNTIFS($C$5:$C$306,$K17,$D$5:$D$306,4) -> 0 | P17: =COUNTIFS($C$5:$C$306,$K17,$D$5:$D$306,5) -> 0 | Q17: =COUNTIFS($C$5:$C$306,$K17,$D$5:$D$306,6) -> 0 | R17: =COUNTIFS($C$5:$C$306,$K17,$D$5:$D$306,7) -> 0 | S17: =COUNTIFS($C$5:$C$306,$K17,$D$5:$D$306,8) -> 0 | T17: =COUNTIFS($C$5:$C$306,$K17,$D$5:$D$306,9) -> 0 | U17: =COUNTIFS($C$5:$C$306,$K17,$D$5:$D$306,10) -> 0 | V17: =COUNTIFS($C$5:$C$306,$K17,$D$5:$D$306,11) -> 0 | W17: =COUNTIFS($C$5:$C$306,$K17,$D$5:$D$306,12) -> 0 | X17: =COUNTIFS($C$5:$C$306,$K17,$D$5:$D$306,13) -> 0 | Y17: =COUNTIFS($C$5:$C$306,$K17,$D$5:$D$306,14) -> 0 | Z17: =COUNTIFS($C$5:$C$306,$K17,$D$5:$D$306,15) -> 0 | AA17: =COUNTIFS($C$5:$C$306,$K17,$D$5:$D$306,16) -> 0 | AB17: =COUNTIF(Dependencies!$C$6:$C$216,$K17) -> 4
A18: T5.2 | B18: P5.2 | C18: =VALUE(MID(A18,2,FIND(".",A18)-2)) -> 5 | D18: =VALUE(MID(B18,2,FIND(".",B18)-2)) -> 5 | E18: =MATCH(A18,Dependencies!$A$6:$A$216,0) -> 29 | F18: =MATCH(B18,Dependencies!$A$6:$A$216,0) -> 28 | G18: =INDEX(Dependencies!$L$6:$HN$216,F18,E18) -> 1 | K18: 2 | L18: =COUNTIFS($C$5:$C$306,$K18,$D$5:$D$306,1) -> 0 | M18: =COUNTIFS($C$5:$C$306,$K18,$D$5:$D$306,2) -> 4 | N18: =COUNTIFS($C$5:$C$306,$K18,$D$5:$D$306,3) -> 0 | O18: =COUNTIFS($C$5:$C$306,$K18,$D$5:$D$306,4) -> 0 | P18: =COUNTIFS($C$5:$C$306,$K18,$D$5:$D$306,5) -> 0 | Q18: =COUNTIFS($C$5:$C$306,$K18,$D$5:$D$306,6) -> 0 | R18: =COUNTIFS($C$5:$C$306,$K18,$D$5:$D$306,7) -> 0 | S18: =COUNTIFS($C$5:$C$306,$K18,$D$5:$D$306,8) -> 0 | T18: =COUNTIFS($C$5:$C$306,$K18,$D$5:$D$306,9) -> 0 | U18: =COUNTIFS($C$5:$C$306,$K18,$D$5:$D$306,10) -> 0 | V18: =COUNTIFS($C$5:$C$306,$K18,$D$5:$D$306,11) -> 0 | W18: =COUNTIFS($C$5:$C$306,$K18,$D$5:$D$306,12) -> 0 | X18: =COUNTIFS($C$5:$C$306,$K18,$D$5:$D$306,13) -> 0 | Y18: =COUNTIFS($C$5:$C$306,$K18,$D$5:$D$306,14) -> 0 | Z18: =COUNTIFS($C$5:$C$306,$K18,$D$5:$D$306,15) -> 0 | AA18: =COUNTIFS($C$5:$C$306,$K18,$D$5:$D$306,16) -> 0 | AB18: =COUNTIF(Dependencies!$C$6:$C$216,$K18) -> 7
A19: P5.3 | B19: P3.1 | C19: =VALUE(MID(A19,2,FIND(".",A19)-2)) -> 5 | D19: =VALUE(MID(B19,2,FIND(".",B19)-2)) -> 3 | E19: =MATCH(A19,Dependencies!$A$6:$A$216,0) -> 30 | F19: =MATCH(B19,Dependencies!$A$6:$A$216,0) -> 12 | G19: =INDEX(Dependencies!$L$6:$HN$216,F19,E19) -> 1 | K19: 3 | L19: =COUNTIFS($C$5:$C$306,$K19,$D$5:$D$306,1) -> 0 | M19: =COUNTIFS($C$5:$C$306,$K19,$D$5:$D$306,2) -> 0 | N19: =COUNTIFS($C$5:$C$306,$K19,$D$5:$D$306,3) -> 1 | O19: =COUNTIFS($C$5:$C$306,$K19,$D$5:$D$306,4) -> 0 | P19: =COUNTIFS($C$5:$C$306,$K19,$D$5:$D$306,5) -> 0 | Q19: =COUNTIFS($C$5:$C$306,$K19,$D$5:$D$306,6) -> 0 | R19: =COUNTIFS($C$5:$C$306,$K19,$D$5:$D$306,7) -> 0 | S19: =COUNTIFS($C$5:$C$306,$K19,$D$5:$D$306,8) -> 0 | T19: =COUNTIFS($C$5:$C$306,$K19,$D$5:$D$306,9) -> 0 | U19: =COUNTIFS($C$5:$C$306,$K19,$D$5:$D$306,10) -> 0 | V19: =COUNTIFS($C$5:$C$306,$K19,$D$5:$D$306,11) -> 0 | W19: =COUNTIFS($C$5:$C$306,$K19,$D$5:$D$306,12) -> 0 | X19: =COUNTIFS($C$5:$C$306,$K19,$D$5:$D$306,13) -> 0 | Y19: =COUNTIFS($C$5:$C$306,$K19,$D$5:$D$306,14) -> 0 | Z19: =COUNTIFS($C$5:$C$306,$K19,$D$5:$D$306,15) -> 0 | AA19: =COUNTIFS($C$5:$C$306,$K19,$D$5:$D$306,16) -> 0 | AB19: =COUNTIF(Dependencies!$C$6:$C$216,$K19) -> 7
A20: T5.3 | B20: T2.1 | C20: =VALUE(MID(A20,2,FIND(".",A20)-2)) -> 5 | D20: =VALUE(MID(B20,2,FIND(".",B20)-2)) -> 2 | E20: =MATCH(A20,Dependencies!$A$6:$A$216,0) -> 32 | F20: =MATCH(B20,Dependencies!$A$6:$A$216,0) -> 6 | G20: =INDEX(Dependencies!$L$6:$HN$216,F20,E20) -> 1 | K20: 4 | L20: =COUNTIFS($C$5:$C$306,$K20,$D$5:$D$306,1) -> 0 | M20: =COUNTIFS($C$5:$C$306,$K20,$D$5:$D$306,2) -> 1 | N20: =COUNTIFS($C$5:$C$306,$K20,$D$5:$D$306,3) -> 2 | O20: =COUNTIFS($C$5:$C$306,$K20,$D$5:$D$306,4) -> 1 | P20: =COUNTIFS($C$5:$C$306,$K20,$D$5:$D$306,5) -> 0 | Q20: =COUNTIFS($C$5:$C$306,$K20,$D$5:$D$306,6) -> 0 | R20: =COUNTIFS($C$5:$C$306,$K20,$D$5:$D$306,7) -> 0 | S20: =COUNTIFS($C$5:$C$306,$K20,$D$5:$D$306,8) -> 0 | T20: =COUNTIFS($C$5:$C$306,$K20,$D$5:$D$306,9) -> 0 | U20: =COUNTIFS($C$5:$C$306,$K20,$D$5:$D$306,10) -> 0 | V20: =COUNTIFS($C$5:$C$306,$K20,$D$5:$D$306,11) -> 0 | W20: =COUNTIFS($C$5:$C$306,$K20,$D$5:$D$306,12) -> 0 | X20: =COUNTIFS($C$5:$C$306,$K20,$D$5:$D$306,13) -> 0 | Y20: =COUNTIFS($C$5:$C$306,$K20,$D$5:$D$306,14) -> 0 | Z20: =COUNTIFS($C$5:$C$306,$K20,$D$5:$D$306,15) -> 0 | AA20: =COUNTIFS($C$5:$C$306,$K20,$D$5:$D$306,16) -> 0 | AB20: =COUNTIF(Dependencies!$C$6:$C$216,$K20) -> 7
A21: T5.3 | B21: T5.4 | C21: =VALUE(MID(A21,2,FIND(".",A21)-2)) -> 5 | D21: =VALUE(MID(B21,2,FIND(".",B21)-2)) -> 5 | E21: =MATCH(A21,Dependencies!$A$6:$A$216,0) -> 32 | F21: =MATCH(B21,Dependencies!$A$6:$A$216,0) -> 31 | G21: =INDEX(Dependencies!$L$6:$HN$216,F21,E21) -> 1 | K21: 5 | L21: =COUNTIFS($C$5:$C$306,$K21,$D$5:$D$306,1) -> 0 | M21: =COUNTIFS($C$5:$C$306,$K21,$D$5:$D$306,2) -> 2 | N21: =COUNTIFS($C$5:$C$306,$K21,$D$5:$D$306,3) -> 3 | O21: =COUNTIFS($C$5:$C$306,$K21,$D$5:$D$306,4) -> 0 | P21: =COUNTIFS($C$5:$C$306,$K21,$D$5:$D$306,5) -> 10 | Q21: =COUNTIFS($C$5:$C$306,$K21,$D$5:$D$306,6) -> 0 | R21: =COUNTIFS($C$5:$C$306,$K21,$D$5:$D$306,7) -> 0 | S21: =COUNTIFS($C$5:$C$306,$K21,$D$5:$D$306,8) -> 0 | T21: =COUNTIFS($C$5:$C$306,$K21,$D$5:$D$306,9) -> 0 | U21: =COUNTIFS($C$5:$C$306,$K21,$D$5:$D$306,10) -> 0 | V21: =COUNTIFS($C$5:$C$306,$K21,$D$5:$D$306,11) -> 0 | W21: =COUNTIFS($C$5:$C$306,$K21,$D$5:$D$306,12) -> 0 | X21: =COUNTIFS($C$5:$C$306,$K21,$D$5:$D$306,13) -> 0 | Y21: =COUNTIFS($C$5:$C$306,$K21,$D$5:$D$306,14) -> 0 | Z21: =COUNTIFS($C$5:$C$306,$K21,$D$5:$D$306,15) -> 0 | AA21: =COUNTIFS($C$5:$C$306,$K21,$D$5:$D$306,16) -> 0 | AB21: =COUNTIF(Dependencies!$C$6:$C$216,$K21) -> 17
A22: P5.4 | B22: P5.3 | C22: =VALUE(MID(A22,2,FIND(".",A22)-2)) -> 5 | D22: =VALUE(MID(B22,2,FIND(".",B22)-2)) -> 5 | E22: =MATCH(A22,Dependencies!$A$6:$A$216,0) -> 33 | F22: =MATCH(B22,Dependencies!$A$6:$A$216,0) -> 30 | G22: =INDEX(Dependencies!$L$6:$HN$216,F22,E22) -> 1 | K22: 6 | L22: =COUNTIFS($C$5:$C$306,$K22,$D$5:$D$306,1) -> 0 | M22: =COUNTIFS($C$5:$C$306,$K22,$D$5:$D$306,2) -> 1 | N22: =COUNTIFS($C$5:$C$306,$K22,$D$5:$D$306,3) -> 4 | O22: =COUNTIFS($C$5:$C$306,$K22,$D$5:$D$306,4) -> 0 | P22: =COUNTIFS($C$5:$C$306,$K22,$D$5:$D$306,5) -> 3 | Q22: =COUNTIFS($C$5:$C$306,$K22,$D$5:$D$306,6) -> 7 | R22: =COUNTIFS($C$5:$C$306,$K22,$D$5:$D$306,7) -> 0 | S22: =COUNTIFS($C$5:$C$306,$K22,$D$5:$D$306,8) -> 0 | T22: =COUNTIFS($C$5:$C$306,$K22,$D$5:$D$306,9) -> 0 | U22: =COUNTIFS($C$5:$C$306,$K22,$D$5:$D$306,10) -> 0 | V22: =COUNTIFS($C$5:$C$306,$K22,$D$5:$D$306,11) -> 0 | W22: =COUNTIFS($C$5:$C$306,$K22,$D$5:$D$306,12) -> 0 | X22: =COUNTIFS($C$5:$C$306,$K22,$D$5:$D$306,13) -> 0 | Y22: =COUNTIFS($C$5:$C$306,$K22,$D$5:$D$306,14) -> 0 | Z22: =COUNTIFS($C$5:$C$306,$K22,$D$5:$D$306,15) -> 0 | AA22: =COUNTIFS($C$5:$C$306,$K22,$D$5:$D$306,16) -> 0 | AB22: =COUNTIF(Dependencies!$C$6:$C$216,$K22) -> 13
A23: P5.4 | B23: T5.3 | C23: =VALUE(MID(A23,2,FIND(".",A23)-2)) -> 5 | D23: =VALUE(MID(B23,2,FIND(".",B23)-2)) -> 5 | E23: =MATCH(A23,Dependencies!$A$6:$A$216,0) -> 33 | F23: =MATCH(B23,Dependencies!$A$6:$A$216,0) -> 32 | G23: =INDEX(Dependencies!$L$6:$HN$216,F23,E23) -> 1 | K23: 7 | L23: =COUNTIFS($C$5:$C$306,$K23,$D$5:$D$306,1) -> 0 | M23: =COUNTIFS($C$5:$C$306,$K23,$D$5:$D$306,2) -> 3 | N23: =COUNTIFS($C$5:$C$306,$K23,$D$5:$D$306,3) -> 0 | O23: =COUNTIFS($C$5:$C$306,$K23,$D$5:$D$306,4) -> 0 | P23: =COUNTIFS($C$5:$C$306,$K23,$D$5:$D$306,5) -> 6 | Q23: =COUNTIFS($C$5:$C$306,$K23,$D$5:$D$306,6) -> 0 | R23: =COUNTIFS($C$5:$C$306,$K23,$D$5:$D$306,7) -> 19 | S23: =COUNTIFS($C$5:$C$306,$K23,$D$5:$D$306,8) -> 0 | T23: =COUNTIFS($C$5:$C$306,$K23,$D$5:$D$306,9) -> 0 | U23: =COUNTIFS($C$5:$C$306,$K23,$D$5:$D$306,10) -> 0 | V23: =COUNTIFS($C$5:$C$306,$K23,$D$5:$D$306,11) -> 0 | W23: =COUNTIFS($C$5:$C$306,$K23,$D$5:$D$306,12) -> 0 | X23: =COUNTIFS($C$5:$C$306,$K23,$D$5:$D$306,13) -> 0 | Y23: =COUNTIFS($C$5:$C$306,$K23,$D$5:$D$306,14) -> 0 | Z23: =COUNTIFS($C$5:$C$306,$K23,$D$5:$D$306,15) -> 0 | AA23: =COUNTIFS($C$5:$C$306,$K23,$D$5:$D$306,16) -> 0 | AB23: =COUNTIF(Dependencies!$C$6:$C$216,$K23) -> 18
A24: E5.B.1 | B24: T5.3 | C24: =VALUE(MID(A24,2,FIND(".",A24)-2)) -> 5 | D24: =VALUE(MID(B24,2,FIND(".",B24)-2)) -> 5 | E24: =MATCH(A24,Dependencies!$A$6:$A$216,0) -> 36 | F24: =MATCH(B24,Dependencies!$A$6:$A$216,0) -> 32 | G24: =INDEX(Dependencies!$L$6:$HN$216,F24,E24) -> 1 | K24: 8 | L24: =COUNTIFS($C$5:$C$306,$K24,$D$5:$D$306,1) -> 0 | M24: =COUNTIFS($C$5:$C$306,$K24,$D$5:$D$306,2) -> 2 | N24: =COUNTIFS($C$5:$C$306,$K24,$D$5:$D$306,3) -> 0 | O24: =COUNTIFS($C$5:$C$306,$K24,$D$5:$D$306,4) -> 1 | P24: =COUNTIFS($C$5:$C$306,$K24,$D$5:$D$306,5) -> 2 | Q24: =COUNTIFS($C$5:$C$306,$K24,$D$5:$D$306,6) -> 1 | R24: =COUNTIFS($C$5:$C$306,$K24,$D$5:$D$306,7) -> 1 | S24: =COUNTIFS($C$5:$C$306,$K24,$D$5:$D$306,8) -> 10 | T24: =COUNTIFS($C$5:$C$306,$K24,$D$5:$D$306,9) -> 0 | U24: =COUNTIFS($C$5:$C$306,$K24,$D$5:$D$306,10) -> 0 | V24: =COUNTIFS($C$5:$C$306,$K24,$D$5:$D$306,11) -> 0 | W24: =COUNTIFS($C$5:$C$306,$K24,$D$5:$D$306,12) -> 0 | X24: =COUNTIFS($C$5:$C$306,$K24,$D$5:$D$306,13) -> 0 | Y24: =COUNTIFS($C$5:$C$306,$K24,$D$5:$D$306,14) -> 0 | Z24: =COUNTIFS($C$5:$C$306,$K24,$D$5:$D$306,15) -> 0 | AA24: =COUNTIFS($C$5:$C$306,$K24,$D$5:$D$306,16) -> 0 | AB24: =COUNTIF(Dependencies!$C$6:$C$216,$K24) -> 18
A25: E5.B.4 | B25: T5.4 | C25: =VALUE(MID(A25,2,FIND(".",A25)-2)) -> 5 | D25: =VALUE(MID(B25,2,FIND(".",B25)-2)) -> 5 | E25: =MATCH(A25,Dependencies!$A$6:$A$216,0) -> 39 | F25: =MATCH(B25,Dependencies!$A$6:$A$216,0) -> 31 | G25: =INDEX(Dependencies!$L$6:$HN$216,F25,E25) -> 1 | K25: 9 | L25: =COUNTIFS($C$5:$C$306,$K25,$D$5:$D$306,1) -> 0 | M25: =COUNTIFS($C$5:$C$306,$K25,$D$5:$D$306,2) -> 1 | N25: =COUNTIFS($C$5:$C$306,$K25,$D$5:$D$306,3) -> 0 | O25: =COUNTIFS($C$5:$C$306,$K25,$D$5:$D$306,4) -> 2 | P25: =COUNTIFS($C$5:$C$306,$K25,$D$5:$D$306,5) -> 0 | Q25: =COUNTIFS($C$5:$C$306,$K25,$D$5:$D$306,6) -> 0 | R25: =COUNTIFS($C$5:$C$306,$K25,$D$5:$D$306,7) -> 0 | S25: =COUNTIFS($C$5:$C$306,$K25,$D$5:$D$306,8) -> 0 | T25: =COUNTIFS($C$5:$C$306,$K25,$D$5:$D$306,9) -> 10 | U25: =COUNTIFS($C$5:$C$306,$K25,$D$5:$D$306,10) -> 0 | V25: =COUNTIFS($C$5:$C$306,$K25,$D$5:$D$306,11) -> 0 | W25: =COUNTIFS($C$5:$C$306,$K25,$D$5:$D$306,12) -> 0 | X25: =COUNTIFS($C$5:$C$306,$K25,$D$5:$D$306,13) -> 0 | Y25: =COUNTIFS($C$5:$C$306,$K25,$D$5:$D$306,14) -> 0 | Z25: =COUNTIFS($C$5:$C$306,$K25,$D$5:$D$306,15) -> 0 | AA25: =COUNTIFS($C$5:$C$306,$K25,$D$5:$D$306,16) -> 0 | AB25: =COUNTIF(Dependencies!$C$6:$C$216,$K25) -> 18
A26: R5.B.5 | B26: E5.B.4 | C26: =VALUE(MID(A26,2,FIND(".",A26)-2)) -> 5 | D26: =VALUE(MID(B26,2,FIND(".",B26)-2)) -> 5 | E26: =MATCH(A26,Dependencies!$A$6:$A$216,0) -> 40 | F26: =MATCH(B26,Dependencies!$A$6:$A$216,0) -> 39 | G26: =INDEX(Dependencies!$L$6:$HN$216,F26,E26) -> 1 | K26: 10 | L26: =COUNTIFS($C$5:$C$306,$K26,$D$5:$D$306,1) -> 0 | M26: =COUNTIFS($C$5:$C$306,$K26,$D$5:$D$306,2) -> 0 | N26: =COUNTIFS($C$5:$C$306,$K26,$D$5:$D$306,3) -> 0 | O26: =COUNTIFS($C$5:$C$306,$K26,$D$5:$D$306,4) -> 1 | P26: =COUNTIFS($C$5:$C$306,$K26,$D$5:$D$306,5) -> 0 | Q26: =COUNTIFS($C$5:$C$306,$K26,$D$5:$D$306,6) -> 1 | R26: =COUNTIFS($C$5:$C$306,$K26,$D$5:$D$306,7) -> 1 | S26: =COUNTIFS($C$5:$C$306,$K26,$D$5:$D$306,8) -> 0 | T26: =COUNTIFS($C$5:$C$306,$K26,$D$5:$D$306,9) -> 3 | U26: =COUNTIFS($C$5:$C$306,$K26,$D$5:$D$306,10) -> 8 | V26: =COUNTIFS($C$5:$C$306,$K26,$D$5:$D$306,11) -> 0 | W26: =COUNTIFS($C$5:$C$306,$K26,$D$5:$D$306,12) -> 0 | X26: =COUNTIFS($C$5:$C$306,$K26,$D$5:$D$306,13) -> 0 | Y26: =COUNTIFS($C$5:$C$306,$K26,$D$5:$D$306,14) -> 0 | Z26: =COUNTIFS($C$5:$C$306,$K26,$D$5:$D$306,15) -> 0 | AA26: =COUNTIFS($C$5:$C$306,$K26,$D$5:$D$306,16) -> 0 | AB26: =COUNTIF(Dependencies!$C$6:$C$216,$K26) -> 16
A27: E5.B.6 | B27: T5.4 | C27: =VALUE(MID(A27,2,FIND(".",A27)-2)) -> 5 | D27: =VALUE(MID(B27,2,FIND(".",B27)-2)) -> 5 | E27: =MATCH(A27,Dependencies!$A$6:$A$216,0) -> 41 | F27: =MATCH(B27,Dependencies!$A$6:$A$216,0) -> 31 | G27: =INDEX(Dependencies!$L$6:$HN$216,F27,E27) -> 1 | K27: 11 | L27: =COUNTIFS($C$5:$C$306,$K27,$D$5:$D$306,1) -> 0 | M27: =COUNTIFS($C$5:$C$306,$K27,$D$5:$D$306,2) -> 0 | N27: =COUNTIFS($C$5:$C$306,$K27,$D$5:$D$306,3) -> 0 | O27: =COUNTIFS($C$5:$C$306,$K27,$D$5:$D$306,4) -> 1 | P27: =COUNTIFS($C$5:$C$306,$K27,$D$5:$D$306,5) -> 0 | Q27: =COUNTIFS($C$5:$C$306,$K27,$D$5:$D$306,6) -> 0 | R27: =COUNTIFS($C$5:$C$306,$K27,$D$5:$D$306,7) -> 1 | S27: =COUNTIFS($C$5:$C$306,$K27,$D$5:$D$306,8) -> 4 | T27: =COUNTIFS($C$5:$C$306,$K27,$D$5:$D$306,9) -> 3 | U27: =COUNTIFS($C$5:$C$306,$K27,$D$5:$D$306,10) -> 0 | V27: =COUNTIFS($C$5:$C$306,$K27,$D$5:$D$306,11) -> 7 | W27: =COUNTIFS($C$5:$C$306,$K27,$D$5:$D$306,12) -> 0 | X27: =COUNTIFS($C$5:$C$306,$K27,$D$5:$D$306,13) -> 0 | Y27: =COUNTIFS($C$5:$C$306,$K27,$D$5:$D$306,14) -> 0 | Z27: =COUNTIFS($C$5:$C$306,$K27,$D$5:$D$306,15) -> 0 | AA27: =COUNTIFS($C$5:$C$306,$K27,$D$5:$D$306,16) -> 0 | AB27: =COUNTIF(Dependencies!$C$6:$C$216,$K27) -> 14
A28: E5.B.7 | B28: T5.4 | C28: =VALUE(MID(A28,2,FIND(".",A28)-2)) -> 5 | D28: =VALUE(MID(B28,2,FIND(".",B28)-2)) -> 5 | E28: =MATCH(A28,Dependencies!$A$6:$A$216,0) -> 42 | F28: =MATCH(B28,Dependencies!$A$6:$A$216,0) -> 31 | G28: =INDEX(Dependencies!$L$6:$HN$216,F28,E28) -> 1 | K28: 12 | L28: =COUNTIFS($C$5:$C$306,$K28,$D$5:$D$306,1) -> 0 | M28: =COUNTIFS($C$5:$C$306,$K28,$D$5:$D$306,2) -> 0 | N28: =COUNTIFS($C$5:$C$306,$K28,$D$5:$D$306,3) -> 0 | O28: =COUNTIFS($C$5:$C$306,$K28,$D$5:$D$306,4) -> 0 | P28: =COUNTIFS($C$5:$C$306,$K28,$D$5:$D$306,5) -> 0 | Q28: =COUNTIFS($C$5:$C$306,$K28,$D$5:$D$306,6) -> 0 | R28: =COUNTIFS($C$5:$C$306,$K28,$D$5:$D$306,7) -> 3 | S28: =COUNTIFS($C$5:$C$306,$K28,$D$5:$D$306,8) -> 3 | T28: =COUNTIFS($C$5:$C$306,$K28,$D$5:$D$306,9) -> 2 | U28: =COUNTIFS($C$5:$C$306,$K28,$D$5:$D$306,10) -> 1 | V28: =COUNTIFS($C$5:$C$306,$K28,$D$5:$D$306,11) -> 2 | W28: =COUNTIFS($C$5:$C$306,$K28,$D$5:$D$306,12) -> 6 | X28: =COUNTIFS($C$5:$C$306,$K28,$D$5:$D$306,13) -> 0 | Y28: =COUNTIFS($C$5:$C$306,$K28,$D$5:$D$306,14) -> 0 | Z28: =COUNTIFS($C$5:$C$306,$K28,$D$5:$D$306,15) -> 0 | AA28: =COUNTIFS($C$5:$C$306,$K28,$D$5:$D$306,16) -> 0 | AB28: =COUNTIF(Dependencies!$C$6:$C$216,$K28) -> 13
... A32: T6.3 | B32: P6.2 | C32: =VALUE(MID(A32,2,FIND(".",A32)-2)) -> 6 | D32: =VALUE(MID(B32,2,FIND(".",B32)-2)) -> 6 | E32: =MATCH(A32,Dependencies!$A$6:$A$216,0) -> 47 | F32: =MATCH(B32,Dependencies!$A$6:$A$216,0) -> 45 | G32: =INDEX(Dependencies!$L$6:$HN$216,F32,E32) -> 1 | K32: 16 | L32: =COUNTIFS($C$5:$C$306,$K32,$D$5:$D$306,1) -> 0 | M32: =COUNTIFS($C$5:$C$306,$K32,$D$5:$D$306,2) -> 0 | N32: =COUNTIFS($C$5:$C$306,$K32,$D$5:$D$306,3) -> 0 | O32: =COUNTIFS($C$5:$C$306,$K32,$D$5:$D$306,4) -> 2 | P32: =COUNTIFS($C$5:$C$306,$K32,$D$5:$D$306,5) -> 0 | Q32: =COUNTIFS($C$5:$C$306,$K32,$D$5:$D$306,6) -> 0 | R32: =COUNTIFS($C$5:$C$306,$K32,$D$5:$D$306,7) -> 0 | S32: =COUNTIFS($C$5:$C$306,$K32,$D$5:$D$306,8) -> 0 | T32: =COUNTIFS($C$5:$C$306,$K32,$D$5:$D$306,9) -> 0 | U32: =COUNTIFS($C$5:$C$306,$K32,$D$5:$D$306,10) -> 0 | V32: =COUNTIFS($C$5:$C$306,$K32,$D$5:$D$306,11) -> 0 | W32: =COUNTIFS($C$5:$C$306,$K32,$D$5:$D$306,12) -> 0 | X32: =COUNTIFS($C$5:$C$306,$K32,$D$5:$D$306,13) -> 5 | Y32: =COUNTIFS($C$5:$C$306,$K32,$D$5:$D$306,14) -> 7 | Z32: =COUNTIFS($C$5:$C$306,$K32,$D$5:$D$306,15) -> 12 | AA32: =COUNTIFS($C$5:$C$306,$K32,$D$5:$D$306,16) -> 4 | AB32: =COUNTIF(Dependencies!$C$6:$C$216,$K32) -> 9
A33: P6.4 | B33: P3.1 | C33: =VALUE(MID(A33,2,FIND(".",A33)-2)) -> 6 | D33: =VALUE(MID(B33,2,FIND(".",B33)-2)) -> 3 | E33: =MATCH(A33,Dependencies!$A$6:$A$216,0) -> 48 | F33: =MATCH(B33,Dependencies!$A$6:$A$216,0) -> 12 | G33: =INDEX(Dependencies!$L$6:$HN$216,F33,E33) -> 1
A34: T6.2 | B34: P3.1 | C34: =VALUE(MID(A34,2,FIND(".",A34)-2)) -> 6 | D34: =VALUE(MID(B34,2,FIND(".",B34)-2)) -> 3 | E34: =MATCH(A34,Dependencies!$A$6:$A$216,0) -> 49 | F34: =MATCH(B34,Dependencies!$A$6:$A$216,0) -> 12 | G34: =INDEX(Dependencies!$L$6:$HN$216,F34,E34) -> 1
A35: T6.2 | B35: T3.2 | C35: =VALUE(MID(A35,2,FIND(".",A35)-2)) -> 6 | D35: =VALUE(MID(B35,2,FIND(".",B35)-2)) -> 3 | E35: =MATCH(A35,Dependencies!$A$6:$A$216,0) -> 49 | F35: =MATCH(B35,Dependencies!$A$6:$A$216,0) -> 15 | G35: =INDEX(Dependencies!$L$6:$HN$216,F35,E35) -> 1 | K35: Numbered results | L35: =COUNTA(Dependencies!A6:A216) -> 211 | M35: 211
A36: T6.2 | B36: P6.2 | C36: =VALUE(MID(A36,2,FIND(".",A36)-2)) -> 6 | D36: =VALUE(MID(B36,2,FIND(".",B36)-2)) -> 6 | E36: =MATCH(A36,Dependencies!$A$6:$A$216,0) -> 49 | F36: =MATCH(B36,Dependencies!$A$6:$A$216,0) -> 45 | G36: =INDEX(Dependencies!$L$6:$HN$216,F36,E36) -> 1 | K36: Citations | L36: =COUNTA(A5:A306) -> 302 | M36: 302
A37: T6.2 | B37: P6.3 | C37: =VALUE(MID(A37,2,FIND(".",A37)-2)) -> 6 | D37: =VALUE(MID(B37,2,FIND(".",B37)-2)) -> 6 | E37: =MATCH(A37,Dependencies!$A$6:$A$216,0) -> 49 | F37: =MATCH(B37,Dependencies!$A$6:$A$216,0) -> 46 | G37: =INDEX(Dependencies!$L$6:$HN$216,F37,E37) -> 1 | K37: Pointers set aside | L37: =COUNTA(K5:K13) -> 9 | M37: nine
A38: T6.2 | B38: P6.4 | C38: =VALUE(MID(A38,2,FIND(".",A38)-2)) -> 6 | D38: =VALUE(MID(B38,2,FIND(".",B38)-2)) -> 6 | E38: =MATCH(A38,Dependencies!$A$6:$A$216,0) -> 49 | F38: =MATCH(B38,Dependencies!$A$6:$A$216,0) -> 48 | G38: =INDEX(Dependencies!$L$6:$HN$216,F38,E38) -> 1 | K38: Within a chapter (the diagonal) | L38: =L17+M18+N19+O20+P21+Q22+R23+S24+T25+U26+V27+W28+X29+Y30+Z31+AA32 -> 138 | M38: 138
A39: P6.5 | B39: P6.2 | C39: =VALUE(MID(A39,2,FIND(".",A39)-2)) -> 6 | D39: =VALUE(MID(B39,2,FIND(".",B39)-2)) -> 6 | E39: =MATCH(A39,Dependencies!$A$6:$A$216,0) -> 51 | F39: =MATCH(B39,Dependencies!$A$6:$A$216,0) -> 45 | G39: =INDEX(Dependencies!$L$6:$HN$216,F39,E39) -> 1 | K39: To earlier chapters | L39: =SUMPRODUCT(--(D5:D306<C5:C306)) -> 164 | M39: 164
A40: T6.5 | B40: T5.4 | C40: =VALUE(MID(A40,2,FIND(".",A40)-2)) -> 6 | D40: =VALUE(MID(B40,2,FIND(".",B40)-2)) -> 5 | E40: =MATCH(A40,Dependencies!$A$6:$A$216,0) -> 52 | F40: =MATCH(B40,Dependencies!$A$6:$A$216,0) -> 31 | G40: =INDEX(Dependencies!$L$6:$HN$216,F40,E40) -> 1 | K40: To later chapters (above the diagonal) | L40: =SUM(M17:AA17)+SUM(N18:AA18)+SUM(O19:AA19)+SUM(P20:AA20)+SUM(Q21:AA21)+SUM(R22:AA22)+SUM(S23:AA23)+SUM(T24:AA24)+SUM(U25:AA25)+SUM(V26:AA26)+SUM(W27:AA27)+SUM(X28:AA28)+SUM(Y29:AA29)+SUM(Z30:AA30)+SUM(AA31:AA31) -> 0 | M40: none
A41: E6.B.1 | B41: T5.4 | C41: =VALUE(MID(A41,2,FIND(".",A41)-2)) -> 6 | D41: =VALUE(MID(B41,2,FIND(".",B41)-2)) -> 5 | E41: =MATCH(A41,Dependencies!$A$6:$A$216,0) -> 53 | F41: =MATCH(B41,Dependencies!$A$6:$A$216,0) -> 31 | G41: =INDEX(Dependencies!$L$6:$HN$216,F41,E41) -> 1 | K41: Citations against the order (cited after citing) | L41: =SUMPRODUCT(--(F5:F306>=E5:E306)) -> 0 | M41: none: an order with every cited result first exists, so there is no loop
A42: E6.B.1 | B42: T6.1 | C42: =VALUE(MID(A42,2,FIND(".",A42)-2)) -> 6 | D42: =VALUE(MID(B42,2,FIND(".",B42)-2)) -> 6 | E42: =MATCH(A42,Dependencies!$A$6:$A$216,0) -> 53 | F42: =MATCH(B42,Dependencies!$A$6:$A$216,0) -> 44 | G42: =INDEX(Dependencies!$L$6:$HN$216,F42,E42) -> 1 | K42: Citations found in the matrix | L42: =SUM(G5:G306) -> 302 | M42: 302: the two copies agree
A43: R6.B.3 | B43: T6.4 | C43: =VALUE(MID(A43,2,FIND(".",A43)-2)) -> 6 | D43: =VALUE(MID(B43,2,FIND(".",B43)-2)) -> 6 | E43: =MATCH(A43,Dependencies!$A$6:$A$216,0) -> 55 | F43: =MATCH(B43,Dependencies!$A$6:$A$216,0) -> 50 | G43: =INDEX(Dependencies!$L$6:$HN$216,F43,E43) -> 1 | K43: Results per chapter, in all | L43: =SUM(AB17:AB32) -> 211 | M43: 211
A44: T7.1 | B44: T2.1 | C44: =VALUE(MID(A44,2,FIND(".",A44)-2)) -> 7 | D44: =VALUE(MID(B44,2,FIND(".",B44)-2)) -> 2 | E44: =MATCH(A44,Dependencies!$A$6:$A$216,0) -> 56 | F44: =MATCH(B44,Dependencies!$A$6:$A$216,0) -> 6 | G44: =INDEX(Dependencies!$L$6:$HN$216,F44,E44) -> 1 | K44: The dependency navigator | L44: Value | M44: Reading
A45: T7.1 | B45: P5.3 | C45: =VALUE(MID(A45,2,FIND(".",A45)-2)) -> 7 | D45: =VALUE(MID(B45,2,FIND(".",B45)-2)) -> 5 | E45: =MATCH(A45,Dependencies!$A$6:$A$216,0) -> 56 | F45: =MATCH(B45,Dependencies!$A$6:$A$216,0) -> 30 | G45: =INDEX(Dependencies!$L$6:$HN$216,F45,E45) -> 1 | K45: Results citing no other result | L45: =COUNTIF(Dependencies!D6:D216,0) -> 62 | M45: 62
A46: T7.1 | B46: T5.3 | C46: =VALUE(MID(A46,2,FIND(".",A46)-2)) -> 7 | D46: =VALUE(MID(B46,2,FIND(".",B46)-2)) -> 5 | E46: =MATCH(A46,Dependencies!$A$6:$A$216,0) -> 56 | F46: =MATCH(B46,Dependencies!$A$6:$A$216,0) -> 32 | G46: =INDEX(Dependencies!$L$6:$HN$216,F46,E46) -> 1 | K46: Longest chain of citations | L46: =MAX(Dependencies!F6:F216) -> 15 | M46: 15
A47: T7.1 | B47: T5.4 | C47: =VALUE(MID(A47,2,FIND(".",A47)-2)) -> 7 | D47: =VALUE(MID(B47,2,FIND(".",B47)-2)) -> 5 | E47: =MATCH(A47,Dependencies!$A$6:$A$216,0) -> 56 | F47: =MATCH(B47,Dependencies!$A$6:$A$216,0) -> 31 | G47: =INDEX(Dependencies!$L$6:$HN$216,F47,E47) -> 1 | K47: Chains of that length | L47: =SUMIF(Dependencies!F6:F216,L46,Dependencies!G6:G216) -> 8 | M47: eight
A48: T7.1 | B48: E5.B.1 | C48: =VALUE(MID(A48,2,FIND(".",A48)-2)) -> 7 | D48: =VALUE(MID(B48,2,FIND(".",B48)-2)) -> 5 | E48: =MATCH(A48,Dependencies!$A$6:$A$216,0) -> 56 | F48: =MATCH(B48,Dependencies!$A$6:$A$216,0) -> 36 | G48: =INDEX(Dependencies!$L$6:$HN$216,F48,E48) -> 1 | K48: Results the longest chains start at | L48: =COUNTIF(Dependencies!F6:F216,L46) -> 2 | M48: Theorem 16.1 and Example 16.B.2
A49: P7.1 | B49: T7.1 | C49: =VALUE(MID(A49,2,FIND(".",A49)-2)) -> 7 | D49: =VALUE(MID(B49,2,FIND(".",B49)-2)) -> 7 | E49: =MATCH(A49,Dependencies!$A$6:$A$216,0) -> 57 | F49: =MATCH(B49,Dependencies!$A$6:$A$216,0) -> 56 | G49: =INDEX(Dependencies!$L$6:$HN$216,F49,E49) -> 1 | K49: Results Theorem 16.4 cites | L49: =INDEX(Dependencies!D6:D216,MATCH("T16.4",Dependencies!A6:A216,0)) -> 4 | M49: four
A50: T7.2 | B50: T7.1 | C50: =VALUE(MID(A50,2,FIND(".",A50)-2)) -> 7 | D50: =VALUE(MID(B50,2,FIND(".",B50)-2)) -> 7 | E50: =MATCH(A50,Dependencies!$A$6:$A$216,0) -> 58 | F50: =MATCH(B50,Dependencies!$A$6:$A$216,0) -> 56 | G50: =INDEX(Dependencies!$L$6:$HN$216,F50,E50) -> 1 | K50: Results Theorem 16.4 rests on | L50: =SUM(Dependencies!H6:H216)-1 -> 70 | M50: AXIOM Lab 1.16, step 4
A51: P7.2 | B51: T7.1 | C51: =VALUE(MID(A51,2,FIND(".",A51)-2)) -> 7 | D51: =VALUE(MID(B51,2,FIND(".",B51)-2)) -> 7 | E51: =MATCH(A51,Dependencies!$A$6:$A$216,0) -> 59 | F51: =MATCH(B51,Dependencies!$A$6:$A$216,0) -> 56 | G51: =INDEX(Dependencies!$L$6:$HN$216,F51,E51) -> 1 | K51: Theorem 16.4's longest chain | L51: =INDEX(Dependencies!F6:F216,MATCH("T16.4",Dependencies!A6:A216,0)) -> 14 | M51: ends at Theorem 3.3
A52: P7.2 | B52: T7.2 | C52: =VALUE(MID(A52,2,FIND(".",A52)-2)) -> 7 | D52: =VALUE(MID(B52,2,FIND(".",B52)-2)) -> 7 | E52: =MATCH(A52,Dependencies!$A$6:$A$216,0) -> 59 | F52: =MATCH(B52,Dependencies!$A$6:$A$216,0) -> 58 | G52: =INDEX(Dependencies!$L$6:$HN$216,F52,E52) -> 1
A53: P7.3 | B53: P7.1 | C53: =VALUE(MID(A53,2,FIND(".",A53)-2)) -> 7 | D53: =VALUE(MID(B53,2,FIND(".",B53)-2)) -> 7 | E53: =MATCH(A53,Dependencies!$A$6:$A$216,0) -> 60 | F53: =MATCH(B53,Dependencies!$A$6:$A$216,0) -> 57 | G53: =INDEX(Dependencies!$L$6:$HN$216,F53,E53) -> 1
A54: P7.3 | B54: T7.1 | C54: =VALUE(MID(A54,2,FIND(".",A54)-2)) -> 7 | D54: =VALUE(MID(B54,2,FIND(".",B54)-2)) -> 7 | E54: =MATCH(A54,Dependencies!$A$6:$A$216,0) -> 60 | F54: =MATCH(B54,Dependencies!$A$6:$A$216,0) -> 56 | G54: =INDEX(Dependencies!$L$6:$HN$216,F54,E54) -> 1
A55: P7.4 | B55: T5.3 | C55: =VALUE(MID(A55,2,FIND(".",A55)-2)) -> 7 | D55: =VALUE(MID(B55,2,FIND(".",B55)-2)) -> 5 | E55: =MATCH(A55,Dependencies!$A$6:$A$216,0) -> 61 | F55: =MATCH(B55,Dependencies!$A$6:$A$216,0) -> 32 | G55: =INDEX(Dependencies!$L$6:$HN$216,F55,E55) -> 1
A56: P7.4 | B56: P7.2 | C56: =VALUE(MID(A56,2,FIND(".",A56)-2)) -> 7 | D56: =VALUE(MID(B56,2,FIND(".",B56)-2)) -> 7 | E56: =MATCH(A56,Dependencies!$A$6:$A$216,0) -> 61 | F56: =MATCH(B56,Dependencies!$A$6:$A$216,0) -> 59 | G56: =INDEX(Dependencies!$L$6:$HN$216,F56,E56) -> 1
A57: T7.3 | B57: P5.3 | C57: =VALUE(MID(A57,2,FIND(".",A57)-2)) -> 7 | D57: =VALUE(MID(B57,2,FIND(".",B57)-2)) -> 5 | E57: =MATCH(A57,Dependencies!$A$6:$A$216,0) -> 62 | F57: =MATCH(B57,Dependencies!$A$6:$A$216,0) -> 30 | G57: =INDEX(Dependencies!$L$6:$HN$216,F57,E57) -> 1
A58: T7.3 | B58: T7.1 | C58: =VALUE(MID(A58,2,FIND(".",A58)-2)) -> 7 | D58: =VALUE(MID(B58,2,FIND(".",B58)-2)) -> 7 | E58: =MATCH(A58,Dependencies!$A$6:$A$216,0) -> 62 | F58: =MATCH(B58,Dependencies!$A$6:$A$216,0) -> 56 | G58: =INDEX(Dependencies!$L$6:$HN$216,F58,E58) -> 1
A59: T7.3 | B59: P7.3 | C59: =VALUE(MID(A59,2,FIND(".",A59)-2)) -> 7 | D59: =VALUE(MID(B59,2,FIND(".",B59)-2)) -> 7 | E59: =MATCH(A59,Dependencies!$A$6:$A$216,0) -> 62 | F59: =MATCH(B59,Dependencies!$A$6:$A$216,0) -> 60 | G59: =INDEX(Dependencies!$L$6:$HN$216,F59,E59) -> 1
A60: T7.3 | B60: P7.4 | C60: =VALUE(MID(A60,2,FIND(".",A60)-2)) -> 7 | D60: =VALUE(MID(B60,2,FIND(".",B60)-2)) -> 7 | E60: =MATCH(A60,Dependencies!$A$6:$A$216,0) -> 62 | F60: =MATCH(B60,Dependencies!$A$6:$A$216,0) -> 61 | G60: =INDEX(Dependencies!$L$6:$HN$216,F60,E60) -> 1
A61: P7.5 | B61: P2.2 | C61: =VALUE(MID(A61,2,FIND(".",A61)-2)) -> 7 | D61: =VALUE(MID(B61,2,FIND(".",B61)-2)) -> 2 | E61: =MATCH(A61,Dependencies!$A$6:$A$216,0) -> 64 | F61: =MATCH(B61,Dependencies!$A$6:$A$216,0) -> 7 | G61: =INDEX(Dependencies!$L$6:$HN$216,F61,E61) -> 1
A62: T7.5 | B62: T7.4 | C62: =VALUE(MID(A62,2,FIND(".",A62)-2)) -> 7 | D62: =VALUE(MID(B62,2,FIND(".",B62)-2)) -> 7 | E62: =MATCH(A62,Dependencies!$A$6:$A$216,0) -> 65 | F62: =MATCH(B62,Dependencies!$A$6:$A$216,0) -> 63 | G62: =INDEX(Dependencies!$L$6:$HN$216,F62,E62) -> 1
A63: T7.5 | B63: P7.5 | C63: =VALUE(MID(A63,2,FIND(".",A63)-2)) -> 7 | D63: =VALUE(MID(B63,2,FIND(".",B63)-2)) -> 7 | E63: =MATCH(A63,Dependencies!$A$6:$A$216,0) -> 65 | F63: =MATCH(B63,Dependencies!$A$6:$A$216,0) -> 64 | G63: =INDEX(Dependencies!$L$6:$HN$216,F63,E63) -> 1
... A306: T16.1 | B306: E16.B.3 | C306: =VALUE(MID(A306,2,FIND(".",A306)-2)) -> 16 | D306: =VALUE(MID(B306,2,FIND(".",B306)-2)) -> 16 | E306: =MATCH(A306,Dependencies!$A$6:$A$216,0) -> 211 | F306: =MATCH(B306,Dependencies!$A$6:$A$216,0) -> 210 | G306: =INDEX(Dependencies!$L$6:$HN$216,F306,E306) -> 1

Sheet Export
A1: Export the certified instance in Volume II's canonical form (AXIOM Lab 1.16, step 5; Table 16.3)
A2: max over u in D of J(x, u) subject to x = f(u), g_i(x, u) <= 0: every entry links to the declaration or to the audit that certified it; the notebook writes the same instance as a JSON document.
A4: Section | B4: Entry | C4: Value | D4: Owner
A5: decision | B5: standby line, $ million, 0 to 400 in $5 million steps | C5: =Quantiles!B93 -> 170 | D5: CFO
A6: decision | B6: delay, quarters, 0 to 7 | C6: =Quantiles!B94 -> 0.66757636 | D6: transformation office
A7: objective | B7: minimize Fee x line + Vq x delay ($ million) | C7: =Quantiles!B95 -> 10.440611 | D7: CFO; transformation office
A8: dynamics | B8: Chapter 1's liquidity path at $6.2 million a point, depth 28 - 4 x delay | C8: =Usd_pt -> 6.2
A9: environment | B9: Chapter 8's laws on 100,000 paths, seed 8 | C9: =Book_seed -> 8
A10: policy class | B10: a package committed today (open loop)
A11: commitment | B11: P(liquidity < 350 in some quarter) <= 5% | C11: =R4_Horizon!B23 -> 0.05 | D11: board
A12: commitment | B12: (net debt + line) / EBITDA <= 4.5 | C12: =R4_Horizon!B26 -> 3.7430186 | D12: CFO
A13: commitment | B13: capability >= 55 | C13: =Capability -> 58 | D13: HR, CTO
A14: commitment | B14: peak strategic risk <= 75 | C14: =R4_Horizon!B31 -> 73.552546 | D14: CRO, board
A15: commitment | B15: every core link at most 0.40 (the register) | C15: =Ceil_gain -> 0.4 | D15: risk office
A16: certificate | B16: gates passing | C16: =Certificate!B9 -> 4
A17: certificate | B17: GEOP-ready for the program as approved | C17: =Certificate!B10 -> yes
A18: lapses if | B18: (R3) the gain audit flags a core link; the phase-two link appears undeclared | D18: risk office
A19: lapses if | B19: (R4) a reading crosses its commitment | D19: the commitment's owner
A20: lapses if | B20: (R1)-(R2) a declared price, law, owner or commitment changes: re-run the gates in order | D20: transformation office
A22: Re-solved from the exported document alone (engine): least cost | C22: 10.440611
A23: Agrees with the certified package? | C23: =IF(ABS(C22-Quantiles!B95)<0.000000001,"yes","no") -> yes

Sheet Reference_Values
A1: Checkpoint | B1: Engine value | C1: Meaning (where in the book)
A2: Table 16.1, L1: deepest draw | B2: 138.04962 | C2: $138 million
A3: Table 16.1, L1: buffer for a 90th-percentile closure | B3: 186.86698 | C3: $187 million
A4: Table 16.1, L2: the average path's trough | B4: 459.85405 | C4: $460 million
A5: Table 16.1, L3: weight points that tie the leaders | B5: 1.5924031 | C5: 1.6
A6: Table 16.1, L4: half-life, quarters | B6: 3.1062837 | C6: 3.1
A7: Table 16.1, L5: least cost at 5% | B7: 10.440611 | C7: $10.4 million
A8: Table 16.1, L5: implied cost of a breach | B8: 180.70148 | C8: about $180 million
A9: Theorem 16.2: unit A in year 5 | B9: 392.05723 | C9: 392
A10: Theorem 16.2: unit B in year 5 | B10: 403.77907 | C10: 404
A11: Theorem 16.2: engineers apart | B11: 11.721838 | C11: 12
A12: Theorem 16.2: the totals model for both | B12: 390.98018 | C12: 391
A13: R1: components | B13: 7 | C13: seven
... A47: Twin: first flag, quarter | B47: 6 | C47: the gain audit fires
A48: Twin: the flagged reading | B48: 0.42670797
A49: Twin: re-certified spectral radius | B49: 0.81357684
A50: Twin: largest gain the board's rule tolerates | B50: 0.47799938
A51: Twin: quarter the drift passes it | B51: 9
A52: R4: quarters the first declaration honors the appetite | B52: 3 | C52: Theorem 16.4(vi)'s artifact
A53: R4: simulation error, points | B53: 0.068920244 | C53: 0.07
A54: R4: leverage with the line fully drawn | B54: 3.7430186 | C54: 3.74x
A55: R4: covenant margin | B55: 0.75698144 | C55: 0.76
A56: R4: covenant band | B56: 0.074860371 | C56: 0.075
A57: R4: capability margin | B57: 3 | C57: 3
A58: R4: strategic risk, peak | B58: 73.552546 | C58: 73.6
A59: R4: strategic risk, month of the peak | B59: 10.9 | C59: month 11
A60: R4: strategic risk, margin | B60: 1.4474538 | C60: 1.4
A61: R4: price of the appetite | B61: 1.8070148 | C61: $1.8 million a point
A62: Certificate: gates passing now | B62: 4 | C62: four
A63: Certificate: thin passes | B63: 2 | C63: two
... A78: Export: re-solved least cost | B78: 10.440611 | C78: the package again

Sheet Checks
A1: Checkpoint | B1: Workbook formula value | C1: Engine value | D1: |diff| | E1: Tolerance | F1: Status
A2: Table 16.1, L1: deepest draw | B2: =R2_Consistency!B19 -> 138.04962 | C2: =Reference_Values!B2 -> 138.04962 | D2: =ABS(B2-C2) -> 0 | E2: 1e-09 | F2: =IF(D2<=E2,"PASS","FAIL") -> PASS
A3: Table 16.1, L1: buffer for a 90th-percentile closure | B3: =R2_Consistency!B20 -> 186.86698 | C3: =Reference_Values!B3 -> 186.86698 | D3: =ABS(B3-C3) -> 0 | E3: 1e-06 | F3: =IF(D3<=E3,"PASS","FAIL") -> PASS
A4: Table 16.1, L2: the average path's trough | B4: =R2_Consistency!B24 -> 459.85405 | C4: =Reference_Values!B4 -> 459.85405 | D4: =ABS(B4-C4) -> 0 | E4: 1e-09 | F4: =IF(D4<=E4,"PASS","FAIL") -> PASS
A5: Table 16.1, L3: weight points that tie the leaders | B5: =Scorecard!B43 -> 1.5924031 | C5: =Reference_Values!B5 -> 1.5924031 | D5: =ABS(B5-C5) -> 0 | E5: 1e-09 | F5: =IF(D5<=E5,"PASS","FAIL") -> PASS
A6: Table 16.1, L4: half-life, quarters | B6: =R3_Panel!B9 -> 3.1062837 | C6: =Reference_Values!B6 -> 3.1062837 | D6: =ABS(B6-C6) -> 0 | E6: 1e-09 | F6: =IF(D6<=E6,"PASS","FAIL") -> PASS
A7: Table 16.1, L5: least cost at 5% | B7: =Quantiles!B95 -> 10.440611 | C7: =Reference_Values!B7 -> 10.440611 | D7: =ABS(B7-C7) -> 0 | E7: 1e-09 | F7: =IF(D7<=E7,"PASS","FAIL") -> PASS
A8: Table 16.1, L5: implied cost of a breach | B8: =Quantiles!B102 -> 180.70148 | C8: =Reference_Values!B8 -> 180.70148 | D8: =ABS(B8-C8) -> 7.1054274e-13 | E8: 1e-06 | F8: =IF(D8<=E8,"PASS","FAIL") -> PASS
A9: Theorem 16.2: unit A in year 5 | B9: =Framework!B28 -> 392.05723 | C9: =Reference_Values!B9 -> 392.05723 | D9: =ABS(B9-C9) -> 0 | E9: 1e-09 | F9: =IF(D9<=E9,"PASS","FAIL") -> PASS
A10: Theorem 16.2: unit B in year 5 | B10: =Framework!B29 -> 403.77907 | C10: =Reference_Values!B10 -> 403.77907 | D10: =ABS(B10-C10) -> 0 | E10: 1e-09 | F10: =IF(D10<=E10,"PASS","FAIL") -> PASS
A11: Theorem 16.2: engineers apart | B11: =Framework!B30 -> 11.721838 | C11: =Reference_Values!B11 -> 11.721838 | D11: =ABS(B11-C11) -> 0 | E11: 1e-09 | F11: =IF(D11<=E11,"PASS","FAIL") -> PASS
A12: Theorem 16.2: the totals model for both | B12: =Framework!B31 -> 390.98018 | C12: =Reference_Values!B12 -> 390.98018 | D12: =ABS(B12-C12) -> 0 | E12: 1e-09 | F12: =IF(D12<=E12,"PASS","FAIL") -> PASS
A13: R1: components | B13: =R1_Inventory!B46 -> 7 | C13: =Reference_Values!B13 -> 7 | D13: =ABS(B13-C13) -> 0 | E13: 1e-09 | F13: =IF(D13<=E13,"PASS","FAIL") -> PASS
A14: R1: typed arrows | B14: =R1_Inventory!B47 -> 14 | C14: =Reference_Values!B14 -> 14 | D14: =ABS(B14-C14) -> 0 | E14: 0 | F14: =IF(D14<=E14,"PASS","FAIL") -> PASS
A15: R1: two-way links in the core | B15: =R1_Inventory!B48 -> 4 | C15: =Reference_Values!B15 -> 4 | D15: =ABS(B15-C15) -> 0 | E15: 0 | F15: =IF(D15<=E15,"PASS","FAIL") -> PASS
A16: R1: standing commitments | B16: =R1_Inventory!B49 -> 5 | C16: =Reference_Values!B16 -> 5 | D16: =ABS(B16-C16) -> 0 | E16: 0 | F16: =IF(D16<=E16,"PASS","FAIL") -> PASS
A17: R1: elements of the GEOP | B17: =R1_Inventory!B50 -> 6 | C17: =Reference_Values!B17 -> 6 | D17: =ABS(B17-C17) -> 0 | E17: 0 | F17: =IF(D17<=E17,"PASS","FAIL") -> PASS
A18: R1: Chapter 8 package, cost | B18: =Quantiles!B96 -> 19 | C18: =Reference_Values!B18 -> 19 | D18: =ABS(B18-C18) -> 0 | E18: 1e-09 | F18: =IF(D18<=E18,"PASS","FAIL") -> PASS
A19: R1: cheapest at the package's odds | B19: =Quantiles!B97 -> 14.668098 | C19: =Reference_Values!B19 -> 14.668098 | D19: =ABS(B19-C19) -> 0 | E19: 1e-09 | F19: =IF(D19<=E19,"PASS","FAIL") -> PASS
A20: R1: cost of choosing without prices | B20: =Quantiles!B98 -> 4.3319019 | C20: =Reference_Values!B20 -> 4.3319019 | D20: =ABS(B20-C20) -> 0 | E20: 1e-09 | F20: =IF(D20<=E20,"PASS","FAIL") -> PASS
A21: R1: best-to-worst, restructuring | B21: =Scorecard!F28 -> 52.264029 | C21: =Reference_Values!B21 -> 52.264029 | D21: =ABS(B21-C21) -> 0 | E21: 1e-09 | F21: =IF(D21<=E21,"PASS","FAIL") -> PASS
A22: R1: best-to-worst, digital | B22: =Scorecard!F27 -> 41.39992 | C22: =Reference_Values!B22 -> 41.39992 | D22: =ABS(B22-C22) -> 0 | E22: 1e-09 | F22: =IF(D22<=E22,"PASS","FAIL") -> PASS
A23: R1: best-to-worst, turnaround | B23: =Scorecard!F29 -> 35.323786 | C23: =Reference_Values!B23 -> 35.323786 | D23: =ABS(B23-C23) -> 0 | E23: 1e-09 | F23: =IF(D23<=E23,"PASS","FAIL") -> PASS
A24: R1: percentage improvement, digital | B24: =Scorecard!F32 -> 24.038073 | C24: =Reference_Values!B24 -> 24.038073 | D24: =ABS(B24-C24) -> 0 | E24: 1e-09 | F24: =IF(D24<=E24,"PASS","FAIL") -> PASS
A25: R1: percentage improvement, restructuring | B25: =Scorecard!F33 -> 10.623653 | C25: =Reference_Values!B25 -> 10.623653 | D25: =ABS(B25-C25) -> 0 | E25: 1e-09 | F25: =IF(D25<=E25,"PASS","FAIL") -> PASS
A26: R1: percentage improvement, turnaround | B26: =Scorecard!F34 -> 0.024648044 | C26: =Reference_Values!B26 -> 0.024648044 | D26: =ABS(B26-C26) -> 0 | E26: 1e-09 | F26: =IF(D26<=E26,"PASS","FAIL") -> PASS
A27: R2: draw + buffer as declared | B27: =R2_Consistency!B22 -> 324.91659 | C27: =Reference_Values!B27 -> 324.91659 | D27: =ABS(B27-C27) -> 0 | E27: 1e-06 | F27: =IF(D27<=E27,"PASS","FAIL") -> PASS
A28: R2: short by | B28: =R2_Consistency!B23 -> 54.916594 | C28: =Reference_Values!B28 -> 54.916594 | D28: =ABS(B28-C28) -> 0 | E28: 1e-06 | F28: =IF(D28<=E28,"PASS","FAIL") -> PASS
A29: R2: the package's line | B29: =Quantiles!B93 -> 170 | C29: =Reference_Values!B29 -> 170 | D29: =ABS(B29-C29) -> 0 | E29: 0 | F29: =IF(D29<=E29,"PASS","FAIL") -> PASS
A30: R2: the package's delay | B30: =Quantiles!B94 -> 0.66757636 | C30: =Reference_Values!B30 -> 0.66757636 | D30: =ABS(B30-C30) -> 0 | E30: 1e-09 | F30: =IF(D30<=E30,"PASS","FAIL") -> PASS
A31: R2: deepest draw with the delay | B31: =R2_Consistency!B32 -> 121.63437 | C31: =Reference_Values!B31 -> 121.63437 | D31: =ABS(B31-C31) -> 0 | E31: 1e-09 | F31: =IF(D31<=E31,"PASS","FAIL") -> PASS
A32: R2: buffer the line leaves | B32: =R2_Consistency!B33 -> 16.866976 | C32: =Reference_Values!B32 -> 16.866976 | D32: =ABS(B32-C32) -> 8.1712415e-14 | E32: 1e-06 | F32: =IF(D32<=E32,"PASS","FAIL") -> PASS
A33: R2: draw + buffer now | B33: =R2_Consistency!B34 -> 138.50134 | C33: =Reference_Values!B33 -> 138.50134 | D33: =ABS(B33-C33) -> 0 | E33: 1e-06 | F33: =IF(D33<=E33,"PASS","FAIL") -> PASS
A34: R2: unclaimed | B34: =R2_Consistency!B35 -> 131.49866 | C34: =Reference_Values!B34 -> 131.49866 | D34: =ABS(B34-C34) -> 0 | E34: 1e-06 | F34: =IF(D34<=E34,"PASS","FAIL") -> PASS
A35: R3: spectral radius of the core | B35: =R3_Panel!B7 -> 0.8 | C35: =Reference_Values!B35 -> 0.8 | D35: =ABS(B35-C35) -> 0 | E35: 1e-09 | F35: =IF(D35<=E35,"PASS","FAIL") -> PASS
A36: R3: the board's rule | B36: =R3_Panel!B8 -> 0.84089642 | C36: =Reference_Values!B36 -> 0.84089642 | D36: =ABS(B36-C36) -> 0 | E36: 1e-09 | F36: =IF(D36<=E36,"PASS","FAIL") -> PASS
A37: R3: multiplier | B37: =R3_Panel!B10 -> 5 | C37: =Reference_Values!B37 -> 5 | D37: =ABS(B37-C37) -> 0 | E37: 1e-09 | F37: =IF(D37<=E37,"PASS","FAIL") -> PASS
A38: R3: echo of $10m, next quarter | B38: =R3_Panel!B19 -> 8 | C38: =Reference_Values!B38 -> 8 | D38: =ABS(B38-C38) -> 0 | E38: 1e-09 | F38: =IF(D38<=E38,"PASS","FAIL") -> PASS
A39: R3: echo of $10m, the quarter after | B39: =R3_Panel!B20 -> 6.4 | C39: =Reference_Values!B39 -> 6.4 | D39: =ABS(B39-C39) -> 0 | E39: 1e-09 | F39: =IF(D39<=E39,"PASS","FAIL") -> PASS
A40: R3: echo of $10m, in all | B40: =R3_Panel!B22 -> 49.999999 | C40: =Reference_Values!B40 -> 49.999999 | D40: =ABS(B40-C40) -> 0 | E40: 1e-06 | F40: =IF(D40<=E40,"PASS","FAIL") -> PASS
A41: R3: phase-two link at 0.40 | B41: =R3_Panel!B26 -> 1.0246211 | C41: =Reference_Values!B41 -> 1.0246211 | D41: =ABS(B41-C41) -> 0 | E41: 1e-09 | F41: =IF(D41<=E41,"PASS","FAIL") -> PASS
A42: R3: repair, new link at most | B42: =R3_Panel!B29 -> 0.079803862 | C42: =Reference_Values!B42 -> 0.079803862 | D42: =ABS(B42-C42) -> 0 | E42: 1e-09 | F42: =IF(D42<=E42,"PASS","FAIL") -> PASS
A43: R3: repair, treasury links at most | B43: =R3_Panel!B31 -> 0.15929252 | C43: =Reference_Values!B43 -> 0.15929252 | D43: =ABS(B43-C43) -> 0 | E43: 1e-09 | F43: =IF(D43<=E43,"PASS","FAIL") -> PASS
A44: R3: repair, all four links at | B44: =R3_Panel!B33 -> 0.30444549 | C44: =Reference_Values!B44 -> 0.30444549 | D44: =ABS(B44-C44) -> 0 | E44: 1e-09 | F44: =IF(D44<=E44,"PASS","FAIL") -> PASS
A45: 16.B.2: the register's echo, quarter 3 | B45: =DigitalTwin!E50 -> 5.12 | C45: =Reference_Values!B45 -> 5.12 | D45: =ABS(B45-C45) -> 0 | E45: 1e-09 | F45: =IF(D45<=E45,"PASS","FAIL") -> PASS
A46: Twin: first thin pass, quarter | B46: =DigitalTwin!B25 -> 4 | C46: =Reference_Values!B46 -> 4 | D46: =ABS(B46-C46) -> 0 | E46: 0 | F46: =IF(D46<=E46,"PASS","FAIL") -> PASS
A47: Twin: first flag, quarter | B47: =DigitalTwin!B26 -> 6 | C47: =Reference_Values!B47 -> 6 | D47: =ABS(B47-C47) -> 0 | E47: 0 | F47: =IF(D47<=E47,"PASS","FAIL") -> PASS
A48: Twin: the flagged reading | B48: =DigitalTwin!B28 -> 0.42670797 | C48: =Reference_Values!B48 -> 0.42670797 | D48: =ABS(B48-C48) -> 0 | E48: 1e-12 | F48: =IF(D48<=E48,"PASS","FAIL") -> PASS
A49: Twin: re-certified spectral radius | B49: =DigitalTwin!B33 -> 0.81357684 | C49: =Reference_Values!B49 -> 0.81357684 | D49: =ABS(B49-C49) -> 0 | E49: 1e-09 | F49: =IF(D49<=E49,"PASS","FAIL") -> PASS
A50: Twin: largest gain the board's rule tolerates | B50: =DigitalTwin!B41 -> 0.47799938 | C50: =Reference_Values!B50 -> 0.47799938 | D50: =ABS(B50-C50) -> 0 | E50: 1e-09 | F50: =IF(D50<=E50,"PASS","FAIL") -> PASS
A51: Twin: quarter the drift passes it | B51: =DigitalTwin!B42 -> 9 | C51: =Reference_Values!B51 -> 9 | D51: =ABS(B51-C51) -> 0 | E51: 0 | F51: =IF(D51<=E51,"PASS","FAIL") -> PASS
A52: R4: quarters the first declaration honors the appetite | B52: =R4_Horizon!B20 -> 3 | C52: =Reference_Values!B52 -> 3 | D52: =ABS(B52-C52) -> 0 | E52: 0 | F52: =IF(D52<=E52,"PASS","FAIL") -> PASS
A53: R4: simulation error, points | B53: =R4_Horizon!B24 -> 0.068920244 | C53: =Reference_Values!B53 -> 0.068920244 | D53: =ABS(B53-C53) -> 0 | E53: 1e-09 | F53: =IF(D53<=E53,"PASS","FAIL") -> PASS
A54: R4: leverage with the line fully drawn | B54: =R4_Horizon!B26 -> 3.7430186 | C54: =Reference_Values!B54 -> 3.7430186 | D54: =ABS(B54-C54) -> 0 | E54: 1e-09 | F54: =IF(D54<=E54,"PASS","FAIL") -> PASS
A55: R4: covenant margin | B55: =R4_Horizon!B27 -> 0.75698144 | C55: =Reference_Values!B55 -> 0.75698144 | D55: =ABS(B55-C55) -> 0 | E55: 1e-09 | F55: =IF(D55<=E55,"PASS","FAIL") -> PASS
A56: R4: covenant band | B56: =R4_Horizon!B28 -> 0.074860371 | C56: =Reference_Values!B56 -> 0.074860371 | D56: =ABS(B56-C56) -> 0 | E56: 1e-09 | F56: =IF(D56<=E56,"PASS","FAIL") -> PASS
A57: R4: capability margin | B57: =R4_Horizon!B30 -> 3 | C57: =Reference_Values!B57 -> 3 | D57: =ABS(B57-C57) -> 0 | E57: 0 | F57: =IF(D57<=E57,"PASS","FAIL") -> PASS
A58: R4: strategic risk, peak | B58: =R4_Horizon!B31 -> 73.552546 | C58: =Reference_Values!B58 -> 73.552546 | D58: =ABS(B58-C58) -> 0 | E58: 1e-09 | F58: =IF(D58<=E58,"PASS","FAIL") -> PASS
A59: R4: strategic risk, month of the peak | B59: =R4_Horizon!B32 -> 10.9 | C59: =Reference_Values!B59 -> 10.9 | D59: =ABS(B59-C59) -> 0 | E59: 1e-09 | F59: =IF(D59<=E59,"PASS","FAIL") -> PASS
A60: R4: strategic risk, margin | B60: =R4_Horizon!B33 -> 1.4474538 | C60: =Reference_Values!B60 -> 1.4474538 | D60: =ABS(B60-C60) -> 0 | E60: 1e-09 | F60: =IF(D60<=E60,"PASS","FAIL") -> PASS
A61: R4: price of the appetite | B61: =Quantiles!B101 -> 1.8070148 | C61: =Reference_Values!B61 -> 1.8070148 | D61: =ABS(B61-C61) -> 7.327472e-15 | E61: 1e-09 | F61: =IF(D61<=E61,"PASS","FAIL") -> PASS
A62: Certificate: gates passing now | B62: =Certificate!B9 -> 4 | C62: =Reference_Values!B62 -> 4 | D62: =ABS(B62-C62) -> 0 | E62: 0 | F62: =IF(D62<=E62,"PASS","FAIL") -> PASS
A63: Certificate: thin passes | B63: =Certificate!B11 -> 2 | C63: =Reference_Values!B63 -> 2 | D63: =ABS(B63-C63) -> 0 | E63: 0 | F63: =IF(D63<=E63,"PASS","FAIL") -> PASS
A64: Appendix 16.A: the runway's cash in quarter 4 | B64: =Certificate!B34 -> -20 | C64: =Reference_Values!B64 -> -20 | D64: =ABS(B64-C64) -> 0 | E64: 0 | F64: =IF(D64<=E64,"PASS","FAIL") -> PASS
A65: 16.B.1: numbered results | B65: =Citations!L35 -> 211 | C65: =Reference_Values!B65 -> 211 | D65: =ABS(B65-C65) -> 0 | E65: 0 | F65: =IF(D65<=E65,"PASS","FAIL") -> PASS
A66: 16.B.1: citations | B66: =Citations!L36 -> 302 | C66: =Reference_Values!B66 -> 302 | D66: =ABS(B66-C66) -> 0 | E66: 0 | F66: =IF(D66<=E66,"PASS","FAIL") -> PASS
A67: 16.B.1: citations within a chapter | B67: =Citations!L38 -> 138 | C67: =Reference_Values!B67 -> 138 | D67: =ABS(B67-C67) -> 0 | E67: 0 | F67: =IF(D67<=E67,"PASS","FAIL") -> PASS
A68: 16.B.1: citations to earlier chapters | B68: =Citations!L39 -> 164 | C68: =Reference_Values!B68 -> 164 | D68: =ABS(B68-C68) -> 0 | E68: 0 | F68: =IF(D68<=E68,"PASS","FAIL") -> PASS
A69: 16.B.1: citations to later chapters | B69: =Citations!L40 -> 0 | C69: =Reference_Values!B69 -> 0 | D69: =ABS(B69-C69) -> 0 | E69: 0 | F69: =IF(D69<=E69,"PASS","FAIL") -> PASS
A70: 16.B.1: citations against the order | B70: =Citations!L41 -> 0 | C70: =Reference_Values!B70 -> 0 | D70: =ABS(B70-C70) -> 0 | E70: 0 | F70: =IF(D70<=E70,"PASS","FAIL") -> PASS
A71: 16.B.1: citations found in the matrix | B71: =Citations!L42 -> 302 | C71: =Reference_Values!B71 -> 302 | D71: =ABS(B71-C71) -> 0 | E71: 0 | F71: =IF(D71<=E71,"PASS","FAIL") -> PASS
A72: 16.B.1: results citing none | B72: =Citations!L45 -> 62 | C72: =Reference_Values!B72 -> 62 | D72: =ABS(B72-C72) -> 0 | E72: 0 | F72: =IF(D72<=E72,"PASS","FAIL") -> PASS
A73: 16.B.1: longest chain | B73: =Citations!L46 -> 15 | C73: =Reference_Values!B73 -> 15 | D73: =ABS(B73-C73) -> 0 | E73: 0 | F73: =IF(D73<=E73,"PASS","FAIL") -> PASS
A74: 16.B.1: chains of that length | B74: =Citations!L47 -> 8 | C74: =Reference_Values!B74 -> 8 | D74: =ABS(B74-C74) -> 0 | E74: 0 | F74: =IF(D74<=E74,"PASS","FAIL") -> PASS
A75: 16.B.1: results the longest chains start at | B75: =Citations!L48 -> 2 | C75: =Reference_Values!B75 -> 2 | D75: =ABS(B75-C75) -> 0 | E75: 0 | F75: =IF(D75<=E75,"PASS","FAIL") -> PASS
A76: Theorem 16.4: results it rests on | B76: =Citations!L50 -> 70 | C76: =Reference_Values!B76 -> 70 | D76: =ABS(B76-C76) -> 0 | E76: 0 | F76: =IF(D76<=E76,"PASS","FAIL") -> PASS
A77: Theorem 16.4: its longest chain | B77: =Citations!L51 -> 14 | C77: =Reference_Values!B77 -> 14 | D77: =ABS(B77-C77) -> 0 | E77: 0 | F77: =IF(D77<=E77,"PASS","FAIL") -> PASS
A78: Export: re-solved least cost | B78: =Export!C22 -> 10.440611 | C78: =Reference_Values!B78 -> 10.440611 | D78: =ABS(B78-C78) -> 0 | E78: 1e-09 | F78: =IF(D78<=E78,"PASS","FAIL") -> PASS
A80: All checkpoints | F80: =IF(COUNTIF(F2:F78,"PASS")=77,"ALL PASS","CHECK") -> ALL PASS
