Workbook

Sheet README
B1: DCT Laboratory — Vol II, Ch 8: Hamilton–Jacobi–Bellman Enterprise Framework
B2: Seed 26208 · Companion to DCT_V2_Ch08_Lab.ipynb and AXIOM Lab 2.8 (module AXIOM-08). Money in $ million.
B4: Worked Example 8.1, How Fast Should Meridian Close Its Engineering Gap?, with the book's declarations, and Chapter 6's capability problem solved with the HJB equation (Sections 8.2, 8.4 and 8.6). Nothing in the chapter is random.
B5: Declarations: the hiring loop of Step 1 and Chapter 6's capability declarations.
B6: Riccati: the quadratic value, its two roots, the rule and the price of an engineer of gap (Step 2; Theorem 8.3), and Theorem 8.2(iii)'s residual audit of other candidates.
B7: Hamiltonian: approvals where the marginal premium equals the value of an approval, at three gaps (Proposition 8.1(ii)).
B8: PolicyIteration: Kleinman's iteration from Volume I's cautious gain (Theorem 8.3(iii)); the costs of proportional rules if approvals landed at once.
B9: Delay: the predicted gap and the best rule with the quarter's delay (Step 3; Proposition 8.3(ii)), and the least cost against the months approvals take to land (Figure 8.3(b)).
B10: Rules: Table 8.3. The costs, surpluses and gaps of rules run with the delay need a simulation and come from the engine; gains, extra costs and the at-once column are formulas.
B11: CriticalGain: the gain above which a rule on today's gap swings ever wider, by bisection.
B12: Sensitivities: Step 5, the gain through q/r, a misdeclared delay, and productivity of 30 percent.
B13: Capability: Chapter 6's value and prices in closed form, the never-start threshold, the corners, the HJB equation at 58, and the costate against the value's slope along the best plans.
... B21: Cross-sheet link: green.

Sheet Declarations
A1: Declarations (Worked Example 8.1, Step 1; Chapter 6's capability problem). Money in $ million; time in years.
A3: Quantity | B3: Value | C3: Source
A4: Share of a gap carried over a quarter | B4: 0.9 | C4: Retraining and internal moves close 10 percent of any gap each quarter (Volume I, Worked Example 7.1)
A5: a: the gap closes on its own, a year | B5: =-4*LN(B4) -> 0.42144206 | C5: a = 4 ln(10/9) = 0.42
A6: b: share of approvals that become engineers | B6: 0.6 | C6: 60 percent of approved external hires become productive engineers
A7: tau: approvals become engineers after (years) | B7: 0.25 | C7: A quarter
A8: Cost of a gap of 100 engineers, a year | B8: 32 | C8: Program office: as much as stopping the build (a quarter of delay is worth $8 million, Volume I, Chapter 15)
A9: q = that cost / 100^2 | B9: =B8/100^2 -> 0.0032 | C9: A gap of d engineers costs q d^2 a year
A10: Premium for approving 400 a year, a year | B10: 20 | C10: Human resources: agency fees and signing bonuses beyond planned salaries
A11: r = that premium / 400^2 | B11: =B10/400^2 -> 0.000125 | C11: Approving v a year costs r v^2 a year
A12: Hurdle rate a year | B12: 0.1 | C12: The board's 10 percent (Chapter 5)
A13: rho = ln(1 + hurdle rate) | B13: =LN(1+B12) -> 0.09531018 | C13: 9.5 percent in continuous time
A14: Gap today: bench minus target (engineers) | B14: -100 | C14: 100 short, nothing in the pipeline
A15: Volume I's cautious gain, a quarter | B15: 0.5 | C15: Approve half the gap each quarter
A16: Volume I's deadbeat gain, a quarter | B16: 1.5 | C16: One and a half times the gap each quarter
A17: Cautious gain as a rate a year | B17: =4*B15 -> 2 | C17: Rules run continuously: v = -k d
A18: Deadbeat gain as a rate a year | B18: =4*B16 -> 6
A19: q / r | B19: =B9/B11 -> 25.6 | C19: The gain depends on the two costs only through their ratio
A20: Premium per hire at 400 a year | B20: =B11*400 -> 0.05 | C20: $50,000 a hire; at 100 a year, $12,500
A22: Chapter 6's capability problem (Worked Example 6.1)
A23: Attrition a quarter | B23: 0.025 | C23: 2.5 percent a quarter (Volume I, Chapter 10)
A24: delta = -4 ln(1 - attrition), a year | B24: =-4*LN(1-B23) -> 0.10127123 | C24: 0.101 a year
A25: Hiring cap a quarter (points) | B25: 2.5
A26: Volume I's ceiling = cap / attrition | B26: =B25/B23 -> 100 | C26: 100
A27: Hiring cap a year, u bar = ceiling x delta | B27: =B26*B24 -> 10.127123 | C27: 10.13 points a year
A28: Cost of hiring and training a point, k | B28: 4 | C28: $4 million a point
A29: Capability floor of the digital build | B29: 55 | C29: The build runs from the first moment capability reaches 55, which it must then keep
A30: Delay while the build waits, a year | B30: 32 | C30: $32 million a year
A32: Hiring loop: d'(t) = -a d(t) + b v(t - tau); cost of a rule = PV of q d^2 + r v^2 at rho over an open horizon. Capability: dc/dt = u - delta c, 0 <= u <= u bar, cost k u plus the delay below the floor.

Sheet Riccati
A1: Assemble the equation: a quadratic value -p d^2 and its two roots (Theorem 8.3; Worked Example 8.1, Step 2; AXIOM Lab 2.8, step 1)
A3: Quantity | B3: Value | C3: Reading
A4: Coefficient b^2 / r | B4: =B_share^2/R_prem -> 2880 | C4: (b^2/r) p^2 + (2a + rho) p - q = 0
A5: Coefficient 2a + rho | B5: =2*A_close+Rho_a -> 0.93819431
A6: Constant -q | B6: =-Q_gap -> -0.0032
A7: Positive root p | B7: =(-(B5)+SQRT((B5)^2+4*(B4)*(Q_gap)))/(2*(B4)) -> 0.00090372174 | C7: The value is -p d^2
A8: Second root p- | B8: =(-B5-SQRT(B5^2+4*B4*Q_gap))/(2*B4) -> -0.0012294837 | C8: Also solves the equation
A9: Gain K = b p / r, a year | B9: =B_share*B7/R_prem -> 4.3378644 | C9: The best rule v = -K d
A10: Gain a quarter | B10: =B9/4 -> 1.0844661 | C10: Between Volume I's cautious (0.5) and deadbeat (1.5) gains
A11: The gap closes at a + bK, a year | B11: =A_close+B_share*B9 -> 3.0241607
A12: Half-life of the gap (years) | B12: =LN(2)/B11 -> 0.22920316
A13: Half-life of the gap (months) | B13: =12*B12 -> 2.7504379 | C13: 2.75 months
A14: Least cost from 100 short, p d0^2 | B14: =B7*D0_gap^2 -> 9.0372174 | C14: $9.04 million
A15: Price of an engineer of gap at 100 short, 2p|d0| | B15: =2*B7*ABS(D0_gap) -> 0.18074435 | C15: $181,000
A16: First approval rate, K|d0| (a year) | B16: =B9*ABS(D0_gap) -> 433.78644
A17: Marginal premium on the last approval, 2 r v | B17: =2*R_prem*B16 -> 0.10844661 | C17: $108,000
A18: Value of an approval, b x price | B18: =B_share*B15 -> 0.10844661 | C18: Equal: Proposition 8.1(ii)
A19: Second root's gain, b p- / r | B19: =B_share*B8/R_prem -> -5.9015215 | C19: Its rule is v = -K- d
A20: It releases at 100 short (a year) | B20: =-B19*ABS(D0_gap) -> 590.15215 | C20: Releases engineers while the bench is short
A21: Its closed loop grows at -a - b K-, a year | B21: =-A_close-B_share*B19 -> 3.1194709 | C21: e^(-rho t) W(d(t)) does not tend to zero: Theorem 8.2(ii) certifies nothing
A22: Effective horizon 1/rho (years) | B22: =1/Rho_a -> 10.492059 | C22: Theorem 8.2(iii)
A23: A residual of $0.1 million a year puts the values within | B23: =0.1/Rho_a -> 1.0492059 | C23: $1.05 million
A25: Theorem 8.2(iii) audit of candidate values -p d^2 on the gaps from 100 short to 100 over
A26: Candidate p | B26: Riccati quadratic at p | C26: Residual at 100 short, eps | D26: Bound eps/rho | E26: Value off by |p - p*| d0^2 | F26: Greedy gain b p / r | G26: Its cost from 100 short | H26: Loss against the best | I26: Bound 2 eps/rho
A27: 0.0005 | B27: =$B$4*A27^2+$B$5*A27+$B$6 -> -0.0020109028 | C27: =D0_gap^2*ABS(B27) -> 20.109028 | D27: =C27/Rho_a -> 210.98511 | E27: =ABS(A27-$B$7)*D0_gap^2 -> 4.0372174 | F27: =B_share*A27/R_prem -> 2.4 | G27: =(Q_gap+R_prem*F27^2)*D0_gap^2/(2*(A_close+B_share*F27)+Rho_a) -> 10.266633 | H27: =G27-$B$14 -> 1.2294157 | I27: =2*C27/Rho_a -> 421.97021
A28: 0.0008 | B28: =$B$4*A28^2+$B$5*A28+$B$6 -> -0.00060624456 | C28: =D0_gap^2*ABS(B28) -> 6.0624456 | D28: =C28/Rho_a -> 63.607535 | E28: =ABS(A28-$B$7)*D0_gap^2 -> 1.0372174 | F28: =B_share*A28/R_prem -> 3.84 | G28: =(Q_gap+R_prem*F28^2)*D0_gap^2/(2*(A_close+B_share*F28)+Rho_a) -> 9.0930821 | H28: =G28-$B$14 -> 0.055864642 | I28: =2*C28/Rho_a -> 127.21507
A29: 0.0009 | B29: =$B$4*A29^2+$B$5*A29+$B$6 -> -2.2825125e-05 | C29: =D0_gap^2*ABS(B29) -> 0.22825125 | D29: =C29/Rho_a -> 2.3948256 | E29: =ABS(A29-$B$7)*D0_gap^2 -> 0.037217429 | F29: =B_share*A29/R_prem -> 4.32 | G29: =(Q_gap+R_prem*F29^2)*D0_gap^2/(2*(A_close+B_share*F29)+Rho_a) -> 9.0372826 | H29: =G29-$B$14 -> 6.5159558e-05 | I29: =2*C29/Rho_a -> 4.7896511
A30: =B7 -> 0.00090372174 | B30: =$B$4*A30^2+$B$5*A30+$B$6 -> 0 | C30: =D0_gap^2*ABS(B30) -> 0 | D30: =C30/Rho_a -> 0 | E30: =ABS(A30-$B$7)*D0_gap^2 -> 0 | F30: =B_share*A30/R_prem -> 4.3378644 | G30: =(Q_gap+R_prem*F30^2)*D0_gap^2/(2*(A_close+B_share*F30)+Rho_a) -> 9.0372174 | H30: =G30-$B$14 -> 0 | I30: =2*C30/Rho_a -> 0
A31: 0.001 | B31: =$B$4*A31^2+$B$5*A31+$B$6 -> 0.00061819431 | C31: =D0_gap^2*ABS(B31) -> 6.1819431 | D31: =C31/Rho_a -> 64.861309 | E31: =ABS(A31-$B$7)*D0_gap^2 -> 0.96278257 | F31: =B_share*A31/R_prem -> 4.8 | G31: =(Q_gap+R_prem*F31^2)*D0_gap^2/(2*(A_close+B_share*F31)+Rho_a) -> 9.0770732 | H31: =G31-$B$14 -> 0.039855768 | I31: =2*C31/Rho_a -> 129.72262
A32: 0.0012 | B32: =$B$4*A32^2+$B$5*A32+$B$6 -> 0.0020730332 | C32: =D0_gap^2*ABS(B32) -> 20.730332 | D32: =C32/Rho_a -> 217.50386 | E32: =ABS(A32-$B$7)*D0_gap^2 -> 2.9627826 | F32: =B_share*A32/R_prem -> 5.76 | G32: =(Q_gap+R_prem*F32^2)*D0_gap^2/(2*(A_close+B_share*F32)+Rho_a) -> 9.3592588 | H32: =G32-$B$14 -> 0.32204135 | I32: =2*C32/Rho_a -> 435.00771
A34: The residual of -p d^2 at the gap d is -d^2 times the Riccati quadratic: it vanishes everywhere at the two roots. The value's error and the greedy rule's loss stay within the bounds.

Sheet Hamiltonian
A1: Read the Hamiltonian: approve until the marginal premium equals the value of an approval (Proposition 8.1(ii); AXIOM Lab 2.8, step 2)
A2: At the gap d, the part of the Hamiltonian the approval rate moves is -r v^2 + b V'(d) v, with V'(d) = -2 p d, the price of an engineer of gap.
A4: Gap d | B4: -100 | C4: -50 | D4: -25
A5: Price of an engineer of gap, V'(d) = -2 p d | B5: =-2*Riccati!$B$7*B4 -> 0.18074435 | C5: =-2*Riccati!$B$7*C4 -> 0.090372174 | D5: =-2*Riccati!$B$7*D4 -> 0.045186087
A6: Best approval rate, b V'(d) / (2r) | B6: =B_share*B5/(2*R_prem) -> 433.78644 | C6: =B_share*C5/(2*R_prem) -> 216.89322 | D6: =B_share*D5/(2*R_prem) -> 108.44661
A7: Marginal premium at it, 2 r v | B7: =2*R_prem*B6 -> 0.10844661 | C7: =2*R_prem*C6 -> 0.054223305 | D7: =2*R_prem*D6 -> 0.027111652
A8: Value of an approval, b V'(d) | B8: =B_share*B5 -> 0.10844661 | C8: =B_share*C5 -> 0.054223305 | D8: =B_share*D5 -> 0.027111652
A10: Approval rate v (a year) | B10: -r v^2 + b V'(d) v at gap 1 | C10: at gap 2 | D10: at gap 3
A11: 0 | B11: =-R_prem*$A11^2+B$8*$A11 -> 0 | C11: =-R_prem*$A11^2+C$8*$A11 -> 0 | D11: =-R_prem*$A11^2+D$8*$A11 -> 0
A12: 10 | B12: =-R_prem*$A12^2+B$8*$A12 -> 1.0719661 | C12: =-R_prem*$A12^2+C$8*$A12 -> 0.52973305 | D12: =-R_prem*$A12^2+D$8*$A12 -> 0.25861652
A13: 20 | B13: =-R_prem*$A13^2+B$8*$A13 -> 2.1189322 | C13: =-R_prem*$A13^2+C$8*$A13 -> 1.0344661 | D13: =-R_prem*$A13^2+D$8*$A13 -> 0.49223305
A14: 30 | B14: =-R_prem*$A14^2+B$8*$A14 -> 3.1408983 | C14: =-R_prem*$A14^2+C$8*$A14 -> 1.5141991 | D14: =-R_prem*$A14^2+D$8*$A14 -> 0.70084957
A15: 40 | B15: =-R_prem*$A15^2+B$8*$A15 -> 4.1378644 | C15: =-R_prem*$A15^2+C$8*$A15 -> 1.9689322 | D15: =-R_prem*$A15^2+D$8*$A15 -> 0.88446609
A16: 50 | B16: =-R_prem*$A16^2+B$8*$A16 -> 5.1098305 | C16: =-R_prem*$A16^2+C$8*$A16 -> 2.3986652 | D16: =-R_prem*$A16^2+D$8*$A16 -> 1.0430826
A17: 60 | B17: =-R_prem*$A17^2+B$8*$A17 -> 6.0567965 | C17: =-R_prem*$A17^2+C$8*$A17 -> 2.8033983 | D17: =-R_prem*$A17^2+D$8*$A17 -> 1.1766991
A18: 70 | B18: =-R_prem*$A18^2+B$8*$A18 -> 6.9787626 | C18: =-R_prem*$A18^2+C$8*$A18 -> 3.1831313 | D18: =-R_prem*$A18^2+D$8*$A18 -> 1.2853157
A19: 80 | B19: =-R_prem*$A19^2+B$8*$A19 -> 7.8757287 | C19: =-R_prem*$A19^2+C$8*$A19 -> 3.5378644 | D19: =-R_prem*$A19^2+D$8*$A19 -> 1.3689322
A20: 90 | B20: =-R_prem*$A20^2+B$8*$A20 -> 8.7476948 | C20: =-R_prem*$A20^2+C$8*$A20 -> 3.8675974 | D20: =-R_prem*$A20^2+D$8*$A20 -> 1.4275487
A21: 100 | B21: =-R_prem*$A21^2+B$8*$A21 -> 9.5946609 | C21: =-R_prem*$A21^2+C$8*$A21 -> 4.1723305 | D21: =-R_prem*$A21^2+D$8*$A21 -> 1.4611652
A22: 110 | B22: =-R_prem*$A22^2+B$8*$A22 -> 10.416627 | C22: =-R_prem*$A22^2+C$8*$A22 -> 4.4520635 | D22: =-R_prem*$A22^2+D$8*$A22 -> 1.4697818
... A61: 500 | B61: =-R_prem*$A61^2+B$8*$A61 -> 22.973305 | C61: =-R_prem*$A61^2+C$8*$A61 -> -4.1383477 | D61: =-R_prem*$A61^2+D$8*$A61 -> -17.694174
A63: Best rate on this grid of 10 | B63: =INDEX($A$11:$A$61,MATCH(MAX(B11:B61),B11:B61,0)) -> 430 | C63: =INDEX($A$11:$A$61,MATCH(MAX(C11:C61),C11:C61,0)) -> 220 | D63: =INDEX($A$11:$A$61,MATCH(MAX(D11:D61),D11:D61,0)) -> 110

Sheet PolicyIteration
A1: Find the gain by policy iteration from Volume I's cautious gain (Theorem 8.3(iii); Section 8.6)
A2: Evaluate the rule v = -k d: its cost is p_k d^2 with p_k = (q + r k^2)/(2(a + b k) + rho). Make it greedy for that cost: k <- b p_k / r. Kleinman: Newton's method on the Riccati equation.
A4: Step | B4: Gain k a year | C4: p_k | D4: Cost from 100 short | E4: Above the best | F4: Discounted gap dies out at (a year)
A5: 0 | B5: =K_caut -> 2 | C5: =(Q_gap+R_prem*B5^2)/(2*(A_close+B_share*B5)+Rho_a) -> 0.0011083837 | D5: =C5*D0_gap^2 -> 11.083837 | E5: =D5-Riccati!$B$14 -> 2.0466191 | F5: =A_close+B_share*B5+Rho_a/2 -> 1.6690972
A6: 1 | B6: =B_share*C5/R_prem -> 5.3202415 | C6: =(Q_gap+R_prem*B6^2)/(2*(A_close+B_share*B6)+Rho_a) -> 0.00092019609 | D6: =C6*D0_gap^2 -> 9.2019609 | E6: =D6-Riccati!$B$14 -> 0.16474343 | F6: =A_close+B_share*B6+Rho_a/2 -> 3.6612421
A7: 2 | B7: =B_share*C6/R_prem -> 4.4169412 | C7: =(Q_gap+R_prem*B7^2)/(2*(A_close+B_share*B7)+Rho_a) -> 0.00090384704 | D7: =C7*D0_gap^2 -> 9.0384704 | E7: =D7-Riccati!$B$14 -> 0.0012529301 | F7: =A_close+B_share*B7+Rho_a/2 -> 3.1192619
A8: 3 | B8: =B_share*C7/R_prem -> 4.3384658 | C8: =(Q_gap+R_prem*B8^2)/(2*(A_close+B_share*B8)+Rho_a) -> 0.00090372175 | D8: =C8*D0_gap^2 -> 9.0372175 | E8: =D8-Riccati!$B$14 -> 7.3581731e-08 | F8: =A_close+B_share*B8+Rho_a/2 -> 3.0721766
A9: 4 | B9: =B_share*C8/R_prem -> 4.3378644 | C9: =(Q_gap+R_prem*B9^2)/(2*(A_close+B_share*B9)+Rho_a) -> 0.00090372174 | D9: =C9*D0_gap^2 -> 9.0372174 | E9: =D9-Riccati!$B$14 -> 0 | F9: =A_close+B_share*B9+Rho_a/2 -> 3.0718158
A10: 5 | B10: =B_share*C9/R_prem -> 4.3378644 | C10: =(Q_gap+R_prem*B10^2)/(2*(A_close+B_share*B10)+Rho_a) -> 0.00090372174 | D10: =C10*D0_gap^2 -> 9.0372174 | E10: =D10-Riccati!$B$14 -> 0 | F10: =A_close+B_share*B10+Rho_a/2 -> 3.0718158
A11: 6 | B11: =B_share*C10/R_prem -> 4.3378644 | C11: =(Q_gap+R_prem*B11^2)/(2*(A_close+B_share*B11)+Rho_a) -> 0.00090372174 | D11: =C11*D0_gap^2 -> 9.0372174 | E11: =D11-Riccati!$B$14 -> 0 | F11: =A_close+B_share*B11+Rho_a/2 -> 3.0718158
A13: Costs from 100 short if approvals landed at once
A14: Rule | B14: Gain k a year | C14: Cost (q + r k^2) d0^2 / (2(a + b k) + rho)
A15: Step 2's gain (the Riccati rule) | B15: =Riccati!B9 -> 4.3378644 | C15: =(Q_gap+R_prem*B15^2)*D0_gap^2/(2*(A_close+B_share*B15)+Rho_a) -> 9.0372174
A16: Best gain on today's gap (engine: a search over simulated costs) | B16: 2.4823475 | C16: =(Q_gap+R_prem*B16^2)*D0_gap^2/(2*(A_close+B_share*B16)+Rho_a) -> 10.135932
A17: Volume I's cautious gain | B17: =K_caut -> 2 | C17: =(Q_gap+R_prem*B17^2)*D0_gap^2/(2*(A_close+B_share*B17)+Rho_a) -> 11.083837
A18: Volume I's deadbeat gain | B18: =K_dead -> 6 | C18: =(Q_gap+R_prem*B18^2)*D0_gap^2/(2*(A_close+B_share*B18)+Rho_a) -> 9.4615583
A19: The cautious gain is the worst of these, above the best by | C19: =C17-C15 -> 2.0466191

Sheet Delay
A1: Allow for the delay: steer by the predicted gap (Proposition 8.3(ii); Worked Example 8.1, Step 3; Figure 8.3(b))
A2: The predicted gap z(t) = d(t + tau) moves as the gap would if approvals landed at once; the first quarter's cost is fixed; the rest is Theorem 8.3's problem in z with q' = q e^(-rho tau).
A3: Quantity | B3: Value | C3: Reading
A4: q' = q e^(-rho tau) | B4: =Q_gap*EXP(-Rho_a*Tau_d) -> 0.0031246531 | C4: The gap's cost, a quarter later
A5: p': positive root with q' | B5: =(-(Riccati!B5)+SQRT((Riccati!B5)^2+4*(Riccati!B4)*(B4)))/(2*(Riccati!B4)) -> 0.00089138618
A6: Gain K' = b p' / r, a year | B6: =B_share*B5/R_prem -> 4.2786537 | C6: Approve 4.28 times the predicted gap
A7: Gain a quarter | B7: =B6/4 -> 1.0696634
A8: Predicted gap today, z0 = e^(-a tau) d0 | B8: =EXP(-A_close*Tau_d)*D0_gap -> -90 | C8: Nothing in flight: 90 short a quarter from now
A9: First quarter's cost (fixed) | B9: =Q_gap*D0_gap^2*(1-EXP(-(2*A_close+Rho_a)*Tau_d))/(2*A_close+Rho_a) -> 7.1310495 | C9: Nothing HR does reaches the bench
A10: The rest, p' z0^2 | B10: =B5*B8^2 -> 7.2202281
A11: Least cost with the delay | B11: =B9+B10 -> 14.351278 | C11: $14.35 million
A12: The quarter's delay costs | B12: =B11-Riccati!B14 -> 5.3140601 | C12: $5.31 million
A13: The predicted gap closes at a + b K' | B13: =A_close+B_share*B6 -> 2.9886343
A14: First approval rate, K' |z0| (a year) | B14: =B6*ABS(B8) -> 385.07883 | C14: 385 a year
A15: Approvals in the first quarter | B15: =B14*(1-EXP(-B13*Tau_d))/B13 -> 67.811203 | C15: 68
A16: Gap after a year | B16: =B8*EXP(-B13*(1-Tau_d)) -> -9.5671368 | C16: 10 short, no overshoot
A17: Marginal premium at the start, 2 r v | B17: =2*R_prem*B14 -> 0.096269707
A18: Value of an approval at the start, b 2p'|z0| | B18: =B_share*2*B5*ABS(B8) -> 0.096269707 | C18: Equal
A19: Price of an engineer already on the bench | B19: =2*Q_gap*ABS(D0_gap)*(1-EXP(-(2*A_close+Rho_a)*Tau_d))/(2*A_close+Rho_a)+2*B5*ABS(B8)*EXP(-A_close*Tau_d) -> 0.28702555 | C19: $287,000, against $181,000 without the delay
A21: The least cost against the time approvals take to land (Figure 8.3(b))
A22: Months to land | B22: tau (years) | C22: q' | D22: p' | E22: z0 | F22: First period's cost | G22: Least cost
A23: 0 | B23: =A23/12 -> 0 | C23: =Q_gap*EXP(-Rho_a*B23) -> 0.0032 | D23: =(-(Riccati!$B$5)+SQRT((Riccati!$B$5)^2+4*(Riccati!$B$4)*(C23)))/(2*(Riccati!$B$4)) -> 0.00090372174 | E23: =EXP(-A_close*B23)*D0_gap -> -100 | F23: =Q_gap*D0_gap^2*(1-EXP(-(2*A_close+Rho_a)*B23))/(2*A_close+Rho_a) -> 0 | G23: =F23+D23*E23^2 -> 9.0372174
A24: 1 | B24: =A24/12 -> 0.083333333 | C24: =Q_gap*EXP(-Rho_a*B24) -> 0.0031746846 | D24: =(-(Riccati!$B$5)+SQRT((Riccati!$B$5)^2+4*(Riccati!$B$4)*(C24)))/(2*(Riccati!$B$4)) -> 0.00089959316 | E24: =EXP(-A_close*B24)*D0_gap -> -96.548938 | F24: =Q_gap*D0_gap^2*(1-EXP(-(2*A_close+Rho_a)*B24))/(2*A_close+Rho_a) -> 2.5650873 | G24: =F24+D24*E24^2 -> 10.950823
A25: 2 | B25: =A25/12 -> 0.16666667 | C25: =Q_gap*EXP(-Rho_a*B25) -> 0.0031495695 | D25: =(-(Riccati!$B$5)+SQRT((Riccati!$B$5)^2+4*(Riccati!$B$4)*(C25)))/(2*(Riccati!$B$4)) -> 0.00089548133 | E25: =EXP(-A_close*B25)*D0_gap -> -93.216975 | F25: =Q_gap*D0_gap^2*(1-EXP(-(2*A_close+Rho_a)*B25))/(2*A_close+Rho_a) -> 4.9372679 | G25: =F25+D25*E25^2 -> 12.718467
A26: 3 | B26: =A26/12 -> 0.25 | C26: =Q_gap*EXP(-Rho_a*B26) -> 0.0031246531 | D26: =(-(Riccati!$B$5)+SQRT((Riccati!$B$5)^2+4*(Riccati!$B$4)*(C26)))/(2*(Riccati!$B$4)) -> 0.00089138618 | E26: =EXP(-A_close*B26)*D0_gap -> -90 | F26: =Q_gap*D0_gap^2*(1-EXP(-(2*A_close+Rho_a)*B26))/(2*A_close+Rho_a) -> 7.1310495 | G26: =F26+D26*E26^2 -> 14.351278
A27: 4 | B27: =A27/12 -> 0.33333333 | C27: =Q_gap*EXP(-Rho_a*B27) -> 0.0030999338 | D27: =(-(Riccati!$B$5)+SQRT((Riccati!$B$5)^2+4*(Riccati!$B$4)*(C27)))/(2*(Riccati!$B$4)) -> 0.00088730765 | E27: =EXP(-A_close*B27)*D0_gap -> -86.894045 | F27: =Q_gap*D0_gap^2*(1-EXP(-(2*A_close+Rho_a)*B27))/(2*A_close+Rho_a) -> 9.1598483 | G27: =F27+D27*E27^2 -> 15.859531
A28: 5 | B28: =A28/12 -> 0.41666667 | C28: =Q_gap*EXP(-Rho_a*B28) -> 0.00307541 | D28: =(-(Riccati!$B$5)+SQRT((Riccati!$B$5)^2+4*(Riccati!$B$4)*(C28)))/(2*(Riccati!$B$4)) -> 0.00088324567 | E28: =EXP(-A_close*B28)*D0_gap -> -83.895278 | F28: =Q_gap*D0_gap^2*(1-EXP(-(2*A_close+Rho_a)*B28))/(2*A_close+Rho_a) -> 11.036072 | G28: =F28+D28*E28^2 -> 17.252724
A29: 6 | B29: =A29/12 -> 0.5 | C29: =Q_gap*EXP(-Rho_a*B29) -> 0.0030510803 | D29: =(-(Riccati!$B$5)+SQRT((Riccati!$B$5)^2+4*(Riccati!$B$4)*(C29)))/(2*(Riccati!$B$4)) -> 0.00087920017 | E29: =EXP(-A_close*B29)*D0_gap -> -81 | F29: =Q_gap*D0_gap^2*(1-EXP(-(2*A_close+Rho_a)*B29))/(2*A_close+Rho_a) -> 12.771195 | G29: =F29+D29*E29^2 -> 18.539627
A31: Cutting the delay from a quarter to a month is worth | G31: =G26-G24 -> 3.4004549

Sheet Rules
A1: Table 8.3: rules for closing a gap of 100 engineers when approvals take a quarter to land (Worked Example 8.1, Step 4; AXIOM Lab 2.8, step 3)
A2: Engine values (green): the delay equation simulated at steps of 1e-4 and 5e-5 years over 12 years, the cost extrapolated (Online Appendix 8.B.1). Gains, extra costs and the at-once column are formulas.
A4: Rule | B4: Steers by | C4: Gain a year | D4: Gain a quarter | E4: Approved, first quarter | F4: Largest surplus | G4: Gap after a year | H4: Cost | I4: Extra | J4: At once
A5: Best rule: steer by the predicted gap | B5: the predicted gap | C5: =Delay!B6 -> 4.2786537 | D5: =C5/4 -> 1.0696634 | E5: 67.814643 | F5: 0 | G5: -9.5659029 | H5: 14.351277 | I5: - | J5: =Riccati!B14 -> 9.0372174
A6: Step 2's gain on today's gap | B6: today's gap | C6: =Riccati!B9 -> 4.3378644 | D6: =C6/4 -> 1.0844661 | E6: 102.93016 | F6: 15.866575 | G6: 12.242305 | H6: 17.470796 | I6: =H6-$H$5 -> 3.1195184 | J6: =(Q_gap+R_prem*C6^2)*D0_gap^2/(2*(A_close+B_share*C6)+Rho_a) -> 9.0372174
A7: Best gain on today's gap | B7: today's gap | C7: 2.4823475 | D7: =C7/4 -> 0.62058686 | E7: 58.901895 | F7: 0.11914512 | G7: -5.8606917 | H7: 14.581192 | I7: =H7-$H$5 -> 0.22991454 | J7: =(Q_gap+R_prem*C7^2)*D0_gap^2/(2*(A_close+B_share*C7)+Rho_a) -> 10.135932
A8: Volume I's cautious gain | B8: today's gap | C8: =K_caut -> 2 | D8: =C8/4 -> 0.5 | E8: 47.456608 | F8: 0 | G8: -14.173388 | H8: 14.844011 | I8: =H8-$H$5 -> 0.49273311 | J8: =(Q_gap+R_prem*C8^2)*D0_gap^2/(2*(A_close+B_share*C8)+Rho_a) -> 11.083837
A9: Volume I's deadbeat gain | B9: today's gap | C9: =K_dead -> 6 | D9: =C9/4 -> 1.5 | E9: 142.36982 | F9: 36.558913 | G9: 10.941216 | H9: 25.069531 | I9: =H9-$H$5 -> 10.718254 | J9: =(Q_gap+R_prem*C9^2)*D0_gap^2/(2*(A_close+B_share*C9)+Rho_a) -> 9.4615583
A11: The best rule in closed form (Delay sheet), and its simulated cost less it | H11: =Delay!B11 -> 14.351278 | I11: =H5-H11 -> -8.2721927e-08
A12: If approvals landed at once, the cautious gain would be above the best by | J12: =J8-J5 -> 2.0466191
A14: Figure 8.3(a): the cost of v = -k d from 100 short, against the gain
A15: Gain k a year | B15: Approvals land at once (formula) | C15: A quarter late (engine)
A16: 1 | B16: =(Q_gap+R_prem*A16^2)*D0_gap^2/(2*(A_close+B_share*A16)+Rho_a) -> 15.550504 | C16: 18.013038
A17: 2 | B17: =(Q_gap+R_prem*A17^2)*D0_gap^2/(2*(A_close+B_share*A17)+Rho_a) -> 11.083837 | C17: 14.844009
A18: 3 | B18: =(Q_gap+R_prem*A18^2)*D0_gap^2/(2*(A_close+B_share*A18)+Rho_a) -> 9.5302222 | C18: 14.83181
A19: 4 | B19: =(Q_gap+R_prem*A19^2)*D0_gap^2/(2*(A_close+B_share*A19)+Rho_a) -> 9.0620842 | C19: 16.547144
A20: 5 | B20: =(Q_gap+R_prem*A20^2)*D0_gap^2/(2*(A_close+B_share*A20)+Rho_a) -> 9.1162048 | C20: 19.825708
A21: 6 | B21: =(Q_gap+R_prem*A21^2)*D0_gap^2/(2*(A_close+B_share*A21)+Rho_a) -> 9.4615583 | C21: 25.069506
A22: 7 | B22: =(Q_gap+R_prem*A22^2)*D0_gap^2/(2*(A_close+B_share*A22)+Rho_a) -> 9.9858706 | C22: 33.382257
A23: 8 | B23: =(Q_gap+R_prem*A23^2)*D0_gap^2/(2*(A_close+B_share*A23)+Rho_a) -> 10.628007 | C23: 47.465922
A25: Steering harder on today's gap pays only if approvals land at once; a quarter late, the best gain on today's gap is 2.48 a year and the cost climbs steeply above it.

Sheet CriticalGain
A1: Why a rule on today's gap must be gentle: its critical gain (Proposition 8.3(i); Online Appendix 8.B.1)
A2: d'(t) = -a d(t) - b k d(t - tau) has a root s = i w when b k cos(w tau) = -a and b k sin(w tau) = w: w solves w + a tan(w tau) = 0 between pi/(2 tau) and pi/tau. Bisection.
A4: Step | B4: Low | C4: High | D4: Middle | E4: w + a tan(w tau) | G4: Result | H4: Value
A5: 1 | B5: =PI()/(2*Tau_d)+0.000000001 -> 6.2831853 | C5: =PI()/Tau_d-0.000000001 -> 12.566371 | D5: =(B5+C5)/2 -> 9.424778 | E5: =D5+A_close*TAN(D5*Tau_d) -> 9.0033359 | G5: w (radians a year) | H5: =D64 -> 6.5405698
A6: 2 | B6: =IF(E5<0,D5,B5) -> 6.2831853 | C6: =IF(E5<0,C5,D5) -> 9.424778 | D6: =(B6+C6)/2 -> 7.8539816 | E6: =D6+A_close*TAN(D6*Tau_d) -> 6.8365305 | G6: Critical gain (a^2 + w^2)^(1/2) / b, a year | H6: =SQRT(A_close^2+H5^2)/B_share -> 10.923556
A7: 3 | B7: =IF(E6<0,D6,B6) -> 6.2831853 | C7: =IF(E6<0,C6,D6) -> 7.8539816 | D7: =(B7+C7)/2 -> 7.0685835 | E7: =D7+A_close*TAN(D7*Tau_d) -> 4.9498511 | G7: a quarter | H7: =H6/4 -> 2.730889
A8: 4 | B8: =IF(E7<0,D7,B7) -> 6.2831853 | C8: =IF(E7<0,C7,D7) -> 7.0685835 | D8: =(B8+C8)/2 -> 6.6758844 | E8: =D8+A_close*TAN(D8*Tau_d) -> 2.3969113 | G8: Period of the swings 2 pi / w (years) | H8: =2*PI()/H5 -> 0.96064801
A9: 5 | B9: =IF(E8<0,D8,B8) -> 6.2831853 | C9: =IF(E8<0,C8,D8) -> 6.6758844 | D9: =(B9+C9)/2 -> 6.4795348 | E9: =D9+A_close*TAN(D9*Tau_d) -> -2.0991154 | G9: Volume I's quarterly review: stable below 1/b, a quarter | H9: =1/B_share -> 1.6666667
A10: 6 | B10: =IF(E9<0,D9,B9) -> 6.4795348 | C10: =IF(E9<0,C9,D9) -> 6.6758844 | D10: =(B10+C10)/2 -> 6.5777096 | E10: =D10+A_close*TAN(D10*Tau_d) -> 0.86435899
A11: 7 | B11: =IF(E10<0,D10,B10) -> 6.4795348 | C11: =IF(E10<0,C10,D10) -> 6.5777096 | D11: =(B11+C11)/2 -> 6.5286222 | E11: =D11+A_close*TAN(D11*Tau_d) -> -0.33119355 | G11: Largest gap of v = -k d (engine) | H11: Years 2-4 | I11: Years 10-12
A12: 8 | B12: =IF(E11<0,D11,B11) -> 6.5286222 | C12: =IF(E11<0,C11,D11) -> 6.5777096 | D12: =(B12+C12)/2 -> 6.5531659 | E12: =D12+A_close*TAN(D12*Tau_d) -> 0.31861627 | G12: Gain 10 a year (2.5 a quarter) | H12: 61.399625 | I12: 8.3704876
A13: 9 | B13: =IF(E12<0,D12,B12) -> 6.5286222 | C13: =IF(E12<0,C12,D12) -> 6.5531659 | D13: =(B13+C13)/2 -> 6.5408941 | E13: =D13+A_close*TAN(D13*Tau_d) -> 0.008578091 | G13: Gain 12 a year (3.0 a quarter) | H13: 280.33302 | I13: 2412.6239
A14: 10 | B14: =IF(E13<0,D13,B13) -> 6.5286222 | C14: =IF(E13<0,C13,D13) -> 6.5408941 | D14: =(B14+C14)/2 -> 6.5347582 | E14: =D14+A_close*TAN(D14*Tau_d) -> -0.15731909
A15: 11 | B15: =IF(E14<0,D14,B14) -> 6.5347582 | C15: =IF(E14<0,C14,D14) -> 6.5408941 | D15: =(B15+C15)/2 -> 6.5378261 | E15: =D15+A_close*TAN(D15*Tau_d) -> -0.073409384 | G15: Engine values: the delay equation simulated at steps of 5e-5 and 2.5e-5 years; a window's largest gap converges at first order in the step, so it is extrapolated, 2 m(dt/2) - m(dt) (Online Appendix 8.B.1).
A16: 12 | B16: =IF(E15<0,D15,B15) -> 6.5378261 | C16: =IF(E15<0,C15,D15) -> 6.5408941 | D16: =(B16+C16)/2 -> 6.5393601 | E16: =D16+A_close*TAN(D16*Tau_d) -> -0.032179684 | G16: Below the critical gain the swings die out; above it they grow. Steering by the predicted gap removes the delay from the loop.
A17: 13 | B17: =IF(E16<0,D16,B16) -> 6.5393601 | C17: =IF(E16<0,C16,D16) -> 6.5408941 | D17: =(B17+C17)/2 -> 6.5401271 | E17: =D17+A_close*TAN(D17*Tau_d) -> -0.011742334
A18: 14 | B18: =IF(E17<0,D17,B17) -> 6.5401271 | C18: =IF(E17<0,C17,D17) -> 6.5408941 | D18: =(B18+C18)/2 -> 6.5405106 | E18: =D18+A_close*TAN(D18*Tau_d) -> -0.0015675712
A19: 15 | B19: =IF(E18<0,D18,B18) -> 6.5405106 | C19: =IF(E18<0,C18,D18) -> 6.5408941 | D19: =(B19+C19)/2 -> 6.5407023 | E19: =D19+A_close*TAN(D19*Tau_d) -> 0.0035088894
A20: 16 | B20: =IF(E19<0,D19,B19) -> 6.5405106 | C20: =IF(E19<0,C19,D19) -> 6.5407023 | D20: =(B20+C20)/2 -> 6.5406065 | E20: =D20+A_close*TAN(D20*Tau_d) -> 0.00097156748
A21: 17 | B21: =IF(E20<0,D20,B20) -> 6.5405106 | C21: =IF(E20<0,C20,D20) -> 6.5406065 | D21: =(B21+C21)/2 -> 6.5405585 | E21: =D21+A_close*TAN(D21*Tau_d) -> -0.00029777462
A22: 18 | B22: =IF(E21<0,D21,B21) -> 6.5405585 | C22: =IF(E21<0,C21,D21) -> 6.5406065 | D22: =(B22+C22)/2 -> 6.5405825 | E22: =D22+A_close*TAN(D22*Tau_d) -> 0.00033695322
A23: 19 | B23: =IF(E22<0,D22,B22) -> 6.5405585 | C23: =IF(E22<0,C22,D22) -> 6.5405825 | D23: =(B23+C23)/2 -> 6.5405705 | E23: =D23+A_close*TAN(D23*Tau_d) -> 1.9603496e-05
A24: 20 | B24: =IF(E23<0,D23,B23) -> 6.5405585 | C24: =IF(E23<0,C23,D23) -> 6.5405705 | D24: =(B24+C24)/2 -> 6.5405645 | E24: =D24+A_close*TAN(D24*Tau_d) -> -0.00013908201
A25: 21 | B25: =IF(E24<0,D24,B24) -> 6.5405645 | C25: =IF(E24<0,C24,D24) -> 6.5405705 | D25: =(B25+C25)/2 -> 6.5405675 | E25: =D25+A_close*TAN(D25*Tau_d) -> -5.9738371e-05
A26: 22 | B26: =IF(E25<0,D25,B25) -> 6.5405675 | C26: =IF(E25<0,C25,D25) -> 6.5405705 | D26: =(B26+C26)/2 -> 6.540569 | E26: =D26+A_close*TAN(D26*Tau_d) -> -2.0067215e-05
A27: 23 | B27: =IF(E26<0,D26,B26) -> 6.540569 | C27: =IF(E26<0,C26,D26) -> 6.5405705 | D27: =(B27+C27)/2 -> 6.5405698 | E27: =D27+A_close*TAN(D27*Tau_d) -> -2.3180403e-07
A28: 24 | B28: =IF(E27<0,D27,B27) -> 6.5405698 | C28: =IF(E27<0,C27,D27) -> 6.5405705 | D28: =(B28+C28)/2 -> 6.5405701 | E28: =D28+A_close*TAN(D28*Tau_d) -> 9.68586e-06
... A64: 60 | B64: =IF(E63<0,D63,B63) -> 6.5405698 | C64: =IF(E63<0,C63,D63) -> 6.5405698 | D64: =(B64+C64)/2 -> 6.5405698 | E64: =D64+A_close*TAN(D64*Tau_d) -> 0

Sheet Sensitivities
A1: Test the declarations (Worked Example 8.1, Step 5; Figure 8.3(b))
A3: Declaration | B3: q multiplier | C3: r multiplier | D3: q | E3: r | F3: p at once | G3: Gain K at once | H3: Least cost at once | I3: q' | J3: p' | K3: Gain K' with the delay | L3: Least cost with the delay
A4: Base | B4: 1 | C4: 1 | D4: =Q_gap*B4 -> 0.0032 | E4: =R_prem*C4 -> 0.000125 | F4: =(-(2*A_close+Rho_a)+SQRT((2*A_close+Rho_a)^2+4*(B_share^2/E4)*(D4)))/(2*(B_share^2/E4)) -> 0.00090372174 | G4: =B_share*F4/E4 -> 4.3378644 | H4: =F4*D0_gap^2 -> 9.0372174 | I4: =D4*EXP(-Rho_a*Tau_d) -> 0.0031246531 | J4: =(-(2*A_close+Rho_a)+SQRT((2*A_close+Rho_a)^2+4*(B_share^2/E4)*(I4)))/(2*(B_share^2/E4)) -> 0.00089138618 | K4: =B_share*J4/E4 -> 4.2786537 | L4: =D4*D0_gap^2*(1-EXP(-(2*A_close+Rho_a)*Tau_d))/(2*A_close+Rho_a)+J4*(EXP(-A_close*Tau_d)*D0_gap)^2 -> 14.351278
A5: Gap cost doubled | B5: 2 | C5: 1 | D5: =Q_gap*B5 -> 0.0064 | E5: =R_prem*C5 -> 0.000125 | F5: =(-(2*A_close+Rho_a)+SQRT((2*A_close+Rho_a)^2+4*(B_share^2/E5)*(D5)))/(2*(B_share^2/E5)) -> 0.0013367031 | G5: =B_share*F5/E5 -> 6.416175 | H5: =F5*D0_gap^2 -> 13.367031 | I5: =D5*EXP(-Rho_a*Tau_d) -> 0.0062493062 | J5: =(-(2*A_close+Rho_a)+SQRT((2*A_close+Rho_a)^2+4*(B_share^2/E5)*(I5)))/(2*(B_share^2/E5)) -> 0.0013191542 | K5: =B_share*J5/E5 -> 6.3319401 | L5: =D5*D0_gap^2*(1-EXP(-(2*A_close+Rho_a)*Tau_d))/(2*A_close+Rho_a)+J5*(EXP(-A_close*Tau_d)*D0_gap)^2 -> 24.947248
A6: Gap cost halved | B6: 0.5 | C6: 1 | D6: =Q_gap*B6 -> 0.0016 | E6: =R_prem*C6 -> 0.000125 | F6: =(-(2*A_close+Rho_a)+SQRT((2*A_close+Rho_a)^2+4*(B_share^2/E6)*(D6)))/(2*(B_share^2/E6)) -> 0.0006000645 | G6: =B_share*F6/E6 -> 2.8803096 | H6: =F6*D0_gap^2 -> 6.000645 | I6: =D6*EXP(-Rho_a*Tau_d) -> 0.0015623265 | J6: =(-(2*A_close+Rho_a)+SQRT((2*A_close+Rho_a)^2+4*(B_share^2/E6)*(I6)))/(2*(B_share^2/E6)) -> 0.00059144305 | K6: =B_share*J6/E6 -> 2.8389266 | L6: =D6*D0_gap^2*(1-EXP(-(2*A_close+Rho_a)*Tau_d))/(2*A_close+Rho_a)+J6*(EXP(-A_close*Tau_d)*D0_gap)^2 -> 8.3562134
A7: Premium doubled | B7: 1 | C7: 2 | D7: =Q_gap*B7 -> 0.0032 | E7: =R_prem*C7 -> 0.00025 | F7: =(-(2*A_close+Rho_a)+SQRT((2*A_close+Rho_a)^2+4*(B_share^2/E7)*(D7)))/(2*(B_share^2/E7)) -> 0.001200129 | G7: =B_share*F7/E7 -> 2.8803096 | H7: =F7*D0_gap^2 -> 12.00129 | I7: =D7*EXP(-Rho_a*Tau_d) -> 0.0031246531 | J7: =(-(2*A_close+Rho_a)+SQRT((2*A_close+Rho_a)^2+4*(B_share^2/E7)*(I7)))/(2*(B_share^2/E7)) -> 0.0011828861 | K7: =B_share*J7/E7 -> 2.8389266 | L7: =D7*D0_gap^2*(1-EXP(-(2*A_close+Rho_a)*Tau_d))/(2*A_close+Rho_a)+J7*(EXP(-A_close*Tau_d)*D0_gap)^2 -> 16.712427
A8: Premium halved | B8: 1 | C8: 0.5 | D8: =Q_gap*B8 -> 0.0032 | E8: =R_prem*C8 -> 6.25e-05 | F8: =(-(2*A_close+Rho_a)+SQRT((2*A_close+Rho_a)^2+4*(B_share^2/E8)*(D8)))/(2*(B_share^2/E8)) -> 0.00066835156 | G8: =B_share*F8/E8 -> 6.416175 | H8: =F8*D0_gap^2 -> 6.6835156 | I8: =D8*EXP(-Rho_a*Tau_d) -> 0.0031246531 | J8: =(-(2*A_close+Rho_a)+SQRT((2*A_close+Rho_a)^2+4*(B_share^2/E8)*(I8)))/(2*(B_share^2/E8)) -> 0.0006595771 | K8: =B_share*J8/E8 -> 6.3319401 | L8: =D8*D0_gap^2*(1-EXP(-(2*A_close+Rho_a)*Tau_d))/(2*A_close+Rho_a)+J8*(EXP(-A_close*Tau_d)*D0_gap)^2 -> 12.473624
A10: Approvals take half a year while HR steers for a quarter (engine: the delay equation simulated over 14 years)
A11: Rule | B11: Cost | C11: Largest surplus
A12: Best rule, built for a quarter | B12: 19.994894 | C12: 16.347645
A13: Step 2's gain on today's gap | B13: 42.850427 | C13: 64.291656
A14: Volume I's cautious gain | B14: 19.529529 | C14: 12.070892
A16: Rule built for half a year: q' | B16: =Q_gap*EXP(-Rho_a*0.5) -> 0.0030510803
A17: p' | B17: =(-(Riccati!B5)+SQRT((Riccati!B5)^2+4*(Riccati!B4)*(B16)))/(2*(Riccati!B4)) -> 0.00087920017
A18: Gain K', a year | B18: =B_share*B17/R_prem -> 4.2201608 | C18: 4.220
A19: Least cost | B19: =Q_gap*D0_gap^2*(1-EXP(-(2*A_close+Rho_a)*0.5))/(2*A_close+Rho_a)+B17*(EXP(-A_close*0.5)*D0_gap)^2 -> 18.539627 | C19: No overshoot
A20: Simulated (engine) | B20: 18.539627 | C20: The closed form, simulated
A22: Only 30 percent of approvals become engineers
A23: Share that becomes engineers | B23: 0.3 | C23: HR's rule still counts 60 percent
A24: Rule built for 60 percent: cost (engine, simulated over 14 years) | B24: 19.610881
A25: Redesigned: p' | B25: =(-(2*A_close+Rho_a)+SQRT((2*A_close+Rho_a)^2+4*(B23^2/R_prem)*(Delay!B4)))/(2*(B23^2/R_prem)) -> 0.0015311991
A26: Redesigned: gain K', a year | B26: =B23*B25/R_prem -> 3.6748778 | C26: 3.675
A27: Redesigned: least cost | B27: =Delay!B9+B25*Delay!B8^2 -> 19.533762
A28: The rule built for 60 percent comes within | B28: =B24-B27 -> 0.077119036 | C28: $0.08 million

Sheet Capability
A1: Chapter 6's capability problem by the HJB equation: values, prices, corners (Propositions 8.1 and 8.2; AXIOM Lab 2.8, step 4)
A3: Capability c | B3: Value V(c) | C3: Price of a point V'(c) | D3: Switching function V' - k | E3: Decision
A4: 45 | B4: =IF(A4<Floor_F,MAX((-(Cost_k*Ubar_c+Delay_D)*(1-EXP(-Rho_a*LN((Top_c-A4)/(Top_c-Floor_F))/Delta_c))/Rho_a+EXP(-Rho_a*LN((Top_c-A4)/(Top_c-Floor_F))/Delta_c)*(-Cost_k*Delta_c*Floor_F/Rho_a)),(-Delay_D/Rho_a)),(EXP(-Rho_a*LN(A4/Floor_F)/Delta_c)*(-Cost_k*Delta_c*Floor_F/Rho_a))) -> -324.45516 | C4: =IF(A4<Floor_F,EXP(-Rho_a*LN((Top_c-A4)/(Top_c-Floor_F))/Delta_c)*(Cost_k*Ubar_c+Delay_D+Rho_a*(-Cost_k*Delta_c*Floor_F/Rho_a))/(Ubar_c-Delta_c*A4),IF(A4=Floor_F,Cost_k,EXP(-Rho_a*LN(A4/Floor_F)/Delta_c)*(-Rho_a*(-Cost_k*Delta_c*Floor_F/Rho_a))/(Delta_c*A4))) -> 7.4659295 | D4: =C4-Cost_k -> 3.4659295 | E4: =IF(ABS(D4)<0.000000001,"hold: pay the rent",IF(D4>0,"hire at the cap","hire nothing")) -> hire at the cap
A5: 53 | B5: =IF(A5<Floor_F,MAX((-(Cost_k*Ubar_c+Delay_D)*(1-EXP(-Rho_a*LN((Top_c-A5)/(Top_c-Floor_F))/Delta_c))/Rho_a+EXP(-Rho_a*LN((Top_c-A5)/(Top_c-Floor_F))/Delta_c)*(-Cost_k*Delta_c*Floor_F/Rho_a)),(-Delay_D/Rho_a)),(EXP(-Rho_a*LN(A5/Floor_F)/Delta_c)*(-Cost_k*Delta_c*Floor_F/Rho_a))) -> -254.89212 | C5: =IF(A5<Floor_F,EXP(-Rho_a*LN((Top_c-A5)/(Top_c-Floor_F))/Delta_c)*(Cost_k*Ubar_c+Delay_D+Rho_a*(-Cost_k*Delta_c*Floor_F/Rho_a))/(Ubar_c-Delta_c*A5),IF(A5=Floor_F,Cost_k,EXP(-Rho_a*LN(A5/Floor_F)/Delta_c)*(-Rho_a*(-Cost_k*Delta_c*Floor_F/Rho_a))/(Delta_c*A5))) -> 10.129671 | D5: =C5-Cost_k -> 6.1296707 | E5: =IF(ABS(D5)<0.000000001,"hold: pay the rent",IF(D5>0,"hire at the cap","hire nothing")) -> hire at the cap
A6: 55 | B6: =IF(A6<Floor_F,MAX((-(Cost_k*Ubar_c+Delay_D)*(1-EXP(-Rho_a*LN((Top_c-A6)/(Top_c-Floor_F))/Delta_c))/Rho_a+EXP(-Rho_a*LN((Top_c-A6)/(Top_c-Floor_F))/Delta_c)*(-Cost_k*Delta_c*Floor_F/Rho_a)),(-Delay_D/Rho_a)),(EXP(-Rho_a*LN(A6/Floor_F)/Delta_c)*(-Cost_k*Delta_c*Floor_F/Rho_a))) -> -233.75962 | C6: =IF(A6<Floor_F,EXP(-Rho_a*LN((Top_c-A6)/(Top_c-Floor_F))/Delta_c)*(Cost_k*Ubar_c+Delay_D+Rho_a*(-Cost_k*Delta_c*Floor_F/Rho_a))/(Ubar_c-Delta_c*A6),IF(A6=Floor_F,Cost_k,EXP(-Rho_a*LN(A6/Floor_F)/Delta_c)*(-Rho_a*(-Cost_k*Delta_c*Floor_F/Rho_a))/(Delta_c*A6))) -> 4 | D6: =C6-Cost_k -> 0 | E6: =IF(ABS(D6)<0.000000001,"hold: pay the rent",IF(D6>0,"hire at the cap","hire nothing")) -> hold: pay the rent
A7: 58 | B7: =IF(A7<Floor_F,MAX((-(Cost_k*Ubar_c+Delay_D)*(1-EXP(-Rho_a*LN((Top_c-A7)/(Top_c-Floor_F))/Delta_c))/Rho_a+EXP(-Rho_a*LN((Top_c-A7)/(Top_c-Floor_F))/Delta_c)*(-Cost_k*Delta_c*Floor_F/Rho_a)),(-Delay_D/Rho_a)),(EXP(-Rho_a*LN(A7/Floor_F)/Delta_c)*(-Cost_k*Delta_c*Floor_F/Rho_a))) -> -222.36266 | C7: =IF(A7<Floor_F,EXP(-Rho_a*LN((Top_c-A7)/(Top_c-Floor_F))/Delta_c)*(Cost_k*Ubar_c+Delay_D+Rho_a*(-Cost_k*Delta_c*Floor_F/Rho_a))/(Ubar_c-Delta_c*A7),IF(A7=Floor_F,Cost_k,EXP(-Rho_a*LN(A7/Floor_F)/Delta_c)*(-Rho_a*(-Cost_k*Delta_c*Floor_F/Rho_a))/(Delta_c*A7))) -> 3.6081706 | D7: =C7-Cost_k -> -0.39182944 | E7: =IF(ABS(D7)<0.000000001,"hold: pay the rent",IF(D7>0,"hire at the cap","hire nothing")) -> hire nothing
A9: Quantity | B9: Value | C9: Reading
A10: Value of the floor forever, V(55) = -k delta 55 / rho | B10: =(-Cost_k*Delta_c*Floor_F/Rho_a) -> -233.75962
A11: Never starting the build: -D / rho | B11: =(-Delay_D/Rho_a) -> -335.74588
A12: x = k u bar / (k u bar + D + rho V(55)) | B12: =Cost_k*Ubar_c/(Cost_k*Ubar_c+Delay_D+Rho_a*(-Cost_k*Delta_c*Floor_F/Rho_a)) -> 0.80647906 | C12: e^(-rho tau) where racing ties never starting
A13: Never-start threshold c_a = 100 - 45 x^(-delta/rho) | B13: =Top_c-(Top_c-Floor_F)*B12^(-Delta_c/Rho_a) -> 43.446247 | C13: Corner: below it the build never starts
A14: Racing from c_a, a check: V_race(c_a) | B14: =(-(Cost_k*Ubar_c+Delay_D)*(1-EXP(-Rho_a*LN((Top_c-B13)/(Top_c-Floor_F))/Delta_c))/Rho_a+EXP(-Rho_a*LN((Top_c-B13)/(Top_c-Floor_F))/Delta_c)*(-Cost_k*Delta_c*Floor_F/Rho_a)) -> -335.74588 | C14: Equals -D / rho
A15: Price just above c_a | B15: =IF(B13<Floor_F,EXP(-Rho_a*LN((Top_c-B13)/(Top_c-Floor_F))/Delta_c)*(Cost_k*Ubar_c+Delay_D+Rho_a*(-Cost_k*Delta_c*Floor_F/Rho_a))/(Ubar_c-Delta_c*B13),IF(B13=Floor_F,Cost_k,EXP(-Rho_a*LN(B13/Floor_F)/Delta_c)*(-Rho_a*(-Cost_k*Delta_c*Floor_F/Rho_a))/(Delta_c*B13))) -> 7.0729169 | C15: Jumps from 0 below
A16: Price just below the floor, k + D / (u bar - delta 55) | B16: =Cost_k+Delay_D/(Ubar_c-Delta_c*Floor_F) -> 11.021847 | C16: Its cost plus the delay it saves; $4 million above
A17: Rent on the floor, k delta 55 (a year) | B17: =Cost_k*Delta_c*Floor_F -> 22.279671
A18: Rent as a share of the position's value | B18: =B17/-B10 -> 0.09531018 | C18: rho: the hurdle return
A19: Holding at c_a: rent on c_a plus the delay (a year) | B19: =Cost_k*Delta_c*B13+Delay_D -> 49.59942 | C19: More than D, what never starting costs at the hurdle rate
A21: HJB at 58: rho V(58) | B21: =Rho_a*B7 -> -21.193425
A22: Drift at 58, delta x 58 (points a year) | B22: =Delta_c*A7 -> 5.8737315
A23: Price of a point at 58 | B23: =C7 -> 3.6081706
A24: Cost of the drift, drift x price (a year) | B24: =B22*B23 -> 21.193425 | C24: Equals -rho V(58)
A25: Hiring's coefficient in the Hamiltonian, V'(58) - k | B25: =B23-Cost_k -> -0.39182944 | C25: Negative: hire nothing
A27: PMP-HJB comparison: Chapter 6's costate m(0) e^((rho + delta) t) against the value's slope at c(t)
A28: Years | B28: Drift from 58: c(t) | C28: Costate | D28: Slope V'(c(t)) | E28: Gap | F28: Race from 53: c(t) | G28: Costate | H28: Slope V'(c(t)) | I28: Gap
A29: 0 | B29: =$A$7*EXP(-Delta_c*A29) -> 58 | C29: =$C$7*EXP((Rho_a+Delta_c)*A29) -> 3.6081706 | D29: =IF(B29<Floor_F,EXP(-Rho_a*LN((Top_c-B29)/(Top_c-Floor_F))/Delta_c)*(Cost_k*Ubar_c+Delay_D+Rho_a*(-Cost_k*Delta_c*Floor_F/Rho_a))/(Ubar_c-Delta_c*B29),IF(B29=Floor_F,Cost_k,EXP(-Rho_a*LN(B29/Floor_F)/Delta_c)*(-Rho_a*(-Cost_k*Delta_c*Floor_F/Rho_a))/(Delta_c*B29))) -> 3.6081706 | E29: =ABS(C29-D29) -> 0 | F29: =Top_c-(Top_c-$A$5)*EXP(-Delta_c*A29) -> 53 | G29: =$C$5*EXP((Rho_a+Delta_c)*A29) -> 10.129671 | H29: =IF(F29<Floor_F,EXP(-Rho_a*LN((Top_c-F29)/(Top_c-Floor_F))/Delta_c)*(Cost_k*Ubar_c+Delay_D+Rho_a*(-Cost_k*Delta_c*Floor_F/Rho_a))/(Ubar_c-Delta_c*F29),IF(F29=Floor_F,Cost_k,EXP(-Rho_a*LN(F29/Floor_F)/Delta_c)*(-Rho_a*(-Cost_k*Delta_c*Floor_F/Rho_a))/(Delta_c*F29))) -> 10.129671 | I29: =ABS(G29-H29) -> 0
A30: 0.04 | B30: =$A$7*EXP(-Delta_c*A30) -> 57.765526 | C30: =$C$7*EXP((Rho_a+Delta_c)*A30) -> 3.6366544 | D30: =IF(B30<Floor_F,EXP(-Rho_a*LN((Top_c-B30)/(Top_c-Floor_F))/Delta_c)*(Cost_k*Ubar_c+Delay_D+Rho_a*(-Cost_k*Delta_c*Floor_F/Rho_a))/(Ubar_c-Delta_c*B30),IF(B30=Floor_F,Cost_k,EXP(-Rho_a*LN(B30/Floor_F)/Delta_c)*(-Rho_a*(-Cost_k*Delta_c*Floor_F/Rho_a))/(Delta_c*B30))) -> 3.6366544 | E30: =ABS(C30-D30) -> 0 | F30: =Top_c-(Top_c-$A$5)*EXP(-Delta_c*A30) -> 53.190005 | G30: =$C$5*EXP((Rho_a+Delta_c)*A30) -> 10.209637 | H30: =IF(F30<Floor_F,EXP(-Rho_a*LN((Top_c-F30)/(Top_c-Floor_F))/Delta_c)*(Cost_k*Ubar_c+Delay_D+Rho_a*(-Cost_k*Delta_c*Floor_F/Rho_a))/(Ubar_c-Delta_c*F30),IF(F30=Floor_F,Cost_k,EXP(-Rho_a*LN(F30/Floor_F)/Delta_c)*(-Rho_a*(-Cost_k*Delta_c*Floor_F/Rho_a))/(Delta_c*F30))) -> 10.209637 | I30: =ABS(G30-H30) -> 0
A31: 0.08 | B31: =$A$7*EXP(-Delta_c*A31) -> 57.532 | C31: =$C$7*EXP((Rho_a+Delta_c)*A31) -> 3.665363 | D31: =IF(B31<Floor_F,EXP(-Rho_a*LN((Top_c-B31)/(Top_c-Floor_F))/Delta_c)*(Cost_k*Ubar_c+Delay_D+Rho_a*(-Cost_k*Delta_c*Floor_F/Rho_a))/(Ubar_c-Delta_c*B31),IF(B31=Floor_F,Cost_k,EXP(-Rho_a*LN(B31/Floor_F)/Delta_c)*(-Rho_a*(-Cost_k*Delta_c*Floor_F/Rho_a))/(Delta_c*B31))) -> 3.665363 | E31: =ABS(C31-D31) -> 0 | F31: =Top_c-(Top_c-$A$5)*EXP(-Delta_c*A31) -> 53.379242 | G31: =$C$5*EXP((Rho_a+Delta_c)*A31) -> 10.290234 | H31: =IF(F31<Floor_F,EXP(-Rho_a*LN((Top_c-F31)/(Top_c-Floor_F))/Delta_c)*(Cost_k*Ubar_c+Delay_D+Rho_a*(-Cost_k*Delta_c*Floor_F/Rho_a))/(Ubar_c-Delta_c*F31),IF(F31=Floor_F,Cost_k,EXP(-Rho_a*LN(F31/Floor_F)/Delta_c)*(-Rho_a*(-Cost_k*Delta_c*Floor_F/Rho_a))/(Delta_c*F31))) -> 10.290234 | I31: =ABS(G31-H31) -> 0
A32: 0.12 | B32: =$A$7*EXP(-Delta_c*A32) -> 57.299418 | C32: =$C$7*EXP((Rho_a+Delta_c)*A32) -> 3.6942983 | D32: =IF(B32<Floor_F,EXP(-Rho_a*LN((Top_c-B32)/(Top_c-Floor_F))/Delta_c)*(Cost_k*Ubar_c+Delay_D+Rho_a*(-Cost_k*Delta_c*Floor_F/Rho_a))/(Ubar_c-Delta_c*B32),IF(B32=Floor_F,Cost_k,EXP(-Rho_a*LN(B32/Floor_F)/Delta_c)*(-Rho_a*(-Cost_k*Delta_c*Floor_F/Rho_a))/(Delta_c*B32))) -> 3.6942983 | E32: =ABS(C32-D32) -> 0 | F32: =Top_c-(Top_c-$A$5)*EXP(-Delta_c*A32) -> 53.567713 | G32: =$C$5*EXP((Rho_a+Delta_c)*A32) -> 10.371468 | H32: =IF(F32<Floor_F,EXP(-Rho_a*LN((Top_c-F32)/(Top_c-Floor_F))/Delta_c)*(Cost_k*Ubar_c+Delay_D+Rho_a*(-Cost_k*Delta_c*Floor_F/Rho_a))/(Ubar_c-Delta_c*F32),IF(F32=Floor_F,Cost_k,EXP(-Rho_a*LN(F32/Floor_F)/Delta_c)*(-Rho_a*(-Cost_k*Delta_c*Floor_F/Rho_a))/(Delta_c*F32))) -> 10.371468 | I32: =ABS(G32-H32) -> 0
A33: 0.16 | B33: =$A$7*EXP(-Delta_c*A33) -> 57.067776 | C33: =$C$7*EXP((Rho_a+Delta_c)*A33) -> 3.7234621 | D33: =IF(B33<Floor_F,EXP(-Rho_a*LN((Top_c-B33)/(Top_c-Floor_F))/Delta_c)*(Cost_k*Ubar_c+Delay_D+Rho_a*(-Cost_k*Delta_c*Floor_F/Rho_a))/(Ubar_c-Delta_c*B33),IF(B33=Floor_F,Cost_k,EXP(-Rho_a*LN(B33/Floor_F)/Delta_c)*(-Rho_a*(-Cost_k*Delta_c*Floor_F/Rho_a))/(Delta_c*B33))) -> 3.7234621 | E33: =ABS(C33-D33) -> 0 | F33: =Top_c-(Top_c-$A$5)*EXP(-Delta_c*A33) -> 53.755423 | G33: =$C$5*EXP((Rho_a+Delta_c)*A33) -> 10.453343 | H33: =IF(F33<Floor_F,EXP(-Rho_a*LN((Top_c-F33)/(Top_c-Floor_F))/Delta_c)*(Cost_k*Ubar_c+Delay_D+Rho_a*(-Cost_k*Delta_c*Floor_F/Rho_a))/(Ubar_c-Delta_c*F33),IF(F33=Floor_F,Cost_k,EXP(-Rho_a*LN(F33/Floor_F)/Delta_c)*(-Rho_a*(-Cost_k*Delta_c*Floor_F/Rho_a))/(Delta_c*F33))) -> 10.453343 | I33: =ABS(G33-H33) -> 0
A34: 0.2 | B34: =$A$7*EXP(-Delta_c*A34) -> 56.837071 | C34: =$C$7*EXP((Rho_a+Delta_c)*A34) -> 3.752856 | D34: =IF(B34<Floor_F,EXP(-Rho_a*LN((Top_c-B34)/(Top_c-Floor_F))/Delta_c)*(Cost_k*Ubar_c+Delay_D+Rho_a*(-Cost_k*Delta_c*Floor_F/Rho_a))/(Ubar_c-Delta_c*B34),IF(B34=Floor_F,Cost_k,EXP(-Rho_a*LN(B34/Floor_F)/Delta_c)*(-Rho_a*(-Cost_k*Delta_c*Floor_F/Rho_a))/(Delta_c*B34))) -> 3.752856 | E34: =ABS(C34-D34) -> 0 | F34: =Top_c-(Top_c-$A$5)*EXP(-Delta_c*A34) -> 53.942374 | G34: =$C$5*EXP((Rho_a+Delta_c)*A34) -> 10.535864 | H34: =IF(F34<Floor_F,EXP(-Rho_a*LN((Top_c-F34)/(Top_c-Floor_F))/Delta_c)*(Cost_k*Ubar_c+Delay_D+Rho_a*(-Cost_k*Delta_c*Floor_F/Rho_a))/(Ubar_c-Delta_c*F34),IF(F34=Floor_F,Cost_k,EXP(-Rho_a*LN(F34/Floor_F)/Delta_c)*(-Rho_a*(-Cost_k*Delta_c*Floor_F/Rho_a))/(Delta_c*F34))) -> 10.535864 | I34: =ABS(G34-H34) -> 0
A35: 0.24 | B35: =$A$7*EXP(-Delta_c*A35) -> 56.607298 | C35: =$C$7*EXP((Rho_a+Delta_c)*A35) -> 3.782482 | D35: =IF(B35<Floor_F,EXP(-Rho_a*LN((Top_c-B35)/(Top_c-Floor_F))/Delta_c)*(Cost_k*Ubar_c+Delay_D+Rho_a*(-Cost_k*Delta_c*Floor_F/Rho_a))/(Ubar_c-Delta_c*B35),IF(B35=Floor_F,Cost_k,EXP(-Rho_a*LN(B35/Floor_F)/Delta_c)*(-Rho_a*(-Cost_k*Delta_c*Floor_F/Rho_a))/(Delta_c*B35))) -> 3.782482 | E35: =ABS(C35-D35) -> 0 | F35: =Top_c-(Top_c-$A$5)*EXP(-Delta_c*A35) -> 54.128569 | G35: =$C$5*EXP((Rho_a+Delta_c)*A35) -> 10.619037 | H35: =IF(F35<Floor_F,EXP(-Rho_a*LN((Top_c-F35)/(Top_c-Floor_F))/Delta_c)*(Cost_k*Ubar_c+Delay_D+Rho_a*(-Cost_k*Delta_c*Floor_F/Rho_a))/(Ubar_c-Delta_c*F35),IF(F35=Floor_F,Cost_k,EXP(-Rho_a*LN(F35/Floor_F)/Delta_c)*(-Rho_a*(-Cost_k*Delta_c*Floor_F/Rho_a))/(Delta_c*F35))) -> 10.619037 | I35: =ABS(G35-H35) -> 0
A36: 0.28 | B36: =$A$7*EXP(-Delta_c*A36) -> 56.378454 | C36: =$C$7*EXP((Rho_a+Delta_c)*A36) -> 3.8123419 | D36: =IF(B36<Floor_F,EXP(-Rho_a*LN((Top_c-B36)/(Top_c-Floor_F))/Delta_c)*(Cost_k*Ubar_c+Delay_D+Rho_a*(-Cost_k*Delta_c*Floor_F/Rho_a))/(Ubar_c-Delta_c*B36),IF(B36=Floor_F,Cost_k,EXP(-Rho_a*LN(B36/Floor_F)/Delta_c)*(-Rho_a*(-Cost_k*Delta_c*Floor_F/Rho_a))/(Delta_c*B36))) -> 3.8123419 | E36: =ABS(C36-D36) -> 0 | F36: =Top_c-(Top_c-$A$5)*EXP(-Delta_c*A36) -> 54.314011 | G36: =$C$5*EXP((Rho_a+Delta_c)*A36) -> 10.702867 | H36: =IF(F36<Floor_F,EXP(-Rho_a*LN((Top_c-F36)/(Top_c-Floor_F))/Delta_c)*(Cost_k*Ubar_c+Delay_D+Rho_a*(-Cost_k*Delta_c*Floor_F/Rho_a))/(Ubar_c-Delta_c*F36),IF(F36=Floor_F,Cost_k,EXP(-Rho_a*LN(F36/Floor_F)/Delta_c)*(-Rho_a*(-Cost_k*Delta_c*Floor_F/Rho_a))/(Delta_c*F36))) -> 10.702867 | I36: =ABS(G36-H36) -> 0
A37: 0.32 | B37: =$A$7*EXP(-Delta_c*A37) -> 56.150535 | C37: =$C$7*EXP((Rho_a+Delta_c)*A37) -> 3.8424375 | D37: =IF(B37<Floor_F,EXP(-Rho_a*LN((Top_c-B37)/(Top_c-Floor_F))/Delta_c)*(Cost_k*Ubar_c+Delay_D+Rho_a*(-Cost_k*Delta_c*Floor_F/Rho_a))/(Ubar_c-Delta_c*B37),IF(B37=Floor_F,Cost_k,EXP(-Rho_a*LN(B37/Floor_F)/Delta_c)*(-Rho_a*(-Cost_k*Delta_c*Floor_F/Rho_a))/(Delta_c*B37))) -> 3.8424375 | E37: =ABS(C37-D37) -> 0 | F37: =Top_c-(Top_c-$A$5)*EXP(-Delta_c*A37) -> 54.498704 | G37: =$C$5*EXP((Rho_a+Delta_c)*A37) -> 10.787358 | H37: =IF(F37<Floor_F,EXP(-Rho_a*LN((Top_c-F37)/(Top_c-Floor_F))/Delta_c)*(Cost_k*Ubar_c+Delay_D+Rho_a*(-Cost_k*Delta_c*Floor_F/Rho_a))/(Ubar_c-Delta_c*F37),IF(F37=Floor_F,Cost_k,EXP(-Rho_a*LN(F37/Floor_F)/Delta_c)*(-Rho_a*(-Cost_k*Delta_c*Floor_F/Rho_a))/(Delta_c*F37))) -> 10.787358 | I37: =ABS(G37-H37) -> 0
A38: 0.36 | B38: =$A$7*EXP(-Delta_c*A38) -> 55.923538 | C38: =$C$7*EXP((Rho_a+Delta_c)*A38) -> 3.8727707 | D38: =IF(B38<Floor_F,EXP(-Rho_a*LN((Top_c-B38)/(Top_c-Floor_F))/Delta_c)*(Cost_k*Ubar_c+Delay_D+Rho_a*(-Cost_k*Delta_c*Floor_F/Rho_a))/(Ubar_c-Delta_c*B38),IF(B38=Floor_F,Cost_k,EXP(-Rho_a*LN(B38/Floor_F)/Delta_c)*(-Rho_a*(-Cost_k*Delta_c*Floor_F/Rho_a))/(Delta_c*B38))) -> 3.8727707 | E38: =ABS(C38-D38) -> 0 | F38: =Top_c-(Top_c-$A$5)*EXP(-Delta_c*A38) -> 54.68265 | G38: =$C$5*EXP((Rho_a+Delta_c)*A38) -> 10.872516 | H38: =IF(F38<Floor_F,EXP(-Rho_a*LN((Top_c-F38)/(Top_c-Floor_F))/Delta_c)*(Cost_k*Ubar_c+Delay_D+Rho_a*(-Cost_k*Delta_c*Floor_F/Rho_a))/(Ubar_c-Delta_c*F38),IF(F38=Floor_F,Cost_k,EXP(-Rho_a*LN(F38/Floor_F)/Delta_c)*(-Rho_a*(-Cost_k*Delta_c*Floor_F/Rho_a))/(Delta_c*F38))) -> 10.872516 | I38: =ABS(G38-H38) -> 0
A39: 0.4 | B39: =$A$7*EXP(-Delta_c*A39) -> 55.697459 | C39: =$C$7*EXP((Rho_a+Delta_c)*A39) -> 3.9033433 | D39: =IF(B39<Floor_F,EXP(-Rho_a*LN((Top_c-B39)/(Top_c-Floor_F))/Delta_c)*(Cost_k*Ubar_c+Delay_D+Rho_a*(-Cost_k*Delta_c*Floor_F/Rho_a))/(Ubar_c-Delta_c*B39),IF(B39=Floor_F,Cost_k,EXP(-Rho_a*LN(B39/Floor_F)/Delta_c)*(-Rho_a*(-Cost_k*Delta_c*Floor_F/Rho_a))/(Delta_c*B39))) -> 3.9033433 | E39: =ABS(C39-D39) -> 0 | F39: =Top_c-(Top_c-$A$5)*EXP(-Delta_c*A39) -> 54.865853 | G39: =$C$5*EXP((Rho_a+Delta_c)*A39) -> 10.958346 | H39: =IF(F39<Floor_F,EXP(-Rho_a*LN((Top_c-F39)/(Top_c-Floor_F))/Delta_c)*(Cost_k*Ubar_c+Delay_D+Rho_a*(-Cost_k*Delta_c*Floor_F/Rho_a))/(Ubar_c-Delta_c*F39),IF(F39=Floor_F,Cost_k,EXP(-Rho_a*LN(F39/Floor_F)/Delta_c)*(-Rho_a*(-Cost_k*Delta_c*Floor_F/Rho_a))/(Delta_c*F39))) -> 10.958346 | I39: =ABS(G39-H39) -> 0
A41: The drift from 58 reaches the floor after 0.524 years, the race from 53 after 0.429: the table stops before either arrives. Along both the costate and the value's slope agree (Theorem 8.1(iii)).

Sheet Scheme
A1: Solve on a grid: the upwind scheme's values on grids of 1 to 1/16 point, against the closed form (Proposition 8.4; Figure 8.1; AXIOM Lab 2.8, step 5)
A2: For the rule policy iteration converges to (race from the never-start edge, hold the floor, drift above it) the upwind equations solve level by level: racing, V_j = (-(k u bar + D) + (f/h) V_j+1)/(rho + f/h), f = u bar - delta c, from the floor down, and no lower than -D/rho; drifting, V_j = (|f|/h) V_j-1/(rho + |f|/h), |f| = delta c, from the floor up. Policy-iteration steps are the engine's.
A4: Grid of 1 point | H4: Grid of 1/2 point | O4: Grid of 1/4 point | V4: Grid of 1/8 point | AC4: Grid of 1/16 point
A5: Spacing h | B5: 1 | H5: Spacing h | I5: 0.5 | O5: Spacing h | P5: 0.25 | V5: Spacing h | W5: 0.125 | AC5: Spacing h | AD5: 0.0625
A6: Levels | B6: =COUNT($A$20:$A$70) -> 51 | H6: Levels | I6: =COUNT($H$20:$H$120) -> 101 | O6: Levels | P6: =COUNT($O$20:$O$220) -> 201 | V6: Levels | W6: =COUNT($V$20:$V$420) -> 401 | AC6: Levels | AD6: =COUNT($AC$20:$AC$820) -> 801
A7: Policy-iteration steps (engine) | B7: 15 | H7: Policy-iteration steps (engine) | I7: 28 | O7: Policy-iteration steps (engine) | P7: 55 | V7: Policy-iteration steps (engine) | W7: 109 | AC7: Policy-iteration steps (engine) | AD7: 216
A8: V(45) | B8: =INDEX($D$20:$D$70,MATCH(45,$A$20:$A$70,0)) -> -322.87269 | H8: V(45) | I8: =INDEX($K$20:$K$120,MATCH(45,$H$20:$H$120,0)) -> -323.65703 | O8: V(45) | P8: =INDEX($R$20:$R$220,MATCH(45,$O$20:$O$220,0)) -> -324.05435 | V8: V(45) | W8: =INDEX($Y$20:$Y$420,MATCH(45,$V$20:$V$420,0)) -> -324.25431 | AC8: V(45) | AD8: =INDEX($AF$20:$AF$820,MATCH(45,$AC$20:$AC$820,0)) -> -324.35462
A9: V(53) | B9: =INDEX($D$20:$D$70,MATCH(53,$A$20:$A$70,0)) -> -254.46393 | H9: V(53) | I9: =INDEX($K$20:$K$120,MATCH(53,$H$20:$H$120,0)) -> -254.67585 | O9: V(53) | P9: =INDEX($R$20:$R$220,MATCH(53,$O$20:$O$220,0)) -> -254.78344 | V9: V(53) | W9: =INDEX($Y$20:$Y$420,MATCH(53,$V$20:$V$420,0)) -> -254.83764 | AC9: V(53) | AD9: =INDEX($AF$20:$AF$820,MATCH(53,$AC$20:$AC$820,0)) -> -254.86484
A10: V(55) | B10: =INDEX($D$20:$D$70,MATCH(55,$A$20:$A$70,0)) -> -233.75962 | H10: V(55) | I10: =INDEX($K$20:$K$120,MATCH(55,$H$20:$H$120,0)) -> -233.75962 | O10: V(55) | P10: =INDEX($R$20:$R$220,MATCH(55,$O$20:$O$220,0)) -> -233.75962 | V10: V(55) | W10: =INDEX($Y$20:$Y$420,MATCH(55,$V$20:$V$420,0)) -> -233.75962 | AC10: V(55) | AD10: =INDEX($AF$20:$AF$820,MATCH(55,$AC$20:$AC$820,0)) -> -233.75962
A11: V(58) | B11: =INDEX($D$20:$D$70,MATCH(58,$A$20:$A$70,0)) -> -222.55056 | H11: V(58) | I11: =INDEX($K$20:$K$120,MATCH(58,$H$20:$H$120,0)) -> -222.45738 | O11: V(58) | P11: =INDEX($R$20:$R$220,MATCH(58,$O$20:$O$220,0)) -> -222.41021 | V11: V(58) | W11: =INDEX($Y$20:$Y$420,MATCH(58,$V$20:$V$420,0)) -> -222.38649 | AC11: V(58) | AD11: =INDEX($AF$20:$AF$820,MATCH(58,$AC$20:$AC$820,0)) -> -222.37458
A12: Largest error at 45, 53, 55, 58 | B12: =MAX(ABS(INDEX($D$20:$D$70,MATCH(45,$A$20:$A$70,0))-INDEX($E$20:$E$70,MATCH(45,$A$20:$A$70,0))),ABS(INDEX($D$20:$D$70,MATCH(53,$A$20:$A$70,0))-INDEX($E$20:$E$70,MATCH(53,$A$20:$A$70,0))),ABS(INDEX($D$20:$D$70,MATCH(55,$A$20:$A$70,0))-INDEX($E$20:$E$70,MATCH(55,$A$20:$A$70,0))),ABS(INDEX($D$20:$D$70,MATCH(58,$A$20:$A$70,0))-INDEX($E$20:$E$70,MATCH(58,$A$20:$A$70,0)))) -> 1.5824661 | H12: Largest error at 45, 53, 55, 58 | I12: =MAX(ABS(INDEX($K$20:$K$120,MATCH(45,$H$20:$H$120,0))-INDEX($L$20:$L$120,MATCH(45,$H$20:$H$120,0))),ABS(INDEX($K$20:$K$120,MATCH(53,$H$20:$H$120,0))-INDEX($L$20:$L$120,MATCH(53,$H$20:$H$120,0))),ABS(INDEX($K$20:$K$120,MATCH(55,$H$20:$H$120,0))-INDEX($L$20:$L$120,MATCH(55,$H$20:$H$120,0))),ABS(INDEX($K$20:$K$120,MATCH(58,$H$20:$H$120,0))-INDEX($L$20:$L$120,MATCH(58,$H$20:$H$120,0)))) -> 0.79812336 | O12: Largest error at 45, 53, 55, 58 | P12: =MAX(ABS(INDEX($R$20:$R$220,MATCH(45,$O$20:$O$220,0))-INDEX($S$20:$S$220,MATCH(45,$O$20:$O$220,0))),ABS(INDEX($R$20:$R$220,MATCH(53,$O$20:$O$220,0))-INDEX($S$20:$S$220,MATCH(53,$O$20:$O$220,0))),ABS(INDEX($R$20:$R$220,MATCH(55,$O$20:$O$220,0))-INDEX($S$20:$S$220,MATCH(55,$O$20:$O$220,0))),ABS(INDEX($R$20:$R$220,MATCH(58,$O$20:$O$220,0))-INDEX($S$20:$S$220,MATCH(58,$O$20:$O$220,0)))) -> 0.40080657 | V12: Largest error at 45, 53, 55, 58 | W12: =MAX(ABS(INDEX($Y$20:$Y$420,MATCH(45,$V$20:$V$420,0))-INDEX($Z$20:$Z$420,MATCH(45,$V$20:$V$420,0))),ABS(INDEX($Y$20:$Y$420,MATCH(53,$V$20:$V$420,0))-INDEX($Z$20:$Z$420,MATCH(53,$V$20:$V$420,0))),ABS(INDEX($Y$20:$Y$420,MATCH(55,$V$20:$V$420,0))-INDEX($Z$20:$Z$420,MATCH(55,$V$20:$V$420,0))),ABS(INDEX($Y$20:$Y$420,MATCH(58,$V$20:$V$420,0))-INDEX($Z$20:$Z$420,MATCH(58,$V$20:$V$420,0)))) -> 0.20084234 | AC12: Largest error at 45, 53, 55, 58 | AD12: =MAX(ABS(INDEX($AF$20:$AF$820,MATCH(45,$AC$20:$AC$820,0))-INDEX($AG$20:$AG$820,MATCH(45,$AC$20:$AC$820,0))),ABS(INDEX($AF$20:$AF$820,MATCH(53,$AC$20:$AC$820,0))-INDEX($AG$20:$AG$820,MATCH(53,$AC$20:$AC$820,0))),ABS(INDEX($AF$20:$AF$820,MATCH(55,$AC$20:$AC$820,0))-INDEX($AG$20:$AG$820,MATCH(55,$AC$20:$AC$820,0))),ABS(INDEX($AF$20:$AF$820,MATCH(58,$AC$20:$AC$820,0))-INDEX($AG$20:$AG$820,MATCH(58,$AC$20:$AC$820,0)))) -> 0.10053129
A13: Largest error over all levels | B13: =MAX($F$20:$F$70) -> 1.6813842 | H13: Largest error over all levels | I13: =MAX($M$20:$M$120) -> 0.87132784 | O13: Largest error over all levels | P13: =MAX($T$20:$T$220) -> 0.43752 | V13: Largest error over all levels | W13: =MAX($AA$20:$AA$420) -> 0.21922696 | AC13: Largest error over all levels | AD13: =MAX($AH$20:$AH$820) -> 0.10973059
A14: at the level | B14: =INDEX($A$20:$A$70,MATCH(MAX($F$20:$F$70),$F$20:$F$70,0)) -> 44 | H14: at the level | I14: =INDEX($H$20:$H$120,MATCH(MAX($M$20:$M$120),$M$20:$M$120,0)) -> 43.5 | O14: at the level | P14: =INDEX($O$20:$O$220,MATCH(MAX($T$20:$T$220),$T$20:$T$220,0)) -> 43.5 | V14: at the level | W14: =INDEX($V$20:$V$420,MATCH(MAX($AA$20:$AA$420),$AA$20:$AA$420,0)) -> 43.5 | AC14: at the level | AD14: =INDEX($AC$20:$AC$820,MATCH(MAX($AH$20:$AH$820),$AH$20:$AH$820,0)) -> 43.5
A15: The race starts from | B15: =_xlfn.MINIFS($A$20:$A$70,$C$20:$C$70,">="&(-Delay_D/Rho_a),$A$20:$A$70,"<"&Floor_F) -> 44 | H15: The race starts from | I15: =_xlfn.MINIFS($H$20:$H$120,$J$20:$J$120,">="&(-Delay_D/Rho_a),$H$20:$H$120,"<"&Floor_F) -> 43.5 | O15: The race starts from | P15: =_xlfn.MINIFS($O$20:$O$220,$Q$20:$Q$220,">="&(-Delay_D/Rho_a),$O$20:$O$220,"<"&Floor_F) -> 43.5 | V15: The race starts from | W15: =_xlfn.MINIFS($V$20:$V$420,$X$20:$X$420,">="&(-Delay_D/Rho_a),$V$20:$V$420,"<"&Floor_F) -> 43.5 | AC15: The race starts from | AD15: =_xlfn.MINIFS($AC$20:$AC$820,$AE$20:$AE$820,">="&(-Delay_D/Rho_a),$AC$20:$AC$820,"<"&Floor_F) -> 43.4375
A16: Price just below the floor | B16: =(D45-D44)/B5 -> 10.566065 | H16: Price just below the floor | I16: =(K70-K69)/I5 -> 10.789145 | O16: Price just below the floor | P16: =(R120-R119)/P5 -> 10.904255 | V16: Price just below the floor | W16: =(Y220-Y219)/W5 -> 10.962736 | AC16: Price just below the floor | AD16: =(AF420-AF419)/AD5 -> 10.992212
A17: Price just above the floor | B17: =(D46-D45)/B5 -> 3.863639 | H17: Price just above the floor | I17: =(K71-K70)/I5 -> 3.9306372 | O17: Price just above the floor | P17: =(R121-R120)/P5 -> 3.9650153 | V17: Price just above the floor | W17: =(Y221-Y220)/W5 -> 3.9824308 | AC17: Price just above the floor | AD17: =(AF421-AF420)/AD5 -> 3.9911961
A19: c | B19: Drift f | C19: V, racing | D19: V, scheme | E19: Closed form | F19: |Error| | H19: c | I19: Drift f | J19: V, racing | K19: V, scheme | L19: Closed form | M19: |Error| | O19: c | P19: Drift f | Q19: V, racing | R19: V, scheme | S19: Closed form | T19: |Error| | V19: c | W19: Drift f | X19: V, racing | Y19: V, scheme | Z19: Closed form | AA19: |Error| | AC19: c | AD19: Drift f | AE19: V, racing | AF19: V, scheme | AG19: Closed form | AH19: |Error|
A20: =30+0*$B$5 -> 30 | B20: =Ubar_c-Delta_c*A20 -> 7.0889862 | C20: =(-(Cost_k*Ubar_c+Delay_D)+B20/$B$5*C21)/(Rho_a+B20/$B$5) -> -410.56255 | D20: =MAX(C20,-Delay_D/Rho_a) -> -335.74588 | E20: =IF(A20<Floor_F,MAX((-(Cost_k*Ubar_c+Delay_D)*(1-EXP(-Rho_a*LN((Top_c-A20)/(Top_c-Floor_F))/Delta_c))/Rho_a+EXP(-Rho_a*LN((Top_c-A20)/(Top_c-Floor_F))/Delta_c)*(-Cost_k*Delta_c*Floor_F/Rho_a)),(-Delay_D/Rho_a)),(EXP(-Rho_a*LN(A20/Floor_F)/Delta_c)*(-Cost_k*Delta_c*Floor_F/Rho_a))) -> -335.74588 | F20: =ABS(D20-E20) -> 0 | H20: =30+0*$I$5 -> 30 | I20: =Ubar_c-Delta_c*H20 -> 7.0889862 | J20: =(-(Cost_k*Ubar_c+Delay_D)+I20/$I$5*J21)/(Rho_a+I20/$I$5) -> -411.79704 | K20: =MAX(J20,-Delay_D/Rho_a) -> -335.74588 | L20: =IF(H20<Floor_F,MAX((-(Cost_k*Ubar_c+Delay_D)*(1-EXP(-Rho_a*LN((Top_c-H20)/(Top_c-Floor_F))/Delta_c))/Rho_a+EXP(-Rho_a*LN((Top_c-H20)/(Top_c-Floor_F))/Delta_c)*(-Cost_k*Delta_c*Floor_F/Rho_a)),(-Delay_D/Rho_a)),(EXP(-Rho_a*LN(H20/Floor_F)/Delta_c)*(-Cost_k*Delta_c*Floor_F/Rho_a))) -> -335.74588 | M20: =ABS(K20-L20) -> 0 | O20: =30+0*$P$5 -> 30 | P20: =Ubar_c-Delta_c*O20 -> 7.0889862 | Q20: =(-(Cost_k*Ubar_c+Delay_D)+P20/$P$5*Q21)/(Rho_a+P20/$P$5) -> -412.42071 | R20: =MAX(Q20,-Delay_D/Rho_a) -> -335.74588 | S20: =IF(O20<Floor_F,MAX((-(Cost_k*Ubar_c+Delay_D)*(1-EXP(-Rho_a*LN((Top_c-O20)/(Top_c-Floor_F))/Delta_c))/Rho_a+EXP(-Rho_a*LN((Top_c-O20)/(Top_c-Floor_F))/Delta_c)*(-Cost_k*Delta_c*Floor_F/Rho_a)),(-Delay_D/Rho_a)),(EXP(-Rho_a*LN(O20/Floor_F)/Delta_c)*(-Cost_k*Delta_c*Floor_F/Rho_a))) -> -335.74588 | T20: =ABS(R20-S20) -> 0 | V20: =30+0*$W$5 -> 30 | W20: =Ubar_c-Delta_c*V20 -> 7.0889862 | X20: =(-(Cost_k*Ubar_c+Delay_D)+W20/$W$5*X21)/(Rho_a+W20/$W$5) -> -412.73416 | Y20: =MAX(X20,-Delay_D/Rho_a) -> -335.74588 | Z20: =IF(V20<Floor_F,MAX((-(Cost_k*Ubar_c+Delay_D)*(1-EXP(-Rho_a*LN((Top_c-V20)/(Top_c-Floor_F))/Delta_c))/Rho_a+EXP(-Rho_a*LN((Top_c-V20)/(Top_c-Floor_F))/Delta_c)*(-Cost_k*Delta_c*Floor_F/Rho_a)),(-Delay_D/Rho_a)),(EXP(-Rho_a*LN(V20/Floor_F)/Delta_c)*(-Cost_k*Delta_c*Floor_F/Rho_a))) -> -335.74588 | AA20: =ABS(Y20-Z20) -> 0 | AC20: =30+0*$AD$5 -> 30 | AD20: =Ubar_c-Delta_c*AC20 -> 7.0889862 | AE20: =(-(Cost_k*Ubar_c+Delay_D)+AD20/$AD$5*AE21)/(Rho_a+AD20/$AD$5) -> -412.8913 | AF20: =MAX(AE20,-Delay_D/Rho_a) -> -335.74588 | AG20: =IF(AC20<Floor_F,MAX((-(Cost_k*Ubar_c+Delay_D)*(1-EXP(-Rho_a*LN((Top_c-AC20)/(Top_c-Floor_F))/Delta_c))/Rho_a+EXP(-Rho_a*LN((Top_c-AC20)/(Top_c-Floor_F))/Delta_c)*(-Cost_k*Delta_c*Floor_F/Rho_a)),(-Delay_D/Rho_a)),(EXP(-Rho_a*LN(AC20/Floor_F)/Delta_c)*(-Cost_k*Delta_c*Floor_F/Rho_a))) -> -335.74588 | AH20: =ABS(AF20-AG20) -> 0
A21: =30+1*$B$5 -> 31 | B21: =Ubar_c-Delta_c*A21 -> 6.987715 | C21: =(-(Cost_k*Ubar_c+Delay_D)+B21/$B$5*C22)/(Rho_a+B21/$B$5) -> -405.85416 | D21: =MAX(C21,-Delay_D/Rho_a) -> -335.74588 | E21: =IF(A21<Floor_F,MAX((-(Cost_k*Ubar_c+Delay_D)*(1-EXP(-Rho_a*LN((Top_c-A21)/(Top_c-Floor_F))/Delta_c))/Rho_a+EXP(-Rho_a*LN((Top_c-A21)/(Top_c-Floor_F))/Delta_c)*(-Cost_k*Delta_c*Floor_F/Rho_a)),(-Delay_D/Rho_a)),(EXP(-Rho_a*LN(A21/Floor_F)/Delta_c)*(-Cost_k*Delta_c*Floor_F/Rho_a))) -> -335.74588 | F21: =ABS(D21-E21) -> 0 | H21: =30+1*$I$5 -> 30.5 | I21: =Ubar_c-Delta_c*H21 -> 7.0383506 | J21: =(-(Cost_k*Ubar_c+Delay_D)+I21/$I$5*J22)/(Rho_a+I21/$I$5) -> -409.45114 | K21: =MAX(J21,-Delay_D/Rho_a) -> -335.74588 | L21: =IF(H21<Floor_F,MAX((-(Cost_k*Ubar_c+Delay_D)*(1-EXP(-Rho_a*LN((Top_c-H21)/(Top_c-Floor_F))/Delta_c))/Rho_a+EXP(-Rho_a*LN((Top_c-H21)/(Top_c-Floor_F))/Delta_c)*(-Cost_k*Delta_c*Floor_F/Rho_a)),(-Delay_D/Rho_a)),(EXP(-Rho_a*LN(H21/Floor_F)/Delta_c)*(-Cost_k*Delta_c*Floor_F/Rho_a))) -> -335.74588 | M21: =ABS(K21-L21) -> 0 | O21: =30+1*$P$5 -> 30.25 | P21: =Ubar_c-Delta_c*O21 -> 7.0636684 | Q21: =(-(Cost_k*Ubar_c+Delay_D)+P21/$P$5*Q22)/(Rho_a+P21/$P$5) -> -411.24985 | R21: =MAX(Q21,-Delay_D/Rho_a) -> -335.74588 | S21: =IF(O21<Floor_F,MAX((-(Cost_k*Ubar_c+Delay_D)*(1-EXP(-Rho_a*LN((Top_c-O21)/(Top_c-Floor_F))/Delta_c))/Rho_a+EXP(-Rho_a*LN((Top_c-O21)/(Top_c-Floor_F))/Delta_c)*(-Cost_k*Delta_c*Floor_F/Rho_a)),(-Delay_D/Rho_a)),(EXP(-Rho_a*LN(O21/Floor_F)/Delta_c)*(-Cost_k*Delta_c*Floor_F/Rho_a))) -> -335.74588 | T21: =ABS(R21-S21) -> 0 | V21: =30+1*$W$5 -> 30.125 | W21: =Ubar_c-Delta_c*V21 -> 7.0763273 | X21: =(-(Cost_k*Ubar_c+Delay_D)+W21/$W$5*X22)/(Rho_a+W21/$W$5) -> -412.14926 | Y21: =MAX(X21,-Delay_D/Rho_a) -> -335.74588 | Z21: =IF(V21<Floor_F,MAX((-(Cost_k*Ubar_c+Delay_D)*(1-EXP(-Rho_a*LN((Top_c-V21)/(Top_c-Floor_F))/Delta_c))/Rho_a+EXP(-Rho_a*LN((Top_c-V21)/(Top_c-Floor_F))/Delta_c)*(-Cost_k*Delta_c*Floor_F/Rho_a)),(-Delay_D/Rho_a)),(EXP(-Rho_a*LN(V21/Floor_F)/Delta_c)*(-Cost_k*Delta_c*Floor_F/Rho_a))) -> -335.74588 | AA21: =ABS(Y21-Z21) -> 0 | AC21: =30+1*$AD$5 -> 30.0625 | AD21: =Ubar_c-Delta_c*AC21 -> 7.0826568 | AE21: =(-(Cost_k*Ubar_c+Delay_D)+AD21/$AD$5*AE22)/(Rho_a+AD21/$AD$5) -> -412.59898 | AF21: =MAX(AE21,-Delay_D/Rho_a) -> -335.74588 | AG21: =IF(AC21<Floor_F,MAX((-(Cost_k*Ubar_c+Delay_D)*(1-EXP(-Rho_a*LN((Top_c-AC21)/(Top_c-Floor_F))/Delta_c))/Rho_a+EXP(-Rho_a*LN((Top_c-AC21)/(Top_c-Floor_F))/Delta_c)*(-Cost_k*Delta_c*Floor_F/Rho_a)),(-Delay_D/Rho_a)),(EXP(-Rho_a*LN(AC21/Floor_F)/Delta_c)*(-Cost_k*Delta_c*Floor_F/Rho_a))) -> -335.74588 | AH21: =ABS(AF21-AG21) -> 0
A22: =30+2*$B$5 -> 32 | B22: =Ubar_c-Delta_c*A22 -> 6.8864438 | C22: =(-(Cost_k*Ubar_c+Delay_D)+B22/$B$5*C23)/(Rho_a+B22/$B$5) -> -401.01331 | D22: =MAX(C22,-Delay_D/Rho_a) -> -335.74588 | E22: =IF(A22<Floor_F,MAX((-(Cost_k*Ubar_c+Delay_D)*(1-EXP(-Rho_a*LN((Top_c-A22)/(Top_c-Floor_F))/Delta_c))/Rho_a+EXP(-Rho_a*LN((Top_c-A22)/(Top_c-Floor_F))/Delta_c)*(-Cost_k*Delta_c*Floor_F/Rho_a)),(-Delay_D/Rho_a)),(EXP(-Rho_a*LN(A22/Floor_F)/Delta_c)*(-Cost_k*Delta_c*Floor_F/Rho_a))) -> -335.74588 | F22: =ABS(D22-E22) -> 0 | H22: =30+2*$I$5 -> 31 | I22: =Ubar_c-Delta_c*H22 -> 6.987715 | J22: =(-(Cost_k*Ubar_c+Delay_D)+I22/$I$5*J23)/(Rho_a+I22/$I$5) -> -407.07249 | K22: =MAX(J22,-Delay_D/Rho_a) -> -335.74588 | L22: =IF(H22<Floor_F,MAX((-(Cost_k*Ubar_c+Delay_D)*(1-EXP(-Rho_a*LN((Top_c-H22)/(Top_c-Floor_F))/Delta_c))/Rho_a+EXP(-Rho_a*LN((Top_c-H22)/(Top_c-Floor_F))/Delta_c)*(-Cost_k*Delta_c*Floor_F/Rho_a)),(-Delay_D/Rho_a)),(EXP(-Rho_a*LN(H22/Floor_F)/Delta_c)*(-Cost_k*Delta_c*Floor_F/Rho_a))) -> -335.74588 | M22: =ABS(K22-L22) -> 0 | O22: =30+2*$P$5 -> 30.5 | P22: =Ubar_c-Delta_c*O22 -> 7.0383506 | Q22: =(-(Cost_k*Ubar_c+Delay_D)+P22/$P$5*Q23)/(Rho_a+P22/$P$5) -> -410.07086 | R22: =MAX(Q22,-Delay_D/Rho_a) -> -335.74588 | S22: =IF(O22<Floor_F,MAX((-(Cost_k*Ubar_c+Delay_D)*(1-EXP(-Rho_a*LN((Top_c-O22)/(Top_c-Floor_F))/Delta_c))/Rho_a+EXP(-Rho_a*LN((Top_c-O22)/(Top_c-Floor_F))/Delta_c)*(-Cost_k*Delta_c*Floor_F/Rho_a)),(-Delay_D/Rho_a)),(EXP(-Rho_a*LN(O22/Floor_F)/Delta_c)*(-Cost_k*Delta_c*Floor_F/Rho_a))) -> -335.74588 | T22: =ABS(R22-S22) -> 0 | V22: =30+2*$W$5 -> 30.25 | W22: =Ubar_c-Delta_c*V22 -> 7.0636684 | X22: =(-(Cost_k*Ubar_c+Delay_D)+W22/$W$5*X23)/(Rho_a+W22/$W$5) -> -411.56233 | Y22: =MAX(X22,-Delay_D/Rho_a) -> -335.74588 | Z22: =IF(V22<Floor_F,MAX((-(Cost_k*Ubar_c+Delay_D)*(1-EXP(-Rho_a*LN((Top_c-V22)/(Top_c-Floor_F))/Delta_c))/Rho_a+EXP(-Rho_a*LN((Top_c-V22)/(Top_c-Floor_F))/Delta_c)*(-Cost_k*Delta_c*Floor_F/Rho_a)),(-Delay_D/Rho_a)),(EXP(-Rho_a*LN(V22/Floor_F)/Delta_c)*(-Cost_k*Delta_c*Floor_F/Rho_a))) -> -335.74588 | AA22: =ABS(Y22-Z22) -> 0 | AC22: =30+2*$AD$5 -> 30.125 | AD22: =Ubar_c-Delta_c*AC22 -> 7.0763273 | AE22: =(-(Cost_k*Ubar_c+Delay_D)+AD22/$AD$5*AE23)/(Rho_a+AD22/$AD$5) -> -412.30616 | AF22: =MAX(AE22,-Delay_D/Rho_a) -> -335.74588 | AG22: =IF(AC22<Floor_F,MAX((-(Cost_k*Ubar_c+Delay_D)*(1-EXP(-Rho_a*LN((Top_c-AC22)/(Top_c-Floor_F))/Delta_c))/Rho_a+EXP(-Rho_a*LN((Top_c-AC22)/(Top_c-Floor_F))/Delta_c)*(-Cost_k*Delta_c*Floor_F/Rho_a)),(-Delay_D/Rho_a)),(EXP(-Rho_a*LN(AC22/Floor_F)/Delta_c)*(-Cost_k*Delta_c*Floor_F/Rho_a))) -> -335.74588 | AH22: =ABS(AF22-AG22) -> 0
A23: =30+3*$B$5 -> 33 | B23: =Ubar_c-Delta_c*A23 -> 6.7851725 | C23: =(-(Cost_k*Ubar_c+Delay_D)+B23/$B$5*C24)/(Rho_a+B23/$B$5) -> -396.03427 | D23: =MAX(C23,-Delay_D/Rho_a) -> -335.74588 | E23: =IF(A23<Floor_F,MAX((-(Cost_k*Ubar_c+Delay_D)*(1-EXP(-Rho_a*LN((Top_c-A23)/(Top_c-Floor_F))/Delta_c))/Rho_a+EXP(-Rho_a*LN((Top_c-A23)/(Top_c-Floor_F))/Delta_c)*(-Cost_k*Delta_c*Floor_F/Rho_a)),(-Delay_D/Rho_a)),(EXP(-Rho_a*LN(A23/Floor_F)/Delta_c)*(-Cost_k*Delta_c*Floor_F/Rho_a))) -> -335.74588 | F23: =ABS(D23-E23) -> 0 | H23: =30+3*$I$5 -> 31.5 | I23: =Ubar_c-Delta_c*H23 -> 6.9370794 | J23: =(-(Cost_k*Ubar_c+Delay_D)+I23/$I$5*J24)/(Rho_a+I23/$I$5) -> -404.66037 | K23: =MAX(J23,-Delay_D/Rho_a) -> -335.74588 | L23: =IF(H23<Floor_F,MAX((-(Cost_k*Ubar_c+Delay_D)*(1-EXP(-Rho_a*LN((Top_c-H23)/(Top_c-Floor_F))/Delta_c))/Rho_a+EXP(-Rho_a*LN((Top_c-H23)/(Top_c-Floor_F))/Delta_c)*(-Cost_k*Delta_c*Floor_F/Rho_a)),(-Delay_D/Rho_a)),(EXP(-Rho_a*LN(H23/Floor_F)/Delta_c)*(-Cost_k*Delta_c*Floor_F/Rho_a))) -> -335.74588 | M23: =ABS(K23-L23) -> 0 | O23: =30+3*$P$5 -> 30.75 | P23: =Ubar_c-Delta_c*O23 -> 7.0130328 | Q23: =(-(Cost_k*Ubar_c+Delay_D)+P23/$P$5*Q24)/(Rho_a+P23/$P$5) -> -408.88363 | R23: =MAX(Q23,-Delay_D/Rho_a) -> -335.74588 | S23: =IF(O23<Floor_F,MAX((-(Cost_k*Ubar_c+Delay_D)*(1-EXP(-Rho_a*LN((Top_c-O23)/(Top_c-Floor_F))/Delta_c))/Rho_a+EXP(-Rho_a*LN((Top_c-O23)/(Top_c-Floor_F))/Delta_c)*(-Cost_k*Delta_c*Floor_F/Rho_a)),(-Delay_D/Rho_a)),(EXP(-Rho_a*LN(O23/Floor_F)/Delta_c)*(-Cost_k*Delta_c*Floor_F/Rho_a))) -> -335.74588 | T23: =ABS(R23-S23) -> 0 | V23: =30+3*$W$5 -> 30.375 | W23: =Ubar_c-Delta_c*V23 -> 7.0510095 | X23: =(-(Cost_k*Ubar_c+Delay_D)+W23/$W$5*X24)/(Rho_a+W23/$W$5) -> -410.97336 | Y23: =MAX(X23,-Delay_D/Rho_a) -> -335.74588 | Z23: =IF(V23<Floor_F,MAX((-(Cost_k*Ubar_c+Delay_D)*(1-EXP(-Rho_a*LN((Top_c-V23)/(Top_c-Floor_F))/Delta_c))/Rho_a+EXP(-Rho_a*LN((Top_c-V23)/(Top_c-Floor_F))/Delta_c)*(-Cost_k*Delta_c*Floor_F/Rho_a)),(-Delay_D/Rho_a)),(EXP(-Rho_a*LN(V23/Floor_F)/Delta_c)*(-Cost_k*Delta_c*Floor_F/Rho_a))) -> -335.74588 | AA23: =ABS(Y23-Z23) -> 0 | AC23: =30+3*$AD$5 -> 30.1875 | AD23: =Ubar_c-Delta_c*AC23 -> 7.0699979 | AE23: =(-(Cost_k*Ubar_c+Delay_D)+AD23/$AD$5*AE24)/(Rho_a+AD23/$AD$5) -> -412.01283 | AF23: =MAX(AE23,-Delay_D/Rho_a) -> -335.74588 | AG23: =IF(AC23<Floor_F,MAX((-(Cost_k*Ubar_c+Delay_D)*(1-EXP(-Rho_a*LN((Top_c-AC23)/(Top_c-Floor_F))/Delta_c))/Rho_a+EXP(-Rho_a*LN((Top_c-AC23)/(Top_c-Floor_F))/Delta_c)*(-Cost_k*Delta_c*Floor_F/Rho_a)),(-Delay_D/Rho_a)),(EXP(-Rho_a*LN(AC23/Floor_F)/Delta_c)*(-Cost_k*Delta_c*Floor_F/Rho_a))) -> -335.74588 | AH23: =ABS(AF23-AG23) -> 0
A24: =30+4*$B$5 -> 34 | B24: =Ubar_c-Delta_c*A24 -> 6.6839013 | C24: =(-(Cost_k*Ubar_c+Delay_D)+B24/$B$5*C25)/(Rho_a+B24/$B$5) -> -390.91099 | D24: =MAX(C24,-Delay_D/Rho_a) -> -335.74588 | E24: =IF(A24<Floor_F,MAX((-(Cost_k*Ubar_c+Delay_D)*(1-EXP(-Rho_a*LN((Top_c-A24)/(Top_c-Floor_F))/Delta_c))/Rho_a+EXP(-Rho_a*LN((Top_c-A24)/(Top_c-Floor_F))/Delta_c)*(-Cost_k*Delta_c*Floor_F/Rho_a)),(-Delay_D/Rho_a)),(EXP(-Rho_a*LN(A24/Floor_F)/Delta_c)*(-Cost_k*Delta_c*Floor_F/Rho_a))) -> -335.74588 | F24: =ABS(D24-E24) -> 0 | H24: =30+4*$I$5 -> 32 | I24: =Ubar_c-Delta_c*H24 -> 6.8864438 | J24: =(-(Cost_k*Ubar_c+Delay_D)+I24/$I$5*J25)/(Rho_a+I24/$I$5) -> -402.21408 | K24: =MAX(J24,-Delay_D/Rho_a) -> -335.74588 | L24: =IF(H24<Floor_F,MAX((-(Cost_k*Ubar_c+Delay_D)*(1-EXP(-Rho_a*LN((Top_c-H24)/(Top_c-Floor_F))/Delta_c))/Rho_a+EXP(-Rho_a*LN((Top_c-H24)/(Top_c-Floor_F))/Delta_c)*(-Cost_k*Delta_c*Floor_F/Rho_a)),(-Delay_D/Rho_a)),(EXP(-Rho_a*LN(H24/Floor_F)/Delta_c)*(-Cost_k*Delta_c*Floor_F/Rho_a))) -> -335.74588 | M24: =ABS(K24-L24) -> 0 | O24: =30+4*$P$5 -> 31 | P24: =Ubar_c-Delta_c*O24 -> 6.987715 | Q24: =(-(Cost_k*Ubar_c+Delay_D)+P24/$P$5*Q25)/(Rho_a+P24/$P$5) -> -407.68808 | R24: =MAX(Q24,-Delay_D/Rho_a) -> -335.74588 | S24: =IF(O24<Floor_F,MAX((-(Cost_k*Ubar_c+Delay_D)*(1-EXP(-Rho_a*LN((Top_c-O24)/(Top_c-Floor_F))/Delta_c))/Rho_a+EXP(-Rho_a*LN((Top_c-O24)/(Top_c-Floor_F))/Delta_c)*(-Cost_k*Delta_c*Floor_F/Rho_a)),(-Delay_D/Rho_a)),(EXP(-Rho_a*LN(O24/Floor_F)/Delta_c)*(-Cost_k*Delta_c*Floor_F/Rho_a))) -> -335.74588 | T24: =ABS(R24-S24) -> 0 | V24: =30+4*$W$5 -> 30.5 | W24: =Ubar_c-Delta_c*V24 -> 7.0383506 | X24: =(-(Cost_k*Ubar_c+Delay_D)+W24/$W$5*X25)/(Rho_a+W24/$W$5) -> -410.38234 | Y24: =MAX(X24,-Delay_D/Rho_a) -> -335.74588 | Z24: =IF(V24<Floor_F,MAX((-(Cost_k*Ubar_c+Delay_D)*(1-EXP(-Rho_a*LN((Top_c-V24)/(Top_c-Floor_F))/Delta_c))/Rho_a+EXP(-Rho_a*LN((Top_c-V24)/(Top_c-Floor_F))/Delta_c)*(-Cost_k*Delta_c*Floor_F/Rho_a)),(-Delay_D/Rho_a)),(EXP(-Rho_a*LN(V24/Floor_F)/Delta_c)*(-Cost_k*Delta_c*Floor_F/Rho_a))) -> -335.74588 | AA24: =ABS(Y24-Z24) -> 0 | AC24: =30+4*$AD$5 -> 30.25 | AD24: =Ubar_c-Delta_c*AC24 -> 7.0636684 | AE24: =(-(Cost_k*Ubar_c+Delay_D)+AD24/$AD$5*AE25)/(Rho_a+AD24/$AD$5) -> -411.71898 | AF24: =MAX(AE24,-Delay_D/Rho_a) -> -335.74588 | AG24: =IF(AC24<Floor_F,MAX((-(Cost_k*Ubar_c+Delay_D)*(1-EXP(-Rho_a*LN((Top_c-AC24)/(Top_c-Floor_F))/Delta_c))/Rho_a+EXP(-Rho_a*LN((Top_c-AC24)/(Top_c-Floor_F))/Delta_c)*(-Cost_k*Delta_c*Floor_F/Rho_a)),(-Delay_D/Rho_a)),(EXP(-Rho_a*LN(AC24/Floor_F)/Delta_c)*(-Cost_k*Delta_c*Floor_F/Rho_a))) -> -335.74588 | AH24: =ABS(AF24-AG24) -> 0
A25: =30+5*$B$5 -> 35 | B25: =Ubar_c-Delta_c*A25 -> 6.5826301 | C25: =(-(Cost_k*Ubar_c+Delay_D)+B25/$B$5*C26)/(Rho_a+B25/$B$5) -> -385.63702 | D25: =MAX(C25,-Delay_D/Rho_a) -> -335.74588 | E25: =IF(A25<Floor_F,MAX((-(Cost_k*Ubar_c+Delay_D)*(1-EXP(-Rho_a*LN((Top_c-A25)/(Top_c-Floor_F))/Delta_c))/Rho_a+EXP(-Rho_a*LN((Top_c-A25)/(Top_c-Floor_F))/Delta_c)*(-Cost_k*Delta_c*Floor_F/Rho_a)),(-Delay_D/Rho_a)),(EXP(-Rho_a*LN(A25/Floor_F)/Delta_c)*(-Cost_k*Delta_c*Floor_F/Rho_a))) -> -335.74588 | F25: =ABS(D25-E25) -> 0 | H25: =30+5*$I$5 -> 32.5 | I25: =Ubar_c-Delta_c*H25 -> 6.8358082 | J25: =(-(Cost_k*Ubar_c+Delay_D)+I25/$I$5*J26)/(Rho_a+I25/$I$5) -> -399.73287 | K25: =MAX(J25,-Delay_D/Rho_a) -> -335.74588 | L25: =IF(H25<Floor_F,MAX((-(Cost_k*Ubar_c+Delay_D)*(1-EXP(-Rho_a*LN((Top_c-H25)/(Top_c-Floor_F))/Delta_c))/Rho_a+EXP(-Rho_a*LN((Top_c-H25)/(Top_c-Floor_F))/Delta_c)*(-Cost_k*Delta_c*Floor_F/Rho_a)),(-Delay_D/Rho_a)),(EXP(-Rho_a*LN(H25/Floor_F)/Delta_c)*(-Cost_k*Delta_c*Floor_F/Rho_a))) -> -335.74588 | M25: =ABS(K25-L25) -> 0 | O25: =30+5*$P$5 -> 31.25 | P25: =Ubar_c-Delta_c*O25 -> 6.9623972 | Q25: =(-(Cost_k*Ubar_c+Delay_D)+P25/$P$5*Q26)/(Rho_a+P25/$P$5) -> -406.48412 | R25: =MAX(Q25,-Delay_D/Rho_a) -> -335.74588 | S25: =IF(O25<Floor_F,MAX((-(Cost_k*Ubar_c+Delay_D)*(1-EXP(-Rho_a*LN((Top_c-O25)/(Top_c-Floor_F))/Delta_c))/Rho_a+EXP(-Rho_a*LN((Top_c-O25)/(Top_c-Floor_F))/Delta_c)*(-Cost_k*Delta_c*Floor_F/Rho_a)),(-Delay_D/Rho_a)),(EXP(-Rho_a*LN(O25/Floor_F)/Delta_c)*(-Cost_k*Delta_c*Floor_F/Rho_a))) -> -335.74588 | T25: =ABS(R25-S25) -> 0 | V25: =30+5*$W$5 -> 30.625 | W25: =Ubar_c-Delta_c*V25 -> 7.0256917 | X25: =(-(Cost_k*Ubar_c+Delay_D)+W25/$W$5*X26)/(Rho_a+W25/$W$5) -> -409.78925 | Y25: =MAX(X25,-Delay_D/Rho_a) -> -335.74588 | Z25: =IF(V25<Floor_F,MAX((-(Cost_k*Ubar_c+Delay_D)*(1-EXP(-Rho_a*LN((Top_c-V25)/(Top_c-Floor_F))/Delta_c))/Rho_a+EXP(-Rho_a*LN((Top_c-V25)/(Top_c-Floor_F))/Delta_c)*(-Cost_k*Delta_c*Floor_F/Rho_a)),(-Delay_D/Rho_a)),(EXP(-Rho_a*LN(V25/Floor_F)/Delta_c)*(-Cost_k*Delta_c*Floor_F/Rho_a))) -> -335.74588 | AA25: =ABS(Y25-Z25) -> 0 | AC25: =30+5*$AD$5 -> 30.3125 | AD25: =Ubar_c-Delta_c*AC25 -> 7.057339 | AE25: =(-(Cost_k*Ubar_c+Delay_D)+AD25/$AD$5*AE26)/(Rho_a+AD25/$AD$5) -> -411.42463 | AF25: =MAX(AE25,-Delay_D/Rho_a) -> -335.74588 | AG25: =IF(AC25<Floor_F,MAX((-(Cost_k*Ubar_c+Delay_D)*(1-EXP(-Rho_a*LN((Top_c-AC25)/(Top_c-Floor_F))/Delta_c))/Rho_a+EXP(-Rho_a*LN((Top_c-AC25)/(Top_c-Floor_F))/Delta_c)*(-Cost_k*Delta_c*Floor_F/Rho_a)),(-Delay_D/Rho_a)),(EXP(-Rho_a*LN(AC25/Floor_F)/Delta_c)*(-Cost_k*Delta_c*Floor_F/Rho_a))) -> -335.74588 | AH25: =ABS(AF25-AG25) -> 0
A26: =30+6*$B$5 -> 36 | B26: =Ubar_c-Delta_c*A26 -> 6.4813588 | C26: =(-(Cost_k*Ubar_c+Delay_D)+B26/$B$5*C27)/(Rho_a+B26/$B$5) -> -380.20555 | D26: =MAX(C26,-Delay_D/Rho_a) -> -335.74588 | E26: =IF(A26<Floor_F,MAX((-(Cost_k*Ubar_c+Delay_D)*(1-EXP(-Rho_a*LN((Top_c-A26)/(Top_c-Floor_F))/Delta_c))/Rho_a+EXP(-Rho_a*LN((Top_c-A26)/(Top_c-Floor_F))/Delta_c)*(-Cost_k*Delta_c*Floor_F/Rho_a)),(-Delay_D/Rho_a)),(EXP(-Rho_a*LN(A26/Floor_F)/Delta_c)*(-Cost_k*Delta_c*Floor_F/Rho_a))) -> -335.74588 | F26: =ABS(D26-E26) -> 0 | H26: =30+6*$I$5 -> 33 | I26: =Ubar_c-Delta_c*H26 -> 6.7851725 | J26: =(-(Cost_k*Ubar_c+Delay_D)+I26/$I$5*J27)/(Rho_a+I26/$I$5) -> -397.21599 | K26: =MAX(J26,-Delay_D/Rho_a) -> -335.74588 | L26: =IF(H26<Floor_F,MAX((-(Cost_k*Ubar_c+Delay_D)*(1-EXP(-Rho_a*LN((Top_c-H26)/(Top_c-Floor_F))/Delta_c))/Rho_a+EXP(-Rho_a*LN((Top_c-H26)/(Top_c-Floor_F))/Delta_c)*(-Cost_k*Delta_c*Floor_F/Rho_a)),(-Delay_D/Rho_a)),(EXP(-Rho_a*LN(H26/Floor_F)/Delta_c)*(-Cost_k*Delta_c*Floor_F/Rho_a))) -> -335.74588 | M26: =ABS(K26-L26) -> 0 | O26: =30+6*$P$5 -> 31.5 | P26: =Ubar_c-Delta_c*O26 -> 6.9370794 | Q26: =(-(Cost_k*Ubar_c+Delay_D)+P26/$P$5*Q27)/(Rho_a+P26/$P$5) -> -405.27166 | R26: =MAX(Q26,-Delay_D/Rho_a) -> -335.74588 | S26: =IF(O26<Floor_F,MAX((-(Cost_k*Ubar_c+Delay_D)*(1-EXP(-Rho_a*LN((Top_c-O26)/(Top_c-Floor_F))/Delta_c))/Rho_a+EXP(-Rho_a*LN((Top_c-O26)/(Top_c-Floor_F))/Delta_c)*(-Cost_k*Delta_c*Floor_F/Rho_a)),(-Delay_D/Rho_a)),(EXP(-Rho_a*LN(O26/Floor_F)/Delta_c)*(-Cost_k*Delta_c*Floor_F/Rho_a))) -> -335.74588 | T26: =ABS(R26-S26) -> 0 | V26: =30+6*$W$5 -> 30.75 | W26: =Ubar_c-Delta_c*V26 -> 7.0130328 | X26: =(-(Cost_k*Ubar_c+Delay_D)+W26/$W$5*X27)/(Rho_a+W26/$W$5) -> -409.19409 | Y26: =MAX(X26,-Delay_D/Rho_a) -> -335.74588 | Z26: =IF(V26<Floor_F,MAX((-(Cost_k*Ubar_c+Delay_D)*(1-EXP(-Rho_a*LN((Top_c-V26)/(Top_c-Floor_F))/Delta_c))/Rho_a+EXP(-Rho_a*LN((Top_c-V26)/(Top_c-Floor_F))/Delta_c)*(-Cost_k*Delta_c*Floor_F/Rho_a)),(-Delay_D/Rho_a)),(EXP(-Rho_a*LN(V26/Floor_F)/Delta_c)*(-Cost_k*Delta_c*Floor_F/Rho_a))) -> -335.74588 | AA26: =ABS(Y26-Z26) -> 0 | AC26: =30+6*$AD$5 -> 30.375 | AD26: =Ubar_c-Delta_c*AC26 -> 7.0510095 | AE26: =(-(Cost_k*Ubar_c+Delay_D)+AD26/$AD$5*AE27)/(Rho_a+AD26/$AD$5) -> -411.12976 | AF26: =MAX(AE26,-Delay_D/Rho_a) -> -335.74588 | AG26: =IF(AC26<Floor_F,MAX((-(Cost_k*Ubar_c+Delay_D)*(1-EXP(-Rho_a*LN((Top_c-AC26)/(Top_c-Floor_F))/Delta_c))/Rho_a+EXP(-Rho_a*LN((Top_c-AC26)/(Top_c-Floor_F))/Delta_c)*(-Cost_k*Delta_c*Floor_F/Rho_a)),(-Delay_D/Rho_a)),(EXP(-Rho_a*LN(AC26/Floor_F)/Delta_c)*(-Cost_k*Delta_c*Floor_F/Rho_a))) -> -335.74588 | AH26: =ABS(AF26-AG26) -> 0
A27: =30+7*$B$5 -> 37 | B27: =Ubar_c-Delta_c*A27 -> 6.3800876 | C27: =(-(Cost_k*Ubar_c+Delay_D)+B27/$B$5*C28)/(Rho_a+B27/$B$5) -> -374.60934 | D27: =MAX(C27,-Delay_D/Rho_a) -> -335.74588 | E27: =IF(A27<Floor_F,MAX((-(Cost_k*Ubar_c+Delay_D)*(1-EXP(-Rho_a*LN((Top_c-A27)/(Top_c-Floor_F))/Delta_c))/Rho_a+EXP(-Rho_a*LN((Top_c-A27)/(Top_c-Floor_F))/Delta_c)*(-Cost_k*Delta_c*Floor_F/Rho_a)),(-Delay_D/Rho_a)),(EXP(-Rho_a*LN(A27/Floor_F)/Delta_c)*(-Cost_k*Delta_c*Floor_F/Rho_a))) -> -335.74588 | F27: =ABS(D27-E27) -> 0 | H27: =30+7*$I$5 -> 33.5 | I27: =Ubar_c-Delta_c*H27 -> 6.7345369 | J27: =(-(Cost_k*Ubar_c+Delay_D)+I27/$I$5*J28)/(Rho_a+I27/$I$5) -> -394.66264 | K27: =MAX(J27,-Delay_D/Rho_a) -> -335.74588 | L27: =IF(H27<Floor_F,MAX((-(Cost_k*Ubar_c+Delay_D)*(1-EXP(-Rho_a*LN((Top_c-H27)/(Top_c-Floor_F))/Delta_c))/Rho_a+EXP(-Rho_a*LN((Top_c-H27)/(Top_c-Floor_F))/Delta_c)*(-Cost_k*Delta_c*Floor_F/Rho_a)),(-Delay_D/Rho_a)),(EXP(-Rho_a*LN(H27/Floor_F)/Delta_c)*(-Cost_k*Delta_c*Floor_F/Rho_a))) -> -335.74588 | M27: =ABS(K27-L27) -> 0 | O27: =30+7*$P$5 -> 31.75 | P27: =Ubar_c-Delta_c*O27 -> 6.9117616 | Q27: =(-(Cost_k*Ubar_c+Delay_D)+P27/$P$5*Q28)/(Rho_a+P27/$P$5) -> -404.05062 | R27: =MAX(Q27,-Delay_D/Rho_a) -> -335.74588 | S27: =IF(O27<Floor_F,MAX((-(Cost_k*Ubar_c+Delay_D)*(1-EXP(-Rho_a*LN((Top_c-O27)/(Top_c-Floor_F))/Delta_c))/Rho_a+EXP(-Rho_a*LN((Top_c-O27)/(Top_c-Floor_F))/Delta_c)*(-Cost_k*Delta_c*Floor_F/Rho_a)),(-Delay_D/Rho_a)),(EXP(-Rho_a*LN(O27/Floor_F)/Delta_c)*(-Cost_k*Delta_c*Floor_F/Rho_a))) -> -335.74588 | T27: =ABS(R27-S27) -> 0 | V27: =30+7*$W$5 -> 30.875 | W27: =Ubar_c-Delta_c*V27 -> 7.0003739 | X27: =(-(Cost_k*Ubar_c+Delay_D)+W27/$W$5*X28)/(Rho_a+W27/$W$5) -> -408.59684 | Y27: =MAX(X27,-Delay_D/Rho_a) -> -335.74588 | Z27: =IF(V27<Floor_F,MAX((-(Cost_k*Ubar_c+Delay_D)*(1-EXP(-Rho_a*LN((Top_c-V27)/(Top_c-Floor_F))/Delta_c))/Rho_a+EXP(-Rho_a*LN((Top_c-V27)/(Top_c-Floor_F))/Delta_c)*(-Cost_k*Delta_c*Floor_F/Rho_a)),(-Delay_D/Rho_a)),(EXP(-Rho_a*LN(V27/Floor_F)/Delta_c)*(-Cost_k*Delta_c*Floor_F/Rho_a))) -> -335.74588 | AA27: =ABS(Y27-Z27) -> 0 | AC27: =30+7*$AD$5 -> 30.4375 | AD27: =Ubar_c-Delta_c*AC27 -> 7.0446801 | AE27: =(-(Cost_k*Ubar_c+Delay_D)+AD27/$AD$5*AE28)/(Rho_a+AD27/$AD$5) -> -410.83438 | AF27: =MAX(AE27,-Delay_D/Rho_a) -> -335.74588 | AG27: =IF(AC27<Floor_F,MAX((-(Cost_k*Ubar_c+Delay_D)*(1-EXP(-Rho_a*LN((Top_c-AC27)/(Top_c-Floor_F))/Delta_c))/Rho_a+EXP(-Rho_a*LN((Top_c-AC27)/(Top_c-Floor_F))/Delta_c)*(-Cost_k*Delta_c*Floor_F/Rho_a)),(-Delay_D/Rho_a)),(EXP(-Rho_a*LN(AC27/Floor_F)/Delta_c)*(-Cost_k*Delta_c*Floor_F/Rho_a))) -> -335.74588 | AH27: =ABS(AF27-AG27) -> 0
A28: =30+8*$B$5 -> 38 | B28: =Ubar_c-Delta_c*A28 -> 6.2788164 | C28: =(-(Cost_k*Ubar_c+Delay_D)+B28/$B$5*C29)/(Rho_a+B28/$B$5) -> -368.8407 | D28: =MAX(C28,-Delay_D/Rho_a) -> -335.74588 | E28: =IF(A28<Floor_F,MAX((-(Cost_k*Ubar_c+Delay_D)*(1-EXP(-Rho_a*LN((Top_c-A28)/(Top_c-Floor_F))/Delta_c))/Rho_a+EXP(-Rho_a*LN((Top_c-A28)/(Top_c-Floor_F))/Delta_c)*(-Cost_k*Delta_c*Floor_F/Rho_a)),(-Delay_D/Rho_a)),(EXP(-Rho_a*LN(A28/Floor_F)/Delta_c)*(-Cost_k*Delta_c*Floor_F/Rho_a))) -> -335.74588 | F28: =ABS(D28-E28) -> 0 | H28: =30+8*$I$5 -> 34 | I28: =Ubar_c-Delta_c*H28 -> 6.6839013 | J28: =(-(Cost_k*Ubar_c+Delay_D)+I28/$I$5*J29)/(Rho_a+I28/$I$5) -> -392.07203 | K28: =MAX(J28,-Delay_D/Rho_a) -> -335.74588 | L28: =IF(H28<Floor_F,MAX((-(Cost_k*Ubar_c+Delay_D)*(1-EXP(-Rho_a*LN((Top_c-H28)/(Top_c-Floor_F))/Delta_c))/Rho_a+EXP(-Rho_a*LN((Top_c-H28)/(Top_c-Floor_F))/Delta_c)*(-Cost_k*Delta_c*Floor_F/Rho_a)),(-Delay_D/Rho_a)),(EXP(-Rho_a*LN(H28/Floor_F)/Delta_c)*(-Cost_k*Delta_c*Floor_F/Rho_a))) -> -335.74588 | M28: =ABS(K28-L28) -> 0 | O28: =30+8*$P$5 -> 32 | P28: =Ubar_c-Delta_c*O28 -> 6.8864438 | Q28: =(-(Cost_k*Ubar_c+Delay_D)+P28/$P$5*Q29)/(Rho_a+P28/$P$5) -> -402.82089 | R28: =MAX(Q28,-Delay_D/Rho_a) -> -335.74588 | S28: =IF(O28<Floor_F,MAX((-(Cost_k*Ubar_c+Delay_D)*(1-EXP(-Rho_a*LN((Top_c-O28)/(Top_c-Floor_F))/Delta_c))/Rho_a+EXP(-Rho_a*LN((Top_c-O28)/(Top_c-Floor_F))/Delta_c)*(-Cost_k*Delta_c*Floor_F/Rho_a)),(-Delay_D/Rho_a)),(EXP(-Rho_a*LN(O28/Floor_F)/Delta_c)*(-Cost_k*Delta_c*Floor_F/Rho_a))) -> -335.74588 | T28: =ABS(R28-S28) -> 0 | V28: =30+8*$W$5 -> 31 | W28: =Ubar_c-Delta_c*V28 -> 6.987715 | X28: =(-(Cost_k*Ubar_c+Delay_D)+W28/$W$5*X29)/(Rho_a+W28/$W$5) -> -407.9975 | Y28: =MAX(X28,-Delay_D/Rho_a) -> -335.74588 | Z28: =IF(V28<Floor_F,MAX((-(Cost_k*Ubar_c+Delay_D)*(1-EXP(-Rho_a*LN((Top_c-V28)/(Top_c-Floor_F))/Delta_c))/Rho_a+EXP(-Rho_a*LN((Top_c-V28)/(Top_c-Floor_F))/Delta_c)*(-Cost_k*Delta_c*Floor_F/Rho_a)),(-Delay_D/Rho_a)),(EXP(-Rho_a*LN(V28/Floor_F)/Delta_c)*(-Cost_k*Delta_c*Floor_F/Rho_a))) -> -335.74588 | AA28: =ABS(Y28-Z28) -> 0 | AC28: =30+8*$AD$5 -> 30.5 | AD28: =Ubar_c-Delta_c*AC28 -> 7.0383506 | AE28: =(-(Cost_k*Ubar_c+Delay_D)+AD28/$AD$5*AE29)/(Rho_a+AD28/$AD$5) -> -410.53849 | AF28: =MAX(AE28,-Delay_D/Rho_a) -> -335.74588 | AG28: =IF(AC28<Floor_F,MAX((-(Cost_k*Ubar_c+Delay_D)*(1-EXP(-Rho_a*LN((Top_c-AC28)/(Top_c-Floor_F))/Delta_c))/Rho_a+EXP(-Rho_a*LN((Top_c-AC28)/(Top_c-Floor_F))/Delta_c)*(-Cost_k*Delta_c*Floor_F/Rho_a)),(-Delay_D/Rho_a)),(EXP(-Rho_a*LN(AC28/Floor_F)/Delta_c)*(-Cost_k*Delta_c*Floor_F/Rho_a))) -> -335.74588 | AH28: =ABS(AF28-AG28) -> 0
A29: =30+9*$B$5 -> 39 | B29: =Ubar_c-Delta_c*A29 -> 6.1775451 | C29: =(-(Cost_k*Ubar_c+Delay_D)+B29/$B$5*C30)/(Rho_a+B29/$B$5) -> -362.89146 | D29: =MAX(C29,-Delay_D/Rho_a) -> -335.74588 | E29: =IF(A29<Floor_F,MAX((-(Cost_k*Ubar_c+Delay_D)*(1-EXP(-Rho_a*LN((Top_c-A29)/(Top_c-Floor_F))/Delta_c))/Rho_a+EXP(-Rho_a*LN((Top_c-A29)/(Top_c-Floor_F))/Delta_c)*(-Cost_k*Delta_c*Floor_F/Rho_a)),(-Delay_D/Rho_a)),(EXP(-Rho_a*LN(A29/Floor_F)/Delta_c)*(-Cost_k*Delta_c*Floor_F/Rho_a))) -> -335.74588 | F29: =ABS(D29-E29) -> 0 | H29: =30+9*$I$5 -> 34.5 | I29: =Ubar_c-Delta_c*H29 -> 6.6332657 | J29: =(-(Cost_k*Ubar_c+Delay_D)+I29/$I$5*J30)/(Rho_a+I29/$I$5) -> -389.44333 | K29: =MAX(J29,-Delay_D/Rho_a) -> -335.74588 | L29: =IF(H29<Floor_F,MAX((-(Cost_k*Ubar_c+Delay_D)*(1-EXP(-Rho_a*LN((Top_c-H29)/(Top_c-Floor_F))/Delta_c))/Rho_a+EXP(-Rho_a*LN((Top_c-H29)/(Top_c-Floor_F))/Delta_c)*(-Cost_k*Delta_c*Floor_F/Rho_a)),(-Delay_D/Rho_a)),(EXP(-Rho_a*LN(H29/Floor_F)/Delta_c)*(-Cost_k*Delta_c*Floor_F/Rho_a))) -> -335.74588 | M29: =ABS(K29-L29) -> 0 | O29: =30+9*$P$5 -> 32.25 | P29: =Ubar_c-Delta_c*O29 -> 6.861126 | Q29: =(-(Cost_k*Ubar_c+Delay_D)+P29/$P$5*Q30)/(Rho_a+P29/$P$5) -> -401.58238 | R29: =MAX(Q29,-Delay_D/Rho_a) -> -335.74588 | S29: =IF(O29<Floor_F,MAX((-(Cost_k*Ubar_c+Delay_D)*(1-EXP(-Rho_a*LN((Top_c-O29)/(Top_c-Floor_F))/Delta_c))/Rho_a+EXP(-Rho_a*LN((Top_c-O29)/(Top_c-Floor_F))/Delta_c)*(-Cost_k*Delta_c*Floor_F/Rho_a)),(-Delay_D/Rho_a)),(EXP(-Rho_a*LN(O29/Floor_F)/Delta_c)*(-Cost_k*Delta_c*Floor_F/Rho_a))) -> -335.74588 | T29: =ABS(R29-S29) -> 0 | V29: =30+9*$W$5 -> 31.125 | W29: =Ubar_c-Delta_c*V29 -> 6.9750561 | X29: =(-(Cost_k*Ubar_c+Delay_D)+W29/$W$5*X30)/(Rho_a+W29/$W$5) -> -407.39605 | Y29: =MAX(X29,-Delay_D/Rho_a) -> -335.74588 | Z29: =IF(V29<Floor_F,MAX((-(Cost_k*Ubar_c+Delay_D)*(1-EXP(-Rho_a*LN((Top_c-V29)/(Top_c-Floor_F))/Delta_c))/Rho_a+EXP(-Rho_a*LN((Top_c-V29)/(Top_c-Floor_F))/Delta_c)*(-Cost_k*Delta_c*Floor_F/Rho_a)),(-Delay_D/Rho_a)),(EXP(-Rho_a*LN(V29/Floor_F)/Delta_c)*(-Cost_k*Delta_c*Floor_F/Rho_a))) -> -335.74588 | AA29: =ABS(Y29-Z29) -> 0 | AC29: =30+9*$AD$5 -> 30.5625 | AD29: =Ubar_c-Delta_c*AC29 -> 7.0320212 | AE29: =(-(Cost_k*Ubar_c+Delay_D)+AD29/$AD$5*AE30)/(Rho_a+AD29/$AD$5) -> -410.24208 | AF29: =MAX(AE29,-Delay_D/Rho_a) -> -335.74588 | AG29: =IF(AC29<Floor_F,MAX((-(Cost_k*Ubar_c+Delay_D)*(1-EXP(-Rho_a*LN((Top_c-AC29)/(Top_c-Floor_F))/Delta_c))/Rho_a+EXP(-Rho_a*LN((Top_c-AC29)/(Top_c-Floor_F))/Delta_c)*(-Cost_k*Delta_c*Floor_F/Rho_a)),(-Delay_D/Rho_a)),(EXP(-Rho_a*LN(AC29/Floor_F)/Delta_c)*(-Cost_k*Delta_c*Floor_F/Rho_a))) -> -335.74588 | AH29: =ABS(AF29-AG29) -> 0
A30: =30+10*$B$5 -> 40 | B30: =Ubar_c-Delta_c*A30 -> 6.0762739 | C30: =(-(Cost_k*Ubar_c+Delay_D)+B30/$B$5*C31)/(Rho_a+B30/$B$5) -> -356.75289 | D30: =MAX(C30,-Delay_D/Rho_a) -> -335.74588 | E30: =IF(A30<Floor_F,MAX((-(Cost_k*Ubar_c+Delay_D)*(1-EXP(-Rho_a*LN((Top_c-A30)/(Top_c-Floor_F))/Delta_c))/Rho_a+EXP(-Rho_a*LN((Top_c-A30)/(Top_c-Floor_F))/Delta_c)*(-Cost_k*Delta_c*Floor_F/Rho_a)),(-Delay_D/Rho_a)),(EXP(-Rho_a*LN(A30/Floor_F)/Delta_c)*(-Cost_k*Delta_c*Floor_F/Rho_a))) -> -335.74588 | F30: =ABS(D30-E30) -> 0 | H30: =30+10*$I$5 -> 35 | I30: =Ubar_c-Delta_c*H30 -> 6.5826301 | J30: =(-(Cost_k*Ubar_c+Delay_D)+I30/$I$5*J31)/(Rho_a+I30/$I$5) -> -386.77567 | K30: =MAX(J30,-Delay_D/Rho_a) -> -335.74588 | L30: =IF(H30<Floor_F,MAX((-(Cost_k*Ubar_c+Delay_D)*(1-EXP(-Rho_a*LN((Top_c-H30)/(Top_c-Floor_F))/Delta_c))/Rho_a+EXP(-Rho_a*LN((Top_c-H30)/(Top_c-Floor_F))/Delta_c)*(-Cost_k*Delta_c*Floor_F/Rho_a)),(-Delay_D/Rho_a)),(EXP(-Rho_a*LN(H30/Floor_F)/Delta_c)*(-Cost_k*Delta_c*Floor_F/Rho_a))) -> -335.74588 | M30: =ABS(K30-L30) -> 0 | O30: =30+10*$P$5 -> 32.5 | P30: =Ubar_c-Delta_c*O30 -> 6.8358082 | Q30: =(-(Cost_k*Ubar_c+Delay_D)+P30/$P$5*Q31)/(Rho_a+P30/$P$5) -> -400.33501 | R30: =MAX(Q30,-Delay_D/Rho_a) -> -335.74588 | S30: =IF(O30<Floor_F,MAX((-(Cost_k*Ubar_c+Delay_D)*(1-EXP(-Rho_a*LN((Top_c-O30)/(Top_c-Floor_F))/Delta_c))/Rho_a+EXP(-Rho_a*LN((Top_c-O30)/(Top_c-Floor_F))/Delta_c)*(-Cost_k*Delta_c*Floor_F/Rho_a)),(-Delay_D/Rho_a)),(EXP(-Rho_a*LN(O30/Floor_F)/Delta_c)*(-Cost_k*Delta_c*Floor_F/Rho_a))) -> -335.74588 | T30: =ABS(R30-S30) -> 0 | V30: =30+10*$W$5 -> 31.25 | W30: =Ubar_c-Delta_c*V30 -> 6.9623972 | X30: =(-(Cost_k*Ubar_c+Delay_D)+W30/$W$5*X31)/(Rho_a+W30/$W$5) -> -406.79247 | Y30: =MAX(X30,-Delay_D/Rho_a) -> -335.74588 | Z30: =IF(V30<Floor_F,MAX((-(Cost_k*Ubar_c+Delay_D)*(1-EXP(-Rho_a*LN((Top_c-V30)/(Top_c-Floor_F))/Delta_c))/Rho_a+EXP(-Rho_a*LN((Top_c-V30)/(Top_c-Floor_F))/Delta_c)*(-Cost_k*Delta_c*Floor_F/Rho_a)),(-Delay_D/Rho_a)),(EXP(-Rho_a*LN(V30/Floor_F)/Delta_c)*(-Cost_k*Delta_c*Floor_F/Rho_a))) -> -335.74588 | AA30: =ABS(Y30-Z30) -> 0 | AC30: =30+10*$AD$5 -> 30.625 | AD30: =Ubar_c-Delta_c*AC30 -> 7.0256917 | AE30: =(-(Cost_k*Ubar_c+Delay_D)+AD30/$AD$5*AE31)/(Rho_a+AD30/$AD$5) -> -409.94515 | AF30: =MAX(AE30,-Delay_D/Rho_a) -> -335.74588 | AG30: =IF(AC30<Floor_F,MAX((-(Cost_k*Ubar_c+Delay_D)*(1-EXP(-Rho_a*LN((Top_c-AC30)/(Top_c-Floor_F))/Delta_c))/Rho_a+EXP(-Rho_a*LN((Top_c-AC30)/(Top_c-Floor_F))/Delta_c)*(-Cost_k*Delta_c*Floor_F/Rho_a)),(-Delay_D/Rho_a)),(EXP(-Rho_a*LN(AC30/Floor_F)/Delta_c)*(-Cost_k*Delta_c*Floor_F/Rho_a))) -> -335.74588 | AH30: =ABS(AF30-AG30) -> 0
A31: =30+11*$B$5 -> 41 | B31: =Ubar_c-Delta_c*A31 -> 5.9750027 | C31: =(-(Cost_k*Ubar_c+Delay_D)+B31/$B$5*C32)/(Rho_a+B31/$B$5) -> -350.41574 | D31: =MAX(C31,-Delay_D/Rho_a) -> -335.74588 | E31: =IF(A31<Floor_F,MAX((-(Cost_k*Ubar_c+Delay_D)*(1-EXP(-Rho_a*LN((Top_c-A31)/(Top_c-Floor_F))/Delta_c))/Rho_a+EXP(-Rho_a*LN((Top_c-A31)/(Top_c-Floor_F))/Delta_c)*(-Cost_k*Delta_c*Floor_F/Rho_a)),(-Delay_D/Rho_a)),(EXP(-Rho_a*LN(A31/Floor_F)/Delta_c)*(-Cost_k*Delta_c*Floor_F/Rho_a))) -> -335.74588 | F31: =ABS(D31-E31) -> 0 | H31: =30+11*$I$5 -> 35.5 | I31: =Ubar_c-Delta_c*H31 -> 6.5319945 | J31: =(-(Cost_k*Ubar_c+Delay_D)+I31/$I$5*J32)/(Rho_a+I31/$I$5) -> -384.06817 | K31: =MAX(J31,-Delay_D/Rho_a) -> -335.74588 | L31: =IF(H31<Floor_F,MAX((-(Cost_k*Ubar_c+Delay_D)*(1-EXP(-Rho_a*LN((Top_c-H31)/(Top_c-Floor_F))/Delta_c))/Rho_a+EXP(-Rho_a*LN((Top_c-H31)/(Top_c-Floor_F))/Delta_c)*(-Cost_k*Delta_c*Floor_F/Rho_a)),(-Delay_D/Rho_a)),(EXP(-Rho_a*LN(H31/Floor_F)/Delta_c)*(-Cost_k*Delta_c*Floor_F/Rho_a))) -> -335.74588 | M31: =ABS(K31-L31) -> 0 | O31: =30+11*$P$5 -> 32.75 | P31: =Ubar_c-Delta_c*O31 -> 6.8104903 | Q31: =(-(Cost_k*Ubar_c+Delay_D)+P31/$P$5*Q32)/(Rho_a+P31/$P$5) -> -399.07866 | R31: =MAX(Q31,-Delay_D/Rho_a) -> -335.74588 | S31: =IF(O31<Floor_F,MAX((-(Cost_k*Ubar_c+Delay_D)*(1-EXP(-Rho_a*LN((Top_c-O31)/(Top_c-Floor_F))/Delta_c))/Rho_a+EXP(-Rho_a*LN((Top_c-O31)/(Top_c-Floor_F))/Delta_c)*(-Cost_k*Delta_c*Floor_F/Rho_a)),(-Delay_D/Rho_a)),(EXP(-Rho_a*LN(O31/Floor_F)/Delta_c)*(-Cost_k*Delta_c*Floor_F/Rho_a))) -> -335.74588 | T31: =ABS(R31-S31) -> 0 | V31: =30+11*$W$5 -> 31.375 | W31: =Ubar_c-Delta_c*V31 -> 6.9497383 | X31: =(-(Cost_k*Ubar_c+Delay_D)+W31/$W$5*X32)/(Rho_a+W31/$W$5) -> -406.18677 | Y31: =MAX(X31,-Delay_D/Rho_a) -> -335.74588 | Z31: =IF(V31<Floor_F,MAX((-(Cost_k*Ubar_c+Delay_D)*(1-EXP(-Rho_a*LN((Top_c-V31)/(Top_c-Floor_F))/Delta_c))/Rho_a+EXP(-Rho_a*LN((Top_c-V31)/(Top_c-Floor_F))/Delta_c)*(-Cost_k*Delta_c*Floor_F/Rho_a)),(-Delay_D/Rho_a)),(EXP(-Rho_a*LN(V31/Floor_F)/Delta_c)*(-Cost_k*Delta_c*Floor_F/Rho_a))) -> -335.74588 | AA31: =ABS(Y31-Z31) -> 0 | AC31: =30+11*$AD$5 -> 30.6875 | AD31: =Ubar_c-Delta_c*AC31 -> 7.0193623 | AE31: =(-(Cost_k*Ubar_c+Delay_D)+AD31/$AD$5*AE32)/(Rho_a+AD31/$AD$5) -> -409.6477 | AF31: =MAX(AE31,-Delay_D/Rho_a) -> -335.74588 | AG31: =IF(AC31<Floor_F,MAX((-(Cost_k*Ubar_c+Delay_D)*(1-EXP(-Rho_a*LN((Top_c-AC31)/(Top_c-Floor_F))/Delta_c))/Rho_a+EXP(-Rho_a*LN((Top_c-AC31)/(Top_c-Floor_F))/Delta_c)*(-Cost_k*Delta_c*Floor_F/Rho_a)),(-Delay_D/Rho_a)),(EXP(-Rho_a*LN(AC31/Floor_F)/Delta_c)*(-Cost_k*Delta_c*Floor_F/Rho_a))) -> -335.74588 | AH31: =ABS(AF31-AG31) -> 0
A32: =30+12*$B$5 -> 42 | B32: =Ubar_c-Delta_c*A32 -> 5.8737315 | C32: =(-(Cost_k*Ubar_c+Delay_D)+B32/$B$5*C33)/(Rho_a+B32/$B$5) -> -343.87008 | D32: =MAX(C32,-Delay_D/Rho_a) -> -335.74588 | E32: =IF(A32<Floor_F,MAX((-(Cost_k*Ubar_c+Delay_D)*(1-EXP(-Rho_a*LN((Top_c-A32)/(Top_c-Floor_F))/Delta_c))/Rho_a+EXP(-Rho_a*LN((Top_c-A32)/(Top_c-Floor_F))/Delta_c)*(-Cost_k*Delta_c*Floor_F/Rho_a)),(-Delay_D/Rho_a)),(EXP(-Rho_a*LN(A32/Floor_F)/Delta_c)*(-Cost_k*Delta_c*Floor_F/Rho_a))) -> -335.74588 | F32: =ABS(D32-E32) -> 0 | H32: =30+12*$I$5 -> 36 | I32: =Ubar_c-Delta_c*H32 -> 6.4813588 | J32: =(-(Cost_k*Ubar_c+Delay_D)+I32/$I$5*J33)/(Rho_a+I32/$I$5) -> -381.31994 | K32: =MAX(J32,-Delay_D/Rho_a) -> -335.74588 | L32: =IF(H32<Floor_F,MAX((-(Cost_k*Ubar_c+Delay_D)*(1-EXP(-Rho_a*LN((Top_c-H32)/(Top_c-Floor_F))/Delta_c))/Rho_a+EXP(-Rho_a*LN((Top_c-H32)/(Top_c-Floor_F))/Delta_c)*(-Cost_k*Delta_c*Floor_F/Rho_a)),(-Delay_D/Rho_a)),(EXP(-Rho_a*LN(H32/Floor_F)/Delta_c)*(-Cost_k*Delta_c*Floor_F/Rho_a))) -> -335.74588 | M32: =ABS(K32-L32) -> 0 | O32: =30+12*$P$5 -> 33 | P32: =Ubar_c-Delta_c*O32 -> 6.7851725 | Q32: =(-(Cost_k*Ubar_c+Delay_D)+P32/$P$5*Q33)/(Rho_a+P32/$P$5) -> -397.81325 | R32: =MAX(Q32,-Delay_D/Rho_a) -> -335.74588 | S32: =IF(O32<Floor_F,MAX((-(Cost_k*Ubar_c+Delay_D)*(1-EXP(-Rho_a*LN((Top_c-O32)/(Top_c-Floor_F))/Delta_c))/Rho_a+EXP(-Rho_a*LN((Top_c-O32)/(Top_c-Floor_F))/Delta_c)*(-Cost_k*Delta_c*Floor_F/Rho_a)),(-Delay_D/Rho_a)),(EXP(-Rho_a*LN(O32/Floor_F)/Delta_c)*(-Cost_k*Delta_c*Floor_F/Rho_a))) -> -335.74588 | T32: =ABS(R32-S32) -> 0 | V32: =30+12*$W$5 -> 31.5 | W32: =Ubar_c-Delta_c*V32 -> 6.9370794 | X32: =(-(Cost_k*Ubar_c+Delay_D)+W32/$W$5*X33)/(Rho_a+W32/$W$5) -> -405.57893 | Y32: =MAX(X32,-Delay_D/Rho_a) -> -335.74588 | Z32: =IF(V32<Floor_F,MAX((-(Cost_k*Ubar_c+Delay_D)*(1-EXP(-Rho_a*LN((Top_c-V32)/(Top_c-Floor_F))/Delta_c))/Rho_a+EXP(-Rho_a*LN((Top_c-V32)/(Top_c-Floor_F))/Delta_c)*(-Cost_k*Delta_c*Floor_F/Rho_a)),(-Delay_D/Rho_a)),(EXP(-Rho_a*LN(V32/Floor_F)/Delta_c)*(-Cost_k*Delta_c*Floor_F/Rho_a))) -> -335.74588 | AA32: =ABS(Y32-Z32) -> 0 | AC32: =30+12*$AD$5 -> 30.75 | AD32: =Ubar_c-Delta_c*AC32 -> 7.0130328 | AE32: =(-(Cost_k*Ubar_c+Delay_D)+AD32/$AD$5*AE33)/(Rho_a+AD32/$AD$5) -> -409.34973 | AF32: =MAX(AE32,-Delay_D/Rho_a) -> -335.74588 | AG32: =IF(AC32<Floor_F,MAX((-(Cost_k*Ubar_c+Delay_D)*(1-EXP(-Rho_a*LN((Top_c-AC32)/(Top_c-Floor_F))/Delta_c))/Rho_a+EXP(-Rho_a*LN((Top_c-AC32)/(Top_c-Floor_F))/Delta_c)*(-Cost_k*Delta_c*Floor_F/Rho_a)),(-Delay_D/Rho_a)),(EXP(-Rho_a*LN(AC32/Floor_F)/Delta_c)*(-Cost_k*Delta_c*Floor_F/Rho_a))) -> -335.74588 | AH32: =ABS(AF32-AG32) -> 0
A33: =30+13*$B$5 -> 43 | B33: =Ubar_c-Delta_c*A33 -> 5.7724602 | C33: =(-(Cost_k*Ubar_c+Delay_D)+B33/$B$5*C34)/(Rho_a+B33/$B$5) -> -337.10536 | D33: =MAX(C33,-Delay_D/Rho_a) -> -335.74588 | E33: =IF(A33<Floor_F,MAX((-(Cost_k*Ubar_c+Delay_D)*(1-EXP(-Rho_a*LN((Top_c-A33)/(Top_c-Floor_F))/Delta_c))/Rho_a+EXP(-Rho_a*LN((Top_c-A33)/(Top_c-Floor_F))/Delta_c)*(-Cost_k*Delta_c*Floor_F/Rho_a)),(-Delay_D/Rho_a)),(EXP(-Rho_a*LN(A33/Floor_F)/Delta_c)*(-Cost_k*Delta_c*Floor_F/Rho_a))) -> -335.74588 | F33: =ABS(D33-E33) -> 0 | H33: =30+13*$I$5 -> 36.5 | I33: =Ubar_c-Delta_c*H33 -> 6.4307232 | J33: =(-(Cost_k*Ubar_c+Delay_D)+I33/$I$5*J34)/(Rho_a+I33/$I$5) -> -378.53003 | K33: =MAX(J33,-Delay_D/Rho_a) -> -335.74588 | L33: =IF(H33<Floor_F,MAX((-(Cost_k*Ubar_c+Delay_D)*(1-EXP(-Rho_a*LN((Top_c-H33)/(Top_c-Floor_F))/Delta_c))/Rho_a+EXP(-Rho_a*LN((Top_c-H33)/(Top_c-Floor_F))/Delta_c)*(-Cost_k*Delta_c*Floor_F/Rho_a)),(-Delay_D/Rho_a)),(EXP(-Rho_a*LN(H33/Floor_F)/Delta_c)*(-Cost_k*Delta_c*Floor_F/Rho_a))) -> -335.74588 | M33: =ABS(K33-L33) -> 0 | O33: =30+13*$P$5 -> 33.25 | P33: =Ubar_c-Delta_c*O33 -> 6.7598547 | Q33: =(-(Cost_k*Ubar_c+Delay_D)+P33/$P$5*Q34)/(Rho_a+P33/$P$5) -> -396.53868 | R33: =MAX(Q33,-Delay_D/Rho_a) -> -335.74588 | S33: =IF(O33<Floor_F,MAX((-(Cost_k*Ubar_c+Delay_D)*(1-EXP(-Rho_a*LN((Top_c-O33)/(Top_c-Floor_F))/Delta_c))/Rho_a+EXP(-Rho_a*LN((Top_c-O33)/(Top_c-Floor_F))/Delta_c)*(-Cost_k*Delta_c*Floor_F/Rho_a)),(-Delay_D/Rho_a)),(EXP(-Rho_a*LN(O33/Floor_F)/Delta_c)*(-Cost_k*Delta_c*Floor_F/Rho_a))) -> -335.74588 | T33: =ABS(R33-S33) -> 0 | V33: =30+13*$W$5 -> 31.625 | W33: =Ubar_c-Delta_c*V33 -> 6.9244205 | X33: =(-(Cost_k*Ubar_c+Delay_D)+W33/$W$5*X34)/(Rho_a+W33/$W$5) -> -404.96894 | Y33: =MAX(X33,-Delay_D/Rho_a) -> -335.74588 | Z33: =IF(V33<Floor_F,MAX((-(Cost_k*Ubar_c+Delay_D)*(1-EXP(-Rho_a*LN((Top_c-V33)/(Top_c-Floor_F))/Delta_c))/Rho_a+EXP(-Rho_a*LN((Top_c-V33)/(Top_c-Floor_F))/Delta_c)*(-Cost_k*Delta_c*Floor_F/Rho_a)),(-Delay_D/Rho_a)),(EXP(-Rho_a*LN(V33/Floor_F)/Delta_c)*(-Cost_k*Delta_c*Floor_F/Rho_a))) -> -335.74588 | AA33: =ABS(Y33-Z33) -> 0 | AC33: =30+13*$AD$5 -> 30.8125 | AD33: =Ubar_c-Delta_c*AC33 -> 7.0067034 | AE33: =(-(Cost_k*Ubar_c+Delay_D)+AD33/$AD$5*AE34)/(Rho_a+AD33/$AD$5) -> -409.05124 | AF33: =MAX(AE33,-Delay_D/Rho_a) -> -335.74588 | AG33: =IF(AC33<Floor_F,MAX((-(Cost_k*Ubar_c+Delay_D)*(1-EXP(-Rho_a*LN((Top_c-AC33)/(Top_c-Floor_F))/Delta_c))/Rho_a+EXP(-Rho_a*LN((Top_c-AC33)/(Top_c-Floor_F))/Delta_c)*(-Cost_k*Delta_c*Floor_F/Rho_a)),(-Delay_D/Rho_a)),(EXP(-Rho_a*LN(AC33/Floor_F)/Delta_c)*(-Cost_k*Delta_c*Floor_F/Rho_a))) -> -335.74588 | AH33: =ABS(AF33-AG33) -> 0
A34: =30+14*$B$5 -> 44 | B34: =Ubar_c-Delta_c*A34 -> 5.671189 | C34: =(-(Cost_k*Ubar_c+Delay_D)+B34/$B$5*C35)/(Rho_a+B34/$B$5) -> -330.11026 | D34: =MAX(C34,-Delay_D/Rho_a) -> -330.11026 | E34: =IF(A34<Floor_F,MAX((-(Cost_k*Ubar_c+Delay_D)*(1-EXP(-Rho_a*LN((Top_c-A34)/(Top_c-Floor_F))/Delta_c))/Rho_a+EXP(-Rho_a*LN((Top_c-A34)/(Top_c-Floor_F))/Delta_c)*(-Cost_k*Delta_c*Floor_F/Rho_a)),(-Delay_D/Rho_a)),(EXP(-Rho_a*LN(A34/Floor_F)/Delta_c)*(-Cost_k*Delta_c*Floor_F/Rho_a))) -> -331.79164 | F34: =ABS(D34-E34) -> 1.6813842 | H34: =30+14*$I$5 -> 37 | I34: =Ubar_c-Delta_c*H34 -> 6.3800876 | J34: =(-(Cost_k*Ubar_c+Delay_D)+I34/$I$5*J35)/(Rho_a+I34/$I$5) -> -375.69748 | K34: =MAX(J34,-Delay_D/Rho_a) -> -335.74588 | L34: =IF(H34<Floor_F,MAX((-(Cost_k*Ubar_c+Delay_D)*(1-EXP(-Rho_a*LN((Top_c-H34)/(Top_c-Floor_F))/Delta_c))/Rho_a+EXP(-Rho_a*LN((Top_c-H34)/(Top_c-Floor_F))/Delta_c)*(-Cost_k*Delta_c*Floor_F/Rho_a)),(-Delay_D/Rho_a)),(EXP(-Rho_a*LN(H34/Floor_F)/Delta_c)*(-Cost_k*Delta_c*Floor_F/Rho_a))) -> -335.74588 | M34: =ABS(K34-L34) -> 0 | O34: =30+14*$P$5 -> 33.5 | P34: =Ubar_c-Delta_c*O34 -> 6.7345369 | Q34: =(-(Cost_k*Ubar_c+Delay_D)+P34/$P$5*Q35)/(Rho_a+P34/$P$5) -> -395.25484 | R34: =MAX(Q34,-Delay_D/Rho_a) -> -335.74588 | S34: =IF(O34<Floor_F,MAX((-(Cost_k*Ubar_c+Delay_D)*(1-EXP(-Rho_a*LN((Top_c-O34)/(Top_c-Floor_F))/Delta_c))/Rho_a+EXP(-Rho_a*LN((Top_c-O34)/(Top_c-Floor_F))/Delta_c)*(-Cost_k*Delta_c*Floor_F/Rho_a)),(-Delay_D/Rho_a)),(EXP(-Rho_a*LN(O34/Floor_F)/Delta_c)*(-Cost_k*Delta_c*Floor_F/Rho_a))) -> -335.74588 | T34: =ABS(R34-S34) -> 0 | V34: =30+14*$W$5 -> 31.75 | W34: =Ubar_c-Delta_c*V34 -> 6.9117616 | X34: =(-(Cost_k*Ubar_c+Delay_D)+W34/$W$5*X35)/(Rho_a+W34/$W$5) -> -404.35678 | Y34: =MAX(X34,-Delay_D/Rho_a) -> -335.74588 | Z34: =IF(V34<Floor_F,MAX((-(Cost_k*Ubar_c+Delay_D)*(1-EXP(-Rho_a*LN((Top_c-V34)/(Top_c-Floor_F))/Delta_c))/Rho_a+EXP(-Rho_a*LN((Top_c-V34)/(Top_c-Floor_F))/Delta_c)*(-Cost_k*Delta_c*Floor_F/Rho_a)),(-Delay_D/Rho_a)),(EXP(-Rho_a*LN(V34/Floor_F)/Delta_c)*(-Cost_k*Delta_c*Floor_F/Rho_a))) -> -335.74588 | AA34: =ABS(Y34-Z34) -> 0 | AC34: =30+14*$AD$5 -> 30.875 | AD34: =Ubar_c-Delta_c*AC34 -> 7.0003739 | AE34: =(-(Cost_k*Ubar_c+Delay_D)+AD34/$AD$5*AE35)/(Rho_a+AD34/$AD$5) -> -408.75222 | AF34: =MAX(AE34,-Delay_D/Rho_a) -> -335.74588 | AG34: =IF(AC34<Floor_F,MAX((-(Cost_k*Ubar_c+Delay_D)*(1-EXP(-Rho_a*LN((Top_c-AC34)/(Top_c-Floor_F))/Delta_c))/Rho_a+EXP(-Rho_a*LN((Top_c-AC34)/(Top_c-Floor_F))/Delta_c)*(-Cost_k*Delta_c*Floor_F/Rho_a)),(-Delay_D/Rho_a)),(EXP(-Rho_a*LN(AC34/Floor_F)/Delta_c)*(-Cost_k*Delta_c*Floor_F/Rho_a))) -> -335.74588 | AH34: =ABS(AF34-AG34) -> 0
A35: =30+15*$B$5 -> 45 | B35: =Ubar_c-Delta_c*A35 -> 5.5699178 | C35: =(-(Cost_k*Ubar_c+Delay_D)+B35/$B$5*C36)/(Rho_a+B35/$B$5) -> -322.87269 | D35: =MAX(C35,-Delay_D/Rho_a) -> -322.87269 | E35: =IF(A35<Floor_F,MAX((-(Cost_k*Ubar_c+Delay_D)*(1-EXP(-Rho_a*LN((Top_c-A35)/(Top_c-Floor_F))/Delta_c))/Rho_a+EXP(-Rho_a*LN((Top_c-A35)/(Top_c-Floor_F))/Delta_c)*(-Cost_k*Delta_c*Floor_F/Rho_a)),(-Delay_D/Rho_a)),(EXP(-Rho_a*LN(A35/Floor_F)/Delta_c)*(-Cost_k*Delta_c*Floor_F/Rho_a))) -> -324.45516 | F35: =ABS(D35-E35) -> 1.5824661 | H35: =30+15*$I$5 -> 37.5 | I35: =Ubar_c-Delta_c*H35 -> 6.329452 | J35: =(-(Cost_k*Ubar_c+Delay_D)+I35/$I$5*J36)/(Rho_a+I35/$I$5) -> -372.82129 | K35: =MAX(J35,-Delay_D/Rho_a) -> -335.74588 | L35: =IF(H35<Floor_F,MAX((-(Cost_k*Ubar_c+Delay_D)*(1-EXP(-Rho_a*LN((Top_c-H35)/(Top_c-Floor_F))/Delta_c))/Rho_a+EXP(-Rho_a*LN((Top_c-H35)/(Top_c-Floor_F))/Delta_c)*(-Cost_k*Delta_c*Floor_F/Rho_a)),(-Delay_D/Rho_a)),(EXP(-Rho_a*LN(H35/Floor_F)/Delta_c)*(-Cost_k*Delta_c*Floor_F/Rho_a))) -> -335.74588 | M35: =ABS(K35-L35) -> 0 | O35: =30+15*$P$5 -> 33.75 | P35: =Ubar_c-Delta_c*O35 -> 6.7092191 | Q35: =(-(Cost_k*Ubar_c+Delay_D)+P35/$P$5*Q36)/(Rho_a+P35/$P$5) -> -393.96163 | R35: =MAX(Q35,-Delay_D/Rho_a) -> -335.74588 | S35: =IF(O35<Floor_F,MAX((-(Cost_k*Ubar_c+Delay_D)*(1-EXP(-Rho_a*LN((Top_c-O35)/(Top_c-Floor_F))/Delta_c))/Rho_a+EXP(-Rho_a*LN((Top_c-O35)/(Top_c-Floor_F))/Delta_c)*(-Cost_k*Delta_c*Floor_F/Rho_a)),(-Delay_D/Rho_a)),(EXP(-Rho_a*LN(O35/Floor_F)/Delta_c)*(-Cost_k*Delta_c*Floor_F/Rho_a))) -> -335.74588 | T35: =ABS(R35-S35) -> 0 | V35: =30+15*$W$5 -> 31.875 | W35: =Ubar_c-Delta_c*V35 -> 6.8991027 | X35: =(-(Cost_k*Ubar_c+Delay_D)+W35/$W$5*X36)/(Rho_a+W35/$W$5) -> -403.74244 | Y35: =MAX(X35,-Delay_D/Rho_a) -> -335.74588 | Z35: =IF(V35<Floor_F,MAX((-(Cost_k*Ubar_c+Delay_D)*(1-EXP(-Rho_a*LN((Top_c-V35)/(Top_c-Floor_F))/Delta_c))/Rho_a+EXP(-Rho_a*LN((Top_c-V35)/(Top_c-Floor_F))/Delta_c)*(-Cost_k*Delta_c*Floor_F/Rho_a)),(-Delay_D/Rho_a)),(EXP(-Rho_a*LN(V35/Floor_F)/Delta_c)*(-Cost_k*Delta_c*Floor_F/Rho_a))) -> -335.74588 | AA35: =ABS(Y35-Z35) -> 0 | AC35: =30+15*$AD$5 -> 30.9375 | AD35: =Ubar_c-Delta_c*AC35 -> 6.9940445 | AE35: =(-(Cost_k*Ubar_c+Delay_D)+AD35/$AD$5*AE36)/(Rho_a+AD35/$AD$5) -> -408.45268 | AF35: =MAX(AE35,-Delay_D/Rho_a) -> -335.74588 | AG35: =IF(AC35<Floor_F,MAX((-(Cost_k*Ubar_c+Delay_D)*(1-EXP(-Rho_a*LN((Top_c-AC35)/(Top_c-Floor_F))/Delta_c))/Rho_a+EXP(-Rho_a*LN((Top_c-AC35)/(Top_c-Floor_F))/Delta_c)*(-Cost_k*Delta_c*Floor_F/Rho_a)),(-Delay_D/Rho_a)),(EXP(-Rho_a*LN(AC35/Floor_F)/Delta_c)*(-Cost_k*Delta_c*Floor_F/Rho_a))) -> -335.74588 | AH35: =ABS(AF35-AG35) -> 0
A36: =30+16*$B$5 -> 46 | B36: =Ubar_c-Delta_c*A36 -> 5.4686465 | C36: =(-(Cost_k*Ubar_c+Delay_D)+B36/$B$5*C37)/(Rho_a+B36/$B$5) -> -315.37968 | D36: =MAX(C36,-Delay_D/Rho_a) -> -315.37968 | E36: =IF(A36<Floor_F,MAX((-(Cost_k*Ubar_c+Delay_D)*(1-EXP(-Rho_a*LN((Top_c-A36)/(Top_c-Floor_F))/Delta_c))/Rho_a+EXP(-Rho_a*LN((Top_c-A36)/(Top_c-Floor_F))/Delta_c)*(-Cost_k*Delta_c*Floor_F/Rho_a)),(-Delay_D/Rho_a)),(EXP(-Rho_a*LN(A36/Floor_F)/Delta_c)*(-Cost_k*Delta_c*Floor_F/Rho_a))) -> -316.85509 | F36: =ABS(D36-E36) -> 1.4754043 | H36: =30+16*$I$5 -> 38 | I36: =Ubar_c-Delta_c*H36 -> 6.2788164 | J36: =(-(Cost_k*Ubar_c+Delay_D)+I36/$I$5*J37)/(Rho_a+I36/$I$5) -> -369.90043 | K36: =MAX(J36,-Delay_D/Rho_a) -> -335.74588 | L36: =IF(H36<Floor_F,MAX((-(Cost_k*Ubar_c+Delay_D)*(1-EXP(-Rho_a*LN((Top_c-H36)/(Top_c-Floor_F))/Delta_c))/Rho_a+EXP(-Rho_a*LN((Top_c-H36)/(Top_c-Floor_F))/Delta_c)*(-Cost_k*Delta_c*Floor_F/Rho_a)),(-Delay_D/Rho_a)),(EXP(-Rho_a*LN(H36/Floor_F)/Delta_c)*(-Cost_k*Delta_c*Floor_F/Rho_a))) -> -335.74588 | M36: =ABS(K36-L36) -> 0 | O36: =30+16*$P$5 -> 34 | P36: =Ubar_c-Delta_c*O36 -> 6.6839013 | Q36: =(-(Cost_k*Ubar_c+Delay_D)+P36/$P$5*Q37)/(Rho_a+P36/$P$5) -> -392.65895 | R36: =MAX(Q36,-Delay_D/Rho_a) -> -335.74588 | S36: =IF(O36<Floor_F,MAX((-(Cost_k*Ubar_c+Delay_D)*(1-EXP(-Rho_a*LN((Top_c-O36)/(Top_c-Floor_F))/Delta_c))/Rho_a+EXP(-Rho_a*LN((Top_c-O36)/(Top_c-Floor_F))/Delta_c)*(-Cost_k*Delta_c*Floor_F/Rho_a)),(-Delay_D/Rho_a)),(EXP(-Rho_a*LN(O36/Floor_F)/Delta_c)*(-Cost_k*Delta_c*Floor_F/Rho_a))) -> -335.74588 | T36: =ABS(R36-S36) -> 0 | V36: =30+16*$W$5 -> 32 | W36: =Ubar_c-Delta_c*V36 -> 6.8864438 | X36: =(-(Cost_k*Ubar_c+Delay_D)+W36/$W$5*X37)/(Rho_a+W36/$W$5) -> -403.12592 | Y36: =MAX(X36,-Delay_D/Rho_a) -> -335.74588 | Z36: =IF(V36<Floor_F,MAX((-(Cost_k*Ubar_c+Delay_D)*(1-EXP(-Rho_a*LN((Top_c-V36)/(Top_c-Floor_F))/Delta_c))/Rho_a+EXP(-Rho_a*LN((Top_c-V36)/(Top_c-Floor_F))/Delta_c)*(-Cost_k*Delta_c*Floor_F/Rho_a)),(-Delay_D/Rho_a)),(EXP(-Rho_a*LN(V36/Floor_F)/Delta_c)*(-Cost_k*Delta_c*Floor_F/Rho_a))) -> -335.74588 | AA36: =ABS(Y36-Z36) -> 0 | AC36: =30+16*$AD$5 -> 31 | AD36: =Ubar_c-Delta_c*AC36 -> 6.987715 | AE36: =(-(Cost_k*Ubar_c+Delay_D)+AD36/$AD$5*AE37)/(Rho_a+AD36/$AD$5) -> -408.15262 | AF36: =MAX(AE36,-Delay_D/Rho_a) -> -335.74588 | AG36: =IF(AC36<Floor_F,MAX((-(Cost_k*Ubar_c+Delay_D)*(1-EXP(-Rho_a*LN((Top_c-AC36)/(Top_c-Floor_F))/Delta_c))/Rho_a+EXP(-Rho_a*LN((Top_c-AC36)/(Top_c-Floor_F))/Delta_c)*(-Cost_k*Delta_c*Floor_F/Rho_a)),(-Delay_D/Rho_a)),(EXP(-Rho_a*LN(AC36/Floor_F)/Delta_c)*(-Cost_k*Delta_c*Floor_F/Rho_a))) -> -335.74588 | AH36: =ABS(AF36-AG36) -> 0
A37: =30+17*$B$5 -> 47 | B37: =Ubar_c-Delta_c*A37 -> 5.3673753 | C37: =(-(Cost_k*Ubar_c+Delay_D)+B37/$B$5*C38)/(Rho_a+B37/$B$5) -> -307.61732 | D37: =MAX(C37,-Delay_D/Rho_a) -> -307.61732 | E37: =IF(A37<Floor_F,MAX((-(Cost_k*Ubar_c+Delay_D)*(1-EXP(-Rho_a*LN((Top_c-A37)/(Top_c-Floor_F))/Delta_c))/Rho_a+EXP(-Rho_a*LN((Top_c-A37)/(Top_c-Floor_F))/Delta_c)*(-Cost_k*Delta_c*Floor_F/Rho_a)),(-Delay_D/Rho_a)),(EXP(-Rho_a*LN(A37/Floor_F)/Delta_c)*(-Cost_k*Delta_c*Floor_F/Rho_a))) -> -308.97681 | F37: =ABS(D37-E37) -> 1.3594923 | H37: =30+17*$I$5 -> 38.5 | I37: =Ubar_c-Delta_c*H37 -> 6.2281808 | J37: =(-(Cost_k*Ubar_c+Delay_D)+I37/$I$5*J38)/(Rho_a+I37/$I$5) -> -366.93385 | K37: =MAX(J37,-Delay_D/Rho_a) -> -335.74588 | L37: =IF(H37<Floor_F,MAX((-(Cost_k*Ubar_c+Delay_D)*(1-EXP(-Rho_a*LN((Top_c-H37)/(Top_c-Floor_F))/Delta_c))/Rho_a+EXP(-Rho_a*LN((Top_c-H37)/(Top_c-Floor_F))/Delta_c)*(-Cost_k*Delta_c*Floor_F/Rho_a)),(-Delay_D/Rho_a)),(EXP(-Rho_a*LN(H37/Floor_F)/Delta_c)*(-Cost_k*Delta_c*Floor_F/Rho_a))) -> -335.74588 | M37: =ABS(K37-L37) -> 0 | O37: =30+17*$P$5 -> 34.25 | P37: =Ubar_c-Delta_c*O37 -> 6.6585835 | Q37: =(-(Cost_k*Ubar_c+Delay_D)+P37/$P$5*Q38)/(Rho_a+P37/$P$5) -> -391.34668 | R37: =MAX(Q37,-Delay_D/Rho_a) -> -335.74588 | S37: =IF(O37<Floor_F,MAX((-(Cost_k*Ubar_c+Delay_D)*(1-EXP(-Rho_a*LN((Top_c-O37)/(Top_c-Floor_F))/Delta_c))/Rho_a+EXP(-Rho_a*LN((Top_c-O37)/(Top_c-Floor_F))/Delta_c)*(-Cost_k*Delta_c*Floor_F/Rho_a)),(-Delay_D/Rho_a)),(EXP(-Rho_a*LN(O37/Floor_F)/Delta_c)*(-Cost_k*Delta_c*Floor_F/Rho_a))) -> -335.74588 | T37: =ABS(R37-S37) -> 0 | V37: =30+17*$W$5 -> 32.125 | W37: =Ubar_c-Delta_c*V37 -> 6.8737849 | X37: =(-(Cost_k*Ubar_c+Delay_D)+W37/$W$5*X38)/(Rho_a+W37/$W$5) -> -402.50719 | Y37: =MAX(X37,-Delay_D/Rho_a) -> -335.74588 | Z37: =IF(V37<Floor_F,MAX((-(Cost_k*Ubar_c+Delay_D)*(1-EXP(-Rho_a*LN((Top_c-V37)/(Top_c-Floor_F))/Delta_c))/Rho_a+EXP(-Rho_a*LN((Top_c-V37)/(Top_c-Floor_F))/Delta_c)*(-Cost_k*Delta_c*Floor_F/Rho_a)),(-Delay_D/Rho_a)),(EXP(-Rho_a*LN(V37/Floor_F)/Delta_c)*(-Cost_k*Delta_c*Floor_F/Rho_a))) -> -335.74588 | AA37: =ABS(Y37-Z37) -> 0 | AC37: =30+17*$AD$5 -> 31.0625 | AD37: =Ubar_c-Delta_c*AC37 -> 6.9813856 | AE37: =(-(Cost_k*Ubar_c+Delay_D)+AD37/$AD$5*AE38)/(Rho_a+AD37/$AD$5) -> -407.85202 | AF37: =MAX(AE37,-Delay_D/Rho_a) -> -335.74588 | AG37: =IF(AC37<Floor_F,MAX((-(Cost_k*Ubar_c+Delay_D)*(1-EXP(-Rho_a*LN((Top_c-AC37)/(Top_c-Floor_F))/Delta_c))/Rho_a+EXP(-Rho_a*LN((Top_c-AC37)/(Top_c-Floor_F))/Delta_c)*(-Cost_k*Delta_c*Floor_F/Rho_a)),(-Delay_D/Rho_a)),(EXP(-Rho_a*LN(AC37/Floor_F)/Delta_c)*(-Cost_k*Delta_c*Floor_F/Rho_a))) -> -335.74588 | AH37: =ABS(AF37-AG37) -> 0
A38: =30+18*$B$5 -> 48 | B38: =Ubar_c-Delta_c*A38 -> 5.2661041 | C38: =(-(Cost_k*Ubar_c+Delay_D)+B38/$B$5*C39)/(Rho_a+B38/$B$5) -> -299.57066 | D38: =MAX(C38,-Delay_D/Rho_a) -> -299.57066 | E38: =IF(A38<Floor_F,MAX((-(Cost_k*Ubar_c+Delay_D)*(1-EXP(-Rho_a*LN((Top_c-A38)/(Top_c-Floor_F))/Delta_c))/Rho_a+EXP(-Rho_a*LN((Top_c-A38)/(Top_c-Floor_F))/Delta_c)*(-Cost_k*Delta_c*Floor_F/Rho_a)),(-Delay_D/Rho_a)),(EXP(-Rho_a*LN(A38/Floor_F)/Delta_c)*(-Cost_k*Delta_c*Floor_F/Rho_a))) -> -300.80462 | F38: =ABS(D38-E38) -> 1.2339509 | H38: =30+18*$I$5 -> 39 | I38: =Ubar_c-Delta_c*H38 -> 6.1775451 | J38: =(-(Cost_k*Ubar_c+Delay_D)+I38/$I$5*J39)/(Rho_a+I38/$I$5) -> -363.92046 | K38: =MAX(J38,-Delay_D/Rho_a) -> -335.74588 | L38: =IF(H38<Floor_F,MAX((-(Cost_k*Ubar_c+Delay_D)*(1-EXP(-Rho_a*LN((Top_c-H38)/(Top_c-Floor_F))/Delta_c))/Rho_a+EXP(-Rho_a*LN((Top_c-H38)/(Top_c-Floor_F))/Delta_c)*(-Cost_k*Delta_c*Floor_F/Rho_a)),(-Delay_D/Rho_a)),(EXP(-Rho_a*LN(H38/Floor_F)/Delta_c)*(-Cost_k*Delta_c*Floor_F/Rho_a))) -> -335.74588 | M38: =ABS(K38-L38) -> 0 | O38: =30+18*$P$5 -> 34.5 | P38: =Ubar_c-Delta_c*O38 -> 6.6332657 | Q38: =(-(Cost_k*Ubar_c+Delay_D)+P38/$P$5*Q39)/(Rho_a+P38/$P$5) -> -390.02474 | R38: =MAX(Q38,-Delay_D/Rho_a) -> -335.74588 | S38: =IF(O38<Floor_F,MAX((-(Cost_k*Ubar_c+Delay_D)*(1-EXP(-Rho_a*LN((Top_c-O38)/(Top_c-Floor_F))/Delta_c))/Rho_a+EXP(-Rho_a*LN((Top_c-O38)/(Top_c-Floor_F))/Delta_c)*(-Cost_k*Delta_c*Floor_F/Rho_a)),(-Delay_D/Rho_a)),(EXP(-Rho_a*LN(O38/Floor_F)/Delta_c)*(-Cost_k*Delta_c*Floor_F/Rho_a))) -> -335.74588 | T38: =ABS(R38-S38) -> 0 | V38: =30+18*$W$5 -> 32.25 | W38: =Ubar_c-Delta_c*V38 -> 6.861126 | X38: =(-(Cost_k*Ubar_c+Delay_D)+W38/$W$5*X39)/(Rho_a+W38/$W$5) -> -401.88625 | Y38: =MAX(X38,-Delay_D/Rho_a) -> -335.74588 | Z38: =IF(V38<Floor_F,MAX((-(Cost_k*Ubar_c+Delay_D)*(1-EXP(-Rho_a*LN((Top_c-V38)/(Top_c-Floor_F))/Delta_c))/Rho_a+EXP(-Rho_a*LN((Top_c-V38)/(Top_c-Floor_F))/Delta_c)*(-Cost_k*Delta_c*Floor_F/Rho_a)),(-Delay_D/Rho_a)),(EXP(-Rho_a*LN(V38/Floor_F)/Delta_c)*(-Cost_k*Delta_c*Floor_F/Rho_a))) -> -335.74588 | AA38: =ABS(Y38-Z38) -> 0 | AC38: =30+18*$AD$5 -> 31.125 | AD38: =Ubar_c-Delta_c*AC38 -> 6.9750561 | AE38: =(-(Cost_k*Ubar_c+Delay_D)+AD38/$AD$5*AE39)/(Rho_a+AD38/$AD$5) -> -407.5509 | AF38: =MAX(AE38,-Delay_D/Rho_a) -> -335.74588 | AG38: =IF(AC38<Floor_F,MAX((-(Cost_k*Ubar_c+Delay_D)*(1-EXP(-Rho_a*LN((Top_c-AC38)/(Top_c-Floor_F))/Delta_c))/Rho_a+EXP(-Rho_a*LN((Top_c-AC38)/(Top_c-Floor_F))/Delta_c)*(-Cost_k*Delta_c*Floor_F/Rho_a)),(-Delay_D/Rho_a)),(EXP(-Rho_a*LN(AC38/Floor_F)/Delta_c)*(-Cost_k*Delta_c*Floor_F/Rho_a))) -> -335.74588 | AH38: =ABS(AF38-AG38) -> 0
A39: =30+19*$B$5 -> 49 | B39: =Ubar_c-Delta_c*A39 -> 5.1648328 | C39: =(-(Cost_k*Ubar_c+Delay_D)+B39/$B$5*C40)/(Rho_a+B39/$B$5) -> -291.22363 | D39: =MAX(C39,-Delay_D/Rho_a) -> -291.22363 | E39: =IF(A39<Floor_F,MAX((-(Cost_k*Ubar_c+Delay_D)*(1-EXP(-Rho_a*LN((Top_c-A39)/(Top_c-Floor_F))/Delta_c))/Rho_a+EXP(-Rho_a*LN((Top_c-A39)/(Top_c-Floor_F))/Delta_c)*(-Cost_k*Delta_c*Floor_F/Rho_a)),(-Delay_D/Rho_a)),(EXP(-Rho_a*LN(A39/Floor_F)/Delta_c)*(-Cost_k*Delta_c*Floor_F/Rho_a))) -> -292.32155 | F39: =ABS(D39-E39) -> 1.0979191 | H39: =30+19*$I$5 -> 39.5 | I39: =Ubar_c-Delta_c*H39 -> 6.1269095 | J39: =(-(Cost_k*Ubar_c+Delay_D)+I39/$I$5*J40)/(Rho_a+I39/$I$5) -> -360.85911 | K39: =MAX(J39,-Delay_D/Rho_a) -> -335.74588 | L39: =IF(H39<Floor_F,MAX((-(Cost_k*Ubar_c+Delay_D)*(1-EXP(-Rho_a*LN((Top_c-H39)/(Top_c-Floor_F))/Delta_c))/Rho_a+EXP(-Rho_a*LN((Top_c-H39)/(Top_c-Floor_F))/Delta_c)*(-Cost_k*Delta_c*Floor_F/Rho_a)),(-Delay_D/Rho_a)),(EXP(-Rho_a*LN(H39/Floor_F)/Delta_c)*(-Cost_k*Delta_c*Floor_F/Rho_a))) -> -335.74588 | M39: =ABS(K39-L39) -> 0 | O39: =30+19*$P$5 -> 34.75 | P39: =Ubar_c-Delta_c*O39 -> 6.6079479 | Q39: =(-(Cost_k*Ubar_c+Delay_D)+P39/$P$5*Q40)/(Rho_a+P39/$P$5) -> -388.693 | R39: =MAX(Q39,-Delay_D/Rho_a) -> -335.74588 | S39: =IF(O39<Floor_F,MAX((-(Cost_k*Ubar_c+Delay_D)*(1-EXP(-Rho_a*LN((Top_c-O39)/(Top_c-Floor_F))/Delta_c))/Rho_a+EXP(-Rho_a*LN((Top_c-O39)/(Top_c-Floor_F))/Delta_c)*(-Cost_k*Delta_c*Floor_F/Rho_a)),(-Delay_D/Rho_a)),(EXP(-Rho_a*LN(O39/Floor_F)/Delta_c)*(-Cost_k*Delta_c*Floor_F/Rho_a))) -> -335.74588 | T39: =ABS(R39-S39) -> 0 | V39: =30+19*$W$5 -> 32.375 | W39: =Ubar_c-Delta_c*V39 -> 6.8484671 | X39: =(-(Cost_k*Ubar_c+Delay_D)+W39/$W$5*X40)/(Rho_a+W39/$W$5) -> -401.26309 | Y39: =MAX(X39,-Delay_D/Rho_a) -> -335.74588 | Z39: =IF(V39<Floor_F,MAX((-(Cost_k*Ubar_c+Delay_D)*(1-EXP(-Rho_a*LN((Top_c-V39)/(Top_c-Floor_F))/Delta_c))/Rho_a+EXP(-Rho_a*LN((Top_c-V39)/(Top_c-Floor_F))/Delta_c)*(-Cost_k*Delta_c*Floor_F/Rho_a)),(-Delay_D/Rho_a)),(EXP(-Rho_a*LN(V39/Floor_F)/Delta_c)*(-Cost_k*Delta_c*Floor_F/Rho_a))) -> -335.74588 | AA39: =ABS(Y39-Z39) -> 0 | AC39: =30+19*$AD$5 -> 31.1875 | AD39: =Ubar_c-Delta_c*AC39 -> 6.9687266 | AE39: =(-(Cost_k*Ubar_c+Delay_D)+AD39/$AD$5*AE40)/(Rho_a+AD39/$AD$5) -> -407.24925 | AF39: =MAX(AE39,-Delay_D/Rho_a) -> -335.74588 | AG39: =IF(AC39<Floor_F,MAX((-(Cost_k*Ubar_c+Delay_D)*(1-EXP(-Rho_a*LN((Top_c-AC39)/(Top_c-Floor_F))/Delta_c))/Rho_a+EXP(-Rho_a*LN((Top_c-AC39)/(Top_c-Floor_F))/Delta_c)*(-Cost_k*Delta_c*Floor_F/Rho_a)),(-Delay_D/Rho_a)),(EXP(-Rho_a*LN(AC39/Floor_F)/Delta_c)*(-Cost_k*Delta_c*Floor_F/Rho_a))) -> -335.74588 | AH39: =ABS(AF39-AG39) -> 0
A40: =30+20*$B$5 -> 50 | B40: =Ubar_c-Delta_c*A40 -> 5.0635616 | C40: =(-(Cost_k*Ubar_c+Delay_D)+B40/$B$5*C41)/(Rho_a+B40/$B$5) -> -282.55889 | D40: =MAX(C40,-Delay_D/Rho_a) -> -282.55889 | E40: =IF(A40<Floor_F,MAX((-(Cost_k*Ubar_c+Delay_D)*(1-EXP(-Rho_a*LN((Top_c-A40)/(Top_c-Floor_F))/Delta_c))/Rho_a+EXP(-Rho_a*LN((Top_c-A40)/(Top_c-Floor_F))/Delta_c)*(-Cost_k*Delta_c*Floor_F/Rho_a)),(-Delay_D/Rho_a)),(EXP(-Rho_a*LN(A40/Floor_F)/Delta_c)*(-Cost_k*Delta_c*Floor_F/Rho_a))) -> -283.50934 | F40: =ABS(D40-E40) -> 0.9504441 | H40: =30+20*$I$5 -> 40 | I40: =Ubar_c-Delta_c*H40 -> 6.0762739 | J40: =(-(Cost_k*Ubar_c+Delay_D)+I40/$I$5*J41)/(Rho_a+I40/$I$5) -> -357.74866 | K40: =MAX(J40,-Delay_D/Rho_a) -> -335.74588 | L40: =IF(H40<Floor_F,MAX((-(Cost_k*Ubar_c+Delay_D)*(1-EXP(-Rho_a*LN((Top_c-H40)/(Top_c-Floor_F))/Delta_c))/Rho_a+EXP(-Rho_a*LN((Top_c-H40)/(Top_c-Floor_F))/Delta_c)*(-Cost_k*Delta_c*Floor_F/Rho_a)),(-Delay_D/Rho_a)),(EXP(-Rho_a*LN(H40/Floor_F)/Delta_c)*(-Cost_k*Delta_c*Floor_F/Rho_a))) -> -335.74588 | M40: =ABS(K40-L40) -> 0 | O40: =30+20*$P$5 -> 35 | P40: =Ubar_c-Delta_c*O40 -> 6.5826301 | Q40: =(-(Cost_k*Ubar_c+Delay_D)+P40/$P$5*Q41)/(Rho_a+P40/$P$5) -> -387.35135 | R40: =MAX(Q40,-Delay_D/Rho_a) -> -335.74588 | S40: =IF(O40<Floor_F,MAX((-(Cost_k*Ubar_c+Delay_D)*(1-EXP(-Rho_a*LN((Top_c-O40)/(Top_c-Floor_F))/Delta_c))/Rho_a+EXP(-Rho_a*LN((Top_c-O40)/(Top_c-Floor_F))/Delta_c)*(-Cost_k*Delta_c*Floor_F/Rho_a)),(-Delay_D/Rho_a)),(EXP(-Rho_a*LN(O40/Floor_F)/Delta_c)*(-Cost_k*Delta_c*Floor_F/Rho_a))) -> -335.74588 | T40: =ABS(R40-S40) -> 0 | V40: =30+20*$W$5 -> 32.5 | W40: =Ubar_c-Delta_c*V40 -> 6.8358082 | X40: =(-(Cost_k*Ubar_c+Delay_D)+W40/$W$5*X41)/(Rho_a+W40/$W$5) -> -400.6377 | Y40: =MAX(X40,-Delay_D/Rho_a) -> -335.74588 | Z40: =IF(V40<Floor_F,MAX((-(Cost_k*Ubar_c+Delay_D)*(1-EXP(-Rho_a*LN((Top_c-V40)/(Top_c-Floor_F))/Delta_c))/Rho_a+EXP(-Rho_a*LN((Top_c-V40)/(Top_c-Floor_F))/Delta_c)*(-Cost_k*Delta_c*Floor_F/Rho_a)),(-Delay_D/Rho_a)),(EXP(-Rho_a*LN(V40/Floor_F)/Delta_c)*(-Cost_k*Delta_c*Floor_F/Rho_a))) -> -335.74588 | AA40: =ABS(Y40-Z40) -> 0 | AC40: =30+20*$AD$5 -> 31.25 | AD40: =Ubar_c-Delta_c*AC40 -> 6.9623972 | AE40: =(-(Cost_k*Ubar_c+Delay_D)+AD40/$AD$5*AE41)/(Rho_a+AD40/$AD$5) -> -406.94706 | AF40: =MAX(AE40,-Delay_D/Rho_a) -> -335.74588 | AG40: =IF(AC40<Floor_F,MAX((-(Cost_k*Ubar_c+Delay_D)*(1-EXP(-Rho_a*LN((Top_c-AC40)/(Top_c-Floor_F))/Delta_c))/Rho_a+EXP(-Rho_a*LN((Top_c-AC40)/(Top_c-Floor_F))/Delta_c)*(-Cost_k*Delta_c*Floor_F/Rho_a)),(-Delay_D/Rho_a)),(EXP(-Rho_a*LN(AC40/Floor_F)/Delta_c)*(-Cost_k*Delta_c*Floor_F/Rho_a))) -> -335.74588 | AH40: =ABS(AF40-AG40) -> 0
A41: =30+21*$B$5 -> 51 | B41: =Ubar_c-Delta_c*A41 -> 4.9622904 | C41: =(-(Cost_k*Ubar_c+Delay_D)+B41/$B$5*C42)/(Rho_a+B41/$B$5) -> -273.55777 | D41: =MAX(C41,-Delay_D/Rho_a) -> -273.55777 | E41: =IF(A41<Floor_F,MAX((-(Cost_k*Ubar_c+Delay_D)*(1-EXP(-Rho_a*LN((Top_c-A41)/(Top_c-Floor_F))/Delta_c))/Rho_a+EXP(-Rho_a*LN((Top_c-A41)/(Top_c-Floor_F))/Delta_c)*(-Cost_k*Delta_c*Floor_F/Rho_a)),(-Delay_D/Rho_a)),(EXP(-Rho_a*LN(A41/Floor_F)/Delta_c)*(-Cost_k*Delta_c*Floor_F/Rho_a))) -> -274.34824 | F41: =ABS(D41-E41) -> 0.79046925 | H41: =30+21*$I$5 -> 40.5 | I41: =Ubar_c-Delta_c*H41 -> 6.0256383 | J41: =(-(Cost_k*Ubar_c+Delay_D)+I41/$I$5*J42)/(Rho_a+I41/$I$5) -> -354.58789 | K41: =MAX(J41,-Delay_D/Rho_a) -> -335.74588 | L41: =IF(H41<Floor_F,MAX((-(Cost_k*Ubar_c+Delay_D)*(1-EXP(-Rho_a*LN((Top_c-H41)/(Top_c-Floor_F))/Delta_c))/Rho_a+EXP(-Rho_a*LN((Top_c-H41)/(Top_c-Floor_F))/Delta_c)*(-Cost_k*Delta_c*Floor_F/Rho_a)),(-Delay_D/Rho_a)),(EXP(-Rho_a*LN(H41/Floor_F)/Delta_c)*(-Cost_k*Delta_c*Floor_F/Rho_a))) -> -335.74588 | M41: =ABS(K41-L41) -> 0 | O41: =30+21*$P$5 -> 35.25 | P41: =Ubar_c-Delta_c*O41 -> 6.5573123 | Q41: =(-(Cost_k*Ubar_c+Delay_D)+P41/$P$5*Q42)/(Rho_a+P41/$P$5) -> -385.99969 | R41: =MAX(Q41,-Delay_D/Rho_a) -> -335.74588 | S41: =IF(O41<Floor_F,MAX((-(Cost_k*Ubar_c+Delay_D)*(1-EXP(-Rho_a*LN((Top_c-O41)/(Top_c-Floor_F))/Delta_c))/Rho_a+EXP(-Rho_a*LN((Top_c-O41)/(Top_c-Floor_F))/Delta_c)*(-Cost_k*Delta_c*Floor_F/Rho_a)),(-Delay_D/Rho_a)),(EXP(-Rho_a*LN(O41/Floor_F)/Delta_c)*(-Cost_k*Delta_c*Floor_F/Rho_a))) -> -335.74588 | T41: =ABS(R41-S41) -> 0 | V41: =30+21*$W$5 -> 32.625 | W41: =Ubar_c-Delta_c*V41 -> 6.8231493 | X41: =(-(Cost_k*Ubar_c+Delay_D)+W41/$W$5*X42)/(Rho_a+W41/$W$5) -> -400.01005 | Y41: =MAX(X41,-Delay_D/Rho_a) -> -335.74588 | Z41: =IF(V41<Floor_F,MAX((-(Cost_k*Ubar_c+Delay_D)*(1-EXP(-Rho_a*LN((Top_c-V41)/(Top_c-Floor_F))/Delta_c))/Rho_a+EXP(-Rho_a*LN((Top_c-V41)/(Top_c-Floor_F))/Delta_c)*(-Cost_k*Delta_c*Floor_F/Rho_a)),(-Delay_D/Rho_a)),(EXP(-Rho_a*LN(V41/Floor_F)/Delta_c)*(-Cost_k*Delta_c*Floor_F/Rho_a))) -> -335.74588 | AA41: =ABS(Y41-Z41) -> 0 | AC41: =30+21*$AD$5 -> 31.3125 | AD41: =Ubar_c-Delta_c*AC41 -> 6.9560677 | AE41: =(-(Cost_k*Ubar_c+Delay_D)+AD41/$AD$5*AE42)/(Rho_a+AD41/$AD$5) -> -406.64434 | AF41: =MAX(AE41,-Delay_D/Rho_a) -> -335.74588 | AG41: =IF(AC41<Floor_F,MAX((-(Cost_k*Ubar_c+Delay_D)*(1-EXP(-Rho_a*LN((Top_c-AC41)/(Top_c-Floor_F))/Delta_c))/Rho_a+EXP(-Rho_a*LN((Top_c-AC41)/(Top_c-Floor_F))/Delta_c)*(-Cost_k*Delta_c*Floor_F/Rho_a)),(-Delay_D/Rho_a)),(EXP(-Rho_a*LN(AC41/Floor_F)/Delta_c)*(-Cost_k*Delta_c*Floor_F/Rho_a))) -> -335.74588 | AH41: =ABS(AF41-AG41) -> 0
A42: =30+22*$B$5 -> 52 | B42: =Ubar_c-Delta_c*A42 -> 4.8610191 | C42: =(-(Cost_k*Ubar_c+Delay_D)+B42/$B$5*C43)/(Rho_a+B42/$B$5) -> -264.20006 | D42: =MAX(C42,-Delay_D/Rho_a) -> -264.20006 | E42: =IF(A42<Floor_F,MAX((-(Cost_k*Ubar_c+Delay_D)*(1-EXP(-Rho_a*LN((Top_c-A42)/(Top_c-Floor_F))/Delta_c))/Rho_a+EXP(-Rho_a*LN((Top_c-A42)/(Top_c-Floor_F))/Delta_c)*(-Cost_k*Delta_c*Floor_F/Rho_a)),(-Delay_D/Rho_a)),(EXP(-Rho_a*LN(A42/Floor_F)/Delta_c)*(-Cost_k*Delta_c*Floor_F/Rho_a))) -> -264.81688 | F42: =ABS(D42-E42) -> 0.61682096 | H42: =30+22*$I$5 -> 41 | I42: =Ubar_c-Delta_c*H42 -> 5.9750027 | J42: =(-(Cost_k*Ubar_c+Delay_D)+I42/$I$5*J43)/(Rho_a+I42/$I$5) -> -351.37556 | K42: =MAX(J42,-Delay_D/Rho_a) -> -335.74588 | L42: =IF(H42<Floor_F,MAX((-(Cost_k*Ubar_c+Delay_D)*(1-EXP(-Rho_a*LN((Top_c-H42)/(Top_c-Floor_F))/Delta_c))/Rho_a+EXP(-Rho_a*LN((Top_c-H42)/(Top_c-Floor_F))/Delta_c)*(-Cost_k*Delta_c*Floor_F/Rho_a)),(-Delay_D/Rho_a)),(EXP(-Rho_a*LN(H42/Floor_F)/Delta_c)*(-Cost_k*Delta_c*Floor_F/Rho_a))) -> -335.74588 | M42: =ABS(K42-L42) -> 0 | O42: =30+22*$P$5 -> 35.5 | P42: =Ubar_c-Delta_c*O42 -> 6.5319945 | Q42: =(-(Cost_k*Ubar_c+Delay_D)+P42/$P$5*Q43)/(Rho_a+P42/$P$5) -> -384.6379 | R42: =MAX(Q42,-Delay_D/Rho_a) -> -335.74588 | S42: =IF(O42<Floor_F,MAX((-(Cost_k*Ubar_c+Delay_D)*(1-EXP(-Rho_a*LN((Top_c-O42)/(Top_c-Floor_F))/Delta_c))/Rho_a+EXP(-Rho_a*LN((Top_c-O42)/(Top_c-Floor_F))/Delta_c)*(-Cost_k*Delta_c*Floor_F/Rho_a)),(-Delay_D/Rho_a)),(EXP(-Rho_a*LN(O42/Floor_F)/Delta_c)*(-Cost_k*Delta_c*Floor_F/Rho_a))) -> -335.74588 | T42: =ABS(R42-S42) -> 0 | V42: =30+22*$W$5 -> 32.75 | W42: =Ubar_c-Delta_c*V42 -> 6.8104903 | X42: =(-(Cost_k*Ubar_c+Delay_D)+W42/$W$5*X43)/(Rho_a+W42/$W$5) -> -399.38015 | Y42: =MAX(X42,-Delay_D/Rho_a) -> -335.74588 | Z42: =IF(V42<Floor_F,MAX((-(Cost_k*Ubar_c+Delay_D)*(1-EXP(-Rho_a*LN((Top_c-V42)/(Top_c-Floor_F))/Delta_c))/Rho_a+EXP(-Rho_a*LN((Top_c-V42)/(Top_c-Floor_F))/Delta_c)*(-Cost_k*Delta_c*Floor_F/Rho_a)),(-Delay_D/Rho_a)),(EXP(-Rho_a*LN(V42/Floor_F)/Delta_c)*(-Cost_k*Delta_c*Floor_F/Rho_a))) -> -335.74588 | AA42: =ABS(Y42-Z42) -> 0 | AC42: =30+22*$AD$5 -> 31.375 | AD42: =Ubar_c-Delta_c*AC42 -> 6.9497383 | AE42: =(-(Cost_k*Ubar_c+Delay_D)+AD42/$AD$5*AE43)/(Rho_a+AD42/$AD$5) -> -406.34109 | AF42: =MAX(AE42,-Delay_D/Rho_a) -> -335.74588 | AG42: =IF(AC42<Floor_F,MAX((-(Cost_k*Ubar_c+Delay_D)*(1-EXP(-Rho_a*LN((Top_c-AC42)/(Top_c-Floor_F))/Delta_c))/Rho_a+EXP(-Rho_a*LN((Top_c-AC42)/(Top_c-Floor_F))/Delta_c)*(-Cost_k*Delta_c*Floor_F/Rho_a)),(-Delay_D/Rho_a)),(EXP(-Rho_a*LN(AC42/Floor_F)/Delta_c)*(-Cost_k*Delta_c*Floor_F/Rho_a))) -> -335.74588 | AH42: =ABS(AF42-AG42) -> 0
A43: =30+23*$B$5 -> 53 | B43: =Ubar_c-Delta_c*A43 -> 4.7597479 | C43: =(-(Cost_k*Ubar_c+Delay_D)+B43/$B$5*C44)/(Rho_a+B43/$B$5) -> -254.46393 | D43: =MAX(C43,-Delay_D/Rho_a) -> -254.46393 | E43: =IF(A43<Floor_F,MAX((-(Cost_k*Ubar_c+Delay_D)*(1-EXP(-Rho_a*LN((Top_c-A43)/(Top_c-Floor_F))/Delta_c))/Rho_a+EXP(-Rho_a*LN((Top_c-A43)/(Top_c-Floor_F))/Delta_c)*(-Cost_k*Delta_c*Floor_F/Rho_a)),(-Delay_D/Rho_a)),(EXP(-Rho_a*LN(A43/Floor_F)/Delta_c)*(-Cost_k*Delta_c*Floor_F/Rho_a))) -> -254.89212 | F43: =ABS(D43-E43) -> 0.428193 | H43: =30+23*$I$5 -> 41.5 | I43: =Ubar_c-Delta_c*H43 -> 5.9243671 | J43: =(-(Cost_k*Ubar_c+Delay_D)+I43/$I$5*J44)/(Rho_a+I43/$I$5) -> -348.11039 | K43: =MAX(J43,-Delay_D/Rho_a) -> -335.74588 | L43: =IF(H43<Floor_F,MAX((-(Cost_k*Ubar_c+Delay_D)*(1-EXP(-Rho_a*LN((Top_c-H43)/(Top_c-Floor_F))/Delta_c))/Rho_a+EXP(-Rho_a*LN((Top_c-H43)/(Top_c-Floor_F))/Delta_c)*(-Cost_k*Delta_c*Floor_F/Rho_a)),(-Delay_D/Rho_a)),(EXP(-Rho_a*LN(H43/Floor_F)/Delta_c)*(-Cost_k*Delta_c*Floor_F/Rho_a))) -> -335.74588 | M43: =ABS(K43-L43) -> 0 | O43: =30+23*$P$5 -> 35.75 | P43: =Ubar_c-Delta_c*O43 -> 6.5066767 | Q43: =(-(Cost_k*Ubar_c+Delay_D)+P43/$P$5*Q44)/(Rho_a+P43/$P$5) -> -383.26586 | R43: =MAX(Q43,-Delay_D/Rho_a) -> -335.74588 | S43: =IF(O43<Floor_F,MAX((-(Cost_k*Ubar_c+Delay_D)*(1-EXP(-Rho_a*LN((Top_c-O43)/(Top_c-Floor_F))/Delta_c))/Rho_a+EXP(-Rho_a*LN((Top_c-O43)/(Top_c-Floor_F))/Delta_c)*(-Cost_k*Delta_c*Floor_F/Rho_a)),(-Delay_D/Rho_a)),(EXP(-Rho_a*LN(O43/Floor_F)/Delta_c)*(-Cost_k*Delta_c*Floor_F/Rho_a))) -> -335.74588 | T43: =ABS(R43-S43) -> 0 | V43: =30+23*$W$5 -> 32.875 | W43: =Ubar_c-Delta_c*V43 -> 6.7978314 | X43: =(-(Cost_k*Ubar_c+Delay_D)+W43/$W$5*X44)/(Rho_a+W43/$W$5) -> -398.74797 | Y43: =MAX(X43,-Delay_D/Rho_a) -> -335.74588 | Z43: =IF(V43<Floor_F,MAX((-(Cost_k*Ubar_c+Delay_D)*(1-EXP(-Rho_a*LN((Top_c-V43)/(Top_c-Floor_F))/Delta_c))/Rho_a+EXP(-Rho_a*LN((Top_c-V43)/(Top_c-Floor_F))/Delta_c)*(-Cost_k*Delta_c*Floor_F/Rho_a)),(-Delay_D/Rho_a)),(EXP(-Rho_a*LN(V43/Floor_F)/Delta_c)*(-Cost_k*Delta_c*Floor_F/Rho_a))) -> -335.74588 | AA43: =ABS(Y43-Z43) -> 0 | AC43: =30+23*$AD$5 -> 31.4375 | AD43: =Ubar_c-Delta_c*AC43 -> 6.9434088 | AE43: =(-(Cost_k*Ubar_c+Delay_D)+AD43/$AD$5*AE44)/(Rho_a+AD43/$AD$5) -> -406.0373 | AF43: =MAX(AE43,-Delay_D/Rho_a) -> -335.74588 | AG43: =IF(AC43<Floor_F,MAX((-(Cost_k*Ubar_c+Delay_D)*(1-EXP(-Rho_a*LN((Top_c-AC43)/(Top_c-Floor_F))/Delta_c))/Rho_a+EXP(-Rho_a*LN((Top_c-AC43)/(Top_c-Floor_F))/Delta_c)*(-Cost_k*Delta_c*Floor_F/Rho_a)),(-Delay_D/Rho_a)),(EXP(-Rho_a*LN(AC43/Floor_F)/Delta_c)*(-Cost_k*Delta_c*Floor_F/Rho_a))) -> -335.74588 | AH43: =ABS(AF43-AG43) -> 0
A44: =30+24*$B$5 -> 54 | B44: =Ubar_c-Delta_c*A44 -> 4.6584767 | C44: =(-(Cost_k*Ubar_c+Delay_D)+B44/$B$5*C45)/(Rho_a+B44/$B$5) -> -244.32568 | D44: =MAX(C44,-Delay_D/Rho_a) -> -244.32568 | E44: =IF(A44<Floor_F,MAX((-(Cost_k*Ubar_c+Delay_D)*(1-EXP(-Rho_a*LN((Top_c-A44)/(Top_c-Floor_F))/Delta_c))/Rho_a+EXP(-Rho_a*LN((Top_c-A44)/(Top_c-Floor_F))/Delta_c)*(-Cost_k*Delta_c*Floor_F/Rho_a)),(-Delay_D/Rho_a)),(EXP(-Rho_a*LN(A44/Floor_F)/Delta_c)*(-Cost_k*Delta_c*Floor_F/Rho_a))) -> -244.54881 | F44: =ABS(D44-E44) -> 0.22312867 | H44: =30+24*$I$5 -> 42 | I44: =Ubar_c-Delta_c*H44 -> 5.8737315 | J44: =(-(Cost_k*Ubar_c+Delay_D)+I44/$I$5*J45)/(Rho_a+I44/$I$5) -> -344.79104 | K44: =MAX(J44,-Delay_D/Rho_a) -> -335.74588 | L44: =IF(H44<Floor_F,MAX((-(Cost_k*Ubar_c+Delay_D)*(1-EXP(-Rho_a*LN((Top_c-H44)/(Top_c-Floor_F))/Delta_c))/Rho_a+EXP(-Rho_a*LN((Top_c-H44)/(Top_c-Floor_F))/Delta_c)*(-Cost_k*Delta_c*Floor_F/Rho_a)),(-Delay_D/Rho_a)),(EXP(-Rho_a*LN(H44/Floor_F)/Delta_c)*(-Cost_k*Delta_c*Floor_F/Rho_a))) -> -335.74588 | M44: =ABS(K44-L44) -> 0 | O44: =30+24*$P$5 -> 36 | P44: =Ubar_c-Delta_c*O44 -> 6.4813588 | Q44: =(-(Cost_k*Ubar_c+Delay_D)+P44/$P$5*Q45)/(Rho_a+P44/$P$5) -> -381.88346 | R44: =MAX(Q44,-Delay_D/Rho_a) -> -335.74588 | S44: =IF(O44<Floor_F,MAX((-(Cost_k*Ubar_c+Delay_D)*(1-EXP(-Rho_a*LN((Top_c-O44)/(Top_c-Floor_F))/Delta_c))/Rho_a+EXP(-Rho_a*LN((Top_c-O44)/(Top_c-Floor_F))/Delta_c)*(-Cost_k*Delta_c*Floor_F/Rho_a)),(-Delay_D/Rho_a)),(EXP(-Rho_a*LN(O44/Floor_F)/Delta_c)*(-Cost_k*Delta_c*Floor_F/Rho_a))) -> -335.74588 | T44: =ABS(R44-S44) -> 0 | V44: =30+24*$W$5 -> 33 | W44: =Ubar_c-Delta_c*V44 -> 6.7851725 | X44: =(-(Cost_k*Ubar_c+Delay_D)+W44/$W$5*X45)/(Rho_a+W44/$W$5) -> -398.11351 | Y44: =MAX(X44,-Delay_D/Rho_a) -> -335.74588 | Z44: =IF(V44<Floor_F,MAX((-(Cost_k*Ubar_c+Delay_D)*(1-EXP(-Rho_a*LN((Top_c-V44)/(Top_c-Floor_F))/Delta_c))/Rho_a+EXP(-Rho_a*LN((Top_c-V44)/(Top_c-Floor_F))/Delta_c)*(-Cost_k*Delta_c*Floor_F/Rho_a)),(-Delay_D/Rho_a)),(EXP(-Rho_a*LN(V44/Floor_F)/Delta_c)*(-Cost_k*Delta_c*Floor_F/Rho_a))) -> -335.74588 | AA44: =ABS(Y44-Z44) -> 0 | AC44: =30+24*$AD$5 -> 31.5 | AD44: =Ubar_c-Delta_c*AC44 -> 6.9370794 | AE44: =(-(Cost_k*Ubar_c+Delay_D)+AD44/$AD$5*AE45)/(Rho_a+AD44/$AD$5) -> -405.73298 | AF44: =MAX(AE44,-Delay_D/Rho_a) -> -335.74588 | AG44: =IF(AC44<Floor_F,MAX((-(Cost_k*Ubar_c+Delay_D)*(1-EXP(-Rho_a*LN((Top_c-AC44)/(Top_c-Floor_F))/Delta_c))/Rho_a+EXP(-Rho_a*LN((Top_c-AC44)/(Top_c-Floor_F))/Delta_c)*(-Cost_k*Delta_c*Floor_F/Rho_a)),(-Delay_D/Rho_a)),(EXP(-Rho_a*LN(AC44/Floor_F)/Delta_c)*(-Cost_k*Delta_c*Floor_F/Rho_a))) -> -335.74588 | AH44: =ABS(AF44-AG44) -> 0
A45: =30+25*$B$5 -> 55 | B45: 0 | C45: =-Cost_k*Delta_c*Floor_F/Rho_a -> -233.75962 | D45: =C45 -> -233.75962 | E45: =IF(A45<Floor_F,MAX((-(Cost_k*Ubar_c+Delay_D)*(1-EXP(-Rho_a*LN((Top_c-A45)/(Top_c-Floor_F))/Delta_c))/Rho_a+EXP(-Rho_a*LN((Top_c-A45)/(Top_c-Floor_F))/Delta_c)*(-Cost_k*Delta_c*Floor_F/Rho_a)),(-Delay_D/Rho_a)),(EXP(-Rho_a*LN(A45/Floor_F)/Delta_c)*(-Cost_k*Delta_c*Floor_F/Rho_a))) -> -233.75962 | F45: =ABS(D45-E45) -> 0 | H45: =30+25*$I$5 -> 42.5 | I45: =Ubar_c-Delta_c*H45 -> 5.8230958 | J45: =(-(Cost_k*Ubar_c+Delay_D)+I45/$I$5*J46)/(Rho_a+I45/$I$5) -> -341.41615 | K45: =MAX(J45,-Delay_D/Rho_a) -> -335.74588 | L45: =IF(H45<Floor_F,MAX((-(Cost_k*Ubar_c+Delay_D)*(1-EXP(-Rho_a*LN((Top_c-H45)/(Top_c-Floor_F))/Delta_c))/Rho_a+EXP(-Rho_a*LN((Top_c-H45)/(Top_c-Floor_F))/Delta_c)*(-Cost_k*Delta_c*Floor_F/Rho_a)),(-Delay_D/Rho_a)),(EXP(-Rho_a*LN(H45/Floor_F)/Delta_c)*(-Cost_k*Delta_c*Floor_F/Rho_a))) -> -335.74588 | M45: =ABS(K45-L45) -> 0 | O45: =30+25*$P$5 -> 36.25 | P45: =Ubar_c-Delta_c*O45 -> 6.456041 | Q45: =(-(Cost_k*Ubar_c+Delay_D)+P45/$P$5*Q46)/(Rho_a+P45/$P$5) -> -380.49057 | R45: =MAX(Q45,-Delay_D/Rho_a) -> -335.74588 | S45: =IF(O45<Floor_F,MAX((-(Cost_k*Ubar_c+Delay_D)*(1-EXP(-Rho_a*LN((Top_c-O45)/(Top_c-Floor_F))/Delta_c))/Rho_a+EXP(-Rho_a*LN((Top_c-O45)/(Top_c-Floor_F))/Delta_c)*(-Cost_k*Delta_c*Floor_F/Rho_a)),(-Delay_D/Rho_a)),(EXP(-Rho_a*LN(O45/Floor_F)/Delta_c)*(-Cost_k*Delta_c*Floor_F/Rho_a))) -> -335.74588 | T45: =ABS(R45-S45) -> 0 | V45: =30+25*$W$5 -> 33.125 | W45: =Ubar_c-Delta_c*V45 -> 6.7725136 | X45: =(-(Cost_k*Ubar_c+Delay_D)+W45/$W$5*X46)/(Rho_a+W45/$W$5) -> -397.47675 | Y45: =MAX(X45,-Delay_D/Rho_a) -> -335.74588 | Z45: =IF(V45<Floor_F,MAX((-(Cost_k*Ubar_c+Delay_D)*(1-EXP(-Rho_a*LN((Top_c-V45)/(Top_c-Floor_F))/Delta_c))/Rho_a+EXP(-Rho_a*LN((Top_c-V45)/(Top_c-Floor_F))/Delta_c)*(-Cost_k*Delta_c*Floor_F/Rho_a)),(-Delay_D/Rho_a)),(EXP(-Rho_a*LN(V45/Floor_F)/Delta_c)*(-Cost_k*Delta_c*Floor_F/Rho_a))) -> -335.74588 | AA45: =ABS(Y45-Z45) -> 0 | AC45: =30+25*$AD$5 -> 31.5625 | AD45: =Ubar_c-Delta_c*AC45 -> 6.9307499 | AE45: =(-(Cost_k*Ubar_c+Delay_D)+AD45/$AD$5*AE46)/(Rho_a+AD45/$AD$5) -> -405.42811 | AF45: =MAX(AE45,-Delay_D/Rho_a) -> -335.74588 | AG45: =IF(AC45<Floor_F,MAX((-(Cost_k*Ubar_c+Delay_D)*(1-EXP(-Rho_a*LN((Top_c-AC45)/(Top_c-Floor_F))/Delta_c))/Rho_a+EXP(-Rho_a*LN((Top_c-AC45)/(Top_c-Floor_F))/Delta_c)*(-Cost_k*Delta_c*Floor_F/Rho_a)),(-Delay_D/Rho_a)),(EXP(-Rho_a*LN(AC45/Floor_F)/Delta_c)*(-Cost_k*Delta_c*Floor_F/Rho_a))) -> -335.74588 | AH45: =ABS(AF45-AG45) -> 0
A46: =30+26*$B$5 -> 56 | B46: =-Delta_c*A46 -> -5.671189 | D46: =(-B46/$B$5*D45)/(Rho_a-B46/$B$5) -> -229.89598 | E46: =IF(A46<Floor_F,MAX((-(Cost_k*Ubar_c+Delay_D)*(1-EXP(-Rho_a*LN((Top_c-A46)/(Top_c-Floor_F))/Delta_c))/Rho_a+EXP(-Rho_a*LN((Top_c-A46)/(Top_c-Floor_F))/Delta_c)*(-Cost_k*Delta_c*Floor_F/Rho_a)),(-Delay_D/Rho_a)),(EXP(-Rho_a*LN(A46/Floor_F)/Delta_c)*(-Cost_k*Delta_c*Floor_F/Rho_a))) -> -229.82897 | F46: =ABS(D46-E46) -> 0.067010255 | H46: =30+26*$I$5 -> 43 | I46: =Ubar_c-Delta_c*H46 -> 5.7724602 | J46: =(-(Cost_k*Ubar_c+Delay_D)+I46/$I$5*J47)/(Rho_a+I46/$I$5) -> -337.9843 | K46: =MAX(J46,-Delay_D/Rho_a) -> -335.74588 | L46: =IF(H46<Floor_F,MAX((-(Cost_k*Ubar_c+Delay_D)*(1-EXP(-Rho_a*LN((Top_c-H46)/(Top_c-Floor_F))/Delta_c))/Rho_a+EXP(-Rho_a*LN((Top_c-H46)/(Top_c-Floor_F))/Delta_c)*(-Cost_k*Delta_c*Floor_F/Rho_a)),(-Delay_D/Rho_a)),(EXP(-Rho_a*LN(H46/Floor_F)/Delta_c)*(-Cost_k*Delta_c*Floor_F/Rho_a))) -> -335.74588 | M46: =ABS(K46-L46) -> 0 | O46: =30+26*$P$5 -> 36.5 | P46: =Ubar_c-Delta_c*O46 -> 6.4307232 | Q46: =(-(Cost_k*Ubar_c+Delay_D)+P46/$P$5*Q47)/(Rho_a+P46/$P$5) -> -379.08709 | R46: =MAX(Q46,-Delay_D/Rho_a) -> -335.74588 | S46: =IF(O46<Floor_F,MAX((-(Cost_k*Ubar_c+Delay_D)*(1-EXP(-Rho_a*LN((Top_c-O46)/(Top_c-Floor_F))/Delta_c))/Rho_a+EXP(-Rho_a*LN((Top_c-O46)/(Top_c-Floor_F))/Delta_c)*(-Cost_k*Delta_c*Floor_F/Rho_a)),(-Delay_D/Rho_a)),(EXP(-Rho_a*LN(O46/Floor_F)/Delta_c)*(-Cost_k*Delta_c*Floor_F/Rho_a))) -> -335.74588 | T46: =ABS(R46-S46) -> 0 | V46: =30+26*$W$5 -> 33.25 | W46: =Ubar_c-Delta_c*V46 -> 6.7598547 | X46: =(-(Cost_k*Ubar_c+Delay_D)+W46/$W$5*X47)/(Rho_a+W46/$W$5) -> -396.83768 | Y46: =MAX(X46,-Delay_D/Rho_a) -> -335.74588 | Z46: =IF(V46<Floor_F,MAX((-(Cost_k*Ubar_c+Delay_D)*(1-EXP(-Rho_a*LN((Top_c-V46)/(Top_c-Floor_F))/Delta_c))/Rho_a+EXP(-Rho_a*LN((Top_c-V46)/(Top_c-Floor_F))/Delta_c)*(-Cost_k*Delta_c*Floor_F/Rho_a)),(-Delay_D/Rho_a)),(EXP(-Rho_a*LN(V46/Floor_F)/Delta_c)*(-Cost_k*Delta_c*Floor_F/Rho_a))) -> -335.74588 | AA46: =ABS(Y46-Z46) -> 0 | AC46: =30+26*$AD$5 -> 31.625 | AD46: =Ubar_c-Delta_c*AC46 -> 6.9244205 | AE46: =(-(Cost_k*Ubar_c+Delay_D)+AD46/$AD$5*AE47)/(Rho_a+AD46/$AD$5) -> -405.1227 | AF46: =MAX(AE46,-Delay_D/Rho_a) -> -335.74588 | AG46: =IF(AC46<Floor_F,MAX((-(Cost_k*Ubar_c+Delay_D)*(1-EXP(-Rho_a*LN((Top_c-AC46)/(Top_c-Floor_F))/Delta_c))/Rho_a+EXP(-Rho_a*LN((Top_c-AC46)/(Top_c-Floor_F))/Delta_c)*(-Cost_k*Delta_c*Floor_F/Rho_a)),(-Delay_D/Rho_a)),(EXP(-Rho_a*LN(AC46/Floor_F)/Delta_c)*(-Cost_k*Delta_c*Floor_F/Rho_a))) -> -335.74588 | AH46: =ABS(AF46-AG46) -> 0
A47: =30+27*$B$5 -> 57 | B47: =-Delta_c*A47 -> -5.7724602 | D47: =(-B47/$B$5*D46)/(Rho_a-B47/$B$5) -> -226.16178 | E47: =IF(A47<Floor_F,MAX((-(Cost_k*Ubar_c+Delay_D)*(1-EXP(-Rho_a*LN((Top_c-A47)/(Top_c-Floor_F))/Delta_c))/Rho_a+EXP(-Rho_a*LN((Top_c-A47)/(Top_c-Floor_F))/Delta_c)*(-Cost_k*Delta_c*Floor_F/Rho_a)),(-Delay_D/Rho_a)),(EXP(-Rho_a*LN(A47/Floor_F)/Delta_c)*(-Cost_k*Delta_c*Floor_F/Rho_a))) -> -226.03225 | F47: =ABS(D47-E47) -> 0.12953152 | H47: =30+27*$I$5 -> 43.5 | I47: =Ubar_c-Delta_c*H47 -> 5.7218246 | J47: =(-(Cost_k*Ubar_c+Delay_D)+I47/$I$5*J48)/(Rho_a+I47/$I$5) -> -334.49401 | K47: =MAX(J47,-Delay_D/Rho_a) -> -334.49401 | L47: =IF(H47<Floor_F,MAX((-(Cost_k*Ubar_c+Delay_D)*(1-EXP(-Rho_a*LN((Top_c-H47)/(Top_c-Floor_F))/Delta_c))/Rho_a+EXP(-Rho_a*LN((Top_c-H47)/(Top_c-Floor_F))/Delta_c)*(-Cost_k*Delta_c*Floor_F/Rho_a)),(-Delay_D/Rho_a)),(EXP(-Rho_a*LN(H47/Floor_F)/Delta_c)*(-Cost_k*Delta_c*Floor_F/Rho_a))) -> -335.36533 | M47: =ABS(K47-L47) -> 0.87132784 | O47: =30+27*$P$5 -> 36.75 | P47: =Ubar_c-Delta_c*O47 -> 6.4054054 | Q47: =(-(Cost_k*Ubar_c+Delay_D)+P47/$P$5*Q48)/(Rho_a+P47/$P$5) -> -377.67287 | R47: =MAX(Q47,-Delay_D/Rho_a) -> -335.74588 | S47: =IF(O47<Floor_F,MAX((-(Cost_k*Ubar_c+Delay_D)*(1-EXP(-Rho_a*LN((Top_c-O47)/(Top_c-Floor_F))/Delta_c))/Rho_a+EXP(-Rho_a*LN((Top_c-O47)/(Top_c-Floor_F))/Delta_c)*(-Cost_k*Delta_c*Floor_F/Rho_a)),(-Delay_D/Rho_a)),(EXP(-Rho_a*LN(O47/Floor_F)/Delta_c)*(-Cost_k*Delta_c*Floor_F/Rho_a))) -> -335.74588 | T47: =ABS(R47-S47) -> 0 | V47: =30+27*$W$5 -> 33.375 | W47: =Ubar_c-Delta_c*V47 -> 6.7471958 | X47: =(-(Cost_k*Ubar_c+Delay_D)+W47/$W$5*X48)/(Rho_a+W47/$W$5) -> -396.19629 | Y47: =MAX(X47,-Delay_D/Rho_a) -> -335.74588 | Z47: =IF(V47<Floor_F,MAX((-(Cost_k*Ubar_c+Delay_D)*(1-EXP(-Rho_a*LN((Top_c-V47)/(Top_c-Floor_F))/Delta_c))/Rho_a+EXP(-Rho_a*LN((Top_c-V47)/(Top_c-Floor_F))/Delta_c)*(-Cost_k*Delta_c*Floor_F/Rho_a)),(-Delay_D/Rho_a)),(EXP(-Rho_a*LN(V47/Floor_F)/Delta_c)*(-Cost_k*Delta_c*Floor_F/Rho_a))) -> -335.74588 | AA47: =ABS(Y47-Z47) -> 0 | AC47: =30+27*$AD$5 -> 31.6875 | AD47: =Ubar_c-Delta_c*AC47 -> 6.918091 | AE47: =(-(Cost_k*Ubar_c+Delay_D)+AD47/$AD$5*AE48)/(Rho_a+AD47/$AD$5) -> -404.81676 | AF47: =MAX(AE47,-Delay_D/Rho_a) -> -335.74588 | AG47: =IF(AC47<Floor_F,MAX((-(Cost_k*Ubar_c+Delay_D)*(1-EXP(-Rho_a*LN((Top_c-AC47)/(Top_c-Floor_F))/Delta_c))/Rho_a+EXP(-Rho_a*LN((Top_c-AC47)/(Top_c-Floor_F))/Delta_c)*(-Cost_k*Delta_c*Floor_F/Rho_a)),(-Delay_D/Rho_a)),(EXP(-Rho_a*LN(AC47/Floor_F)/Delta_c)*(-Cost_k*Delta_c*Floor_F/Rho_a))) -> -335.74588 | AH47: =ABS(AF47-AG47) -> 0
A48: =30+28*$B$5 -> 58 | B48: =-Delta_c*A48 -> -5.8737315 | D48: =(-B48/$B$5*D47)/(Rho_a-B48/$B$5) -> -222.55056 | E48: =IF(A48<Floor_F,MAX((-(Cost_k*Ubar_c+Delay_D)*(1-EXP(-Rho_a*LN((Top_c-A48)/(Top_c-Floor_F))/Delta_c))/Rho_a+EXP(-Rho_a*LN((Top_c-A48)/(Top_c-Floor_F))/Delta_c)*(-Cost_k*Delta_c*Floor_F/Rho_a)),(-Delay_D/Rho_a)),(EXP(-Rho_a*LN(A48/Floor_F)/Delta_c)*(-Cost_k*Delta_c*Floor_F/Rho_a))) -> -222.36266 | F48: =ABS(D48-E48) -> 0.18789972 | H48: =30+28*$I$5 -> 44 | I48: =Ubar_c-Delta_c*H48 -> 5.671189 | J48: =(-(Cost_k*Ubar_c+Delay_D)+I48/$I$5*J49)/(Rho_a+I48/$I$5) -> -330.94376 | K48: =MAX(J48,-Delay_D/Rho_a) -> -330.94376 | L48: =IF(H48<Floor_F,MAX((-(Cost_k*Ubar_c+Delay_D)*(1-EXP(-Rho_a*LN((Top_c-H48)/(Top_c-Floor_F))/Delta_c))/Rho_a+EXP(-Rho_a*LN((Top_c-H48)/(Top_c-Floor_F))/Delta_c)*(-Cost_k*Delta_c*Floor_F/Rho_a)),(-Delay_D/Rho_a)),(EXP(-Rho_a*LN(H48/Floor_F)/Delta_c)*(-Cost_k*Delta_c*Floor_F/Rho_a))) -> -331.79164 | M48: =ABS(K48-L48) -> 0.84788735 | O48: =30+28*$P$5 -> 37 | P48: =Ubar_c-Delta_c*O48 -> 6.3800876 | Q48: =(-(Cost_k*Ubar_c+Delay_D)+P48/$P$5*Q49)/(Rho_a+P48/$P$5) -> -376.24781 | R48: =MAX(Q48,-Delay_D/Rho_a) -> -335.74588 | S48: =IF(O48<Floor_F,MAX((-(Cost_k*Ubar_c+Delay_D)*(1-EXP(-Rho_a*LN((Top_c-O48)/(Top_c-Floor_F))/Delta_c))/Rho_a+EXP(-Rho_a*LN((Top_c-O48)/(Top_c-Floor_F))/Delta_c)*(-Cost_k*Delta_c*Floor_F/Rho_a)),(-Delay_D/Rho_a)),(EXP(-Rho_a*LN(O48/Floor_F)/Delta_c)*(-Cost_k*Delta_c*Floor_F/Rho_a))) -> -335.74588 | T48: =ABS(R48-S48) -> 0 | V48: =30+28*$W$5 -> 33.5 | W48: =Ubar_c-Delta_c*V48 -> 6.7345369 | X48: =(-(Cost_k*Ubar_c+Delay_D)+W48/$W$5*X49)/(Rho_a+W48/$W$5) -> -395.55256 | Y48: =MAX(X48,-Delay_D/Rho_a) -> -335.74588 | Z48: =IF(V48<Floor_F,MAX((-(Cost_k*Ubar_c+Delay_D)*(1-EXP(-Rho_a*LN((Top_c-V48)/(Top_c-Floor_F))/Delta_c))/Rho_a+EXP(-Rho_a*LN((Top_c-V48)/(Top_c-Floor_F))/Delta_c)*(-Cost_k*Delta_c*Floor_F/Rho_a)),(-Delay_D/Rho_a)),(EXP(-Rho_a*LN(V48/Floor_F)/Delta_c)*(-Cost_k*Delta_c*Floor_F/Rho_a))) -> -335.74588 | AA48: =ABS(Y48-Z48) -> 0 | AC48: =30+28*$AD$5 -> 31.75 | AD48: =Ubar_c-Delta_c*AC48 -> 6.9117616 | AE48: =(-(Cost_k*Ubar_c+Delay_D)+AD48/$AD$5*AE49)/(Rho_a+AD48/$AD$5) -> -404.51027 | AF48: =MAX(AE48,-Delay_D/Rho_a) -> -335.74588 | AG48: =IF(AC48<Floor_F,MAX((-(Cost_k*Ubar_c+Delay_D)*(1-EXP(-Rho_a*LN((Top_c-AC48)/(Top_c-Floor_F))/Delta_c))/Rho_a+EXP(-Rho_a*LN((Top_c-AC48)/(Top_c-Floor_F))/Delta_c)*(-Cost_k*Delta_c*Floor_F/Rho_a)),(-Delay_D/Rho_a)),(EXP(-Rho_a*LN(AC48/Floor_F)/Delta_c)*(-Cost_k*Delta_c*Floor_F/Rho_a))) -> -335.74588 | AH48: =ABS(AF48-AG48) -> 0
A49: =30+29*$B$5 -> 59 | B49: =-Delta_c*A49 -> -5.9750027 | D49: =(-B49/$B$5*D48)/(Rho_a-B49/$B$5) -> -219.05628 | E49: =IF(A49<Floor_F,MAX((-(Cost_k*Ubar_c+Delay_D)*(1-EXP(-Rho_a*LN((Top_c-A49)/(Top_c-Floor_F))/Delta_c))/Rho_a+EXP(-Rho_a*LN((Top_c-A49)/(Top_c-Floor_F))/Delta_c)*(-Cost_k*Delta_c*Floor_F/Rho_a)),(-Delay_D/Rho_a)),(EXP(-Rho_a*LN(A49/Floor_F)/Delta_c)*(-Cost_k*Delta_c*Floor_F/Rho_a))) -> -218.81386 | F49: =ABS(D49-E49) -> 0.24242135 | H49: =30+29*$I$5 -> 44.5 | I49: =Ubar_c-Delta_c*H49 -> 5.6205534 | J49: =(-(Cost_k*Ubar_c+Delay_D)+I49/$I$5*J50)/(Rho_a+I49/$I$5) -> -327.33197 | K49: =MAX(J49,-Delay_D/Rho_a) -> -327.33197 | L49: =IF(H49<Floor_F,MAX((-(Cost_k*Ubar_c+Delay_D)*(1-EXP(-Rho_a*LN((Top_c-H49)/(Top_c-Floor_F))/Delta_c))/Rho_a+EXP(-Rho_a*LN((Top_c-H49)/(Top_c-Floor_F))/Delta_c)*(-Cost_k*Delta_c*Floor_F/Rho_a)),(-Delay_D/Rho_a)),(EXP(-Rho_a*LN(H49/Floor_F)/Delta_c)*(-Cost_k*Delta_c*Floor_F/Rho_a))) -> -328.15547 | M49: =ABS(K49-L49) -> 0.82349909 | O49: =30+29*$P$5 -> 37.25 | P49: =Ubar_c-Delta_c*O49 -> 6.3547698 | Q49: =(-(Cost_k*Ubar_c+Delay_D)+P49/$P$5*Q50)/(Rho_a+P49/$P$5) -> -374.81177 | R49: =MAX(Q49,-Delay_D/Rho_a) -> -335.74588 | S49: =IF(O49<Floor_F,MAX((-(Cost_k*Ubar_c+Delay_D)*(1-EXP(-Rho_a*LN((Top_c-O49)/(Top_c-Floor_F))/Delta_c))/Rho_a+EXP(-Rho_a*LN((Top_c-O49)/(Top_c-Floor_F))/Delta_c)*(-Cost_k*Delta_c*Floor_F/Rho_a)),(-Delay_D/Rho_a)),(EXP(-Rho_a*LN(O49/Floor_F)/Delta_c)*(-Cost_k*Delta_c*Floor_F/Rho_a))) -> -335.74588 | T49: =ABS(R49-S49) -> 0 | V49: =30+29*$W$5 -> 33.625 | W49: =Ubar_c-Delta_c*V49 -> 6.721878 | X49: =(-(Cost_k*Ubar_c+Delay_D)+W49/$W$5*X50)/(Rho_a+W49/$W$5) -> -394.90648 | Y49: =MAX(X49,-Delay_D/Rho_a) -> -335.74588 | Z49: =IF(V49<Floor_F,MAX((-(Cost_k*Ubar_c+Delay_D)*(1-EXP(-Rho_a*LN((Top_c-V49)/(Top_c-Floor_F))/Delta_c))/Rho_a+EXP(-Rho_a*LN((Top_c-V49)/(Top_c-Floor_F))/Delta_c)*(-Cost_k*Delta_c*Floor_F/Rho_a)),(-Delay_D/Rho_a)),(EXP(-Rho_a*LN(V49/Floor_F)/Delta_c)*(-Cost_k*Delta_c*Floor_F/Rho_a))) -> -335.74588 | AA49: =ABS(Y49-Z49) -> 0 | AC49: =30+29*$AD$5 -> 31.8125 | AD49: =Ubar_c-Delta_c*AC49 -> 6.9054321 | AE49: =(-(Cost_k*Ubar_c+Delay_D)+AD49/$AD$5*AE50)/(Rho_a+AD49/$AD$5) -> -404.20323 | AF49: =MAX(AE49,-Delay_D/Rho_a) -> -335.74588 | AG49: =IF(AC49<Floor_F,MAX((-(Cost_k*Ubar_c+Delay_D)*(1-EXP(-Rho_a*LN((Top_c-AC49)/(Top_c-Floor_F))/Delta_c))/Rho_a+EXP(-Rho_a*LN((Top_c-AC49)/(Top_c-Floor_F))/Delta_c)*(-Cost_k*Delta_c*Floor_F/Rho_a)),(-Delay_D/Rho_a)),(EXP(-Rho_a*LN(AC49/Floor_F)/Delta_c)*(-Cost_k*Delta_c*Floor_F/Rho_a))) -> -335.74588 | AH49: =ABS(AF49-AG49) -> 0
A50: =30+30*$B$5 -> 60 | B50: =-Delta_c*A50 -> -6.0762739 | D50: =(-B50/$B$5*D49)/(Rho_a-B50/$B$5) -> -215.67331 | E50: =IF(A50<Floor_F,MAX((-(Cost_k*Ubar_c+Delay_D)*(1-EXP(-Rho_a*LN((Top_c-A50)/(Top_c-Floor_F))/Delta_c))/Rho_a+EXP(-Rho_a*LN((Top_c-A50)/(Top_c-Floor_F))/Delta_c)*(-Cost_k*Delta_c*Floor_F/Rho_a)),(-Delay_D/Rho_a)),(EXP(-Rho_a*LN(A50/Floor_F)/Delta_c)*(-Cost_k*Delta_c*Floor_F/Rho_a))) -> -215.37994 | F50: =ABS(D50-E50) -> 0.29337642 | H50: =30+30*$I$5 -> 45 | I50: =Ubar_c-Delta_c*H50 -> 5.5699178 | J50: =(-(Cost_k*Ubar_c+Delay_D)+I50/$I$5*J51)/(Rho_a+I50/$I$5) -> -323.65703 | K50: =MAX(J50,-Delay_D/Rho_a) -> -323.65703 | L50: =IF(H50<Floor_F,MAX((-(Cost_k*Ubar_c+Delay_D)*(1-EXP(-Rho_a*LN((Top_c-H50)/(Top_c-Floor_F))/Delta_c))/Rho_a+EXP(-Rho_a*LN((Top_c-H50)/(Top_c-Floor_F))/Delta_c)*(-Cost_k*Delta_c*Floor_F/Rho_a)),(-Delay_D/Rho_a)),(EXP(-Rho_a*LN(H50/Floor_F)/Delta_c)*(-Cost_k*Delta_c*Floor_F/Rho_a))) -> -324.45516 | M50: =ABS(K50-L50) -> 0.79812336 | O50: =30+30*$P$5 -> 37.5 | P50: =Ubar_c-Delta_c*O50 -> 6.329452 | Q50: =(-(Cost_k*Ubar_c+Delay_D)+P50/$P$5*Q51)/(Rho_a+P50/$P$5) -> -373.36463 | R50: =MAX(Q50,-Delay_D/Rho_a) -> -335.74588 | S50: =IF(O50<Floor_F,MAX((-(Cost_k*Ubar_c+Delay_D)*(1-EXP(-Rho_a*LN((Top_c-O50)/(Top_c-Floor_F))/Delta_c))/Rho_a+EXP(-Rho_a*LN((Top_c-O50)/(Top_c-Floor_F))/Delta_c)*(-Cost_k*Delta_c*Floor_F/Rho_a)),(-Delay_D/Rho_a)),(EXP(-Rho_a*LN(O50/Floor_F)/Delta_c)*(-Cost_k*Delta_c*Floor_F/Rho_a))) -> -335.74588 | T50: =ABS(R50-S50) -> 0 | V50: =30+30*$W$5 -> 33.75 | W50: =Ubar_c-Delta_c*V50 -> 6.7092191 | X50: =(-(Cost_k*Ubar_c+Delay_D)+W50/$W$5*X51)/(Rho_a+W50/$W$5) -> -394.25804 | Y50: =MAX(X50,-Delay_D/Rho_a) -> -335.74588 | Z50: =IF(V50<Floor_F,MAX((-(Cost_k*Ubar_c+Delay_D)*(1-EXP(-Rho_a*LN((Top_c-V50)/(Top_c-Floor_F))/Delta_c))/Rho_a+EXP(-Rho_a*LN((Top_c-V50)/(Top_c-Floor_F))/Delta_c)*(-Cost_k*Delta_c*Floor_F/Rho_a)),(-Delay_D/Rho_a)),(EXP(-Rho_a*LN(V50/Floor_F)/Delta_c)*(-Cost_k*Delta_c*Floor_F/Rho_a))) -> -335.74588 | AA50: =ABS(Y50-Z50) -> 0 | AC50: =30+30*$AD$5 -> 31.875 | AD50: =Ubar_c-Delta_c*AC50 -> 6.8991027 | AE50: =(-(Cost_k*Ubar_c+Delay_D)+AD50/$AD$5*AE51)/(Rho_a+AD50/$AD$5) -> -403.89565 | AF50: =MAX(AE50,-Delay_D/Rho_a) -> -335.74588 | AG50: =IF(AC50<Floor_F,MAX((-(Cost_k*Ubar_c+Delay_D)*(1-EXP(-Rho_a*LN((Top_c-AC50)/(Top_c-Floor_F))/Delta_c))/Rho_a+EXP(-Rho_a*LN((Top_c-AC50)/(Top_c-Floor_F))/Delta_c)*(-Cost_k*Delta_c*Floor_F/Rho_a)),(-Delay_D/Rho_a)),(EXP(-Rho_a*LN(AC50/Floor_F)/Delta_c)*(-Cost_k*Delta_c*Floor_F/Rho_a))) -> -335.74588 | AH50: =ABS(AF50-AG50) -> 0
A51: =30+31*$B$5 -> 61 | B51: =-Delta_c*A51 -> -6.1775451 | D51: =(-B51/$B$5*D50)/(Rho_a-B51/$B$5) -> -212.39636 | E51: =IF(A51<Floor_F,MAX((-(Cost_k*Ubar_c+Delay_D)*(1-EXP(-Rho_a*LN((Top_c-A51)/(Top_c-Floor_F))/Delta_c))/Rho_a+EXP(-Rho_a*LN((Top_c-A51)/(Top_c-Floor_F))/Delta_c)*(-Cost_k*Delta_c*Floor_F/Rho_a)),(-Delay_D/Rho_a)),(EXP(-Rho_a*LN(A51/Floor_F)/Delta_c)*(-Cost_k*Delta_c*Floor_F/Rho_a))) -> -212.05534 | F51: =ABS(D51-E51) -> 0.34102114 | H51: =30+31*$I$5 -> 45.5 | I51: =Ubar_c-Delta_c*H51 -> 5.5192821 | J51: =(-(Cost_k*Ubar_c+Delay_D)+I51/$I$5*J52)/(Rho_a+I51/$I$5) -> -319.91724 | K51: =MAX(J51,-Delay_D/Rho_a) -> -319.91724 | L51: =IF(H51<Floor_F,MAX((-(Cost_k*Ubar_c+Delay_D)*(1-EXP(-Rho_a*LN((Top_c-H51)/(Top_c-Floor_F))/Delta_c))/Rho_a+EXP(-Rho_a*LN((Top_c-H51)/(Top_c-Floor_F))/Delta_c)*(-Cost_k*Delta_c*Floor_F/Rho_a)),(-Delay_D/Rho_a)),(EXP(-Rho_a*LN(H51/Floor_F)/Delta_c)*(-Cost_k*Delta_c*Floor_F/Rho_a))) -> -320.68896 | M51: =ABS(K51-L51) -> 0.77171847 | O51: =30+31*$P$5 -> 37.75 | P51: =Ubar_c-Delta_c*O51 -> 6.3041342 | Q51: =(-(Cost_k*Ubar_c+Delay_D)+P51/$P$5*Q52)/(Rho_a+P51/$P$5) -> -371.90624 | R51: =MAX(Q51,-Delay_D/Rho_a) -> -335.74588 | S51: =IF(O51<Floor_F,MAX((-(Cost_k*Ubar_c+Delay_D)*(1-EXP(-Rho_a*LN((Top_c-O51)/(Top_c-Floor_F))/Delta_c))/Rho_a+EXP(-Rho_a*LN((Top_c-O51)/(Top_c-Floor_F))/Delta_c)*(-Cost_k*Delta_c*Floor_F/Rho_a)),(-Delay_D/Rho_a)),(EXP(-Rho_a*LN(O51/Floor_F)/Delta_c)*(-Cost_k*Delta_c*Floor_F/Rho_a))) -> -335.74588 | T51: =ABS(R51-S51) -> 0 | V51: =30+31*$W$5 -> 33.875 | W51: =Ubar_c-Delta_c*V51 -> 6.6965602 | X51: =(-(Cost_k*Ubar_c+Delay_D)+W51/$W$5*X52)/(Rho_a+W51/$W$5) -> -393.60722 | Y51: =MAX(X51,-Delay_D/Rho_a) -> -335.74588 | Z51: =IF(V51<Floor_F,MAX((-(Cost_k*Ubar_c+Delay_D)*(1-EXP(-Rho_a*LN((Top_c-V51)/(Top_c-Floor_F))/Delta_c))/Rho_a+EXP(-Rho_a*LN((Top_c-V51)/(Top_c-Floor_F))/Delta_c)*(-Cost_k*Delta_c*Floor_F/Rho_a)),(-Delay_D/Rho_a)),(EXP(-Rho_a*LN(V51/Floor_F)/Delta_c)*(-Cost_k*Delta_c*Floor_F/Rho_a))) -> -335.74588 | AA51: =ABS(Y51-Z51) -> 0 | AC51: =30+31*$AD$5 -> 31.9375 | AD51: =Ubar_c-Delta_c*AC51 -> 6.8927732 | AE51: =(-(Cost_k*Ubar_c+Delay_D)+AD51/$AD$5*AE52)/(Rho_a+AD51/$AD$5) -> -403.58752 | AF51: =MAX(AE51,-Delay_D/Rho_a) -> -335.74588 | AG51: =IF(AC51<Floor_F,MAX((-(Cost_k*Ubar_c+Delay_D)*(1-EXP(-Rho_a*LN((Top_c-AC51)/(Top_c-Floor_F))/Delta_c))/Rho_a+EXP(-Rho_a*LN((Top_c-AC51)/(Top_c-Floor_F))/Delta_c)*(-Cost_k*Delta_c*Floor_F/Rho_a)),(-Delay_D/Rho_a)),(EXP(-Rho_a*LN(AC51/Floor_F)/Delta_c)*(-Cost_k*Delta_c*Floor_F/Rho_a))) -> -335.74588 | AH51: =ABS(AF51-AG51) -> 0
A52: =30+32*$B$5 -> 62 | B52: =-Delta_c*A52 -> -6.2788164 | D52: =(-B52/$B$5*D51)/(Rho_a-B52/$B$5) -> -209.22047 | E52: =IF(A52<Floor_F,MAX((-(Cost_k*Ubar_c+Delay_D)*(1-EXP(-Rho_a*LN((Top_c-A52)/(Top_c-Floor_F))/Delta_c))/Rho_a+EXP(-Rho_a*LN((Top_c-A52)/(Top_c-Floor_F))/Delta_c)*(-Cost_k*Delta_c*Floor_F/Rho_a)),(-Delay_D/Rho_a)),(EXP(-Rho_a*LN(A52/Floor_F)/Delta_c)*(-Cost_k*Delta_c*Floor_F/Rho_a))) -> -208.83488 | F52: =ABS(D52-E52) -> 0.38559024 | H52: =30+32*$I$5 -> 46 | I52: =Ubar_c-Delta_c*H52 -> 5.4686465 | J52: =(-(Cost_k*Ubar_c+Delay_D)+I52/$I$5*J53)/(Rho_a+I52/$I$5) -> -316.11084 | K52: =MAX(J52,-Delay_D/Rho_a) -> -316.11084 | L52: =IF(H52<Floor_F,MAX((-(Cost_k*Ubar_c+Delay_D)*(1-EXP(-Rho_a*LN((Top_c-H52)/(Top_c-Floor_F))/Delta_c))/Rho_a+EXP(-Rho_a*LN((Top_c-H52)/(Top_c-Floor_F))/Delta_c)*(-Cost_k*Delta_c*Floor_F/Rho_a)),(-Delay_D/Rho_a)),(EXP(-Rho_a*LN(H52/Floor_F)/Delta_c)*(-Cost_k*Delta_c*Floor_F/Rho_a))) -> -316.85509 | M52: =ABS(K52-L52) -> 0.74424067 | O52: =30+32*$P$5 -> 38 | P52: =Ubar_c-Delta_c*O52 -> 6.2788164 | Q52: =(-(Cost_k*Ubar_c+Delay_D)+P52/$P$5*Q53)/(Rho_a+P52/$P$5) -> -370.43649 | R52: =MAX(Q52,-Delay_D/Rho_a) -> -335.74588 | S52: =IF(O52<Floor_F,MAX((-(Cost_k*Ubar_c+Delay_D)*(1-EXP(-Rho_a*LN((Top_c-O52)/(Top_c-Floor_F))/Delta_c))/Rho_a+EXP(-Rho_a*LN((Top_c-O52)/(Top_c-Floor_F))/Delta_c)*(-Cost_k*Delta_c*Floor_F/Rho_a)),(-Delay_D/Rho_a)),(EXP(-Rho_a*LN(O52/Floor_F)/Delta_c)*(-Cost_k*Delta_c*Floor_F/Rho_a))) -> -335.74588 | T52: =ABS(R52-S52) -> 0 | V52: =30+32*$W$5 -> 34 | W52: =Ubar_c-Delta_c*V52 -> 6.6839013 | X52: =(-(Cost_k*Ubar_c+Delay_D)+W52/$W$5*X53)/(Rho_a+W52/$W$5) -> -392.95402 | Y52: =MAX(X52,-Delay_D/Rho_a) -> -335.74588 | Z52: =IF(V52<Floor_F,MAX((-(Cost_k*Ubar_c+Delay_D)*(1-EXP(-Rho_a*LN((Top_c-V52)/(Top_c-Floor_F))/Delta_c))/Rho_a+EXP(-Rho_a*LN((Top_c-V52)/(Top_c-Floor_F))/Delta_c)*(-Cost_k*Delta_c*Floor_F/Rho_a)),(-Delay_D/Rho_a)),(EXP(-Rho_a*LN(V52/Floor_F)/Delta_c)*(-Cost_k*Delta_c*Floor_F/Rho_a))) -> -335.74588 | AA52: =ABS(Y52-Z52) -> 0 | AC52: =30+32*$AD$5 -> 32 | AD52: =Ubar_c-Delta_c*AC52 -> 6.8864438 | AE52: =(-(Cost_k*Ubar_c+Delay_D)+AD52/$AD$5*AE53)/(Rho_a+AD52/$AD$5) -> -403.27884 | AF52: =MAX(AE52,-Delay_D/Rho_a) -> -335.74588 | AG52: =IF(AC52<Floor_F,MAX((-(Cost_k*Ubar_c+Delay_D)*(1-EXP(-Rho_a*LN((Top_c-AC52)/(Top_c-Floor_F))/Delta_c))/Rho_a+EXP(-Rho_a*LN((Top_c-AC52)/(Top_c-Floor_F))/Delta_c)*(-Cost_k*Delta_c*Floor_F/Rho_a)),(-Delay_D/Rho_a)),(EXP(-Rho_a*LN(AC52/Floor_F)/Delta_c)*(-Cost_k*Delta_c*Floor_F/Rho_a))) -> -335.74588 | AH52: =ABS(AF52-AG52) -> 0
A53: =30+33*$B$5 -> 63 | B53: =-Delta_c*A53 -> -6.3800876 | D53: =(-B53/$B$5*D52)/(Rho_a-B53/$B$5) -> -206.14099 | E53: =IF(A53<Floor_F,MAX((-(Cost_k*Ubar_c+Delay_D)*(1-EXP(-Rho_a*LN((Top_c-A53)/(Top_c-Floor_F))/Delta_c))/Rho_a+EXP(-Rho_a*LN((Top_c-A53)/(Top_c-Floor_F))/Delta_c)*(-Cost_k*Delta_c*Floor_F/Rho_a)),(-Delay_D/Rho_a)),(EXP(-Rho_a*LN(A53/Floor_F)/Delta_c)*(-Cost_k*Delta_c*Floor_F/Rho_a))) -> -205.71369 | F53: =ABS(D53-E53) -> 0.42729904 | H53: =30+33*$I$5 -> 46.5 | I53: =Ubar_c-Delta_c*H53 -> 5.4180109 | J53: =(-(Cost_k*Ubar_c+Delay_D)+I53/$I$5*J54)/(Rho_a+I53/$I$5) -> -312.23604 | K53: =MAX(J53,-Delay_D/Rho_a) -> -312.23604 | L53: =IF(H53<Floor_F,MAX((-(Cost_k*Ubar_c+Delay_D)*(1-EXP(-Rho_a*LN((Top_c-H53)/(Top_c-Floor_F))/Delta_c))/Rho_a+EXP(-Rho_a*LN((Top_c-H53)/(Top_c-Floor_F))/Delta_c)*(-Cost_k*Delta_c*Floor_F/Rho_a)),(-Delay_D/Rho_a)),(EXP(-Rho_a*LN(H53/Floor_F)/Delta_c)*(-Cost_k*Delta_c*Floor_F/Rho_a))) -> -312.95168 | M53: =ABS(K53-L53) -> 0.71564404 | O53: =30+33*$P$5 -> 38.25 | P53: =Ubar_c-Delta_c*O53 -> 6.2534986 | Q53: =(-(Cost_k*Ubar_c+Delay_D)+P53/$P$5*Q54)/(Rho_a+P53/$P$5) -> -368.95524 | R53: =MAX(Q53,-Delay_D/Rho_a) -> -335.74588 | S53: =IF(O53<Floor_F,MAX((-(Cost_k*Ubar_c+Delay_D)*(1-EXP(-Rho_a*LN((Top_c-O53)/(Top_c-Floor_F))/Delta_c))/Rho_a+EXP(-Rho_a*LN((Top_c-O53)/(Top_c-Floor_F))/Delta_c)*(-Cost_k*Delta_c*Floor_F/Rho_a)),(-Delay_D/Rho_a)),(EXP(-Rho_a*LN(O53/Floor_F)/Delta_c)*(-Cost_k*Delta_c*Floor_F/Rho_a))) -> -335.74588 | T53: =ABS(R53-S53) -> 0 | V53: =30+33*$W$5 -> 34.125 | W53: =Ubar_c-Delta_c*V53 -> 6.6712424 | X53: =(-(Cost_k*Ubar_c+Delay_D)+W53/$W$5*X54)/(Rho_a+W53/$W$5) -> -392.29841 | Y53: =MAX(X53,-Delay_D/Rho_a) -> -335.74588 | Z53: =IF(V53<Floor_F,MAX((-(Cost_k*Ubar_c+Delay_D)*(1-EXP(-Rho_a*LN((Top_c-V53)/(Top_c-Floor_F))/Delta_c))/Rho_a+EXP(-Rho_a*LN((Top_c-V53)/(Top_c-Floor_F))/Delta_c)*(-Cost_k*Delta_c*Floor_F/Rho_a)),(-Delay_D/Rho_a)),(EXP(-Rho_a*LN(V53/Floor_F)/Delta_c)*(-Cost_k*Delta_c*Floor_F/Rho_a))) -> -335.74588 | AA53: =ABS(Y53-Z53) -> 0 | AC53: =30+33*$AD$5 -> 32.0625 | AD53: =Ubar_c-Delta_c*AC53 -> 6.8801143 | AE53: =(-(Cost_k*Ubar_c+Delay_D)+AD53/$AD$5*AE54)/(Rho_a+AD53/$AD$5) -> -402.96961 | AF53: =MAX(AE53,-Delay_D/Rho_a) -> -335.74588 | AG53: =IF(AC53<Floor_F,MAX((-(Cost_k*Ubar_c+Delay_D)*(1-EXP(-Rho_a*LN((Top_c-AC53)/(Top_c-Floor_F))/Delta_c))/Rho_a+EXP(-Rho_a*LN((Top_c-AC53)/(Top_c-Floor_F))/Delta_c)*(-Cost_k*Delta_c*Floor_F/Rho_a)),(-Delay_D/Rho_a)),(EXP(-Rho_a*LN(AC53/Floor_F)/Delta_c)*(-Cost_k*Delta_c*Floor_F/Rho_a))) -> -335.74588 | AH53: =ABS(AF53-AG53) -> 0
A54: =30+34*$B$5 -> 64 | B54: =-Delta_c*A54 -> -6.4813588 | D54: =(-B54/$B$5*D53)/(Rho_a-B54/$B$5) -> -203.15356 | E54: =IF(A54<Floor_F,MAX((-(Cost_k*Ubar_c+Delay_D)*(1-EXP(-Rho_a*LN((Top_c-A54)/(Top_c-Floor_F))/Delta_c))/Rho_a+EXP(-Rho_a*LN((Top_c-A54)/(Top_c-Floor_F))/Delta_c)*(-Cost_k*Delta_c*Floor_F/Rho_a)),(-Delay_D/Rho_a)),(EXP(-Rho_a*LN(A54/Floor_F)/Delta_c)*(-Cost_k*Delta_c*Floor_F/Rho_a))) -> -202.68721 | F54: =ABS(D54-E54) -> 0.46634531 | H54: =30+34*$I$5 -> 47 | I54: =Ubar_c-Delta_c*H54 -> 5.3673753 | J54: =(-(Cost_k*Ubar_c+Delay_D)+I54/$I$5*J55)/(Rho_a+I54/$I$5) -> -308.29093 | K54: =MAX(J54,-Delay_D/Rho_a) -> -308.29093 | L54: =IF(H54<Floor_F,MAX((-(Cost_k*Ubar_c+Delay_D)*(1-EXP(-Rho_a*LN((Top_c-H54)/(Top_c-Floor_F))/Delta_c))/Rho_a+EXP(-Rho_a*LN((Top_c-H54)/(Top_c-Floor_F))/Delta_c)*(-Cost_k*Delta_c*Floor_F/Rho_a)),(-Delay_D/Rho_a)),(EXP(-Rho_a*LN(H54/Floor_F)/Delta_c)*(-Cost_k*Delta_c*Floor_F/Rho_a))) -> -308.97681 | M54: =ABS(K54-L54) -> 0.68588033 | O54: =30+34*$P$5 -> 38.5 | P54: =Ubar_c-Delta_c*O54 -> 6.2281808 | Q54: =(-(Cost_k*Ubar_c+Delay_D)+P54/$P$5*Q55)/(Rho_a+P54/$P$5) -> -367.46234 | R54: =MAX(Q54,-Delay_D/Rho_a) -> -335.74588 | S54: =IF(O54<Floor_F,MAX((-(Cost_k*Ubar_c+Delay_D)*(1-EXP(-Rho_a*LN((Top_c-O54)/(Top_c-Floor_F))/Delta_c))/Rho_a+EXP(-Rho_a*LN((Top_c-O54)/(Top_c-Floor_F))/Delta_c)*(-Cost_k*Delta_c*Floor_F/Rho_a)),(-Delay_D/Rho_a)),(EXP(-Rho_a*LN(O54/Floor_F)/Delta_c)*(-Cost_k*Delta_c*Floor_F/Rho_a))) -> -335.74588 | T54: =ABS(R54-S54) -> 0 | V54: =30+34*$W$5 -> 34.25 | W54: =Ubar_c-Delta_c*V54 -> 6.6585835 | X54: =(-(Cost_k*Ubar_c+Delay_D)+W54/$W$5*X55)/(Rho_a+W54/$W$5) -> -391.6404 | Y54: =MAX(X54,-Delay_D/Rho_a) -> -335.74588 | Z54: =IF(V54<Floor_F,MAX((-(Cost_k*Ubar_c+Delay_D)*(1-EXP(-Rho_a*LN((Top_c-V54)/(Top_c-Floor_F))/Delta_c))/Rho_a+EXP(-Rho_a*LN((Top_c-V54)/(Top_c-Floor_F))/Delta_c)*(-Cost_k*Delta_c*Floor_F/Rho_a)),(-Delay_D/Rho_a)),(EXP(-Rho_a*LN(V54/Floor_F)/Delta_c)*(-Cost_k*Delta_c*Floor_F/Rho_a))) -> -335.74588 | AA54: =ABS(Y54-Z54) -> 0 | AC54: =30+34*$AD$5 -> 32.125 | AD54: =Ubar_c-Delta_c*AC54 -> 6.8737849 | AE54: =(-(Cost_k*Ubar_c+Delay_D)+AD54/$AD$5*AE55)/(Rho_a+AD54/$AD$5) -> -402.65983 | AF54: =MAX(AE54,-Delay_D/Rho_a) -> -335.74588 | AG54: =IF(AC54<Floor_F,MAX((-(Cost_k*Ubar_c+Delay_D)*(1-EXP(-Rho_a*LN((Top_c-AC54)/(Top_c-Floor_F))/Delta_c))/Rho_a+EXP(-Rho_a*LN((Top_c-AC54)/(Top_c-Floor_F))/Delta_c)*(-Cost_k*Delta_c*Floor_F/Rho_a)),(-Delay_D/Rho_a)),(EXP(-Rho_a*LN(AC54/Floor_F)/Delta_c)*(-Cost_k*Delta_c*Floor_F/Rho_a))) -> -335.74588 | AH54: =ABS(AF54-AG54) -> 0
A55: =30+35*$B$5 -> 65 | B55: =-Delta_c*A55 -> -6.5826301 | D55: =(-B55/$B$5*D54)/(Rho_a-B55/$B$5) -> -200.25407 | E55: =IF(A55<Floor_F,MAX((-(Cost_k*Ubar_c+Delay_D)*(1-EXP(-Rho_a*LN((Top_c-A55)/(Top_c-Floor_F))/Delta_c))/Rho_a+EXP(-Rho_a*LN((Top_c-A55)/(Top_c-Floor_F))/Delta_c)*(-Cost_k*Delta_c*Floor_F/Rho_a)),(-Delay_D/Rho_a)),(EXP(-Rho_a*LN(A55/Floor_F)/Delta_c)*(-Cost_k*Delta_c*Floor_F/Rho_a))) -> -199.75116 | F55: =ABS(D55-E55) -> 0.50291095 | H55: =30+35*$I$5 -> 47.5 | I55: =Ubar_c-Delta_c*H55 -> 5.3167397 | J55: =(-(Cost_k*Ubar_c+Delay_D)+I55/$I$5*J56)/(Rho_a+I55/$I$5) -> -304.27359 | K55: =MAX(J55,-Delay_D/Rho_a) -> -304.27359 | L55: =IF(H55<Floor_F,MAX((-(Cost_k*Ubar_c+Delay_D)*(1-EXP(-Rho_a*LN((Top_c-H55)/(Top_c-Floor_F))/Delta_c))/Rho_a+EXP(-Rho_a*LN((Top_c-H55)/(Top_c-Floor_F))/Delta_c)*(-Cost_k*Delta_c*Floor_F/Rho_a)),(-Delay_D/Rho_a)),(EXP(-Rho_a*LN(H55/Floor_F)/Delta_c)*(-Cost_k*Delta_c*Floor_F/Rho_a))) -> -304.92848 | M55: =ABS(K55-L55) -> 0.65489882 | O55: =30+35*$P$5 -> 38.75 | P55: =Ubar_c-Delta_c*O55 -> 6.202863 | Q55: =(-(Cost_k*Ubar_c+Delay_D)+P55/$P$5*Q56)/(Rho_a+P55/$P$5) -> -365.95766 | R55: =MAX(Q55,-Delay_D/Rho_a) -> -335.74588 | S55: =IF(O55<Floor_F,MAX((-(Cost_k*Ubar_c+Delay_D)*(1-EXP(-Rho_a*LN((Top_c-O55)/(Top_c-Floor_F))/Delta_c))/Rho_a+EXP(-Rho_a*LN((Top_c-O55)/(Top_c-Floor_F))/Delta_c)*(-Cost_k*Delta_c*Floor_F/Rho_a)),(-Delay_D/Rho_a)),(EXP(-Rho_a*LN(O55/Floor_F)/Delta_c)*(-Cost_k*Delta_c*Floor_F/Rho_a))) -> -335.74588 | T55: =ABS(R55-S55) -> 0 | V55: =30+35*$W$5 -> 34.375 | W55: =Ubar_c-Delta_c*V55 -> 6.6459246 | X55: =(-(Cost_k*Ubar_c+Delay_D)+W55/$W$5*X56)/(Rho_a+W55/$W$5) -> -390.97995 | Y55: =MAX(X55,-Delay_D/Rho_a) -> -335.74588 | Z55: =IF(V55<Floor_F,MAX((-(Cost_k*Ubar_c+Delay_D)*(1-EXP(-Rho_a*LN((Top_c-V55)/(Top_c-Floor_F))/Delta_c))/Rho_a+EXP(-Rho_a*LN((Top_c-V55)/(Top_c-Floor_F))/Delta_c)*(-Cost_k*Delta_c*Floor_F/Rho_a)),(-Delay_D/Rho_a)),(EXP(-Rho_a*LN(V55/Floor_F)/Delta_c)*(-Cost_k*Delta_c*Floor_F/Rho_a))) -> -335.74588 | AA55: =ABS(Y55-Z55) -> 0 | AC55: =30+35*$AD$5 -> 32.1875 | AD55: =Ubar_c-Delta_c*AC55 -> 6.8674554 | AE55: =(-(Cost_k*Ubar_c+Delay_D)+AD55/$AD$5*AE56)/(Rho_a+AD55/$AD$5) -> -402.34949 | AF55: =MAX(AE55,-Delay_D/Rho_a) -> -335.74588 | AG55: =IF(AC55<Floor_F,MAX((-(Cost_k*Ubar_c+Delay_D)*(1-EXP(-Rho_a*LN((Top_c-AC55)/(Top_c-Floor_F))/Delta_c))/Rho_a+EXP(-Rho_a*LN((Top_c-AC55)/(Top_c-Floor_F))/Delta_c)*(-Cost_k*Delta_c*Floor_F/Rho_a)),(-Delay_D/Rho_a)),(EXP(-Rho_a*LN(AC55/Floor_F)/Delta_c)*(-Cost_k*Delta_c*Floor_F/Rho_a))) -> -335.74588 | AH55: =ABS(AF55-AG55) -> 0
A56: =30+36*$B$5 -> 66 | B56: =-Delta_c*A56 -> -6.6839013 | D56: =(-B56/$B$5*D55)/(Rho_a-B56/$B$5) -> -197.43866 | E56: =IF(A56<Floor_F,MAX((-(Cost_k*Ubar_c+Delay_D)*(1-EXP(-Rho_a*LN((Top_c-A56)/(Top_c-Floor_F))/Delta_c))/Rho_a+EXP(-Rho_a*LN((Top_c-A56)/(Top_c-Floor_F))/Delta_c)*(-Cost_k*Delta_c*Floor_F/Rho_a)),(-Delay_D/Rho_a)),(EXP(-Rho_a*LN(A56/Floor_F)/Delta_c)*(-Cost_k*Delta_c*Floor_F/Rho_a))) -> -196.9015 | F56: =ABS(D56-E56) -> 0.53716341 | H56: =30+36*$I$5 -> 48 | I56: =Ubar_c-Delta_c*H56 -> 5.2661041 | J56: =(-(Cost_k*Ubar_c+Delay_D)+I56/$I$5*J57)/(Rho_a+I56/$I$5) -> -300.18197 | K56: =MAX(J56,-Delay_D/Rho_a) -> -300.18197 | L56: =IF(H56<Floor_F,MAX((-(Cost_k*Ubar_c+Delay_D)*(1-EXP(-Rho_a*LN((Top_c-H56)/(Top_c-Floor_F))/Delta_c))/Rho_a+EXP(-Rho_a*LN((Top_c-H56)/(Top_c-Floor_F))/Delta_c)*(-Cost_k*Delta_c*Floor_F/Rho_a)),(-Delay_D/Rho_a)),(EXP(-Rho_a*LN(H56/Floor_F)/Delta_c)*(-Cost_k*Delta_c*Floor_F/Rho_a))) -> -300.80462 | M56: =ABS(K56-L56) -> 0.6226462 | O56: =30+36*$P$5 -> 39 | P56: =Ubar_c-Delta_c*O56 -> 6.1775451 | Q56: =(-(Cost_k*Ubar_c+Delay_D)+P56/$P$5*Q57)/(Rho_a+P56/$P$5) -> -364.44106 | R56: =MAX(Q56,-Delay_D/Rho_a) -> -335.74588 | S56: =IF(O56<Floor_F,MAX((-(Cost_k*Ubar_c+Delay_D)*(1-EXP(-Rho_a*LN((Top_c-O56)/(Top_c-Floor_F))/Delta_c))/Rho_a+EXP(-Rho_a*LN((Top_c-O56)/(Top_c-Floor_F))/Delta_c)*(-Cost_k*Delta_c*Floor_F/Rho_a)),(-Delay_D/Rho_a)),(EXP(-Rho_a*LN(O56/Floor_F)/Delta_c)*(-Cost_k*Delta_c*Floor_F/Rho_a))) -> -335.74588 | T56: =ABS(R56-S56) -> 0 | V56: =30+36*$W$5 -> 34.5 | W56: =Ubar_c-Delta_c*V56 -> 6.6332657 | X56: =(-(Cost_k*Ubar_c+Delay_D)+W56/$W$5*X57)/(Rho_a+W56/$W$5) -> -390.31706 | Y56: =MAX(X56,-Delay_D/Rho_a) -> -335.74588 | Z56: =IF(V56<Floor_F,MAX((-(Cost_k*Ubar_c+Delay_D)*(1-EXP(-Rho_a*LN((Top_c-V56)/(Top_c-Floor_F))/Delta_c))/Rho_a+EXP(-Rho_a*LN((Top_c-V56)/(Top_c-Floor_F))/Delta_c)*(-Cost_k*Delta_c*Floor_F/Rho_a)),(-Delay_D/Rho_a)),(EXP(-Rho_a*LN(V56/Floor_F)/Delta_c)*(-Cost_k*Delta_c*Floor_F/Rho_a))) -> -335.74588 | AA56: =ABS(Y56-Z56) -> 0 | AC56: =30+36*$AD$5 -> 32.25 | AD56: =Ubar_c-Delta_c*AC56 -> 6.861126 | AE56: =(-(Cost_k*Ubar_c+Delay_D)+AD56/$AD$5*AE57)/(Rho_a+AD56/$AD$5) -> -402.0386 | AF56: =MAX(AE56,-Delay_D/Rho_a) -> -335.74588 | AG56: =IF(AC56<Floor_F,MAX((-(Cost_k*Ubar_c+Delay_D)*(1-EXP(-Rho_a*LN((Top_c-AC56)/(Top_c-Floor_F))/Delta_c))/Rho_a+EXP(-Rho_a*LN((Top_c-AC56)/(Top_c-Floor_F))/Delta_c)*(-Cost_k*Delta_c*Floor_F/Rho_a)),(-Delay_D/Rho_a)),(EXP(-Rho_a*LN(AC56/Floor_F)/Delta_c)*(-Cost_k*Delta_c*Floor_F/Rho_a))) -> -335.74588 | AH56: =ABS(AF56-AG56) -> 0
A57: =30+37*$B$5 -> 67 | B57: =-Delta_c*A57 -> -6.7851725 | D57: =(-B57/$B$5*D56)/(Rho_a-B57/$B$5) -> -194.70369 | E57: =IF(A57<Floor_F,MAX((-(Cost_k*Ubar_c+Delay_D)*(1-EXP(-Rho_a*LN((Top_c-A57)/(Top_c-Floor_F))/Delta_c))/Rho_a+EXP(-Rho_a*LN((Top_c-A57)/(Top_c-Floor_F))/Delta_c)*(-Cost_k*Delta_c*Floor_F/Rho_a)),(-Delay_D/Rho_a)),(EXP(-Rho_a*LN(A57/Floor_F)/Delta_c)*(-Cost_k*Delta_c*Floor_F/Rho_a))) -> -194.13444 | F57: =ABS(D57-E57) -> 0.56925703 | H57: =30+37*$I$5 -> 48.5 | I57: =Ubar_c-Delta_c*H57 -> 5.2154684 | J57: =(-(Cost_k*Ubar_c+Delay_D)+I57/$I$5*J58)/(Rho_a+I57/$I$5) -> -296.01398 | K57: =MAX(J57,-Delay_D/Rho_a) -> -296.01398 | L57: =IF(H57<Floor_F,MAX((-(Cost_k*Ubar_c+Delay_D)*(1-EXP(-Rho_a*LN((Top_c-H57)/(Top_c-Floor_F))/Delta_c))/Rho_a+EXP(-Rho_a*LN((Top_c-H57)/(Top_c-Floor_F))/Delta_c)*(-Cost_k*Delta_c*Floor_F/Rho_a)),(-Delay_D/Rho_a)),(EXP(-Rho_a*LN(H57/Floor_F)/Delta_c)*(-Cost_k*Delta_c*Floor_F/Rho_a))) -> -296.60305 | M57: =ABS(K57-L57) -> 0.58906639 | O57: =30+37*$P$5 -> 39.25 | P57: =Ubar_c-Delta_c*O57 -> 6.1522273 | Q57: =(-(Cost_k*Ubar_c+Delay_D)+P57/$P$5*Q58)/(Rho_a+P57/$P$5) -> -362.9124 | R57: =MAX(Q57,-Delay_D/Rho_a) -> -335.74588 | S57: =IF(O57<Floor_F,MAX((-(Cost_k*Ubar_c+Delay_D)*(1-EXP(-Rho_a*LN((Top_c-O57)/(Top_c-Floor_F))/Delta_c))/Rho_a+EXP(-Rho_a*LN((Top_c-O57)/(Top_c-Floor_F))/Delta_c)*(-Cost_k*Delta_c*Floor_F/Rho_a)),(-Delay_D/Rho_a)),(EXP(-Rho_a*LN(O57/Floor_F)/Delta_c)*(-Cost_k*Delta_c*Floor_F/Rho_a))) -> -335.74588 | T57: =ABS(R57-S57) -> 0 | V57: =30+37*$W$5 -> 34.625 | W57: =Ubar_c-Delta_c*V57 -> 6.6206068 | X57: =(-(Cost_k*Ubar_c+Delay_D)+W57/$W$5*X58)/(Rho_a+W57/$W$5) -> -389.65171 | Y57: =MAX(X57,-Delay_D/Rho_a) -> -335.74588 | Z57: =IF(V57<Floor_F,MAX((-(Cost_k*Ubar_c+Delay_D)*(1-EXP(-Rho_a*LN((Top_c-V57)/(Top_c-Floor_F))/Delta_c))/Rho_a+EXP(-Rho_a*LN((Top_c-V57)/(Top_c-Floor_F))/Delta_c)*(-Cost_k*Delta_c*Floor_F/Rho_a)),(-Delay_D/Rho_a)),(EXP(-Rho_a*LN(V57/Floor_F)/Delta_c)*(-Cost_k*Delta_c*Floor_F/Rho_a))) -> -335.74588 | AA57: =ABS(Y57-Z57) -> 0 | AC57: =30+37*$AD$5 -> 32.3125 | AD57: =Ubar_c-Delta_c*AC57 -> 6.8547965 | AE57: =(-(Cost_k*Ubar_c+Delay_D)+AD57/$AD$5*AE58)/(Rho_a+AD57/$AD$5) -> -401.72715 | AF57: =MAX(AE57,-Delay_D/Rho_a) -> -335.74588 | AG57: =IF(AC57<Floor_F,MAX((-(Cost_k*Ubar_c+Delay_D)*(1-EXP(-Rho_a*LN((Top_c-AC57)/(Top_c-Floor_F))/Delta_c))/Rho_a+EXP(-Rho_a*LN((Top_c-AC57)/(Top_c-Floor_F))/Delta_c)*(-Cost_k*Delta_c*Floor_F/Rho_a)),(-Delay_D/Rho_a)),(EXP(-Rho_a*LN(AC57/Floor_F)/Delta_c)*(-Cost_k*Delta_c*Floor_F/Rho_a))) -> -335.74588 | AH57: =ABS(AF57-AG57) -> 0
A58: =30+38*$B$5 -> 68 | B58: =-Delta_c*A58 -> -6.8864438 | D58: =(-B58/$B$5*D57)/(Rho_a-B58/$B$5) -> -192.04573 | E58: =IF(A58<Floor_F,MAX((-(Cost_k*Ubar_c+Delay_D)*(1-EXP(-Rho_a*LN((Top_c-A58)/(Top_c-Floor_F))/Delta_c))/Rho_a+EXP(-Rho_a*LN((Top_c-A58)/(Top_c-Floor_F))/Delta_c)*(-Cost_k*Delta_c*Floor_F/Rho_a)),(-Delay_D/Rho_a)),(EXP(-Rho_a*LN(A58/Floor_F)/Delta_c)*(-Cost_k*Delta_c*Floor_F/Rho_a))) -> -191.4464 | F58: =ABS(D58-E58) -> 0.59933426 | H58: =30+38*$I$5 -> 49 | I58: =Ubar_c-Delta_c*H58 -> 5.1648328 | J58: =(-(Cost_k*Ubar_c+Delay_D)+I58/$I$5*J59)/(Rho_a+I58/$I$5) -> -291.76745 | K58: =MAX(J58,-Delay_D/Rho_a) -> -291.76745 | L58: =IF(H58<Floor_F,MAX((-(Cost_k*Ubar_c+Delay_D)*(1-EXP(-Rho_a*LN((Top_c-H58)/(Top_c-Floor_F))/Delta_c))/Rho_a+EXP(-Rho_a*LN((Top_c-H58)/(Top_c-Floor_F))/Delta_c)*(-Cost_k*Delta_c*Floor_F/Rho_a)),(-Delay_D/Rho_a)),(EXP(-Rho_a*LN(H58/Floor_F)/Delta_c)*(-Cost_k*Delta_c*Floor_F/Rho_a))) -> -292.32155 | M58: =ABS(K58-L58) -> 0.5541004 | O58: =30+38*$P$5 -> 39.5 | P58: =Ubar_c-Delta_c*O58 -> 6.1269095 | Q58: =(-(Cost_k*Ubar_c+Delay_D)+P58/$P$5*Q59)/(Rho_a+P58/$P$5) -> -361.37153 | R58: =MAX(Q58,-Delay_D/Rho_a) -> -335.74588 | S58: =IF(O58<Floor_F,MAX((-(Cost_k*Ubar_c+Delay_D)*(1-EXP(-Rho_a*LN((Top_c-O58)/(Top_c-Floor_F))/Delta_c))/Rho_a+EXP(-Rho_a*LN((Top_c-O58)/(Top_c-Floor_F))/Delta_c)*(-Cost_k*Delta_c*Floor_F/Rho_a)),(-Delay_D/Rho_a)),(EXP(-Rho_a*LN(O58/Floor_F)/Delta_c)*(-Cost_k*Delta_c*Floor_F/Rho_a))) -> -335.74588 | T58: =ABS(R58-S58) -> 0 | V58: =30+38*$W$5 -> 34.75 | W58: =Ubar_c-Delta_c*V58 -> 6.6079479 | X58: =(-(Cost_k*Ubar_c+Delay_D)+W58/$W$5*X59)/(Rho_a+W58/$W$5) -> -388.9839 | Y58: =MAX(X58,-Delay_D/Rho_a) -> -335.74588 | Z58: =IF(V58<Floor_F,MAX((-(Cost_k*Ubar_c+Delay_D)*(1-EXP(-Rho_a*LN((Top_c-V58)/(Top_c-Floor_F))/Delta_c))/Rho_a+EXP(-Rho_a*LN((Top_c-V58)/(Top_c-Floor_F))/Delta_c)*(-Cost_k*Delta_c*Floor_F/Rho_a)),(-Delay_D/Rho_a)),(EXP(-Rho_a*LN(V58/Floor_F)/Delta_c)*(-Cost_k*Delta_c*Floor_F/Rho_a))) -> -335.74588 | AA58: =ABS(Y58-Z58) -> 0 | AC58: =30+38*$AD$5 -> 32.375 | AD58: =Ubar_c-Delta_c*AC58 -> 6.8484671 | AE58: =(-(Cost_k*Ubar_c+Delay_D)+AD58/$AD$5*AE59)/(Rho_a+AD58/$AD$5) -> -401.41515 | AF58: =MAX(AE58,-Delay_D/Rho_a) -> -335.74588 | AG58: =IF(AC58<Floor_F,MAX((-(Cost_k*Ubar_c+Delay_D)*(1-EXP(-Rho_a*LN((Top_c-AC58)/(Top_c-Floor_F))/Delta_c))/Rho_a+EXP(-Rho_a*LN((Top_c-AC58)/(Top_c-Floor_F))/Delta_c)*(-Cost_k*Delta_c*Floor_F/Rho_a)),(-Delay_D/Rho_a)),(EXP(-Rho_a*LN(AC58/Floor_F)/Delta_c)*(-Cost_k*Delta_c*Floor_F/Rho_a))) -> -335.74588 | AH58: =ABS(AF58-AG58) -> 0
A59: =30+39*$B$5 -> 69 | B59: =-Delta_c*A59 -> -6.987715 | D59: =(-B59/$B$5*D58)/(Rho_a-B59/$B$5) -> -189.46154 | E59: =IF(A59<Floor_F,MAX((-(Cost_k*Ubar_c+Delay_D)*(1-EXP(-Rho_a*LN((Top_c-A59)/(Top_c-Floor_F))/Delta_c))/Rho_a+EXP(-Rho_a*LN((Top_c-A59)/(Top_c-Floor_F))/Delta_c)*(-Cost_k*Delta_c*Floor_F/Rho_a)),(-Delay_D/Rho_a)),(EXP(-Rho_a*LN(A59/Floor_F)/Delta_c)*(-Cost_k*Delta_c*Floor_F/Rho_a))) -> -188.83401 | F59: =ABS(D59-E59) -> 0.62752665 | H59: =30+39*$I$5 -> 49.5 | I59: =Ubar_c-Delta_c*H59 -> 5.1141972 | J59: =(-(Cost_k*Ubar_c+Delay_D)+I59/$I$5*J60)/(Rho_a+I59/$I$5) -> -287.4401 | K59: =MAX(J59,-Delay_D/Rho_a) -> -287.4401 | L59: =IF(H59<Floor_F,MAX((-(Cost_k*Ubar_c+Delay_D)*(1-EXP(-Rho_a*LN((Top_c-H59)/(Top_c-Floor_F))/Delta_c))/Rho_a+EXP(-Rho_a*LN((Top_c-H59)/(Top_c-Floor_F))/Delta_c)*(-Cost_k*Delta_c*Floor_F/Rho_a)),(-Delay_D/Rho_a)),(EXP(-Rho_a*LN(H59/Floor_F)/Delta_c)*(-Cost_k*Delta_c*Floor_F/Rho_a))) -> -287.95778 | M59: =ABS(K59-L59) -> 0.5176861 | O59: =30+39*$P$5 -> 39.75 | P59: =Ubar_c-Delta_c*O59 -> 6.1015917 | Q59: =(-(Cost_k*Ubar_c+Delay_D)+P59/$P$5*Q60)/(Rho_a+P59/$P$5) -> -359.81829 | R59: =MAX(Q59,-Delay_D/Rho_a) -> -335.74588 | S59: =IF(O59<Floor_F,MAX((-(Cost_k*Ubar_c+Delay_D)*(1-EXP(-Rho_a*LN((Top_c-O59)/(Top_c-Floor_F))/Delta_c))/Rho_a+EXP(-Rho_a*LN((Top_c-O59)/(Top_c-Floor_F))/Delta_c)*(-Cost_k*Delta_c*Floor_F/Rho_a)),(-Delay_D/Rho_a)),(EXP(-Rho_a*LN(O59/Floor_F)/Delta_c)*(-Cost_k*Delta_c*Floor_F/Rho_a))) -> -335.74588 | T59: =ABS(R59-S59) -> 0 | V59: =30+39*$W$5 -> 34.875 | W59: =Ubar_c-Delta_c*V59 -> 6.595289 | X59: =(-(Cost_k*Ubar_c+Delay_D)+W59/$W$5*X60)/(Rho_a+W59/$W$5) -> -388.3136 | Y59: =MAX(X59,-Delay_D/Rho_a) -> -335.74588 | Z59: =IF(V59<Floor_F,MAX((-(Cost_k*Ubar_c+Delay_D)*(1-EXP(-Rho_a*LN((Top_c-V59)/(Top_c-Floor_F))/Delta_c))/Rho_a+EXP(-Rho_a*LN((Top_c-V59)/(Top_c-Floor_F))/Delta_c)*(-Cost_k*Delta_c*Floor_F/Rho_a)),(-Delay_D/Rho_a)),(EXP(-Rho_a*LN(V59/Floor_F)/Delta_c)*(-Cost_k*Delta_c*Floor_F/Rho_a))) -> -335.74588 | AA59: =ABS(Y59-Z59) -> 0 | AC59: =30+39*$AD$5 -> 32.4375 | AD59: =Ubar_c-Delta_c*AC59 -> 6.8421376 | AE59: =(-(Cost_k*Ubar_c+Delay_D)+AD59/$AD$5*AE60)/(Rho_a+AD59/$AD$5) -> -401.10258 | AF59: =MAX(AE59,-Delay_D/Rho_a) -> -335.74588 | AG59: =IF(AC59<Floor_F,MAX((-(Cost_k*Ubar_c+Delay_D)*(1-EXP(-Rho_a*LN((Top_c-AC59)/(Top_c-Floor_F))/Delta_c))/Rho_a+EXP(-Rho_a*LN((Top_c-AC59)/(Top_c-Floor_F))/Delta_c)*(-Cost_k*Delta_c*Floor_F/Rho_a)),(-Delay_D/Rho_a)),(EXP(-Rho_a*LN(AC59/Floor_F)/Delta_c)*(-Cost_k*Delta_c*Floor_F/Rho_a))) -> -335.74588 | AH59: =ABS(AF59-AG59) -> 0
A60: =30+40*$B$5 -> 70 | B60: =-Delta_c*A60 -> -7.0889862 | D60: =(-B60/$B$5*D59)/(Rho_a-B60/$B$5) -> -186.94805 | E60: =IF(A60<Floor_F,MAX((-(Cost_k*Ubar_c+Delay_D)*(1-EXP(-Rho_a*LN((Top_c-A60)/(Top_c-Floor_F))/Delta_c))/Rho_a+EXP(-Rho_a*LN((Top_c-A60)/(Top_c-Floor_F))/Delta_c)*(-Cost_k*Delta_c*Floor_F/Rho_a)),(-Delay_D/Rho_a)),(EXP(-Rho_a*LN(A60/Floor_F)/Delta_c)*(-Cost_k*Delta_c*Floor_F/Rho_a))) -> -186.2941 | F60: =ABS(D60-E60) -> 0.65395588 | H60: =30+40*$I$5 -> 50 | I60: =Ubar_c-Delta_c*H60 -> 5.0635616 | J60: =(-(Cost_k*Ubar_c+Delay_D)+I60/$I$5*J61)/(Rho_a+I60/$I$5) -> -283.02958 | K60: =MAX(J60,-Delay_D/Rho_a) -> -283.02958 | L60: =IF(H60<Floor_F,MAX((-(Cost_k*Ubar_c+Delay_D)*(1-EXP(-Rho_a*LN((Top_c-H60)/(Top_c-Floor_F))/Delta_c))/Rho_a+EXP(-Rho_a*LN((Top_c-H60)/(Top_c-Floor_F))/Delta_c)*(-Cost_k*Delta_c*Floor_F/Rho_a)),(-Delay_D/Rho_a)),(EXP(-Rho_a*LN(H60/Floor_F)/Delta_c)*(-Cost_k*Delta_c*Floor_F/Rho_a))) -> -283.50934 | M60: =ABS(K60-L60) -> 0.47975806 | O60: =30+40*$P$5 -> 40 | P60: =Ubar_c-Delta_c*O60 -> 6.0762739 | Q60: =(-(Cost_k*Ubar_c+Delay_D)+P60/$P$5*Q61)/(Rho_a+P60/$P$5) -> -358.25255 | R60: =MAX(Q60,-Delay_D/Rho_a) -> -335.74588 | S60: =IF(O60<Floor_F,MAX((-(Cost_k*Ubar_c+Delay_D)*(1-EXP(-Rho_a*LN((Top_c-O60)/(Top_c-Floor_F))/Delta_c))/Rho_a+EXP(-Rho_a*LN((Top_c-O60)/(Top_c-Floor_F))/Delta_c)*(-Cost_k*Delta_c*Floor_F/Rho_a)),(-Delay_D/Rho_a)),(EXP(-Rho_a*LN(O60/Floor_F)/Delta_c)*(-Cost_k*Delta_c*Floor_F/Rho_a))) -> -335.74588 | T60: =ABS(R60-S60) -> 0 | V60: =30+40*$W$5 -> 35 | W60: =Ubar_c-Delta_c*V60 -> 6.5826301 | X60: =(-(Cost_k*Ubar_c+Delay_D)+W60/$W$5*X61)/(Rho_a+W60/$W$5) -> -387.6408 | Y60: =MAX(X60,-Delay_D/Rho_a) -> -335.74588 | Z60: =IF(V60<Floor_F,MAX((-(Cost_k*Ubar_c+Delay_D)*(1-EXP(-Rho_a*LN((Top_c-V60)/(Top_c-Floor_F))/Delta_c))/Rho_a+EXP(-Rho_a*LN((Top_c-V60)/(Top_c-Floor_F))/Delta_c)*(-Cost_k*Delta_c*Floor_F/Rho_a)),(-Delay_D/Rho_a)),(EXP(-Rho_a*LN(V60/Floor_F)/Delta_c)*(-Cost_k*Delta_c*Floor_F/Rho_a))) -> -335.74588 | AA60: =ABS(Y60-Z60) -> 0 | AC60: =30+40*$AD$5 -> 32.5 | AD60: =Ubar_c-Delta_c*AC60 -> 6.8358082 | AE60: =(-(Cost_k*Ubar_c+Delay_D)+AD60/$AD$5*AE61)/(Rho_a+AD60/$AD$5) -> -400.78945 | AF60: =MAX(AE60,-Delay_D/Rho_a) -> -335.74588 | AG60: =IF(AC60<Floor_F,MAX((-(Cost_k*Ubar_c+Delay_D)*(1-EXP(-Rho_a*LN((Top_c-AC60)/(Top_c-Floor_F))/Delta_c))/Rho_a+EXP(-Rho_a*LN((Top_c-AC60)/(Top_c-Floor_F))/Delta_c)*(-Cost_k*Delta_c*Floor_F/Rho_a)),(-Delay_D/Rho_a)),(EXP(-Rho_a*LN(AC60/Floor_F)/Delta_c)*(-Cost_k*Delta_c*Floor_F/Rho_a))) -> -335.74588 | AH60: =ABS(AF60-AG60) -> 0
A61: =30+41*$B$5 -> 71 | B61: =-Delta_c*A61 -> -7.1902575 | D61: =(-B61/$B$5*D60)/(Rho_a-B61/$B$5) -> -184.50239 | E61: =IF(A61<Floor_F,MAX((-(Cost_k*Ubar_c+Delay_D)*(1-EXP(-Rho_a*LN((Top_c-A61)/(Top_c-Floor_F))/Delta_c))/Rho_a+EXP(-Rho_a*LN((Top_c-A61)/(Top_c-Floor_F))/Delta_c)*(-Cost_k*Delta_c*Floor_F/Rho_a)),(-Delay_D/Rho_a)),(EXP(-Rho_a*LN(A61/Floor_F)/Delta_c)*(-Cost_k*Delta_c*Floor_F/Rho_a))) -> -183.82365 | F61: =ABS(D61-E61) -> 0.67873456 | H61: =30+41*$I$5 -> 50.5 | I61: =Ubar_c-Delta_c*H61 -> 5.012926 | J61: =(-(Cost_k*Ubar_c+Delay_D)+I61/$I$5*J62)/(Rho_a+I61/$I$5) -> -278.53345 | K61: =MAX(J61,-Delay_D/Rho_a) -> -278.53345 | L61: =IF(H61<Floor_F,MAX((-(Cost_k*Ubar_c+Delay_D)*(1-EXP(-Rho_a*LN((Top_c-H61)/(Top_c-Floor_F))/Delta_c))/Rho_a+EXP(-Rho_a*LN((Top_c-H61)/(Top_c-Floor_F))/Delta_c)*(-Cost_k*Delta_c*Floor_F/Rho_a)),(-Delay_D/Rho_a)),(EXP(-Rho_a*LN(H61/Floor_F)/Delta_c)*(-Cost_k*Delta_c*Floor_F/Rho_a))) -> -278.97369 | M61: =ABS(K61-L61) -> 0.44024736 | O61: =30+41*$P$5 -> 40.25 | P61: =Ubar_c-Delta_c*O61 -> 6.0509561 | Q61: =(-(Cost_k*Ubar_c+Delay_D)+P61/$P$5*Q62)/(Rho_a+P61/$P$5) -> -356.67414 | R61: =MAX(Q61,-Delay_D/Rho_a) -> -335.74588 | S61: =IF(O61<Floor_F,MAX((-(Cost_k*Ubar_c+Delay_D)*(1-EXP(-Rho_a*LN((Top_c-O61)/(Top_c-Floor_F))/Delta_c))/Rho_a+EXP(-Rho_a*LN((Top_c-O61)/(Top_c-Floor_F))/Delta_c)*(-Cost_k*Delta_c*Floor_F/Rho_a)),(-Delay_D/Rho_a)),(EXP(-Rho_a*LN(O61/Floor_F)/Delta_c)*(-Cost_k*Delta_c*Floor_F/Rho_a))) -> -335.74588 | T61: =ABS(R61-S61) -> 0 | V61: =30+41*$W$5 -> 35.125 | W61: =Ubar_c-Delta_c*V61 -> 6.5699712 | X61: =(-(Cost_k*Ubar_c+Delay_D)+W61/$W$5*X62)/(Rho_a+W61/$W$5) -> -386.9655 | Y61: =MAX(X61,-Delay_D/Rho_a) -> -335.74588 | Z61: =IF(V61<Floor_F,MAX((-(Cost_k*Ubar_c+Delay_D)*(1-EXP(-Rho_a*LN((Top_c-V61)/(Top_c-Floor_F))/Delta_c))/Rho_a+EXP(-Rho_a*LN((Top_c-V61)/(Top_c-Floor_F))/Delta_c)*(-Cost_k*Delta_c*Floor_F/Rho_a)),(-Delay_D/Rho_a)),(EXP(-Rho_a*LN(V61/Floor_F)/Delta_c)*(-Cost_k*Delta_c*Floor_F/Rho_a))) -> -335.74588 | AA61: =ABS(Y61-Z61) -> 0 | AC61: =30+41*$AD$5 -> 32.5625 | AD61: =Ubar_c-Delta_c*AC61 -> 6.8294787 | AE61: =(-(Cost_k*Ubar_c+Delay_D)+AD61/$AD$5*AE62)/(Rho_a+AD61/$AD$5) -> -400.47576 | AF61: =MAX(AE61,-Delay_D/Rho_a) -> -335.74588 | AG61: =IF(AC61<Floor_F,MAX((-(Cost_k*Ubar_c+Delay_D)*(1-EXP(-Rho_a*LN((Top_c-AC61)/(Top_c-Floor_F))/Delta_c))/Rho_a+EXP(-Rho_a*LN((Top_c-AC61)/(Top_c-Floor_F))/Delta_c)*(-Cost_k*Delta_c*Floor_F/Rho_a)),(-Delay_D/Rho_a)),(EXP(-Rho_a*LN(AC61/Floor_F)/Delta_c)*(-Cost_k*Delta_c*Floor_F/Rho_a))) -> -335.74588 | AH61: =ABS(AF61-AG61) -> 0
A62: =30+42*$B$5 -> 72 | B62: =-Delta_c*A62 -> -7.2915287 | D62: =(-B62/$B$5*D61)/(Rho_a-B62/$B$5) -> -182.12181 | E62: =IF(A62<Floor_F,MAX((-(Cost_k*Ubar_c+Delay_D)*(1-EXP(-Rho_a*LN((Top_c-A62)/(Top_c-Floor_F))/Delta_c))/Rho_a+EXP(-Rho_a*LN((Top_c-A62)/(Top_c-Floor_F))/Delta_c)*(-Cost_k*Delta_c*Floor_F/Rho_a)),(-Delay_D/Rho_a)),(EXP(-Rho_a*LN(A62/Floor_F)/Delta_c)*(-Cost_k*Delta_c*Floor_F/Rho_a))) -> -181.41984 | F62: =ABS(D62-E62) -> 0.70196702 | H62: =30+42*$I$5 -> 51 | I62: =Ubar_c-Delta_c*H62 -> 4.9622904 | J62: =(-(Cost_k*Ubar_c+Delay_D)+I62/$I$5*J63)/(Rho_a+I62/$I$5) -> -273.94915 | K62: =MAX(J62,-Delay_D/Rho_a) -> -273.94915 | L62: =IF(H62<Floor_F,MAX((-(Cost_k*Ubar_c+Delay_D)*(1-EXP(-Rho_a*LN((Top_c-H62)/(Top_c-Floor_F))/Delta_c))/Rho_a+EXP(-Rho_a*LN((Top_c-H62)/(Top_c-Floor_F))/Delta_c)*(-Cost_k*Delta_c*Floor_F/Rho_a)),(-Delay_D/Rho_a)),(EXP(-Rho_a*LN(H62/Floor_F)/Delta_c)*(-Cost_k*Delta_c*Floor_F/Rho_a))) -> -274.34824 | M62: =ABS(K62-L62) -> 0.39908132 | O62: =30+42*$P$5 -> 40.5 | P62: =Ubar_c-Delta_c*O62 -> 6.0256383 | Q62: =(-(Cost_k*Ubar_c+Delay_D)+P62/$P$5*Q63)/(Rho_a+P62/$P$5) -> -355.08291 | R62: =MAX(Q62,-Delay_D/Rho_a) -> -335.74588 | S62: =IF(O62<Floor_F,MAX((-(Cost_k*Ubar_c+Delay_D)*(1-EXP(-Rho_a*LN((Top_c-O62)/(Top_c-Floor_F))/Delta_c))/Rho_a+EXP(-Rho_a*LN((Top_c-O62)/(Top_c-Floor_F))/Delta_c)*(-Cost_k*Delta_c*Floor_F/Rho_a)),(-Delay_D/Rho_a)),(EXP(-Rho_a*LN(O62/Floor_F)/Delta_c)*(-Cost_k*Delta_c*Floor_F/Rho_a))) -> -335.74588 | T62: =ABS(R62-S62) -> 0 | V62: =30+42*$W$5 -> 35.25 | W62: =Ubar_c-Delta_c*V62 -> 6.5573123 | X62: =(-(Cost_k*Ubar_c+Delay_D)+W62/$W$5*X63)/(Rho_a+W62/$W$5) -> -386.28766 | Y62: =MAX(X62,-Delay_D/Rho_a) -> -335.74588 | Z62: =IF(V62<Floor_F,MAX((-(Cost_k*Ubar_c+Delay_D)*(1-EXP(-Rho_a*LN((Top_c-V62)/(Top_c-Floor_F))/Delta_c))/Rho_a+EXP(-Rho_a*LN((Top_c-V62)/(Top_c-Floor_F))/Delta_c)*(-Cost_k*Delta_c*Floor_F/Rho_a)),(-Delay_D/Rho_a)),(EXP(-Rho_a*LN(V62/Floor_F)/Delta_c)*(-Cost_k*Delta_c*Floor_F/Rho_a))) -> -335.74588 | AA62: =ABS(Y62-Z62) -> 0 | AC62: =30+42*$AD$5 -> 32.625 | AD62: =Ubar_c-Delta_c*AC62 -> 6.8231493 | AE62: =(-(Cost_k*Ubar_c+Delay_D)+AD62/$AD$5*AE63)/(Rho_a+AD62/$AD$5) -> -400.16151 | AF62: =MAX(AE62,-Delay_D/Rho_a) -> -335.74588 | AG62: =IF(AC62<Floor_F,MAX((-(Cost_k*Ubar_c+Delay_D)*(1-EXP(-Rho_a*LN((Top_c-AC62)/(Top_c-Floor_F))/Delta_c))/Rho_a+EXP(-Rho_a*LN((Top_c-AC62)/(Top_c-Floor_F))/Delta_c)*(-Cost_k*Delta_c*Floor_F/Rho_a)),(-Delay_D/Rho_a)),(EXP(-Rho_a*LN(AC62/Floor_F)/Delta_c)*(-Cost_k*Delta_c*Floor_F/Rho_a))) -> -335.74588 | AH62: =ABS(AF62-AG62) -> 0
A63: =30+43*$B$5 -> 73 | B63: =-Delta_c*A63 -> -7.3927999 | D63: =(-B63/$B$5*D62)/(Rho_a-B63/$B$5) -> -179.80373 | E63: =IF(A63<Floor_F,MAX((-(Cost_k*Ubar_c+Delay_D)*(1-EXP(-Rho_a*LN((Top_c-A63)/(Top_c-Floor_F))/Delta_c))/Rho_a+EXP(-Rho_a*LN((Top_c-A63)/(Top_c-Floor_F))/Delta_c)*(-Cost_k*Delta_c*Floor_F/Rho_a)),(-Delay_D/Rho_a)),(EXP(-Rho_a*LN(A63/Floor_F)/Delta_c)*(-Cost_k*Delta_c*Floor_F/Rho_a))) -> -179.07998 | F63: =ABS(D63-E63) -> 0.72375004 | H63: =30+43*$I$5 -> 51.5 | I63: =Ubar_c-Delta_c*H63 -> 4.9116547 | J63: =(-(Cost_k*Ubar_c+Delay_D)+I63/$I$5*J64)/(Rho_a+I63/$I$5) -> -269.27406 | K63: =MAX(J63,-Delay_D/Rho_a) -> -269.27406 | L63: =IF(H63<Floor_F,MAX((-(Cost_k*Ubar_c+Delay_D)*(1-EXP(-Rho_a*LN((Top_c-H63)/(Top_c-Floor_F))/Delta_c))/Rho_a+EXP(-Rho_a*LN((Top_c-H63)/(Top_c-Floor_F))/Delta_c)*(-Cost_k*Delta_c*Floor_F/Rho_a)),(-Delay_D/Rho_a)),(EXP(-Rho_a*LN(H63/Floor_F)/Delta_c)*(-Cost_k*Delta_c*Floor_F/Rho_a))) -> -269.63024 | M63: =ABS(K63-L63) -> 0.35618329 | O63: =30+43*$P$5 -> 40.75 | P63: =Ubar_c-Delta_c*O63 -> 6.0003205 | Q63: =(-(Cost_k*Ubar_c+Delay_D)+P63/$P$5*Q64)/(Rho_a+P63/$P$5) -> -353.4787 | R63: =MAX(Q63,-Delay_D/Rho_a) -> -335.74588 | S63: =IF(O63<Floor_F,MAX((-(Cost_k*Ubar_c+Delay_D)*(1-EXP(-Rho_a*LN((Top_c-O63)/(Top_c-Floor_F))/Delta_c))/Rho_a+EXP(-Rho_a*LN((Top_c-O63)/(Top_c-Floor_F))/Delta_c)*(-Cost_k*Delta_c*Floor_F/Rho_a)),(-Delay_D/Rho_a)),(EXP(-Rho_a*LN(O63/Floor_F)/Delta_c)*(-Cost_k*Delta_c*Floor_F/Rho_a))) -> -335.74588 | T63: =ABS(R63-S63) -> 0 | V63: =30+43*$W$5 -> 35.375 | W63: =Ubar_c-Delta_c*V63 -> 6.5446534 | X63: =(-(Cost_k*Ubar_c+Delay_D)+W63/$W$5*X64)/(Rho_a+W63/$W$5) -> -385.60729 | Y63: =MAX(X63,-Delay_D/Rho_a) -> -335.74588 | Z63: =IF(V63<Floor_F,MAX((-(Cost_k*Ubar_c+Delay_D)*(1-EXP(-Rho_a*LN((Top_c-V63)/(Top_c-Floor_F))/Delta_c))/Rho_a+EXP(-Rho_a*LN((Top_c-V63)/(Top_c-Floor_F))/Delta_c)*(-Cost_k*Delta_c*Floor_F/Rho_a)),(-Delay_D/Rho_a)),(EXP(-Rho_a*LN(V63/Floor_F)/Delta_c)*(-Cost_k*Delta_c*Floor_F/Rho_a))) -> -335.74588 | AA63: =ABS(Y63-Z63) -> 0 | AC63: =30+43*$AD$5 -> 32.6875 | AD63: =Ubar_c-Delta_c*AC63 -> 6.8168198 | AE63: =(-(Cost_k*Ubar_c+Delay_D)+AD63/$AD$5*AE64)/(Rho_a+AD63/$AD$5) -> -399.84669 | AF63: =MAX(AE63,-Delay_D/Rho_a) -> -335.74588 | AG63: =IF(AC63<Floor_F,MAX((-(Cost_k*Ubar_c+Delay_D)*(1-EXP(-Rho_a*LN((Top_c-AC63)/(Top_c-Floor_F))/Delta_c))/Rho_a+EXP(-Rho_a*LN((Top_c-AC63)/(Top_c-Floor_F))/Delta_c)*(-Cost_k*Delta_c*Floor_F/Rho_a)),(-Delay_D/Rho_a)),(EXP(-Rho_a*LN(AC63/Floor_F)/Delta_c)*(-Cost_k*Delta_c*Floor_F/Rho_a))) -> -335.74588 | AH63: =ABS(AF63-AG63) -> 0
A64: =30+44*$B$5 -> 74 | B64: =-Delta_c*A64 -> -7.4940712 | D64: =(-B64/$B$5*D63)/(Rho_a-B64/$B$5) -> -177.54569 | E64: =IF(A64<Floor_F,MAX((-(Cost_k*Ubar_c+Delay_D)*(1-EXP(-Rho_a*LN((Top_c-A64)/(Top_c-Floor_F))/Delta_c))/Rho_a+EXP(-Rho_a*LN((Top_c-A64)/(Top_c-Floor_F))/Delta_c)*(-Cost_k*Delta_c*Floor_F/Rho_a)),(-Delay_D/Rho_a)),(EXP(-Rho_a*LN(A64/Floor_F)/Delta_c)*(-Cost_k*Delta_c*Floor_F/Rho_a))) -> -176.80151 | F64: =ABS(D64-E64) -> 0.74417343 | H64: =30+44*$I$5 -> 52 | I64: =Ubar_c-Delta_c*H64 -> 4.8610191 | J64: =(-(Cost_k*Ubar_c+Delay_D)+I64/$I$5*J65)/(Rho_a+I64/$I$5) -> -264.50541 | K64: =MAX(J64,-Delay_D/Rho_a) -> -264.50541 | L64: =IF(H64<Floor_F,MAX((-(Cost_k*Ubar_c+Delay_D)*(1-EXP(-Rho_a*LN((Top_c-H64)/(Top_c-Floor_F))/Delta_c))/Rho_a+EXP(-Rho_a*LN((Top_c-H64)/(Top_c-Floor_F))/Delta_c)*(-Cost_k*Delta_c*Floor_F/Rho_a)),(-Delay_D/Rho_a)),(EXP(-Rho_a*LN(H64/Floor_F)/Delta_c)*(-Cost_k*Delta_c*Floor_F/Rho_a))) -> -264.81688 | M64: =ABS(K64-L64) -> 0.3114724 | O64: =30+44*$P$5 -> 41 | P64: =Ubar_c-Delta_c*O64 -> 5.9750027 | Q64: =(-(Cost_k*Ubar_c+Delay_D)+P64/$P$5*Q65)/(Rho_a+P64/$P$5) -> -351.86136 | R64: =MAX(Q64,-Delay_D/Rho_a) -> -335.74588 | S64: =IF(O64<Floor_F,MAX((-(Cost_k*Ubar_c+Delay_D)*(1-EXP(-Rho_a*LN((Top_c-O64)/(Top_c-Floor_F))/Delta_c))/Rho_a+EXP(-Rho_a*LN((Top_c-O64)/(Top_c-Floor_F))/Delta_c)*(-Cost_k*Delta_c*Floor_F/Rho_a)),(-Delay_D/Rho_a)),(EXP(-Rho_a*LN(O64/Floor_F)/Delta_c)*(-Cost_k*Delta_c*Floor_F/Rho_a))) -> -335.74588 | T64: =ABS(R64-S64) -> 0 | V64: =30+44*$W$5 -> 35.5 | W64: =Ubar_c-Delta_c*V64 -> 6.5319945 | X64: =(-(Cost_k*Ubar_c+Delay_D)+W64/$W$5*X65)/(Rho_a+W64/$W$5) -> -384.92436 | Y64: =MAX(X64,-Delay_D/Rho_a) -> -335.74588 | Z64: =IF(V64<Floor_F,MAX((-(Cost_k*Ubar_c+Delay_D)*(1-EXP(-Rho_a*LN((Top_c-V64)/(Top_c-Floor_F))/Delta_c))/Rho_a+EXP(-Rho_a*LN((Top_c-V64)/(Top_c-Floor_F))/Delta_c)*(-Cost_k*Delta_c*Floor_F/Rho_a)),(-Delay_D/Rho_a)),(EXP(-Rho_a*LN(V64/Floor_F)/Delta_c)*(-Cost_k*Delta_c*Floor_F/Rho_a))) -> -335.74588 | AA64: =ABS(Y64-Z64) -> 0 | AC64: =30+44*$AD$5 -> 32.75 | AD64: =Ubar_c-Delta_c*AC64 -> 6.8104903 | AE64: =(-(Cost_k*Ubar_c+Delay_D)+AD64/$AD$5*AE65)/(Rho_a+AD64/$AD$5) -> -399.5313 | AF64: =MAX(AE64,-Delay_D/Rho_a) -> -335.74588 | AG64: =IF(AC64<Floor_F,MAX((-(Cost_k*Ubar_c+Delay_D)*(1-EXP(-Rho_a*LN((Top_c-AC64)/(Top_c-Floor_F))/Delta_c))/Rho_a+EXP(-Rho_a*LN((Top_c-AC64)/(Top_c-Floor_F))/Delta_c)*(-Cost_k*Delta_c*Floor_F/Rho_a)),(-Delay_D/Rho_a)),(EXP(-Rho_a*LN(AC64/Floor_F)/Delta_c)*(-Cost_k*Delta_c*Floor_F/Rho_a))) -> -335.74588 | AH64: =ABS(AF64-AG64) -> 0
A65: =30+45*$B$5 -> 75 | B65: =-Delta_c*A65 -> -7.5953424 | D65: =(-B65/$B$5*D64)/(Rho_a-B65/$B$5) -> -175.34536 | E65: =IF(A65<Floor_F,MAX((-(Cost_k*Ubar_c+Delay_D)*(1-EXP(-Rho_a*LN((Top_c-A65)/(Top_c-Floor_F))/Delta_c))/Rho_a+EXP(-Rho_a*LN((Top_c-A65)/(Top_c-Floor_F))/Delta_c)*(-Cost_k*Delta_c*Floor_F/Rho_a)),(-Delay_D/Rho_a)),(EXP(-Rho_a*LN(A65/Floor_F)/Delta_c)*(-Cost_k*Delta_c*Floor_F/Rho_a))) -> -174.58204 | F65: =ABS(D65-E65) -> 0.76332065 | H65: =30+45*$I$5 -> 52.5 | I65: =Ubar_c-Delta_c*H65 -> 4.8103835 | J65: =(-(Cost_k*Ubar_c+Delay_D)+I65/$I$5*J66)/(Rho_a+I65/$I$5) -> -259.64034 | K65: =MAX(J65,-Delay_D/Rho_a) -> -259.64034 | L65: =IF(H65<Floor_F,MAX((-(Cost_k*Ubar_c+Delay_D)*(1-EXP(-Rho_a*LN((Top_c-H65)/(Top_c-Floor_F))/Delta_c))/Rho_a+EXP(-Rho_a*LN((Top_c-H65)/(Top_c-Floor_F))/Delta_c)*(-Cost_k*Delta_c*Floor_F/Rho_a)),(-Delay_D/Rho_a)),(EXP(-Rho_a*LN(H65/Floor_F)/Delta_c)*(-Cost_k*Delta_c*Floor_F/Rho_a))) -> -259.9052 | M65: =ABS(K65-L65) -> 0.26486325 | O65: =30+45*$P$5 -> 41.25 | P65: =Ubar_c-Delta_c*O65 -> 5.9496849 | Q65: =(-(Cost_k*Ubar_c+Delay_D)+P65/$P$5*Q66)/(Rho_a+P65/$P$5) -> -350.23071 | R65: =MAX(Q65,-Delay_D/Rho_a) -> -335.74588 | S65: =IF(O65<Floor_F,MAX((-(Cost_k*Ubar_c+Delay_D)*(1-EXP(-Rho_a*LN((Top_c-O65)/(Top_c-Floor_F))/Delta_c))/Rho_a+EXP(-Rho_a*LN((Top_c-O65)/(Top_c-Floor_F))/Delta_c)*(-Cost_k*Delta_c*Floor_F/Rho_a)),(-Delay_D/Rho_a)),(EXP(-Rho_a*LN(O65/Floor_F)/Delta_c)*(-Cost_k*Delta_c*Floor_F/Rho_a))) -> -335.74588 | T65: =ABS(R65-S65) -> 0 | V65: =30+45*$W$5 -> 35.625 | W65: =Ubar_c-Delta_c*V65 -> 6.5193356 | X65: =(-(Cost_k*Ubar_c+Delay_D)+W65/$W$5*X66)/(Rho_a+W65/$W$5) -> -384.23887 | Y65: =MAX(X65,-Delay_D/Rho_a) -> -335.74588 | Z65: =IF(V65<Floor_F,MAX((-(Cost_k*Ubar_c+Delay_D)*(1-EXP(-Rho_a*LN((Top_c-V65)/(Top_c-Floor_F))/Delta_c))/Rho_a+EXP(-Rho_a*LN((Top_c-V65)/(Top_c-Floor_F))/Delta_c)*(-Cost_k*Delta_c*Floor_F/Rho_a)),(-Delay_D/Rho_a)),(EXP(-Rho_a*LN(V65/Floor_F)/Delta_c)*(-Cost_k*Delta_c*Floor_F/Rho_a))) -> -335.74588 | AA65: =ABS(Y65-Z65) -> 0 | AC65: =30+45*$AD$5 -> 32.8125 | AD65: =Ubar_c-Delta_c*AC65 -> 6.8041609 | AE65: =(-(Cost_k*Ubar_c+Delay_D)+AD65/$AD$5*AE66)/(Rho_a+AD65/$AD$5) -> -399.21534 | AF65: =MAX(AE65,-Delay_D/Rho_a) -> -335.74588 | AG65: =IF(AC65<Floor_F,MAX((-(Cost_k*Ubar_c+Delay_D)*(1-EXP(-Rho_a*LN((Top_c-AC65)/(Top_c-Floor_F))/Delta_c))/Rho_a+EXP(-Rho_a*LN((Top_c-AC65)/(Top_c-Floor_F))/Delta_c)*(-Cost_k*Delta_c*Floor_F/Rho_a)),(-Delay_D/Rho_a)),(EXP(-Rho_a*LN(AC65/Floor_F)/Delta_c)*(-Cost_k*Delta_c*Floor_F/Rho_a))) -> -335.74588 | AH65: =ABS(AF65-AG65) -> 0
A66: =30+46*$B$5 -> 76 | B66: =-Delta_c*A66 -> -7.6966136 | D66: =(-B66/$B$5*D65)/(Rho_a-B66/$B$5) -> -173.20055 | E66: =IF(A66<Floor_F,MAX((-(Cost_k*Ubar_c+Delay_D)*(1-EXP(-Rho_a*LN((Top_c-A66)/(Top_c-Floor_F))/Delta_c))/Rho_a+EXP(-Rho_a*LN((Top_c-A66)/(Top_c-Floor_F))/Delta_c)*(-Cost_k*Delta_c*Floor_F/Rho_a)),(-Delay_D/Rho_a)),(EXP(-Rho_a*LN(A66/Floor_F)/Delta_c)*(-Cost_k*Delta_c*Floor_F/Rho_a))) -> -172.41928 | F66: =ABS(D66-E66) -> 0.78126929 | H66: =30+46*$I$5 -> 53 | I66: =Ubar_c-Delta_c*H66 -> 4.7597479 | J66: =(-(Cost_k*Ubar_c+Delay_D)+I66/$I$5*J67)/(Rho_a+I66/$I$5) -> -254.67585 | K66: =MAX(J66,-Delay_D/Rho_a) -> -254.67585 | L66: =IF(H66<Floor_F,MAX((-(Cost_k*Ubar_c+Delay_D)*(1-EXP(-Rho_a*LN((Top_c-H66)/(Top_c-Floor_F))/Delta_c))/Rho_a+EXP(-Rho_a*LN((Top_c-H66)/(Top_c-Floor_F))/Delta_c)*(-Cost_k*Delta_c*Floor_F/Rho_a)),(-Delay_D/Rho_a)),(EXP(-Rho_a*LN(H66/Floor_F)/Delta_c)*(-Cost_k*Delta_c*Floor_F/Rho_a))) -> -254.89212 | M66: =ABS(K66-L66) -> 0.21626566 | O66: =30+46*$P$5 -> 41.5 | P66: =Ubar_c-Delta_c*O66 -> 5.9243671 | Q66: =(-(Cost_k*Ubar_c+Delay_D)+P66/$P$5*Q67)/(Rho_a+P66/$P$5) -> -348.58659 | R66: =MAX(Q66,-Delay_D/Rho_a) -> -335.74588 | S66: =IF(O66<Floor_F,MAX((-(Cost_k*Ubar_c+Delay_D)*(1-EXP(-Rho_a*LN((Top_c-O66)/(Top_c-Floor_F))/Delta_c))/Rho_a+EXP(-Rho_a*LN((Top_c-O66)/(Top_c-Floor_F))/Delta_c)*(-Cost_k*Delta_c*Floor_F/Rho_a)),(-Delay_D/Rho_a)),(EXP(-Rho_a*LN(O66/Floor_F)/Delta_c)*(-Cost_k*Delta_c*Floor_F/Rho_a))) -> -335.74588 | T66: =ABS(R66-S66) -> 0 | V66: =30+46*$W$5 -> 35.75 | W66: =Ubar_c-Delta_c*V66 -> 6.5066767 | X66: =(-(Cost_k*Ubar_c+Delay_D)+W66/$W$5*X67)/(Rho_a+W66/$W$5) -> -383.55079 | Y66: =MAX(X66,-Delay_D/Rho_a) -> -335.74588 | Z66: =IF(V66<Floor_F,MAX((-(Cost_k*Ubar_c+Delay_D)*(1-EXP(-Rho_a*LN((Top_c-V66)/(Top_c-Floor_F))/Delta_c))/Rho_a+EXP(-Rho_a*LN((Top_c-V66)/(Top_c-Floor_F))/Delta_c)*(-Cost_k*Delta_c*Floor_F/Rho_a)),(-Delay_D/Rho_a)),(EXP(-Rho_a*LN(V66/Floor_F)/Delta_c)*(-Cost_k*Delta_c*Floor_F/Rho_a))) -> -335.74588 | AA66: =ABS(Y66-Z66) -> 0 | AC66: =30+46*$AD$5 -> 32.875 | AD66: =Ubar_c-Delta_c*AC66 -> 6.7978314 | AE66: =(-(Cost_k*Ubar_c+Delay_D)+AD66/$AD$5*AE67)/(Rho_a+AD66/$AD$5) -> -398.89882 | AF66: =MAX(AE66,-Delay_D/Rho_a) -> -335.74588 | AG66: =IF(AC66<Floor_F,MAX((-(Cost_k*Ubar_c+Delay_D)*(1-EXP(-Rho_a*LN((Top_c-AC66)/(Top_c-Floor_F))/Delta_c))/Rho_a+EXP(-Rho_a*LN((Top_c-AC66)/(Top_c-Floor_F))/Delta_c)*(-Cost_k*Delta_c*Floor_F/Rho_a)),(-Delay_D/Rho_a)),(EXP(-Rho_a*LN(AC66/Floor_F)/Delta_c)*(-Cost_k*Delta_c*Floor_F/Rho_a))) -> -335.74588 | AH66: =ABS(AF66-AG66) -> 0
A67: =30+47*$B$5 -> 77 | B67: =-Delta_c*A67 -> -7.7978849 | D67: =(-B67/$B$5*D66)/(Rho_a-B67/$B$5) -> -171.10916 | E67: =IF(A67<Floor_F,MAX((-(Cost_k*Ubar_c+Delay_D)*(1-EXP(-Rho_a*LN((Top_c-A67)/(Top_c-Floor_F))/Delta_c))/Rho_a+EXP(-Rho_a*LN((Top_c-A67)/(Top_c-Floor_F))/Delta_c)*(-Cost_k*Delta_c*Floor_F/Rho_a)),(-Delay_D/Rho_a)),(EXP(-Rho_a*LN(A67/Floor_F)/Delta_c)*(-Cost_k*Delta_c*Floor_F/Rho_a))) -> -170.31107 | F67: =ABS(D67-E67) -> 0.79809159 | H67: =30+47*$I$5 -> 53.5 | I67: =Ubar_c-Delta_c*H67 -> 4.7091123 | J67: =(-(Cost_k*Ubar_c+Delay_D)+I67/$I$5*J68)/(Rho_a+I67/$I$5) -> -249.60885 | K67: =MAX(J67,-Delay_D/Rho_a) -> -249.60885 | L67: =IF(H67<Floor_F,MAX((-(Cost_k*Ubar_c+Delay_D)*(1-EXP(-Rho_a*LN((Top_c-H67)/(Top_c-Floor_F))/Delta_c))/Rho_a+EXP(-Rho_a*LN((Top_c-H67)/(Top_c-Floor_F))/Delta_c)*(-Cost_k*Delta_c*Floor_F/Rho_a)),(-Delay_D/Rho_a)),(EXP(-Rho_a*LN(H67/Floor_F)/Delta_c)*(-Cost_k*Delta_c*Floor_F/Rho_a))) -> -249.77444 | M67: =ABS(K67-L67) -> 0.16558429 | O67: =30+47*$P$5 -> 41.75 | P67: =Ubar_c-Delta_c*O67 -> 5.8990493 | Q67: =(-(Cost_k*Ubar_c+Delay_D)+P67/$P$5*Q68)/(Rho_a+P67/$P$5) -> -346.92883 | R67: =MAX(Q67,-Delay_D/Rho_a) -> -335.74588 | S67: =IF(O67<Floor_F,MAX((-(Cost_k*Ubar_c+Delay_D)*(1-EXP(-Rho_a*LN((Top_c-O67)/(Top_c-Floor_F))/Delta_c))/Rho_a+EXP(-Rho_a*LN((Top_c-O67)/(Top_c-Floor_F))/Delta_c)*(-Cost_k*Delta_c*Floor_F/Rho_a)),(-Delay_D/Rho_a)),(EXP(-Rho_a*LN(O67/Floor_F)/Delta_c)*(-Cost_k*Delta_c*Floor_F/Rho_a))) -> -335.74588 | T67: =ABS(R67-S67) -> 0 | V67: =30+47*$W$5 -> 35.875 | W67: =Ubar_c-Delta_c*V67 -> 6.4940177 | X67: =(-(Cost_k*Ubar_c+Delay_D)+W67/$W$5*X68)/(Rho_a+W67/$W$5) -> -382.86011 | Y67: =MAX(X67,-Delay_D/Rho_a) -> -335.74588 | Z67: =IF(V67<Floor_F,MAX((-(Cost_k*Ubar_c+Delay_D)*(1-EXP(-Rho_a*LN((Top_c-V67)/(Top_c-Floor_F))/Delta_c))/Rho_a+EXP(-Rho_a*LN((Top_c-V67)/(Top_c-Floor_F))/Delta_c)*(-Cost_k*Delta_c*Floor_F/Rho_a)),(-Delay_D/Rho_a)),(EXP(-Rho_a*LN(V67/Floor_F)/Delta_c)*(-Cost_k*Delta_c*Floor_F/Rho_a))) -> -335.74588 | AA67: =ABS(Y67-Z67) -> 0 | AC67: =30+47*$AD$5 -> 32.9375 | AD67: =Ubar_c-Delta_c*AC67 -> 6.791502 | AE67: =(-(Cost_k*Ubar_c+Delay_D)+AD67/$AD$5*AE68)/(Rho_a+AD67/$AD$5) -> -398.58172 | AF67: =MAX(AE67,-Delay_D/Rho_a) -> -335.74588 | AG67: =IF(AC67<Floor_F,MAX((-(Cost_k*Ubar_c+Delay_D)*(1-EXP(-Rho_a*LN((Top_c-AC67)/(Top_c-Floor_F))/Delta_c))/Rho_a+EXP(-Rho_a*LN((Top_c-AC67)/(Top_c-Floor_F))/Delta_c)*(-Cost_k*Delta_c*Floor_F/Rho_a)),(-Delay_D/Rho_a)),(EXP(-Rho_a*LN(AC67/Floor_F)/Delta_c)*(-Cost_k*Delta_c*Floor_F/Rho_a))) -> -335.74588 | AH67: =ABS(AF67-AG67) -> 0
A68: =30+48*$B$5 -> 78 | B68: =-Delta_c*A68 -> -7.8991561 | D68: =(-B68/$B$5*D67)/(Rho_a-B68/$B$5) -> -169.06919 | E68: =IF(A68<Floor_F,MAX((-(Cost_k*Ubar_c+Delay_D)*(1-EXP(-Rho_a*LN((Top_c-A68)/(Top_c-Floor_F))/Delta_c))/Rho_a+EXP(-Rho_a*LN((Top_c-A68)/(Top_c-Floor_F))/Delta_c)*(-Cost_k*Delta_c*Floor_F/Rho_a)),(-Delay_D/Rho_a)),(EXP(-Rho_a*LN(A68/Floor_F)/Delta_c)*(-Cost_k*Delta_c*Floor_F/Rho_a))) -> -168.25534 | F68: =ABS(D68-E68) -> 0.8138548 | H68: =30+48*$I$5 -> 54 | I68: =Ubar_c-Delta_c*H68 -> 4.6584767 | J68: =(-(Cost_k*Ubar_c+Delay_D)+I68/$I$5*J69)/(Rho_a+I68/$I$5) -> -244.43609 | K68: =MAX(J68,-Delay_D/Rho_a) -> -244.43609 | L68: =IF(H68<Floor_F,MAX((-(Cost_k*Ubar_c+Delay_D)*(1-EXP(-Rho_a*LN((Top_c-H68)/(Top_c-Floor_F))/Delta_c))/Rho_a+EXP(-Rho_a*LN((Top_c-H68)/(Top_c-Floor_F))/Delta_c)*(-Cost_k*Delta_c*Floor_F/Rho_a)),(-Delay_D/Rho_a)),(EXP(-Rho_a*LN(H68/Floor_F)/Delta_c)*(-Cost_k*Delta_c*Floor_F/Rho_a))) -> -244.54881 | M68: =ABS(K68-L68) -> 0.11271836 | O68: =30+48*$P$5 -> 42 | P68: =Ubar_c-Delta_c*O68 -> 5.8737315 | Q68: =(-(Cost_k*Ubar_c+Delay_D)+P68/$P$5*Q69)/(Rho_a+P68/$P$5) -> -345.25727 | R68: =MAX(Q68,-Delay_D/Rho_a) -> -335.74588 | S68: =IF(O68<Floor_F,MAX((-(Cost_k*Ubar_c+Delay_D)*(1-EXP(-Rho_a*LN((Top_c-O68)/(Top_c-Floor_F))/Delta_c))/Rho_a+EXP(-Rho_a*LN((Top_c-O68)/(Top_c-Floor_F))/Delta_c)*(-Cost_k*Delta_c*Floor_F/Rho_a)),(-Delay_D/Rho_a)),(EXP(-Rho_a*LN(O68/Floor_F)/Delta_c)*(-Cost_k*Delta_c*Floor_F/Rho_a))) -> -335.74588 | T68: =ABS(R68-S68) -> 0 | V68: =30+48*$W$5 -> 36 | W68: =Ubar_c-Delta_c*V68 -> 6.4813588 | X68: =(-(Cost_k*Ubar_c+Delay_D)+W68/$W$5*X69)/(Rho_a+W68/$W$5) -> -382.16681 | Y68: =MAX(X68,-Delay_D/Rho_a) -> -335.74588 | Z68: =IF(V68<Floor_F,MAX((-(Cost_k*Ubar_c+Delay_D)*(1-EXP(-Rho_a*LN((Top_c-V68)/(Top_c-Floor_F))/Delta_c))/Rho_a+EXP(-Rho_a*LN((Top_c-V68)/(Top_c-Floor_F))/Delta_c)*(-Cost_k*Delta_c*Floor_F/Rho_a)),(-Delay_D/Rho_a)),(EXP(-Rho_a*LN(V68/Floor_F)/Delta_c)*(-Cost_k*Delta_c*Floor_F/Rho_a))) -> -335.74588 | AA68: =ABS(Y68-Z68) -> 0 | AC68: =30+48*$AD$5 -> 33 | AD68: =Ubar_c-Delta_c*AC68 -> 6.7851725 | AE68: =(-(Cost_k*Ubar_c+Delay_D)+AD68/$AD$5*AE69)/(Rho_a+AD68/$AD$5) -> -398.26405 | AF68: =MAX(AE68,-Delay_D/Rho_a) -> -335.74588 | AG68: =IF(AC68<Floor_F,MAX((-(Cost_k*Ubar_c+Delay_D)*(1-EXP(-Rho_a*LN((Top_c-AC68)/(Top_c-Floor_F))/Delta_c))/Rho_a+EXP(-Rho_a*LN((Top_c-AC68)/(Top_c-Floor_F))/Delta_c)*(-Cost_k*Delta_c*Floor_F/Rho_a)),(-Delay_D/Rho_a)),(EXP(-Rho_a*LN(AC68/Floor_F)/Delta_c)*(-Cost_k*Delta_c*Floor_F/Rho_a))) -> -335.74588 | AH68: =ABS(AF68-AG68) -> 0
A69: =30+49*$B$5 -> 79 | B69: =-Delta_c*A69 -> -8.0004273 | D69: =(-B69/$B$5*D68)/(Rho_a-B69/$B$5) -> -167.07876 | E69: =IF(A69<Floor_F,MAX((-(Cost_k*Ubar_c+Delay_D)*(1-EXP(-Rho_a*LN((Top_c-A69)/(Top_c-Floor_F))/Delta_c))/Rho_a+EXP(-Rho_a*LN((Top_c-A69)/(Top_c-Floor_F))/Delta_c)*(-Cost_k*Delta_c*Floor_F/Rho_a)),(-Delay_D/Rho_a)),(EXP(-Rho_a*LN(A69/Floor_F)/Delta_c)*(-Cost_k*Delta_c*Floor_F/Rho_a))) -> -166.25014 | F69: =ABS(D69-E69) -> 0.82862163 | H69: =30+49*$I$5 -> 54.5 | I69: =Ubar_c-Delta_c*H69 -> 4.6078411 | J69: =(-(Cost_k*Ubar_c+Delay_D)+I69/$I$5*J70)/(Rho_a+I69/$I$5) -> -239.15419 | K69: =MAX(J69,-Delay_D/Rho_a) -> -239.15419 | L69: =IF(H69<Floor_F,MAX((-(Cost_k*Ubar_c+Delay_D)*(1-EXP(-Rho_a*LN((Top_c-H69)/(Top_c-Floor_F))/Delta_c))/Rho_a+EXP(-Rho_a*LN((Top_c-H69)/(Top_c-Floor_F))/Delta_c)*(-Cost_k*Delta_c*Floor_F/Rho_a)),(-Delay_D/Rho_a)),(EXP(-Rho_a*LN(H69/Floor_F)/Delta_c)*(-Cost_k*Delta_c*Floor_F/Rho_a))) -> -239.21175 | M69: =ABS(K69-L69) -> 0.057561228 | O69: =30+49*$P$5 -> 42.25 | P69: =Ubar_c-Delta_c*O69 -> 5.8484136 | Q69: =(-(Cost_k*Ubar_c+Delay_D)+P69/$P$5*Q70)/(Rho_a+P69/$P$5) -> -343.57171 | R69: =MAX(Q69,-Delay_D/Rho_a) -> -335.74588 | S69: =IF(O69<Floor_F,MAX((-(Cost_k*Ubar_c+Delay_D)*(1-EXP(-Rho_a*LN((Top_c-O69)/(Top_c-Floor_F))/Delta_c))/Rho_a+EXP(-Rho_a*LN((Top_c-O69)/(Top_c-Floor_F))/Delta_c)*(-Cost_k*Delta_c*Floor_F/Rho_a)),(-Delay_D/Rho_a)),(EXP(-Rho_a*LN(O69/Floor_F)/Delta_c)*(-Cost_k*Delta_c*Floor_F/Rho_a))) -> -335.74588 | T69: =ABS(R69-S69) -> 0 | V69: =30+49*$W$5 -> 36.125 | W69: =Ubar_c-Delta_c*V69 -> 6.4686999 | X69: =(-(Cost_k*Ubar_c+Delay_D)+W69/$W$5*X70)/(Rho_a+W69/$W$5) -> -381.47089 | Y69: =MAX(X69,-Delay_D/Rho_a) -> -335.74588 | Z69: =IF(V69<Floor_F,MAX((-(Cost_k*Ubar_c+Delay_D)*(1-EXP(-Rho_a*LN((Top_c-V69)/(Top_c-Floor_F))/Delta_c))/Rho_a+EXP(-Rho_a*LN((Top_c-V69)/(Top_c-Floor_F))/Delta_c)*(-Cost_k*Delta_c*Floor_F/Rho_a)),(-Delay_D/Rho_a)),(EXP(-Rho_a*LN(V69/Floor_F)/Delta_c)*(-Cost_k*Delta_c*Floor_F/Rho_a))) -> -335.74588 | AA69: =ABS(Y69-Z69) -> 0 | AC69: =30+49*$AD$5 -> 33.0625 | AD69: =Ubar_c-Delta_c*AC69 -> 6.7788431 | AE69: =(-(Cost_k*Ubar_c+Delay_D)+AD69/$AD$5*AE70)/(Rho_a+AD69/$AD$5) -> -397.9458 | AF69: =MAX(AE69,-Delay_D/Rho_a) -> -335.74588 | AG69: =IF(AC69<Floor_F,MAX((-(Cost_k*Ubar_c+Delay_D)*(1-EXP(-Rho_a*LN((Top_c-AC69)/(Top_c-Floor_F))/Delta_c))/Rho_a+EXP(-Rho_a*LN((Top_c-AC69)/(Top_c-Floor_F))/Delta_c)*(-Cost_k*Delta_c*Floor_F/Rho_a)),(-Delay_D/Rho_a)),(EXP(-Rho_a*LN(AC69/Floor_F)/Delta_c)*(-Cost_k*Delta_c*Floor_F/Rho_a))) -> -335.74588 | AH69: =ABS(AF69-AG69) -> 0
A70: =30+50*$B$5 -> 80 | B70: =-Delta_c*A70 -> -8.1016986 | D70: =(-B70/$B$5*D69)/(Rho_a-B70/$B$5) -> -165.13606 | E70: =IF(A70<Floor_F,MAX((-(Cost_k*Ubar_c+Delay_D)*(1-EXP(-Rho_a*LN((Top_c-A70)/(Top_c-Floor_F))/Delta_c))/Rho_a+EXP(-Rho_a*LN((Top_c-A70)/(Top_c-Floor_F))/Delta_c)*(-Cost_k*Delta_c*Floor_F/Rho_a)),(-Delay_D/Rho_a)),(EXP(-Rho_a*LN(A70/Floor_F)/Delta_c)*(-Cost_k*Delta_c*Floor_F/Rho_a))) -> -164.29361 | F70: =ABS(D70-E70) -> 0.84245058 | H70: =30+50*$I$5 -> 55 | I70: 0 | J70: =-Cost_k*Delta_c*Floor_F/Rho_a -> -233.75962 | K70: =J70 -> -233.75962 | L70: =IF(H70<Floor_F,MAX((-(Cost_k*Ubar_c+Delay_D)*(1-EXP(-Rho_a*LN((Top_c-H70)/(Top_c-Floor_F))/Delta_c))/Rho_a+EXP(-Rho_a*LN((Top_c-H70)/(Top_c-Floor_F))/Delta_c)*(-Cost_k*Delta_c*Floor_F/Rho_a)),(-Delay_D/Rho_a)),(EXP(-Rho_a*LN(H70/Floor_F)/Delta_c)*(-Cost_k*Delta_c*Floor_F/Rho_a))) -> -233.75962 | M70: =ABS(K70-L70) -> 0 | O70: =30+50*$P$5 -> 42.5 | P70: =Ubar_c-Delta_c*O70 -> 5.8230958 | Q70: =(-(Cost_k*Ubar_c+Delay_D)+P70/$P$5*Q71)/(Rho_a+P70/$P$5) -> -341.87199 | R70: =MAX(Q70,-Delay_D/Rho_a) -> -335.74588 | S70: =IF(O70<Floor_F,MAX((-(Cost_k*Ubar_c+Delay_D)*(1-EXP(-Rho_a*LN((Top_c-O70)/(Top_c-Floor_F))/Delta_c))/Rho_a+EXP(-Rho_a*LN((Top_c-O70)/(Top_c-Floor_F))/Delta_c)*(-Cost_k*Delta_c*Floor_F/Rho_a)),(-Delay_D/Rho_a)),(EXP(-Rho_a*LN(O70/Floor_F)/Delta_c)*(-Cost_k*Delta_c*Floor_F/Rho_a))) -> -335.74588 | T70: =ABS(R70-S70) -> 0 | V70: =30+50*$W$5 -> 36.25 | W70: =Ubar_c-Delta_c*V70 -> 6.456041 | X70: =(-(Cost_k*Ubar_c+Delay_D)+W70/$W$5*X71)/(Rho_a+W70/$W$5) -> -380.77233 | Y70: =MAX(X70,-Delay_D/Rho_a) -> -335.74588 | Z70: =IF(V70<Floor_F,MAX((-(Cost_k*Ubar_c+Delay_D)*(1-EXP(-Rho_a*LN((Top_c-V70)/(Top_c-Floor_F))/Delta_c))/Rho_a+EXP(-Rho_a*LN((Top_c-V70)/(Top_c-Floor_F))/Delta_c)*(-Cost_k*Delta_c*Floor_F/Rho_a)),(-Delay_D/Rho_a)),(EXP(-Rho_a*LN(V70/Floor_F)/Delta_c)*(-Cost_k*Delta_c*Floor_F/Rho_a))) -> -335.74588 | AA70: =ABS(Y70-Z70) -> 0 | AC70: =30+50*$AD$5 -> 33.125 | AD70: =Ubar_c-Delta_c*AC70 -> 6.7725136 | AE70: =(-(Cost_k*Ubar_c+Delay_D)+AD70/$AD$5*AE71)/(Rho_a+AD70/$AD$5) -> -397.62697 | AF70: =MAX(AE70,-Delay_D/Rho_a) -> -335.74588 | AG70: =IF(AC70<Floor_F,MAX((-(Cost_k*Ubar_c+Delay_D)*(1-EXP(-Rho_a*LN((Top_c-AC70)/(Top_c-Floor_F))/Delta_c))/Rho_a+EXP(-Rho_a*LN((Top_c-AC70)/(Top_c-Floor_F))/Delta_c)*(-Cost_k*Delta_c*Floor_F/Rho_a)),(-Delay_D/Rho_a)),(EXP(-Rho_a*LN(AC70/Floor_F)/Delta_c)*(-Cost_k*Delta_c*Floor_F/Rho_a))) -> -335.74588 | AH70: =ABS(AF70-AG70) -> 0
H71: =30+51*$I$5 -> 55.5 | I71: =-Delta_c*H71 -> -5.6205534 | K71: =(-I71/$I$5*K70)/(Rho_a-I71/$I$5) -> -231.7943 | L71: =IF(H71<Floor_F,MAX((-(Cost_k*Ubar_c+Delay_D)*(1-EXP(-Rho_a*LN((Top_c-H71)/(Top_c-Floor_F))/Delta_c))/Rho_a+EXP(-Rho_a*LN((Top_c-H71)/(Top_c-Floor_F))/Delta_c)*(-Cost_k*Delta_c*Floor_F/Rho_a)),(-Delay_D/Rho_a)),(EXP(-Rho_a*LN(H71/Floor_F)/Delta_c)*(-Cost_k*Delta_c*Floor_F/Rho_a))) -> -231.77711 | M71: =ABS(K71-L71) -> 0.017190575 | O71: =30+51*$P$5 -> 42.75 | P71: =Ubar_c-Delta_c*O71 -> 5.797778 | Q71: =(-(Cost_k*Ubar_c+Delay_D)+P71/$P$5*Q72)/(Rho_a+P71/$P$5) -> -340.15793 | R71: =MAX(Q71,-Delay_D/Rho_a) -> -335.74588 | S71: =IF(O71<Floor_F,MAX((-(Cost_k*Ubar_c+Delay_D)*(1-EXP(-Rho_a*LN((Top_c-O71)/(Top_c-Floor_F))/Delta_c))/Rho_a+EXP(-Rho_a*LN((Top_c-O71)/(Top_c-Floor_F))/Delta_c)*(-Cost_k*Delta_c*Floor_F/Rho_a)),(-Delay_D/Rho_a)),(EXP(-Rho_a*LN(O71/Floor_F)/Delta_c)*(-Cost_k*Delta_c*Floor_F/Rho_a))) -> -335.74588 | T71: =ABS(R71-S71) -> 0 | V71: =30+51*$W$5 -> 36.375 | W71: =Ubar_c-Delta_c*V71 -> 6.4433821 | X71: =(-(Cost_k*Ubar_c+Delay_D)+W71/$W$5*X72)/(Rho_a+W71/$W$5) -> -380.07111 | Y71: =MAX(X71,-Delay_D/Rho_a) -> -335.74588 | Z71: =IF(V71<Floor_F,MAX((-(Cost_k*Ubar_c+Delay_D)*(1-EXP(-Rho_a*LN((Top_c-V71)/(Top_c-Floor_F))/Delta_c))/Rho_a+EXP(-Rho_a*LN((Top_c-V71)/(Top_c-Floor_F))/Delta_c)*(-Cost_k*Delta_c*Floor_F/Rho_a)),(-Delay_D/Rho_a)),(EXP(-Rho_a*LN(V71/Floor_F)/Delta_c)*(-Cost_k*Delta_c*Floor_F/Rho_a))) -> -335.74588 | AA71: =ABS(Y71-Z71) -> 0 | AC71: =30+51*$AD$5 -> 33.1875 | AD71: =Ubar_c-Delta_c*AC71 -> 6.7661842 | AE71: =(-(Cost_k*Ubar_c+Delay_D)+AD71/$AD$5*AE72)/(Rho_a+AD71/$AD$5) -> -397.30757 | AF71: =MAX(AE71,-Delay_D/Rho_a) -> -335.74588 | AG71: =IF(AC71<Floor_F,MAX((-(Cost_k*Ubar_c+Delay_D)*(1-EXP(-Rho_a*LN((Top_c-AC71)/(Top_c-Floor_F))/Delta_c))/Rho_a+EXP(-Rho_a*LN((Top_c-AC71)/(Top_c-Floor_F))/Delta_c)*(-Cost_k*Delta_c*Floor_F/Rho_a)),(-Delay_D/Rho_a)),(EXP(-Rho_a*LN(AC71/Floor_F)/Delta_c)*(-Cost_k*Delta_c*Floor_F/Rho_a))) -> -335.74588 | AH71: =ABS(AF71-AG71) -> 0
H72: =30+52*$I$5 -> 56 | I72: =-Delta_c*H72 -> -5.671189 | K72: =(-I72/$I$5*K71)/(Rho_a-I72/$I$5) -> -229.86276 | L72: =IF(H72<Floor_F,MAX((-(Cost_k*Ubar_c+Delay_D)*(1-EXP(-Rho_a*LN((Top_c-H72)/(Top_c-Floor_F))/Delta_c))/Rho_a+EXP(-Rho_a*LN((Top_c-H72)/(Top_c-Floor_F))/Delta_c)*(-Cost_k*Delta_c*Floor_F/Rho_a)),(-Delay_D/Rho_a)),(EXP(-Rho_a*LN(H72/Floor_F)/Delta_c)*(-Cost_k*Delta_c*Floor_F/Rho_a))) -> -229.82897 | M72: =ABS(K72-L72) -> 0.0337903 | O72: =30+52*$P$5 -> 43 | P72: =Ubar_c-Delta_c*O72 -> 5.7724602 | Q72: =(-(Cost_k*Ubar_c+Delay_D)+P72/$P$5*Q73)/(Rho_a+P72/$P$5) -> -338.42934 | R72: =MAX(Q72,-Delay_D/Rho_a) -> -335.74588 | S72: =IF(O72<Floor_F,MAX((-(Cost_k*Ubar_c+Delay_D)*(1-EXP(-Rho_a*LN((Top_c-O72)/(Top_c-Floor_F))/Delta_c))/Rho_a+EXP(-Rho_a*LN((Top_c-O72)/(Top_c-Floor_F))/Delta_c)*(-Cost_k*Delta_c*Floor_F/Rho_a)),(-Delay_D/Rho_a)),(EXP(-Rho_a*LN(O72/Floor_F)/Delta_c)*(-Cost_k*Delta_c*Floor_F/Rho_a))) -> -335.74588 | T72: =ABS(R72-S72) -> 0 | V72: =30+52*$W$5 -> 36.5 | W72: =Ubar_c-Delta_c*V72 -> 6.4307232 | X72: =(-(Cost_k*Ubar_c+Delay_D)+W72/$W$5*X73)/(Rho_a+W72/$W$5) -> -379.36721 | Y72: =MAX(X72,-Delay_D/Rho_a) -> -335.74588 | Z72: =IF(V72<Floor_F,MAX((-(Cost_k*Ubar_c+Delay_D)*(1-EXP(-Rho_a*LN((Top_c-V72)/(Top_c-Floor_F))/Delta_c))/Rho_a+EXP(-Rho_a*LN((Top_c-V72)/(Top_c-Floor_F))/Delta_c)*(-Cost_k*Delta_c*Floor_F/Rho_a)),(-Delay_D/Rho_a)),(EXP(-Rho_a*LN(V72/Floor_F)/Delta_c)*(-Cost_k*Delta_c*Floor_F/Rho_a))) -> -335.74588 | AA72: =ABS(Y72-Z72) -> 0 | AC72: =30+52*$AD$5 -> 33.25 | AD72: =Ubar_c-Delta_c*AC72 -> 6.7598547 | AE72: =(-(Cost_k*Ubar_c+Delay_D)+AD72/$AD$5*AE73)/(Rho_a+AD72/$AD$5) -> -396.98759 | AF72: =MAX(AE72,-Delay_D/Rho_a) -> -335.74588 | AG72: =IF(AC72<Floor_F,MAX((-(Cost_k*Ubar_c+Delay_D)*(1-EXP(-Rho_a*LN((Top_c-AC72)/(Top_c-Floor_F))/Delta_c))/Rho_a+EXP(-Rho_a*LN((Top_c-AC72)/(Top_c-Floor_F))/Delta_c)*(-Cost_k*Delta_c*Floor_F/Rho_a)),(-Delay_D/Rho_a)),(EXP(-Rho_a*LN(AC72/Floor_F)/Delta_c)*(-Cost_k*Delta_c*Floor_F/Rho_a))) -> -335.74588 | AH72: =ABS(AF72-AG72) -> 0
H73: =30+53*$I$5 -> 56.5 | I73: =-Delta_c*H73 -> -5.7218246 | K73: =(-I73/$I$5*K72)/(Rho_a-I73/$I$5) -> -227.96412 | L73: =IF(H73<Floor_F,MAX((-(Cost_k*Ubar_c+Delay_D)*(1-EXP(-Rho_a*LN((Top_c-H73)/(Top_c-Floor_F))/Delta_c))/Rho_a+EXP(-Rho_a*LN((Top_c-H73)/(Top_c-Floor_F))/Delta_c)*(-Cost_k*Delta_c*Floor_F/Rho_a)),(-Delay_D/Rho_a)),(EXP(-Rho_a*LN(H73/Floor_F)/Delta_c)*(-Cost_k*Delta_c*Floor_F/Rho_a))) -> -227.9143 | M73: =ABS(K73-L73) -> 0.049822049 | O73: =30+53*$P$5 -> 43.25 | P73: =Ubar_c-Delta_c*O73 -> 5.7471424 | Q73: =(-(Cost_k*Ubar_c+Delay_D)+P73/$P$5*Q74)/(Rho_a+P73/$P$5) -> -336.68603 | R73: =MAX(Q73,-Delay_D/Rho_a) -> -335.74588 | S73: =IF(O73<Floor_F,MAX((-(Cost_k*Ubar_c+Delay_D)*(1-EXP(-Rho_a*LN((Top_c-O73)/(Top_c-Floor_F))/Delta_c))/Rho_a+EXP(-Rho_a*LN((Top_c-O73)/(Top_c-Floor_F))/Delta_c)*(-Cost_k*Delta_c*Floor_F/Rho_a)),(-Delay_D/Rho_a)),(EXP(-Rho_a*LN(O73/Floor_F)/Delta_c)*(-Cost_k*Delta_c*Floor_F/Rho_a))) -> -335.74588 | T73: =ABS(R73-S73) -> 0 | V73: =30+53*$W$5 -> 36.625 | W73: =Ubar_c-Delta_c*V73 -> 6.4180643 | X73: =(-(Cost_k*Ubar_c+Delay_D)+W73/$W$5*X74)/(Rho_a+W73/$W$5) -> -378.66062 | Y73: =MAX(X73,-Delay_D/Rho_a) -> -335.74588 | Z73: =IF(V73<Floor_F,MAX((-(Cost_k*Ubar_c+Delay_D)*(1-EXP(-Rho_a*LN((Top_c-V73)/(Top_c-Floor_F))/Delta_c))/Rho_a+EXP(-Rho_a*LN((Top_c-V73)/(Top_c-Floor_F))/Delta_c)*(-Cost_k*Delta_c*Floor_F/Rho_a)),(-Delay_D/Rho_a)),(EXP(-Rho_a*LN(V73/Floor_F)/Delta_c)*(-Cost_k*Delta_c*Floor_F/Rho_a))) -> -335.74588 | AA73: =ABS(Y73-Z73) -> 0 | AC73: =30+53*$AD$5 -> 33.3125 | AD73: =Ubar_c-Delta_c*AC73 -> 6.7535253 | AE73: =(-(Cost_k*Ubar_c+Delay_D)+AD73/$AD$5*AE74)/(Rho_a+AD73/$AD$5) -> -396.66702 | AF73: =MAX(AE73,-Delay_D/Rho_a) -> -335.74588 | AG73: =IF(AC73<Floor_F,MAX((-(Cost_k*Ubar_c+Delay_D)*(1-EXP(-Rho_a*LN((Top_c-AC73)/(Top_c-Floor_F))/Delta_c))/Rho_a+EXP(-Rho_a*LN((Top_c-AC73)/(Top_c-Floor_F))/Delta_c)*(-Cost_k*Delta_c*Floor_F/Rho_a)),(-Delay_D/Rho_a)),(EXP(-Rho_a*LN(AC73/Floor_F)/Delta_c)*(-Cost_k*Delta_c*Floor_F/Rho_a))) -> -335.74588 | AH73: =ABS(AF73-AG73) -> 0
H74: =30+54*$I$5 -> 57 | I74: =-Delta_c*H74 -> -5.7724602 | K74: =(-I74/$I$5*K73)/(Rho_a-I74/$I$5) -> -226.09755 | L74: =IF(H74<Floor_F,MAX((-(Cost_k*Ubar_c+Delay_D)*(1-EXP(-Rho_a*LN((Top_c-H74)/(Top_c-Floor_F))/Delta_c))/Rho_a+EXP(-Rho_a*LN((Top_c-H74)/(Top_c-Floor_F))/Delta_c)*(-Cost_k*Delta_c*Floor_F/Rho_a)),(-Delay_D/Rho_a)),(EXP(-Rho_a*LN(H74/Floor_F)/Delta_c)*(-Cost_k*Delta_c*Floor_F/Rho_a))) -> -226.03225 | M74: =ABS(K74-L74) -> 0.065307651 | O74: =30+54*$P$5 -> 43.5 | P74: =Ubar_c-Delta_c*O74 -> 5.7218246 | Q74: =(-(Cost_k*Ubar_c+Delay_D)+P74/$P$5*Q75)/(Rho_a+P74/$P$5) -> -334.92781 | R74: =MAX(Q74,-Delay_D/Rho_a) -> -334.92781 | S74: =IF(O74<Floor_F,MAX((-(Cost_k*Ubar_c+Delay_D)*(1-EXP(-Rho_a*LN((Top_c-O74)/(Top_c-Floor_F))/Delta_c))/Rho_a+EXP(-Rho_a*LN((Top_c-O74)/(Top_c-Floor_F))/Delta_c)*(-Cost_k*Delta_c*Floor_F/Rho_a)),(-Delay_D/Rho_a)),(EXP(-Rho_a*LN(O74/Floor_F)/Delta_c)*(-Cost_k*Delta_c*Floor_F/Rho_a))) -> -335.36533 | T74: =ABS(R74-S74) -> 0.43752 | V74: =30+54*$W$5 -> 36.75 | W74: =Ubar_c-Delta_c*V74 -> 6.4054054 | X74: =(-(Cost_k*Ubar_c+Delay_D)+W74/$W$5*X75)/(Rho_a+W74/$W$5) -> -377.95133 | Y74: =MAX(X74,-Delay_D/Rho_a) -> -335.74588 | Z74: =IF(V74<Floor_F,MAX((-(Cost_k*Ubar_c+Delay_D)*(1-EXP(-Rho_a*LN((Top_c-V74)/(Top_c-Floor_F))/Delta_c))/Rho_a+EXP(-Rho_a*LN((Top_c-V74)/(Top_c-Floor_F))/Delta_c)*(-Cost_k*Delta_c*Floor_F/Rho_a)),(-Delay_D/Rho_a)),(EXP(-Rho_a*LN(V74/Floor_F)/Delta_c)*(-Cost_k*Delta_c*Floor_F/Rho_a))) -> -335.74588 | AA74: =ABS(Y74-Z74) -> 0 | AC74: =30+54*$AD$5 -> 33.375 | AD74: =Ubar_c-Delta_c*AC74 -> 6.7471958 | AE74: =(-(Cost_k*Ubar_c+Delay_D)+AD74/$AD$5*AE75)/(Rho_a+AD74/$AD$5) -> -396.34587 | AF74: =MAX(AE74,-Delay_D/Rho_a) -> -335.74588 | AG74: =IF(AC74<Floor_F,MAX((-(Cost_k*Ubar_c+Delay_D)*(1-EXP(-Rho_a*LN((Top_c-AC74)/(Top_c-Floor_F))/Delta_c))/Rho_a+EXP(-Rho_a*LN((Top_c-AC74)/(Top_c-Floor_F))/Delta_c)*(-Cost_k*Delta_c*Floor_F/Rho_a)),(-Delay_D/Rho_a)),(EXP(-Rho_a*LN(AC74/Floor_F)/Delta_c)*(-Cost_k*Delta_c*Floor_F/Rho_a))) -> -335.74588 | AH74: =ABS(AF74-AG74) -> 0
H75: =30+55*$I$5 -> 57.5 | I75: =-Delta_c*H75 -> -5.8230958 | K75: =(-I75/$I$5*K74)/(Rho_a-I75/$I$5) -> -224.26223 | L75: =IF(H75<Floor_F,MAX((-(Cost_k*Ubar_c+Delay_D)*(1-EXP(-Rho_a*LN((Top_c-H75)/(Top_c-Floor_F))/Delta_c))/Rho_a+EXP(-Rho_a*LN((Top_c-H75)/(Top_c-Floor_F))/Delta_c)*(-Cost_k*Delta_c*Floor_F/Rho_a)),(-Delay_D/Rho_a)),(EXP(-Rho_a*LN(H75/Floor_F)/Delta_c)*(-Cost_k*Delta_c*Floor_F/Rho_a))) -> -224.18197 | M75: =ABS(K75-L75) -> 0.080267946 | O75: =30+55*$P$5 -> 43.75 | P75: =Ubar_c-Delta_c*O75 -> 5.6965068 | Q75: =(-(Cost_k*Ubar_c+Delay_D)+P75/$P$5*Q76)/(Rho_a+P75/$P$5) -> -333.15449 | R75: =MAX(Q75,-Delay_D/Rho_a) -> -333.15449 | S75: =IF(O75<Floor_F,MAX((-(Cost_k*Ubar_c+Delay_D)*(1-EXP(-Rho_a*LN((Top_c-O75)/(Top_c-Floor_F))/Delta_c))/Rho_a+EXP(-Rho_a*LN((Top_c-O75)/(Top_c-Floor_F))/Delta_c)*(-Cost_k*Delta_c*Floor_F/Rho_a)),(-Delay_D/Rho_a)),(EXP(-Rho_a*LN(O75/Floor_F)/Delta_c)*(-Cost_k*Delta_c*Floor_F/Rho_a))) -> -333.5862 | T75: =ABS(R75-S75) -> 0.43170105 | V75: =30+55*$W$5 -> 36.875 | W75: =Ubar_c-Delta_c*V75 -> 6.3927465 | X75: =(-(Cost_k*Ubar_c+Delay_D)+W75/$W$5*X76)/(Rho_a+W75/$W$5) -> -377.23931 | Y75: =MAX(X75,-Delay_D/Rho_a) -> -335.74588 | Z75: =IF(V75<Floor_F,MAX((-(Cost_k*Ubar_c+Delay_D)*(1-EXP(-Rho_a*LN((Top_c-V75)/(Top_c-Floor_F))/Delta_c))/Rho_a+EXP(-Rho_a*LN((Top_c-V75)/(Top_c-Floor_F))/Delta_c)*(-Cost_k*Delta_c*Floor_F/Rho_a)),(-Delay_D/Rho_a)),(EXP(-Rho_a*LN(V75/Floor_F)/Delta_c)*(-Cost_k*Delta_c*Floor_F/Rho_a))) -> -335.74588 | AA75: =ABS(Y75-Z75) -> 0 | AC75: =30+55*$AD$5 -> 33.4375 | AD75: =Ubar_c-Delta_c*AC75 -> 6.7408664 | AE75: =(-(Cost_k*Ubar_c+Delay_D)+AD75/$AD$5*AE76)/(Rho_a+AD75/$AD$5) -> -396.02414 | AF75: =MAX(AE75,-Delay_D/Rho_a) -> -335.74588 | AG75: =IF(AC75<Floor_F,MAX((-(Cost_k*Ubar_c+Delay_D)*(1-EXP(-Rho_a*LN((Top_c-AC75)/(Top_c-Floor_F))/Delta_c))/Rho_a+EXP(-Rho_a*LN((Top_c-AC75)/(Top_c-Floor_F))/Delta_c)*(-Cost_k*Delta_c*Floor_F/Rho_a)),(-Delay_D/Rho_a)),(EXP(-Rho_a*LN(AC75/Floor_F)/Delta_c)*(-Cost_k*Delta_c*Floor_F/Rho_a))) -> -335.74588 | AH75: =ABS(AF75-AG75) -> 0
