Workbook

Sheet README
B1: DCT Laboratory — Vol II, Ch 6: Optimal Control of Enterprise Systems
B2: Seed 26206 · Companion to DCT_V2_Ch06_Lab.ipynb and AXIOM Lab 2.6 (module AXIOM-06). Money in $ million.
B4: Worked Example 6.1, What Is Meridian's Engineering Team Worth?, with the book's declarations.
B5: Declarations: the inputs of Step 1. Simulate: the race, the drift and Volume I's schedules over three years (Figure 6.3(a)). Plans: Table 6.3.
B6: Hamiltonian: the part hiring moves at three prices (Figure 6.1(b)) and the switching function along each plan.
B7: Floor: the rent and the floor's price, the user cost. Prices: the value of a position and the price of a point, with finite differences (Figure 6.1(a)).
B8: Shooting: the starting prices by bisection. Transcription: the linear program's best plan on weekly and daily calendars, in closed form, beside the HiGHS solutions the notebook computes.
B9: Certify: c_a, the dynamic-programming condition, and the team's value. Compare: the declarations tested (Step 6).
B10: CapitalProblems: the chapter's two small capital problems, with a rising and a linear cost (Figure 6.2).
B11: The state simulator, the HiGHS solves and the random-plan test of the certificate run in the notebook.
B12: Reference_Values and Checks: the engine's numbers and a PASS/FAIL comparison with this workbook's formulas.
B14: LEGEND
... B18: Cross-sheet link: green.

Sheet Declarations
A1: Declarations (Worked Example 6.1, Step 1). Money in $ million; capability in points; time in years.
A3: Quantity | B3: Value | C3: Source
A4: Attrition a quarter | B4: 0.025 | C4: 2.5 percent a quarter (Volume I, Chapter 10)
A5: Attrition a year in continuous time, delta | B5: =-4*LN(1-B4) -> 0.10127123 | C5: delta = 4 ln(1/0.975) = 0.101
A6: Hiring cap a quarter (points) | B6: 2.5 | C6: At most 2.5 points a quarter (Volume I, Chapter 10)
A7: Volume I's ceiling (points) | B7: =B6/B4 -> 100 | C7: 2.5 / 0.025 = 100
A8: Hiring cap a year, u bar = ceiling x delta | B8: =B7*B5 -> 10.127123 | C8: 10.13 points a year: keeps Volume I's ceiling and its time to build exactly
A9: Cost of hiring and training a point, k | B9: 4 | C9: $4 million a point (Volume I, Worked Example 10.1)
A10: Capability floor of the digital build | B10: 55 | C10: The build runs from the first moment capability reaches 55; from then on capability stays at or above 55
A11: A quarter of delay | B11: 8 | C11: $8 million (Volume I, Chapter 15)
A12: Delay a year while the build waits, D | B12: =4*B11 -> 32 | C12: $32 million a year
A13: Hurdle rate a year | B13: 0.1 | C13: The board's 10 percent (Chapter 5)
A14: rho = ln(1 + hurdle rate) | B14: =LN(1+B13) -> 0.09531018 | C14: 9.5 percent in continuous time
A15: Capability with the engineering team | B15: 58 | C15: Team kept
A16: Capability without it | B16: 53 | C16: Team gone: below the floor
A17: Proceeds with the team kept | B17: 92 | C17: $92 million net
A18: Proceeds with the team gone | B18: 112 | C18: $112 million net
A19: rho + delta | B19: =B14+B5 -> 0.19658141 | C19: Off the floor the price of a point grows at 19.7 percent a year
A21: State: capability c, with dc/dt = u - delta c. Decision: hiring and training u in [0, u bar]. Value of a position: minus the present value of hiring and delay over an open horizon.

Sheet Simulate
A1: Simulate: Volume I's schedules and the race-and-rent plan (AXIOM Lab 2.6, step 1; Figure 6.3(a))
A3: Quantity | B3: Years | C3: Quarters | D3: Reading
A4: Race from 53 to the floor at the cap | B4: =LN((Cap_top-C_gone)/(Cap_top-Floor_F))/Delta_a -> 0.42939254 | C4: =4*B4 -> 1.7175702 | D4: Volume I's time to build: the build starts
A5: Drift from 58 to the floor, hiring nothing | B5: =LN(C_kept/Floor_F)/Delta_a -> 0.52443151 | C5: =4*B5 -> 2.097726 | D5: Then pay the rent
A6: Rebuild from 53 to 58 at the cap | B6: =LN((Cap_top-C_gone)/(Cap_top-C_kept))/Delta_a -> 1.1106608 | C6: =4*B6 -> 4.442643 | D6: Volume I's schedule
A7: Build starts, team kept | B7: 0 | C7: =4*B7 -> 0 | D7: Capability is above the floor at once
A8: Build starts, team gone (race or rebuild) | B8: =B4 -> 0.42939254 | C8: =4*B8 -> 1.7175702 | D8: Both pass 55 at the cap
A10: Years after the sale | B10: Team kept: drift, then the rent | C10: Team gone: race, then the rent | D10: Volume I: hold 58 | E10: Volume I: rebuild to 58 | F10: Hiring, team kept | G10: Hiring, team gone | H10: Hiring, hold 58 | I10: Hiring, rebuild
A11: 0 | B11: =IF(A11<Tau_drift,C_kept*EXP(-Delta_a*A11),Floor_F) -> 58 | C11: =IF(A11<Tau_race,Cap_top-(Cap_top-C_gone)*EXP(-Delta_a*A11),Floor_F) -> 53 | D11: =C_kept -> 58 | E11: =IF(A11<Time_58,Cap_top-(Cap_top-C_gone)*EXP(-Delta_a*A11),C_kept) -> 53 | F11: =IF(A11<Tau_drift,0,Delta_a*Floor_F) -> 0 | G11: =IF(A11<Tau_race,Ubar_a,Delta_a*Floor_F) -> 10.127123 | H11: =Delta_a*C_kept -> 5.8737315 | I11: =IF(A11<Time_58,Ubar_a,Delta_a*C_kept) -> 10.127123
A12: 0.05 | B12: =IF(A12<Tau_drift,C_kept*EXP(-Delta_a*A12),Floor_F) -> 57.707056 | C12: =IF(A12<Tau_race,Cap_top-(Cap_top-C_gone)*EXP(-Delta_a*A12),Floor_F) -> 53.237386 | D12: =C_kept -> 58 | E12: =IF(A12<Time_58,Cap_top-(Cap_top-C_gone)*EXP(-Delta_a*A12),C_kept) -> 53.237386 | F12: =IF(A12<Tau_drift,0,Delta_a*Floor_F) -> 0 | G12: =IF(A12<Tau_race,Ubar_a,Delta_a*Floor_F) -> 10.127123 | H12: =Delta_a*C_kept -> 5.8737315 | I12: =IF(A12<Time_58,Ubar_a,Delta_a*C_kept) -> 10.127123
A13: 0.1 | B13: =IF(A13<Tau_drift,C_kept*EXP(-Delta_a*A13),Floor_F) -> 57.415591 | C13: =IF(A13<Tau_race,Cap_top-(Cap_top-C_gone)*EXP(-Delta_a*A13),Floor_F) -> 53.473573 | D13: =C_kept -> 58 | E13: =IF(A13<Time_58,Cap_top-(Cap_top-C_gone)*EXP(-Delta_a*A13),C_kept) -> 53.473573 | F13: =IF(A13<Tau_drift,0,Delta_a*Floor_F) -> 0 | G13: =IF(A13<Tau_race,Ubar_a,Delta_a*Floor_F) -> 10.127123 | H13: =Delta_a*C_kept -> 5.8737315 | I13: =IF(A13<Time_58,Ubar_a,Delta_a*C_kept) -> 10.127123
A14: 0.15 | B14: =IF(A14<Tau_drift,C_kept*EXP(-Delta_a*A14),Floor_F) -> 57.125598 | C14: =IF(A14<Tau_race,Cap_top-(Cap_top-C_gone)*EXP(-Delta_a*A14),Floor_F) -> 53.708567 | D14: =C_kept -> 58 | E14: =IF(A14<Time_58,Cap_top-(Cap_top-C_gone)*EXP(-Delta_a*A14),C_kept) -> 53.708567 | F14: =IF(A14<Tau_drift,0,Delta_a*Floor_F) -> 0 | G14: =IF(A14<Tau_race,Ubar_a,Delta_a*Floor_F) -> 10.127123 | H14: =Delta_a*C_kept -> 5.8737315 | I14: =IF(A14<Time_58,Ubar_a,Delta_a*C_kept) -> 10.127123
A15: 0.2 | B15: =IF(A15<Tau_drift,C_kept*EXP(-Delta_a*A15),Floor_F) -> 56.837071 | C15: =IF(A15<Tau_race,Cap_top-(Cap_top-C_gone)*EXP(-Delta_a*A15),Floor_F) -> 53.942374 | D15: =C_kept -> 58 | E15: =IF(A15<Time_58,Cap_top-(Cap_top-C_gone)*EXP(-Delta_a*A15),C_kept) -> 53.942374 | F15: =IF(A15<Tau_drift,0,Delta_a*Floor_F) -> 0 | G15: =IF(A15<Tau_race,Ubar_a,Delta_a*Floor_F) -> 10.127123 | H15: =Delta_a*C_kept -> 5.8737315 | I15: =IF(A15<Time_58,Ubar_a,Delta_a*C_kept) -> 10.127123
A16: 0.25 | B16: =IF(A16<Tau_drift,C_kept*EXP(-Delta_a*A16),Floor_F) -> 56.55 | C16: =IF(A16<Tau_race,Cap_top-(Cap_top-C_gone)*EXP(-Delta_a*A16),Floor_F) -> 54.175 | D16: =C_kept -> 58 | E16: =IF(A16<Time_58,Cap_top-(Cap_top-C_gone)*EXP(-Delta_a*A16),C_kept) -> 54.175 | F16: =IF(A16<Tau_drift,0,Delta_a*Floor_F) -> 0 | G16: =IF(A16<Tau_race,Ubar_a,Delta_a*Floor_F) -> 10.127123 | H16: =Delta_a*C_kept -> 5.8737315 | I16: =IF(A16<Time_58,Ubar_a,Delta_a*C_kept) -> 10.127123
A17: 0.3 | B17: =IF(A17<Tau_drift,C_kept*EXP(-Delta_a*A17),Floor_F) -> 56.264379 | C17: =IF(A17<Tau_race,Cap_top-(Cap_top-C_gone)*EXP(-Delta_a*A17),Floor_F) -> 54.406451 | D17: =C_kept -> 58 | E17: =IF(A17<Time_58,Cap_top-(Cap_top-C_gone)*EXP(-Delta_a*A17),C_kept) -> 54.406451 | F17: =IF(A17<Tau_drift,0,Delta_a*Floor_F) -> 0 | G17: =IF(A17<Tau_race,Ubar_a,Delta_a*Floor_F) -> 10.127123 | H17: =Delta_a*C_kept -> 5.8737315 | I17: =IF(A17<Time_58,Ubar_a,Delta_a*C_kept) -> 10.127123
A18: 0.35 | B18: =IF(A18<Tau_drift,C_kept*EXP(-Delta_a*A18),Floor_F) -> 55.980201 | C18: =IF(A18<Tau_race,Cap_top-(Cap_top-C_gone)*EXP(-Delta_a*A18),Floor_F) -> 54.636733 | D18: =C_kept -> 58 | E18: =IF(A18<Time_58,Cap_top-(Cap_top-C_gone)*EXP(-Delta_a*A18),C_kept) -> 54.636733 | F18: =IF(A18<Tau_drift,0,Delta_a*Floor_F) -> 0 | G18: =IF(A18<Tau_race,Ubar_a,Delta_a*Floor_F) -> 10.127123 | H18: =Delta_a*C_kept -> 5.8737315 | I18: =IF(A18<Time_58,Ubar_a,Delta_a*C_kept) -> 10.127123
A19: 0.4 | B19: =IF(A19<Tau_drift,C_kept*EXP(-Delta_a*A19),Floor_F) -> 55.697459 | C19: =IF(A19<Tau_race,Cap_top-(Cap_top-C_gone)*EXP(-Delta_a*A19),Floor_F) -> 54.865853 | D19: =C_kept -> 58 | E19: =IF(A19<Time_58,Cap_top-(Cap_top-C_gone)*EXP(-Delta_a*A19),C_kept) -> 54.865853 | F19: =IF(A19<Tau_drift,0,Delta_a*Floor_F) -> 0 | G19: =IF(A19<Tau_race,Ubar_a,Delta_a*Floor_F) -> 10.127123 | H19: =Delta_a*C_kept -> 5.8737315 | I19: =IF(A19<Time_58,Ubar_a,Delta_a*C_kept) -> 10.127123
A20: 0.45 | B20: =IF(A20<Tau_drift,C_kept*EXP(-Delta_a*A20),Floor_F) -> 55.416144 | C20: =IF(A20<Tau_race,Cap_top-(Cap_top-C_gone)*EXP(-Delta_a*A20),Floor_F) -> 55 | D20: =C_kept -> 58 | E20: =IF(A20<Time_58,Cap_top-(Cap_top-C_gone)*EXP(-Delta_a*A20),C_kept) -> 55.093814 | F20: =IF(A20<Tau_drift,0,Delta_a*Floor_F) -> 0 | G20: =IF(A20<Tau_race,Ubar_a,Delta_a*Floor_F) -> 5.5699178 | H20: =Delta_a*C_kept -> 5.8737315 | I20: =IF(A20<Time_58,Ubar_a,Delta_a*C_kept) -> 10.127123
A21: 0.5 | B21: =IF(A21<Tau_drift,C_kept*EXP(-Delta_a*A21),Floor_F) -> 55.13625 | C21: =IF(A21<Tau_race,Cap_top-(Cap_top-C_gone)*EXP(-Delta_a*A21),Floor_F) -> 55 | D21: =C_kept -> 58 | E21: =IF(A21<Time_58,Cap_top-(Cap_top-C_gone)*EXP(-Delta_a*A21),C_kept) -> 55.320625 | F21: =IF(A21<Tau_drift,0,Delta_a*Floor_F) -> 0 | G21: =IF(A21<Tau_race,Ubar_a,Delta_a*Floor_F) -> 5.5699178 | H21: =Delta_a*C_kept -> 5.8737315 | I21: =IF(A21<Time_58,Ubar_a,Delta_a*C_kept) -> 10.127123
A22: 0.55 | B22: =IF(A22<Tau_drift,C_kept*EXP(-Delta_a*A22),Floor_F) -> 55 | C22: =IF(A22<Tau_race,Cap_top-(Cap_top-C_gone)*EXP(-Delta_a*A22),Floor_F) -> 55 | D22: =C_kept -> 58 | E22: =IF(A22<Time_58,Cap_top-(Cap_top-C_gone)*EXP(-Delta_a*A22),C_kept) -> 55.54629 | F22: =IF(A22<Tau_drift,0,Delta_a*Floor_F) -> 5.5699178 | G22: =IF(A22<Tau_race,Ubar_a,Delta_a*Floor_F) -> 5.5699178 | H22: =Delta_a*C_kept -> 5.8737315 | I22: =IF(A22<Time_58,Ubar_a,Delta_a*C_kept) -> 10.127123
... A71: 3 | B71: =IF(A71<Tau_drift,C_kept*EXP(-Delta_a*A71),Floor_F) -> 55 | C71: =IF(A71<Tau_race,Cap_top-(Cap_top-C_gone)*EXP(-Delta_a*A71),Floor_F) -> 55 | D71: =C_kept -> 58 | E71: =IF(A71<Time_58,Cap_top-(Cap_top-C_gone)*EXP(-Delta_a*A71),C_kept) -> 58 | F71: =IF(A71<Tau_drift,0,Delta_a*Floor_F) -> 5.5699178 | G71: =IF(A71<Tau_race,Ubar_a,Delta_a*Floor_F) -> 5.5699178 | H71: =Delta_a*C_kept -> 5.8737315 | I71: =IF(A71<Time_58,Ubar_a,Delta_a*C_kept) -> 5.8737315
A73: Capability at the cap: 100 - (100 - c0) e^(-delta t); with no hiring: c0 e^(-delta t); the rent delta x 55 holds the floor. Hiring in points a year.

Sheet Plans
A1: Table 6.3: the plans compared ($ million, present values at 10 percent over an open horizon)
A3: Plan | B3: Build starts (quarters) | C3: Hiring | D3: Delay | E3: Total cost | F3: Proceeds | G3: Proceeds less costs
A4: Team kept: drift to 55, pay the rent | B4: =4*Simulate!B7 -> 0 | C4: =EXP(-Rho_a*Tau_drift)*Cost_k*Delta_a*Floor_F/Rho_a -> 222.36266 | D4: 0 | E4: =C4+D4 -> 222.36266 | F4: =Proc_kept -> 92 | G4: =F4-E4 -> -130.36266
A5: Team gone: race to 55, pay the rent | B5: =4*Tau_race -> 1.7175702 | C5: =Cost_k*Ubar_a*(1-EXP(-Rho_a*Tau_race))/Rho_a+EXP(-Rho_a*Tau_race)*Cost_k*Delta_a*Floor_F/Rho_a -> 241.42893 | D5: =Delay_D*(1-EXP(-Rho_a*Tau_race))/Rho_a -> 13.463189 | E5: =C5+D5 -> 254.89212 | F5: =Proc_gone -> 112 | G5: =F5-E5 -> -142.89212
A6: Volume I's schedules
A7: Team kept: hold 58 | B7: 0 | C7: =Cost_k*Delta_a*C_kept/Rho_a -> 246.51014 | D7: 0 | E7: =C7+D7 -> 246.51014 | F7: =Proc_kept -> 92 | G7: =F7-E7 -> -154.51014
A8: Team gone: rebuild to 58, hold it | B8: =4*Tau_race -> 1.7175702 | C8: =Cost_k*Ubar_a*(1-EXP(-Rho_a*Time_58))/Rho_a+EXP(-Rho_a*Time_58)*Cost_k*Delta_a*C_kept/Rho_a -> 264.44066 | D8: =Delay_D*(1-EXP(-Rho_a*Tau_race))/Rho_a -> 13.463189 | E8: =C8+D8 -> 277.90385 | F8: =Proc_gone -> 112 | G8: =F8-E8 -> -165.90385
A10: Holding 58 costs more than the drift | B10: =C7-C4 -> 24.147483 | C10: Step 4: $24.1 million
A11: Rebuilding to 58 costs more than the race | B11: =E8-E5 -> 23.011732 | C11: Step 4: $23.0 million
A12: Keeping the team leads by (best plans) | B12: =G4-G5 -> 12.529461 | C12: Step 5: $12.5 million
A13: Keeping the team leads by (Volume I's schedules) | B13: =G7-G8 -> 11.393711 | C13: Online Appendix 6.B.3: 11.39
A14: The team: V(58) - V(53) | B14: =E5-E4 -> 32.529461 | C14: $32.5 million

Sheet Floor
A1: Price the floor: the rent and the user cost (Worked Example 6.1, Step 3; Proposition 6.3(ii))
A3: Quantity | B3: Value | C3: Reading
A4: The rent: points a year that hold capability at 55, delta x 55 | B4: =Delta_a*Floor_F -> 5.5699178 | C4: 5.57 points a year
A5: The rent in $ million a year | B5: =Cost_k*B4 -> 22.279671 | C5: $22.3 million
A6: V(55): paying the rent forever | B6: =-B5/Rho_a -> -233.75962 | C6: -$233.8 million
A7: Interest on a point's $4 million, rho k | B7: =Rho_a*Cost_k -> 0.38124072 | C7: $0.38 million a year
A8: Attrition of a point, delta k | B8: =Delta_a*Cost_k -> 0.40508493 | C8: $0.41 million a year
A9: The floor's price: the user cost (rho + delta) k | B9: =B7+B8 -> 0.78632565 | C9: $0.79 million a point a year
A10: Costate equation on the floor: (rho + delta) x 4 - 0 - the floor's price | B10: =Rho_delta*Cost_k-B9 -> 0 | C10: Zero: the price stays at $4 million
A11: Five points of margin over the floor, a year | B11: =5*B9 -> 3.9316282 | C11: $3.9 million a year
A13: On the floor the build runs and a point earns nothing directly; the floor's price is what one more point saves in rent (Proposition 6.3(ii): eta = (rho + delta) k less the marginal earnings).

Sheet Prices
A1: Price capability: the value of a position and the price of a point, checked by finite differences (AXIOM Lab 2.6, step 3; Theorem 6.1; Figure 6.1(a))
A3: Capability c | B3: V(c) | C3: Price m = V'(c) | D3: Central finite difference | E3: Tobin's q | F3: Reading
A4: 53 | B4: =IF(A4<Floor_F,-(Cost_k*Ubar_a+Delay_D)*(1-EXP(-Rho_a*LN((Cap_top-A4)/(Cap_top-Floor_F))/Delta_a))/Rho_a+EXP(-Rho_a*LN((Cap_top-A4)/(Cap_top-Floor_F))/Delta_a)*(-Cost_k*Delta_a*Floor_F/Rho_a),EXP(-Rho_a*LN(A4/Floor_F)/Delta_a)*(-Cost_k*Delta_a*Floor_F/Rho_a)) -> -254.89212 | C4: =IF(A4<Floor_F,EXP(-Rho_a*LN((Cap_top-A4)/(Cap_top-Floor_F))/Delta_a)*(Cost_k*Ubar_a+Delay_D+Rho_a*(-Cost_k*Delta_a*Floor_F/Rho_a))/(Ubar_a-Delta_a*A4),IF(A4=Floor_F,Cost_k,EXP(-Rho_a*LN(A4/Floor_F)/Delta_a)*(-Rho_a*(-Cost_k*Delta_a*Floor_F/Rho_a))/(Delta_a*A4))) -> 10.129671 | D4: =(IF((A4+0.0001)<Floor_F,-(Cost_k*Ubar_a+Delay_D)*(1-EXP(-Rho_a*LN((Cap_top-(A4+0.0001))/(Cap_top-Floor_F))/Delta_a))/Rho_a+EXP(-Rho_a*LN((Cap_top-(A4+0.0001))/(Cap_top-Floor_F))/Delta_a)*(-Cost_k*Delta_a*Floor_F/Rho_a),EXP(-Rho_a*LN((A4+0.0001)/Floor_F)/Delta_a)*(-Cost_k*Delta_a*Floor_F/Rho_a))-IF((A4-0.0001)<Floor_F,-(Cost_k*Ubar_a+Delay_D)*(1-EXP(-Rho_a*LN((Cap_top-(A4-0.0001))/(Cap_top-Floor_F))/Delta_a))/Rho_a+EXP(-Rho_a*LN((Cap_top-(A4-0.0001))/(Cap_top-Floor_F))/Delta_a)*(-Cost_k*Delta_a*Floor_F/Rho_a),EXP(-Rho_a*LN((A4-0.0001)/Floor_F)/Delta_a)*(-Cost_k*Delta_a*Floor_F/Rho_a)))/(2*0.0001) -> 10.129671 | E4: =C4/Cost_k -> 2.5324177 | F4: Team gone: hire at the cap
A5: 54 | B5: =IF(A5<Floor_F,-(Cost_k*Ubar_a+Delay_D)*(1-EXP(-Rho_a*LN((Cap_top-A5)/(Cap_top-Floor_F))/Delta_a))/Rho_a+EXP(-Rho_a*LN((Cap_top-A5)/(Cap_top-Floor_F))/Delta_a)*(-Cost_k*Delta_a*Floor_F/Rho_a),EXP(-Rho_a*LN(A5/Floor_F)/Delta_a)*(-Cost_k*Delta_a*Floor_F/Rho_a)) -> -244.54881 | C5: =IF(A5<Floor_F,EXP(-Rho_a*LN((Cap_top-A5)/(Cap_top-Floor_F))/Delta_a)*(Cost_k*Ubar_a+Delay_D+Rho_a*(-Cost_k*Delta_a*Floor_F/Rho_a))/(Ubar_a-Delta_a*A5),IF(A5=Floor_F,Cost_k,EXP(-Rho_a*LN(A5/Floor_F)/Delta_a)*(-Rho_a*(-Cost_k*Delta_a*Floor_F/Rho_a))/(Delta_a*A5))) -> 10.5615 | D5: =(IF((A5+0.0001)<Floor_F,-(Cost_k*Ubar_a+Delay_D)*(1-EXP(-Rho_a*LN((Cap_top-(A5+0.0001))/(Cap_top-Floor_F))/Delta_a))/Rho_a+EXP(-Rho_a*LN((Cap_top-(A5+0.0001))/(Cap_top-Floor_F))/Delta_a)*(-Cost_k*Delta_a*Floor_F/Rho_a),EXP(-Rho_a*LN((A5+0.0001)/Floor_F)/Delta_a)*(-Cost_k*Delta_a*Floor_F/Rho_a))-IF((A5-0.0001)<Floor_F,-(Cost_k*Ubar_a+Delay_D)*(1-EXP(-Rho_a*LN((Cap_top-(A5-0.0001))/(Cap_top-Floor_F))/Delta_a))/Rho_a+EXP(-Rho_a*LN((Cap_top-(A5-0.0001))/(Cap_top-Floor_F))/Delta_a)*(-Cost_k*Delta_a*Floor_F/Rho_a),EXP(-Rho_a*LN((A5-0.0001)/Floor_F)/Delta_a)*(-Cost_k*Delta_a*Floor_F/Rho_a)))/(2*0.0001) -> 10.5615 | E5: =C5/Cost_k -> 2.640375
A6: 54.999 | B6: =IF(A6<Floor_F,-(Cost_k*Ubar_a+Delay_D)*(1-EXP(-Rho_a*LN((Cap_top-A6)/(Cap_top-Floor_F))/Delta_a))/Rho_a+EXP(-Rho_a*LN((Cap_top-A6)/(Cap_top-Floor_F))/Delta_a)*(-Cost_k*Delta_a*Floor_F/Rho_a),EXP(-Rho_a*LN(A6/Floor_F)/Delta_a)*(-Cost_k*Delta_a*Floor_F/Rho_a)) -> -233.77064 | C6: =IF(A6<Floor_F,EXP(-Rho_a*LN((Cap_top-A6)/(Cap_top-Floor_F))/Delta_a)*(Cost_k*Ubar_a+Delay_D+Rho_a*(-Cost_k*Delta_a*Floor_F/Rho_a))/(Ubar_a-Delta_a*A6),IF(A6=Floor_F,Cost_k,EXP(-Rho_a*LN(A6/Floor_F)/Delta_a)*(-Rho_a*(-Cost_k*Delta_a*Floor_F/Rho_a))/(Delta_a*A6))) -> 11.021372 | D6: =(IF((A6+0.0001)<Floor_F,-(Cost_k*Ubar_a+Delay_D)*(1-EXP(-Rho_a*LN((Cap_top-(A6+0.0001))/(Cap_top-Floor_F))/Delta_a))/Rho_a+EXP(-Rho_a*LN((Cap_top-(A6+0.0001))/(Cap_top-Floor_F))/Delta_a)*(-Cost_k*Delta_a*Floor_F/Rho_a),EXP(-Rho_a*LN((A6+0.0001)/Floor_F)/Delta_a)*(-Cost_k*Delta_a*Floor_F/Rho_a))-IF((A6-0.0001)<Floor_F,-(Cost_k*Ubar_a+Delay_D)*(1-EXP(-Rho_a*LN((Cap_top-(A6-0.0001))/(Cap_top-Floor_F))/Delta_a))/Rho_a+EXP(-Rho_a*LN((Cap_top-(A6-0.0001))/(Cap_top-Floor_F))/Delta_a)*(-Cost_k*Delta_a*Floor_F/Rho_a),EXP(-Rho_a*LN((A6-0.0001)/Floor_F)/Delta_a)*(-Cost_k*Delta_a*Floor_F/Rho_a)))/(2*0.0001) -> 11.021372 | E6: =C6/Cost_k -> 2.7553429 | F6: Just below the floor
A7: 55 | B7: =IF(A7<Floor_F,-(Cost_k*Ubar_a+Delay_D)*(1-EXP(-Rho_a*LN((Cap_top-A7)/(Cap_top-Floor_F))/Delta_a))/Rho_a+EXP(-Rho_a*LN((Cap_top-A7)/(Cap_top-Floor_F))/Delta_a)*(-Cost_k*Delta_a*Floor_F/Rho_a),EXP(-Rho_a*LN(A7/Floor_F)/Delta_a)*(-Cost_k*Delta_a*Floor_F/Rho_a)) -> -233.75962 | C7: =IF(A7<Floor_F,EXP(-Rho_a*LN((Cap_top-A7)/(Cap_top-Floor_F))/Delta_a)*(Cost_k*Ubar_a+Delay_D+Rho_a*(-Cost_k*Delta_a*Floor_F/Rho_a))/(Ubar_a-Delta_a*A7),IF(A7=Floor_F,Cost_k,EXP(-Rho_a*LN(A7/Floor_F)/Delta_a)*(-Rho_a*(-Cost_k*Delta_a*Floor_F/Rho_a))/(Delta_a*A7))) -> 4 | E7: =C7/Cost_k -> 1 | F7: On the floor, build running: the cost
A8: 56 | B8: =IF(A8<Floor_F,-(Cost_k*Ubar_a+Delay_D)*(1-EXP(-Rho_a*LN((Cap_top-A8)/(Cap_top-Floor_F))/Delta_a))/Rho_a+EXP(-Rho_a*LN((Cap_top-A8)/(Cap_top-Floor_F))/Delta_a)*(-Cost_k*Delta_a*Floor_F/Rho_a),EXP(-Rho_a*LN(A8/Floor_F)/Delta_a)*(-Cost_k*Delta_a*Floor_F/Rho_a)) -> -229.82897 | C8: =IF(A8<Floor_F,EXP(-Rho_a*LN((Cap_top-A8)/(Cap_top-Floor_F))/Delta_a)*(Cost_k*Ubar_a+Delay_D+Rho_a*(-Cost_k*Delta_a*Floor_F/Rho_a))/(Ubar_a-Delta_a*A8),IF(A8=Floor_F,Cost_k,EXP(-Rho_a*LN(A8/Floor_F)/Delta_a)*(-Rho_a*(-Cost_k*Delta_a*Floor_F/Rho_a))/(Delta_a*A8))) -> 3.8625128 | D8: =(IF((A8+0.0001)<Floor_F,-(Cost_k*Ubar_a+Delay_D)*(1-EXP(-Rho_a*LN((Cap_top-(A8+0.0001))/(Cap_top-Floor_F))/Delta_a))/Rho_a+EXP(-Rho_a*LN((Cap_top-(A8+0.0001))/(Cap_top-Floor_F))/Delta_a)*(-Cost_k*Delta_a*Floor_F/Rho_a),EXP(-Rho_a*LN((A8+0.0001)/Floor_F)/Delta_a)*(-Cost_k*Delta_a*Floor_F/Rho_a))-IF((A8-0.0001)<Floor_F,-(Cost_k*Ubar_a+Delay_D)*(1-EXP(-Rho_a*LN((Cap_top-(A8-0.0001))/(Cap_top-Floor_F))/Delta_a))/Rho_a+EXP(-Rho_a*LN((Cap_top-(A8-0.0001))/(Cap_top-Floor_F))/Delta_a)*(-Cost_k*Delta_a*Floor_F/Rho_a),EXP(-Rho_a*LN((A8-0.0001)/Floor_F)/Delta_a)*(-Cost_k*Delta_a*Floor_F/Rho_a)))/(2*0.0001) -> 3.8625128 | E8: =C8/Cost_k -> 0.9656282
A9: 58 | B9: =IF(A9<Floor_F,-(Cost_k*Ubar_a+Delay_D)*(1-EXP(-Rho_a*LN((Cap_top-A9)/(Cap_top-Floor_F))/Delta_a))/Rho_a+EXP(-Rho_a*LN((Cap_top-A9)/(Cap_top-Floor_F))/Delta_a)*(-Cost_k*Delta_a*Floor_F/Rho_a),EXP(-Rho_a*LN(A9/Floor_F)/Delta_a)*(-Cost_k*Delta_a*Floor_F/Rho_a)) -> -222.36266 | C9: =IF(A9<Floor_F,EXP(-Rho_a*LN((Cap_top-A9)/(Cap_top-Floor_F))/Delta_a)*(Cost_k*Ubar_a+Delay_D+Rho_a*(-Cost_k*Delta_a*Floor_F/Rho_a))/(Ubar_a-Delta_a*A9),IF(A9=Floor_F,Cost_k,EXP(-Rho_a*LN(A9/Floor_F)/Delta_a)*(-Rho_a*(-Cost_k*Delta_a*Floor_F/Rho_a))/(Delta_a*A9))) -> 3.6081706 | D9: =(IF((A9+0.0001)<Floor_F,-(Cost_k*Ubar_a+Delay_D)*(1-EXP(-Rho_a*LN((Cap_top-(A9+0.0001))/(Cap_top-Floor_F))/Delta_a))/Rho_a+EXP(-Rho_a*LN((Cap_top-(A9+0.0001))/(Cap_top-Floor_F))/Delta_a)*(-Cost_k*Delta_a*Floor_F/Rho_a),EXP(-Rho_a*LN((A9+0.0001)/Floor_F)/Delta_a)*(-Cost_k*Delta_a*Floor_F/Rho_a))-IF((A9-0.0001)<Floor_F,-(Cost_k*Ubar_a+Delay_D)*(1-EXP(-Rho_a*LN((Cap_top-(A9-0.0001))/(Cap_top-Floor_F))/Delta_a))/Rho_a+EXP(-Rho_a*LN((Cap_top-(A9-0.0001))/(Cap_top-Floor_F))/Delta_a)*(-Cost_k*Delta_a*Floor_F/Rho_a),EXP(-Rho_a*LN((A9-0.0001)/Floor_F)/Delta_a)*(-Cost_k*Delta_a*Floor_F/Rho_a)))/(2*0.0001) -> 3.6081706 | E9: =C9/Cost_k -> 0.90204264 | F9: Team kept: hire nothing
A10: 60 | B10: =IF(A10<Floor_F,-(Cost_k*Ubar_a+Delay_D)*(1-EXP(-Rho_a*LN((Cap_top-A10)/(Cap_top-Floor_F))/Delta_a))/Rho_a+EXP(-Rho_a*LN((Cap_top-A10)/(Cap_top-Floor_F))/Delta_a)*(-Cost_k*Delta_a*Floor_F/Rho_a),EXP(-Rho_a*LN(A10/Floor_F)/Delta_a)*(-Cost_k*Delta_a*Floor_F/Rho_a)) -> -215.37994 | C10: =IF(A10<Floor_F,EXP(-Rho_a*LN((Cap_top-A10)/(Cap_top-Floor_F))/Delta_a)*(Cost_k*Ubar_a+Delay_D+Rho_a*(-Cost_k*Delta_a*Floor_F/Rho_a))/(Ubar_a-Delta_a*A10),IF(A10=Floor_F,Cost_k,EXP(-Rho_a*LN(A10/Floor_F)/Delta_a)*(-Rho_a*(-Cost_k*Delta_a*Floor_F/Rho_a))/(Delta_a*A10))) -> 3.3783698 | D10: =(IF((A10+0.0001)<Floor_F,-(Cost_k*Ubar_a+Delay_D)*(1-EXP(-Rho_a*LN((Cap_top-(A10+0.0001))/(Cap_top-Floor_F))/Delta_a))/Rho_a+EXP(-Rho_a*LN((Cap_top-(A10+0.0001))/(Cap_top-Floor_F))/Delta_a)*(-Cost_k*Delta_a*Floor_F/Rho_a),EXP(-Rho_a*LN((A10+0.0001)/Floor_F)/Delta_a)*(-Cost_k*Delta_a*Floor_F/Rho_a))-IF((A10-0.0001)<Floor_F,-(Cost_k*Ubar_a+Delay_D)*(1-EXP(-Rho_a*LN((Cap_top-(A10-0.0001))/(Cap_top-Floor_F))/Delta_a))/Rho_a+EXP(-Rho_a*LN((Cap_top-(A10-0.0001))/(Cap_top-Floor_F))/Delta_a)*(-Cost_k*Delta_a*Floor_F/Rho_a),EXP(-Rho_a*LN((A10-0.0001)/Floor_F)/Delta_a)*(-Cost_k*Delta_a*Floor_F/Rho_a)))/(2*0.0001) -> 3.3783698 | E10: =C10/Cost_k -> 0.84459246
A12: Price as capability reaches 55: the cost plus the delay a point saves, 4 + D/(u bar - 55 delta) | C12: =Cost_k+Delay_D/(Ubar_a-Delta_a*Floor_F) -> 11.021847
A13: Years sooner the build starts with one more point, 1/(u bar - 55 delta) | C13: =1/(Ubar_a-Delta_a*Floor_F) -> 0.21943272
A14: Price at 53 grown at rho + delta over the race | C14: =C4*EXP(Rho_delta*Tau_race) -> 11.021847
A15: Price at 58 grown at rho + delta over the drift | C15: =C9*EXP(Rho_delta*Tau_drift) -> 4
A16: The floor's price as earnings from the drift's end, discounted at rho + delta | C16: =Eta_floor*EXP(-Rho_delta*Tau_drift)/Rho_delta -> 3.6081706
A17: The team: V(58) - V(53) | C17: =B9-B4 -> 32.529461
A19: Theorem 6.1(iii): along a best plan the price is the slope of the best value. Off the floor it grows at rho + delta; it falls to the $4 million cost the moment the build starts.
A21: Capability today | B21: PV of hiring and delay, -V(c) | C21: Price m | D21: Central finite difference
A22: 50 | B22: =-IF(A22<Floor_F,-(Cost_k*Ubar_a+Delay_D)*(1-EXP(-Rho_a*LN((Cap_top-A22)/(Cap_top-Floor_F))/Delta_a))/Rho_a+EXP(-Rho_a*LN((Cap_top-A22)/(Cap_top-Floor_F))/Delta_a)*(-Cost_k*Delta_a*Floor_F/Rho_a),EXP(-Rho_a*LN(A22/Floor_F)/Delta_a)*(-Cost_k*Delta_a*Floor_F/Rho_a)) -> 283.50934 | C22: =IF(A22<Floor_F,EXP(-Rho_a*LN((Cap_top-A22)/(Cap_top-Floor_F))/Delta_a)*(Cost_k*Ubar_a+Delay_D+Rho_a*(-Cost_k*Delta_a*Floor_F/Rho_a))/(Ubar_a-Delta_a*A22),IF(A22=Floor_F,Cost_k,EXP(-Rho_a*LN(A22/Floor_F)/Delta_a)*(-Rho_a*(-Cost_k*Delta_a*Floor_F/Rho_a))/(Delta_a*A22))) -> 8.9832356 | D22: =(IF((A22+0.0001)<Floor_F,-(Cost_k*Ubar_a+Delay_D)*(1-EXP(-Rho_a*LN((Cap_top-(A22+0.0001))/(Cap_top-Floor_F))/Delta_a))/Rho_a+EXP(-Rho_a*LN((Cap_top-(A22+0.0001))/(Cap_top-Floor_F))/Delta_a)*(-Cost_k*Delta_a*Floor_F/Rho_a),EXP(-Rho_a*LN((A22+0.0001)/Floor_F)/Delta_a)*(-Cost_k*Delta_a*Floor_F/Rho_a))-IF((A22-0.0001)<Floor_F,-(Cost_k*Ubar_a+Delay_D)*(1-EXP(-Rho_a*LN((Cap_top-(A22-0.0001))/(Cap_top-Floor_F))/Delta_a))/Rho_a+EXP(-Rho_a*LN((Cap_top-(A22-0.0001))/(Cap_top-Floor_F))/Delta_a)*(-Cost_k*Delta_a*Floor_F/Rho_a),EXP(-Rho_a*LN((A22-0.0001)/Floor_F)/Delta_a)*(-Cost_k*Delta_a*Floor_F/Rho_a)))/(2*0.0001) -> 8.9832356
A23: 50.25 | B23: =-IF(A23<Floor_F,-(Cost_k*Ubar_a+Delay_D)*(1-EXP(-Rho_a*LN((Cap_top-A23)/(Cap_top-Floor_F))/Delta_a))/Rho_a+EXP(-Rho_a*LN((Cap_top-A23)/(Cap_top-Floor_F))/Delta_a)*(-Cost_k*Delta_a*Floor_F/Rho_a),EXP(-Rho_a*LN(A23/Floor_F)/Delta_a)*(-Cost_k*Delta_a*Floor_F/Rho_a)) -> 281.25258 | C23: =IF(A23<Floor_F,EXP(-Rho_a*LN((Cap_top-A23)/(Cap_top-Floor_F))/Delta_a)*(Cost_k*Ubar_a+Delay_D+Rho_a*(-Cost_k*Delta_a*Floor_F/Rho_a))/(Ubar_a-Delta_a*A23),IF(A23=Floor_F,Cost_k,EXP(-Rho_a*LN(A23/Floor_F)/Delta_a)*(-Rho_a*(-Cost_k*Delta_a*Floor_F/Rho_a))/(Delta_a*A23))) -> 9.0710694 | D23: =(IF((A23+0.0001)<Floor_F,-(Cost_k*Ubar_a+Delay_D)*(1-EXP(-Rho_a*LN((Cap_top-(A23+0.0001))/(Cap_top-Floor_F))/Delta_a))/Rho_a+EXP(-Rho_a*LN((Cap_top-(A23+0.0001))/(Cap_top-Floor_F))/Delta_a)*(-Cost_k*Delta_a*Floor_F/Rho_a),EXP(-Rho_a*LN((A23+0.0001)/Floor_F)/Delta_a)*(-Cost_k*Delta_a*Floor_F/Rho_a))-IF((A23-0.0001)<Floor_F,-(Cost_k*Ubar_a+Delay_D)*(1-EXP(-Rho_a*LN((Cap_top-(A23-0.0001))/(Cap_top-Floor_F))/Delta_a))/Rho_a+EXP(-Rho_a*LN((Cap_top-(A23-0.0001))/(Cap_top-Floor_F))/Delta_a)*(-Cost_k*Delta_a*Floor_F/Rho_a),EXP(-Rho_a*LN((A23-0.0001)/Floor_F)/Delta_a)*(-Cost_k*Delta_a*Floor_F/Rho_a)))/(2*0.0001) -> 9.0710694
A24: 50.5 | B24: =-IF(A24<Floor_F,-(Cost_k*Ubar_a+Delay_D)*(1-EXP(-Rho_a*LN((Cap_top-A24)/(Cap_top-Floor_F))/Delta_a))/Rho_a+EXP(-Rho_a*LN((Cap_top-A24)/(Cap_top-Floor_F))/Delta_a)*(-Cost_k*Delta_a*Floor_F/Rho_a),EXP(-Rho_a*LN(A24/Floor_F)/Delta_a)*(-Cost_k*Delta_a*Floor_F/Rho_a)) -> 278.97369 | C24: =IF(A24<Floor_F,EXP(-Rho_a*LN((Cap_top-A24)/(Cap_top-Floor_F))/Delta_a)*(Cost_k*Ubar_a+Delay_D+Rho_a*(-Cost_k*Delta_a*Floor_F/Rho_a))/(Ubar_a-Delta_a*A24),IF(A24=Floor_F,Cost_k,EXP(-Rho_a*LN(A24/Floor_F)/Delta_a)*(-Rho_a*(-Cost_k*Delta_a*Floor_F/Rho_a))/(Delta_a*A24))) -> 9.1602111 | D24: =(IF((A24+0.0001)<Floor_F,-(Cost_k*Ubar_a+Delay_D)*(1-EXP(-Rho_a*LN((Cap_top-(A24+0.0001))/(Cap_top-Floor_F))/Delta_a))/Rho_a+EXP(-Rho_a*LN((Cap_top-(A24+0.0001))/(Cap_top-Floor_F))/Delta_a)*(-Cost_k*Delta_a*Floor_F/Rho_a),EXP(-Rho_a*LN((A24+0.0001)/Floor_F)/Delta_a)*(-Cost_k*Delta_a*Floor_F/Rho_a))-IF((A24-0.0001)<Floor_F,-(Cost_k*Ubar_a+Delay_D)*(1-EXP(-Rho_a*LN((Cap_top-(A24-0.0001))/(Cap_top-Floor_F))/Delta_a))/Rho_a+EXP(-Rho_a*LN((Cap_top-(A24-0.0001))/(Cap_top-Floor_F))/Delta_a)*(-Cost_k*Delta_a*Floor_F/Rho_a),EXP(-Rho_a*LN((A24-0.0001)/Floor_F)/Delta_a)*(-Cost_k*Delta_a*Floor_F/Rho_a)))/(2*0.0001) -> 9.1602111
A25: 50.75 | B25: =-IF(A25<Floor_F,-(Cost_k*Ubar_a+Delay_D)*(1-EXP(-Rho_a*LN((Cap_top-A25)/(Cap_top-Floor_F))/Delta_a))/Rho_a+EXP(-Rho_a*LN((Cap_top-A25)/(Cap_top-Floor_F))/Delta_a)*(-Cost_k*Delta_a*Floor_F/Rho_a),EXP(-Rho_a*LN(A25/Floor_F)/Delta_a)*(-Cost_k*Delta_a*Floor_F/Rho_a)) -> 276.67236 | C25: =IF(A25<Floor_F,EXP(-Rho_a*LN((Cap_top-A25)/(Cap_top-Floor_F))/Delta_a)*(Cost_k*Ubar_a+Delay_D+Rho_a*(-Cost_k*Delta_a*Floor_F/Rho_a))/(Ubar_a-Delta_a*A25),IF(A25=Floor_F,Cost_k,EXP(-Rho_a*LN(A25/Floor_F)/Delta_a)*(-Rho_a*(-Cost_k*Delta_a*Floor_F/Rho_a))/(Delta_a*A25))) -> 9.2506867 | D25: =(IF((A25+0.0001)<Floor_F,-(Cost_k*Ubar_a+Delay_D)*(1-EXP(-Rho_a*LN((Cap_top-(A25+0.0001))/(Cap_top-Floor_F))/Delta_a))/Rho_a+EXP(-Rho_a*LN((Cap_top-(A25+0.0001))/(Cap_top-Floor_F))/Delta_a)*(-Cost_k*Delta_a*Floor_F/Rho_a),EXP(-Rho_a*LN((A25+0.0001)/Floor_F)/Delta_a)*(-Cost_k*Delta_a*Floor_F/Rho_a))-IF((A25-0.0001)<Floor_F,-(Cost_k*Ubar_a+Delay_D)*(1-EXP(-Rho_a*LN((Cap_top-(A25-0.0001))/(Cap_top-Floor_F))/Delta_a))/Rho_a+EXP(-Rho_a*LN((Cap_top-(A25-0.0001))/(Cap_top-Floor_F))/Delta_a)*(-Cost_k*Delta_a*Floor_F/Rho_a),EXP(-Rho_a*LN((A25-0.0001)/Floor_F)/Delta_a)*(-Cost_k*Delta_a*Floor_F/Rho_a)))/(2*0.0001) -> 9.2506867
A26: 51 | B26: =-IF(A26<Floor_F,-(Cost_k*Ubar_a+Delay_D)*(1-EXP(-Rho_a*LN((Cap_top-A26)/(Cap_top-Floor_F))/Delta_a))/Rho_a+EXP(-Rho_a*LN((Cap_top-A26)/(Cap_top-Floor_F))/Delta_a)*(-Cost_k*Delta_a*Floor_F/Rho_a),EXP(-Rho_a*LN(A26/Floor_F)/Delta_a)*(-Cost_k*Delta_a*Floor_F/Rho_a)) -> 274.34824 | C26: =IF(A26<Floor_F,EXP(-Rho_a*LN((Cap_top-A26)/(Cap_top-Floor_F))/Delta_a)*(Cost_k*Ubar_a+Delay_D+Rho_a*(-Cost_k*Delta_a*Floor_F/Rho_a))/(Ubar_a-Delta_a*A26),IF(A26=Floor_F,Cost_k,EXP(-Rho_a*LN(A26/Floor_F)/Delta_a)*(-Rho_a*(-Cost_k*Delta_a*Floor_F/Rho_a))/(Delta_a*A26))) -> 9.3425232 | D26: =(IF((A26+0.0001)<Floor_F,-(Cost_k*Ubar_a+Delay_D)*(1-EXP(-Rho_a*LN((Cap_top-(A26+0.0001))/(Cap_top-Floor_F))/Delta_a))/Rho_a+EXP(-Rho_a*LN((Cap_top-(A26+0.0001))/(Cap_top-Floor_F))/Delta_a)*(-Cost_k*Delta_a*Floor_F/Rho_a),EXP(-Rho_a*LN((A26+0.0001)/Floor_F)/Delta_a)*(-Cost_k*Delta_a*Floor_F/Rho_a))-IF((A26-0.0001)<Floor_F,-(Cost_k*Ubar_a+Delay_D)*(1-EXP(-Rho_a*LN((Cap_top-(A26-0.0001))/(Cap_top-Floor_F))/Delta_a))/Rho_a+EXP(-Rho_a*LN((Cap_top-(A26-0.0001))/(Cap_top-Floor_F))/Delta_a)*(-Cost_k*Delta_a*Floor_F/Rho_a),EXP(-Rho_a*LN((A26-0.0001)/Floor_F)/Delta_a)*(-Cost_k*Delta_a*Floor_F/Rho_a)))/(2*0.0001) -> 9.3425232
A27: 51.25 | B27: =-IF(A27<Floor_F,-(Cost_k*Ubar_a+Delay_D)*(1-EXP(-Rho_a*LN((Cap_top-A27)/(Cap_top-Floor_F))/Delta_a))/Rho_a+EXP(-Rho_a*LN((Cap_top-A27)/(Cap_top-Floor_F))/Delta_a)*(-Cost_k*Delta_a*Floor_F/Rho_a),EXP(-Rho_a*LN(A27/Floor_F)/Delta_a)*(-Cost_k*Delta_a*Floor_F/Rho_a)) -> 272.00098 | C27: =IF(A27<Floor_F,EXP(-Rho_a*LN((Cap_top-A27)/(Cap_top-Floor_F))/Delta_a)*(Cost_k*Ubar_a+Delay_D+Rho_a*(-Cost_k*Delta_a*Floor_F/Rho_a))/(Ubar_a-Delta_a*A27),IF(A27=Floor_F,Cost_k,EXP(-Rho_a*LN(A27/Floor_F)/Delta_a)*(-Rho_a*(-Cost_k*Delta_a*Floor_F/Rho_a))/(Delta_a*A27))) -> 9.4357483 | D27: =(IF((A27+0.0001)<Floor_F,-(Cost_k*Ubar_a+Delay_D)*(1-EXP(-Rho_a*LN((Cap_top-(A27+0.0001))/(Cap_top-Floor_F))/Delta_a))/Rho_a+EXP(-Rho_a*LN((Cap_top-(A27+0.0001))/(Cap_top-Floor_F))/Delta_a)*(-Cost_k*Delta_a*Floor_F/Rho_a),EXP(-Rho_a*LN((A27+0.0001)/Floor_F)/Delta_a)*(-Cost_k*Delta_a*Floor_F/Rho_a))-IF((A27-0.0001)<Floor_F,-(Cost_k*Ubar_a+Delay_D)*(1-EXP(-Rho_a*LN((Cap_top-(A27-0.0001))/(Cap_top-Floor_F))/Delta_a))/Rho_a+EXP(-Rho_a*LN((Cap_top-(A27-0.0001))/(Cap_top-Floor_F))/Delta_a)*(-Cost_k*Delta_a*Floor_F/Rho_a),EXP(-Rho_a*LN((A27-0.0001)/Floor_F)/Delta_a)*(-Cost_k*Delta_a*Floor_F/Rho_a)))/(2*0.0001) -> 9.4357483
A28: 51.5 | B28: =-IF(A28<Floor_F,-(Cost_k*Ubar_a+Delay_D)*(1-EXP(-Rho_a*LN((Cap_top-A28)/(Cap_top-Floor_F))/Delta_a))/Rho_a+EXP(-Rho_a*LN((Cap_top-A28)/(Cap_top-Floor_F))/Delta_a)*(-Cost_k*Delta_a*Floor_F/Rho_a),EXP(-Rho_a*LN(A28/Floor_F)/Delta_a)*(-Cost_k*Delta_a*Floor_F/Rho_a)) -> 269.63024 | C28: =IF(A28<Floor_F,EXP(-Rho_a*LN((Cap_top-A28)/(Cap_top-Floor_F))/Delta_a)*(Cost_k*Ubar_a+Delay_D+Rho_a*(-Cost_k*Delta_a*Floor_F/Rho_a))/(Ubar_a-Delta_a*A28),IF(A28=Floor_F,Cost_k,EXP(-Rho_a*LN(A28/Floor_F)/Delta_a)*(-Rho_a*(-Cost_k*Delta_a*Floor_F/Rho_a))/(Delta_a*A28))) -> 9.5303901 | D28: =(IF((A28+0.0001)<Floor_F,-(Cost_k*Ubar_a+Delay_D)*(1-EXP(-Rho_a*LN((Cap_top-(A28+0.0001))/(Cap_top-Floor_F))/Delta_a))/Rho_a+EXP(-Rho_a*LN((Cap_top-(A28+0.0001))/(Cap_top-Floor_F))/Delta_a)*(-Cost_k*Delta_a*Floor_F/Rho_a),EXP(-Rho_a*LN((A28+0.0001)/Floor_F)/Delta_a)*(-Cost_k*Delta_a*Floor_F/Rho_a))-IF((A28-0.0001)<Floor_F,-(Cost_k*Ubar_a+Delay_D)*(1-EXP(-Rho_a*LN((Cap_top-(A28-0.0001))/(Cap_top-Floor_F))/Delta_a))/Rho_a+EXP(-Rho_a*LN((Cap_top-(A28-0.0001))/(Cap_top-Floor_F))/Delta_a)*(-Cost_k*Delta_a*Floor_F/Rho_a),EXP(-Rho_a*LN((A28-0.0001)/Floor_F)/Delta_a)*(-Cost_k*Delta_a*Floor_F/Rho_a)))/(2*0.0001) -> 9.5303901
A29: 51.75 | B29: =-IF(A29<Floor_F,-(Cost_k*Ubar_a+Delay_D)*(1-EXP(-Rho_a*LN((Cap_top-A29)/(Cap_top-Floor_F))/Delta_a))/Rho_a+EXP(-Rho_a*LN((Cap_top-A29)/(Cap_top-Floor_F))/Delta_a)*(-Cost_k*Delta_a*Floor_F/Rho_a),EXP(-Rho_a*LN(A29/Floor_F)/Delta_a)*(-Cost_k*Delta_a*Floor_F/Rho_a)) -> 267.23567 | C29: =IF(A29<Floor_F,EXP(-Rho_a*LN((Cap_top-A29)/(Cap_top-Floor_F))/Delta_a)*(Cost_k*Ubar_a+Delay_D+Rho_a*(-Cost_k*Delta_a*Floor_F/Rho_a))/(Ubar_a-Delta_a*A29),IF(A29=Floor_F,Cost_k,EXP(-Rho_a*LN(A29/Floor_F)/Delta_a)*(-Rho_a*(-Cost_k*Delta_a*Floor_F/Rho_a))/(Delta_a*A29))) -> 9.6264777 | D29: =(IF((A29+0.0001)<Floor_F,-(Cost_k*Ubar_a+Delay_D)*(1-EXP(-Rho_a*LN((Cap_top-(A29+0.0001))/(Cap_top-Floor_F))/Delta_a))/Rho_a+EXP(-Rho_a*LN((Cap_top-(A29+0.0001))/(Cap_top-Floor_F))/Delta_a)*(-Cost_k*Delta_a*Floor_F/Rho_a),EXP(-Rho_a*LN((A29+0.0001)/Floor_F)/Delta_a)*(-Cost_k*Delta_a*Floor_F/Rho_a))-IF((A29-0.0001)<Floor_F,-(Cost_k*Ubar_a+Delay_D)*(1-EXP(-Rho_a*LN((Cap_top-(A29-0.0001))/(Cap_top-Floor_F))/Delta_a))/Rho_a+EXP(-Rho_a*LN((Cap_top-(A29-0.0001))/(Cap_top-Floor_F))/Delta_a)*(-Cost_k*Delta_a*Floor_F/Rho_a),EXP(-Rho_a*LN((A29-0.0001)/Floor_F)/Delta_a)*(-Cost_k*Delta_a*Floor_F/Rho_a)))/(2*0.0001) -> 9.6264777
A30: 52 | B30: =-IF(A30<Floor_F,-(Cost_k*Ubar_a+Delay_D)*(1-EXP(-Rho_a*LN((Cap_top-A30)/(Cap_top-Floor_F))/Delta_a))/Rho_a+EXP(-Rho_a*LN((Cap_top-A30)/(Cap_top-Floor_F))/Delta_a)*(-Cost_k*Delta_a*Floor_F/Rho_a),EXP(-Rho_a*LN(A30/Floor_F)/Delta_a)*(-Cost_k*Delta_a*Floor_F/Rho_a)) -> 264.81688 | C30: =IF(A30<Floor_F,EXP(-Rho_a*LN((Cap_top-A30)/(Cap_top-Floor_F))/Delta_a)*(Cost_k*Ubar_a+Delay_D+Rho_a*(-Cost_k*Delta_a*Floor_F/Rho_a))/(Ubar_a-Delta_a*A30),IF(A30=Floor_F,Cost_k,EXP(-Rho_a*LN(A30/Floor_F)/Delta_a)*(-Rho_a*(-Cost_k*Delta_a*Floor_F/Rho_a))/(Delta_a*A30))) -> 9.7240408 | D30: =(IF((A30+0.0001)<Floor_F,-(Cost_k*Ubar_a+Delay_D)*(1-EXP(-Rho_a*LN((Cap_top-(A30+0.0001))/(Cap_top-Floor_F))/Delta_a))/Rho_a+EXP(-Rho_a*LN((Cap_top-(A30+0.0001))/(Cap_top-Floor_F))/Delta_a)*(-Cost_k*Delta_a*Floor_F/Rho_a),EXP(-Rho_a*LN((A30+0.0001)/Floor_F)/Delta_a)*(-Cost_k*Delta_a*Floor_F/Rho_a))-IF((A30-0.0001)<Floor_F,-(Cost_k*Ubar_a+Delay_D)*(1-EXP(-Rho_a*LN((Cap_top-(A30-0.0001))/(Cap_top-Floor_F))/Delta_a))/Rho_a+EXP(-Rho_a*LN((Cap_top-(A30-0.0001))/(Cap_top-Floor_F))/Delta_a)*(-Cost_k*Delta_a*Floor_F/Rho_a),EXP(-Rho_a*LN((A30-0.0001)/Floor_F)/Delta_a)*(-Cost_k*Delta_a*Floor_F/Rho_a)))/(2*0.0001) -> 9.7240408
A31: 52.25 | B31: =-IF(A31<Floor_F,-(Cost_k*Ubar_a+Delay_D)*(1-EXP(-Rho_a*LN((Cap_top-A31)/(Cap_top-Floor_F))/Delta_a))/Rho_a+EXP(-Rho_a*LN((Cap_top-A31)/(Cap_top-Floor_F))/Delta_a)*(-Cost_k*Delta_a*Floor_F/Rho_a),EXP(-Rho_a*LN(A31/Floor_F)/Delta_a)*(-Cost_k*Delta_a*Floor_F/Rho_a)) -> 262.37352 | C31: =IF(A31<Floor_F,EXP(-Rho_a*LN((Cap_top-A31)/(Cap_top-Floor_F))/Delta_a)*(Cost_k*Ubar_a+Delay_D+Rho_a*(-Cost_k*Delta_a*Floor_F/Rho_a))/(Ubar_a-Delta_a*A31),IF(A31=Floor_F,Cost_k,EXP(-Rho_a*LN(A31/Floor_F)/Delta_a)*(-Rho_a*(-Cost_k*Delta_a*Floor_F/Rho_a))/(Delta_a*A31))) -> 9.8231099 | D31: =(IF((A31+0.0001)<Floor_F,-(Cost_k*Ubar_a+Delay_D)*(1-EXP(-Rho_a*LN((Cap_top-(A31+0.0001))/(Cap_top-Floor_F))/Delta_a))/Rho_a+EXP(-Rho_a*LN((Cap_top-(A31+0.0001))/(Cap_top-Floor_F))/Delta_a)*(-Cost_k*Delta_a*Floor_F/Rho_a),EXP(-Rho_a*LN((A31+0.0001)/Floor_F)/Delta_a)*(-Cost_k*Delta_a*Floor_F/Rho_a))-IF((A31-0.0001)<Floor_F,-(Cost_k*Ubar_a+Delay_D)*(1-EXP(-Rho_a*LN((Cap_top-(A31-0.0001))/(Cap_top-Floor_F))/Delta_a))/Rho_a+EXP(-Rho_a*LN((Cap_top-(A31-0.0001))/(Cap_top-Floor_F))/Delta_a)*(-Cost_k*Delta_a*Floor_F/Rho_a),EXP(-Rho_a*LN((A31-0.0001)/Floor_F)/Delta_a)*(-Cost_k*Delta_a*Floor_F/Rho_a)))/(2*0.0001) -> 9.8231099
A32: 52.5 | B32: =-IF(A32<Floor_F,-(Cost_k*Ubar_a+Delay_D)*(1-EXP(-Rho_a*LN((Cap_top-A32)/(Cap_top-Floor_F))/Delta_a))/Rho_a+EXP(-Rho_a*LN((Cap_top-A32)/(Cap_top-Floor_F))/Delta_a)*(-Cost_k*Delta_a*Floor_F/Rho_a),EXP(-Rho_a*LN(A32/Floor_F)/Delta_a)*(-Cost_k*Delta_a*Floor_F/Rho_a)) -> 259.9052 | C32: =IF(A32<Floor_F,EXP(-Rho_a*LN((Cap_top-A32)/(Cap_top-Floor_F))/Delta_a)*(Cost_k*Ubar_a+Delay_D+Rho_a*(-Cost_k*Delta_a*Floor_F/Rho_a))/(Ubar_a-Delta_a*A32),IF(A32=Floor_F,Cost_k,EXP(-Rho_a*LN(A32/Floor_F)/Delta_a)*(-Rho_a*(-Cost_k*Delta_a*Floor_F/Rho_a))/(Delta_a*A32))) -> 9.9237163 | D32: =(IF((A32+0.0001)<Floor_F,-(Cost_k*Ubar_a+Delay_D)*(1-EXP(-Rho_a*LN((Cap_top-(A32+0.0001))/(Cap_top-Floor_F))/Delta_a))/Rho_a+EXP(-Rho_a*LN((Cap_top-(A32+0.0001))/(Cap_top-Floor_F))/Delta_a)*(-Cost_k*Delta_a*Floor_F/Rho_a),EXP(-Rho_a*LN((A32+0.0001)/Floor_F)/Delta_a)*(-Cost_k*Delta_a*Floor_F/Rho_a))-IF((A32-0.0001)<Floor_F,-(Cost_k*Ubar_a+Delay_D)*(1-EXP(-Rho_a*LN((Cap_top-(A32-0.0001))/(Cap_top-Floor_F))/Delta_a))/Rho_a+EXP(-Rho_a*LN((Cap_top-(A32-0.0001))/(Cap_top-Floor_F))/Delta_a)*(-Cost_k*Delta_a*Floor_F/Rho_a),EXP(-Rho_a*LN((A32-0.0001)/Floor_F)/Delta_a)*(-Cost_k*Delta_a*Floor_F/Rho_a)))/(2*0.0001) -> 9.9237163
A33: 52.75 | B33: =-IF(A33<Floor_F,-(Cost_k*Ubar_a+Delay_D)*(1-EXP(-Rho_a*LN((Cap_top-A33)/(Cap_top-Floor_F))/Delta_a))/Rho_a+EXP(-Rho_a*LN((Cap_top-A33)/(Cap_top-Floor_F))/Delta_a)*(-Cost_k*Delta_a*Floor_F/Rho_a),EXP(-Rho_a*LN(A33/Floor_F)/Delta_a)*(-Cost_k*Delta_a*Floor_F/Rho_a)) -> 257.41153 | C33: =IF(A33<Floor_F,EXP(-Rho_a*LN((Cap_top-A33)/(Cap_top-Floor_F))/Delta_a)*(Cost_k*Ubar_a+Delay_D+Rho_a*(-Cost_k*Delta_a*Floor_F/Rho_a))/(Ubar_a-Delta_a*A33),IF(A33=Floor_F,Cost_k,EXP(-Rho_a*LN(A33/Floor_F)/Delta_a)*(-Rho_a*(-Cost_k*Delta_a*Floor_F/Rho_a))/(Delta_a*A33))) -> 10.025892 | D33: =(IF((A33+0.0001)<Floor_F,-(Cost_k*Ubar_a+Delay_D)*(1-EXP(-Rho_a*LN((Cap_top-(A33+0.0001))/(Cap_top-Floor_F))/Delta_a))/Rho_a+EXP(-Rho_a*LN((Cap_top-(A33+0.0001))/(Cap_top-Floor_F))/Delta_a)*(-Cost_k*Delta_a*Floor_F/Rho_a),EXP(-Rho_a*LN((A33+0.0001)/Floor_F)/Delta_a)*(-Cost_k*Delta_a*Floor_F/Rho_a))-IF((A33-0.0001)<Floor_F,-(Cost_k*Ubar_a+Delay_D)*(1-EXP(-Rho_a*LN((Cap_top-(A33-0.0001))/(Cap_top-Floor_F))/Delta_a))/Rho_a+EXP(-Rho_a*LN((Cap_top-(A33-0.0001))/(Cap_top-Floor_F))/Delta_a)*(-Cost_k*Delta_a*Floor_F/Rho_a),EXP(-Rho_a*LN((A33-0.0001)/Floor_F)/Delta_a)*(-Cost_k*Delta_a*Floor_F/Rho_a)))/(2*0.0001) -> 10.025892
... A41: 54.75 | B41: =-IF(A41<Floor_F,-(Cost_k*Ubar_a+Delay_D)*(1-EXP(-Rho_a*LN((Cap_top-A41)/(Cap_top-Floor_F))/Delta_a))/Rho_a+EXP(-Rho_a*LN((Cap_top-A41)/(Cap_top-Floor_F))/Delta_a)*(-Cost_k*Delta_a*Floor_F/Rho_a),EXP(-Rho_a*LN(A41/Floor_F)/Delta_a)*(-Cost_k*Delta_a*Floor_F/Rho_a)) -> 236.5003 | C41: =IF(A41<Floor_F,EXP(-Rho_a*LN((Cap_top-A41)/(Cap_top-Floor_F))/Delta_a)*(Cost_k*Ubar_a+Delay_D+Rho_a*(-Cost_k*Delta_a*Floor_F/Rho_a))/(Ubar_a-Delta_a*A41),IF(A41=Floor_F,Cost_k,EXP(-Rho_a*LN(A41/Floor_F)/Delta_a)*(-Rho_a*(-Cost_k*Delta_a*Floor_F/Rho_a))/(Delta_a*A41))) -> 10.90395 | D41: =(IF((A41+0.0001)<Floor_F,-(Cost_k*Ubar_a+Delay_D)*(1-EXP(-Rho_a*LN((Cap_top-(A41+0.0001))/(Cap_top-Floor_F))/Delta_a))/Rho_a+EXP(-Rho_a*LN((Cap_top-(A41+0.0001))/(Cap_top-Floor_F))/Delta_a)*(-Cost_k*Delta_a*Floor_F/Rho_a),EXP(-Rho_a*LN((A41+0.0001)/Floor_F)/Delta_a)*(-Cost_k*Delta_a*Floor_F/Rho_a))-IF((A41-0.0001)<Floor_F,-(Cost_k*Ubar_a+Delay_D)*(1-EXP(-Rho_a*LN((Cap_top-(A41-0.0001))/(Cap_top-Floor_F))/Delta_a))/Rho_a+EXP(-Rho_a*LN((Cap_top-(A41-0.0001))/(Cap_top-Floor_F))/Delta_a)*(-Cost_k*Delta_a*Floor_F/Rho_a),EXP(-Rho_a*LN((A41-0.0001)/Floor_F)/Delta_a)*(-Cost_k*Delta_a*Floor_F/Rho_a)))/(2*0.0001) -> 10.90395
A42: 55 | B42: =-IF(A42<Floor_F,-(Cost_k*Ubar_a+Delay_D)*(1-EXP(-Rho_a*LN((Cap_top-A42)/(Cap_top-Floor_F))/Delta_a))/Rho_a+EXP(-Rho_a*LN((Cap_top-A42)/(Cap_top-Floor_F))/Delta_a)*(-Cost_k*Delta_a*Floor_F/Rho_a),EXP(-Rho_a*LN(A42/Floor_F)/Delta_a)*(-Cost_k*Delta_a*Floor_F/Rho_a)) -> 233.75962 | C42: =IF(A42<Floor_F,EXP(-Rho_a*LN((Cap_top-A42)/(Cap_top-Floor_F))/Delta_a)*(Cost_k*Ubar_a+Delay_D+Rho_a*(-Cost_k*Delta_a*Floor_F/Rho_a))/(Ubar_a-Delta_a*A42),IF(A42=Floor_F,Cost_k,EXP(-Rho_a*LN(A42/Floor_F)/Delta_a)*(-Rho_a*(-Cost_k*Delta_a*Floor_F/Rho_a))/(Delta_a*A42))) -> 4
A43: 55.25 | B43: =-IF(A43<Floor_F,-(Cost_k*Ubar_a+Delay_D)*(1-EXP(-Rho_a*LN((Cap_top-A43)/(Cap_top-Floor_F))/Delta_a))/Rho_a+EXP(-Rho_a*LN((Cap_top-A43)/(Cap_top-Floor_F))/Delta_a)*(-Cost_k*Delta_a*Floor_F/Rho_a),EXP(-Rho_a*LN(A43/Floor_F)/Delta_a)*(-Cost_k*Delta_a*Floor_F/Rho_a)) -> 232.76401 | C43: =IF(A43<Floor_F,EXP(-Rho_a*LN((Cap_top-A43)/(Cap_top-Floor_F))/Delta_a)*(Cost_k*Ubar_a+Delay_D+Rho_a*(-Cost_k*Delta_a*Floor_F/Rho_a))/(Ubar_a-Delta_a*A43),IF(A43=Floor_F,Cost_k,EXP(-Rho_a*LN(A43/Floor_F)/Delta_a)*(-Rho_a*(-Cost_k*Delta_a*Floor_F/Rho_a))/(Delta_a*A43))) -> 3.9649411 | D43: =(IF((A43+0.0001)<Floor_F,-(Cost_k*Ubar_a+Delay_D)*(1-EXP(-Rho_a*LN((Cap_top-(A43+0.0001))/(Cap_top-Floor_F))/Delta_a))/Rho_a+EXP(-Rho_a*LN((Cap_top-(A43+0.0001))/(Cap_top-Floor_F))/Delta_a)*(-Cost_k*Delta_a*Floor_F/Rho_a),EXP(-Rho_a*LN((A43+0.0001)/Floor_F)/Delta_a)*(-Cost_k*Delta_a*Floor_F/Rho_a))-IF((A43-0.0001)<Floor_F,-(Cost_k*Ubar_a+Delay_D)*(1-EXP(-Rho_a*LN((Cap_top-(A43-0.0001))/(Cap_top-Floor_F))/Delta_a))/Rho_a+EXP(-Rho_a*LN((Cap_top-(A43-0.0001))/(Cap_top-Floor_F))/Delta_a)*(-Cost_k*Delta_a*Floor_F/Rho_a),EXP(-Rho_a*LN((A43-0.0001)/Floor_F)/Delta_a)*(-Cost_k*Delta_a*Floor_F/Rho_a)))/(2*0.0001) -> 3.9649411
A44: 55.5 | B44: =-IF(A44<Floor_F,-(Cost_k*Ubar_a+Delay_D)*(1-EXP(-Rho_a*LN((Cap_top-A44)/(Cap_top-Floor_F))/Delta_a))/Rho_a+EXP(-Rho_a*LN((Cap_top-A44)/(Cap_top-Floor_F))/Delta_a)*(-Cost_k*Delta_a*Floor_F/Rho_a),EXP(-Rho_a*LN(A44/Floor_F)/Delta_a)*(-Cost_k*Delta_a*Floor_F/Rho_a)) -> 231.77711 | C44: =IF(A44<Floor_F,EXP(-Rho_a*LN((Cap_top-A44)/(Cap_top-Floor_F))/Delta_a)*(Cost_k*Ubar_a+Delay_D+Rho_a*(-Cost_k*Delta_a*Floor_F/Rho_a))/(Ubar_a-Delta_a*A44),IF(A44=Floor_F,Cost_k,EXP(-Rho_a*LN(A44/Floor_F)/Delta_a)*(-Rho_a*(-Cost_k*Delta_a*Floor_F/Rho_a))/(Delta_a*A44))) -> 3.9303457 | D44: =(IF((A44+0.0001)<Floor_F,-(Cost_k*Ubar_a+Delay_D)*(1-EXP(-Rho_a*LN((Cap_top-(A44+0.0001))/(Cap_top-Floor_F))/Delta_a))/Rho_a+EXP(-Rho_a*LN((Cap_top-(A44+0.0001))/(Cap_top-Floor_F))/Delta_a)*(-Cost_k*Delta_a*Floor_F/Rho_a),EXP(-Rho_a*LN((A44+0.0001)/Floor_F)/Delta_a)*(-Cost_k*Delta_a*Floor_F/Rho_a))-IF((A44-0.0001)<Floor_F,-(Cost_k*Ubar_a+Delay_D)*(1-EXP(-Rho_a*LN((Cap_top-(A44-0.0001))/(Cap_top-Floor_F))/Delta_a))/Rho_a+EXP(-Rho_a*LN((Cap_top-(A44-0.0001))/(Cap_top-Floor_F))/Delta_a)*(-Cost_k*Delta_a*Floor_F/Rho_a),EXP(-Rho_a*LN((A44-0.0001)/Floor_F)/Delta_a)*(-Cost_k*Delta_a*Floor_F/Rho_a)))/(2*0.0001) -> 3.9303457
A45: 55.75 | B45: =-IF(A45<Floor_F,-(Cost_k*Ubar_a+Delay_D)*(1-EXP(-Rho_a*LN((Cap_top-A45)/(Cap_top-Floor_F))/Delta_a))/Rho_a+EXP(-Rho_a*LN((Cap_top-A45)/(Cap_top-Floor_F))/Delta_a)*(-Cost_k*Delta_a*Floor_F/Rho_a),EXP(-Rho_a*LN(A45/Floor_F)/Delta_a)*(-Cost_k*Delta_a*Floor_F/Rho_a)) -> 230.7988 | C45: =IF(A45<Floor_F,EXP(-Rho_a*LN((Cap_top-A45)/(Cap_top-Floor_F))/Delta_a)*(Cost_k*Ubar_a+Delay_D+Rho_a*(-Cost_k*Delta_a*Floor_F/Rho_a))/(Ubar_a-Delta_a*A45),IF(A45=Floor_F,Cost_k,EXP(-Rho_a*LN(A45/Floor_F)/Delta_a)*(-Rho_a*(-Cost_k*Delta_a*Floor_F/Rho_a))/(Delta_a*A45))) -> 3.8962056 | D45: =(IF((A45+0.0001)<Floor_F,-(Cost_k*Ubar_a+Delay_D)*(1-EXP(-Rho_a*LN((Cap_top-(A45+0.0001))/(Cap_top-Floor_F))/Delta_a))/Rho_a+EXP(-Rho_a*LN((Cap_top-(A45+0.0001))/(Cap_top-Floor_F))/Delta_a)*(-Cost_k*Delta_a*Floor_F/Rho_a),EXP(-Rho_a*LN((A45+0.0001)/Floor_F)/Delta_a)*(-Cost_k*Delta_a*Floor_F/Rho_a))-IF((A45-0.0001)<Floor_F,-(Cost_k*Ubar_a+Delay_D)*(1-EXP(-Rho_a*LN((Cap_top-(A45-0.0001))/(Cap_top-Floor_F))/Delta_a))/Rho_a+EXP(-Rho_a*LN((Cap_top-(A45-0.0001))/(Cap_top-Floor_F))/Delta_a)*(-Cost_k*Delta_a*Floor_F/Rho_a),EXP(-Rho_a*LN((A45-0.0001)/Floor_F)/Delta_a)*(-Cost_k*Delta_a*Floor_F/Rho_a)))/(2*0.0001) -> 3.8962056
A46: 56 | B46: =-IF(A46<Floor_F,-(Cost_k*Ubar_a+Delay_D)*(1-EXP(-Rho_a*LN((Cap_top-A46)/(Cap_top-Floor_F))/Delta_a))/Rho_a+EXP(-Rho_a*LN((Cap_top-A46)/(Cap_top-Floor_F))/Delta_a)*(-Cost_k*Delta_a*Floor_F/Rho_a),EXP(-Rho_a*LN(A46/Floor_F)/Delta_a)*(-Cost_k*Delta_a*Floor_F/Rho_a)) -> 229.82897 | C46: =IF(A46<Floor_F,EXP(-Rho_a*LN((Cap_top-A46)/(Cap_top-Floor_F))/Delta_a)*(Cost_k*Ubar_a+Delay_D+Rho_a*(-Cost_k*Delta_a*Floor_F/Rho_a))/(Ubar_a-Delta_a*A46),IF(A46=Floor_F,Cost_k,EXP(-Rho_a*LN(A46/Floor_F)/Delta_a)*(-Rho_a*(-Cost_k*Delta_a*Floor_F/Rho_a))/(Delta_a*A46))) -> 3.8625128 | D46: =(IF((A46+0.0001)<Floor_F,-(Cost_k*Ubar_a+Delay_D)*(1-EXP(-Rho_a*LN((Cap_top-(A46+0.0001))/(Cap_top-Floor_F))/Delta_a))/Rho_a+EXP(-Rho_a*LN((Cap_top-(A46+0.0001))/(Cap_top-Floor_F))/Delta_a)*(-Cost_k*Delta_a*Floor_F/Rho_a),EXP(-Rho_a*LN((A46+0.0001)/Floor_F)/Delta_a)*(-Cost_k*Delta_a*Floor_F/Rho_a))-IF((A46-0.0001)<Floor_F,-(Cost_k*Ubar_a+Delay_D)*(1-EXP(-Rho_a*LN((Cap_top-(A46-0.0001))/(Cap_top-Floor_F))/Delta_a))/Rho_a+EXP(-Rho_a*LN((Cap_top-(A46-0.0001))/(Cap_top-Floor_F))/Delta_a)*(-Cost_k*Delta_a*Floor_F/Rho_a),EXP(-Rho_a*LN((A46-0.0001)/Floor_F)/Delta_a)*(-Cost_k*Delta_a*Floor_F/Rho_a)))/(2*0.0001) -> 3.8625128
A47: 56.25 | B47: =-IF(A47<Floor_F,-(Cost_k*Ubar_a+Delay_D)*(1-EXP(-Rho_a*LN((Cap_top-A47)/(Cap_top-Floor_F))/Delta_a))/Rho_a+EXP(-Rho_a*LN((Cap_top-A47)/(Cap_top-Floor_F))/Delta_a)*(-Cost_k*Delta_a*Floor_F/Rho_a),EXP(-Rho_a*LN(A47/Floor_F)/Delta_a)*(-Cost_k*Delta_a*Floor_F/Rho_a)) -> 228.8675 | C47: =IF(A47<Floor_F,EXP(-Rho_a*LN((Cap_top-A47)/(Cap_top-Floor_F))/Delta_a)*(Cost_k*Ubar_a+Delay_D+Rho_a*(-Cost_k*Delta_a*Floor_F/Rho_a))/(Ubar_a-Delta_a*A47),IF(A47=Floor_F,Cost_k,EXP(-Rho_a*LN(A47/Floor_F)/Delta_a)*(-Rho_a*(-Cost_k*Delta_a*Floor_F/Rho_a))/(Delta_a*A47))) -> 3.8292595 | D47: =(IF((A47+0.0001)<Floor_F,-(Cost_k*Ubar_a+Delay_D)*(1-EXP(-Rho_a*LN((Cap_top-(A47+0.0001))/(Cap_top-Floor_F))/Delta_a))/Rho_a+EXP(-Rho_a*LN((Cap_top-(A47+0.0001))/(Cap_top-Floor_F))/Delta_a)*(-Cost_k*Delta_a*Floor_F/Rho_a),EXP(-Rho_a*LN((A47+0.0001)/Floor_F)/Delta_a)*(-Cost_k*Delta_a*Floor_F/Rho_a))-IF((A47-0.0001)<Floor_F,-(Cost_k*Ubar_a+Delay_D)*(1-EXP(-Rho_a*LN((Cap_top-(A47-0.0001))/(Cap_top-Floor_F))/Delta_a))/Rho_a+EXP(-Rho_a*LN((Cap_top-(A47-0.0001))/(Cap_top-Floor_F))/Delta_a)*(-Cost_k*Delta_a*Floor_F/Rho_a),EXP(-Rho_a*LN((A47-0.0001)/Floor_F)/Delta_a)*(-Cost_k*Delta_a*Floor_F/Rho_a)))/(2*0.0001) -> 3.8292595
A48: 56.5 | B48: =-IF(A48<Floor_F,-(Cost_k*Ubar_a+Delay_D)*(1-EXP(-Rho_a*LN((Cap_top-A48)/(Cap_top-Floor_F))/Delta_a))/Rho_a+EXP(-Rho_a*LN((Cap_top-A48)/(Cap_top-Floor_F))/Delta_a)*(-Cost_k*Delta_a*Floor_F/Rho_a),EXP(-Rho_a*LN(A48/Floor_F)/Delta_a)*(-Cost_k*Delta_a*Floor_F/Rho_a)) -> 227.9143 | C48: =IF(A48<Floor_F,EXP(-Rho_a*LN((Cap_top-A48)/(Cap_top-Floor_F))/Delta_a)*(Cost_k*Ubar_a+Delay_D+Rho_a*(-Cost_k*Delta_a*Floor_F/Rho_a))/(Ubar_a-Delta_a*A48),IF(A48=Floor_F,Cost_k,EXP(-Rho_a*LN(A48/Floor_F)/Delta_a)*(-Rho_a*(-Cost_k*Delta_a*Floor_F/Rho_a))/(Delta_a*A48))) -> 3.7964381 | D48: =(IF((A48+0.0001)<Floor_F,-(Cost_k*Ubar_a+Delay_D)*(1-EXP(-Rho_a*LN((Cap_top-(A48+0.0001))/(Cap_top-Floor_F))/Delta_a))/Rho_a+EXP(-Rho_a*LN((Cap_top-(A48+0.0001))/(Cap_top-Floor_F))/Delta_a)*(-Cost_k*Delta_a*Floor_F/Rho_a),EXP(-Rho_a*LN((A48+0.0001)/Floor_F)/Delta_a)*(-Cost_k*Delta_a*Floor_F/Rho_a))-IF((A48-0.0001)<Floor_F,-(Cost_k*Ubar_a+Delay_D)*(1-EXP(-Rho_a*LN((Cap_top-(A48-0.0001))/(Cap_top-Floor_F))/Delta_a))/Rho_a+EXP(-Rho_a*LN((Cap_top-(A48-0.0001))/(Cap_top-Floor_F))/Delta_a)*(-Cost_k*Delta_a*Floor_F/Rho_a),EXP(-Rho_a*LN((A48-0.0001)/Floor_F)/Delta_a)*(-Cost_k*Delta_a*Floor_F/Rho_a)))/(2*0.0001) -> 3.7964381
A49: 56.75 | B49: =-IF(A49<Floor_F,-(Cost_k*Ubar_a+Delay_D)*(1-EXP(-Rho_a*LN((Cap_top-A49)/(Cap_top-Floor_F))/Delta_a))/Rho_a+EXP(-Rho_a*LN((Cap_top-A49)/(Cap_top-Floor_F))/Delta_a)*(-Cost_k*Delta_a*Floor_F/Rho_a),EXP(-Rho_a*LN(A49/Floor_F)/Delta_a)*(-Cost_k*Delta_a*Floor_F/Rho_a)) -> 226.96925 | C49: =IF(A49<Floor_F,EXP(-Rho_a*LN((Cap_top-A49)/(Cap_top-Floor_F))/Delta_a)*(Cost_k*Ubar_a+Delay_D+Rho_a*(-Cost_k*Delta_a*Floor_F/Rho_a))/(Ubar_a-Delta_a*A49),IF(A49=Floor_F,Cost_k,EXP(-Rho_a*LN(A49/Floor_F)/Delta_a)*(-Rho_a*(-Cost_k*Delta_a*Floor_F/Rho_a))/(Delta_a*A49))) -> 3.7640411 | D49: =(IF((A49+0.0001)<Floor_F,-(Cost_k*Ubar_a+Delay_D)*(1-EXP(-Rho_a*LN((Cap_top-(A49+0.0001))/(Cap_top-Floor_F))/Delta_a))/Rho_a+EXP(-Rho_a*LN((Cap_top-(A49+0.0001))/(Cap_top-Floor_F))/Delta_a)*(-Cost_k*Delta_a*Floor_F/Rho_a),EXP(-Rho_a*LN((A49+0.0001)/Floor_F)/Delta_a)*(-Cost_k*Delta_a*Floor_F/Rho_a))-IF((A49-0.0001)<Floor_F,-(Cost_k*Ubar_a+Delay_D)*(1-EXP(-Rho_a*LN((Cap_top-(A49-0.0001))/(Cap_top-Floor_F))/Delta_a))/Rho_a+EXP(-Rho_a*LN((Cap_top-(A49-0.0001))/(Cap_top-Floor_F))/Delta_a)*(-Cost_k*Delta_a*Floor_F/Rho_a),EXP(-Rho_a*LN((A49-0.0001)/Floor_F)/Delta_a)*(-Cost_k*Delta_a*Floor_F/Rho_a)))/(2*0.0001) -> 3.7640411
A50: 57 | B50: =-IF(A50<Floor_F,-(Cost_k*Ubar_a+Delay_D)*(1-EXP(-Rho_a*LN((Cap_top-A50)/(Cap_top-Floor_F))/Delta_a))/Rho_a+EXP(-Rho_a*LN((Cap_top-A50)/(Cap_top-Floor_F))/Delta_a)*(-Cost_k*Delta_a*Floor_F/Rho_a),EXP(-Rho_a*LN(A50/Floor_F)/Delta_a)*(-Cost_k*Delta_a*Floor_F/Rho_a)) -> 226.03225 | C50: =IF(A50<Floor_F,EXP(-Rho_a*LN((Cap_top-A50)/(Cap_top-Floor_F))/Delta_a)*(Cost_k*Ubar_a+Delay_D+Rho_a*(-Cost_k*Delta_a*Floor_F/Rho_a))/(Ubar_a-Delta_a*A50),IF(A50=Floor_F,Cost_k,EXP(-Rho_a*LN(A50/Floor_F)/Delta_a)*(-Rho_a*(-Cost_k*Delta_a*Floor_F/Rho_a))/(Delta_a*A50))) -> 3.7320611 | D50: =(IF((A50+0.0001)<Floor_F,-(Cost_k*Ubar_a+Delay_D)*(1-EXP(-Rho_a*LN((Cap_top-(A50+0.0001))/(Cap_top-Floor_F))/Delta_a))/Rho_a+EXP(-Rho_a*LN((Cap_top-(A50+0.0001))/(Cap_top-Floor_F))/Delta_a)*(-Cost_k*Delta_a*Floor_F/Rho_a),EXP(-Rho_a*LN((A50+0.0001)/Floor_F)/Delta_a)*(-Cost_k*Delta_a*Floor_F/Rho_a))-IF((A50-0.0001)<Floor_F,-(Cost_k*Ubar_a+Delay_D)*(1-EXP(-Rho_a*LN((Cap_top-(A50-0.0001))/(Cap_top-Floor_F))/Delta_a))/Rho_a+EXP(-Rho_a*LN((Cap_top-(A50-0.0001))/(Cap_top-Floor_F))/Delta_a)*(-Cost_k*Delta_a*Floor_F/Rho_a),EXP(-Rho_a*LN((A50-0.0001)/Floor_F)/Delta_a)*(-Cost_k*Delta_a*Floor_F/Rho_a)))/(2*0.0001) -> 3.7320611
A51: 57.25 | B51: =-IF(A51<Floor_F,-(Cost_k*Ubar_a+Delay_D)*(1-EXP(-Rho_a*LN((Cap_top-A51)/(Cap_top-Floor_F))/Delta_a))/Rho_a+EXP(-Rho_a*LN((Cap_top-A51)/(Cap_top-Floor_F))/Delta_a)*(-Cost_k*Delta_a*Floor_F/Rho_a),EXP(-Rho_a*LN(A51/Floor_F)/Delta_a)*(-Cost_k*Delta_a*Floor_F/Rho_a)) -> 225.10319 | C51: =IF(A51<Floor_F,EXP(-Rho_a*LN((Cap_top-A51)/(Cap_top-Floor_F))/Delta_a)*(Cost_k*Ubar_a+Delay_D+Rho_a*(-Cost_k*Delta_a*Floor_F/Rho_a))/(Ubar_a-Delta_a*A51),IF(A51=Floor_F,Cost_k,EXP(-Rho_a*LN(A51/Floor_F)/Delta_a)*(-Rho_a*(-Cost_k*Delta_a*Floor_F/Rho_a))/(Delta_a*A51))) -> 3.7004909 | D51: =(IF((A51+0.0001)<Floor_F,-(Cost_k*Ubar_a+Delay_D)*(1-EXP(-Rho_a*LN((Cap_top-(A51+0.0001))/(Cap_top-Floor_F))/Delta_a))/Rho_a+EXP(-Rho_a*LN((Cap_top-(A51+0.0001))/(Cap_top-Floor_F))/Delta_a)*(-Cost_k*Delta_a*Floor_F/Rho_a),EXP(-Rho_a*LN((A51+0.0001)/Floor_F)/Delta_a)*(-Cost_k*Delta_a*Floor_F/Rho_a))-IF((A51-0.0001)<Floor_F,-(Cost_k*Ubar_a+Delay_D)*(1-EXP(-Rho_a*LN((Cap_top-(A51-0.0001))/(Cap_top-Floor_F))/Delta_a))/Rho_a+EXP(-Rho_a*LN((Cap_top-(A51-0.0001))/(Cap_top-Floor_F))/Delta_a)*(-Cost_k*Delta_a*Floor_F/Rho_a),EXP(-Rho_a*LN((A51-0.0001)/Floor_F)/Delta_a)*(-Cost_k*Delta_a*Floor_F/Rho_a)))/(2*0.0001) -> 3.7004909
A52: 57.5 | B52: =-IF(A52<Floor_F,-(Cost_k*Ubar_a+Delay_D)*(1-EXP(-Rho_a*LN((Cap_top-A52)/(Cap_top-Floor_F))/Delta_a))/Rho_a+EXP(-Rho_a*LN((Cap_top-A52)/(Cap_top-Floor_F))/Delta_a)*(-Cost_k*Delta_a*Floor_F/Rho_a),EXP(-Rho_a*LN(A52/Floor_F)/Delta_a)*(-Cost_k*Delta_a*Floor_F/Rho_a)) -> 224.18197 | C52: =IF(A52<Floor_F,EXP(-Rho_a*LN((Cap_top-A52)/(Cap_top-Floor_F))/Delta_a)*(Cost_k*Ubar_a+Delay_D+Rho_a*(-Cost_k*Delta_a*Floor_F/Rho_a))/(Ubar_a-Delta_a*A52),IF(A52=Floor_F,Cost_k,EXP(-Rho_a*LN(A52/Floor_F)/Delta_a)*(-Rho_a*(-Cost_k*Delta_a*Floor_F/Rho_a))/(Delta_a*A52))) -> 3.6693237 | D52: =(IF((A52+0.0001)<Floor_F,-(Cost_k*Ubar_a+Delay_D)*(1-EXP(-Rho_a*LN((Cap_top-(A52+0.0001))/(Cap_top-Floor_F))/Delta_a))/Rho_a+EXP(-Rho_a*LN((Cap_top-(A52+0.0001))/(Cap_top-Floor_F))/Delta_a)*(-Cost_k*Delta_a*Floor_F/Rho_a),EXP(-Rho_a*LN((A52+0.0001)/Floor_F)/Delta_a)*(-Cost_k*Delta_a*Floor_F/Rho_a))-IF((A52-0.0001)<Floor_F,-(Cost_k*Ubar_a+Delay_D)*(1-EXP(-Rho_a*LN((Cap_top-(A52-0.0001))/(Cap_top-Floor_F))/Delta_a))/Rho_a+EXP(-Rho_a*LN((Cap_top-(A52-0.0001))/(Cap_top-Floor_F))/Delta_a)*(-Cost_k*Delta_a*Floor_F/Rho_a),EXP(-Rho_a*LN((A52-0.0001)/Floor_F)/Delta_a)*(-Cost_k*Delta_a*Floor_F/Rho_a)))/(2*0.0001) -> 3.6693237
A53: 57.75 | B53: =-IF(A53<Floor_F,-(Cost_k*Ubar_a+Delay_D)*(1-EXP(-Rho_a*LN((Cap_top-A53)/(Cap_top-Floor_F))/Delta_a))/Rho_a+EXP(-Rho_a*LN((Cap_top-A53)/(Cap_top-Floor_F))/Delta_a)*(-Cost_k*Delta_a*Floor_F/Rho_a),EXP(-Rho_a*LN(A53/Floor_F)/Delta_a)*(-Cost_k*Delta_a*Floor_F/Rho_a)) -> 223.26849 | C53: =IF(A53<Floor_F,EXP(-Rho_a*LN((Cap_top-A53)/(Cap_top-Floor_F))/Delta_a)*(Cost_k*Ubar_a+Delay_D+Rho_a*(-Cost_k*Delta_a*Floor_F/Rho_a))/(Ubar_a-Delta_a*A53),IF(A53=Floor_F,Cost_k,EXP(-Rho_a*LN(A53/Floor_F)/Delta_a)*(-Rho_a*(-Cost_k*Delta_a*Floor_F/Rho_a))/(Delta_a*A53))) -> 3.6385525 | D53: =(IF((A53+0.0001)<Floor_F,-(Cost_k*Ubar_a+Delay_D)*(1-EXP(-Rho_a*LN((Cap_top-(A53+0.0001))/(Cap_top-Floor_F))/Delta_a))/Rho_a+EXP(-Rho_a*LN((Cap_top-(A53+0.0001))/(Cap_top-Floor_F))/Delta_a)*(-Cost_k*Delta_a*Floor_F/Rho_a),EXP(-Rho_a*LN((A53+0.0001)/Floor_F)/Delta_a)*(-Cost_k*Delta_a*Floor_F/Rho_a))-IF((A53-0.0001)<Floor_F,-(Cost_k*Ubar_a+Delay_D)*(1-EXP(-Rho_a*LN((Cap_top-(A53-0.0001))/(Cap_top-Floor_F))/Delta_a))/Rho_a+EXP(-Rho_a*LN((Cap_top-(A53-0.0001))/(Cap_top-Floor_F))/Delta_a)*(-Cost_k*Delta_a*Floor_F/Rho_a),EXP(-Rho_a*LN((A53-0.0001)/Floor_F)/Delta_a)*(-Cost_k*Delta_a*Floor_F/Rho_a)))/(2*0.0001) -> 3.6385525
A54: 58 | B54: =-IF(A54<Floor_F,-(Cost_k*Ubar_a+Delay_D)*(1-EXP(-Rho_a*LN((Cap_top-A54)/(Cap_top-Floor_F))/Delta_a))/Rho_a+EXP(-Rho_a*LN((Cap_top-A54)/(Cap_top-Floor_F))/Delta_a)*(-Cost_k*Delta_a*Floor_F/Rho_a),EXP(-Rho_a*LN(A54/Floor_F)/Delta_a)*(-Cost_k*Delta_a*Floor_F/Rho_a)) -> 222.36266 | C54: =IF(A54<Floor_F,EXP(-Rho_a*LN((Cap_top-A54)/(Cap_top-Floor_F))/Delta_a)*(Cost_k*Ubar_a+Delay_D+Rho_a*(-Cost_k*Delta_a*Floor_F/Rho_a))/(Ubar_a-Delta_a*A54),IF(A54=Floor_F,Cost_k,EXP(-Rho_a*LN(A54/Floor_F)/Delta_a)*(-Rho_a*(-Cost_k*Delta_a*Floor_F/Rho_a))/(Delta_a*A54))) -> 3.6081706 | D54: =(IF((A54+0.0001)<Floor_F,-(Cost_k*Ubar_a+Delay_D)*(1-EXP(-Rho_a*LN((Cap_top-(A54+0.0001))/(Cap_top-Floor_F))/Delta_a))/Rho_a+EXP(-Rho_a*LN((Cap_top-(A54+0.0001))/(Cap_top-Floor_F))/Delta_a)*(-Cost_k*Delta_a*Floor_F/Rho_a),EXP(-Rho_a*LN((A54+0.0001)/Floor_F)/Delta_a)*(-Cost_k*Delta_a*Floor_F/Rho_a))-IF((A54-0.0001)<Floor_F,-(Cost_k*Ubar_a+Delay_D)*(1-EXP(-Rho_a*LN((Cap_top-(A54-0.0001))/(Cap_top-Floor_F))/Delta_a))/Rho_a+EXP(-Rho_a*LN((Cap_top-(A54-0.0001))/(Cap_top-Floor_F))/Delta_a)*(-Cost_k*Delta_a*Floor_F/Rho_a),EXP(-Rho_a*LN((A54-0.0001)/Floor_F)/Delta_a)*(-Cost_k*Delta_a*Floor_F/Rho_a)))/(2*0.0001) -> 3.6081706
... A70: 62 | B70: =-IF(A70<Floor_F,-(Cost_k*Ubar_a+Delay_D)*(1-EXP(-Rho_a*LN((Cap_top-A70)/(Cap_top-Floor_F))/Delta_a))/Rho_a+EXP(-Rho_a*LN((Cap_top-A70)/(Cap_top-Floor_F))/Delta_a)*(-Cost_k*Delta_a*Floor_F/Rho_a),EXP(-Rho_a*LN(A70/Floor_F)/Delta_a)*(-Cost_k*Delta_a*Floor_F/Rho_a)) -> 208.83488 | C70: =IF(A70<Floor_F,EXP(-Rho_a*LN((Cap_top-A70)/(Cap_top-Floor_F))/Delta_a)*(Cost_k*Ubar_a+Delay_D+Rho_a*(-Cost_k*Delta_a*Floor_F/Rho_a))/(Ubar_a-Delta_a*A70),IF(A70=Floor_F,Cost_k,EXP(-Rho_a*LN(A70/Floor_F)/Delta_a)*(-Rho_a*(-Cost_k*Delta_a*Floor_F/Rho_a))/(Delta_a*A70))) -> 3.1700385 | D70: =(IF((A70+0.0001)<Floor_F,-(Cost_k*Ubar_a+Delay_D)*(1-EXP(-Rho_a*LN((Cap_top-(A70+0.0001))/(Cap_top-Floor_F))/Delta_a))/Rho_a+EXP(-Rho_a*LN((Cap_top-(A70+0.0001))/(Cap_top-Floor_F))/Delta_a)*(-Cost_k*Delta_a*Floor_F/Rho_a),EXP(-Rho_a*LN((A70+0.0001)/Floor_F)/Delta_a)*(-Cost_k*Delta_a*Floor_F/Rho_a))-IF((A70-0.0001)<Floor_F,-(Cost_k*Ubar_a+Delay_D)*(1-EXP(-Rho_a*LN((Cap_top-(A70-0.0001))/(Cap_top-Floor_F))/Delta_a))/Rho_a+EXP(-Rho_a*LN((Cap_top-(A70-0.0001))/(Cap_top-Floor_F))/Delta_a)*(-Cost_k*Delta_a*Floor_F/Rho_a),EXP(-Rho_a*LN((A70-0.0001)/Floor_F)/Delta_a)*(-Cost_k*Delta_a*Floor_F/Rho_a)))/(2*0.0001) -> 3.1700385
A71: Figure 6.1(a): the cost of the position and its slope. At 55 the price jumps from $11.0 million (it starts the build) to the $4 million cost (once the build runs); no finite difference across the jump.

Sheet Hamiltonian
A1: Read the Hamiltonian: hire at the cap, nothing, or the rent (AXIOM Lab 2.6, step 2; Theorem 6.2; Figure 6.1(b))
A2: H = -4u - 32 1{c < 55} + m(u - delta c): the value earned now plus the value banked. Hiring moves only (m - 4)u, so the switching function m - 4 decides: the cap above 0, nothing below, any rate at 0.
A4: Where | B4: Price m | C4: Switching function m - 4 | D4: Best hiring | E4: Best rate on the grid
A5: At 53, team gone | B5: =Prices!C4 -> 10.129671 | C5: =B5-Cost_k -> 6.1296707 | D5: =IF(C5>0.000000001,"the cap",IF(C5<-0.000000001,"nothing","any rate: the rent")) -> the cap | E5: =INDEX($A$10:$A$31,MATCH(MAX(B10:B31),B10:B31,0)) -> 10.127123
A6: On the floor, build running | B6: =Cost_k -> 4 | C6: =B6-Cost_k -> 0 | D6: =IF(C6>0.000000001,"the cap",IF(C6<-0.000000001,"nothing","any rate: the rent")) -> any rate: the rent | E6: =INDEX($A$10:$A$31,MATCH(MAX(C10:C31),C10:C31,0)) -> 0
A7: At 58, team kept | B7: =Prices!C9 -> 3.6081706 | C7: =B7-Cost_k -> -0.39182944 | D7: =IF(C7>0.000000001,"the cap",IF(C7<-0.000000001,"nothing","any rate: the rent")) -> nothing | E7: =INDEX($A$10:$A$31,MATCH(MAX(D10:D31),D10:D31,0)) -> 0
A9: Hiring u (points a year) | B9: (m - 4)u at 53 | C9: (m - 4)u on the floor | D9: (m - 4)u at 58
A10: 0 | B10: =($B$5-Cost_k)*$A10 -> 0 | C10: =($B$6-Cost_k)*$A10 -> 0 | D10: =($B$7-Cost_k)*$A10 -> 0
A11: 0.5 | B11: =($B$5-Cost_k)*$A11 -> 3.0648354 | C11: =($B$6-Cost_k)*$A11 -> 0 | D11: =($B$7-Cost_k)*$A11 -> -0.19591472
A12: 1 | B12: =($B$5-Cost_k)*$A12 -> 6.1296707 | C12: =($B$6-Cost_k)*$A12 -> 0 | D12: =($B$7-Cost_k)*$A12 -> -0.39182944
A13: 1.5 | B13: =($B$5-Cost_k)*$A13 -> 9.1945061 | C13: =($B$6-Cost_k)*$A13 -> 0 | D13: =($B$7-Cost_k)*$A13 -> -0.58774416
A14: 2 | B14: =($B$5-Cost_k)*$A14 -> 12.259341 | C14: =($B$6-Cost_k)*$A14 -> 0 | D14: =($B$7-Cost_k)*$A14 -> -0.78365888
A15: 2.5 | B15: =($B$5-Cost_k)*$A15 -> 15.324177 | C15: =($B$6-Cost_k)*$A15 -> 0 | D15: =($B$7-Cost_k)*$A15 -> -0.9795736
A16: 3 | B16: =($B$5-Cost_k)*$A16 -> 18.389012 | C16: =($B$6-Cost_k)*$A16 -> 0 | D16: =($B$7-Cost_k)*$A16 -> -1.1754883
A17: 3.5 | B17: =($B$5-Cost_k)*$A17 -> 21.453848 | C17: =($B$6-Cost_k)*$A17 -> 0 | D17: =($B$7-Cost_k)*$A17 -> -1.371403
A18: 4 | B18: =($B$5-Cost_k)*$A18 -> 24.518683 | C18: =($B$6-Cost_k)*$A18 -> 0 | D18: =($B$7-Cost_k)*$A18 -> -1.5673178
A19: 4.5 | B19: =($B$5-Cost_k)*$A19 -> 27.583518 | C19: =($B$6-Cost_k)*$A19 -> 0 | D19: =($B$7-Cost_k)*$A19 -> -1.7632325
A20: 5 | B20: =($B$5-Cost_k)*$A20 -> 30.648354 | C20: =($B$6-Cost_k)*$A20 -> 0 | D20: =($B$7-Cost_k)*$A20 -> -1.9591472
A21: 5.5 | B21: =($B$5-Cost_k)*$A21 -> 33.713189 | C21: =($B$6-Cost_k)*$A21 -> 0 | D21: =($B$7-Cost_k)*$A21 -> -2.1550619
... A30: 10 | B30: =($B$5-Cost_k)*$A30 -> 61.296707 | C30: =($B$6-Cost_k)*$A30 -> 0 | D30: =($B$7-Cost_k)*$A30 -> -3.9182944
A31: =Ubar_a -> 10.127123 | B31: =($B$5-Cost_k)*$A31 -> 62.075931 | C31: =($B$6-Cost_k)*$A31 -> 0 | D31: =($B$7-Cost_k)*$A31 -> -3.968105
A34: Quarter | B34: Years | C34: Gone: capability | D34: Gone: price | E34: Gone: m - 4 | F34: Gone: hiring | G34: Gone: max H | H34: Gone: rho V(c) | I34: Gone: |max H - rho V| | J34: Kept: capability | K34: Kept: price | L34: Kept: m - 4 | M34: Kept: hiring | N34: Kept: max H | O34: Kept: rho V(c) | P34: Kept: |max H - rho V|
A35: 0 | B35: =A35/4 -> 0 | C35: =IF(B35<Tau_race,Cap_top-(Cap_top-C_gone)*EXP(-Delta_a*B35),Floor_F) -> 53 | D35: =IF(B35<Tau_race,IF(C35<Floor_F,EXP(-Rho_a*LN((Cap_top-C35)/(Cap_top-Floor_F))/Delta_a)*(Cost_k*Ubar_a+Delay_D+Rho_a*(-Cost_k*Delta_a*Floor_F/Rho_a))/(Ubar_a-Delta_a*C35),IF(C35=Floor_F,Cost_k,EXP(-Rho_a*LN(C35/Floor_F)/Delta_a)*(-Rho_a*(-Cost_k*Delta_a*Floor_F/Rho_a))/(Delta_a*C35))),Cost_k) -> 10.129671 | E35: =D35-Cost_k -> 6.1296707 | F35: =IF(E35>0.000000001,Ubar_a,IF(E35<-0.000000001,0,Delta_a*Floor_F)) -> 10.127123 | G35: =MAX(-Delay_D*IF(B35<Tau_race,1,0)-D35*Delta_a*C35,-Cost_k*Ubar_a-Delay_D*IF(B35<Tau_race,1,0)+D35*(Ubar_a-Delta_a*C35)) -> -24.293814 | H35: =Rho_a*IF(B35<Tau_race,IF(C35<Floor_F,-(Cost_k*Ubar_a+Delay_D)*(1-EXP(-Rho_a*LN((Cap_top-C35)/(Cap_top-Floor_F))/Delta_a))/Rho_a+EXP(-Rho_a*LN((Cap_top-C35)/(Cap_top-Floor_F))/Delta_a)*(-Cost_k*Delta_a*Floor_F/Rho_a),EXP(-Rho_a*LN(C35/Floor_F)/Delta_a)*(-Cost_k*Delta_a*Floor_F/Rho_a)),V_F) -> -24.293814 | I35: =ABS(G35-H35) -> 0 | J35: =IF(B35<Tau_drift,C_kept*EXP(-Delta_a*B35),Floor_F) -> 58 | K35: =IF(B35<Tau_drift,IF(J35<Floor_F,EXP(-Rho_a*LN((Cap_top-J35)/(Cap_top-Floor_F))/Delta_a)*(Cost_k*Ubar_a+Delay_D+Rho_a*(-Cost_k*Delta_a*Floor_F/Rho_a))/(Ubar_a-Delta_a*J35),IF(J35=Floor_F,Cost_k,EXP(-Rho_a*LN(J35/Floor_F)/Delta_a)*(-Rho_a*(-Cost_k*Delta_a*Floor_F/Rho_a))/(Delta_a*J35))),Cost_k) -> 3.6081706 | L35: =K35-Cost_k -> -0.39182944 | M35: =IF(L35>0.000000001,Ubar_a,IF(L35<-0.000000001,0,Delta_a*Floor_F)) -> 0 | N35: =MAX(-Delay_D*0-K35*Delta_a*J35,-Cost_k*Ubar_a-Delay_D*0+K35*(Ubar_a-Delta_a*J35)) -> -21.193425 | O35: =Rho_a*IF(B35<Tau_drift,IF(J35<Floor_F,-(Cost_k*Ubar_a+Delay_D)*(1-EXP(-Rho_a*LN((Cap_top-J35)/(Cap_top-Floor_F))/Delta_a))/Rho_a+EXP(-Rho_a*LN((Cap_top-J35)/(Cap_top-Floor_F))/Delta_a)*(-Cost_k*Delta_a*Floor_F/Rho_a),EXP(-Rho_a*LN(J35/Floor_F)/Delta_a)*(-Cost_k*Delta_a*Floor_F/Rho_a)),V_F) -> -21.193425 | P35: =ABS(N35-O35) -> 0
A36: 0.5 | B36: =A36/4 -> 0.125 | C36: =IF(B36<Tau_race,Cap_top-(Cap_top-C_gone)*EXP(-Delta_a*B36),Floor_F) -> 53.591219 | D36: =IF(B36<Tau_race,IF(C36<Floor_F,EXP(-Rho_a*LN((Cap_top-C36)/(Cap_top-Floor_F))/Delta_a)*(Cost_k*Ubar_a+Delay_D+Rho_a*(-Cost_k*Delta_a*Floor_F/Rho_a))/(Ubar_a-Delta_a*C36),IF(C36=Floor_F,Cost_k,EXP(-Rho_a*LN(C36/Floor_F)/Delta_a)*(-Rho_a*(-Cost_k*Delta_a*Floor_F/Rho_a))/(Delta_a*C36))),Cost_k) -> 10.381667 | E36: =D36-Cost_k -> 6.3816673 | F36: =IF(E36>0.000000001,Ubar_a,IF(E36<-0.000000001,0,Delta_a*Floor_F)) -> 10.127123 | G36: =MAX(-Delay_D*IF(B36<Tau_race,1,0)-D36*Delta_a*C36,-Cost_k*Ubar_a-Delay_D*IF(B36<Tau_race,1,0)+D36*(Ubar_a-Delta_a*C36)) -> -23.71596 | H36: =Rho_a*IF(B36<Tau_race,IF(C36<Floor_F,-(Cost_k*Ubar_a+Delay_D)*(1-EXP(-Rho_a*LN((Cap_top-C36)/(Cap_top-Floor_F))/Delta_a))/Rho_a+EXP(-Rho_a*LN((Cap_top-C36)/(Cap_top-Floor_F))/Delta_a)*(-Cost_k*Delta_a*Floor_F/Rho_a),EXP(-Rho_a*LN(C36/Floor_F)/Delta_a)*(-Cost_k*Delta_a*Floor_F/Rho_a)),V_F) -> -23.71596 | I36: =ABS(G36-H36) -> 0 | J36: =IF(B36<Tau_drift,C_kept*EXP(-Delta_a*B36),Floor_F) -> 57.270411 | K36: =IF(B36<Tau_drift,IF(J36<Floor_F,EXP(-Rho_a*LN((Cap_top-J36)/(Cap_top-Floor_F))/Delta_a)*(Cost_k*Ubar_a+Delay_D+Rho_a*(-Cost_k*Delta_a*Floor_F/Rho_a))/(Ubar_a-Delta_a*J36),IF(J36=Floor_F,Cost_k,EXP(-Rho_a*LN(J36/Floor_F)/Delta_a)*(-Rho_a*(-Cost_k*Delta_a*Floor_F/Rho_a))/(Delta_a*J36))),Cost_k) -> 3.6979313 | L36: =K36-Cost_k -> -0.30206872 | M36: =IF(L36>0.000000001,Ubar_a,IF(L36<-0.000000001,0,Delta_a*Floor_F)) -> 0 | N36: =MAX(-Delay_D*0-K36*Delta_a*J36,-Cost_k*Ubar_a-Delay_D*0+K36*(Ubar_a-Delta_a*J36)) -> -21.447429 | O36: =Rho_a*IF(B36<Tau_drift,IF(J36<Floor_F,-(Cost_k*Ubar_a+Delay_D)*(1-EXP(-Rho_a*LN((Cap_top-J36)/(Cap_top-Floor_F))/Delta_a))/Rho_a+EXP(-Rho_a*LN((Cap_top-J36)/(Cap_top-Floor_F))/Delta_a)*(-Cost_k*Delta_a*Floor_F/Rho_a),EXP(-Rho_a*LN(J36/Floor_F)/Delta_a)*(-Cost_k*Delta_a*Floor_F/Rho_a)),V_F) -> -21.447429 | P36: =ABS(N36-O36) -> 0
A37: 1 | B37: =A37/4 -> 0.25 | C37: =IF(B37<Tau_race,Cap_top-(Cap_top-C_gone)*EXP(-Delta_a*B37),Floor_F) -> 54.175 | D37: =IF(B37<Tau_race,IF(C37<Floor_F,EXP(-Rho_a*LN((Cap_top-C37)/(Cap_top-Floor_F))/Delta_a)*(Cost_k*Ubar_a+Delay_D+Rho_a*(-Cost_k*Delta_a*Floor_F/Rho_a))/(Ubar_a-Delta_a*C37),IF(C37=Floor_F,Cost_k,EXP(-Rho_a*LN(C37/Floor_F)/Delta_a)*(-Rho_a*(-Cost_k*Delta_a*Floor_F/Rho_a))/(Delta_a*C37))),Cost_k) -> 10.639933 | E37: =D37-Cost_k -> 6.6399328 | F37: =IF(E37>0.000000001,Ubar_a,IF(E37<-0.000000001,0,Delta_a*Floor_F)) -> 10.127123 | G37: =MAX(-Delay_D*IF(B37<Tau_race,1,0)-D37*Delta_a*C37,-Cost_k*Ubar_a-Delay_D*IF(B37<Tau_race,1,0)+D37*(Ubar_a-Delta_a*C37)) -> -23.13118 | H37: =Rho_a*IF(B37<Tau_race,IF(C37<Floor_F,-(Cost_k*Ubar_a+Delay_D)*(1-EXP(-Rho_a*LN((Cap_top-C37)/(Cap_top-Floor_F))/Delta_a))/Rho_a+EXP(-Rho_a*LN((Cap_top-C37)/(Cap_top-Floor_F))/Delta_a)*(-Cost_k*Delta_a*Floor_F/Rho_a),EXP(-Rho_a*LN(C37/Floor_F)/Delta_a)*(-Cost_k*Delta_a*Floor_F/Rho_a)),V_F) -> -23.13118 | I37: =ABS(G37-H37) -> 0 | J37: =IF(B37<Tau_drift,C_kept*EXP(-Delta_a*B37),Floor_F) -> 56.55 | K37: =IF(B37<Tau_drift,IF(J37<Floor_F,EXP(-Rho_a*LN((Cap_top-J37)/(Cap_top-Floor_F))/Delta_a)*(Cost_k*Ubar_a+Delay_D+Rho_a*(-Cost_k*Delta_a*Floor_F/Rho_a))/(Ubar_a-Delta_a*J37),IF(J37=Floor_F,Cost_k,EXP(-Rho_a*LN(J37/Floor_F)/Delta_a)*(-Rho_a*(-Cost_k*Delta_a*Floor_F/Rho_a))/(Delta_a*J37))),Cost_k) -> 3.789925 | L37: =K37-Cost_k -> -0.21007501 | M37: =IF(L37>0.000000001,Ubar_a,IF(L37<-0.000000001,0,Delta_a*Floor_F)) -> 0 | N37: =MAX(-Delay_D*0-K37*Delta_a*J37,-Cost_k*Ubar_a-Delay_D*0+K37*(Ubar_a-Delta_a*J37)) -> -21.704477 | O37: =Rho_a*IF(B37<Tau_drift,IF(J37<Floor_F,-(Cost_k*Ubar_a+Delay_D)*(1-EXP(-Rho_a*LN((Cap_top-J37)/(Cap_top-Floor_F))/Delta_a))/Rho_a+EXP(-Rho_a*LN((Cap_top-J37)/(Cap_top-Floor_F))/Delta_a)*(-Cost_k*Delta_a*Floor_F/Rho_a),EXP(-Rho_a*LN(J37/Floor_F)/Delta_a)*(-Cost_k*Delta_a*Floor_F/Rho_a)),V_F) -> -21.704477 | P37: =ABS(N37-O37) -> 0
A38: 1.5 | B38: =A38/4 -> 0.375 | C38: =IF(B38<Tau_race,Cap_top-(Cap_top-C_gone)*EXP(-Delta_a*B38),Floor_F) -> 54.751438 | D38: =IF(B38<Tau_race,IF(C38<Floor_F,EXP(-Rho_a*LN((Cap_top-C38)/(Cap_top-Floor_F))/Delta_a)*(Cost_k*Ubar_a+Delay_D+Rho_a*(-Cost_k*Delta_a*Floor_F/Rho_a))/(Ubar_a-Delta_a*C38),IF(C38=Floor_F,Cost_k,EXP(-Rho_a*LN(C38/Floor_F)/Delta_a)*(-Rho_a*(-Cost_k*Delta_a*Floor_F/Rho_a))/(Delta_a*C38))),Cost_k) -> 10.904623 | E38: =D38-Cost_k -> 6.9046232 | F38: =IF(E38>0.000000001,Ubar_a,IF(E38<-0.000000001,0,Delta_a*Floor_F)) -> 10.127123 | G38: =MAX(-Delay_D*IF(B38<Tau_race,1,0)-D38*Delta_a*C38,-Cost_k*Ubar_a-Delay_D*IF(B38<Tau_race,1,0)+D38*(Ubar_a-Delta_a*C38)) -> -22.539392 | H38: =Rho_a*IF(B38<Tau_race,IF(C38<Floor_F,-(Cost_k*Ubar_a+Delay_D)*(1-EXP(-Rho_a*LN((Cap_top-C38)/(Cap_top-Floor_F))/Delta_a))/Rho_a+EXP(-Rho_a*LN((Cap_top-C38)/(Cap_top-Floor_F))/Delta_a)*(-Cost_k*Delta_a*Floor_F/Rho_a),EXP(-Rho_a*LN(C38/Floor_F)/Delta_a)*(-Cost_k*Delta_a*Floor_F/Rho_a)),V_F) -> -22.539392 | I38: =ABS(G38-H38) -> 0 | J38: =IF(B38<Tau_drift,C_kept*EXP(-Delta_a*B38),Floor_F) -> 55.838651 | K38: =IF(B38<Tau_drift,IF(J38<Floor_F,EXP(-Rho_a*LN((Cap_top-J38)/(Cap_top-Floor_F))/Delta_a)*(Cost_k*Ubar_a+Delay_D+Rho_a*(-Cost_k*Delta_a*Floor_F/Rho_a))/(Ubar_a-Delta_a*J38),IF(J38=Floor_F,Cost_k,EXP(-Rho_a*LN(J38/Floor_F)/Delta_a)*(-Rho_a*(-Cost_k*Delta_a*Floor_F/Rho_a))/(Delta_a*J38))),Cost_k) -> 3.8842072 | L38: =K38-Cost_k -> -0.11579277 | M38: =IF(L38>0.000000001,Ubar_a,IF(L38<-0.000000001,0,Delta_a*Floor_F)) -> 0 | N38: =MAX(-Delay_D*0-K38*Delta_a*J38,-Cost_k*Ubar_a-Delay_D*0+K38*(Ubar_a-Delta_a*J38)) -> -21.964605 | O38: =Rho_a*IF(B38<Tau_drift,IF(J38<Floor_F,-(Cost_k*Ubar_a+Delay_D)*(1-EXP(-Rho_a*LN((Cap_top-J38)/(Cap_top-Floor_F))/Delta_a))/Rho_a+EXP(-Rho_a*LN((Cap_top-J38)/(Cap_top-Floor_F))/Delta_a)*(-Cost_k*Delta_a*Floor_F/Rho_a),EXP(-Rho_a*LN(J38/Floor_F)/Delta_a)*(-Cost_k*Delta_a*Floor_F/Rho_a)),V_F) -> -21.964605 | P38: =ABS(N38-O38) -> 0
A39: 2 | B39: =A39/4 -> 0.5 | C39: =IF(B39<Tau_race,Cap_top-(Cap_top-C_gone)*EXP(-Delta_a*B39),Floor_F) -> 55 | D39: =IF(B39<Tau_race,IF(C39<Floor_F,EXP(-Rho_a*LN((Cap_top-C39)/(Cap_top-Floor_F))/Delta_a)*(Cost_k*Ubar_a+Delay_D+Rho_a*(-Cost_k*Delta_a*Floor_F/Rho_a))/(Ubar_a-Delta_a*C39),IF(C39=Floor_F,Cost_k,EXP(-Rho_a*LN(C39/Floor_F)/Delta_a)*(-Rho_a*(-Cost_k*Delta_a*Floor_F/Rho_a))/(Delta_a*C39))),Cost_k) -> 4 | E39: =D39-Cost_k -> 0 | F39: =IF(E39>0.000000001,Ubar_a,IF(E39<-0.000000001,0,Delta_a*Floor_F)) -> 5.5699178 | G39: =MAX(-Delay_D*IF(B39<Tau_race,1,0)-D39*Delta_a*C39,-Cost_k*Ubar_a-Delay_D*IF(B39<Tau_race,1,0)+D39*(Ubar_a-Delta_a*C39)) -> -22.279671 | H39: =Rho_a*IF(B39<Tau_race,IF(C39<Floor_F,-(Cost_k*Ubar_a+Delay_D)*(1-EXP(-Rho_a*LN((Cap_top-C39)/(Cap_top-Floor_F))/Delta_a))/Rho_a+EXP(-Rho_a*LN((Cap_top-C39)/(Cap_top-Floor_F))/Delta_a)*(-Cost_k*Delta_a*Floor_F/Rho_a),EXP(-Rho_a*LN(C39/Floor_F)/Delta_a)*(-Cost_k*Delta_a*Floor_F/Rho_a)),V_F) -> -22.279671 | I39: =ABS(G39-H39) -> 0 | J39: =IF(B39<Tau_drift,C_kept*EXP(-Delta_a*B39),Floor_F) -> 55.13625 | K39: =IF(B39<Tau_drift,IF(J39<Floor_F,EXP(-Rho_a*LN((Cap_top-J39)/(Cap_top-Floor_F))/Delta_a)*(Cost_k*Ubar_a+Delay_D+Rho_a*(-Cost_k*Delta_a*Floor_F/Rho_a))/(Ubar_a-Delta_a*J39),IF(J39=Floor_F,Cost_k,EXP(-Rho_a*LN(J39/Floor_F)/Delta_a)*(-Rho_a*(-Cost_k*Delta_a*Floor_F/Rho_a))/(Delta_a*J39))),Cost_k) -> 3.9808349 | L39: =K39-Cost_k -> -0.019165065 | M39: =IF(L39>0.000000001,Ubar_a,IF(L39<-0.000000001,0,Delta_a*Floor_F)) -> 0 | N39: =MAX(-Delay_D*0-K39*Delta_a*J39,-Cost_k*Ubar_a-Delay_D*0+K39*(Ubar_a-Delta_a*J39)) -> -22.227852 | O39: =Rho_a*IF(B39<Tau_drift,IF(J39<Floor_F,-(Cost_k*Ubar_a+Delay_D)*(1-EXP(-Rho_a*LN((Cap_top-J39)/(Cap_top-Floor_F))/Delta_a))/Rho_a+EXP(-Rho_a*LN((Cap_top-J39)/(Cap_top-Floor_F))/Delta_a)*(-Cost_k*Delta_a*Floor_F/Rho_a),EXP(-Rho_a*LN(J39/Floor_F)/Delta_a)*(-Cost_k*Delta_a*Floor_F/Rho_a)),V_F) -> -22.227852 | P39: =ABS(N39-O39) -> 0
A40: 2.5 | B40: =A40/4 -> 0.625 | C40: =IF(B40<Tau_race,Cap_top-(Cap_top-C_gone)*EXP(-Delta_a*B40),Floor_F) -> 55 | D40: =IF(B40<Tau_race,IF(C40<Floor_F,EXP(-Rho_a*LN((Cap_top-C40)/(Cap_top-Floor_F))/Delta_a)*(Cost_k*Ubar_a+Delay_D+Rho_a*(-Cost_k*Delta_a*Floor_F/Rho_a))/(Ubar_a-Delta_a*C40),IF(C40=Floor_F,Cost_k,EXP(-Rho_a*LN(C40/Floor_F)/Delta_a)*(-Rho_a*(-Cost_k*Delta_a*Floor_F/Rho_a))/(Delta_a*C40))),Cost_k) -> 4 | E40: =D40-Cost_k -> 0 | F40: =IF(E40>0.000000001,Ubar_a,IF(E40<-0.000000001,0,Delta_a*Floor_F)) -> 5.5699178 | G40: =MAX(-Delay_D*IF(B40<Tau_race,1,0)-D40*Delta_a*C40,-Cost_k*Ubar_a-Delay_D*IF(B40<Tau_race,1,0)+D40*(Ubar_a-Delta_a*C40)) -> -22.279671 | H40: =Rho_a*IF(B40<Tau_race,IF(C40<Floor_F,-(Cost_k*Ubar_a+Delay_D)*(1-EXP(-Rho_a*LN((Cap_top-C40)/(Cap_top-Floor_F))/Delta_a))/Rho_a+EXP(-Rho_a*LN((Cap_top-C40)/(Cap_top-Floor_F))/Delta_a)*(-Cost_k*Delta_a*Floor_F/Rho_a),EXP(-Rho_a*LN(C40/Floor_F)/Delta_a)*(-Cost_k*Delta_a*Floor_F/Rho_a)),V_F) -> -22.279671 | I40: =ABS(G40-H40) -> 0 | J40: =IF(B40<Tau_drift,C_kept*EXP(-Delta_a*B40),Floor_F) -> 55 | K40: =IF(B40<Tau_drift,IF(J40<Floor_F,EXP(-Rho_a*LN((Cap_top-J40)/(Cap_top-Floor_F))/Delta_a)*(Cost_k*Ubar_a+Delay_D+Rho_a*(-Cost_k*Delta_a*Floor_F/Rho_a))/(Ubar_a-Delta_a*J40),IF(J40=Floor_F,Cost_k,EXP(-Rho_a*LN(J40/Floor_F)/Delta_a)*(-Rho_a*(-Cost_k*Delta_a*Floor_F/Rho_a))/(Delta_a*J40))),Cost_k) -> 4 | L40: =K40-Cost_k -> 0 | M40: =IF(L40>0.000000001,Ubar_a,IF(L40<-0.000000001,0,Delta_a*Floor_F)) -> 5.5699178 | N40: =MAX(-Delay_D*0-K40*Delta_a*J40,-Cost_k*Ubar_a-Delay_D*0+K40*(Ubar_a-Delta_a*J40)) -> -22.279671 | O40: =Rho_a*IF(B40<Tau_drift,IF(J40<Floor_F,-(Cost_k*Ubar_a+Delay_D)*(1-EXP(-Rho_a*LN((Cap_top-J40)/(Cap_top-Floor_F))/Delta_a))/Rho_a+EXP(-Rho_a*LN((Cap_top-J40)/(Cap_top-Floor_F))/Delta_a)*(-Cost_k*Delta_a*Floor_F/Rho_a),EXP(-Rho_a*LN(J40/Floor_F)/Delta_a)*(-Cost_k*Delta_a*Floor_F/Rho_a)),V_F) -> -22.279671 | P40: =ABS(N40-O40) -> 0
A41: 3 | B41: =A41/4 -> 0.75 | C41: =IF(B41<Tau_race,Cap_top-(Cap_top-C_gone)*EXP(-Delta_a*B41),Floor_F) -> 55 | D41: =IF(B41<Tau_race,IF(C41<Floor_F,EXP(-Rho_a*LN((Cap_top-C41)/(Cap_top-Floor_F))/Delta_a)*(Cost_k*Ubar_a+Delay_D+Rho_a*(-Cost_k*Delta_a*Floor_F/Rho_a))/(Ubar_a-Delta_a*C41),IF(C41=Floor_F,Cost_k,EXP(-Rho_a*LN(C41/Floor_F)/Delta_a)*(-Rho_a*(-Cost_k*Delta_a*Floor_F/Rho_a))/(Delta_a*C41))),Cost_k) -> 4 | E41: =D41-Cost_k -> 0 | F41: =IF(E41>0.000000001,Ubar_a,IF(E41<-0.000000001,0,Delta_a*Floor_F)) -> 5.5699178 | G41: =MAX(-Delay_D*IF(B41<Tau_race,1,0)-D41*Delta_a*C41,-Cost_k*Ubar_a-Delay_D*IF(B41<Tau_race,1,0)+D41*(Ubar_a-Delta_a*C41)) -> -22.279671 | H41: =Rho_a*IF(B41<Tau_race,IF(C41<Floor_F,-(Cost_k*Ubar_a+Delay_D)*(1-EXP(-Rho_a*LN((Cap_top-C41)/(Cap_top-Floor_F))/Delta_a))/Rho_a+EXP(-Rho_a*LN((Cap_top-C41)/(Cap_top-Floor_F))/Delta_a)*(-Cost_k*Delta_a*Floor_F/Rho_a),EXP(-Rho_a*LN(C41/Floor_F)/Delta_a)*(-Cost_k*Delta_a*Floor_F/Rho_a)),V_F) -> -22.279671 | I41: =ABS(G41-H41) -> 0 | J41: =IF(B41<Tau_drift,C_kept*EXP(-Delta_a*B41),Floor_F) -> 55 | K41: =IF(B41<Tau_drift,IF(J41<Floor_F,EXP(-Rho_a*LN((Cap_top-J41)/(Cap_top-Floor_F))/Delta_a)*(Cost_k*Ubar_a+Delay_D+Rho_a*(-Cost_k*Delta_a*Floor_F/Rho_a))/(Ubar_a-Delta_a*J41),IF(J41=Floor_F,Cost_k,EXP(-Rho_a*LN(J41/Floor_F)/Delta_a)*(-Rho_a*(-Cost_k*Delta_a*Floor_F/Rho_a))/(Delta_a*J41))),Cost_k) -> 4 | L41: =K41-Cost_k -> 0 | M41: =IF(L41>0.000000001,Ubar_a,IF(L41<-0.000000001,0,Delta_a*Floor_F)) -> 5.5699178 | N41: =MAX(-Delay_D*0-K41*Delta_a*J41,-Cost_k*Ubar_a-Delay_D*0+K41*(Ubar_a-Delta_a*J41)) -> -22.279671 | O41: =Rho_a*IF(B41<Tau_drift,IF(J41<Floor_F,-(Cost_k*Ubar_a+Delay_D)*(1-EXP(-Rho_a*LN((Cap_top-J41)/(Cap_top-Floor_F))/Delta_a))/Rho_a+EXP(-Rho_a*LN((Cap_top-J41)/(Cap_top-Floor_F))/Delta_a)*(-Cost_k*Delta_a*Floor_F/Rho_a),EXP(-Rho_a*LN(J41/Floor_F)/Delta_a)*(-Cost_k*Delta_a*Floor_F/Rho_a)),V_F) -> -22.279671 | P41: =ABS(N41-O41) -> 0
A42: 3.5 | B42: =A42/4 -> 0.875 | C42: =IF(B42<Tau_race,Cap_top-(Cap_top-C_gone)*EXP(-Delta_a*B42),Floor_F) -> 55 | D42: =IF(B42<Tau_race,IF(C42<Floor_F,EXP(-Rho_a*LN((Cap_top-C42)/(Cap_top-Floor_F))/Delta_a)*(Cost_k*Ubar_a+Delay_D+Rho_a*(-Cost_k*Delta_a*Floor_F/Rho_a))/(Ubar_a-Delta_a*C42),IF(C42=Floor_F,Cost_k,EXP(-Rho_a*LN(C42/Floor_F)/Delta_a)*(-Rho_a*(-Cost_k*Delta_a*Floor_F/Rho_a))/(Delta_a*C42))),Cost_k) -> 4 | E42: =D42-Cost_k -> 0 | F42: =IF(E42>0.000000001,Ubar_a,IF(E42<-0.000000001,0,Delta_a*Floor_F)) -> 5.5699178 | G42: =MAX(-Delay_D*IF(B42<Tau_race,1,0)-D42*Delta_a*C42,-Cost_k*Ubar_a-Delay_D*IF(B42<Tau_race,1,0)+D42*(Ubar_a-Delta_a*C42)) -> -22.279671 | H42: =Rho_a*IF(B42<Tau_race,IF(C42<Floor_F,-(Cost_k*Ubar_a+Delay_D)*(1-EXP(-Rho_a*LN((Cap_top-C42)/(Cap_top-Floor_F))/Delta_a))/Rho_a+EXP(-Rho_a*LN((Cap_top-C42)/(Cap_top-Floor_F))/Delta_a)*(-Cost_k*Delta_a*Floor_F/Rho_a),EXP(-Rho_a*LN(C42/Floor_F)/Delta_a)*(-Cost_k*Delta_a*Floor_F/Rho_a)),V_F) -> -22.279671 | I42: =ABS(G42-H42) -> 0 | J42: =IF(B42<Tau_drift,C_kept*EXP(-Delta_a*B42),Floor_F) -> 55 | K42: =IF(B42<Tau_drift,IF(J42<Floor_F,EXP(-Rho_a*LN((Cap_top-J42)/(Cap_top-Floor_F))/Delta_a)*(Cost_k*Ubar_a+Delay_D+Rho_a*(-Cost_k*Delta_a*Floor_F/Rho_a))/(Ubar_a-Delta_a*J42),IF(J42=Floor_F,Cost_k,EXP(-Rho_a*LN(J42/Floor_F)/Delta_a)*(-Rho_a*(-Cost_k*Delta_a*Floor_F/Rho_a))/(Delta_a*J42))),Cost_k) -> 4 | L42: =K42-Cost_k -> 0 | M42: =IF(L42>0.000000001,Ubar_a,IF(L42<-0.000000001,0,Delta_a*Floor_F)) -> 5.5699178 | N42: =MAX(-Delay_D*0-K42*Delta_a*J42,-Cost_k*Ubar_a-Delay_D*0+K42*(Ubar_a-Delta_a*J42)) -> -22.279671 | O42: =Rho_a*IF(B42<Tau_drift,IF(J42<Floor_F,-(Cost_k*Ubar_a+Delay_D)*(1-EXP(-Rho_a*LN((Cap_top-J42)/(Cap_top-Floor_F))/Delta_a))/Rho_a+EXP(-Rho_a*LN((Cap_top-J42)/(Cap_top-Floor_F))/Delta_a)*(-Cost_k*Delta_a*Floor_F/Rho_a),EXP(-Rho_a*LN(J42/Floor_F)/Delta_a)*(-Cost_k*Delta_a*Floor_F/Rho_a)),V_F) -> -22.279671 | P42: =ABS(N42-O42) -> 0
A43: 4 | B43: =A43/4 -> 1 | C43: =IF(B43<Tau_race,Cap_top-(Cap_top-C_gone)*EXP(-Delta_a*B43),Floor_F) -> 55 | D43: =IF(B43<Tau_race,IF(C43<Floor_F,EXP(-Rho_a*LN((Cap_top-C43)/(Cap_top-Floor_F))/Delta_a)*(Cost_k*Ubar_a+Delay_D+Rho_a*(-Cost_k*Delta_a*Floor_F/Rho_a))/(Ubar_a-Delta_a*C43),IF(C43=Floor_F,Cost_k,EXP(-Rho_a*LN(C43/Floor_F)/Delta_a)*(-Rho_a*(-Cost_k*Delta_a*Floor_F/Rho_a))/(Delta_a*C43))),Cost_k) -> 4 | E43: =D43-Cost_k -> 0 | F43: =IF(E43>0.000000001,Ubar_a,IF(E43<-0.000000001,0,Delta_a*Floor_F)) -> 5.5699178 | G43: =MAX(-Delay_D*IF(B43<Tau_race,1,0)-D43*Delta_a*C43,-Cost_k*Ubar_a-Delay_D*IF(B43<Tau_race,1,0)+D43*(Ubar_a-Delta_a*C43)) -> -22.279671 | H43: =Rho_a*IF(B43<Tau_race,IF(C43<Floor_F,-(Cost_k*Ubar_a+Delay_D)*(1-EXP(-Rho_a*LN((Cap_top-C43)/(Cap_top-Floor_F))/Delta_a))/Rho_a+EXP(-Rho_a*LN((Cap_top-C43)/(Cap_top-Floor_F))/Delta_a)*(-Cost_k*Delta_a*Floor_F/Rho_a),EXP(-Rho_a*LN(C43/Floor_F)/Delta_a)*(-Cost_k*Delta_a*Floor_F/Rho_a)),V_F) -> -22.279671 | I43: =ABS(G43-H43) -> 0 | J43: =IF(B43<Tau_drift,C_kept*EXP(-Delta_a*B43),Floor_F) -> 55 | K43: =IF(B43<Tau_drift,IF(J43<Floor_F,EXP(-Rho_a*LN((Cap_top-J43)/(Cap_top-Floor_F))/Delta_a)*(Cost_k*Ubar_a+Delay_D+Rho_a*(-Cost_k*Delta_a*Floor_F/Rho_a))/(Ubar_a-Delta_a*J43),IF(J43=Floor_F,Cost_k,EXP(-Rho_a*LN(J43/Floor_F)/Delta_a)*(-Rho_a*(-Cost_k*Delta_a*Floor_F/Rho_a))/(Delta_a*J43))),Cost_k) -> 4 | L43: =K43-Cost_k -> 0 | M43: =IF(L43>0.000000001,Ubar_a,IF(L43<-0.000000001,0,Delta_a*Floor_F)) -> 5.5699178 | N43: =MAX(-Delay_D*0-K43*Delta_a*J43,-Cost_k*Ubar_a-Delay_D*0+K43*(Ubar_a-Delta_a*J43)) -> -22.279671 | O43: =Rho_a*IF(B43<Tau_drift,IF(J43<Floor_F,-(Cost_k*Ubar_a+Delay_D)*(1-EXP(-Rho_a*LN((Cap_top-J43)/(Cap_top-Floor_F))/Delta_a))/Rho_a+EXP(-Rho_a*LN((Cap_top-J43)/(Cap_top-Floor_F))/Delta_a)*(-Cost_k*Delta_a*Floor_F/Rho_a),EXP(-Rho_a*LN(J43/Floor_F)/Delta_a)*(-Cost_k*Delta_a*Floor_F/Rho_a)),V_F) -> -22.279671 | P43: =ABS(N43-O43) -> 0
A44: 4.5 | B44: =A44/4 -> 1.125 | C44: =IF(B44<Tau_race,Cap_top-(Cap_top-C_gone)*EXP(-Delta_a*B44),Floor_F) -> 55 | D44: =IF(B44<Tau_race,IF(C44<Floor_F,EXP(-Rho_a*LN((Cap_top-C44)/(Cap_top-Floor_F))/Delta_a)*(Cost_k*Ubar_a+Delay_D+Rho_a*(-Cost_k*Delta_a*Floor_F/Rho_a))/(Ubar_a-Delta_a*C44),IF(C44=Floor_F,Cost_k,EXP(-Rho_a*LN(C44/Floor_F)/Delta_a)*(-Rho_a*(-Cost_k*Delta_a*Floor_F/Rho_a))/(Delta_a*C44))),Cost_k) -> 4 | E44: =D44-Cost_k -> 0 | F44: =IF(E44>0.000000001,Ubar_a,IF(E44<-0.000000001,0,Delta_a*Floor_F)) -> 5.5699178 | G44: =MAX(-Delay_D*IF(B44<Tau_race,1,0)-D44*Delta_a*C44,-Cost_k*Ubar_a-Delay_D*IF(B44<Tau_race,1,0)+D44*(Ubar_a-Delta_a*C44)) -> -22.279671 | H44: =Rho_a*IF(B44<Tau_race,IF(C44<Floor_F,-(Cost_k*Ubar_a+Delay_D)*(1-EXP(-Rho_a*LN((Cap_top-C44)/(Cap_top-Floor_F))/Delta_a))/Rho_a+EXP(-Rho_a*LN((Cap_top-C44)/(Cap_top-Floor_F))/Delta_a)*(-Cost_k*Delta_a*Floor_F/Rho_a),EXP(-Rho_a*LN(C44/Floor_F)/Delta_a)*(-Cost_k*Delta_a*Floor_F/Rho_a)),V_F) -> -22.279671 | I44: =ABS(G44-H44) -> 0 | J44: =IF(B44<Tau_drift,C_kept*EXP(-Delta_a*B44),Floor_F) -> 55 | K44: =IF(B44<Tau_drift,IF(J44<Floor_F,EXP(-Rho_a*LN((Cap_top-J44)/(Cap_top-Floor_F))/Delta_a)*(Cost_k*Ubar_a+Delay_D+Rho_a*(-Cost_k*Delta_a*Floor_F/Rho_a))/(Ubar_a-Delta_a*J44),IF(J44=Floor_F,Cost_k,EXP(-Rho_a*LN(J44/Floor_F)/Delta_a)*(-Rho_a*(-Cost_k*Delta_a*Floor_F/Rho_a))/(Delta_a*J44))),Cost_k) -> 4 | L44: =K44-Cost_k -> 0 | M44: =IF(L44>0.000000001,Ubar_a,IF(L44<-0.000000001,0,Delta_a*Floor_F)) -> 5.5699178 | N44: =MAX(-Delay_D*0-K44*Delta_a*J44,-Cost_k*Ubar_a-Delay_D*0+K44*(Ubar_a-Delta_a*J44)) -> -22.279671 | O44: =Rho_a*IF(B44<Tau_drift,IF(J44<Floor_F,-(Cost_k*Ubar_a+Delay_D)*(1-EXP(-Rho_a*LN((Cap_top-J44)/(Cap_top-Floor_F))/Delta_a))/Rho_a+EXP(-Rho_a*LN((Cap_top-J44)/(Cap_top-Floor_F))/Delta_a)*(-Cost_k*Delta_a*Floor_F/Rho_a),EXP(-Rho_a*LN(J44/Floor_F)/Delta_a)*(-Cost_k*Delta_a*Floor_F/Rho_a)),V_F) -> -22.279671 | P44: =ABS(N44-O44) -> 0
A45: 5 | B45: =A45/4 -> 1.25 | C45: =IF(B45<Tau_race,Cap_top-(Cap_top-C_gone)*EXP(-Delta_a*B45),Floor_F) -> 55 | D45: =IF(B45<Tau_race,IF(C45<Floor_F,EXP(-Rho_a*LN((Cap_top-C45)/(Cap_top-Floor_F))/Delta_a)*(Cost_k*Ubar_a+Delay_D+Rho_a*(-Cost_k*Delta_a*Floor_F/Rho_a))/(Ubar_a-Delta_a*C45),IF(C45=Floor_F,Cost_k,EXP(-Rho_a*LN(C45/Floor_F)/Delta_a)*(-Rho_a*(-Cost_k*Delta_a*Floor_F/Rho_a))/(Delta_a*C45))),Cost_k) -> 4 | E45: =D45-Cost_k -> 0 | F45: =IF(E45>0.000000001,Ubar_a,IF(E45<-0.000000001,0,Delta_a*Floor_F)) -> 5.5699178 | G45: =MAX(-Delay_D*IF(B45<Tau_race,1,0)-D45*Delta_a*C45,-Cost_k*Ubar_a-Delay_D*IF(B45<Tau_race,1,0)+D45*(Ubar_a-Delta_a*C45)) -> -22.279671 | H45: =Rho_a*IF(B45<Tau_race,IF(C45<Floor_F,-(Cost_k*Ubar_a+Delay_D)*(1-EXP(-Rho_a*LN((Cap_top-C45)/(Cap_top-Floor_F))/Delta_a))/Rho_a+EXP(-Rho_a*LN((Cap_top-C45)/(Cap_top-Floor_F))/Delta_a)*(-Cost_k*Delta_a*Floor_F/Rho_a),EXP(-Rho_a*LN(C45/Floor_F)/Delta_a)*(-Cost_k*Delta_a*Floor_F/Rho_a)),V_F) -> -22.279671 | I45: =ABS(G45-H45) -> 0 | J45: =IF(B45<Tau_drift,C_kept*EXP(-Delta_a*B45),Floor_F) -> 55 | K45: =IF(B45<Tau_drift,IF(J45<Floor_F,EXP(-Rho_a*LN((Cap_top-J45)/(Cap_top-Floor_F))/Delta_a)*(Cost_k*Ubar_a+Delay_D+Rho_a*(-Cost_k*Delta_a*Floor_F/Rho_a))/(Ubar_a-Delta_a*J45),IF(J45=Floor_F,Cost_k,EXP(-Rho_a*LN(J45/Floor_F)/Delta_a)*(-Rho_a*(-Cost_k*Delta_a*Floor_F/Rho_a))/(Delta_a*J45))),Cost_k) -> 4 | L45: =K45-Cost_k -> 0 | M45: =IF(L45>0.000000001,Ubar_a,IF(L45<-0.000000001,0,Delta_a*Floor_F)) -> 5.5699178 | N45: =MAX(-Delay_D*0-K45*Delta_a*J45,-Cost_k*Ubar_a-Delay_D*0+K45*(Ubar_a-Delta_a*J45)) -> -22.279671 | O45: =Rho_a*IF(B45<Tau_drift,IF(J45<Floor_F,-(Cost_k*Ubar_a+Delay_D)*(1-EXP(-Rho_a*LN((Cap_top-J45)/(Cap_top-Floor_F))/Delta_a))/Rho_a+EXP(-Rho_a*LN((Cap_top-J45)/(Cap_top-Floor_F))/Delta_a)*(-Cost_k*Delta_a*Floor_F/Rho_a),EXP(-Rho_a*LN(J45/Floor_F)/Delta_a)*(-Cost_k*Delta_a*Floor_F/Rho_a)),V_F) -> -22.279671 | P45: =ABS(N45-O45) -> 0
A46: 5.5 | B46: =A46/4 -> 1.375 | C46: =IF(B46<Tau_race,Cap_top-(Cap_top-C_gone)*EXP(-Delta_a*B46),Floor_F) -> 55 | D46: =IF(B46<Tau_race,IF(C46<Floor_F,EXP(-Rho_a*LN((Cap_top-C46)/(Cap_top-Floor_F))/Delta_a)*(Cost_k*Ubar_a+Delay_D+Rho_a*(-Cost_k*Delta_a*Floor_F/Rho_a))/(Ubar_a-Delta_a*C46),IF(C46=Floor_F,Cost_k,EXP(-Rho_a*LN(C46/Floor_F)/Delta_a)*(-Rho_a*(-Cost_k*Delta_a*Floor_F/Rho_a))/(Delta_a*C46))),Cost_k) -> 4 | E46: =D46-Cost_k -> 0 | F46: =IF(E46>0.000000001,Ubar_a,IF(E46<-0.000000001,0,Delta_a*Floor_F)) -> 5.5699178 | G46: =MAX(-Delay_D*IF(B46<Tau_race,1,0)-D46*Delta_a*C46,-Cost_k*Ubar_a-Delay_D*IF(B46<Tau_race,1,0)+D46*(Ubar_a-Delta_a*C46)) -> -22.279671 | H46: =Rho_a*IF(B46<Tau_race,IF(C46<Floor_F,-(Cost_k*Ubar_a+Delay_D)*(1-EXP(-Rho_a*LN((Cap_top-C46)/(Cap_top-Floor_F))/Delta_a))/Rho_a+EXP(-Rho_a*LN((Cap_top-C46)/(Cap_top-Floor_F))/Delta_a)*(-Cost_k*Delta_a*Floor_F/Rho_a),EXP(-Rho_a*LN(C46/Floor_F)/Delta_a)*(-Cost_k*Delta_a*Floor_F/Rho_a)),V_F) -> -22.279671 | I46: =ABS(G46-H46) -> 0 | J46: =IF(B46<Tau_drift,C_kept*EXP(-Delta_a*B46),Floor_F) -> 55 | K46: =IF(B46<Tau_drift,IF(J46<Floor_F,EXP(-Rho_a*LN((Cap_top-J46)/(Cap_top-Floor_F))/Delta_a)*(Cost_k*Ubar_a+Delay_D+Rho_a*(-Cost_k*Delta_a*Floor_F/Rho_a))/(Ubar_a-Delta_a*J46),IF(J46=Floor_F,Cost_k,EXP(-Rho_a*LN(J46/Floor_F)/Delta_a)*(-Rho_a*(-Cost_k*Delta_a*Floor_F/Rho_a))/(Delta_a*J46))),Cost_k) -> 4 | L46: =K46-Cost_k -> 0 | M46: =IF(L46>0.000000001,Ubar_a,IF(L46<-0.000000001,0,Delta_a*Floor_F)) -> 5.5699178 | N46: =MAX(-Delay_D*0-K46*Delta_a*J46,-Cost_k*Ubar_a-Delay_D*0+K46*(Ubar_a-Delta_a*J46)) -> -22.279671 | O46: =Rho_a*IF(B46<Tau_drift,IF(J46<Floor_F,-(Cost_k*Ubar_a+Delay_D)*(1-EXP(-Rho_a*LN((Cap_top-J46)/(Cap_top-Floor_F))/Delta_a))/Rho_a+EXP(-Rho_a*LN((Cap_top-J46)/(Cap_top-Floor_F))/Delta_a)*(-Cost_k*Delta_a*Floor_F/Rho_a),EXP(-Rho_a*LN(J46/Floor_F)/Delta_a)*(-Cost_k*Delta_a*Floor_F/Rho_a)),V_F) -> -22.279671 | P46: =ABS(N46-O46) -> 0
A47: 6 | B47: =A47/4 -> 1.5 | C47: =IF(B47<Tau_race,Cap_top-(Cap_top-C_gone)*EXP(-Delta_a*B47),Floor_F) -> 55 | D47: =IF(B47<Tau_race,IF(C47<Floor_F,EXP(-Rho_a*LN((Cap_top-C47)/(Cap_top-Floor_F))/Delta_a)*(Cost_k*Ubar_a+Delay_D+Rho_a*(-Cost_k*Delta_a*Floor_F/Rho_a))/(Ubar_a-Delta_a*C47),IF(C47=Floor_F,Cost_k,EXP(-Rho_a*LN(C47/Floor_F)/Delta_a)*(-Rho_a*(-Cost_k*Delta_a*Floor_F/Rho_a))/(Delta_a*C47))),Cost_k) -> 4 | E47: =D47-Cost_k -> 0 | F47: =IF(E47>0.000000001,Ubar_a,IF(E47<-0.000000001,0,Delta_a*Floor_F)) -> 5.5699178 | G47: =MAX(-Delay_D*IF(B47<Tau_race,1,0)-D47*Delta_a*C47,-Cost_k*Ubar_a-Delay_D*IF(B47<Tau_race,1,0)+D47*(Ubar_a-Delta_a*C47)) -> -22.279671 | H47: =Rho_a*IF(B47<Tau_race,IF(C47<Floor_F,-(Cost_k*Ubar_a+Delay_D)*(1-EXP(-Rho_a*LN((Cap_top-C47)/(Cap_top-Floor_F))/Delta_a))/Rho_a+EXP(-Rho_a*LN((Cap_top-C47)/(Cap_top-Floor_F))/Delta_a)*(-Cost_k*Delta_a*Floor_F/Rho_a),EXP(-Rho_a*LN(C47/Floor_F)/Delta_a)*(-Cost_k*Delta_a*Floor_F/Rho_a)),V_F) -> -22.279671 | I47: =ABS(G47-H47) -> 0 | J47: =IF(B47<Tau_drift,C_kept*EXP(-Delta_a*B47),Floor_F) -> 55 | K47: =IF(B47<Tau_drift,IF(J47<Floor_F,EXP(-Rho_a*LN((Cap_top-J47)/(Cap_top-Floor_F))/Delta_a)*(Cost_k*Ubar_a+Delay_D+Rho_a*(-Cost_k*Delta_a*Floor_F/Rho_a))/(Ubar_a-Delta_a*J47),IF(J47=Floor_F,Cost_k,EXP(-Rho_a*LN(J47/Floor_F)/Delta_a)*(-Rho_a*(-Cost_k*Delta_a*Floor_F/Rho_a))/(Delta_a*J47))),Cost_k) -> 4 | L47: =K47-Cost_k -> 0 | M47: =IF(L47>0.000000001,Ubar_a,IF(L47<-0.000000001,0,Delta_a*Floor_F)) -> 5.5699178 | N47: =MAX(-Delay_D*0-K47*Delta_a*J47,-Cost_k*Ubar_a-Delay_D*0+K47*(Ubar_a-Delta_a*J47)) -> -22.279671 | O47: =Rho_a*IF(B47<Tau_drift,IF(J47<Floor_F,-(Cost_k*Ubar_a+Delay_D)*(1-EXP(-Rho_a*LN((Cap_top-J47)/(Cap_top-Floor_F))/Delta_a))/Rho_a+EXP(-Rho_a*LN((Cap_top-J47)/(Cap_top-Floor_F))/Delta_a)*(-Cost_k*Delta_a*Floor_F/Rho_a),EXP(-Rho_a*LN(J47/Floor_F)/Delta_a)*(-Cost_k*Delta_a*Floor_F/Rho_a)),V_F) -> -22.279671 | P47: =ABS(N47-O47) -> 0
A49: Largest |max H - rho V(c)| along both plans (the dynamic-programming condition of Step 5) | I49: =MAX(I35:I47,P35:P47) -> 0
A50: Gone: the price grows from $10.1 million to $11.0 million, then falls to the $4 million cost when the build starts. Kept: it grows from $3.6 million to $4 million as capability reaches the floor.

Sheet Shooting
A1: Solve by shooting: guess the starting price, run forward, correct (AXIOM Lab 2.6, step 4; Theorem 6.2)
A2: The forward run is exact: off the floor the price grows at rho + delta; while the price stays above the cost the decision is the cap (race), while below it nothing (drift). Bisection corrects the guess.
A4: Race from 53: the price on arrival must be the cost plus the delay a point saves | F4: =Prices!C12 -> 11.021847 | H4: Drift from 58: the price must reach the $4 million cost as capability reaches 55
A5: Race from 53: years to the floor at the cap | F5: =Tau_race -> 0.42939254 | H5: Drift from 58: years to the floor, hiring nothing | M5: =Tau_drift -> 0.52443151
A7: Step | B7: Low guess | C7: High guess | D7: Guess | E7: Price on arrival | F7: Miss | I7: Low guess | J7: High guess | K7: Guess | L7: Years until the price reaches $4m | M7: Miss
A8: 1 | B8: 4 | C8: 20 | D8: =(B8+C8)/2 -> 12 | E8: =D8*EXP(Rho_delta*$F$5) -> 13.056907 | F8: =E8-$F$4 -> 2.0350595 | I8: 0.5 | J8: 4 | K8: =(I8+J8)/2 -> 2.25 | L8: =LN(Cost_k/K8)/Rho_delta -> 2.9268492 | M8: =L8-$M$5 -> 2.4024177
A9: 2 | B9: =IF(F8<0,D8,B8) -> 4 | C9: =IF(F8<0,C8,D8) -> 12 | D9: =(B9+C9)/2 -> 8 | E9: =D9*EXP(Rho_delta*$F$5) -> 8.7046045 | F9: =E9-$F$4 -> -2.3172427 | I9: =IF(M8>0,K8,I8) -> 2.25 | J9: =IF(M8>0,J8,K8) -> 4 | K9: =(I9+J9)/2 -> 3.125 | L9: =LN(Cost_k/K9)/Rho_delta -> 1.2557651 | M9: =L9-$M$5 -> 0.7313336
A10: 3 | B10: =IF(F9<0,D9,B9) -> 8 | C10: =IF(F9<0,C9,D9) -> 12 | D10: =(B10+C10)/2 -> 10 | E10: =D10*EXP(Rho_delta*$F$5) -> 10.880756 | F10: =E10-$F$4 -> -0.14109157 | I10: =IF(M9>0,K9,I9) -> 3.125 | J10: =IF(M9>0,J9,K9) -> 4 | K10: =(I10+J10)/2 -> 3.5625 | L10: =LN(Cost_k/K10)/Rho_delta -> 0.58923076 | M10: =L10-$M$5 -> 0.064799252
A11: 4 | B11: =IF(F10<0,D10,B10) -> 10 | C11: =IF(F10<0,C10,D10) -> 12 | D11: =(B11+C11)/2 -> 11 | E11: =D11*EXP(Rho_delta*$F$5) -> 11.968831 | F11: =E11-$F$4 -> 0.94698399 | I11: =IF(M10>0,K10,I10) -> 3.5625 | J11: =IF(M10>0,J10,K10) -> 4 | K11: =(I11+J11)/2 -> 3.78125 | L11: =LN(Cost_k/K11)/Rho_delta -> 0.28608869 | M11: =L11-$M$5 -> -0.23834282
A12: 5 | B12: =IF(F11<0,D11,B11) -> 10 | C12: =IF(F11<0,C11,D11) -> 11 | D12: =(B12+C12)/2 -> 10.5 | E12: =D12*EXP(Rho_delta*$F$5) -> 11.424793 | F12: =E12-$F$4 -> 0.40294621 | I12: =IF(M11>0,K11,I11) -> 3.5625 | J12: =IF(M11>0,J11,K11) -> 3.78125 | K12: =(I12+J12)/2 -> 3.671875 | L12: =LN(Cost_k/K12)/Rho_delta -> 0.43540195 | M12: =L12-$M$5 -> -0.089029561
A13: 6 | B13: =IF(F12<0,D12,B12) -> 10 | C13: =IF(F12<0,C12,D12) -> 10.5 | D13: =(B13+C13)/2 -> 10.25 | E13: =D13*EXP(Rho_delta*$F$5) -> 11.152774 | F13: =E13-$F$4 -> 0.13092732 | I13: =IF(M12>0,K12,I12) -> 3.5625 | J13: =IF(M12>0,J12,K12) -> 3.671875 | K13: =(I13+J13)/2 -> 3.6171875 | L13: =LN(Cost_k/K13)/Rho_delta -> 0.51173491 | M13: =L13-$M$5 -> -0.012696603
A14: 7 | B14: =IF(F13<0,D13,B13) -> 10 | C14: =IF(F13<0,C13,D13) -> 10.25 | D14: =(B14+C14)/2 -> 10.125 | E14: =D14*EXP(Rho_delta*$F$5) -> 11.016765 | F14: =E14-$F$4 -> -0.0050821248 | I14: =IF(M13>0,K13,I13) -> 3.5625 | J14: =IF(M13>0,J13,K13) -> 3.6171875 | K14: =(I14+J14)/2 -> 3.5898438 | L14: =LN(Cost_k/K14)/Rho_delta -> 0.55033526 | M14: =L14-$M$5 -> 0.025903752
A15: 8 | B15: =IF(F14<0,D14,B14) -> 10.125 | C15: =IF(F14<0,C14,D14) -> 10.25 | D15: =(B15+C15)/2 -> 10.1875 | E15: =D15*EXP(Rho_delta*$F$5) -> 11.08477 | F15: =E15-$F$4 -> 0.062922598 | I15: =IF(M14>0,K14,I14) -> 3.5898438 | J15: =IF(M14>0,J14,K14) -> 3.6171875 | K15: =(I15+J15)/2 -> 3.6035156 | L15: =LN(Cost_k/K15)/Rho_delta -> 0.53099847 | M15: =L15-$M$5 -> 0.0065669619
A16: 9 | B16: =IF(F15<0,D15,B15) -> 10.125 | C16: =IF(F15<0,C15,D15) -> 10.1875 | D16: =(B16+C16)/2 -> 10.15625 | E16: =D16*EXP(Rho_delta*$F$5) -> 11.050767 | F16: =E16-$F$4 -> 0.028920236 | I16: =IF(M15>0,K15,I15) -> 3.6035156 | J16: =IF(M15>0,J15,K15) -> 3.6171875 | K16: =(I16+J16)/2 -> 3.6103516 | L16: =LN(Cost_k/K16)/Rho_delta -> 0.52135757 | M16: =L16-$M$5 -> -0.003073939
A17: 10 | B17: =IF(F16<0,D16,B16) -> 10.125 | C17: =IF(F16<0,C16,D16) -> 10.15625 | D17: =(B17+C17)/2 -> 10.140625 | E17: =D17*EXP(Rho_delta*$F$5) -> 11.033766 | F17: =E17-$F$4 -> 0.011919056 | I17: =IF(M16>0,K16,I16) -> 3.6035156 | J17: =IF(M16>0,J16,K16) -> 3.6103516 | K17: =(I17+J17)/2 -> 3.6069336 | L17: =LN(Cost_k/K17)/Rho_delta -> 0.52617574 | M17: =L17-$M$5 -> 0.0017442275
A18: 11 | B18: =IF(F17<0,D17,B17) -> 10.125 | C18: =IF(F17<0,C17,D17) -> 10.140625 | D18: =(B18+C18)/2 -> 10.132812 | E18: =D18*EXP(Rho_delta*$F$5) -> 11.025266 | F18: =E18-$F$4 -> 0.0034184655 | I18: =IF(M17>0,K17,I17) -> 3.6069336 | J18: =IF(M17>0,J17,K17) -> 3.6103516 | K18: =(I18+J18)/2 -> 3.6086426 | L18: =LN(Cost_k/K18)/Rho_delta -> 0.52376609 | M18: =L18-$M$5 -> -0.00066542617
A19: 12 | B19: =IF(F18<0,D18,B18) -> 10.125 | C19: =IF(F18<0,C18,D18) -> 10.132812 | D19: =(B19+C19)/2 -> 10.128906 | E19: =D19*EXP(Rho_delta*$F$5) -> 11.021015 | F19: =E19-$F$4 -> -0.00083182963 | I19: =IF(M18>0,K18,I18) -> 3.6069336 | J19: =IF(M18>0,J18,K18) -> 3.6086426 | K19: =(I19+J19)/2 -> 3.6077881 | L19: =LN(Cost_k/K19)/Rho_delta -> 0.52497077 | M19: =L19-$M$5 -> 0.00053925799
A20: 13 | B20: =IF(F19<0,D19,B19) -> 10.128906 | C20: =IF(F19<0,C19,D19) -> 10.132812 | D20: =(B20+C20)/2 -> 10.130859 | E20: =D20*EXP(Rho_delta*$F$5) -> 11.02314 | F20: =E20-$F$4 -> 0.0012933179 | I20: =IF(M19>0,K19,I19) -> 3.6077881 | J20: =IF(M19>0,J19,K19) -> 3.6086426 | K20: =(I20+J20)/2 -> 3.6082153 | L20: =LN(Cost_k/K20)/Rho_delta -> 0.52436839 | M20: =L20-$M$5 -> -6.311975e-05
... A57: 50 | B57: =IF(F56<0,D56,B56) -> 10.129671 | C57: =IF(F56<0,C56,D56) -> 10.129671 | D57: =(B57+C57)/2 -> 10.129671 | E57: =D57*EXP(Rho_delta*$F$5) -> 11.021847 | F57: =E57-$F$4 -> -4.7961635e-14 | I57: =IF(M56>0,K56,I56) -> 3.6081706 | J57: =IF(M56>0,J56,K56) -> 3.6081706 | K57: =(I57+J57)/2 -> 3.6081706 | L57: =LN(Cost_k/K57)/Rho_delta -> 0.52443151 | M57: =L57-$M$5 -> 4.2188475e-15
A59: Starting price found by shooting: race from 53 | D59: =D57 -> 10.129671 | H59: Drift from 58 | K59: =K57 -> 3.6081706
A60: They are the prices at 53 and 58 of the Prices sheet: shooting recovers the costate at the start.

Sheet Transcription
A1: Solve by direct transcription: the linear program's best plan, in formulas (AXIOM Lab 2.6, step 4; Section 6.6; Online Appendix 6.B.3)
A2: Hiring held level in each step of h years (exact discretization: c' = a c + b u); capability at or above 55 at every grid date from the start step; the delay charged up to it. HiGHS solves the program in the notebook (green). Its best plan is simple, and computed here: nothing, one partial step, then the cap, arriving at 55 exactly on the start date; then the rent.
A4: Quantity | B4: Weekly | C4: Daily
A5: Step h (years) | B5: =1/52 -> 0.019230769 | C5: =1/365 -> 0.002739726
A6: a = exp(-delta h) | B6: =EXP(-Delta_a*B5) -> 0.99805437 | C6: =EXP(-Delta_a*C5) -> 0.99972258
A7: b = (1 - a)/delta | B7: =(1-B6)/Delta_a -> 0.019212055 | C7: =(1-C6)/Delta_a -> 0.002739346
A8: w = (1 - exp(-rho h))/rho: PV weight of a step | B8: =(1-EXP(-Rho_a*B5))/Rho_a -> 0.019213156 | C8: =(1-EXP(-Rho_a*C5))/Rho_a -> 0.0027393684
A9: Earliest reachable start step | B9: =ROUNDUP(Tau_race/B5-0.000000001,0) -> 23 | C9: =ROUNDUP(Tau_race/C5-0.000000001,0) -> 157
A10: Earliest start in years | B10: =B9*B5 -> 0.44230769 | C10: =C9*C5 -> 0.43013699
A11: Price of a point on the floor from the multipliers: k w exp(rho h)/b | B11: =Cost_k*B8*EXP(Rho_a*B5)/B7 -> 4.0075679 | C11: =Cost_k*C8*EXP(Rho_a*C5)/C7 -> 4.0010773
A12: The floor's price a point a year: price x (1 - exp(-(rho + delta) h))/h | B12: =B11*(1-EXP(-Rho_delta*B5))/B5 -> 0.7863261 | C12: =C11*(1-EXP(-Rho_delta*C5))/C5 -> 0.78632566
A13: HiGHS (engine): price of a point on the floor | B13: 4.0075679 | C13: 4.0010773
A14: HiGHS (engine): the floor's price a point a year | B14: 0.7863261 | C14: 0.78632566
A16: Calendar | B16: Start step K | C16: Steps hiring, n | D16: Need: 55 - 53 a^K | E16: Partial rate, first hiring step | F16: Cost (formulas) | G16: Cost (HiGHS, engine) | H16: |difference| | I16: Above the closed form
A17: weekly | B17: 23 | C17: =ROUNDUP(LN(1-D17/Cap_top)/LN($B$6)-0.000000000001,0) -> 23 | D17: =Floor_F-C_gone*$B$6^B17 -> 4.3216464 | E17: =(D17-Cap_top*(1-$B$6^(C17-1)))/($B$7*$B$6^(C17-1)) -> 6.9315574 | F17: =Cost_k*$B$8*(Ubar_a*EXP(-Rho_a*$B$5*(B17-C17+1))*(1-EXP(-Rho_a*$B$5*(C17-1)))/(1-EXP(-Rho_a*$B$5))+E17*EXP(-Rho_a*$B$5*(B17-C17)))+Delay_D*(1-EXP(-Rho_a*$B$5*B17))/Rho_a+EXP(-Rho_a*$B$5*B17)*Cost_k*Delta_a*Floor_F/Rho_a -> 255.26885 | G17: 255.26885 | H17: =ABS(F17-G17) -> 0 | I17: =F17+Prices!$B$4 -> 0.37672901
A18: weekly | B18: 24 | C18: =ROUNDUP(LN(1-D18/Cap_top)/LN($B$6)-0.000000000001,0) -> 24 | D18: =Floor_F-C_gone*$B$6^B18 -> 4.4202477 | E18: =(D18-Cap_top*(1-$B$6^(C18-1)))/($B$7*$B$6^(C18-1)) -> 2.16558 | F18: =Cost_k*$B$8*(Ubar_a*EXP(-Rho_a*$B$5*(B18-C18+1))*(1-EXP(-Rho_a*$B$5*(C18-1)))/(1-EXP(-Rho_a*$B$5))+E18*EXP(-Rho_a*$B$5*(B18-C18)))+Delay_D*(1-EXP(-Rho_a*$B$5*B18))/Rho_a+EXP(-Rho_a*$B$5*B18)*Cost_k*Delta_a*Floor_F/Rho_a -> 255.82779 | G18: 255.82779 | H18: =ABS(F18-G18) -> 0 | I18: =F18+Prices!$B$4 -> 0.9356677
A19: weekly | B19: 26 | C19: =ROUNDUP(LN(1-D19/Cap_top)/LN($B$6)-0.000000000001,0) -> 25 | D19: =Floor_F-C_gone*$B$6^B19 -> 4.616875 | E19: =(D19-Cap_top*(1-$B$6^(C19-1)))/($B$7*$B$6^(C19-1)) -> 2.7472441 | F19: =Cost_k*$B$8*(Ubar_a*EXP(-Rho_a*$B$5*(B19-C19+1))*(1-EXP(-Rho_a*$B$5*(C19-1)))/(1-EXP(-Rho_a*$B$5))+E19*EXP(-Rho_a*$B$5*(B19-C19)))+Delay_D*(1-EXP(-Rho_a*$B$5*B19))/Rho_a+EXP(-Rho_a*$B$5*B19)*Cost_k*Delta_a*Floor_F/Rho_a -> 256.94059 | G19: 256.94059 | H19: =ABS(F19-G19) -> 0 | I19: =F19+Prices!$B$4 -> 2.0484661
A20: weekly | B20: 30 | C20: =ROUNDUP(LN(1-D20/Cap_top)/LN($B$6)-0.000000000001,0) -> 27 | D20: =Floor_F-C_gone*$B$6^B20 -> 5.0078395 | E20: =(D20-Cap_top*(1-$B$6^(C20-1)))/($B$7*$B$6^(C20-1)) -> 3.8513795 | F20: =Cost_k*$B$8*(Ubar_a*EXP(-Rho_a*$B$5*(B20-C20+1))*(1-EXP(-Rho_a*$B$5*(C20-1)))/(1-EXP(-Rho_a*$B$5))+E20*EXP(-Rho_a*$B$5*(B20-C20)))+Delay_D*(1-EXP(-Rho_a*$B$5*B20))/Rho_a+EXP(-Rho_a*$B$5*B20)*Cost_k*Delta_a*Floor_F/Rho_a -> 259.1452 | G20: 259.1452 | H20: =ABS(F20-G20) -> 0 | I20: =F20+Prices!$B$4 -> 4.2530839
A21: weekly | B21: 36 | C21: =ROUNDUP(LN(1-D21/Cap_top)/LN($B$6)-0.000000000001,0) -> 30 | D21: =Floor_F-C_gone*$B$6^B21 -> 5.5886052 | E21: =(D21-Cap_top*(1-$B$6^(C21-1)))/($B$7*$B$6^(C21-1)) -> 5.3596318 | F21: =Cost_k*$B$8*(Ubar_a*EXP(-Rho_a*$B$5*(B21-C21+1))*(1-EXP(-Rho_a*$B$5*(C21-1)))/(1-EXP(-Rho_a*$B$5))+E21*EXP(-Rho_a*$B$5*(B21-C21)))+Delay_D*(1-EXP(-Rho_a*$B$5*B21))/Rho_a+EXP(-Rho_a*$B$5*B21)*Cost_k*Delta_a*Floor_F/Rho_a -> 262.40014 | G21: 262.40014 | H21: =ABS(F21-G21) -> 0 | I21: =F21+Prices!$B$4 -> 7.5080258
A22: daily | B22: 157 | C22: =ROUNDUP(LN(1-D22/Cap_top)/LN($C$6)-0.000000000001,0) -> 157 | D22: =Floor_F-C_gone*$C$6^B22 -> 4.2591447 | E22: =(D22-Cap_top*(1-$C$6^(C22-1)))/($C$7*$C$6^(C22-1)) -> 8.8339287 | F22: =Cost_k*$C$8*(Ubar_a*EXP(-Rho_a*$C$5*(B22-C22+1))*(1-EXP(-Rho_a*$C$5*(C22-1)))/(1-EXP(-Rho_a*$C$5))+E22*EXP(-Rho_a*$C$5*(B22-C22)))+Delay_D*(1-EXP(-Rho_a*$C$5*B22))/Rho_a+EXP(-Rho_a*$C$5*B22)*Cost_k*Delta_a*Floor_F/Rho_a -> 254.91384 | G22: 254.91384 | H22: =ABS(F22-G22) -> 1.9070967e-11 | I22: =F22+Prices!$B$4 -> 0.021721618
A23: daily | B23: 158 | C23: =ROUNDUP(LN(1-D23/Cap_top)/LN($C$6)-0.000000000001,0) -> 158 | D23: =Floor_F-C_gone*$C$6^B23 -> 4.273221 | E23: =(D23-Cap_top*(1-$C$6^(C23-1)))/($C$7*$C$6^(C23-1)) -> 4.073822 | F23: =Cost_k*$C$8*(Ubar_a*EXP(-Rho_a*$C$5*(B23-C23+1))*(1-EXP(-Rho_a*$C$5*(C23-1)))/(1-EXP(-Rho_a*$C$5))+E23*EXP(-Rho_a*$C$5*(B23-C23)))+Delay_D*(1-EXP(-Rho_a*$C$5*B23))/Rho_a+EXP(-Rho_a*$C$5*B23)*Cost_k*Delta_a*Floor_F/Rho_a -> 254.99375 | G23: 254.99375 | H23: =ABS(F23-G23) -> 1.9042545e-11 | I23: =F23+Prices!$B$4 -> 0.10163127
A24: daily | B24: 164 | C24: =ROUNDUP(LN(1-D24/Cap_top)/LN($C$6)-0.000000000001,0) -> 161 | D24: =Floor_F-C_gone*$C$6^B24 -> 4.3575973 | E24: =(D24-Cap_top*(1-$C$6^(C24-1)))/($C$7*$C$6^(C24-1)) -> 5.8787684 | F24: =Cost_k*$C$8*(Ubar_a*EXP(-Rho_a*$C$5*(B24-C24+1))*(1-EXP(-Rho_a*$C$5*(C24-1)))/(1-EXP(-Rho_a*$C$5))+E24*EXP(-Rho_a*$C$5*(B24-C24)))+Delay_D*(1-EXP(-Rho_a*$C$5*B24))/Rho_a+EXP(-Rho_a*$C$5*B24)*Cost_k*Delta_a*Floor_F/Rho_a -> 255.47243 | G24: 255.47243 | H24: =ABS(F24-G24) -> 1.8928858e-11 | I24: =F24+Prices!$B$4 -> 0.5803158
A26: Team kept | B26: Last grid date before 55, j | C26: Partial rate at step j | D26: Cost (formulas) | E26: Cost (HiGHS, engine) | F26: |difference| | G26: Above the closed form
A27: weekly | B27: =INT(LN(C_kept/Floor_F)/(Delta_a*$B$5)) -> 27 | C27: =(Floor_F-$B$6^(B27+1)*C_kept)/$B$7 -> 4.0646667 | D27: =Cost_k*$B$8*C27*EXP(-Rho_a*$B$5*B27)+EXP(-Rho_a*$B$5*(B27+1))*Cost_k*Delta_a*Floor_F/Rho_a -> 222.36281 | E27: 222.36281 | F27: =ABS(D27-E27) -> 0 | G27: =D27+Prices!$B$9 -> 0.0001519326
A28: daily | B28: =INT(LN(C_kept/Floor_F)/(Delta_a*$C$5)) -> 191 | C28: =(Floor_F-$C$6^(B28+1)*C_kept)/$C$7 -> 3.244654 | D28: =Cost_k*$C$8*C28*EXP(-Rho_a*$C$5*B28)+EXP(-Rho_a*$C$5*(B28+1))*Cost_k*Delta_a*Floor_F/Rho_a -> 222.36266 | E28: 222.36266 | F28: =ABS(D28-E28) -> 1.8815172e-11 | G28: =D28+Prices!$B$9 -> 3.8025195e-06
A30: Week j | B30: Hiring u_j (points a year) | C30: Capability c_j | D30: PV of the week's hiring
A31: 0 | B31: =IF(A31>=$B$17,Delta_a*Floor_F,IF(A31<$B$17-$C$17,0,IF(A31=$B$17-$C$17,$E$17,Ubar_a))) -> 6.9315574 | C31: =C_gone -> 53 | D31: =Cost_k*$B$8*B31*EXP(-Rho_a*$B$5*A31) -> 0.53270838
A32: 1 | B32: =IF(A32>=$B$17,Delta_a*Floor_F,IF(A32<$B$17-$C$17,0,IF(A32=$B$17-$C$17,$E$17,Ubar_a))) -> 10.127123 | C32: =$B$6*C31+$B$7*B31 -> 53.030051 | D32: =Cost_k*$B$8*B32*EXP(-Rho_a*$B$5*A32) -> 0.77687077
A33: 2 | B33: =IF(A33>=$B$17,Delta_a*Floor_F,IF(A33<$B$17-$C$17,0,IF(A33=$B$17-$C$17,$E$17,Ubar_a))) -> 10.127123 | C33: =$B$6*C32+$B$7*B32 -> 53.121437 | D33: =Cost_k*$B$8*B33*EXP(-Rho_a*$B$5*A33) -> 0.77544816
A34: 3 | B34: =IF(A34>=$B$17,Delta_a*Floor_F,IF(A34<$B$17-$C$17,0,IF(A34=$B$17-$C$17,$E$17,Ubar_a))) -> 10.127123 | C34: =$B$6*C33+$B$7*B33 -> 53.212645 | D34: =Cost_k*$B$8*B34*EXP(-Rho_a*$B$5*A34) -> 0.77402815
A35: 4 | B35: =IF(A35>=$B$17,Delta_a*Floor_F,IF(A35<$B$17-$C$17,0,IF(A35=$B$17-$C$17,$E$17,Ubar_a))) -> 10.127123 | C35: =$B$6*C34+$B$7*B34 -> 53.303676 | D35: =Cost_k*$B$8*B35*EXP(-Rho_a*$B$5*A35) -> 0.77261074
A36: 5 | B36: =IF(A36>=$B$17,Delta_a*Floor_F,IF(A36<$B$17-$C$17,0,IF(A36=$B$17-$C$17,$E$17,Ubar_a))) -> 10.127123 | C36: =$B$6*C35+$B$7*B35 -> 53.39453 | D36: =Cost_k*$B$8*B36*EXP(-Rho_a*$B$5*A36) -> 0.77119593
A37: 6 | B37: =IF(A37>=$B$17,Delta_a*Floor_F,IF(A37<$B$17-$C$17,0,IF(A37=$B$17-$C$17,$E$17,Ubar_a))) -> 10.127123 | C37: =$B$6*C36+$B$7*B36 -> 53.485207 | D37: =Cost_k*$B$8*B37*EXP(-Rho_a*$B$5*A37) -> 0.76978371
A38: 7 | B38: =IF(A38>=$B$17,Delta_a*Floor_F,IF(A38<$B$17-$C$17,0,IF(A38=$B$17-$C$17,$E$17,Ubar_a))) -> 10.127123 | C38: =$B$6*C37+$B$7*B37 -> 53.575707 | D38: =Cost_k*$B$8*B38*EXP(-Rho_a*$B$5*A38) -> 0.76837407
A39: 8 | B39: =IF(A39>=$B$17,Delta_a*Floor_F,IF(A39<$B$17-$C$17,0,IF(A39=$B$17-$C$17,$E$17,Ubar_a))) -> 10.127123 | C39: =$B$6*C38+$B$7*B38 -> 53.666032 | D39: =Cost_k*$B$8*B39*EXP(-Rho_a*$B$5*A39) -> 0.76696702
A40: 9 | B40: =IF(A40>=$B$17,Delta_a*Floor_F,IF(A40<$B$17-$C$17,0,IF(A40=$B$17-$C$17,$E$17,Ubar_a))) -> 10.127123 | C40: =$B$6*C39+$B$7*B39 -> 53.756181 | D40: =Cost_k*$B$8*B40*EXP(-Rho_a*$B$5*A40) -> 0.76556254
A41: 10 | B41: =IF(A41>=$B$17,Delta_a*Floor_F,IF(A41<$B$17-$C$17,0,IF(A41=$B$17-$C$17,$E$17,Ubar_a))) -> 10.127123 | C41: =$B$6*C40+$B$7*B40 -> 53.846154 | D41: =Cost_k*$B$8*B41*EXP(-Rho_a*$B$5*A41) -> 0.76416064
A42: 11 | B42: =IF(A42>=$B$17,Delta_a*Floor_F,IF(A42<$B$17-$C$17,0,IF(A42=$B$17-$C$17,$E$17,Ubar_a))) -> 10.127123 | C42: =$B$6*C41+$B$7*B41 -> 53.935952 | D42: =Cost_k*$B$8*B42*EXP(-Rho_a*$B$5*A42) -> 0.7627613
A43: 12 | B43: =IF(A43>=$B$17,Delta_a*Floor_F,IF(A43<$B$17-$C$17,0,IF(A43=$B$17-$C$17,$E$17,Ubar_a))) -> 10.127123 | C43: =$B$6*C42+$B$7*B42 -> 54.025576 | D43: =Cost_k*$B$8*B43*EXP(-Rho_a*$B$5*A43) -> 0.76136452
... A61: 30 | B61: =IF(A61>=$B$17,Delta_a*Floor_F,IF(A61<$B$17-$C$17,0,IF(A61=$B$17-$C$17,$E$17,Ubar_a))) -> 5.5699178 | C61: =$B$6*C60+$B$7*B60 -> 55 | D61: =Cost_k*$B$8*B61*EXP(-Rho_a*$B$5*A61) -> 0.40516049
A63: Capability at the start week | B63: =INDEX(C31:C61,$B$17+1) -> 55
A64: PV of the hiring before the start | B64: =SUMPRODUCT((A31:A61<$B$17)*D31:D61) -> 17.299219
A65: PV of the delay to the start week | B65: =Delay_D*(1-EXP(-Rho_a*$B$5*$B$17))/Rho_a -> 13.859657
A66: PV of the rent from the start week | B66: =EXP(-Rho_a*$B$5*$B$17)*Cost_k*Delta_a*Floor_F/Rho_a -> 224.10997
A67: Total: the weekly program's optimum | B67: =SUM(B64:B66) -> 255.26885
A69: The program never beats the closed form (Theorem 5.1(i)): it starts the build on a grid date, $0.38 million above it weekly, $0.02 million daily. Its multipliers give the $4 million cost on the floor and the floor's price, the user cost.

Sheet Certify
A1: Certify the race and value the team (Worked Example 6.1, Step 5; Theorem 6.3; Online Appendix 6.B.3)
A3: Never starting the build: the delay forever, D/rho | E3: =Delay_D/Rho_a -> 335.74588
A4: Below c_a racing to the floor costs more than never starting the build: find V(c_a) = -D/rho by bisection.
A6: Step | B6: Low | C6: High | D6: Middle | E6: V(middle) + D/rho
A7: 1 | B7: 30 | C7: 54.99 | D7: =(B7+C7)/2 -> 42.495 | E7: =IF(D7<Floor_F,-(Cost_k*Ubar_a+Delay_D)*(1-EXP(-Rho_a*LN((Cap_top-D7)/(Cap_top-Floor_F))/Delta_a))/Rho_a+EXP(-Rho_a*LN((Cap_top-D7)/(Cap_top-Floor_F))/Delta_a)*(-Cost_k*Delta_a*Floor_F/Rho_a),EXP(-Rho_a*LN(D7/Floor_F)/Delta_a)*(-Cost_k*Delta_a*Floor_F/Rho_a))+$E$3 -> -6.620032
A8: 2 | B8: =IF(E7<0,D7,B7) -> 42.495 | C8: =IF(E7<0,C7,D7) -> 54.99 | D8: =(B8+C8)/2 -> 48.7425 | E8: =IF(D8<Floor_F,-(Cost_k*Ubar_a+Delay_D)*(1-EXP(-Rho_a*LN((Cap_top-D8)/(Cap_top-Floor_F))/Delta_a))/Rho_a+EXP(-Rho_a*LN((Cap_top-D8)/(Cap_top-Floor_F))/Delta_a)*(-Cost_k*Delta_a*Floor_F/Rho_a),EXP(-Rho_a*LN(D8/Floor_F)/Delta_a)*(-Cost_k*Delta_a*Floor_F/Rho_a))+$E$3 -> 41.209232
A9: 3 | B9: =IF(E8<0,D8,B8) -> 42.495 | C9: =IF(E8<0,C8,D8) -> 48.7425 | D9: =(B9+C9)/2 -> 45.61875 | E9: =IF(D9<Floor_F,-(Cost_k*Ubar_a+Delay_D)*(1-EXP(-Rho_a*LN((Cap_top-D9)/(Cap_top-Floor_F))/Delta_a))/Rho_a+EXP(-Rho_a*LN((Cap_top-D9)/(Cap_top-Floor_F))/Delta_a)*(-Cost_k*Delta_a*Floor_F/Rho_a),EXP(-Rho_a*LN(D9/Floor_F)/Delta_a)*(-Cost_k*Delta_a*Floor_F/Rho_a))+$E$3 -> 15.961269
A10: 4 | B10: =IF(E9<0,D9,B9) -> 42.495 | C10: =IF(E9<0,C9,D9) -> 45.61875 | D10: =(B10+C10)/2 -> 44.056875 | E10: =IF(D10<Floor_F,-(Cost_k*Ubar_a+Delay_D)*(1-EXP(-Rho_a*LN((Cap_top-D10)/(Cap_top-Floor_F))/Delta_a))/Rho_a+EXP(-Rho_a*LN((Cap_top-D10)/(Cap_top-Floor_F))/Delta_a)*(-Cost_k*Delta_a*Floor_F/Rho_a),EXP(-Rho_a*LN(D10/Floor_F)/Delta_a)*(-Cost_k*Delta_a*Floor_F/Rho_a))+$E$3 -> 4.3646691
A11: 5 | B11: =IF(E10<0,D10,B10) -> 42.495 | C11: =IF(E10<0,C10,D10) -> 44.056875 | D11: =(B11+C11)/2 -> 43.275937 | E11: =IF(D11<Floor_F,-(Cost_k*Ubar_a+Delay_D)*(1-EXP(-Rho_a*LN((Cap_top-D11)/(Cap_top-Floor_F))/Delta_a))/Rho_a+EXP(-Rho_a*LN((Cap_top-D11)/(Cap_top-Floor_F))/Delta_a)*(-Cost_k*Delta_a*Floor_F/Rho_a),EXP(-Rho_a*LN(D11/Floor_F)/Delta_a)*(-Cost_k*Delta_a*Floor_F/Rho_a))+$E$3 -> -1.2010711
A12: 6 | B12: =IF(E11<0,D11,B11) -> 43.275937 | C12: =IF(E11<0,C11,D11) -> 44.056875 | D12: =(B12+C12)/2 -> 43.666406 | E12: =IF(D12<Floor_F,-(Cost_k*Ubar_a+Delay_D)*(1-EXP(-Rho_a*LN((Cap_top-D12)/(Cap_top-Floor_F))/Delta_a))/Rho_a+EXP(-Rho_a*LN((Cap_top-D12)/(Cap_top-Floor_F))/Delta_a)*(-Cost_k*Delta_a*Floor_F/Rho_a),EXP(-Rho_a*LN(D12/Floor_F)/Delta_a)*(-Cost_k*Delta_a*Floor_F/Rho_a))+$E$3 -> 1.5630776
A13: 7 | B13: =IF(E12<0,D12,B12) -> 43.275937 | C13: =IF(E12<0,C12,D12) -> 43.666406 | D13: =(B13+C13)/2 -> 43.471172 | E13: =IF(D13<Floor_F,-(Cost_k*Ubar_a+Delay_D)*(1-EXP(-Rho_a*LN((Cap_top-D13)/(Cap_top-Floor_F))/Delta_a))/Rho_a+EXP(-Rho_a*LN((Cap_top-D13)/(Cap_top-Floor_F))/Delta_a)*(-Cost_k*Delta_a*Floor_F/Rho_a),EXP(-Rho_a*LN(D13/Floor_F)/Delta_a)*(-Cost_k*Delta_a*Floor_F/Rho_a))+$E$3 -> 0.17637046
A14: 8 | B14: =IF(E13<0,D13,B13) -> 43.275937 | C14: =IF(E13<0,C13,D13) -> 43.471172 | D14: =(B14+C14)/2 -> 43.373555 | E14: =IF(D14<Floor_F,-(Cost_k*Ubar_a+Delay_D)*(1-EXP(-Rho_a*LN((Cap_top-D14)/(Cap_top-Floor_F))/Delta_a))/Rho_a+EXP(-Rho_a*LN((Cap_top-D14)/(Cap_top-Floor_F))/Delta_a)*(-Cost_k*Delta_a*Floor_F/Rho_a),EXP(-Rho_a*LN(D14/Floor_F)/Delta_a)*(-Cost_k*Delta_a*Floor_F/Rho_a))+$E$3 -> -0.51350264
A15: 9 | B15: =IF(E14<0,D14,B14) -> 43.373555 | C15: =IF(E14<0,C14,D14) -> 43.471172 | D15: =(B15+C15)/2 -> 43.422363 | E15: =IF(D15<Floor_F,-(Cost_k*Ubar_a+Delay_D)*(1-EXP(-Rho_a*LN((Cap_top-D15)/(Cap_top-Floor_F))/Delta_a))/Rho_a+EXP(-Rho_a*LN((Cap_top-D15)/(Cap_top-Floor_F))/Delta_a)*(-Cost_k*Delta_a*Floor_F/Rho_a),EXP(-Rho_a*LN(D15/Floor_F)/Delta_a)*(-Cost_k*Delta_a*Floor_F/Rho_a))+$E$3 -> -0.1688549
A16: 10 | B16: =IF(E15<0,D15,B15) -> 43.422363 | C16: =IF(E15<0,C15,D15) -> 43.471172 | D16: =(B16+C16)/2 -> 43.446768 | E16: =IF(D16<Floor_F,-(Cost_k*Ubar_a+Delay_D)*(1-EXP(-Rho_a*LN((Cap_top-D16)/(Cap_top-Floor_F))/Delta_a))/Rho_a+EXP(-Rho_a*LN((Cap_top-D16)/(Cap_top-Floor_F))/Delta_a)*(-Cost_k*Delta_a*Floor_F/Rho_a),EXP(-Rho_a*LN(D16/Floor_F)/Delta_a)*(-Cost_k*Delta_a*Floor_F/Rho_a))+$E$3 -> 0.0036854824
A17: 11 | B17: =IF(E16<0,D16,B16) -> 43.422363 | C17: =IF(E16<0,C16,D16) -> 43.446768 | D17: =(B17+C17)/2 -> 43.434565 | E17: =IF(D17<Floor_F,-(Cost_k*Ubar_a+Delay_D)*(1-EXP(-Rho_a*LN((Cap_top-D17)/(Cap_top-Floor_F))/Delta_a))/Rho_a+EXP(-Rho_a*LN((Cap_top-D17)/(Cap_top-Floor_F))/Delta_a)*(-Cost_k*Delta_a*Floor_F/Rho_a),EXP(-Rho_a*LN(D17/Floor_F)/Delta_a)*(-Cost_k*Delta_a*Floor_F/Rho_a))+$E$3 -> -0.082602773
A18: 12 | B18: =IF(E17<0,D17,B17) -> 43.434565 | C18: =IF(E17<0,C17,D17) -> 43.446768 | D18: =(B18+C18)/2 -> 43.440667 | E18: =IF(D18<Floor_F,-(Cost_k*Ubar_a+Delay_D)*(1-EXP(-Rho_a*LN((Cap_top-D18)/(Cap_top-Floor_F))/Delta_a))/Rho_a+EXP(-Rho_a*LN((Cap_top-D18)/(Cap_top-Floor_F))/Delta_a)*(-Cost_k*Delta_a*Floor_F/Rho_a),EXP(-Rho_a*LN(D18/Floor_F)/Delta_a)*(-Cost_k*Delta_a*Floor_F/Rho_a))+$E$3 -> -0.039463162
A19: 13 | B19: =IF(E18<0,D18,B18) -> 43.440667 | C19: =IF(E18<0,C18,D18) -> 43.446768 | D19: =(B19+C19)/2 -> 43.443717 | E19: =IF(D19<Floor_F,-(Cost_k*Ubar_a+Delay_D)*(1-EXP(-Rho_a*LN((Cap_top-D19)/(Cap_top-Floor_F))/Delta_a))/Rho_a+EXP(-Rho_a*LN((Cap_top-D19)/(Cap_top-Floor_F))/Delta_a)*(-Cost_k*Delta_a*Floor_F/Rho_a),EXP(-Rho_a*LN(D19/Floor_F)/Delta_a)*(-Cost_k*Delta_a*Floor_F/Rho_a))+$E$3 -> -0.017889969
... A56: 50 | B56: =IF(E55<0,D55,B55) -> 43.446247 | C56: =IF(E55<0,C55,D55) -> 43.446247 | D56: =(B56+C56)/2 -> 43.446247 | E56: =IF(D56<Floor_F,-(Cost_k*Ubar_a+Delay_D)*(1-EXP(-Rho_a*LN((Cap_top-D56)/(Cap_top-Floor_F))/Delta_a))/Rho_a+EXP(-Rho_a*LN((Cap_top-D56)/(Cap_top-Floor_F))/Delta_a)*(-Cost_k*Delta_a*Floor_F/Rho_a),EXP(-Rho_a*LN(D56/Floor_F)/Delta_a)*(-Cost_k*Delta_a*Floor_F/Rho_a))+$E$3 -> 0
A58: c_a: racing beats never starting the build above it | E58: =D56 -> 43.446247
A59: Smallest price of a point below the floor, at c_a (it exceeds the $4 million cost) | E59: =IF(E58<Floor_F,EXP(-Rho_a*LN((Cap_top-E58)/(Cap_top-Floor_F))/Delta_a)*(Cost_k*Ubar_a+Delay_D+Rho_a*(-Cost_k*Delta_a*Floor_F/Rho_a))/(Ubar_a-Delta_a*E58),IF(E58=Floor_F,Cost_k,EXP(-Rho_a*LN(E58/Floor_F)/Delta_a)*(-Rho_a*(-Cost_k*Delta_a*Floor_F/Rho_a))/(Delta_a*E58))) -> 7.0729169
A61: Capability c | B61: V(c) | C61: V'(c) | D61: Delay running | E61: Best of {0, cap} | F61: rho V - best
A62: 44 | B62: =IF(A62<Floor_F,-(Cost_k*Ubar_a+Delay_D)*(1-EXP(-Rho_a*LN((Cap_top-A62)/(Cap_top-Floor_F))/Delta_a))/Rho_a+EXP(-Rho_a*LN((Cap_top-A62)/(Cap_top-Floor_F))/Delta_a)*(-Cost_k*Delta_a*Floor_F/Rho_a),EXP(-Rho_a*LN(A62/Floor_F)/Delta_a)*(-Cost_k*Delta_a*Floor_F/Rho_a)) -> -331.79164 | C62: =IF(A62<Floor_F,EXP(-Rho_a*LN((Cap_top-A62)/(Cap_top-Floor_F))/Delta_a)*(Cost_k*Ubar_a+Delay_D+Rho_a*(-Cost_k*Delta_a*Floor_F/Rho_a))/(Ubar_a-Delta_a*A62),IF(A62=Floor_F,Cost_k,EXP(-Rho_a*LN(A62/Floor_F)/Delta_a)*(-Rho_a*(-Cost_k*Delta_a*Floor_F/Rho_a))/(Delta_a*A62))) -> 7.2093121 | D62: =IF(A62<Floor_F,1,0) -> 1 | E62: =MAX(-Delay_D*D62-C62*Delta_a*A62,-Cost_k*Ubar_a-Delay_D*D62+C62*(Ubar_a-Delta_a*A62)) -> -31.623121 | F62: =Rho_a*B62-E62 -> 0
A63: 46 | B63: =IF(A63<Floor_F,-(Cost_k*Ubar_a+Delay_D)*(1-EXP(-Rho_a*LN((Cap_top-A63)/(Cap_top-Floor_F))/Delta_a))/Rho_a+EXP(-Rho_a*LN((Cap_top-A63)/(Cap_top-Floor_F))/Delta_a)*(-Cost_k*Delta_a*Floor_F/Rho_a),EXP(-Rho_a*LN(A63/Floor_F)/Delta_a)*(-Cost_k*Delta_a*Floor_F/Rho_a)) -> -316.85509 | C63: =IF(A63<Floor_F,EXP(-Rho_a*LN((Cap_top-A63)/(Cap_top-Floor_F))/Delta_a)*(Cost_k*Ubar_a+Delay_D+Rho_a*(-Cost_k*Delta_a*Floor_F/Rho_a))/(Ubar_a-Delta_a*A63),IF(A63=Floor_F,Cost_k,EXP(-Rho_a*LN(A63/Floor_F)/Delta_a)*(-Rho_a*(-Cost_k*Delta_a*Floor_F/Rho_a))/(Delta_a*A63))) -> 7.7366451 | D63: =IF(A63<Floor_F,1,0) -> 1 | E63: =MAX(-Delay_D*D63-C63*Delta_a*A63,-Cost_k*Ubar_a-Delay_D*D63+C63*(Ubar_a-Delta_a*A63)) -> -30.199515 | F63: =Rho_a*B63-E63 -> 0
A64: 48 | B64: =IF(A64<Floor_F,-(Cost_k*Ubar_a+Delay_D)*(1-EXP(-Rho_a*LN((Cap_top-A64)/(Cap_top-Floor_F))/Delta_a))/Rho_a+EXP(-Rho_a*LN((Cap_top-A64)/(Cap_top-Floor_F))/Delta_a)*(-Cost_k*Delta_a*Floor_F/Rho_a),EXP(-Rho_a*LN(A64/Floor_F)/Delta_a)*(-Cost_k*Delta_a*Floor_F/Rho_a)) -> -300.80462 | C64: =IF(A64<Floor_F,EXP(-Rho_a*LN((Cap_top-A64)/(Cap_top-Floor_F))/Delta_a)*(Cost_k*Ubar_a+Delay_D+Rho_a*(-Cost_k*Delta_a*Floor_F/Rho_a))/(Ubar_a-Delta_a*A64),IF(A64=Floor_F,Cost_k,EXP(-Rho_a*LN(A64/Floor_F)/Delta_a)*(-Rho_a*(-Cost_k*Delta_a*Floor_F/Rho_a))/(Delta_a*A64))) -> 8.3247027 | D64: =IF(A64<Floor_F,1,0) -> 1 | E64: =MAX(-Delay_D*D64-C64*Delta_a*A64,-Cost_k*Ubar_a-Delay_D*D64+C64*(Ubar_a-Delta_a*A64)) -> -28.669742 | F64: =Rho_a*B64-E64 -> 0
A65: 50 | B65: =IF(A65<Floor_F,-(Cost_k*Ubar_a+Delay_D)*(1-EXP(-Rho_a*LN((Cap_top-A65)/(Cap_top-Floor_F))/Delta_a))/Rho_a+EXP(-Rho_a*LN((Cap_top-A65)/(Cap_top-Floor_F))/Delta_a)*(-Cost_k*Delta_a*Floor_F/Rho_a),EXP(-Rho_a*LN(A65/Floor_F)/Delta_a)*(-Cost_k*Delta_a*Floor_F/Rho_a)) -> -283.50934 | C65: =IF(A65<Floor_F,EXP(-Rho_a*LN((Cap_top-A65)/(Cap_top-Floor_F))/Delta_a)*(Cost_k*Ubar_a+Delay_D+Rho_a*(-Cost_k*Delta_a*Floor_F/Rho_a))/(Ubar_a-Delta_a*A65),IF(A65=Floor_F,Cost_k,EXP(-Rho_a*LN(A65/Floor_F)/Delta_a)*(-Rho_a*(-Cost_k*Delta_a*Floor_F/Rho_a))/(Delta_a*A65))) -> 8.9832356 | D65: =IF(A65<Floor_F,1,0) -> 1 | E65: =MAX(-Delay_D*D65-C65*Delta_a*A65,-Cost_k*Ubar_a-Delay_D*D65+C65*(Ubar_a-Delta_a*A65)) -> -27.021326 | F65: =Rho_a*B65-E65 -> 0
A66: 52 | B66: =IF(A66<Floor_F,-(Cost_k*Ubar_a+Delay_D)*(1-EXP(-Rho_a*LN((Cap_top-A66)/(Cap_top-Floor_F))/Delta_a))/Rho_a+EXP(-Rho_a*LN((Cap_top-A66)/(Cap_top-Floor_F))/Delta_a)*(-Cost_k*Delta_a*Floor_F/Rho_a),EXP(-Rho_a*LN(A66/Floor_F)/Delta_a)*(-Cost_k*Delta_a*Floor_F/Rho_a)) -> -264.81688 | C66: =IF(A66<Floor_F,EXP(-Rho_a*LN((Cap_top-A66)/(Cap_top-Floor_F))/Delta_a)*(Cost_k*Ubar_a+Delay_D+Rho_a*(-Cost_k*Delta_a*Floor_F/Rho_a))/(Ubar_a-Delta_a*A66),IF(A66=Floor_F,Cost_k,EXP(-Rho_a*LN(A66/Floor_F)/Delta_a)*(-Rho_a*(-Cost_k*Delta_a*Floor_F/Rho_a))/(Delta_a*A66))) -> 9.7240408 | D66: =IF(A66<Floor_F,1,0) -> 1 | E66: =MAX(-Delay_D*D66-C66*Delta_a*A66,-Cost_k*Ubar_a-Delay_D*D66+C66*(Ubar_a-Delta_a*A66)) -> -25.239745 | F66: =Rho_a*B66-E66 -> 0
A67: 53 | B67: =IF(A67<Floor_F,-(Cost_k*Ubar_a+Delay_D)*(1-EXP(-Rho_a*LN((Cap_top-A67)/(Cap_top-Floor_F))/Delta_a))/Rho_a+EXP(-Rho_a*LN((Cap_top-A67)/(Cap_top-Floor_F))/Delta_a)*(-Cost_k*Delta_a*Floor_F/Rho_a),EXP(-Rho_a*LN(A67/Floor_F)/Delta_a)*(-Cost_k*Delta_a*Floor_F/Rho_a)) -> -254.89212 | C67: =IF(A67<Floor_F,EXP(-Rho_a*LN((Cap_top-A67)/(Cap_top-Floor_F))/Delta_a)*(Cost_k*Ubar_a+Delay_D+Rho_a*(-Cost_k*Delta_a*Floor_F/Rho_a))/(Ubar_a-Delta_a*A67),IF(A67=Floor_F,Cost_k,EXP(-Rho_a*LN(A67/Floor_F)/Delta_a)*(-Rho_a*(-Cost_k*Delta_a*Floor_F/Rho_a))/(Delta_a*A67))) -> 10.129671 | D67: =IF(A67<Floor_F,1,0) -> 1 | E67: =MAX(-Delay_D*D67-C67*Delta_a*A67,-Cost_k*Ubar_a-Delay_D*D67+C67*(Ubar_a-Delta_a*A67)) -> -24.293814 | F67: =Rho_a*B67-E67 -> 0
A68: 54 | B68: =IF(A68<Floor_F,-(Cost_k*Ubar_a+Delay_D)*(1-EXP(-Rho_a*LN((Cap_top-A68)/(Cap_top-Floor_F))/Delta_a))/Rho_a+EXP(-Rho_a*LN((Cap_top-A68)/(Cap_top-Floor_F))/Delta_a)*(-Cost_k*Delta_a*Floor_F/Rho_a),EXP(-Rho_a*LN(A68/Floor_F)/Delta_a)*(-Cost_k*Delta_a*Floor_F/Rho_a)) -> -244.54881 | C68: =IF(A68<Floor_F,EXP(-Rho_a*LN((Cap_top-A68)/(Cap_top-Floor_F))/Delta_a)*(Cost_k*Ubar_a+Delay_D+Rho_a*(-Cost_k*Delta_a*Floor_F/Rho_a))/(Ubar_a-Delta_a*A68),IF(A68=Floor_F,Cost_k,EXP(-Rho_a*LN(A68/Floor_F)/Delta_a)*(-Rho_a*(-Cost_k*Delta_a*Floor_F/Rho_a))/(Delta_a*A68))) -> 10.5615 | D68: =IF(A68<Floor_F,1,0) -> 1 | E68: =MAX(-Delay_D*D68-C68*Delta_a*A68,-Cost_k*Ubar_a-Delay_D*D68+C68*(Ubar_a-Delta_a*A68)) -> -23.307991 | F68: =Rho_a*B68-E68 -> 0
A69: 54.5 | B69: =IF(A69<Floor_F,-(Cost_k*Ubar_a+Delay_D)*(1-EXP(-Rho_a*LN((Cap_top-A69)/(Cap_top-Floor_F))/Delta_a))/Rho_a+EXP(-Rho_a*LN((Cap_top-A69)/(Cap_top-Floor_F))/Delta_a)*(-Cost_k*Delta_a*Floor_F/Rho_a),EXP(-Rho_a*LN(A69/Floor_F)/Delta_a)*(-Cost_k*Delta_a*Floor_F/Rho_a)) -> -239.21175 | C69: =IF(A69<Floor_F,EXP(-Rho_a*LN((Cap_top-A69)/(Cap_top-Floor_F))/Delta_a)*(Cost_k*Ubar_a+Delay_D+Rho_a*(-Cost_k*Delta_a*Floor_F/Rho_a))/(Ubar_a-Delta_a*A69),IF(A69=Floor_F,Cost_k,EXP(-Rho_a*LN(A69/Floor_F)/Delta_a)*(-Rho_a*(-Cost_k*Delta_a*Floor_F/Rho_a))/(Delta_a*A69))) -> 10.787954 | D69: =IF(A69<Floor_F,1,0) -> 1 | E69: =MAX(-Delay_D*D69-C69*Delta_a*A69,-Cost_k*Ubar_a-Delay_D*D69+C69*(Ubar_a-Delta_a*A69)) -> -22.799315 | F69: =Rho_a*B69-E69 -> 0
A70: 54.9 | B70: =IF(A70<Floor_F,-(Cost_k*Ubar_a+Delay_D)*(1-EXP(-Rho_a*LN((Cap_top-A70)/(Cap_top-Floor_F))/Delta_a))/Rho_a+EXP(-Rho_a*LN((Cap_top-A70)/(Cap_top-Floor_F))/Delta_a)*(-Cost_k*Delta_a*Floor_F/Rho_a),EXP(-Rho_a*LN(A70/Floor_F)/Delta_a)*(-Cost_k*Delta_a*Floor_F/Rho_a)) -> -234.85943 | C70: =IF(A70<Floor_F,EXP(-Rho_a*LN((Cap_top-A70)/(Cap_top-Floor_F))/Delta_a)*(Cost_k*Ubar_a+Delay_D+Rho_a*(-Cost_k*Delta_a*Floor_F/Rho_a))/(Ubar_a-Delta_a*A70),IF(A70=Floor_F,Cost_k,EXP(-Rho_a*LN(A70/Floor_F)/Delta_a)*(-Rho_a*(-Cost_k*Delta_a*Floor_F/Rho_a))/(Delta_a*A70))) -> 10.974458 | D70: =IF(A70<Floor_F,1,0) -> 1 | E70: =MAX(-Delay_D*D70-C70*Delta_a*A70,-Cost_k*Ubar_a-Delay_D*D70+C70*(Ubar_a-Delta_a*A70)) -> -22.384494 | F70: =Rho_a*B70-E70 -> 0
A71: 55.5 | B71: =IF(A71<Floor_F,-(Cost_k*Ubar_a+Delay_D)*(1-EXP(-Rho_a*LN((Cap_top-A71)/(Cap_top-Floor_F))/Delta_a))/Rho_a+EXP(-Rho_a*LN((Cap_top-A71)/(Cap_top-Floor_F))/Delta_a)*(-Cost_k*Delta_a*Floor_F/Rho_a),EXP(-Rho_a*LN(A71/Floor_F)/Delta_a)*(-Cost_k*Delta_a*Floor_F/Rho_a)) -> -231.77711 | C71: =IF(A71<Floor_F,EXP(-Rho_a*LN((Cap_top-A71)/(Cap_top-Floor_F))/Delta_a)*(Cost_k*Ubar_a+Delay_D+Rho_a*(-Cost_k*Delta_a*Floor_F/Rho_a))/(Ubar_a-Delta_a*A71),IF(A71=Floor_F,Cost_k,EXP(-Rho_a*LN(A71/Floor_F)/Delta_a)*(-Rho_a*(-Cost_k*Delta_a*Floor_F/Rho_a))/(Delta_a*A71))) -> 3.9303457 | D71: =IF(A71<Floor_F,1,0) -> 0 | E71: =MAX(-Delay_D*D71-C71*Delta_a*A71,-Cost_k*Ubar_a-Delay_D*D71+C71*(Ubar_a-Delta_a*A71)) -> -22.090718 | F71: =Rho_a*B71-E71 -> 0
A72: 56 | B72: =IF(A72<Floor_F,-(Cost_k*Ubar_a+Delay_D)*(1-EXP(-Rho_a*LN((Cap_top-A72)/(Cap_top-Floor_F))/Delta_a))/Rho_a+EXP(-Rho_a*LN((Cap_top-A72)/(Cap_top-Floor_F))/Delta_a)*(-Cost_k*Delta_a*Floor_F/Rho_a),EXP(-Rho_a*LN(A72/Floor_F)/Delta_a)*(-Cost_k*Delta_a*Floor_F/Rho_a)) -> -229.82897 | C72: =IF(A72<Floor_F,EXP(-Rho_a*LN((Cap_top-A72)/(Cap_top-Floor_F))/Delta_a)*(Cost_k*Ubar_a+Delay_D+Rho_a*(-Cost_k*Delta_a*Floor_F/Rho_a))/(Ubar_a-Delta_a*A72),IF(A72=Floor_F,Cost_k,EXP(-Rho_a*LN(A72/Floor_F)/Delta_a)*(-Rho_a*(-Cost_k*Delta_a*Floor_F/Rho_a))/(Delta_a*A72))) -> 3.8625128 | D72: =IF(A72<Floor_F,1,0) -> 0 | E72: =MAX(-Delay_D*D72-C72*Delta_a*A72,-Cost_k*Ubar_a-Delay_D*D72+C72*(Ubar_a-Delta_a*A72)) -> -21.90504 | F72: =Rho_a*B72-E72 -> 0
A73: 57 | B73: =IF(A73<Floor_F,-(Cost_k*Ubar_a+Delay_D)*(1-EXP(-Rho_a*LN((Cap_top-A73)/(Cap_top-Floor_F))/Delta_a))/Rho_a+EXP(-Rho_a*LN((Cap_top-A73)/(Cap_top-Floor_F))/Delta_a)*(-Cost_k*Delta_a*Floor_F/Rho_a),EXP(-Rho_a*LN(A73/Floor_F)/Delta_a)*(-Cost_k*Delta_a*Floor_F/Rho_a)) -> -226.03225 | C73: =IF(A73<Floor_F,EXP(-Rho_a*LN((Cap_top-A73)/(Cap_top-Floor_F))/Delta_a)*(Cost_k*Ubar_a+Delay_D+Rho_a*(-Cost_k*Delta_a*Floor_F/Rho_a))/(Ubar_a-Delta_a*A73),IF(A73=Floor_F,Cost_k,EXP(-Rho_a*LN(A73/Floor_F)/Delta_a)*(-Rho_a*(-Cost_k*Delta_a*Floor_F/Rho_a))/(Delta_a*A73))) -> 3.7320611 | D73: =IF(A73<Floor_F,1,0) -> 0 | E73: =MAX(-Delay_D*D73-C73*Delta_a*A73,-Cost_k*Ubar_a-Delay_D*D73+C73*(Ubar_a-Delta_a*A73)) -> -21.543174 | F73: =Rho_a*B73-E73 -> 0
... A78: 70 | B78: =IF(A78<Floor_F,-(Cost_k*Ubar_a+Delay_D)*(1-EXP(-Rho_a*LN((Cap_top-A78)/(Cap_top-Floor_F))/Delta_a))/Rho_a+EXP(-Rho_a*LN((Cap_top-A78)/(Cap_top-Floor_F))/Delta_a)*(-Cost_k*Delta_a*Floor_F/Rho_a),EXP(-Rho_a*LN(A78/Floor_F)/Delta_a)*(-Cost_k*Delta_a*Floor_F/Rho_a)) -> -186.2941 | C78: =IF(A78<Floor_F,EXP(-Rho_a*LN((Cap_top-A78)/(Cap_top-Floor_F))/Delta_a)*(Cost_k*Ubar_a+Delay_D+Rho_a*(-Cost_k*Delta_a*Floor_F/Rho_a))/(Ubar_a-Delta_a*A78),IF(A78=Floor_F,Cost_k,EXP(-Rho_a*LN(A78/Floor_F)/Delta_a)*(-Rho_a*(-Cost_k*Delta_a*Floor_F/Rho_a))/(Delta_a*A78))) -> 2.5046915 | D78: =IF(A78<Floor_F,1,0) -> 0 | E78: =MAX(-Delay_D*D78-C78*Delta_a*A78,-Cost_k*Ubar_a-Delay_D*D78+C78*(Ubar_a-Delta_a*A78)) -> -17.755724 | F78: =Rho_a*B78-E78 -> 0
A79: Largest residual: the closed form satisfies the condition at every level above c_a | F79: =MAX(ABS(MAX(F62:F78)),ABS(MIN(F62:F78))) -> 0
A81: Hiring the rebuild needs: k u bar (1 - exp(-rho tau))/rho | B81: =Cost_k*Ubar_a*(1-EXP(-Rho_a*Tau_race))/Rho_a -> 17.042921 | C81: $17.0 million
A82: The build's delay: D (1 - exp(-rho tau))/rho | B82: =Delay_D*(1-EXP(-Rho_a*Tau_race))/Rho_a -> 13.463189 | C82: $13.5 million
A83: The rent starts later | B83: =(EXP(-Rho_a*Tau_race)-EXP(-Rho_a*Tau_drift))*-V_F -> 2.0233513 | C83: $2.0 million
A84: The team: V(58) - V(53) | B84: =SUM(B81:B83) -> 32.529461 | C84: $32.5 million
A85: Net of the buyer's $20 million: keep the team by | B85: =B84-(Proc_gone-Proc_kept) -> 12.529461 | C85: $12.5 million
A87: The team-kept plan is certified by Theorem 6.3 (linear Hamiltonian and floor; the floor's multiplier is the user cost). The race is certified by its closed form, as above.

Sheet Compare
A1: Compare: test the declarations, record the team's value (AXIOM Lab 2.6, step 5; Worked Example 6.1, Step 6)
A3: Declaration | B3: Base | C3: Attrition 6% a year | D3: Attrition 11% a year | E3: Cap 2.0 a quarter | F3: Delay $4m a quarter | G3: Delay $16m a quarter | H3: Floor 60
A4: Attrition a year | B4: =1-(1-Attr_q)^4 -> 0.096312109 | C4: 0.06 | D4: 0.11 | E4: =$B$4 -> 0.096312109 | F4: =$B$4 -> 0.096312109 | G4: =$B$4 -> 0.096312109 | H4: =$B$4 -> 0.096312109
A5: Attrition a quarter | B5: =1-(1-B4)^(1/4) -> 0.025 | C5: =1-(1-C4)^(1/4) -> 0.015349823 | D5: =1-(1-D4)^(1/4) -> 0.028713166 | E5: =1-(1-E4)^(1/4) -> 0.025 | F5: =1-(1-F4)^(1/4) -> 0.025 | G5: =1-(1-G4)^(1/4) -> 0.025 | H5: =1-(1-H4)^(1/4) -> 0.025
A6: delta | B6: =-LN(1-B4) -> 0.10127123 | C6: =-LN(1-C4) -> 0.061875404 | D6: =-LN(1-D4) -> 0.11653382 | E6: =-LN(1-E4) -> 0.10127123 | F6: =-LN(1-F4) -> 0.10127123 | G6: =-LN(1-G4) -> 0.10127123 | H6: =-LN(1-H4) -> 0.10127123
A7: Hiring cap a quarter (points) | B7: =Cap_q -> 2.5 | C7: 2.5 | D7: 2.5 | E7: 2 | F7: =$B$7 -> 2.5 | G7: =$B$7 -> 2.5 | H7: =$B$7 -> 2.5
A8: Ceiling, cap / quarterly attrition | B8: =B7/B5 -> 100 | C8: =C7/C5 -> 162.86833 | D8: =D7/D5 -> 87.068071 | E8: =E7/E5 -> 80 | F8: =F7/F5 -> 100 | G8: =G7/G5 -> 100 | H8: =H7/H5 -> 100
A9: u bar | B9: =B8*B6 -> 10.127123 | C9: =C8*C6 -> 10.077544 | D9: =D8*D6 -> 10.146375 | E9: =E8*E6 -> 8.1016986 | F9: =F8*F6 -> 10.127123 | G9: =G8*G6 -> 10.127123 | H9: =H8*H6 -> 10.127123
A10: A quarter of delay | B10: =Delay_q -> 8 | C10: =$B$10 -> 8 | D10: =$B$10 -> 8 | E10: =$B$10 -> 8 | F10: 4 | G10: 16 | H10: =$B$10 -> 8
A11: D, delay a year | B11: =4*B10 -> 32 | C11: =4*C10 -> 32 | D11: =4*D10 -> 32 | E11: =4*E10 -> 32 | F11: =4*F10 -> 16 | G11: =4*G10 -> 64 | H11: =4*H10 -> 32
A12: Floor | B12: =Floor_F -> 55 | C12: =$B$12 -> 55 | D12: =$B$12 -> 55 | E12: =$B$12 -> 55 | F12: =$B$12 -> 55 | G12: =$B$12 -> 55 | H12: 60
A13: k | B13: =Cost_k -> 4 | C13: =Cost_k -> 4 | D13: =Cost_k -> 4 | E13: =Cost_k -> 4 | F13: =Cost_k -> 4 | G13: =Cost_k -> 4 | H13: =Cost_k -> 4
A14: rho | B14: =Rho_a -> 0.09531018 | C14: =Rho_a -> 0.09531018 | D14: =Rho_a -> 0.09531018 | E14: =Rho_a -> 0.09531018 | F14: =Rho_a -> 0.09531018 | G14: =Rho_a -> 0.09531018 | H14: =Rho_a -> 0.09531018
A16: Race from 53 to the floor (quarters) | B16: =4*IF(C_gone<B12,LN((B8-C_gone)/(B8-B12))/B6,0) -> 1.7175702 | C16: =4*IF(C_gone<C12,LN((C8-C_gone)/(C8-C12))/C6,0) -> 1.1876339 | D16: =4*IF(C_gone<D12,LN((D8-C_gone)/(D8-D12))/D6,0) -> 2.0766418 | E16: =4*IF(C_gone<E12,LN((E8-C_gone)/(E8-E12))/E6,0) -> 3.0397988 | F16: =4*IF(C_gone<F12,LN((F8-C_gone)/(F8-F12))/F6,0) -> 1.7175702 | G16: =4*IF(C_gone<G12,LN((G8-C_gone)/(G8-G12))/G6,0) -> 1.7175702 | H16: =4*IF(C_gone<H12,LN((H8-C_gone)/(H8-H12))/H6,0) -> 6.3697516
A17: Drift from 58 to the floor (quarters) | B17: =4*IF(C_kept>B12,LN(C_kept/B12)/B6,0) -> 2.097726 | C17: =4*IF(C_kept>C12,LN(C_kept/C12)/C6,0) -> 3.43334 | D17: =4*IF(C_kept>D12,LN(C_kept/D12)/D6,0) -> 1.8229842 | E17: =4*IF(C_kept>E12,LN(C_kept/E12)/E6,0) -> 2.097726 | F17: =4*IF(C_kept>F12,LN(C_kept/F12)/F6,0) -> 2.097726 | G17: =4*IF(C_kept>G12,LN(C_kept/G12)/G6,0) -> 2.097726 | H17: =4*IF(C_kept>H12,LN(C_kept/H12)/H6,0) -> 0
A18: V(53) | B18: =IF(C_gone<B12,-(B13*B9+B11)*(1-EXP(-B14*LN((B8-C_gone)/(B8-B12))/B6))/B14+EXP(-B14*LN((B8-C_gone)/(B8-B12))/B6)*(-B13*B6*B12/B14),EXP(-B14*LN(C_gone/B12)/B6)*(-B13*B6*B12/B14)) -> -254.89212 | C18: =IF(C_gone<C12,-(C13*C9+C11)*(1-EXP(-C14*LN((C8-C_gone)/(C8-C12))/C6))/C14+EXP(-C14*LN((C8-C_gone)/(C8-C12))/C6)*(-C13*C6*C12/C14),EXP(-C14*LN(C_gone/C12)/C6)*(-C13*C6*C12/C14)) -> -160.00761 | D18: =IF(C_gone<D12,-(D13*D9+D11)*(1-EXP(-D14*LN((D8-C_gone)/(D8-D12))/D6))/D14+EXP(-D14*LN((D8-C_gone)/(D8-D12))/D6)*(-D13*D6*D12/D14),EXP(-D14*LN(C_gone/D12)/D6)*(-D13*D6*D12/D14)) -> -292.7699 | E18: =IF(C_gone<E12,-(E13*E9+E11)*(1-EXP(-E14*LN((E8-C_gone)/(E8-E12))/E6))/E14+EXP(-E14*LN((E8-C_gone)/(E8-E12))/E6)*(-E13*E6*E12/E14),EXP(-E14*LN(C_gone/E12)/E6)*(-E13*E6*E12/E14)) -> -264.64218 | F18: =IF(C_gone<F12,-(F13*F9+F11)*(1-EXP(-F14*LN((F8-C_gone)/(F8-F12))/F6))/F14+EXP(-F14*LN((F8-C_gone)/(F8-F12))/F6)*(-F13*F6*F12/F14),EXP(-F14*LN(C_gone/F12)/F6)*(-F13*F6*F12/F14)) -> -248.16052 | G18: =IF(C_gone<G12,-(G13*G9+G11)*(1-EXP(-G14*LN((G8-C_gone)/(G8-G12))/G6))/G14+EXP(-G14*LN((G8-C_gone)/(G8-G12))/G6)*(-G13*G6*G12/G14),EXP(-G14*LN(C_gone/G12)/G6)*(-G13*G6*G12/G14)) -> -268.35531 | H18: =IF(C_gone<H12,-(H13*H9+H11)*(1-EXP(-H14*LN((H8-C_gone)/(H8-H12))/H6))/H14+EXP(-H14*LN((H8-C_gone)/(H8-H12))/H6)*(-H13*H6*H12/H14),EXP(-H14*LN(C_gone/H12)/H6)*(-H13*H6*H12/H14)) -> -326.23005
A19: V(58) | B19: =IF(C_kept<B12,-(B13*B9+B11)*(1-EXP(-B14*LN((B8-C_kept)/(B8-B12))/B6))/B14+EXP(-B14*LN((B8-C_kept)/(B8-B12))/B6)*(-B13*B6*B12/B14),EXP(-B14*LN(C_kept/B12)/B6)*(-B13*B6*B12/B14)) -> -222.36266 | C19: =IF(C_kept<C12,-(C13*C9+C11)*(1-EXP(-C14*LN((C8-C_kept)/(C8-C12))/C6))/C14+EXP(-C14*LN((C8-C_kept)/(C8-C12))/C6)*(-C13*C6*C12/C14),EXP(-C14*LN(C_kept/C12)/C6)*(-C13*C6*C12/C14)) -> -131.60508 | D19: =IF(C_kept<D12,-(D13*D9+D11)*(1-EXP(-D14*LN((D8-C_kept)/(D8-D12))/D6))/D14+EXP(-D14*LN((D8-C_kept)/(D8-D12))/D6)*(-D13*D6*D12/D14),EXP(-D14*LN(C_kept/D12)/D6)*(-D13*D6*D12/D14)) -> -257.55549 | E19: =IF(C_kept<E12,-(E13*E9+E11)*(1-EXP(-E14*LN((E8-C_kept)/(E8-E12))/E6))/E14+EXP(-E14*LN((E8-C_kept)/(E8-E12))/E6)*(-E13*E6*E12/E14),EXP(-E14*LN(C_kept/E12)/E6)*(-E13*E6*E12/E14)) -> -222.36266 | F19: =IF(C_kept<F12,-(F13*F9+F11)*(1-EXP(-F14*LN((F8-C_kept)/(F8-F12))/F6))/F14+EXP(-F14*LN((F8-C_kept)/(F8-F12))/F6)*(-F13*F6*F12/F14),EXP(-F14*LN(C_kept/F12)/F6)*(-F13*F6*F12/F14)) -> -222.36266 | G19: =IF(C_kept<G12,-(G13*G9+G11)*(1-EXP(-G14*LN((G8-C_kept)/(G8-G12))/G6))/G14+EXP(-G14*LN((G8-C_kept)/(G8-G12))/G6)*(-G13*G6*G12/G14),EXP(-G14*LN(C_kept/G12)/G6)*(-G13*G6*G12/G14)) -> -222.36266 | H19: =IF(C_kept<H12,-(H13*H9+H11)*(1-EXP(-H14*LN((H8-C_kept)/(H8-H12))/H6))/H14+EXP(-H14*LN((H8-C_kept)/(H8-H12))/H6)*(-H13*H6*H12/H14),EXP(-H14*LN(C_kept/H12)/H6)*(-H13*H6*H12/H14)) -> -277.70867
A20: The team: V(58) - V(53) | B20: =B19-B18 -> 32.529461 | C20: =C19-C18 -> 28.402534 | D20: =D19-D18 -> 35.214415 | E20: =E19-E18 -> 42.279525 | F20: =F19-F18 -> 25.797867 | G20: =G19-G18 -> 45.99265 | H20: =H19-H18 -> 48.521382
A21: Price of a point at 53 | B21: =IF(C_gone<B12,EXP(-B14*LN((B8-C_gone)/(B8-B12))/B6)*(B13*B9+B11+B14*(-B13*B6*B12/B14))/(B9-B6*C_gone),IF(C_gone=B12,B13,EXP(-B14*LN(C_gone/B12)/B6)*(-B14*(-B13*B6*B12/B14))/(B6*C_gone))) -> 10.129671 | C21: =IF(C_gone<C12,EXP(-C14*LN((C8-C_gone)/(C8-C12))/C6)*(C13*C9+C11+C14*(-C13*C6*C12/C14))/(C9-C6*C_gone),IF(C_gone=C12,C13,EXP(-C14*LN(C_gone/C12)/C6)*(-C14*(-C13*C6*C12/C14))/(C6*C_gone))) -> 8.3934369 | D21: =IF(C_gone<D12,EXP(-D14*LN((D8-C_gone)/(D8-D12))/D6)*(D13*D9+D11+D14*(-D13*D6*D12/D14))/(D9-D6*C_gone),IF(C_gone=D12,D13,EXP(-D14*LN(C_gone/D12)/D6)*(-D14*(-D13*D6*D12/D14))/(D6*C_gone))) -> 11.254564 | E21: =IF(C_gone<E12,EXP(-E14*LN((E8-C_gone)/(E8-E12))/E6)*(E13*E9+E11+E14*(-E13*E6*E12/E14))/(E9-E6*C_gone),IF(C_gone=E12,E13,EXP(-E14*LN(C_gone/E12)/E6)*(-E14*(-E13*E6*E12/E14))/(E6*C_gone))) -> 14.33031 | F21: =IF(C_gone<F12,EXP(-F14*LN((F8-C_gone)/(F8-F12))/F6)*(F13*F9+F11+F14*(-F13*F6*F12/F14))/(F9-F6*C_gone),IF(C_gone=F12,F13,EXP(-F14*LN(C_gone/F12)/F6)*(-F14*(-F13*F6*F12/F14))/(F6*C_gone))) -> 6.902943 | G21: =IF(C_gone<G12,EXP(-G14*LN((G8-C_gone)/(G8-G12))/G6)*(G13*G9+G11+G14*(-G13*G6*G12/G14))/(G9-G6*C_gone),IF(C_gone=G12,G13,EXP(-G14*LN(C_gone/G12)/G6)*(-G14*(-G13*G6*G12/G14))/(G6*C_gone))) -> 16.583126 | H21: =IF(C_gone<H12,EXP(-H14*LN((H8-C_gone)/(H8-H12))/H6)*(H13*H9+H11+H14*(-H13*H6*H12/H14))/(H9-H6*C_gone),IF(C_gone=H12,H13,EXP(-H14*LN(C_gone/H12)/H6)*(-H14*(-H13*H6*H12/H14))/(H6*C_gone))) -> 8.7011852
A22: Team kept: race from 58 to the floor (quarters) | B22: =4*IF(C_kept<B12,LN((B8-C_kept)/(B8-B12))/B6,0) -> 0 | C22: =4*IF(C_kept<C12,LN((C8-C_kept)/(C8-C12))/C6,0) -> 0 | D22: =4*IF(C_kept<D12,LN((D8-C_kept)/(D8-D12))/D6,0) -> 0 | E22: =4*IF(C_kept<E12,LN((E8-C_kept)/(E8-E12))/E6,0) -> 0 | F22: =4*IF(C_kept<F12,LN((F8-C_kept)/(F8-F12))/F6,0) -> 0 | G22: =4*IF(C_kept<G12,LN((G8-C_kept)/(G8-G12))/G6,0) -> 0 | H22: =4*IF(C_kept<H12,LN((H8-C_kept)/(H8-H12))/H6,0) -> 1.9271085
A24: Figures below a $20 million ask | B24: =COUNTIF(B20:H20,"<20") -> 0
A25: Figures below a $30 million ask | B25: =COUNTIF(B20:H20,"<30") -> 2
A26: A floor at 60: five points of margin cost a year | B26: =5*Eta_floor -> 3.9316282
A28: Attrition scenarios keep the cap at 2.5 points a quarter (Volume I's sensitivities); the floor at 60 answers a survey good to +/-5 points (Volume I, Worked Example 16.1).

Sheet CapitalProblems
A1: Two small capital problems: a rising cost and a linear one (Proposition 6.2; Figure 6.2; Online Appendix 6.B.2)
A2: Generic, not Meridian: one stock dx/dt = u - delta x earning v a year a unit, no terminal value. The costate m(t) = v/(rho + delta)(1 - exp(-(rho + delta)(T - t))) does not depend on the plan.
A3: Declaration | B3: Value | D3: Race to a level and hold it | E3: Value
A4: Earnings a year of a unit, v | B4: 1 | D4: Figure 6.2(c): the level held | E4: 60
A5: Decay, delta | B5: 0.1 | D5: Cap (units a year) | E5: 12
A6: Discount rate, rho | B6: 0.08 | D6: Decay | E6: 0.1
A7: Horizon T (years) | B7: 8
A8: Cost of a unit, k | B8: 3 | D8: From 35, building at the cap (years) | E8: =LN((E5/E6-35)/(E5/E6-E4))/E6 -> 3.4830669
A9: Investment cap (linear cost) | B9: 1 | D9: From 75, letting the stock decay (years) | E9: =LN(75/E4)/E6 -> 2.2314355
A10: Rising cost: k u + kappa u^2/2, kappa | B10: 4 | D10: Then the rent a year | E10: =E6*E4 -> 6
A12: Price of a unit at the start, m(0) | B12: =B4/(B5+B6)*(1-EXP(-(B5+B6)*B7)) -> 4.2392902
A13: Switch: the price falls through the cost at t_s | B13: =B7+LN(1-B8*(B5+B6)/B4)/(B5+B6) -> 3.6859512
A14: Rising cost: investment at the start, (m(0) - k)/kappa | B14: =(B12-B8)/B10 -> 0.30982256
A15: Marginal value of capital at the start: v times the integral of exp(-(rho + delta)t), Simpson's rule | B15: =B4*SUMPRODUCT(I20:I100,J20:J100) -> 4.2392902
A16: Linear cost: number of switches on the grid | B16: =SUMPRODUCT(--(G21:G100<>G20:G99)) -> 1
D19: Years | E19: Price m(t) | F19: Switching function m - k | G19: Linear cost: invest | H19: Rising cost: invest | I19: exp(-(rho + delta)t) | J19: Simpson weight
D20: 0 | E20: =$B$4/($B$5+$B$6)*(1-EXP(-($B$5+$B$6)*($B$7-D20))) -> 4.2392902 | F20: =E20-$B$8 -> 1.2392902 | G20: =IF(F20>0,$B$9,0) -> 1 | H20: =MAX(0,F20/$B$10) -> 0.30982256 | I20: =EXP(-($B$5+$B$6)*D20) -> 1 | J20: =1*0.1/3 -> 0.033333333
D21: 0.1 | E21: =$B$4/($B$5+$B$6)*(1-EXP(-($B$5+$B$6)*($B$7-D21))) -> 4.2153829 | F21: =E21-$B$8 -> 1.2153829 | G21: =IF(F21>0,$B$9,0) -> 1 | H21: =MAX(0,F21/$B$10) -> 0.30384573 | I21: =EXP(-($B$5+$B$6)*D21) -> 0.98216103 | J21: =4*0.1/3 -> 0.13333333
D22: 0.2 | E22: =$B$4/($B$5+$B$6)*(1-EXP(-($B$5+$B$6)*($B$7-D22))) -> 4.1910414 | F22: =E22-$B$8 -> 1.1910414 | G22: =IF(F22>0,$B$9,0) -> 1 | H22: =MAX(0,F22/$B$10) -> 0.29776035 | I22: =EXP(-($B$5+$B$6)*D22) -> 0.96464029 | J22: =2*0.1/3 -> 0.066666667
D23: 0.3 | E23: =$B$4/($B$5+$B$6)*(1-EXP(-($B$5+$B$6)*($B$7-D23))) -> 4.1662578 | F23: =E23-$B$8 -> 1.1662578 | G23: =IF(F23>0,$B$9,0) -> 1 | H23: =MAX(0,F23/$B$10) -> 0.29156444 | I23: =EXP(-($B$5+$B$6)*D23) -> 0.94743211 | J23: =4*0.1/3 -> 0.13333333
D24: 0.4 | E24: =$B$4/($B$5+$B$6)*(1-EXP(-($B$5+$B$6)*($B$7-D24))) -> 4.141024 | F24: =E24-$B$8 -> 1.141024 | G24: =IF(F24>0,$B$9,0) -> 1 | H24: =MAX(0,F24/$B$10) -> 0.285256 | I24: =EXP(-($B$5+$B$6)*D24) -> 0.9305309 | J24: =2*0.1/3 -> 0.066666667
D25: 0.5 | E25: =$B$4/($B$5+$B$6)*(1-EXP(-($B$5+$B$6)*($B$7-D25))) -> 4.1153319 | F25: =E25-$B$8 -> 1.1153319 | G25: =IF(F25>0,$B$9,0) -> 1 | H25: =MAX(0,F25/$B$10) -> 0.27883297 | I25: =EXP(-($B$5+$B$6)*D25) -> 0.91393119 | J25: =4*0.1/3 -> 0.13333333
D26: 0.6 | E26: =$B$4/($B$5+$B$6)*(1-EXP(-($B$5+$B$6)*($B$7-D26))) -> 4.0891731 | F26: =E26-$B$8 -> 1.0891731 | G26: =IF(F26>0,$B$9,0) -> 1 | H26: =MAX(0,F26/$B$10) -> 0.27229328 | I26: =EXP(-($B$5+$B$6)*D26) -> 0.8976276 | J26: =2*0.1/3 -> 0.066666667
D27: 0.7 | E27: =$B$4/($B$5+$B$6)*(1-EXP(-($B$5+$B$6)*($B$7-D27))) -> 4.0625393 | F27: =E27-$B$8 -> 1.0625393 | G27: =IF(F27>0,$B$9,0) -> 1 | H27: =MAX(0,F27/$B$10) -> 0.26563482 | I27: =EXP(-($B$5+$B$6)*D27) -> 0.88161485 | J27: =4*0.1/3 -> 0.13333333
D28: 0.8 | E28: =$B$4/($B$5+$B$6)*(1-EXP(-($B$5+$B$6)*($B$7-D28))) -> 4.0354216 | F28: =E28-$B$8 -> 1.0354216 | G28: =IF(F28>0,$B$9,0) -> 1 | H28: =MAX(0,F28/$B$10) -> 0.25885541 | I28: =EXP(-($B$5+$B$6)*D28) -> 0.86588775 | J28: =2*0.1/3 -> 0.066666667
D29: 0.9 | E29: =$B$4/($B$5+$B$6)*(1-EXP(-($B$5+$B$6)*($B$7-D29))) -> 4.0078115 | F29: =E29-$B$8 -> 1.0078115 | G29: =IF(F29>0,$B$9,0) -> 1 | H29: =MAX(0,F29/$B$10) -> 0.25195287 | I29: =EXP(-($B$5+$B$6)*D29) -> 0.8504412 | J29: =4*0.1/3 -> 0.13333333
D30: 1 | E30: =$B$4/($B$5+$B$6)*(1-EXP(-($B$5+$B$6)*($B$7-D30))) -> 3.9796999 | F30: =E30-$B$8 -> 0.97969985 | G30: =IF(F30>0,$B$9,0) -> 1 | H30: =MAX(0,F30/$B$10) -> 0.24492496 | I30: =EXP(-($B$5+$B$6)*D30) -> 0.83527021 | J30: =2*0.1/3 -> 0.066666667
D31: 1.1 | E31: =$B$4/($B$5+$B$6)*(1-EXP(-($B$5+$B$6)*($B$7-D31))) -> 3.9510776 | F31: =E31-$B$8 -> 0.95107762 | G31: =IF(F31>0,$B$9,0) -> 1 | H31: =MAX(0,F31/$B$10) -> 0.23776941 | I31: =EXP(-($B$5+$B$6)*D31) -> 0.82036985 | J31: =4*0.1/3 -> 0.13333333
D32: 1.2 | E32: =$B$4/($B$5+$B$6)*(1-EXP(-($B$5+$B$6)*($B$7-D32))) -> 3.9219355 | F32: =E32-$B$8 -> 0.92193553 | G32: =IF(F32>0,$B$9,0) -> 1 | H32: =MAX(0,F32/$B$10) -> 0.23048388 | I32: =EXP(-($B$5+$B$6)*D32) -> 0.8057353 | J32: =2*0.1/3 -> 0.066666667
D33: 1.3 | E33: =$B$4/($B$5+$B$6)*(1-EXP(-($B$5+$B$6)*($B$7-D33))) -> 3.8922641 | F33: =E33-$B$8 -> 0.89226413 | G33: =IF(F33>0,$B$9,0) -> 1 | H33: =MAX(0,F33/$B$10) -> 0.22306603 | I33: =EXP(-($B$5+$B$6)*D33) -> 0.79136182 | J33: =4*0.1/3 -> 0.13333333
D34: 1.4 | E34: =$B$4/($B$5+$B$6)*(1-EXP(-($B$5+$B$6)*($B$7-D34))) -> 3.8620538 | F34: =E34-$B$8 -> 0.8620538 | G34: =IF(F34>0,$B$9,0) -> 1 | H34: =MAX(0,F34/$B$10) -> 0.21551345 | I34: =EXP(-($B$5+$B$6)*D34) -> 0.77724474 | J34: =2*0.1/3 -> 0.066666667
D35: 1.5 | E35: =$B$4/($B$5+$B$6)*(1-EXP(-($B$5+$B$6)*($B$7-D35))) -> 3.8312948 | F35: =E35-$B$8 -> 0.83129477 | G35: =IF(F35>0,$B$9,0) -> 1 | H35: =MAX(0,F35/$B$10) -> 0.20782369 | I35: =EXP(-($B$5+$B$6)*D35) -> 0.76337949 | J35: =4*0.1/3 -> 0.13333333
D36: 1.6 | E36: =$B$4/($B$5+$B$6)*(1-EXP(-($B$5+$B$6)*($B$7-D36))) -> 3.7999771 | F36: =E36-$B$8 -> 0.79997706 | G36: =IF(F36>0,$B$9,0) -> 1 | H36: =MAX(0,F36/$B$10) -> 0.19999427 | I36: =EXP(-($B$5+$B$6)*D36) -> 0.74976159 | J36: =2*0.1/3 -> 0.066666667
D37: 1.7 | E37: =$B$4/($B$5+$B$6)*(1-EXP(-($B$5+$B$6)*($B$7-D37))) -> 3.7680905 | F37: =E37-$B$8 -> 0.76809053 | G37: =IF(F37>0,$B$9,0) -> 1 | H37: =MAX(0,F37/$B$10) -> 0.19202263 | I37: =EXP(-($B$5+$B$6)*D37) -> 0.73638662 | J37: =4*0.1/3 -> 0.13333333
D38: 1.8 | E38: =$B$4/($B$5+$B$6)*(1-EXP(-($B$5+$B$6)*($B$7-D38))) -> 3.7356248 | F38: =E38-$B$8 -> 0.73562485 | G38: =IF(F38>0,$B$9,0) -> 1 | H38: =MAX(0,F38/$B$10) -> 0.18390621 | I38: =EXP(-($B$5+$B$6)*D38) -> 0.72325024 | J38: =2*0.1/3 -> 0.066666667
D39: 1.9 | E39: =$B$4/($B$5+$B$6)*(1-EXP(-($B$5+$B$6)*($B$7-D39))) -> 3.7025695 | F39: =E39-$B$8 -> 0.70256949 | G39: =IF(F39>0,$B$9,0) -> 1 | H39: =MAX(0,F39/$B$10) -> 0.17564237 | I39: =EXP(-($B$5+$B$6)*D39) -> 0.7103482 | J39: =4*0.1/3 -> 0.13333333
D40: 2 | E40: =$B$4/($B$5+$B$6)*(1-EXP(-($B$5+$B$6)*($B$7-D40))) -> 3.6689137 | F40: =E40-$B$8 -> 0.66891375 | G40: =IF(F40>0,$B$9,0) -> 1 | H40: =MAX(0,F40/$B$10) -> 0.16722844 | I40: =EXP(-($B$5+$B$6)*D40) -> 0.69767633 | J40: =2*0.1/3 -> 0.066666667
D41: 2.1 | E41: =$B$4/($B$5+$B$6)*(1-EXP(-($B$5+$B$6)*($B$7-D41))) -> 3.6346467 | F41: =E41-$B$8 -> 0.63464672 | G41: =IF(F41>0,$B$9,0) -> 1 | H41: =MAX(0,F41/$B$10) -> 0.15866168 | I41: =EXP(-($B$5+$B$6)*D41) -> 0.6852305 | J41: =4*0.1/3 -> 0.13333333
D42: 2.2 | E42: =$B$4/($B$5+$B$6)*(1-EXP(-($B$5+$B$6)*($B$7-D42))) -> 3.5997573 | F42: =E42-$B$8 -> 0.59975729 | G42: =IF(F42>0,$B$9,0) -> 1 | H42: =MAX(0,F42/$B$10) -> 0.14993932 | I42: =EXP(-($B$5+$B$6)*D42) -> 0.6730067 | J42: =2*0.1/3 -> 0.066666667
D43: 2.3 | E43: =$B$4/($B$5+$B$6)*(1-EXP(-($B$5+$B$6)*($B$7-D43))) -> 3.5642342 | F43: =E43-$B$8 -> 0.56423418 | G43: =IF(F43>0,$B$9,0) -> 1 | H43: =MAX(0,F43/$B$10) -> 0.14105854 | I43: =EXP(-($B$5+$B$6)*D43) -> 0.66100095 | J43: =4*0.1/3 -> 0.13333333
D44: 2.4 | E44: =$B$4/($B$5+$B$6)*(1-EXP(-($B$5+$B$6)*($B$7-D44))) -> 3.5280659 | F44: =E44-$B$8 -> 0.52806585 | G44: =IF(F44>0,$B$9,0) -> 1 | H44: =MAX(0,F44/$B$10) -> 0.13201646 | I44: =EXP(-($B$5+$B$6)*D44) -> 0.64920938 | J44: =2*0.1/3 -> 0.066666667
D45: 2.5 | E45: =$B$4/($B$5+$B$6)*(1-EXP(-($B$5+$B$6)*($B$7-D45))) -> 3.4912406 | F45: =E45-$B$8 -> 0.49124061 | G45: =IF(F45>0,$B$9,0) -> 1 | H45: =MAX(0,F45/$B$10) -> 0.12281015 | I45: =EXP(-($B$5+$B$6)*D45) -> 0.63762815 | J45: =4*0.1/3 -> 0.13333333
D46: 2.6 | E46: =$B$4/($B$5+$B$6)*(1-EXP(-($B$5+$B$6)*($B$7-D46))) -> 3.4537465 | F46: =E46-$B$8 -> 0.4537465 | G46: =IF(F46>0,$B$9,0) -> 1 | H46: =MAX(0,F46/$B$10) -> 0.11343663 | I46: =EXP(-($B$5+$B$6)*D46) -> 0.62625352 | J46: =2*0.1/3 -> 0.066666667
D47: 2.7 | E47: =$B$4/($B$5+$B$6)*(1-EXP(-($B$5+$B$6)*($B$7-D47))) -> 3.4155714 | F47: =E47-$B$8 -> 0.41557139 | G47: =IF(F47>0,$B$9,0) -> 1 | H47: =MAX(0,F47/$B$10) -> 0.10389285 | I47: =EXP(-($B$5+$B$6)*D47) -> 0.61508181 | J47: =4*0.1/3 -> 0.13333333
D48: 2.8 | E48: =$B$4/($B$5+$B$6)*(1-EXP(-($B$5+$B$6)*($B$7-D48))) -> 3.3767029 | F48: =E48-$B$8 -> 0.37670291 | G48: =IF(F48>0,$B$9,0) -> 1 | H48: =MAX(0,F48/$B$10) -> 0.094175728 | I48: =EXP(-($B$5+$B$6)*D48) -> 0.60410938 | J48: =2*0.1/3 -> 0.066666667
D49: 2.9 | E49: =$B$4/($B$5+$B$6)*(1-EXP(-($B$5+$B$6)*($B$7-D49))) -> 3.3371285 | F49: =E49-$B$8 -> 0.33712846 | G49: =IF(F49>0,$B$9,0) -> 1 | H49: =MAX(0,F49/$B$10) -> 0.084282116 | I49: =EXP(-($B$5+$B$6)*D49) -> 0.5933327 | J49: =4*0.1/3 -> 0.13333333
D50: 3 | E50: =$B$4/($B$5+$B$6)*(1-EXP(-($B$5+$B$6)*($B$7-D50))) -> 3.2968352 | F50: =E50-$B$8 -> 0.29683522 | G50: =IF(F50>0,$B$9,0) -> 1 | H50: =MAX(0,F50/$B$10) -> 0.074208806 | I50: =EXP(-($B$5+$B$6)*D50) -> 0.58274825 | J50: =2*0.1/3 -> 0.066666667
D51: 3.1 | E51: =$B$4/($B$5+$B$6)*(1-EXP(-($B$5+$B$6)*($B$7-D51))) -> 3.2558101 | F51: =E51-$B$8 -> 0.25581014 | G51: =IF(F51>0,$B$9,0) -> 1 | H51: =MAX(0,F51/$B$10) -> 0.063952535 | I51: =EXP(-($B$5+$B$6)*D51) -> 0.57235263 | J51: =4*0.1/3 -> 0.13333333
D52: 3.2 | E52: =$B$4/($B$5+$B$6)*(1-EXP(-($B$5+$B$6)*($B$7-D52))) -> 3.2140399 | F52: =E52-$B$8 -> 0.21403992 | G52: =IF(F52>0,$B$9,0) -> 1 | H52: =MAX(0,F52/$B$10) -> 0.053509979 | I52: =EXP(-($B$5+$B$6)*D52) -> 0.56214245 | J52: =2*0.1/3 -> 0.066666667
D53: 3.3 | E53: =$B$4/($B$5+$B$6)*(1-EXP(-($B$5+$B$6)*($B$7-D53))) -> 3.171511 | F53: =E53-$B$8 -> 0.17151102 | G53: =IF(F53>0,$B$9,0) -> 1 | H53: =MAX(0,F53/$B$10) -> 0.042877756 | I53: =EXP(-($B$5+$B$6)*D53) -> 0.5521144 | J53: =4*0.1/3 -> 0.13333333
D54: 3.4 | E54: =$B$4/($B$5+$B$6)*(1-EXP(-($B$5+$B$6)*($B$7-D54))) -> 3.1282097 | F54: =E54-$B$8 -> 0.12820968 | G54: =IF(F54>0,$B$9,0) -> 1 | H54: =MAX(0,F54/$B$10) -> 0.03205242 | I54: =EXP(-($B$5+$B$6)*D54) -> 0.54226525 | J54: =2*0.1/3 -> 0.066666667
D55: 3.5 | E55: =$B$4/($B$5+$B$6)*(1-EXP(-($B$5+$B$6)*($B$7-D55))) -> 3.0841219 | F55: =E55-$B$8 -> 0.084121854 | G55: =IF(F55>0,$B$9,0) -> 1 | H55: =MAX(0,F55/$B$10) -> 0.021030464 | I55: =EXP(-($B$5+$B$6)*D55) -> 0.5325918 | J55: =4*0.1/3 -> 0.13333333
D56: 3.6 | E56: =$B$4/($B$5+$B$6)*(1-EXP(-($B$5+$B$6)*($B$7-D56))) -> 3.0392333 | F56: =E56-$B$8 -> 0.039233262 | G56: =IF(F56>0,$B$9,0) -> 1 | H56: =MAX(0,F56/$B$10) -> 0.0098083156 | I56: =EXP(-($B$5+$B$6)*D56) -> 0.52309091 | J56: =2*0.1/3 -> 0.066666667
D57: 3.7 | E57: =$B$4/($B$5+$B$6)*(1-EXP(-($B$5+$B$6)*($B$7-D57))) -> 2.9935294 | F57: =E57-$B$8 -> -0.00647064 | G57: =IF(F57>0,$B$9,0) -> 0 | H57: =MAX(0,F57/$B$10) -> 0 | I57: =EXP(-($B$5+$B$6)*D57) -> 0.51375951 | J57: =4*0.1/3 -> 0.13333333
D58: 3.8 | E58: =$B$4/($B$5+$B$6)*(1-EXP(-($B$5+$B$6)*($B$7-D58))) -> 2.9469953 | F58: =E58-$B$8 -> -0.053004661 | G58: =IF(F58>0,$B$9,0) -> 0 | H58: =MAX(0,F58/$B$10) -> 0 | I58: =EXP(-($B$5+$B$6)*D58) -> 0.50459457 | J58: =2*0.1/3 -> 0.066666667
D59: 3.9 | E59: =$B$4/($B$5+$B$6)*(1-EXP(-($B$5+$B$6)*($B$7-D59))) -> 2.8996161 | F59: =E59-$B$8 -> -0.10038388 | G59: =IF(F59>0,$B$9,0) -> 0 | H59: =MAX(0,F59/$B$10) -> 0 | I59: =EXP(-($B$5+$B$6)*D59) -> 0.49559313 | J59: =4*0.1/3 -> 0.13333333
D60: 4 | E60: =$B$4/($B$5+$B$6)*(1-EXP(-($B$5+$B$6)*($B$7-D60))) -> 2.8513764 | F60: =E60-$B$8 -> -0.14862364 | G60: =IF(F60>0,$B$9,0) -> 0 | H60: =MAX(0,F60/$B$10) -> 0 | I60: =EXP(-($B$5+$B$6)*D60) -> 0.48675226 | J60: =2*0.1/3 -> 0.066666667
D61: 4.1 | E61: =$B$4/($B$5+$B$6)*(1-EXP(-($B$5+$B$6)*($B$7-D61))) -> 2.8022604 | F61: =E61-$B$8 -> -0.19773959 | G61: =IF(F61>0,$B$9,0) -> 0 | H61: =MAX(0,F61/$B$10) -> 0 | I61: =EXP(-($B$5+$B$6)*D61) -> 0.4780691 | J61: =4*0.1/3 -> 0.13333333
D62: 4.2 | E62: =$B$4/($B$5+$B$6)*(1-EXP(-($B$5+$B$6)*($B$7-D62))) -> 2.7522524 | F62: =E62-$B$8 -> -0.24774762 | G62: =IF(F62>0,$B$9,0) -> 0 | H62: =MAX(0,F62/$B$10) -> 0 | I62: =EXP(-($B$5+$B$6)*D62) -> 0.46954084 | J62: =2*0.1/3 -> 0.066666667
D63: 4.3 | E63: =$B$4/($B$5+$B$6)*(1-EXP(-($B$5+$B$6)*($B$7-D63))) -> 2.701336 | F63: =E63-$B$8 -> -0.29866395 | G63: =IF(F63>0,$B$9,0) -> 0 | H63: =MAX(0,F63/$B$10) -> 0 | I63: =EXP(-($B$5+$B$6)*D63) -> 0.46116472 | J63: =4*0.1/3 -> 0.13333333
D64: 4.4 | E64: =$B$4/($B$5+$B$6)*(1-EXP(-($B$5+$B$6)*($B$7-D64))) -> 2.6494949 | F64: =E64-$B$8 -> -0.35050507 | G64: =IF(F64>0,$B$9,0) -> 0 | H64: =MAX(0,F64/$B$10) -> 0 | I64: =EXP(-($B$5+$B$6)*D64) -> 0.45293801 | J64: =2*0.1/3 -> 0.066666667
D65: 4.5 | E65: =$B$4/($B$5+$B$6)*(1-EXP(-($B$5+$B$6)*($B$7-D65))) -> 2.5967122 | F65: =E65-$B$8 -> -0.40328778 | G65: =IF(F65>0,$B$9,0) -> 0 | H65: =MAX(0,F65/$B$10) -> 0 | I65: =EXP(-($B$5+$B$6)*D65) -> 0.44485807 | J65: =4*0.1/3 -> 0.13333333
D66: 4.6 | E66: =$B$4/($B$5+$B$6)*(1-EXP(-($B$5+$B$6)*($B$7-D66))) -> 2.5429708 | F66: =E66-$B$8 -> -0.45702919 | G66: =IF(F66>0,$B$9,0) -> 0 | H66: =MAX(0,F66/$B$10) -> 0 | I66: =EXP(-($B$5+$B$6)*D66) -> 0.43692226 | J66: =2*0.1/3 -> 0.066666667
D67: 4.7 | E67: =$B$4/($B$5+$B$6)*(1-EXP(-($B$5+$B$6)*($B$7-D67))) -> 2.4882533 | F67: =E67-$B$8 -> -0.51174669 | G67: =IF(F67>0,$B$9,0) -> 0 | H67: =MAX(0,F67/$B$10) -> 0 | I67: =EXP(-($B$5+$B$6)*D67) -> 0.42912802 | J67: =4*0.1/3 -> 0.13333333
D68: 4.8 | E68: =$B$4/($B$5+$B$6)*(1-EXP(-($B$5+$B$6)*($B$7-D68))) -> 2.432542 | F68: =E68-$B$8 -> -0.56745803 | G68: =IF(F68>0,$B$9,0) -> 0 | H68: =MAX(0,F68/$B$10) -> 0 | I68: =EXP(-($B$5+$B$6)*D68) -> 0.42147281 | J68: =2*0.1/3 -> 0.066666667
D69: 4.9 | E69: =$B$4/($B$5+$B$6)*(1-EXP(-($B$5+$B$6)*($B$7-D69))) -> 2.3758187 | F69: =E69-$B$8 -> -0.62418125 | G69: =IF(F69>0,$B$9,0) -> 0 | H69: =MAX(0,F69/$B$10) -> 0 | I69: =EXP(-($B$5+$B$6)*D69) -> 0.41395417 | J69: =4*0.1/3 -> 0.13333333
D70: 5 | E70: =$B$4/($B$5+$B$6)*(1-EXP(-($B$5+$B$6)*($B$7-D70))) -> 2.3180653 | F70: =E70-$B$8 -> -0.68193474 | G70: =IF(F70>0,$B$9,0) -> 0 | H70: =MAX(0,F70/$B$10) -> 0 | I70: =EXP(-($B$5+$B$6)*D70) -> 0.40656966 | J70: =2*0.1/3 -> 0.066666667
D71: 5.1 | E71: =$B$4/($B$5+$B$6)*(1-EXP(-($B$5+$B$6)*($B$7-D71))) -> 2.2592628 | F71: =E71-$B$8 -> -0.7407372 | G71: =IF(F71>0,$B$9,0) -> 0 | H71: =MAX(0,F71/$B$10) -> 0 | I71: =EXP(-($B$5+$B$6)*D71) -> 0.39931688 | J71: =4*0.1/3 -> 0.13333333
D72: 5.2 | E72: =$B$4/($B$5+$B$6)*(1-EXP(-($B$5+$B$6)*($B$7-D72))) -> 2.1993923 | F72: =E72-$B$8 -> -0.80060768 | G72: =IF(F72>0,$B$9,0) -> 0 | H72: =MAX(0,F72/$B$10) -> 0 | I72: =EXP(-($B$5+$B$6)*D72) -> 0.39219348 | J72: =2*0.1/3 -> 0.066666667
D73: 5.3 | E73: =$B$4/($B$5+$B$6)*(1-EXP(-($B$5+$B$6)*($B$7-D73))) -> 2.1384344 | F73: =E73-$B$8 -> -0.8615656 | G73: =IF(F73>0,$B$9,0) -> 0 | H73: =MAX(0,F73/$B$10) -> 0 | I73: =EXP(-($B$5+$B$6)*D73) -> 0.38519715 | J73: =4*0.1/3 -> 0.13333333
D74: 5.4 | E74: =$B$4/($B$5+$B$6)*(1-EXP(-($B$5+$B$6)*($B$7-D74))) -> 2.0763693 | F74: =E74-$B$8 -> -0.92363069 | G74: =IF(F74>0,$B$9,0) -> 0 | H74: =MAX(0,F74/$B$10) -> 0 | I74: =EXP(-($B$5+$B$6)*D74) -> 0.37832563 | J74: =2*0.1/3 -> 0.066666667
D75: 5.5 | E75: =$B$4/($B$5+$B$6)*(1-EXP(-($B$5+$B$6)*($B$7-D75))) -> 2.0131769 | F75: =E75-$B$8 -> -0.98682306 | G75: =IF(F75>0,$B$9,0) -> 0 | H75: =MAX(0,F75/$B$10) -> 0 | I75: =EXP(-($B$5+$B$6)*D75) -> 0.37157669 | J75: =4*0.1/3 -> 0.13333333
D76: 5.6 | E76: =$B$4/($B$5+$B$6)*(1-EXP(-($B$5+$B$6)*($B$7-D76))) -> 1.9488368 | F76: =E76-$B$8 -> -1.0511632 | G76: =IF(F76>0,$B$9,0) -> 0 | H76: =MAX(0,F76/$B$10) -> 0 | I76: =EXP(-($B$5+$B$6)*D76) -> 0.36494815 | J76: =2*0.1/3 -> 0.066666667
D77: 5.7 | E77: =$B$4/($B$5+$B$6)*(1-EXP(-($B$5+$B$6)*($B$7-D77))) -> 1.883328 | F77: =E77-$B$8 -> -1.116672 | G77: =IF(F77>0,$B$9,0) -> 0 | H77: =MAX(0,F77/$B$10) -> 0 | I77: =EXP(-($B$5+$B$6)*D77) -> 0.35843785 | J77: =4*0.1/3 -> 0.13333333
D78: 5.8 | E78: =$B$4/($B$5+$B$6)*(1-EXP(-($B$5+$B$6)*($B$7-D78))) -> 1.8166295 | F78: =E78-$B$8 -> -1.1833705 | G78: =IF(F78>0,$B$9,0) -> 0 | H78: =MAX(0,F78/$B$10) -> 0 | I78: =EXP(-($B$5+$B$6)*D78) -> 0.35204369 | J78: =2*0.1/3 -> 0.066666667
D79: 5.9 | E79: =$B$4/($B$5+$B$6)*(1-EXP(-($B$5+$B$6)*($B$7-D79))) -> 1.7487194 | F79: =E79-$B$8 -> -1.2512806 | G79: =IF(F79>0,$B$9,0) -> 0 | H79: =MAX(0,F79/$B$10) -> 0 | I79: =EXP(-($B$5+$B$6)*D79) -> 0.34576359 | J79: =4*0.1/3 -> 0.13333333
D80: 6 | E80: =$B$4/($B$5+$B$6)*(1-EXP(-($B$5+$B$6)*($B$7-D80))) -> 1.679576 | F80: =E80-$B$8 -> -1.320424 | G80: =IF(F80>0,$B$9,0) -> 0 | H80: =MAX(0,F80/$B$10) -> 0 | I80: =EXP(-($B$5+$B$6)*D80) -> 0.33959553 | J80: =2*0.1/3 -> 0.066666667
D81: 6.1 | E81: =$B$4/($B$5+$B$6)*(1-EXP(-($B$5+$B$6)*($B$7-D81))) -> 1.6091766 | F81: =E81-$B$8 -> -1.3908234 | G81: =IF(F81>0,$B$9,0) -> 0 | H81: =MAX(0,F81/$B$10) -> 0 | I81: =EXP(-($B$5+$B$6)*D81) -> 0.33353749 | J81: =4*0.1/3 -> 0.13333333
D82: 6.2 | E82: =$B$4/($B$5+$B$6)*(1-EXP(-($B$5+$B$6)*($B$7-D82))) -> 1.5374987 | F82: =E82-$B$8 -> -1.4625013 | G82: =IF(F82>0,$B$9,0) -> 0 | H82: =MAX(0,F82/$B$10) -> 0 | I82: =EXP(-($B$5+$B$6)*D82) -> 0.32758753 | J82: =2*0.1/3 -> 0.066666667
D83: 6.3 | E83: =$B$4/($B$5+$B$6)*(1-EXP(-($B$5+$B$6)*($B$7-D83))) -> 1.4645188 | F83: =E83-$B$8 -> -1.5354812 | G83: =IF(F83>0,$B$9,0) -> 0 | H83: =MAX(0,F83/$B$10) -> 0 | I83: =EXP(-($B$5+$B$6)*D83) -> 0.3217437 | J83: =4*0.1/3 -> 0.13333333
D84: 6.4 | E84: =$B$4/($B$5+$B$6)*(1-EXP(-($B$5+$B$6)*($B$7-D84))) -> 1.3902134 | F84: =E84-$B$8 -> -1.6097866 | G84: =IF(F84>0,$B$9,0) -> 0 | H84: =MAX(0,F84/$B$10) -> 0 | I84: =EXP(-($B$5+$B$6)*D84) -> 0.31600413 | J84: =2*0.1/3 -> 0.066666667
D85: 6.5 | E85: =$B$4/($B$5+$B$6)*(1-EXP(-($B$5+$B$6)*($B$7-D85))) -> 1.3145584 | F85: =E85-$B$8 -> -1.6854416 | G85: =IF(F85>0,$B$9,0) -> 0 | H85: =MAX(0,F85/$B$10) -> 0 | I85: =EXP(-($B$5+$B$6)*D85) -> 0.31036694 | J85: =4*0.1/3 -> 0.13333333
D86: 6.6 | E86: =$B$4/($B$5+$B$6)*(1-EXP(-($B$5+$B$6)*($B$7-D86))) -> 1.2375292 | F86: =E86-$B$8 -> -1.7624708 | G86: =IF(F86>0,$B$9,0) -> 0 | H86: =MAX(0,F86/$B$10) -> 0 | I86: =EXP(-($B$5+$B$6)*D86) -> 0.30483032 | J86: =2*0.1/3 -> 0.066666667
D87: 6.7 | E87: =$B$4/($B$5+$B$6)*(1-EXP(-($B$5+$B$6)*($B$7-D87))) -> 1.159101 | F87: =E87-$B$8 -> -1.840899 | G87: =IF(F87>0,$B$9,0) -> 0 | H87: =MAX(0,F87/$B$10) -> 0 | I87: =EXP(-($B$5+$B$6)*D87) -> 0.29939246 | J87: =4*0.1/3 -> 0.13333333
D88: 6.8 | E88: =$B$4/($B$5+$B$6)*(1-EXP(-($B$5+$B$6)*($B$7-D88))) -> 1.0792483 | F88: =E88-$B$8 -> -1.9207517 | G88: =IF(F88>0,$B$9,0) -> 0 | H88: =MAX(0,F88/$B$10) -> 0 | I88: =EXP(-($B$5+$B$6)*D88) -> 0.2940516 | J88: =2*0.1/3 -> 0.066666667
D89: 6.9 | E89: =$B$4/($B$5+$B$6)*(1-EXP(-($B$5+$B$6)*($B$7-D89))) -> 0.99794526 | F89: =E89-$B$8 -> -2.0020547 | G89: =IF(F89>0,$B$9,0) -> 0 | H89: =MAX(0,F89/$B$10) -> 0 | I89: =EXP(-($B$5+$B$6)*D89) -> 0.28880603 | J89: =4*0.1/3 -> 0.13333333
D90: 7 | E90: =$B$4/($B$5+$B$6)*(1-EXP(-($B$5+$B$6)*($B$7-D90))) -> 0.91516549 | F90: =E90-$B$8 -> -2.0848345 | G90: =IF(F90>0,$B$9,0) -> 0 | H90: =MAX(0,F90/$B$10) -> 0 | I90: =EXP(-($B$5+$B$6)*D90) -> 0.28365403 | J90: =2*0.1/3 -> 0.066666667
D91: 7.1 | E91: =$B$4/($B$5+$B$6)*(1-EXP(-($B$5+$B$6)*($B$7-D91))) -> 0.8308822 | F91: =E91-$B$8 -> -2.1691178 | G91: =IF(F91>0,$B$9,0) -> 0 | H91: =MAX(0,F91/$B$10) -> 0 | I91: =EXP(-($B$5+$B$6)*D91) -> 0.27859393 | J91: =4*0.1/3 -> 0.13333333
D92: 7.2 | E92: =$B$4/($B$5+$B$6)*(1-EXP(-($B$5+$B$6)*($B$7-D92))) -> 0.74506807 | F92: =E92-$B$8 -> -2.2549319 | G92: =IF(F92>0,$B$9,0) -> 0 | H92: =MAX(0,F92/$B$10) -> 0 | I92: =EXP(-($B$5+$B$6)*D92) -> 0.2736241 | J92: =2*0.1/3 -> 0.066666667
D93: 7.3 | E93: =$B$4/($B$5+$B$6)*(1-EXP(-($B$5+$B$6)*($B$7-D93))) -> 0.6576953 | F93: =E93-$B$8 -> -2.3423047 | G93: =IF(F93>0,$B$9,0) -> 0 | H93: =MAX(0,F93/$B$10) -> 0 | I93: =EXP(-($B$5+$B$6)*D93) -> 0.26874293 | J93: =4*0.1/3 -> 0.13333333
D94: 7.4 | E94: =$B$4/($B$5+$B$6)*(1-EXP(-($B$5+$B$6)*($B$7-D94))) -> 0.56873558 | F94: =E94-$B$8 -> -2.4312644 | G94: =IF(F94>0,$B$9,0) -> 0 | H94: =MAX(0,F94/$B$10) -> 0 | I94: =EXP(-($B$5+$B$6)*D94) -> 0.26394884 | J94: =2*0.1/3 -> 0.066666667
D95: 7.5 | E95: =$B$4/($B$5+$B$6)*(1-EXP(-($B$5+$B$6)*($B$7-D95))) -> 0.47816008 | F95: =E95-$B$8 -> -2.5218399 | G95: =IF(F95>0,$B$9,0) -> 0 | H95: =MAX(0,F95/$B$10) -> 0 | I95: =EXP(-($B$5+$B$6)*D95) -> 0.25924026 | J95: =4*0.1/3 -> 0.13333333
D96: 7.6 | E96: =$B$4/($B$5+$B$6)*(1-EXP(-($B$5+$B$6)*($B$7-D96))) -> 0.38593947 | F96: =E96-$B$8 -> -2.6140605 | G96: =IF(F96>0,$B$9,0) -> 0 | H96: =MAX(0,F96/$B$10) -> 0 | I96: =EXP(-($B$5+$B$6)*D96) -> 0.25461568 | J96: =2*0.1/3 -> 0.066666667
D97: 7.7 | E97: =$B$4/($B$5+$B$6)*(1-EXP(-($B$5+$B$6)*($B$7-D97))) -> 0.29204385 | F97: =E97-$B$8 -> -2.7079561 | G97: =IF(F97>0,$B$9,0) -> 0 | H97: =MAX(0,F97/$B$10) -> 0 | I97: =EXP(-($B$5+$B$6)*D97) -> 0.2500736 | J97: =4*0.1/3 -> 0.13333333
D98: 7.8 | E98: =$B$4/($B$5+$B$6)*(1-EXP(-($B$5+$B$6)*($B$7-D98))) -> 0.19644281 | F98: =E98-$B$8 -> -2.8035572 | G98: =IF(F98>0,$B$9,0) -> 0 | H98: =MAX(0,F98/$B$10) -> 0 | I98: =EXP(-($B$5+$B$6)*D98) -> 0.24561255 | J98: =2*0.1/3 -> 0.066666667
D99: 7.9 | E99: =$B$4/($B$5+$B$6)*(1-EXP(-($B$5+$B$6)*($B$7-D99))) -> 0.099105376 | F99: =E99-$B$8 -> -2.9008946 | G99: =IF(F99>0,$B$9,0) -> 0 | H99: =MAX(0,F99/$B$10) -> 0 | I99: =EXP(-($B$5+$B$6)*D99) -> 0.24123107 | J99: =4*0.1/3 -> 0.13333333
D100: 8 | E100: =$B$4/($B$5+$B$6)*(1-EXP(-($B$5+$B$6)*($B$7-D100))) -> 0 | F100: =E100-$B$8 -> -3 | G100: =IF(F100>0,$B$9,0) -> 0 | H100: =MAX(0,F100/$B$10) -> 0 | I100: =EXP(-($B$5+$B$6)*D100) -> 0.23692776 | J100: =1*0.1/3 -> 0.033333333

Sheet Reference_Values
A1: Checkpoint | B1: Engine value | C1: Meaning (where in the book)
A2: delta, attrition a year | B2: 0.10127123 | C2: Worked Example 6.1, Step 1: 0.101
A3: u bar, hiring cap a year | B3: 10.127123 | C3: 10.13 points a year
A4: Race 53 to 55 (quarters) | B4: 1.7175702 | C4: 1.7 quarters
A5: Drift 58 to 55 (quarters) | B5: 2.097726 | C5: 2.1 quarters
A6: Rebuild 53 to 58 (quarters) | B6: 4.442643 | C6: Online Appendix 6.B.3: 4.443
A7: Rent at the floor ($ a year) | B7: 22.279671 | C7: Step 3: $22.3 million
A8: V(55), the rent forever | B8: -233.75962 | C8: Step 3: -$233.8 million
A9: The floor's price, user cost | B9: 0.78632565 | C9: Step 3: $0.79 million a point a year
A10: V(58) | B10: -222.36266 | C10: -222.36
A11: V(53) | B11: -254.89212 | C11: -254.89
A12: The team V(58) - V(53) | B12: 32.529461 | C12: Step 5: $32.5 million
A13: Team: hiring the rebuild needs | B13: 17.042921 | C13: $17.0 million
... A50: Capital problem: smooth investment at the start | B50: 0.30982256 | C50: 0.310

Sheet Checks
A1: Checkpoint | B1: Workbook formula value | C1: Engine value | D1: |diff| | E1: Tolerance | F1: Status
A2: delta, attrition a year | B2: =Declarations!B5 -> 0.10127123 | C2: =Reference_Values!B2 -> 0.10127123 | D2: =ABS(B2-C2) -> 4.1633363e-16 | E2: 1e-12 | F2: =IF(D2<=E2,"PASS","FAIL") -> PASS
A3: u bar, hiring cap a year | B3: =Declarations!B8 -> 10.127123 | C3: =Reference_Values!B3 -> 10.127123 | D3: =ABS(B3-C3) -> 4.0856207e-14 | E3: 1e-12 | F3: =IF(D3<=E3,"PASS","FAIL") -> PASS
A4: Race 53 to 55 (quarters) | B4: =Simulate!C4 -> 1.7175702 | C4: =Reference_Values!B4 -> 1.7175702 | D4: =ABS(B4-C4) -> 7.5495166e-15 | E4: 1e-09 | F4: =IF(D4<=E4,"PASS","FAIL") -> PASS
A5: Drift 58 to 55 (quarters) | B5: =Simulate!C5 -> 2.097726 | C5: =Reference_Values!B5 -> 2.097726 | D5: =ABS(B5-C5) -> 8.8817842e-15 | E5: 1e-09 | F5: =IF(D5<=E5,"PASS","FAIL") -> PASS
A6: Rebuild 53 to 58 (quarters) | B6: =Simulate!C6 -> 4.442643 | C6: =Reference_Values!B6 -> 4.442643 | D6: =ABS(B6-C6) -> 1.8651747e-14 | E6: 1e-09 | F6: =IF(D6<=E6,"PASS","FAIL") -> PASS
A7: Rent at the floor ($ a year) | B7: =Floor!B5 -> 22.279671 | C7: =Reference_Values!B7 -> 22.279671 | D7: =ABS(B7-C7) -> 9.2370556e-14 | E7: 1e-09 | F7: =IF(D7<=E7,"PASS","FAIL") -> PASS
A8: V(55), the rent forever | B8: =Floor!B6 -> -233.75962 | C8: =Reference_Values!B8 -> -233.75962 | D8: =ABS(B8-C8) -> 9.9475983e-13 | E8: 1e-09 | F8: =IF(D8<=E8,"PASS","FAIL") -> PASS
A9: The floor's price, user cost | B9: =Floor!B9 -> 0.78632565 | C9: =Reference_Values!B9 -> 0.78632565 | D9: =ABS(B9-C9) -> 0 | E9: 1e-12 | F9: =IF(D9<=E9,"PASS","FAIL") -> PASS
A10: V(58) | B10: =Prices!B9 -> -222.36266 | C10: =Reference_Values!B10 -> -222.36266 | D10: =ABS(B10-C10) -> 1.0516032e-12 | E10: 1e-09 | F10: =IF(D10<=E10,"PASS","FAIL") -> PASS
A11: V(53) | B11: =Prices!B4 -> -254.89212 | C11: =Reference_Values!B11 -> -254.89212 | D11: =ABS(B11-C11) -> 9.9475983e-13 | E11: 1e-09 | F11: =IF(D11<=E11,"PASS","FAIL") -> PASS
A12: The team V(58) - V(53) | B12: =Certify!B84 -> 32.529461 | C12: =Reference_Values!B12 -> 32.529461 | D12: =ABS(B12-C12) -> 0 | E12: 1e-09 | F12: =IF(D12<=E12,"PASS","FAIL") -> PASS
A13: Team: hiring the rebuild needs | B13: =Certify!B81 -> 17.042921 | C13: =Reference_Values!B13 -> 17.042921 | D13: =ABS(B13-C13) -> 0 | E13: 1e-09 | F13: =IF(D13<=E13,"PASS","FAIL") -> PASS
A14: Team: the build's delay | B14: =Certify!B82 -> 13.463189 | C14: =Reference_Values!B14 -> 13.463189 | D14: =ABS(B14-C14) -> 0 | E14: 1e-09 | F14: =IF(D14<=E14,"PASS","FAIL") -> PASS
A15: Team: the rent starts later | B15: =Certify!B83 -> 2.0233513 | C15: =Reference_Values!B15 -> 2.0233513 | D15: =ABS(B15-C15) -> 1.6431301e-14 | E15: 1e-09 | F15: =IF(D15<=E15,"PASS","FAIL") -> PASS
A16: Price of a point at 53 | B16: =Prices!C4 -> 10.129671 | C16: =Reference_Values!B16 -> 10.129671 | D16: =ABS(B16-C16) -> 0 | E16: 1e-09 | F16: =IF(D16<=E16,"PASS","FAIL") -> PASS
A17: Price of a point at 54 | B17: =Prices!C5 -> 10.5615 | C17: =Reference_Values!B17 -> 10.5615 | D17: =ABS(B17-C17) -> 0 | E17: 1e-09 | F17: =IF(D17<=E17,"PASS","FAIL") -> PASS
A18: Price as capability reaches 55 | B18: =Prices!C12 -> 11.021847 | C18: =Reference_Values!B18 -> 11.021847 | D18: =ABS(B18-C18) -> 0 | E18: 1e-09 | F18: =IF(D18<=E18,"PASS","FAIL") -> PASS
A19: Price of a point at 56 | B19: =Prices!C8 -> 3.8625128 | C19: =Reference_Values!B19 -> 3.8625128 | D19: =ABS(B19-C19) -> 0 | E19: 1e-09 | F19: =IF(D19<=E19,"PASS","FAIL") -> PASS
A20: Price of a point at 58 | B20: =Prices!C9 -> 3.6081706 | C20: =Reference_Values!B20 -> 3.6081706 | D20: =ABS(B20-C20) -> 0 | E20: 1e-09 | F20: =IF(D20<=E20,"PASS","FAIL") -> PASS
A21: Price of a point at 60 | B21: =Prices!C10 -> 3.3783698 | C21: =Reference_Values!B21 -> 3.3783698 | D21: =ABS(B21-C21) -> 0 | E21: 1e-09 | F21: =IF(D21<=E21,"PASS","FAIL") -> PASS
A22: Finite difference of V at 53 | B22: =Prices!D4 -> 10.129671 | C22: =Reference_Values!B22 -> 10.129671 | D22: =ABS(B22-C22) -> 1.5631905e-09 | E22: 1e-06 | F22: =IF(D22<=E22,"PASS","FAIL") -> PASS
A23: Hamiltonian: largest |max H - rho V| along the plans | B23: =Hamiltonian!I49 -> 0 | C23: =Reference_Values!B23 -> 1.4210855e-14 | D23: =ABS(B23-C23) -> 1.4210855e-14 | E23: 1e-09 | F23: =IF(D23<=E23,"PASS","FAIL") -> PASS
A24: Shooting: starting price of the race | B24: =Shooting!D59 -> 10.129671 | C24: =Reference_Values!B24 -> 10.129671 | D24: =ABS(B24-C24) -> 3.9612758e-13 | E24: 1e-09 | F24: =IF(D24<=E24,"PASS","FAIL") -> PASS
A25: Shooting: starting price of the drift | B25: =Shooting!K59 -> 3.6081706 | C25: =Reference_Values!B25 -> 3.6081706 | D25: =ABS(B25-C25) -> 2.593481e-13 | E25: 1e-09 | F25: =IF(D25<=E25,"PASS","FAIL") -> PASS
A26: Transcription weekly: earliest start week | B26: =Transcription!B9 -> 23 | C26: =Reference_Values!B26 -> 23 | D26: =ABS(B26-C26) -> 0 | E26: 0 | F26: =IF(D26<=E26,"PASS","FAIL") -> PASS
A27: Transcription daily: earliest start day | B27: =Transcription!C9 -> 157 | C27: =Reference_Values!B27 -> 157 | D27: =ABS(B27-C27) -> 0 | E27: 0 | F27: =IF(D27<=E27,"PASS","FAIL") -> PASS
A28: Transcription weekly: cost, start week 23 | B28: =Transcription!F17 -> 255.26885 | C28: =Reference_Values!B28 -> 255.26885 | D28: =ABS(B28-C28) -> 0 | E28: 1e-06 | F28: =IF(D28<=E28,"PASS","FAIL") -> PASS
A29: Transcription weekly: cost, start week 36 | B29: =Transcription!F21 -> 262.40014 | C29: =Reference_Values!B29 -> 262.40014 | D29: =ABS(B29-C29) -> 0 | E29: 1e-06 | F29: =IF(D29<=E29,"PASS","FAIL") -> PASS
A30: Transcription weekly: the schedule's total | B30: =Transcription!B67 -> 255.26885 | C30: =Reference_Values!B30 -> 255.26885 | D30: =ABS(B30-C30) -> 0 | E30: 1e-06 | F30: =IF(D30<=E30,"PASS","FAIL") -> PASS
A31: Transcription daily: above the closed form | B31: =Transcription!I22 -> 0.021721618 | C31: =Reference_Values!B31 -> 0.021721618 | D31: =ABS(B31-C31) -> 2.0008883e-11 | E31: 1e-06 | F31: =IF(D31<=E31,"PASS","FAIL") -> PASS
A32: Transcription weekly: team kept | B32: =Transcription!D27 -> 222.36281 | C32: =Reference_Values!B32 -> 222.36281 | D32: =ABS(B32-C32) -> 0 | E32: 1e-06 | F32: =IF(D32<=E32,"PASS","FAIL") -> PASS
A33: Transcription weekly: price on the floor | B33: =Transcription!B11 -> 4.0075679 | C33: =Reference_Values!B33 -> 4.0075679 | D33: =ABS(B33-C33) -> 2.1138646e-13 | E33: 1e-06 | F33: =IF(D33<=E33,"PASS","FAIL") -> PASS
A34: Transcription daily: the floor's price | B34: =Transcription!C12 -> 0.78632566 | C34: =Reference_Values!B34 -> 0.78632566 | D34: =ABS(B34-C34) -> 7.4162898e-14 | E34: 1e-06 | F34: =IF(D34<=E34,"PASS","FAIL") -> PASS
A35: Racing beats never starting above c_a | B35: =Certify!E58 -> 43.446247 | C35: =Reference_Values!B35 -> 43.446247 | D35: =ABS(B35-C35) -> 2.5579538e-13 | E35: 1e-09 | F35: =IF(D35<=E35,"PASS","FAIL") -> PASS
A36: Dynamic-programming condition: largest residual | B36: =Certify!F79 -> 0 | C36: =Reference_Values!B36 -> 1.4210855e-14 | D36: =ABS(B36-C36) -> 1.4210855e-14 | E36: 1e-09 | F36: =IF(D36<=E36,"PASS","FAIL") -> PASS
A37: Holding 58 less the drift | B37: =Plans!B10 -> 24.147483 | C37: =Reference_Values!B37 -> 24.147483 | D37: =ABS(B37-C37) -> 0 | E37: 1e-09 | F37: =IF(D37<=E37,"PASS","FAIL") -> PASS
A38: Rebuilding to 58 less the race | B38: =Plans!B11 -> 23.011732 | C38: =Reference_Values!B38 -> 23.011732 | D38: =ABS(B38-C38) -> 0 | E38: 1e-09 | F38: =IF(D38<=E38,"PASS","FAIL") -> PASS
A39: Table 6.3: team gone, proceeds less costs | B39: =Plans!G5 -> -142.89212 | C39: =Reference_Values!B39 -> -142.89212 | D39: =ABS(B39-C39) -> 9.9475983e-13 | E39: 1e-09 | F39: =IF(D39<=E39,"PASS","FAIL") -> PASS
A40: Table 6.3: rebuild to 58, proceeds less costs | B40: =Plans!G8 -> -165.90385 | C40: =Reference_Values!B40 -> -165.90385 | D40: =ABS(B40-C40) -> 1.080025e-12 | E40: 1e-09 | F40: =IF(D40<=E40,"PASS","FAIL") -> PASS
A41: Team, attrition 6% a year | B41: =Compare!C20 -> 28.402534 | C41: =Reference_Values!B41 -> 28.402534 | D41: =ABS(B41-C41) -> 0 | E41: 1e-09 | F41: =IF(D41<=E41,"PASS","FAIL") -> PASS
A42: Team, attrition 11% a year | B42: =Compare!D20 -> 35.214415 | C42: =Reference_Values!B42 -> 35.214415 | D42: =ABS(B42-C42) -> 0 | E42: 1e-09 | F42: =IF(D42<=E42,"PASS","FAIL") -> PASS
A43: Team, cap 2.0 a quarter | B43: =Compare!E20 -> 42.279525 | C43: =Reference_Values!B43 -> 42.279525 | D43: =ABS(B43-C43) -> 1.9895197e-13 | E43: 1e-09 | F43: =IF(D43<=E43,"PASS","FAIL") -> PASS
A44: Team, delay $4m a quarter | B44: =Compare!F20 -> 25.797867 | C44: =Reference_Values!B44 -> 25.797867 | D44: =ABS(B44-C44) -> 0 | E44: 1e-09 | F44: =IF(D44<=E44,"PASS","FAIL") -> PASS
A45: Team, delay $16m a quarter | B45: =Compare!G20 -> 45.99265 | C45: =Reference_Values!B45 -> 45.99265 | D45: =ABS(B45-C45) -> 0 | E45: 1e-09 | F45: =IF(D45<=E45,"PASS","FAIL") -> PASS
A46: Team, floor 60 | B46: =Compare!H20 -> 48.521382 | C46: =Reference_Values!B46 -> 48.521382 | D46: =ABS(B46-C46) -> 0 | E46: 1e-09 | F46: =IF(D46<=E46,"PASS","FAIL") -> PASS
A47: Capital problem: price at the start | B47: =CapitalProblems!B12 -> 4.2392902 | C47: =Reference_Values!B47 -> 4.2392902 | D47: =ABS(B47-C47) -> 0 | E47: 1e-09 | F47: =IF(D47<=E47,"PASS","FAIL") -> PASS
A48: Capital problem: marginal value of capital, Simpson | B48: =CapitalProblems!B15 -> 4.2392902 | C48: =Reference_Values!B48 -> 4.2392902 | D48: =ABS(B48-C48) -> 2.472258e-09 | E48: 1e-06 | F48: =IF(D48<=E48,"PASS","FAIL") -> PASS
A49: Capital problem: the switch (years) | B49: =CapitalProblems!B13 -> 3.6859512 | C49: =Reference_Values!B49 -> 3.6859512 | D49: =ABS(B49-C49) -> 0 | E49: 1e-09 | F49: =IF(D49<=E49,"PASS","FAIL") -> PASS
A50: Capital problem: smooth investment at the start | B50: =CapitalProblems!B14 -> 0.30982256 | C50: =Reference_Values!B50 -> 0.30982256 | D50: =ABS(B50-C50) -> 0 | E50: 1e-09 | F50: =IF(D50<=E50,"PASS","FAIL") -> PASS
A52: All checkpoints | F52: =IF(COUNTIF(F2:F50,"PASS")=49,"ALL PASS","CHECK") -> ALL PASS
