Workbook

Sheet README
B1: DCT Laboratory — Vol II, Ch 11: Distributionally Robust Enterprise Optimization
B2: Seed 26211 · Companion to DCT_V2_Ch11_Lab.ipynb and AXIOM Lab 2.11 (module AXIOM-11). Money in $ million.
B4: Worked Example 11.1, How Much Should Meridian Trust Its Law?, with the book's declarations: Chapter 9's law, levers and floor; the treasury's record (two closures in twenty years) and the engineering office's (forty quarters of deviations). Chances are simulated on Chapter 9's 100,000 paths (seed 8) and checked on its 100,000 fresh paths (seed 26209); a higher rate adds closures from seeds 1108 and 26208 (Online Appendix Remark 11.B.1).
B5: Declarations: the law, the levers and their prices, the records.
B6: Records: Garwood's bound for the rate and the chi-square bounds for the spread, Bonferroni's confidence, Garwood's exact coverage, and Volume I's package under the laws the records allow (Proposition 11.2; Step 1).
B7: Family: the cheapest package at each declaration's worst law, its cost, the price of ambiguity and the value of a longer record; the family's package on the 49-law grid (Theorem 11.1(iv); Step 2).
B8: Divergence and KL_Bisection: the radii of the records' doubts, kl(q || p), the law's appetite alpha'(d) and the worst chance q*(p, d) by bisection, the ball's packages, and a ball of any radius (Theorem 11.2; Figure 11.1; Step 3).
B9: Wasserstein: the thinnest-margin requirement eps / 0.05, the ball's packages, and the radius that holds the spread's doubt (Theorem 11.3; Figure 11.2(a); Step 3).
B10: Records1000: designs on 200 records of 1,000 paths with margins and radii, and reliability per dollar (Figure 11.2(b); Step 4).
B11: Moments: Cantelli's bounds quarter by quarter, the 4.36 multiplier and the moment package's delay and cost (Proposition 11.1; Section 11.4).
B12: PriceTheDoubt: Table 11.3, every declaration's package, its chances under the law and the records' worst law, the fresh paths' gaps and the standard errors (Step 5).
B13: Engine values (green) are what needs the simulated paths: chances, the designs' lines and delays, the margins' means and spreads, the records of 1,000 paths. Everything else is a formula.
... B20: Cross-sheet link: green.

Sheet Declarations
A1: Declarations (Worked Example 11.1, Step 1; Chapter 9's law and levers; the records behind the law). Money in $ million.
A3: Quantity | B3: Value | C3: Source
A4: Years in the program, H | B4: 3 | C4: Twelve quarters
A5: Quarters in the program | B5: 12
A6: Paths (the book's, seed 8; fresh, seed 26209) | B6: 100000 | C6: Chapter 9's law
A7: Floor | B7: 350 | C7: The board's floor, in every quarter
A8: Persistence of a deviation a quarter | B8: 0.6 | C8: E' = 0.6 E + w (Volume I, Chapter 8)
A9: Declared spread of the innovations w, a quarter | B9: 50 | C9: The engineering office's record
A10: Declared rate of funding-window closures, a year | B10: 0.1 | C10: The treasury's record
A11: Closure size: mean | B11: 120 | C11: Gamma-distributed, never recovered
A12: Closure size: standard deviation | B12: 50
A13: Line fees over the program, per $ of line | B13: 0.03 | C13: The treasury
A14: A quarter of delay | B14: 8 | C14: The transformation office
A15: The draw's depth (index points) | B15: 28 | C15: Deepest at two years
A16: Depth cut by a quarter of delay (points) | B16: 4
A17: $ million per index point | B17: =620/100 -> 6.2 | C17: Index 100 = $620 million
A18: The draw is deepest at (years) | B18: 2 | C18: Shape S(t) = (t/2) e^(1 - t/2)
A19: The appetite | B19: 0.05 | C19: At most a 5 percent chance of a breach in some quarter
A20: The extra stream's rate ceiling (a year) | B20: 0.4 | C20: Online Appendix Remark 11.B.1: a higher rate adds closures from an extra stream at 0.40 - 0.10, thinned
A22: The records (Worked Example 11.1, Step 1; Proposition 11.2)
A23: The treasury's record: closures | B23: 2 | C23: Two closures...
A24: in years of history | B24: 20 | C24: ...in twenty years: the declared 0.10 a year
A25: The engineering office's record: quarters of deviations | B25: 40
A26: innovations (the persistence 0.6 taken as known) | B26: =B25-1 -> 39 | C26: 39 innovations
A27: their root-mean-square | B27: 50 | C27: The declared spread
A28: Confidence of each bound | B28: 0.95 | C28: One-sided, 95 percent each
A29: Twice the record: closures | B29: 4 | C29: Four closures in forty years, the same estimate
A30: in years | B30: 40
A31: quarters of deviations | B31: 80 | C31: Eighty quarters
A32: innovations | B32: =B31-1 -> 79 | C32: 79 innovations

Sheet Records
A1: Read the records: confidence bounds for the rate and the spread (Proposition 11.2(i)-(iii); Worked Example 11.1, Step 1; AXIOM Lab 2.11, step 1)
A2: Rate: n closures in T years give the one-sided bound chi2_(conf)(2n + 2) / (2T) (Garwood). Spread: n Gaussian innovations of root-mean-square s give s sqrt(n / chi2_(1-conf)(n)) above and s sqrt(n / chi2_(conf)(n)) below.
A3: Quantity | B3: Value | C3: Reading
A4: Rate: the record's estimate (closures a year) | B4: =NCl/TYrs -> 0.1 | C4: 0.10
A5: Rate: upper 95% bound (Garwood) | B5: =_xlfn.CHISQ.INV(Conf,2*NCl+2)/(2*TYrs) -> 0.31478968 | C5: 0.3148: Section 11.1's 0.315
A6: the same from the right tail | B6: =_xlfn.CHISQ.INV.RT(1-Conf,2*NCl+2)/(2*TYrs) -> 0.31478968
A7: Rate: lower 95% bound | B7: =_xlfn.CHISQ.INV(1-Conf,2*NCl)/(2*TYrs) -> 0.017768076 | C7: 0.0178
A8: Spread: lower 95% bound | B8: =RMS*SQRT(NInn/_xlfn.CHISQ.INV(Conf,NInn)) -> 42.268464 | C8: $42.27 million
A9: Spread: upper 95% bound | B9: =RMS*SQRT(NInn/_xlfn.CHISQ.INV(1-Conf,NInn)) -> 61.599147 | C9: $61.60 million
A10: The records' family holds the true law with at least (Bonferroni) | B10: =1-2*(1-Conf) -> 0.9 | C10: 90 percent: Proposition 11.2(iii)
A11: The corner's spread, as a multiple of the declared | B11: =B9/Sig0 -> 1.2319829 | C11: 1.232
A12: Twice the record: rate, upper bound | B12: =_xlfn.CHISQ.INV(Conf,2*NCl2+2)/(2*TYrs2) -> 0.22883798 | C12: 0.2288 (Step 5's 0.229)
A13: Twice the record: spread, upper bound | B13: =RMS*SQRT(NInn2/_xlfn.CHISQ.INV(1-Conf,NInn2)) -> 57.602817 | C13: $57.60 million
A14: Twice the record: spread, lower bound | B14: =RMS*SQRT(NInn2/_xlfn.CHISQ.INV(Conf,NInn2)) -> 44.275554 | C14: $44.28 million
A16: Garwood's bound errs on the safe side: the chance it holds the true rate, exactly (Proposition 11.2(i))
A17: Closures n in the record | B17: Its upper bound | C17: P(n) at a true rate of 0.10 | D17: P(n) at 0.20 | E17: P(n) at the bound
A18: 0 | B18: =_xlfn.CHISQ.INV(Conf,2*A18+2)/(2*TYrs) -> 0.14978661 | C18: =_xlfn.POISSON.DIST(A18,Lam0*TYrs,FALSE()) -> 0.13533528 | D18: =_xlfn.POISSON.DIST(A18,0.2*TYrs,FALSE()) -> 0.018315639 | E18: =_xlfn.POISSON.DIST(A18,LamU*TYrs,FALSE()) -> 0.0018440452
A19: 1 | B19: =_xlfn.CHISQ.INV(Conf,2*A19+2)/(2*TYrs) -> 0.23719323 | C19: =_xlfn.POISSON.DIST(A19,Lam0*TYrs,FALSE()) -> 0.27067057 | D19: =_xlfn.POISSON.DIST(A19,0.2*TYrs,FALSE()) -> 0.073262556 | E19: =_xlfn.POISSON.DIST(A19,LamU*TYrs,FALSE()) -> 0.011609728
A20: 2 | B20: =_xlfn.CHISQ.INV(Conf,2*A20+2)/(2*TYrs) -> 0.31478968 | C20: =_xlfn.POISSON.DIST(A20,Lam0*TYrs,FALSE()) -> 0.27067057 | D20: =_xlfn.POISSON.DIST(A20,0.2*TYrs,FALSE()) -> 0.14652511 | E20: =_xlfn.POISSON.DIST(A20,LamU*TYrs,FALSE()) -> 0.036546227
A21: 3 | B21: =_xlfn.CHISQ.INV(Conf,2*A21+2)/(2*TYrs) -> 0.38768283 | C21: =_xlfn.POISSON.DIST(A21,Lam0*TYrs,FALSE()) -> 0.18044704 | D21: =_xlfn.POISSON.DIST(A21,0.2*TYrs,FALSE()) -> 0.19536681 | E21: =_xlfn.POISSON.DIST(A21,LamU*TYrs,FALSE()) -> 0.076695833
A22: 4 | B22: =_xlfn.CHISQ.INV(Conf,2*A22+2)/(2*TYrs) -> 0.45767595 | C22: =_xlfn.POISSON.DIST(A22,Lam0*TYrs,FALSE()) -> 0.090223522 | D22: =_xlfn.POISSON.DIST(A22,0.2*TYrs,FALSE()) -> 0.19536681 | E22: =_xlfn.POISSON.DIST(A22,LamU*TYrs,FALSE()) -> 0.12071528
A23: 5 | B23: =_xlfn.CHISQ.INV(Conf,2*A23+2)/(2*TYrs) -> 0.52565175 | C23: =_xlfn.POISSON.DIST(A23,Lam0*TYrs,FALSE()) -> 0.036089409 | D23: =_xlfn.POISSON.DIST(A23,0.2*TYrs,FALSE()) -> 0.15629345 | E23: =_xlfn.POISSON.DIST(A23,LamU*TYrs,FALSE()) -> 0.1519997
A24: 6 | B24: =_xlfn.CHISQ.INV(Conf,2*A24+2)/(2*TYrs) -> 0.59211978 | C24: =_xlfn.POISSON.DIST(A24,Lam0*TYrs,FALSE()) -> 0.012029803 | D24: =_xlfn.POISSON.DIST(A24,0.2*TYrs,FALSE()) -> 0.10419563 | E24: =_xlfn.POISSON.DIST(A24,LamU*TYrs,FALSE()) -> 0.15949313
A25: 7 | B25: =_xlfn.CHISQ.INV(Conf,2*A25+2)/(2*TYrs) -> 0.65740569 | C25: =_xlfn.POISSON.DIST(A25,Lam0*TYrs,FALSE()) -> 0.0034370866 | D25: =_xlfn.POISSON.DIST(A25,0.2*TYrs,FALSE()) -> 0.059540363 | E25: =_xlfn.POISSON.DIST(A25,LamU*TYrs,FALSE()) -> 0.14344797
A26: 8 | B26: =_xlfn.CHISQ.INV(Conf,2*A26+2)/(2*TYrs) -> 0.72173249 | C26: =_xlfn.POISSON.DIST(A26,Lam0*TYrs,FALSE()) -> 0.00085927164 | D26: =_xlfn.POISSON.DIST(A26,0.2*TYrs,FALSE()) -> 0.029770181 | E26: =_xlfn.POISSON.DIST(A26,LamU*TYrs,FALSE()) -> 0.11288985
A27: 9 | B27: =_xlfn.CHISQ.INV(Conf,2*A27+2)/(2*TYrs) -> 0.78526082 | C27: =_xlfn.POISSON.DIST(A27,Lam0*TYrs,FALSE()) -> 0.00019094925 | D27: =_xlfn.POISSON.DIST(A27,0.2*TYrs,FALSE()) -> 0.013231192 | E27: =_xlfn.POISSON.DIST(A27,LamU*TYrs,FALSE()) -> 0.078970136
A28: 10 | B28: =_xlfn.CHISQ.INV(Conf,2*A28+2)/(2*TYrs) -> 0.84811096 | C28: =_xlfn.POISSON.DIST(A28,Lam0*TYrs,FALSE()) -> 3.8189851e-05 | D28: =_xlfn.POISSON.DIST(A28,0.2*TYrs,FALSE()) -> 0.0052924767 | E28: =_xlfn.POISSON.DIST(A28,LamU*TYrs,FALSE()) -> 0.049717968
A29: 11 | B29: =_xlfn.CHISQ.INV(Conf,2*A29+2)/(2*TYrs) -> 0.91037571 | C29: =_xlfn.POISSON.DIST(A29,Lam0*TYrs,FALSE()) -> 6.9436092e-06 | D29: =_xlfn.POISSON.DIST(A29,0.2*TYrs,FALSE()) -> 0.001924537 | E29: =_xlfn.POISSON.DIST(A29,LamU*TYrs,FALSE()) -> 0.028455824
... A33: 15 | B33: =_xlfn.CHISQ.INV(Conf,2*A33+2)/(2*TYrs) -> 1.1548565 | C33: =_xlfn.POISSON.DIST(A33,Lam0*TYrs,FALSE()) -> 3.3912621e-09 | D33: =_xlfn.POISSON.DIST(A33,0.2*TYrs,FALSE()) -> 1.5039117e-05 | E33: =_xlfn.POISSON.DIST(A33,LamU*TYrs,FALSE()) -> 0.0013646749
A35: Chance the bound holds a true rate of 0.10 | B35: =1-SUMPRODUCT(($B$18:$B$33<Lam0)*C18:C33) -> 1
A36: Chance the bound holds a true rate of 0.20 | B36: =1-SUMPRODUCT(($B$18:$B$33<0.2)*D18:D33) -> 0.98168436
A37: Chance the bound holds a true rate of the bound, 0.3148 | B37: =1-SUMPRODUCT(($B$18:$B$33<LamU)*E18:E33) -> 0.98654623
A38: Simulated records under the declared law (engine, the lab's seed 26211): the rate's bound holds | B38: 1 | C38: 100,000 records; with no closure at all the bound is 0.150
A39: the spread's bound holds | B39: 0.94986 | C39: 95 percent: Proposition 11.2(ii)
A40: both hold | B40: 0.94986 | C40: At least 90 percent (Bonferroni)
A42: Volume I's package ($170 million line, 0.668 quarter) under the laws the records allow (engine)
A43: Rate a year (spread $50m) | B43: Chance of a breach (engine) | D43: Spread (rate 0.10) | E43: Chance of a breach (engine)
A44: 0 | B44: 0.04471 | D44: 40 | E44: 0.01034
A45: =LamL -> 0.017768076 | B45: 0.04567 | D45: =SigL -> 42.268464 | E45: 0.01591
A46: 0.05 | B46: 0.04732 | D46: 45 | E46: 0.02515
A47: =Lam0 -> 0.1 | B47: 0.05 | D47: =Sig0 -> 50 | E47: 0.05
A48: 0.15 | B48: 0.05271 | D48: 55 | E48: 0.08585
A49: 0.2 | B49: 0.05529 | D49: 60 | E49: 0.12917
A50: 0.25 | B50: 0.05796 | D50: =SigU -> 61.599147 | E50: 0.14427
A51: =LamU -> 0.31478968 | B51: 0.0616 | D51: 65 | E51: 0.17865
A52: 0.35 | B52: 0.06353
A54: Across the closures' range (0 to the bound): from | B54: =MIN(B44:B51) -> 0.04471 | C54: 4.5 percent
A55: to | B55: =MAX(B44:B51) -> 0.0616 | C55: 6.2 percent
A56: Across the spread's range (the two bounds): from | B56: =E45 -> 0.01591 | C56: 1.6 percent
A57: to | B57: =E50 -> 0.14427 | C57: 14.4 percent
A58: At the corner, both bounds (engine) | B58: 0.15789 | C58: 15.8 percent; fresh paths 15.83

Sheet Family
A1: Price the family: the cheapest package at each declaration's worst law (Theorem 11.1(iv); Proposition 11.2(iii); Worked Example 11.1, Step 2; AXIOM Lab 2.11, step 2)
A2: Lines and delays are Chapter 9's design at each law (engine: the line on a $5 million grid, the delay the least that keeps 5 percent on the simulated paths); costs, the price of ambiguity and the value of a longer record are formulas.
A4: Declaration | B4: Rate a year | C4: Spread | D4: Volume I's package at the law (engine) | E4: fresh (engine) | F4: Line (engine) | G4: Delay (engine) | H4: Fees | I4: Delay cost | J4: Cost | K4: Fresh paths at its law (engine) | L4: Under the declared law (engine) | M4: fresh (engine) | N4: Extra over Volume I's package
A5: Volume I's package (one law) | B5: =Lam0 -> 0.1 | C5: =Sig0 -> 50 | D5: 0.05 | E5: 0.04907 | F5: 170 | G5: 0.66757636 | H5: =Fee*F5 -> 5.1 | I5: =VQ*G5 -> 5.3406109 | J5: =H5+I5 -> 10.440611 | K5: 0.04907 | L5: 0.05 | M5: 0.04907 | N5: =J5-$J$5 -> 0
A6: Closures' doubt (rate at its bound) | B6: =LamU -> 0.31478968 | C6: =Sig0 -> 50 | D6: 0.0616 | E6: 0.06064 | F6: 210 | G6: 0.66716792 | H6: =Fee*F6 -> 6.3 | I6: =VQ*G6 -> 5.3373433 | J6: =H6+I6 -> 11.637343 | K6: 0.04883 | L6: 0.04631 | M6: 0.04534 | N6: =J6-$J$5 -> 1.1967324
A7: Spread's doubt (spread at its bound) | B7: =Lam0 -> 0.1 | C7: =SigU -> 61.599147 | D7: 0.14427 | E7: 0.14443 | F7: 170 | G7: 2.218368 | H7: =Fee*F7 -> 5.1 | I7: =VQ*G7 -> 17.746944 | J7: =H7+I7 -> 22.846944 | K7: 0.04914 | L7: 0.01063 | M7: 0.01032 | N7: =J7-$J$5 -> 12.406333
A8: The records' family (both: the corner) | B8: =LamU -> 0.31478968 | C8: =SigU -> 61.599147 | D8: 0.15789 | E8: 0.15835 | F8: 200 | G8: 2.2504041 | H8: =Fee*F8 -> 6 | I8: =VQ*G8 -> 18.003233 | J8: =H8+I8 -> 24.003233 | K8: 0.04905 | L8: 0.00894 | M8: 0.0086 | N8: =J8-$J$5 -> 13.562622
A9: Records twice as long | B9: =LamU2 -> 0.22883798 | C9: =SigU2 -> 57.602817 | D9: 0.11598 | E9: 0.11429 | F9: 195 | G9: 1.6900824 | H9: =Fee*F9 -> 5.85 | I9: =VQ*G9 -> 13.520659 | J9: =H9+I9 -> 19.370659 | K9: 0.04871 | L9: 0.01664 | M9: 0.01622 | N9: =J9-$J$5 -> 8.9300482
A11: The price of ambiguity: the records' family less one law | B11: =J8-J5 -> 13.562622 | C11: $13.56 million (Step 5)
A12: of which the spread's doubt alone | B12: =J7-J5 -> 12.406333 | C12: Most of it: the spread is what costs
A13: and the closures' doubt alone | B13: =J6-J5 -> 1.1967324
A14: The value of a record twice as long | B14: =J8-J9 -> 4.6325741 | C14: $4.63 million on this program alone
A16: The records' family's package ($200 million line, 2.250 quarters) across the family: 49 laws (engine)
A17: Rows: seven rates from 0 to the bound; columns: seven spreads from the lower bound to the upper (Online Appendix Remark 11.B.1). The chance rises with both: the worst law is the corner.
A18: Rate \ spread | B18: =SigL+(SigU-SigL)*0/6 -> 42.268464 | C18: =SigL+(SigU-SigL)*1/6 -> 45.490244 | D18: =SigL+(SigU-SigL)*2/6 -> 48.712025 | E18: =SigL+(SigU-SigL)*3/6 -> 51.933805 | F18: =SigL+(SigU-SigL)*4/6 -> 55.155586 | G18: =SigL+(SigU-SigL)*5/6 -> 58.377366 | H18: =SigL+(SigU-SigL)*6/6 -> 61.599147
A19: =LamU*0/6 -> 0 | B19: 0.00098 | C19: 0.00256 | D19: 0.00613 | E19: 0.0112 | F19: 0.01925 | G19: 0.03049 | H19: 0.04505
A20: =LamU*1/6 -> 0.052464947 | B20: 0.00123 | C20: 0.00292 | D20: 0.00655 | E20: 0.0118 | F20: 0.01991 | G20: 0.03116 | H20: 0.04587
A21: =LamU*2/6 -> 0.10492989 | B21: 0.00163 | C21: 0.0034 | D21: 0.00718 | E21: 0.01251 | F21: 0.02063 | G21: 0.03194 | H21: 0.04669
A22: =LamU*3/6 -> 0.15739484 | B22: 0.00189 | C22: 0.00369 | D22: 0.00759 | E22: 0.01298 | F22: 0.02131 | G22: 0.03271 | H22: 0.04746
A23: =LamU*4/6 -> 0.20985979 | B23: 0.00219 | C23: 0.00408 | D23: 0.00805 | E23: 0.01356 | F23: 0.02196 | G23: 0.03343 | H23: 0.04822
A24: =LamU*5/6 -> 0.26232473 | B24: 0.00257 | C24: 0.00453 | D24: 0.00856 | E24: 0.01413 | F24: 0.02266 | G24: 0.03415 | H24: 0.04903
A25: =LamU*6/6 -> 0.31478968 | B25: 0.00292 | C25: 0.00491 | D25: 0.00901 | E25: 0.0147 | F25: 0.02342 | G25: 0.03501 | H25: 0.05
A27: The largest chance on the grid | B27: =MAX(B19:H25) -> 0.05 | C27: 5.00 percent
A28: at the corner? (1 = yes) | B28: =IF(MAX(B19:H25)=H25,1,0) -> 1 | C28: The corner: both bounds

Sheet Divergence
A1: Try balls: Kullback-Leibler families (Theorem 11.2; Figure 11.1; Worked Example 11.1, Step 3; AXIOM Lab 2.11, step 3)
A2: kl(q || p) = q ln(q/p) + (1 - q) ln((1 - q)/(1 - p)). The ball of radius d keeps 5 percent exactly when the law keeps alpha'(d), kl(0.05 || alpha') = d; the ball's package is Chapter 9's design at that appetite.
A4: The radius that holds each doubt (Theorem 11.2(iii)) | B4: Radius d | C4: alpha'(d) by bisection | D4: alpha'(d) (engine) | E4: Reading | L4: Explore: a ball of any radius
A5: Closures at the bound over the program: H (l' ln(l'/l) - l' + l) | B5: =H_yrs*(LamU*LN(LamU/Lam0)-LamU+Lam0) -> 0.43857157 | C5: =KL_Bisection!B71 -> 2.9265667e-06 | D5: 2.9265667e-06 | E5: 0.439: 3 in a million | L5: Radius d (change it) | M5: 0.01
A6: Spread at the bound, twelve innovations: n (ln(1/c) + (c^2 - 1)/2) | B6: =NQ*(LN(1/Records!B11)+(Records!B11^2-1)/2) -> 0.60319157 | C6: =KL_Bisection!D71 -> 1.0875871e-07 | D6: 1.0875871e-07 | E6: 0.603 | L6: The law must keep alpha'(d) | M6: =KL_Bisection!AP71 -> 0.024981145
A7: Both: divergences add over independent parts | B7: =B5+B6 -> 1.0417631 | C7: =KL_Bisection!F71 -> 1.6868595e-11 | D7: 1.6868595e-11 | E7: 1.042: 2 in 100 billion | L7: Volume I's package (5% under the law) breaches on up to q*(5%, d) | M7: =KL_Bisection!AR71 -> 0.083648267
L8: Check: kl(0.05 || alpha') - d | M8: =(Alpha)*LN((Alpha)/(M6))+(1-(Alpha))*LN((1-(Alpha))/(1-(M6)))-M5 -> 5.0306981e-17
A9: The levers' floor: the fewest paths a $400m line and 7 quarters leave breached (engine) | B9: 1 | E9: One path in 100,000
A10: as a chance | B10: =B9/NPaths -> 1e-05 | L10: Change d in M5: the bisection on KL_Bisection recomputes alpha'(d) and q*(5%, d). For d = 0.01 the law must keep 2.50 percent: a $175 million line and 1.354 quarters, $16.08 million (engine, row 29).
A11: the ball is beyond the levers from kl(0.05 || that chance) | B11: =(Alpha)*LN((Alpha)/(B10))+(1-(Alpha))*LN((1-(Alpha))/(1-(B10))) -> 0.37714053 | E11: 0.377 (Online Appendix 11.B.2; Figure 11.1(b): 0.38)
A13: The worst chance of Volume I's package over the ball (it keeps 5.00 percent under the law)
A14: Radius d | B14: q* by bisection | C14: q* (engine) | D14: kl(q* engine || 0.05) - d
A15: 0.001 | B15: =KL_Bisection!AB71 -> 0.060040821 | C15: 0.060040821 | D15: =(C15)*LN((C15)/(Alpha))+(1-(C15))*LN((1-(C15))/(1-(Alpha)))-A15 -> 1.1275703e-17
A16: 0.003 | B16: =KL_Bisection!AD71 -> 0.067751818 | C16: 0.067751818 | D16: =(C16)*LN((C16)/(Alpha))+(1-(C16))*LN((1-(C16))/(1-(Alpha)))-A16 -> -2.8622937e-17
A17: 0.01 | B17: =KL_Bisection!AF71 -> 0.083648267 | C17: 0.083648267 | D17: =(C17)*LN((C17)/(Alpha))+(1-(C17))*LN((1-(C17))/(1-(Alpha)))-A17 -> -3.989864e-17
A18: 0.03 | B18: =KL_Bisection!AH71 -> 0.11154805 | C18: 0.11154805 | D18: =(C18)*LN((C18)/(Alpha))+(1-(C18))*LN((1-(C18))/(1-(Alpha)))-A18 -> 0
A19: 0.1 | B19: =KL_Bisection!AJ71 -> 0.17294935 | C19: 0.17294935 | D19: =(C19)*LN((C19)/(Alpha))+(1-(C19))*LN((1-(C19))/(1-(Alpha)))-A19 -> 0
A20: 0.3 | B20: =KL_Bisection!AL71 -> 0.2885192 | C20: 0.2885192 | D20: =(C20)*LN((C20)/(Alpha))+(1-(C20))*LN((1-(C20))/(1-(Alpha)))-A20 -> 0
A21: 1 | B21: =KL_Bisection!AN71 -> 0.55551415 | C21: 0.55551415 | D21: =(C21)*LN((C21)/(Alpha))+(1-(C21))*LN((1-(C21))/(1-(Alpha)))-A21 -> 0
A23: Keeping 5 percent over the ball: Chapter 9's design at the law's appetite alpha'(d) (engine) and its cost
A24: Radius d | B24: alpha' by bisection | C24: alpha' (engine) | D24: kl(0.05 || alpha' engine) - d | E24: Line (engine) | F24: Delay (engine) | G24: Cost | H24: Under the law (engine) | I24: Fresh paths (engine) | J24: Extra over Volume I's
A25: 0 | B25: =Alpha -> 0.05 | C25: 0.05 | E25: 170 | F25: 0.66757636 | G25: =Fee*E25+VQ*F25 -> 10.440611 | H25: 0.05 | I25: 0.04907 | J25: =G25-$G$25 -> 0
A26: 0.001 | B26: =KL_Bisection!H71 -> 0.040848256 | C26: 0.040848256 | D26: =(Alpha)*LN((Alpha)/(C26))+(1-(Alpha))*LN((1-(Alpha))/(1-(C26)))-A26 -> -5.6378513e-17 | E26: 160 | F26: 0.92428019 | G26: =Fee*E26+VQ*F26 -> 12.194242 | H26: 0.04084 | I26: 0.04049 | J26: =G26-$G$25 -> 1.7536307
A27: 0.002 | B27: =KL_Bisection!J71 -> 0.037401261 | C27: 0.037401261 | D27: =(Alpha)*LN((Alpha)/(C27))+(1-(Alpha))*LN((1-(Alpha))/(1-(C27)))-A27 -> 5.7245875e-17 | E27: 165 | F27: 0.99808349 | G27: =Fee*E27+VQ*F27 -> 12.934668 | H27: 0.0374 | I27: 0.0368 | J27: =G27-$G$25 -> 2.494057
A28: 0.005 | B28: =KL_Bisection!L71 -> 0.031142017 | C28: 0.031142017 | D28: =(Alpha)*LN((Alpha)/(C28))+(1-(Alpha))*LN((1-(Alpha))/(1-(C28)))-A28 -> -5.1174343e-17 | E28: 170 | F28: 1.1621673 | G28: =Fee*E28+VQ*F28 -> 14.397338 | H28: 0.03114 | I28: 0.03093 | J28: =G28-$G$25 -> 3.9567275
A29: 0.01 | B29: =KL_Bisection!N71 -> 0.024981145 | C29: 0.024981145 | D29: =(Alpha)*LN((Alpha)/(C29))+(1-(Alpha))*LN((1-(Alpha))/(1-(C29)))-A29 -> 0 | E29: 175 | F29: 1.3539024 | G29: =Fee*E29+VQ*F29 -> 16.081219 | H29: 0.02498 | I29: 0.02515 | J29: =G29-$G$25 -> 5.640608
A30: 0.02 | B30: =KL_Bisection!P71 -> 0.017786384 | C30: 0.017786384 | D30: =(Alpha)*LN((Alpha)/(C30))+(1-(Alpha))*LN((1-(Alpha))/(1-(C30)))-A30 -> 0 | E30: 180 | F30: 1.6708183 | G30: =Fee*E30+VQ*F30 -> 18.766546 | H30: 0.01778 | I30: 0.01745 | J30: =G30-$G$25 -> 8.3259354
A31: 0.03 | B31: =KL_Bisection!R71 -> 0.013373251 | C31: 0.013373251 | D31: =(Alpha)*LN((Alpha)/(C31))+(1-(Alpha))*LN((1-(Alpha))/(1-(C31)))-A31 -> 0 | E31: 175 | F31: 1.9552346 | G31: =Fee*E31+VQ*F31 -> 20.891877 | H31: 0.01337 | I31: 0.01302 | J31: =G31-$G$25 -> 10.451266
A32: 0.05 | B32: =KL_Bisection!T71 -> 0.0081010838 | C32: 0.0081010838 | D32: =(Alpha)*LN((Alpha)/(C32))+(1-(Alpha))*LN((1-(Alpha))/(1-(C32)))-A32 -> 0 | E32: 195 | F32: 2.3562579 | G32: =Fee*E32+VQ*F32 -> 24.700063 | H32: 0.0081 | I32: 0.00792 | J32: =G32-$G$25 -> 14.259452
A33: 0.075 | B33: =KL_Bisection!V71 -> 0.0045949388 | C33: 0.0045949388 | D33: =(Alpha)*LN((Alpha)/(C33))+(1-(Alpha))*LN((1-(Alpha))/(1-(C33)))-A33 -> 0 | E33: 215 | F33: 2.7372767 | G33: =Fee*E33+VQ*F33 -> 28.348214 | H33: 0.00459 | I33: 0.00457 | J33: =G33-$G$25 -> 17.907603
A34: 0.1 | B34: =KL_Bisection!X71 -> 0.0026874158 | C34: 0.0026874158 | D34: =(Alpha)*LN((Alpha)/(C34))+(1-(Alpha))*LN((1-(Alpha))/(1-(C34)))-A34 -> 0 | E34: 200 | F34: 3.1731757 | G34: =Fee*E34+VQ*F34 -> 31.385406 | H34: 0.00268 | I34: 0.00299 | J34: =G34-$G$25 -> 20.944795
A35: 0.15 | B35: =KL_Bisection!Z71 -> 0.00095660434 | C35: 0.00095660434 | D35: =(Alpha)*LN((Alpha)/(C35))+(1-(Alpha))*LN((1-(Alpha))/(1-(C35)))-A35 -> 0 | E35: 240 | F35: 3.8507391 | G35: =Fee*E35+VQ*F35 -> 38.005913 | H35: 0.00095 | I35: 0.00106 | J35: =G35-$G$25 -> 27.565302

Sheet KL_Bisection
A1: Theorem 11.2(ii) by bisection: the law's appetite alpha'(d), kl(0.05 || alpha') = d, and the worst chance q*(p, d), kl(q* || p) = d
A2: Each problem takes two columns (low and high end of the bracket) and 60 halvings. alpha' is bracketed in ln p between ln(1E-30) and ln(0.05): kl(0.05 || p) falls as p rises. q* is bracketed between p and 1: kl(q || p) rises with q.
A4: Problem | B4: closures' doubt | D4: spread's doubt | F4: both doubts | H4: design d = 0.001 | J4: design d = 0.002 | L4: design d = 0.005 | N4: design d = 0.01 | P4: design d = 0.02 | R4: design d = 0.03 | T4: design d = 0.05 | V4: design d = 0.075 | X4: design d = 0.1 | Z4: design d = 0.15 | AB4: Volume I's package, d = 0.001 | AD4: Volume I's package, d = 0.003 | AF4: Volume I's package, d = 0.01 | AH4: Volume I's package, d = 0.03 | AJ4: Volume I's package, d = 0.1 | AL4: Volume I's package, d = 0.3 | AN4: Volume I's package, d = 1 | AP4: the input d | AR4: the input d
B5: alpha' | D5: alpha' | F5: alpha' | H5: alpha' | J5: alpha' | L5: alpha' | N5: alpha' | P5: alpha' | R5: alpha' | T5: alpha' | V5: alpha' | X5: alpha' | Z5: alpha' | AB5: q* | AD5: q* | AF5: q* | AH5: q* | AJ5: q* | AL5: q* | AN5: q* | AP5: alpha' | AR5: q*
A6: d | B6: =Divergence!B5 -> 0.43857157 | D6: =Divergence!B6 -> 0.60319157 | F6: =Divergence!B7 -> 1.0417631 | H6: 0.001 | J6: 0.002 | L6: 0.005 | N6: 0.01 | P6: 0.02 | R6: 0.03 | T6: 0.05 | V6: 0.075 | X6: 0.1 | Z6: 0.15 | AB6: 0.001 | AD6: 0.003 | AF6: 0.01 | AH6: 0.03 | AJ6: 0.1 | AL6: 0.3 | AN6: 1 | AP6: =Divergence!M5 -> 0.01 | AR6: =Divergence!M5 -> 0.01
A7: chance p | B7: =Alpha -> 0.05 | D7: =Alpha -> 0.05 | F7: =Alpha -> 0.05 | H7: =Alpha -> 0.05 | J7: =Alpha -> 0.05 | L7: =Alpha -> 0.05 | N7: =Alpha -> 0.05 | P7: =Alpha -> 0.05 | R7: =Alpha -> 0.05 | T7: =Alpha -> 0.05 | V7: =Alpha -> 0.05 | X7: =Alpha -> 0.05 | Z7: =Alpha -> 0.05 | AB7: =Alpha -> 0.05 | AD7: =Alpha -> 0.05 | AF7: =Alpha -> 0.05 | AH7: =Alpha -> 0.05 | AJ7: =Alpha -> 0.05 | AL7: =Alpha -> 0.05 | AN7: =Alpha -> 0.05 | AP7: =Alpha -> 0.05 | AR7: =Alpha -> 0.05
A9: halving 0 | B9: =LN(1E-030) -> -69.077553 | C9: =LN(B7) -> -2.9957323 | D9: =LN(1E-030) -> -69.077553 | E9: =LN(D7) -> -2.9957323 | F9: =LN(1E-030) -> -69.077553 | G9: =LN(F7) -> -2.9957323 | H9: =LN(1E-030) -> -69.077553 | I9: =LN(H7) -> -2.9957323 | J9: =LN(1E-030) -> -69.077553 | K9: =LN(J7) -> -2.9957323 | L9: =LN(1E-030) -> -69.077553 | M9: =LN(L7) -> -2.9957323 | N9: =LN(1E-030) -> -69.077553 | O9: =LN(N7) -> -2.9957323 | P9: =LN(1E-030) -> -69.077553 | Q9: =LN(P7) -> -2.9957323 | R9: =LN(1E-030) -> -69.077553 | S9: =LN(R7) -> -2.9957323 | T9: =LN(1E-030) -> -69.077553 | U9: =LN(T7) -> -2.9957323 | V9: =LN(1E-030) -> -69.077553 | W9: =LN(V7) -> -2.9957323 | X9: =LN(1E-030) -> -69.077553 | Y9: =LN(X7) -> -2.9957323 | Z9: =LN(1E-030) -> -69.077553 | AA9: =LN(Z7) -> -2.9957323 | AB9: =AB7 -> 0.05 | AC9: =1-1E-015 -> 1 | AD9: =AD7 -> 0.05 | AE9: =1-1E-015 -> 1 | AF9: =AF7 -> 0.05 | AG9: =1-1E-015 -> 1 | AH9: =AH7 -> 0.05 | AI9: =1-1E-015 -> 1 | AJ9: =AJ7 -> 0.05 | AK9: =1-1E-015 -> 1 | AL9: =AL7 -> 0.05 | AM9: =1-1E-015 -> 1 | AN9: =AN7 -> 0.05 | AO9: =1-1E-015 -> 1 | AP9: =LN(1E-030) -> -69.077553 | AQ9: =LN(AP7) -> -2.9957323 | AR9: =AR7 -> 0.05 | AS9: =1-1E-015 -> 1
B10: =IF(B$7*LN(B$7)-B$7*((B9+C9)/2)+(1-B$7)*LN(1-B$7)-(1-B$7)*LN(1-EXP(((B9+C9)/2)))-B$6>0,((B9+C9)/2),B9) -> -36.036643 | C10: =IF(B$7*LN(B$7)-B$7*((B9+C9)/2)+(1-B$7)*LN(1-B$7)-(1-B$7)*LN(1-EXP(((B9+C9)/2)))-B$6>0,C9,((B9+C9)/2)) -> -2.9957323 | D10: =IF(D$7*LN(D$7)-D$7*((D9+E9)/2)+(1-D$7)*LN(1-D$7)-(1-D$7)*LN(1-EXP(((D9+E9)/2)))-D$6>0,((D9+E9)/2),D9) -> -36.036643 | E10: =IF(D$7*LN(D$7)-D$7*((D9+E9)/2)+(1-D$7)*LN(1-D$7)-(1-D$7)*LN(1-EXP(((D9+E9)/2)))-D$6>0,E9,((D9+E9)/2)) -> -2.9957323 | F10: =IF(F$7*LN(F$7)-F$7*((F9+G9)/2)+(1-F$7)*LN(1-F$7)-(1-F$7)*LN(1-EXP(((F9+G9)/2)))-F$6>0,((F9+G9)/2),F9) -> -36.036643 | G10: =IF(F$7*LN(F$7)-F$7*((F9+G9)/2)+(1-F$7)*LN(1-F$7)-(1-F$7)*LN(1-EXP(((F9+G9)/2)))-F$6>0,G9,((F9+G9)/2)) -> -2.9957323 | H10: =IF(H$7*LN(H$7)-H$7*((H9+I9)/2)+(1-H$7)*LN(1-H$7)-(1-H$7)*LN(1-EXP(((H9+I9)/2)))-H$6>0,((H9+I9)/2),H9) -> -36.036643 | I10: =IF(H$7*LN(H$7)-H$7*((H9+I9)/2)+(1-H$7)*LN(1-H$7)-(1-H$7)*LN(1-EXP(((H9+I9)/2)))-H$6>0,I9,((H9+I9)/2)) -> -2.9957323 | J10: =IF(J$7*LN(J$7)-J$7*((J9+K9)/2)+(1-J$7)*LN(1-J$7)-(1-J$7)*LN(1-EXP(((J9+K9)/2)))-J$6>0,((J9+K9)/2),J9) -> -36.036643 | K10: =IF(J$7*LN(J$7)-J$7*((J9+K9)/2)+(1-J$7)*LN(1-J$7)-(1-J$7)*LN(1-EXP(((J9+K9)/2)))-J$6>0,K9,((J9+K9)/2)) -> -2.9957323 | L10: =IF(L$7*LN(L$7)-L$7*((L9+M9)/2)+(1-L$7)*LN(1-L$7)-(1-L$7)*LN(1-EXP(((L9+M9)/2)))-L$6>0,((L9+M9)/2),L9) -> -36.036643 | M10: =IF(L$7*LN(L$7)-L$7*((L9+M9)/2)+(1-L$7)*LN(1-L$7)-(1-L$7)*LN(1-EXP(((L9+M9)/2)))-L$6>0,M9,((L9+M9)/2)) -> -2.9957323 | N10: =IF(N$7*LN(N$7)-N$7*((N9+O9)/2)+(1-N$7)*LN(1-N$7)-(1-N$7)*LN(1-EXP(((N9+O9)/2)))-N$6>0,((N9+O9)/2),N9) -> -36.036643 | O10: =IF(N$7*LN(N$7)-N$7*((N9+O9)/2)+(1-N$7)*LN(1-N$7)-(1-N$7)*LN(1-EXP(((N9+O9)/2)))-N$6>0,O9,((N9+O9)/2)) -> -2.9957323 | P10: =IF(P$7*LN(P$7)-P$7*((P9+Q9)/2)+(1-P$7)*LN(1-P$7)-(1-P$7)*LN(1-EXP(((P9+Q9)/2)))-P$6>0,((P9+Q9)/2),P9) -> -36.036643 | Q10: =IF(P$7*LN(P$7)-P$7*((P9+Q9)/2)+(1-P$7)*LN(1-P$7)-(1-P$7)*LN(1-EXP(((P9+Q9)/2)))-P$6>0,Q9,((P9+Q9)/2)) -> -2.9957323 | R10: =IF(R$7*LN(R$7)-R$7*((R9+S9)/2)+(1-R$7)*LN(1-R$7)-(1-R$7)*LN(1-EXP(((R9+S9)/2)))-R$6>0,((R9+S9)/2),R9) -> -36.036643 | S10: =IF(R$7*LN(R$7)-R$7*((R9+S9)/2)+(1-R$7)*LN(1-R$7)-(1-R$7)*LN(1-EXP(((R9+S9)/2)))-R$6>0,S9,((R9+S9)/2)) -> -2.9957323 | T10: =IF(T$7*LN(T$7)-T$7*((T9+U9)/2)+(1-T$7)*LN(1-T$7)-(1-T$7)*LN(1-EXP(((T9+U9)/2)))-T$6>0,((T9+U9)/2),T9) -> -36.036643 | U10: =IF(T$7*LN(T$7)-T$7*((T9+U9)/2)+(1-T$7)*LN(1-T$7)-(1-T$7)*LN(1-EXP(((T9+U9)/2)))-T$6>0,U9,((T9+U9)/2)) -> -2.9957323 | V10: =IF(V$7*LN(V$7)-V$7*((V9+W9)/2)+(1-V$7)*LN(1-V$7)-(1-V$7)*LN(1-EXP(((V9+W9)/2)))-V$6>0,((V9+W9)/2),V9) -> -36.036643 | W10: =IF(V$7*LN(V$7)-V$7*((V9+W9)/2)+(1-V$7)*LN(1-V$7)-(1-V$7)*LN(1-EXP(((V9+W9)/2)))-V$6>0,W9,((V9+W9)/2)) -> -2.9957323 | X10: =IF(X$7*LN(X$7)-X$7*((X9+Y9)/2)+(1-X$7)*LN(1-X$7)-(1-X$7)*LN(1-EXP(((X9+Y9)/2)))-X$6>0,((X9+Y9)/2),X9) -> -36.036643 | Y10: =IF(X$7*LN(X$7)-X$7*((X9+Y9)/2)+(1-X$7)*LN(1-X$7)-(1-X$7)*LN(1-EXP(((X9+Y9)/2)))-X$6>0,Y9,((X9+Y9)/2)) -> -2.9957323 | Z10: =IF(Z$7*LN(Z$7)-Z$7*((Z9+AA9)/2)+(1-Z$7)*LN(1-Z$7)-(1-Z$7)*LN(1-EXP(((Z9+AA9)/2)))-Z$6>0,((Z9+AA9)/2),Z9) -> -36.036643 | AA10: =IF(Z$7*LN(Z$7)-Z$7*((Z9+AA9)/2)+(1-Z$7)*LN(1-Z$7)-(1-Z$7)*LN(1-EXP(((Z9+AA9)/2)))-Z$6>0,AA9,((Z9+AA9)/2)) -> -2.9957323 | AB10: =IF((((AB9+AC9)/2))*LN((((AB9+AC9)/2))/(AB$7))+(1-(((AB9+AC9)/2)))*LN((1-(((AB9+AC9)/2)))/(1-(AB$7)))-AB$6<0,((AB9+AC9)/2),AB9) -> 0.05 | AC10: =IF((((AB9+AC9)/2))*LN((((AB9+AC9)/2))/(AB$7))+(1-(((AB9+AC9)/2)))*LN((1-(((AB9+AC9)/2)))/(1-(AB$7)))-AB$6<0,AC9,((AB9+AC9)/2)) -> 0.525 | AD10: =IF((((AD9+AE9)/2))*LN((((AD9+AE9)/2))/(AD$7))+(1-(((AD9+AE9)/2)))*LN((1-(((AD9+AE9)/2)))/(1-(AD$7)))-AD$6<0,((AD9+AE9)/2),AD9) -> 0.05 | AE10: =IF((((AD9+AE9)/2))*LN((((AD9+AE9)/2))/(AD$7))+(1-(((AD9+AE9)/2)))*LN((1-(((AD9+AE9)/2)))/(1-(AD$7)))-AD$6<0,AE9,((AD9+AE9)/2)) -> 0.525 | AF10: =IF((((AF9+AG9)/2))*LN((((AF9+AG9)/2))/(AF$7))+(1-(((AF9+AG9)/2)))*LN((1-(((AF9+AG9)/2)))/(1-(AF$7)))-AF$6<0,((AF9+AG9)/2),AF9) -> 0.05 | AG10: =IF((((AF9+AG9)/2))*LN((((AF9+AG9)/2))/(AF$7))+(1-(((AF9+AG9)/2)))*LN((1-(((AF9+AG9)/2)))/(1-(AF$7)))-AF$6<0,AG9,((AF9+AG9)/2)) -> 0.525 | AH10: =IF((((AH9+AI9)/2))*LN((((AH9+AI9)/2))/(AH$7))+(1-(((AH9+AI9)/2)))*LN((1-(((AH9+AI9)/2)))/(1-(AH$7)))-AH$6<0,((AH9+AI9)/2),AH9) -> 0.05 | AI10: =IF((((AH9+AI9)/2))*LN((((AH9+AI9)/2))/(AH$7))+(1-(((AH9+AI9)/2)))*LN((1-(((AH9+AI9)/2)))/(1-(AH$7)))-AH$6<0,AI9,((AH9+AI9)/2)) -> 0.525 | AJ10: =IF((((AJ9+AK9)/2))*LN((((AJ9+AK9)/2))/(AJ$7))+(1-(((AJ9+AK9)/2)))*LN((1-(((AJ9+AK9)/2)))/(1-(AJ$7)))-AJ$6<0,((AJ9+AK9)/2),AJ9) -> 0.05 | AK10: =IF((((AJ9+AK9)/2))*LN((((AJ9+AK9)/2))/(AJ$7))+(1-(((AJ9+AK9)/2)))*LN((1-(((AJ9+AK9)/2)))/(1-(AJ$7)))-AJ$6<0,AK9,((AJ9+AK9)/2)) -> 0.525 | AL10: =IF((((AL9+AM9)/2))*LN((((AL9+AM9)/2))/(AL$7))+(1-(((AL9+AM9)/2)))*LN((1-(((AL9+AM9)/2)))/(1-(AL$7)))-AL$6<0,((AL9+AM9)/2),AL9) -> 0.05 | AM10: =IF((((AL9+AM9)/2))*LN((((AL9+AM9)/2))/(AL$7))+(1-(((AL9+AM9)/2)))*LN((1-(((AL9+AM9)/2)))/(1-(AL$7)))-AL$6<0,AM9,((AL9+AM9)/2)) -> 0.525 | AN10: =IF((((AN9+AO9)/2))*LN((((AN9+AO9)/2))/(AN$7))+(1-(((AN9+AO9)/2)))*LN((1-(((AN9+AO9)/2)))/(1-(AN$7)))-AN$6<0,((AN9+AO9)/2),AN9) -> 0.525 | AO10: =IF((((AN9+AO9)/2))*LN((((AN9+AO9)/2))/(AN$7))+(1-(((AN9+AO9)/2)))*LN((1-(((AN9+AO9)/2)))/(1-(AN$7)))-AN$6<0,AO9,((AN9+AO9)/2)) -> 1 | AP10: =IF(AP$7*LN(AP$7)-AP$7*((AP9+AQ9)/2)+(1-AP$7)*LN(1-AP$7)-(1-AP$7)*LN(1-EXP(((AP9+AQ9)/2)))-AP$6>0,((AP9+AQ9)/2),AP9) -> -36.036643 | AQ10: =IF(AP$7*LN(AP$7)-AP$7*((AP9+AQ9)/2)+(1-AP$7)*LN(1-AP$7)-(1-AP$7)*LN(1-EXP(((AP9+AQ9)/2)))-AP$6>0,AQ9,((AP9+AQ9)/2)) -> -2.9957323 | AR10: =IF((((AR9+AS9)/2))*LN((((AR9+AS9)/2))/(AR$7))+(1-(((AR9+AS9)/2)))*LN((1-(((AR9+AS9)/2)))/(1-(AR$7)))-AR$6<0,((AR9+AS9)/2),AR9) -> 0.05 | AS10: =IF((((AR9+AS9)/2))*LN((((AR9+AS9)/2))/(AR$7))+(1-(((AR9+AS9)/2)))*LN((1-(((AR9+AS9)/2)))/(1-(AR$7)))-AR$6<0,AS9,((AR9+AS9)/2)) -> 0.525
B11: =IF(B$7*LN(B$7)-B$7*((B10+C10)/2)+(1-B$7)*LN(1-B$7)-(1-B$7)*LN(1-EXP(((B10+C10)/2)))-B$6>0,((B10+C10)/2),B10) -> -19.516187 | C11: =IF(B$7*LN(B$7)-B$7*((B10+C10)/2)+(1-B$7)*LN(1-B$7)-(1-B$7)*LN(1-EXP(((B10+C10)/2)))-B$6>0,C10,((B10+C10)/2)) -> -2.9957323 | D11: =IF(D$7*LN(D$7)-D$7*((D10+E10)/2)+(1-D$7)*LN(1-D$7)-(1-D$7)*LN(1-EXP(((D10+E10)/2)))-D$6>0,((D10+E10)/2),D10) -> -19.516187 | E11: =IF(D$7*LN(D$7)-D$7*((D10+E10)/2)+(1-D$7)*LN(1-D$7)-(1-D$7)*LN(1-EXP(((D10+E10)/2)))-D$6>0,E10,((D10+E10)/2)) -> -2.9957323 | F11: =IF(F$7*LN(F$7)-F$7*((F10+G10)/2)+(1-F$7)*LN(1-F$7)-(1-F$7)*LN(1-EXP(((F10+G10)/2)))-F$6>0,((F10+G10)/2),F10) -> -36.036643 | G11: =IF(F$7*LN(F$7)-F$7*((F10+G10)/2)+(1-F$7)*LN(1-F$7)-(1-F$7)*LN(1-EXP(((F10+G10)/2)))-F$6>0,G10,((F10+G10)/2)) -> -19.516187 | H11: =IF(H$7*LN(H$7)-H$7*((H10+I10)/2)+(1-H$7)*LN(1-H$7)-(1-H$7)*LN(1-EXP(((H10+I10)/2)))-H$6>0,((H10+I10)/2),H10) -> -19.516187 | I11: =IF(H$7*LN(H$7)-H$7*((H10+I10)/2)+(1-H$7)*LN(1-H$7)-(1-H$7)*LN(1-EXP(((H10+I10)/2)))-H$6>0,I10,((H10+I10)/2)) -> -2.9957323 | J11: =IF(J$7*LN(J$7)-J$7*((J10+K10)/2)+(1-J$7)*LN(1-J$7)-(1-J$7)*LN(1-EXP(((J10+K10)/2)))-J$6>0,((J10+K10)/2),J10) -> -19.516187 | K11: =IF(J$7*LN(J$7)-J$7*((J10+K10)/2)+(1-J$7)*LN(1-J$7)-(1-J$7)*LN(1-EXP(((J10+K10)/2)))-J$6>0,K10,((J10+K10)/2)) -> -2.9957323 | L11: =IF(L$7*LN(L$7)-L$7*((L10+M10)/2)+(1-L$7)*LN(1-L$7)-(1-L$7)*LN(1-EXP(((L10+M10)/2)))-L$6>0,((L10+M10)/2),L10) -> -19.516187 | M11: =IF(L$7*LN(L$7)-L$7*((L10+M10)/2)+(1-L$7)*LN(1-L$7)-(1-L$7)*LN(1-EXP(((L10+M10)/2)))-L$6>0,M10,((L10+M10)/2)) -> -2.9957323 | N11: =IF(N$7*LN(N$7)-N$7*((N10+O10)/2)+(1-N$7)*LN(1-N$7)-(1-N$7)*LN(1-EXP(((N10+O10)/2)))-N$6>0,((N10+O10)/2),N10) -> -19.516187 | O11: =IF(N$7*LN(N$7)-N$7*((N10+O10)/2)+(1-N$7)*LN(1-N$7)-(1-N$7)*LN(1-EXP(((N10+O10)/2)))-N$6>0,O10,((N10+O10)/2)) -> -2.9957323 | P11: =IF(P$7*LN(P$7)-P$7*((P10+Q10)/2)+(1-P$7)*LN(1-P$7)-(1-P$7)*LN(1-EXP(((P10+Q10)/2)))-P$6>0,((P10+Q10)/2),P10) -> -19.516187 | Q11: =IF(P$7*LN(P$7)-P$7*((P10+Q10)/2)+(1-P$7)*LN(1-P$7)-(1-P$7)*LN(1-EXP(((P10+Q10)/2)))-P$6>0,Q10,((P10+Q10)/2)) -> -2.9957323 | R11: =IF(R$7*LN(R$7)-R$7*((R10+S10)/2)+(1-R$7)*LN(1-R$7)-(1-R$7)*LN(1-EXP(((R10+S10)/2)))-R$6>0,((R10+S10)/2),R10) -> -19.516187 | S11: =IF(R$7*LN(R$7)-R$7*((R10+S10)/2)+(1-R$7)*LN(1-R$7)-(1-R$7)*LN(1-EXP(((R10+S10)/2)))-R$6>0,S10,((R10+S10)/2)) -> -2.9957323 | T11: =IF(T$7*LN(T$7)-T$7*((T10+U10)/2)+(1-T$7)*LN(1-T$7)-(1-T$7)*LN(1-EXP(((T10+U10)/2)))-T$6>0,((T10+U10)/2),T10) -> -19.516187 | U11: =IF(T$7*LN(T$7)-T$7*((T10+U10)/2)+(1-T$7)*LN(1-T$7)-(1-T$7)*LN(1-EXP(((T10+U10)/2)))-T$6>0,U10,((T10+U10)/2)) -> -2.9957323 | V11: =IF(V$7*LN(V$7)-V$7*((V10+W10)/2)+(1-V$7)*LN(1-V$7)-(1-V$7)*LN(1-EXP(((V10+W10)/2)))-V$6>0,((V10+W10)/2),V10) -> -19.516187 | W11: =IF(V$7*LN(V$7)-V$7*((V10+W10)/2)+(1-V$7)*LN(1-V$7)-(1-V$7)*LN(1-EXP(((V10+W10)/2)))-V$6>0,W10,((V10+W10)/2)) -> -2.9957323 | X11: =IF(X$7*LN(X$7)-X$7*((X10+Y10)/2)+(1-X$7)*LN(1-X$7)-(1-X$7)*LN(1-EXP(((X10+Y10)/2)))-X$6>0,((X10+Y10)/2),X10) -> -19.516187 | Y11: =IF(X$7*LN(X$7)-X$7*((X10+Y10)/2)+(1-X$7)*LN(1-X$7)-(1-X$7)*LN(1-EXP(((X10+Y10)/2)))-X$6>0,Y10,((X10+Y10)/2)) -> -2.9957323 | Z11: =IF(Z$7*LN(Z$7)-Z$7*((Z10+AA10)/2)+(1-Z$7)*LN(1-Z$7)-(1-Z$7)*LN(1-EXP(((Z10+AA10)/2)))-Z$6>0,((Z10+AA10)/2),Z10) -> -19.516187 | AA11: =IF(Z$7*LN(Z$7)-Z$7*((Z10+AA10)/2)+(1-Z$7)*LN(1-Z$7)-(1-Z$7)*LN(1-EXP(((Z10+AA10)/2)))-Z$6>0,AA10,((Z10+AA10)/2)) -> -2.9957323 | AB11: =IF((((AB10+AC10)/2))*LN((((AB10+AC10)/2))/(AB$7))+(1-(((AB10+AC10)/2)))*LN((1-(((AB10+AC10)/2)))/(1-(AB$7)))-AB$6<0,((AB10+AC10)/2),AB10) -> 0.05 | AC11: =IF((((AB10+AC10)/2))*LN((((AB10+AC10)/2))/(AB$7))+(1-(((AB10+AC10)/2)))*LN((1-(((AB10+AC10)/2)))/(1-(AB$7)))-AB$6<0,AC10,((AB10+AC10)/2)) -> 0.2875 | AD11: =IF((((AD10+AE10)/2))*LN((((AD10+AE10)/2))/(AD$7))+(1-(((AD10+AE10)/2)))*LN((1-(((AD10+AE10)/2)))/(1-(AD$7)))-AD$6<0,((AD10+AE10)/2),AD10) -> 0.05 | AE11: =IF((((AD10+AE10)/2))*LN((((AD10+AE10)/2))/(AD$7))+(1-(((AD10+AE10)/2)))*LN((1-(((AD10+AE10)/2)))/(1-(AD$7)))-AD$6<0,AE10,((AD10+AE10)/2)) -> 0.2875 | AF11: =IF((((AF10+AG10)/2))*LN((((AF10+AG10)/2))/(AF$7))+(1-(((AF10+AG10)/2)))*LN((1-(((AF10+AG10)/2)))/(1-(AF$7)))-AF$6<0,((AF10+AG10)/2),AF10) -> 0.05 | AG11: =IF((((AF10+AG10)/2))*LN((((AF10+AG10)/2))/(AF$7))+(1-(((AF10+AG10)/2)))*LN((1-(((AF10+AG10)/2)))/(1-(AF$7)))-AF$6<0,AG10,((AF10+AG10)/2)) -> 0.2875 | AH11: =IF((((AH10+AI10)/2))*LN((((AH10+AI10)/2))/(AH$7))+(1-(((AH10+AI10)/2)))*LN((1-(((AH10+AI10)/2)))/(1-(AH$7)))-AH$6<0,((AH10+AI10)/2),AH10) -> 0.05 | AI11: =IF((((AH10+AI10)/2))*LN((((AH10+AI10)/2))/(AH$7))+(1-(((AH10+AI10)/2)))*LN((1-(((AH10+AI10)/2)))/(1-(AH$7)))-AH$6<0,AI10,((AH10+AI10)/2)) -> 0.2875 | AJ11: =IF((((AJ10+AK10)/2))*LN((((AJ10+AK10)/2))/(AJ$7))+(1-(((AJ10+AK10)/2)))*LN((1-(((AJ10+AK10)/2)))/(1-(AJ$7)))-AJ$6<0,((AJ10+AK10)/2),AJ10) -> 0.05 | AK11: =IF((((AJ10+AK10)/2))*LN((((AJ10+AK10)/2))/(AJ$7))+(1-(((AJ10+AK10)/2)))*LN((1-(((AJ10+AK10)/2)))/(1-(AJ$7)))-AJ$6<0,AK10,((AJ10+AK10)/2)) -> 0.2875 | AL11: =IF((((AL10+AM10)/2))*LN((((AL10+AM10)/2))/(AL$7))+(1-(((AL10+AM10)/2)))*LN((1-(((AL10+AM10)/2)))/(1-(AL$7)))-AL$6<0,((AL10+AM10)/2),AL10) -> 0.2875 | AM11: =IF((((AL10+AM10)/2))*LN((((AL10+AM10)/2))/(AL$7))+(1-(((AL10+AM10)/2)))*LN((1-(((AL10+AM10)/2)))/(1-(AL$7)))-AL$6<0,AM10,((AL10+AM10)/2)) -> 0.525 | AN11: =IF((((AN10+AO10)/2))*LN((((AN10+AO10)/2))/(AN$7))+(1-(((AN10+AO10)/2)))*LN((1-(((AN10+AO10)/2)))/(1-(AN$7)))-AN$6<0,((AN10+AO10)/2),AN10) -> 0.525 | AO11: =IF((((AN10+AO10)/2))*LN((((AN10+AO10)/2))/(AN$7))+(1-(((AN10+AO10)/2)))*LN((1-(((AN10+AO10)/2)))/(1-(AN$7)))-AN$6<0,AO10,((AN10+AO10)/2)) -> 0.7625 | AP11: =IF(AP$7*LN(AP$7)-AP$7*((AP10+AQ10)/2)+(1-AP$7)*LN(1-AP$7)-(1-AP$7)*LN(1-EXP(((AP10+AQ10)/2)))-AP$6>0,((AP10+AQ10)/2),AP10) -> -19.516187 | AQ11: =IF(AP$7*LN(AP$7)-AP$7*((AP10+AQ10)/2)+(1-AP$7)*LN(1-AP$7)-(1-AP$7)*LN(1-EXP(((AP10+AQ10)/2)))-AP$6>0,AQ10,((AP10+AQ10)/2)) -> -2.9957323 | AR11: =IF((((AR10+AS10)/2))*LN((((AR10+AS10)/2))/(AR$7))+(1-(((AR10+AS10)/2)))*LN((1-(((AR10+AS10)/2)))/(1-(AR$7)))-AR$6<0,((AR10+AS10)/2),AR10) -> 0.05 | AS11: =IF((((AR10+AS10)/2))*LN((((AR10+AS10)/2))/(AR$7))+(1-(((AR10+AS10)/2)))*LN((1-(((AR10+AS10)/2)))/(1-(AR$7)))-AR$6<0,AS10,((AR10+AS10)/2)) -> 0.2875
B12: =IF(B$7*LN(B$7)-B$7*((B11+C11)/2)+(1-B$7)*LN(1-B$7)-(1-B$7)*LN(1-EXP(((B11+C11)/2)))-B$6>0,((B11+C11)/2),B11) -> -19.516187 | C12: =IF(B$7*LN(B$7)-B$7*((B11+C11)/2)+(1-B$7)*LN(1-B$7)-(1-B$7)*LN(1-EXP(((B11+C11)/2)))-B$6>0,C11,((B11+C11)/2)) -> -11.25596 | D12: =IF(D$7*LN(D$7)-D$7*((D11+E11)/2)+(1-D$7)*LN(1-D$7)-(1-D$7)*LN(1-EXP(((D11+E11)/2)))-D$6>0,((D11+E11)/2),D11) -> -19.516187 | E12: =IF(D$7*LN(D$7)-D$7*((D11+E11)/2)+(1-D$7)*LN(1-D$7)-(1-D$7)*LN(1-EXP(((D11+E11)/2)))-D$6>0,E11,((D11+E11)/2)) -> -11.25596 | F12: =IF(F$7*LN(F$7)-F$7*((F11+G11)/2)+(1-F$7)*LN(1-F$7)-(1-F$7)*LN(1-EXP(((F11+G11)/2)))-F$6>0,((F11+G11)/2),F11) -> -27.776415 | G12: =IF(F$7*LN(F$7)-F$7*((F11+G11)/2)+(1-F$7)*LN(1-F$7)-(1-F$7)*LN(1-EXP(((F11+G11)/2)))-F$6>0,G11,((F11+G11)/2)) -> -19.516187 | H12: =IF(H$7*LN(H$7)-H$7*((H11+I11)/2)+(1-H$7)*LN(1-H$7)-(1-H$7)*LN(1-EXP(((H11+I11)/2)))-H$6>0,((H11+I11)/2),H11) -> -11.25596 | I12: =IF(H$7*LN(H$7)-H$7*((H11+I11)/2)+(1-H$7)*LN(1-H$7)-(1-H$7)*LN(1-EXP(((H11+I11)/2)))-H$6>0,I11,((H11+I11)/2)) -> -2.9957323 | J12: =IF(J$7*LN(J$7)-J$7*((J11+K11)/2)+(1-J$7)*LN(1-J$7)-(1-J$7)*LN(1-EXP(((J11+K11)/2)))-J$6>0,((J11+K11)/2),J11) -> -11.25596 | K12: =IF(J$7*LN(J$7)-J$7*((J11+K11)/2)+(1-J$7)*LN(1-J$7)-(1-J$7)*LN(1-EXP(((J11+K11)/2)))-J$6>0,K11,((J11+K11)/2)) -> -2.9957323 | L12: =IF(L$7*LN(L$7)-L$7*((L11+M11)/2)+(1-L$7)*LN(1-L$7)-(1-L$7)*LN(1-EXP(((L11+M11)/2)))-L$6>0,((L11+M11)/2),L11) -> -11.25596 | M12: =IF(L$7*LN(L$7)-L$7*((L11+M11)/2)+(1-L$7)*LN(1-L$7)-(1-L$7)*LN(1-EXP(((L11+M11)/2)))-L$6>0,M11,((L11+M11)/2)) -> -2.9957323 | N12: =IF(N$7*LN(N$7)-N$7*((N11+O11)/2)+(1-N$7)*LN(1-N$7)-(1-N$7)*LN(1-EXP(((N11+O11)/2)))-N$6>0,((N11+O11)/2),N11) -> -11.25596 | O12: =IF(N$7*LN(N$7)-N$7*((N11+O11)/2)+(1-N$7)*LN(1-N$7)-(1-N$7)*LN(1-EXP(((N11+O11)/2)))-N$6>0,O11,((N11+O11)/2)) -> -2.9957323 | P12: =IF(P$7*LN(P$7)-P$7*((P11+Q11)/2)+(1-P$7)*LN(1-P$7)-(1-P$7)*LN(1-EXP(((P11+Q11)/2)))-P$6>0,((P11+Q11)/2),P11) -> -11.25596 | Q12: =IF(P$7*LN(P$7)-P$7*((P11+Q11)/2)+(1-P$7)*LN(1-P$7)-(1-P$7)*LN(1-EXP(((P11+Q11)/2)))-P$6>0,Q11,((P11+Q11)/2)) -> -2.9957323 | R12: =IF(R$7*LN(R$7)-R$7*((R11+S11)/2)+(1-R$7)*LN(1-R$7)-(1-R$7)*LN(1-EXP(((R11+S11)/2)))-R$6>0,((R11+S11)/2),R11) -> -11.25596 | S12: =IF(R$7*LN(R$7)-R$7*((R11+S11)/2)+(1-R$7)*LN(1-R$7)-(1-R$7)*LN(1-EXP(((R11+S11)/2)))-R$6>0,S11,((R11+S11)/2)) -> -2.9957323 | T12: =IF(T$7*LN(T$7)-T$7*((T11+U11)/2)+(1-T$7)*LN(1-T$7)-(1-T$7)*LN(1-EXP(((T11+U11)/2)))-T$6>0,((T11+U11)/2),T11) -> -11.25596 | U12: =IF(T$7*LN(T$7)-T$7*((T11+U11)/2)+(1-T$7)*LN(1-T$7)-(1-T$7)*LN(1-EXP(((T11+U11)/2)))-T$6>0,U11,((T11+U11)/2)) -> -2.9957323 | V12: =IF(V$7*LN(V$7)-V$7*((V11+W11)/2)+(1-V$7)*LN(1-V$7)-(1-V$7)*LN(1-EXP(((V11+W11)/2)))-V$6>0,((V11+W11)/2),V11) -> -11.25596 | W12: =IF(V$7*LN(V$7)-V$7*((V11+W11)/2)+(1-V$7)*LN(1-V$7)-(1-V$7)*LN(1-EXP(((V11+W11)/2)))-V$6>0,W11,((V11+W11)/2)) -> -2.9957323 | X12: =IF(X$7*LN(X$7)-X$7*((X11+Y11)/2)+(1-X$7)*LN(1-X$7)-(1-X$7)*LN(1-EXP(((X11+Y11)/2)))-X$6>0,((X11+Y11)/2),X11) -> -11.25596 | Y12: =IF(X$7*LN(X$7)-X$7*((X11+Y11)/2)+(1-X$7)*LN(1-X$7)-(1-X$7)*LN(1-EXP(((X11+Y11)/2)))-X$6>0,Y11,((X11+Y11)/2)) -> -2.9957323 | Z12: =IF(Z$7*LN(Z$7)-Z$7*((Z11+AA11)/2)+(1-Z$7)*LN(1-Z$7)-(1-Z$7)*LN(1-EXP(((Z11+AA11)/2)))-Z$6>0,((Z11+AA11)/2),Z11) -> -11.25596 | AA12: =IF(Z$7*LN(Z$7)-Z$7*((Z11+AA11)/2)+(1-Z$7)*LN(1-Z$7)-(1-Z$7)*LN(1-EXP(((Z11+AA11)/2)))-Z$6>0,AA11,((Z11+AA11)/2)) -> -2.9957323 | AB12: =IF((((AB11+AC11)/2))*LN((((AB11+AC11)/2))/(AB$7))+(1-(((AB11+AC11)/2)))*LN((1-(((AB11+AC11)/2)))/(1-(AB$7)))-AB$6<0,((AB11+AC11)/2),AB11) -> 0.05 | AC12: =IF((((AB11+AC11)/2))*LN((((AB11+AC11)/2))/(AB$7))+(1-(((AB11+AC11)/2)))*LN((1-(((AB11+AC11)/2)))/(1-(AB$7)))-AB$6<0,AC11,((AB11+AC11)/2)) -> 0.16875 | AD12: =IF((((AD11+AE11)/2))*LN((((AD11+AE11)/2))/(AD$7))+(1-(((AD11+AE11)/2)))*LN((1-(((AD11+AE11)/2)))/(1-(AD$7)))-AD$6<0,((AD11+AE11)/2),AD11) -> 0.05 | AE12: =IF((((AD11+AE11)/2))*LN((((AD11+AE11)/2))/(AD$7))+(1-(((AD11+AE11)/2)))*LN((1-(((AD11+AE11)/2)))/(1-(AD$7)))-AD$6<0,AE11,((AD11+AE11)/2)) -> 0.16875 | AF12: =IF((((AF11+AG11)/2))*LN((((AF11+AG11)/2))/(AF$7))+(1-(((AF11+AG11)/2)))*LN((1-(((AF11+AG11)/2)))/(1-(AF$7)))-AF$6<0,((AF11+AG11)/2),AF11) -> 0.05 | AG12: =IF((((AF11+AG11)/2))*LN((((AF11+AG11)/2))/(AF$7))+(1-(((AF11+AG11)/2)))*LN((1-(((AF11+AG11)/2)))/(1-(AF$7)))-AF$6<0,AG11,((AF11+AG11)/2)) -> 0.16875 | AH12: =IF((((AH11+AI11)/2))*LN((((AH11+AI11)/2))/(AH$7))+(1-(((AH11+AI11)/2)))*LN((1-(((AH11+AI11)/2)))/(1-(AH$7)))-AH$6<0,((AH11+AI11)/2),AH11) -> 0.05 | AI12: =IF((((AH11+AI11)/2))*LN((((AH11+AI11)/2))/(AH$7))+(1-(((AH11+AI11)/2)))*LN((1-(((AH11+AI11)/2)))/(1-(AH$7)))-AH$6<0,AI11,((AH11+AI11)/2)) -> 0.16875 | AJ12: =IF((((AJ11+AK11)/2))*LN((((AJ11+AK11)/2))/(AJ$7))+(1-(((AJ11+AK11)/2)))*LN((1-(((AJ11+AK11)/2)))/(1-(AJ$7)))-AJ$6<0,((AJ11+AK11)/2),AJ11) -> 0.16875 | AK12: =IF((((AJ11+AK11)/2))*LN((((AJ11+AK11)/2))/(AJ$7))+(1-(((AJ11+AK11)/2)))*LN((1-(((AJ11+AK11)/2)))/(1-(AJ$7)))-AJ$6<0,AK11,((AJ11+AK11)/2)) -> 0.2875 | AL12: =IF((((AL11+AM11)/2))*LN((((AL11+AM11)/2))/(AL$7))+(1-(((AL11+AM11)/2)))*LN((1-(((AL11+AM11)/2)))/(1-(AL$7)))-AL$6<0,((AL11+AM11)/2),AL11) -> 0.2875 | AM12: =IF((((AL11+AM11)/2))*LN((((AL11+AM11)/2))/(AL$7))+(1-(((AL11+AM11)/2)))*LN((1-(((AL11+AM11)/2)))/(1-(AL$7)))-AL$6<0,AM11,((AL11+AM11)/2)) -> 0.40625 | AN12: =IF((((AN11+AO11)/2))*LN((((AN11+AO11)/2))/(AN$7))+(1-(((AN11+AO11)/2)))*LN((1-(((AN11+AO11)/2)))/(1-(AN$7)))-AN$6<0,((AN11+AO11)/2),AN11) -> 0.525 | AO12: =IF((((AN11+AO11)/2))*LN((((AN11+AO11)/2))/(AN$7))+(1-(((AN11+AO11)/2)))*LN((1-(((AN11+AO11)/2)))/(1-(AN$7)))-AN$6<0,AO11,((AN11+AO11)/2)) -> 0.64375 | AP12: =IF(AP$7*LN(AP$7)-AP$7*((AP11+AQ11)/2)+(1-AP$7)*LN(1-AP$7)-(1-AP$7)*LN(1-EXP(((AP11+AQ11)/2)))-AP$6>0,((AP11+AQ11)/2),AP11) -> -11.25596 | AQ12: =IF(AP$7*LN(AP$7)-AP$7*((AP11+AQ11)/2)+(1-AP$7)*LN(1-AP$7)-(1-AP$7)*LN(1-EXP(((AP11+AQ11)/2)))-AP$6>0,AQ11,((AP11+AQ11)/2)) -> -2.9957323 | AR12: =IF((((AR11+AS11)/2))*LN((((AR11+AS11)/2))/(AR$7))+(1-(((AR11+AS11)/2)))*LN((1-(((AR11+AS11)/2)))/(1-(AR$7)))-AR$6<0,((AR11+AS11)/2),AR11) -> 0.05 | AS12: =IF((((AR11+AS11)/2))*LN((((AR11+AS11)/2))/(AR$7))+(1-(((AR11+AS11)/2)))*LN((1-(((AR11+AS11)/2)))/(1-(AR$7)))-AR$6<0,AS11,((AR11+AS11)/2)) -> 0.16875
B13: =IF(B$7*LN(B$7)-B$7*((B12+C12)/2)+(1-B$7)*LN(1-B$7)-(1-B$7)*LN(1-EXP(((B12+C12)/2)))-B$6>0,((B12+C12)/2),B12) -> -15.386074 | C13: =IF(B$7*LN(B$7)-B$7*((B12+C12)/2)+(1-B$7)*LN(1-B$7)-(1-B$7)*LN(1-EXP(((B12+C12)/2)))-B$6>0,C12,((B12+C12)/2)) -> -11.25596 | D13: =IF(D$7*LN(D$7)-D$7*((D12+E12)/2)+(1-D$7)*LN(1-D$7)-(1-D$7)*LN(1-EXP(((D12+E12)/2)))-D$6>0,((D12+E12)/2),D12) -> -19.516187 | E13: =IF(D$7*LN(D$7)-D$7*((D12+E12)/2)+(1-D$7)*LN(1-D$7)-(1-D$7)*LN(1-EXP(((D12+E12)/2)))-D$6>0,E12,((D12+E12)/2)) -> -15.386074 | F13: =IF(F$7*LN(F$7)-F$7*((F12+G12)/2)+(1-F$7)*LN(1-F$7)-(1-F$7)*LN(1-EXP(((F12+G12)/2)))-F$6>0,((F12+G12)/2),F12) -> -27.776415 | G13: =IF(F$7*LN(F$7)-F$7*((F12+G12)/2)+(1-F$7)*LN(1-F$7)-(1-F$7)*LN(1-EXP(((F12+G12)/2)))-F$6>0,G12,((F12+G12)/2)) -> -23.646301 | H13: =IF(H$7*LN(H$7)-H$7*((H12+I12)/2)+(1-H$7)*LN(1-H$7)-(1-H$7)*LN(1-EXP(((H12+I12)/2)))-H$6>0,((H12+I12)/2),H12) -> -7.1258461 | I13: =IF(H$7*LN(H$7)-H$7*((H12+I12)/2)+(1-H$7)*LN(1-H$7)-(1-H$7)*LN(1-EXP(((H12+I12)/2)))-H$6>0,I12,((H12+I12)/2)) -> -2.9957323 | J13: =IF(J$7*LN(J$7)-J$7*((J12+K12)/2)+(1-J$7)*LN(1-J$7)-(1-J$7)*LN(1-EXP(((J12+K12)/2)))-J$6>0,((J12+K12)/2),J12) -> -7.1258461 | K13: =IF(J$7*LN(J$7)-J$7*((J12+K12)/2)+(1-J$7)*LN(1-J$7)-(1-J$7)*LN(1-EXP(((J12+K12)/2)))-J$6>0,K12,((J12+K12)/2)) -> -2.9957323 | L13: =IF(L$7*LN(L$7)-L$7*((L12+M12)/2)+(1-L$7)*LN(1-L$7)-(1-L$7)*LN(1-EXP(((L12+M12)/2)))-L$6>0,((L12+M12)/2),L12) -> -7.1258461 | M13: =IF(L$7*LN(L$7)-L$7*((L12+M12)/2)+(1-L$7)*LN(1-L$7)-(1-L$7)*LN(1-EXP(((L12+M12)/2)))-L$6>0,M12,((L12+M12)/2)) -> -2.9957323 | N13: =IF(N$7*LN(N$7)-N$7*((N12+O12)/2)+(1-N$7)*LN(1-N$7)-(1-N$7)*LN(1-EXP(((N12+O12)/2)))-N$6>0,((N12+O12)/2),N12) -> -7.1258461 | O13: =IF(N$7*LN(N$7)-N$7*((N12+O12)/2)+(1-N$7)*LN(1-N$7)-(1-N$7)*LN(1-EXP(((N12+O12)/2)))-N$6>0,O12,((N12+O12)/2)) -> -2.9957323 | P13: =IF(P$7*LN(P$7)-P$7*((P12+Q12)/2)+(1-P$7)*LN(1-P$7)-(1-P$7)*LN(1-EXP(((P12+Q12)/2)))-P$6>0,((P12+Q12)/2),P12) -> -7.1258461 | Q13: =IF(P$7*LN(P$7)-P$7*((P12+Q12)/2)+(1-P$7)*LN(1-P$7)-(1-P$7)*LN(1-EXP(((P12+Q12)/2)))-P$6>0,Q12,((P12+Q12)/2)) -> -2.9957323 | R13: =IF(R$7*LN(R$7)-R$7*((R12+S12)/2)+(1-R$7)*LN(1-R$7)-(1-R$7)*LN(1-EXP(((R12+S12)/2)))-R$6>0,((R12+S12)/2),R12) -> -7.1258461 | S13: =IF(R$7*LN(R$7)-R$7*((R12+S12)/2)+(1-R$7)*LN(1-R$7)-(1-R$7)*LN(1-EXP(((R12+S12)/2)))-R$6>0,S12,((R12+S12)/2)) -> -2.9957323 | T13: =IF(T$7*LN(T$7)-T$7*((T12+U12)/2)+(1-T$7)*LN(1-T$7)-(1-T$7)*LN(1-EXP(((T12+U12)/2)))-T$6>0,((T12+U12)/2),T12) -> -7.1258461 | U13: =IF(T$7*LN(T$7)-T$7*((T12+U12)/2)+(1-T$7)*LN(1-T$7)-(1-T$7)*LN(1-EXP(((T12+U12)/2)))-T$6>0,U12,((T12+U12)/2)) -> -2.9957323 | V13: =IF(V$7*LN(V$7)-V$7*((V12+W12)/2)+(1-V$7)*LN(1-V$7)-(1-V$7)*LN(1-EXP(((V12+W12)/2)))-V$6>0,((V12+W12)/2),V12) -> -7.1258461 | W13: =IF(V$7*LN(V$7)-V$7*((V12+W12)/2)+(1-V$7)*LN(1-V$7)-(1-V$7)*LN(1-EXP(((V12+W12)/2)))-V$6>0,W12,((V12+W12)/2)) -> -2.9957323 | X13: =IF(X$7*LN(X$7)-X$7*((X12+Y12)/2)+(1-X$7)*LN(1-X$7)-(1-X$7)*LN(1-EXP(((X12+Y12)/2)))-X$6>0,((X12+Y12)/2),X12) -> -7.1258461 | Y13: =IF(X$7*LN(X$7)-X$7*((X12+Y12)/2)+(1-X$7)*LN(1-X$7)-(1-X$7)*LN(1-EXP(((X12+Y12)/2)))-X$6>0,Y12,((X12+Y12)/2)) -> -2.9957323 | Z13: =IF(Z$7*LN(Z$7)-Z$7*((Z12+AA12)/2)+(1-Z$7)*LN(1-Z$7)-(1-Z$7)*LN(1-EXP(((Z12+AA12)/2)))-Z$6>0,((Z12+AA12)/2),Z12) -> -7.1258461 | AA13: =IF(Z$7*LN(Z$7)-Z$7*((Z12+AA12)/2)+(1-Z$7)*LN(1-Z$7)-(1-Z$7)*LN(1-EXP(((Z12+AA12)/2)))-Z$6>0,AA12,((Z12+AA12)/2)) -> -2.9957323 | AB13: =IF((((AB12+AC12)/2))*LN((((AB12+AC12)/2))/(AB$7))+(1-(((AB12+AC12)/2)))*LN((1-(((AB12+AC12)/2)))/(1-(AB$7)))-AB$6<0,((AB12+AC12)/2),AB12) -> 0.05 | AC13: =IF((((AB12+AC12)/2))*LN((((AB12+AC12)/2))/(AB$7))+(1-(((AB12+AC12)/2)))*LN((1-(((AB12+AC12)/2)))/(1-(AB$7)))-AB$6<0,AC12,((AB12+AC12)/2)) -> 0.109375 | AD13: =IF((((AD12+AE12)/2))*LN((((AD12+AE12)/2))/(AD$7))+(1-(((AD12+AE12)/2)))*LN((1-(((AD12+AE12)/2)))/(1-(AD$7)))-AD$6<0,((AD12+AE12)/2),AD12) -> 0.05 | AE13: =IF((((AD12+AE12)/2))*LN((((AD12+AE12)/2))/(AD$7))+(1-(((AD12+AE12)/2)))*LN((1-(((AD12+AE12)/2)))/(1-(AD$7)))-AD$6<0,AE12,((AD12+AE12)/2)) -> 0.109375 | AF13: =IF((((AF12+AG12)/2))*LN((((AF12+AG12)/2))/(AF$7))+(1-(((AF12+AG12)/2)))*LN((1-(((AF12+AG12)/2)))/(1-(AF$7)))-AF$6<0,((AF12+AG12)/2),AF12) -> 0.05 | AG13: =IF((((AF12+AG12)/2))*LN((((AF12+AG12)/2))/(AF$7))+(1-(((AF12+AG12)/2)))*LN((1-(((AF12+AG12)/2)))/(1-(AF$7)))-AF$6<0,AG12,((AF12+AG12)/2)) -> 0.109375 | AH13: =IF((((AH12+AI12)/2))*LN((((AH12+AI12)/2))/(AH$7))+(1-(((AH12+AI12)/2)))*LN((1-(((AH12+AI12)/2)))/(1-(AH$7)))-AH$6<0,((AH12+AI12)/2),AH12) -> 0.109375 | AI13: =IF((((AH12+AI12)/2))*LN((((AH12+AI12)/2))/(AH$7))+(1-(((AH12+AI12)/2)))*LN((1-(((AH12+AI12)/2)))/(1-(AH$7)))-AH$6<0,AI12,((AH12+AI12)/2)) -> 0.16875 | AJ13: =IF((((AJ12+AK12)/2))*LN((((AJ12+AK12)/2))/(AJ$7))+(1-(((AJ12+AK12)/2)))*LN((1-(((AJ12+AK12)/2)))/(1-(AJ$7)))-AJ$6<0,((AJ12+AK12)/2),AJ12) -> 0.16875 | AK13: =IF((((AJ12+AK12)/2))*LN((((AJ12+AK12)/2))/(AJ$7))+(1-(((AJ12+AK12)/2)))*LN((1-(((AJ12+AK12)/2)))/(1-(AJ$7)))-AJ$6<0,AK12,((AJ12+AK12)/2)) -> 0.228125 | AL13: =IF((((AL12+AM12)/2))*LN((((AL12+AM12)/2))/(AL$7))+(1-(((AL12+AM12)/2)))*LN((1-(((AL12+AM12)/2)))/(1-(AL$7)))-AL$6<0,((AL12+AM12)/2),AL12) -> 0.2875 | AM13: =IF((((AL12+AM12)/2))*LN((((AL12+AM12)/2))/(AL$7))+(1-(((AL12+AM12)/2)))*LN((1-(((AL12+AM12)/2)))/(1-(AL$7)))-AL$6<0,AM12,((AL12+AM12)/2)) -> 0.346875 | AN13: =IF((((AN12+AO12)/2))*LN((((AN12+AO12)/2))/(AN$7))+(1-(((AN12+AO12)/2)))*LN((1-(((AN12+AO12)/2)))/(1-(AN$7)))-AN$6<0,((AN12+AO12)/2),AN12) -> 0.525 | AO13: =IF((((AN12+AO12)/2))*LN((((AN12+AO12)/2))/(AN$7))+(1-(((AN12+AO12)/2)))*LN((1-(((AN12+AO12)/2)))/(1-(AN$7)))-AN$6<0,AO12,((AN12+AO12)/2)) -> 0.584375 | AP13: =IF(AP$7*LN(AP$7)-AP$7*((AP12+AQ12)/2)+(1-AP$7)*LN(1-AP$7)-(1-AP$7)*LN(1-EXP(((AP12+AQ12)/2)))-AP$6>0,((AP12+AQ12)/2),AP12) -> -7.1258461 | AQ13: =IF(AP$7*LN(AP$7)-AP$7*((AP12+AQ12)/2)+(1-AP$7)*LN(1-AP$7)-(1-AP$7)*LN(1-EXP(((AP12+AQ12)/2)))-AP$6>0,AQ12,((AP12+AQ12)/2)) -> -2.9957323 | AR13: =IF((((AR12+AS12)/2))*LN((((AR12+AS12)/2))/(AR$7))+(1-(((AR12+AS12)/2)))*LN((1-(((AR12+AS12)/2)))/(1-(AR$7)))-AR$6<0,((AR12+AS12)/2),AR12) -> 0.05 | AS13: =IF((((AR12+AS12)/2))*LN((((AR12+AS12)/2))/(AR$7))+(1-(((AR12+AS12)/2)))*LN((1-(((AR12+AS12)/2)))/(1-(AR$7)))-AR$6<0,AS12,((AR12+AS12)/2)) -> 0.109375
B14: =IF(B$7*LN(B$7)-B$7*((B13+C13)/2)+(1-B$7)*LN(1-B$7)-(1-B$7)*LN(1-EXP(((B13+C13)/2)))-B$6>0,((B13+C13)/2),B13) -> -13.321017 | C14: =IF(B$7*LN(B$7)-B$7*((B13+C13)/2)+(1-B$7)*LN(1-B$7)-(1-B$7)*LN(1-EXP(((B13+C13)/2)))-B$6>0,C13,((B13+C13)/2)) -> -11.25596 | D14: =IF(D$7*LN(D$7)-D$7*((D13+E13)/2)+(1-D$7)*LN(1-D$7)-(1-D$7)*LN(1-EXP(((D13+E13)/2)))-D$6>0,((D13+E13)/2),D13) -> -17.451131 | E14: =IF(D$7*LN(D$7)-D$7*((D13+E13)/2)+(1-D$7)*LN(1-D$7)-(1-D$7)*LN(1-EXP(((D13+E13)/2)))-D$6>0,E13,((D13+E13)/2)) -> -15.386074 | F14: =IF(F$7*LN(F$7)-F$7*((F13+G13)/2)+(1-F$7)*LN(1-F$7)-(1-F$7)*LN(1-EXP(((F13+G13)/2)))-F$6>0,((F13+G13)/2),F13) -> -25.711358 | G14: =IF(F$7*LN(F$7)-F$7*((F13+G13)/2)+(1-F$7)*LN(1-F$7)-(1-F$7)*LN(1-EXP(((F13+G13)/2)))-F$6>0,G13,((F13+G13)/2)) -> -23.646301 | H14: =IF(H$7*LN(H$7)-H$7*((H13+I13)/2)+(1-H$7)*LN(1-H$7)-(1-H$7)*LN(1-EXP(((H13+I13)/2)))-H$6>0,((H13+I13)/2),H13) -> -5.0607892 | I14: =IF(H$7*LN(H$7)-H$7*((H13+I13)/2)+(1-H$7)*LN(1-H$7)-(1-H$7)*LN(1-EXP(((H13+I13)/2)))-H$6>0,I13,((H13+I13)/2)) -> -2.9957323 | J14: =IF(J$7*LN(J$7)-J$7*((J13+K13)/2)+(1-J$7)*LN(1-J$7)-(1-J$7)*LN(1-EXP(((J13+K13)/2)))-J$6>0,((J13+K13)/2),J13) -> -5.0607892 | K14: =IF(J$7*LN(J$7)-J$7*((J13+K13)/2)+(1-J$7)*LN(1-J$7)-(1-J$7)*LN(1-EXP(((J13+K13)/2)))-J$6>0,K13,((J13+K13)/2)) -> -2.9957323 | L14: =IF(L$7*LN(L$7)-L$7*((L13+M13)/2)+(1-L$7)*LN(1-L$7)-(1-L$7)*LN(1-EXP(((L13+M13)/2)))-L$6>0,((L13+M13)/2),L13) -> -5.0607892 | M14: =IF(L$7*LN(L$7)-L$7*((L13+M13)/2)+(1-L$7)*LN(1-L$7)-(1-L$7)*LN(1-EXP(((L13+M13)/2)))-L$6>0,M13,((L13+M13)/2)) -> -2.9957323 | N14: =IF(N$7*LN(N$7)-N$7*((N13+O13)/2)+(1-N$7)*LN(1-N$7)-(1-N$7)*LN(1-EXP(((N13+O13)/2)))-N$6>0,((N13+O13)/2),N13) -> -5.0607892 | O14: =IF(N$7*LN(N$7)-N$7*((N13+O13)/2)+(1-N$7)*LN(1-N$7)-(1-N$7)*LN(1-EXP(((N13+O13)/2)))-N$6>0,O13,((N13+O13)/2)) -> -2.9957323 | P14: =IF(P$7*LN(P$7)-P$7*((P13+Q13)/2)+(1-P$7)*LN(1-P$7)-(1-P$7)*LN(1-EXP(((P13+Q13)/2)))-P$6>0,((P13+Q13)/2),P13) -> -5.0607892 | Q14: =IF(P$7*LN(P$7)-P$7*((P13+Q13)/2)+(1-P$7)*LN(1-P$7)-(1-P$7)*LN(1-EXP(((P13+Q13)/2)))-P$6>0,Q13,((P13+Q13)/2)) -> -2.9957323 | R14: =IF(R$7*LN(R$7)-R$7*((R13+S13)/2)+(1-R$7)*LN(1-R$7)-(1-R$7)*LN(1-EXP(((R13+S13)/2)))-R$6>0,((R13+S13)/2),R13) -> -5.0607892 | S14: =IF(R$7*LN(R$7)-R$7*((R13+S13)/2)+(1-R$7)*LN(1-R$7)-(1-R$7)*LN(1-EXP(((R13+S13)/2)))-R$6>0,S13,((R13+S13)/2)) -> -2.9957323 | T14: =IF(T$7*LN(T$7)-T$7*((T13+U13)/2)+(1-T$7)*LN(1-T$7)-(1-T$7)*LN(1-EXP(((T13+U13)/2)))-T$6>0,((T13+U13)/2),T13) -> -5.0607892 | U14: =IF(T$7*LN(T$7)-T$7*((T13+U13)/2)+(1-T$7)*LN(1-T$7)-(1-T$7)*LN(1-EXP(((T13+U13)/2)))-T$6>0,U13,((T13+U13)/2)) -> -2.9957323 | V14: =IF(V$7*LN(V$7)-V$7*((V13+W13)/2)+(1-V$7)*LN(1-V$7)-(1-V$7)*LN(1-EXP(((V13+W13)/2)))-V$6>0,((V13+W13)/2),V13) -> -7.1258461 | W14: =IF(V$7*LN(V$7)-V$7*((V13+W13)/2)+(1-V$7)*LN(1-V$7)-(1-V$7)*LN(1-EXP(((V13+W13)/2)))-V$6>0,W13,((V13+W13)/2)) -> -5.0607892 | X14: =IF(X$7*LN(X$7)-X$7*((X13+Y13)/2)+(1-X$7)*LN(1-X$7)-(1-X$7)*LN(1-EXP(((X13+Y13)/2)))-X$6>0,((X13+Y13)/2),X13) -> -7.1258461 | Y14: =IF(X$7*LN(X$7)-X$7*((X13+Y13)/2)+(1-X$7)*LN(1-X$7)-(1-X$7)*LN(1-EXP(((X13+Y13)/2)))-X$6>0,Y13,((X13+Y13)/2)) -> -5.0607892 | Z14: =IF(Z$7*LN(Z$7)-Z$7*((Z13+AA13)/2)+(1-Z$7)*LN(1-Z$7)-(1-Z$7)*LN(1-EXP(((Z13+AA13)/2)))-Z$6>0,((Z13+AA13)/2),Z13) -> -7.1258461 | AA14: =IF(Z$7*LN(Z$7)-Z$7*((Z13+AA13)/2)+(1-Z$7)*LN(1-Z$7)-(1-Z$7)*LN(1-EXP(((Z13+AA13)/2)))-Z$6>0,AA13,((Z13+AA13)/2)) -> -5.0607892 | AB14: =IF((((AB13+AC13)/2))*LN((((AB13+AC13)/2))/(AB$7))+(1-(((AB13+AC13)/2)))*LN((1-(((AB13+AC13)/2)))/(1-(AB$7)))-AB$6<0,((AB13+AC13)/2),AB13) -> 0.05 | AC14: =IF((((AB13+AC13)/2))*LN((((AB13+AC13)/2))/(AB$7))+(1-(((AB13+AC13)/2)))*LN((1-(((AB13+AC13)/2)))/(1-(AB$7)))-AB$6<0,AC13,((AB13+AC13)/2)) -> 0.0796875 | AD14: =IF((((AD13+AE13)/2))*LN((((AD13+AE13)/2))/(AD$7))+(1-(((AD13+AE13)/2)))*LN((1-(((AD13+AE13)/2)))/(1-(AD$7)))-AD$6<0,((AD13+AE13)/2),AD13) -> 0.05 | AE14: =IF((((AD13+AE13)/2))*LN((((AD13+AE13)/2))/(AD$7))+(1-(((AD13+AE13)/2)))*LN((1-(((AD13+AE13)/2)))/(1-(AD$7)))-AD$6<0,AE13,((AD13+AE13)/2)) -> 0.0796875 | AF14: =IF((((AF13+AG13)/2))*LN((((AF13+AG13)/2))/(AF$7))+(1-(((AF13+AG13)/2)))*LN((1-(((AF13+AG13)/2)))/(1-(AF$7)))-AF$6<0,((AF13+AG13)/2),AF13) -> 0.0796875 | AG14: =IF((((AF13+AG13)/2))*LN((((AF13+AG13)/2))/(AF$7))+(1-(((AF13+AG13)/2)))*LN((1-(((AF13+AG13)/2)))/(1-(AF$7)))-AF$6<0,AG13,((AF13+AG13)/2)) -> 0.109375 | AH14: =IF((((AH13+AI13)/2))*LN((((AH13+AI13)/2))/(AH$7))+(1-(((AH13+AI13)/2)))*LN((1-(((AH13+AI13)/2)))/(1-(AH$7)))-AH$6<0,((AH13+AI13)/2),AH13) -> 0.109375 | AI14: =IF((((AH13+AI13)/2))*LN((((AH13+AI13)/2))/(AH$7))+(1-(((AH13+AI13)/2)))*LN((1-(((AH13+AI13)/2)))/(1-(AH$7)))-AH$6<0,AI13,((AH13+AI13)/2)) -> 0.1390625 | AJ14: =IF((((AJ13+AK13)/2))*LN((((AJ13+AK13)/2))/(AJ$7))+(1-(((AJ13+AK13)/2)))*LN((1-(((AJ13+AK13)/2)))/(1-(AJ$7)))-AJ$6<0,((AJ13+AK13)/2),AJ13) -> 0.16875 | AK14: =IF((((AJ13+AK13)/2))*LN((((AJ13+AK13)/2))/(AJ$7))+(1-(((AJ13+AK13)/2)))*LN((1-(((AJ13+AK13)/2)))/(1-(AJ$7)))-AJ$6<0,AK13,((AJ13+AK13)/2)) -> 0.1984375 | AL14: =IF((((AL13+AM13)/2))*LN((((AL13+AM13)/2))/(AL$7))+(1-(((AL13+AM13)/2)))*LN((1-(((AL13+AM13)/2)))/(1-(AL$7)))-AL$6<0,((AL13+AM13)/2),AL13) -> 0.2875 | AM14: =IF((((AL13+AM13)/2))*LN((((AL13+AM13)/2))/(AL$7))+(1-(((AL13+AM13)/2)))*LN((1-(((AL13+AM13)/2)))/(1-(AL$7)))-AL$6<0,AM13,((AL13+AM13)/2)) -> 0.3171875 | AN14: =IF((((AN13+AO13)/2))*LN((((AN13+AO13)/2))/(AN$7))+(1-(((AN13+AO13)/2)))*LN((1-(((AN13+AO13)/2)))/(1-(AN$7)))-AN$6<0,((AN13+AO13)/2),AN13) -> 0.5546875 | AO14: =IF((((AN13+AO13)/2))*LN((((AN13+AO13)/2))/(AN$7))+(1-(((AN13+AO13)/2)))*LN((1-(((AN13+AO13)/2)))/(1-(AN$7)))-AN$6<0,AO13,((AN13+AO13)/2)) -> 0.584375 | AP14: =IF(AP$7*LN(AP$7)-AP$7*((AP13+AQ13)/2)+(1-AP$7)*LN(1-AP$7)-(1-AP$7)*LN(1-EXP(((AP13+AQ13)/2)))-AP$6>0,((AP13+AQ13)/2),AP13) -> -5.0607892 | AQ14: =IF(AP$7*LN(AP$7)-AP$7*((AP13+AQ13)/2)+(1-AP$7)*LN(1-AP$7)-(1-AP$7)*LN(1-EXP(((AP13+AQ13)/2)))-AP$6>0,AQ13,((AP13+AQ13)/2)) -> -2.9957323 | AR14: =IF((((AR13+AS13)/2))*LN((((AR13+AS13)/2))/(AR$7))+(1-(((AR13+AS13)/2)))*LN((1-(((AR13+AS13)/2)))/(1-(AR$7)))-AR$6<0,((AR13+AS13)/2),AR13) -> 0.0796875 | AS14: =IF((((AR13+AS13)/2))*LN((((AR13+AS13)/2))/(AR$7))+(1-(((AR13+AS13)/2)))*LN((1-(((AR13+AS13)/2)))/(1-(AR$7)))-AR$6<0,AS13,((AR13+AS13)/2)) -> 0.109375
B15: =IF(B$7*LN(B$7)-B$7*((B14+C14)/2)+(1-B$7)*LN(1-B$7)-(1-B$7)*LN(1-EXP(((B14+C14)/2)))-B$6>0,((B14+C14)/2),B14) -> -13.321017 | C15: =IF(B$7*LN(B$7)-B$7*((B14+C14)/2)+(1-B$7)*LN(1-B$7)-(1-B$7)*LN(1-EXP(((B14+C14)/2)))-B$6>0,C14,((B14+C14)/2)) -> -12.288488 | D15: =IF(D$7*LN(D$7)-D$7*((D14+E14)/2)+(1-D$7)*LN(1-D$7)-(1-D$7)*LN(1-EXP(((D14+E14)/2)))-D$6>0,((D14+E14)/2),D14) -> -16.418602 | E15: =IF(D$7*LN(D$7)-D$7*((D14+E14)/2)+(1-D$7)*LN(1-D$7)-(1-D$7)*LN(1-EXP(((D14+E14)/2)))-D$6>0,E14,((D14+E14)/2)) -> -15.386074 | F15: =IF(F$7*LN(F$7)-F$7*((F14+G14)/2)+(1-F$7)*LN(1-F$7)-(1-F$7)*LN(1-EXP(((F14+G14)/2)))-F$6>0,((F14+G14)/2),F14) -> -25.711358 | G15: =IF(F$7*LN(F$7)-F$7*((F14+G14)/2)+(1-F$7)*LN(1-F$7)-(1-F$7)*LN(1-EXP(((F14+G14)/2)))-F$6>0,G14,((F14+G14)/2)) -> -24.67883 | H15: =IF(H$7*LN(H$7)-H$7*((H14+I14)/2)+(1-H$7)*LN(1-H$7)-(1-H$7)*LN(1-EXP(((H14+I14)/2)))-H$6>0,((H14+I14)/2),H14) -> -4.0282607 | I15: =IF(H$7*LN(H$7)-H$7*((H14+I14)/2)+(1-H$7)*LN(1-H$7)-(1-H$7)*LN(1-EXP(((H14+I14)/2)))-H$6>0,I14,((H14+I14)/2)) -> -2.9957323 | J15: =IF(J$7*LN(J$7)-J$7*((J14+K14)/2)+(1-J$7)*LN(1-J$7)-(1-J$7)*LN(1-EXP(((J14+K14)/2)))-J$6>0,((J14+K14)/2),J14) -> -4.0282607 | K15: =IF(J$7*LN(J$7)-J$7*((J14+K14)/2)+(1-J$7)*LN(1-J$7)-(1-J$7)*LN(1-EXP(((J14+K14)/2)))-J$6>0,K14,((J14+K14)/2)) -> -2.9957323 | L15: =IF(L$7*LN(L$7)-L$7*((L14+M14)/2)+(1-L$7)*LN(1-L$7)-(1-L$7)*LN(1-EXP(((L14+M14)/2)))-L$6>0,((L14+M14)/2),L14) -> -4.0282607 | M15: =IF(L$7*LN(L$7)-L$7*((L14+M14)/2)+(1-L$7)*LN(1-L$7)-(1-L$7)*LN(1-EXP(((L14+M14)/2)))-L$6>0,M14,((L14+M14)/2)) -> -2.9957323 | N15: =IF(N$7*LN(N$7)-N$7*((N14+O14)/2)+(1-N$7)*LN(1-N$7)-(1-N$7)*LN(1-EXP(((N14+O14)/2)))-N$6>0,((N14+O14)/2),N14) -> -4.0282607 | O15: =IF(N$7*LN(N$7)-N$7*((N14+O14)/2)+(1-N$7)*LN(1-N$7)-(1-N$7)*LN(1-EXP(((N14+O14)/2)))-N$6>0,O14,((N14+O14)/2)) -> -2.9957323 | P15: =IF(P$7*LN(P$7)-P$7*((P14+Q14)/2)+(1-P$7)*LN(1-P$7)-(1-P$7)*LN(1-EXP(((P14+Q14)/2)))-P$6>0,((P14+Q14)/2),P14) -> -5.0607892 | Q15: =IF(P$7*LN(P$7)-P$7*((P14+Q14)/2)+(1-P$7)*LN(1-P$7)-(1-P$7)*LN(1-EXP(((P14+Q14)/2)))-P$6>0,Q14,((P14+Q14)/2)) -> -4.0282607 | R15: =IF(R$7*LN(R$7)-R$7*((R14+S14)/2)+(1-R$7)*LN(1-R$7)-(1-R$7)*LN(1-EXP(((R14+S14)/2)))-R$6>0,((R14+S14)/2),R14) -> -5.0607892 | S15: =IF(R$7*LN(R$7)-R$7*((R14+S14)/2)+(1-R$7)*LN(1-R$7)-(1-R$7)*LN(1-EXP(((R14+S14)/2)))-R$6>0,S14,((R14+S14)/2)) -> -4.0282607 | T15: =IF(T$7*LN(T$7)-T$7*((T14+U14)/2)+(1-T$7)*LN(1-T$7)-(1-T$7)*LN(1-EXP(((T14+U14)/2)))-T$6>0,((T14+U14)/2),T14) -> -5.0607892 | U15: =IF(T$7*LN(T$7)-T$7*((T14+U14)/2)+(1-T$7)*LN(1-T$7)-(1-T$7)*LN(1-EXP(((T14+U14)/2)))-T$6>0,U14,((T14+U14)/2)) -> -4.0282607 | V15: =IF(V$7*LN(V$7)-V$7*((V14+W14)/2)+(1-V$7)*LN(1-V$7)-(1-V$7)*LN(1-EXP(((V14+W14)/2)))-V$6>0,((V14+W14)/2),V14) -> -6.0933176 | W15: =IF(V$7*LN(V$7)-V$7*((V14+W14)/2)+(1-V$7)*LN(1-V$7)-(1-V$7)*LN(1-EXP(((V14+W14)/2)))-V$6>0,W14,((V14+W14)/2)) -> -5.0607892 | X15: =IF(X$7*LN(X$7)-X$7*((X14+Y14)/2)+(1-X$7)*LN(1-X$7)-(1-X$7)*LN(1-EXP(((X14+Y14)/2)))-X$6>0,((X14+Y14)/2),X14) -> -6.0933176 | Y15: =IF(X$7*LN(X$7)-X$7*((X14+Y14)/2)+(1-X$7)*LN(1-X$7)-(1-X$7)*LN(1-EXP(((X14+Y14)/2)))-X$6>0,Y14,((X14+Y14)/2)) -> -5.0607892 | Z15: =IF(Z$7*LN(Z$7)-Z$7*((Z14+AA14)/2)+(1-Z$7)*LN(1-Z$7)-(1-Z$7)*LN(1-EXP(((Z14+AA14)/2)))-Z$6>0,((Z14+AA14)/2),Z14) -> -7.1258461 | AA15: =IF(Z$7*LN(Z$7)-Z$7*((Z14+AA14)/2)+(1-Z$7)*LN(1-Z$7)-(1-Z$7)*LN(1-EXP(((Z14+AA14)/2)))-Z$6>0,AA14,((Z14+AA14)/2)) -> -6.0933176 | AB15: =IF((((AB14+AC14)/2))*LN((((AB14+AC14)/2))/(AB$7))+(1-(((AB14+AC14)/2)))*LN((1-(((AB14+AC14)/2)))/(1-(AB$7)))-AB$6<0,((AB14+AC14)/2),AB14) -> 0.05 | AC15: =IF((((AB14+AC14)/2))*LN((((AB14+AC14)/2))/(AB$7))+(1-(((AB14+AC14)/2)))*LN((1-(((AB14+AC14)/2)))/(1-(AB$7)))-AB$6<0,AC14,((AB14+AC14)/2)) -> 0.06484375 | AD15: =IF((((AD14+AE14)/2))*LN((((AD14+AE14)/2))/(AD$7))+(1-(((AD14+AE14)/2)))*LN((1-(((AD14+AE14)/2)))/(1-(AD$7)))-AD$6<0,((AD14+AE14)/2),AD14) -> 0.06484375 | AE15: =IF((((AD14+AE14)/2))*LN((((AD14+AE14)/2))/(AD$7))+(1-(((AD14+AE14)/2)))*LN((1-(((AD14+AE14)/2)))/(1-(AD$7)))-AD$6<0,AE14,((AD14+AE14)/2)) -> 0.0796875 | AF15: =IF((((AF14+AG14)/2))*LN((((AF14+AG14)/2))/(AF$7))+(1-(((AF14+AG14)/2)))*LN((1-(((AF14+AG14)/2)))/(1-(AF$7)))-AF$6<0,((AF14+AG14)/2),AF14) -> 0.0796875 | AG15: =IF((((AF14+AG14)/2))*LN((((AF14+AG14)/2))/(AF$7))+(1-(((AF14+AG14)/2)))*LN((1-(((AF14+AG14)/2)))/(1-(AF$7)))-AF$6<0,AG14,((AF14+AG14)/2)) -> 0.09453125 | AH15: =IF((((AH14+AI14)/2))*LN((((AH14+AI14)/2))/(AH$7))+(1-(((AH14+AI14)/2)))*LN((1-(((AH14+AI14)/2)))/(1-(AH$7)))-AH$6<0,((AH14+AI14)/2),AH14) -> 0.109375 | AI15: =IF((((AH14+AI14)/2))*LN((((AH14+AI14)/2))/(AH$7))+(1-(((AH14+AI14)/2)))*LN((1-(((AH14+AI14)/2)))/(1-(AH$7)))-AH$6<0,AI14,((AH14+AI14)/2)) -> 0.12421875 | AJ15: =IF((((AJ14+AK14)/2))*LN((((AJ14+AK14)/2))/(AJ$7))+(1-(((AJ14+AK14)/2)))*LN((1-(((AJ14+AK14)/2)))/(1-(AJ$7)))-AJ$6<0,((AJ14+AK14)/2),AJ14) -> 0.16875 | AK15: =IF((((AJ14+AK14)/2))*LN((((AJ14+AK14)/2))/(AJ$7))+(1-(((AJ14+AK14)/2)))*LN((1-(((AJ14+AK14)/2)))/(1-(AJ$7)))-AJ$6<0,AK14,((AJ14+AK14)/2)) -> 0.18359375 | AL15: =IF((((AL14+AM14)/2))*LN((((AL14+AM14)/2))/(AL$7))+(1-(((AL14+AM14)/2)))*LN((1-(((AL14+AM14)/2)))/(1-(AL$7)))-AL$6<0,((AL14+AM14)/2),AL14) -> 0.2875 | AM15: =IF((((AL14+AM14)/2))*LN((((AL14+AM14)/2))/(AL$7))+(1-(((AL14+AM14)/2)))*LN((1-(((AL14+AM14)/2)))/(1-(AL$7)))-AL$6<0,AM14,((AL14+AM14)/2)) -> 0.30234375 | AN15: =IF((((AN14+AO14)/2))*LN((((AN14+AO14)/2))/(AN$7))+(1-(((AN14+AO14)/2)))*LN((1-(((AN14+AO14)/2)))/(1-(AN$7)))-AN$6<0,((AN14+AO14)/2),AN14) -> 0.5546875 | AO15: =IF((((AN14+AO14)/2))*LN((((AN14+AO14)/2))/(AN$7))+(1-(((AN14+AO14)/2)))*LN((1-(((AN14+AO14)/2)))/(1-(AN$7)))-AN$6<0,AO14,((AN14+AO14)/2)) -> 0.56953125 | AP15: =IF(AP$7*LN(AP$7)-AP$7*((AP14+AQ14)/2)+(1-AP$7)*LN(1-AP$7)-(1-AP$7)*LN(1-EXP(((AP14+AQ14)/2)))-AP$6>0,((AP14+AQ14)/2),AP14) -> -4.0282607 | AQ15: =IF(AP$7*LN(AP$7)-AP$7*((AP14+AQ14)/2)+(1-AP$7)*LN(1-AP$7)-(1-AP$7)*LN(1-EXP(((AP14+AQ14)/2)))-AP$6>0,AQ14,((AP14+AQ14)/2)) -> -2.9957323 | AR15: =IF((((AR14+AS14)/2))*LN((((AR14+AS14)/2))/(AR$7))+(1-(((AR14+AS14)/2)))*LN((1-(((AR14+AS14)/2)))/(1-(AR$7)))-AR$6<0,((AR14+AS14)/2),AR14) -> 0.0796875 | AS15: =IF((((AR14+AS14)/2))*LN((((AR14+AS14)/2))/(AR$7))+(1-(((AR14+AS14)/2)))*LN((1-(((AR14+AS14)/2)))/(1-(AR$7)))-AR$6<0,AS14,((AR14+AS14)/2)) -> 0.09453125
B16: =IF(B$7*LN(B$7)-B$7*((B15+C15)/2)+(1-B$7)*LN(1-B$7)-(1-B$7)*LN(1-EXP(((B15+C15)/2)))-B$6>0,((B15+C15)/2),B15) -> -12.804753 | C16: =IF(B$7*LN(B$7)-B$7*((B15+C15)/2)+(1-B$7)*LN(1-B$7)-(1-B$7)*LN(1-EXP(((B15+C15)/2)))-B$6>0,C15,((B15+C15)/2)) -> -12.288488 | D16: =IF(D$7*LN(D$7)-D$7*((D15+E15)/2)+(1-D$7)*LN(1-D$7)-(1-D$7)*LN(1-EXP(((D15+E15)/2)))-D$6>0,((D15+E15)/2),D15) -> -16.418602 | E16: =IF(D$7*LN(D$7)-D$7*((D15+E15)/2)+(1-D$7)*LN(1-D$7)-(1-D$7)*LN(1-EXP(((D15+E15)/2)))-D$6>0,E15,((D15+E15)/2)) -> -15.902338 | F16: =IF(F$7*LN(F$7)-F$7*((F15+G15)/2)+(1-F$7)*LN(1-F$7)-(1-F$7)*LN(1-EXP(((F15+G15)/2)))-F$6>0,((F15+G15)/2),F15) -> -25.195094 | G16: =IF(F$7*LN(F$7)-F$7*((F15+G15)/2)+(1-F$7)*LN(1-F$7)-(1-F$7)*LN(1-EXP(((F15+G15)/2)))-F$6>0,G15,((F15+G15)/2)) -> -24.67883 | H16: =IF(H$7*LN(H$7)-H$7*((H15+I15)/2)+(1-H$7)*LN(1-H$7)-(1-H$7)*LN(1-EXP(((H15+I15)/2)))-H$6>0,((H15+I15)/2),H15) -> -3.5119965 | I16: =IF(H$7*LN(H$7)-H$7*((H15+I15)/2)+(1-H$7)*LN(1-H$7)-(1-H$7)*LN(1-EXP(((H15+I15)/2)))-H$6>0,I15,((H15+I15)/2)) -> -2.9957323 | J16: =IF(J$7*LN(J$7)-J$7*((J15+K15)/2)+(1-J$7)*LN(1-J$7)-(1-J$7)*LN(1-EXP(((J15+K15)/2)))-J$6>0,((J15+K15)/2),J15) -> -3.5119965 | K16: =IF(J$7*LN(J$7)-J$7*((J15+K15)/2)+(1-J$7)*LN(1-J$7)-(1-J$7)*LN(1-EXP(((J15+K15)/2)))-J$6>0,K15,((J15+K15)/2)) -> -2.9957323 | L16: =IF(L$7*LN(L$7)-L$7*((L15+M15)/2)+(1-L$7)*LN(1-L$7)-(1-L$7)*LN(1-EXP(((L15+M15)/2)))-L$6>0,((L15+M15)/2),L15) -> -3.5119965 | M16: =IF(L$7*LN(L$7)-L$7*((L15+M15)/2)+(1-L$7)*LN(1-L$7)-(1-L$7)*LN(1-EXP(((L15+M15)/2)))-L$6>0,M15,((L15+M15)/2)) -> -2.9957323 | N16: =IF(N$7*LN(N$7)-N$7*((N15+O15)/2)+(1-N$7)*LN(1-N$7)-(1-N$7)*LN(1-EXP(((N15+O15)/2)))-N$6>0,((N15+O15)/2),N15) -> -4.0282607 | O16: =IF(N$7*LN(N$7)-N$7*((N15+O15)/2)+(1-N$7)*LN(1-N$7)-(1-N$7)*LN(1-EXP(((N15+O15)/2)))-N$6>0,O15,((N15+O15)/2)) -> -3.5119965 | P16: =IF(P$7*LN(P$7)-P$7*((P15+Q15)/2)+(1-P$7)*LN(1-P$7)-(1-P$7)*LN(1-EXP(((P15+Q15)/2)))-P$6>0,((P15+Q15)/2),P15) -> -4.5445249 | Q16: =IF(P$7*LN(P$7)-P$7*((P15+Q15)/2)+(1-P$7)*LN(1-P$7)-(1-P$7)*LN(1-EXP(((P15+Q15)/2)))-P$6>0,Q15,((P15+Q15)/2)) -> -4.0282607 | R16: =IF(R$7*LN(R$7)-R$7*((R15+S15)/2)+(1-R$7)*LN(1-R$7)-(1-R$7)*LN(1-EXP(((R15+S15)/2)))-R$6>0,((R15+S15)/2),R15) -> -4.5445249 | S16: =IF(R$7*LN(R$7)-R$7*((R15+S15)/2)+(1-R$7)*LN(1-R$7)-(1-R$7)*LN(1-EXP(((R15+S15)/2)))-R$6>0,S15,((R15+S15)/2)) -> -4.0282607 | T16: =IF(T$7*LN(T$7)-T$7*((T15+U15)/2)+(1-T$7)*LN(1-T$7)-(1-T$7)*LN(1-EXP(((T15+U15)/2)))-T$6>0,((T15+U15)/2),T15) -> -5.0607892 | U16: =IF(T$7*LN(T$7)-T$7*((T15+U15)/2)+(1-T$7)*LN(1-T$7)-(1-T$7)*LN(1-EXP(((T15+U15)/2)))-T$6>0,U15,((T15+U15)/2)) -> -4.5445249 | V16: =IF(V$7*LN(V$7)-V$7*((V15+W15)/2)+(1-V$7)*LN(1-V$7)-(1-V$7)*LN(1-EXP(((V15+W15)/2)))-V$6>0,((V15+W15)/2),V15) -> -5.5770534 | W16: =IF(V$7*LN(V$7)-V$7*((V15+W15)/2)+(1-V$7)*LN(1-V$7)-(1-V$7)*LN(1-EXP(((V15+W15)/2)))-V$6>0,W15,((V15+W15)/2)) -> -5.0607892 | X16: =IF(X$7*LN(X$7)-X$7*((X15+Y15)/2)+(1-X$7)*LN(1-X$7)-(1-X$7)*LN(1-EXP(((X15+Y15)/2)))-X$6>0,((X15+Y15)/2),X15) -> -6.0933176 | Y16: =IF(X$7*LN(X$7)-X$7*((X15+Y15)/2)+(1-X$7)*LN(1-X$7)-(1-X$7)*LN(1-EXP(((X15+Y15)/2)))-X$6>0,Y15,((X15+Y15)/2)) -> -5.5770534 | Z16: =IF(Z$7*LN(Z$7)-Z$7*((Z15+AA15)/2)+(1-Z$7)*LN(1-Z$7)-(1-Z$7)*LN(1-EXP(((Z15+AA15)/2)))-Z$6>0,((Z15+AA15)/2),Z15) -> -7.1258461 | AA16: =IF(Z$7*LN(Z$7)-Z$7*((Z15+AA15)/2)+(1-Z$7)*LN(1-Z$7)-(1-Z$7)*LN(1-EXP(((Z15+AA15)/2)))-Z$6>0,AA15,((Z15+AA15)/2)) -> -6.6095818 | AB16: =IF((((AB15+AC15)/2))*LN((((AB15+AC15)/2))/(AB$7))+(1-(((AB15+AC15)/2)))*LN((1-(((AB15+AC15)/2)))/(1-(AB$7)))-AB$6<0,((AB15+AC15)/2),AB15) -> 0.057421875 | AC16: =IF((((AB15+AC15)/2))*LN((((AB15+AC15)/2))/(AB$7))+(1-(((AB15+AC15)/2)))*LN((1-(((AB15+AC15)/2)))/(1-(AB$7)))-AB$6<0,AC15,((AB15+AC15)/2)) -> 0.06484375 | AD16: =IF((((AD15+AE15)/2))*LN((((AD15+AE15)/2))/(AD$7))+(1-(((AD15+AE15)/2)))*LN((1-(((AD15+AE15)/2)))/(1-(AD$7)))-AD$6<0,((AD15+AE15)/2),AD15) -> 0.06484375 | AE16: =IF((((AD15+AE15)/2))*LN((((AD15+AE15)/2))/(AD$7))+(1-(((AD15+AE15)/2)))*LN((1-(((AD15+AE15)/2)))/(1-(AD$7)))-AD$6<0,AE15,((AD15+AE15)/2)) -> 0.072265625 | AF16: =IF((((AF15+AG15)/2))*LN((((AF15+AG15)/2))/(AF$7))+(1-(((AF15+AG15)/2)))*LN((1-(((AF15+AG15)/2)))/(1-(AF$7)))-AF$6<0,((AF15+AG15)/2),AF15) -> 0.0796875 | AG16: =IF((((AF15+AG15)/2))*LN((((AF15+AG15)/2))/(AF$7))+(1-(((AF15+AG15)/2)))*LN((1-(((AF15+AG15)/2)))/(1-(AF$7)))-AF$6<0,AG15,((AF15+AG15)/2)) -> 0.087109375 | AH16: =IF((((AH15+AI15)/2))*LN((((AH15+AI15)/2))/(AH$7))+(1-(((AH15+AI15)/2)))*LN((1-(((AH15+AI15)/2)))/(1-(AH$7)))-AH$6<0,((AH15+AI15)/2),AH15) -> 0.109375 | AI16: =IF((((AH15+AI15)/2))*LN((((AH15+AI15)/2))/(AH$7))+(1-(((AH15+AI15)/2)))*LN((1-(((AH15+AI15)/2)))/(1-(AH$7)))-AH$6<0,AI15,((AH15+AI15)/2)) -> 0.11679687 | AJ16: =IF((((AJ15+AK15)/2))*LN((((AJ15+AK15)/2))/(AJ$7))+(1-(((AJ15+AK15)/2)))*LN((1-(((AJ15+AK15)/2)))/(1-(AJ$7)))-AJ$6<0,((AJ15+AK15)/2),AJ15) -> 0.16875 | AK16: =IF((((AJ15+AK15)/2))*LN((((AJ15+AK15)/2))/(AJ$7))+(1-(((AJ15+AK15)/2)))*LN((1-(((AJ15+AK15)/2)))/(1-(AJ$7)))-AJ$6<0,AK15,((AJ15+AK15)/2)) -> 0.17617188 | AL16: =IF((((AL15+AM15)/2))*LN((((AL15+AM15)/2))/(AL$7))+(1-(((AL15+AM15)/2)))*LN((1-(((AL15+AM15)/2)))/(1-(AL$7)))-AL$6<0,((AL15+AM15)/2),AL15) -> 0.2875 | AM16: =IF((((AL15+AM15)/2))*LN((((AL15+AM15)/2))/(AL$7))+(1-(((AL15+AM15)/2)))*LN((1-(((AL15+AM15)/2)))/(1-(AL$7)))-AL$6<0,AM15,((AL15+AM15)/2)) -> 0.29492188 | AN16: =IF((((AN15+AO15)/2))*LN((((AN15+AO15)/2))/(AN$7))+(1-(((AN15+AO15)/2)))*LN((1-(((AN15+AO15)/2)))/(1-(AN$7)))-AN$6<0,((AN15+AO15)/2),AN15) -> 0.5546875 | AO16: =IF((((AN15+AO15)/2))*LN((((AN15+AO15)/2))/(AN$7))+(1-(((AN15+AO15)/2)))*LN((1-(((AN15+AO15)/2)))/(1-(AN$7)))-AN$6<0,AO15,((AN15+AO15)/2)) -> 0.56210938 | AP16: =IF(AP$7*LN(AP$7)-AP$7*((AP15+AQ15)/2)+(1-AP$7)*LN(1-AP$7)-(1-AP$7)*LN(1-EXP(((AP15+AQ15)/2)))-AP$6>0,((AP15+AQ15)/2),AP15) -> -4.0282607 | AQ16: =IF(AP$7*LN(AP$7)-AP$7*((AP15+AQ15)/2)+(1-AP$7)*LN(1-AP$7)-(1-AP$7)*LN(1-EXP(((AP15+AQ15)/2)))-AP$6>0,AQ15,((AP15+AQ15)/2)) -> -3.5119965 | AR16: =IF((((AR15+AS15)/2))*LN((((AR15+AS15)/2))/(AR$7))+(1-(((AR15+AS15)/2)))*LN((1-(((AR15+AS15)/2)))/(1-(AR$7)))-AR$6<0,((AR15+AS15)/2),AR15) -> 0.0796875 | AS16: =IF((((AR15+AS15)/2))*LN((((AR15+AS15)/2))/(AR$7))+(1-(((AR15+AS15)/2)))*LN((1-(((AR15+AS15)/2)))/(1-(AR$7)))-AR$6<0,AS15,((AR15+AS15)/2)) -> 0.087109375
B17: =IF(B$7*LN(B$7)-B$7*((B16+C16)/2)+(1-B$7)*LN(1-B$7)-(1-B$7)*LN(1-EXP(((B16+C16)/2)))-B$6>0,((B16+C16)/2),B16) -> -12.804753 | C17: =IF(B$7*LN(B$7)-B$7*((B16+C16)/2)+(1-B$7)*LN(1-B$7)-(1-B$7)*LN(1-EXP(((B16+C16)/2)))-B$6>0,C16,((B16+C16)/2)) -> -12.54662 | D17: =IF(D$7*LN(D$7)-D$7*((D16+E16)/2)+(1-D$7)*LN(1-D$7)-(1-D$7)*LN(1-EXP(((D16+E16)/2)))-D$6>0,((D16+E16)/2),D16) -> -16.16047 | E17: =IF(D$7*LN(D$7)-D$7*((D16+E16)/2)+(1-D$7)*LN(1-D$7)-(1-D$7)*LN(1-EXP(((D16+E16)/2)))-D$6>0,E16,((D16+E16)/2)) -> -15.902338 | F17: =IF(F$7*LN(F$7)-F$7*((F16+G16)/2)+(1-F$7)*LN(1-F$7)-(1-F$7)*LN(1-EXP(((F16+G16)/2)))-F$6>0,((F16+G16)/2),F16) -> -24.936962 | G17: =IF(F$7*LN(F$7)-F$7*((F16+G16)/2)+(1-F$7)*LN(1-F$7)-(1-F$7)*LN(1-EXP(((F16+G16)/2)))-F$6>0,G16,((F16+G16)/2)) -> -24.67883 | H17: =IF(H$7*LN(H$7)-H$7*((H16+I16)/2)+(1-H$7)*LN(1-H$7)-(1-H$7)*LN(1-EXP(((H16+I16)/2)))-H$6>0,((H16+I16)/2),H16) -> -3.2538644 | I17: =IF(H$7*LN(H$7)-H$7*((H16+I16)/2)+(1-H$7)*LN(1-H$7)-(1-H$7)*LN(1-EXP(((H16+I16)/2)))-H$6>0,I16,((H16+I16)/2)) -> -2.9957323 | J17: =IF(J$7*LN(J$7)-J$7*((J16+K16)/2)+(1-J$7)*LN(1-J$7)-(1-J$7)*LN(1-EXP(((J16+K16)/2)))-J$6>0,((J16+K16)/2),J16) -> -3.5119965 | K17: =IF(J$7*LN(J$7)-J$7*((J16+K16)/2)+(1-J$7)*LN(1-J$7)-(1-J$7)*LN(1-EXP(((J16+K16)/2)))-J$6>0,K16,((J16+K16)/2)) -> -3.2538644 | L17: =IF(L$7*LN(L$7)-L$7*((L16+M16)/2)+(1-L$7)*LN(1-L$7)-(1-L$7)*LN(1-EXP(((L16+M16)/2)))-L$6>0,((L16+M16)/2),L16) -> -3.5119965 | M17: =IF(L$7*LN(L$7)-L$7*((L16+M16)/2)+(1-L$7)*LN(1-L$7)-(1-L$7)*LN(1-EXP(((L16+M16)/2)))-L$6>0,M16,((L16+M16)/2)) -> -3.2538644 | N17: =IF(N$7*LN(N$7)-N$7*((N16+O16)/2)+(1-N$7)*LN(1-N$7)-(1-N$7)*LN(1-EXP(((N16+O16)/2)))-N$6>0,((N16+O16)/2),N16) -> -3.7701286 | O17: =IF(N$7*LN(N$7)-N$7*((N16+O16)/2)+(1-N$7)*LN(1-N$7)-(1-N$7)*LN(1-EXP(((N16+O16)/2)))-N$6>0,O16,((N16+O16)/2)) -> -3.5119965 | P17: =IF(P$7*LN(P$7)-P$7*((P16+Q16)/2)+(1-P$7)*LN(1-P$7)-(1-P$7)*LN(1-EXP(((P16+Q16)/2)))-P$6>0,((P16+Q16)/2),P16) -> -4.2863928 | Q17: =IF(P$7*LN(P$7)-P$7*((P16+Q16)/2)+(1-P$7)*LN(1-P$7)-(1-P$7)*LN(1-EXP(((P16+Q16)/2)))-P$6>0,Q16,((P16+Q16)/2)) -> -4.0282607 | R17: =IF(R$7*LN(R$7)-R$7*((R16+S16)/2)+(1-R$7)*LN(1-R$7)-(1-R$7)*LN(1-EXP(((R16+S16)/2)))-R$6>0,((R16+S16)/2),R16) -> -4.5445249 | S17: =IF(R$7*LN(R$7)-R$7*((R16+S16)/2)+(1-R$7)*LN(1-R$7)-(1-R$7)*LN(1-EXP(((R16+S16)/2)))-R$6>0,S16,((R16+S16)/2)) -> -4.2863928 | T17: =IF(T$7*LN(T$7)-T$7*((T16+U16)/2)+(1-T$7)*LN(1-T$7)-(1-T$7)*LN(1-EXP(((T16+U16)/2)))-T$6>0,((T16+U16)/2),T16) -> -5.0607892 | U17: =IF(T$7*LN(T$7)-T$7*((T16+U16)/2)+(1-T$7)*LN(1-T$7)-(1-T$7)*LN(1-EXP(((T16+U16)/2)))-T$6>0,U16,((T16+U16)/2)) -> -4.8026571 | V17: =IF(V$7*LN(V$7)-V$7*((V16+W16)/2)+(1-V$7)*LN(1-V$7)-(1-V$7)*LN(1-EXP(((V16+W16)/2)))-V$6>0,((V16+W16)/2),V16) -> -5.5770534 | W17: =IF(V$7*LN(V$7)-V$7*((V16+W16)/2)+(1-V$7)*LN(1-V$7)-(1-V$7)*LN(1-EXP(((V16+W16)/2)))-V$6>0,W16,((V16+W16)/2)) -> -5.3189213 | X17: =IF(X$7*LN(X$7)-X$7*((X16+Y16)/2)+(1-X$7)*LN(1-X$7)-(1-X$7)*LN(1-EXP(((X16+Y16)/2)))-X$6>0,((X16+Y16)/2),X16) -> -6.0933176 | Y17: =IF(X$7*LN(X$7)-X$7*((X16+Y16)/2)+(1-X$7)*LN(1-X$7)-(1-X$7)*LN(1-EXP(((X16+Y16)/2)))-X$6>0,Y16,((X16+Y16)/2)) -> -5.8351855 | Z17: =IF(Z$7*LN(Z$7)-Z$7*((Z16+AA16)/2)+(1-Z$7)*LN(1-Z$7)-(1-Z$7)*LN(1-EXP(((Z16+AA16)/2)))-Z$6>0,((Z16+AA16)/2),Z16) -> -7.1258461 | AA17: =IF(Z$7*LN(Z$7)-Z$7*((Z16+AA16)/2)+(1-Z$7)*LN(1-Z$7)-(1-Z$7)*LN(1-EXP(((Z16+AA16)/2)))-Z$6>0,AA16,((Z16+AA16)/2)) -> -6.8677139 | AB17: =IF((((AB16+AC16)/2))*LN((((AB16+AC16)/2))/(AB$7))+(1-(((AB16+AC16)/2)))*LN((1-(((AB16+AC16)/2)))/(1-(AB$7)))-AB$6<0,((AB16+AC16)/2),AB16) -> 0.057421875 | AC17: =IF((((AB16+AC16)/2))*LN((((AB16+AC16)/2))/(AB$7))+(1-(((AB16+AC16)/2)))*LN((1-(((AB16+AC16)/2)))/(1-(AB$7)))-AB$6<0,AC16,((AB16+AC16)/2)) -> 0.061132813 | AD17: =IF((((AD16+AE16)/2))*LN((((AD16+AE16)/2))/(AD$7))+(1-(((AD16+AE16)/2)))*LN((1-(((AD16+AE16)/2)))/(1-(AD$7)))-AD$6<0,((AD16+AE16)/2),AD16) -> 0.06484375 | AE17: =IF((((AD16+AE16)/2))*LN((((AD16+AE16)/2))/(AD$7))+(1-(((AD16+AE16)/2)))*LN((1-(((AD16+AE16)/2)))/(1-(AD$7)))-AD$6<0,AE16,((AD16+AE16)/2)) -> 0.068554688 | AF17: =IF((((AF16+AG16)/2))*LN((((AF16+AG16)/2))/(AF$7))+(1-(((AF16+AG16)/2)))*LN((1-(((AF16+AG16)/2)))/(1-(AF$7)))-AF$6<0,((AF16+AG16)/2),AF16) -> 0.083398438 | AG17: =IF((((AF16+AG16)/2))*LN((((AF16+AG16)/2))/(AF$7))+(1-(((AF16+AG16)/2)))*LN((1-(((AF16+AG16)/2)))/(1-(AF$7)))-AF$6<0,AG16,((AF16+AG16)/2)) -> 0.087109375 | AH17: =IF((((AH16+AI16)/2))*LN((((AH16+AI16)/2))/(AH$7))+(1-(((AH16+AI16)/2)))*LN((1-(((AH16+AI16)/2)))/(1-(AH$7)))-AH$6<0,((AH16+AI16)/2),AH16) -> 0.109375 | AI17: =IF((((AH16+AI16)/2))*LN((((AH16+AI16)/2))/(AH$7))+(1-(((AH16+AI16)/2)))*LN((1-(((AH16+AI16)/2)))/(1-(AH$7)))-AH$6<0,AI16,((AH16+AI16)/2)) -> 0.11308594 | AJ17: =IF((((AJ16+AK16)/2))*LN((((AJ16+AK16)/2))/(AJ$7))+(1-(((AJ16+AK16)/2)))*LN((1-(((AJ16+AK16)/2)))/(1-(AJ$7)))-AJ$6<0,((AJ16+AK16)/2),AJ16) -> 0.17246094 | AK17: =IF((((AJ16+AK16)/2))*LN((((AJ16+AK16)/2))/(AJ$7))+(1-(((AJ16+AK16)/2)))*LN((1-(((AJ16+AK16)/2)))/(1-(AJ$7)))-AJ$6<0,AK16,((AJ16+AK16)/2)) -> 0.17617188 | AL17: =IF((((AL16+AM16)/2))*LN((((AL16+AM16)/2))/(AL$7))+(1-(((AL16+AM16)/2)))*LN((1-(((AL16+AM16)/2)))/(1-(AL$7)))-AL$6<0,((AL16+AM16)/2),AL16) -> 0.2875 | AM17: =IF((((AL16+AM16)/2))*LN((((AL16+AM16)/2))/(AL$7))+(1-(((AL16+AM16)/2)))*LN((1-(((AL16+AM16)/2)))/(1-(AL$7)))-AL$6<0,AM16,((AL16+AM16)/2)) -> 0.29121094 | AN17: =IF((((AN16+AO16)/2))*LN((((AN16+AO16)/2))/(AN$7))+(1-(((AN16+AO16)/2)))*LN((1-(((AN16+AO16)/2)))/(1-(AN$7)))-AN$6<0,((AN16+AO16)/2),AN16) -> 0.5546875 | AO17: =IF((((AN16+AO16)/2))*LN((((AN16+AO16)/2))/(AN$7))+(1-(((AN16+AO16)/2)))*LN((1-(((AN16+AO16)/2)))/(1-(AN$7)))-AN$6<0,AO16,((AN16+AO16)/2)) -> 0.55839844 | AP17: =IF(AP$7*LN(AP$7)-AP$7*((AP16+AQ16)/2)+(1-AP$7)*LN(1-AP$7)-(1-AP$7)*LN(1-EXP(((AP16+AQ16)/2)))-AP$6>0,((AP16+AQ16)/2),AP16) -> -3.7701286 | AQ17: =IF(AP$7*LN(AP$7)-AP$7*((AP16+AQ16)/2)+(1-AP$7)*LN(1-AP$7)-(1-AP$7)*LN(1-EXP(((AP16+AQ16)/2)))-AP$6>0,AQ16,((AP16+AQ16)/2)) -> -3.5119965 | AR17: =IF((((AR16+AS16)/2))*LN((((AR16+AS16)/2))/(AR$7))+(1-(((AR16+AS16)/2)))*LN((1-(((AR16+AS16)/2)))/(1-(AR$7)))-AR$6<0,((AR16+AS16)/2),AR16) -> 0.083398438 | AS17: =IF((((AR16+AS16)/2))*LN((((AR16+AS16)/2))/(AR$7))+(1-(((AR16+AS16)/2)))*LN((1-(((AR16+AS16)/2)))/(1-(AR$7)))-AR$6<0,AS16,((AR16+AS16)/2)) -> 0.087109375
B18: =IF(B$7*LN(B$7)-B$7*((B17+C17)/2)+(1-B$7)*LN(1-B$7)-(1-B$7)*LN(1-EXP(((B17+C17)/2)))-B$6>0,((B17+C17)/2),B17) -> -12.804753 | C18: =IF(B$7*LN(B$7)-B$7*((B17+C17)/2)+(1-B$7)*LN(1-B$7)-(1-B$7)*LN(1-EXP(((B17+C17)/2)))-B$6>0,C17,((B17+C17)/2)) -> -12.675686 | D18: =IF(D$7*LN(D$7)-D$7*((D17+E17)/2)+(1-D$7)*LN(1-D$7)-(1-D$7)*LN(1-EXP(((D17+E17)/2)))-D$6>0,((D17+E17)/2),D17) -> -16.16047 | E18: =IF(D$7*LN(D$7)-D$7*((D17+E17)/2)+(1-D$7)*LN(1-D$7)-(1-D$7)*LN(1-EXP(((D17+E17)/2)))-D$6>0,E17,((D17+E17)/2)) -> -16.031404 | F18: =IF(F$7*LN(F$7)-F$7*((F17+G17)/2)+(1-F$7)*LN(1-F$7)-(1-F$7)*LN(1-EXP(((F17+G17)/2)))-F$6>0,((F17+G17)/2),F17) -> -24.807896 | G18: =IF(F$7*LN(F$7)-F$7*((F17+G17)/2)+(1-F$7)*LN(1-F$7)-(1-F$7)*LN(1-EXP(((F17+G17)/2)))-F$6>0,G17,((F17+G17)/2)) -> -24.67883 | H18: =IF(H$7*LN(H$7)-H$7*((H17+I17)/2)+(1-H$7)*LN(1-H$7)-(1-H$7)*LN(1-EXP(((H17+I17)/2)))-H$6>0,((H17+I17)/2),H17) -> -3.2538644 | I18: =IF(H$7*LN(H$7)-H$7*((H17+I17)/2)+(1-H$7)*LN(1-H$7)-(1-H$7)*LN(1-EXP(((H17+I17)/2)))-H$6>0,I17,((H17+I17)/2)) -> -3.1247983 | J18: =IF(J$7*LN(J$7)-J$7*((J17+K17)/2)+(1-J$7)*LN(1-J$7)-(1-J$7)*LN(1-EXP(((J17+K17)/2)))-J$6>0,((J17+K17)/2),J17) -> -3.3829304 | K18: =IF(J$7*LN(J$7)-J$7*((J17+K17)/2)+(1-J$7)*LN(1-J$7)-(1-J$7)*LN(1-EXP(((J17+K17)/2)))-J$6>0,K17,((J17+K17)/2)) -> -3.2538644 | L18: =IF(L$7*LN(L$7)-L$7*((L17+M17)/2)+(1-L$7)*LN(1-L$7)-(1-L$7)*LN(1-EXP(((L17+M17)/2)))-L$6>0,((L17+M17)/2),L17) -> -3.5119965 | M18: =IF(L$7*LN(L$7)-L$7*((L17+M17)/2)+(1-L$7)*LN(1-L$7)-(1-L$7)*LN(1-EXP(((L17+M17)/2)))-L$6>0,M17,((L17+M17)/2)) -> -3.3829304 | N18: =IF(N$7*LN(N$7)-N$7*((N17+O17)/2)+(1-N$7)*LN(1-N$7)-(1-N$7)*LN(1-EXP(((N17+O17)/2)))-N$6>0,((N17+O17)/2),N17) -> -3.7701286 | O18: =IF(N$7*LN(N$7)-N$7*((N17+O17)/2)+(1-N$7)*LN(1-N$7)-(1-N$7)*LN(1-EXP(((N17+O17)/2)))-N$6>0,O17,((N17+O17)/2)) -> -3.6410626 | P18: =IF(P$7*LN(P$7)-P$7*((P17+Q17)/2)+(1-P$7)*LN(1-P$7)-(1-P$7)*LN(1-EXP(((P17+Q17)/2)))-P$6>0,((P17+Q17)/2),P17) -> -4.1573268 | Q18: =IF(P$7*LN(P$7)-P$7*((P17+Q17)/2)+(1-P$7)*LN(1-P$7)-(1-P$7)*LN(1-EXP(((P17+Q17)/2)))-P$6>0,Q17,((P17+Q17)/2)) -> -4.0282607 | R18: =IF(R$7*LN(R$7)-R$7*((R17+S17)/2)+(1-R$7)*LN(1-R$7)-(1-R$7)*LN(1-EXP(((R17+S17)/2)))-R$6>0,((R17+S17)/2),R17) -> -4.4154589 | S18: =IF(R$7*LN(R$7)-R$7*((R17+S17)/2)+(1-R$7)*LN(1-R$7)-(1-R$7)*LN(1-EXP(((R17+S17)/2)))-R$6>0,S17,((R17+S17)/2)) -> -4.2863928 | T18: =IF(T$7*LN(T$7)-T$7*((T17+U17)/2)+(1-T$7)*LN(1-T$7)-(1-T$7)*LN(1-EXP(((T17+U17)/2)))-T$6>0,((T17+U17)/2),T17) -> -4.9317231 | U18: =IF(T$7*LN(T$7)-T$7*((T17+U17)/2)+(1-T$7)*LN(1-T$7)-(1-T$7)*LN(1-EXP(((T17+U17)/2)))-T$6>0,U17,((T17+U17)/2)) -> -4.8026571 | V18: =IF(V$7*LN(V$7)-V$7*((V17+W17)/2)+(1-V$7)*LN(1-V$7)-(1-V$7)*LN(1-EXP(((V17+W17)/2)))-V$6>0,((V17+W17)/2),V17) -> -5.4479873 | W18: =IF(V$7*LN(V$7)-V$7*((V17+W17)/2)+(1-V$7)*LN(1-V$7)-(1-V$7)*LN(1-EXP(((V17+W17)/2)))-V$6>0,W17,((V17+W17)/2)) -> -5.3189213 | X18: =IF(X$7*LN(X$7)-X$7*((X17+Y17)/2)+(1-X$7)*LN(1-X$7)-(1-X$7)*LN(1-EXP(((X17+Y17)/2)))-X$6>0,((X17+Y17)/2),X17) -> -5.9642516 | Y18: =IF(X$7*LN(X$7)-X$7*((X17+Y17)/2)+(1-X$7)*LN(1-X$7)-(1-X$7)*LN(1-EXP(((X17+Y17)/2)))-X$6>0,Y17,((X17+Y17)/2)) -> -5.8351855 | Z18: =IF(Z$7*LN(Z$7)-Z$7*((Z17+AA17)/2)+(1-Z$7)*LN(1-Z$7)-(1-Z$7)*LN(1-EXP(((Z17+AA17)/2)))-Z$6>0,((Z17+AA17)/2),Z17) -> -6.99678 | AA18: =IF(Z$7*LN(Z$7)-Z$7*((Z17+AA17)/2)+(1-Z$7)*LN(1-Z$7)-(1-Z$7)*LN(1-EXP(((Z17+AA17)/2)))-Z$6>0,AA17,((Z17+AA17)/2)) -> -6.8677139 | AB18: =IF((((AB17+AC17)/2))*LN((((AB17+AC17)/2))/(AB$7))+(1-(((AB17+AC17)/2)))*LN((1-(((AB17+AC17)/2)))/(1-(AB$7)))-AB$6<0,((AB17+AC17)/2),AB17) -> 0.059277344 | AC18: =IF((((AB17+AC17)/2))*LN((((AB17+AC17)/2))/(AB$7))+(1-(((AB17+AC17)/2)))*LN((1-(((AB17+AC17)/2)))/(1-(AB$7)))-AB$6<0,AC17,((AB17+AC17)/2)) -> 0.061132813 | AD18: =IF((((AD17+AE17)/2))*LN((((AD17+AE17)/2))/(AD$7))+(1-(((AD17+AE17)/2)))*LN((1-(((AD17+AE17)/2)))/(1-(AD$7)))-AD$6<0,((AD17+AE17)/2),AD17) -> 0.066699219 | AE18: =IF((((AD17+AE17)/2))*LN((((AD17+AE17)/2))/(AD$7))+(1-(((AD17+AE17)/2)))*LN((1-(((AD17+AE17)/2)))/(1-(AD$7)))-AD$6<0,AE17,((AD17+AE17)/2)) -> 0.068554688 | AF18: =IF((((AF17+AG17)/2))*LN((((AF17+AG17)/2))/(AF$7))+(1-(((AF17+AG17)/2)))*LN((1-(((AF17+AG17)/2)))/(1-(AF$7)))-AF$6<0,((AF17+AG17)/2),AF17) -> 0.083398438 | AG18: =IF((((AF17+AG17)/2))*LN((((AF17+AG17)/2))/(AF$7))+(1-(((AF17+AG17)/2)))*LN((1-(((AF17+AG17)/2)))/(1-(AF$7)))-AF$6<0,AG17,((AF17+AG17)/2)) -> 0.085253906 | AH18: =IF((((AH17+AI17)/2))*LN((((AH17+AI17)/2))/(AH$7))+(1-(((AH17+AI17)/2)))*LN((1-(((AH17+AI17)/2)))/(1-(AH$7)))-AH$6<0,((AH17+AI17)/2),AH17) -> 0.11123047 | AI18: =IF((((AH17+AI17)/2))*LN((((AH17+AI17)/2))/(AH$7))+(1-(((AH17+AI17)/2)))*LN((1-(((AH17+AI17)/2)))/(1-(AH$7)))-AH$6<0,AI17,((AH17+AI17)/2)) -> 0.11308594 | AJ18: =IF((((AJ17+AK17)/2))*LN((((AJ17+AK17)/2))/(AJ$7))+(1-(((AJ17+AK17)/2)))*LN((1-(((AJ17+AK17)/2)))/(1-(AJ$7)))-AJ$6<0,((AJ17+AK17)/2),AJ17) -> 0.17246094 | AK18: =IF((((AJ17+AK17)/2))*LN((((AJ17+AK17)/2))/(AJ$7))+(1-(((AJ17+AK17)/2)))*LN((1-(((AJ17+AK17)/2)))/(1-(AJ$7)))-AJ$6<0,AK17,((AJ17+AK17)/2)) -> 0.17431641 | AL18: =IF((((AL17+AM17)/2))*LN((((AL17+AM17)/2))/(AL$7))+(1-(((AL17+AM17)/2)))*LN((1-(((AL17+AM17)/2)))/(1-(AL$7)))-AL$6<0,((AL17+AM17)/2),AL17) -> 0.2875 | AM18: =IF((((AL17+AM17)/2))*LN((((AL17+AM17)/2))/(AL$7))+(1-(((AL17+AM17)/2)))*LN((1-(((AL17+AM17)/2)))/(1-(AL$7)))-AL$6<0,AM17,((AL17+AM17)/2)) -> 0.28935547 | AN18: =IF((((AN17+AO17)/2))*LN((((AN17+AO17)/2))/(AN$7))+(1-(((AN17+AO17)/2)))*LN((1-(((AN17+AO17)/2)))/(1-(AN$7)))-AN$6<0,((AN17+AO17)/2),AN17) -> 0.5546875 | AO18: =IF((((AN17+AO17)/2))*LN((((AN17+AO17)/2))/(AN$7))+(1-(((AN17+AO17)/2)))*LN((1-(((AN17+AO17)/2)))/(1-(AN$7)))-AN$6<0,AO17,((AN17+AO17)/2)) -> 0.55654297 | AP18: =IF(AP$7*LN(AP$7)-AP$7*((AP17+AQ17)/2)+(1-AP$7)*LN(1-AP$7)-(1-AP$7)*LN(1-EXP(((AP17+AQ17)/2)))-AP$6>0,((AP17+AQ17)/2),AP17) -> -3.7701286 | AQ18: =IF(AP$7*LN(AP$7)-AP$7*((AP17+AQ17)/2)+(1-AP$7)*LN(1-AP$7)-(1-AP$7)*LN(1-EXP(((AP17+AQ17)/2)))-AP$6>0,AQ17,((AP17+AQ17)/2)) -> -3.6410626 | AR18: =IF((((AR17+AS17)/2))*LN((((AR17+AS17)/2))/(AR$7))+(1-(((AR17+AS17)/2)))*LN((1-(((AR17+AS17)/2)))/(1-(AR$7)))-AR$6<0,((AR17+AS17)/2),AR17) -> 0.083398438 | AS18: =IF((((AR17+AS17)/2))*LN((((AR17+AS17)/2))/(AR$7))+(1-(((AR17+AS17)/2)))*LN((1-(((AR17+AS17)/2)))/(1-(AR$7)))-AR$6<0,AS17,((AR17+AS17)/2)) -> 0.085253906
B19: =IF(B$7*LN(B$7)-B$7*((B18+C18)/2)+(1-B$7)*LN(1-B$7)-(1-B$7)*LN(1-EXP(((B18+C18)/2)))-B$6>0,((B18+C18)/2),B18) -> -12.804753 | C19: =IF(B$7*LN(B$7)-B$7*((B18+C18)/2)+(1-B$7)*LN(1-B$7)-(1-B$7)*LN(1-EXP(((B18+C18)/2)))-B$6>0,C18,((B18+C18)/2)) -> -12.740219 | D19: =IF(D$7*LN(D$7)-D$7*((D18+E18)/2)+(1-D$7)*LN(1-D$7)-(1-D$7)*LN(1-EXP(((D18+E18)/2)))-D$6>0,((D18+E18)/2),D18) -> -16.095937 | E19: =IF(D$7*LN(D$7)-D$7*((D18+E18)/2)+(1-D$7)*LN(1-D$7)-(1-D$7)*LN(1-EXP(((D18+E18)/2)))-D$6>0,E18,((D18+E18)/2)) -> -16.031404 | F19: =IF(F$7*LN(F$7)-F$7*((F18+G18)/2)+(1-F$7)*LN(1-F$7)-(1-F$7)*LN(1-EXP(((F18+G18)/2)))-F$6>0,((F18+G18)/2),F18) -> -24.807896 | G19: =IF(F$7*LN(F$7)-F$7*((F18+G18)/2)+(1-F$7)*LN(1-F$7)-(1-F$7)*LN(1-EXP(((F18+G18)/2)))-F$6>0,G18,((F18+G18)/2)) -> -24.743363 | H19: =IF(H$7*LN(H$7)-H$7*((H18+I18)/2)+(1-H$7)*LN(1-H$7)-(1-H$7)*LN(1-EXP(((H18+I18)/2)))-H$6>0,((H18+I18)/2),H18) -> -3.2538644 | I19: =IF(H$7*LN(H$7)-H$7*((H18+I18)/2)+(1-H$7)*LN(1-H$7)-(1-H$7)*LN(1-EXP(((H18+I18)/2)))-H$6>0,I18,((H18+I18)/2)) -> -3.1893314 | J19: =IF(J$7*LN(J$7)-J$7*((J18+K18)/2)+(1-J$7)*LN(1-J$7)-(1-J$7)*LN(1-EXP(((J18+K18)/2)))-J$6>0,((J18+K18)/2),J18) -> -3.3183974 | K19: =IF(J$7*LN(J$7)-J$7*((J18+K18)/2)+(1-J$7)*LN(1-J$7)-(1-J$7)*LN(1-EXP(((J18+K18)/2)))-J$6>0,K18,((J18+K18)/2)) -> -3.2538644 | L19: =IF(L$7*LN(L$7)-L$7*((L18+M18)/2)+(1-L$7)*LN(1-L$7)-(1-L$7)*LN(1-EXP(((L18+M18)/2)))-L$6>0,((L18+M18)/2),L18) -> -3.5119965 | M19: =IF(L$7*LN(L$7)-L$7*((L18+M18)/2)+(1-L$7)*LN(1-L$7)-(1-L$7)*LN(1-EXP(((L18+M18)/2)))-L$6>0,M18,((L18+M18)/2)) -> -3.4474635 | N19: =IF(N$7*LN(N$7)-N$7*((N18+O18)/2)+(1-N$7)*LN(1-N$7)-(1-N$7)*LN(1-EXP(((N18+O18)/2)))-N$6>0,((N18+O18)/2),N18) -> -3.7055956 | O19: =IF(N$7*LN(N$7)-N$7*((N18+O18)/2)+(1-N$7)*LN(1-N$7)-(1-N$7)*LN(1-EXP(((N18+O18)/2)))-N$6>0,O18,((N18+O18)/2)) -> -3.6410626 | P19: =IF(P$7*LN(P$7)-P$7*((P18+Q18)/2)+(1-P$7)*LN(1-P$7)-(1-P$7)*LN(1-EXP(((P18+Q18)/2)))-P$6>0,((P18+Q18)/2),P18) -> -4.0927937 | Q19: =IF(P$7*LN(P$7)-P$7*((P18+Q18)/2)+(1-P$7)*LN(1-P$7)-(1-P$7)*LN(1-EXP(((P18+Q18)/2)))-P$6>0,Q18,((P18+Q18)/2)) -> -4.0282607 | R19: =IF(R$7*LN(R$7)-R$7*((R18+S18)/2)+(1-R$7)*LN(1-R$7)-(1-R$7)*LN(1-EXP(((R18+S18)/2)))-R$6>0,((R18+S18)/2),R18) -> -4.3509259 | S19: =IF(R$7*LN(R$7)-R$7*((R18+S18)/2)+(1-R$7)*LN(1-R$7)-(1-R$7)*LN(1-EXP(((R18+S18)/2)))-R$6>0,S18,((R18+S18)/2)) -> -4.2863928 | T19: =IF(T$7*LN(T$7)-T$7*((T18+U18)/2)+(1-T$7)*LN(1-T$7)-(1-T$7)*LN(1-EXP(((T18+U18)/2)))-T$6>0,((T18+U18)/2),T18) -> -4.8671901 | U19: =IF(T$7*LN(T$7)-T$7*((T18+U18)/2)+(1-T$7)*LN(1-T$7)-(1-T$7)*LN(1-EXP(((T18+U18)/2)))-T$6>0,U18,((T18+U18)/2)) -> -4.8026571 | V19: =IF(V$7*LN(V$7)-V$7*((V18+W18)/2)+(1-V$7)*LN(1-V$7)-(1-V$7)*LN(1-EXP(((V18+W18)/2)))-V$6>0,((V18+W18)/2),V18) -> -5.3834543 | W19: =IF(V$7*LN(V$7)-V$7*((V18+W18)/2)+(1-V$7)*LN(1-V$7)-(1-V$7)*LN(1-EXP(((V18+W18)/2)))-V$6>0,W18,((V18+W18)/2)) -> -5.3189213 | X19: =IF(X$7*LN(X$7)-X$7*((X18+Y18)/2)+(1-X$7)*LN(1-X$7)-(1-X$7)*LN(1-EXP(((X18+Y18)/2)))-X$6>0,((X18+Y18)/2),X18) -> -5.9642516 | Y19: =IF(X$7*LN(X$7)-X$7*((X18+Y18)/2)+(1-X$7)*LN(1-X$7)-(1-X$7)*LN(1-EXP(((X18+Y18)/2)))-X$6>0,Y18,((X18+Y18)/2)) -> -5.8997185 | Z19: =IF(Z$7*LN(Z$7)-Z$7*((Z18+AA18)/2)+(1-Z$7)*LN(1-Z$7)-(1-Z$7)*LN(1-EXP(((Z18+AA18)/2)))-Z$6>0,((Z18+AA18)/2),Z18) -> -6.99678 | AA19: =IF(Z$7*LN(Z$7)-Z$7*((Z18+AA18)/2)+(1-Z$7)*LN(1-Z$7)-(1-Z$7)*LN(1-EXP(((Z18+AA18)/2)))-Z$6>0,AA18,((Z18+AA18)/2)) -> -6.932247 | AB19: =IF((((AB18+AC18)/2))*LN((((AB18+AC18)/2))/(AB$7))+(1-(((AB18+AC18)/2)))*LN((1-(((AB18+AC18)/2)))/(1-(AB$7)))-AB$6<0,((AB18+AC18)/2),AB18) -> 0.059277344 | AC19: =IF((((AB18+AC18)/2))*LN((((AB18+AC18)/2))/(AB$7))+(1-(((AB18+AC18)/2)))*LN((1-(((AB18+AC18)/2)))/(1-(AB$7)))-AB$6<0,AC18,((AB18+AC18)/2)) -> 0.060205078 | AD19: =IF((((AD18+AE18)/2))*LN((((AD18+AE18)/2))/(AD$7))+(1-(((AD18+AE18)/2)))*LN((1-(((AD18+AE18)/2)))/(1-(AD$7)))-AD$6<0,((AD18+AE18)/2),AD18) -> 0.067626953 | AE19: =IF((((AD18+AE18)/2))*LN((((AD18+AE18)/2))/(AD$7))+(1-(((AD18+AE18)/2)))*LN((1-(((AD18+AE18)/2)))/(1-(AD$7)))-AD$6<0,AE18,((AD18+AE18)/2)) -> 0.068554688 | AF19: =IF((((AF18+AG18)/2))*LN((((AF18+AG18)/2))/(AF$7))+(1-(((AF18+AG18)/2)))*LN((1-(((AF18+AG18)/2)))/(1-(AF$7)))-AF$6<0,((AF18+AG18)/2),AF18) -> 0.083398438 | AG19: =IF((((AF18+AG18)/2))*LN((((AF18+AG18)/2))/(AF$7))+(1-(((AF18+AG18)/2)))*LN((1-(((AF18+AG18)/2)))/(1-(AF$7)))-AF$6<0,AG18,((AF18+AG18)/2)) -> 0.084326172 | AH19: =IF((((AH18+AI18)/2))*LN((((AH18+AI18)/2))/(AH$7))+(1-(((AH18+AI18)/2)))*LN((1-(((AH18+AI18)/2)))/(1-(AH$7)))-AH$6<0,((AH18+AI18)/2),AH18) -> 0.11123047 | AI19: =IF((((AH18+AI18)/2))*LN((((AH18+AI18)/2))/(AH$7))+(1-(((AH18+AI18)/2)))*LN((1-(((AH18+AI18)/2)))/(1-(AH$7)))-AH$6<0,AI18,((AH18+AI18)/2)) -> 0.1121582 | AJ19: =IF((((AJ18+AK18)/2))*LN((((AJ18+AK18)/2))/(AJ$7))+(1-(((AJ18+AK18)/2)))*LN((1-(((AJ18+AK18)/2)))/(1-(AJ$7)))-AJ$6<0,((AJ18+AK18)/2),AJ18) -> 0.17246094 | AK19: =IF((((AJ18+AK18)/2))*LN((((AJ18+AK18)/2))/(AJ$7))+(1-(((AJ18+AK18)/2)))*LN((1-(((AJ18+AK18)/2)))/(1-(AJ$7)))-AJ$6<0,AK18,((AJ18+AK18)/2)) -> 0.17338867 | AL19: =IF((((AL18+AM18)/2))*LN((((AL18+AM18)/2))/(AL$7))+(1-(((AL18+AM18)/2)))*LN((1-(((AL18+AM18)/2)))/(1-(AL$7)))-AL$6<0,((AL18+AM18)/2),AL18) -> 0.28842773 | AM19: =IF((((AL18+AM18)/2))*LN((((AL18+AM18)/2))/(AL$7))+(1-(((AL18+AM18)/2)))*LN((1-(((AL18+AM18)/2)))/(1-(AL$7)))-AL$6<0,AM18,((AL18+AM18)/2)) -> 0.28935547 | AN19: =IF((((AN18+AO18)/2))*LN((((AN18+AO18)/2))/(AN$7))+(1-(((AN18+AO18)/2)))*LN((1-(((AN18+AO18)/2)))/(1-(AN$7)))-AN$6<0,((AN18+AO18)/2),AN18) -> 0.5546875 | AO19: =IF((((AN18+AO18)/2))*LN((((AN18+AO18)/2))/(AN$7))+(1-(((AN18+AO18)/2)))*LN((1-(((AN18+AO18)/2)))/(1-(AN$7)))-AN$6<0,AO18,((AN18+AO18)/2)) -> 0.55561523 | AP19: =IF(AP$7*LN(AP$7)-AP$7*((AP18+AQ18)/2)+(1-AP$7)*LN(1-AP$7)-(1-AP$7)*LN(1-EXP(((AP18+AQ18)/2)))-AP$6>0,((AP18+AQ18)/2),AP18) -> -3.7055956 | AQ19: =IF(AP$7*LN(AP$7)-AP$7*((AP18+AQ18)/2)+(1-AP$7)*LN(1-AP$7)-(1-AP$7)*LN(1-EXP(((AP18+AQ18)/2)))-AP$6>0,AQ18,((AP18+AQ18)/2)) -> -3.6410626 | AR19: =IF((((AR18+AS18)/2))*LN((((AR18+AS18)/2))/(AR$7))+(1-(((AR18+AS18)/2)))*LN((1-(((AR18+AS18)/2)))/(1-(AR$7)))-AR$6<0,((AR18+AS18)/2),AR18) -> 0.083398438 | AS19: =IF((((AR18+AS18)/2))*LN((((AR18+AS18)/2))/(AR$7))+(1-(((AR18+AS18)/2)))*LN((1-(((AR18+AS18)/2)))/(1-(AR$7)))-AR$6<0,AS18,((AR18+AS18)/2)) -> 0.084326172
B20: =IF(B$7*LN(B$7)-B$7*((B19+C19)/2)+(1-B$7)*LN(1-B$7)-(1-B$7)*LN(1-EXP(((B19+C19)/2)))-B$6>0,((B19+C19)/2),B19) -> -12.772486 | C20: =IF(B$7*LN(B$7)-B$7*((B19+C19)/2)+(1-B$7)*LN(1-B$7)-(1-B$7)*LN(1-EXP(((B19+C19)/2)))-B$6>0,C19,((B19+C19)/2)) -> -12.740219 | D20: =IF(D$7*LN(D$7)-D$7*((D19+E19)/2)+(1-D$7)*LN(1-D$7)-(1-D$7)*LN(1-EXP(((D19+E19)/2)))-D$6>0,((D19+E19)/2),D19) -> -16.06367 | E20: =IF(D$7*LN(D$7)-D$7*((D19+E19)/2)+(1-D$7)*LN(1-D$7)-(1-D$7)*LN(1-EXP(((D19+E19)/2)))-D$6>0,E19,((D19+E19)/2)) -> -16.031404 | F20: =IF(F$7*LN(F$7)-F$7*((F19+G19)/2)+(1-F$7)*LN(1-F$7)-(1-F$7)*LN(1-EXP(((F19+G19)/2)))-F$6>0,((F19+G19)/2),F19) -> -24.807896 | G20: =IF(F$7*LN(F$7)-F$7*((F19+G19)/2)+(1-F$7)*LN(1-F$7)-(1-F$7)*LN(1-EXP(((F19+G19)/2)))-F$6>0,G19,((F19+G19)/2)) -> -24.775629 | H20: =IF(H$7*LN(H$7)-H$7*((H19+I19)/2)+(1-H$7)*LN(1-H$7)-(1-H$7)*LN(1-EXP(((H19+I19)/2)))-H$6>0,((H19+I19)/2),H19) -> -3.2215979 | I20: =IF(H$7*LN(H$7)-H$7*((H19+I19)/2)+(1-H$7)*LN(1-H$7)-(1-H$7)*LN(1-EXP(((H19+I19)/2)))-H$6>0,I19,((H19+I19)/2)) -> -3.1893314 | J20: =IF(J$7*LN(J$7)-J$7*((J19+K19)/2)+(1-J$7)*LN(1-J$7)-(1-J$7)*LN(1-EXP(((J19+K19)/2)))-J$6>0,((J19+K19)/2),J19) -> -3.2861309 | K20: =IF(J$7*LN(J$7)-J$7*((J19+K19)/2)+(1-J$7)*LN(1-J$7)-(1-J$7)*LN(1-EXP(((J19+K19)/2)))-J$6>0,K19,((J19+K19)/2)) -> -3.2538644 | L20: =IF(L$7*LN(L$7)-L$7*((L19+M19)/2)+(1-L$7)*LN(1-L$7)-(1-L$7)*LN(1-EXP(((L19+M19)/2)))-L$6>0,((L19+M19)/2),L19) -> -3.47973 | M20: =IF(L$7*LN(L$7)-L$7*((L19+M19)/2)+(1-L$7)*LN(1-L$7)-(1-L$7)*LN(1-EXP(((L19+M19)/2)))-L$6>0,M19,((L19+M19)/2)) -> -3.4474635 | N20: =IF(N$7*LN(N$7)-N$7*((N19+O19)/2)+(1-N$7)*LN(1-N$7)-(1-N$7)*LN(1-EXP(((N19+O19)/2)))-N$6>0,((N19+O19)/2),N19) -> -3.7055956 | O20: =IF(N$7*LN(N$7)-N$7*((N19+O19)/2)+(1-N$7)*LN(1-N$7)-(1-N$7)*LN(1-EXP(((N19+O19)/2)))-N$6>0,O19,((N19+O19)/2)) -> -3.6733291 | P20: =IF(P$7*LN(P$7)-P$7*((P19+Q19)/2)+(1-P$7)*LN(1-P$7)-(1-P$7)*LN(1-EXP(((P19+Q19)/2)))-P$6>0,((P19+Q19)/2),P19) -> -4.0605272 | Q20: =IF(P$7*LN(P$7)-P$7*((P19+Q19)/2)+(1-P$7)*LN(1-P$7)-(1-P$7)*LN(1-EXP(((P19+Q19)/2)))-P$6>0,Q19,((P19+Q19)/2)) -> -4.0282607 | R20: =IF(R$7*LN(R$7)-R$7*((R19+S19)/2)+(1-R$7)*LN(1-R$7)-(1-R$7)*LN(1-EXP(((R19+S19)/2)))-R$6>0,((R19+S19)/2),R19) -> -4.3186593 | S20: =IF(R$7*LN(R$7)-R$7*((R19+S19)/2)+(1-R$7)*LN(1-R$7)-(1-R$7)*LN(1-EXP(((R19+S19)/2)))-R$6>0,S19,((R19+S19)/2)) -> -4.2863928 | T20: =IF(T$7*LN(T$7)-T$7*((T19+U19)/2)+(1-T$7)*LN(1-T$7)-(1-T$7)*LN(1-EXP(((T19+U19)/2)))-T$6>0,((T19+U19)/2),T19) -> -4.8349236 | U20: =IF(T$7*LN(T$7)-T$7*((T19+U19)/2)+(1-T$7)*LN(1-T$7)-(1-T$7)*LN(1-EXP(((T19+U19)/2)))-T$6>0,U19,((T19+U19)/2)) -> -4.8026571 | V20: =IF(V$7*LN(V$7)-V$7*((V19+W19)/2)+(1-V$7)*LN(1-V$7)-(1-V$7)*LN(1-EXP(((V19+W19)/2)))-V$6>0,((V19+W19)/2),V19) -> -5.3834543 | W20: =IF(V$7*LN(V$7)-V$7*((V19+W19)/2)+(1-V$7)*LN(1-V$7)-(1-V$7)*LN(1-EXP(((V19+W19)/2)))-V$6>0,W19,((V19+W19)/2)) -> -5.3511878 | X20: =IF(X$7*LN(X$7)-X$7*((X19+Y19)/2)+(1-X$7)*LN(1-X$7)-(1-X$7)*LN(1-EXP(((X19+Y19)/2)))-X$6>0,((X19+Y19)/2),X19) -> -5.931985 | Y20: =IF(X$7*LN(X$7)-X$7*((X19+Y19)/2)+(1-X$7)*LN(1-X$7)-(1-X$7)*LN(1-EXP(((X19+Y19)/2)))-X$6>0,Y19,((X19+Y19)/2)) -> -5.8997185 | Z20: =IF(Z$7*LN(Z$7)-Z$7*((Z19+AA19)/2)+(1-Z$7)*LN(1-Z$7)-(1-Z$7)*LN(1-EXP(((Z19+AA19)/2)))-Z$6>0,((Z19+AA19)/2),Z19) -> -6.9645135 | AA20: =IF(Z$7*LN(Z$7)-Z$7*((Z19+AA19)/2)+(1-Z$7)*LN(1-Z$7)-(1-Z$7)*LN(1-EXP(((Z19+AA19)/2)))-Z$6>0,AA19,((Z19+AA19)/2)) -> -6.932247 | AB20: =IF((((AB19+AC19)/2))*LN((((AB19+AC19)/2))/(AB$7))+(1-(((AB19+AC19)/2)))*LN((1-(((AB19+AC19)/2)))/(1-(AB$7)))-AB$6<0,((AB19+AC19)/2),AB19) -> 0.059741211 | AC20: =IF((((AB19+AC19)/2))*LN((((AB19+AC19)/2))/(AB$7))+(1-(((AB19+AC19)/2)))*LN((1-(((AB19+AC19)/2)))/(1-(AB$7)))-AB$6<0,AC19,((AB19+AC19)/2)) -> 0.060205078 | AD20: =IF((((AD19+AE19)/2))*LN((((AD19+AE19)/2))/(AD$7))+(1-(((AD19+AE19)/2)))*LN((1-(((AD19+AE19)/2)))/(1-(AD$7)))-AD$6<0,((AD19+AE19)/2),AD19) -> 0.067626953 | AE20: =IF((((AD19+AE19)/2))*LN((((AD19+AE19)/2))/(AD$7))+(1-(((AD19+AE19)/2)))*LN((1-(((AD19+AE19)/2)))/(1-(AD$7)))-AD$6<0,AE19,((AD19+AE19)/2)) -> 0.06809082 | AF20: =IF((((AF19+AG19)/2))*LN((((AF19+AG19)/2))/(AF$7))+(1-(((AF19+AG19)/2)))*LN((1-(((AF19+AG19)/2)))/(1-(AF$7)))-AF$6<0,((AF19+AG19)/2),AF19) -> 0.083398438 | AG20: =IF((((AF19+AG19)/2))*LN((((AF19+AG19)/2))/(AF$7))+(1-(((AF19+AG19)/2)))*LN((1-(((AF19+AG19)/2)))/(1-(AF$7)))-AF$6<0,AG19,((AF19+AG19)/2)) -> 0.083862305 | AH20: =IF((((AH19+AI19)/2))*LN((((AH19+AI19)/2))/(AH$7))+(1-(((AH19+AI19)/2)))*LN((1-(((AH19+AI19)/2)))/(1-(AH$7)))-AH$6<0,((AH19+AI19)/2),AH19) -> 0.11123047 | AI20: =IF((((AH19+AI19)/2))*LN((((AH19+AI19)/2))/(AH$7))+(1-(((AH19+AI19)/2)))*LN((1-(((AH19+AI19)/2)))/(1-(AH$7)))-AH$6<0,AI19,((AH19+AI19)/2)) -> 0.11169434 | AJ20: =IF((((AJ19+AK19)/2))*LN((((AJ19+AK19)/2))/(AJ$7))+(1-(((AJ19+AK19)/2)))*LN((1-(((AJ19+AK19)/2)))/(1-(AJ$7)))-AJ$6<0,((AJ19+AK19)/2),AJ19) -> 0.1729248 | AK20: =IF((((AJ19+AK19)/2))*LN((((AJ19+AK19)/2))/(AJ$7))+(1-(((AJ19+AK19)/2)))*LN((1-(((AJ19+AK19)/2)))/(1-(AJ$7)))-AJ$6<0,AK19,((AJ19+AK19)/2)) -> 0.17338867 | AL20: =IF((((AL19+AM19)/2))*LN((((AL19+AM19)/2))/(AL$7))+(1-(((AL19+AM19)/2)))*LN((1-(((AL19+AM19)/2)))/(1-(AL$7)))-AL$6<0,((AL19+AM19)/2),AL19) -> 0.28842773 | AM20: =IF((((AL19+AM19)/2))*LN((((AL19+AM19)/2))/(AL$7))+(1-(((AL19+AM19)/2)))*LN((1-(((AL19+AM19)/2)))/(1-(AL$7)))-AL$6<0,AM19,((AL19+AM19)/2)) -> 0.2888916 | AN20: =IF((((AN19+AO19)/2))*LN((((AN19+AO19)/2))/(AN$7))+(1-(((AN19+AO19)/2)))*LN((1-(((AN19+AO19)/2)))/(1-(AN$7)))-AN$6<0,((AN19+AO19)/2),AN19) -> 0.55515137 | AO20: =IF((((AN19+AO19)/2))*LN((((AN19+AO19)/2))/(AN$7))+(1-(((AN19+AO19)/2)))*LN((1-(((AN19+AO19)/2)))/(1-(AN$7)))-AN$6<0,AO19,((AN19+AO19)/2)) -> 0.55561523 | AP20: =IF(AP$7*LN(AP$7)-AP$7*((AP19+AQ19)/2)+(1-AP$7)*LN(1-AP$7)-(1-AP$7)*LN(1-EXP(((AP19+AQ19)/2)))-AP$6>0,((AP19+AQ19)/2),AP19) -> -3.7055956 | AQ20: =IF(AP$7*LN(AP$7)-AP$7*((AP19+AQ19)/2)+(1-AP$7)*LN(1-AP$7)-(1-AP$7)*LN(1-EXP(((AP19+AQ19)/2)))-AP$6>0,AQ19,((AP19+AQ19)/2)) -> -3.6733291 | AR20: =IF((((AR19+AS19)/2))*LN((((AR19+AS19)/2))/(AR$7))+(1-(((AR19+AS19)/2)))*LN((1-(((AR19+AS19)/2)))/(1-(AR$7)))-AR$6<0,((AR19+AS19)/2),AR19) -> 0.083398438 | AS20: =IF((((AR19+AS19)/2))*LN((((AR19+AS19)/2))/(AR$7))+(1-(((AR19+AS19)/2)))*LN((1-(((AR19+AS19)/2)))/(1-(AR$7)))-AR$6<0,AS19,((AR19+AS19)/2)) -> 0.083862305
B21: =IF(B$7*LN(B$7)-B$7*((B20+C20)/2)+(1-B$7)*LN(1-B$7)-(1-B$7)*LN(1-EXP(((B20+C20)/2)))-B$6>0,((B20+C20)/2),B20) -> -12.756353 | C21: =IF(B$7*LN(B$7)-B$7*((B20+C20)/2)+(1-B$7)*LN(1-B$7)-(1-B$7)*LN(1-EXP(((B20+C20)/2)))-B$6>0,C20,((B20+C20)/2)) -> -12.740219 | D21: =IF(D$7*LN(D$7)-D$7*((D20+E20)/2)+(1-D$7)*LN(1-D$7)-(1-D$7)*LN(1-EXP(((D20+E20)/2)))-D$6>0,((D20+E20)/2),D20) -> -16.047537 | E21: =IF(D$7*LN(D$7)-D$7*((D20+E20)/2)+(1-D$7)*LN(1-D$7)-(1-D$7)*LN(1-EXP(((D20+E20)/2)))-D$6>0,E20,((D20+E20)/2)) -> -16.031404 | F21: =IF(F$7*LN(F$7)-F$7*((F20+G20)/2)+(1-F$7)*LN(1-F$7)-(1-F$7)*LN(1-EXP(((F20+G20)/2)))-F$6>0,((F20+G20)/2),F20) -> -24.807896 | G21: =IF(F$7*LN(F$7)-F$7*((F20+G20)/2)+(1-F$7)*LN(1-F$7)-(1-F$7)*LN(1-EXP(((F20+G20)/2)))-F$6>0,G20,((F20+G20)/2)) -> -24.791762 | H21: =IF(H$7*LN(H$7)-H$7*((H20+I20)/2)+(1-H$7)*LN(1-H$7)-(1-H$7)*LN(1-EXP(((H20+I20)/2)))-H$6>0,((H20+I20)/2),H20) -> -3.2054646 | I21: =IF(H$7*LN(H$7)-H$7*((H20+I20)/2)+(1-H$7)*LN(1-H$7)-(1-H$7)*LN(1-EXP(((H20+I20)/2)))-H$6>0,I20,((H20+I20)/2)) -> -3.1893314 | J21: =IF(J$7*LN(J$7)-J$7*((J20+K20)/2)+(1-J$7)*LN(1-J$7)-(1-J$7)*LN(1-EXP(((J20+K20)/2)))-J$6>0,((J20+K20)/2),J20) -> -3.2861309 | K21: =IF(J$7*LN(J$7)-J$7*((J20+K20)/2)+(1-J$7)*LN(1-J$7)-(1-J$7)*LN(1-EXP(((J20+K20)/2)))-J$6>0,K20,((J20+K20)/2)) -> -3.2699976 | L21: =IF(L$7*LN(L$7)-L$7*((L20+M20)/2)+(1-L$7)*LN(1-L$7)-(1-L$7)*LN(1-EXP(((L20+M20)/2)))-L$6>0,((L20+M20)/2),L20) -> -3.47973 | M21: =IF(L$7*LN(L$7)-L$7*((L20+M20)/2)+(1-L$7)*LN(1-L$7)-(1-L$7)*LN(1-EXP(((L20+M20)/2)))-L$6>0,M20,((L20+M20)/2)) -> -3.4635967 | N21: =IF(N$7*LN(N$7)-N$7*((N20+O20)/2)+(1-N$7)*LN(1-N$7)-(1-N$7)*LN(1-EXP(((N20+O20)/2)))-N$6>0,((N20+O20)/2),N20) -> -3.7055956 | O21: =IF(N$7*LN(N$7)-N$7*((N20+O20)/2)+(1-N$7)*LN(1-N$7)-(1-N$7)*LN(1-EXP(((N20+O20)/2)))-N$6>0,O20,((N20+O20)/2)) -> -3.6894623 | P21: =IF(P$7*LN(P$7)-P$7*((P20+Q20)/2)+(1-P$7)*LN(1-P$7)-(1-P$7)*LN(1-EXP(((P20+Q20)/2)))-P$6>0,((P20+Q20)/2),P20) -> -4.044394 | Q21: =IF(P$7*LN(P$7)-P$7*((P20+Q20)/2)+(1-P$7)*LN(1-P$7)-(1-P$7)*LN(1-EXP(((P20+Q20)/2)))-P$6>0,Q20,((P20+Q20)/2)) -> -4.0282607 | R21: =IF(R$7*LN(R$7)-R$7*((R20+S20)/2)+(1-R$7)*LN(1-R$7)-(1-R$7)*LN(1-EXP(((R20+S20)/2)))-R$6>0,((R20+S20)/2),R20) -> -4.3186593 | S21: =IF(R$7*LN(R$7)-R$7*((R20+S20)/2)+(1-R$7)*LN(1-R$7)-(1-R$7)*LN(1-EXP(((R20+S20)/2)))-R$6>0,S20,((R20+S20)/2)) -> -4.3025261 | T21: =IF(T$7*LN(T$7)-T$7*((T20+U20)/2)+(1-T$7)*LN(1-T$7)-(1-T$7)*LN(1-EXP(((T20+U20)/2)))-T$6>0,((T20+U20)/2),T20) -> -4.8187903 | U21: =IF(T$7*LN(T$7)-T$7*((T20+U20)/2)+(1-T$7)*LN(1-T$7)-(1-T$7)*LN(1-EXP(((T20+U20)/2)))-T$6>0,U20,((T20+U20)/2)) -> -4.8026571 | V21: =IF(V$7*LN(V$7)-V$7*((V20+W20)/2)+(1-V$7)*LN(1-V$7)-(1-V$7)*LN(1-EXP(((V20+W20)/2)))-V$6>0,((V20+W20)/2),V20) -> -5.3834543 | W21: =IF(V$7*LN(V$7)-V$7*((V20+W20)/2)+(1-V$7)*LN(1-V$7)-(1-V$7)*LN(1-EXP(((V20+W20)/2)))-V$6>0,W20,((V20+W20)/2)) -> -5.367321 | X21: =IF(X$7*LN(X$7)-X$7*((X20+Y20)/2)+(1-X$7)*LN(1-X$7)-(1-X$7)*LN(1-EXP(((X20+Y20)/2)))-X$6>0,((X20+Y20)/2),X20) -> -5.931985 | Y21: =IF(X$7*LN(X$7)-X$7*((X20+Y20)/2)+(1-X$7)*LN(1-X$7)-(1-X$7)*LN(1-EXP(((X20+Y20)/2)))-X$6>0,Y20,((X20+Y20)/2)) -> -5.9158518 | Z21: =IF(Z$7*LN(Z$7)-Z$7*((Z20+AA20)/2)+(1-Z$7)*LN(1-Z$7)-(1-Z$7)*LN(1-EXP(((Z20+AA20)/2)))-Z$6>0,((Z20+AA20)/2),Z20) -> -6.9645135 | AA21: =IF(Z$7*LN(Z$7)-Z$7*((Z20+AA20)/2)+(1-Z$7)*LN(1-Z$7)-(1-Z$7)*LN(1-EXP(((Z20+AA20)/2)))-Z$6>0,AA20,((Z20+AA20)/2)) -> -6.9483802 | AB21: =IF((((AB20+AC20)/2))*LN((((AB20+AC20)/2))/(AB$7))+(1-(((AB20+AC20)/2)))*LN((1-(((AB20+AC20)/2)))/(1-(AB$7)))-AB$6<0,((AB20+AC20)/2),AB20) -> 0.059973145 | AC21: =IF((((AB20+AC20)/2))*LN((((AB20+AC20)/2))/(AB$7))+(1-(((AB20+AC20)/2)))*LN((1-(((AB20+AC20)/2)))/(1-(AB$7)))-AB$6<0,AC20,((AB20+AC20)/2)) -> 0.060205078 | AD21: =IF((((AD20+AE20)/2))*LN((((AD20+AE20)/2))/(AD$7))+(1-(((AD20+AE20)/2)))*LN((1-(((AD20+AE20)/2)))/(1-(AD$7)))-AD$6<0,((AD20+AE20)/2),AD20) -> 0.067626953 | AE21: =IF((((AD20+AE20)/2))*LN((((AD20+AE20)/2))/(AD$7))+(1-(((AD20+AE20)/2)))*LN((1-(((AD20+AE20)/2)))/(1-(AD$7)))-AD$6<0,AE20,((AD20+AE20)/2)) -> 0.067858887 | AF21: =IF((((AF20+AG20)/2))*LN((((AF20+AG20)/2))/(AF$7))+(1-(((AF20+AG20)/2)))*LN((1-(((AF20+AG20)/2)))/(1-(AF$7)))-AF$6<0,((AF20+AG20)/2),AF20) -> 0.083630371 | AG21: =IF((((AF20+AG20)/2))*LN((((AF20+AG20)/2))/(AF$7))+(1-(((AF20+AG20)/2)))*LN((1-(((AF20+AG20)/2)))/(1-(AF$7)))-AF$6<0,AG20,((AF20+AG20)/2)) -> 0.083862305 | AH21: =IF((((AH20+AI20)/2))*LN((((AH20+AI20)/2))/(AH$7))+(1-(((AH20+AI20)/2)))*LN((1-(((AH20+AI20)/2)))/(1-(AH$7)))-AH$6<0,((AH20+AI20)/2),AH20) -> 0.1114624 | AI21: =IF((((AH20+AI20)/2))*LN((((AH20+AI20)/2))/(AH$7))+(1-(((AH20+AI20)/2)))*LN((1-(((AH20+AI20)/2)))/(1-(AH$7)))-AH$6<0,AI20,((AH20+AI20)/2)) -> 0.11169434 | AJ21: =IF((((AJ20+AK20)/2))*LN((((AJ20+AK20)/2))/(AJ$7))+(1-(((AJ20+AK20)/2)))*LN((1-(((AJ20+AK20)/2)))/(1-(AJ$7)))-AJ$6<0,((AJ20+AK20)/2),AJ20) -> 0.1729248 | AK21: =IF((((AJ20+AK20)/2))*LN((((AJ20+AK20)/2))/(AJ$7))+(1-(((AJ20+AK20)/2)))*LN((1-(((AJ20+AK20)/2)))/(1-(AJ$7)))-AJ$6<0,AK20,((AJ20+AK20)/2)) -> 0.17315674 | AL21: =IF((((AL20+AM20)/2))*LN((((AL20+AM20)/2))/(AL$7))+(1-(((AL20+AM20)/2)))*LN((1-(((AL20+AM20)/2)))/(1-(AL$7)))-AL$6<0,((AL20+AM20)/2),AL20) -> 0.28842773 | AM21: =IF((((AL20+AM20)/2))*LN((((AL20+AM20)/2))/(AL$7))+(1-(((AL20+AM20)/2)))*LN((1-(((AL20+AM20)/2)))/(1-(AL$7)))-AL$6<0,AM20,((AL20+AM20)/2)) -> 0.28865967 | AN21: =IF((((AN20+AO20)/2))*LN((((AN20+AO20)/2))/(AN$7))+(1-(((AN20+AO20)/2)))*LN((1-(((AN20+AO20)/2)))/(1-(AN$7)))-AN$6<0,((AN20+AO20)/2),AN20) -> 0.5553833 | AO21: =IF((((AN20+AO20)/2))*LN((((AN20+AO20)/2))/(AN$7))+(1-(((AN20+AO20)/2)))*LN((1-(((AN20+AO20)/2)))/(1-(AN$7)))-AN$6<0,AO20,((AN20+AO20)/2)) -> 0.55561523 | AP21: =IF(AP$7*LN(AP$7)-AP$7*((AP20+AQ20)/2)+(1-AP$7)*LN(1-AP$7)-(1-AP$7)*LN(1-EXP(((AP20+AQ20)/2)))-AP$6>0,((AP20+AQ20)/2),AP20) -> -3.7055956 | AQ21: =IF(AP$7*LN(AP$7)-AP$7*((AP20+AQ20)/2)+(1-AP$7)*LN(1-AP$7)-(1-AP$7)*LN(1-EXP(((AP20+AQ20)/2)))-AP$6>0,AQ20,((AP20+AQ20)/2)) -> -3.6894623 | AR21: =IF((((AR20+AS20)/2))*LN((((AR20+AS20)/2))/(AR$7))+(1-(((AR20+AS20)/2)))*LN((1-(((AR20+AS20)/2)))/(1-(AR$7)))-AR$6<0,((AR20+AS20)/2),AR20) -> 0.083630371 | AS21: =IF((((AR20+AS20)/2))*LN((((AR20+AS20)/2))/(AR$7))+(1-(((AR20+AS20)/2)))*LN((1-(((AR20+AS20)/2)))/(1-(AR$7)))-AR$6<0,AS20,((AR20+AS20)/2)) -> 0.083862305
... B69: =IF(B$7*LN(B$7)-B$7*((B68+C68)/2)+(1-B$7)*LN(1-B$7)-(1-B$7)*LN(1-EXP(((B68+C68)/2)))-B$6>0,((B68+C68)/2),B68) -> -12.741681 | C69: =IF(B$7*LN(B$7)-B$7*((B68+C68)/2)+(1-B$7)*LN(1-B$7)-(1-B$7)*LN(1-EXP(((B68+C68)/2)))-B$6>0,C68,((B68+C68)/2)) -> -12.741681 | D69: =IF(D$7*LN(D$7)-D$7*((D68+E68)/2)+(1-D$7)*LN(1-D$7)-(1-D$7)*LN(1-EXP(((D68+E68)/2)))-D$6>0,((D68+E68)/2),D68) -> -16.034134 | E69: =IF(D$7*LN(D$7)-D$7*((D68+E68)/2)+(1-D$7)*LN(1-D$7)-(1-D$7)*LN(1-EXP(((D68+E68)/2)))-D$6>0,E68,((D68+E68)/2)) -> -16.034134 | F69: =IF(F$7*LN(F$7)-F$7*((F68+G68)/2)+(1-F$7)*LN(1-F$7)-(1-F$7)*LN(1-EXP(((F68+G68)/2)))-F$6>0,((F68+G68)/2),F68) -> -24.805568 | G69: =IF(F$7*LN(F$7)-F$7*((F68+G68)/2)+(1-F$7)*LN(1-F$7)-(1-F$7)*LN(1-EXP(((F68+G68)/2)))-F$6>0,G68,((F68+G68)/2)) -> -24.805568 | H69: =IF(H$7*LN(H$7)-H$7*((H68+I68)/2)+(1-H$7)*LN(1-H$7)-(1-H$7)*LN(1-EXP(((H68+I68)/2)))-H$6>0,((H68+I68)/2),H68) -> -3.1978911 | I69: =IF(H$7*LN(H$7)-H$7*((H68+I68)/2)+(1-H$7)*LN(1-H$7)-(1-H$7)*LN(1-EXP(((H68+I68)/2)))-H$6>0,I68,((H68+I68)/2)) -> -3.1978911 | J69: =IF(J$7*LN(J$7)-J$7*((J68+K68)/2)+(1-J$7)*LN(1-J$7)-(1-J$7)*LN(1-EXP(((J68+K68)/2)))-J$6>0,((J68+K68)/2),J68) -> -3.2860509 | K69: =IF(J$7*LN(J$7)-J$7*((J68+K68)/2)+(1-J$7)*LN(1-J$7)-(1-J$7)*LN(1-EXP(((J68+K68)/2)))-J$6>0,K68,((J68+K68)/2)) -> -3.2860509 | L69: =IF(L$7*LN(L$7)-L$7*((L68+M68)/2)+(1-L$7)*LN(1-L$7)-(1-L$7)*LN(1-EXP(((L68+M68)/2)))-L$6>0,((L68+M68)/2),L68) -> -3.4691973 | M69: =IF(L$7*LN(L$7)-L$7*((L68+M68)/2)+(1-L$7)*LN(1-L$7)-(1-L$7)*LN(1-EXP(((L68+M68)/2)))-L$6>0,M68,((L68+M68)/2)) -> -3.4691973 | N69: =IF(N$7*LN(N$7)-N$7*((N68+O68)/2)+(1-N$7)*LN(1-N$7)-(1-N$7)*LN(1-EXP(((N68+O68)/2)))-N$6>0,((N68+O68)/2),N68) -> -3.6896339 | O69: =IF(N$7*LN(N$7)-N$7*((N68+O68)/2)+(1-N$7)*LN(1-N$7)-(1-N$7)*LN(1-EXP(((N68+O68)/2)))-N$6>0,O68,((N68+O68)/2)) -> -3.6896339 | P69: =IF(P$7*LN(P$7)-P$7*((P68+Q68)/2)+(1-P$7)*LN(1-P$7)-(1-P$7)*LN(1-EXP(((P68+Q68)/2)))-P$6>0,((P68+Q68)/2),P68) -> -4.0293221 | Q69: =IF(P$7*LN(P$7)-P$7*((P68+Q68)/2)+(1-P$7)*LN(1-P$7)-(1-P$7)*LN(1-EXP(((P68+Q68)/2)))-P$6>0,Q68,((P68+Q68)/2)) -> -4.0293221 | R69: =IF(R$7*LN(R$7)-R$7*((R68+S68)/2)+(1-R$7)*LN(1-R$7)-(1-R$7)*LN(1-EXP(((R68+S68)/2)))-R$6>0,((R68+S68)/2),R68) -> -4.3144988 | S69: =IF(R$7*LN(R$7)-R$7*((R68+S68)/2)+(1-R$7)*LN(1-R$7)-(1-R$7)*LN(1-EXP(((R68+S68)/2)))-R$6>0,S68,((R68+S68)/2)) -> -4.3144988 | T69: =IF(T$7*LN(T$7)-T$7*((T68+U68)/2)+(1-T$7)*LN(1-T$7)-(1-T$7)*LN(1-EXP(((T68+U68)/2)))-T$6>0,((T68+U68)/2),T68) -> -4.8157574 | U69: =IF(T$7*LN(T$7)-T$7*((T68+U68)/2)+(1-T$7)*LN(1-T$7)-(1-T$7)*LN(1-EXP(((T68+U68)/2)))-T$6>0,U68,((T68+U68)/2)) -> -4.8157574 | V69: =IF(V$7*LN(V$7)-V$7*((V68+W68)/2)+(1-V$7)*LN(1-V$7)-(1-V$7)*LN(1-EXP(((V68+W68)/2)))-V$6>0,((V68+W68)/2),V68) -> -5.3827998 | W69: =IF(V$7*LN(V$7)-V$7*((V68+W68)/2)+(1-V$7)*LN(1-V$7)-(1-V$7)*LN(1-EXP(((V68+W68)/2)))-V$6>0,W68,((V68+W68)/2)) -> -5.3827998 | X69: =IF(X$7*LN(X$7)-X$7*((X68+Y68)/2)+(1-X$7)*LN(1-X$7)-(1-X$7)*LN(1-EXP(((X68+Y68)/2)))-X$6>0,((X68+Y68)/2),X68) -> -5.9191752 | Y69: =IF(X$7*LN(X$7)-X$7*((X68+Y68)/2)+(1-X$7)*LN(1-X$7)-(1-X$7)*LN(1-EXP(((X68+Y68)/2)))-X$6>0,Y68,((X68+Y68)/2)) -> -5.9191752 | Z69: =IF(Z$7*LN(Z$7)-Z$7*((Z68+AA68)/2)+(1-Z$7)*LN(1-Z$7)-(1-Z$7)*LN(1-EXP(((Z68+AA68)/2)))-Z$6>0,((Z68+AA68)/2),Z68) -> -6.9521207 | AA69: =IF(Z$7*LN(Z$7)-Z$7*((Z68+AA68)/2)+(1-Z$7)*LN(1-Z$7)-(1-Z$7)*LN(1-EXP(((Z68+AA68)/2)))-Z$6>0,AA68,((Z68+AA68)/2)) -> -6.9521207 | AB69: =IF((((AB68+AC68)/2))*LN((((AB68+AC68)/2))/(AB$7))+(1-(((AB68+AC68)/2)))*LN((1-(((AB68+AC68)/2)))/(1-(AB$7)))-AB$6<0,((AB68+AC68)/2),AB68) -> 0.060040821 | AC69: =IF((((AB68+AC68)/2))*LN((((AB68+AC68)/2))/(AB$7))+(1-(((AB68+AC68)/2)))*LN((1-(((AB68+AC68)/2)))/(1-(AB$7)))-AB$6<0,AC68,((AB68+AC68)/2)) -> 0.060040821 | AD69: =IF((((AD68+AE68)/2))*LN((((AD68+AE68)/2))/(AD$7))+(1-(((AD68+AE68)/2)))*LN((1-(((AD68+AE68)/2)))/(1-(AD$7)))-AD$6<0,((AD68+AE68)/2),AD68) -> 0.067751818 | AE69: =IF((((AD68+AE68)/2))*LN((((AD68+AE68)/2))/(AD$7))+(1-(((AD68+AE68)/2)))*LN((1-(((AD68+AE68)/2)))/(1-(AD$7)))-AD$6<0,AE68,((AD68+AE68)/2)) -> 0.067751818 | AF69: =IF((((AF68+AG68)/2))*LN((((AF68+AG68)/2))/(AF$7))+(1-(((AF68+AG68)/2)))*LN((1-(((AF68+AG68)/2)))/(1-(AF$7)))-AF$6<0,((AF68+AG68)/2),AF68) -> 0.083648267 | AG69: =IF((((AF68+AG68)/2))*LN((((AF68+AG68)/2))/(AF$7))+(1-(((AF68+AG68)/2)))*LN((1-(((AF68+AG68)/2)))/(1-(AF$7)))-AF$6<0,AG68,((AF68+AG68)/2)) -> 0.083648267 | AH69: =IF((((AH68+AI68)/2))*LN((((AH68+AI68)/2))/(AH$7))+(1-(((AH68+AI68)/2)))*LN((1-(((AH68+AI68)/2)))/(1-(AH$7)))-AH$6<0,((AH68+AI68)/2),AH68) -> 0.11154805 | AI69: =IF((((AH68+AI68)/2))*LN((((AH68+AI68)/2))/(AH$7))+(1-(((AH68+AI68)/2)))*LN((1-(((AH68+AI68)/2)))/(1-(AH$7)))-AH$6<0,AI68,((AH68+AI68)/2)) -> 0.11154805 | AJ69: =IF((((AJ68+AK68)/2))*LN((((AJ68+AK68)/2))/(AJ$7))+(1-(((AJ68+AK68)/2)))*LN((1-(((AJ68+AK68)/2)))/(1-(AJ$7)))-AJ$6<0,((AJ68+AK68)/2),AJ68) -> 0.17294935 | AK69: =IF((((AJ68+AK68)/2))*LN((((AJ68+AK68)/2))/(AJ$7))+(1-(((AJ68+AK68)/2)))*LN((1-(((AJ68+AK68)/2)))/(1-(AJ$7)))-AJ$6<0,AK68,((AJ68+AK68)/2)) -> 0.17294935 | AL69: =IF((((AL68+AM68)/2))*LN((((AL68+AM68)/2))/(AL$7))+(1-(((AL68+AM68)/2)))*LN((1-(((AL68+AM68)/2)))/(1-(AL$7)))-AL$6<0,((AL68+AM68)/2),AL68) -> 0.2885192 | AM69: =IF((((AL68+AM68)/2))*LN((((AL68+AM68)/2))/(AL$7))+(1-(((AL68+AM68)/2)))*LN((1-(((AL68+AM68)/2)))/(1-(AL$7)))-AL$6<0,AM68,((AL68+AM68)/2)) -> 0.2885192 | AN69: =IF((((AN68+AO68)/2))*LN((((AN68+AO68)/2))/(AN$7))+(1-(((AN68+AO68)/2)))*LN((1-(((AN68+AO68)/2)))/(1-(AN$7)))-AN$6<0,((AN68+AO68)/2),AN68) -> 0.55551415 | AO69: =IF((((AN68+AO68)/2))*LN((((AN68+AO68)/2))/(AN$7))+(1-(((AN68+AO68)/2)))*LN((1-(((AN68+AO68)/2)))/(1-(AN$7)))-AN$6<0,AO68,((AN68+AO68)/2)) -> 0.55551415 | AP69: =IF(AP$7*LN(AP$7)-AP$7*((AP68+AQ68)/2)+(1-AP$7)*LN(1-AP$7)-(1-AP$7)*LN(1-EXP(((AP68+AQ68)/2)))-AP$6>0,((AP68+AQ68)/2),AP68) -> -3.6896339 | AQ69: =IF(AP$7*LN(AP$7)-AP$7*((AP68+AQ68)/2)+(1-AP$7)*LN(1-AP$7)-(1-AP$7)*LN(1-EXP(((AP68+AQ68)/2)))-AP$6>0,AQ68,((AP68+AQ68)/2)) -> -3.6896339 | AR69: =IF((((AR68+AS68)/2))*LN((((AR68+AS68)/2))/(AR$7))+(1-(((AR68+AS68)/2)))*LN((1-(((AR68+AS68)/2)))/(1-(AR$7)))-AR$6<0,((AR68+AS68)/2),AR68) -> 0.083648267 | AS69: =IF((((AR68+AS68)/2))*LN((((AR68+AS68)/2))/(AR$7))+(1-(((AR68+AS68)/2)))*LN((1-(((AR68+AS68)/2)))/(1-(AR$7)))-AR$6<0,AS68,((AR68+AS68)/2)) -> 0.083648267
A71: Result | B71: =EXP((B69+C69)/2) -> 2.9265667e-06 | D71: =EXP((D69+E69)/2) -> 1.0875871e-07 | F71: =EXP((F69+G69)/2) -> 1.6868595e-11 | H71: =EXP((H69+I69)/2) -> 0.040848256 | J71: =EXP((J69+K69)/2) -> 0.037401261 | L71: =EXP((L69+M69)/2) -> 0.031142017 | N71: =EXP((N69+O69)/2) -> 0.024981145 | P71: =EXP((P69+Q69)/2) -> 0.017786384 | R71: =EXP((R69+S69)/2) -> 0.013373251 | T71: =EXP((T69+U69)/2) -> 0.0081010838 | V71: =EXP((V69+W69)/2) -> 0.0045949388 | X71: =EXP((X69+Y69)/2) -> 0.0026874158 | Z71: =EXP((Z69+AA69)/2) -> 0.00095660434 | AB71: =(AB69+AC69)/2 -> 0.060040821 | AD71: =(AD69+AE69)/2 -> 0.067751818 | AF71: =(AF69+AG69)/2 -> 0.083648267 | AH71: =(AH69+AI69)/2 -> 0.11154805 | AJ71: =(AJ69+AK69)/2 -> 0.17294935 | AL71: =(AL69+AM69)/2 -> 0.2885192 | AN71: =(AN69+AO69)/2 -> 0.55551415 | AP71: =EXP((AP69+AQ69)/2) -> 0.024981145 | AR71: =(AR69+AS69)/2 -> 0.083648267

Sheet Wasserstein
A1: Try balls: Wasserstein families on the record (Theorem 11.3(ii)-(iii); Figure 11.2(a); Worked Example 11.1, Step 3; AXIOM Lab 2.11, step 3)
A2: A path's distance from a breach is its thinnest margin over the quarters (a move shifts its deviations; the cost is the largest shift). The ball of radius eps keeps 5 percent exactly when the thinnest K = 0.05 N paths average at least eps / 0.05 above the floor.
A4: Paths K that must keep the average margin, 0.05 N | B4: =Alpha*NPaths -> 5000 | C4: 5,000 of 100,000
A6: Radius eps ($m) | B6: Required average of the thinnest 5% (eps / 0.05) | C6: Achieved by the design (engine) | D6: Worst chance of Volume I's package (engine) | E6: Line (engine) | F6: Delay (engine) | G6: Cost | H6: Under the law (engine) | I6: Fresh paths (engine) | J6: Extra over Volume I's
A7: 0.01 | B7: =A7/Alpha -> 0.2 | C7: 0.2 | D7: 0.056425656 | E7: 165 | F7: 0.82696418 | G7: =Fee*E7+VQ*F7 -> 11.565713 | H7: 0.044 | I7: 0.04317 | J7: =G7-Family!$J$5 -> 1.1251026
A8: 0.02 | B8: =A8/Alpha -> 0.4 | C8: 0.4 | E8: 165 | F8: 0.8865198 | G8: =Fee*E8+VQ*F8 -> 12.042158 | H8: 0.04167 | I8: 0.04107 | J8: =G8-Family!$J$5 -> 1.6015475
A9: 0.05 | B9: =A9/Alpha -> 1 | C9: 1 | D9: 0.064692828 | E9: 165 | F9: 1.0068464 | G9: =Fee*E9+VQ*F9 -> 13.004771 | H9: 0.03709 | I9: 0.03655 | J9: =G9-Family!$J$5 -> 2.5641603
A10: 0.1 | B10: =A10/Alpha -> 2 | C10: 2 | D10: 0.071131776 | E10: 165 | F10: 1.1480452 | G10: =Fee*E10+VQ*F10 -> 14.134361 | H10: 0.03233 | I10: 0.03205 | J10: =G10-Family!$J$5 -> 3.6937503
A11: 0.2 | B11: =A11/Alpha -> 4 | C11: 4 | D11: 0.080529238 | E11: 170 | F11: 1.3351318 | G11: =Fee*E11+VQ*F11 -> 15.781055 | H11: 0.02613 | I11: 0.02607 | J11: =G11-Family!$J$5 -> 5.3404437
A12: 0.5 | B12: =A12/Alpha -> 10 | C12: 10 | D12: 0.10000587 | E12: 175 | F12: 1.7607467 | G12: =Fee*E12+VQ*F12 -> 19.335974 | H12: 0.0167 | I12: 0.01613 | J12: =G12-Family!$J$5 -> 8.895363
A13: 1 | B13: =A13/Alpha -> 20 | C13: 20 | D13: 0.12319954 | E13: 175 | F13: 2.3370437 | G13: =Fee*E13+VQ*F13 -> 23.94635 | H13: 0.00912 | I13: 0.00889 | J13: =G13-Family!$J$5 -> 13.505739
A16: The spread's doubt: its excess over the declared spread, c - 1 | B16: =Records!B11-1 -> 0.23198294 | C16: 0.232
A17: The paths' average largest deviation, $m (engine) | B17: 113.23192 | C17: $113.2 million
A18: The radius that holds the spread's doubt (Theorem 11.3(ii)) | B18: =B16*B17 -> 26.267874 | C18: $26.3 million
A19: The thinnest 5% would need to average | B19: =B18/Alpha -> 525.35748 | C19: $525 million
A20: What a $400m line and 7 quarters give them (engine) | B20: 121.93557 | C20: $121.9 million: no package can do it
A21: shortfall, as a multiple | B21: =B19/B20 -> 4.3084842

Sheet Records1000
A1: Set a radius from a record: 200 records of 1,000 paths, checked on the fresh 100,000 (Theorem 11.3(iv); Proposition 11.2(iv); Figure 11.2(b); Worked Example 11.1, Step 4; AXIOM Lab 2.11, step 4)
A2: Engine: on each record (seeds 900000-900199) a package is designed aimed at a lower target or kept over a Wasserstein ball around the record, among Chapter 9's lines ($120-220 million); its true chance is read on the fresh paths. The formulas compare reliability per dollar.
A4: Design | B4: Keep 5% (engine) | C4: Mean true chance (engine) | D4: 90th percentile (engine) | E4: Mean cost (engine) | F4: Mean line (engine) | G4: Extra cost over no margin | H4: Extra reliability (points) | I4: Points of reliability per $ million
A5: No margin: aim at 5% | B5: 0.385 | C5: 0.0520926 | D5: 0.062296 | E5: 10.185045 | F5: 161.45
A6: Target lower by 0.5 points | B6: 0.7 | C6: 0.047018 | D6: 0.057738 | E6: 11.089252 | F6: 164.1 | G6: =E6-$E$5 -> 0.90420769 | H6: =100*(B6-$B$5) -> 31.5 | I6: =H6/G6 -> 34.837129
A7: Target lower by 1 point | B7: 0.87 | C7: 0.04210155 | D7: 0.050855 | E7: 12.086363 | F7: 163.75 | G7: =E7-$E$5 -> 1.9013185 | H7: =100*(B7-$B$5) -> 48.5 | I7: =H7/G7 -> 25.508614
A8: Target lower by 1.5 points | B8: 0.985 | C8: 0.0372773 | D8: 0.045212 | E8: 13.122294 | F8: 165.25 | G8: =E8-$E$5 -> 2.9372497 | H8: =100*(B8-$B$5) -> 60 | I8: =H8/G8 -> 20.427273
A9: Target lower by 2 points | B9: 1 | C9: 0.0322493 | D9: 0.038511 | E9: 14.32758 | F9: 168.625 | G9: =E9-$E$5 -> 4.1425353 | H9: =100*(B9-$B$5) -> 61.5 | I9: =H9/G9 -> 14.845981
A10: Wasserstein radius $10,000 | B10: 0.785 | C10: 0.04505895 | D10: 0.055135 | E10: 11.442322 | F10: 163.8 | G10: =E10-$E$5 -> 1.2572778 | H10: =100*(B10-$B$5) -> 40 | I10: =H10/G10 -> 31.814766
A11: Wasserstein radius $20,000 | B11: 0.865 | C11: 0.0425661 | D11: 0.051903 | E11: 11.941611 | F11: 164.875 | G11: =E11-$E$5 -> 1.7565659 | H11: =100*(B11-$B$5) -> 48 | I11: =H11/G11 -> 27.326045
A12: Wasserstein radius $30,000 | B12: 0.915 | C12: 0.040799 | D12: 0.049599 | E12: 12.327297 | F12: 164.375 | G12: =E12-$E$5 -> 2.1422527 | H12: =100*(B12-$B$5) -> 53 | I12: =H12/G12 -> 24.740312
A13: Wasserstein radius $50,000 | B13: 0.975 | C13: 0.0379999 | D13: 0.046046 | E13: 12.938837 | F13: 164.55 | G13: =E13-$E$5 -> 2.753792 | H13: =100*(B13-$B$5) -> 59 | I13: =H13/G13 -> 21.425003
A14: Wasserstein radius $100,000 | B14: 0.995 | C14: 0.0332301 | D14: 0.040581 | E14: 14.066769 | F14: 167.25 | G14: =E14-$E$5 -> 3.8817244 | H14: =100*(B14-$B$5) -> 61 | I14: =H14/G14 -> 15.714666
A15: Wasserstein radius $200,000 | B15: 1 | C15: 0.02700645 | D15: 0.033121 | E15: 15.731952 | F15: 169.3 | G15: =E15-$E$5 -> 5.5469076 | H15: =100*(B15-$B$5) -> 61.5 | I15: =H15/G15 -> 11.087259
A17: A radius of $50,000 makes 97.5 percent of designs keep 5 percent at $12.94 million on average, about what lowering the target by 1.5 points buys: the radius should follow the record's size.

Sheet Moments
A1: Moments only: Cantelli's bounds and the cost of keeping every quarter at 5 percent (Proposition 11.1(iii)-(iv); Section 11.4; AXIOM Lab 2.11, step 5)
A2: Among laws of a margin with mean mu > 0 and spread sigma, the worst chance that it falls to zero is sigma^2 / (sigma^2 + mu^2), on two points. Means and spreads of each quarter's margin are the engine's.
A4: Quarter k | B4: t (years) | C4: The draw's shape S | D4: Lift of a quarter of delay, l_k | E4: Mean margin, Volume I's package (engine) | F4: Spread (engine) | G4: Cantelli bound | H4: Mean margin at $160m, no delay (engine) | I4: Spread at $160m (engine) | J4: Delay its bound needs
A5: 1 | B5: =A5/4 -> 0.25 | C5: =(B5/Tpk)*EXP(1-B5/Tpk) -> 0.29985941 | D5: =DPQ*PerPt*C5 -> 7.4365134 | E5: 229.01241 | F5: 50.105003 | G5: =IF(E5>0,F5^2/(F5^2+E5^2),1) -> 0.045681213 | H5: 224.00691 | I5: 50.137979 | J5: =MAX(0,($B$24*I5-H5)/D5) -> 0
A6: 2 | B6: =A6/4 -> 0.5 | C6: =(B6/Tpk)*EXP(1-B6/Tpk) -> 0.52925 | D6: =DPQ*PerPt*C6 -> 13.1254 | E6: 198.61506 | F6: 58.375532 | G6: =IF(E6>0,F6^2/(F6^2+E6^2),1) -> 0.079515845 | H6: 189.77022 | I6: 58.43141 | J6: =MAX(0,($B$24*I6-H6)/D6) -> 4.9466219
A7: 3 | B7: =A7/4 -> 0.75 | C7: =(B7/Tpk)*EXP(1-B7/Tpk) -> 0.70059223 | D7: =DPQ*PerPt*C7 -> 17.374687 | E7: 176.91085 | F7: 61.156725 | G7: =IF(E7>0,F7^2/(F7^2+E7^2),1) -> 0.10674663 | H7: 165.18243 | I7: 61.23547 | J7: =MAX(0,($B$24*I7-H7)/D7) -> 5.8554607
A8: 4 | B8: =A8/4 -> 1 | C8: =(B8/Tpk)*EXP(1-B8/Tpk) -> 0.82436064 | D8: =DPQ*PerPt*C8 -> 20.444144 | E8: 162.07243 | F8: 62.336821 | G8: =IF(E8>0,F8^2/(F8^2+E8^2),1) -> 0.12887055 | H8: 148.25079 | I8: 62.442325 | J8: =MAX(0,($B$24*I8-H8)/D8) -> 6.0618333
A9: 5 | B9: =A9/4 -> 1.25 | C9: =(B9/Tpk)*EXP(1-B9/Tpk) -> 0.90936963 | D9: =DPQ*PerPt*C9 -> 22.552367 | E9: 152.87235 | F9: 62.679035 | G9: =IF(E9>0,F9^2/(F9^2+E9^2),1) -> 0.1439143 | H9: 137.59837 | I9: 62.804782 | J9: =MAX(0,($B$24*I9-H9)/D9) -> 6.0375624
A10: 6 | B10: =A10/4 -> 1.5 | C10: =(B10/Tpk)*EXP(1-B10/Tpk) -> 0.96301906 | D10: =DPQ*PerPt*C10 -> 23.882873 | E10: 148.40602 | F10: 62.85367 | G10: =IF(E10>0,F10^2/(F10^2+E10^2),1) -> 0.15209219 | H10: 132.19697 | I10: 63.003795 | J10: =MAX(0,($B$24*I10-H10)/D10) -> 5.9636965
A11: 7 | B11: =A11/4 -> 1.75 | C11: =(B11/Tpk)*EXP(1-B11/Tpk) -> 0.9915049 | D11: =DPQ*PerPt*C11 -> 24.589321 | E11: 147.47721 | F11: 62.869247 | G11: =IF(E11>0,F11^2/(F11^2+E11^2),1) -> 0.15378304 | H11: 130.75496 | I11: 63.048946 | J11: =MAX(0,($B$24*I11-H11)/D11) -> 5.859008
A12: 8 | B12: =A12/4 -> 2 | C12: =(B12/Tpk)*EXP(1-B12/Tpk) -> 1 | D12: =DPQ*PerPt*C12 -> 24.8 | E12: 149.49243 | F12: 62.915153 | G12: =IF(E12>0,F12^2/(F12^2+E12^2),1) -> 0.15047026 | H12: 132.58765 | I12: 63.122126 | J12: =MAX(0,($B$24*I12-H12)/D12) -> 5.7481982
A13: 9 | B13: =A13/4 -> 2.25 | C13: =(B13/Tpk)*EXP(1-B13/Tpk) -> 0.99280902 | D13: =DPQ*PerPt*C13 -> 24.621664 | E13: 153.25291 | F13: 63.087122 | G13: =IF(E13>0,F13^2/(F13^2+E13^2),1) -> 0.14490356 | H13: 136.42363 | I13: 63.314983 | J13: =MAX(0,($B$24*I13-H13)/D13) -> 5.6681784
A14: 10 | B14: =A14/4 -> 2.5 | C14: =(B14/Tpk)*EXP(1-B14/Tpk) -> 0.97350098 | D14: =DPQ*PerPt*C14 -> 24.142824 | E14: 158.93725 | F14: 63.06844 | G14: =IF(E14>0,F14^2/(F14^2+E14^2),1) -> 0.13603994 | H14: 142.38318 | I14: 63.328496 | J14: =MAX(0,($B$24*I14-H14)/D14) -> 5.536193
A15: 11 | B15: =A15/4 -> 2.75 | C15: =(B15/Tpk)*EXP(1-B15/Tpk) -> 0.94502276 | D15: =DPQ*PerPt*C15 -> 23.436564 | E15: 166.12599 | F15: 63.306404 | G15: =IF(E15>0,F15^2/(F15^2+E15^2),1) -> 0.12680372 | H15: 149.99508 | I15: 63.593741 | J15: =MAX(0,($B$24*I15-H15)/D15) -> 5.4275706
A16: 12 | B16: =A16/4 -> 3 | C16: =(B16/Tpk)*EXP(1-B16/Tpk) -> 0.90979599 | D16: =DPQ*PerPt*C16 -> 22.562941 | E16: 173.98337 | F16: 63.489429 | G16: =IF(E16>0,F16^2/(F16^2+E16^2),1) -> 0.11751534 | H16: 158.39238 | I16: 63.804306 | J16: =MAX(0,($B$24*I16-H16)/D16) -> 5.3062297
A18: The worst quarter | B18: =MATCH(MAX(G5:G16),G5:G16,0) -> 7 | C18: Quarter 7
A19: its bound | B19: =MAX(G5:G16) -> 0.15378304 | C19: 15.4 percent
A20: the two-point law: the margin is zero with that chance, otherwise | B20: =INDEX(E5:E16,B18)+INDEX(F5:F16,B18)^2/INDEX(E5:E16,B18) -> 174.27825 | C20: The lump a closure produces
A21: the two-point law's mean (equals the declared mean) | B21: =(1-B19)*B20 -> 147.47721 | C21: $147.5 million
A22: The bounds' sum: the union bound (Proposition 11.1(iv)) | B22: =SUM(G5:G16) -> 1.4863366 | C22: 148.6 percent: it says nothing
A24: Spreads of margin each quarter needs at 5 percent, sqrt((1 - a)/a) | B24: =SQRT((1-Alpha)/Alpha) -> 4.3588989 | C24: 4.36 = sqrt(19)
A25: Spreads the union bound would need, at a / 12 per quarter | B25: =SQRT((1-Alpha/NQ)/(Alpha/NQ)) -> 15.459625 | C25: 15.46
A27: The moment package: line (engine) | B27: 160 | C27: $160 million
A28: delay: the largest any quarter's bound needs | B28: =MAX(J5:J16) -> 6.0618333 | C28: 6.062 quarters
A29: cost | B29: =Fee*B27+VQ*B28 -> 53.294667 | C29: $53.29 million
A30: its chance of a breach under the law (engine) | B30: 0.00026 | C30: 0.026 percent

Sheet PriceTheDoubt
A1: Price the doubt: Table 11.3, every declaration's package (Worked Example 11.1, Step 5; Figure 11.3(b))
A2: Lines, delays and chances are the engine's (the book's 100,000 paths and the fresh 100,000); the costs, the gaps and the standard errors are formulas. The worst law: closures 0.315 a year, spread $61.6 million.
A4: Declaration | B4: Line (engine) | C4: Delay (engine) | D4: Cost | E4: Under the law (engine) | F4: fresh (engine) | G4: Under the worst law (engine) | H4: fresh (engine) | I4: Law: |book - fresh| | J4: Worst: |book - fresh| | K4: Standard error, law | L4: Standard error, worst
A5: One law (Chapter 9) | B5: 170 | C5: 0.66757636 | D5: =Fee*B5+VQ*C5 -> 10.440611 | E5: 0.05 | F5: 0.04907 | G5: 0.15789 | H5: 0.15835 | I5: =ABS(E5-F5) -> 0.00093 | J5: =ABS(G5-H5) -> 0.00046 | K5: =SQRT(E5*(1-E5)/NPaths) -> 0.00068920244 | L5: =SQRT(G5*(1-G5)/NPaths) -> 0.0011530861
A6: A set, max-min choice (Chapter 10) | B6: 231.6 | C6: 0.44936651 | D6: =Fee*B6+VQ*C6 -> 10.542932 | E6: 0.05637 | F6: 0.05508 | G6: 0.1616 | H6: 0.16046 | I6: =ABS(E6-F6) -> 0.00129 | J6: =ABS(G6-H6) -> 0.00114 | K6: =SQRT(E6*(1-E6)/NPaths) -> 0.00072933136 | L6: =SQRT(G6*(1-G6)/NPaths) -> 0.0011639821
A7: Wasserstein ball, $0.1 million | B7: 165 | C7: 1.1480452 | D7: =Fee*B7+VQ*C7 -> 14.134361 | E7: 0.03233 | F7: 0.03205 | G7: 0.12153 | H7: 0.12051 | I7: =ABS(E7-F7) -> 0.00028 | J7: =ABS(G7-H7) -> 0.00102 | K7: =SQRT(E7*(1-E7)/NPaths) -> 0.00055932791 | L7: =SQRT(G7*(1-G7)/NPaths) -> 0.0010332495
A8: Divergence ball, d = 0.01 | B8: 175 | C8: 1.3539024 | D8: =Fee*B8+VQ*C8 -> 16.081219 | E8: 0.02498 | F8: 0.02515 | G8: 0.10248 | H8: 0.10075 | I8: =ABS(E8-F8) -> 0.00017 | J8: =ABS(G8-H8) -> 0.00173 | K8: =SQRT(E8*(1-E8)/NPaths) -> 0.00049351798 | L8: =SQRT(G8*(1-G8)/NPaths) -> 0.00095905083
A9: Closures' doubt (rate <= 0.315) | B9: 210 | C9: 0.66716792 | D9: =Fee*B9+VQ*C9 -> 11.637343 | E9: 0.04631 | F9: 0.04534 | G9: 0.14431 | H9: 0.14391 | I9: =ABS(E9-F9) -> 0.00097 | J9: =ABS(G9-H9) -> 0.0004 | K9: =SQRT(E9*(1-E9)/NPaths) -> 0.00066457042 | L9: =SQRT(G9*(1-G9)/NPaths) -> 0.0011112364
A10: Spread's doubt (spread <= 61.6) | B10: 170 | C10: 2.218368 | D10: =Fee*B10+VQ*C10 -> 22.846944 | E10: 0.01063 | F10: 0.01032 | G10: 0.05858 | H10: 0.05751 | I10: =ABS(E10-F10) -> 0.00031 | J10: =ABS(G10-H10) -> 0.00107 | K10: =SQRT(E10*(1-E10)/NPaths) -> 0.00032429929 | L10: =SQRT(G10*(1-G10)/NPaths) -> 0.00074261958
A11: The records' family (both) | B11: 200 | C11: 2.2504041 | D11: =Fee*B11+VQ*C11 -> 24.003233 | E11: 0.00894 | F11: 0.0086 | G11: 0.05 | H11: 0.04905 | I11: =ABS(E11-F11) -> 0.00034 | J11: =ABS(G11-H11) -> 0.00095 | K11: =SQRT(E11*(1-E11)/NPaths) -> 0.0002976588 | L11: =SQRT(G11*(1-G11)/NPaths) -> 0.00068920244
A12: Records twice as long | B12: 195 | C12: 1.6900824 | D12: =Fee*B12+VQ*C12 -> 19.370659 | E12: 0.01664 | F12: 0.01622 | G12: 0.07665 | H12: 0.07438 | I12: =ABS(E12-F12) -> 0.00042 | J12: =ABS(G12-H12) -> 0.00227 | K12: =SQRT(E12*(1-E12)/NPaths) -> 0.00040451342 | L12: =SQRT(G12*(1-G12)/NPaths) -> 0.00084127747
A13: Moments only (every quarter) | B13: 160 | C13: 6.0618333 | D13: =Fee*B13+VQ*C13 -> 53.294667 | E13: 0.00026 | F13: 0.00027 | G13: 0.00354 | H13: 0.00369 | I13: =ABS(E13-F13) -> 1e-05 | J13: =ABS(G13-H13) -> 0.00015 | K13: =SQRT(E13*(1-E13)/NPaths) -> 5.0983566e-05 | L13: =SQRT(G13*(1-G13)/NPaths) -> 0.00018781556
A15: The price of ambiguity: the records' family less one law | B15: =D11-D5 -> 13.562622 | C15: $13.56 million
A16: The value of a record twice as long | B16: =D11-D12 -> 4.6325741 | C16: $4.63 million
A17: Fresh paths: the largest gap, points | B17: =100*MAX(I5:J13) -> 0.227 | C17: Within 0.3 points (Table 11.3)
A18: within 0.3 points? (1 = yes) | B18: =IF(MAX(I5:J13)<=0.003,1,0) -> 1
A19: The largest standard error of a chance, points | B19: =100*MAX(K5:L13) -> 0.11639821 | C19: Below 0.12 points (Section 11.5)
A20: below 0.12 points? (1 = yes) | B20: =IF(MAX(K5:L13)<0.0012,1,0) -> 1

Sheet Reference_Values
A1: Checkpoint | B1: Engine value | C1: Meaning (where in the book)
A2: Rate: upper 95% bound (Garwood) | B2: 0.31478968 | C2: Proposition 11.2(i); Step 1: 0.3148
A3: Rate: upper bound from the right tail | B3: 0.31478968 | C3: The same bound
A4: Rate: lower 95% bound | B4: 0.017768076 | C4: 0.0178
A5: Spread: upper 95% bound | B5: 61.599147 | C5: Proposition 11.2(ii): $61.60 million
A6: Spread: lower 95% bound | B6: 42.268464 | C6: $42.27 million
A7: Twice the record: rate bound | B7: 0.22883798 | C7: 0.2288
A8: Twice the record: spread, upper bound | B8: 57.602817 | C8: $57.60 million
A9: Twice the record: spread, lower bound | B9: 44.275554 | C9: $44.28 million
A10: The records' family: confidence together | B10: 0.9 | C10: Proposition 11.2(iii): 90 percent
A11: Volume I's package: cost | B11: 10.440611 | C11: $10.44 million
A12: Closures' doubt: cost | B12: 11.637343 | C12: $11.64 million
A13: Spread's doubt: cost | B13: 22.846944 | C13: $22.85 million
... A106: Chapter 10's max-min package: cost | B106: 10.542932 | C106: $10.54 million

Sheet Checks
A1: Checkpoint | B1: Workbook formula value | C1: Engine value | D1: |diff| | E1: Tolerance | F1: Status
A2: Rate: upper 95% bound (Garwood) | B2: =Records!B5 -> 0.31478968 | C2: =Reference_Values!B2 -> 0.31478968 | D2: =ABS(B2-C2) -> 0 | E2: 1e-09 | F2: =IF(D2<=E2,"PASS","FAIL") -> PASS
A3: Rate: upper bound from the right tail | B3: =Records!B6 -> 0.31478968 | C3: =Reference_Values!B3 -> 0.31478968 | D3: =ABS(B3-C3) -> 0 | E3: 1e-09 | F3: =IF(D3<=E3,"PASS","FAIL") -> PASS
A4: Rate: lower 95% bound | B4: =Records!B7 -> 0.017768076 | C4: =Reference_Values!B4 -> 0.017768076 | D4: =ABS(B4-C4) -> 0 | E4: 1e-09 | F4: =IF(D4<=E4,"PASS","FAIL") -> PASS
A5: Spread: upper 95% bound | B5: =Records!B9 -> 61.599147 | C5: =Reference_Values!B5 -> 61.599147 | D5: =ABS(B5-C5) -> 0 | E5: 1e-07 | F5: =IF(D5<=E5,"PASS","FAIL") -> PASS
A6: Spread: lower 95% bound | B6: =Records!B8 -> 42.268464 | C6: =Reference_Values!B6 -> 42.268464 | D6: =ABS(B6-C6) -> 0 | E6: 1e-07 | F6: =IF(D6<=E6,"PASS","FAIL") -> PASS
A7: Twice the record: rate bound | B7: =Records!B12 -> 0.22883798 | C7: =Reference_Values!B7 -> 0.22883798 | D7: =ABS(B7-C7) -> 0 | E7: 1e-09 | F7: =IF(D7<=E7,"PASS","FAIL") -> PASS
A8: Twice the record: spread, upper bound | B8: =Records!B13 -> 57.602817 | C8: =Reference_Values!B8 -> 57.602817 | D8: =ABS(B8-C8) -> 0 | E8: 1e-07 | F8: =IF(D8<=E8,"PASS","FAIL") -> PASS
A9: Twice the record: spread, lower bound | B9: =Records!B14 -> 44.275554 | C9: =Reference_Values!B9 -> 44.275554 | D9: =ABS(B9-C9) -> 0 | E9: 1e-07 | F9: =IF(D9<=E9,"PASS","FAIL") -> PASS
A10: The records' family: confidence together | B10: =Records!B10 -> 0.9 | C10: =Reference_Values!B10 -> 0.9 | D10: =ABS(B10-C10) -> 0 | E10: 1e-09 | F10: =IF(D10<=E10,"PASS","FAIL") -> PASS
A11: Volume I's package: cost | B11: =Family!J5 -> 10.440611 | C11: =Reference_Values!B11 -> 10.440611 | D11: =ABS(B11-C11) -> 0 | E11: 1e-09 | F11: =IF(D11<=E11,"PASS","FAIL") -> PASS
A12: Closures' doubt: cost | B12: =Family!J6 -> 11.637343 | C12: =Reference_Values!B12 -> 11.637343 | D12: =ABS(B12-C12) -> 0 | E12: 1e-09 | F12: =IF(D12<=E12,"PASS","FAIL") -> PASS
A13: Spread's doubt: cost | B13: =Family!J7 -> 22.846944 | C13: =Reference_Values!B13 -> 22.846944 | D13: =ABS(B13-C13) -> 0 | E13: 1e-09 | F13: =IF(D13<=E13,"PASS","FAIL") -> PASS
A14: The records' family: cost | B14: =Family!J8 -> 24.003233 | C14: =Reference_Values!B14 -> 24.003233 | D14: =ABS(B14-C14) -> 0 | E14: 1e-09 | F14: =IF(D14<=E14,"PASS","FAIL") -> PASS
A15: Twice the record: cost | B15: =Family!J9 -> 19.370659 | C15: =Reference_Values!B15 -> 19.370659 | D15: =ABS(B15-C15) -> 0 | E15: 1e-09 | F15: =IF(D15<=E15,"PASS","FAIL") -> PASS
A16: Price of ambiguity | B16: =Family!B11 -> 13.562622 | C16: =Reference_Values!B16 -> 13.562622 | D16: =ABS(B16-C16) -> 0 | E16: 1e-09 | F16: =IF(D16<=E16,"PASS","FAIL") -> PASS
A17: Value of a record twice as long | B17: =Family!B14 -> 4.6325741 | C17: =Reference_Values!B17 -> 4.6325741 | D17: =ABS(B17-C17) -> 0 | E17: 1e-09 | F17: =IF(D17<=E17,"PASS","FAIL") -> PASS
A18: The family's package: largest chance on the 49-law grid | B18: =100*Family!B27 -> 5 | C18: =Reference_Values!B18 -> 5 | D18: =ABS(B18-C18) -> 0 | E18: 1e-09 | F18: =IF(D18<=E18,"PASS","FAIL") -> PASS
A19: The family's package: the grid's worst law is the corner | B19: =Family!B28 -> 1 | C19: =Reference_Values!B19 -> 1 | D19: =ABS(B19-C19) -> 0 | E19: 0 | F19: =IF(D19<=E19,"PASS","FAIL") -> PASS
A20: Divergence: radius of the closures' doubt | B20: =Divergence!B5 -> 0.43857157 | C20: =Reference_Values!B20 -> 0.43857157 | D20: =ABS(B20-C20) -> 0 | E20: 1e-09 | F20: =IF(D20<=E20,"PASS","FAIL") -> PASS
A21: Divergence: radius of the spread's doubt | B21: =Divergence!B6 -> 0.60319157 | C21: =Reference_Values!B21 -> 0.60319157 | D21: =ABS(B21-C21) -> 2.3314684e-15 | E21: 1e-09 | F21: =IF(D21<=E21,"PASS","FAIL") -> PASS
A22: Divergence: radius of both doubts | B22: =Divergence!B7 -> 1.0417631 | C22: =Reference_Values!B22 -> 1.0417631 | D22: =ABS(B22-C22) -> 0 | E22: 1e-09 | F22: =IF(D22<=E22,"PASS","FAIL") -> PASS
A23: The law's appetite at the closures' radius, per million | B23: =1000000*Divergence!C5 -> 2.9265667 | C23: =Reference_Values!B23 -> 2.9265667 | D23: =ABS(B23-C23) -> 1.0835777e-13 | E23: 1e-06 | F23: =IF(D23<=E23,"PASS","FAIL") -> PASS
A24: The law's appetite at the spread's radius, per 10 million | B24: =10000000*Divergence!C6 -> 1.0875871 | C24: =Reference_Values!B24 -> 1.0875871 | D24: =ABS(B24-C24) -> 0 | E24: 1e-06 | F24: =IF(D24<=E24,"PASS","FAIL") -> PASS
A25: The law's appetite at both radii, per 100 billion | B25: =100000000000*Divergence!C7 -> 1.6868595 | C25: =Reference_Values!B25 -> 1.6868595 | D25: =ABS(B25-C25) -> 5.3734794e-14 | E25: 1e-06 | F25: =IF(D25<=E25,"PASS","FAIL") -> PASS
A26: The levers' floor: kl(0.05 || 1 path in 100,000) | B26: =Divergence!B11 -> 0.37714053 | C26: =Reference_Values!B26 -> 0.37714053 | D26: =ABS(B26-C26) -> 0 | E26: 1e-09 | F26: =IF(D26<=E26,"PASS","FAIL") -> PASS
A27: Volume I's package: worst chance over the ball of 0.001 | B27: =100*Divergence!B15 -> 6.0040821 | C27: =Reference_Values!B27 -> 6.0040821 | D27: =ABS(B27-C27) -> 0 | E27: 1e-08 | F27: =IF(D27<=E27,"PASS","FAIL") -> PASS
A28: Volume I's package: worst chance over the ball of 0.003 | B28: =100*Divergence!B16 -> 6.7751818 | C28: =Reference_Values!B28 -> 6.7751818 | D28: =ABS(B28-C28) -> 0 | E28: 1e-08 | F28: =IF(D28<=E28,"PASS","FAIL") -> PASS
A29: Volume I's package: worst chance over the ball of 0.01 | B29: =100*Divergence!B17 -> 8.3648267 | C29: =Reference_Values!B29 -> 8.3648267 | D29: =ABS(B29-C29) -> 0 | E29: 1e-08 | F29: =IF(D29<=E29,"PASS","FAIL") -> PASS
A30: Volume I's package: worst chance over the ball of 0.03 | B30: =100*Divergence!B18 -> 11.154805 | C30: =Reference_Values!B30 -> 11.154805 | D30: =ABS(B30-C30) -> 0 | E30: 1e-08 | F30: =IF(D30<=E30,"PASS","FAIL") -> PASS
A31: Volume I's package: worst chance over the ball of 0.1 | B31: =100*Divergence!B19 -> 17.294935 | C31: =Reference_Values!B31 -> 17.294935 | D31: =ABS(B31-C31) -> 0 | E31: 1e-08 | F31: =IF(D31<=E31,"PASS","FAIL") -> PASS
A32: Volume I's package: worst chance over the ball of 0.3 | B32: =100*Divergence!B20 -> 28.85192 | C32: =Reference_Values!B32 -> 28.85192 | D32: =ABS(B32-C32) -> 0 | E32: 1e-08 | F32: =IF(D32<=E32,"PASS","FAIL") -> PASS
A33: Volume I's package: worst chance over the ball of 1 | B33: =100*Divergence!B21 -> 55.551415 | C33: =Reference_Values!B33 -> 55.551415 | D33: =ABS(B33-C33) -> 0 | E33: 1e-08 | F33: =IF(D33<=E33,"PASS","FAIL") -> PASS
A34: The law's appetite for the ball of 0.001, % | B34: =100*Divergence!B26 -> 4.0848256 | C34: =Reference_Values!B34 -> 4.0848256 | D34: =ABS(B34-C34) -> 5.1514348e-14 | E34: 1e-08 | F34: =IF(D34<=E34,"PASS","FAIL") -> PASS
A35: The ball of 0.001: package cost | B35: =Divergence!G26 -> 12.194242 | C35: =Reference_Values!B35 -> 12.194242 | D35: =ABS(B35-C35) -> 0 | E35: 1e-09 | F35: =IF(D35<=E35,"PASS","FAIL") -> PASS
A36: The law's appetite for the ball of 0.002, % | B36: =100*Divergence!B27 -> 3.7401261 | C36: =Reference_Values!B36 -> 3.7401261 | D36: =ABS(B36-C36) -> 0 | E36: 1e-08 | F36: =IF(D36<=E36,"PASS","FAIL") -> PASS
A37: The ball of 0.002: package cost | B37: =Divergence!G27 -> 12.934668 | C37: =Reference_Values!B37 -> 12.934668 | D37: =ABS(B37-C37) -> 0 | E37: 1e-09 | F37: =IF(D37<=E37,"PASS","FAIL") -> PASS
A38: The law's appetite for the ball of 0.005, % | B38: =100*Divergence!B28 -> 3.1142017 | C38: =Reference_Values!B38 -> 3.1142017 | D38: =ABS(B38-C38) -> 0 | E38: 1e-08 | F38: =IF(D38<=E38,"PASS","FAIL") -> PASS
A39: The ball of 0.005: package cost | B39: =Divergence!G28 -> 14.397338 | C39: =Reference_Values!B39 -> 14.397338 | D39: =ABS(B39-C39) -> 0 | E39: 1e-09 | F39: =IF(D39<=E39,"PASS","FAIL") -> PASS
A40: The law's appetite for the ball of 0.01, % | B40: =100*Divergence!B29 -> 2.4981145 | C40: =Reference_Values!B40 -> 2.4981145 | D40: =ABS(B40-C40) -> 0 | E40: 1e-08 | F40: =IF(D40<=E40,"PASS","FAIL") -> PASS
A41: The ball of 0.01: package cost | B41: =Divergence!G29 -> 16.081219 | C41: =Reference_Values!B41 -> 16.081219 | D41: =ABS(B41-C41) -> 0 | E41: 1e-09 | F41: =IF(D41<=E41,"PASS","FAIL") -> PASS
A42: The law's appetite for the ball of 0.02, % | B42: =100*Divergence!B30 -> 1.7786384 | C42: =Reference_Values!B42 -> 1.7786384 | D42: =ABS(B42-C42) -> 0 | E42: 1e-08 | F42: =IF(D42<=E42,"PASS","FAIL") -> PASS
A43: The ball of 0.02: package cost | B43: =Divergence!G30 -> 18.766546 | C43: =Reference_Values!B43 -> 18.766546 | D43: =ABS(B43-C43) -> 0 | E43: 1e-09 | F43: =IF(D43<=E43,"PASS","FAIL") -> PASS
A44: The law's appetite for the ball of 0.03, % | B44: =100*Divergence!B31 -> 1.3373251 | C44: =Reference_Values!B44 -> 1.3373251 | D44: =ABS(B44-C44) -> 0 | E44: 1e-08 | F44: =IF(D44<=E44,"PASS","FAIL") -> PASS
A45: The ball of 0.03: package cost | B45: =Divergence!G31 -> 20.891877 | C45: =Reference_Values!B45 -> 20.891877 | D45: =ABS(B45-C45) -> 0 | E45: 1e-09 | F45: =IF(D45<=E45,"PASS","FAIL") -> PASS
A46: The law's appetite for the ball of 0.05, % | B46: =100*Divergence!B32 -> 0.81010838 | C46: =Reference_Values!B46 -> 0.81010838 | D46: =ABS(B46-C46) -> 5.3290705e-15 | E46: 1e-08 | F46: =IF(D46<=E46,"PASS","FAIL") -> PASS
A47: The ball of 0.05: package cost | B47: =Divergence!G32 -> 24.700063 | C47: =Reference_Values!B47 -> 24.700063 | D47: =ABS(B47-C47) -> 0 | E47: 1e-09 | F47: =IF(D47<=E47,"PASS","FAIL") -> PASS
A48: The law's appetite for the ball of 0.075, % | B48: =100*Divergence!B33 -> 0.45949388 | C48: =Reference_Values!B48 -> 0.45949388 | D48: =ABS(B48-C48) -> 1.9984014e-15 | E48: 1e-08 | F48: =IF(D48<=E48,"PASS","FAIL") -> PASS
A49: The ball of 0.075: package cost | B49: =Divergence!G33 -> 28.348214 | C49: =Reference_Values!B49 -> 28.348214 | D49: =ABS(B49-C49) -> 0 | E49: 1e-09 | F49: =IF(D49<=E49,"PASS","FAIL") -> PASS
A50: The law's appetite for the ball of 0.1, % | B50: =100*Divergence!B34 -> 0.26874158 | C50: =Reference_Values!B50 -> 0.26874158 | D50: =ABS(B50-C50) -> 2.0539126e-15 | E50: 1e-08 | F50: =IF(D50<=E50,"PASS","FAIL") -> PASS
A51: The ball of 0.1: package cost | B51: =Divergence!G34 -> 31.385406 | C51: =Reference_Values!B51 -> 31.385406 | D51: =ABS(B51-C51) -> 0 | E51: 1e-09 | F51: =IF(D51<=E51,"PASS","FAIL") -> PASS
A52: The law's appetite for the ball of 0.15, % | B52: =100*Divergence!B35 -> 0.095660434 | C52: =Reference_Values!B52 -> 0.095660434 | D52: =ABS(B52-C52) -> 1.1241008e-15 | E52: 1e-08 | F52: =IF(D52<=E52,"PASS","FAIL") -> PASS
A53: The ball of 0.15: package cost | B53: =Divergence!G35 -> 38.005913 | C53: =Reference_Values!B53 -> 38.005913 | D53: =ABS(B53-C53) -> 0 | E53: 1e-09 | F53: =IF(D53<=E53,"PASS","FAIL") -> PASS
A54: kl at the engine's worst chances, largest |kl - d| | B54: =MAX(ABS(MIN(Divergence!D15:D21)),ABS(MAX(Divergence!D15:D21))) -> 3.989864e-17 | C54: =Reference_Values!B54 -> 0 | D54: =ABS(B54-C54) -> 3.989864e-17 | E54: 1e-09 | F54: =IF(D54<=E54,"PASS","FAIL") -> PASS
A55: kl at the engine's appetites, largest |kl - d| | B55: =MAX(ABS(MIN(Divergence!D26:D35)),ABS(MAX(Divergence!D26:D35))) -> 5.7245875e-17 | C55: =Reference_Values!B55 -> 0 | D55: =ABS(B55-C55) -> 5.7245875e-17 | E55: 1e-09 | F55: =IF(D55<=E55,"PASS","FAIL") -> PASS
A56: The paths that must keep the average margin, K | B56: =Wasserstein!B4 -> 5000 | C56: =Reference_Values!B56 -> 5000 | D56: =ABS(B56-C56) -> 0 | E56: 0 | F56: =IF(D56<=E56,"PASS","FAIL") -> PASS
A57: Wasserstein $0.01m: the thinnest 5% average eps / 0.05 | B57: =Wasserstein!B7 -> 0.2 | C57: =Reference_Values!B57 -> 0.2 | D57: =ABS(B57-C57) -> 6.7315431e-10 | E57: 1e-06 | F57: =IF(D57<=E57,"PASS","FAIL") -> PASS
A58: Wasserstein $0.01m: package cost | B58: =Wasserstein!G7 -> 11.565713 | C58: =Reference_Values!B58 -> 11.565713 | D58: =ABS(B58-C58) -> 0 | E58: 1e-09 | F58: =IF(D58<=E58,"PASS","FAIL") -> PASS
A59: Wasserstein $0.02m: the thinnest 5% average eps / 0.05 | B59: =Wasserstein!B8 -> 0.4 | C59: =Reference_Values!B59 -> 0.4 | D59: =ABS(B59-C59) -> 1.4260227e-09 | E59: 1e-06 | F59: =IF(D59<=E59,"PASS","FAIL") -> PASS
A60: Wasserstein $0.02m: package cost | B60: =Wasserstein!G8 -> 12.042158 | C60: =Reference_Values!B60 -> 12.042158 | D60: =ABS(B60-C60) -> 0 | E60: 1e-09 | F60: =IF(D60<=E60,"PASS","FAIL") -> PASS
A61: Wasserstein $0.05m: the thinnest 5% average eps / 0.05 | B61: =Wasserstein!B9 -> 1 | C61: =Reference_Values!B61 -> 1 | D61: =ABS(B61-C61) -> 9.3200003e-10 | E61: 1e-06 | F61: =IF(D61<=E61,"PASS","FAIL") -> PASS
A62: Wasserstein $0.05m: package cost | B62: =Wasserstein!G9 -> 13.004771 | C62: =Reference_Values!B62 -> 13.004771 | D62: =ABS(B62-C62) -> 0 | E62: 1e-09 | F62: =IF(D62<=E62,"PASS","FAIL") -> PASS
A63: Wasserstein $0.1m: the thinnest 5% average eps / 0.05 | B63: =Wasserstein!B10 -> 2 | C63: =Reference_Values!B63 -> 2 | D63: =ABS(B63-C63) -> 2.1312609e-09 | E63: 1e-06 | F63: =IF(D63<=E63,"PASS","FAIL") -> PASS
A64: Wasserstein $0.1m: package cost | B64: =Wasserstein!G10 -> 14.134361 | C64: =Reference_Values!B64 -> 14.134361 | D64: =ABS(B64-C64) -> 0 | E64: 1e-09 | F64: =IF(D64<=E64,"PASS","FAIL") -> PASS
A65: Wasserstein $0.2m: the thinnest 5% average eps / 0.05 | B65: =Wasserstein!B11 -> 4 | C65: =Reference_Values!B65 -> 4 | D65: =ABS(B65-C65) -> 7.3310336e-10 | E65: 1e-06 | F65: =IF(D65<=E65,"PASS","FAIL") -> PASS
A66: Wasserstein $0.2m: package cost | B66: =Wasserstein!G11 -> 15.781055 | C66: =Reference_Values!B66 -> 15.781055 | D66: =ABS(B66-C66) -> 0 | E66: 1e-09 | F66: =IF(D66<=E66,"PASS","FAIL") -> PASS
A67: Wasserstein $0.5m: the thinnest 5% average eps / 0.05 | B67: =Wasserstein!B12 -> 10 | C67: =Reference_Values!B67 -> 10 | D67: =ABS(B67-C67) -> 4.6319393e-09 | E67: 1e-06 | F67: =IF(D67<=E67,"PASS","FAIL") -> PASS
A68: Wasserstein $0.5m: package cost | B68: =Wasserstein!G12 -> 19.335974 | C68: =Reference_Values!B68 -> 19.335974 | D68: =ABS(B68-C68) -> 0 | E68: 1e-09 | F68: =IF(D68<=E68,"PASS","FAIL") -> PASS
A69: Wasserstein $1m: the thinnest 5% average eps / 0.05 | B69: =Wasserstein!B13 -> 20 | C69: =Reference_Values!B69 -> 20 | D69: =ABS(B69-C69) -> 1.8595969e-10 | E69: 1e-06 | F69: =IF(D69<=E69,"PASS","FAIL") -> PASS
A70: Wasserstein $1m: package cost | B70: =Wasserstein!G13 -> 23.94635 | C70: =Reference_Values!B70 -> 23.94635 | D70: =ABS(B70-C70) -> 0 | E70: 1e-09 | F70: =IF(D70<=E70,"PASS","FAIL") -> PASS
A71: The spread's excess, c - 1 | B71: =Wasserstein!B16 -> 0.23198294 | C71: =Reference_Values!B71 -> 0.23198294 | D71: =ABS(B71-C71) -> 0 | E71: 1e-09 | F71: =IF(D71<=E71,"PASS","FAIL") -> PASS
A72: The radius that holds the spread's doubt | B72: =Wasserstein!B18 -> 26.267874 | C72: =Reference_Values!B72 -> 26.267874 | D72: =ABS(B72-C72) -> 0 | E72: 1e-07 | F72: =IF(D72<=E72,"PASS","FAIL") -> PASS
A73: The thinnest 5% would need | B73: =Wasserstein!B19 -> 525.35748 | C73: =Reference_Values!B73 -> 525.35748 | D73: =ABS(B73-C73) -> 0 | E73: 1e-06 | F73: =IF(D73<=E73,"PASS","FAIL") -> PASS
A74: Cantelli bound, quarter 1 | B74: =100*Moments!G5 -> 4.5681213 | C74: =Reference_Values!B74 -> 4.5681213 | D74: =ABS(B74-C74) -> 0 | E74: 1e-09 | F74: =IF(D74<=E74,"PASS","FAIL") -> PASS
A75: Cantelli bound, quarter 2 | B75: =100*Moments!G6 -> 7.9515845 | C75: =Reference_Values!B75 -> 7.9515845 | D75: =ABS(B75-C75) -> 0 | E75: 1e-09 | F75: =IF(D75<=E75,"PASS","FAIL") -> PASS
A76: Cantelli bound, quarter 3 | B76: =100*Moments!G7 -> 10.674663 | C76: =Reference_Values!B76 -> 10.674663 | D76: =ABS(B76-C76) -> 0 | E76: 1e-09 | F76: =IF(D76<=E76,"PASS","FAIL") -> PASS
A77: Cantelli bound, quarter 4 | B77: =100*Moments!G8 -> 12.887055 | C77: =Reference_Values!B77 -> 12.887055 | D77: =ABS(B77-C77) -> 0 | E77: 1e-09 | F77: =IF(D77<=E77,"PASS","FAIL") -> PASS
A78: Cantelli bound, quarter 5 | B78: =100*Moments!G9 -> 14.39143 | C78: =Reference_Values!B78 -> 14.39143 | D78: =ABS(B78-C78) -> 0 | E78: 1e-09 | F78: =IF(D78<=E78,"PASS","FAIL") -> PASS
A79: Cantelli bound, quarter 6 | B79: =100*Moments!G10 -> 15.209219 | C79: =Reference_Values!B79 -> 15.209219 | D79: =ABS(B79-C79) -> 0 | E79: 1e-09 | F79: =IF(D79<=E79,"PASS","FAIL") -> PASS
A80: Cantelli bound, quarter 7 | B80: =100*Moments!G11 -> 15.378304 | C80: =Reference_Values!B80 -> 15.378304 | D80: =ABS(B80-C80) -> 0 | E80: 1e-09 | F80: =IF(D80<=E80,"PASS","FAIL") -> PASS
A81: Cantelli bound, quarter 8 | B81: =100*Moments!G12 -> 15.047026 | C81: =Reference_Values!B81 -> 15.047026 | D81: =ABS(B81-C81) -> 0 | E81: 1e-09 | F81: =IF(D81<=E81,"PASS","FAIL") -> PASS
A82: Cantelli bound, quarter 9 | B82: =100*Moments!G13 -> 14.490356 | C82: =Reference_Values!B82 -> 14.490356 | D82: =ABS(B82-C82) -> 0 | E82: 1e-09 | F82: =IF(D82<=E82,"PASS","FAIL") -> PASS
A83: Cantelli bound, quarter 10 | B83: =100*Moments!G14 -> 13.603994 | C83: =Reference_Values!B83 -> 13.603994 | D83: =ABS(B83-C83) -> 0 | E83: 1e-09 | F83: =IF(D83<=E83,"PASS","FAIL") -> PASS
A84: Cantelli bound, quarter 11 | B84: =100*Moments!G15 -> 12.680372 | C84: =Reference_Values!B84 -> 12.680372 | D84: =ABS(B84-C84) -> 0 | E84: 1e-09 | F84: =IF(D84<=E84,"PASS","FAIL") -> PASS
A85: Cantelli bound, quarter 12 | B85: =100*Moments!G16 -> 11.751534 | C85: =Reference_Values!B85 -> 11.751534 | D85: =ABS(B85-C85) -> 0 | E85: 1e-09 | F85: =IF(D85<=E85,"PASS","FAIL") -> PASS
A86: Cantelli: the worst quarter | B86: =Moments!B18 -> 7 | C86: =Reference_Values!B86 -> 7 | D86: =ABS(B86-C86) -> 0 | E86: 0 | F86: =IF(D86<=E86,"PASS","FAIL") -> PASS
A87: Cantelli: the bounds' sum, % | B87: =100*Moments!B22 -> 148.63366 | C87: =Reference_Values!B87 -> 148.63366 | D87: =ABS(B87-C87) -> 0 | E87: 1e-09 | F87: =IF(D87<=E87,"PASS","FAIL") -> PASS
A88: Spreads of margin at 5 percent | B88: =Moments!B24 -> 4.3588989 | C88: =Reference_Values!B88 -> 4.3588989 | D88: =ABS(B88-C88) -> 0 | E88: 1e-12 | F88: =IF(D88<=E88,"PASS","FAIL") -> PASS
A89: Spreads the union bound would need | B89: =Moments!B25 -> 15.459625 | C89: =Reference_Values!B89 -> 15.459625 | D89: =ABS(B89-C89) -> 0 | E89: 1e-12 | F89: =IF(D89<=E89,"PASS","FAIL") -> PASS
A90: The moment package: delay | B90: =Moments!B28 -> 6.0618333 | C90: =Reference_Values!B90 -> 6.0618333 | D90: =ABS(B90-C90) -> 0 | E90: 1e-09 | F90: =IF(D90<=E90,"PASS","FAIL") -> PASS
A91: The moment package: cost | B91: =Moments!B29 -> 53.294667 | C91: =Reference_Values!B91 -> 53.294667 | D91: =ABS(B91-C91) -> 0 | E91: 1e-09 | F91: =IF(D91<=E91,"PASS","FAIL") -> PASS
A92: The two-point law keeps the mean of quarter 7 | B92: =Moments!B21 -> 147.47721 | C92: =Reference_Values!B92 -> 147.47721 | D92: =ABS(B92-C92) -> 0 | E92: 1e-09 | F92: =IF(D92<=E92,"PASS","FAIL") -> PASS
A93: Table 11.3, One law (Chapter 9): cost | B93: =PriceTheDoubt!D5 -> 10.440611 | C93: =Reference_Values!B93 -> 10.440611 | D93: =ABS(B93-C93) -> 0 | E93: 1e-09 | F93: =IF(D93<=E93,"PASS","FAIL") -> PASS
A94: Table 11.3, A set, max-min choice (Chapter 10): cost | B94: =PriceTheDoubt!D6 -> 10.542932 | C94: =Reference_Values!B94 -> 10.542932 | D94: =ABS(B94-C94) -> 0 | E94: 1e-09 | F94: =IF(D94<=E94,"PASS","FAIL") -> PASS
A95: Table 11.3, Wasserstein ball, $0.1 million: cost | B95: =PriceTheDoubt!D7 -> 14.134361 | C95: =Reference_Values!B95 -> 14.134361 | D95: =ABS(B95-C95) -> 0 | E95: 1e-09 | F95: =IF(D95<=E95,"PASS","FAIL") -> PASS
A96: Table 11.3, Divergence ball, d = 0.01: cost | B96: =PriceTheDoubt!D8 -> 16.081219 | C96: =Reference_Values!B96 -> 16.081219 | D96: =ABS(B96-C96) -> 0 | E96: 1e-09 | F96: =IF(D96<=E96,"PASS","FAIL") -> PASS
A97: Table 11.3, Closures' doubt (rate <= 0.315): cost | B97: =PriceTheDoubt!D9 -> 11.637343 | C97: =Reference_Values!B97 -> 11.637343 | D97: =ABS(B97-C97) -> 0 | E97: 1e-09 | F97: =IF(D97<=E97,"PASS","FAIL") -> PASS
A98: Table 11.3, Spread's doubt (spread <= 61.6): cost | B98: =PriceTheDoubt!D10 -> 22.846944 | C98: =Reference_Values!B98 -> 22.846944 | D98: =ABS(B98-C98) -> 0 | E98: 1e-09 | F98: =IF(D98<=E98,"PASS","FAIL") -> PASS
A99: Table 11.3, The records' family (both): cost | B99: =PriceTheDoubt!D11 -> 24.003233 | C99: =Reference_Values!B99 -> 24.003233 | D99: =ABS(B99-C99) -> 0 | E99: 1e-09 | F99: =IF(D99<=E99,"PASS","FAIL") -> PASS
A100: Table 11.3, Records twice as long: cost | B100: =PriceTheDoubt!D12 -> 19.370659 | C100: =Reference_Values!B100 -> 19.370659 | D100: =ABS(B100-C100) -> 0 | E100: 1e-09 | F100: =IF(D100<=E100,"PASS","FAIL") -> PASS
...
