Workbook

Sheet README
B1: DCT Laboratory — Vol I, Ch 5: Enterprise State Representation
B2: Seed 26105 · Companion to DCT_V1_Ch05_Lab.ipynb and AXIOM Lab 1.5 (module AXIOM-05). Money in $ million; liquidity also as an index, today = 100 = $620 million.
B4: Worked Example 5.1, Where Does the Turnaround Settle?, with the book's declarations, and the five steps of AXIOM Lab 1.5, Meridian's Room to Maneuver.
B5: Declarations: Meridian's declared state (Table 5.2), the walls with numbers (Table 5.4), Chapter 1's model (Online Appendix 1.B.4, Table 1.B.1) and its scorecard.
B6: State: the eight readings with their types, tags and scaled errors; the attrition rate's switch from parameter to state variable (lab step 1).
B7: Walls: slack on every wall today, at the digital low point (Newton's method) and at its tightest along each option's five-year path, month by month (Proposition 5.5; Figure 5.4; lab step 2).
B8: Blend: two configurations under a capacity budget and a minimum efficient scale (Theorem 5.2(iii); Figure 5.1), and a covenant written weakly and strictly (Theorem 5.5).
B9: PathSampling: the digital liquidity path stepped quarterly and half-yearly with its exact flow map, its two phases joined, and the steps undone (Propositions 5.3-5.4; Figure 5.2; lab step 3).
B10: Turnaround: the annual map, the contraction constant, the day-one bound and Table 5.5, and the same map from two other starting states (Theorem 5.4(i); Equation 5.1; Worked Example 5.1; lab step 4).
B11: Equilibria: the start-up, the unstable middle and the service operation of Online Appendix 5.B.4-5.B.7.
B12: Profiles: today and the Year-5 states on Chapter 3's scale, the distance readout, and the volume of a ball in a cube (Figure 5.5; Section 5.8; lab step 5).
B13: Every result is a formula of the declarations. Reference_Values and Checks: the notebook engine's numbers and a PASS/FAIL comparison with this workbook's formulas.
... B19: Cross-sheet link: green.

Sheet Declarations
A1: Declarations (Tables 5.2 and 5.4; Chapter 1's model, Online Appendix 1.B.4). Money in $ million; liquidity also as an index, today = 100.
A3: x | B3: Reading | C3: Today | D3: Unit | E3: Type (Table 5.1) | F3: Measured by | G3: Error as printed | H3: Error in the reading's unit | I3: Chapter 3 scale | J3: Tag (Part III)
A4: x1 | B4: liquidity | C4: 100 | D4: index, today = 100 = $620 million (US$ billion in Table 5.2) | E4: stock | F4: treasury systems | G4: +/-1% | H4: =0.01*C4 -> 1 | I4: =C4 -> 100 | J4: ECA
A5: x2 | B5: net leverage | C5: 3.4 | D5: ND/EBITDA | E5: ratio | F5: audited accounts | G5: +/-2% | H5: =0.02*C5 -> 0.068 | I5: =C5 -> 3.4 | J5: ECA
A6: x3 | B6: workforce capability | C6: 58 | D6: 0-100 | E6: index | F6: skills survey | G6: +/-5 | H6: 5 | I6: 100 | J6: ECA
A7: x4 | B7: technology platform | C7: 41 | D7: 0-100 | E7: index | F7: architecture audit | G7: +/-4 | H7: 4 | I7: 100 | J7: ECA
A8: x5 | B8: operational efficiency | C8: 71 | D8: 0-100 | E8: index | F8: cost benchmarking | G8: +/-3 | H8: 3 | I8: 100 | J8: EPA
A9: x6 | B9: ROIC | C9: 0.083 | D9: ratio | E9: ratio | F9: audited accounts | G9: +/-0.4 pp | H9: 0.004 | I9: =C9 -> 0.083 | J9: EPA
A10: x7 | B10: strategic risk (lower is better) | C10: 64 | D10: 0-100 | E10: index | F10: risk committee | G10: +/-6 | H10: 6 | I10: 100 | J10: ERRA
A11: x8 | B11: market share | C11: 0.19 | D11: ratio | E11: ratio | F11: industry data | G11: +/-0.8 pp | H11: 0.008 | I11: =C11 -> 0.19 | J11: EPA
A13: Quantity | C13: Value | E13: Declared in
A14: Liquidity today ($ million) | C14: 620 | E14: Table 5.2; Chapter 3, Table 3.1: $0.62 billion
A15: $ million per liquidity point | C15: =C14/C4 -> 6.2 | E15: today = 100 = $620 million
A16: Board liquidity floor ($ million) | C16: 350 | E16: Table 5.4: policy, $0.35 billion
A17: The floor as a liquidity index | C17: =C16/C15 -> 56.451613
A18: Loan covenant: net leverage at most | C18: 4.5 | E18: Table 5.4: regulatory and contractual
A19: Strategic-risk ceiling | C19: 75 | E19: Table 5.4: policy
A20: Indices: lowest | C20: 0 | E20: Table 5.4: definitional
A21: Indices: highest | C21: 100 | E21: Table 5.4: definitional
A22: Shares: lowest | C22: 0 | E22: Table 5.4: definitional
A23: Shares: highest | C23: 1 | E23: Table 5.4: definitional
A24: The restructuring's sale closes at t (years) | C24: 1 | E24: Online Appendix 1.B.4
A26: Option | B26: Reading | C26: Target | D26: Speed k (a year) | E26: Trough (sign x depth) | F26: Trough time tau | G26: Jump at the sale
A27: Digital | B27: liquidity | C27: 112 | D27: 0.35 | E27: -28 | F27: 2 | G27: 0
B28: technology | C28: 78 | D28: 0.55 | E28: 0 | F28: 1 | G28: 0
B29: efficiency | C29: 77 | D29: 0.5 | E29: -9 | F29: 1.5 | G29: 0
B30: strategic risk | C30: 51 | D30: 0.4 | E30: 14 | F30: 1.2 | G30: 0
A31: Restructuring | B31: liquidity | C31: 104 | D31: 0.3 | E31: 0 | F31: 1 | G31: 18
B32: technology | C32: 38 | D32: 0.25 | E32: 0 | F32: 1 | G32: 0
B33: efficiency | C33: 74 | D33: 0.45 | E33: 0 | F33: 1 | G33: 0
B34: strategic risk | C34: 56 | D34: 0.35 | E34: 0 | F34: 1 | G34: -8
A35: Turnaround | B35: liquidity | C35: 106 | D35: 0.45 | E35: 0 | F35: 1 | G35: 0
B36: technology | C36: 33 | D36: 0.2 | E36: 0 | F36: 1 | G36: 0
B37: efficiency | C37: 79 | D37: 0.6 | E37: 0 | F37: 1 | G37: 0
B38: strategic risk | C38: 67 | D38: 0.3 | E38: 0 | F38: 1 | G38: 0
A39: Table 1.B.1 (Online Appendix 1.B.4), Equation 1.B.1; a blank trough is 0 (its time is then unused). The turnaround is Worked Example 5.1's: targets 106, 33, 79, 67.
A41: Chapter 1's scorecard | C41: Weight
A42: liquidity | C42: 0.25
A43: technology platform | C43: 0.25
A44: operational efficiency | C44: 0.25
A45: strategic risk (subtracted) | C45: -0.25
A47: The attrition rate (Table 5.1: a parameter) | C47: Value | E47: Declared in
A48: Attrition a year: lowest | C48: 0.06 | E48: Chapter 4, Table 4.3: talent attrition 6-11 percent a year
A49: Attrition a year: highest | C49: 0.11 | E49: Chapter 4, Table 4.3: talent attrition 6-11 percent a year

Sheet State
A1: Declare the state: Meridian's eight readings (Tables 5.1-5.2; Definitions 5.2-5.3; AXIOM Lab 1.5, step 1)
A2: Chapter 3's scale divides indices by their range of 100 and the other readings by today's value; the scaled error puts the error bars on one footing.
A3: x | B3: Reading | C3: Today | D3: Type (Table 5.1) | E3: Tag (Part III) | F3: Error in the reading's unit | G3: Chapter 3 scale | H3: Scaled error
A4: x1 | B4: =Declarations!B4 -> liquidity | C4: =Declarations!C4 -> 100 | D4: =Declarations!E4 -> stock | E4: =Declarations!J4 -> ECA | F4: =Declarations!H4 -> 1 | G4: =Declarations!I4 -> 100 | H4: =F4/G4 -> 0.01
A5: x2 | B5: =Declarations!B5 -> net leverage | C5: =Declarations!C5 -> 3.4 | D5: =Declarations!E5 -> ratio | E5: =Declarations!J5 -> ECA | F5: =Declarations!H5 -> 0.068 | G5: =Declarations!I5 -> 3.4 | H5: =F5/G5 -> 0.02
A6: x3 | B6: =Declarations!B6 -> workforce capability | C6: =Declarations!C6 -> 58 | D6: =Declarations!E6 -> index | E6: =Declarations!J6 -> ECA | F6: =Declarations!H6 -> 5 | G6: =Declarations!I6 -> 100 | H6: =F6/G6 -> 0.05
A7: x4 | B7: =Declarations!B7 -> technology platform | C7: =Declarations!C7 -> 41 | D7: =Declarations!E7 -> index | E7: =Declarations!J7 -> ECA | F7: =Declarations!H7 -> 4 | G7: =Declarations!I7 -> 100 | H7: =F7/G7 -> 0.04
A8: x5 | B8: =Declarations!B8 -> operational efficiency | C8: =Declarations!C8 -> 71 | D8: =Declarations!E8 -> index | E8: =Declarations!J8 -> EPA | F8: =Declarations!H8 -> 3 | G8: =Declarations!I8 -> 100 | H8: =F8/G8 -> 0.03
A9: x6 | B9: =Declarations!B9 -> ROIC | C9: =Declarations!C9 -> 0.083 | D9: =Declarations!E9 -> ratio | E9: =Declarations!J9 -> EPA | F9: =Declarations!H9 -> 0.004 | G9: =Declarations!I9 -> 0.083 | H9: =F9/G9 -> 0.048192771
A10: x7 | B10: =Declarations!B10 -> strategic risk (lower is better) | C10: =Declarations!C10 -> 64 | D10: =Declarations!E10 -> index | E10: =Declarations!J10 -> ERRA | F10: =Declarations!H10 -> 6 | G10: =Declarations!I10 -> 100 | H10: =F10/G10 -> 0.06
A11: x8 | B11: =Declarations!B11 -> market share | C11: =Declarations!C11 -> 0.19 | D11: =Declarations!E11 -> ratio | E11: =Declarations!J11 -> EPA | F11: =Declarations!H11 -> 0.008 | G11: =Declarations!I11 -> 0.19 | H11: =F11/G11 -> 0.042105263
A13: Readings in the declared state | B13: =COUNTA(B4:B11) -> 8
A14: Stocks | B14: =COUNTIF(D4:D11,"stock") -> 1
A15: Ratios | B15: =COUNTIF(D4:D11,"ratio") -> 3
A16: Indices | B16: =COUNTIF(D4:D11,"index") -> 4
A17: Capital readings (ECA) | B17: =COUNTIF(E4:E11,"ECA") -> 4
A18: Performance readings (EPA) | B18: =COUNTIF(E4:E11,"EPA") -> 3
A19: Risk readings (ERRA) | B19: =COUNTIF(E4:E11,"ERRA") -> 1
A20: Widest scaled error | B20: =MAX(H4:H11) -> 0.06 | C20: =INDEX(B4:B11,MATCH(B20,H4:H11,0)) -> strategic risk (lower is better)
A21: Second widest scaled error | B21: =LARGE(H4:H11,2) -> 0.05 | C21: =INDEX(B4:B11,MATCH(B21,H4:H11,0)) -> workforce capability
A23: The switch: promote the attrition rate to a state variable | B23: Value
A24: Dimension before the switch | B24: =B13 -> 8
A25: Dimension after the switch | B25: =B13+1 -> 9
A26: Attrition a year: declared lowest | B26: =Attr_lo -> 0.06
A27: Attrition a year: declared highest | B27: =Attr_hi -> 0.11
A28: Chapter 1's model reads no attrition rate, so the eight readings' paths are the same from either end of its range (Walls), and the ninth coordinate stays where it starts: at a five-year horizon it is a parameter (Table 5.1). By Theorem 5.1 it earns a place in the state only in a model whose future depends on it.

Sheet Walls
A1: Build the walls: slack on every wall of Table 5.4, today, at the digital low point and along each option's path (Proposition 5.5; Figure 5.4; AXIOM Lab 1.5, step 2)
A2: Slack is the room left before a wall, in the wall's unit; zero means the wall binds. Chapter 1's model moves liquidity, technology, efficiency and strategic risk; leverage, workforce, ROIC and market share stay at today's values, so the covenant's slack is held.
A4: Wall (Table 5.4) | B4: Type | C4: Unit | D4: Today | E4: Digital low point | F4: Tightest: digital | G4: Month | H4: Tightest: restructuring | I4: Month | J4: Tightest: turnaround | K4: Month
A5: Liquidity at least zero | B5: physical | C5: $ million | D5: =Liq_today*USD_pt -> 620 | E5: =$J$21 -> 481.91794 | F5: =MIN($O$45:$O$105) -> 481.95038 | G5: =INDEX($A$45:$A$105,MATCH(F5,$O$45:$O$105,0)) -> 21 | H5: =MIN($S$45:$S$105) -> 620 | I5: =INDEX($A$45:$A$105,MATCH(H5,$S$45:$S$105,0)) -> 0 | J5: =MIN($W$45:$W$105) -> 620 | K5: =INDEX($A$45:$A$105,MATCH(J5,$W$45:$W$105,0)) -> 0
A6: Board floor: liquidity at least $350 million | B6: policy | C6: $ million | D6: =Liq_today*USD_pt-Floor_usd -> 270 | E6: =$J$21-Floor_usd -> 131.91794 | F6: =MIN($P$45:$P$105) -> 131.95038 | G6: =INDEX($A$45:$A$105,MATCH(F6,$P$45:$P$105,0)) -> 21 | H6: =MIN($T$45:$T$105) -> 270 | I6: =INDEX($A$45:$A$105,MATCH(H6,$T$45:$T$105,0)) -> 0 | J6: =MIN($X$45:$X$105) -> 270 | K6: =INDEX($A$45:$A$105,MATCH(J6,$X$45:$X$105,0)) -> 0
A7: Covenant: net leverage at most 4.5 | B7: regulatory and contractual | C7: turns | D7: =Covenant-Lev_today -> 1.1 | E7: =Covenant-Lev_today -> 1.1 | F7: =D7 -> 1.1 | G7: held | H7: =D7 -> 1.1 | I7: held | J7: =D7 -> 1.1 | K7: held
A8: Risk ceiling: strategic risk at most 75 | B8: policy | C8: points | D8: =Risk_ceiling-Risk_today -> 11 | E8: =Risk_ceiling-(Declarations!$C$30+(Declarations!$C$10-Declarations!$C$30)*EXP(-Declarations!$D$30*$B$19)+IF(Declarations!$E$30=0,0,Declarations!$E$30*($B$19/Declarations!$F$30)*EXP(1-$B$19/Declarations!$F$30))+IF($B$19>=T_sale,Declarations!$G$30,0)) -> 4.4242054 | F8: =MIN($Q$45:$Q$105) -> 1.4479365 | G8: =INDEX($A$45:$A$105,MATCH(F8,$Q$45:$Q$105,0)) -> 11 | H8: =MIN($U$45:$U$105) -> 11 | I8: =INDEX($A$45:$A$105,MATCH(H8,$U$45:$U$105,0)) -> 0 | J8: =MIN($Y$45:$Y$105) -> 8.6693905 | K8: =INDEX($A$45:$A$105,MATCH(J8,$Y$45:$Y$105,0)) -> 60
A9: Indices between 0 and 100 | B9: definitional | C9: points | D9: =MIN(Wf_today-Idx_lo,Idx_hi-Wf_today,Tech_today-Idx_lo,Idx_hi-Tech_today,Eff_today-Idx_lo,Idx_hi-Eff_today,Risk_today-Idx_lo,Idx_hi-Risk_today) -> 29 | E9: =MIN(Wf_today-Idx_lo,Idx_hi-Wf_today,(Declarations!$C$28+(Declarations!$C$7-Declarations!$C$28)*EXP(-Declarations!$D$28*$B$19)+IF(Declarations!$E$28=0,0,Declarations!$E$28*($B$19/Declarations!$F$28)*EXP(1-$B$19/Declarations!$F$28))+IF($B$19>=T_sale,Declarations!$G$28,0))-Idx_lo,Idx_hi-(Declarations!$C$28+(Declarations!$C$7-Declarations!$C$28)*EXP(-Declarations!$D$28*$B$19)+IF(Declarations!$E$28=0,0,Declarations!$E$28*($B$19/Declarations!$F$28)*EXP(1-$B$19/Declarations!$F$28))+IF($B$19>=T_sale,Declarations!$G$28,0)),(Declarations!$C$29+(Declarations!$C$8-Declarations!$C$29)*EXP(-Declarations!$D$29*$B$19)+IF(Declarations!$E$29=0,0,Declarations!$E$29*($B$19/Declarations!$F$29)*EXP(1-$B$19/Declarations!$F$29))+IF($B$19>=T_sale,Declarations!$G$29,0))-Idx_lo,Idx_hi-(Declarations!$C$29+(Declarations!$C$8-Declarations!$C$29)*EXP(-Declarations!$D$29*$B$19)+IF(Declarations!$E$29=0,0,Declarations!$E$29*($B$19/Declarations!$F$29)*EXP(1-$B$19/Declarations!$F$29))+IF($B$19>=T_sale,Declarations!$G$29,0)),(Declarations!$C$30+(Declarations!$C$10-Declarations!$C$30)*EXP(-Declarations!$D$30*$B$19)+IF(Declarations!$E$30=0,0,Declarations!$E$30*($B$19/Declarations!$F$30)*EXP(1-$B$19/Declarations!$F$30))+IF($B$19>=T_sale,Declarations!$G$30,0))-Idx_lo,Idx_hi-(Declarations!$C$30+(Declarations!$C$10-Declarations!$C$30)*EXP(-Declarations!$D$30*$B$19)+IF(Declarations!$E$30=0,0,Declarations!$E$30*($B$19/Declarations!$F$30)*EXP(1-$B$19/Declarations!$F$30))+IF($B$19>=T_sale,Declarations!$G$30,0))) -> 29.424205 | F9: =MIN($R$45:$R$105) -> 24.365331 | G9: =INDEX($A$45:$A$105,MATCH(F9,$R$45:$R$105,0)) -> 60 | H9: =MIN($V$45:$V$105) -> 26.316198 | I9: =INDEX($A$45:$A$105,MATCH(H9,$V$45:$V$105,0)) -> 60 | J9: =MIN($Z$45:$Z$105) -> 21.398297 | K9: =INDEX($A$45:$A$105,MATCH(J9,$Z$45:$Z$105,0)) -> 60
A10: Shares between 0 and 1 | B10: definitional | C10: share | D10: =MIN(Share_today-Shr_lo,Shr_hi-Share_today) -> 0.19 | E10: =MIN(Share_today-Shr_lo,Shr_hi-Share_today) -> 0.19 | F10: =D10 -> 0.19 | G10: held | H10: =D10 -> 0.19 | I10: held | J10: =D10 -> 0.19 | K10: held
A11: Walls binding (slack zero) | D11: =SUMPRODUCT(--(ABS(D5:D10)<0.000000001)) -> 0 | E11: =SUMPRODUCT(--(ABS(E5:E10)<0.000000001)) -> 0
A13: The digital low point: Newton's method on the slope of liquidity | B13: t (years) | C13: slope x'(t) | D13: curvature x''(t) | E13: reading x(t)
A14: iteration 0 (start: month 21) | B14: 1.75 | C14: =-Declarations!$D$27*(Declarations!$C$4-Declarations!$C$27)*EXP(-Declarations!$D$27*B14)+(Declarations!$E$27/Declarations!$F$27)*EXP(1-B14/Declarations!$F$27)*(1-B14/Declarations!$F$27) -> 0.2933658 | D14: =Declarations!$D$27^2*(Declarations!$C$4-Declarations!$C$27)*EXP(-Declarations!$D$27*B14)-(Declarations!$E$27/Declarations!$F$27^2)*EXP(1-B14/Declarations!$F$27)*(2-B14/Declarations!$F$27) -> 8.1268126 | E14: =Declarations!$C$27+(Declarations!$C$4-Declarations!$C$27)*EXP(-Declarations!$D$27*B14)+IF(Declarations!$E$27=0,0,Declarations!$E$27*(B14/Declarations!$F$27)*EXP(1-B14/Declarations!$F$27))+IF(B14>=T_sale,Declarations!$G$27,0) -> 77.733933
A15: iteration 1 | B15: =B14-C14/D14 -> 1.7139015 | C15: =-Declarations!$D$27*(Declarations!$C$4-Declarations!$C$27)*EXP(-Declarations!$D$27*B15)+(Declarations!$E$27/Declarations!$F$27)*EXP(1-B15/Declarations!$F$27)*(1-B15/Declarations!$F$27) -> -0.0053575547 | D15: =Declarations!$D$27^2*(Declarations!$C$4-Declarations!$C$27)*EXP(-Declarations!$D$27*B15)-(Declarations!$E$27/Declarations!$F$27^2)*EXP(1-B15/Declarations!$F$27)*(2-B15/Declarations!$F$27) -> 8.424983 | E15: =Declarations!$C$27+(Declarations!$C$4-Declarations!$C$27)*EXP(-Declarations!$D$27*B15)+IF(Declarations!$E$27=0,0,Declarations!$E$27*(B15/Declarations!$F$27)*EXP(1-B15/Declarations!$F$27))+IF(B15>=T_sale,Declarations!$G$27,0) -> 77.728702
A16: iteration 2 | B16: =B15-C15/D15 -> 1.7145374 | C16: =-Declarations!$D$27*(Declarations!$C$4-Declarations!$C$27)*EXP(-Declarations!$D$27*B16)+(Declarations!$E$27/Declarations!$F$27)*EXP(1-B16/Declarations!$F$27)*(1-B16/Declarations!$F$27) -> -1.6924427e-06 | D16: =Declarations!$D$27^2*(Declarations!$C$4-Declarations!$C$27)*EXP(-Declarations!$D$27*B16)-(Declarations!$E$27/Declarations!$F$27^2)*EXP(1-B16/Declarations!$F$27)*(2-B16/Declarations!$F$27) -> 8.4196605 | E16: =Declarations!$C$27+(Declarations!$C$4-Declarations!$C$27)*EXP(-Declarations!$D$27*B16)+IF(Declarations!$E$27=0,0,Declarations!$E$27*(B16/Declarations!$F$27)*EXP(1-B16/Declarations!$F$27))+IF(B16>=T_sale,Declarations!$G$27,0) -> 77.7287
A17: iteration 3 | B17: =B16-C16/D16 -> 1.7145376 | C17: =-Declarations!$D$27*(Declarations!$C$4-Declarations!$C$27)*EXP(-Declarations!$D$27*B17)+(Declarations!$E$27/Declarations!$F$27)*EXP(1-B17/Declarations!$F$27)*(1-B17/Declarations!$F$27) -> -1.7008617e-13 | D17: =Declarations!$D$27^2*(Declarations!$C$4-Declarations!$C$27)*EXP(-Declarations!$D$27*B17)-(Declarations!$E$27/Declarations!$F$27^2)*EXP(1-B17/Declarations!$F$27)*(2-B17/Declarations!$F$27) -> 8.4196589 | E17: =Declarations!$C$27+(Declarations!$C$4-Declarations!$C$27)*EXP(-Declarations!$D$27*B17)+IF(Declarations!$E$27=0,0,Declarations!$E$27*(B17/Declarations!$F$27)*EXP(1-B17/Declarations!$F$27))+IF(B17>=T_sale,Declarations!$G$27,0) -> 77.7287
A18: iteration 4 | B18: =B17-C17/D17 -> 1.7145376 | C18: =-Declarations!$D$27*(Declarations!$C$4-Declarations!$C$27)*EXP(-Declarations!$D$27*B18)+(Declarations!$E$27/Declarations!$F$27)*EXP(1-B18/Declarations!$F$27)*(1-B18/Declarations!$F$27) -> 0 | D18: =Declarations!$D$27^2*(Declarations!$C$4-Declarations!$C$27)*EXP(-Declarations!$D$27*B18)-(Declarations!$E$27/Declarations!$F$27^2)*EXP(1-B18/Declarations!$F$27)*(2-B18/Declarations!$F$27) -> 8.4196589 | E18: =Declarations!$C$27+(Declarations!$C$4-Declarations!$C$27)*EXP(-Declarations!$D$27*B18)+IF(Declarations!$E$27=0,0,Declarations!$E$27*(B18/Declarations!$F$27)*EXP(1-B18/Declarations!$F$27))+IF(B18>=T_sale,Declarations!$G$27,0) -> 77.7287
A19: iteration 5 | B19: =B18-C18/D18 -> 1.7145376 | C19: =-Declarations!$D$27*(Declarations!$C$4-Declarations!$C$27)*EXP(-Declarations!$D$27*B19)+(Declarations!$E$27/Declarations!$F$27)*EXP(1-B19/Declarations!$F$27)*(1-B19/Declarations!$F$27) -> 0 | D19: =Declarations!$D$27^2*(Declarations!$C$4-Declarations!$C$27)*EXP(-Declarations!$D$27*B19)-(Declarations!$E$27/Declarations!$F$27^2)*EXP(1-B19/Declarations!$F$27)*(2-B19/Declarations!$F$27) -> 8.4196589 | E19: =Declarations!$C$27+(Declarations!$C$4-Declarations!$C$27)*EXP(-Declarations!$D$27*B19)+IF(Declarations!$E$27=0,0,Declarations!$E$27*(B19/Declarations!$F$27)*EXP(1-B19/Declarations!$F$27))+IF(B19>=T_sale,Declarations!$G$27,0) -> 77.7287 | G19: Time of the low point (years) | J19: =B19 -> 1.7145376
G20: Low point (liquidity index) | J20: =E19 -> 77.7287
G21: Low point ($ million) | J21: =E19*USD_pt -> 481.91794
G22: Low point (month) | J22: =12*B19 -> 20.574451
G23: Slack above the floor at the low point ($ million) | J23: =J21-Floor_usd -> 131.91794
G24: Highest floor the digital program can meet ($ million) | J24: =J21 -> 481.91794
G25: Lowest monthly reading (index) | J25: =MIN($C$45:$C$105) -> 77.733933
G26: Its month | J26: =INDEX($A$45:$A$105,MATCH(J25,$C$45:$C$105,0)) -> 21
A28: The digital strategic-risk peak: Newton's method on the slope of strategic risk | B28: t (years) | C28: slope x'(t) | D28: curvature x''(t) | E28: reading x(t)
A29: iteration 0 (start: month 11) | B29: 0.9 | C29: =-Declarations!$D$30*(Declarations!$C$10-Declarations!$C$30)*EXP(-Declarations!$D$30*B29)+(Declarations!$E$30/Declarations!$F$30)*EXP(1-B29/Declarations!$F$30)*(1-B29/Declarations!$F$30) -> 0.11715724 | D29: =Declarations!$D$30^2*(Declarations!$C$10-Declarations!$C$30)*EXP(-Declarations!$D$30*B29)-(Declarations!$E$30/Declarations!$F$30^2)*EXP(1-B29/Declarations!$F$30)*(2-B29/Declarations!$F$30) -> -14.153309 | E29: =Declarations!$C$30+(Declarations!$C$10-Declarations!$C$30)*EXP(-Declarations!$D$30*B29)+IF(Declarations!$E$30=0,0,Declarations!$E$30*(B29/Declarations!$F$30)*EXP(1-B29/Declarations!$F$30))+IF(B29>=T_sale,Declarations!$G$30,0) -> 73.552059
A30: iteration 1 | B30: =B29-C29/D29 -> 0.90827773 | C30: =-Declarations!$D$30*(Declarations!$C$10-Declarations!$C$30)*EXP(-Declarations!$D$30*B30)+(Declarations!$E$30/Declarations!$F$30)*EXP(1-B30/Declarations!$F$30)*(1-B30/Declarations!$F$30) -> 0.00077940056 | D30: =Declarations!$D$30^2*(Declarations!$C$10-Declarations!$C$30)*EXP(-Declarations!$D$30*B30)-(Declarations!$E$30/Declarations!$F$30^2)*EXP(1-B30/Declarations!$F$30)*(2-B30/Declarations!$F$30) -> -13.965314 | E30: =Declarations!$C$30+(Declarations!$C$10-Declarations!$C$30)*EXP(-Declarations!$D$30*B30)+IF(Declarations!$E$30=0,0,Declarations!$E$30*(B30/Declarations!$F$30)*EXP(1-B30/Declarations!$F$30))+IF(B30>=T_sale,Declarations!$G$30,0) -> 73.552546
A31: iteration 2 | B31: =B30-C30/D30 -> 0.90833354 | C31: =-Declarations!$D$30*(Declarations!$C$10-Declarations!$C$30)*EXP(-Declarations!$D$30*B31)+(Declarations!$E$30/Declarations!$F$30)*EXP(1-B31/Declarations!$F$30)*(1-B31/Declarations!$F$30) -> 3.5189375e-08 | D31: =Declarations!$D$30^2*(Declarations!$C$10-Declarations!$C$30)*EXP(-Declarations!$D$30*B31)-(Declarations!$E$30/Declarations!$F$30^2)*EXP(1-B31/Declarations!$F$30)*(2-B31/Declarations!$F$30) -> -13.964053 | E31: =Declarations!$C$30+(Declarations!$C$10-Declarations!$C$30)*EXP(-Declarations!$D$30*B31)+IF(Declarations!$E$30=0,0,Declarations!$E$30*(B31/Declarations!$F$30)*EXP(1-B31/Declarations!$F$30))+IF(B31>=T_sale,Declarations!$G$30,0) -> 73.552546
A32: iteration 3 | B32: =B31-C31/D31 -> 0.90833354 | C32: =-Declarations!$D$30*(Declarations!$C$10-Declarations!$C$30)*EXP(-Declarations!$D$30*B32)+(Declarations!$E$30/Declarations!$F$30)*EXP(1-B32/Declarations!$F$30)*(1-B32/Declarations!$F$30) -> 0 | D32: =Declarations!$D$30^2*(Declarations!$C$10-Declarations!$C$30)*EXP(-Declarations!$D$30*B32)-(Declarations!$E$30/Declarations!$F$30^2)*EXP(1-B32/Declarations!$F$30)*(2-B32/Declarations!$F$30) -> -13.964053 | E32: =Declarations!$C$30+(Declarations!$C$10-Declarations!$C$30)*EXP(-Declarations!$D$30*B32)+IF(Declarations!$E$30=0,0,Declarations!$E$30*(B32/Declarations!$F$30)*EXP(1-B32/Declarations!$F$30))+IF(B32>=T_sale,Declarations!$G$30,0) -> 73.552546
A33: iteration 4 | B33: =B32-C32/D32 -> 0.90833354 | C33: =-Declarations!$D$30*(Declarations!$C$10-Declarations!$C$30)*EXP(-Declarations!$D$30*B33)+(Declarations!$E$30/Declarations!$F$30)*EXP(1-B33/Declarations!$F$30)*(1-B33/Declarations!$F$30) -> 0 | D33: =Declarations!$D$30^2*(Declarations!$C$10-Declarations!$C$30)*EXP(-Declarations!$D$30*B33)-(Declarations!$E$30/Declarations!$F$30^2)*EXP(1-B33/Declarations!$F$30)*(2-B33/Declarations!$F$30) -> -13.964053 | E33: =Declarations!$C$30+(Declarations!$C$10-Declarations!$C$30)*EXP(-Declarations!$D$30*B33)+IF(Declarations!$E$30=0,0,Declarations!$E$30*(B33/Declarations!$F$30)*EXP(1-B33/Declarations!$F$30))+IF(B33>=T_sale,Declarations!$G$30,0) -> 73.552546
A34: iteration 5 | B34: =B33-C33/D33 -> 0.90833354 | C34: =-Declarations!$D$30*(Declarations!$C$10-Declarations!$C$30)*EXP(-Declarations!$D$30*B34)+(Declarations!$E$30/Declarations!$F$30)*EXP(1-B34/Declarations!$F$30)*(1-B34/Declarations!$F$30) -> 0 | D34: =Declarations!$D$30^2*(Declarations!$C$10-Declarations!$C$30)*EXP(-Declarations!$D$30*B34)-(Declarations!$E$30/Declarations!$F$30^2)*EXP(1-B34/Declarations!$F$30)*(2-B34/Declarations!$F$30) -> -13.964053 | E34: =Declarations!$C$30+(Declarations!$C$10-Declarations!$C$30)*EXP(-Declarations!$D$30*B34)+IF(Declarations!$E$30=0,0,Declarations!$E$30*(B34/Declarations!$F$30)*EXP(1-B34/Declarations!$F$30))+IF(B34>=T_sale,Declarations!$G$30,0) -> 73.552546 | G34: Time of the peak (years) | J34: =B34 -> 0.90833354
G35: Strategic-risk peak | J35: =E34 -> 73.552546
G36: Its month | J36: =12*B34 -> 10.900002
G37: Margin under the risk ceiling | J37: =Risk_ceiling-E34 -> 1.4474538
G38: Highest monthly reading | J38: =MAX($F$45:$F$105) -> 73.552064
G39: Its month | J39: =INDEX($A$45:$A$105,MATCH(J38,$F$45:$F$105,0)) -> 11
A41: Section 5.7: in Figure 5.4's projection the floor is the wall the digital program approaches most closely. Off that projection the risk ceiling comes closer: strategic risk peaks 1.4 points under 75 in month 11 (Chapter 1, Table 1.5; Worked Example 16.1), inside the risk committee's +/-6 reading error.
A44: Month | B44: t (years) | C44: Digital: liquidity | D44: technology | E44: efficiency | F44: strategic risk | G44: Restructuring: liquidity | H44: technology | I44: efficiency | J44: strategic risk | K44: Turnaround: liquidity | L44: technology | M44: efficiency | N44: strategic risk | O44: Digital: liquidity ($m) | P44: floor slack ($m) | Q44: risk-ceiling slack | R44: index slack | S44: Restructuring: liquidity ($m) | T44: floor slack ($m) | U44: risk-ceiling slack | V44: index slack | W44: Turnaround: liquidity ($m) | X44: floor slack ($m) | Y44: risk-ceiling slack | Z44: index slack
A45: 0 | B45: =A45/12 -> 0 | C45: =Declarations!$C$27+(Declarations!$C$4-Declarations!$C$27)*EXP(-Declarations!$D$27*$B45)+IF(Declarations!$E$27=0,0,Declarations!$E$27*($B45/Declarations!$F$27)*EXP(1-$B45/Declarations!$F$27))+IF($B45>=T_sale,Declarations!$G$27,0) -> 100 | D45: =Declarations!$C$28+(Declarations!$C$7-Declarations!$C$28)*EXP(-Declarations!$D$28*$B45)+IF(Declarations!$E$28=0,0,Declarations!$E$28*($B45/Declarations!$F$28)*EXP(1-$B45/Declarations!$F$28))+IF($B45>=T_sale,Declarations!$G$28,0) -> 41 | E45: =Declarations!$C$29+(Declarations!$C$8-Declarations!$C$29)*EXP(-Declarations!$D$29*$B45)+IF(Declarations!$E$29=0,0,Declarations!$E$29*($B45/Declarations!$F$29)*EXP(1-$B45/Declarations!$F$29))+IF($B45>=T_sale,Declarations!$G$29,0) -> 71 | F45: =Declarations!$C$30+(Declarations!$C$10-Declarations!$C$30)*EXP(-Declarations!$D$30*$B45)+IF(Declarations!$E$30=0,0,Declarations!$E$30*($B45/Declarations!$F$30)*EXP(1-$B45/Declarations!$F$30))+IF($B45>=T_sale,Declarations!$G$30,0) -> 64 | G45: =Declarations!$C$31+(Declarations!$C$4-Declarations!$C$31)*EXP(-Declarations!$D$31*$B45)+IF(Declarations!$E$31=0,0,Declarations!$E$31*($B45/Declarations!$F$31)*EXP(1-$B45/Declarations!$F$31))+IF($B45>=T_sale,Declarations!$G$31,0) -> 100 | H45: =Declarations!$C$32+(Declarations!$C$7-Declarations!$C$32)*EXP(-Declarations!$D$32*$B45)+IF(Declarations!$E$32=0,0,Declarations!$E$32*($B45/Declarations!$F$32)*EXP(1-$B45/Declarations!$F$32))+IF($B45>=T_sale,Declarations!$G$32,0) -> 41 | I45: =Declarations!$C$33+(Declarations!$C$8-Declarations!$C$33)*EXP(-Declarations!$D$33*$B45)+IF(Declarations!$E$33=0,0,Declarations!$E$33*($B45/Declarations!$F$33)*EXP(1-$B45/Declarations!$F$33))+IF($B45>=T_sale,Declarations!$G$33,0) -> 71 | J45: =Declarations!$C$34+(Declarations!$C$10-Declarations!$C$34)*EXP(-Declarations!$D$34*$B45)+IF(Declarations!$E$34=0,0,Declarations!$E$34*($B45/Declarations!$F$34)*EXP(1-$B45/Declarations!$F$34))+IF($B45>=T_sale,Declarations!$G$34,0) -> 64 | K45: =Declarations!$C$35+(Declarations!$C$4-Declarations!$C$35)*EXP(-Declarations!$D$35*$B45)+IF(Declarations!$E$35=0,0,Declarations!$E$35*($B45/Declarations!$F$35)*EXP(1-$B45/Declarations!$F$35))+IF($B45>=T_sale,Declarations!$G$35,0) -> 100 | L45: =Declarations!$C$36+(Declarations!$C$7-Declarations!$C$36)*EXP(-Declarations!$D$36*$B45)+IF(Declarations!$E$36=0,0,Declarations!$E$36*($B45/Declarations!$F$36)*EXP(1-$B45/Declarations!$F$36))+IF($B45>=T_sale,Declarations!$G$36,0) -> 41 | M45: =Declarations!$C$37+(Declarations!$C$8-Declarations!$C$37)*EXP(-Declarations!$D$37*$B45)+IF(Declarations!$E$37=0,0,Declarations!$E$37*($B45/Declarations!$F$37)*EXP(1-$B45/Declarations!$F$37))+IF($B45>=T_sale,Declarations!$G$37,0) -> 71 | N45: =Declarations!$C$38+(Declarations!$C$10-Declarations!$C$38)*EXP(-Declarations!$D$38*$B45)+IF(Declarations!$E$38=0,0,Declarations!$E$38*($B45/Declarations!$F$38)*EXP(1-$B45/Declarations!$F$38))+IF($B45>=T_sale,Declarations!$G$38,0) -> 64 | O45: =C45*USD_pt -> 620 | P45: =C45*USD_pt-Floor_usd -> 270 | Q45: =Risk_ceiling-F45 -> 11 | R45: =MIN(Wf_today-Idx_lo,Idx_hi-Wf_today,D45-Idx_lo,Idx_hi-D45,E45-Idx_lo,Idx_hi-E45,F45-Idx_lo,Idx_hi-F45) -> 29 | S45: =G45*USD_pt -> 620 | T45: =G45*USD_pt-Floor_usd -> 270 | U45: =Risk_ceiling-J45 -> 11 | V45: =MIN(Wf_today-Idx_lo,Idx_hi-Wf_today,H45-Idx_lo,Idx_hi-H45,I45-Idx_lo,Idx_hi-I45,J45-Idx_lo,Idx_hi-J45) -> 29 | W45: =K45*USD_pt -> 620 | X45: =K45*USD_pt-Floor_usd -> 270 | Y45: =Risk_ceiling-N45 -> 11 | Z45: =MIN(Wf_today-Idx_lo,Idx_hi-Wf_today,L45-Idx_lo,Idx_hi-L45,M45-Idx_lo,Idx_hi-M45,N45-Idx_lo,Idx_hi-N45) -> 29
A46: 1 | B46: =A46/12 -> 0.083333333 | C46: =Declarations!$C$27+(Declarations!$C$4-Declarations!$C$27)*EXP(-Declarations!$D$27*$B46)+IF(Declarations!$E$27=0,0,Declarations!$E$27*($B46/Declarations!$F$27)*EXP(1-$B46/Declarations!$F$27))+IF($B46>=T_sale,Declarations!$G$27,0) -> 97.30304 | D46: =Declarations!$C$28+(Declarations!$C$7-Declarations!$C$28)*EXP(-Declarations!$D$28*$B46)+IF(Declarations!$E$28=0,0,Declarations!$E$28*($B46/Declarations!$F$28)*EXP(1-$B46/Declarations!$F$28))+IF($B46>=T_sale,Declarations!$G$28,0) -> 42.657557 | E46: =Declarations!$C$29+(Declarations!$C$8-Declarations!$C$29)*EXP(-Declarations!$D$29*$B46)+IF(Declarations!$E$29=0,0,Declarations!$E$29*($B46/Declarations!$F$29)*EXP(1-$B46/Declarations!$F$29))+IF($B46>=T_sale,Declarations!$G$29,0) -> 69.959171 | F46: =Declarations!$C$30+(Declarations!$C$10-Declarations!$C$30)*EXP(-Declarations!$D$30*$B46)+IF(Declarations!$E$30=0,0,Declarations!$E$30*($B46/Declarations!$F$30)*EXP(1-$B46/Declarations!$F$30))+IF($B46>=T_sale,Declarations!$G$30,0) -> 66.039285 | G46: =Declarations!$C$31+(Declarations!$C$4-Declarations!$C$31)*EXP(-Declarations!$D$31*$B46)+IF(Declarations!$E$31=0,0,Declarations!$E$31*($B46/Declarations!$F$31)*EXP(1-$B46/Declarations!$F$31))+IF($B46>=T_sale,Declarations!$G$31,0) -> 100.09876 | H46: =Declarations!$C$32+(Declarations!$C$7-Declarations!$C$32)*EXP(-Declarations!$D$32*$B46)+IF(Declarations!$E$32=0,0,Declarations!$E$32*($B46/Declarations!$F$32)*EXP(1-$B46/Declarations!$F$32))+IF($B46>=T_sale,Declarations!$G$32,0) -> 40.938147 | I46: =Declarations!$C$33+(Declarations!$C$8-Declarations!$C$33)*EXP(-Declarations!$D$33*$B46)+IF(Declarations!$E$33=0,0,Declarations!$E$33*($B46/Declarations!$F$33)*EXP(1-$B46/Declarations!$F$33))+IF($B46>=T_sale,Declarations!$G$33,0) -> 71.110417 | J46: =Declarations!$C$34+(Declarations!$C$10-Declarations!$C$34)*EXP(-Declarations!$D$34*$B46)+IF(Declarations!$E$34=0,0,Declarations!$E$34*($B46/Declarations!$F$34)*EXP(1-$B46/Declarations!$F$34))+IF($B46>=T_sale,Declarations!$G$34,0) -> 63.770037 | K46: =Declarations!$C$35+(Declarations!$C$4-Declarations!$C$35)*EXP(-Declarations!$D$35*$B46)+IF(Declarations!$E$35=0,0,Declarations!$E$35*($B46/Declarations!$F$35)*EXP(1-$B46/Declarations!$F$35))+IF($B46>=T_sale,Declarations!$G$35,0) -> 100.22083 | L46: =Declarations!$C$36+(Declarations!$C$7-Declarations!$C$36)*EXP(-Declarations!$D$36*$B46)+IF(Declarations!$E$36=0,0,Declarations!$E$36*($B46/Declarations!$F$36)*EXP(1-$B46/Declarations!$F$36))+IF($B46>=T_sale,Declarations!$G$36,0) -> 40.867772 | M46: =Declarations!$C$37+(Declarations!$C$8-Declarations!$C$37)*EXP(-Declarations!$D$37*$B46)+IF(Declarations!$E$37=0,0,Declarations!$E$37*($B46/Declarations!$F$37)*EXP(1-$B46/Declarations!$F$37))+IF($B46>=T_sale,Declarations!$G$37,0) -> 71.390165 | N46: =Declarations!$C$38+(Declarations!$C$10-Declarations!$C$38)*EXP(-Declarations!$D$38*$B46)+IF(Declarations!$E$38=0,0,Declarations!$E$38*($B46/Declarations!$F$38)*EXP(1-$B46/Declarations!$F$38))+IF($B46>=T_sale,Declarations!$G$38,0) -> 64.07407 | O46: =C46*USD_pt -> 603.27885 | P46: =C46*USD_pt-Floor_usd -> 253.27885 | Q46: =Risk_ceiling-F46 -> 8.9607152 | R46: =MIN(Wf_today-Idx_lo,Idx_hi-Wf_today,D46-Idx_lo,Idx_hi-D46,E46-Idx_lo,Idx_hi-E46,F46-Idx_lo,Idx_hi-F46) -> 30.040829 | S46: =G46*USD_pt -> 620.61231 | T46: =G46*USD_pt-Floor_usd -> 270.61231 | U46: =Risk_ceiling-J46 -> 11.229963 | V46: =MIN(Wf_today-Idx_lo,Idx_hi-Wf_today,H46-Idx_lo,Idx_hi-H46,I46-Idx_lo,Idx_hi-I46,J46-Idx_lo,Idx_hi-J46) -> 28.889583 | W46: =K46*USD_pt -> 621.36917 | X46: =K46*USD_pt-Floor_usd -> 271.36917 | Y46: =Risk_ceiling-N46 -> 10.92593 | Z46: =MIN(Wf_today-Idx_lo,Idx_hi-Wf_today,L46-Idx_lo,Idx_hi-L46,M46-Idx_lo,Idx_hi-M46,N46-Idx_lo,Idx_hi-N46) -> 28.609835
A47: 2 | B47: =A47/12 -> 0.16666667 | C47: =Declarations!$C$27+(Declarations!$C$4-Declarations!$C$27)*EXP(-Declarations!$D$27*$B47)+IF(Declarations!$E$27=0,0,Declarations!$E$27*($B47/Declarations!$F$27)*EXP(1-$B47/Declarations!$F$27))+IF($B47>=T_sale,Declarations!$G$27,0) -> 94.844448 | D47: =Declarations!$C$28+(Declarations!$C$7-Declarations!$C$28)*EXP(-Declarations!$D$28*$B47)+IF(Declarations!$E$28=0,0,Declarations!$E$28*($B47/Declarations!$F$28)*EXP(1-$B47/Declarations!$F$28))+IF($B47>=T_sale,Declarations!$G$28,0) -> 44.240858 | E47: =Declarations!$C$29+(Declarations!$C$8-Declarations!$C$29)*EXP(-Declarations!$D$29*$B47)+IF(Declarations!$E$29=0,0,Declarations!$E$29*($B47/Declarations!$F$29)*EXP(1-$B47/Declarations!$F$29))+IF($B47>=T_sale,Declarations!$G$29,0) -> 69.047308 | F47: =Declarations!$C$30+(Declarations!$C$10-Declarations!$C$30)*EXP(-Declarations!$D$30*$B47)+IF(Declarations!$E$30=0,0,Declarations!$E$30*($B47/Declarations!$F$30)*EXP(1-$B47/Declarations!$F$30))+IF($B47>=T_sale,Declarations!$G$30,0) -> 67.761734 | G47: =Declarations!$C$31+(Declarations!$C$4-Declarations!$C$31)*EXP(-Declarations!$D$31*$B47)+IF(Declarations!$E$31=0,0,Declarations!$E$31*($B47/Declarations!$F$31)*EXP(1-$B47/Declarations!$F$31))+IF($B47>=T_sale,Declarations!$G$31,0) -> 100.19508 | H47: =Declarations!$C$32+(Declarations!$C$7-Declarations!$C$32)*EXP(-Declarations!$D$32*$B47)+IF(Declarations!$E$32=0,0,Declarations!$E$32*($B47/Declarations!$F$32)*EXP(1-$B47/Declarations!$F$32))+IF($B47>=T_sale,Declarations!$G$32,0) -> 40.877568 | I47: =Declarations!$C$33+(Declarations!$C$8-Declarations!$C$33)*EXP(-Declarations!$D$33*$B47)+IF(Declarations!$E$33=0,0,Declarations!$E$33*($B47/Declarations!$F$33)*EXP(1-$B47/Declarations!$F$33))+IF($B47>=T_sale,Declarations!$G$33,0) -> 71.21677 | J47: =Declarations!$C$34+(Declarations!$C$10-Declarations!$C$34)*EXP(-Declarations!$D$34*$B47)+IF(Declarations!$E$34=0,0,Declarations!$E$34*($B47/Declarations!$F$34)*EXP(1-$B47/Declarations!$F$34))+IF($B47>=T_sale,Declarations!$G$34,0) -> 63.546684 | K47: =Declarations!$C$35+(Declarations!$C$4-Declarations!$C$35)*EXP(-Declarations!$D$35*$B47)+IF(Declarations!$E$35=0,0,Declarations!$E$35*($B47/Declarations!$F$35)*EXP(1-$B47/Declarations!$F$35))+IF($B47>=T_sale,Declarations!$G$35,0) -> 100.43354 | L47: =Declarations!$C$36+(Declarations!$C$7-Declarations!$C$36)*EXP(-Declarations!$D$36*$B47)+IF(Declarations!$E$36=0,0,Declarations!$E$36*($B47/Declarations!$F$36)*EXP(1-$B47/Declarations!$F$36))+IF($B47>=T_sale,Declarations!$G$36,0) -> 40.737729 | M47: =Declarations!$C$37+(Declarations!$C$8-Declarations!$C$37)*EXP(-Declarations!$D$37*$B47)+IF(Declarations!$E$37=0,0,Declarations!$E$37*($B47/Declarations!$F$37)*EXP(1-$B47/Declarations!$F$37))+IF($B47>=T_sale,Declarations!$G$37,0) -> 71.761301 | N47: =Declarations!$C$38+(Declarations!$C$10-Declarations!$C$38)*EXP(-Declarations!$D$38*$B47)+IF(Declarations!$E$38=0,0,Declarations!$E$38*($B47/Declarations!$F$38)*EXP(1-$B47/Declarations!$F$38))+IF($B47>=T_sale,Declarations!$G$38,0) -> 64.146312 | O47: =C47*USD_pt -> 588.03558 | P47: =C47*USD_pt-Floor_usd -> 238.03558 | Q47: =Risk_ceiling-F47 -> 7.2382661 | R47: =MIN(Wf_today-Idx_lo,Idx_hi-Wf_today,D47-Idx_lo,Idx_hi-D47,E47-Idx_lo,Idx_hi-E47,F47-Idx_lo,Idx_hi-F47) -> 30.952692 | S47: =G47*USD_pt -> 621.20951 | T47: =G47*USD_pt-Floor_usd -> 271.20951 | U47: =Risk_ceiling-J47 -> 11.453316 | V47: =MIN(Wf_today-Idx_lo,Idx_hi-Wf_today,H47-Idx_lo,Idx_hi-H47,I47-Idx_lo,Idx_hi-I47,J47-Idx_lo,Idx_hi-J47) -> 28.78323 | W47: =K47*USD_pt -> 622.68794 | X47: =K47*USD_pt-Floor_usd -> 272.68794 | Y47: =Risk_ceiling-N47 -> 10.853688 | Z47: =MIN(Wf_today-Idx_lo,Idx_hi-Wf_today,L47-Idx_lo,Idx_hi-L47,M47-Idx_lo,Idx_hi-M47,N47-Idx_lo,Idx_hi-N47) -> 28.238699
A48: 3 | B48: =A48/12 -> 0.25 | C48: =Declarations!$C$27+(Declarations!$C$4-Declarations!$C$27)*EXP(-Declarations!$D$27*$B48)+IF(Declarations!$E$27=0,0,Declarations!$E$27*($B48/Declarations!$F$27)*EXP(1-$B48/Declarations!$F$27))+IF($B48>=T_sale,Declarations!$G$27,0) -> 92.60931 | D48: =Declarations!$C$28+(Declarations!$C$7-Declarations!$C$28)*EXP(-Declarations!$D$28*$B48)+IF(Declarations!$E$28=0,0,Declarations!$E$28*($B48/Declarations!$F$28)*EXP(1-$B48/Declarations!$F$28))+IF($B48>=T_sale,Declarations!$G$28,0) -> 45.753229 | E48: =Declarations!$C$29+(Declarations!$C$8-Declarations!$C$29)*EXP(-Declarations!$D$29*$B48)+IF(Declarations!$E$29=0,0,Declarations!$E$29*($B48/Declarations!$F$29)*EXP(1-$B48/Declarations!$F$29))+IF($B48>=T_sale,Declarations!$G$29,0) -> 68.253555 | F48: =Declarations!$C$30+(Declarations!$C$10-Declarations!$C$30)*EXP(-Declarations!$D$30*$B48)+IF(Declarations!$E$30=0,0,Declarations!$E$30*($B48/Declarations!$F$30)*EXP(1-$B48/Declarations!$F$30))+IF($B48>=T_sale,Declarations!$G$30,0) -> 69.200179 | G48: =Declarations!$C$31+(Declarations!$C$4-Declarations!$C$31)*EXP(-Declarations!$D$31*$B48)+IF(Declarations!$E$31=0,0,Declarations!$E$31*($B48/Declarations!$F$31)*EXP(1-$B48/Declarations!$F$31))+IF($B48>=T_sale,Declarations!$G$31,0) -> 100.28903 | H48: =Declarations!$C$32+(Declarations!$C$7-Declarations!$C$32)*EXP(-Declarations!$D$32*$B48)+IF(Declarations!$E$32=0,0,Declarations!$E$32*($B48/Declarations!$F$32)*EXP(1-$B48/Declarations!$F$32))+IF($B48>=T_sale,Declarations!$G$32,0) -> 40.818239 | I48: =Declarations!$C$33+(Declarations!$C$8-Declarations!$C$33)*EXP(-Declarations!$D$33*$B48)+IF(Declarations!$E$33=0,0,Declarations!$E$33*($B48/Declarations!$F$33)*EXP(1-$B48/Declarations!$F$33))+IF($B48>=T_sale,Declarations!$G$33,0) -> 71.319208 | J48: =Declarations!$C$34+(Declarations!$C$10-Declarations!$C$34)*EXP(-Declarations!$D$34*$B48)+IF(Declarations!$E$34=0,0,Declarations!$E$34*($B48/Declarations!$F$34)*EXP(1-$B48/Declarations!$F$34))+IF($B48>=T_sale,Declarations!$G$34,0) -> 63.329751 | K48: =Declarations!$C$35+(Declarations!$C$4-Declarations!$C$35)*EXP(-Declarations!$D$35*$B48)+IF(Declarations!$E$35=0,0,Declarations!$E$35*($B48/Declarations!$F$35)*EXP(1-$B48/Declarations!$F$35))+IF($B48>=T_sale,Declarations!$G$35,0) -> 100.63842 | L48: =Declarations!$C$36+(Declarations!$C$7-Declarations!$C$36)*EXP(-Declarations!$D$36*$B48)+IF(Declarations!$E$36=0,0,Declarations!$E$36*($B48/Declarations!$F$36)*EXP(1-$B48/Declarations!$F$36))+IF($B48>=T_sale,Declarations!$G$36,0) -> 40.609835 | M48: =Declarations!$C$37+(Declarations!$C$8-Declarations!$C$37)*EXP(-Declarations!$D$37*$B48)+IF(Declarations!$E$37=0,0,Declarations!$E$37*($B48/Declarations!$F$37)*EXP(1-$B48/Declarations!$F$37))+IF($B48>=T_sale,Declarations!$G$37,0) -> 72.114336 | N48: =Declarations!$C$38+(Declarations!$C$10-Declarations!$C$38)*EXP(-Declarations!$D$38*$B48)+IF(Declarations!$E$38=0,0,Declarations!$E$38*($B48/Declarations!$F$38)*EXP(1-$B48/Declarations!$F$38))+IF($B48>=T_sale,Declarations!$G$38,0) -> 64.21677 | O48: =C48*USD_pt -> 574.17772 | P48: =C48*USD_pt-Floor_usd -> 224.17772 | Q48: =Risk_ceiling-F48 -> 5.7998208 | R48: =MIN(Wf_today-Idx_lo,Idx_hi-Wf_today,D48-Idx_lo,Idx_hi-D48,E48-Idx_lo,Idx_hi-E48,F48-Idx_lo,Idx_hi-F48) -> 30.799821 | S48: =G48*USD_pt -> 621.79196 | T48: =G48*USD_pt-Floor_usd -> 271.79196 | U48: =Risk_ceiling-J48 -> 11.670249 | V48: =MIN(Wf_today-Idx_lo,Idx_hi-Wf_today,H48-Idx_lo,Idx_hi-H48,I48-Idx_lo,Idx_hi-I48,J48-Idx_lo,Idx_hi-J48) -> 28.680792 | W48: =K48*USD_pt -> 623.95818 | X48: =K48*USD_pt-Floor_usd -> 273.95818 | Y48: =Risk_ceiling-N48 -> 10.78323 | Z48: =MIN(Wf_today-Idx_lo,Idx_hi-Wf_today,L48-Idx_lo,Idx_hi-L48,M48-Idx_lo,Idx_hi-M48,N48-Idx_lo,Idx_hi-N48) -> 27.885664
A49: 4 | B49: =A49/12 -> 0.33333333 | C49: =Declarations!$C$27+(Declarations!$C$4-Declarations!$C$27)*EXP(-Declarations!$D$27*$B49)+IF(Declarations!$E$27=0,0,Declarations!$E$27*($B49/Declarations!$F$27)*EXP(1-$B49/Declarations!$F$27))+IF($B49>=T_sale,Declarations!$G$27,0) -> 90.583531 | D49: =Declarations!$C$28+(Declarations!$C$7-Declarations!$C$28)*EXP(-Declarations!$D$28*$B49)+IF(Declarations!$E$28=0,0,Declarations!$E$28*($B49/Declarations!$F$28)*EXP(1-$B49/Declarations!$F$28))+IF($B49>=T_sale,Declarations!$G$28,0) -> 47.197847 | E49: =Declarations!$C$29+(Declarations!$C$8-Declarations!$C$29)*EXP(-Declarations!$D$29*$B49)+IF(Declarations!$E$29=0,0,Declarations!$E$29*($B49/Declarations!$F$29)*EXP(1-$B49/Declarations!$F$29))+IF($B49>=T_sale,Declarations!$G$29,0) -> 67.56785 | F49: =Declarations!$C$30+(Declarations!$C$10-Declarations!$C$30)*EXP(-Declarations!$D$30*$B49)+IF(Declarations!$E$30=0,0,Declarations!$E$30*($B49/Declarations!$F$30)*EXP(1-$B49/Declarations!$F$30))+IF($B49>=T_sale,Declarations!$G$30,0) -> 70.38449 | G49: =Declarations!$C$31+(Declarations!$C$4-Declarations!$C$31)*EXP(-Declarations!$D$31*$B49)+IF(Declarations!$E$31=0,0,Declarations!$E$31*($B49/Declarations!$F$31)*EXP(1-$B49/Declarations!$F$31))+IF($B49>=T_sale,Declarations!$G$31,0) -> 100.38065 | H49: =Declarations!$C$32+(Declarations!$C$7-Declarations!$C$32)*EXP(-Declarations!$D$32*$B49)+IF(Declarations!$E$32=0,0,Declarations!$E$32*($B49/Declarations!$F$32)*EXP(1-$B49/Declarations!$F$32))+IF($B49>=T_sale,Declarations!$G$32,0) -> 40.760133 | I49: =Declarations!$C$33+(Declarations!$C$8-Declarations!$C$33)*EXP(-Declarations!$D$33*$B49)+IF(Declarations!$E$33=0,0,Declarations!$E$33*($B49/Declarations!$F$33)*EXP(1-$B49/Declarations!$F$33))+IF($B49>=T_sale,Declarations!$G$33,0) -> 71.417876 | J49: =Declarations!$C$34+(Declarations!$C$10-Declarations!$C$34)*EXP(-Declarations!$D$34*$B49)+IF(Declarations!$E$34=0,0,Declarations!$E$34*($B49/Declarations!$F$34)*EXP(1-$B49/Declarations!$F$34))+IF($B49>=T_sale,Declarations!$G$34,0) -> 63.119054 | K49: =Declarations!$C$35+(Declarations!$C$4-Declarations!$C$35)*EXP(-Declarations!$D$35*$B49)+IF(Declarations!$E$35=0,0,Declarations!$E$35*($B49/Declarations!$F$35)*EXP(1-$B49/Declarations!$F$35))+IF($B49>=T_sale,Declarations!$G$35,0) -> 100.83575 | L49: =Declarations!$C$36+(Declarations!$C$7-Declarations!$C$36)*EXP(-Declarations!$D$36*$B49)+IF(Declarations!$E$36=0,0,Declarations!$E$36*($B49/Declarations!$F$36)*EXP(1-$B49/Declarations!$F$36))+IF($B49>=T_sale,Declarations!$G$36,0) -> 40.484056 | M49: =Declarations!$C$37+(Declarations!$C$8-Declarations!$C$37)*EXP(-Declarations!$D$37*$B49)+IF(Declarations!$E$37=0,0,Declarations!$E$37*($B49/Declarations!$F$37)*EXP(1-$B49/Declarations!$F$37))+IF($B49>=T_sale,Declarations!$G$37,0) -> 72.450154 | N49: =Declarations!$C$38+(Declarations!$C$10-Declarations!$C$38)*EXP(-Declarations!$D$38*$B49)+IF(Declarations!$E$38=0,0,Declarations!$E$38*($B49/Declarations!$F$38)*EXP(1-$B49/Declarations!$F$38))+IF($B49>=T_sale,Declarations!$G$38,0) -> 64.285488 | O49: =C49*USD_pt -> 561.61789 | P49: =C49*USD_pt-Floor_usd -> 211.61789 | Q49: =Risk_ceiling-F49 -> 4.6155103 | R49: =MIN(Wf_today-Idx_lo,Idx_hi-Wf_today,D49-Idx_lo,Idx_hi-D49,E49-Idx_lo,Idx_hi-E49,F49-Idx_lo,Idx_hi-F49) -> 29.61551 | S49: =G49*USD_pt -> 622.36003 | T49: =G49*USD_pt-Floor_usd -> 272.36003 | U49: =Risk_ceiling-J49 -> 11.880946 | V49: =MIN(Wf_today-Idx_lo,Idx_hi-Wf_today,H49-Idx_lo,Idx_hi-H49,I49-Idx_lo,Idx_hi-I49,J49-Idx_lo,Idx_hi-J49) -> 28.582124 | W49: =K49*USD_pt -> 625.18166 | X49: =K49*USD_pt-Floor_usd -> 275.18166 | Y49: =Risk_ceiling-N49 -> 10.714512 | Z49: =MIN(Wf_today-Idx_lo,Idx_hi-Wf_today,L49-Idx_lo,Idx_hi-L49,M49-Idx_lo,Idx_hi-M49,N49-Idx_lo,Idx_hi-N49) -> 27.549846
A50: 5 | B50: =A50/12 -> 0.41666667 | C50: =Declarations!$C$27+(Declarations!$C$4-Declarations!$C$27)*EXP(-Declarations!$D$27*$B50)+IF(Declarations!$E$27=0,0,Declarations!$E$27*($B50/Declarations!$F$27)*EXP(1-$B50/Declarations!$F$27))+IF($B50>=T_sale,Declarations!$G$27,0) -> 88.753794 | D50: =Declarations!$C$28+(Declarations!$C$7-Declarations!$C$28)*EXP(-Declarations!$D$28*$B50)+IF(Declarations!$E$28=0,0,Declarations!$E$28*($B50/Declarations!$F$28)*EXP(1-$B50/Declarations!$F$28))+IF($B50>=T_sale,Declarations!$G$28,0) -> 48.577748 | E50: =Declarations!$C$29+(Declarations!$C$8-Declarations!$C$29)*EXP(-Declarations!$D$29*$B50)+IF(Declarations!$E$29=0,0,Declarations!$E$29*($B50/Declarations!$F$29)*EXP(1-$B50/Declarations!$F$29))+IF($B50>=T_sale,Declarations!$G$29,0) -> 66.980873 | F50: =Declarations!$C$30+(Declarations!$C$10-Declarations!$C$30)*EXP(-Declarations!$D$30*$B50)+IF(Declarations!$E$30=0,0,Declarations!$E$30*($B50/Declarations!$F$30)*EXP(1-$B50/Declarations!$F$30))+IF($B50>=T_sale,Declarations!$G$30,0) -> 71.341821 | G50: =Declarations!$C$31+(Declarations!$C$4-Declarations!$C$31)*EXP(-Declarations!$D$31*$B50)+IF(Declarations!$E$31=0,0,Declarations!$E$31*($B50/Declarations!$F$31)*EXP(1-$B50/Declarations!$F$31))+IF($B50>=T_sale,Declarations!$G$31,0) -> 100.47001 | H50: =Declarations!$C$32+(Declarations!$C$7-Declarations!$C$32)*EXP(-Declarations!$D$32*$B50)+IF(Declarations!$E$32=0,0,Declarations!$E$32*($B50/Declarations!$F$32)*EXP(1-$B50/Declarations!$F$32))+IF($B50>=T_sale,Declarations!$G$32,0) -> 40.703225 | I50: =Declarations!$C$33+(Declarations!$C$8-Declarations!$C$33)*EXP(-Declarations!$D$33*$B50)+IF(Declarations!$E$33=0,0,Declarations!$E$33*($B50/Declarations!$F$33)*EXP(1-$B50/Declarations!$F$33))+IF($B50>=T_sale,Declarations!$G$33,0) -> 71.512913 | J50: =Declarations!$C$34+(Declarations!$C$10-Declarations!$C$34)*EXP(-Declarations!$D$34*$B50)+IF(Declarations!$E$34=0,0,Declarations!$E$34*($B50/Declarations!$F$34)*EXP(1-$B50/Declarations!$F$34))+IF($B50>=T_sale,Declarations!$G$34,0) -> 62.914414 | K50: =Declarations!$C$35+(Declarations!$C$4-Declarations!$C$35)*EXP(-Declarations!$D$35*$B50)+IF(Declarations!$E$35=0,0,Declarations!$E$35*($B50/Declarations!$F$35)*EXP(1-$B50/Declarations!$F$35))+IF($B50>=T_sale,Declarations!$G$35,0) -> 101.02583 | L50: =Declarations!$C$36+(Declarations!$C$7-Declarations!$C$36)*EXP(-Declarations!$D$36*$B50)+IF(Declarations!$E$36=0,0,Declarations!$E$36*($B50/Declarations!$F$36)*EXP(1-$B50/Declarations!$F$36))+IF($B50>=T_sale,Declarations!$G$36,0) -> 40.360355 | M50: =Declarations!$C$37+(Declarations!$C$8-Declarations!$C$37)*EXP(-Declarations!$D$37*$B50)+IF(Declarations!$E$37=0,0,Declarations!$E$37*($B50/Declarations!$F$37)*EXP(1-$B50/Declarations!$F$37))+IF($B50>=T_sale,Declarations!$G$37,0) -> 72.769594 | N50: =Declarations!$C$38+(Declarations!$C$10-Declarations!$C$38)*EXP(-Declarations!$D$38*$B50)+IF(Declarations!$E$38=0,0,Declarations!$E$38*($B50/Declarations!$F$38)*EXP(1-$B50/Declarations!$F$38))+IF($B50>=T_sale,Declarations!$G$38,0) -> 64.352509 | O50: =C50*USD_pt -> 550.27352 | P50: =C50*USD_pt-Floor_usd -> 200.27352 | Q50: =Risk_ceiling-F50 -> 3.6581791 | R50: =MIN(Wf_today-Idx_lo,Idx_hi-Wf_today,D50-Idx_lo,Idx_hi-D50,E50-Idx_lo,Idx_hi-E50,F50-Idx_lo,Idx_hi-F50) -> 28.658179 | S50: =G50*USD_pt -> 622.91408 | T50: =G50*USD_pt-Floor_usd -> 272.91408 | U50: =Risk_ceiling-J50 -> 12.085586 | V50: =MIN(Wf_today-Idx_lo,Idx_hi-Wf_today,H50-Idx_lo,Idx_hi-H50,I50-Idx_lo,Idx_hi-I50,J50-Idx_lo,Idx_hi-J50) -> 28.487087 | W50: =K50*USD_pt -> 626.36012 | X50: =K50*USD_pt-Floor_usd -> 276.36012 | Y50: =Risk_ceiling-N50 -> 10.647491 | Z50: =MIN(Wf_today-Idx_lo,Idx_hi-Wf_today,L50-Idx_lo,Idx_hi-L50,M50-Idx_lo,Idx_hi-M50,N50-Idx_lo,Idx_hi-N50) -> 27.230406
A51: 6 | B51: =A51/12 -> 0.5 | C51: =Declarations!$C$27+(Declarations!$C$4-Declarations!$C$27)*EXP(-Declarations!$D$27*$B51)+IF(Declarations!$E$27=0,0,Declarations!$E$27*($B51/Declarations!$F$27)*EXP(1-$B51/Declarations!$F$27))+IF($B51>=T_sale,Declarations!$G$27,0) -> 87.107516 | D51: =Declarations!$C$28+(Declarations!$C$7-Declarations!$C$28)*EXP(-Declarations!$D$28*$B51)+IF(Declarations!$E$28=0,0,Declarations!$E$28*($B51/Declarations!$F$28)*EXP(1-$B51/Declarations!$F$28))+IF($B51>=T_sale,Declarations!$G$28,0) -> 49.895831 | E51: =Declarations!$C$29+(Declarations!$C$8-Declarations!$C$29)*EXP(-Declarations!$D$29*$B51)+IF(Declarations!$E$29=0,0,Declarations!$E$29*($B51/Declarations!$F$29)*EXP(1-$B51/Declarations!$F$29))+IF($B51>=T_sale,Declarations!$G$29,0) -> 66.483993 | F51: =Declarations!$C$30+(Declarations!$C$10-Declarations!$C$30)*EXP(-Declarations!$D$30*$B51)+IF(Declarations!$E$30=0,0,Declarations!$E$30*($B51/Declarations!$F$30)*EXP(1-$B51/Declarations!$F$30))+IF($B51>=T_sale,Declarations!$G$30,0) -> 72.096844 | G51: =Declarations!$C$31+(Declarations!$C$4-Declarations!$C$31)*EXP(-Declarations!$D$31*$B51)+IF(Declarations!$E$31=0,0,Declarations!$E$31*($B51/Declarations!$F$31)*EXP(1-$B51/Declarations!$F$31))+IF($B51>=T_sale,Declarations!$G$31,0) -> 100.55717 | H51: =Declarations!$C$32+(Declarations!$C$7-Declarations!$C$32)*EXP(-Declarations!$D$32*$B51)+IF(Declarations!$E$32=0,0,Declarations!$E$32*($B51/Declarations!$F$32)*EXP(1-$B51/Declarations!$F$32))+IF($B51>=T_sale,Declarations!$G$32,0) -> 40.647491 | I51: =Declarations!$C$33+(Declarations!$C$8-Declarations!$C$33)*EXP(-Declarations!$D$33*$B51)+IF(Declarations!$E$33=0,0,Declarations!$E$33*($B51/Declarations!$F$33)*EXP(1-$B51/Declarations!$F$33))+IF($B51>=T_sale,Declarations!$G$33,0) -> 71.604451 | J51: =Declarations!$C$34+(Declarations!$C$10-Declarations!$C$34)*EXP(-Declarations!$D$34*$B51)+IF(Declarations!$E$34=0,0,Declarations!$E$34*($B51/Declarations!$F$34)*EXP(1-$B51/Declarations!$F$34))+IF($B51>=T_sale,Declarations!$G$34,0) -> 62.715656 | K51: =Declarations!$C$35+(Declarations!$C$4-Declarations!$C$35)*EXP(-Declarations!$D$35*$B51)+IF(Declarations!$E$35=0,0,Declarations!$E$35*($B51/Declarations!$F$35)*EXP(1-$B51/Declarations!$F$35))+IF($B51>=T_sale,Declarations!$G$35,0) -> 101.2089 | L51: =Declarations!$C$36+(Declarations!$C$7-Declarations!$C$36)*EXP(-Declarations!$D$36*$B51)+IF(Declarations!$E$36=0,0,Declarations!$E$36*($B51/Declarations!$F$36)*EXP(1-$B51/Declarations!$F$36))+IF($B51>=T_sale,Declarations!$G$36,0) -> 40.238699 | M51: =Declarations!$C$37+(Declarations!$C$8-Declarations!$C$37)*EXP(-Declarations!$D$37*$B51)+IF(Declarations!$E$37=0,0,Declarations!$E$37*($B51/Declarations!$F$37)*EXP(1-$B51/Declarations!$F$37))+IF($B51>=T_sale,Declarations!$G$37,0) -> 73.073454 | N51: =Declarations!$C$38+(Declarations!$C$10-Declarations!$C$38)*EXP(-Declarations!$D$38*$B51)+IF(Declarations!$E$38=0,0,Declarations!$E$38*($B51/Declarations!$F$38)*EXP(1-$B51/Declarations!$F$38))+IF($B51>=T_sale,Declarations!$G$38,0) -> 64.417876 | O51: =C51*USD_pt -> 540.0666 | P51: =C51*USD_pt-Floor_usd -> 190.0666 | Q51: =Risk_ceiling-F51 -> 2.9031562 | R51: =MIN(Wf_today-Idx_lo,Idx_hi-Wf_today,D51-Idx_lo,Idx_hi-D51,E51-Idx_lo,Idx_hi-E51,F51-Idx_lo,Idx_hi-F51) -> 27.903156 | S51: =G51*USD_pt -> 623.45444 | T51: =G51*USD_pt-Floor_usd -> 273.45444 | U51: =Risk_ceiling-J51 -> 12.284344 | V51: =MIN(Wf_today-Idx_lo,Idx_hi-Wf_today,H51-Idx_lo,Idx_hi-H51,I51-Idx_lo,Idx_hi-I51,J51-Idx_lo,Idx_hi-J51) -> 28.395549 | W51: =K51*USD_pt -> 627.4952 | X51: =K51*USD_pt-Floor_usd -> 277.4952 | Y51: =Risk_ceiling-N51 -> 10.582124 | Z51: =MIN(Wf_today-Idx_lo,Idx_hi-Wf_today,L51-Idx_lo,Idx_hi-L51,M51-Idx_lo,Idx_hi-M51,N51-Idx_lo,Idx_hi-N51) -> 26.926546
A52: 7 | B52: =A52/12 -> 0.58333333 | C52: =Declarations!$C$27+(Declarations!$C$4-Declarations!$C$27)*EXP(-Declarations!$D$27*$B52)+IF(Declarations!$E$27=0,0,Declarations!$E$27*($B52/Declarations!$F$27)*EXP(1-$B52/Declarations!$F$27))+IF($B52>=T_sale,Declarations!$G$27,0) -> 85.632816 | D52: =Declarations!$C$28+(Declarations!$C$7-Declarations!$C$28)*EXP(-Declarations!$D$28*$B52)+IF(Declarations!$E$28=0,0,Declarations!$E$28*($B52/Declarations!$F$28)*EXP(1-$B52/Declarations!$F$28))+IF($B52>=T_sale,Declarations!$G$28,0) -> 51.154866 | E52: =Declarations!$C$29+(Declarations!$C$8-Declarations!$C$29)*EXP(-Declarations!$D$29*$B52)+IF(Declarations!$E$29=0,0,Declarations!$E$29*($B52/Declarations!$F$29)*EXP(1-$B52/Declarations!$F$29))+IF($B52>=T_sale,Declarations!$G$29,0) -> 66.069224 | F52: =Declarations!$C$30+(Declarations!$C$10-Declarations!$C$30)*EXP(-Declarations!$D$30*$B52)+IF(Declarations!$E$30=0,0,Declarations!$E$30*($B52/Declarations!$F$30)*EXP(1-$B52/Declarations!$F$30))+IF($B52>=T_sale,Declarations!$G$30,0) -> 72.671956 | G52: =Declarations!$C$31+(Declarations!$C$4-Declarations!$C$31)*EXP(-Declarations!$D$31*$B52)+IF(Declarations!$E$31=0,0,Declarations!$E$31*($B52/Declarations!$F$31)*EXP(1-$B52/Declarations!$F$31))+IF($B52>=T_sale,Declarations!$G$31,0) -> 100.64217 | H52: =Declarations!$C$32+(Declarations!$C$7-Declarations!$C$32)*EXP(-Declarations!$D$32*$B52)+IF(Declarations!$E$32=0,0,Declarations!$E$32*($B52/Declarations!$F$32)*EXP(1-$B52/Declarations!$F$32))+IF($B52>=T_sale,Declarations!$G$32,0) -> 40.592905 | I52: =Declarations!$C$33+(Declarations!$C$8-Declarations!$C$33)*EXP(-Declarations!$D$33*$B52)+IF(Declarations!$E$33=0,0,Declarations!$E$33*($B52/Declarations!$F$33)*EXP(1-$B52/Declarations!$F$33))+IF($B52>=T_sale,Declarations!$G$33,0) -> 71.692621 | J52: =Declarations!$C$34+(Declarations!$C$10-Declarations!$C$34)*EXP(-Declarations!$D$34*$B52)+IF(Declarations!$E$34=0,0,Declarations!$E$34*($B52/Declarations!$F$34)*EXP(1-$B52/Declarations!$F$34))+IF($B52>=T_sale,Declarations!$G$34,0) -> 62.522612 | K52: =Declarations!$C$35+(Declarations!$C$4-Declarations!$C$35)*EXP(-Declarations!$D$35*$B52)+IF(Declarations!$E$35=0,0,Declarations!$E$35*($B52/Declarations!$F$35)*EXP(1-$B52/Declarations!$F$35))+IF($B52>=T_sale,Declarations!$G$35,0) -> 101.38524 | L52: =Declarations!$C$36+(Declarations!$C$7-Declarations!$C$36)*EXP(-Declarations!$D$36*$B52)+IF(Declarations!$E$36=0,0,Declarations!$E$36*($B52/Declarations!$F$36)*EXP(1-$B52/Declarations!$F$36))+IF($B52>=T_sale,Declarations!$G$36,0) -> 40.119054 | M52: =Declarations!$C$37+(Declarations!$C$8-Declarations!$C$37)*EXP(-Declarations!$D$37*$B52)+IF(Declarations!$E$37=0,0,Declarations!$E$37*($B52/Declarations!$F$37)*EXP(1-$B52/Declarations!$F$37))+IF($B52>=T_sale,Declarations!$G$37,0) -> 73.362495 | N52: =Declarations!$C$38+(Declarations!$C$10-Declarations!$C$38)*EXP(-Declarations!$D$38*$B52)+IF(Declarations!$E$38=0,0,Declarations!$E$38*($B52/Declarations!$F$38)*EXP(1-$B52/Declarations!$F$38))+IF($B52>=T_sale,Declarations!$G$38,0) -> 64.481629 | O52: =C52*USD_pt -> 530.92346 | P52: =C52*USD_pt-Floor_usd -> 180.92346 | Q52: =Risk_ceiling-F52 -> 2.3280444 | R52: =MIN(Wf_today-Idx_lo,Idx_hi-Wf_today,D52-Idx_lo,Idx_hi-D52,E52-Idx_lo,Idx_hi-E52,F52-Idx_lo,Idx_hi-F52) -> 27.328044 | S52: =G52*USD_pt -> 623.98147 | T52: =G52*USD_pt-Floor_usd -> 273.98147 | U52: =Risk_ceiling-J52 -> 12.477388 | V52: =MIN(Wf_today-Idx_lo,Idx_hi-Wf_today,H52-Idx_lo,Idx_hi-H52,I52-Idx_lo,Idx_hi-I52,J52-Idx_lo,Idx_hi-J52) -> 28.307379 | W52: =K52*USD_pt -> 628.5885 | X52: =K52*USD_pt-Floor_usd -> 278.5885 | Y52: =Risk_ceiling-N52 -> 10.518371 | Z52: =MIN(Wf_today-Idx_lo,Idx_hi-Wf_today,L52-Idx_lo,Idx_hi-L52,M52-Idx_lo,Idx_hi-M52,N52-Idx_lo,Idx_hi-N52) -> 26.637505
A53: 8 | B53: =A53/12 -> 0.66666667 | C53: =Declarations!$C$27+(Declarations!$C$4-Declarations!$C$27)*EXP(-Declarations!$D$27*$B53)+IF(Declarations!$E$27=0,0,Declarations!$E$27*($B53/Declarations!$F$27)*EXP(1-$B53/Declarations!$F$27))+IF($B53>=T_sale,Declarations!$G$27,0) -> 84.318474 | D53: =Declarations!$C$28+(Declarations!$C$7-Declarations!$C$28)*EXP(-Declarations!$D$28*$B53)+IF(Declarations!$E$28=0,0,Declarations!$E$28*($B53/Declarations!$F$28)*EXP(1-$B53/Declarations!$F$28))+IF($B53>=T_sale,Declarations!$G$28,0) -> 52.357497 | E53: =Declarations!$C$29+(Declarations!$C$8-Declarations!$C$29)*EXP(-Declarations!$D$29*$B53)+IF(Declarations!$E$29=0,0,Declarations!$E$29*($B53/Declarations!$F$29)*EXP(1-$B53/Declarations!$F$29))+IF($B53>=T_sale,Declarations!$G$29,0) -> 65.729176 | F53: =Declarations!$C$30+(Declarations!$C$10-Declarations!$C$30)*EXP(-Declarations!$D$30*$B53)+IF(Declarations!$E$30=0,0,Declarations!$E$30*($B53/Declarations!$F$30)*EXP(1-$B53/Declarations!$F$30))+IF($B53>=T_sale,Declarations!$G$30,0) -> 73.087473 | G53: =Declarations!$C$31+(Declarations!$C$4-Declarations!$C$31)*EXP(-Declarations!$D$31*$B53)+IF(Declarations!$E$31=0,0,Declarations!$E$31*($B53/Declarations!$F$31)*EXP(1-$B53/Declarations!$F$31))+IF($B53>=T_sale,Declarations!$G$31,0) -> 100.72508 | H53: =Declarations!$C$32+(Declarations!$C$7-Declarations!$C$32)*EXP(-Declarations!$D$32*$B53)+IF(Declarations!$E$32=0,0,Declarations!$E$32*($B53/Declarations!$F$32)*EXP(1-$B53/Declarations!$F$32))+IF($B53>=T_sale,Declarations!$G$32,0) -> 40.539445 | I53: =Declarations!$C$33+(Declarations!$C$8-Declarations!$C$33)*EXP(-Declarations!$D$33*$B53)+IF(Declarations!$E$33=0,0,Declarations!$E$33*($B53/Declarations!$F$33)*EXP(1-$B53/Declarations!$F$33))+IF($B53>=T_sale,Declarations!$G$33,0) -> 71.777545 | J53: =Declarations!$C$34+(Declarations!$C$10-Declarations!$C$34)*EXP(-Declarations!$D$34*$B53)+IF(Declarations!$E$34=0,0,Declarations!$E$34*($B53/Declarations!$F$34)*EXP(1-$B53/Declarations!$F$34))+IF($B53>=T_sale,Declarations!$G$34,0) -> 62.335117 | K53: =Declarations!$C$35+(Declarations!$C$4-Declarations!$C$35)*EXP(-Declarations!$D$35*$B53)+IF(Declarations!$E$35=0,0,Declarations!$E$35*($B53/Declarations!$F$35)*EXP(1-$B53/Declarations!$F$35))+IF($B53>=T_sale,Declarations!$G$35,0) -> 101.55509 | L53: =Declarations!$C$36+(Declarations!$C$7-Declarations!$C$36)*EXP(-Declarations!$D$36*$B53)+IF(Declarations!$E$36=0,0,Declarations!$E$36*($B53/Declarations!$F$36)*EXP(1-$B53/Declarations!$F$36))+IF($B53>=T_sale,Declarations!$G$36,0) -> 40.001387 | M53: =Declarations!$C$37+(Declarations!$C$8-Declarations!$C$37)*EXP(-Declarations!$D$37*$B53)+IF(Declarations!$E$37=0,0,Declarations!$E$37*($B53/Declarations!$F$37)*EXP(1-$B53/Declarations!$F$37))+IF($B53>=T_sale,Declarations!$G$37,0) -> 73.63744 | N53: =Declarations!$C$38+(Declarations!$C$10-Declarations!$C$38)*EXP(-Declarations!$D$38*$B53)+IF(Declarations!$E$38=0,0,Declarations!$E$38*($B53/Declarations!$F$38)*EXP(1-$B53/Declarations!$F$38))+IF($B53>=T_sale,Declarations!$G$38,0) -> 64.543808 | O53: =C53*USD_pt -> 522.77454 | P53: =C53*USD_pt-Floor_usd -> 172.77454 | Q53: =Risk_ceiling-F53 -> 1.9125266 | R53: =MIN(Wf_today-Idx_lo,Idx_hi-Wf_today,D53-Idx_lo,Idx_hi-D53,E53-Idx_lo,Idx_hi-E53,F53-Idx_lo,Idx_hi-F53) -> 26.912527 | S53: =G53*USD_pt -> 624.49548 | T53: =G53*USD_pt-Floor_usd -> 274.49548 | U53: =Risk_ceiling-J53 -> 12.664883 | V53: =MIN(Wf_today-Idx_lo,Idx_hi-Wf_today,H53-Idx_lo,Idx_hi-H53,I53-Idx_lo,Idx_hi-I53,J53-Idx_lo,Idx_hi-J53) -> 28.222455 | W53: =K53*USD_pt -> 629.64156 | X53: =K53*USD_pt-Floor_usd -> 279.64156 | Y53: =Risk_ceiling-N53 -> 10.456192 | Z53: =MIN(Wf_today-Idx_lo,Idx_hi-Wf_today,L53-Idx_lo,Idx_hi-L53,M53-Idx_lo,Idx_hi-M53,N53-Idx_lo,Idx_hi-N53) -> 26.36256
A54: 9 | B54: =A54/12 -> 0.75 | C54: =Declarations!$C$27+(Declarations!$C$4-Declarations!$C$27)*EXP(-Declarations!$D$27*$B54)+IF(Declarations!$E$27=0,0,Declarations!$E$27*($B54/Declarations!$F$27)*EXP(1-$B54/Declarations!$F$27))+IF($B54>=T_sale,Declarations!$G$27,0) -> 83.153901 | D54: =Declarations!$C$28+(Declarations!$C$7-Declarations!$C$28)*EXP(-Declarations!$D$28*$B54)+IF(Declarations!$E$28=0,0,Declarations!$E$28*($B54/Declarations!$F$28)*EXP(1-$B54/Declarations!$F$28))+IF($B54>=T_sale,Declarations!$G$28,0) -> 53.506252 | E54: =Declarations!$C$29+(Declarations!$C$8-Declarations!$C$29)*EXP(-Declarations!$D$29*$B54)+IF(Declarations!$E$29=0,0,Declarations!$E$29*($B54/Declarations!$F$29)*EXP(1-$B54/Declarations!$F$29))+IF($B54>=T_sale,Declarations!$G$29,0) -> 65.457019 | F54: =Declarations!$C$30+(Declarations!$C$10-Declarations!$C$30)*EXP(-Declarations!$D$30*$B54)+IF(Declarations!$E$30=0,0,Declarations!$E$30*($B54/Declarations!$F$30)*EXP(1-$B54/Declarations!$F$30))+IF($B54>=T_sale,Declarations!$G$30,0) -> 73.361812 | G54: =Declarations!$C$31+(Declarations!$C$4-Declarations!$C$31)*EXP(-Declarations!$D$31*$B54)+IF(Declarations!$E$31=0,0,Declarations!$E$31*($B54/Declarations!$F$31)*EXP(1-$B54/Declarations!$F$31))+IF($B54>=T_sale,Declarations!$G$31,0) -> 100.80594 | H54: =Declarations!$C$32+(Declarations!$C$7-Declarations!$C$32)*EXP(-Declarations!$D$32*$B54)+IF(Declarations!$E$32=0,0,Declarations!$E$32*($B54/Declarations!$F$32)*EXP(1-$B54/Declarations!$F$32))+IF($B54>=T_sale,Declarations!$G$32,0) -> 40.487087 | I54: =Declarations!$C$33+(Declarations!$C$8-Declarations!$C$33)*EXP(-Declarations!$D$33*$B54)+IF(Declarations!$E$33=0,0,Declarations!$E$33*($B54/Declarations!$F$33)*EXP(1-$B54/Declarations!$F$33))+IF($B54>=T_sale,Declarations!$G$33,0) -> 71.859344 | J54: =Declarations!$C$34+(Declarations!$C$10-Declarations!$C$34)*EXP(-Declarations!$D$34*$B54)+IF(Declarations!$E$34=0,0,Declarations!$E$34*($B54/Declarations!$F$34)*EXP(1-$B54/Declarations!$F$34))+IF($B54>=T_sale,Declarations!$G$34,0) -> 62.153011 | K54: =Declarations!$C$35+(Declarations!$C$4-Declarations!$C$35)*EXP(-Declarations!$D$35*$B54)+IF(Declarations!$E$35=0,0,Declarations!$E$35*($B54/Declarations!$F$35)*EXP(1-$B54/Declarations!$F$35))+IF($B54>=T_sale,Declarations!$G$35,0) -> 101.71869 | L54: =Declarations!$C$36+(Declarations!$C$7-Declarations!$C$36)*EXP(-Declarations!$D$36*$B54)+IF(Declarations!$E$36=0,0,Declarations!$E$36*($B54/Declarations!$F$36)*EXP(1-$B54/Declarations!$F$36))+IF($B54>=T_sale,Declarations!$G$36,0) -> 39.885664 | M54: =Declarations!$C$37+(Declarations!$C$8-Declarations!$C$37)*EXP(-Declarations!$D$37*$B54)+IF(Declarations!$E$37=0,0,Declarations!$E$37*($B54/Declarations!$F$37)*EXP(1-$B54/Declarations!$F$37))+IF($B54>=T_sale,Declarations!$G$37,0) -> 73.898975 | N54: =Declarations!$C$38+(Declarations!$C$10-Declarations!$C$38)*EXP(-Declarations!$D$38*$B54)+IF(Declarations!$E$38=0,0,Declarations!$E$38*($B54/Declarations!$F$38)*EXP(1-$B54/Declarations!$F$38))+IF($B54>=T_sale,Declarations!$G$38,0) -> 64.604451 | O54: =C54*USD_pt -> 515.55419 | P54: =C54*USD_pt-Floor_usd -> 165.55419 | Q54: =Risk_ceiling-F54 -> 1.6381883 | R54: =MIN(Wf_today-Idx_lo,Idx_hi-Wf_today,D54-Idx_lo,Idx_hi-D54,E54-Idx_lo,Idx_hi-E54,F54-Idx_lo,Idx_hi-F54) -> 26.638188 | S54: =G54*USD_pt -> 624.9968 | T54: =G54*USD_pt-Floor_usd -> 274.9968 | U54: =Risk_ceiling-J54 -> 12.846989 | V54: =MIN(Wf_today-Idx_lo,Idx_hi-Wf_today,H54-Idx_lo,Idx_hi-H54,I54-Idx_lo,Idx_hi-I54,J54-Idx_lo,Idx_hi-J54) -> 28.140656 | W54: =K54*USD_pt -> 630.65587 | X54: =K54*USD_pt-Floor_usd -> 280.65587 | Y54: =Risk_ceiling-N54 -> 10.395549 | Z54: =MIN(Wf_today-Idx_lo,Idx_hi-Wf_today,L54-Idx_lo,Idx_hi-L54,M54-Idx_lo,Idx_hi-M54,N54-Idx_lo,Idx_hi-N54) -> 26.101025
A55: 10 | B55: =A55/12 -> 0.83333333 | C55: =Declarations!$C$27+(Declarations!$C$4-Declarations!$C$27)*EXP(-Declarations!$D$27*$B55)+IF(Declarations!$E$27=0,0,Declarations!$E$27*($B55/Declarations!$F$27)*EXP(1-$B55/Declarations!$F$27))+IF($B55>=T_sale,Declarations!$G$27,0) -> 82.129102 | D55: =Declarations!$C$28+(Declarations!$C$7-Declarations!$C$28)*EXP(-Declarations!$D$28*$B55)+IF(Declarations!$E$28=0,0,Declarations!$E$28*($B55/Declarations!$F$28)*EXP(1-$B55/Declarations!$F$28))+IF($B55>=T_sale,Declarations!$G$28,0) -> 54.603543 | E55: =Declarations!$C$29+(Declarations!$C$8-Declarations!$C$29)*EXP(-Declarations!$D$29*$B55)+IF(Declarations!$E$29=0,0,Declarations!$E$29*($B55/Declarations!$F$29)*EXP(1-$B55/Declarations!$F$29))+IF($B55>=T_sale,Declarations!$G$29,0) -> 65.246439 | F55: =Declarations!$C$30+(Declarations!$C$10-Declarations!$C$30)*EXP(-Declarations!$D$30*$B55)+IF(Declarations!$E$30=0,0,Declarations!$E$30*($B55/Declarations!$F$30)*EXP(1-$B55/Declarations!$F$30))+IF($B55>=T_sale,Declarations!$G$30,0) -> 73.511646 | G55: =Declarations!$C$31+(Declarations!$C$4-Declarations!$C$31)*EXP(-Declarations!$D$31*$B55)+IF(Declarations!$E$31=0,0,Declarations!$E$31*($B55/Declarations!$F$31)*EXP(1-$B55/Declarations!$F$31))+IF($B55>=T_sale,Declarations!$G$31,0) -> 100.8848 | H55: =Declarations!$C$32+(Declarations!$C$7-Declarations!$C$32)*EXP(-Declarations!$D$32*$B55)+IF(Declarations!$E$32=0,0,Declarations!$E$32*($B55/Declarations!$F$32)*EXP(1-$B55/Declarations!$F$32))+IF($B55>=T_sale,Declarations!$G$32,0) -> 40.435809 | I55: =Declarations!$C$33+(Declarations!$C$8-Declarations!$C$33)*EXP(-Declarations!$D$33*$B55)+IF(Declarations!$E$33=0,0,Declarations!$E$33*($B55/Declarations!$F$33)*EXP(1-$B55/Declarations!$F$33))+IF($B55>=T_sale,Declarations!$G$33,0) -> 71.938132 | J55: =Declarations!$C$34+(Declarations!$C$10-Declarations!$C$34)*EXP(-Declarations!$D$34*$B55)+IF(Declarations!$E$34=0,0,Declarations!$E$34*($B55/Declarations!$F$34)*EXP(1-$B55/Declarations!$F$34))+IF($B55>=T_sale,Declarations!$G$34,0) -> 61.97614 | K55: =Declarations!$C$35+(Declarations!$C$4-Declarations!$C$35)*EXP(-Declarations!$D$35*$B55)+IF(Declarations!$E$35=0,0,Declarations!$E$35*($B55/Declarations!$F$35)*EXP(1-$B55/Declarations!$F$35))+IF($B55>=T_sale,Declarations!$G$35,0) -> 101.87626 | L55: =Declarations!$C$36+(Declarations!$C$7-Declarations!$C$36)*EXP(-Declarations!$D$36*$B55)+IF(Declarations!$E$36=0,0,Declarations!$E$36*($B55/Declarations!$F$36)*EXP(1-$B55/Declarations!$F$36))+IF($B55>=T_sale,Declarations!$G$36,0) -> 39.771854 | M55: =Declarations!$C$37+(Declarations!$C$8-Declarations!$C$37)*EXP(-Declarations!$D$37*$B55)+IF(Declarations!$E$37=0,0,Declarations!$E$37*($B55/Declarations!$F$37)*EXP(1-$B55/Declarations!$F$37))+IF($B55>=T_sale,Declarations!$G$37,0) -> 74.147755 | N55: =Declarations!$C$38+(Declarations!$C$10-Declarations!$C$38)*EXP(-Declarations!$D$38*$B55)+IF(Declarations!$E$38=0,0,Declarations!$E$38*($B55/Declarations!$F$38)*EXP(1-$B55/Declarations!$F$38))+IF($B55>=T_sale,Declarations!$G$38,0) -> 64.663598 | O55: =C55*USD_pt -> 509.20043 | P55: =C55*USD_pt-Floor_usd -> 159.20043 | Q55: =Risk_ceiling-F55 -> 1.4883537 | R55: =MIN(Wf_today-Idx_lo,Idx_hi-Wf_today,D55-Idx_lo,Idx_hi-D55,E55-Idx_lo,Idx_hi-E55,F55-Idx_lo,Idx_hi-F55) -> 26.488354 | S55: =G55*USD_pt -> 625.48574 | T55: =G55*USD_pt-Floor_usd -> 275.48574 | U55: =Risk_ceiling-J55 -> 13.02386 | V55: =MIN(Wf_today-Idx_lo,Idx_hi-Wf_today,H55-Idx_lo,Idx_hi-H55,I55-Idx_lo,Idx_hi-I55,J55-Idx_lo,Idx_hi-J55) -> 28.061868 | W55: =K55*USD_pt -> 631.63284 | X55: =K55*USD_pt-Floor_usd -> 281.63284 | Y55: =Risk_ceiling-N55 -> 10.336402 | Z55: =MIN(Wf_today-Idx_lo,Idx_hi-Wf_today,L55-Idx_lo,Idx_hi-L55,M55-Idx_lo,Idx_hi-M55,N55-Idx_lo,Idx_hi-N55) -> 25.852245
A56: 11 | B56: =A56/12 -> 0.91666667 | C56: =Declarations!$C$27+(Declarations!$C$4-Declarations!$C$27)*EXP(-Declarations!$D$27*$B56)+IF(Declarations!$E$27=0,0,Declarations!$E$27*($B56/Declarations!$F$27)*EXP(1-$B56/Declarations!$F$27))+IF($B56>=T_sale,Declarations!$G$27,0) -> 81.234648 | D56: =Declarations!$C$28+(Declarations!$C$7-Declarations!$C$28)*EXP(-Declarations!$D$28*$B56)+IF(Declarations!$E$28=0,0,Declarations!$E$28*($B56/Declarations!$F$28)*EXP(1-$B56/Declarations!$F$28))+IF($B56>=T_sale,Declarations!$G$28,0) -> 55.651678 | E56: =Declarations!$C$29+(Declarations!$C$8-Declarations!$C$29)*EXP(-Declarations!$D$29*$B56)+IF(Declarations!$E$29=0,0,Declarations!$E$29*($B56/Declarations!$F$29)*EXP(1-$B56/Declarations!$F$29))+IF($B56>=T_sale,Declarations!$G$29,0) -> 65.091607 | F56: =Declarations!$C$30+(Declarations!$C$10-Declarations!$C$30)*EXP(-Declarations!$D$30*$B56)+IF(Declarations!$E$30=0,0,Declarations!$E$30*($B56/Declarations!$F$30)*EXP(1-$B56/Declarations!$F$30))+IF($B56>=T_sale,Declarations!$G$30,0) -> 73.552064 | G56: =Declarations!$C$31+(Declarations!$C$4-Declarations!$C$31)*EXP(-Declarations!$D$31*$B56)+IF(Declarations!$E$31=0,0,Declarations!$E$31*($B56/Declarations!$F$31)*EXP(1-$B56/Declarations!$F$31))+IF($B56>=T_sale,Declarations!$G$31,0) -> 100.96171 | H56: =Declarations!$C$32+(Declarations!$C$7-Declarations!$C$32)*EXP(-Declarations!$D$32*$B56)+IF(Declarations!$E$32=0,0,Declarations!$E$32*($B56/Declarations!$F$32)*EXP(1-$B56/Declarations!$F$32))+IF($B56>=T_sale,Declarations!$G$32,0) -> 40.385588 | I56: =Declarations!$C$33+(Declarations!$C$8-Declarations!$C$33)*EXP(-Declarations!$D$33*$B56)+IF(Declarations!$E$33=0,0,Declarations!$E$33*($B56/Declarations!$F$33)*EXP(1-$B56/Declarations!$F$33))+IF($B56>=T_sale,Declarations!$G$33,0) -> 72.01402 | J56: =Declarations!$C$34+(Declarations!$C$10-Declarations!$C$34)*EXP(-Declarations!$D$34*$B56)+IF(Declarations!$E$34=0,0,Declarations!$E$34*($B56/Declarations!$F$34)*EXP(1-$B56/Declarations!$F$34))+IF($B56>=T_sale,Declarations!$G$34,0) -> 61.804353 | K56: =Declarations!$C$35+(Declarations!$C$4-Declarations!$C$35)*EXP(-Declarations!$D$35*$B56)+IF(Declarations!$E$35=0,0,Declarations!$E$35*($B56/Declarations!$F$35)*EXP(1-$B56/Declarations!$F$35))+IF($B56>=T_sale,Declarations!$G$35,0) -> 102.02804 | L56: =Declarations!$C$36+(Declarations!$C$7-Declarations!$C$36)*EXP(-Declarations!$D$36*$B56)+IF(Declarations!$E$36=0,0,Declarations!$E$36*($B56/Declarations!$F$36)*EXP(1-$B56/Declarations!$F$36))+IF($B56>=T_sale,Declarations!$G$36,0) -> 39.659925 | M56: =Declarations!$C$37+(Declarations!$C$8-Declarations!$C$37)*EXP(-Declarations!$D$37*$B56)+IF(Declarations!$E$37=0,0,Declarations!$E$37*($B56/Declarations!$F$37)*EXP(1-$B56/Declarations!$F$37))+IF($B56>=T_sale,Declarations!$G$37,0) -> 74.384402 | N56: =Declarations!$C$38+(Declarations!$C$10-Declarations!$C$38)*EXP(-Declarations!$D$38*$B56)+IF(Declarations!$E$38=0,0,Declarations!$E$38*($B56/Declarations!$F$38)*EXP(1-$B56/Declarations!$F$38))+IF($B56>=T_sale,Declarations!$G$38,0) -> 64.721284 | O56: =C56*USD_pt -> 503.65482 | P56: =C56*USD_pt-Floor_usd -> 153.65482 | Q56: =Risk_ceiling-F56 -> 1.4479365 | R56: =MIN(Wf_today-Idx_lo,Idx_hi-Wf_today,D56-Idx_lo,Idx_hi-D56,E56-Idx_lo,Idx_hi-E56,F56-Idx_lo,Idx_hi-F56) -> 26.447936 | S56: =G56*USD_pt -> 625.96261 | T56: =G56*USD_pt-Floor_usd -> 275.96261 | U56: =Risk_ceiling-J56 -> 13.195647 | V56: =MIN(Wf_today-Idx_lo,Idx_hi-Wf_today,H56-Idx_lo,Idx_hi-H56,I56-Idx_lo,Idx_hi-I56,J56-Idx_lo,Idx_hi-J56) -> 27.98598 | W56: =K56*USD_pt -> 632.57385 | X56: =K56*USD_pt-Floor_usd -> 282.57385 | Y56: =Risk_ceiling-N56 -> 10.278716 | Z56: =MIN(Wf_today-Idx_lo,Idx_hi-Wf_today,L56-Idx_lo,Idx_hi-L56,M56-Idx_lo,Idx_hi-M56,N56-Idx_lo,Idx_hi-N56) -> 25.615598
... A105: 60 | B105: =A105/12 -> 5 | C105: =Declarations!$C$27+(Declarations!$C$4-Declarations!$C$27)*EXP(-Declarations!$D$27*$B105)+IF(Declarations!$E$27=0,0,Declarations!$E$27*($B105/Declarations!$F$27)*EXP(1-$B105/Declarations!$F$27))+IF($B105>=T_sale,Declarations!$G$27,0) -> 94.295601 | D105: =Declarations!$C$28+(Declarations!$C$7-Declarations!$C$28)*EXP(-Declarations!$D$28*$B105)+IF(Declarations!$E$28=0,0,Declarations!$E$28*($B105/Declarations!$F$28)*EXP(1-$B105/Declarations!$F$28))+IF($B105>=T_sale,Declarations!$G$28,0) -> 75.634669 | E105: =Declarations!$C$29+(Declarations!$C$8-Declarations!$C$29)*EXP(-Declarations!$D$29*$B105)+IF(Declarations!$E$29=0,0,Declarations!$E$29*($B105/Declarations!$F$29)*EXP(1-$B105/Declarations!$F$29))+IF($B105>=T_sale,Declarations!$G$29,0) -> 73.598331 | F105: =Declarations!$C$30+(Declarations!$C$10-Declarations!$C$30)*EXP(-Declarations!$D$30*$B105)+IF(Declarations!$E$30=0,0,Declarations!$E$30*($B105/Declarations!$F$30)*EXP(1-$B105/Declarations!$F$30))+IF($B105>=T_sale,Declarations!$G$30,0) -> 55.21775 | G105: =Declarations!$C$31+(Declarations!$C$4-Declarations!$C$31)*EXP(-Declarations!$D$31*$B105)+IF(Declarations!$E$31=0,0,Declarations!$E$31*($B105/Declarations!$F$31)*EXP(1-$B105/Declarations!$F$31))+IF($B105>=T_sale,Declarations!$G$31,0) -> 121.10748 | H105: =Declarations!$C$32+(Declarations!$C$7-Declarations!$C$32)*EXP(-Declarations!$D$32*$B105)+IF(Declarations!$E$32=0,0,Declarations!$E$32*($B105/Declarations!$F$32)*EXP(1-$B105/Declarations!$F$32))+IF($B105>=T_sale,Declarations!$G$32,0) -> 38.859514 | I105: =Declarations!$C$33+(Declarations!$C$8-Declarations!$C$33)*EXP(-Declarations!$D$33*$B105)+IF(Declarations!$E$33=0,0,Declarations!$E$33*($B105/Declarations!$F$33)*EXP(1-$B105/Declarations!$F$33))+IF($B105>=T_sale,Declarations!$G$33,0) -> 73.683802 | J105: =Declarations!$C$34+(Declarations!$C$10-Declarations!$C$34)*EXP(-Declarations!$D$34*$B105)+IF(Declarations!$E$34=0,0,Declarations!$E$34*($B105/Declarations!$F$34)*EXP(1-$B105/Declarations!$F$34))+IF($B105>=T_sale,Declarations!$G$34,0) -> 49.390192 | K105: =Declarations!$C$35+(Declarations!$C$4-Declarations!$C$35)*EXP(-Declarations!$D$35*$B105)+IF(Declarations!$E$35=0,0,Declarations!$E$35*($B105/Declarations!$F$35)*EXP(1-$B105/Declarations!$F$35))+IF($B105>=T_sale,Declarations!$G$35,0) -> 105.3676 | L105: =Declarations!$C$36+(Declarations!$C$7-Declarations!$C$36)*EXP(-Declarations!$D$36*$B105)+IF(Declarations!$E$36=0,0,Declarations!$E$36*($B105/Declarations!$F$36)*EXP(1-$B105/Declarations!$F$36))+IF($B105>=T_sale,Declarations!$G$36,0) -> 35.943036 | M105: =Declarations!$C$37+(Declarations!$C$8-Declarations!$C$37)*EXP(-Declarations!$D$37*$B105)+IF(Declarations!$E$37=0,0,Declarations!$E$37*($B105/Declarations!$F$37)*EXP(1-$B105/Declarations!$F$37))+IF($B105>=T_sale,Declarations!$G$37,0) -> 78.601703 | N105: =Declarations!$C$38+(Declarations!$C$10-Declarations!$C$38)*EXP(-Declarations!$D$38*$B105)+IF(Declarations!$E$38=0,0,Declarations!$E$38*($B105/Declarations!$F$38)*EXP(1-$B105/Declarations!$F$38))+IF($B105>=T_sale,Declarations!$G$38,0) -> 66.33061 | O105: =C105*USD_pt -> 584.63273 | P105: =C105*USD_pt-Floor_usd -> 234.63273 | Q105: =Risk_ceiling-F105 -> 19.78225 | R105: =MIN(Wf_today-Idx_lo,Idx_hi-Wf_today,D105-Idx_lo,Idx_hi-D105,E105-Idx_lo,Idx_hi-E105,F105-Idx_lo,Idx_hi-F105) -> 24.365331 | S105: =G105*USD_pt -> 750.86637 | T105: =G105*USD_pt-Floor_usd -> 400.86637 | U105: =Risk_ceiling-J105 -> 25.609808 | V105: =MIN(Wf_today-Idx_lo,Idx_hi-Wf_today,H105-Idx_lo,Idx_hi-H105,I105-Idx_lo,Idx_hi-I105,J105-Idx_lo,Idx_hi-J105) -> 26.316198 | W105: =K105*USD_pt -> 653.27915 | X105: =K105*USD_pt-Floor_usd -> 303.27915 | Y105: =Risk_ceiling-N105 -> 8.6693905 | Z105: =MIN(Wf_today-Idx_lo,Idx_hi-Wf_today,L105-Idx_lo,Idx_hi-L105,M105-Idx_lo,Idx_hi-M105,N105-Idx_lo,Idx_hi-N105) -> 21.398297

Sheet Blend
A1: A wall that is not convex: blending two configurations (Theorem 5.2(iii); Figure 5.1; Theorem 5.5; AXIOM Lab 1.5, step 2)
A3: Configuration | B3: Legacy platform | C3: New platform
A4: A | B4: 80 | C4: 10
A5: B | B5: 0 | C5: 90
A6: Capacity budget: legacy + new at most | B6: 100
A7: Minimum efficient scale: legacy 0 or at least | B7: 60
A9: Weight on A | B9: Legacy | C9: New | D9: Budget slack | E9: Minimum-scale g = min(legacy, 60 - legacy) | F9: Under the budget alone | G9: With the minimum scale
A10: 0 | B10: =A10*$B$4+(1-A10)*$B$5 -> 0 | C10: =A10*$C$4+(1-A10)*$C$5 -> 90 | D10: =$B$6-B10-C10 -> 10 | E10: =MIN(B10,$B$7-B10) -> 0 | F10: =IF(AND(D10>=-0.000000001,B10>=0,C10>=0),"feasible","infeasible") -> feasible | G10: =IF(AND(F10="feasible",E10<=0.000000001),"feasible","infeasible") -> feasible
A11: 0.05 | B11: =A11*$B$4+(1-A11)*$B$5 -> 4 | C11: =A11*$C$4+(1-A11)*$C$5 -> 86 | D11: =$B$6-B11-C11 -> 10 | E11: =MIN(B11,$B$7-B11) -> 4 | F11: =IF(AND(D11>=-0.000000001,B11>=0,C11>=0),"feasible","infeasible") -> feasible | G11: =IF(AND(F11="feasible",E11<=0.000000001),"feasible","infeasible") -> infeasible
A12: 0.1 | B12: =A12*$B$4+(1-A12)*$B$5 -> 8 | C12: =A12*$C$4+(1-A12)*$C$5 -> 82 | D12: =$B$6-B12-C12 -> 10 | E12: =MIN(B12,$B$7-B12) -> 8 | F12: =IF(AND(D12>=-0.000000001,B12>=0,C12>=0),"feasible","infeasible") -> feasible | G12: =IF(AND(F12="feasible",E12<=0.000000001),"feasible","infeasible") -> infeasible
A13: 0.15 | B13: =A13*$B$4+(1-A13)*$B$5 -> 12 | C13: =A13*$C$4+(1-A13)*$C$5 -> 78 | D13: =$B$6-B13-C13 -> 10 | E13: =MIN(B13,$B$7-B13) -> 12 | F13: =IF(AND(D13>=-0.000000001,B13>=0,C13>=0),"feasible","infeasible") -> feasible | G13: =IF(AND(F13="feasible",E13<=0.000000001),"feasible","infeasible") -> infeasible
A14: 0.2 | B14: =A14*$B$4+(1-A14)*$B$5 -> 16 | C14: =A14*$C$4+(1-A14)*$C$5 -> 74 | D14: =$B$6-B14-C14 -> 10 | E14: =MIN(B14,$B$7-B14) -> 16 | F14: =IF(AND(D14>=-0.000000001,B14>=0,C14>=0),"feasible","infeasible") -> feasible | G14: =IF(AND(F14="feasible",E14<=0.000000001),"feasible","infeasible") -> infeasible
A15: 0.25 | B15: =A15*$B$4+(1-A15)*$B$5 -> 20 | C15: =A15*$C$4+(1-A15)*$C$5 -> 70 | D15: =$B$6-B15-C15 -> 10 | E15: =MIN(B15,$B$7-B15) -> 20 | F15: =IF(AND(D15>=-0.000000001,B15>=0,C15>=0),"feasible","infeasible") -> feasible | G15: =IF(AND(F15="feasible",E15<=0.000000001),"feasible","infeasible") -> infeasible
A16: 0.3 | B16: =A16*$B$4+(1-A16)*$B$5 -> 24 | C16: =A16*$C$4+(1-A16)*$C$5 -> 66 | D16: =$B$6-B16-C16 -> 10 | E16: =MIN(B16,$B$7-B16) -> 24 | F16: =IF(AND(D16>=-0.000000001,B16>=0,C16>=0),"feasible","infeasible") -> feasible | G16: =IF(AND(F16="feasible",E16<=0.000000001),"feasible","infeasible") -> infeasible
A17: 0.35 | B17: =A17*$B$4+(1-A17)*$B$5 -> 28 | C17: =A17*$C$4+(1-A17)*$C$5 -> 62 | D17: =$B$6-B17-C17 -> 10 | E17: =MIN(B17,$B$7-B17) -> 28 | F17: =IF(AND(D17>=-0.000000001,B17>=0,C17>=0),"feasible","infeasible") -> feasible | G17: =IF(AND(F17="feasible",E17<=0.000000001),"feasible","infeasible") -> infeasible
A18: 0.4 | B18: =A18*$B$4+(1-A18)*$B$5 -> 32 | C18: =A18*$C$4+(1-A18)*$C$5 -> 58 | D18: =$B$6-B18-C18 -> 10 | E18: =MIN(B18,$B$7-B18) -> 28 | F18: =IF(AND(D18>=-0.000000001,B18>=0,C18>=0),"feasible","infeasible") -> feasible | G18: =IF(AND(F18="feasible",E18<=0.000000001),"feasible","infeasible") -> infeasible
A19: 0.45 | B19: =A19*$B$4+(1-A19)*$B$5 -> 36 | C19: =A19*$C$4+(1-A19)*$C$5 -> 54 | D19: =$B$6-B19-C19 -> 10 | E19: =MIN(B19,$B$7-B19) -> 24 | F19: =IF(AND(D19>=-0.000000001,B19>=0,C19>=0),"feasible","infeasible") -> feasible | G19: =IF(AND(F19="feasible",E19<=0.000000001),"feasible","infeasible") -> infeasible
A20: 0.5 | B20: =A20*$B$4+(1-A20)*$B$5 -> 40 | C20: =A20*$C$4+(1-A20)*$C$5 -> 50 | D20: =$B$6-B20-C20 -> 10 | E20: =MIN(B20,$B$7-B20) -> 20 | F20: =IF(AND(D20>=-0.000000001,B20>=0,C20>=0),"feasible","infeasible") -> feasible | G20: =IF(AND(F20="feasible",E20<=0.000000001),"feasible","infeasible") -> infeasible
A21: 0.55 | B21: =A21*$B$4+(1-A21)*$B$5 -> 44 | C21: =A21*$C$4+(1-A21)*$C$5 -> 46 | D21: =$B$6-B21-C21 -> 10 | E21: =MIN(B21,$B$7-B21) -> 16 | F21: =IF(AND(D21>=-0.000000001,B21>=0,C21>=0),"feasible","infeasible") -> feasible | G21: =IF(AND(F21="feasible",E21<=0.000000001),"feasible","infeasible") -> infeasible
... A30: 1 | B30: =A30*$B$4+(1-A30)*$B$5 -> 80 | C30: =A30*$C$4+(1-A30)*$C$5 -> 10 | D30: =$B$6-B30-C30 -> 10 | E30: =MIN(B30,$B$7-B30) -> -20 | F30: =IF(AND(D30>=-0.000000001,B30>=0,C30>=0),"feasible","infeasible") -> feasible | G30: =IF(AND(F30="feasible",E30<=0.000000001),"feasible","infeasible") -> feasible
A32: Blends feasible under the budget alone (of 21) | B32: =COUNTIF(F10:F30,"feasible") -> 21
A33: Blends feasible with the minimum scale (of 21) | B33: =COUNTIF(G10:G30,"feasible") -> 7
A34: Minimum-scale g at the 50/50 blend (legacy 40, new 50) | B34: =E20 -> 20
A35: Smallest positive weight on A that is feasible: 60 / 80 | B35: =B7/B4 -> 0.75
A36: Both pure configurations are feasible; the 50/50 blend runs legacy at 40, too small to run economically and too large to have been shut (Section 5.4).
A38: Theorem 5.5: k | B38: Leverage 4.5 - 1/k | C38: Weak covenant (at most 4.5) | D38: Strict covenant (below 4.5)
A39: 1 | B39: =Covenant-1/A39 -> 3.5 | C39: =IF(B39<=Covenant,"feasible","infeasible") -> feasible | D39: =IF(B39<Covenant,"feasible","infeasible") -> feasible
A40: 2 | B40: =Covenant-1/A40 -> 4 | C40: =IF(B40<=Covenant,"feasible","infeasible") -> feasible | D40: =IF(B40<Covenant,"feasible","infeasible") -> feasible
A41: 3 | B41: =Covenant-1/A41 -> 4.1666667 | C41: =IF(B41<=Covenant,"feasible","infeasible") -> feasible | D41: =IF(B41<Covenant,"feasible","infeasible") -> feasible
A42: 4 | B42: =Covenant-1/A42 -> 4.25 | C42: =IF(B42<=Covenant,"feasible","infeasible") -> feasible | D42: =IF(B42<Covenant,"feasible","infeasible") -> feasible
A43: 5 | B43: =Covenant-1/A43 -> 4.3 | C43: =IF(B43<=Covenant,"feasible","infeasible") -> feasible | D43: =IF(B43<Covenant,"feasible","infeasible") -> feasible
A44: 6 | B44: =Covenant-1/A44 -> 4.3333333 | C44: =IF(B44<=Covenant,"feasible","infeasible") -> feasible | D44: =IF(B44<Covenant,"feasible","infeasible") -> feasible
A45: the limit | B45: =Covenant -> 4.5 | C45: =IF(B45<=Covenant,"feasible","infeasible") -> feasible | D45: =IF(B45<Covenant,"feasible","infeasible") -> infeasible
A46: Written strictly, the covenant excludes the state in which it binds: feasible states converge to an infeasible limit, and no feasible state is the most levered (Theorem 5.5(iii)).

Sheet PathSampling
A1: Sample a path: the digital program's liquidity quarter by quarter and half-year by half-year (Definition 5.6; Propositions 5.3-5.4; Figure 5.2; AXIOM Lab 1.5, step 3)
A2: Equation 1.B.1 as a system in three numbers, (x, z1, z2): z2 is the trough term, z1 drives it, and x - z2 relaxes toward the target. The step over a spacing d is exact: y = x - z2 becomes T + (y - T)e^(-kd); z1 becomes z1 e^(-d/tau); z2 becomes (z2 + d z1)e^(-d/tau); x is the new y plus the new z2.
A4: Parameter | B4: Value | I4: Proposition 5.3 | J4: Value
A5: Target T | B5: =Declarations!C27 -> 112 | I5: Phases join at year 2 (liquidity index) | J5: =C23 -> 78.040976
A6: Speed k (a year) | B6: =Declarations!D27 -> 0.35 | I6: Largest |quarterly steps - closed form| | J6: =MAX(G15:G35) -> 0
A7: Trough (sign x depth) D | B7: =Declarations!E27 -> -28 | I7: Largest |half-yearly - two quarterly steps| | J7: =MAX(O15:O25) -> 0
A8: Trough time tau (years) | B8: =Declarations!F27 -> 2 | I8: Largest |build + scale-up - whole path| | J8: =MAX(G39:G51) -> 0
A9: Liquidity today (index) | B9: =Liq_today -> 100 | I9: Twenty quarters back: today's liquidity | J9: =C75 -> 100
A10: z1 at the start, D e / tau | B10: =B7*EXP(1)/B8 -> -38.055946 | I10: Lowest quarterly reading (index) | J10: =MIN(C15:C35) -> 77.733933
A11: A quarter (years) | B11: 0.25
A12: A half-year (years) | B12: 0.5
A14: Quarter | B14: t (years) | C14: x: liquidity | D14: z1 | E14: z2 | F14: Chapter 1's closed form | G14: |difference| | I14: Half-year | J14: t (years) | K14: x: liquidity | L14: z1 | M14: z2 | N14: Two quarterly steps: x | O14: |difference|
A15: 0 | B15: =A15*$B$11 -> 0 | C15: =B9 -> 100 | D15: =B10 -> -38.055946 | E15: 0 | F15: =Declarations!$C$27+(Declarations!$C$4-Declarations!$C$27)*EXP(-Declarations!$D$27*B15)+IF(Declarations!$E$27=0,0,Declarations!$E$27*(B15/Declarations!$F$27)*EXP(1-B15/Declarations!$F$27))+IF(B15>=T_sale,Declarations!$G$27,0) -> 100 | G15: =ABS(C15-F15) -> 0 | I15: 0 | J15: =I15*$B$12 -> 0 | K15: =B9 -> 100 | L15: =B10 -> -38.055946 | M15: 0 | N15: =INDEX($C$15:$C$35,2*I15+1) -> 100 | O15: =MAX(ABS(K15-N15),ABS(L15-INDEX($D$15:$D$35,2*I15+1)),ABS(M15-INDEX($E$15:$E$35,2*I15+1))) -> 0
A16: 1 | B16: =A16*$B$11 -> 0.25 | C16: =$B$5+(C15-E15-$B$5)*EXP(-$B$6*$B$11)+(E15+$B$11*D15)*EXP(-$B$11/$B$8) -> 92.60931 | D16: =D15*EXP(-$B$11/$B$8) -> -33.584254 | E16: =(E15+$B$11*D15)*EXP(-$B$11/$B$8) -> -8.3960635 | F16: =Declarations!$C$27+(Declarations!$C$4-Declarations!$C$27)*EXP(-Declarations!$D$27*B16)+IF(Declarations!$E$27=0,0,Declarations!$E$27*(B16/Declarations!$F$27)*EXP(1-B16/Declarations!$F$27))+IF(B16>=T_sale,Declarations!$G$27,0) -> 92.60931 | G16: =ABS(C16-F16) -> 0 | I16: 1 | J16: =I16*$B$12 -> 0.5 | K16: =$B$5+(K15-M15-$B$5)*EXP(-$B$6*$B$12)+(M15+$B$12*L15)*EXP(-$B$12/$B$8) -> 87.107516 | L16: =L15*EXP(-$B$12/$B$8) -> -29.638 | M16: =(M15+$B$12*L15)*EXP(-$B$12/$B$8) -> -14.819 | N16: =INDEX($C$15:$C$35,2*I16+1) -> 87.107516 | O16: =MAX(ABS(K16-N16),ABS(L16-INDEX($D$15:$D$35,2*I16+1)),ABS(M16-INDEX($E$15:$E$35,2*I16+1))) -> 0
A17: 2 | B17: =A17*$B$11 -> 0.5 | C17: =$B$5+(C16-E16-$B$5)*EXP(-$B$6*$B$11)+(E16+$B$11*D16)*EXP(-$B$11/$B$8) -> 87.107516 | D17: =D16*EXP(-$B$11/$B$8) -> -29.638 | E17: =(E16+$B$11*D16)*EXP(-$B$11/$B$8) -> -14.819 | F17: =Declarations!$C$27+(Declarations!$C$4-Declarations!$C$27)*EXP(-Declarations!$D$27*B17)+IF(Declarations!$E$27=0,0,Declarations!$E$27*(B17/Declarations!$F$27)*EXP(1-B17/Declarations!$F$27))+IF(B17>=T_sale,Declarations!$G$27,0) -> 87.107516 | G17: =ABS(C17-F17) -> 0 | I17: 2 | J17: =I17*$B$12 -> 1 | K17: =$B$5+(K16-M16-$B$5)*EXP(-$B$6*$B$12)+(M16+$B$12*L16)*EXP(-$B$12/$B$8) -> 80.461645 | L17: =L16*EXP(-$B$12/$B$8) -> -23.082098 | M17: =(M16+$B$12*L16)*EXP(-$B$12/$B$8) -> -23.082098 | N17: =INDEX($C$15:$C$35,2*I17+1) -> 80.461645 | O17: =MAX(ABS(K17-N17),ABS(L17-INDEX($D$15:$D$35,2*I17+1)),ABS(M17-INDEX($E$15:$E$35,2*I17+1))) -> 0
A18: 3 | B18: =A18*$B$11 -> 0.75 | C18: =$B$5+(C17-E17-$B$5)*EXP(-$B$6*$B$11)+(E17+$B$11*D17)*EXP(-$B$11/$B$8) -> 83.153901 | D18: =D17*EXP(-$B$11/$B$8) -> -26.155443 | E18: =(E17+$B$11*D17)*EXP(-$B$11/$B$8) -> -19.616583 | F18: =Declarations!$C$27+(Declarations!$C$4-Declarations!$C$27)*EXP(-Declarations!$D$27*B18)+IF(Declarations!$E$27=0,0,Declarations!$E$27*(B18/Declarations!$F$27)*EXP(1-B18/Declarations!$F$27))+IF(B18>=T_sale,Declarations!$G$27,0) -> 83.153901 | G18: =ABS(C18-F18) -> 0 | I18: 3 | J18: =I18*$B$12 -> 1.5 | K18: =$B$5+(K17-M17-$B$5)*EXP(-$B$6*$B$12)+(M17+$B$12*L17)*EXP(-$B$12/$B$8) -> 77.936802 | L18: =L17*EXP(-$B$12/$B$8) -> -17.976356 | M18: =(M17+$B$12*L17)*EXP(-$B$12/$B$8) -> -26.964534 | N18: =INDEX($C$15:$C$35,2*I18+1) -> 77.936802 | O18: =MAX(ABS(K18-N18),ABS(L18-INDEX($D$15:$D$35,2*I18+1)),ABS(M18-INDEX($E$15:$E$35,2*I18+1))) -> 0
A19: 4 | B19: =A19*$B$11 -> 1 | C19: =$B$5+(C18-E18-$B$5)*EXP(-$B$6*$B$11)+(E18+$B$11*D18)*EXP(-$B$11/$B$8) -> 80.461645 | D19: =D18*EXP(-$B$11/$B$8) -> -23.082098 | E19: =(E18+$B$11*D18)*EXP(-$B$11/$B$8) -> -23.082098 | F19: =Declarations!$C$27+(Declarations!$C$4-Declarations!$C$27)*EXP(-Declarations!$D$27*B19)+IF(Declarations!$E$27=0,0,Declarations!$E$27*(B19/Declarations!$F$27)*EXP(1-B19/Declarations!$F$27))+IF(B19>=T_sale,Declarations!$G$27,0) -> 80.461645 | G19: =ABS(C19-F19) -> 0 | I19: 4 | J19: =I19*$B$12 -> 2 | K19: =$B$5+(K18-M18-$B$5)*EXP(-$B$6*$B$12)+(M18+$B$12*L18)*EXP(-$B$12/$B$8) -> 78.040976 | L19: =L18*EXP(-$B$12/$B$8) -> -14 | M19: =(M18+$B$12*L18)*EXP(-$B$12/$B$8) -> -28 | N19: =INDEX($C$15:$C$35,2*I19+1) -> 78.040976 | O19: =MAX(ABS(K19-N19),ABS(L19-INDEX($D$15:$D$35,2*I19+1)),ABS(M19-INDEX($E$15:$E$35,2*I19+1))) -> 0
A20: 5 | B20: =A20*$B$11 -> 1.25 | C20: =$B$5+(C19-E19-$B$5)*EXP(-$B$6*$B$11)+(E19+$B$11*D19)*EXP(-$B$11/$B$8) -> 78.789868 | D20: =D19*EXP(-$B$11/$B$8) -> -20.36988 | E20: =(E19+$B$11*D19)*EXP(-$B$11/$B$8) -> -25.46235 | F20: =Declarations!$C$27+(Declarations!$C$4-Declarations!$C$27)*EXP(-Declarations!$D$27*B20)+IF(Declarations!$E$27=0,0,Declarations!$E$27*(B20/Declarations!$F$27)*EXP(1-B20/Declarations!$F$27))+IF(B20>=T_sale,Declarations!$G$27,0) -> 78.789868 | G20: =ABS(C20-F20) -> 0 | I20: 5 | J20: =I20*$B$12 -> 2.5 | K20: =$B$5+(K19-M19-$B$5)*EXP(-$B$6*$B$12)+(M19+$B$12*L19)*EXP(-$B$12/$B$8) -> 79.739628 | L20: =L19*EXP(-$B$12/$B$8) -> -10.903211 | M20: =(M19+$B$12*L19)*EXP(-$B$12/$B$8) -> -27.258027 | N20: =INDEX($C$15:$C$35,2*I20+1) -> 79.739628 | O20: =MAX(ABS(K20-N20),ABS(L20-INDEX($D$15:$D$35,2*I20+1)),ABS(M20-INDEX($E$15:$E$35,2*I20+1))) -> 0
A21: 6 | B21: =A21*$B$11 -> 1.5 | C21: =$B$5+(C20-E20-$B$5)*EXP(-$B$6*$B$11)+(E20+$B$11*D20)*EXP(-$B$11/$B$8) -> 77.936802 | D21: =D20*EXP(-$B$11/$B$8) -> -17.976356 | E21: =(E20+$B$11*D20)*EXP(-$B$11/$B$8) -> -26.964534 | F21: =Declarations!$C$27+(Declarations!$C$4-Declarations!$C$27)*EXP(-Declarations!$D$27*B21)+IF(Declarations!$E$27=0,0,Declarations!$E$27*(B21/Declarations!$F$27)*EXP(1-B21/Declarations!$F$27))+IF(B21>=T_sale,Declarations!$G$27,0) -> 77.936802 | G21: =ABS(C21-F21) -> 0 | I21: 6 | J21: =I21*$B$12 -> 3 | K21: =$B$5+(K20-M20-$B$5)*EXP(-$B$6*$B$12)+(M20+$B$12*L20)*EXP(-$B$12/$B$8) -> 82.326459 | L21: =L20*EXP(-$B$12/$B$8) -> -8.4914292 | M21: =(M20+$B$12*L20)*EXP(-$B$12/$B$8) -> -25.474288 | N21: =INDEX($C$15:$C$35,2*I21+1) -> 82.326459 | O21: =MAX(ABS(K21-N21),ABS(L21-INDEX($D$15:$D$35,2*I21+1)),ABS(M21-INDEX($E$15:$E$35,2*I21+1))) -> 0
A22: 7 | B22: =A22*$B$11 -> 1.75 | C22: =$B$5+(C21-E21-$B$5)*EXP(-$B$6*$B$11)+(E21+$B$11*D21)*EXP(-$B$11/$B$8) -> 77.733933 | D22: =D21*EXP(-$B$11/$B$8) -> -15.864078 | E22: =(E21+$B$11*D21)*EXP(-$B$11/$B$8) -> -27.762137 | F22: =Declarations!$C$27+(Declarations!$C$4-Declarations!$C$27)*EXP(-Declarations!$D$27*B22)+IF(Declarations!$E$27=0,0,Declarations!$E$27*(B22/Declarations!$F$27)*EXP(1-B22/Declarations!$F$27))+IF(B22>=T_sale,Declarations!$G$27,0) -> 77.733933 | G22: =ABS(C22-F22) -> 0 | I22: 7 | J22: =I22*$B$12 -> 3.5 | K22: =$B$5+(K21-M21-$B$5)*EXP(-$B$6*$B$12)+(M21+$B$12*L21)*EXP(-$B$12/$B$8) -> 85.328947 | L22: =L21*EXP(-$B$12/$B$8) -> -6.6131317 | M22: =(M21+$B$12*L21)*EXP(-$B$12/$B$8) -> -23.145961 | N22: =INDEX($C$15:$C$35,2*I22+1) -> 85.328947 | O22: =MAX(ABS(K22-N22),ABS(L22-INDEX($D$15:$D$35,2*I22+1)),ABS(M22-INDEX($E$15:$E$35,2*I22+1))) -> 0
A23: 8 | B23: =A23*$B$11 -> 2 | C23: =$B$5+(C22-E22-$B$5)*EXP(-$B$6*$B$11)+(E22+$B$11*D22)*EXP(-$B$11/$B$8) -> 78.040976 | D23: =D22*EXP(-$B$11/$B$8) -> -14 | E23: =(E22+$B$11*D22)*EXP(-$B$11/$B$8) -> -28 | F23: =Declarations!$C$27+(Declarations!$C$4-Declarations!$C$27)*EXP(-Declarations!$D$27*B23)+IF(Declarations!$E$27=0,0,Declarations!$E$27*(B23/Declarations!$F$27)*EXP(1-B23/Declarations!$F$27))+IF(B23>=T_sale,Declarations!$G$27,0) -> 78.040976 | G23: =ABS(C23-F23) -> 0 | I23: 8 | J23: =I23*$B$12 -> 4 | K23: =$B$5+(K22-M22-$B$5)*EXP(-$B$6*$B$12)+(M22+$B$12*L22)*EXP(-$B$12/$B$8) -> 88.439588 | L23: =L22*EXP(-$B$12/$B$8) -> -5.1503122 | M23: =(M22+$B$12*L22)*EXP(-$B$12/$B$8) -> -20.601249 | N23: =INDEX($C$15:$C$35,2*I23+1) -> 88.439588 | O23: =MAX(ABS(K23-N23),ABS(L23-INDEX($D$15:$D$35,2*I23+1)),ABS(M23-INDEX($E$15:$E$35,2*I23+1))) -> 0
A24: 9 | B24: =A24*$B$11 -> 2.25 | C24: =$B$5+(C23-E23-$B$5)*EXP(-$B$6*$B$11)+(E23+$B$11*D23)*EXP(-$B$11/$B$8) -> 78.741578 | D24: =D23*EXP(-$B$11/$B$8) -> -12.354957 | E24: =(E23+$B$11*D23)*EXP(-$B$11/$B$8) -> -27.798652 | F24: =Declarations!$C$27+(Declarations!$C$4-Declarations!$C$27)*EXP(-Declarations!$D$27*B24)+IF(Declarations!$E$27=0,0,Declarations!$E$27*(B24/Declarations!$F$27)*EXP(1-B24/Declarations!$F$27))+IF(B24>=T_sale,Declarations!$G$27,0) -> 78.741578 | G24: =ABS(C24-F24) -> 0 | I24: 9 | J24: =I24*$B$12 -> 4.5 | K24: =$B$5+(K23-M23-$B$5)*EXP(-$B$6*$B$12)+(M23+$B$12*L23)*EXP(-$B$12/$B$8) -> 91.466107 | L24: =L23*EXP(-$B$12/$B$8) -> -4.0110672 | M24: =(M23+$B$12*L23)*EXP(-$B$12/$B$8) -> -18.049802 | N24: =INDEX($C$15:$C$35,2*I24+1) -> 91.466107 | O24: =MAX(ABS(K24-N24),ABS(L24-INDEX($D$15:$D$35,2*I24+1)),ABS(M24-INDEX($E$15:$E$35,2*I24+1))) -> 0
A25: 10 | B25: =A25*$B$11 -> 2.5 | C25: =$B$5+(C24-E24-$B$5)*EXP(-$B$6*$B$11)+(E24+$B$11*D24)*EXP(-$B$11/$B$8) -> 79.739628 | D25: =D24*EXP(-$B$11/$B$8) -> -10.903211 | E25: =(E24+$B$11*D24)*EXP(-$B$11/$B$8) -> -27.258027 | F25: =Declarations!$C$27+(Declarations!$C$4-Declarations!$C$27)*EXP(-Declarations!$D$27*B25)+IF(Declarations!$E$27=0,0,Declarations!$E$27*(B25/Declarations!$F$27)*EXP(1-B25/Declarations!$F$27))+IF(B25>=T_sale,Declarations!$G$27,0) -> 79.739628 | G25: =ABS(C25-F25) -> 0 | I25: 10 | J25: =I25*$B$12 -> 5 | K25: =$B$5+(K24-M24-$B$5)*EXP(-$B$6*$B$12)+(M24+$B$12*L24)*EXP(-$B$12/$B$8) -> 94.295601 | L25: =L24*EXP(-$B$12/$B$8) -> -3.1238222 | M25: =(M24+$B$12*L24)*EXP(-$B$12/$B$8) -> -15.619111 | N25: =INDEX($C$15:$C$35,2*I25+1) -> 94.295601 | O25: =MAX(ABS(K25-N25),ABS(L25-INDEX($D$15:$D$35,2*I25+1)),ABS(M25-INDEX($E$15:$E$35,2*I25+1))) -> 0
A26: 11 | B26: =A26*$B$11 -> 2.75 | C26: =$B$5+(C25-E25-$B$5)*EXP(-$B$6*$B$11)+(E25+$B$11*D25)*EXP(-$B$11/$B$8) -> 80.956121 | D26: =D25*EXP(-$B$11/$B$8) -> -9.6220499 | E26: =(E25+$B$11*D25)*EXP(-$B$11/$B$8) -> -26.460637 | F26: =Declarations!$C$27+(Declarations!$C$4-Declarations!$C$27)*EXP(-Declarations!$D$27*B26)+IF(Declarations!$E$27=0,0,Declarations!$E$27*(B26/Declarations!$F$27)*EXP(1-B26/Declarations!$F$27))+IF(B26>=T_sale,Declarations!$G$27,0) -> 80.956121 | G26: =ABS(C26-F26) -> 0
A27: 12 | B27: =A27*$B$11 -> 3 | C27: =$B$5+(C26-E26-$B$5)*EXP(-$B$6*$B$11)+(E26+$B$11*D26)*EXP(-$B$11/$B$8) -> 82.326459 | D27: =D26*EXP(-$B$11/$B$8) -> -8.4914292 | E27: =(E26+$B$11*D26)*EXP(-$B$11/$B$8) -> -25.474288 | F27: =Declarations!$C$27+(Declarations!$C$4-Declarations!$C$27)*EXP(-Declarations!$D$27*B27)+IF(Declarations!$E$27=0,0,Declarations!$E$27*(B27/Declarations!$F$27)*EXP(1-B27/Declarations!$F$27))+IF(B27>=T_sale,Declarations!$G$27,0) -> 82.326459 | G27: =ABS(C27-F27) -> 0
A28: 13 | B28: =A28*$B$11 -> 3.25 | C28: =$B$5+(C27-E27-$B$5)*EXP(-$B$6*$B$11)+(E27+$B$11*D27)*EXP(-$B$11/$B$8) -> 83.79817 | D28: =D27*EXP(-$B$11/$B$8) -> -7.49366 | E28: =(E27+$B$11*D27)*EXP(-$B$11/$B$8) -> -24.354395 | F28: =Declarations!$C$27+(Declarations!$C$4-Declarations!$C$27)*EXP(-Declarations!$D$27*B28)+IF(Declarations!$E$27=0,0,Declarations!$E$27*(B28/Declarations!$F$27)*EXP(1-B28/Declarations!$F$27))+IF(B28>=T_sale,Declarations!$G$27,0) -> 83.79817 | G28: =ABS(C28-F28) -> 0
A29: 14 | B29: =A29*$B$11 -> 3.5 | C29: =$B$5+(C28-E28-$B$5)*EXP(-$B$6*$B$11)+(E28+$B$11*D28)*EXP(-$B$11/$B$8) -> 85.328947 | D29: =D28*EXP(-$B$11/$B$8) -> -6.6131317 | E29: =(E28+$B$11*D28)*EXP(-$B$11/$B$8) -> -23.145961 | F29: =Declarations!$C$27+(Declarations!$C$4-Declarations!$C$27)*EXP(-Declarations!$D$27*B29)+IF(Declarations!$E$27=0,0,Declarations!$E$27*(B29/Declarations!$F$27)*EXP(1-B29/Declarations!$F$27))+IF(B29>=T_sale,Declarations!$G$27,0) -> 85.328947 | G29: =ABS(C29-F29) -> 0
A30: 15 | B30: =A30*$B$11 -> 3.75 | C30: =$B$5+(C29-E29-$B$5)*EXP(-$B$6*$B$11)+(E29+$B$11*D29)*EXP(-$B$11/$B$8) -> 86.884988 | D30: =D29*EXP(-$B$11/$B$8) -> -5.8360683 | E30: =(E29+$B$11*D29)*EXP(-$B$11/$B$8) -> -21.885256 | F30: =Declarations!$C$27+(Declarations!$C$4-Declarations!$C$27)*EXP(-Declarations!$D$27*B30)+IF(Declarations!$E$27=0,0,Declarations!$E$27*(B30/Declarations!$F$27)*EXP(1-B30/Declarations!$F$27))+IF(B30>=T_sale,Declarations!$G$27,0) -> 86.884988 | G30: =ABS(C30-F30) -> 0
A31: 16 | B31: =A31*$B$11 -> 4 | C31: =$B$5+(C30-E30-$B$5)*EXP(-$B$6*$B$11)+(E30+$B$11*D30)*EXP(-$B$11/$B$8) -> 88.439588 | D31: =D30*EXP(-$B$11/$B$8) -> -5.1503122 | E31: =(E30+$B$11*D30)*EXP(-$B$11/$B$8) -> -20.601249 | F31: =Declarations!$C$27+(Declarations!$C$4-Declarations!$C$27)*EXP(-Declarations!$D$27*B31)+IF(Declarations!$E$27=0,0,Declarations!$E$27*(B31/Declarations!$F$27)*EXP(1-B31/Declarations!$F$27))+IF(B31>=T_sale,Declarations!$G$27,0) -> 88.439588 | G31: =ABS(C31-F31) -> 0
A32: 17 | B32: =A32*$B$11 -> 4.25 | C32: =$B$5+(C31-E31-$B$5)*EXP(-$B$6*$B$11)+(E31+$B$11*D31)*EXP(-$B$11/$B$8) -> 89.971937 | D32: =D31*EXP(-$B$11/$B$8) -> -4.5451345 | E32: =(E31+$B$11*D31)*EXP(-$B$11/$B$8) -> -19.316822 | F32: =Declarations!$C$27+(Declarations!$C$4-Declarations!$C$27)*EXP(-Declarations!$D$27*B32)+IF(Declarations!$E$27=0,0,Declarations!$E$27*(B32/Declarations!$F$27)*EXP(1-B32/Declarations!$F$27))+IF(B32>=T_sale,Declarations!$G$27,0) -> 89.971937 | G32: =ABS(C32-F32) -> 0
A33: 18 | B33: =A33*$B$11 -> 4.5 | C33: =$B$5+(C32-E32-$B$5)*EXP(-$B$6*$B$11)+(E32+$B$11*D32)*EXP(-$B$11/$B$8) -> 91.466107 | D33: =D32*EXP(-$B$11/$B$8) -> -4.0110672 | E33: =(E32+$B$11*D32)*EXP(-$B$11/$B$8) -> -18.049802 | F33: =Declarations!$C$27+(Declarations!$C$4-Declarations!$C$27)*EXP(-Declarations!$D$27*B33)+IF(Declarations!$E$27=0,0,Declarations!$E$27*(B33/Declarations!$F$27)*EXP(1-B33/Declarations!$F$27))+IF(B33>=T_sale,Declarations!$G$27,0) -> 91.466107 | G33: =ABS(C33-F33) -> 0
A34: 19 | B34: =A34*$B$11 -> 4.75 | C34: =$B$5+(C33-E33-$B$5)*EXP(-$B$6*$B$11)+(E33+$B$11*D33)*EXP(-$B$11/$B$8) -> 92.910196 | D34: =D33*EXP(-$B$11/$B$8) -> -3.5397543 | E34: =(E33+$B$11*D33)*EXP(-$B$11/$B$8) -> -16.813833 | F34: =Declarations!$C$27+(Declarations!$C$4-Declarations!$C$27)*EXP(-Declarations!$D$27*B34)+IF(Declarations!$E$27=0,0,Declarations!$E$27*(B34/Declarations!$F$27)*EXP(1-B34/Declarations!$F$27))+IF(B34>=T_sale,Declarations!$G$27,0) -> 92.910196 | G34: =ABS(C34-F34) -> 0
A35: 20 | B35: =A35*$B$11 -> 5 | C35: =$B$5+(C34-E34-$B$5)*EXP(-$B$6*$B$11)+(E34+$B$11*D34)*EXP(-$B$11/$B$8) -> 94.295601 | D35: =D34*EXP(-$B$11/$B$8) -> -3.1238222 | E35: =(E34+$B$11*D34)*EXP(-$B$11/$B$8) -> -15.619111 | F35: =Declarations!$C$27+(Declarations!$C$4-Declarations!$C$27)*EXP(-Declarations!$D$27*B35)+IF(Declarations!$E$27=0,0,Declarations!$E$27*(B35/Declarations!$F$27)*EXP(1-B35/Declarations!$F$27))+IF(B35>=T_sale,Declarations!$G$27,0) -> 94.295601 | G35: =ABS(C35-F35) -> 0
A38: Phase 2 from the build's end: quarter | B38: t (years) | C38: x: liquidity | D38: z1 | E38: z2 | F38: Whole path: x | G38: |difference|
A39: 8 | B39: =A39*$B$11 -> 2 | C39: =C23 -> 78.040976 | D39: =D23 -> -14 | E39: =E23 -> -28 | F39: =INDEX($C$15:$C$35,A39+1) -> 78.040976 | G39: =ABS(C39-F39) -> 0
A40: 9 | B40: =A40*$B$11 -> 2.25 | C40: =$B$5+(C39-E39-$B$5)*EXP(-$B$6*$B$11)+(E39+$B$11*D39)*EXP(-$B$11/$B$8) -> 78.741578 | D40: =D39*EXP(-$B$11/$B$8) -> -12.354957 | E40: =(E39+$B$11*D39)*EXP(-$B$11/$B$8) -> -27.798652 | F40: =INDEX($C$15:$C$35,A40+1) -> 78.741578 | G40: =ABS(C40-F40) -> 0
A41: 10 | B41: =A41*$B$11 -> 2.5 | C41: =$B$5+(C40-E40-$B$5)*EXP(-$B$6*$B$11)+(E40+$B$11*D40)*EXP(-$B$11/$B$8) -> 79.739628 | D41: =D40*EXP(-$B$11/$B$8) -> -10.903211 | E41: =(E40+$B$11*D40)*EXP(-$B$11/$B$8) -> -27.258027 | F41: =INDEX($C$15:$C$35,A41+1) -> 79.739628 | G41: =ABS(C41-F41) -> 0
A42: 11 | B42: =A42*$B$11 -> 2.75 | C42: =$B$5+(C41-E41-$B$5)*EXP(-$B$6*$B$11)+(E41+$B$11*D41)*EXP(-$B$11/$B$8) -> 80.956121 | D42: =D41*EXP(-$B$11/$B$8) -> -9.6220499 | E42: =(E41+$B$11*D41)*EXP(-$B$11/$B$8) -> -26.460637 | F42: =INDEX($C$15:$C$35,A42+1) -> 80.956121 | G42: =ABS(C42-F42) -> 0
A43: 12 | B43: =A43*$B$11 -> 3 | C43: =$B$5+(C42-E42-$B$5)*EXP(-$B$6*$B$11)+(E42+$B$11*D42)*EXP(-$B$11/$B$8) -> 82.326459 | D43: =D42*EXP(-$B$11/$B$8) -> -8.4914292 | E43: =(E42+$B$11*D42)*EXP(-$B$11/$B$8) -> -25.474288 | F43: =INDEX($C$15:$C$35,A43+1) -> 82.326459 | G43: =ABS(C43-F43) -> 0
A44: 13 | B44: =A44*$B$11 -> 3.25 | C44: =$B$5+(C43-E43-$B$5)*EXP(-$B$6*$B$11)+(E43+$B$11*D43)*EXP(-$B$11/$B$8) -> 83.79817 | D44: =D43*EXP(-$B$11/$B$8) -> -7.49366 | E44: =(E43+$B$11*D43)*EXP(-$B$11/$B$8) -> -24.354395 | F44: =INDEX($C$15:$C$35,A44+1) -> 83.79817 | G44: =ABS(C44-F44) -> 0
A45: 14 | B45: =A45*$B$11 -> 3.5 | C45: =$B$5+(C44-E44-$B$5)*EXP(-$B$6*$B$11)+(E44+$B$11*D44)*EXP(-$B$11/$B$8) -> 85.328947 | D45: =D44*EXP(-$B$11/$B$8) -> -6.6131317 | E45: =(E44+$B$11*D44)*EXP(-$B$11/$B$8) -> -23.145961 | F45: =INDEX($C$15:$C$35,A45+1) -> 85.328947 | G45: =ABS(C45-F45) -> 0
A46: 15 | B46: =A46*$B$11 -> 3.75 | C46: =$B$5+(C45-E45-$B$5)*EXP(-$B$6*$B$11)+(E45+$B$11*D45)*EXP(-$B$11/$B$8) -> 86.884988 | D46: =D45*EXP(-$B$11/$B$8) -> -5.8360683 | E46: =(E45+$B$11*D45)*EXP(-$B$11/$B$8) -> -21.885256 | F46: =INDEX($C$15:$C$35,A46+1) -> 86.884988 | G46: =ABS(C46-F46) -> 0
A47: 16 | B47: =A47*$B$11 -> 4 | C47: =$B$5+(C46-E46-$B$5)*EXP(-$B$6*$B$11)+(E46+$B$11*D46)*EXP(-$B$11/$B$8) -> 88.439588 | D47: =D46*EXP(-$B$11/$B$8) -> -5.1503122 | E47: =(E46+$B$11*D46)*EXP(-$B$11/$B$8) -> -20.601249 | F47: =INDEX($C$15:$C$35,A47+1) -> 88.439588 | G47: =ABS(C47-F47) -> 0
A48: 17 | B48: =A48*$B$11 -> 4.25 | C48: =$B$5+(C47-E47-$B$5)*EXP(-$B$6*$B$11)+(E47+$B$11*D47)*EXP(-$B$11/$B$8) -> 89.971937 | D48: =D47*EXP(-$B$11/$B$8) -> -4.5451345 | E48: =(E47+$B$11*D47)*EXP(-$B$11/$B$8) -> -19.316822 | F48: =INDEX($C$15:$C$35,A48+1) -> 89.971937 | G48: =ABS(C48-F48) -> 0
A49: 18 | B49: =A49*$B$11 -> 4.5 | C49: =$B$5+(C48-E48-$B$5)*EXP(-$B$6*$B$11)+(E48+$B$11*D48)*EXP(-$B$11/$B$8) -> 91.466107 | D49: =D48*EXP(-$B$11/$B$8) -> -4.0110672 | E49: =(E48+$B$11*D48)*EXP(-$B$11/$B$8) -> -18.049802 | F49: =INDEX($C$15:$C$35,A49+1) -> 91.466107 | G49: =ABS(C49-F49) -> 0
A50: 19 | B50: =A50*$B$11 -> 4.75 | C50: =$B$5+(C49-E49-$B$5)*EXP(-$B$6*$B$11)+(E49+$B$11*D49)*EXP(-$B$11/$B$8) -> 92.910196 | D50: =D49*EXP(-$B$11/$B$8) -> -3.5397543 | E50: =(E49+$B$11*D49)*EXP(-$B$11/$B$8) -> -16.813833 | F50: =INDEX($C$15:$C$35,A50+1) -> 92.910196 | G50: =ABS(C50-F50) -> 0
A51: 20 | B51: =A51*$B$11 -> 5 | C51: =$B$5+(C50-E50-$B$5)*EXP(-$B$6*$B$11)+(E50+$B$11*D50)*EXP(-$B$11/$B$8) -> 94.295601 | D51: =D50*EXP(-$B$11/$B$8) -> -3.1238222 | E51: =(E50+$B$11*D50)*EXP(-$B$11/$B$8) -> -15.619111 | F51: =INDEX($C$15:$C$35,A51+1) -> 94.295601 | G51: =ABS(C51-F51) -> 0
A54: Undo: quarters back from year 5 | B54: t (years) | C54: x: liquidity | D54: z1 | E54: z2
A55: 20 | B55: =A55*$B$11 -> 5 | C55: =C35 -> 94.295601 | D55: =D35 -> -3.1238222 | E55: =E35 -> -15.619111
A56: 19 | B56: =A56*$B$11 -> 4.75 | C56: =$B$5+(C55-E55-$B$5)*EXP(-$B$6*(-$B$11))+(E55+(-$B$11)*D55)*EXP(-(-$B$11)/$B$8) -> 92.910196 | D56: =D55*EXP(-(-$B$11)/$B$8) -> -3.5397543 | E56: =(E55+(-$B$11)*D55)*EXP(-(-$B$11)/$B$8) -> -16.813833
A57: 18 | B57: =A57*$B$11 -> 4.5 | C57: =$B$5+(C56-E56-$B$5)*EXP(-$B$6*(-$B$11))+(E56+(-$B$11)*D56)*EXP(-(-$B$11)/$B$8) -> 91.466107 | D57: =D56*EXP(-(-$B$11)/$B$8) -> -4.0110672 | E57: =(E56+(-$B$11)*D56)*EXP(-(-$B$11)/$B$8) -> -18.049802
A58: 17 | B58: =A58*$B$11 -> 4.25 | C58: =$B$5+(C57-E57-$B$5)*EXP(-$B$6*(-$B$11))+(E57+(-$B$11)*D57)*EXP(-(-$B$11)/$B$8) -> 89.971937 | D58: =D57*EXP(-(-$B$11)/$B$8) -> -4.5451345 | E58: =(E57+(-$B$11)*D57)*EXP(-(-$B$11)/$B$8) -> -19.316822
A59: 16 | B59: =A59*$B$11 -> 4 | C59: =$B$5+(C58-E58-$B$5)*EXP(-$B$6*(-$B$11))+(E58+(-$B$11)*D58)*EXP(-(-$B$11)/$B$8) -> 88.439588 | D59: =D58*EXP(-(-$B$11)/$B$8) -> -5.1503122 | E59: =(E58+(-$B$11)*D58)*EXP(-(-$B$11)/$B$8) -> -20.601249
A60: 15 | B60: =A60*$B$11 -> 3.75 | C60: =$B$5+(C59-E59-$B$5)*EXP(-$B$6*(-$B$11))+(E59+(-$B$11)*D59)*EXP(-(-$B$11)/$B$8) -> 86.884988 | D60: =D59*EXP(-(-$B$11)/$B$8) -> -5.8360683 | E60: =(E59+(-$B$11)*D59)*EXP(-(-$B$11)/$B$8) -> -21.885256
A61: 14 | B61: =A61*$B$11 -> 3.5 | C61: =$B$5+(C60-E60-$B$5)*EXP(-$B$6*(-$B$11))+(E60+(-$B$11)*D60)*EXP(-(-$B$11)/$B$8) -> 85.328947 | D61: =D60*EXP(-(-$B$11)/$B$8) -> -6.6131317 | E61: =(E60+(-$B$11)*D60)*EXP(-(-$B$11)/$B$8) -> -23.145961
A62: 13 | B62: =A62*$B$11 -> 3.25 | C62: =$B$5+(C61-E61-$B$5)*EXP(-$B$6*(-$B$11))+(E61+(-$B$11)*D61)*EXP(-(-$B$11)/$B$8) -> 83.79817 | D62: =D61*EXP(-(-$B$11)/$B$8) -> -7.49366 | E62: =(E61+(-$B$11)*D61)*EXP(-(-$B$11)/$B$8) -> -24.354395
A63: 12 | B63: =A63*$B$11 -> 3 | C63: =$B$5+(C62-E62-$B$5)*EXP(-$B$6*(-$B$11))+(E62+(-$B$11)*D62)*EXP(-(-$B$11)/$B$8) -> 82.326459 | D63: =D62*EXP(-(-$B$11)/$B$8) -> -8.4914292 | E63: =(E62+(-$B$11)*D62)*EXP(-(-$B$11)/$B$8) -> -25.474288
A64: 11 | B64: =A64*$B$11 -> 2.75 | C64: =$B$5+(C63-E63-$B$5)*EXP(-$B$6*(-$B$11))+(E63+(-$B$11)*D63)*EXP(-(-$B$11)/$B$8) -> 80.956121 | D64: =D63*EXP(-(-$B$11)/$B$8) -> -9.6220499 | E64: =(E63+(-$B$11)*D63)*EXP(-(-$B$11)/$B$8) -> -26.460637
A65: 10 | B65: =A65*$B$11 -> 2.5 | C65: =$B$5+(C64-E64-$B$5)*EXP(-$B$6*(-$B$11))+(E64+(-$B$11)*D64)*EXP(-(-$B$11)/$B$8) -> 79.739628 | D65: =D64*EXP(-(-$B$11)/$B$8) -> -10.903211 | E65: =(E64+(-$B$11)*D64)*EXP(-(-$B$11)/$B$8) -> -27.258027
A66: 9 | B66: =A66*$B$11 -> 2.25 | C66: =$B$5+(C65-E65-$B$5)*EXP(-$B$6*(-$B$11))+(E65+(-$B$11)*D65)*EXP(-(-$B$11)/$B$8) -> 78.741578 | D66: =D65*EXP(-(-$B$11)/$B$8) -> -12.354957 | E66: =(E65+(-$B$11)*D65)*EXP(-(-$B$11)/$B$8) -> -27.798652
A67: 8 | B67: =A67*$B$11 -> 2 | C67: =$B$5+(C66-E66-$B$5)*EXP(-$B$6*(-$B$11))+(E66+(-$B$11)*D66)*EXP(-(-$B$11)/$B$8) -> 78.040976 | D67: =D66*EXP(-(-$B$11)/$B$8) -> -14 | E67: =(E66+(-$B$11)*D66)*EXP(-(-$B$11)/$B$8) -> -28
... A75: 0 | B75: =A75*$B$11 -> 0 | C75: =$B$5+(C74-E74-$B$5)*EXP(-$B$6*(-$B$11))+(E74+(-$B$11)*D74)*EXP(-(-$B$11)/$B$8) -> 100 | D75: =D74*EXP(-(-$B$11)/$B$8) -> -38.055946 | E75: =(E74+(-$B$11)*D74)*EXP(-(-$B$11)/$B$8) -> 0

Sheet Turnaround
A1: Find the steady state: the turnaround's annual map, the day-one bound and Table 5.5 (Theorem 5.4(i); Equation 5.1; Worked Example 5.1; AXIOM Lab 1.5, step 4)
B3: Liquidity (index) | C3: Technology | D3: Efficiency | E3: Strategic risk | J3: Convergence budget | K3: Value | L3: Worked Example 5.1
A4: Target: the steady state | B4: =Declarations!C35 -> 106 | C4: =Declarations!C36 -> 33 | D4: =Declarations!C37 -> 79 | E4: =Declarations!C38 -> 67 | J4: First year the day-one bound is below one point | K4: =COUNTIF(G16:G56,">=1") -> 15 | L4: Step 3: year 15
A5: Speed a year (Chapter 1's model) | B5: =Declarations!D35 -> 0.45 | C5: =Declarations!D36 -> 0.2 | D5: =Declarations!D37 -> 0.6 | E5: =Declarations!D38 -> 0.3 | J5: First year the largest gap is below one point | K5: =COUNTIF(F16:F56,">=1") -> 11 | L5: Step 4: year 11
A6: Factor: next year's gap / this year's | B6: =EXP(-B5) -> 0.63762815 | C6: =EXP(-C5) -> 0.81873075 | D6: =EXP(-D5) -> 0.54881164 | E6: =EXP(-E5) -> 0.74081822 | J6: Scorecard at the steady state | K6: =W_L*B4+W_T*C4+W_E*D4+W_R*E4 -> 37.75 | L6: Table 5.5: 37.8
A7: Share of the gap closed a year | B7: =1-B6 -> 0.36237185 | C7: =1-C6 -> 0.18126925 | D7: =1-D6 -> 0.45118836 | E7: =1-E6 -> 0.25918178 | J7: Scorecard's peak, years 0-15 | K7: =MAX(H16:H31) -> 38.445169 | L7: about 38.4 in years 3-5
A8: Today | B8: =Liq_today -> 100 | C8: =Tech_today -> 41 | D8: =Eff_today -> 71 | E8: =Risk_today -> 64 | J8: Its year | K8: =INDEX(A16:A31,MATCH(K7,H16:H31,0)) -> 4
A10: Contraction constant L, the largest factor | B10: =MAX(B6:E6) -> 0.81873075 | J10: Table 5.5 (Worked Example 5.1) | P10: Steady state
A11: Set by | B11: =INDEX(B3:E3,MATCH(B10,B6:E6,0)) -> Technology | J11: Year | K11: 0 | L11: 1 | M11: 3 | N11: 5 | O11: 11
A12: Largest first-year move | B12: =MAX(ABS(B17-B16),ABS(C17-C16),ABS(D17-D16),ABS(E17-E16)) -> 3.6095069 | J12: Liquidity (index) | K12: =INDEX($B$16:$B$56,K$11+1) -> 100 | L12: =INDEX($B$16:$B$56,L$11+1) -> 102.17423 | M12: =INDEX($B$16:$B$56,M$11+1) -> 104.44456 | N12: =INDEX($B$16:$B$56,N$11+1) -> 105.3676 | O12: =INDEX($B$16:$B$56,O$11+1) -> 105.9575 | P12: =B4 -> 106
A13: Day-one bound coefficient: move / (1 - L) | B13: =B12/(1-B10) -> 19.912406 | J13: Technology | K13: =INDEX($C$16:$C$56,K$11+1) -> 41 | L13: =INDEX($C$16:$C$56,L$11+1) -> 39.549846 | M13: =INDEX($C$16:$C$56,M$11+1) -> 37.390493 | N13: =INDEX($C$16:$C$56,N$11+1) -> 35.943036 | O13: =INDEX($C$16:$C$56,O$11+1) -> 33.886425 | P13: =C4 -> 33
J14: Efficiency | K14: =INDEX($D$16:$D$56,K$11+1) -> 71 | L14: =INDEX($D$16:$D$56,L$11+1) -> 74.609507 | M14: =INDEX($D$16:$D$56,M$11+1) -> 77.677609 | N14: =INDEX($D$16:$D$56,N$11+1) -> 78.601703 | O14: =INDEX($D$16:$D$56,O$11+1) -> 78.989117 | P14: =D4 -> 79
A15: Year | B15: Liquidity | C15: Technology | D15: Efficiency | E15: Strategic risk | F15: Largest gap | G15: Day-one bound | H15: Scorecard | J15: Strategic risk | K15: =INDEX($E$16:$E$56,K$11+1) -> 64 | L15: =INDEX($E$16:$E$56,L$11+1) -> 64.777545 | M15: =INDEX($E$16:$E$56,M$11+1) -> 65.780291 | N15: =INDEX($E$16:$E$56,N$11+1) -> 66.33061 | O15: =INDEX($E$16:$E$56,O$11+1) -> 66.88935 | P15: =E4 -> 67
A16: 0 | B16: =B$8 -> 100 | C16: =C$8 -> 41 | D16: =D$8 -> 71 | E16: =E$8 -> 64 | F16: =MAX(ABS(B16-B$4),ABS(C16-C$4),ABS(D16-D$4),ABS(E16-E$4)) -> 8 | G16: =$B$13*$B$10^A16 -> 19.912406 | H16: =W_L*B16+W_T*C16+W_E*D16+W_R*E16 -> 37 | J16: Largest gap to steady state | K16: =INDEX($F$16:$F$56,K$11+1) -> 8 | L16: =INDEX($F$16:$F$56,L$11+1) -> 6.549846 | M16: =INDEX($F$16:$F$56,M$11+1) -> 4.3904931 | N16: =INDEX($F$16:$F$56,N$11+1) -> 2.9430355 | O16: =INDEX($F$16:$F$56,O$11+1) -> 0.88642527 | P16: 0
A17: 1 | B17: =B$4+B$6*(B16-B$4) -> 102.17423 | C17: =C$4+C$6*(C16-C$4) -> 39.549846 | D17: =D$4+D$6*(D16-D$4) -> 74.609507 | E17: =E$4+E$6*(E16-E$4) -> 64.777545 | F17: =MAX(ABS(B17-B$4),ABS(C17-C$4),ABS(D17-D$4),ABS(E17-E$4)) -> 6.549846 | G17: =$B$13*$B$10^A17 -> 16.302899 | H17: =W_L*B17+W_T*C17+W_E*D17+W_R*E17 -> 37.88901 | J17: Day-one bound | K17: =INDEX($G$16:$G$56,K$11+1) -> 19.912406 | L17: =INDEX($G$16:$G$56,L$11+1) -> 16.302899 | M17: =INDEX($G$16:$G$56,M$11+1) -> 10.92816 | N17: =INDEX($G$16:$G$56,N$11+1) -> 7.3253649 | O17: =INDEX($G$16:$G$56,O$11+1) -> 2.2063575 | P17: 0
A18: 2 | B18: =B$4+B$6*(B17-B$4) -> 103.56058 | C18: =C$4+C$6*(C17-C$4) -> 38.36256 | D18: =D$4+D$6*(D17-D$4) -> 76.590446 | E18: =E$4+E$6*(E17-E$4) -> 65.353565 | F18: =MAX(ABS(B18-B$4),ABS(C18-C$4),ABS(D18-D$4),ABS(E18-E$4)) -> 5.3625604 | G18: =$B$13*$B$10^A18 -> 13.347685 | H18: =W_L*B18+W_T*C18+W_E*D18+W_R*E18 -> 38.290006 | J18: Scorecard | K18: =INDEX($H$16:$H$56,K$11+1) -> 37 | L18: =INDEX($H$16:$H$56,L$11+1) -> 37.88901 | M18: =INDEX($H$16:$H$56,M$11+1) -> 38.433092 | N18: =INDEX($H$16:$H$56,N$11+1) -> 38.395434 | O18: =INDEX($H$16:$H$56,O$11+1) -> 37.985923 | P18: =K6 -> 37.75
A19: 3 | B19: =B$4+B$6*(B18-B$4) -> 104.44456 | C19: =C$4+C$6*(C18-C$4) -> 37.390493 | D19: =D$4+D$6*(D18-D$4) -> 77.677609 | E19: =E$4+E$6*(E18-E$4) -> 65.780291 | F19: =MAX(ABS(B19-B$4),ABS(C19-C$4),ABS(D19-D$4),ABS(E19-E$4)) -> 4.3904931 | G19: =$B$13*$B$10^A19 -> 10.92816 | H19: =W_L*B19+W_T*C19+W_E*D19+W_R*E19 -> 38.433092
A20: 4 | B20: =B$4+B$6*(B19-B$4) -> 105.00821 | C20: =C$4+C$6*(C19-C$4) -> 36.594632 | D20: =D$4+D$6*(D19-D$4) -> 78.274256 | E20: =E$4+E$6*(E19-E$4) -> 66.096417 | F20: =MAX(ABS(B20-B$4),ABS(C20-C$4),ABS(D20-D$4),ABS(E20-E$4)) -> 3.5946317 | G20: =$B$13*$B$10^A20 -> 8.9472209 | H20: =W_L*B20+W_T*C20+W_E*D20+W_R*E20 -> 38.445169
A21: 5 | B21: =B$4+B$6*(B20-B$4) -> 105.3676 | C21: =C$4+C$6*(C20-C$4) -> 35.943036 | D21: =D$4+D$6*(D20-D$4) -> 78.601703 | E21: =E$4+E$6*(E20-E$4) -> 66.33061 | F21: =MAX(ABS(B21-B$4),ABS(C21-C$4),ABS(D21-D$4),ABS(E21-E$4)) -> 2.9430355 | G21: =$B$13*$B$10^A21 -> 7.3253649 | H21: =W_L*B21+W_T*C21+W_E*D21+W_R*E21 -> 38.395434
A22: 6 | B22: =B$4+B$6*(B21-B$4) -> 105.59677 | C22: =C$4+C$6*(C21-C$4) -> 35.409554 | D22: =D$4+D$6*(D21-D$4) -> 78.78141 | E22: =E$4+E$6*(E21-E$4) -> 66.504103 | F22: =MAX(ABS(B22-B$4),ABS(C22-C$4),ABS(D22-D$4),ABS(E22-E$4)) -> 2.4095537 | G22: =$B$13*$B$10^A22 -> 5.9975016 | H22: =W_L*B22+W_T*C22+W_E*D22+W_R*E22 -> 38.320907
A23: 7 | B23: =B$4+B$6*(B22-B$4) -> 105.74289 | C23: =C$4+C$6*(C22-C$4) -> 34.972776 | D23: =D$4+D$6*(D22-D$4) -> 78.880035 | E23: =E$4+E$6*(E22-E$4) -> 66.632631 | F23: =MAX(ABS(B23-B$4),ABS(C23-C$4),ABS(D23-D$4),ABS(E23-E$4)) -> 1.9727757 | G23: =$B$13*$B$10^A23 -> 4.910339 | H23: =W_L*B23+W_T*C23+W_E*D23+W_R*E23 -> 38.240767
A24: 8 | B24: =B$4+B$6*(B23-B$4) -> 105.83606 | C24: =C$4+C$6*(C23-C$4) -> 34.615172 | D24: =D$4+D$6*(D23-D$4) -> 78.934162 | E24: =E$4+E$6*(E23-E$4) -> 66.727846 | F24: =MAX(ABS(B24-B$4),ABS(C24-C$4),ABS(D24-D$4),ABS(E24-E$4)) -> 1.6151721 | G24: =$B$13*$B$10^A24 -> 4.0202455 | H24: =W_L*B24+W_T*C24+W_E*D24+W_R*E24 -> 38.164386
A25: 9 | B25: =B$4+B$6*(B24-B$4) -> 105.89547 | C25: =C$4+C$6*(C24-C$4) -> 34.322391 | D25: =D$4+D$6*(D24-D$4) -> 78.963867 | E25: =E$4+E$6*(E24-E$4) -> 66.798383 | F25: =MAX(ABS(B25-B$4),ABS(C25-C$4),ABS(D25-D$4),ABS(E25-E$4)) -> 1.3223911 | G25: =$B$13*$B$10^A25 -> 3.2914986 | H25: =W_L*B25+W_T*C25+W_E*D25+W_R*E25 -> 38.095835
A26: 10 | B26: =B$4+B$6*(B25-B$4) -> 105.93335 | C26: =C$4+C$6*(C25-C$4) -> 34.082682 | D26: =D$4+D$6*(D25-D$4) -> 78.98017 | E26: =E$4+E$6*(E25-E$4) -> 66.850639 | F26: =MAX(ABS(B26-B$4),ABS(C26-C$4),ABS(D26-D$4),ABS(E26-E$4)) -> 1.0826823 | G26: =$B$13*$B$10^A26 -> 2.6948512 | H26: =W_L*B26+W_T*C26+W_E*D26+W_R*E26 -> 38.03639
A27: 11 | B27: =B$4+B$6*(B26-B$4) -> 105.9575 | C27: =C$4+C$6*(C26-C$4) -> 33.886425 | D27: =D$4+D$6*(D26-D$4) -> 78.989117 | E27: =E$4+E$6*(E26-E$4) -> 66.88935 | F27: =MAX(ABS(B27-B$4),ABS(C27-C$4),ABS(D27-D$4),ABS(E27-E$4)) -> 0.88642527 | G27: =$B$13*$B$10^A27 -> 2.2063575 | H27: =W_L*B27+W_T*C27+W_E*D27+W_R*E27 -> 37.985923
A28: 12 | B28: =B$4+B$6*(B27-B$4) -> 105.9729 | C28: =C$4+C$6*(C27-C$4) -> 33.725744 | D28: =D$4+D$6*(D27-D$4) -> 78.994027 | E28: =E$4+E$6*(E27-E$4) -> 66.918029 | F28: =MAX(ABS(B28-B$4),ABS(C28-C$4),ABS(D28-D$4),ABS(E28-E$4)) -> 0.72574363 | G28: =$B$13*$B$10^A28 -> 1.8064128 | H28: =W_L*B28+W_T*C28+W_E*D28+W_R*E28 -> 37.943661
A29: 13 | B29: =B$4+B$6*(B28-B$4) -> 105.98272 | C29: =C$4+C$6*(C28-C$4) -> 33.594189 | D29: =D$4+D$6*(D28-D$4) -> 78.996722 | E29: =E$4+E$6*(E28-E$4) -> 66.939274 | F29: =MAX(ABS(B29-B$4),ABS(C29-C$4),ABS(D29-D$4),ABS(E29-E$4)) -> 0.59418863 | G29: =$B$13*$B$10^A29 -> 1.4789657 | H29: =W_L*B29+W_T*C29+W_E*D29+W_R*E29 -> 37.908589
A30: 14 | B30: =B$4+B$6*(B29-B$4) -> 105.98898 | C30: =C$4+C$6*(C29-C$4) -> 33.486481 | D30: =D$4+D$6*(D29-D$4) -> 78.998201 | E30: =E$4+E$6*(E29-E$4) -> 66.955013 | F30: =MAX(ABS(B30-B$4),ABS(C30-C$4),ABS(D30-D$4),ABS(E30-E$4)) -> 0.4864805 | G30: =$B$13*$B$10^A30 -> 1.2108747 | H30: =W_L*B30+W_T*C30+W_E*D30+W_R*E30 -> 37.879663
... A56: 40 | B56: =B$4+B$6*(B55-B$4) -> 106 | C56: =C$4+C$6*(C55-C$4) -> 33.002684 | D56: =D$4+D$6*(D55-D$4) -> 79 | E56: =E$4+E$6*(E55-E$4) -> 66.999982 | F56: =MAX(ABS(B56-B$4),ABS(C56-C$4),ABS(D56-D$4),ABS(E56-E$4)) -> 0.002683701 | G56: =$B$13*$B$10^A56 -> 0.0066798682 | H56: =W_L*B56+W_T*C56+W_E*D56+W_R*E56 -> 37.750676
A58: AXIOM Lab 1.5, step 4: run the map from two other starting states. From the digital Year-5 state the bound is attained: technology makes the largest first move and is also the slowest reading.
A60: From the digital Year-5 state | J60: From the restructuring Year-5 state
A61: Year | B61: Liquidity | C61: Technology | D61: Efficiency | E61: Strategic risk | F61: Largest gap | G61: Day-one bound | H61: Bound coefficient | J61: Year | K61: Liquidity | L61: Technology | M61: Efficiency | N61: Strategic risk | O61: Largest gap | P61: Day-one bound | Q61: Bound coefficient
A62: 0 | B62: =Declarations!$C$27+(Declarations!$C$4-Declarations!$C$27)*EXP(-Declarations!$D$27*5)+IF(Declarations!$E$27=0,0,Declarations!$E$27*(5/Declarations!$F$27)*EXP(1-5/Declarations!$F$27))+IF(5>=T_sale,Declarations!$G$27,0) -> 94.295601 | C62: =Declarations!$C$28+(Declarations!$C$7-Declarations!$C$28)*EXP(-Declarations!$D$28*5)+IF(Declarations!$E$28=0,0,Declarations!$E$28*(5/Declarations!$F$28)*EXP(1-5/Declarations!$F$28))+IF(5>=T_sale,Declarations!$G$28,0) -> 75.634669 | D62: =Declarations!$C$29+(Declarations!$C$8-Declarations!$C$29)*EXP(-Declarations!$D$29*5)+IF(Declarations!$E$29=0,0,Declarations!$E$29*(5/Declarations!$F$29)*EXP(1-5/Declarations!$F$29))+IF(5>=T_sale,Declarations!$G$29,0) -> 73.598331 | E62: =Declarations!$C$30+(Declarations!$C$10-Declarations!$C$30)*EXP(-Declarations!$D$30*5)+IF(Declarations!$E$30=0,0,Declarations!$E$30*(5/Declarations!$F$30)*EXP(1-5/Declarations!$F$30))+IF(5>=T_sale,Declarations!$G$30,0) -> 55.21775 | F62: =MAX(ABS(B62-B$4),ABS(C62-C$4),ABS(D62-D$4),ABS(E62-E$4)) -> 42.634669 | G62: =$H$62*$B$10^A62 -> 42.634669 | H62: =MAX(ABS(B63-B62),ABS(C63-C62),ABS(D63-D62),ABS(E63-E62))/(1-$B$10) -> 42.634669 | J62: 0 | K62: =Declarations!$C$31+(Declarations!$C$4-Declarations!$C$31)*EXP(-Declarations!$D$31*5)+IF(Declarations!$E$31=0,0,Declarations!$E$31*(5/Declarations!$F$31)*EXP(1-5/Declarations!$F$31))+IF(5>=T_sale,Declarations!$G$31,0) -> 121.10748 | L62: =Declarations!$C$32+(Declarations!$C$7-Declarations!$C$32)*EXP(-Declarations!$D$32*5)+IF(Declarations!$E$32=0,0,Declarations!$E$32*(5/Declarations!$F$32)*EXP(1-5/Declarations!$F$32))+IF(5>=T_sale,Declarations!$G$32,0) -> 38.859514 | M62: =Declarations!$C$33+(Declarations!$C$8-Declarations!$C$33)*EXP(-Declarations!$D$33*5)+IF(Declarations!$E$33=0,0,Declarations!$E$33*(5/Declarations!$F$33)*EXP(1-5/Declarations!$F$33))+IF(5>=T_sale,Declarations!$G$33,0) -> 73.683802 | N62: =Declarations!$C$34+(Declarations!$C$10-Declarations!$C$34)*EXP(-Declarations!$D$34*5)+IF(Declarations!$E$34=0,0,Declarations!$E$34*(5/Declarations!$F$34)*EXP(1-5/Declarations!$F$34))+IF(5>=T_sale,Declarations!$G$34,0) -> 49.390192 | O62: =MAX(ABS(K62-B$4),ABS(L62-C$4),ABS(M62-D$4),ABS(N62-E$4)) -> 17.609808 | P62: =$Q$62*$B$10^J62 -> 30.20107 | Q62: =MAX(ABS(K63-K62),ABS(L63-L62),ABS(M63-M62),ABS(N63-N62))/(1-$B$10) -> 30.20107
A63: 1 | B63: =B$4+B$6*(B62-B$4) -> 98.536946 | C63: =C$4+C$6*(C62-C$4) -> 67.906315 | D63: =D$4+D$6*(D62-D$4) -> 76.035501 | E63: =E$4+E$6*(E62-E$4) -> 58.271494 | F63: =MAX(ABS(B63-B$4),ABS(C63-C$4),ABS(D63-D$4),ABS(E63-E$4)) -> 34.906315 | G63: =$H$62*$B$10^A63 -> 34.906315 | J63: 1 | K63: =B$4+B$6*(K62-B$4) -> 115.63295 | L63: =C$4+C$6*(L62-C$4) -> 37.797365 | M63: =D$4+D$6*(M62-D$4) -> 76.082409 | N63: =E$4+E$6*(N62-E$4) -> 53.954333 | O63: =MAX(ABS(K63-B$4),ABS(L63-C$4),ABS(M63-D$4),ABS(N63-E$4)) -> 13.045667 | P63: =$Q$62*$B$10^J63 -> 24.726545
A64: 2 | B64: =B$4+B$6*(B63-B$4) -> 101.24135 | C64: =C$4+C$6*(C63-C$4) -> 61.578873 | D64: =D$4+D$6*(D63-D$4) -> 77.373049 | E64: =E$4+E$6*(E63-E$4) -> 60.533764 | F64: =MAX(ABS(B64-B$4),ABS(C64-C$4),ABS(D64-D$4),ABS(E64-E$4)) -> 28.578873 | G64: =$H$62*$B$10^A64 -> 28.578873 | J64: 2 | K64: =B$4+B$6*(K63-B$4) -> 112.14224 | L64: =C$4+C$6*(L63-C$4) -> 36.92775 | M64: =D$4+D$6*(M63-D$4) -> 77.398792 | N64: =E$4+E$6*(N63-E$4) -> 57.335532 | O64: =MAX(ABS(K64-B$4),ABS(L64-C$4),ABS(M64-D$4),ABS(N64-E$4)) -> 9.6644678 | P64: =$Q$62*$B$10^J64 -> 20.244383
A65: 3 | B65: =B$4+B$6*(B64-B$4) -> 102.96575 | C65: =C$4+C$6*(C64-C$4) -> 56.398403 | D65: =D$4+D$6*(D64-D$4) -> 78.10711 | E65: =E$4+E$6*(E64-E$4) -> 62.209694 | F65: =MAX(ABS(B65-B$4),ABS(C65-C$4),ABS(D65-D$4),ABS(E65-E$4)) -> 23.398403 | G65: =$H$62*$B$10^A65 -> 23.398403 | J65: 3 | K65: =B$4+B$6*(K64-B$4) -> 109.91647 | L65: =C$4+C$6*(L64-C$4) -> 36.21577 | M65: =D$4+D$6*(M64-D$4) -> 78.121238 | N65: =E$4+E$6*(N64-E$4) -> 59.840386 | O65: =MAX(ABS(K65-B$4),ABS(L65-C$4),ABS(M65-D$4),ABS(N65-E$4)) -> 7.1596138 | P65: =$Q$62*$B$10^J65 -> 16.574699
A66: 4 | B66: =B$4+B$6*(B65-B$4) -> 104.06528 | C66: =C$4+C$6*(C65-C$4) -> 52.156992 | D66: =D$4+D$6*(D65-D$4) -> 78.509972 | E66: =E$4+E$6*(E65-E$4) -> 63.451254 | F66: =MAX(ABS(B66-B$4),ABS(C66-C$4),ABS(D66-D$4),ABS(E66-E$4)) -> 19.156992 | G66: =$H$62*$B$10^A66 -> 19.156992 | J66: 4 | K66: =B$4+B$6*(K65-B$4) -> 108.49725 | L66: =C$4+C$6*(L65-C$4) -> 35.63285 | M66: =D$4+D$6*(M65-D$4) -> 78.517725 | N66: =E$4+E$6*(N65-E$4) -> 61.696028 | O66: =MAX(ABS(K66-B$4),ABS(L66-C$4),ABS(M66-D$4),ABS(N66-E$4)) -> 5.3039724 | P66: =$Q$62*$B$10^J66 -> 13.570216
A67: 5 | B67: =B$4+B$6*(B66-B$4) -> 104.76637 | C67: =C$4+C$6*(C66-C$4) -> 48.684418 | D67: =D$4+D$6*(D66-D$4) -> 78.731067 | E67: =E$4+E$6*(E66-E$4) -> 64.371025 | F67: =MAX(ABS(B67-B$4),ABS(C67-C$4),ABS(D67-D$4),ABS(E67-E$4)) -> 15.684418 | G67: =$H$62*$B$10^A67 -> 15.684418 | J67: 5 | K67: =B$4+B$6*(K66-B$4) -> 107.59232 | L67: =C$4+C$6*(L66-C$4) -> 35.155595 | M67: =D$4+D$6*(M66-D$4) -> 78.735322 | N67: =E$4+E$6*(N66-E$4) -> 63.070721 | O67: =MAX(ABS(K67-B$4),ABS(L67-C$4),ABS(M67-D$4),ABS(N67-E$4)) -> 3.9292794 | P67: =$Q$62*$B$10^J67 -> 11.110353
A68: 6 | B68: =B$4+B$6*(B67-B$4) -> 105.2134 | C68: =C$4+C$6*(C67-C$4) -> 45.841316 | D68: =D$4+D$6*(D67-D$4) -> 78.852406 | E68: =E$4+E$6*(E67-E$4) -> 65.052407 | F68: =MAX(ABS(B68-B$4),ABS(C68-C$4),ABS(D68-D$4),ABS(E68-E$4)) -> 12.841316 | G68: =$H$62*$B$10^A68 -> 12.841316 | J68: 6 | K68: =B$4+B$6*(K67-B$4) -> 107.01531 | L68: =C$4+C$6*(L67-C$4) -> 34.764852 | M68: =D$4+D$6*(M67-D$4) -> 78.854742 | N68: =E$4+E$6*(N67-E$4) -> 64.089118 | O68: =MAX(ABS(K68-B$4),ABS(L68-C$4),ABS(M68-D$4),ABS(N68-E$4)) -> 2.9108818 | P68: =$Q$62*$B$10^J68 -> 9.0963875
A69: 7 | B69: =B$4+B$6*(B68-B$4) -> 105.49844 | C69: =C$4+C$6*(C68-C$4) -> 43.51358 | D69: =D$4+D$6*(D68-D$4) -> 78.918999 | E69: =E$4+E$6*(E68-E$4) -> 65.557188 | F69: =MAX(ABS(B69-B$4),ABS(C69-C$4),ABS(D69-D$4),ABS(E69-E$4)) -> 10.51358 | G69: =$H$62*$B$10^A69 -> 10.51358 | J69: 7 | K69: =B$4+B$6*(K68-B$4) -> 106.64739 | L69: =C$4+C$6*(L68-C$4) -> 34.444938 | M69: =D$4+D$6*(M68-D$4) -> 78.920281 | N69: =E$4+E$6*(N68-E$4) -> 64.843566 | O69: =MAX(ABS(K69-B$4),ABS(L69-C$4),ABS(M69-D$4),ABS(N69-E$4)) -> 2.1564342 | P69: =$Q$62*$B$10^J69 -> 7.4474922
A70: 8 | B70: =B$4+B$6*(B69-B$4) -> 105.68019 | C70: =C$4+C$6*(C69-C$4) -> 41.607791 | D70: =D$4+D$6*(D69-D$4) -> 78.955546 | E70: =E$4+E$6*(E69-E$4) -> 65.931138 | F70: =MAX(ABS(B70-B$4),ABS(C70-C$4),ABS(D70-D$4),ABS(E70-E$4)) -> 8.6077912 | G70: =$H$62*$B$10^A70 -> 8.6077912 | J70: 8 | K70: =B$4+B$6*(K69-B$4) -> 106.41279 | L70: =C$4+C$6*(L69-C$4) -> 34.183016 | M70: =D$4+D$6*(M69-D$4) -> 78.956249 | N70: =E$4+E$6*(N69-E$4) -> 65.402474 | O70: =MAX(ABS(K70-B$4),ABS(L70-C$4),ABS(M70-D$4),ABS(N70-E$4)) -> 1.5975258 | P70: =$Q$62*$B$10^J70 -> 6.0974909
A71: 9 | B71: =B$4+B$6*(B70-B$4) -> 105.79608 | C71: =C$4+C$6*(C70-C$4) -> 40.047463 | D71: =D$4+D$6*(D70-D$4) -> 78.975603 | E71: =E$4+E$6*(E70-E$4) -> 66.208168 | F71: =MAX(ABS(B71-B$4),ABS(C71-C$4),ABS(D71-D$4),ABS(E71-E$4)) -> 7.0474634 | G71: =$H$62*$B$10^A71 -> 7.0474634 | J71: 9 | K71: =B$4+B$6*(K70-B$4) -> 106.26321 | L71: =C$4+C$6*(L70-C$4) -> 33.968571 | M71: =D$4+D$6*(M70-D$4) -> 78.975989 | N71: =E$4+E$6*(N70-E$4) -> 65.816524 | O71: =MAX(ABS(K71-B$4),ABS(L71-C$4),ABS(M71-D$4),ABS(N71-E$4)) -> 1.1834762 | P71: =$Q$62*$B$10^J71 -> 4.9922033
A72: 10 | B72: =B$4+B$6*(B71-B$4) -> 105.86998 | C72: =C$4+C$6*(C71-C$4) -> 38.769975 | D72: =D$4+D$6*(D71-D$4) -> 78.986611 | E72: =E$4+E$6*(E71-E$4) -> 66.413396 | F72: =MAX(ABS(B72-B$4),ABS(C72-C$4),ABS(D72-D$4),ABS(E72-E$4)) -> 5.769975 | G72: =$H$62*$B$10^A72 -> 5.769975 | J72: 10 | K72: =B$4+B$6*(K71-B$4) -> 106.16783 | L72: =C$4+C$6*(L71-C$4) -> 33.792999 | M72: =D$4+D$6*(M71-D$4) -> 78.986822 | N72: =E$4+E$6*(N71-E$4) -> 66.123259 | O72: =MAX(ABS(K72-B$4),ABS(L72-C$4),ABS(M72-D$4),ABS(N72-E$4)) -> 0.87674074 | P72: =$Q$62*$B$10^J72 -> 4.0872704
A73: 11 | B73: =B$4+B$6*(B72-B$4) -> 105.91709 | C73: =C$4+C$6*(C72-C$4) -> 37.724056 | D73: =D$4+D$6*(D72-D$4) -> 78.992652 | E73: =E$4+E$6*(E72-E$4) -> 66.565433 | F73: =MAX(ABS(B73-B$4),ABS(C73-C$4),ABS(D73-D$4),ABS(E73-E$4)) -> 4.724056 | G73: =$H$62*$B$10^A73 -> 4.724056 | J73: 11 | K73: =B$4+B$6*(K72-B$4) -> 106.10701 | L73: =C$4+C$6*(L72-C$4) -> 33.649253 | M73: =D$4+D$6*(M72-D$4) -> 78.992768 | N73: =E$4+E$6*(N72-E$4) -> 66.350494 | O73: =MAX(ABS(K73-B$4),ABS(L73-C$4),ABS(M73-D$4),ABS(N73-E$4)) -> 0.64950551 | P73: =$Q$62*$B$10^J73 -> 3.3463739
A74: 12 | B74: =B$4+B$6*(B73-B$4) -> 105.94714 | C74: =C$4+C$6*(C73-C$4) -> 36.86773 | D74: =D$4+D$6*(D73-D$4) -> 78.995967 | E74: =E$4+E$6*(E73-E$4) -> 66.678065 | F74: =MAX(ABS(B74-B$4),ABS(C74-C$4),ABS(D74-D$4),ABS(E74-E$4)) -> 3.8677299 | G74: =$H$62*$B$10^A74 -> 3.8677299 | J74: 12 | K74: =B$4+B$6*(K73-B$4) -> 106.06823 | L74: =C$4+C$6*(L73-C$4) -> 33.531563 | M74: =D$4+D$6*(M73-D$4) -> 78.996031 | N74: =E$4+E$6*(N73-E$4) -> 66.518834 | O74: =MAX(ABS(K74-B$4),ABS(L74-C$4),ABS(M74-D$4),ABS(N74-E$4)) -> 0.53156315 | P74: =$Q$62*$B$10^J74 -> 2.7397793
... A102: 40 | B102: =B$4+B$6*(B101-B$4) -> 106 | C102: =C$4+C$6*(C101-C$4) -> 33.014302 | D102: =D$4+D$6*(D101-D$4) -> 79 | E102: =E$4+E$6*(E101-E$4) -> 66.999928 | F102: =MAX(ABS(B102-B$4),ABS(C102-C$4),ABS(D102-D$4),ABS(E102-E$4)) -> 0.014302338 | G102: =$H$62*$B$10^A102 -> 0.014302338 | J102: 40 | K102: =B$4+B$6*(K101-B$4) -> 106 | L102: =C$4+C$6*(L101-C$4) -> 33.001966 | M102: =D$4+D$6*(M101-D$4) -> 79 | N102: =E$4+E$6*(N101-E$4) -> 66.999892 | O102: =MAX(ABS(K102-B$4),ABS(L102-C$4),ABS(M102-D$4),ABS(N102-E$4)) -> 0.0019656481 | P102: =$Q$62*$B$10^J102 -> 0.01013133
A104: First year below one point: bound, then actual | F104: =COUNTIF(G62:G102,">=1") -> 19 | G104: =COUNTIF(F62:F102,">=1") -> 19 | J104: First year below one point: bound, then actual | O104: =COUNTIF(P62:P102,">=1") -> 18 | P104: =COUNTIF(O62:O102,">=1") -> 10
A105: Years the gap exceeds its bound | F105: =SUMPRODUCT(--(F62:F102>G62:G102+0.000000001)) -> 0 | J105: Years the gap exceeds its bound | O105: =SUMPRODUCT(--(O62:O102>P62:P102+0.000000001)) -> 0

Sheet Equilibria
A1: Two more equilibrium worlds: a start-up, an unstable middle, a coupled contraction (Figure 5.3; Online Appendix 5.B.4-5.B.7; AXIOM Lab 1.5, step 4)
A3: The start-up (Online Appendix 5.B.7) | B3: Value | C3: Book | F3: Stuck in the middle (5.B.6): f(x) = 3x^2 - 2x^3 | G3: x | H3: f(x) - x | I3: Slope f'(x) = 6x(1 - x) | K3: A service operation (5.B.4) | L3: Occupancy | M3: Staffing
A4: Growth rate r | B4: 0.9 | F4: cost leadership | G4: 0 | H4: =3*G4^2-2*G4^3-G4 -> 0 | I4: =6*G4*(1-G4) -> 0 | K4: A, first row | L4: 0.55 | M4: 0.2
A5: Market capacity kappa | B5: 100 | F5: the middle | G5: 0.5 | H5: =3*G5^2-2*G5^3-G5 -> 0 | I5: =6*G5*(1-G5) -> 1.5 | K5: A, second row | L5: 0.1 | M5: 0.6
A6: Quarterly step (years) | B6: 0.25 | F6: differentiation | G6: 1 | H6: =3*G6^2-2*G6^3-G6 -> 0 | I6: =6*G6*(1-G6) -> 0 | K6: b | L6: 28 | M6: 24
A7: User base at the start | B7: 2 | F7: Equilibria (f(x) = x) | G7: =SUMPRODUCT(--(ABS(H4:H6)<0.000000000001)) -> 3 | K7: Start x0 | L7: 70 | M7: 60
A8: Slope near zero, f'(0) = 1 + step x r | B8: =1+B6*B4 -> 1.225 | C8: 1.225: 22.5 percent a quarter | K8: Row sums | L8: =ABS(L4)+ABS(M4) -> 0.75 | M8: =ABS(L5)+ABS(M5) -> 0.7
A9: Slope at the wall, f'(kappa) = 1 - step x r | B9: =1-B6*B4 -> 0.775 | C9: 0.775 | F9: Year | G9: From 0.49 | H9: From 0.51 | K9: L: the largest row sum | L9: =MAX(L8:M8) -> 0.75
A10: f(60) | B10: =60+B6*B4*60*(1-60/B5) -> 65.4 | C10: 65.4 | F10: 0 | G10: 0.49 | H10: 0.51 | K10: Determinant of I - A | L10: =(1-L4)*(1-M5)-M4*L5 -> 0.16
A11: Slope at 60, f'(60) | B11: =1+B6*B4*(1-2*60/B5) -> 0.955 | C11: 0.955 | F11: 1 | G11: =3*G10^2-2*G10^3 -> 0.485002 | H11: =3*H10^2-2*H10^3 -> 0.514998 | K11: Equilibrium x* | L11: =((1-M5)*L6+M4*M6)/L10 -> 100 | M11: =(L5*L6+(1-L4)*M6)/L10 -> 85
A12: User base at year 5 | B12: =INDEX(C17:C65,21) -> 58.128602 | C12: 58.1 | F12: 2 | G12: =3*G11^2-2*G11^3 -> 0.47750975 | H12: =3*H11^2-2*H11^3 -> 0.52249025 | K12: First step: largest move | L12: =MAX(ABS(L17-L16),ABS(M17-M16)) -> 8.5
A13: User base at year 10 | B13: =INDEX(C17:C65,41) -> 99.490886 | C13: 99.5 | F13: 3 | G13: =3*G12^2-2*G12^3 -> 0.46628737 | H13: =3*H12^2-2*H12^3 -> 0.53371263 | K13: Bound coefficient: step / (1 - L) | L13: =L12/(1-L9) -> 34
A14: First passes 60 (year) | B14: =COUNTIF(C17:C65,"<=60")*B6 -> 5.25 | C14: year 5.25 | F14: 4 | G14: =3*G13^2-2*G13^3 -> 0.44950769 | H14: =3*H13^2-2*H13^3 -> 0.55049231
F15: 5 | G15: =3*G14^2-2*G14^3 -> 0.42451899 | H15: =3*H14^2-2*H14^3 -> 0.57548101 | K15: k | L15: Occupancy | M15: Staffing | N15: Distance to x* | O15: A priori bound | P15: A posteriori bound
A16: Quarter | B16: Year | C16: User base | D16: Slope f'(x) | F16: 6 | G16: =3*G15^2-2*G15^3 -> 0.38763858 | H16: =3*H15^2-2*H15^3 -> 0.61236142 | K16: 0 | L16: =L7 -> 70 | M16: =M7 -> 60 | N16: =MAX(ABS(L16-$L$11),ABS(M16-$M$11)) -> 30 | O16: =$L$13*$L$9^K16 -> 34
A17: 0 | B17: =A17*$B$6 -> 0 | C17: =$B$7 -> 2 | D17: =1+$B$6*$B$4*(1-2*C17/$B$5) -> 1.216 | F17: 7 | G17: =3*G16^2-2*G16^3 -> 0.33429501 | H17: =3*H16^2-2*H16^3 -> 0.66570499 | K17: 1 | L17: =$L$4*L16+$M$4*M16+$L$6 -> 78.5 | M17: =$L$5*L16+$M$5*M16+$M$6 -> 67 | N17: =MAX(ABS(L17-$L$11),ABS(M17-$M$11)) -> 21.5 | O17: =$L$13*$L$9^K17 -> 25.5 | P17: =$L$9/(1-$L$9)*MAX(ABS(L17-L16),ABS(M17-M16)) -> 25.5
A18: 1 | B18: =A18*$B$6 -> 0.25 | C18: =C17+$B$6*$B$4*C17*(1-C17/$B$5) -> 2.441 | D18: =1+$B$6*$B$4*(1-2*C18/$B$5) -> 1.2140155 | F18: 8 | G18: =3*G17^2-2*G17^3 -> 0.26054242 | H18: =3*H17^2-2*H17^3 -> 0.73945758 | K18: 2 | L18: =$L$4*L17+$M$4*M17+$L$6 -> 84.575 | M18: =$L$5*L17+$M$5*M17+$M$6 -> 72.05 | N18: =MAX(ABS(L18-$L$11),ABS(M18-$M$11)) -> 15.425 | O18: =$L$13*$L$9^K18 -> 19.125 | P18: =$L$9/(1-$L$9)*MAX(ABS(L18-L17),ABS(M18-M17)) -> 18.225
A19: 2 | B19: =A19*$B$6 -> 0.5 | C19: =C18+$B$6*$B$4*C18*(1-C18/$B$5) -> 2.9768184 | D19: =1+$B$6*$B$4*(1-2*C19/$B$5) -> 1.2116043 | F19: 9 | G19: =3*G18^2-2*G18^3 -> 0.1682746 | H19: =3*H18^2-2*H18^3 -> 0.8317254 | K19: 3 | L19: =$L$4*L18+$M$4*M18+$L$6 -> 88.92625 | M19: =$L$5*L18+$M$5*M18+$M$6 -> 75.6875 | N19: =MAX(ABS(L19-$L$11),ABS(M19-$M$11)) -> 11.07375 | O19: =$L$13*$L$9^K19 -> 14.34375 | P19: =$L$9/(1-$L$9)*MAX(ABS(L19-L18),ABS(M19-M18)) -> 13.05375
A20: 3 | B20: =A20*$B$6 -> 0.75 | C20: =C19+$B$6*$B$4*C19*(1-C19/$B$5) -> 3.6266643 | D20: =1+$B$6*$B$4*(1-2*C20/$B$5) -> 1.20868 | F20: 10 | G20: =3*G19^2-2*G19^3 -> 0.075419178 | H20: =3*H19^2-2*H19^3 -> 0.92458082 | K20: 4 | L20: =$L$4*L19+$M$4*M19+$L$6 -> 92.046937 | M20: =$L$5*L19+$M$5*M19+$M$6 -> 78.305125 | N20: =MAX(ABS(L20-$L$11),ABS(M20-$M$11)) -> 7.9530625 | O20: =$L$13*$L$9^K20 -> 10.757812 | P20: =$L$9/(1-$L$9)*MAX(ABS(L20-L19),ABS(M20-M19)) -> 9.3620625
A21: 4 | B21: =A21*$B$6 -> 1 | C21: =C20+$B$6*$B$4*C20*(1-C20/$B$5) -> 4.4130702 | D21: =1+$B$6*$B$4*(1-2*C21/$B$5) -> 1.2051412 | K21: 5 | L21: =$L$4*L20+$M$4*M20+$L$6 -> 94.286841 | M21: =$L$5*L20+$M$5*M20+$M$6 -> 80.187769 | N21: =MAX(ABS(L21-$L$11),ABS(M21-$M$11)) -> 5.7131594 | O21: =$L$13*$L$9^K21 -> 8.0683594 | P21: =$L$9/(1-$L$9)*MAX(ABS(L21-L20),ABS(M21-M20)) -> 6.7197094
A22: 5 | B22: =A22*$B$6 -> 1.25 | C22: =C21+$B$6*$B$4*C21*(1-C21/$B$5) -> 5.3621918 | D22: =1+$B$6*$B$4*(1-2*C22/$B$5) -> 1.2008701 | K22: 6 | L22: =$L$4*L21+$M$4*M21+$L$6 -> 95.895316 | M22: =$L$5*L21+$M$5*M21+$M$6 -> 81.541345 | N22: =MAX(ABS(L22-$L$11),ABS(M22-$M$11)) -> 4.1046839 | O22: =$L$13*$L$9^K22 -> 6.0512695 | P22: =$L$9/(1-$L$9)*MAX(ABS(L22-L21),ABS(M22-M21)) -> 4.8254264
A23: 6 | B23: =A23*$B$6 -> 1.5 | C23: =C22+$B$6*$B$4*C22*(1-C22/$B$5) -> 6.5039905 | D23: =1+$B$6*$B$4*(1-2*C23/$B$5) -> 1.195732 | K23: 7 | L23: =$L$4*L22+$M$4*M22+$L$6 -> 97.050693 | M23: =$L$5*L22+$M$5*M22+$M$6 -> 82.514339 | N23: =MAX(ABS(L23-$L$11),ABS(M23-$M$11)) -> 2.9493071 | O23: =$L$13*$L$9^K23 -> 4.5384521 | P23: =$L$9/(1-$L$9)*MAX(ABS(L23-L22),ABS(M23-M22)) -> 3.4661305
A24: 7 | B24: =A24*$B$6 -> 1.75 | C24: =C23+$B$6*$B$4*C23*(1-C23/$B$5) -> 7.8722091 | D24: =1+$B$6*$B$4*(1-2*C24/$B$5) -> 1.1895751 | K24: 8 | L24: =$L$4*L23+$M$4*M23+$L$6 -> 97.880749 | M24: =$L$5*L23+$M$5*M23+$M$6 -> 83.213673 | N24: =MAX(ABS(L24-$L$11),ABS(M24-$M$11)) -> 2.1192511 | O24: =$L$13*$L$9^K24 -> 3.4038391 | P24: =$L$9/(1-$L$9)*MAX(ABS(L24-L23),ABS(M24-M23)) -> 2.4901678
A25: 8 | B25: =A25*$B$6 -> 2 | C25: =C24+$B$6*$B$4*C24*(1-C24/$B$5) -> 9.5040199 | D25: =1+$B$6*$B$4*(1-2*C25/$B$5) -> 1.1822319 | K25: 9 | L25: =$L$4*L24+$M$4*M24+$L$6 -> 98.477146 | M25: =$L$5*L24+$M$5*M24+$M$6 -> 83.716278 | N25: =MAX(ABS(L25-$L$11),ABS(M25-$M$11)) -> 1.5228536 | O25: =$L$13*$L$9^K25 -> 2.5528793 | P25: =$L$9/(1-$L$9)*MAX(ABS(L25-L24),ABS(M25-M24)) -> 1.7891926
A26: 9 | B26: =A26*$B$6 -> 2.25 | C26: =C25+$B$6*$B$4*C25*(1-C25/$B$5) -> 11.43919 | D26: =1+$B$6*$B$4*(1-2*C26/$B$5) -> 1.1735236 | K26: 10 | L26: =$L$4*L25+$M$4*M25+$L$6 -> 98.905686 | M26: =$L$5*L25+$M$5*M25+$M$6 -> 84.077482 | N26: =MAX(ABS(L26-$L$11),ABS(M26-$M$11)) -> 1.0943138 | O26: =$L$13*$L$9^K26 -> 1.9146595 | P26: =$L$9/(1-$L$9)*MAX(ABS(L26-L25),ABS(M26-M25)) -> 1.2856194
A27: 10 | B27: =A27*$B$6 -> 2.5 | C27: =C26+$B$6*$B$4*C26*(1-C26/$B$5) -> 13.718584 | D27: =1+$B$6*$B$4*(1-2*C27/$B$5) -> 1.1632664 | K27: 11 | L27: =$L$4*L26+$M$4*M26+$L$6 -> 99.213624 | M27: =$L$5*L26+$M$5*M26+$M$6 -> 84.337058 | N27: =MAX(ABS(L27-$L$11),ABS(M27-$M$11)) -> 0.78637625 | O27: =$L$13*$L$9^K27 -> 1.4359946 | P27: =$L$9/(1-$L$9)*MAX(ABS(L27-L26),ABS(M27-M26)) -> 0.92381265
A28: 11 | B28: =A28*$B$6 -> 2.75 | C28: =C27+$B$6*$B$4*C27*(1-C27/$B$5) -> 16.381816 | D28: =1+$B$6*$B$4*(1-2*C28/$B$5) -> 1.1512818 | K28: 12 | L28: =$L$4*L27+$M$4*M27+$L$6 -> 99.434905 | M28: =$L$5*L27+$M$5*M27+$M$6 -> 84.523597 | N28: =MAX(ABS(L28-$L$11),ABS(M28-$M$11)) -> 0.56509541 | O28: =$L$13*$L$9^K28 -> 1.076996 | P28: =$L$9/(1-$L$9)*MAX(ABS(L28-L27),ABS(M28-M27)) -> 0.66384252
A29: 12 | B29: =A29*$B$6 -> 3 | C29: =C28+$B$6*$B$4*C28*(1-C28/$B$5) -> 19.463906 | D29: =1+$B$6*$B$4*(1-2*C29/$B$5) -> 1.1374124 | K29: 13 | L29: =$L$4*L28+$M$4*M28+$L$6 -> 99.593917 | M29: =$L$5*L28+$M$5*M28+$M$6 -> 84.657649 | N29: =MAX(ABS(L29-$L$11),ABS(M29-$M$11)) -> 0.40608308 | O29: =$L$13*$L$9^K29 -> 0.80774698 | P29: =$L$9/(1-$L$9)*MAX(ABS(L29-L28),ABS(M29-M28)) -> 0.47703698
A30: 13 | B30: =A30*$B$6 -> 3.25 | C30: =C29+$B$6*$B$4*C29*(1-C29/$B$5) -> 22.990887 | D30: =1+$B$6*$B$4*(1-2*C30/$B$5) -> 1.121541 | K30: 14 | L30: =$L$4*L29+$M$4*M29+$L$6 -> 99.708184 | M30: =$L$5*L29+$M$5*M29+$M$6 -> 84.753981 | N30: =MAX(ABS(L30-$L$11),ABS(M30-$M$11)) -> 0.29181597 | O30: =$L$13*$L$9^K30 -> 0.60581023 | P30: =$L$9/(1-$L$9)*MAX(ABS(L30-L29),ABS(M30-M29)) -> 0.34280134
A31: 14 | B31: =A31*$B$6 -> 3.5 | C31: =C30+$B$6*$B$4*C30*(1-C30/$B$5) -> 26.974529 | D31: =1+$B$6*$B$4*(1-2*C31/$B$5) -> 1.1036146 | K31: 15 | L31: =$L$4*L30+$M$4*M30+$L$6 -> 99.790297 | M31: =$L$5*L30+$M$5*M30+$M$6 -> 84.823207 | N31: =MAX(ABS(L31-$L$11),ABS(M31-$M$11)) -> 0.20970261 | O31: =$L$13*$L$9^K31 -> 0.45435767 | P31: =$L$9/(1-$L$9)*MAX(ABS(L31-L30),ABS(M31-M30)) -> 0.24634008
A32: 15 | B32: =A32*$B$6 -> 3.75 | C32: =C31+$B$6*$B$4*C31*(1-C31/$B$5) -> 31.406642 | D32: =1+$B$6*$B$4*(1-2*C32/$B$5) -> 1.0836701 | K32: 16 | L32: =$L$4*L31+$M$4*M31+$L$6 -> 99.849305 | M32: =$L$5*L31+$M$5*M31+$M$6 -> 84.872954 | N32: =MAX(ABS(L32-$L$11),ABS(M32-$M$11)) -> 0.15069505 | O32: =$L$13*$L$9^K32 -> 0.34076826 | P32: =$L$9/(1-$L$9)*MAX(ABS(L32-L31),ABS(M32-M31)) -> 0.17702268
... A46: 29 | B46: =A46*$B$6 -> 7.25 | C46: =C45+$B$6*$B$4*C45*(1-C45/$B$5) -> 92.363373 | D46: =1+$B$6*$B$4*(1-2*C46/$B$5) -> 0.80936482 | K46: 30 | L46: =$L$4*L45+$M$4*M45+$L$6 -> 99.998524 | M46: =$L$5*L45+$M$5*M45+$M$6 -> 84.998756 | N46: =MAX(ABS(L46-$L$11),ABS(M46-$M$11)) -> 0.0014758361 | O46: =$L$13*$L$9^K46 -> 0.0060717911 | P46: =$L$9/(1-$L$9)*MAX(ABS(L46-L45),ABS(M46-M45)) -> 0.0017336685
A47: 30 | B47: =A47*$B$6 -> 7.5 | C47: =C46+$B$6*$B$4*C46*(1-C46/$B$5) -> 93.950398 | D47: =1+$B$6*$B$4*(1-2*C47/$B$5) -> 0.80222321
A48: 31 | B48: =A48*$B$6 -> 7.75 | C48: =C47+$B$6*$B$4*C47*(1-C47/$B$5) -> 95.229214 | D48: =1+$B$6*$B$4*(1-2*C48/$B$5) -> 0.79646854 | K48: A priori bound below one point from k | L48: =COUNTIF(O16:O46,">1") -> 13 | M48: 13
A49: 32 | B49: =A49*$B$6 -> 8 | C49: =C48+$B$6*$B$4*C48*(1-C48/$B$5) -> 96.25143 | D49: =1+$B$6*$B$4*(1-2*C49/$B$5) -> 0.79186857 | K49: Actual distance within one point by k | L49: =COUNTIF(N16:N46,">1") -> 11 | M49: 11
A50: 33 | B50: =A50*$B$6 -> 8.25 | C50: =C49+$B$6*$B$4*C49*(1-C49/$B$5) -> 97.063242 | D50: =1+$B$6*$B$4*(1-2*C50/$B$5) -> 0.78821541 | K50: At k = 5: actual distance | L50: =N21 -> 5.7131594 | M50: 5.7
A51: 34 | B51: =A51*$B$6 -> 8.5 | C51: =C50+$B$6*$B$4*C50*(1-C50/$B$5) -> 97.704607 | D51: =1+$B$6*$B$4*(1-2*C51/$B$5) -> 0.78532927 | K51: At k = 5: a priori bound | L51: =O21 -> 8.0683594 | M51: 8.1
A52: 35 | B52: =A52*$B$6 -> 8.75 | C52: =C51+$B$6*$B$4*C51*(1-C51/$B$5) -> 98.209216 | D52: =1+$B$6*$B$4*(1-2*C52/$B$5) -> 0.78305853 | K52: At k = 5: a posteriori bound (Remark 5.B.5) | L52: =P21 -> 6.7197094 | M52: 6.7
A53: 36 | B53: =A53*$B$6 -> 9 | C53: =C52+$B$6*$B$4*C52*(1-C52/$B$5) -> 98.604926 | D53: =1+$B$6*$B$4*(1-2*C53/$B$5) -> 0.78127783
A54: 37 | B54: =A54*$B$6 -> 9.25 | C54: =C53+$B$6*$B$4*C53*(1-C53/$B$5) -> 98.914439 | D54: =1+$B$6*$B$4*(1-2*C54/$B$5) -> 0.77988502
A55: 38 | B55: =A55*$B$6 -> 9.5 | C55: =C54+$B$6*$B$4*C54*(1-C54/$B$5) -> 99.156039 | D55: =1+$B$6*$B$4*(1-2*C55/$B$5) -> 0.77879783
A56: 39 | B56: =A56*$B$6 -> 9.75 | C56: =C55+$B$6*$B$4*C55*(1-C55/$B$5) -> 99.344327 | D56: =1+$B$6*$B$4*(1-2*C56/$B$5) -> 0.77795053
A57: 40 | B57: =A57*$B$6 -> 10 | C57: =C56+$B$6*$B$4*C56*(1-C56/$B$5) -> 99.490886 | D57: =1+$B$6*$B$4*(1-2*C57/$B$5) -> 0.77729101
A58: 41 | B58: =A58*$B$6 -> 10.25 | C58: =C57+$B$6*$B$4*C57*(1-C57/$B$5) -> 99.604854 | D58: =1+$B$6*$B$4*(1-2*C58/$B$5) -> 0.77677816
A59: 42 | B59: =A59*$B$6 -> 10.5 | C59: =C58+$B$6*$B$4*C58*(1-C58/$B$5) -> 99.69341 | D59: =1+$B$6*$B$4*(1-2*C59/$B$5) -> 0.77637965
A60: 43 | B60: =A60*$B$6 -> 10.75 | C60: =C59+$B$6*$B$4*C59*(1-C59/$B$5) -> 99.762182 | D60: =1+$B$6*$B$4*(1-2*C60/$B$5) -> 0.77607018
A61: 44 | B61: =A61*$B$6 -> 11 | C61: =C60+$B$6*$B$4*C60*(1-C60/$B$5) -> 99.815563 | D61: =1+$B$6*$B$4*(1-2*C61/$B$5) -> 0.77582996
A62: 45 | B62: =A62*$B$6 -> 11.25 | C62: =C61+$B$6*$B$4*C61*(1-C61/$B$5) -> 99.856985 | D62: =1+$B$6*$B$4*(1-2*C62/$B$5) -> 0.77564357
A63: 46 | B63: =A63*$B$6 -> 11.5 | C63: =C62+$B$6*$B$4*C62*(1-C62/$B$5) -> 99.889117 | D63: =1+$B$6*$B$4*(1-2*C63/$B$5) -> 0.77549897
A64: 47 | B64: =A64*$B$6 -> 11.75 | C64: =C63+$B$6*$B$4*C63*(1-C63/$B$5) -> 99.914038 | D64: =1+$B$6*$B$4*(1-2*C64/$B$5) -> 0.77538683
A65: 48 | B65: =A65*$B$6 -> 12 | C65: =C64+$B$6*$B$4*C64*(1-C64/$B$5) -> 99.933363 | D65: =1+$B$6*$B$4*(1-2*C65/$B$5) -> 0.77529987

Sheet Profiles
A1: Compare profiles: today and the three Year-5 states on Chapter 3's scale, with the distance readout (Figure 5.5; Section 5.8; AXIOM Lab 1.5, step 5)
A3: Reading | B3: Chapter 3 scale | C3: Today | D3: Digital, Year 5 | E3: Restructuring, Year 5 | F3: Turnaround, Year 5 | G3: Scaled: today | H3: Scaled: digital | I3: Scaled: restructuring | J3: Scaled: turnaround
A4: =Declarations!B4 -> liquidity | B4: =Declarations!I4 -> 100 | C4: =Declarations!C4 -> 100 | D4: =Declarations!$C$27+(Declarations!$C$4-Declarations!$C$27)*EXP(-Declarations!$D$27*5)+IF(Declarations!$E$27=0,0,Declarations!$E$27*(5/Declarations!$F$27)*EXP(1-5/Declarations!$F$27))+IF(5>=T_sale,Declarations!$G$27,0) -> 94.295601 | E4: =Declarations!$C$31+(Declarations!$C$4-Declarations!$C$31)*EXP(-Declarations!$D$31*5)+IF(Declarations!$E$31=0,0,Declarations!$E$31*(5/Declarations!$F$31)*EXP(1-5/Declarations!$F$31))+IF(5>=T_sale,Declarations!$G$31,0) -> 121.10748 | F4: =Declarations!$C$35+(Declarations!$C$4-Declarations!$C$35)*EXP(-Declarations!$D$35*5)+IF(Declarations!$E$35=0,0,Declarations!$E$35*(5/Declarations!$F$35)*EXP(1-5/Declarations!$F$35))+IF(5>=T_sale,Declarations!$G$35,0) -> 105.3676 | G4: =C4/$B4 -> 1 | H4: =D4/$B4 -> 0.94295601 | I4: =E4/$B4 -> 1.2110748 | J4: =F4/$B4 -> 1.053676
A5: =Declarations!B5 -> net leverage | B5: =Declarations!I5 -> 3.4 | C5: =Declarations!C5 -> 3.4 | D5: =C5 -> 3.4 | E5: =C5 -> 3.4 | F5: =C5 -> 3.4 | G5: =C5/$B5 -> 1 | H5: =D5/$B5 -> 1 | I5: =E5/$B5 -> 1 | J5: =F5/$B5 -> 1
A6: =Declarations!B6 -> workforce capability | B6: =Declarations!I6 -> 100 | C6: =Declarations!C6 -> 58 | D6: =C6 -> 58 | E6: =C6 -> 58 | F6: =C6 -> 58 | G6: =C6/$B6 -> 0.58 | H6: =D6/$B6 -> 0.58 | I6: =E6/$B6 -> 0.58 | J6: =F6/$B6 -> 0.58
A7: =Declarations!B7 -> technology platform | B7: =Declarations!I7 -> 100 | C7: =Declarations!C7 -> 41 | D7: =Declarations!$C$28+(Declarations!$C$7-Declarations!$C$28)*EXP(-Declarations!$D$28*5)+IF(Declarations!$E$28=0,0,Declarations!$E$28*(5/Declarations!$F$28)*EXP(1-5/Declarations!$F$28))+IF(5>=T_sale,Declarations!$G$28,0) -> 75.634669 | E7: =Declarations!$C$32+(Declarations!$C$7-Declarations!$C$32)*EXP(-Declarations!$D$32*5)+IF(Declarations!$E$32=0,0,Declarations!$E$32*(5/Declarations!$F$32)*EXP(1-5/Declarations!$F$32))+IF(5>=T_sale,Declarations!$G$32,0) -> 38.859514 | F7: =Declarations!$C$36+(Declarations!$C$7-Declarations!$C$36)*EXP(-Declarations!$D$36*5)+IF(Declarations!$E$36=0,0,Declarations!$E$36*(5/Declarations!$F$36)*EXP(1-5/Declarations!$F$36))+IF(5>=T_sale,Declarations!$G$36,0) -> 35.943036 | G7: =C7/$B7 -> 0.41 | H7: =D7/$B7 -> 0.75634669 | I7: =E7/$B7 -> 0.38859514 | J7: =F7/$B7 -> 0.35943036
A8: =Declarations!B8 -> operational efficiency | B8: =Declarations!I8 -> 100 | C8: =Declarations!C8 -> 71 | D8: =Declarations!$C$29+(Declarations!$C$8-Declarations!$C$29)*EXP(-Declarations!$D$29*5)+IF(Declarations!$E$29=0,0,Declarations!$E$29*(5/Declarations!$F$29)*EXP(1-5/Declarations!$F$29))+IF(5>=T_sale,Declarations!$G$29,0) -> 73.598331 | E8: =Declarations!$C$33+(Declarations!$C$8-Declarations!$C$33)*EXP(-Declarations!$D$33*5)+IF(Declarations!$E$33=0,0,Declarations!$E$33*(5/Declarations!$F$33)*EXP(1-5/Declarations!$F$33))+IF(5>=T_sale,Declarations!$G$33,0) -> 73.683802 | F8: =Declarations!$C$37+(Declarations!$C$8-Declarations!$C$37)*EXP(-Declarations!$D$37*5)+IF(Declarations!$E$37=0,0,Declarations!$E$37*(5/Declarations!$F$37)*EXP(1-5/Declarations!$F$37))+IF(5>=T_sale,Declarations!$G$37,0) -> 78.601703 | G8: =C8/$B8 -> 0.71 | H8: =D8/$B8 -> 0.73598331 | I8: =E8/$B8 -> 0.73683802 | J8: =F8/$B8 -> 0.78601703
A9: =Declarations!B9 -> ROIC | B9: =Declarations!I9 -> 0.083 | C9: =Declarations!C9 -> 0.083 | D9: =C9 -> 0.083 | E9: =C9 -> 0.083 | F9: =C9 -> 0.083 | G9: =C9/$B9 -> 1 | H9: =D9/$B9 -> 1 | I9: =E9/$B9 -> 1 | J9: =F9/$B9 -> 1
A10: =Declarations!B10 -> strategic risk (lower is better) | B10: =Declarations!I10 -> 100 | C10: =Declarations!C10 -> 64 | D10: =Declarations!$C$30+(Declarations!$C$10-Declarations!$C$30)*EXP(-Declarations!$D$30*5)+IF(Declarations!$E$30=0,0,Declarations!$E$30*(5/Declarations!$F$30)*EXP(1-5/Declarations!$F$30))+IF(5>=T_sale,Declarations!$G$30,0) -> 55.21775 | E10: =Declarations!$C$34+(Declarations!$C$10-Declarations!$C$34)*EXP(-Declarations!$D$34*5)+IF(Declarations!$E$34=0,0,Declarations!$E$34*(5/Declarations!$F$34)*EXP(1-5/Declarations!$F$34))+IF(5>=T_sale,Declarations!$G$34,0) -> 49.390192 | F10: =Declarations!$C$38+(Declarations!$C$10-Declarations!$C$38)*EXP(-Declarations!$D$38*5)+IF(Declarations!$E$38=0,0,Declarations!$E$38*(5/Declarations!$F$38)*EXP(1-5/Declarations!$F$38))+IF(5>=T_sale,Declarations!$G$38,0) -> 66.33061 | G10: =C10/$B10 -> 0.64 | H10: =D10/$B10 -> 0.5521775 | I10: =E10/$B10 -> 0.49390192 | J10: =F10/$B10 -> 0.6633061
A11: =Declarations!B11 -> market share | B11: =Declarations!I11 -> 0.19 | C11: =Declarations!C11 -> 0.19 | D11: =C11 -> 0.19 | E11: =C11 -> 0.19 | F11: =C11 -> 0.19 | G11: =C11/$B11 -> 1 | H11: =D11/$B11 -> 1 | I11: =E11/$B11 -> 1 | J11: =F11/$B11 -> 1
A13: Distance from today (Chapter 3's scale, Euclidean) | H13: =SQRT(SUMXMY2(H4:H11,$G$4:$G$11)) -> 0.36276435 | I13: =SQRT(SUMXMY2(I4:I11,$G$4:$G$11)) -> 0.2589897 | J13: =SQRT(SUMXMY2(J4:J11,$G$4:$G$11)) -> 0.10844432
A14: Largest single move (bottleneck) | H14: =MAX(ABS(H4-$G4),ABS(H5-$G5),ABS(H6-$G6),ABS(H7-$G7),ABS(H8-$G8),ABS(H9-$G9),ABS(H10-$G10),ABS(H11-$G11)) -> 0.34634669 | I14: =MAX(ABS(I4-$G4),ABS(I5-$G5),ABS(I6-$G6),ABS(I7-$G7),ABS(I8-$G8),ABS(I9-$G9),ABS(I10-$G10),ABS(I11-$G11)) -> 0.21107479 | J14: =MAX(ABS(J4-$G4),ABS(J5-$G5),ABS(J6-$G6),ABS(J7-$G7),ABS(J8-$G8),ABS(J9-$G9),ABS(J10-$G10),ABS(J11-$G11)) -> 0.076017035
A15: Digital over the turnaround | H15: =H13/J13 -> 3.3451669
A16: Digital more than three times as far as the turnaround (1 = yes) | H16: =IF(H13>3*J13,1,0) -> 1
A17: Profile proximity is not state proximity: rankings of similar states are computed with the declared distance, never read off the page (Section 5.8).
A19: Dimension n | B19: Ball / cube | C19: log10 of ball / cube | D19: Share of the ball within 0.1 of its surface
A20: 2 | B20: =EXP((A20/2)*LN(PI())-A20*LN(2)-GAMMALN(A20/2+1)) -> 0.78539816 | C20: =LOG10(B20) -> -0.10491012 | D20: =1-0.9^A20 -> 0.19
A21: 3 | B21: =EXP((A21/2)*LN(PI())-A21*LN(2)-GAMMALN(A21/2+1)) -> 0.52359878 | C21: =LOG10(B21) -> -0.28100138 | D21: =1-0.9^A21 -> 0.271
A22: 8 | B22: =EXP((A22/2)*LN(PI())-A22*LN(2)-GAMMALN(A22/2+1)) -> 0.015854344 | C22: =LOG10(B22) -> -1.7998517 | D22: =1-0.9^A22 -> 0.56953279
A23: 32 | B23: =EXP((A23/2)*LN(PI())-A23*LN(2)-GAMMALN(A23/2+1)) -> 1.0018865e-15 | C23: =LOG10(B23) -> -14.999181 | D23: =1-0.9^A23 -> 0.96566316
A24: Online Appendix 5.B: in eight dimensions, Meridian's, more than half of a ball lies in its outer tenth and almost none of a box lies in its inscribed ball.

Sheet Reference_Values
A1: Checkpoint | B1: Engine value | C1: Meaning (where in the book)
A2: Readings in the declared state | B2: 8 | C2: Table 5.2: eight readings; Section 5.8: Meridian's dimension
A3: Indices among the readings | B3: 4 | C3: Table 5.1: capability, technology, efficiency, strategic risk
A4: Widest scaled error (strategic risk) | B4: 0.06 | C4: Table 5.2: +/-6 on 0-100
A5: Second widest scaled error (workforce capability) | B5: 0.05 | C5: Table 5.2: +/-5 on 0-100
A6: Dimension after promoting the attrition rate | B6: 9 | C6: AXIOM Lab 1.5, step 1 (Table 5.1: a parameter)
A7: Slack above the floor today ($ million) | B7: 270 | C7: Section 5.7: $0.27 billion
A8: Covenant headroom today (turns) | B8: 1.1 | C8: Section 5.7: 1.1 turns
A9: Risk-ceiling slack today (points) | B9: 11 | C9: Table 5.4: 75 against 64
A10: Walls binding today | B10: 0 | C10: Section 5.7: the binding set is empty
A11: Walls binding at the digital low point | B11: 0 | C11: Figure 5.4: no constraint binds
A12: Digital low point, Newton's method ($ million) | B12: 481.91794 | C12: Section 5.7: $0.48 billion
A13: Time of the low point (years) | B13: 1.7145377 | C13: around month 21
... A119: Share within 0.1 of the surface, n = 32 | B119: 0.96566316 | C119: Online Appendix 5.B: 0.97

Sheet Checks
A1: Checkpoint | B1: Workbook formula value | C1: Engine value | D1: |diff| | E1: Tolerance | F1: Status
A2: Readings in the declared state | B2: =State!B13 -> 8 | C2: =Reference_Values!B2 -> 8 | D2: =ABS(B2-C2) -> 0 | E2: 0 | F2: =IF(D2<=E2,"PASS","FAIL") -> PASS
A3: Indices among the readings | B3: =State!B16 -> 4 | C3: =Reference_Values!B3 -> 4 | D3: =ABS(B3-C3) -> 0 | E3: 0 | F3: =IF(D3<=E3,"PASS","FAIL") -> PASS
A4: Widest scaled error (strategic risk) | B4: =State!B20 -> 0.06 | C4: =Reference_Values!B4 -> 0.06 | D4: =ABS(B4-C4) -> 0 | E4: 1e-12 | F4: =IF(D4<=E4,"PASS","FAIL") -> PASS
A5: Second widest scaled error (workforce capability) | B5: =State!B21 -> 0.05 | C5: =Reference_Values!B5 -> 0.05 | D5: =ABS(B5-C5) -> 0 | E5: 1e-12 | F5: =IF(D5<=E5,"PASS","FAIL") -> PASS
A6: Dimension after promoting the attrition rate | B6: =State!B25 -> 9 | C6: =Reference_Values!B6 -> 9 | D6: =ABS(B6-C6) -> 0 | E6: 0 | F6: =IF(D6<=E6,"PASS","FAIL") -> PASS
A7: Slack above the floor today ($ million) | B7: =Walls!D6 -> 270 | C7: =Reference_Values!B7 -> 270 | D7: =ABS(B7-C7) -> 0 | E7: 1e-09 | F7: =IF(D7<=E7,"PASS","FAIL") -> PASS
A8: Covenant headroom today (turns) | B8: =Walls!D7 -> 1.1 | C8: =Reference_Values!B8 -> 1.1 | D8: =ABS(B8-C8) -> 0 | E8: 1e-09 | F8: =IF(D8<=E8,"PASS","FAIL") -> PASS
A9: Risk-ceiling slack today (points) | B9: =Walls!D8 -> 11 | C9: =Reference_Values!B9 -> 11 | D9: =ABS(B9-C9) -> 0 | E9: 1e-09 | F9: =IF(D9<=E9,"PASS","FAIL") -> PASS
A10: Walls binding today | B10: =Walls!D11 -> 0 | C10: =Reference_Values!B10 -> 0 | D10: =ABS(B10-C10) -> 0 | E10: 0 | F10: =IF(D10<=E10,"PASS","FAIL") -> PASS
A11: Walls binding at the digital low point | B11: =Walls!E11 -> 0 | C11: =Reference_Values!B11 -> 0 | D11: =ABS(B11-C11) -> 0 | E11: 0 | F11: =IF(D11<=E11,"PASS","FAIL") -> PASS
A12: Digital low point, Newton's method ($ million) | B12: =Walls!J21 -> 481.91794 | C12: =Reference_Values!B12 -> 481.91794 | D12: =ABS(B12-C12) -> 0 | E12: 1e-06 | F12: =IF(D12<=E12,"PASS","FAIL") -> PASS
A13: Time of the low point (years) | B13: =Walls!J19 -> 1.7145376 | C13: =Reference_Values!B13 -> 1.7145377 | D13: =ABS(B13-C13) -> 5.0850867e-08 | E13: 1e-06 | F13: =IF(D13<=E13,"PASS","FAIL") -> PASS
A14: Lowest monthly reading (index) | B14: =Walls!J25 -> 77.733933 | C14: =Reference_Values!B14 -> 77.733933 | D14: =ABS(B14-C14) -> 0 | E14: 1e-09 | F14: =IF(D14<=E14,"PASS","FAIL") -> PASS
A15: Month of the lowest monthly reading | B15: =Walls!J26 -> 21 | C15: =Reference_Values!B15 -> 21 | D15: =ABS(B15-C15) -> 0 | E15: 0 | F15: =IF(D15<=E15,"PASS","FAIL") -> PASS
A16: Floor slack at the low point ($ million) | B16: =Walls!E6 -> 131.91794 | C16: =Reference_Values!B16 -> 131.91794 | D16: =ABS(B16-C16) -> 0 | E16: 1e-06 | F16: =IF(D16<=E16,"PASS","FAIL") -> PASS
A17: Highest floor the digital program can meet ($ million) | B17: =Walls!J24 -> 481.91794 | C17: =Reference_Values!B17 -> 481.91794 | D17: =ABS(B17-C17) -> 0 | E17: 1e-06 | F17: =IF(D17<=E17,"PASS","FAIL") -> PASS
A18: Risk-ceiling slack at the low point | B18: =Walls!E8 -> 4.4242054 | C18: =Reference_Values!B18 -> 4.4242057 | D18: =ABS(B18-C18) -> 2.9886276e-07 | E18: 1e-06 | F18: =IF(D18<=E18,"PASS","FAIL") -> PASS
A19: Strategic-risk peak on the digital path | B19: =Walls!J35 -> 73.552546 | C19: =Reference_Values!B19 -> 73.552546 | D19: =ABS(B19-C19) -> 0 | E19: 1e-09 | F19: =IF(D19<=E19,"PASS","FAIL") -> PASS
A20: Margin under the risk ceiling at the peak | B20: =Walls!J37 -> 1.4474538 | C20: =Reference_Values!B20 -> 1.4474538 | D20: =ABS(B20-C20) -> 0 | E20: 1e-09 | F20: =IF(D20<=E20,"PASS","FAIL") -> PASS
A21: Month of the strategic-risk peak | B21: =Walls!J39 -> 11 | C21: =Reference_Values!B21 -> 11 | D21: =ABS(B21-C21) -> 0 | E21: 0 | F21: =IF(D21<=E21,"PASS","FAIL") -> PASS
A22: Turnaround: tightest risk-ceiling slack (Year 5) | B22: =Walls!J8 -> 8.6693905 | C22: =Reference_Values!B22 -> 8.6693905 | D22: =ABS(B22-C22) -> 0 | E22: 1e-09 | F22: =IF(D22<=E22,"PASS","FAIL") -> PASS
A23: Digital: tightest index slack (technology, Year 5) | B23: =Walls!F9 -> 24.365331 | C23: =Reference_Values!B23 -> 24.365331 | D23: =ABS(B23-C23) -> 0 | E23: 1e-09 | F23: =IF(D23<=E23,"PASS","FAIL") -> PASS
A24: Blends feasible under the budget alone (of 21) | B24: =Blend!B32 -> 21 | C24: =Reference_Values!B24 -> 21 | D24: =ABS(B24-C24) -> 0 | E24: 0 | F24: =IF(D24<=E24,"PASS","FAIL") -> PASS
A25: Blends feasible with the minimum scale (of 21) | B25: =Blend!B33 -> 7 | C25: =Reference_Values!B25 -> 7 | D25: =ABS(B25-C25) -> 0 | E25: 0 | F25: =IF(D25<=E25,"PASS","FAIL") -> PASS
A26: Minimum-scale g at the 50/50 blend | B26: =Blend!B34 -> 20 | C26: =Reference_Values!B26 -> 20 | D26: =ABS(B26-C26) -> 0 | E26: 0 | F26: =IF(D26<=E26,"PASS","FAIL") -> PASS
A27: Phases join at year 2 (liquidity index) | B27: =PathSampling!J5 -> 78.040976 | C27: =Reference_Values!B27 -> 78.040976 | D27: =ABS(B27-C27) -> 0 | E27: 1e-09 | F27: =IF(D27<=E27,"PASS","FAIL") -> PASS
A28: Largest |quarterly steps - closed form| | B28: =PathSampling!J6 -> 0 | C28: =Reference_Values!B28 -> 0 | D28: =ABS(B28-C28) -> 0 | E28: 1e-09 | F28: =IF(D28<=E28,"PASS","FAIL") -> PASS
A29: Largest |half-yearly - two quarterly steps| | B29: =PathSampling!J7 -> 0 | C29: =Reference_Values!B29 -> 2.1316282e-14 | D29: =ABS(B29-C29) -> 2.1316282e-14 | E29: 1e-09 | F29: =IF(D29<=E29,"PASS","FAIL") -> PASS
A30: Largest |build + scale-up - whole path| | B30: =PathSampling!J8 -> 0 | C30: =Reference_Values!B30 -> 0 | D30: =ABS(B30-C30) -> 0 | E30: 1e-09 | F30: =IF(D30<=E30,"PASS","FAIL") -> PASS
A31: Twenty quarters back: today's liquidity | B31: =PathSampling!J9 -> 100 | C31: =Reference_Values!B31 -> 100 | D31: =ABS(B31-C31) -> 3.5527137e-13 | E31: 1e-09 | F31: =IF(D31<=E31,"PASS","FAIL") -> PASS
A32: Factor a year: liquidity | B32: =Turnaround!B6 -> 0.63762815 | C32: =Reference_Values!B32 -> 0.63762815 | D32: =ABS(B32-C32) -> 0 | E32: 1e-12 | F32: =IF(D32<=E32,"PASS","FAIL") -> PASS
A33: Factor a year: technology | B33: =Turnaround!C6 -> 0.81873075 | C33: =Reference_Values!B33 -> 0.81873075 | D33: =ABS(B33-C33) -> 0 | E33: 1e-12 | F33: =IF(D33<=E33,"PASS","FAIL") -> PASS
A34: Factor a year: efficiency | B34: =Turnaround!D6 -> 0.54881164 | C34: =Reference_Values!B34 -> 0.54881164 | D34: =ABS(B34-C34) -> 0 | E34: 1e-12 | F34: =IF(D34<=E34,"PASS","FAIL") -> PASS
A35: Factor a year: strategic risk | B35: =Turnaround!E6 -> 0.74081822 | C35: =Reference_Values!B35 -> 0.74081822 | D35: =ABS(B35-C35) -> 0 | E35: 1e-12 | F35: =IF(D35<=E35,"PASS","FAIL") -> PASS
A36: Gap closed a year: liquidity (%) | B36: =100*Turnaround!B7 -> 36.237185 | C36: =Reference_Values!B36 -> 36.237185 | D36: =ABS(B36-C36) -> 0 | E36: 1e-09 | F36: =IF(D36<=E36,"PASS","FAIL") -> PASS
A37: Gap closed a year: technology (%) | B37: =100*Turnaround!C7 -> 18.126925 | C37: =Reference_Values!B37 -> 18.126925 | D37: =ABS(B37-C37) -> 0 | E37: 1e-09 | F37: =IF(D37<=E37,"PASS","FAIL") -> PASS
A38: Gap closed a year: efficiency (%) | B38: =100*Turnaround!D7 -> 45.118836 | C38: =Reference_Values!B38 -> 45.118836 | D38: =ABS(B38-C38) -> 0 | E38: 1e-09 | F38: =IF(D38<=E38,"PASS","FAIL") -> PASS
A39: Gap closed a year: strategic risk (%) | B39: =100*Turnaround!E7 -> 25.918178 | C39: =Reference_Values!B39 -> 25.918178 | D39: =ABS(B39-C39) -> 0 | E39: 1e-09 | F39: =IF(D39<=E39,"PASS","FAIL") -> PASS
A40: Year 1: liquidity | B40: =Turnaround!B17 -> 102.17423 | C40: =Reference_Values!B40 -> 102.17423 | D40: =ABS(B40-C40) -> 0 | E40: 1e-09 | F40: =IF(D40<=E40,"PASS","FAIL") -> PASS
A41: Year 1: technology | B41: =Turnaround!C17 -> 39.549846 | C41: =Reference_Values!B41 -> 39.549846 | D41: =ABS(B41-C41) -> 0 | E41: 1e-09 | F41: =IF(D41<=E41,"PASS","FAIL") -> PASS
A42: Year 1: efficiency | B42: =Turnaround!D17 -> 74.609507 | C42: =Reference_Values!B42 -> 74.609507 | D42: =ABS(B42-C42) -> 0 | E42: 1e-09 | F42: =IF(D42<=E42,"PASS","FAIL") -> PASS
A43: Year 1: strategic risk | B43: =Turnaround!E17 -> 64.777545 | C43: =Reference_Values!B43 -> 64.777545 | D43: =ABS(B43-C43) -> 0 | E43: 1e-09 | F43: =IF(D43<=E43,"PASS","FAIL") -> PASS
A44: Contraction constant L | B44: =Turnaround!B10 -> 0.81873075 | C44: =Reference_Values!B44 -> 0.81873075 | D44: =ABS(B44-C44) -> 0 | E44: 1e-12 | F44: =IF(D44<=E44,"PASS","FAIL") -> PASS
A45: Largest first-year move | B45: =Turnaround!B12 -> 3.6095069 | C45: =Reference_Values!B45 -> 3.6095069 | D45: =ABS(B45-C45) -> 0 | E45: 1e-09 | F45: =IF(D45<=E45,"PASS","FAIL") -> PASS
A46: Day-one bound coefficient | B46: =Turnaround!B13 -> 19.912406 | C46: =Reference_Values!B46 -> 19.912406 | D46: =ABS(B46-C46) -> 0 | E46: 1e-09 | F46: =IF(D46<=E46,"PASS","FAIL") -> PASS
A47: First year the bound is below one point | B47: =Turnaround!K4 -> 15 | C47: =Reference_Values!B47 -> 15 | D47: =ABS(B47-C47) -> 0 | E47: 0 | F47: =IF(D47<=E47,"PASS","FAIL") -> PASS
A48: First year the gap is below one point | B48: =Turnaround!K5 -> 11 | C48: =Reference_Values!B48 -> 11 | D48: =ABS(B48-C48) -> 0 | E48: 0 | F48: =IF(D48<=E48,"PASS","FAIL") -> PASS
A49: Table 5.5, year 0: largest gap | B49: =Turnaround!K16 -> 8 | C49: =Reference_Values!B49 -> 8 | D49: =ABS(B49-C49) -> 0 | E49: 1e-09 | F49: =IF(D49<=E49,"PASS","FAIL") -> PASS
A50: Table 5.5, year 0: day-one bound | B50: =Turnaround!K17 -> 19.912406 | C50: =Reference_Values!B50 -> 19.912406 | D50: =ABS(B50-C50) -> 0 | E50: 1e-09 | F50: =IF(D50<=E50,"PASS","FAIL") -> PASS
A51: Table 5.5, year 0: scorecard | B51: =Turnaround!K18 -> 37 | C51: =Reference_Values!B51 -> 37 | D51: =ABS(B51-C51) -> 0 | E51: 1e-09 | F51: =IF(D51<=E51,"PASS","FAIL") -> PASS
A52: Table 5.5, year 1: largest gap | B52: =Turnaround!L16 -> 6.549846 | C52: =Reference_Values!B52 -> 6.549846 | D52: =ABS(B52-C52) -> 0 | E52: 1e-09 | F52: =IF(D52<=E52,"PASS","FAIL") -> PASS
A53: Table 5.5, year 1: day-one bound | B53: =Turnaround!L17 -> 16.302899 | C53: =Reference_Values!B53 -> 16.302899 | D53: =ABS(B53-C53) -> 0 | E53: 1e-09 | F53: =IF(D53<=E53,"PASS","FAIL") -> PASS
A54: Table 5.5, year 1: scorecard | B54: =Turnaround!L18 -> 37.88901 | C54: =Reference_Values!B54 -> 37.88901 | D54: =ABS(B54-C54) -> 0 | E54: 1e-09 | F54: =IF(D54<=E54,"PASS","FAIL") -> PASS
A55: Table 5.5, year 3: largest gap | B55: =Turnaround!M16 -> 4.3904931 | C55: =Reference_Values!B55 -> 4.3904931 | D55: =ABS(B55-C55) -> 0 | E55: 1e-09 | F55: =IF(D55<=E55,"PASS","FAIL") -> PASS
A56: Table 5.5, year 3: day-one bound | B56: =Turnaround!M17 -> 10.92816 | C56: =Reference_Values!B56 -> 10.92816 | D56: =ABS(B56-C56) -> 0 | E56: 1e-09 | F56: =IF(D56<=E56,"PASS","FAIL") -> PASS
A57: Table 5.5, year 3: scorecard | B57: =Turnaround!M18 -> 38.433092 | C57: =Reference_Values!B57 -> 38.433092 | D57: =ABS(B57-C57) -> 0 | E57: 1e-09 | F57: =IF(D57<=E57,"PASS","FAIL") -> PASS
A58: Table 5.5, year 5: largest gap | B58: =Turnaround!N16 -> 2.9430355 | C58: =Reference_Values!B58 -> 2.9430355 | D58: =ABS(B58-C58) -> 0 | E58: 1e-09 | F58: =IF(D58<=E58,"PASS","FAIL") -> PASS
A59: Table 5.5, year 5: day-one bound | B59: =Turnaround!N17 -> 7.3253649 | C59: =Reference_Values!B59 -> 7.3253649 | D59: =ABS(B59-C59) -> 0 | E59: 1e-09 | F59: =IF(D59<=E59,"PASS","FAIL") -> PASS
A60: Table 5.5, year 5: scorecard | B60: =Turnaround!N18 -> 38.395434 | C60: =Reference_Values!B60 -> 38.395434 | D60: =ABS(B60-C60) -> 0 | E60: 1e-09 | F60: =IF(D60<=E60,"PASS","FAIL") -> PASS
A61: Table 5.5, year 11: largest gap | B61: =Turnaround!O16 -> 0.88642527 | C61: =Reference_Values!B61 -> 0.88642527 | D61: =ABS(B61-C61) -> 7.1054274e-15 | E61: 1e-09 | F61: =IF(D61<=E61,"PASS","FAIL") -> PASS
A62: Table 5.5, year 11: day-one bound | B62: =Turnaround!O17 -> 2.2063575 | C62: =Reference_Values!B62 -> 2.2063575 | D62: =ABS(B62-C62) -> 0 | E62: 1e-09 | F62: =IF(D62<=E62,"PASS","FAIL") -> PASS
A63: Table 5.5, year 11: scorecard | B63: =Turnaround!O18 -> 37.985923 | C63: =Reference_Values!B63 -> 37.985923 | D63: =ABS(B63-C63) -> 0 | E63: 1e-09 | F63: =IF(D63<=E63,"PASS","FAIL") -> PASS
A64: Table 5.5, year 3: liquidity | B64: =Turnaround!M12 -> 104.44456 | C64: =Reference_Values!B64 -> 104.44456 | D64: =ABS(B64-C64) -> 0 | E64: 1e-09 | F64: =IF(D64<=E64,"PASS","FAIL") -> PASS
A65: Table 5.5, year 3: technology | B65: =Turnaround!M13 -> 37.390493 | C65: =Reference_Values!B65 -> 37.390493 | D65: =ABS(B65-C65) -> 0 | E65: 1e-09 | F65: =IF(D65<=E65,"PASS","FAIL") -> PASS
A66: Table 5.5, year 3: efficiency | B66: =Turnaround!M14 -> 77.677609 | C66: =Reference_Values!B66 -> 77.677609 | D66: =ABS(B66-C66) -> 0 | E66: 1e-09 | F66: =IF(D66<=E66,"PASS","FAIL") -> PASS
A67: Table 5.5, year 3: strategic risk | B67: =Turnaround!M15 -> 65.780291 | C67: =Reference_Values!B67 -> 65.780291 | D67: =ABS(B67-C67) -> 0 | E67: 1e-09 | F67: =IF(D67<=E67,"PASS","FAIL") -> PASS
A68: Table 5.5, year 5: liquidity | B68: =Turnaround!N12 -> 105.3676 | C68: =Reference_Values!B68 -> 105.3676 | D68: =ABS(B68-C68) -> 0 | E68: 1e-09 | F68: =IF(D68<=E68,"PASS","FAIL") -> PASS
A69: Table 5.5, year 5: technology | B69: =Turnaround!N13 -> 35.943036 | C69: =Reference_Values!B69 -> 35.943036 | D69: =ABS(B69-C69) -> 0 | E69: 1e-09 | F69: =IF(D69<=E69,"PASS","FAIL") -> PASS
A70: Table 5.5, year 5: efficiency | B70: =Turnaround!N14 -> 78.601703 | C70: =Reference_Values!B70 -> 78.601703 | D70: =ABS(B70-C70) -> 0 | E70: 1e-09 | F70: =IF(D70<=E70,"PASS","FAIL") -> PASS
A71: Table 5.5, year 5: strategic risk | B71: =Turnaround!N15 -> 66.33061 | C71: =Reference_Values!B71 -> 66.33061 | D71: =ABS(B71-C71) -> 0 | E71: 1e-09 | F71: =IF(D71<=E71,"PASS","FAIL") -> PASS
A72: Table 5.5, year 11: liquidity | B72: =Turnaround!O12 -> 105.9575 | C72: =Reference_Values!B72 -> 105.9575 | D72: =ABS(B72-C72) -> 0 | E72: 1e-09 | F72: =IF(D72<=E72,"PASS","FAIL") -> PASS
A73: Table 5.5, year 11: technology | B73: =Turnaround!O13 -> 33.886425 | C73: =Reference_Values!B73 -> 33.886425 | D73: =ABS(B73-C73) -> 0 | E73: 1e-09 | F73: =IF(D73<=E73,"PASS","FAIL") -> PASS
A74: Table 5.5, year 11: efficiency | B74: =Turnaround!O14 -> 78.989117 | C74: =Reference_Values!B74 -> 78.989117 | D74: =ABS(B74-C74) -> 0 | E74: 1e-09 | F74: =IF(D74<=E74,"PASS","FAIL") -> PASS
A75: Table 5.5, year 11: strategic risk | B75: =Turnaround!O15 -> 66.88935 | C75: =Reference_Values!B75 -> 66.88935 | D75: =ABS(B75-C75) -> 0 | E75: 1e-09 | F75: =IF(D75<=E75,"PASS","FAIL") -> PASS
A76: Table 5.5: scorecard at the steady state | B76: =Turnaround!K6 -> 37.75 | C76: =Reference_Values!B76 -> 37.75 | D76: =ABS(B76-C76) -> 0 | E76: 1e-09 | F76: =IF(D76<=E76,"PASS","FAIL") -> PASS
A77: Scorecard's peak (years 0-15) | B77: =Turnaround!K7 -> 38.445169 | C77: =Reference_Values!B77 -> 38.445169 | D77: =ABS(B77-C77) -> 0 | E77: 1e-09 | F77: =IF(D77<=E77,"PASS","FAIL") -> PASS
A78: Year of the scorecard's peak | B78: =Turnaround!K8 -> 4 | C78: =Reference_Values!B78 -> 4 | D78: =ABS(B78-C78) -> 0 | E78: 0 | F78: =IF(D78<=E78,"PASS","FAIL") -> PASS
A79: From the digital Year-5 state: bound coefficient | B79: =Turnaround!H62 -> 42.634669 | C79: =Reference_Values!B79 -> 42.634669 | D79: =ABS(B79-C79) -> 0 | E79: 1e-09 | F79: =IF(D79<=E79,"PASS","FAIL") -> PASS
A80: From the digital Year-5 state: bound below one by year | B80: =Turnaround!F104 -> 19 | C80: =Reference_Values!B80 -> 19 | D80: =ABS(B80-C80) -> 0 | E80: 0 | F80: =IF(D80<=E80,"PASS","FAIL") -> PASS
A81: From the digital Year-5 state: gap below one by year | B81: =Turnaround!G104 -> 19 | C81: =Reference_Values!B81 -> 19 | D81: =ABS(B81-C81) -> 0 | E81: 0 | F81: =IF(D81<=E81,"PASS","FAIL") -> PASS
A82: From the digital Year-5 state: years above the bound | B82: =Turnaround!F105 -> 0 | C82: =Reference_Values!B82 -> 0 | D82: =ABS(B82-C82) -> 0 | E82: 0 | F82: =IF(D82<=E82,"PASS","FAIL") -> PASS
A83: From the restructuring Year-5 state: bound coefficient | B83: =Turnaround!Q62 -> 30.20107 | C83: =Reference_Values!B83 -> 30.20107 | D83: =ABS(B83-C83) -> 0 | E83: 1e-09 | F83: =IF(D83<=E83,"PASS","FAIL") -> PASS
A84: From the restructuring Year-5 state: bound below one by year | B84: =Turnaround!O104 -> 18 | C84: =Reference_Values!B84 -> 18 | D84: =ABS(B84-C84) -> 0 | E84: 0 | F84: =IF(D84<=E84,"PASS","FAIL") -> PASS
A85: From the restructuring Year-5 state: gap below one by year | B85: =Turnaround!P104 -> 10 | C85: =Reference_Values!B85 -> 10 | D85: =ABS(B85-C85) -> 0 | E85: 0 | F85: =IF(D85<=E85,"PASS","FAIL") -> PASS
A86: From the restructuring Year-5 state: years above the bound | B86: =Turnaround!O105 -> 0 | C86: =Reference_Values!B86 -> 0 | D86: =ABS(B86-C86) -> 0 | E86: 0 | F86: =IF(D86<=E86,"PASS","FAIL") -> PASS
A87: Digital technology in Year 5 | B87: =Profiles!D7 -> 75.634669 | C87: =Reference_Values!B87 -> 75.634669 | D87: =ABS(B87-C87) -> 0 | E87: 1e-09 | F87: =IF(D87<=E87,"PASS","FAIL") -> PASS
A88: Start-up slope near zero | B88: =Equilibria!B8 -> 1.225 | C88: =Reference_Values!B88 -> 1.225 | D88: =ABS(B88-C88) -> 0 | E88: 1e-12 | F88: =IF(D88<=E88,"PASS","FAIL") -> PASS
A89: Start-up slope at the market wall | B89: =Equilibria!B9 -> 0.775 | C89: =Reference_Values!B89 -> 0.775 | D89: =ABS(B89-C89) -> 0 | E89: 1e-12 | F89: =IF(D89<=E89,"PASS","FAIL") -> PASS
A90: Start-up f(60) | B90: =Equilibria!B10 -> 65.4 | C90: =Reference_Values!B90 -> 65.4 | D90: =ABS(B90-C90) -> 0 | E90: 1e-09 | F90: =IF(D90<=E90,"PASS","FAIL") -> PASS
A91: Start-up slope at 60 | B91: =Equilibria!B11 -> 0.955 | C91: =Reference_Values!B91 -> 0.955 | D91: =ABS(B91-C91) -> 0 | E91: 1e-12 | F91: =IF(D91<=E91,"PASS","FAIL") -> PASS
A92: Start-up user base, year 5 | B92: =Equilibria!B12 -> 58.128602 | C92: =Reference_Values!B92 -> 58.128602 | D92: =ABS(B92-C92) -> 0 | E92: 1e-09 | F92: =IF(D92<=E92,"PASS","FAIL") -> PASS
A93: Start-up user base, year 10 | B93: =Equilibria!B13 -> 99.490886 | C93: =Reference_Values!B93 -> 99.490886 | D93: =ABS(B93-C93) -> 0 | E93: 1e-09 | F93: =IF(D93<=E93,"PASS","FAIL") -> PASS
A94: Start-up first passes 60 (year) | B94: =Equilibria!B14 -> 5.25 | C94: =Reference_Values!B94 -> 5.25 | D94: =ABS(B94-C94) -> 0 | E94: 0 | F94: =IF(D94<=E94,"PASS","FAIL") -> PASS
A95: Stuck in the middle: equilibria | B95: =Equilibria!G7 -> 3 | C95: =Reference_Values!B95 -> 3 | D95: =ABS(B95-C95) -> 0 | E95: 0 | F95: =IF(D95<=E95,"PASS","FAIL") -> PASS
A96: Stuck in the middle: slope at 1/2 | B96: =Equilibria!I5 -> 1.5 | C96: =Reference_Values!B96 -> 1.5 | D96: =ABS(B96-C96) -> 0 | E96: 1e-12 | F96: =IF(D96<=E96,"PASS","FAIL") -> PASS
A97: Service: L by the row-sum rule | B97: =Equilibria!L9 -> 0.75 | C97: =Reference_Values!B97 -> 0.75 | D97: =ABS(B97-C97) -> 0 | E97: 1e-12 | F97: =IF(D97<=E97,"PASS","FAIL") -> PASS
A98: Service: steady occupancy | B98: =Equilibria!L11 -> 100 | C98: =Reference_Values!B98 -> 100 | D98: =ABS(B98-C98) -> 0 | E98: 1e-09 | F98: =IF(D98<=E98,"PASS","FAIL") -> PASS
A99: Service: steady staffing | B99: =Equilibria!M11 -> 85 | C99: =Reference_Values!B99 -> 85 | D99: =ABS(B99-C99) -> 0 | E99: 1e-09 | F99: =IF(D99<=E99,"PASS","FAIL") -> PASS
A100: Service: first step | B100: =Equilibria!L12 -> 8.5 | C100: =Reference_Values!B100 -> 8.5 | D100: =ABS(B100-C100) -> 0 | E100: 1e-09 | F100: =IF(D100<=E100,"PASS","FAIL") -> PASS
...
