Workbook

Sheet README
B1: DCT Laboratory — Vol II, Ch 4: Nonlinear and Mixed-Integer Enterprise Optimization
B2: Seed 26204 · Companion to DCT_V2_Ch04_Lab.ipynb and AXIOM Lab 2.4 (module AXIOM-04). Money in $ million, undiscounted.
B4: Worked Example 4.1, Can Meridian Automate Part of a Line?, with the book's declarations: partial rounds, twenty years' credit for the year-6 savings.
B5: Declarations: the inputs of Step 1. Plans: the partial-round model for any plan (yours included), with its liquidity, its floors and its value in Chapter 3's relaxation.
B6: Schedules: the 64 plans of whole rounds, their marginal values and the corner test: three strict local maxima.
B7: Face: years 4 and 5 vary (AXIOM Lab 2.4, step 1): two peaks, the saddle at (0.75, 0.84) and its curvature.
B8: Multistart: the inventory of 100 local searches (step 2), from the notebook's engine.
B9: Audit: multipliers, residuals, LICQ and the reduced Hessian (step 3). Prices: the local prices of Step 3.
B10: Relaxation: Chapter 3's ceiling in closed form and each answer's distance from it (step 4).
B11: BranchAndBound: every node of the twenty-year and ten-year trees solved exactly by formulas (step 5).
B12: Credit: Step 6, the credit at which the best number of rounds changes. Cap: the $60m cap and its price list.
B13: Package: Worked Example 1.1's package by branch-and-bound (Section 4.5), breach odds from the engine.
... B20: Cross-sheet link: green.

Sheet Declarations
A1: Declarations (Worked Example 4.1, Step 1). Money in $ million, undiscounted; rounds as fractions of a round.
A3: Quantity | B3: Value | C3: Source
A4: Cost of a whole round | B4: 120 | C4: Volume I, Worked Example 6.1
A5: Operational efficiency today | B5: 71
A6: Efficiency ceiling | B6: 85
A7: Efficiency gap today (points) | B7: =B6-B5 -> 14 | C7: 14 points
A8: Savings a year per point of efficiency gained | B8: 10 | C8: From the year of the round on
A9: Share of the remaining gap a whole round closes | B9: 0.5 | C9: A fraction z of a round closes the fraction z/2 (the chief operating officer)
A10: Liquidity today | B10: 620
A11: Floor, after paying for a round and at each year end | B11: 350 | C11: The board
A12: End condition: liquidity at the end of year 6 | B12: 470 | C12: Cash for another round
A13: Credit for the year-6 savings (years) | B13: 20 | C13: The expected life of the automated lines
A14: Ten years' credit (Chapters 2 and 3) | B14: 10 | C14: For the comparisons at ten years
A15: Savings a year with the gap closed | B15: =B8*B7 -> 140 | C15: 140
A16: Cash above the end condition today | B16: =B10-B12 -> 150 | C16: 150: paid out if no round runs
A17: Chapter 3's relaxation: gap kept per round, 1 - share | B17: =1-B9 -> 0.5 | C17: Gap after Z rounds: 14 x 0.5^Z (agrees at whole rounds)
A18: Chapter 3's relaxation: slope of its savings at Z = 0 | B18: =-B15*LN(B17) -> 97.040605 | C18: 140 ln 2 = 97.04; the slope at Z is this times 0.5^Z
A20: Payouts are free and can wait, so the floors never bind: a plan z of rounds is worth V(z) = 150 + sum of S_k - 120 sum of z_k + credit x S_6, with S_k = 140 - 10 x gap_k.
A21: The gap after year k is 14 x the product of (1 - z_j/2) over j <= k: Volume I's recursion read for fractions, identical at whole rounds.

Sheet Plans
A1: The partial-round model: any plan of rounds (Worked Example 4.1, Step 1; Proposition 4.2(i))
A2: Each row is a plan z of rounds by year. Payouts deferred to year 6: liquidity and the smallest slack in the floors and the end condition. Columns AD-AK value the same plan in Chapter 3's relaxation (a ceiling).
A4: Plan | B4: z1 | C4: z2 | D4: z3 | E4: z4 | F4: z5 | G4: z6 | H4: gap 1 | I4: gap 2 | J4: gap 3 | K4: gap 4 | L4: gap 5 | M4: gap 6 | N4: S 1 | O4: S 2 | P4: S 3 | Q4: S 4 | R4: S 5 | S4: S 6 | T4: Rounds | U4: V, credit M | V4: V, ten years | W4: q 1 | X4: q 2 | Y4: q 3 | Z4: q 4 | AA4: q 5 | AB4: q 6 | AC4: Smallest slack | AD4: relaxed S 1 | AE4: relaxed S 2 | AF4: relaxed S 3 | AG4: relaxed S 4 | AH4: relaxed S 5 | AI4: relaxed S 6 | AJ4: Relaxation, credit M | AK4: Relaxation, ten years
A5: years 1–4 | B5: 1 | C5: 1 | D5: 1 | E5: 1 | F5: 0 | G5: 0 | H5: =Gap0*(1-Share*B5) -> 7 | I5: =H5*(1-Share*C5) -> 3.5 | J5: =I5*(1-Share*D5) -> 1.75 | K5: =J5*(1-Share*E5) -> 0.875 | L5: =K5*(1-Share*F5) -> 0.875 | M5: =L5*(1-Share*G5) -> 0.875 | N5: =Smax-Val_pt*H5 -> 70 | O5: =Smax-Val_pt*I5 -> 105 | P5: =Smax-Val_pt*J5 -> 122.5 | Q5: =Smax-Val_pt*K5 -> 131.25 | R5: =Smax-Val_pt*L5 -> 131.25 | S5: =Smax-Val_pt*M5 -> 131.25 | T5: =SUM(B5:G5) -> 4 | U5: =Cash0+SUM(N5:S5)-Cost_r*T5+Credit_M*S5 -> 2986.25 | V5: =Cash0+SUM(N5:S5)-Cost_r*T5+Credit_10*S5 -> 1673.75 | W5: =Liq0+N5-Cost_r*B5 -> 570 | X5: =W5+O5-Cost_r*C5 -> 555 | Y5: =X5+P5-Cost_r*D5 -> 557.5 | Z5: =Y5+Q5-Cost_r*E5 -> 568.75 | AA5: =Z5+R5-Cost_r*F5 -> 700 | AB5: =AA5+S5-Cost_r*G5 -> 831.25 | AC5: =MIN(MIN(Liq0-Cost_r*B5,W5-Cost_r*C5,X5-Cost_r*D5,Y5-Cost_r*E5,Z5-Cost_r*F5,AA5-Cost_r*G5,MIN(W5:AB5))-Floor_q,AB5-End_q) -> 85 | AD5: =Smax*(1-POWER(Keep,SUM($B5:B5))) -> 70 | AE5: =Smax*(1-POWER(Keep,SUM($B5:C5))) -> 105 | AF5: =Smax*(1-POWER(Keep,SUM($B5:D5))) -> 122.5 | AG5: =Smax*(1-POWER(Keep,SUM($B5:E5))) -> 131.25 | AH5: =Smax*(1-POWER(Keep,SUM($B5:F5))) -> 131.25 | AI5: =Smax*(1-POWER(Keep,SUM($B5:G5))) -> 131.25 | AJ5: =Cash0+SUM(AD5:AI5)-Cost_r*T5+Credit_M*AI5 -> 2986.25 | AK5: =Cash0+SUM(AD5:AI5)-Cost_r*T5+Credit_10*AI5 -> 1673.75
A6: years 1–3 and 5 | B6: 1 | C6: 1 | D6: 1 | E6: 0 | F6: 1 | G6: 0 | H6: =Gap0*(1-Share*B6) -> 7 | I6: =H6*(1-Share*C6) -> 3.5 | J6: =I6*(1-Share*D6) -> 1.75 | K6: =J6*(1-Share*E6) -> 1.75 | L6: =K6*(1-Share*F6) -> 0.875 | M6: =L6*(1-Share*G6) -> 0.875 | N6: =Smax-Val_pt*H6 -> 70 | O6: =Smax-Val_pt*I6 -> 105 | P6: =Smax-Val_pt*J6 -> 122.5 | Q6: =Smax-Val_pt*K6 -> 122.5 | R6: =Smax-Val_pt*L6 -> 131.25 | S6: =Smax-Val_pt*M6 -> 131.25 | T6: =SUM(B6:G6) -> 4 | U6: =Cash0+SUM(N6:S6)-Cost_r*T6+Credit_M*S6 -> 2977.5 | V6: =Cash0+SUM(N6:S6)-Cost_r*T6+Credit_10*S6 -> 1665 | W6: =Liq0+N6-Cost_r*B6 -> 570 | X6: =W6+O6-Cost_r*C6 -> 555 | Y6: =X6+P6-Cost_r*D6 -> 557.5 | Z6: =Y6+Q6-Cost_r*E6 -> 680 | AA6: =Z6+R6-Cost_r*F6 -> 691.25 | AB6: =AA6+S6-Cost_r*G6 -> 822.5 | AC6: =MIN(MIN(Liq0-Cost_r*B6,W6-Cost_r*C6,X6-Cost_r*D6,Y6-Cost_r*E6,Z6-Cost_r*F6,AA6-Cost_r*G6,MIN(W6:AB6))-Floor_q,AB6-End_q) -> 85 | AD6: =Smax*(1-POWER(Keep,SUM($B6:B6))) -> 70 | AE6: =Smax*(1-POWER(Keep,SUM($B6:C6))) -> 105 | AF6: =Smax*(1-POWER(Keep,SUM($B6:D6))) -> 122.5 | AG6: =Smax*(1-POWER(Keep,SUM($B6:E6))) -> 122.5 | AH6: =Smax*(1-POWER(Keep,SUM($B6:F6))) -> 131.25 | AI6: =Smax*(1-POWER(Keep,SUM($B6:G6))) -> 131.25 | AJ6: =Cash0+SUM(AD6:AI6)-Cost_r*T6+Credit_M*AI6 -> 2977.5 | AK6: =Cash0+SUM(AD6:AI6)-Cost_r*T6+Credit_10*AI6 -> 1665
A7: years 1–3 and 6 | B7: 1 | C7: 1 | D7: 1 | E7: 0 | F7: 0 | G7: 1 | H7: =Gap0*(1-Share*B7) -> 7 | I7: =H7*(1-Share*C7) -> 3.5 | J7: =I7*(1-Share*D7) -> 1.75 | K7: =J7*(1-Share*E7) -> 1.75 | L7: =K7*(1-Share*F7) -> 1.75 | M7: =L7*(1-Share*G7) -> 0.875 | N7: =Smax-Val_pt*H7 -> 70 | O7: =Smax-Val_pt*I7 -> 105 | P7: =Smax-Val_pt*J7 -> 122.5 | Q7: =Smax-Val_pt*K7 -> 122.5 | R7: =Smax-Val_pt*L7 -> 122.5 | S7: =Smax-Val_pt*M7 -> 131.25 | T7: =SUM(B7:G7) -> 4 | U7: =Cash0+SUM(N7:S7)-Cost_r*T7+Credit_M*S7 -> 2968.75 | V7: =Cash0+SUM(N7:S7)-Cost_r*T7+Credit_10*S7 -> 1656.25 | W7: =Liq0+N7-Cost_r*B7 -> 570 | X7: =W7+O7-Cost_r*C7 -> 555 | Y7: =X7+P7-Cost_r*D7 -> 557.5 | Z7: =Y7+Q7-Cost_r*E7 -> 680 | AA7: =Z7+R7-Cost_r*F7 -> 802.5 | AB7: =AA7+S7-Cost_r*G7 -> 813.75 | AC7: =MIN(MIN(Liq0-Cost_r*B7,W7-Cost_r*C7,X7-Cost_r*D7,Y7-Cost_r*E7,Z7-Cost_r*F7,AA7-Cost_r*G7,MIN(W7:AB7))-Floor_q,AB7-End_q) -> 85 | AD7: =Smax*(1-POWER(Keep,SUM($B7:B7))) -> 70 | AE7: =Smax*(1-POWER(Keep,SUM($B7:C7))) -> 105 | AF7: =Smax*(1-POWER(Keep,SUM($B7:D7))) -> 122.5 | AG7: =Smax*(1-POWER(Keep,SUM($B7:E7))) -> 122.5 | AH7: =Smax*(1-POWER(Keep,SUM($B7:F7))) -> 122.5 | AI7: =Smax*(1-POWER(Keep,SUM($B7:G7))) -> 131.25 | AJ7: =Cash0+SUM(AD7:AI7)-Cost_r*T7+Credit_M*AI7 -> 2968.75 | AK7: =Cash0+SUM(AD7:AI7)-Cost_r*T7+Credit_10*AI7 -> 1656.25
A8: years 1–3 | B8: 1 | C8: 1 | D8: 1 | E8: 0 | F8: 0 | G8: 0 | H8: =Gap0*(1-Share*B8) -> 7 | I8: =H8*(1-Share*C8) -> 3.5 | J8: =I8*(1-Share*D8) -> 1.75 | K8: =J8*(1-Share*E8) -> 1.75 | L8: =K8*(1-Share*F8) -> 1.75 | M8: =L8*(1-Share*G8) -> 1.75 | N8: =Smax-Val_pt*H8 -> 70 | O8: =Smax-Val_pt*I8 -> 105 | P8: =Smax-Val_pt*J8 -> 122.5 | Q8: =Smax-Val_pt*K8 -> 122.5 | R8: =Smax-Val_pt*L8 -> 122.5 | S8: =Smax-Val_pt*M8 -> 122.5 | T8: =SUM(B8:G8) -> 3 | U8: =Cash0+SUM(N8:S8)-Cost_r*T8+Credit_M*S8 -> 2905 | V8: =Cash0+SUM(N8:S8)-Cost_r*T8+Credit_10*S8 -> 1680 | W8: =Liq0+N8-Cost_r*B8 -> 570 | X8: =W8+O8-Cost_r*C8 -> 555 | Y8: =X8+P8-Cost_r*D8 -> 557.5 | Z8: =Y8+Q8-Cost_r*E8 -> 680 | AA8: =Z8+R8-Cost_r*F8 -> 802.5 | AB8: =AA8+S8-Cost_r*G8 -> 925 | AC8: =MIN(MIN(Liq0-Cost_r*B8,W8-Cost_r*C8,X8-Cost_r*D8,Y8-Cost_r*E8,Z8-Cost_r*F8,AA8-Cost_r*G8,MIN(W8:AB8))-Floor_q,AB8-End_q) -> 85 | AD8: =Smax*(1-POWER(Keep,SUM($B8:B8))) -> 70 | AE8: =Smax*(1-POWER(Keep,SUM($B8:C8))) -> 105 | AF8: =Smax*(1-POWER(Keep,SUM($B8:D8))) -> 122.5 | AG8: =Smax*(1-POWER(Keep,SUM($B8:E8))) -> 122.5 | AH8: =Smax*(1-POWER(Keep,SUM($B8:F8))) -> 122.5 | AI8: =Smax*(1-POWER(Keep,SUM($B8:G8))) -> 122.5 | AJ8: =Cash0+SUM(AD8:AI8)-Cost_r*T8+Credit_M*AI8 -> 2905 | AK8: =Cash0+SUM(AD8:AI8)-Cost_r*T8+Credit_10*AI8 -> 1680
A9: the saddle: years 1–3, x* in year 4, y* in year 5 | B9: 1 | C9: 1 | D9: 1 | E9: =Face!B17 -> 0.75324675 | F9: =Face!B18 -> 0.84415584 | G9: 0 | H9: =Gap0*(1-Share*B9) -> 7 | I9: =H9*(1-Share*C9) -> 3.5 | J9: =I9*(1-Share*D9) -> 1.75 | K9: =J9*(1-Share*E9) -> 1.0909091 | L9: =K9*(1-Share*F9) -> 0.63046045 | M9: =L9*(1-Share*G9) -> 0.63046045 | N9: =Smax-Val_pt*H9 -> 70 | O9: =Smax-Val_pt*I9 -> 105 | P9: =Smax-Val_pt*J9 -> 122.5 | Q9: =Smax-Val_pt*K9 -> 129.09091 | R9: =Smax-Val_pt*L9 -> 133.6954 | S9: =Smax-Val_pt*M9 -> 133.6954 | T9: =SUM(B9:G9) -> 4.5974026 | U9: =Cash0+SUM(N9:S9)-Cost_r*T9+Credit_M*S9 -> 2966.2013 | V9: =Cash0+SUM(N9:S9)-Cost_r*T9+Credit_10*S9 -> 1629.2473 | W9: =Liq0+N9-Cost_r*B9 -> 570 | X9: =W9+O9-Cost_r*C9 -> 555 | Y9: =X9+P9-Cost_r*D9 -> 557.5 | Z9: =Y9+Q9-Cost_r*E9 -> 596.2013 | AA9: =Z9+R9-Cost_r*F9 -> 628.59799 | AB9: =AA9+S9-Cost_r*G9 -> 762.29339 | AC9: =MIN(MIN(Liq0-Cost_r*B9,W9-Cost_r*C9,X9-Cost_r*D9,Y9-Cost_r*E9,Z9-Cost_r*F9,AA9-Cost_r*G9,MIN(W9:AB9))-Floor_q,AB9-End_q) -> 85 | AD9: =Smax*(1-POWER(Keep,SUM($B9:B9))) -> 70 | AE9: =Smax*(1-POWER(Keep,SUM($B9:C9))) -> 105 | AF9: =Smax*(1-POWER(Keep,SUM($B9:D9))) -> 122.5 | AG9: =Smax*(1-POWER(Keep,SUM($B9:E9))) -> 129.61783 | AH9: =Smax*(1-POWER(Keep,SUM($B9:F9))) -> 134.21675 | AI9: =Smax*(1-POWER(Keep,SUM($B9:G9))) -> 134.21675 | AJ9: =Cash0+SUM(AD9:AI9)-Cost_r*T9+Credit_M*AI9 -> 2978.198 | AK9: =Cash0+SUM(AD9:AI9)-Cost_r*T9+Credit_10*AI9 -> 1636.0305
A10: Chapter 3's relaxation at credit M (its plan) | B10: =Relaxation!B16 -> 1 | C10: =Relaxation!C16 -> 1 | D10: =Relaxation!D16 -> 1 | E10: =Relaxation!E16 -> 1 | F10: =Relaxation!F16 -> 0.15305767 | G10: =Relaxation!G16 -> 0 | H10: =Gap0*(1-Share*B10) -> 7 | I10: =H10*(1-Share*C10) -> 3.5 | J10: =I10*(1-Share*D10) -> 1.75 | K10: =J10*(1-Share*E10) -> 0.875 | L10: =K10*(1-Share*F10) -> 0.80803727 | M10: =L10*(1-Share*G10) -> 0.80803727 | N10: =Smax-Val_pt*H10 -> 70 | O10: =Smax-Val_pt*I10 -> 105 | P10: =Smax-Val_pt*J10 -> 122.5 | Q10: =Smax-Val_pt*K10 -> 131.25 | R10: =Smax-Val_pt*L10 -> 131.91963 | S10: =Smax-Val_pt*M10 -> 131.91963 | T10: =SUM(B10:G10) -> 4.1530577 | U10: =Cash0+SUM(N10:S10)-Cost_r*T10+Credit_M*S10 -> 2982.6149 | V10: =Cash0+SUM(N10:S10)-Cost_r*T10+Credit_10*S10 -> 1663.4186 | W10: =Liq0+N10-Cost_r*B10 -> 570 | X10: =W10+O10-Cost_r*C10 -> 555 | Y10: =X10+P10-Cost_r*D10 -> 557.5 | Z10: =Y10+Q10-Cost_r*E10 -> 568.75 | AA10: =Z10+R10-Cost_r*F10 -> 682.30271 | AB10: =AA10+S10-Cost_r*G10 -> 814.22233 | AC10: =MIN(MIN(Liq0-Cost_r*B10,W10-Cost_r*C10,X10-Cost_r*D10,Y10-Cost_r*E10,Z10-Cost_r*F10,AA10-Cost_r*G10,MIN(W10:AB10))-Floor_q,AB10-End_q) -> 85 | AD10: =Smax*(1-POWER(Keep,SUM($B10:B10))) -> 70 | AE10: =Smax*(1-POWER(Keep,SUM($B10:C10))) -> 105 | AF10: =Smax*(1-POWER(Keep,SUM($B10:D10))) -> 122.5 | AG10: =Smax*(1-POWER(Keep,SUM($B10:E10))) -> 131.25 | AH10: =Smax*(1-POWER(Keep,SUM($B10:F10))) -> 132.13075 | AI10: =Smax*(1-POWER(Keep,SUM($B10:G10))) -> 132.13075 | AJ10: =Cash0+SUM(AD10:AI10)-Cost_r*T10+Credit_M*AI10 -> 2987.2597 | AK10: =Cash0+SUM(AD10:AI10)-Cost_r*T10+Credit_10*AI10 -> 1665.9521
A11: Chapter 3's relaxation at ten years (its plan) | B11: =Relaxation!B32 -> 1 | C11: =Relaxation!C32 -> 1 | D11: =Relaxation!D32 -> 1 | E11: =Relaxation!E32 -> 0.39406577 | F11: =Relaxation!F32 -> 0 | G11: =Relaxation!G32 -> 0 | H11: =Gap0*(1-Share*B11) -> 7 | I11: =H11*(1-Share*C11) -> 3.5 | J11: =I11*(1-Share*D11) -> 1.75 | K11: =J11*(1-Share*E11) -> 1.4051925 | L11: =K11*(1-Share*F11) -> 1.4051925 | M11: =L11*(1-Share*G11) -> 1.4051925 | N11: =Smax-Val_pt*H11 -> 70 | O11: =Smax-Val_pt*I11 -> 105 | P11: =Smax-Val_pt*J11 -> 122.5 | Q11: =Smax-Val_pt*K11 -> 125.94808 | R11: =Smax-Val_pt*L11 -> 125.94808 | S11: =Smax-Val_pt*M11 -> 125.94808 | T11: =SUM(B11:G11) -> 3.3940658 | U11: =Cash0+SUM(N11:S11)-Cost_r*T11+Credit_M*S11 -> 2937.0178 | V11: =Cash0+SUM(N11:S11)-Cost_r*T11+Credit_10*S11 -> 1677.5371 | W11: =Liq0+N11-Cost_r*B11 -> 570 | X11: =W11+O11-Cost_r*C11 -> 555 | Y11: =X11+P11-Cost_r*D11 -> 557.5 | Z11: =Y11+Q11-Cost_r*E11 -> 636.16018 | AA11: =Z11+R11-Cost_r*F11 -> 762.10826 | AB11: =AA11+S11-Cost_r*G11 -> 888.05633 | AC11: =MIN(MIN(Liq0-Cost_r*B11,W11-Cost_r*C11,X11-Cost_r*D11,Y11-Cost_r*E11,Z11-Cost_r*F11,AA11-Cost_r*G11,MIN(W11:AB11))-Floor_q,AB11-End_q) -> 85 | AD11: =Smax*(1-POWER(Keep,SUM($B11:B11))) -> 70 | AE11: =Smax*(1-POWER(Keep,SUM($B11:C11))) -> 105 | AF11: =Smax*(1-POWER(Keep,SUM($B11:D11))) -> 122.5 | AG11: =Smax*(1-POWER(Keep,SUM($B11:E11))) -> 126.68282 | AH11: =Smax*(1-POWER(Keep,SUM($B11:F11))) -> 126.68282 | AI11: =Smax*(1-POWER(Keep,SUM($B11:G11))) -> 126.68282 | AJ11: =Cash0+SUM(AD11:AI11)-Cost_r*T11+Credit_M*AI11 -> 2953.9169 | AK11: =Cash0+SUM(AD11:AI11)-Cost_r*T11+Credit_10*AI11 -> 1687.0887
A12: half a round in year 1 | B12: 0.5 | C12: 0 | D12: 0 | E12: 0 | F12: 0 | G12: 0 | H12: =Gap0*(1-Share*B12) -> 10.5 | I12: =H12*(1-Share*C12) -> 10.5 | J12: =I12*(1-Share*D12) -> 10.5 | K12: =J12*(1-Share*E12) -> 10.5 | L12: =K12*(1-Share*F12) -> 10.5 | M12: =L12*(1-Share*G12) -> 10.5 | N12: =Smax-Val_pt*H12 -> 35 | O12: =Smax-Val_pt*I12 -> 35 | P12: =Smax-Val_pt*J12 -> 35 | Q12: =Smax-Val_pt*K12 -> 35 | R12: =Smax-Val_pt*L12 -> 35 | S12: =Smax-Val_pt*M12 -> 35 | T12: =SUM(B12:G12) -> 0.5 | U12: =Cash0+SUM(N12:S12)-Cost_r*T12+Credit_M*S12 -> 1000 | V12: =Cash0+SUM(N12:S12)-Cost_r*T12+Credit_10*S12 -> 650 | W12: =Liq0+N12-Cost_r*B12 -> 595 | X12: =W12+O12-Cost_r*C12 -> 630 | Y12: =X12+P12-Cost_r*D12 -> 665 | Z12: =Y12+Q12-Cost_r*E12 -> 700 | AA12: =Z12+R12-Cost_r*F12 -> 735 | AB12: =AA12+S12-Cost_r*G12 -> 770 | AC12: =MIN(MIN(Liq0-Cost_r*B12,W12-Cost_r*C12,X12-Cost_r*D12,Y12-Cost_r*E12,Z12-Cost_r*F12,AA12-Cost_r*G12,MIN(W12:AB12))-Floor_q,AB12-End_q) -> 210 | AD12: =Smax*(1-POWER(Keep,SUM($B12:B12))) -> 41.005051 | AE12: =Smax*(1-POWER(Keep,SUM($B12:C12))) -> 41.005051 | AF12: =Smax*(1-POWER(Keep,SUM($B12:D12))) -> 41.005051 | AG12: =Smax*(1-POWER(Keep,SUM($B12:E12))) -> 41.005051 | AH12: =Smax*(1-POWER(Keep,SUM($B12:F12))) -> 41.005051 | AI12: =Smax*(1-POWER(Keep,SUM($B12:G12))) -> 41.005051 | AJ12: =Cash0+SUM(AD12:AI12)-Cost_r*T12+Credit_M*AI12 -> 1156.1313 | AK12: =Cash0+SUM(AD12:AI12)-Cost_r*T12+Credit_10*AI12 -> 746.08081
A13: your plan (change the blue cells) | B13: 1 | C13: 1 | D13: 1 | E13: 0.5 | F13: 0.5 | G13: 0 | H13: =Gap0*(1-Share*B13) -> 7 | I13: =H13*(1-Share*C13) -> 3.5 | J13: =I13*(1-Share*D13) -> 1.75 | K13: =J13*(1-Share*E13) -> 1.3125 | L13: =K13*(1-Share*F13) -> 0.984375 | M13: =L13*(1-Share*G13) -> 0.984375 | N13: =Smax-Val_pt*H13 -> 70 | O13: =Smax-Val_pt*I13 -> 105 | P13: =Smax-Val_pt*J13 -> 122.5 | Q13: =Smax-Val_pt*K13 -> 126.875 | R13: =Smax-Val_pt*L13 -> 130.15625 | S13: =Smax-Val_pt*M13 -> 130.15625 | T13: =SUM(B13:G13) -> 4 | U13: =Cash0+SUM(N13:S13)-Cost_r*T13+Credit_M*S13 -> 2957.8125 | V13: =Cash0+SUM(N13:S13)-Cost_r*T13+Credit_10*S13 -> 1656.25 | W13: =Liq0+N13-Cost_r*B13 -> 570 | X13: =W13+O13-Cost_r*C13 -> 555 | Y13: =X13+P13-Cost_r*D13 -> 557.5 | Z13: =Y13+Q13-Cost_r*E13 -> 624.375 | AA13: =Z13+R13-Cost_r*F13 -> 694.53125 | AB13: =AA13+S13-Cost_r*G13 -> 824.6875 | AC13: =MIN(MIN(Liq0-Cost_r*B13,W13-Cost_r*C13,X13-Cost_r*D13,Y13-Cost_r*E13,Z13-Cost_r*F13,AA13-Cost_r*G13,MIN(W13:AB13))-Floor_q,AB13-End_q) -> 85 | AD13: =Smax*(1-POWER(Keep,SUM($B13:B13))) -> 70 | AE13: =Smax*(1-POWER(Keep,SUM($B13:C13))) -> 105 | AF13: =Smax*(1-POWER(Keep,SUM($B13:D13))) -> 122.5 | AG13: =Smax*(1-POWER(Keep,SUM($B13:E13))) -> 127.62563 | AH13: =Smax*(1-POWER(Keep,SUM($B13:F13))) -> 131.25 | AI13: =Smax*(1-POWER(Keep,SUM($B13:G13))) -> 131.25 | AJ13: =Cash0+SUM(AD13:AI13)-Cost_r*T13+Credit_M*AI13 -> 2982.6256 | AK13: =Cash0+SUM(AD13:AI13)-Cost_r*T13+Credit_10*AI13 -> 1670.1256
A14: your plan with no year-4 round | B14: =B13 -> 1 | C14: =C13 -> 1 | D14: =D13 -> 1 | E14: 0 | F14: =F13 -> 0.5 | G14: =G13 -> 0 | H14: =Gap0*(1-Share*B14) -> 7 | I14: =H14*(1-Share*C14) -> 3.5 | J14: =I14*(1-Share*D14) -> 1.75 | K14: =J14*(1-Share*E14) -> 1.75 | L14: =K14*(1-Share*F14) -> 1.3125 | M14: =L14*(1-Share*G14) -> 1.3125 | N14: =Smax-Val_pt*H14 -> 70 | O14: =Smax-Val_pt*I14 -> 105 | P14: =Smax-Val_pt*J14 -> 122.5 | Q14: =Smax-Val_pt*K14 -> 122.5 | R14: =Smax-Val_pt*L14 -> 126.875 | S14: =Smax-Val_pt*M14 -> 126.875 | T14: =SUM(B14:G14) -> 3.5 | U14: =Cash0+SUM(N14:S14)-Cost_r*T14+Credit_M*S14 -> 2941.25 | V14: =Cash0+SUM(N14:S14)-Cost_r*T14+Credit_10*S14 -> 1672.5 | W14: =Liq0+N14-Cost_r*B14 -> 570 | X14: =W14+O14-Cost_r*C14 -> 555 | Y14: =X14+P14-Cost_r*D14 -> 557.5 | Z14: =Y14+Q14-Cost_r*E14 -> 680 | AA14: =Z14+R14-Cost_r*F14 -> 746.875 | AB14: =AA14+S14-Cost_r*G14 -> 873.75 | AC14: =MIN(MIN(Liq0-Cost_r*B14,W14-Cost_r*C14,X14-Cost_r*D14,Y14-Cost_r*E14,Z14-Cost_r*F14,AA14-Cost_r*G14,MIN(W14:AB14))-Floor_q,AB14-End_q) -> 85 | AD14: =Smax*(1-POWER(Keep,SUM($B14:B14))) -> 70 | AE14: =Smax*(1-POWER(Keep,SUM($B14:C14))) -> 105 | AF14: =Smax*(1-POWER(Keep,SUM($B14:D14))) -> 122.5 | AG14: =Smax*(1-POWER(Keep,SUM($B14:E14))) -> 122.5 | AH14: =Smax*(1-POWER(Keep,SUM($B14:F14))) -> 127.62563 | AI14: =Smax*(1-POWER(Keep,SUM($B14:G14))) -> 127.62563 | AJ14: =Cash0+SUM(AD14:AI14)-Cost_r*T14+Credit_M*AI14 -> 2957.7639 | AK14: =Cash0+SUM(AD14:AI14)-Cost_r*T14+Credit_10*AI14 -> 1681.5076
A15: your plan with a whole year-4 round | B15: =B13 -> 1 | C15: =C13 -> 1 | D15: =D13 -> 1 | E15: 1 | F15: =F13 -> 0.5 | G15: =G13 -> 0 | H15: =Gap0*(1-Share*B15) -> 7 | I15: =H15*(1-Share*C15) -> 3.5 | J15: =I15*(1-Share*D15) -> 1.75 | K15: =J15*(1-Share*E15) -> 0.875 | L15: =K15*(1-Share*F15) -> 0.65625 | M15: =L15*(1-Share*G15) -> 0.65625 | N15: =Smax-Val_pt*H15 -> 70 | O15: =Smax-Val_pt*I15 -> 105 | P15: =Smax-Val_pt*J15 -> 122.5 | Q15: =Smax-Val_pt*K15 -> 131.25 | R15: =Smax-Val_pt*L15 -> 133.4375 | S15: =Smax-Val_pt*M15 -> 133.4375 | T15: =SUM(B15:G15) -> 4.5 | U15: =Cash0+SUM(N15:S15)-Cost_r*T15+Credit_M*S15 -> 2974.375 | V15: =Cash0+SUM(N15:S15)-Cost_r*T15+Credit_10*S15 -> 1640 | W15: =Liq0+N15-Cost_r*B15 -> 570 | X15: =W15+O15-Cost_r*C15 -> 555 | Y15: =X15+P15-Cost_r*D15 -> 557.5 | Z15: =Y15+Q15-Cost_r*E15 -> 568.75 | AA15: =Z15+R15-Cost_r*F15 -> 642.1875 | AB15: =AA15+S15-Cost_r*G15 -> 775.625 | AC15: =MIN(MIN(Liq0-Cost_r*B15,W15-Cost_r*C15,X15-Cost_r*D15,Y15-Cost_r*E15,Z15-Cost_r*F15,AA15-Cost_r*G15,MIN(W15:AB15))-Floor_q,AB15-End_q) -> 85 | AD15: =Smax*(1-POWER(Keep,SUM($B15:B15))) -> 70 | AE15: =Smax*(1-POWER(Keep,SUM($B15:C15))) -> 105 | AF15: =Smax*(1-POWER(Keep,SUM($B15:D15))) -> 122.5 | AG15: =Smax*(1-POWER(Keep,SUM($B15:E15))) -> 131.25 | AH15: =Smax*(1-POWER(Keep,SUM($B15:F15))) -> 133.81282 | AI15: =Smax*(1-POWER(Keep,SUM($B15:G15))) -> 133.81282 | AJ15: =Cash0+SUM(AD15:AI15)-Cost_r*T15+Credit_M*AI15 -> 2982.6319 | AK15: =Cash0+SUM(AD15:AI15)-Cost_r*T15+Credit_10*AI15 -> 1644.5038
A17: The relaxation's plan at credit M, in the partial-round model, below running none | U17: =U5-U10 -> 3.6351196
A18: The relaxation's plan at ten years, in the partial-round model, below three rounds | V18: =V8-V11 -> 2.462911
A19: Your plan's year-4 round as a blend of none and whole: (1 - z4) V(none) + z4 V(whole) | U19: =(1-E13)*U14+E13*U15 -> 2957.8125
A20: Your plan's value less that blend (zero: Proposition 4.2(i)) | U20: =U13-U19 -> 0
A21: V is affine in each round: set any one blue z between 0 and 1 and the value moves in a straight line, never above the better end; the relaxation's value (AJ) always lies above it (2^-z <= 1 - z/2).

Sheet Schedules
A1: All 64 plans of whole rounds: values, floors, marginal values and the corner test (Proposition 4.2(iii))
A2: Plan i runs a round in year k when the k-th binary digit of i is 1 (i = 32 z1 + 16 z2 + ... + z6). Marginal values at credit M are exact: V is affine in each round. A corner is a strict local maximum when every marginal value points out of the box.
A4: i | B4: z1 | C4: z2 | D4: z3 | E4: z4 | F4: z5 | G4: z6 | H4: gap 1 | I4: gap 2 | J4: gap 3 | K4: gap 4 | L4: gap 5 | M4: gap 6 | N4: S 1 | O4: S 2 | P4: S 3 | Q4: S 4 | R4: S 5 | S4: S 6 | T4: Rounds | U4: V, credit M | V4: V, ten years | W4: q 1 | X4: q 2 | Y4: q 3 | Z4: q 4 | AA4: q 5 | AB4: q 6 | AC4: Smallest slack | AD4: marginal 1 | AE4: marginal 2 | AF4: marginal 3 | AG4: marginal 4 | AH4: marginal 5 | AI4: marginal 6 | AJ4: Strict local max | AL4: Summary | AM4: Value
A5: 0 | B5: =MOD(INT($A5/32),2) -> 0 | C5: =MOD(INT($A5/16),2) -> 0 | D5: =MOD(INT($A5/8),2) -> 0 | E5: =MOD(INT($A5/4),2) -> 0 | F5: =MOD(INT($A5/2),2) -> 0 | G5: =MOD(INT($A5/1),2) -> 0 | H5: =Gap0*(1-Share*B5) -> 14 | I5: =H5*(1-Share*C5) -> 14 | J5: =I5*(1-Share*D5) -> 14 | K5: =J5*(1-Share*E5) -> 14 | L5: =K5*(1-Share*F5) -> 14 | M5: =L5*(1-Share*G5) -> 14 | N5: =Smax-Val_pt*H5 -> 0 | O5: =Smax-Val_pt*I5 -> 0 | P5: =Smax-Val_pt*J5 -> 0 | Q5: =Smax-Val_pt*K5 -> 0 | R5: =Smax-Val_pt*L5 -> 0 | S5: =Smax-Val_pt*M5 -> 0 | T5: =SUM(B5:G5) -> 0 | U5: =Cash0+SUM(N5:S5)-Cost_r*T5+Credit_M*S5 -> 150 | V5: =Cash0+SUM(N5:S5)-Cost_r*T5+Credit_10*S5 -> 150 | W5: =Liq0+N5-Cost_r*B5 -> 620 | X5: =W5+O5-Cost_r*C5 -> 620 | Y5: =X5+P5-Cost_r*D5 -> 620 | Z5: =Y5+Q5-Cost_r*E5 -> 620 | AA5: =Z5+R5-Cost_r*F5 -> 620 | AB5: =AA5+S5-Cost_r*G5 -> 620 | AC5: =MIN(MIN(Liq0-Cost_r*B5,W5-Cost_r*C5,X5-Cost_r*D5,Y5-Cost_r*E5,Z5-Cost_r*F5,AA5-Cost_r*G5,MIN(W5:AB5))-Floor_q,AB5-End_q) -> 150 | AD5: =Val_pt*Share/(1-Share*B5)*(SUM(H5:M5)+Credit_M*M5)-Cost_r -> 1700 | AE5: =Val_pt*Share/(1-Share*C5)*(SUM(I5:M5)+Credit_M*M5)-Cost_r -> 1630 | AF5: =Val_pt*Share/(1-Share*D5)*(SUM(J5:M5)+Credit_M*M5)-Cost_r -> 1560 | AG5: =Val_pt*Share/(1-Share*E5)*(SUM(K5:M5)+Credit_M*M5)-Cost_r -> 1490 | AH5: =Val_pt*Share/(1-Share*F5)*(SUM(L5:M5)+Credit_M*M5)-Cost_r -> 1420 | AI5: =Val_pt*Share/(1-Share*G5)*(SUM(M5:M5)+Credit_M*M5)-Cost_r -> 1350 | AJ5: =IF(AND(IF(B5=1,AD5>0,AD5<0),IF(C5=1,AE5>0,AE5<0),IF(D5=1,AF5>0,AF5<0),IF(E5=1,AG5>0,AG5<0),IF(F5=1,AH5>0,AH5<0),IF(G5=1,AI5>0,AI5<0)),1,0) -> 0 | AL5: Strict local maxima at credit M | AM5: =SUM(AJ5:AJ68) -> 3
A6: 1 | B6: =MOD(INT($A6/32),2) -> 0 | C6: =MOD(INT($A6/16),2) -> 0 | D6: =MOD(INT($A6/8),2) -> 0 | E6: =MOD(INT($A6/4),2) -> 0 | F6: =MOD(INT($A6/2),2) -> 0 | G6: =MOD(INT($A6/1),2) -> 1 | H6: =Gap0*(1-Share*B6) -> 14 | I6: =H6*(1-Share*C6) -> 14 | J6: =I6*(1-Share*D6) -> 14 | K6: =J6*(1-Share*E6) -> 14 | L6: =K6*(1-Share*F6) -> 14 | M6: =L6*(1-Share*G6) -> 7 | N6: =Smax-Val_pt*H6 -> 0 | O6: =Smax-Val_pt*I6 -> 0 | P6: =Smax-Val_pt*J6 -> 0 | Q6: =Smax-Val_pt*K6 -> 0 | R6: =Smax-Val_pt*L6 -> 0 | S6: =Smax-Val_pt*M6 -> 70 | T6: =SUM(B6:G6) -> 1 | U6: =Cash0+SUM(N6:S6)-Cost_r*T6+Credit_M*S6 -> 1500 | V6: =Cash0+SUM(N6:S6)-Cost_r*T6+Credit_10*S6 -> 800 | W6: =Liq0+N6-Cost_r*B6 -> 620 | X6: =W6+O6-Cost_r*C6 -> 620 | Y6: =X6+P6-Cost_r*D6 -> 620 | Z6: =Y6+Q6-Cost_r*E6 -> 620 | AA6: =Z6+R6-Cost_r*F6 -> 620 | AB6: =AA6+S6-Cost_r*G6 -> 570 | AC6: =MIN(MIN(Liq0-Cost_r*B6,W6-Cost_r*C6,X6-Cost_r*D6,Y6-Cost_r*E6,Z6-Cost_r*F6,AA6-Cost_r*G6,MIN(W6:AB6))-Floor_q,AB6-End_q) -> 100 | AD6: =Val_pt*Share/(1-Share*B6)*(SUM(H6:M6)+Credit_M*M6)-Cost_r -> 965 | AE6: =Val_pt*Share/(1-Share*C6)*(SUM(I6:M6)+Credit_M*M6)-Cost_r -> 895 | AF6: =Val_pt*Share/(1-Share*D6)*(SUM(J6:M6)+Credit_M*M6)-Cost_r -> 825 | AG6: =Val_pt*Share/(1-Share*E6)*(SUM(K6:M6)+Credit_M*M6)-Cost_r -> 755 | AH6: =Val_pt*Share/(1-Share*F6)*(SUM(L6:M6)+Credit_M*M6)-Cost_r -> 685 | AI6: =Val_pt*Share/(1-Share*G6)*(SUM(M6:M6)+Credit_M*M6)-Cost_r -> 1350 | AJ6: =IF(AND(IF(B6=1,AD6>0,AD6<0),IF(C6=1,AE6>0,AE6<0),IF(D6=1,AF6>0,AF6<0),IF(E6=1,AG6>0,AG6<0),IF(F6=1,AH6>0,AH6<0),IF(G6=1,AI6>0,AI6<0)),1,0) -> 0 | AL6: Best plan of whole rounds at credit M | AM6: =MAX(U5:U68) -> 2986.25
A7: 2 | B7: =MOD(INT($A7/32),2) -> 0 | C7: =MOD(INT($A7/16),2) -> 0 | D7: =MOD(INT($A7/8),2) -> 0 | E7: =MOD(INT($A7/4),2) -> 0 | F7: =MOD(INT($A7/2),2) -> 1 | G7: =MOD(INT($A7/1),2) -> 0 | H7: =Gap0*(1-Share*B7) -> 14 | I7: =H7*(1-Share*C7) -> 14 | J7: =I7*(1-Share*D7) -> 14 | K7: =J7*(1-Share*E7) -> 14 | L7: =K7*(1-Share*F7) -> 7 | M7: =L7*(1-Share*G7) -> 7 | N7: =Smax-Val_pt*H7 -> 0 | O7: =Smax-Val_pt*I7 -> 0 | P7: =Smax-Val_pt*J7 -> 0 | Q7: =Smax-Val_pt*K7 -> 0 | R7: =Smax-Val_pt*L7 -> 70 | S7: =Smax-Val_pt*M7 -> 70 | T7: =SUM(B7:G7) -> 1 | U7: =Cash0+SUM(N7:S7)-Cost_r*T7+Credit_M*S7 -> 1570 | V7: =Cash0+SUM(N7:S7)-Cost_r*T7+Credit_10*S7 -> 870 | W7: =Liq0+N7-Cost_r*B7 -> 620 | X7: =W7+O7-Cost_r*C7 -> 620 | Y7: =X7+P7-Cost_r*D7 -> 620 | Z7: =Y7+Q7-Cost_r*E7 -> 620 | AA7: =Z7+R7-Cost_r*F7 -> 570 | AB7: =AA7+S7-Cost_r*G7 -> 640 | AC7: =MIN(MIN(Liq0-Cost_r*B7,W7-Cost_r*C7,X7-Cost_r*D7,Y7-Cost_r*E7,Z7-Cost_r*F7,AA7-Cost_r*G7,MIN(W7:AB7))-Floor_q,AB7-End_q) -> 150 | AD7: =Val_pt*Share/(1-Share*B7)*(SUM(H7:M7)+Credit_M*M7)-Cost_r -> 930 | AE7: =Val_pt*Share/(1-Share*C7)*(SUM(I7:M7)+Credit_M*M7)-Cost_r -> 860 | AF7: =Val_pt*Share/(1-Share*D7)*(SUM(J7:M7)+Credit_M*M7)-Cost_r -> 790 | AG7: =Val_pt*Share/(1-Share*E7)*(SUM(K7:M7)+Credit_M*M7)-Cost_r -> 720 | AH7: =Val_pt*Share/(1-Share*F7)*(SUM(L7:M7)+Credit_M*M7)-Cost_r -> 1420 | AI7: =Val_pt*Share/(1-Share*G7)*(SUM(M7:M7)+Credit_M*M7)-Cost_r -> 615 | AJ7: =IF(AND(IF(B7=1,AD7>0,AD7<0),IF(C7=1,AE7>0,AE7<0),IF(D7=1,AF7>0,AF7<0),IF(E7=1,AG7>0,AG7<0),IF(F7=1,AH7>0,AH7<0),IF(G7=1,AI7>0,AI7<0)),1,0) -> 0 | AL7: Its index i | AM7: =INDEX(A5:A68,MATCH(AM6,U5:U68,0)) -> 60
A8: 3 | B8: =MOD(INT($A8/32),2) -> 0 | C8: =MOD(INT($A8/16),2) -> 0 | D8: =MOD(INT($A8/8),2) -> 0 | E8: =MOD(INT($A8/4),2) -> 0 | F8: =MOD(INT($A8/2),2) -> 1 | G8: =MOD(INT($A8/1),2) -> 1 | H8: =Gap0*(1-Share*B8) -> 14 | I8: =H8*(1-Share*C8) -> 14 | J8: =I8*(1-Share*D8) -> 14 | K8: =J8*(1-Share*E8) -> 14 | L8: =K8*(1-Share*F8) -> 7 | M8: =L8*(1-Share*G8) -> 3.5 | N8: =Smax-Val_pt*H8 -> 0 | O8: =Smax-Val_pt*I8 -> 0 | P8: =Smax-Val_pt*J8 -> 0 | Q8: =Smax-Val_pt*K8 -> 0 | R8: =Smax-Val_pt*L8 -> 70 | S8: =Smax-Val_pt*M8 -> 105 | T8: =SUM(B8:G8) -> 2 | U8: =Cash0+SUM(N8:S8)-Cost_r*T8+Credit_M*S8 -> 2185 | V8: =Cash0+SUM(N8:S8)-Cost_r*T8+Credit_10*S8 -> 1135 | W8: =Liq0+N8-Cost_r*B8 -> 620 | X8: =W8+O8-Cost_r*C8 -> 620 | Y8: =X8+P8-Cost_r*D8 -> 620 | Z8: =Y8+Q8-Cost_r*E8 -> 620 | AA8: =Z8+R8-Cost_r*F8 -> 570 | AB8: =AA8+S8-Cost_r*G8 -> 555 | AC8: =MIN(MIN(Liq0-Cost_r*B8,W8-Cost_r*C8,X8-Cost_r*D8,Y8-Cost_r*E8,Z8-Cost_r*F8,AA8-Cost_r*G8,MIN(W8:AB8))-Floor_q,AB8-End_q) -> 85 | AD8: =Val_pt*Share/(1-Share*B8)*(SUM(H8:M8)+Credit_M*M8)-Cost_r -> 562.5 | AE8: =Val_pt*Share/(1-Share*C8)*(SUM(I8:M8)+Credit_M*M8)-Cost_r -> 492.5 | AF8: =Val_pt*Share/(1-Share*D8)*(SUM(J8:M8)+Credit_M*M8)-Cost_r -> 422.5 | AG8: =Val_pt*Share/(1-Share*E8)*(SUM(K8:M8)+Credit_M*M8)-Cost_r -> 352.5 | AH8: =Val_pt*Share/(1-Share*F8)*(SUM(L8:M8)+Credit_M*M8)-Cost_r -> 685 | AI8: =Val_pt*Share/(1-Share*G8)*(SUM(M8:M8)+Credit_M*M8)-Cost_r -> 615 | AJ8: =IF(AND(IF(B8=1,AD8>0,AD8<0),IF(C8=1,AE8>0,AE8<0),IF(D8=1,AF8>0,AF8<0),IF(E8=1,AG8>0,AG8<0),IF(F8=1,AH8>0,AH8<0),IF(G8=1,AI8>0,AI8<0)),1,0) -> 0 | AL8: Smallest slack in the floors over the 64 plans | AM8: =MIN(AC5:AC68) -> 85
A9: 4 | B9: =MOD(INT($A9/32),2) -> 0 | C9: =MOD(INT($A9/16),2) -> 0 | D9: =MOD(INT($A9/8),2) -> 0 | E9: =MOD(INT($A9/4),2) -> 1 | F9: =MOD(INT($A9/2),2) -> 0 | G9: =MOD(INT($A9/1),2) -> 0 | H9: =Gap0*(1-Share*B9) -> 14 | I9: =H9*(1-Share*C9) -> 14 | J9: =I9*(1-Share*D9) -> 14 | K9: =J9*(1-Share*E9) -> 7 | L9: =K9*(1-Share*F9) -> 7 | M9: =L9*(1-Share*G9) -> 7 | N9: =Smax-Val_pt*H9 -> 0 | O9: =Smax-Val_pt*I9 -> 0 | P9: =Smax-Val_pt*J9 -> 0 | Q9: =Smax-Val_pt*K9 -> 70 | R9: =Smax-Val_pt*L9 -> 70 | S9: =Smax-Val_pt*M9 -> 70 | T9: =SUM(B9:G9) -> 1 | U9: =Cash0+SUM(N9:S9)-Cost_r*T9+Credit_M*S9 -> 1640 | V9: =Cash0+SUM(N9:S9)-Cost_r*T9+Credit_10*S9 -> 940 | W9: =Liq0+N9-Cost_r*B9 -> 620 | X9: =W9+O9-Cost_r*C9 -> 620 | Y9: =X9+P9-Cost_r*D9 -> 620 | Z9: =Y9+Q9-Cost_r*E9 -> 570 | AA9: =Z9+R9-Cost_r*F9 -> 640 | AB9: =AA9+S9-Cost_r*G9 -> 710 | AC9: =MIN(MIN(Liq0-Cost_r*B9,W9-Cost_r*C9,X9-Cost_r*D9,Y9-Cost_r*E9,Z9-Cost_r*F9,AA9-Cost_r*G9,MIN(W9:AB9))-Floor_q,AB9-End_q) -> 150 | AD9: =Val_pt*Share/(1-Share*B9)*(SUM(H9:M9)+Credit_M*M9)-Cost_r -> 895 | AE9: =Val_pt*Share/(1-Share*C9)*(SUM(I9:M9)+Credit_M*M9)-Cost_r -> 825 | AF9: =Val_pt*Share/(1-Share*D9)*(SUM(J9:M9)+Credit_M*M9)-Cost_r -> 755 | AG9: =Val_pt*Share/(1-Share*E9)*(SUM(K9:M9)+Credit_M*M9)-Cost_r -> 1490 | AH9: =Val_pt*Share/(1-Share*F9)*(SUM(L9:M9)+Credit_M*M9)-Cost_r -> 650 | AI9: =Val_pt*Share/(1-Share*G9)*(SUM(M9:M9)+Credit_M*M9)-Cost_r -> 615 | AJ9: =IF(AND(IF(B9=1,AD9>0,AD9<0),IF(C9=1,AE9>0,AE9<0),IF(D9=1,AF9>0,AF9<0),IF(E9=1,AG9>0,AG9<0),IF(F9=1,AH9>0,AH9<0),IF(G9=1,AI9>0,AI9<0)),1,0) -> 0 | AL9: Best plan of whole rounds at ten years | AM9: =MAX(V5:V68) -> 1680
A10: 5 | B10: =MOD(INT($A10/32),2) -> 0 | C10: =MOD(INT($A10/16),2) -> 0 | D10: =MOD(INT($A10/8),2) -> 0 | E10: =MOD(INT($A10/4),2) -> 1 | F10: =MOD(INT($A10/2),2) -> 0 | G10: =MOD(INT($A10/1),2) -> 1 | H10: =Gap0*(1-Share*B10) -> 14 | I10: =H10*(1-Share*C10) -> 14 | J10: =I10*(1-Share*D10) -> 14 | K10: =J10*(1-Share*E10) -> 7 | L10: =K10*(1-Share*F10) -> 7 | M10: =L10*(1-Share*G10) -> 3.5 | N10: =Smax-Val_pt*H10 -> 0 | O10: =Smax-Val_pt*I10 -> 0 | P10: =Smax-Val_pt*J10 -> 0 | Q10: =Smax-Val_pt*K10 -> 70 | R10: =Smax-Val_pt*L10 -> 70 | S10: =Smax-Val_pt*M10 -> 105 | T10: =SUM(B10:G10) -> 2 | U10: =Cash0+SUM(N10:S10)-Cost_r*T10+Credit_M*S10 -> 2255 | V10: =Cash0+SUM(N10:S10)-Cost_r*T10+Credit_10*S10 -> 1205 | W10: =Liq0+N10-Cost_r*B10 -> 620 | X10: =W10+O10-Cost_r*C10 -> 620 | Y10: =X10+P10-Cost_r*D10 -> 620 | Z10: =Y10+Q10-Cost_r*E10 -> 570 | AA10: =Z10+R10-Cost_r*F10 -> 640 | AB10: =AA10+S10-Cost_r*G10 -> 625 | AC10: =MIN(MIN(Liq0-Cost_r*B10,W10-Cost_r*C10,X10-Cost_r*D10,Y10-Cost_r*E10,Z10-Cost_r*F10,AA10-Cost_r*G10,MIN(W10:AB10))-Floor_q,AB10-End_q) -> 150 | AD10: =Val_pt*Share/(1-Share*B10)*(SUM(H10:M10)+Credit_M*M10)-Cost_r -> 527.5 | AE10: =Val_pt*Share/(1-Share*C10)*(SUM(I10:M10)+Credit_M*M10)-Cost_r -> 457.5 | AF10: =Val_pt*Share/(1-Share*D10)*(SUM(J10:M10)+Credit_M*M10)-Cost_r -> 387.5 | AG10: =Val_pt*Share/(1-Share*E10)*(SUM(K10:M10)+Credit_M*M10)-Cost_r -> 755 | AH10: =Val_pt*Share/(1-Share*F10)*(SUM(L10:M10)+Credit_M*M10)-Cost_r -> 282.5 | AI10: =Val_pt*Share/(1-Share*G10)*(SUM(M10:M10)+Credit_M*M10)-Cost_r -> 615 | AJ10: =IF(AND(IF(B10=1,AD10>0,AD10<0),IF(C10=1,AE10>0,AE10<0),IF(D10=1,AF10>0,AF10<0),IF(E10=1,AG10>0,AG10<0),IF(F10=1,AH10>0,AH10<0),IF(G10=1,AI10>0,AI10<0)),1,0) -> 0
A11: 6 | B11: =MOD(INT($A11/32),2) -> 0 | C11: =MOD(INT($A11/16),2) -> 0 | D11: =MOD(INT($A11/8),2) -> 0 | E11: =MOD(INT($A11/4),2) -> 1 | F11: =MOD(INT($A11/2),2) -> 1 | G11: =MOD(INT($A11/1),2) -> 0 | H11: =Gap0*(1-Share*B11) -> 14 | I11: =H11*(1-Share*C11) -> 14 | J11: =I11*(1-Share*D11) -> 14 | K11: =J11*(1-Share*E11) -> 7 | L11: =K11*(1-Share*F11) -> 3.5 | M11: =L11*(1-Share*G11) -> 3.5 | N11: =Smax-Val_pt*H11 -> 0 | O11: =Smax-Val_pt*I11 -> 0 | P11: =Smax-Val_pt*J11 -> 0 | Q11: =Smax-Val_pt*K11 -> 70 | R11: =Smax-Val_pt*L11 -> 105 | S11: =Smax-Val_pt*M11 -> 105 | T11: =SUM(B11:G11) -> 2 | U11: =Cash0+SUM(N11:S11)-Cost_r*T11+Credit_M*S11 -> 2290 | V11: =Cash0+SUM(N11:S11)-Cost_r*T11+Credit_10*S11 -> 1240 | W11: =Liq0+N11-Cost_r*B11 -> 620 | X11: =W11+O11-Cost_r*C11 -> 620 | Y11: =X11+P11-Cost_r*D11 -> 620 | Z11: =Y11+Q11-Cost_r*E11 -> 570 | AA11: =Z11+R11-Cost_r*F11 -> 555 | AB11: =AA11+S11-Cost_r*G11 -> 660 | AC11: =MIN(MIN(Liq0-Cost_r*B11,W11-Cost_r*C11,X11-Cost_r*D11,Y11-Cost_r*E11,Z11-Cost_r*F11,AA11-Cost_r*G11,MIN(W11:AB11))-Floor_q,AB11-End_q) -> 100 | AD11: =Val_pt*Share/(1-Share*B11)*(SUM(H11:M11)+Credit_M*M11)-Cost_r -> 510 | AE11: =Val_pt*Share/(1-Share*C11)*(SUM(I11:M11)+Credit_M*M11)-Cost_r -> 440 | AF11: =Val_pt*Share/(1-Share*D11)*(SUM(J11:M11)+Credit_M*M11)-Cost_r -> 370 | AG11: =Val_pt*Share/(1-Share*E11)*(SUM(K11:M11)+Credit_M*M11)-Cost_r -> 720 | AH11: =Val_pt*Share/(1-Share*F11)*(SUM(L11:M11)+Credit_M*M11)-Cost_r -> 650 | AI11: =Val_pt*Share/(1-Share*G11)*(SUM(M11:M11)+Credit_M*M11)-Cost_r -> 247.5 | AJ11: =IF(AND(IF(B11=1,AD11>0,AD11<0),IF(C11=1,AE11>0,AE11<0),IF(D11=1,AF11>0,AF11<0),IF(E11=1,AG11>0,AG11<0),IF(F11=1,AH11>0,AH11<0),IF(G11=1,AI11>0,AI11<0)),1,0) -> 0 | AL11: Each slack is affine in each round, so its smallest value over the box [0, 1]^6 is taken at a corner (Online Appendix 4.B.3): 85 over every plan.
A12: 7 | B12: =MOD(INT($A12/32),2) -> 0 | C12: =MOD(INT($A12/16),2) -> 0 | D12: =MOD(INT($A12/8),2) -> 0 | E12: =MOD(INT($A12/4),2) -> 1 | F12: =MOD(INT($A12/2),2) -> 1 | G12: =MOD(INT($A12/1),2) -> 1 | H12: =Gap0*(1-Share*B12) -> 14 | I12: =H12*(1-Share*C12) -> 14 | J12: =I12*(1-Share*D12) -> 14 | K12: =J12*(1-Share*E12) -> 7 | L12: =K12*(1-Share*F12) -> 3.5 | M12: =L12*(1-Share*G12) -> 1.75 | N12: =Smax-Val_pt*H12 -> 0 | O12: =Smax-Val_pt*I12 -> 0 | P12: =Smax-Val_pt*J12 -> 0 | Q12: =Smax-Val_pt*K12 -> 70 | R12: =Smax-Val_pt*L12 -> 105 | S12: =Smax-Val_pt*M12 -> 122.5 | T12: =SUM(B12:G12) -> 3 | U12: =Cash0+SUM(N12:S12)-Cost_r*T12+Credit_M*S12 -> 2537.5 | V12: =Cash0+SUM(N12:S12)-Cost_r*T12+Credit_10*S12 -> 1312.5 | W12: =Liq0+N12-Cost_r*B12 -> 620 | X12: =W12+O12-Cost_r*C12 -> 620 | Y12: =X12+P12-Cost_r*D12 -> 620 | Z12: =Y12+Q12-Cost_r*E12 -> 570 | AA12: =Z12+R12-Cost_r*F12 -> 555 | AB12: =AA12+S12-Cost_r*G12 -> 557.5 | AC12: =MIN(MIN(Liq0-Cost_r*B12,W12-Cost_r*C12,X12-Cost_r*D12,Y12-Cost_r*E12,Z12-Cost_r*F12,AA12-Cost_r*G12,MIN(W12:AB12))-Floor_q,AB12-End_q) -> 85 | AD12: =Val_pt*Share/(1-Share*B12)*(SUM(H12:M12)+Credit_M*M12)-Cost_r -> 326.25 | AE12: =Val_pt*Share/(1-Share*C12)*(SUM(I12:M12)+Credit_M*M12)-Cost_r -> 256.25 | AF12: =Val_pt*Share/(1-Share*D12)*(SUM(J12:M12)+Credit_M*M12)-Cost_r -> 186.25 | AG12: =Val_pt*Share/(1-Share*E12)*(SUM(K12:M12)+Credit_M*M12)-Cost_r -> 352.5 | AH12: =Val_pt*Share/(1-Share*F12)*(SUM(L12:M12)+Credit_M*M12)-Cost_r -> 282.5 | AI12: =Val_pt*Share/(1-Share*G12)*(SUM(M12:M12)+Credit_M*M12)-Cost_r -> 247.5 | AJ12: =IF(AND(IF(B12=1,AD12>0,AD12<0),IF(C12=1,AE12>0,AE12<0),IF(D12=1,AF12>0,AF12<0),IF(E12=1,AG12>0,AG12<0),IF(F12=1,AH12>0,AH12<0),IF(G12=1,AI12>0,AI12<0)),1,0) -> 0
A13: 8 | B13: =MOD(INT($A13/32),2) -> 0 | C13: =MOD(INT($A13/16),2) -> 0 | D13: =MOD(INT($A13/8),2) -> 1 | E13: =MOD(INT($A13/4),2) -> 0 | F13: =MOD(INT($A13/2),2) -> 0 | G13: =MOD(INT($A13/1),2) -> 0 | H13: =Gap0*(1-Share*B13) -> 14 | I13: =H13*(1-Share*C13) -> 14 | J13: =I13*(1-Share*D13) -> 7 | K13: =J13*(1-Share*E13) -> 7 | L13: =K13*(1-Share*F13) -> 7 | M13: =L13*(1-Share*G13) -> 7 | N13: =Smax-Val_pt*H13 -> 0 | O13: =Smax-Val_pt*I13 -> 0 | P13: =Smax-Val_pt*J13 -> 70 | Q13: =Smax-Val_pt*K13 -> 70 | R13: =Smax-Val_pt*L13 -> 70 | S13: =Smax-Val_pt*M13 -> 70 | T13: =SUM(B13:G13) -> 1 | U13: =Cash0+SUM(N13:S13)-Cost_r*T13+Credit_M*S13 -> 1710 | V13: =Cash0+SUM(N13:S13)-Cost_r*T13+Credit_10*S13 -> 1010 | W13: =Liq0+N13-Cost_r*B13 -> 620 | X13: =W13+O13-Cost_r*C13 -> 620 | Y13: =X13+P13-Cost_r*D13 -> 570 | Z13: =Y13+Q13-Cost_r*E13 -> 640 | AA13: =Z13+R13-Cost_r*F13 -> 710 | AB13: =AA13+S13-Cost_r*G13 -> 780 | AC13: =MIN(MIN(Liq0-Cost_r*B13,W13-Cost_r*C13,X13-Cost_r*D13,Y13-Cost_r*E13,Z13-Cost_r*F13,AA13-Cost_r*G13,MIN(W13:AB13))-Floor_q,AB13-End_q) -> 150 | AD13: =Val_pt*Share/(1-Share*B13)*(SUM(H13:M13)+Credit_M*M13)-Cost_r -> 860 | AE13: =Val_pt*Share/(1-Share*C13)*(SUM(I13:M13)+Credit_M*M13)-Cost_r -> 790 | AF13: =Val_pt*Share/(1-Share*D13)*(SUM(J13:M13)+Credit_M*M13)-Cost_r -> 1560 | AG13: =Val_pt*Share/(1-Share*E13)*(SUM(K13:M13)+Credit_M*M13)-Cost_r -> 685 | AH13: =Val_pt*Share/(1-Share*F13)*(SUM(L13:M13)+Credit_M*M13)-Cost_r -> 650 | AI13: =Val_pt*Share/(1-Share*G13)*(SUM(M13:M13)+Credit_M*M13)-Cost_r -> 615 | AJ13: =IF(AND(IF(B13=1,AD13>0,AD13<0),IF(C13=1,AE13>0,AE13<0),IF(D13=1,AF13>0,AF13<0),IF(E13=1,AG13>0,AG13<0),IF(F13=1,AH13>0,AH13<0),IF(G13=1,AI13>0,AI13<0)),1,0) -> 0
A14: 9 | B14: =MOD(INT($A14/32),2) -> 0 | C14: =MOD(INT($A14/16),2) -> 0 | D14: =MOD(INT($A14/8),2) -> 1 | E14: =MOD(INT($A14/4),2) -> 0 | F14: =MOD(INT($A14/2),2) -> 0 | G14: =MOD(INT($A14/1),2) -> 1 | H14: =Gap0*(1-Share*B14) -> 14 | I14: =H14*(1-Share*C14) -> 14 | J14: =I14*(1-Share*D14) -> 7 | K14: =J14*(1-Share*E14) -> 7 | L14: =K14*(1-Share*F14) -> 7 | M14: =L14*(1-Share*G14) -> 3.5 | N14: =Smax-Val_pt*H14 -> 0 | O14: =Smax-Val_pt*I14 -> 0 | P14: =Smax-Val_pt*J14 -> 70 | Q14: =Smax-Val_pt*K14 -> 70 | R14: =Smax-Val_pt*L14 -> 70 | S14: =Smax-Val_pt*M14 -> 105 | T14: =SUM(B14:G14) -> 2 | U14: =Cash0+SUM(N14:S14)-Cost_r*T14+Credit_M*S14 -> 2325 | V14: =Cash0+SUM(N14:S14)-Cost_r*T14+Credit_10*S14 -> 1275 | W14: =Liq0+N14-Cost_r*B14 -> 620 | X14: =W14+O14-Cost_r*C14 -> 620 | Y14: =X14+P14-Cost_r*D14 -> 570 | Z14: =Y14+Q14-Cost_r*E14 -> 640 | AA14: =Z14+R14-Cost_r*F14 -> 710 | AB14: =AA14+S14-Cost_r*G14 -> 695 | AC14: =MIN(MIN(Liq0-Cost_r*B14,W14-Cost_r*C14,X14-Cost_r*D14,Y14-Cost_r*E14,Z14-Cost_r*F14,AA14-Cost_r*G14,MIN(W14:AB14))-Floor_q,AB14-End_q) -> 150 | AD14: =Val_pt*Share/(1-Share*B14)*(SUM(H14:M14)+Credit_M*M14)-Cost_r -> 492.5 | AE14: =Val_pt*Share/(1-Share*C14)*(SUM(I14:M14)+Credit_M*M14)-Cost_r -> 422.5 | AF14: =Val_pt*Share/(1-Share*D14)*(SUM(J14:M14)+Credit_M*M14)-Cost_r -> 825 | AG14: =Val_pt*Share/(1-Share*E14)*(SUM(K14:M14)+Credit_M*M14)-Cost_r -> 317.5 | AH14: =Val_pt*Share/(1-Share*F14)*(SUM(L14:M14)+Credit_M*M14)-Cost_r -> 282.5 | AI14: =Val_pt*Share/(1-Share*G14)*(SUM(M14:M14)+Credit_M*M14)-Cost_r -> 615 | AJ14: =IF(AND(IF(B14=1,AD14>0,AD14<0),IF(C14=1,AE14>0,AE14<0),IF(D14=1,AF14>0,AF14<0),IF(E14=1,AG14>0,AG14<0),IF(F14=1,AH14>0,AH14<0),IF(G14=1,AI14>0,AI14<0)),1,0) -> 0
A15: 10 | B15: =MOD(INT($A15/32),2) -> 0 | C15: =MOD(INT($A15/16),2) -> 0 | D15: =MOD(INT($A15/8),2) -> 1 | E15: =MOD(INT($A15/4),2) -> 0 | F15: =MOD(INT($A15/2),2) -> 1 | G15: =MOD(INT($A15/1),2) -> 0 | H15: =Gap0*(1-Share*B15) -> 14 | I15: =H15*(1-Share*C15) -> 14 | J15: =I15*(1-Share*D15) -> 7 | K15: =J15*(1-Share*E15) -> 7 | L15: =K15*(1-Share*F15) -> 3.5 | M15: =L15*(1-Share*G15) -> 3.5 | N15: =Smax-Val_pt*H15 -> 0 | O15: =Smax-Val_pt*I15 -> 0 | P15: =Smax-Val_pt*J15 -> 70 | Q15: =Smax-Val_pt*K15 -> 70 | R15: =Smax-Val_pt*L15 -> 105 | S15: =Smax-Val_pt*M15 -> 105 | T15: =SUM(B15:G15) -> 2 | U15: =Cash0+SUM(N15:S15)-Cost_r*T15+Credit_M*S15 -> 2360 | V15: =Cash0+SUM(N15:S15)-Cost_r*T15+Credit_10*S15 -> 1310 | W15: =Liq0+N15-Cost_r*B15 -> 620 | X15: =W15+O15-Cost_r*C15 -> 620 | Y15: =X15+P15-Cost_r*D15 -> 570 | Z15: =Y15+Q15-Cost_r*E15 -> 640 | AA15: =Z15+R15-Cost_r*F15 -> 625 | AB15: =AA15+S15-Cost_r*G15 -> 730 | AC15: =MIN(MIN(Liq0-Cost_r*B15,W15-Cost_r*C15,X15-Cost_r*D15,Y15-Cost_r*E15,Z15-Cost_r*F15,AA15-Cost_r*G15,MIN(W15:AB15))-Floor_q,AB15-End_q) -> 150 | AD15: =Val_pt*Share/(1-Share*B15)*(SUM(H15:M15)+Credit_M*M15)-Cost_r -> 475 | AE15: =Val_pt*Share/(1-Share*C15)*(SUM(I15:M15)+Credit_M*M15)-Cost_r -> 405 | AF15: =Val_pt*Share/(1-Share*D15)*(SUM(J15:M15)+Credit_M*M15)-Cost_r -> 790 | AG15: =Val_pt*Share/(1-Share*E15)*(SUM(K15:M15)+Credit_M*M15)-Cost_r -> 300 | AH15: =Val_pt*Share/(1-Share*F15)*(SUM(L15:M15)+Credit_M*M15)-Cost_r -> 650 | AI15: =Val_pt*Share/(1-Share*G15)*(SUM(M15:M15)+Credit_M*M15)-Cost_r -> 247.5 | AJ15: =IF(AND(IF(B15=1,AD15>0,AD15<0),IF(C15=1,AE15>0,AE15<0),IF(D15=1,AF15>0,AF15<0),IF(E15=1,AG15>0,AG15<0),IF(F15=1,AH15>0,AH15<0),IF(G15=1,AI15>0,AI15<0)),1,0) -> 0
A16: 11 | B16: =MOD(INT($A16/32),2) -> 0 | C16: =MOD(INT($A16/16),2) -> 0 | D16: =MOD(INT($A16/8),2) -> 1 | E16: =MOD(INT($A16/4),2) -> 0 | F16: =MOD(INT($A16/2),2) -> 1 | G16: =MOD(INT($A16/1),2) -> 1 | H16: =Gap0*(1-Share*B16) -> 14 | I16: =H16*(1-Share*C16) -> 14 | J16: =I16*(1-Share*D16) -> 7 | K16: =J16*(1-Share*E16) -> 7 | L16: =K16*(1-Share*F16) -> 3.5 | M16: =L16*(1-Share*G16) -> 1.75 | N16: =Smax-Val_pt*H16 -> 0 | O16: =Smax-Val_pt*I16 -> 0 | P16: =Smax-Val_pt*J16 -> 70 | Q16: =Smax-Val_pt*K16 -> 70 | R16: =Smax-Val_pt*L16 -> 105 | S16: =Smax-Val_pt*M16 -> 122.5 | T16: =SUM(B16:G16) -> 3 | U16: =Cash0+SUM(N16:S16)-Cost_r*T16+Credit_M*S16 -> 2607.5 | V16: =Cash0+SUM(N16:S16)-Cost_r*T16+Credit_10*S16 -> 1382.5 | W16: =Liq0+N16-Cost_r*B16 -> 620 | X16: =W16+O16-Cost_r*C16 -> 620 | Y16: =X16+P16-Cost_r*D16 -> 570 | Z16: =Y16+Q16-Cost_r*E16 -> 640 | AA16: =Z16+R16-Cost_r*F16 -> 625 | AB16: =AA16+S16-Cost_r*G16 -> 627.5 | AC16: =MIN(MIN(Liq0-Cost_r*B16,W16-Cost_r*C16,X16-Cost_r*D16,Y16-Cost_r*E16,Z16-Cost_r*F16,AA16-Cost_r*G16,MIN(W16:AB16))-Floor_q,AB16-End_q) -> 150 | AD16: =Val_pt*Share/(1-Share*B16)*(SUM(H16:M16)+Credit_M*M16)-Cost_r -> 291.25 | AE16: =Val_pt*Share/(1-Share*C16)*(SUM(I16:M16)+Credit_M*M16)-Cost_r -> 221.25 | AF16: =Val_pt*Share/(1-Share*D16)*(SUM(J16:M16)+Credit_M*M16)-Cost_r -> 422.5 | AG16: =Val_pt*Share/(1-Share*E16)*(SUM(K16:M16)+Credit_M*M16)-Cost_r -> 116.25 | AH16: =Val_pt*Share/(1-Share*F16)*(SUM(L16:M16)+Credit_M*M16)-Cost_r -> 282.5 | AI16: =Val_pt*Share/(1-Share*G16)*(SUM(M16:M16)+Credit_M*M16)-Cost_r -> 247.5 | AJ16: =IF(AND(IF(B16=1,AD16>0,AD16<0),IF(C16=1,AE16>0,AE16<0),IF(D16=1,AF16>0,AF16<0),IF(E16=1,AG16>0,AG16<0),IF(F16=1,AH16>0,AH16<0),IF(G16=1,AI16>0,AI16<0)),1,0) -> 0
A17: 12 | B17: =MOD(INT($A17/32),2) -> 0 | C17: =MOD(INT($A17/16),2) -> 0 | D17: =MOD(INT($A17/8),2) -> 1 | E17: =MOD(INT($A17/4),2) -> 1 | F17: =MOD(INT($A17/2),2) -> 0 | G17: =MOD(INT($A17/1),2) -> 0 | H17: =Gap0*(1-Share*B17) -> 14 | I17: =H17*(1-Share*C17) -> 14 | J17: =I17*(1-Share*D17) -> 7 | K17: =J17*(1-Share*E17) -> 3.5 | L17: =K17*(1-Share*F17) -> 3.5 | M17: =L17*(1-Share*G17) -> 3.5 | N17: =Smax-Val_pt*H17 -> 0 | O17: =Smax-Val_pt*I17 -> 0 | P17: =Smax-Val_pt*J17 -> 70 | Q17: =Smax-Val_pt*K17 -> 105 | R17: =Smax-Val_pt*L17 -> 105 | S17: =Smax-Val_pt*M17 -> 105 | T17: =SUM(B17:G17) -> 2 | U17: =Cash0+SUM(N17:S17)-Cost_r*T17+Credit_M*S17 -> 2395 | V17: =Cash0+SUM(N17:S17)-Cost_r*T17+Credit_10*S17 -> 1345 | W17: =Liq0+N17-Cost_r*B17 -> 620 | X17: =W17+O17-Cost_r*C17 -> 620 | Y17: =X17+P17-Cost_r*D17 -> 570 | Z17: =Y17+Q17-Cost_r*E17 -> 555 | AA17: =Z17+R17-Cost_r*F17 -> 660 | AB17: =AA17+S17-Cost_r*G17 -> 765 | AC17: =MIN(MIN(Liq0-Cost_r*B17,W17-Cost_r*C17,X17-Cost_r*D17,Y17-Cost_r*E17,Z17-Cost_r*F17,AA17-Cost_r*G17,MIN(W17:AB17))-Floor_q,AB17-End_q) -> 100 | AD17: =Val_pt*Share/(1-Share*B17)*(SUM(H17:M17)+Credit_M*M17)-Cost_r -> 457.5 | AE17: =Val_pt*Share/(1-Share*C17)*(SUM(I17:M17)+Credit_M*M17)-Cost_r -> 387.5 | AF17: =Val_pt*Share/(1-Share*D17)*(SUM(J17:M17)+Credit_M*M17)-Cost_r -> 755 | AG17: =Val_pt*Share/(1-Share*E17)*(SUM(K17:M17)+Credit_M*M17)-Cost_r -> 685 | AH17: =Val_pt*Share/(1-Share*F17)*(SUM(L17:M17)+Credit_M*M17)-Cost_r -> 265 | AI17: =Val_pt*Share/(1-Share*G17)*(SUM(M17:M17)+Credit_M*M17)-Cost_r -> 247.5 | AJ17: =IF(AND(IF(B17=1,AD17>0,AD17<0),IF(C17=1,AE17>0,AE17<0),IF(D17=1,AF17>0,AF17<0),IF(E17=1,AG17>0,AG17<0),IF(F17=1,AH17>0,AH17<0),IF(G17=1,AI17>0,AI17<0)),1,0) -> 0
A18: 13 | B18: =MOD(INT($A18/32),2) -> 0 | C18: =MOD(INT($A18/16),2) -> 0 | D18: =MOD(INT($A18/8),2) -> 1 | E18: =MOD(INT($A18/4),2) -> 1 | F18: =MOD(INT($A18/2),2) -> 0 | G18: =MOD(INT($A18/1),2) -> 1 | H18: =Gap0*(1-Share*B18) -> 14 | I18: =H18*(1-Share*C18) -> 14 | J18: =I18*(1-Share*D18) -> 7 | K18: =J18*(1-Share*E18) -> 3.5 | L18: =K18*(1-Share*F18) -> 3.5 | M18: =L18*(1-Share*G18) -> 1.75 | N18: =Smax-Val_pt*H18 -> 0 | O18: =Smax-Val_pt*I18 -> 0 | P18: =Smax-Val_pt*J18 -> 70 | Q18: =Smax-Val_pt*K18 -> 105 | R18: =Smax-Val_pt*L18 -> 105 | S18: =Smax-Val_pt*M18 -> 122.5 | T18: =SUM(B18:G18) -> 3 | U18: =Cash0+SUM(N18:S18)-Cost_r*T18+Credit_M*S18 -> 2642.5 | V18: =Cash0+SUM(N18:S18)-Cost_r*T18+Credit_10*S18 -> 1417.5 | W18: =Liq0+N18-Cost_r*B18 -> 620 | X18: =W18+O18-Cost_r*C18 -> 620 | Y18: =X18+P18-Cost_r*D18 -> 570 | Z18: =Y18+Q18-Cost_r*E18 -> 555 | AA18: =Z18+R18-Cost_r*F18 -> 660 | AB18: =AA18+S18-Cost_r*G18 -> 662.5 | AC18: =MIN(MIN(Liq0-Cost_r*B18,W18-Cost_r*C18,X18-Cost_r*D18,Y18-Cost_r*E18,Z18-Cost_r*F18,AA18-Cost_r*G18,MIN(W18:AB18))-Floor_q,AB18-End_q) -> 100 | AD18: =Val_pt*Share/(1-Share*B18)*(SUM(H18:M18)+Credit_M*M18)-Cost_r -> 273.75 | AE18: =Val_pt*Share/(1-Share*C18)*(SUM(I18:M18)+Credit_M*M18)-Cost_r -> 203.75 | AF18: =Val_pt*Share/(1-Share*D18)*(SUM(J18:M18)+Credit_M*M18)-Cost_r -> 387.5 | AG18: =Val_pt*Share/(1-Share*E18)*(SUM(K18:M18)+Credit_M*M18)-Cost_r -> 317.5 | AH18: =Val_pt*Share/(1-Share*F18)*(SUM(L18:M18)+Credit_M*M18)-Cost_r -> 81.25 | AI18: =Val_pt*Share/(1-Share*G18)*(SUM(M18:M18)+Credit_M*M18)-Cost_r -> 247.5 | AJ18: =IF(AND(IF(B18=1,AD18>0,AD18<0),IF(C18=1,AE18>0,AE18<0),IF(D18=1,AF18>0,AF18<0),IF(E18=1,AG18>0,AG18<0),IF(F18=1,AH18>0,AH18<0),IF(G18=1,AI18>0,AI18<0)),1,0) -> 0
A19: 14 | B19: =MOD(INT($A19/32),2) -> 0 | C19: =MOD(INT($A19/16),2) -> 0 | D19: =MOD(INT($A19/8),2) -> 1 | E19: =MOD(INT($A19/4),2) -> 1 | F19: =MOD(INT($A19/2),2) -> 1 | G19: =MOD(INT($A19/1),2) -> 0 | H19: =Gap0*(1-Share*B19) -> 14 | I19: =H19*(1-Share*C19) -> 14 | J19: =I19*(1-Share*D19) -> 7 | K19: =J19*(1-Share*E19) -> 3.5 | L19: =K19*(1-Share*F19) -> 1.75 | M19: =L19*(1-Share*G19) -> 1.75 | N19: =Smax-Val_pt*H19 -> 0 | O19: =Smax-Val_pt*I19 -> 0 | P19: =Smax-Val_pt*J19 -> 70 | Q19: =Smax-Val_pt*K19 -> 105 | R19: =Smax-Val_pt*L19 -> 122.5 | S19: =Smax-Val_pt*M19 -> 122.5 | T19: =SUM(B19:G19) -> 3 | U19: =Cash0+SUM(N19:S19)-Cost_r*T19+Credit_M*S19 -> 2660 | V19: =Cash0+SUM(N19:S19)-Cost_r*T19+Credit_10*S19 -> 1435 | W19: =Liq0+N19-Cost_r*B19 -> 620 | X19: =W19+O19-Cost_r*C19 -> 620 | Y19: =X19+P19-Cost_r*D19 -> 570 | Z19: =Y19+Q19-Cost_r*E19 -> 555 | AA19: =Z19+R19-Cost_r*F19 -> 557.5 | AB19: =AA19+S19-Cost_r*G19 -> 680 | AC19: =MIN(MIN(Liq0-Cost_r*B19,W19-Cost_r*C19,X19-Cost_r*D19,Y19-Cost_r*E19,Z19-Cost_r*F19,AA19-Cost_r*G19,MIN(W19:AB19))-Floor_q,AB19-End_q) -> 85 | AD19: =Val_pt*Share/(1-Share*B19)*(SUM(H19:M19)+Credit_M*M19)-Cost_r -> 265 | AE19: =Val_pt*Share/(1-Share*C19)*(SUM(I19:M19)+Credit_M*M19)-Cost_r -> 195 | AF19: =Val_pt*Share/(1-Share*D19)*(SUM(J19:M19)+Credit_M*M19)-Cost_r -> 370 | AG19: =Val_pt*Share/(1-Share*E19)*(SUM(K19:M19)+Credit_M*M19)-Cost_r -> 300 | AH19: =Val_pt*Share/(1-Share*F19)*(SUM(L19:M19)+Credit_M*M19)-Cost_r -> 265 | AI19: =Val_pt*Share/(1-Share*G19)*(SUM(M19:M19)+Credit_M*M19)-Cost_r -> 63.75 | AJ19: =IF(AND(IF(B19=1,AD19>0,AD19<0),IF(C19=1,AE19>0,AE19<0),IF(D19=1,AF19>0,AF19<0),IF(E19=1,AG19>0,AG19<0),IF(F19=1,AH19>0,AH19<0),IF(G19=1,AI19>0,AI19<0)),1,0) -> 0
A20: 15 | B20: =MOD(INT($A20/32),2) -> 0 | C20: =MOD(INT($A20/16),2) -> 0 | D20: =MOD(INT($A20/8),2) -> 1 | E20: =MOD(INT($A20/4),2) -> 1 | F20: =MOD(INT($A20/2),2) -> 1 | G20: =MOD(INT($A20/1),2) -> 1 | H20: =Gap0*(1-Share*B20) -> 14 | I20: =H20*(1-Share*C20) -> 14 | J20: =I20*(1-Share*D20) -> 7 | K20: =J20*(1-Share*E20) -> 3.5 | L20: =K20*(1-Share*F20) -> 1.75 | M20: =L20*(1-Share*G20) -> 0.875 | N20: =Smax-Val_pt*H20 -> 0 | O20: =Smax-Val_pt*I20 -> 0 | P20: =Smax-Val_pt*J20 -> 70 | Q20: =Smax-Val_pt*K20 -> 105 | R20: =Smax-Val_pt*L20 -> 122.5 | S20: =Smax-Val_pt*M20 -> 131.25 | T20: =SUM(B20:G20) -> 4 | U20: =Cash0+SUM(N20:S20)-Cost_r*T20+Credit_M*S20 -> 2723.75 | V20: =Cash0+SUM(N20:S20)-Cost_r*T20+Credit_10*S20 -> 1411.25 | W20: =Liq0+N20-Cost_r*B20 -> 620 | X20: =W20+O20-Cost_r*C20 -> 620 | Y20: =X20+P20-Cost_r*D20 -> 570 | Z20: =Y20+Q20-Cost_r*E20 -> 555 | AA20: =Z20+R20-Cost_r*F20 -> 557.5 | AB20: =AA20+S20-Cost_r*G20 -> 568.75 | AC20: =MIN(MIN(Liq0-Cost_r*B20,W20-Cost_r*C20,X20-Cost_r*D20,Y20-Cost_r*E20,Z20-Cost_r*F20,AA20-Cost_r*G20,MIN(W20:AB20))-Floor_q,AB20-End_q) -> 85 | AD20: =Val_pt*Share/(1-Share*B20)*(SUM(H20:M20)+Credit_M*M20)-Cost_r -> 173.125 | AE20: =Val_pt*Share/(1-Share*C20)*(SUM(I20:M20)+Credit_M*M20)-Cost_r -> 103.125 | AF20: =Val_pt*Share/(1-Share*D20)*(SUM(J20:M20)+Credit_M*M20)-Cost_r -> 186.25 | AG20: =Val_pt*Share/(1-Share*E20)*(SUM(K20:M20)+Credit_M*M20)-Cost_r -> 116.25 | AH20: =Val_pt*Share/(1-Share*F20)*(SUM(L20:M20)+Credit_M*M20)-Cost_r -> 81.25 | AI20: =Val_pt*Share/(1-Share*G20)*(SUM(M20:M20)+Credit_M*M20)-Cost_r -> 63.75 | AJ20: =IF(AND(IF(B20=1,AD20>0,AD20<0),IF(C20=1,AE20>0,AE20<0),IF(D20=1,AF20>0,AF20<0),IF(E20=1,AG20>0,AG20<0),IF(F20=1,AH20>0,AH20<0),IF(G20=1,AI20>0,AI20<0)),1,0) -> 0
A21: 16 | B21: =MOD(INT($A21/32),2) -> 0 | C21: =MOD(INT($A21/16),2) -> 1 | D21: =MOD(INT($A21/8),2) -> 0 | E21: =MOD(INT($A21/4),2) -> 0 | F21: =MOD(INT($A21/2),2) -> 0 | G21: =MOD(INT($A21/1),2) -> 0 | H21: =Gap0*(1-Share*B21) -> 14 | I21: =H21*(1-Share*C21) -> 7 | J21: =I21*(1-Share*D21) -> 7 | K21: =J21*(1-Share*E21) -> 7 | L21: =K21*(1-Share*F21) -> 7 | M21: =L21*(1-Share*G21) -> 7 | N21: =Smax-Val_pt*H21 -> 0 | O21: =Smax-Val_pt*I21 -> 70 | P21: =Smax-Val_pt*J21 -> 70 | Q21: =Smax-Val_pt*K21 -> 70 | R21: =Smax-Val_pt*L21 -> 70 | S21: =Smax-Val_pt*M21 -> 70 | T21: =SUM(B21:G21) -> 1 | U21: =Cash0+SUM(N21:S21)-Cost_r*T21+Credit_M*S21 -> 1780 | V21: =Cash0+SUM(N21:S21)-Cost_r*T21+Credit_10*S21 -> 1080 | W21: =Liq0+N21-Cost_r*B21 -> 620 | X21: =W21+O21-Cost_r*C21 -> 570 | Y21: =X21+P21-Cost_r*D21 -> 640 | Z21: =Y21+Q21-Cost_r*E21 -> 710 | AA21: =Z21+R21-Cost_r*F21 -> 780 | AB21: =AA21+S21-Cost_r*G21 -> 850 | AC21: =MIN(MIN(Liq0-Cost_r*B21,W21-Cost_r*C21,X21-Cost_r*D21,Y21-Cost_r*E21,Z21-Cost_r*F21,AA21-Cost_r*G21,MIN(W21:AB21))-Floor_q,AB21-End_q) -> 150 | AD21: =Val_pt*Share/(1-Share*B21)*(SUM(H21:M21)+Credit_M*M21)-Cost_r -> 825 | AE21: =Val_pt*Share/(1-Share*C21)*(SUM(I21:M21)+Credit_M*M21)-Cost_r -> 1630 | AF21: =Val_pt*Share/(1-Share*D21)*(SUM(J21:M21)+Credit_M*M21)-Cost_r -> 720 | AG21: =Val_pt*Share/(1-Share*E21)*(SUM(K21:M21)+Credit_M*M21)-Cost_r -> 685 | AH21: =Val_pt*Share/(1-Share*F21)*(SUM(L21:M21)+Credit_M*M21)-Cost_r -> 650 | AI21: =Val_pt*Share/(1-Share*G21)*(SUM(M21:M21)+Credit_M*M21)-Cost_r -> 615 | AJ21: =IF(AND(IF(B21=1,AD21>0,AD21<0),IF(C21=1,AE21>0,AE21<0),IF(D21=1,AF21>0,AF21<0),IF(E21=1,AG21>0,AG21<0),IF(F21=1,AH21>0,AH21<0),IF(G21=1,AI21>0,AI21<0)),1,0) -> 0
A22: 17 | B22: =MOD(INT($A22/32),2) -> 0 | C22: =MOD(INT($A22/16),2) -> 1 | D22: =MOD(INT($A22/8),2) -> 0 | E22: =MOD(INT($A22/4),2) -> 0 | F22: =MOD(INT($A22/2),2) -> 0 | G22: =MOD(INT($A22/1),2) -> 1 | H22: =Gap0*(1-Share*B22) -> 14 | I22: =H22*(1-Share*C22) -> 7 | J22: =I22*(1-Share*D22) -> 7 | K22: =J22*(1-Share*E22) -> 7 | L22: =K22*(1-Share*F22) -> 7 | M22: =L22*(1-Share*G22) -> 3.5 | N22: =Smax-Val_pt*H22 -> 0 | O22: =Smax-Val_pt*I22 -> 70 | P22: =Smax-Val_pt*J22 -> 70 | Q22: =Smax-Val_pt*K22 -> 70 | R22: =Smax-Val_pt*L22 -> 70 | S22: =Smax-Val_pt*M22 -> 105 | T22: =SUM(B22:G22) -> 2 | U22: =Cash0+SUM(N22:S22)-Cost_r*T22+Credit_M*S22 -> 2395 | V22: =Cash0+SUM(N22:S22)-Cost_r*T22+Credit_10*S22 -> 1345 | W22: =Liq0+N22-Cost_r*B22 -> 620 | X22: =W22+O22-Cost_r*C22 -> 570 | Y22: =X22+P22-Cost_r*D22 -> 640 | Z22: =Y22+Q22-Cost_r*E22 -> 710 | AA22: =Z22+R22-Cost_r*F22 -> 780 | AB22: =AA22+S22-Cost_r*G22 -> 765 | AC22: =MIN(MIN(Liq0-Cost_r*B22,W22-Cost_r*C22,X22-Cost_r*D22,Y22-Cost_r*E22,Z22-Cost_r*F22,AA22-Cost_r*G22,MIN(W22:AB22))-Floor_q,AB22-End_q) -> 150 | AD22: =Val_pt*Share/(1-Share*B22)*(SUM(H22:M22)+Credit_M*M22)-Cost_r -> 457.5 | AE22: =Val_pt*Share/(1-Share*C22)*(SUM(I22:M22)+Credit_M*M22)-Cost_r -> 895 | AF22: =Val_pt*Share/(1-Share*D22)*(SUM(J22:M22)+Credit_M*M22)-Cost_r -> 352.5 | AG22: =Val_pt*Share/(1-Share*E22)*(SUM(K22:M22)+Credit_M*M22)-Cost_r -> 317.5 | AH22: =Val_pt*Share/(1-Share*F22)*(SUM(L22:M22)+Credit_M*M22)-Cost_r -> 282.5 | AI22: =Val_pt*Share/(1-Share*G22)*(SUM(M22:M22)+Credit_M*M22)-Cost_r -> 615 | AJ22: =IF(AND(IF(B22=1,AD22>0,AD22<0),IF(C22=1,AE22>0,AE22<0),IF(D22=1,AF22>0,AF22<0),IF(E22=1,AG22>0,AG22<0),IF(F22=1,AH22>0,AH22<0),IF(G22=1,AI22>0,AI22<0)),1,0) -> 0
A23: 18 | B23: =MOD(INT($A23/32),2) -> 0 | C23: =MOD(INT($A23/16),2) -> 1 | D23: =MOD(INT($A23/8),2) -> 0 | E23: =MOD(INT($A23/4),2) -> 0 | F23: =MOD(INT($A23/2),2) -> 1 | G23: =MOD(INT($A23/1),2) -> 0 | H23: =Gap0*(1-Share*B23) -> 14 | I23: =H23*(1-Share*C23) -> 7 | J23: =I23*(1-Share*D23) -> 7 | K23: =J23*(1-Share*E23) -> 7 | L23: =K23*(1-Share*F23) -> 3.5 | M23: =L23*(1-Share*G23) -> 3.5 | N23: =Smax-Val_pt*H23 -> 0 | O23: =Smax-Val_pt*I23 -> 70 | P23: =Smax-Val_pt*J23 -> 70 | Q23: =Smax-Val_pt*K23 -> 70 | R23: =Smax-Val_pt*L23 -> 105 | S23: =Smax-Val_pt*M23 -> 105 | T23: =SUM(B23:G23) -> 2 | U23: =Cash0+SUM(N23:S23)-Cost_r*T23+Credit_M*S23 -> 2430 | V23: =Cash0+SUM(N23:S23)-Cost_r*T23+Credit_10*S23 -> 1380 | W23: =Liq0+N23-Cost_r*B23 -> 620 | X23: =W23+O23-Cost_r*C23 -> 570 | Y23: =X23+P23-Cost_r*D23 -> 640 | Z23: =Y23+Q23-Cost_r*E23 -> 710 | AA23: =Z23+R23-Cost_r*F23 -> 695 | AB23: =AA23+S23-Cost_r*G23 -> 800 | AC23: =MIN(MIN(Liq0-Cost_r*B23,W23-Cost_r*C23,X23-Cost_r*D23,Y23-Cost_r*E23,Z23-Cost_r*F23,AA23-Cost_r*G23,MIN(W23:AB23))-Floor_q,AB23-End_q) -> 150 | AD23: =Val_pt*Share/(1-Share*B23)*(SUM(H23:M23)+Credit_M*M23)-Cost_r -> 440 | AE23: =Val_pt*Share/(1-Share*C23)*(SUM(I23:M23)+Credit_M*M23)-Cost_r -> 860 | AF23: =Val_pt*Share/(1-Share*D23)*(SUM(J23:M23)+Credit_M*M23)-Cost_r -> 335 | AG23: =Val_pt*Share/(1-Share*E23)*(SUM(K23:M23)+Credit_M*M23)-Cost_r -> 300 | AH23: =Val_pt*Share/(1-Share*F23)*(SUM(L23:M23)+Credit_M*M23)-Cost_r -> 650 | AI23: =Val_pt*Share/(1-Share*G23)*(SUM(M23:M23)+Credit_M*M23)-Cost_r -> 247.5 | AJ23: =IF(AND(IF(B23=1,AD23>0,AD23<0),IF(C23=1,AE23>0,AE23<0),IF(D23=1,AF23>0,AF23<0),IF(E23=1,AG23>0,AG23<0),IF(F23=1,AH23>0,AH23<0),IF(G23=1,AI23>0,AI23<0)),1,0) -> 0
... A68: 63 | B68: =MOD(INT($A68/32),2) -> 1 | C68: =MOD(INT($A68/16),2) -> 1 | D68: =MOD(INT($A68/8),2) -> 1 | E68: =MOD(INT($A68/4),2) -> 1 | F68: =MOD(INT($A68/2),2) -> 1 | G68: =MOD(INT($A68/1),2) -> 1 | H68: =Gap0*(1-Share*B68) -> 7 | I68: =H68*(1-Share*C68) -> 3.5 | J68: =I68*(1-Share*D68) -> 1.75 | K68: =J68*(1-Share*E68) -> 0.875 | L68: =K68*(1-Share*F68) -> 0.4375 | M68: =L68*(1-Share*G68) -> 0.21875 | N68: =Smax-Val_pt*H68 -> 70 | O68: =Smax-Val_pt*I68 -> 105 | P68: =Smax-Val_pt*J68 -> 122.5 | Q68: =Smax-Val_pt*K68 -> 131.25 | R68: =Smax-Val_pt*L68 -> 135.625 | S68: =Smax-Val_pt*M68 -> 137.8125 | T68: =SUM(B68:G68) -> 6 | U68: =Cash0+SUM(N68:S68)-Cost_r*T68+Credit_M*S68 -> 2888.4375 | V68: =Cash0+SUM(N68:S68)-Cost_r*T68+Credit_10*S68 -> 1510.3125 | W68: =Liq0+N68-Cost_r*B68 -> 570 | X68: =W68+O68-Cost_r*C68 -> 555 | Y68: =X68+P68-Cost_r*D68 -> 557.5 | Z68: =Y68+Q68-Cost_r*E68 -> 568.75 | AA68: =Z68+R68-Cost_r*F68 -> 584.375 | AB68: =AA68+S68-Cost_r*G68 -> 602.1875 | AC68: =MIN(MIN(Liq0-Cost_r*B68,W68-Cost_r*C68,X68-Cost_r*D68,Y68-Cost_r*E68,Z68-Cost_r*F68,AA68-Cost_r*G68,MIN(W68:AB68))-Floor_q,AB68-End_q) -> 85 | AD68: =Val_pt*Share/(1-Share*B68)*(SUM(H68:M68)+Credit_M*M68)-Cost_r -> 61.5625 | AE68: =Val_pt*Share/(1-Share*C68)*(SUM(I68:M68)+Credit_M*M68)-Cost_r -> -8.4375 | AF68: =Val_pt*Share/(1-Share*D68)*(SUM(J68:M68)+Credit_M*M68)-Cost_r -> -43.4375 | AG68: =Val_pt*Share/(1-Share*E68)*(SUM(K68:M68)+Credit_M*M68)-Cost_r -> -60.9375 | AH68: =Val_pt*Share/(1-Share*F68)*(SUM(L68:M68)+Credit_M*M68)-Cost_r -> -69.6875 | AI68: =Val_pt*Share/(1-Share*G68)*(SUM(M68:M68)+Credit_M*M68)-Cost_r -> -74.0625 | AJ68: =IF(AND(IF(B68=1,AD68>0,AD68<0),IF(C68=1,AE68>0,AE68<0),IF(D68=1,AF68>0,AF68<0),IF(E68=1,AG68>0,AG68<0),IF(F68=1,AH68>0,AH68<0),IF(G68=1,AI68>0,AI68<0)),1,0) -> 0

Sheet Face
A1: Explore: the face where only years 4 and 5 vary (AXIOM Lab 2.4, step 1; Figure 4.1(a))
A2: Years 1-3 whole, none in year 6, x of a year-4 round and y of a year-5 round: V = a + b x + c y + d x y, read from the four corners on the Schedules sheet.
A3: Coefficient | B3: Value | C3: Reading
A4: a = V(0, 0), years 1–3 | B4: =INDEX(Schedules!$U$5:$U$68,57) -> 2905 | C4: 2,905
A5: b = V(1, 0) - a | B5: =INDEX(Schedules!$U$5:$U$68,61)-B4 -> 81.25 | C5: 81.25
A6: c = V(0, 1) - a | B6: =INDEX(Schedules!$U$5:$U$68,59)-B4 -> 72.5 | C6: 72.50
A7: d = V(1, 1) - V(1, 0) - V(0, 1) + a | B7: =INDEX(Schedules!$U$5:$U$68,63)-INDEX(Schedules!$U$5:$U$68,61)-INDEX(Schedules!$U$5:$U$68,59)+B4 -> -96.25 | C7: -96.25
A9: Corner (x, y) | B9: x | C9: y | D9: V | E9: Marginal value of x | F9: Marginal value of y | G9: Verdict
A10: years 1–3 | B10: 0 | C10: 0 | D10: =$B$4+$B$5*B10+$B$6*C10+$B$7*B10*C10 -> 2905 | E10: =$B$5+$B$7*C10 -> 81.25 | F10: =$B$6+$B$7*B10 -> 72.5 | G10: =IF(AND(IF(B10=1,E10>0,E10<0),IF(C10=1,F10>0,F10<0)),"strict local maximum","not a local maximum") -> not a local maximum
A11: years 1–4 | B11: 1 | C11: 0 | D11: =$B$4+$B$5*B11+$B$6*C11+$B$7*B11*C11 -> 2986.25 | E11: =$B$5+$B$7*C11 -> 81.25 | F11: =$B$6+$B$7*B11 -> -23.75 | G11: =IF(AND(IF(B11=1,E11>0,E11<0),IF(C11=1,F11>0,F11<0)),"strict local maximum","not a local maximum") -> strict local maximum
A12: years 1–3 and 5 | B12: 0 | C12: 1 | D12: =$B$4+$B$5*B12+$B$6*C12+$B$7*B12*C12 -> 2977.5 | E12: =$B$5+$B$7*C12 -> -15 | F12: =$B$6+$B$7*B12 -> 72.5 | G12: =IF(AND(IF(B12=1,E12>0,E12<0),IF(C12=1,F12>0,F12<0)),"strict local maximum","not a local maximum") -> strict local maximum
A13: years 1–5 | B13: 1 | C13: 1 | D13: =$B$4+$B$5*B13+$B$6*C13+$B$7*B13*C13 -> 2962.5 | E13: =$B$5+$B$7*C13 -> -15 | F13: =$B$6+$B$7*B13 -> -23.75 | G13: =IF(AND(IF(B13=1,E13>0,E13<0),IF(C13=1,F13>0,F13<0)),"strict local maximum","not a local maximum") -> not a local maximum
A16: The stationary plan inside the face | B16: Value | C16: Reading
A17: x* = -c / d (year-4 round) | B17: =-B6/B7 -> 0.75324675 | C17: 0.75
A18: y* = -b / d (year-5 round) | B18: =-B5/B7 -> 0.84415584 | C18: 0.84
A19: V* on the face | B19: =B4+B5*B17+B6*B18+B7*B17*B18 -> 2966.2013 | C19: 2,966.20
A20: V* from the model (Plans, the saddle's row) | B20: =Plans!U9 -> 2966.2013
A21: Hessian on the face, off the diagonal (the diagonal is 0) | B21: =B7 -> -96.25 | C21: the same at every point
A22: Its eigenvalue along (1, 1) | B22: =-ABS(B21) -> -96.25 | C22: value falls
A23: Its eigenvalue along (1, -1) | B23: =ABS(B21) -> 96.25 | C23: value rises: a saddle
A25: t (fraction of a round) | B25: Move t from year 5 to year 4: V - V* | C25: -d t^2 | D25: Add t to both rounds: V - V* | E25: d t^2
A26: 0.05 | B26: =$B$4+$B$5*($B$17+A26)+$B$6*($B$18-A26)+$B$7*($B$17+A26)*($B$18-A26)-$B$19 -> 0.240625 | C26: =-$B$7*A26^2 -> 0.240625 | D26: =$B$4+$B$5*($B$17+A26)+$B$6*($B$18+A26)+$B$7*($B$17+A26)*($B$18+A26)-$B$19 -> -0.240625 | E26: =$B$7*A26^2 -> -0.240625
A27: 0.1 | B27: =$B$4+$B$5*($B$17+A27)+$B$6*($B$18-A27)+$B$7*($B$17+A27)*($B$18-A27)-$B$19 -> 0.9625 | C27: =-$B$7*A27^2 -> 0.9625 | D27: =$B$4+$B$5*($B$17+A27)+$B$6*($B$18+A27)+$B$7*($B$17+A27)*($B$18+A27)-$B$19 -> -0.9625 | E27: =$B$7*A27^2 -> -0.9625
A28: 0.15 | B28: =$B$4+$B$5*($B$17+A28)+$B$6*($B$18-A28)+$B$7*($B$17+A28)*($B$18-A28)-$B$19 -> 2.165625 | C28: =-$B$7*A28^2 -> 2.165625 | D28: =$B$4+$B$5*($B$17+A28)+$B$6*($B$18+A28)+$B$7*($B$17+A28)*($B$18+A28)-$B$19 -> -2.165625 | E28: =$B$7*A28^2 -> -2.165625
A30: The basin boundary: y - y* = x - x*. Plans above it climb to years 1-3 and 5, plans below it to years 1-4. A tenth of a round moved from year 5 to year 4 adds about $1 million.
A32: V on the face: y down, x across | B32: x = 0.0 | C32: x = 0.1 | D32: x = 0.2 | E32: x = 0.3 | F32: x = 0.4 | G32: x = 0.5 | H32: x = 0.6 | I32: x = 0.7 | J32: x = 0.8 | K32: x = 0.9 | L32: x = 1.0
A33: 0 | B33: =$B$4+$B$5*0+$B$6*$A33+$B$7*0*$A33 -> 2905 | C33: =$B$4+$B$5*0.1+$B$6*$A33+$B$7*0.1*$A33 -> 2913.125 | D33: =$B$4+$B$5*0.2+$B$6*$A33+$B$7*0.2*$A33 -> 2921.25 | E33: =$B$4+$B$5*0.3+$B$6*$A33+$B$7*0.3*$A33 -> 2929.375 | F33: =$B$4+$B$5*0.4+$B$6*$A33+$B$7*0.4*$A33 -> 2937.5 | G33: =$B$4+$B$5*0.5+$B$6*$A33+$B$7*0.5*$A33 -> 2945.625 | H33: =$B$4+$B$5*0.6+$B$6*$A33+$B$7*0.6*$A33 -> 2953.75 | I33: =$B$4+$B$5*0.7+$B$6*$A33+$B$7*0.7*$A33 -> 2961.875 | J33: =$B$4+$B$5*0.8+$B$6*$A33+$B$7*0.8*$A33 -> 2970 | K33: =$B$4+$B$5*0.9+$B$6*$A33+$B$7*0.9*$A33 -> 2978.125 | L33: =$B$4+$B$5*1+$B$6*$A33+$B$7*1*$A33 -> 2986.25
A34: 0.1 | B34: =$B$4+$B$5*0+$B$6*$A34+$B$7*0*$A34 -> 2912.25 | C34: =$B$4+$B$5*0.1+$B$6*$A34+$B$7*0.1*$A34 -> 2919.4125 | D34: =$B$4+$B$5*0.2+$B$6*$A34+$B$7*0.2*$A34 -> 2926.575 | E34: =$B$4+$B$5*0.3+$B$6*$A34+$B$7*0.3*$A34 -> 2933.7375 | F34: =$B$4+$B$5*0.4+$B$6*$A34+$B$7*0.4*$A34 -> 2940.9 | G34: =$B$4+$B$5*0.5+$B$6*$A34+$B$7*0.5*$A34 -> 2948.0625 | H34: =$B$4+$B$5*0.6+$B$6*$A34+$B$7*0.6*$A34 -> 2955.225 | I34: =$B$4+$B$5*0.7+$B$6*$A34+$B$7*0.7*$A34 -> 2962.3875 | J34: =$B$4+$B$5*0.8+$B$6*$A34+$B$7*0.8*$A34 -> 2969.55 | K34: =$B$4+$B$5*0.9+$B$6*$A34+$B$7*0.9*$A34 -> 2976.7125 | L34: =$B$4+$B$5*1+$B$6*$A34+$B$7*1*$A34 -> 2983.875
A35: 0.2 | B35: =$B$4+$B$5*0+$B$6*$A35+$B$7*0*$A35 -> 2919.5 | C35: =$B$4+$B$5*0.1+$B$6*$A35+$B$7*0.1*$A35 -> 2925.7 | D35: =$B$4+$B$5*0.2+$B$6*$A35+$B$7*0.2*$A35 -> 2931.9 | E35: =$B$4+$B$5*0.3+$B$6*$A35+$B$7*0.3*$A35 -> 2938.1 | F35: =$B$4+$B$5*0.4+$B$6*$A35+$B$7*0.4*$A35 -> 2944.3 | G35: =$B$4+$B$5*0.5+$B$6*$A35+$B$7*0.5*$A35 -> 2950.5 | H35: =$B$4+$B$5*0.6+$B$6*$A35+$B$7*0.6*$A35 -> 2956.7 | I35: =$B$4+$B$5*0.7+$B$6*$A35+$B$7*0.7*$A35 -> 2962.9 | J35: =$B$4+$B$5*0.8+$B$6*$A35+$B$7*0.8*$A35 -> 2969.1 | K35: =$B$4+$B$5*0.9+$B$6*$A35+$B$7*0.9*$A35 -> 2975.3 | L35: =$B$4+$B$5*1+$B$6*$A35+$B$7*1*$A35 -> 2981.5
A36: 0.3 | B36: =$B$4+$B$5*0+$B$6*$A36+$B$7*0*$A36 -> 2926.75 | C36: =$B$4+$B$5*0.1+$B$6*$A36+$B$7*0.1*$A36 -> 2931.9875 | D36: =$B$4+$B$5*0.2+$B$6*$A36+$B$7*0.2*$A36 -> 2937.225 | E36: =$B$4+$B$5*0.3+$B$6*$A36+$B$7*0.3*$A36 -> 2942.4625 | F36: =$B$4+$B$5*0.4+$B$6*$A36+$B$7*0.4*$A36 -> 2947.7 | G36: =$B$4+$B$5*0.5+$B$6*$A36+$B$7*0.5*$A36 -> 2952.9375 | H36: =$B$4+$B$5*0.6+$B$6*$A36+$B$7*0.6*$A36 -> 2958.175 | I36: =$B$4+$B$5*0.7+$B$6*$A36+$B$7*0.7*$A36 -> 2963.4125 | J36: =$B$4+$B$5*0.8+$B$6*$A36+$B$7*0.8*$A36 -> 2968.65 | K36: =$B$4+$B$5*0.9+$B$6*$A36+$B$7*0.9*$A36 -> 2973.8875 | L36: =$B$4+$B$5*1+$B$6*$A36+$B$7*1*$A36 -> 2979.125
A37: 0.4 | B37: =$B$4+$B$5*0+$B$6*$A37+$B$7*0*$A37 -> 2934 | C37: =$B$4+$B$5*0.1+$B$6*$A37+$B$7*0.1*$A37 -> 2938.275 | D37: =$B$4+$B$5*0.2+$B$6*$A37+$B$7*0.2*$A37 -> 2942.55 | E37: =$B$4+$B$5*0.3+$B$6*$A37+$B$7*0.3*$A37 -> 2946.825 | F37: =$B$4+$B$5*0.4+$B$6*$A37+$B$7*0.4*$A37 -> 2951.1 | G37: =$B$4+$B$5*0.5+$B$6*$A37+$B$7*0.5*$A37 -> 2955.375 | H37: =$B$4+$B$5*0.6+$B$6*$A37+$B$7*0.6*$A37 -> 2959.65 | I37: =$B$4+$B$5*0.7+$B$6*$A37+$B$7*0.7*$A37 -> 2963.925 | J37: =$B$4+$B$5*0.8+$B$6*$A37+$B$7*0.8*$A37 -> 2968.2 | K37: =$B$4+$B$5*0.9+$B$6*$A37+$B$7*0.9*$A37 -> 2972.475 | L37: =$B$4+$B$5*1+$B$6*$A37+$B$7*1*$A37 -> 2976.75
A38: 0.5 | B38: =$B$4+$B$5*0+$B$6*$A38+$B$7*0*$A38 -> 2941.25 | C38: =$B$4+$B$5*0.1+$B$6*$A38+$B$7*0.1*$A38 -> 2944.5625 | D38: =$B$4+$B$5*0.2+$B$6*$A38+$B$7*0.2*$A38 -> 2947.875 | E38: =$B$4+$B$5*0.3+$B$6*$A38+$B$7*0.3*$A38 -> 2951.1875 | F38: =$B$4+$B$5*0.4+$B$6*$A38+$B$7*0.4*$A38 -> 2954.5 | G38: =$B$4+$B$5*0.5+$B$6*$A38+$B$7*0.5*$A38 -> 2957.8125 | H38: =$B$4+$B$5*0.6+$B$6*$A38+$B$7*0.6*$A38 -> 2961.125 | I38: =$B$4+$B$5*0.7+$B$6*$A38+$B$7*0.7*$A38 -> 2964.4375 | J38: =$B$4+$B$5*0.8+$B$6*$A38+$B$7*0.8*$A38 -> 2967.75 | K38: =$B$4+$B$5*0.9+$B$6*$A38+$B$7*0.9*$A38 -> 2971.0625 | L38: =$B$4+$B$5*1+$B$6*$A38+$B$7*1*$A38 -> 2974.375
A39: 0.6 | B39: =$B$4+$B$5*0+$B$6*$A39+$B$7*0*$A39 -> 2948.5 | C39: =$B$4+$B$5*0.1+$B$6*$A39+$B$7*0.1*$A39 -> 2950.85 | D39: =$B$4+$B$5*0.2+$B$6*$A39+$B$7*0.2*$A39 -> 2953.2 | E39: =$B$4+$B$5*0.3+$B$6*$A39+$B$7*0.3*$A39 -> 2955.55 | F39: =$B$4+$B$5*0.4+$B$6*$A39+$B$7*0.4*$A39 -> 2957.9 | G39: =$B$4+$B$5*0.5+$B$6*$A39+$B$7*0.5*$A39 -> 2960.25 | H39: =$B$4+$B$5*0.6+$B$6*$A39+$B$7*0.6*$A39 -> 2962.6 | I39: =$B$4+$B$5*0.7+$B$6*$A39+$B$7*0.7*$A39 -> 2964.95 | J39: =$B$4+$B$5*0.8+$B$6*$A39+$B$7*0.8*$A39 -> 2967.3 | K39: =$B$4+$B$5*0.9+$B$6*$A39+$B$7*0.9*$A39 -> 2969.65 | L39: =$B$4+$B$5*1+$B$6*$A39+$B$7*1*$A39 -> 2972
A40: 0.7 | B40: =$B$4+$B$5*0+$B$6*$A40+$B$7*0*$A40 -> 2955.75 | C40: =$B$4+$B$5*0.1+$B$6*$A40+$B$7*0.1*$A40 -> 2957.1375 | D40: =$B$4+$B$5*0.2+$B$6*$A40+$B$7*0.2*$A40 -> 2958.525 | E40: =$B$4+$B$5*0.3+$B$6*$A40+$B$7*0.3*$A40 -> 2959.9125 | F40: =$B$4+$B$5*0.4+$B$6*$A40+$B$7*0.4*$A40 -> 2961.3 | G40: =$B$4+$B$5*0.5+$B$6*$A40+$B$7*0.5*$A40 -> 2962.6875 | H40: =$B$4+$B$5*0.6+$B$6*$A40+$B$7*0.6*$A40 -> 2964.075 | I40: =$B$4+$B$5*0.7+$B$6*$A40+$B$7*0.7*$A40 -> 2965.4625 | J40: =$B$4+$B$5*0.8+$B$6*$A40+$B$7*0.8*$A40 -> 2966.85 | K40: =$B$4+$B$5*0.9+$B$6*$A40+$B$7*0.9*$A40 -> 2968.2375 | L40: =$B$4+$B$5*1+$B$6*$A40+$B$7*1*$A40 -> 2969.625
A41: 0.8 | B41: =$B$4+$B$5*0+$B$6*$A41+$B$7*0*$A41 -> 2963 | C41: =$B$4+$B$5*0.1+$B$6*$A41+$B$7*0.1*$A41 -> 2963.425 | D41: =$B$4+$B$5*0.2+$B$6*$A41+$B$7*0.2*$A41 -> 2963.85 | E41: =$B$4+$B$5*0.3+$B$6*$A41+$B$7*0.3*$A41 -> 2964.275 | F41: =$B$4+$B$5*0.4+$B$6*$A41+$B$7*0.4*$A41 -> 2964.7 | G41: =$B$4+$B$5*0.5+$B$6*$A41+$B$7*0.5*$A41 -> 2965.125 | H41: =$B$4+$B$5*0.6+$B$6*$A41+$B$7*0.6*$A41 -> 2965.55 | I41: =$B$4+$B$5*0.7+$B$6*$A41+$B$7*0.7*$A41 -> 2965.975 | J41: =$B$4+$B$5*0.8+$B$6*$A41+$B$7*0.8*$A41 -> 2966.4 | K41: =$B$4+$B$5*0.9+$B$6*$A41+$B$7*0.9*$A41 -> 2966.825 | L41: =$B$4+$B$5*1+$B$6*$A41+$B$7*1*$A41 -> 2967.25
A42: 0.9 | B42: =$B$4+$B$5*0+$B$6*$A42+$B$7*0*$A42 -> 2970.25 | C42: =$B$4+$B$5*0.1+$B$6*$A42+$B$7*0.1*$A42 -> 2969.7125 | D42: =$B$4+$B$5*0.2+$B$6*$A42+$B$7*0.2*$A42 -> 2969.175 | E42: =$B$4+$B$5*0.3+$B$6*$A42+$B$7*0.3*$A42 -> 2968.6375 | F42: =$B$4+$B$5*0.4+$B$6*$A42+$B$7*0.4*$A42 -> 2968.1 | G42: =$B$4+$B$5*0.5+$B$6*$A42+$B$7*0.5*$A42 -> 2967.5625 | H42: =$B$4+$B$5*0.6+$B$6*$A42+$B$7*0.6*$A42 -> 2967.025 | I42: =$B$4+$B$5*0.7+$B$6*$A42+$B$7*0.7*$A42 -> 2966.4875 | J42: =$B$4+$B$5*0.8+$B$6*$A42+$B$7*0.8*$A42 -> 2965.95 | K42: =$B$4+$B$5*0.9+$B$6*$A42+$B$7*0.9*$A42 -> 2965.4125 | L42: =$B$4+$B$5*1+$B$6*$A42+$B$7*1*$A42 -> 2964.875
A43: 1 | B43: =$B$4+$B$5*0+$B$6*$A43+$B$7*0*$A43 -> 2977.5 | C43: =$B$4+$B$5*0.1+$B$6*$A43+$B$7*0.1*$A43 -> 2976 | D43: =$B$4+$B$5*0.2+$B$6*$A43+$B$7*0.2*$A43 -> 2974.5 | E43: =$B$4+$B$5*0.3+$B$6*$A43+$B$7*0.3*$A43 -> 2973 | F43: =$B$4+$B$5*0.4+$B$6*$A43+$B$7*0.4*$A43 -> 2971.5 | G43: =$B$4+$B$5*0.5+$B$6*$A43+$B$7*0.5*$A43 -> 2970 | H43: =$B$4+$B$5*0.6+$B$6*$A43+$B$7*0.6*$A43 -> 2968.5 | I43: =$B$4+$B$5*0.7+$B$6*$A43+$B$7*0.7*$A43 -> 2967 | J43: =$B$4+$B$5*0.8+$B$6*$A43+$B$7*0.8*$A43 -> 2965.5 | K43: =$B$4+$B$5*0.9+$B$6*$A43+$B$7*0.9*$A43 -> 2964 | L43: =$B$4+$B$5*1+$B$6*$A43+$B$7*1*$A43 -> 2962.5

Sheet Multistart
A1: Search: where 100 local searches end (AXIOM Lab 2.4, step 2; Worked Example 4.1, Step 2; Table 4.4)
A2: Run counts and iterations are engine values: SciPy's SLSQP and its interior-point trust-constr, run by the notebook from 100 random starts (the book's seed 2026, Online Appendix 4.B.3; the lab's seed 26204).
A4: Plan | B4: Index i | C4: Value at credit M (formula) | D4: SLSQP, book's starts (2026) | E4: SLSQP, lab's starts (26204) | F4: Interior point, lab's starts (26204)
A5: years 1–4 | B5: 60 | C5: =INDEX(Schedules!$U$5:$U$68,B5+1) -> 2986.25 | D5: 87 | E5: 93 | F5: 61
A6: years 1–3 and 5 | B6: 58 | C6: =INDEX(Schedules!$U$5:$U$68,B6+1) -> 2977.5 | D6: 11 | E6: 6 | F6: 22
A7: years 1–3 and 6 | B7: 57 | C7: =INDEX(Schedules!$U$5:$U$68,B7+1) -> 2968.75 | D7: 2 | E7: 1 | F7: 17
A8: Runs in all | D8: =SUM(D5:D7) -> 100 | E8: =SUM(E5:E7) -> 100 | F8: =SUM(F5:F7) -> 100
A9: Mean iterations a run (engine) | D9: 8.51 | E9: 8.7 | F9: 76.74
A10: Every run ends at a corner, none at the saddle; the same three basins, in different proportions.
A12: How many random starts? | B12: Value | C12: Reading
A13: Share of starts a basin attracts, v | B13: 0.05 | C13: 5 percent
A14: Confidence wanted | B14: 0.95
A15: Starts needed, N >= ln(1 - confidence) / ln(1 - v) | B15: =LN(1-B14)/LN(1-B13) -> 58.403975 | C15: 58.4
A16: Rounded up | B16: =ROUNDUP(B15,0) -> 59 | C16: about 59 starts (Section 4.4)
A17: Starts in a run | B17: 100
A18: Chance that every start misses the basin, (1 - v)^N | B18: =(1-B13)^B17 -> 0.0059205292

Sheet Audit
A1: Audit each answer: multipliers, residuals, LICQ and the reduced Hessian (AXIOM Lab 2.4, step 3; Theorems 4.1-4.2)
A2: Only box limits bind (the floors keep at least 85 of slack). A limit z_j <= 1 binding prices at the marginal value, z_j >= 0 at minus it; stationarity: marginal value = price up - price down.
A4: Plan | B4: z1 | C4: z2 | D4: z3 | E4: z4 | F4: z5 | G4: z6 | H4: gap 1 | I4: gap 2 | J4: gap 3 | K4: gap 4 | L4: gap 5 | M4: gap 6 | N4: marginal 1 | O4: marginal 2 | P4: marginal 3 | Q4: marginal 4 | R4: marginal 5 | S4: marginal 6 | T4: price z1<=1 | U4: price z2<=1 | V4: price z3<=1 | W4: price z4<=1 | X4: price z5<=1 | Y4: price z6<=1 | Z4: price z1>=0 | AA4: price z2>=0 | AB4: price z3>=0 | AC4: price z4>=0 | AD4: price z5>=0 | AE4: price z6>=0 | AF4: Stationarity residual | AG4: Sign residual | AH4: KKT residual | AI4: Binding limits | AJ4: Rank (LICQ) | AK4: Critical directions | AL4: Verdict
A5: years 1–4 | B5: =Plans!B5 -> 1 | C5: =Plans!C5 -> 1 | D5: =Plans!D5 -> 1 | E5: =Plans!E5 -> 1 | F5: =Plans!F5 -> 0 | G5: =Plans!G5 -> 0 | H5: =Plans!H5 -> 7 | I5: =Plans!I5 -> 3.5 | ... M5: =Plans!M5 -> 0.875 | N5: =Val_pt*Share/(1-Share*B5)*(SUM(H5:M5)+Credit_M*M5)-Cost_r -> 203.75 | O5: =Val_pt*Share/(1-Share*C5)*(SUM(I5:M5)+Credit_M*M5)-Cost_r -> 133.75 | P5: =Val_pt*Share/(1-Share*D5)*(SUM(J5:M5)+Credit_M*M5)-Cost_r -> 98.75 | Q5: =Val_pt*Share/(1-Share*E5)*(SUM(K5:M5)+Credit_M*M5)-Cost_r -> 81.25 | R5: =Val_pt*Share/(1-Share*F5)*(SUM(L5:M5)+Credit_M*M5)-Cost_r -> -23.75 | S5: =Val_pt*Share/(1-Share*G5)*(SUM(M5:M5)+Credit_M*M5)-Cost_r -> -28.125 | T5: =IF(B5=1,N5,0) -> 203.75 | U5: =IF(C5=1,O5,0) -> 133.75 | V5: =IF(D5=1,P5,0) -> 98.75 | W5: =IF(E5=1,Q5,0) -> 81.25 | X5: =IF(F5=1,R5,0) -> 0 | Y5: =IF(G5=1,S5,0) -> 0 | Z5: =IF(B5=0,-N5,0) -> 0 | AA5: =IF(C5=0,-O5,0) -> 0 | AB5: =IF(D5=0,-P5,0) -> 0 | AC5: =IF(E5=0,-Q5,0) -> 0 | AD5: =IF(F5=0,-R5,0) -> 23.75 | AE5: =IF(G5=0,-S5,0) -> 28.125 | AF5: =MAX(ABS(N5-T5+Z5),ABS(O5-U5+AA5),ABS(P5-V5+AB5),ABS(Q5-W5+AC5),ABS(R5-X5+AD5),ABS(S5-Y5+AE5)) -> 0 | AG5: =MAX(0,-MIN(T5:AE5)) -> 0 | AH5: =MAX(AF5,AG5) -> 0 | AI5: =COUNTIF(B5:G5,1)+COUNTIF(B5:G5,0) -> 6 | AJ5: =AI5 -> 6 | AK5: =SUMPRODUCT((B5:G5>0)*(B5:G5<1))+SUMPRODUCT((B5:G5=1)*(T5:Y5=0))+SUMPRODUCT((B5:G5=0)*(Z5:AE5=0)) -> 0 | AL5: =IF(AH5>0.000001,"not a KKT point",IF(AK5=0,"strict local maximum",IF($C$22>0,"saddle: a KKT point, not a local maximum","check the curvature"))) -> strict local maximum
A6: years 1–3 and 5 | B6: =Plans!B6 -> 1 | C6: =Plans!C6 -> 1 | D6: =Plans!D6 -> 1 | E6: =Plans!E6 -> 0 | F6: =Plans!F6 -> 1 | G6: =Plans!G6 -> 0 | H6: =Plans!H6 -> 7 | I6: =Plans!I6 -> 3.5 | ... M6: =Plans!M6 -> 0.875 | N6: =Val_pt*Share/(1-Share*B6)*(SUM(H6:M6)+Credit_M*M6)-Cost_r -> 212.5 | O6: =Val_pt*Share/(1-Share*C6)*(SUM(I6:M6)+Credit_M*M6)-Cost_r -> 142.5 | P6: =Val_pt*Share/(1-Share*D6)*(SUM(J6:M6)+Credit_M*M6)-Cost_r -> 107.5 | Q6: =Val_pt*Share/(1-Share*E6)*(SUM(K6:M6)+Credit_M*M6)-Cost_r -> -15 | R6: =Val_pt*Share/(1-Share*F6)*(SUM(L6:M6)+Credit_M*M6)-Cost_r -> 72.5 | S6: =Val_pt*Share/(1-Share*G6)*(SUM(M6:M6)+Credit_M*M6)-Cost_r -> -28.125 | T6: =IF(B6=1,N6,0) -> 212.5 | U6: =IF(C6=1,O6,0) -> 142.5 | V6: =IF(D6=1,P6,0) -> 107.5 | W6: =IF(E6=1,Q6,0) -> 0 | X6: =IF(F6=1,R6,0) -> 72.5 | Y6: =IF(G6=1,S6,0) -> 0 | Z6: =IF(B6=0,-N6,0) -> 0 | AA6: =IF(C6=0,-O6,0) -> 0 | AB6: =IF(D6=0,-P6,0) -> 0 | AC6: =IF(E6=0,-Q6,0) -> 15 | AD6: =IF(F6=0,-R6,0) -> 0 | AE6: =IF(G6=0,-S6,0) -> 28.125 | AF6: =MAX(ABS(N6-T6+Z6),ABS(O6-U6+AA6),ABS(P6-V6+AB6),ABS(Q6-W6+AC6),ABS(R6-X6+AD6),ABS(S6-Y6+AE6)) -> 0 | AG6: =MAX(0,-MIN(T6:AE6)) -> 0 | AH6: =MAX(AF6,AG6) -> 0 | AI6: =COUNTIF(B6:G6,1)+COUNTIF(B6:G6,0) -> 6 | AJ6: =AI6 -> 6 | AK6: =SUMPRODUCT((B6:G6>0)*(B6:G6<1))+SUMPRODUCT((B6:G6=1)*(T6:Y6=0))+SUMPRODUCT((B6:G6=0)*(Z6:AE6=0)) -> 0 | AL6: =IF(AH6>0.000001,"not a KKT point",IF(AK6=0,"strict local maximum",IF($C$22>0,"saddle: a KKT point, not a local maximum","check the curvature"))) -> strict local maximum
A7: years 1–3 and 6 | B7: =Plans!B7 -> 1 | C7: =Plans!C7 -> 1 | D7: =Plans!D7 -> 1 | E7: =Plans!E7 -> 0 | F7: =Plans!F7 -> 0 | G7: =Plans!G7 -> 1 | H7: =Plans!H7 -> 7 | I7: =Plans!I7 -> 3.5 | ... M7: =Plans!M7 -> 0.875 | N7: =Val_pt*Share/(1-Share*B7)*(SUM(H7:M7)+Credit_M*M7)-Cost_r -> 221.25 | O7: =Val_pt*Share/(1-Share*C7)*(SUM(I7:M7)+Credit_M*M7)-Cost_r -> 151.25 | P7: =Val_pt*Share/(1-Share*D7)*(SUM(J7:M7)+Credit_M*M7)-Cost_r -> 116.25 | Q7: =Val_pt*Share/(1-Share*E7)*(SUM(K7:M7)+Credit_M*M7)-Cost_r -> -10.625 | R7: =Val_pt*Share/(1-Share*F7)*(SUM(L7:M7)+Credit_M*M7)-Cost_r -> -19.375 | S7: =Val_pt*Share/(1-Share*G7)*(SUM(M7:M7)+Credit_M*M7)-Cost_r -> 63.75 | T7: =IF(B7=1,N7,0) -> 221.25 | U7: =IF(C7=1,O7,0) -> 151.25 | V7: =IF(D7=1,P7,0) -> 116.25 | W7: =IF(E7=1,Q7,0) -> 0 | X7: =IF(F7=1,R7,0) -> 0 | Y7: =IF(G7=1,S7,0) -> 63.75 | Z7: =IF(B7=0,-N7,0) -> 0 | AA7: =IF(C7=0,-O7,0) -> 0 | AB7: =IF(D7=0,-P7,0) -> 0 | AC7: =IF(E7=0,-Q7,0) -> 10.625 | AD7: =IF(F7=0,-R7,0) -> 19.375 | AE7: =IF(G7=0,-S7,0) -> 0 | AF7: =MAX(ABS(N7-T7+Z7),ABS(O7-U7+AA7),ABS(P7-V7+AB7),ABS(Q7-W7+AC7),ABS(R7-X7+AD7),ABS(S7-Y7+AE7)) -> 0 | AG7: =MAX(0,-MIN(T7:AE7)) -> 0 | AH7: =MAX(AF7,AG7) -> 0 | AI7: =COUNTIF(B7:G7,1)+COUNTIF(B7:G7,0) -> 6 | AJ7: =AI7 -> 6 | AK7: =SUMPRODUCT((B7:G7>0)*(B7:G7<1))+SUMPRODUCT((B7:G7=1)*(T7:Y7=0))+SUMPRODUCT((B7:G7=0)*(Z7:AE7=0)) -> 0 | AL7: =IF(AH7>0.000001,"not a KKT point",IF(AK7=0,"strict local maximum",IF($C$22>0,"saddle: a KKT point, not a local maximum","check the curvature"))) -> strict local maximum
A8: years 1–3; 0.75 in 4; 0.84 in 5 (the saddle) | B8: =Plans!B9 -> 1 | C8: =Plans!C9 -> 1 | D8: =Plans!D9 -> 1 | E8: =Plans!E9 -> 0.75324675 | F8: =Plans!F9 -> 0.84415584 | G8: =Plans!G9 -> 0 | H8: =Plans!H9 -> 7 | I8: =Plans!I9 -> 3.5 | ... M8: =Plans!M9 -> 0.63046045 | N8: =Val_pt*Share/(1-Share*B8)*(SUM(H8:M8)+Credit_M*M8)-Cost_r -> 152.11039 | O8: =Val_pt*Share/(1-Share*C8)*(SUM(I8:M8)+Credit_M*M8)-Cost_r -> 82.11039 | P8: =Val_pt*Share/(1-Share*D8)*(SUM(J8:M8)+Credit_M*M8)-Cost_r -> 47.11039 | Q8: =Val_pt*Share/(1-Share*E8)*(SUM(K8:M8)+Credit_M*M8)-Cost_r -> 0 | R8: =Val_pt*Share/(1-Share*F8)*(SUM(L8:M8)+Credit_M*M8)-Cost_r -> 0 | S8: =Val_pt*Share/(1-Share*G8)*(SUM(M8:M8)+Credit_M*M8)-Cost_r -> -53.801653 | T8: =IF(B8=1,N8,0) -> 152.11039 | U8: =IF(C8=1,O8,0) -> 82.11039 | V8: =IF(D8=1,P8,0) -> 47.11039 | W8: =IF(E8=1,Q8,0) -> 0 | X8: =IF(F8=1,R8,0) -> 0 | Y8: =IF(G8=1,S8,0) -> 0 | Z8: =IF(B8=0,-N8,0) -> 0 | AA8: =IF(C8=0,-O8,0) -> 0 | AB8: =IF(D8=0,-P8,0) -> 0 | AC8: =IF(E8=0,-Q8,0) -> 0 | AD8: =IF(F8=0,-R8,0) -> 0 | AE8: =IF(G8=0,-S8,0) -> 53.801653 | AF8: =MAX(ABS(N8-T8+Z8),ABS(O8-U8+AA8),ABS(P8-V8+AB8),ABS(Q8-W8+AC8),ABS(R8-X8+AD8),ABS(S8-Y8+AE8)) -> 0 | AG8: =MAX(0,-MIN(T8:AE8)) -> 0 | AH8: =MAX(AF8,AG8) -> 0 | AI8: =COUNTIF(B8:G8,1)+COUNTIF(B8:G8,0) -> 4 | AJ8: =AI8 -> 4 | AK8: =SUMPRODUCT((B8:G8>0)*(B8:G8<1))+SUMPRODUCT((B8:G8=1)*(T8:Y8=0))+SUMPRODUCT((B8:G8=0)*(Z8:AE8=0)) -> 2 | AL8: =IF(AH8>0.000001,"not a KKT point",IF(AK8=0,"strict local maximum",IF($C$22>0,"saddle: a KKT point, not a local maximum","check the curvature"))) -> saddle: a KKT point, not a local maximum
A10: Rank: the gradients of the binding limits are distinct unit vectors (a round cannot sit at 0 and 1), so the rank equals the number binding and LICQ holds: each plan's multipliers are unique (Theorem 4.2(i)).
A11: At each corner every binding limit has a positive price: no critical direction, so Theorem 4.1(iii)'s test passes at once and value falls linearly away from the plan.
A13: Hessian at the saddle | B13: year 1 | C13: year 2 | D13: year 3 | E13: year 4 | F13: year 5 | G13: year 6
A14: year 1 | B14: 0 | C14: =-Val_pt*Share^2/((1-Share*Plans!B9)*(1-Share*Plans!C9))*(SUM(Plans!I9:M9)+Credit_M*Plans!M9) -> -202.11039 | D14: =-Val_pt*Share^2/((1-Share*Plans!B9)*(1-Share*Plans!D9))*(SUM(Plans!J9:M9)+Credit_M*Plans!M9) -> -167.11039 | E14: =-Val_pt*Share^2/((1-Share*Plans!B9)*(1-Share*Plans!E9))*(SUM(Plans!K9:M9)+Credit_M*Plans!M9) -> -120 | F14: =-Val_pt*Share^2/((1-Share*Plans!B9)*(1-Share*Plans!F9))*(SUM(Plans!L9:M9)+Credit_M*Plans!M9) -> -120 | G14: =-Val_pt*Share^2/((1-Share*Plans!B9)*(1-Share*Plans!G9))*(SUM(Plans!M9:M9)+Credit_M*Plans!M9) -> -66.198347
A15: year 2 | B15: =-Val_pt*Share^2/((1-Share*Plans!C9)*(1-Share*Plans!B9))*(SUM(Plans!I9:M9)+Credit_M*Plans!M9) -> -202.11039 | C15: 0 | D15: =-Val_pt*Share^2/((1-Share*Plans!C9)*(1-Share*Plans!D9))*(SUM(Plans!J9:M9)+Credit_M*Plans!M9) -> -167.11039 | E15: =-Val_pt*Share^2/((1-Share*Plans!C9)*(1-Share*Plans!E9))*(SUM(Plans!K9:M9)+Credit_M*Plans!M9) -> -120 | F15: =-Val_pt*Share^2/((1-Share*Plans!C9)*(1-Share*Plans!F9))*(SUM(Plans!L9:M9)+Credit_M*Plans!M9) -> -120 | G15: =-Val_pt*Share^2/((1-Share*Plans!C9)*(1-Share*Plans!G9))*(SUM(Plans!M9:M9)+Credit_M*Plans!M9) -> -66.198347
A16: year 3 | B16: =-Val_pt*Share^2/((1-Share*Plans!D9)*(1-Share*Plans!B9))*(SUM(Plans!J9:M9)+Credit_M*Plans!M9) -> -167.11039 | C16: =-Val_pt*Share^2/((1-Share*Plans!D9)*(1-Share*Plans!C9))*(SUM(Plans!J9:M9)+Credit_M*Plans!M9) -> -167.11039 | D16: 0 | E16: =-Val_pt*Share^2/((1-Share*Plans!D9)*(1-Share*Plans!E9))*(SUM(Plans!K9:M9)+Credit_M*Plans!M9) -> -120 | F16: =-Val_pt*Share^2/((1-Share*Plans!D9)*(1-Share*Plans!F9))*(SUM(Plans!L9:M9)+Credit_M*Plans!M9) -> -120 | G16: =-Val_pt*Share^2/((1-Share*Plans!D9)*(1-Share*Plans!G9))*(SUM(Plans!M9:M9)+Credit_M*Plans!M9) -> -66.198347
A17: year 4 | B17: =-Val_pt*Share^2/((1-Share*Plans!E9)*(1-Share*Plans!B9))*(SUM(Plans!K9:M9)+Credit_M*Plans!M9) -> -120 | C17: =-Val_pt*Share^2/((1-Share*Plans!E9)*(1-Share*Plans!C9))*(SUM(Plans!K9:M9)+Credit_M*Plans!M9) -> -120 | D17: =-Val_pt*Share^2/((1-Share*Plans!E9)*(1-Share*Plans!D9))*(SUM(Plans!K9:M9)+Credit_M*Plans!M9) -> -120 | E17: 0 | F17: =-Val_pt*Share^2/((1-Share*Plans!E9)*(1-Share*Plans!F9))*(SUM(Plans!L9:M9)+Credit_M*Plans!M9) -> -96.25 | G17: =-Val_pt*Share^2/((1-Share*Plans!E9)*(1-Share*Plans!G9))*(SUM(Plans!M9:M9)+Credit_M*Plans!M9) -> -53.096591
A18: year 5 | B18: =-Val_pt*Share^2/((1-Share*Plans!F9)*(1-Share*Plans!B9))*(SUM(Plans!L9:M9)+Credit_M*Plans!M9) -> -120 | C18: =-Val_pt*Share^2/((1-Share*Plans!F9)*(1-Share*Plans!C9))*(SUM(Plans!L9:M9)+Credit_M*Plans!M9) -> -120 | D18: =-Val_pt*Share^2/((1-Share*Plans!F9)*(1-Share*Plans!D9))*(SUM(Plans!L9:M9)+Credit_M*Plans!M9) -> -120 | E18: =-Val_pt*Share^2/((1-Share*Plans!F9)*(1-Share*Plans!E9))*(SUM(Plans!L9:M9)+Credit_M*Plans!M9) -> -96.25 | F18: 0 | G18: =-Val_pt*Share^2/((1-Share*Plans!F9)*(1-Share*Plans!G9))*(SUM(Plans!M9:M9)+Credit_M*Plans!M9) -> -57.272727
A19: year 6 | B19: =-Val_pt*Share^2/((1-Share*Plans!G9)*(1-Share*Plans!B9))*(SUM(Plans!M9:M9)+Credit_M*Plans!M9) -> -66.198347 | C19: =-Val_pt*Share^2/((1-Share*Plans!G9)*(1-Share*Plans!C9))*(SUM(Plans!M9:M9)+Credit_M*Plans!M9) -> -66.198347 | D19: =-Val_pt*Share^2/((1-Share*Plans!G9)*(1-Share*Plans!D9))*(SUM(Plans!M9:M9)+Credit_M*Plans!M9) -> -66.198347 | E19: =-Val_pt*Share^2/((1-Share*Plans!G9)*(1-Share*Plans!E9))*(SUM(Plans!M9:M9)+Credit_M*Plans!M9) -> -53.096591 | F19: =-Val_pt*Share^2/((1-Share*Plans!G9)*(1-Share*Plans!F9))*(SUM(Plans!M9:M9)+Credit_M*Plans!M9) -> -57.272727 | G19: 0
A21: Free rounds at the saddle: years 4 and 5; reduced Hessian [[0, h], [h, 0]], h = | B21: =F17 -> -96.25
A22: Its eigenvalues, along (1, 1) and along (1, -1) | B22: =-ABS(B21) -> -96.25 | C22: =ABS(B21) -> 96.25 | D22: a positive eigenvalue: along (1, -1) the plan is not a local maximum (Theorem 4.1(ii))

Sheet Prices
A1: Read the local prices (Worked Example 4.1, Step 3; Theorem 4.3(ii))
A2: Each local maximum carries its own prices: the marginal values of the rounds at that plan.
A4: Marginal value of a round ($m) | B4: year 1 | C4: year 2 | D4: year 3 | E4: year 4 | F4: year 5 | G4: year 6
A5: at years 1–4 | B5: =Audit!N5 -> 203.75 | C5: =Audit!O5 -> 133.75 | D5: =Audit!P5 -> 98.75 | E5: =Audit!Q5 -> 81.25 | F5: =Audit!R5 -> -23.75 | G5: =Audit!S5 -> -28.125
A6: at years 1–3 and 5 | B6: =Audit!N6 -> 212.5 | C6: =Audit!O6 -> 142.5 | D6: =Audit!P6 -> 107.5 | E6: =Audit!Q6 -> -15 | F6: =Audit!R6 -> 72.5 | G6: =Audit!S6 -> -28.125
A7: at years 1–3 and 6 | B7: =Audit!N7 -> 221.25 | C7: =Audit!O7 -> 151.25 | D7: =Audit!P7 -> 116.25 | E7: =Audit!Q7 -> -10.625 | F7: =Audit!R7 -> -19.375 | G7: =Audit!S7 -> 63.75
A10: Years 1–4: the year-4 round above its cost at the margin | B10: =E5 -> 81.25
A11: Years 1–4: forcing a round into year 5 loses | B11: =-F5 -> 23.75
A12: Years 1–4: forcing a round into year 6 loses | B12: =-G5 -> 28.125
A13: Years 1–3 and 5: a year-4 round loses at the margin | B13: =-E6 -> 15
A14: Years 1–3 and 5: dropping the year-5 round loses | B14: =F6 -> 72.5
A15: Moving the year-5 round to year 4 gains | B15: =Plans!U5-Plans!U6 -> 8.75
A16: The two one-round changes add to | B16: =E6-F6 -> -87.5
A17: Their interaction: the swap less the two changes | B17: =B15-B16 -> 96.25
A18: The face's -d (Face sheet) | B18: =-Face!B7 -> 96.25
A20: Local prices answer 'what does a small change from here cost?', not 'is there a better basin?': the swap moves two rounds at once, and their interaction is invisible to prices that move one at a time.

Sheet Relaxation
A1: Bound: Chapter 3's relaxation and the gap to each local answer (AXIOM Lab 2.4, step 4; Worked Example 4.1, Step 4)
A2: The relaxation's marginal values fall from year to year, so its best plan runs whole rounds first and one fraction after them. Its value bounds every plan of whole or partial rounds (2^-z <= 1 - z/2).
A4: At credit M (twenty years)
A5: Whole rounds n | B5: 6 - n + M | C5: Z where the next round's marginal value is 0 | D5: Rounds Z, n <= Z <= n + 1 | E5: S(min(1, Z)) | F5: S(min(2, Z)) | G5: S(min(3, Z)) | H5: S(min(4, Z)) | I5: S(min(5, Z)) | J5: S(min(6, Z)) | K5: Value
A6: 0 | B6: =6-A6+Credit_M -> 26 | C6: =LN(Cost_r/(Slope0*B6))/LN(Keep) -> 4.3940658 | D6: =IF(A6=6,6,MIN(MAX(C6,A6),A6+1)) -> 1 | E6: =Smax*(1-POWER(Keep,MIN(1,$D6))) -> 70 | F6: =Smax*(1-POWER(Keep,MIN(2,$D6))) -> 70 | G6: =Smax*(1-POWER(Keep,MIN(3,$D6))) -> 70 | H6: =Smax*(1-POWER(Keep,MIN(4,$D6))) -> 70 | I6: =Smax*(1-POWER(Keep,MIN(5,$D6))) -> 70 | J6: =Smax*(1-POWER(Keep,MIN(6,$D6))) -> 70 | K6: =Cash0+SUM(E6:J6)-Cost_r*D6+Credit_M*J6 -> 1850
A7: 1 | B7: =6-A7+Credit_M -> 25 | C7: =LN(Cost_r/(Slope0*B7))/LN(Keep) -> 4.3374822 | D7: =IF(A7=6,6,MIN(MAX(C7,A7),A7+1)) -> 2 | E7: =Smax*(1-POWER(Keep,MIN(1,$D7))) -> 70 | F7: =Smax*(1-POWER(Keep,MIN(2,$D7))) -> 105 | G7: =Smax*(1-POWER(Keep,MIN(3,$D7))) -> 105 | H7: =Smax*(1-POWER(Keep,MIN(4,$D7))) -> 105 | I7: =Smax*(1-POWER(Keep,MIN(5,$D7))) -> 105 | J7: =Smax*(1-POWER(Keep,MIN(6,$D7))) -> 105 | K7: =Cash0+SUM(E7:J7)-Cost_r*D7+Credit_M*J7 -> 2605
A8: 2 | B8: =6-A8+Credit_M -> 24 | C8: =LN(Cost_r/(Slope0*B8))/LN(Keep) -> 4.2785885 | D8: =IF(A8=6,6,MIN(MAX(C8,A8),A8+1)) -> 3 | E8: =Smax*(1-POWER(Keep,MIN(1,$D8))) -> 70 | F8: =Smax*(1-POWER(Keep,MIN(2,$D8))) -> 105 | G8: =Smax*(1-POWER(Keep,MIN(3,$D8))) -> 122.5 | H8: =Smax*(1-POWER(Keep,MIN(4,$D8))) -> 122.5 | I8: =Smax*(1-POWER(Keep,MIN(5,$D8))) -> 122.5 | J8: =Smax*(1-POWER(Keep,MIN(6,$D8))) -> 122.5 | K8: =Cash0+SUM(E8:J8)-Cost_r*D8+Credit_M*J8 -> 2905
A9: 3 | B9: =6-A9+Credit_M -> 23 | C9: =LN(Cost_r/(Slope0*B9))/LN(Keep) -> 4.217188 | D9: =IF(A9=6,6,MIN(MAX(C9,A9),A9+1)) -> 4 | E9: =Smax*(1-POWER(Keep,MIN(1,$D9))) -> 70 | F9: =Smax*(1-POWER(Keep,MIN(2,$D9))) -> 105 | G9: =Smax*(1-POWER(Keep,MIN(3,$D9))) -> 122.5 | H9: =Smax*(1-POWER(Keep,MIN(4,$D9))) -> 131.25 | I9: =Smax*(1-POWER(Keep,MIN(5,$D9))) -> 131.25 | J9: =Smax*(1-POWER(Keep,MIN(6,$D9))) -> 131.25 | K9: =Cash0+SUM(E9:J9)-Cost_r*D9+Credit_M*J9 -> 2986.25
A10: 4 | B10: =6-A10+Credit_M -> 22 | C10: =LN(Cost_r/(Slope0*B10))/LN(Keep) -> 4.1530577 | D10: =IF(A10=6,6,MIN(MAX(C10,A10),A10+1)) -> 4.1530577 | E10: =Smax*(1-POWER(Keep,MIN(1,$D10))) -> 70 | F10: =Smax*(1-POWER(Keep,MIN(2,$D10))) -> 105 | G10: =Smax*(1-POWER(Keep,MIN(3,$D10))) -> 122.5 | H10: =Smax*(1-POWER(Keep,MIN(4,$D10))) -> 131.25 | I10: =Smax*(1-POWER(Keep,MIN(5,$D10))) -> 132.13075 | J10: =Smax*(1-POWER(Keep,MIN(6,$D10))) -> 132.13075 | K10: =Cash0+SUM(E10:J10)-Cost_r*D10+Credit_M*J10 -> 2987.2597
A11: 5 | B11: =6-A11+Credit_M -> 21 | C11: =LN(Cost_r/(Slope0*B11))/LN(Keep) -> 4.0859435 | D11: =IF(A11=6,6,MIN(MAX(C11,A11),A11+1)) -> 5 | E11: =Smax*(1-POWER(Keep,MIN(1,$D11))) -> 70 | F11: =Smax*(1-POWER(Keep,MIN(2,$D11))) -> 105 | G11: =Smax*(1-POWER(Keep,MIN(3,$D11))) -> 122.5 | H11: =Smax*(1-POWER(Keep,MIN(4,$D11))) -> 131.25 | I11: =Smax*(1-POWER(Keep,MIN(5,$D11))) -> 135.625 | J11: =Smax*(1-POWER(Keep,MIN(6,$D11))) -> 135.625 | K11: =Cash0+SUM(E11:J11)-Cost_r*D11+Credit_M*J11 -> 2962.5
A12: 6 | B12: =6-A12+Credit_M -> 20 | C12: =LN(Cost_r/(Slope0*B12))/LN(Keep) -> 4.0155541 | D12: =IF(A12=6,6,MIN(MAX(C12,A12),A12+1)) -> 6 | E12: =Smax*(1-POWER(Keep,MIN(1,$D12))) -> 70 | F12: =Smax*(1-POWER(Keep,MIN(2,$D12))) -> 105 | G12: =Smax*(1-POWER(Keep,MIN(3,$D12))) -> 122.5 | H12: =Smax*(1-POWER(Keep,MIN(4,$D12))) -> 131.25 | I12: =Smax*(1-POWER(Keep,MIN(5,$D12))) -> 135.625 | J12: =Smax*(1-POWER(Keep,MIN(6,$D12))) -> 137.8125 | K12: =Cash0+SUM(E12:J12)-Cost_r*D12+Credit_M*J12 -> 2888.4375
A14: Ceiling: the best of these | K14: =MAX(K6:K12) -> 2987.2597
A15: Rounds run, Z | K15: =INDEX(D6:D12,MATCH(K14,K6:K12,0)) -> 4.1530577
A16: Its plan, z_k = min(1, max(0, Z - (k - 1))) | B16: =MIN(1,MAX(0,$K$15-0)) -> 1 | C16: =MIN(1,MAX(0,$K$15-1)) -> 1 | D16: =MIN(1,MAX(0,$K$15-2)) -> 1 | E16: =MIN(1,MAX(0,$K$15-3)) -> 1 | F16: =MIN(1,MAX(0,$K$15-4)) -> 0.15305767 | G16: =MIN(1,MAX(0,$K$15-5)) -> 0
A20: At ten years' credit
A21: Whole rounds n | B21: 6 - n + M | C21: Z where the next round's marginal value is 0 | D21: Rounds Z, n <= Z <= n + 1 | E21: S(min(1, Z)) | F21: S(min(2, Z)) | G21: S(min(3, Z)) | H21: S(min(4, Z)) | I21: S(min(5, Z)) | J21: S(min(6, Z)) | K21: Value
A22: 0 | B22: =6-A22+Credit_10 -> 16 | C22: =LN(Cost_r/(Slope0*B22))/LN(Keep) -> 3.693626 | D22: =IF(A22=6,6,MIN(MAX(C22,A22),A22+1)) -> 1 | E22: =Smax*(1-POWER(Keep,MIN(1,$D22))) -> 70 | F22: =Smax*(1-POWER(Keep,MIN(2,$D22))) -> 70 | G22: =Smax*(1-POWER(Keep,MIN(3,$D22))) -> 70 | H22: =Smax*(1-POWER(Keep,MIN(4,$D22))) -> 70 | I22: =Smax*(1-POWER(Keep,MIN(5,$D22))) -> 70 | J22: =Smax*(1-POWER(Keep,MIN(6,$D22))) -> 70 | K22: =Cash0+SUM(E22:J22)-Cost_r*D22+Credit_10*J22 -> 1150
A23: 1 | B23: =6-A23+Credit_10 -> 15 | C23: =LN(Cost_r/(Slope0*B23))/LN(Keep) -> 3.6005166 | D23: =IF(A23=6,6,MIN(MAX(C23,A23),A23+1)) -> 2 | E23: =Smax*(1-POWER(Keep,MIN(1,$D23))) -> 70 | F23: =Smax*(1-POWER(Keep,MIN(2,$D23))) -> 105 | G23: =Smax*(1-POWER(Keep,MIN(3,$D23))) -> 105 | H23: =Smax*(1-POWER(Keep,MIN(4,$D23))) -> 105 | I23: =Smax*(1-POWER(Keep,MIN(5,$D23))) -> 105 | J23: =Smax*(1-POWER(Keep,MIN(6,$D23))) -> 105 | K23: =Cash0+SUM(E23:J23)-Cost_r*D23+Credit_10*J23 -> 1555
A24: 2 | B24: =6-A24+Credit_10 -> 14 | C24: =LN(Cost_r/(Slope0*B24))/LN(Keep) -> 3.500981 | D24: =IF(A24=6,6,MIN(MAX(C24,A24),A24+1)) -> 3 | E24: =Smax*(1-POWER(Keep,MIN(1,$D24))) -> 70 | F24: =Smax*(1-POWER(Keep,MIN(2,$D24))) -> 105 | G24: =Smax*(1-POWER(Keep,MIN(3,$D24))) -> 122.5 | H24: =Smax*(1-POWER(Keep,MIN(4,$D24))) -> 122.5 | I24: =Smax*(1-POWER(Keep,MIN(5,$D24))) -> 122.5 | J24: =Smax*(1-POWER(Keep,MIN(6,$D24))) -> 122.5 | K24: =Cash0+SUM(E24:J24)-Cost_r*D24+Credit_10*J24 -> 1680
A25: 3 | B25: =6-A25+Credit_10 -> 13 | C25: =LN(Cost_r/(Slope0*B25))/LN(Keep) -> 3.3940658 | D25: =IF(A25=6,6,MIN(MAX(C25,A25),A25+1)) -> 3.3940658 | E25: =Smax*(1-POWER(Keep,MIN(1,$D25))) -> 70 | F25: =Smax*(1-POWER(Keep,MIN(2,$D25))) -> 105 | G25: =Smax*(1-POWER(Keep,MIN(3,$D25))) -> 122.5 | H25: =Smax*(1-POWER(Keep,MIN(4,$D25))) -> 126.68282 | I25: =Smax*(1-POWER(Keep,MIN(5,$D25))) -> 126.68282 | J25: =Smax*(1-POWER(Keep,MIN(6,$D25))) -> 126.68282 | K25: =Cash0+SUM(E25:J25)-Cost_r*D25+Credit_10*J25 -> 1687.0887
A26: 4 | B26: =6-A26+Credit_10 -> 12 | C26: =LN(Cost_r/(Slope0*B26))/LN(Keep) -> 3.2785885 | D26: =IF(A26=6,6,MIN(MAX(C26,A26),A26+1)) -> 4 | E26: =Smax*(1-POWER(Keep,MIN(1,$D26))) -> 70 | F26: =Smax*(1-POWER(Keep,MIN(2,$D26))) -> 105 | G26: =Smax*(1-POWER(Keep,MIN(3,$D26))) -> 122.5 | H26: =Smax*(1-POWER(Keep,MIN(4,$D26))) -> 131.25 | I26: =Smax*(1-POWER(Keep,MIN(5,$D26))) -> 131.25 | J26: =Smax*(1-POWER(Keep,MIN(6,$D26))) -> 131.25 | K26: =Cash0+SUM(E26:J26)-Cost_r*D26+Credit_10*J26 -> 1673.75
A27: 5 | B27: =6-A27+Credit_10 -> 11 | C27: =LN(Cost_r/(Slope0*B27))/LN(Keep) -> 3.1530577 | D27: =IF(A27=6,6,MIN(MAX(C27,A27),A27+1)) -> 5 | E27: =Smax*(1-POWER(Keep,MIN(1,$D27))) -> 70 | F27: =Smax*(1-POWER(Keep,MIN(2,$D27))) -> 105 | G27: =Smax*(1-POWER(Keep,MIN(3,$D27))) -> 122.5 | H27: =Smax*(1-POWER(Keep,MIN(4,$D27))) -> 131.25 | I27: =Smax*(1-POWER(Keep,MIN(5,$D27))) -> 135.625 | J27: =Smax*(1-POWER(Keep,MIN(6,$D27))) -> 135.625 | K27: =Cash0+SUM(E27:J27)-Cost_r*D27+Credit_10*J27 -> 1606.25
A28: 6 | B28: =6-A28+Credit_10 -> 10 | C28: =LN(Cost_r/(Slope0*B28))/LN(Keep) -> 3.0155541 | D28: =IF(A28=6,6,MIN(MAX(C28,A28),A28+1)) -> 6 | E28: =Smax*(1-POWER(Keep,MIN(1,$D28))) -> 70 | F28: =Smax*(1-POWER(Keep,MIN(2,$D28))) -> 105 | G28: =Smax*(1-POWER(Keep,MIN(3,$D28))) -> 122.5 | H28: =Smax*(1-POWER(Keep,MIN(4,$D28))) -> 131.25 | I28: =Smax*(1-POWER(Keep,MIN(5,$D28))) -> 135.625 | J28: =Smax*(1-POWER(Keep,MIN(6,$D28))) -> 137.8125 | K28: =Cash0+SUM(E28:J28)-Cost_r*D28+Credit_10*J28 -> 1510.3125
A30: Ceiling: the best of these | K30: =MAX(K22:K28) -> 1687.0887
A31: Rounds run, Z | K31: =INDEX(D22:D28,MATCH(K30,K22:K28,0)) -> 3.3940658
A32: Its plan, z_k = min(1, max(0, Z - (k - 1))) | B32: =MIN(1,MAX(0,$K$31-0)) -> 1 | C32: =MIN(1,MAX(0,$K$31-1)) -> 1 | D32: =MIN(1,MAX(0,$K$31-2)) -> 1 | E32: =MIN(1,MAX(0,$K$31-3)) -> 0.39406577 | F32: =MIN(1,MAX(0,$K$31-4)) -> 0 | G32: =MIN(1,MAX(0,$K$31-5)) -> 0
A35: Plan | B35: Value at credit M | C35: Below the ceiling | D35: Below the ceiling (%)
A36: years 1–4 | B36: =Plans!U5 -> 2986.25 | C36: =$K$14-B36 -> 1.009675 | D36: =100*C36/$K$14 -> 0.033799373
A37: years 1–3 and 5 | B37: =Plans!U6 -> 2977.5 | C37: =$K$14-B37 -> 9.759675 | D37: =100*C37/$K$14 -> 0.32670997
A38: years 1–3 and 6 | B38: =Plans!U7 -> 2968.75 | C38: =$K$14-B38 -> 18.509675 | D38: =100*C38/$K$14 -> 0.61962056
A39: the saddle | B39: =Plans!U9 -> 2966.2013 | C39: =$K$14-B39 -> 21.058376 | D39: =100*C39/$K$14 -> 0.7049396
A41: Part of a round z | B41: 1 - z/2 (partial rounds) | C41: 2^-z (Chapter 3) | D41: Difference
A42: 0 | B42: =1-Share*A42 -> 1 | C42: =POWER(Keep,A42) -> 1 | D42: =B42-C42 -> 0 | F42: Smallest difference (never below 0: the relaxation's gap is never larger)
A43: 0.05 | B43: =1-Share*A43 -> 0.975 | C43: =POWER(Keep,A43) -> 0.96593633 | D43: =B43-C43 -> 0.0090636711 | F43: =MIN(D42:D62) -> 0
A44: 0.1 | B44: =1-Share*A44 -> 0.95 | C44: =POWER(Keep,A44) -> 0.93303299 | D44: =B44-C44 -> 0.016967008
A45: 0.15 | B45: =1-Share*A45 -> 0.925 | C45: =POWER(Keep,A45) -> 0.90125046 | D45: =B45-C45 -> 0.023749537
A46: 0.2 | B46: =1-Share*A46 -> 0.9 | C46: =POWER(Keep,A46) -> 0.87055056 | D46: =B46-C46 -> 0.029449437
A47: 0.25 | B47: =1-Share*A47 -> 0.875 | C47: =POWER(Keep,A47) -> 0.84089642 | D47: =B47-C47 -> 0.034103585
A48: 0.3 | B48: =1-Share*A48 -> 0.85 | C48: =POWER(Keep,A48) -> 0.8122524 | D48: =B48-C48 -> 0.037747604
A49: 0.35 | B49: =1-Share*A49 -> 0.825 | C49: =POWER(Keep,A49) -> 0.7845841 | D49: =B49-C49 -> 0.040415902
A50: 0.4 | B50: =1-Share*A50 -> 0.8 | C50: =POWER(Keep,A50) -> 0.75785828 | D50: =B50-C50 -> 0.042141717
A51: 0.45 | B51: =1-Share*A51 -> 0.775 | C51: =POWER(Keep,A51) -> 0.73204285 | D51: =B51-C51 -> 0.042957152
A52: 0.5 | B52: =1-Share*A52 -> 0.75 | C52: =POWER(Keep,A52) -> 0.70710678 | D52: =B52-C52 -> 0.042893219
A53: 0.55 | B53: =1-Share*A53 -> 0.725 | C53: =POWER(Keep,A53) -> 0.68302013 | D53: =B53-C53 -> 0.041979872
A54: 0.6 | B54: =1-Share*A54 -> 0.7 | C54: =POWER(Keep,A54) -> 0.65975396 | D54: =B54-C54 -> 0.040246045
A55: 0.65 | B55: =1-Share*A55 -> 0.675 | C55: =POWER(Keep,A55) -> 0.63728031 | D55: =B55-C55 -> 0.037719686
... A62: 1 | B62: =1-Share*A62 -> 0.5 | C62: =POWER(Keep,A62) -> 0.5 | D62: =B62-C62 -> 0

Sheet BranchAndBound
A1: Branch: close the gap (AXIOM Lab 2.4, step 5; Worked Example 4.1, Step 5; Figure 4.3; Theorem 4.4)
A2: Each node fixes some rounds (blue: blank = free, 0 = none, 1 = whole; the book's trees, depth first, most fractional round, nearer child first). Its relaxation is solved exactly in the block below: the free rounds run whole up to a pivot, which solves its marginal equation, and none after it; the best pivot wins.
J3: year: | K3: 1 | L3: 2 | M3: 3 | N3: 4 | O3: 5 | P3: 6
A4: Credit | B4: Node | C4: Parent | D4: fix z1 | E4: fix z2 | F4: fix z3 | G4: fix z4 | H4: fix z5 | I4: fix z6 | J4: Ceiling | K4: z1 | L4: z2 | M4: z3 | N4: z4 | O4: z5 | P4: z6 | Q4: Fractional round | R4: Parent's ceiling | S4: Incumbent before | T4: Verdict | U4: Incumbent after | V4: Largest open ceiling after | W4: Gap after the node | X4: Branches on the parent's fractional round
A5: twenty years | B5: 1 | J5: =MAX(AQ26:AQ31) -> 2987.2597 | K5: =INDEX(Y26:Y31,MATCH(J5,AQ26:AQ31,0)) -> 1 | L5: =INDEX(Z26:Z31,MATCH(J5,AQ26:AQ31,0)) -> 1 | M5: =INDEX(AA26:AA31,MATCH(J5,AQ26:AQ31,0)) -> 1 | N5: =INDEX(AB26:AB31,MATCH(J5,AQ26:AQ31,0)) -> 1 | O5: =INDEX(AC26:AC31,MATCH(J5,AQ26:AQ31,0)) -> 0.15305767 | P5: =INDEX(AD26:AD31,MATCH(J5,AQ26:AQ31,0)) -> 0 | Q5: =SUMPRODUCT((K5:P5>0.000001)*(K5:P5<1-0.000001)*$K$3:$P$3) -> 5 | S5: =-1000000000 -> -1000000000 | T5: =IF(J5<=S5+0.000001,"pruned",IF(Q5=0,"incumbent","branch on year "&Q5)) -> branch on year 5 | U5: =IF(T5="incumbent",MAX(S5,J5),S5) -> -1000000000 | V5: =_xlfn.MAXIFS($R$5:$R$9,$B$5:$B$9,">"&B5,$C$5:$C$9,"<="&B5) -> 2987.2597 | W5: =IF(U5<-100000000,"no incumbent",MAX(V5,U5)-U5) -> no incumbent
A6: twenty years | B6: 2 | C6: 1 | H6: 0 | J6: =MAX(AQ32:AQ37) -> 2986.5634 | K6: =INDEX(Y32:Y37,MATCH(J6,AQ32:AQ37,0)) -> 1 | L6: =INDEX(Z32:Z37,MATCH(J6,AQ32:AQ37,0)) -> 1 | M6: =INDEX(AA32:AA37,MATCH(J6,AQ32:AQ37,0)) -> 1 | N6: =INDEX(AB32:AB37,MATCH(J6,AQ32:AQ37,0)) -> 1 | O6: =INDEX(AC32:AC37,MATCH(J6,AQ32:AQ37,0)) -> 0 | P6: =INDEX(AD32:AD37,MATCH(J6,AQ32:AQ37,0)) -> 0.085943471 | Q6: =SUMPRODUCT((K6:P6>0.000001)*(K6:P6<1-0.000001)*$K$3:$P$3) -> 6 | R6: =INDEX($J$5:$J$9,C6) -> 2987.2597 | S6: =MAX(U5:U5) -> -1000000000 | T6: =IF(J6<=S6+0.000001,"pruned",IF(Q6=0,"incumbent","branch on year "&Q6)) -> branch on year 6 | U6: =IF(T6="incumbent",MAX(S6,J6),S6) -> -1000000000 | V6: =_xlfn.MAXIFS($R$5:$R$9,$B$5:$B$9,">"&B6,$C$5:$C$9,"<="&B6) -> 2987.2597 | W6: =IF(U6<-100000000,"no incumbent",MAX(V6,U6)-U6) -> no incumbent | X6: =SUMPRODUCT((D6:I6<>"")*(D5:I5="")*$K$3:$P$3)=Q5 -> TRUE
A7: twenty years | B7: 3 | C7: 2 | H7: 0 | I7: 0 | J7: =MAX(AQ38:AQ43) -> 2986.25 | K7: =INDEX(Y38:Y43,MATCH(J7,AQ38:AQ43,0)) -> 1 | L7: =INDEX(Z38:Z43,MATCH(J7,AQ38:AQ43,0)) -> 1 | M7: =INDEX(AA38:AA43,MATCH(J7,AQ38:AQ43,0)) -> 1 | N7: =INDEX(AB38:AB43,MATCH(J7,AQ38:AQ43,0)) -> 1 | O7: =INDEX(AC38:AC43,MATCH(J7,AQ38:AQ43,0)) -> 0 | P7: =INDEX(AD38:AD43,MATCH(J7,AQ38:AQ43,0)) -> 0 | Q7: =SUMPRODUCT((K7:P7>0.000001)*(K7:P7<1-0.000001)*$K$3:$P$3) -> 0 | R7: =INDEX($J$5:$J$9,C7) -> 2986.5634 | S7: =MAX(U5:U6) -> -1000000000 | T7: =IF(J7<=S7+0.000001,"pruned",IF(Q7=0,"incumbent","branch on year "&Q7)) -> incumbent | U7: =IF(T7="incumbent",MAX(S7,J7),S7) -> 2986.25 | V7: =_xlfn.MAXIFS($R$5:$R$9,$B$5:$B$9,">"&B7,$C$5:$C$9,"<="&B7) -> 2987.2597 | W7: =IF(U7<-100000000,"no incumbent",MAX(V7,U7)-U7) -> 1.009675 | X7: =SUMPRODUCT((D7:I7<>"")*(D6:I6="")*$K$3:$P$3)=Q6 -> TRUE
A8: twenty years | B8: 4 | C8: 2 | H8: 0 | I8: 1 | J8: =MAX(AQ44:AQ49) -> 2973.8787 | K8: =INDEX(Y44:Y49,MATCH(J8,AQ44:AQ49,0)) -> 1 | L8: =INDEX(Z44:Z49,MATCH(J8,AQ44:AQ49,0)) -> 1 | M8: =INDEX(AA44:AA49,MATCH(J8,AQ44:AQ49,0)) -> 1 | N8: =INDEX(AB44:AB49,MATCH(J8,AQ44:AQ49,0)) -> 0.33748224 | O8: =INDEX(AC44:AC49,MATCH(J8,AQ44:AQ49,0)) -> 0 | P8: =INDEX(AD44:AD49,MATCH(J8,AQ44:AQ49,0)) -> 1 | Q8: =SUMPRODUCT((K8:P8>0.000001)*(K8:P8<1-0.000001)*$K$3:$P$3) -> 4 | R8: =INDEX($J$5:$J$9,C8) -> 2986.5634 | S8: =MAX(U5:U7) -> 2986.25 | T8: =IF(J8<=S8+0.000001,"pruned",IF(Q8=0,"incumbent","branch on year "&Q8)) -> pruned | U8: =IF(T8="incumbent",MAX(S8,J8),S8) -> 2986.25 | V8: =_xlfn.MAXIFS($R$5:$R$9,$B$5:$B$9,">"&B8,$C$5:$C$9,"<="&B8) -> 2987.2597 | W8: =IF(U8<-100000000,"no incumbent",MAX(V8,U8)-U8) -> 1.009675 | X8: =SUMPRODUCT((D8:I8<>"")*(D6:I6="")*$K$3:$P$3)=Q6 -> TRUE
A9: twenty years | B9: 5 | C9: 1 | H9: 1 | J9: =MAX(AQ50:AQ55) -> 2980.946 | K9: =INDEX(Y50:Y55,MATCH(J9,AQ50:AQ55,0)) -> 1 | L9: =INDEX(Z50:Z55,MATCH(J9,AQ50:AQ55,0)) -> 1 | M9: =INDEX(AA50:AA55,MATCH(J9,AQ50:AQ55,0)) -> 1 | N9: =INDEX(AB50:AB55,MATCH(J9,AQ50:AQ55,0)) -> 0.27858855 | O9: =INDEX(AC50:AC55,MATCH(J9,AQ50:AQ55,0)) -> 1 | P9: =INDEX(AD50:AD55,MATCH(J9,AQ50:AQ55,0)) -> 0 | Q9: =SUMPRODUCT((K9:P9>0.000001)*(K9:P9<1-0.000001)*$K$3:$P$3) -> 4 | R9: =INDEX($J$5:$J$9,C9) -> 2987.2597 | S9: =MAX(U5:U8) -> 2986.25 | T9: =IF(J9<=S9+0.000001,"pruned",IF(Q9=0,"incumbent","branch on year "&Q9)) -> pruned | U9: =IF(T9="incumbent",MAX(S9,J9),S9) -> 2986.25 | V9: =_xlfn.MAXIFS($R$5:$R$9,$B$5:$B$9,">"&B9,$C$5:$C$9,"<="&B9) -> 0 | W9: =IF(U9<-100000000,"no incumbent",MAX(V9,U9)-U9) -> 0 | X9: =SUMPRODUCT((D9:I9<>"")*(D5:I5="")*$K$3:$P$3)=Q5 -> TRUE
A10: Solves | J10: =COUNT(J5:J9) -> 5 | K10: Best plan, worth | N10: =MAX(U5:U9) -> 2986.25 | S10: Branched nodes x 2 + 1 = nodes: | W10: =2*SUMPRODUCT((Q5:Q9>0)*(T5:T9<>"pruned"))+1=COUNT(J5:J9) -> TRUE
A12: Credit | B12: Node | C12: Parent | D12: fix z1 | E12: fix z2 | F12: fix z3 | G12: fix z4 | H12: fix z5 | I12: fix z6 | J12: Ceiling | K12: z1 | L12: z2 | M12: z3 | N12: z4 | O12: z5 | P12: z6 | Q12: Fractional round | R12: Parent's ceiling | S12: Incumbent before | T12: Verdict | U12: Incumbent after | V12: Largest open ceiling after | W12: Gap after the node | X12: Branches on the parent's fractional round
A13: ten years | B13: 1 | J13: =MAX(AQ56:AQ61) -> 1687.0887 | K13: =INDEX(Y56:Y61,MATCH(J13,AQ56:AQ61,0)) -> 1 | L13: =INDEX(Z56:Z61,MATCH(J13,AQ56:AQ61,0)) -> 1 | M13: =INDEX(AA56:AA61,MATCH(J13,AQ56:AQ61,0)) -> 1 | N13: =INDEX(AB56:AB61,MATCH(J13,AQ56:AQ61,0)) -> 0.39406577 | O13: =INDEX(AC56:AC61,MATCH(J13,AQ56:AQ61,0)) -> 0 | P13: =INDEX(AD56:AD61,MATCH(J13,AQ56:AQ61,0)) -> 0 | Q13: =SUMPRODUCT((K13:P13>0.000001)*(K13:P13<1-0.000001)*$K$3:$P$3) -> 4 | S13: =-1000000000 -> -1000000000 | T13: =IF(J13<=S13+0.000001,"pruned",IF(Q13=0,"incumbent","branch on year "&Q13)) -> branch on year 4 | U13: =IF(T13="incumbent",MAX(S13,J13),S13) -> -1000000000 | V13: =_xlfn.MAXIFS($R$13:$R$19,$B$13:$B$19,">"&B13,$C$13:$C$19,"<="&B13) -> 1687.0887 | W13: =IF(U13<-100000000,"no incumbent",MAX(V13,U13)-U13) -> no incumbent
A14: ten years | B14: 2 | C14: 1 | G14: 0 | J14: =MAX(AQ62:AQ67) -> 1683.446 | K14: =INDEX(Y62:Y67,MATCH(J14,AQ62:AQ67,0)) -> 1 | L14: =INDEX(Z62:Z67,MATCH(J14,AQ62:AQ67,0)) -> 1 | M14: =INDEX(AA62:AA67,MATCH(J14,AQ62:AQ67,0)) -> 1 | N14: =INDEX(AB62:AB67,MATCH(J14,AQ62:AQ67,0)) -> 0 | O14: =INDEX(AC62:AC67,MATCH(J14,AQ62:AQ67,0)) -> 0.27858855 | P14: =INDEX(AD62:AD67,MATCH(J14,AQ62:AQ67,0)) -> 0 | Q14: =SUMPRODUCT((K14:P14>0.000001)*(K14:P14<1-0.000001)*$K$3:$P$3) -> 5 | R14: =INDEX($J$13:$J$19,C14) -> 1687.0887 | S14: =MAX(U13:U13) -> -1000000000 | T14: =IF(J14<=S14+0.000001,"pruned",IF(Q14=0,"incumbent","branch on year "&Q14)) -> branch on year 5 | U14: =IF(T14="incumbent",MAX(S14,J14),S14) -> -1000000000 | V14: =_xlfn.MAXIFS($R$13:$R$19,$B$13:$B$19,">"&B14,$C$13:$C$19,"<="&B14) -> 1687.0887 | W14: =IF(U14<-100000000,"no incumbent",MAX(V14,U14)-U14) -> no incumbent | X14: =SUMPRODUCT((D14:I14<>"")*(D13:I13="")*$K$3:$P$3)=Q13 -> TRUE
A15: ten years | B15: 3 | C15: 2 | G15: 0 | H15: 0 | J15: =MAX(AQ68:AQ73) -> 1681.0097 | K15: =INDEX(Y68:Y73,MATCH(J15,AQ68:AQ73,0)) -> 1 | L15: =INDEX(Z68:Z73,MATCH(J15,AQ68:AQ73,0)) -> 1 | M15: =INDEX(AA68:AA73,MATCH(J15,AQ68:AQ73,0)) -> 1 | N15: =INDEX(AB68:AB73,MATCH(J15,AQ68:AQ73,0)) -> 0 | O15: =INDEX(AC68:AC73,MATCH(J15,AQ68:AQ73,0)) -> 0 | P15: =INDEX(AD68:AD73,MATCH(J15,AQ68:AQ73,0)) -> 0.15305767 | Q15: =SUMPRODUCT((K15:P15>0.000001)*(K15:P15<1-0.000001)*$K$3:$P$3) -> 6 | R15: =INDEX($J$13:$J$19,C15) -> 1683.446 | S15: =MAX(U13:U14) -> -1000000000 | T15: =IF(J15<=S15+0.000001,"pruned",IF(Q15=0,"incumbent","branch on year "&Q15)) -> branch on year 6 | U15: =IF(T15="incumbent",MAX(S15,J15),S15) -> -1000000000 | V15: =_xlfn.MAXIFS($R$13:$R$19,$B$13:$B$19,">"&B15,$C$13:$C$19,"<="&B15) -> 1687.0887 | W15: =IF(U15<-100000000,"no incumbent",MAX(V15,U15)-U15) -> no incumbent | X15: =SUMPRODUCT((D15:I15<>"")*(D14:I14="")*$K$3:$P$3)=Q14 -> TRUE
A16: ten years | B16: 4 | C16: 3 | G16: 0 | H16: 0 | I16: 0 | J16: =MAX(AQ74:AQ79) -> 1680 | K16: =INDEX(Y74:Y79,MATCH(J16,AQ74:AQ79,0)) -> 1 | L16: =INDEX(Z74:Z79,MATCH(J16,AQ74:AQ79,0)) -> 1 | M16: =INDEX(AA74:AA79,MATCH(J16,AQ74:AQ79,0)) -> 1 | N16: =INDEX(AB74:AB79,MATCH(J16,AQ74:AQ79,0)) -> 0 | O16: =INDEX(AC74:AC79,MATCH(J16,AQ74:AQ79,0)) -> 0 | P16: =INDEX(AD74:AD79,MATCH(J16,AQ74:AQ79,0)) -> 0 | Q16: =SUMPRODUCT((K16:P16>0.000001)*(K16:P16<1-0.000001)*$K$3:$P$3) -> 0 | R16: =INDEX($J$13:$J$19,C16) -> 1681.0097 | S16: =MAX(U13:U15) -> -1000000000 | T16: =IF(J16<=S16+0.000001,"pruned",IF(Q16=0,"incumbent","branch on year "&Q16)) -> incumbent | U16: =IF(T16="incumbent",MAX(S16,J16),S16) -> 1680 | V16: =_xlfn.MAXIFS($R$13:$R$19,$B$13:$B$19,">"&B16,$C$13:$C$19,"<="&B16) -> 1687.0887 | W16: =IF(U16<-100000000,"no incumbent",MAX(V16,U16)-U16) -> 7.0887031 | X16: =SUMPRODUCT((D16:I16<>"")*(D15:I15="")*$K$3:$P$3)=Q15 -> TRUE
A17: ten years | B17: 5 | C17: 3 | G17: 0 | H17: 0 | I17: 1 | J17: =MAX(AQ80:AQ85) -> 1658.1459 | K17: =INDEX(Y80:Y85,MATCH(J17,AQ80:AQ85,0)) -> 1 | L17: =INDEX(Z80:Z85,MATCH(J17,AQ80:AQ85,0)) -> 1 | M17: =INDEX(AA80:AA85,MATCH(J17,AQ80:AQ85,0)) -> 0.78108889 | N17: =INDEX(AB80:AB85,MATCH(J17,AQ80:AQ85,0)) -> 0 | O17: =INDEX(AC80:AC85,MATCH(J17,AQ80:AQ85,0)) -> 0 | P17: =INDEX(AD80:AD85,MATCH(J17,AQ80:AQ85,0)) -> 1 | Q17: =SUMPRODUCT((K17:P17>0.000001)*(K17:P17<1-0.000001)*$K$3:$P$3) -> 3 | R17: =INDEX($J$13:$J$19,C17) -> 1681.0097 | S17: =MAX(U13:U16) -> 1680 | T17: =IF(J17<=S17+0.000001,"pruned",IF(Q17=0,"incumbent","branch on year "&Q17)) -> pruned | U17: =IF(T17="incumbent",MAX(S17,J17),S17) -> 1680 | V17: =_xlfn.MAXIFS($R$13:$R$19,$B$13:$B$19,">"&B17,$C$13:$C$19,"<="&B17) -> 1687.0887 | W17: =IF(U17<-100000000,"no incumbent",MAX(V17,U17)-U17) -> 7.0887031 | X17: =SUMPRODUCT((D17:I17<>"")*(D15:I15="")*$K$3:$P$3)=Q15 -> TRUE
A18: ten years | B18: 6 | C18: 2 | G18: 0 | H18: 1 | J18: =MAX(AQ86:AQ91) -> 1668.6415 | K18: =INDEX(Y86:Y91,MATCH(J18,AQ86:AQ91,0)) -> 1 | L18: =INDEX(Z86:Z91,MATCH(J18,AQ86:AQ91,0)) -> 1 | M18: =INDEX(AA86:AA91,MATCH(J18,AQ86:AQ91,0)) -> 0.69362605 | N18: =INDEX(AB86:AB91,MATCH(J18,AQ86:AQ91,0)) -> 0 | O18: =INDEX(AC86:AC91,MATCH(J18,AQ86:AQ91,0)) -> 1 | P18: =INDEX(AD86:AD91,MATCH(J18,AQ86:AQ91,0)) -> 0 | Q18: =SUMPRODUCT((K18:P18>0.000001)*(K18:P18<1-0.000001)*$K$3:$P$3) -> 3 | R18: =INDEX($J$13:$J$19,C18) -> 1683.446 | S18: =MAX(U13:U17) -> 1680 | T18: =IF(J18<=S18+0.000001,"pruned",IF(Q18=0,"incumbent","branch on year "&Q18)) -> pruned | U18: =IF(T18="incumbent",MAX(S18,J18),S18) -> 1680 | V18: =_xlfn.MAXIFS($R$13:$R$19,$B$13:$B$19,">"&B18,$C$13:$C$19,"<="&B18) -> 1687.0887 | W18: =IF(U18<-100000000,"no incumbent",MAX(V18,U18)-U18) -> 7.0887031 | X18: =SUMPRODUCT((D18:I18<>"")*(D14:I14="")*$K$3:$P$3)=Q14 -> TRUE
A19: ten years | B19: 7 | C19: 1 | G19: 1 | J19: =MAX(AQ92:AQ97) -> 1679.8146 | K19: =INDEX(Y92:Y97,MATCH(J19,AQ92:AQ97,0)) -> 1 | L19: =INDEX(Z92:Z97,MATCH(J19,AQ92:AQ97,0)) -> 1 | M19: =INDEX(AA92:AA97,MATCH(J19,AQ92:AQ97,0)) -> 0.60051664 | N19: =INDEX(AB92:AB97,MATCH(J19,AQ92:AQ97,0)) -> 1 | O19: =INDEX(AC92:AC97,MATCH(J19,AQ92:AQ97,0)) -> 0 | P19: =INDEX(AD92:AD97,MATCH(J19,AQ92:AQ97,0)) -> 0 | Q19: =SUMPRODUCT((K19:P19>0.000001)*(K19:P19<1-0.000001)*$K$3:$P$3) -> 3 | R19: =INDEX($J$13:$J$19,C19) -> 1687.0887 | S19: =MAX(U13:U18) -> 1680 | T19: =IF(J19<=S19+0.000001,"pruned",IF(Q19=0,"incumbent","branch on year "&Q19)) -> pruned | U19: =IF(T19="incumbent",MAX(S19,J19),S19) -> 1680 | V19: =_xlfn.MAXIFS($R$13:$R$19,$B$13:$B$19,">"&B19,$C$13:$C$19,"<="&B19) -> 0 | W19: =IF(U19<-100000000,"no incumbent",MAX(V19,U19)-U19) -> 0 | X19: =SUMPRODUCT((D19:I19<>"")*(D13:I13="")*$K$3:$P$3)=Q13 -> TRUE
A20: Solves | J20: =COUNT(J13:J19) -> 7 | K20: Best plan, worth | N20: =MAX(U13:U19) -> 1680 | S20: Branched nodes x 2 + 1 = nodes: | W20: =2*SUMPRODUCT((Q13:Q19>0)*(T13:T19<>"pruned"))+1=COUNT(J13:J19) -> TRUE
A25: Credit | B25: Node row | C25: Pivot f | D25: Free? | E25: z1, pivot 0 | F25: z2, pivot 0 | G25: z3, pivot 0 | H25: z4, pivot 0 | I25: z5, pivot 0 | J25: z6, pivot 0 | K25: Z1, pivot 0 | L25: Z2, pivot 0 | M25: Z3, pivot 0 | N25: Z4, pivot 0 | O25: Z5, pivot 0 | P25: Z6, pivot 0 | Q25: term 1 | R25: term 2 | S25: term 3 | T25: term 4 | U25: term 5 | V25: term 6 | W25: A | X25: Pivot's value | Y25: z1 | Z25: z2 | AA25: z3 | AB25: z4 | AC25: z5 | AD25: z6 | AE25: Z1 | AF25: Z2 | AG25: Z3 | AH25: Z4 | AI25: Z5 | AJ25: Z6 | AK25: S1 | AL25: S2 | AM25: S3 | AN25: S4 | AO25: S5 | AP25: S6 | AQ25: Value
A26: =Credit_M -> 20 | B26: 5 | C26: 1 | D26: =IF($D$5="",1,0) -> 1 | E26: =IF($D$5<>"",$D$5,IF(1<C26,1,0)) -> 0 | F26: =IF($E$5<>"",$E$5,IF(2<C26,1,0)) -> 0 | G26: =IF($F$5<>"",$F$5,IF(3<C26,1,0)) -> 0 | H26: =IF($G$5<>"",$G$5,IF(4<C26,1,0)) -> 0 | I26: =IF($H$5<>"",$H$5,IF(5<C26,1,0)) -> 0 | J26: =IF($I$5<>"",$I$5,IF(6<C26,1,0)) -> 0 | K26: =SUM($E26:E26) -> 0 | L26: =SUM($E26:F26) -> 0 | M26: =SUM($E26:G26) -> 0 | N26: =SUM($E26:H26) -> 0 | O26: =SUM($E26:I26) -> 0 | P26: =SUM($E26:J26) -> 0 | Q26: =IF(1>=C26,POWER(Keep,K26-INDEX(K26:P26,C26)),0) -> 1 | R26: =IF(2>=C26,POWER(Keep,L26-INDEX(K26:P26,C26)),0) -> 1 | S26: =IF(3>=C26,POWER(Keep,M26-INDEX(K26:P26,C26)),0) -> 1 | T26: =IF(4>=C26,POWER(Keep,N26-INDEX(K26:P26,C26)),0) -> 1 | U26: =IF(5>=C26,POWER(Keep,O26-INDEX(K26:P26,C26)),0) -> 1 | V26: =IF(6>=C26,POWER(Keep,P26-INDEX(K26:P26,C26)),0) -> 1 | W26: =SUM(Q26:V26)+A26*POWER(Keep,P26-INDEX(K26:P26,C26)) -> 26 | X26: =MIN(1,MAX(0,LN(Cost_r/(Slope0*W26))/LN(Keep)-INDEX(K26:P26,C26))) -> 1 | Y26: =IF(1=C26,X26,E26) -> 1 | Z26: =IF(2=C26,X26,F26) -> 0 | AA26: =IF(3=C26,X26,G26) -> 0 | AB26: =IF(4=C26,X26,H26) -> 0 | AC26: =IF(5=C26,X26,I26) -> 0 | AD26: =IF(6=C26,X26,J26) -> 0 | AE26: =SUM($Y26:Y26) -> 1 | AF26: =SUM($Y26:Z26) -> 1 | AG26: =SUM($Y26:AA26) -> 1 | AH26: =SUM($Y26:AB26) -> 1 | AI26: =SUM($Y26:AC26) -> 1 | AJ26: =SUM($Y26:AD26) -> 1 | AK26: =Smax*(1-POWER(Keep,AE26)) -> 70 | AL26: =Smax*(1-POWER(Keep,AF26)) -> 70 | AM26: =Smax*(1-POWER(Keep,AG26)) -> 70 | AN26: =Smax*(1-POWER(Keep,AH26)) -> 70 | AO26: =Smax*(1-POWER(Keep,AI26)) -> 70 | AP26: =Smax*(1-POWER(Keep,AJ26)) -> 70 | AQ26: =IF(D26=1,Cash0+SUM(AK26:AP26)-Cost_r*AJ26+A26*AP26,-1000000000) -> 1850
A27: =Credit_M -> 20 | B27: 5 | C27: 2 | D27: =IF($E$5="",1,0) -> 1 | E27: =IF($D$5<>"",$D$5,IF(1<C27,1,0)) -> 1 | F27: =IF($E$5<>"",$E$5,IF(2<C27,1,0)) -> 0 | G27: =IF($F$5<>"",$F$5,IF(3<C27,1,0)) -> 0 | H27: =IF($G$5<>"",$G$5,IF(4<C27,1,0)) -> 0 | I27: =IF($H$5<>"",$H$5,IF(5<C27,1,0)) -> 0 | J27: =IF($I$5<>"",$I$5,IF(6<C27,1,0)) -> 0 | K27: =SUM($E27:E27) -> 1 | L27: =SUM($E27:F27) -> 1 | M27: =SUM($E27:G27) -> 1 | N27: =SUM($E27:H27) -> 1 | O27: =SUM($E27:I27) -> 1 | P27: =SUM($E27:J27) -> 1 | Q27: =IF(1>=C27,POWER(Keep,K27-INDEX(K27:P27,C27)),0) -> 0 | R27: =IF(2>=C27,POWER(Keep,L27-INDEX(K27:P27,C27)),0) -> 1 | S27: =IF(3>=C27,POWER(Keep,M27-INDEX(K27:P27,C27)),0) -> 1 | T27: =IF(4>=C27,POWER(Keep,N27-INDEX(K27:P27,C27)),0) -> 1 | U27: =IF(5>=C27,POWER(Keep,O27-INDEX(K27:P27,C27)),0) -> 1 | V27: =IF(6>=C27,POWER(Keep,P27-INDEX(K27:P27,C27)),0) -> 1 | W27: =SUM(Q27:V27)+A27*POWER(Keep,P27-INDEX(K27:P27,C27)) -> 25 | X27: =MIN(1,MAX(0,LN(Cost_r/(Slope0*W27))/LN(Keep)-INDEX(K27:P27,C27))) -> 1 | Y27: =IF(1=C27,X27,E27) -> 1 | Z27: =IF(2=C27,X27,F27) -> 1 | AA27: =IF(3=C27,X27,G27) -> 0 | AB27: =IF(4=C27,X27,H27) -> 0 | AC27: =IF(5=C27,X27,I27) -> 0 | AD27: =IF(6=C27,X27,J27) -> 0 | AE27: =SUM($Y27:Y27) -> 1 | AF27: =SUM($Y27:Z27) -> 2 | AG27: =SUM($Y27:AA27) -> 2 | AH27: =SUM($Y27:AB27) -> 2 | AI27: =SUM($Y27:AC27) -> 2 | AJ27: =SUM($Y27:AD27) -> 2 | AK27: =Smax*(1-POWER(Keep,AE27)) -> 70 | AL27: =Smax*(1-POWER(Keep,AF27)) -> 105 | AM27: =Smax*(1-POWER(Keep,AG27)) -> 105 | AN27: =Smax*(1-POWER(Keep,AH27)) -> 105 | AO27: =Smax*(1-POWER(Keep,AI27)) -> 105 | AP27: =Smax*(1-POWER(Keep,AJ27)) -> 105 | AQ27: =IF(D27=1,Cash0+SUM(AK27:AP27)-Cost_r*AJ27+A27*AP27,-1000000000) -> 2605
A28: =Credit_M -> 20 | B28: 5 | C28: 3 | D28: =IF($F$5="",1,0) -> 1 | E28: =IF($D$5<>"",$D$5,IF(1<C28,1,0)) -> 1 | F28: =IF($E$5<>"",$E$5,IF(2<C28,1,0)) -> 1 | G28: =IF($F$5<>"",$F$5,IF(3<C28,1,0)) -> 0 | H28: =IF($G$5<>"",$G$5,IF(4<C28,1,0)) -> 0 | I28: =IF($H$5<>"",$H$5,IF(5<C28,1,0)) -> 0 | J28: =IF($I$5<>"",$I$5,IF(6<C28,1,0)) -> 0 | K28: =SUM($E28:E28) -> 1 | L28: =SUM($E28:F28) -> 2 | M28: =SUM($E28:G28) -> 2 | N28: =SUM($E28:H28) -> 2 | O28: =SUM($E28:I28) -> 2 | P28: =SUM($E28:J28) -> 2 | Q28: =IF(1>=C28,POWER(Keep,K28-INDEX(K28:P28,C28)),0) -> 0 | R28: =IF(2>=C28,POWER(Keep,L28-INDEX(K28:P28,C28)),0) -> 0 | S28: =IF(3>=C28,POWER(Keep,M28-INDEX(K28:P28,C28)),0) -> 1 | T28: =IF(4>=C28,POWER(Keep,N28-INDEX(K28:P28,C28)),0) -> 1 | U28: =IF(5>=C28,POWER(Keep,O28-INDEX(K28:P28,C28)),0) -> 1 | V28: =IF(6>=C28,POWER(Keep,P28-INDEX(K28:P28,C28)),0) -> 1 | W28: =SUM(Q28:V28)+A28*POWER(Keep,P28-INDEX(K28:P28,C28)) -> 24 | X28: =MIN(1,MAX(0,LN(Cost_r/(Slope0*W28))/LN(Keep)-INDEX(K28:P28,C28))) -> 1 | Y28: =IF(1=C28,X28,E28) -> 1 | Z28: =IF(2=C28,X28,F28) -> 1 | AA28: =IF(3=C28,X28,G28) -> 1 | AB28: =IF(4=C28,X28,H28) -> 0 | AC28: =IF(5=C28,X28,I28) -> 0 | AD28: =IF(6=C28,X28,J28) -> 0 | AE28: =SUM($Y28:Y28) -> 1 | AF28: =SUM($Y28:Z28) -> 2 | AG28: =SUM($Y28:AA28) -> 3 | AH28: =SUM($Y28:AB28) -> 3 | AI28: =SUM($Y28:AC28) -> 3 | AJ28: =SUM($Y28:AD28) -> 3 | AK28: =Smax*(1-POWER(Keep,AE28)) -> 70 | AL28: =Smax*(1-POWER(Keep,AF28)) -> 105 | AM28: =Smax*(1-POWER(Keep,AG28)) -> 122.5 | AN28: =Smax*(1-POWER(Keep,AH28)) -> 122.5 | AO28: =Smax*(1-POWER(Keep,AI28)) -> 122.5 | AP28: =Smax*(1-POWER(Keep,AJ28)) -> 122.5 | AQ28: =IF(D28=1,Cash0+SUM(AK28:AP28)-Cost_r*AJ28+A28*AP28,-1000000000) -> 2905
A29: =Credit_M -> 20 | B29: 5 | C29: 4 | D29: =IF($G$5="",1,0) -> 1 | E29: =IF($D$5<>"",$D$5,IF(1<C29,1,0)) -> 1 | F29: =IF($E$5<>"",$E$5,IF(2<C29,1,0)) -> 1 | G29: =IF($F$5<>"",$F$5,IF(3<C29,1,0)) -> 1 | H29: =IF($G$5<>"",$G$5,IF(4<C29,1,0)) -> 0 | I29: =IF($H$5<>"",$H$5,IF(5<C29,1,0)) -> 0 | J29: =IF($I$5<>"",$I$5,IF(6<C29,1,0)) -> 0 | K29: =SUM($E29:E29) -> 1 | L29: =SUM($E29:F29) -> 2 | M29: =SUM($E29:G29) -> 3 | N29: =SUM($E29:H29) -> 3 | O29: =SUM($E29:I29) -> 3 | P29: =SUM($E29:J29) -> 3 | Q29: =IF(1>=C29,POWER(Keep,K29-INDEX(K29:P29,C29)),0) -> 0 | R29: =IF(2>=C29,POWER(Keep,L29-INDEX(K29:P29,C29)),0) -> 0 | S29: =IF(3>=C29,POWER(Keep,M29-INDEX(K29:P29,C29)),0) -> 0 | T29: =IF(4>=C29,POWER(Keep,N29-INDEX(K29:P29,C29)),0) -> 1 | U29: =IF(5>=C29,POWER(Keep,O29-INDEX(K29:P29,C29)),0) -> 1 | V29: =IF(6>=C29,POWER(Keep,P29-INDEX(K29:P29,C29)),0) -> 1 | W29: =SUM(Q29:V29)+A29*POWER(Keep,P29-INDEX(K29:P29,C29)) -> 23 | X29: =MIN(1,MAX(0,LN(Cost_r/(Slope0*W29))/LN(Keep)-INDEX(K29:P29,C29))) -> 1 | Y29: =IF(1=C29,X29,E29) -> 1 | Z29: =IF(2=C29,X29,F29) -> 1 | AA29: =IF(3=C29,X29,G29) -> 1 | AB29: =IF(4=C29,X29,H29) -> 1 | AC29: =IF(5=C29,X29,I29) -> 0 | AD29: =IF(6=C29,X29,J29) -> 0 | AE29: =SUM($Y29:Y29) -> 1 | AF29: =SUM($Y29:Z29) -> 2 | AG29: =SUM($Y29:AA29) -> 3 | AH29: =SUM($Y29:AB29) -> 4 | AI29: =SUM($Y29:AC29) -> 4 | AJ29: =SUM($Y29:AD29) -> 4 | AK29: =Smax*(1-POWER(Keep,AE29)) -> 70 | AL29: =Smax*(1-POWER(Keep,AF29)) -> 105 | AM29: =Smax*(1-POWER(Keep,AG29)) -> 122.5 | AN29: =Smax*(1-POWER(Keep,AH29)) -> 131.25 | AO29: =Smax*(1-POWER(Keep,AI29)) -> 131.25 | AP29: =Smax*(1-POWER(Keep,AJ29)) -> 131.25 | AQ29: =IF(D29=1,Cash0+SUM(AK29:AP29)-Cost_r*AJ29+A29*AP29,-1000000000) -> 2986.25
A30: =Credit_M -> 20 | B30: 5 | C30: 5 | D30: =IF($H$5="",1,0) -> 1 | E30: =IF($D$5<>"",$D$5,IF(1<C30,1,0)) -> 1 | F30: =IF($E$5<>"",$E$5,IF(2<C30,1,0)) -> 1 | G30: =IF($F$5<>"",$F$5,IF(3<C30,1,0)) -> 1 | H30: =IF($G$5<>"",$G$5,IF(4<C30,1,0)) -> 1 | I30: =IF($H$5<>"",$H$5,IF(5<C30,1,0)) -> 0 | J30: =IF($I$5<>"",$I$5,IF(6<C30,1,0)) -> 0 | K30: =SUM($E30:E30) -> 1 | L30: =SUM($E30:F30) -> 2 | M30: =SUM($E30:G30) -> 3 | N30: =SUM($E30:H30) -> 4 | O30: =SUM($E30:I30) -> 4 | P30: =SUM($E30:J30) -> 4 | Q30: =IF(1>=C30,POWER(Keep,K30-INDEX(K30:P30,C30)),0) -> 0 | R30: =IF(2>=C30,POWER(Keep,L30-INDEX(K30:P30,C30)),0) -> 0 | S30: =IF(3>=C30,POWER(Keep,M30-INDEX(K30:P30,C30)),0) -> 0 | T30: =IF(4>=C30,POWER(Keep,N30-INDEX(K30:P30,C30)),0) -> 0 | U30: =IF(5>=C30,POWER(Keep,O30-INDEX(K30:P30,C30)),0) -> 1 | V30: =IF(6>=C30,POWER(Keep,P30-INDEX(K30:P30,C30)),0) -> 1 | W30: =SUM(Q30:V30)+A30*POWER(Keep,P30-INDEX(K30:P30,C30)) -> 22 | X30: =MIN(1,MAX(0,LN(Cost_r/(Slope0*W30))/LN(Keep)-INDEX(K30:P30,C30))) -> 0.15305767 | Y30: =IF(1=C30,X30,E30) -> 1 | Z30: =IF(2=C30,X30,F30) -> 1 | AA30: =IF(3=C30,X30,G30) -> 1 | AB30: =IF(4=C30,X30,H30) -> 1 | AC30: =IF(5=C30,X30,I30) -> 0.15305767 | AD30: =IF(6=C30,X30,J30) -> 0 | AE30: =SUM($Y30:Y30) -> 1 | AF30: =SUM($Y30:Z30) -> 2 | AG30: =SUM($Y30:AA30) -> 3 | AH30: =SUM($Y30:AB30) -> 4 | AI30: =SUM($Y30:AC30) -> 4.1530577 | AJ30: =SUM($Y30:AD30) -> 4.1530577 | AK30: =Smax*(1-POWER(Keep,AE30)) -> 70 | AL30: =Smax*(1-POWER(Keep,AF30)) -> 105 | AM30: =Smax*(1-POWER(Keep,AG30)) -> 122.5 | AN30: =Smax*(1-POWER(Keep,AH30)) -> 131.25 | AO30: =Smax*(1-POWER(Keep,AI30)) -> 132.13075 | AP30: =Smax*(1-POWER(Keep,AJ30)) -> 132.13075 | AQ30: =IF(D30=1,Cash0+SUM(AK30:AP30)-Cost_r*AJ30+A30*AP30,-1000000000) -> 2987.2597
A31: =Credit_M -> 20 | B31: 5 | C31: 6 | D31: =IF($I$5="",1,0) -> 1 | E31: =IF($D$5<>"",$D$5,IF(1<C31,1,0)) -> 1 | F31: =IF($E$5<>"",$E$5,IF(2<C31,1,0)) -> 1 | G31: =IF($F$5<>"",$F$5,IF(3<C31,1,0)) -> 1 | H31: =IF($G$5<>"",$G$5,IF(4<C31,1,0)) -> 1 | I31: =IF($H$5<>"",$H$5,IF(5<C31,1,0)) -> 1 | J31: =IF($I$5<>"",$I$5,IF(6<C31,1,0)) -> 0 | K31: =SUM($E31:E31) -> 1 | L31: =SUM($E31:F31) -> 2 | M31: =SUM($E31:G31) -> 3 | N31: =SUM($E31:H31) -> 4 | O31: =SUM($E31:I31) -> 5 | P31: =SUM($E31:J31) -> 5 | Q31: =IF(1>=C31,POWER(Keep,K31-INDEX(K31:P31,C31)),0) -> 0 | R31: =IF(2>=C31,POWER(Keep,L31-INDEX(K31:P31,C31)),0) -> 0 | S31: =IF(3>=C31,POWER(Keep,M31-INDEX(K31:P31,C31)),0) -> 0 | T31: =IF(4>=C31,POWER(Keep,N31-INDEX(K31:P31,C31)),0) -> 0 | U31: =IF(5>=C31,POWER(Keep,O31-INDEX(K31:P31,C31)),0) -> 0 | V31: =IF(6>=C31,POWER(Keep,P31-INDEX(K31:P31,C31)),0) -> 1 | W31: =SUM(Q31:V31)+A31*POWER(Keep,P31-INDEX(K31:P31,C31)) -> 21 | X31: =MIN(1,MAX(0,LN(Cost_r/(Slope0*W31))/LN(Keep)-INDEX(K31:P31,C31))) -> 0 | Y31: =IF(1=C31,X31,E31) -> 1 | Z31: =IF(2=C31,X31,F31) -> 1 | AA31: =IF(3=C31,X31,G31) -> 1 | AB31: =IF(4=C31,X31,H31) -> 1 | AC31: =IF(5=C31,X31,I31) -> 1 | AD31: =IF(6=C31,X31,J31) -> 0 | AE31: =SUM($Y31:Y31) -> 1 | AF31: =SUM($Y31:Z31) -> 2 | AG31: =SUM($Y31:AA31) -> 3 | AH31: =SUM($Y31:AB31) -> 4 | AI31: =SUM($Y31:AC31) -> 5 | AJ31: =SUM($Y31:AD31) -> 5 | AK31: =Smax*(1-POWER(Keep,AE31)) -> 70 | AL31: =Smax*(1-POWER(Keep,AF31)) -> 105 | AM31: =Smax*(1-POWER(Keep,AG31)) -> 122.5 | AN31: =Smax*(1-POWER(Keep,AH31)) -> 131.25 | AO31: =Smax*(1-POWER(Keep,AI31)) -> 135.625 | AP31: =Smax*(1-POWER(Keep,AJ31)) -> 135.625 | AQ31: =IF(D31=1,Cash0+SUM(AK31:AP31)-Cost_r*AJ31+A31*AP31,-1000000000) -> 2962.5
A32: =Credit_M -> 20 | B32: 6 | C32: 1 | D32: =IF($D$6="",1,0) -> 1 | E32: =IF($D$6<>"",$D$6,IF(1<C32,1,0)) -> 0 | F32: =IF($E$6<>"",$E$6,IF(2<C32,1,0)) -> 0 | G32: =IF($F$6<>"",$F$6,IF(3<C32,1,0)) -> 0 | H32: =IF($G$6<>"",$G$6,IF(4<C32,1,0)) -> 0 | I32: =IF($H$6<>"",$H$6,IF(5<C32,1,0)) -> 0 | J32: =IF($I$6<>"",$I$6,IF(6<C32,1,0)) -> 0 | K32: =SUM($E32:E32) -> 0 | L32: =SUM($E32:F32) -> 0 | M32: =SUM($E32:G32) -> 0 | N32: =SUM($E32:H32) -> 0 | O32: =SUM($E32:I32) -> 0 | P32: =SUM($E32:J32) -> 0 | Q32: =IF(1>=C32,POWER(Keep,K32-INDEX(K32:P32,C32)),0) -> 1 | R32: =IF(2>=C32,POWER(Keep,L32-INDEX(K32:P32,C32)),0) -> 1 | S32: =IF(3>=C32,POWER(Keep,M32-INDEX(K32:P32,C32)),0) -> 1 | T32: =IF(4>=C32,POWER(Keep,N32-INDEX(K32:P32,C32)),0) -> 1 | U32: =IF(5>=C32,POWER(Keep,O32-INDEX(K32:P32,C32)),0) -> 1 | V32: =IF(6>=C32,POWER(Keep,P32-INDEX(K32:P32,C32)),0) -> 1 | W32: =SUM(Q32:V32)+A32*POWER(Keep,P32-INDEX(K32:P32,C32)) -> 26 | X32: =MIN(1,MAX(0,LN(Cost_r/(Slope0*W32))/LN(Keep)-INDEX(K32:P32,C32))) -> 1 | Y32: =IF(1=C32,X32,E32) -> 1 | Z32: =IF(2=C32,X32,F32) -> 0 | AA32: =IF(3=C32,X32,G32) -> 0 | AB32: =IF(4=C32,X32,H32) -> 0 | AC32: =IF(5=C32,X32,I32) -> 0 | AD32: =IF(6=C32,X32,J32) -> 0 | AE32: =SUM($Y32:Y32) -> 1 | AF32: =SUM($Y32:Z32) -> 1 | AG32: =SUM($Y32:AA32) -> 1 | AH32: =SUM($Y32:AB32) -> 1 | AI32: =SUM($Y32:AC32) -> 1 | AJ32: =SUM($Y32:AD32) -> 1 | AK32: =Smax*(1-POWER(Keep,AE32)) -> 70 | AL32: =Smax*(1-POWER(Keep,AF32)) -> 70 | AM32: =Smax*(1-POWER(Keep,AG32)) -> 70 | AN32: =Smax*(1-POWER(Keep,AH32)) -> 70 | AO32: =Smax*(1-POWER(Keep,AI32)) -> 70 | AP32: =Smax*(1-POWER(Keep,AJ32)) -> 70 | AQ32: =IF(D32=1,Cash0+SUM(AK32:AP32)-Cost_r*AJ32+A32*AP32,-1000000000) -> 1850
A33: =Credit_M -> 20 | B33: 6 | C33: 2 | D33: =IF($E$6="",1,0) -> 1 | E33: =IF($D$6<>"",$D$6,IF(1<C33,1,0)) -> 1 | F33: =IF($E$6<>"",$E$6,IF(2<C33,1,0)) -> 0 | G33: =IF($F$6<>"",$F$6,IF(3<C33,1,0)) -> 0 | H33: =IF($G$6<>"",$G$6,IF(4<C33,1,0)) -> 0 | I33: =IF($H$6<>"",$H$6,IF(5<C33,1,0)) -> 0 | J33: =IF($I$6<>"",$I$6,IF(6<C33,1,0)) -> 0 | K33: =SUM($E33:E33) -> 1 | L33: =SUM($E33:F33) -> 1 | M33: =SUM($E33:G33) -> 1 | N33: =SUM($E33:H33) -> 1 | O33: =SUM($E33:I33) -> 1 | P33: =SUM($E33:J33) -> 1 | Q33: =IF(1>=C33,POWER(Keep,K33-INDEX(K33:P33,C33)),0) -> 0 | R33: =IF(2>=C33,POWER(Keep,L33-INDEX(K33:P33,C33)),0) -> 1 | S33: =IF(3>=C33,POWER(Keep,M33-INDEX(K33:P33,C33)),0) -> 1 | T33: =IF(4>=C33,POWER(Keep,N33-INDEX(K33:P33,C33)),0) -> 1 | U33: =IF(5>=C33,POWER(Keep,O33-INDEX(K33:P33,C33)),0) -> 1 | V33: =IF(6>=C33,POWER(Keep,P33-INDEX(K33:P33,C33)),0) -> 1 | W33: =SUM(Q33:V33)+A33*POWER(Keep,P33-INDEX(K33:P33,C33)) -> 25 | X33: =MIN(1,MAX(0,LN(Cost_r/(Slope0*W33))/LN(Keep)-INDEX(K33:P33,C33))) -> 1 | Y33: =IF(1=C33,X33,E33) -> 1 | Z33: =IF(2=C33,X33,F33) -> 1 | AA33: =IF(3=C33,X33,G33) -> 0 | AB33: =IF(4=C33,X33,H33) -> 0 | AC33: =IF(5=C33,X33,I33) -> 0 | AD33: =IF(6=C33,X33,J33) -> 0 | AE33: =SUM($Y33:Y33) -> 1 | AF33: =SUM($Y33:Z33) -> 2 | AG33: =SUM($Y33:AA33) -> 2 | AH33: =SUM($Y33:AB33) -> 2 | AI33: =SUM($Y33:AC33) -> 2 | AJ33: =SUM($Y33:AD33) -> 2 | AK33: =Smax*(1-POWER(Keep,AE33)) -> 70 | AL33: =Smax*(1-POWER(Keep,AF33)) -> 105 | AM33: =Smax*(1-POWER(Keep,AG33)) -> 105 | AN33: =Smax*(1-POWER(Keep,AH33)) -> 105 | AO33: =Smax*(1-POWER(Keep,AI33)) -> 105 | AP33: =Smax*(1-POWER(Keep,AJ33)) -> 105 | AQ33: =IF(D33=1,Cash0+SUM(AK33:AP33)-Cost_r*AJ33+A33*AP33,-1000000000) -> 2605
A34: =Credit_M -> 20 | B34: 6 | C34: 3 | D34: =IF($F$6="",1,0) -> 1 | E34: =IF($D$6<>"",$D$6,IF(1<C34,1,0)) -> 1 | F34: =IF($E$6<>"",$E$6,IF(2<C34,1,0)) -> 1 | G34: =IF($F$6<>"",$F$6,IF(3<C34,1,0)) -> 0 | H34: =IF($G$6<>"",$G$6,IF(4<C34,1,0)) -> 0 | I34: =IF($H$6<>"",$H$6,IF(5<C34,1,0)) -> 0 | J34: =IF($I$6<>"",$I$6,IF(6<C34,1,0)) -> 0 | K34: =SUM($E34:E34) -> 1 | L34: =SUM($E34:F34) -> 2 | M34: =SUM($E34:G34) -> 2 | N34: =SUM($E34:H34) -> 2 | O34: =SUM($E34:I34) -> 2 | P34: =SUM($E34:J34) -> 2 | Q34: =IF(1>=C34,POWER(Keep,K34-INDEX(K34:P34,C34)),0) -> 0 | R34: =IF(2>=C34,POWER(Keep,L34-INDEX(K34:P34,C34)),0) -> 0 | S34: =IF(3>=C34,POWER(Keep,M34-INDEX(K34:P34,C34)),0) -> 1 | T34: =IF(4>=C34,POWER(Keep,N34-INDEX(K34:P34,C34)),0) -> 1 | U34: =IF(5>=C34,POWER(Keep,O34-INDEX(K34:P34,C34)),0) -> 1 | V34: =IF(6>=C34,POWER(Keep,P34-INDEX(K34:P34,C34)),0) -> 1 | W34: =SUM(Q34:V34)+A34*POWER(Keep,P34-INDEX(K34:P34,C34)) -> 24 | X34: =MIN(1,MAX(0,LN(Cost_r/(Slope0*W34))/LN(Keep)-INDEX(K34:P34,C34))) -> 1 | Y34: =IF(1=C34,X34,E34) -> 1 | Z34: =IF(2=C34,X34,F34) -> 1 | AA34: =IF(3=C34,X34,G34) -> 1 | AB34: =IF(4=C34,X34,H34) -> 0 | AC34: =IF(5=C34,X34,I34) -> 0 | AD34: =IF(6=C34,X34,J34) -> 0 | AE34: =SUM($Y34:Y34) -> 1 | AF34: =SUM($Y34:Z34) -> 2 | AG34: =SUM($Y34:AA34) -> 3 | AH34: =SUM($Y34:AB34) -> 3 | AI34: =SUM($Y34:AC34) -> 3 | AJ34: =SUM($Y34:AD34) -> 3 | AK34: =Smax*(1-POWER(Keep,AE34)) -> 70 | AL34: =Smax*(1-POWER(Keep,AF34)) -> 105 | AM34: =Smax*(1-POWER(Keep,AG34)) -> 122.5 | AN34: =Smax*(1-POWER(Keep,AH34)) -> 122.5 | AO34: =Smax*(1-POWER(Keep,AI34)) -> 122.5 | AP34: =Smax*(1-POWER(Keep,AJ34)) -> 122.5 | AQ34: =IF(D34=1,Cash0+SUM(AK34:AP34)-Cost_r*AJ34+A34*AP34,-1000000000) -> 2905
A35: =Credit_M -> 20 | B35: 6 | C35: 4 | D35: =IF($G$6="",1,0) -> 1 | E35: =IF($D$6<>"",$D$6,IF(1<C35,1,0)) -> 1 | F35: =IF($E$6<>"",$E$6,IF(2<C35,1,0)) -> 1 | G35: =IF($F$6<>"",$F$6,IF(3<C35,1,0)) -> 1 | H35: =IF($G$6<>"",$G$6,IF(4<C35,1,0)) -> 0 | I35: =IF($H$6<>"",$H$6,IF(5<C35,1,0)) -> 0 | J35: =IF($I$6<>"",$I$6,IF(6<C35,1,0)) -> 0 | K35: =SUM($E35:E35) -> 1 | L35: =SUM($E35:F35) -> 2 | M35: =SUM($E35:G35) -> 3 | N35: =SUM($E35:H35) -> 3 | O35: =SUM($E35:I35) -> 3 | P35: =SUM($E35:J35) -> 3 | Q35: =IF(1>=C35,POWER(Keep,K35-INDEX(K35:P35,C35)),0) -> 0 | R35: =IF(2>=C35,POWER(Keep,L35-INDEX(K35:P35,C35)),0) -> 0 | S35: =IF(3>=C35,POWER(Keep,M35-INDEX(K35:P35,C35)),0) -> 0 | T35: =IF(4>=C35,POWER(Keep,N35-INDEX(K35:P35,C35)),0) -> 1 | U35: =IF(5>=C35,POWER(Keep,O35-INDEX(K35:P35,C35)),0) -> 1 | V35: =IF(6>=C35,POWER(Keep,P35-INDEX(K35:P35,C35)),0) -> 1 | W35: =SUM(Q35:V35)+A35*POWER(Keep,P35-INDEX(K35:P35,C35)) -> 23 | X35: =MIN(1,MAX(0,LN(Cost_r/(Slope0*W35))/LN(Keep)-INDEX(K35:P35,C35))) -> 1 | Y35: =IF(1=C35,X35,E35) -> 1 | Z35: =IF(2=C35,X35,F35) -> 1 | AA35: =IF(3=C35,X35,G35) -> 1 | AB35: =IF(4=C35,X35,H35) -> 1 | AC35: =IF(5=C35,X35,I35) -> 0 | AD35: =IF(6=C35,X35,J35) -> 0 | AE35: =SUM($Y35:Y35) -> 1 | AF35: =SUM($Y35:Z35) -> 2 | AG35: =SUM($Y35:AA35) -> 3 | AH35: =SUM($Y35:AB35) -> 4 | AI35: =SUM($Y35:AC35) -> 4 | AJ35: =SUM($Y35:AD35) -> 4 | AK35: =Smax*(1-POWER(Keep,AE35)) -> 70 | AL35: =Smax*(1-POWER(Keep,AF35)) -> 105 | AM35: =Smax*(1-POWER(Keep,AG35)) -> 122.5 | AN35: =Smax*(1-POWER(Keep,AH35)) -> 131.25 | AO35: =Smax*(1-POWER(Keep,AI35)) -> 131.25 | AP35: =Smax*(1-POWER(Keep,AJ35)) -> 131.25 | AQ35: =IF(D35=1,Cash0+SUM(AK35:AP35)-Cost_r*AJ35+A35*AP35,-1000000000) -> 2986.25
A36: =Credit_M -> 20 | B36: 6 | C36: 5 | D36: =IF($H$6="",1,0) -> 0 | E36: =IF($D$6<>"",$D$6,IF(1<C36,1,0)) -> 1 | F36: =IF($E$6<>"",$E$6,IF(2<C36,1,0)) -> 1 | G36: =IF($F$6<>"",$F$6,IF(3<C36,1,0)) -> 1 | H36: =IF($G$6<>"",$G$6,IF(4<C36,1,0)) -> 1 | I36: =IF($H$6<>"",$H$6,IF(5<C36,1,0)) -> 0 | J36: =IF($I$6<>"",$I$6,IF(6<C36,1,0)) -> 0 | K36: =SUM($E36:E36) -> 1 | L36: =SUM($E36:F36) -> 2 | M36: =SUM($E36:G36) -> 3 | N36: =SUM($E36:H36) -> 4 | O36: =SUM($E36:I36) -> 4 | P36: =SUM($E36:J36) -> 4 | Q36: =IF(1>=C36,POWER(Keep,K36-INDEX(K36:P36,C36)),0) -> 0 | R36: =IF(2>=C36,POWER(Keep,L36-INDEX(K36:P36,C36)),0) -> 0 | S36: =IF(3>=C36,POWER(Keep,M36-INDEX(K36:P36,C36)),0) -> 0 | T36: =IF(4>=C36,POWER(Keep,N36-INDEX(K36:P36,C36)),0) -> 0 | U36: =IF(5>=C36,POWER(Keep,O36-INDEX(K36:P36,C36)),0) -> 1 | V36: =IF(6>=C36,POWER(Keep,P36-INDEX(K36:P36,C36)),0) -> 1 | W36: =SUM(Q36:V36)+A36*POWER(Keep,P36-INDEX(K36:P36,C36)) -> 22 | X36: =MIN(1,MAX(0,LN(Cost_r/(Slope0*W36))/LN(Keep)-INDEX(K36:P36,C36))) -> 0.15305767 | Y36: =IF(1=C36,X36,E36) -> 1 | Z36: =IF(2=C36,X36,F36) -> 1 | AA36: =IF(3=C36,X36,G36) -> 1 | AB36: =IF(4=C36,X36,H36) -> 1 | AC36: =IF(5=C36,X36,I36) -> 0.15305767 | AD36: =IF(6=C36,X36,J36) -> 0 | AE36: =SUM($Y36:Y36) -> 1 | AF36: =SUM($Y36:Z36) -> 2 | AG36: =SUM($Y36:AA36) -> 3 | AH36: =SUM($Y36:AB36) -> 4 | AI36: =SUM($Y36:AC36) -> 4.1530577 | AJ36: =SUM($Y36:AD36) -> 4.1530577 | AK36: =Smax*(1-POWER(Keep,AE36)) -> 70 | AL36: =Smax*(1-POWER(Keep,AF36)) -> 105 | AM36: =Smax*(1-POWER(Keep,AG36)) -> 122.5 | AN36: =Smax*(1-POWER(Keep,AH36)) -> 131.25 | AO36: =Smax*(1-POWER(Keep,AI36)) -> 132.13075 | AP36: =Smax*(1-POWER(Keep,AJ36)) -> 132.13075 | AQ36: =IF(D36=1,Cash0+SUM(AK36:AP36)-Cost_r*AJ36+A36*AP36,-1000000000) -> -1000000000
A37: =Credit_M -> 20 | B37: 6 | C37: 6 | D37: =IF($I$6="",1,0) -> 1 | E37: =IF($D$6<>"",$D$6,IF(1<C37,1,0)) -> 1 | F37: =IF($E$6<>"",$E$6,IF(2<C37,1,0)) -> 1 | G37: =IF($F$6<>"",$F$6,IF(3<C37,1,0)) -> 1 | H37: =IF($G$6<>"",$G$6,IF(4<C37,1,0)) -> 1 | I37: =IF($H$6<>"",$H$6,IF(5<C37,1,0)) -> 0 | J37: =IF($I$6<>"",$I$6,IF(6<C37,1,0)) -> 0 | K37: =SUM($E37:E37) -> 1 | L37: =SUM($E37:F37) -> 2 | M37: =SUM($E37:G37) -> 3 | N37: =SUM($E37:H37) -> 4 | O37: =SUM($E37:I37) -> 4 | P37: =SUM($E37:J37) -> 4 | Q37: =IF(1>=C37,POWER(Keep,K37-INDEX(K37:P37,C37)),0) -> 0 | R37: =IF(2>=C37,POWER(Keep,L37-INDEX(K37:P37,C37)),0) -> 0 | S37: =IF(3>=C37,POWER(Keep,M37-INDEX(K37:P37,C37)),0) -> 0 | T37: =IF(4>=C37,POWER(Keep,N37-INDEX(K37:P37,C37)),0) -> 0 | U37: =IF(5>=C37,POWER(Keep,O37-INDEX(K37:P37,C37)),0) -> 0 | V37: =IF(6>=C37,POWER(Keep,P37-INDEX(K37:P37,C37)),0) -> 1 | W37: =SUM(Q37:V37)+A37*POWER(Keep,P37-INDEX(K37:P37,C37)) -> 21 | X37: =MIN(1,MAX(0,LN(Cost_r/(Slope0*W37))/LN(Keep)-INDEX(K37:P37,C37))) -> 0.085943471 | Y37: =IF(1=C37,X37,E37) -> 1 | Z37: =IF(2=C37,X37,F37) -> 1 | AA37: =IF(3=C37,X37,G37) -> 1 | AB37: =IF(4=C37,X37,H37) -> 1 | AC37: =IF(5=C37,X37,I37) -> 0 | AD37: =IF(6=C37,X37,J37) -> 0.085943471 | AE37: =SUM($Y37:Y37) -> 1 | AF37: =SUM($Y37:Z37) -> 2 | AG37: =SUM($Y37:AA37) -> 3 | AH37: =SUM($Y37:AB37) -> 4 | AI37: =SUM($Y37:AC37) -> 4 | AJ37: =SUM($Y37:AD37) -> 4.0859435 | AK37: =Smax*(1-POWER(Keep,AE37)) -> 70 | AL37: =Smax*(1-POWER(Keep,AF37)) -> 105 | AM37: =Smax*(1-POWER(Keep,AG37)) -> 122.5 | AN37: =Smax*(1-POWER(Keep,AH37)) -> 131.25 | AO37: =Smax*(1-POWER(Keep,AI37)) -> 131.25 | AP37: =Smax*(1-POWER(Keep,AJ37)) -> 131.75603 | AQ37: =IF(D37=1,Cash0+SUM(AK37:AP37)-Cost_r*AJ37+A37*AP37,-1000000000) -> 2986.5634
A38: =Credit_M -> 20 | B38: 7 | C38: 1 | D38: =IF($D$7="",1,0) -> 1 | E38: =IF($D$7<>"",$D$7,IF(1<C38,1,0)) -> 0 | F38: =IF($E$7<>"",$E$7,IF(2<C38,1,0)) -> 0 | G38: =IF($F$7<>"",$F$7,IF(3<C38,1,0)) -> 0 | H38: =IF($G$7<>"",$G$7,IF(4<C38,1,0)) -> 0 | I38: =IF($H$7<>"",$H$7,IF(5<C38,1,0)) -> 0 | J38: =IF($I$7<>"",$I$7,IF(6<C38,1,0)) -> 0 | K38: =SUM($E38:E38) -> 0 | L38: =SUM($E38:F38) -> 0 | M38: =SUM($E38:G38) -> 0 | N38: =SUM($E38:H38) -> 0 | O38: =SUM($E38:I38) -> 0 | P38: =SUM($E38:J38) -> 0 | Q38: =IF(1>=C38,POWER(Keep,K38-INDEX(K38:P38,C38)),0) -> 1 | R38: =IF(2>=C38,POWER(Keep,L38-INDEX(K38:P38,C38)),0) -> 1 | S38: =IF(3>=C38,POWER(Keep,M38-INDEX(K38:P38,C38)),0) -> 1 | T38: =IF(4>=C38,POWER(Keep,N38-INDEX(K38:P38,C38)),0) -> 1 | U38: =IF(5>=C38,POWER(Keep,O38-INDEX(K38:P38,C38)),0) -> 1 | V38: =IF(6>=C38,POWER(Keep,P38-INDEX(K38:P38,C38)),0) -> 1 | W38: =SUM(Q38:V38)+A38*POWER(Keep,P38-INDEX(K38:P38,C38)) -> 26 | X38: =MIN(1,MAX(0,LN(Cost_r/(Slope0*W38))/LN(Keep)-INDEX(K38:P38,C38))) -> 1 | Y38: =IF(1=C38,X38,E38) -> 1 | Z38: =IF(2=C38,X38,F38) -> 0 | AA38: =IF(3=C38,X38,G38) -> 0 | AB38: =IF(4=C38,X38,H38) -> 0 | AC38: =IF(5=C38,X38,I38) -> 0 | AD38: =IF(6=C38,X38,J38) -> 0 | AE38: =SUM($Y38:Y38) -> 1 | AF38: =SUM($Y38:Z38) -> 1 | AG38: =SUM($Y38:AA38) -> 1 | AH38: =SUM($Y38:AB38) -> 1 | AI38: =SUM($Y38:AC38) -> 1 | AJ38: =SUM($Y38:AD38) -> 1 | AK38: =Smax*(1-POWER(Keep,AE38)) -> 70 | AL38: =Smax*(1-POWER(Keep,AF38)) -> 70 | AM38: =Smax*(1-POWER(Keep,AG38)) -> 70 | AN38: =Smax*(1-POWER(Keep,AH38)) -> 70 | AO38: =Smax*(1-POWER(Keep,AI38)) -> 70 | AP38: =Smax*(1-POWER(Keep,AJ38)) -> 70 | AQ38: =IF(D38=1,Cash0+SUM(AK38:AP38)-Cost_r*AJ38+A38*AP38,-1000000000) -> 1850
A39: =Credit_M -> 20 | B39: 7 | C39: 2 | D39: =IF($E$7="",1,0) -> 1 | E39: =IF($D$7<>"",$D$7,IF(1<C39,1,0)) -> 1 | F39: =IF($E$7<>"",$E$7,IF(2<C39,1,0)) -> 0 | G39: =IF($F$7<>"",$F$7,IF(3<C39,1,0)) -> 0 | H39: =IF($G$7<>"",$G$7,IF(4<C39,1,0)) -> 0 | I39: =IF($H$7<>"",$H$7,IF(5<C39,1,0)) -> 0 | J39: =IF($I$7<>"",$I$7,IF(6<C39,1,0)) -> 0 | K39: =SUM($E39:E39) -> 1 | L39: =SUM($E39:F39) -> 1 | M39: =SUM($E39:G39) -> 1 | N39: =SUM($E39:H39) -> 1 | O39: =SUM($E39:I39) -> 1 | P39: =SUM($E39:J39) -> 1 | Q39: =IF(1>=C39,POWER(Keep,K39-INDEX(K39:P39,C39)),0) -> 0 | R39: =IF(2>=C39,POWER(Keep,L39-INDEX(K39:P39,C39)),0) -> 1 | S39: =IF(3>=C39,POWER(Keep,M39-INDEX(K39:P39,C39)),0) -> 1 | T39: =IF(4>=C39,POWER(Keep,N39-INDEX(K39:P39,C39)),0) -> 1 | U39: =IF(5>=C39,POWER(Keep,O39-INDEX(K39:P39,C39)),0) -> 1 | V39: =IF(6>=C39,POWER(Keep,P39-INDEX(K39:P39,C39)),0) -> 1 | W39: =SUM(Q39:V39)+A39*POWER(Keep,P39-INDEX(K39:P39,C39)) -> 25 | X39: =MIN(1,MAX(0,LN(Cost_r/(Slope0*W39))/LN(Keep)-INDEX(K39:P39,C39))) -> 1 | Y39: =IF(1=C39,X39,E39) -> 1 | Z39: =IF(2=C39,X39,F39) -> 1 | AA39: =IF(3=C39,X39,G39) -> 0 | AB39: =IF(4=C39,X39,H39) -> 0 | AC39: =IF(5=C39,X39,I39) -> 0 | AD39: =IF(6=C39,X39,J39) -> 0 | AE39: =SUM($Y39:Y39) -> 1 | AF39: =SUM($Y39:Z39) -> 2 | AG39: =SUM($Y39:AA39) -> 2 | AH39: =SUM($Y39:AB39) -> 2 | AI39: =SUM($Y39:AC39) -> 2 | AJ39: =SUM($Y39:AD39) -> 2 | AK39: =Smax*(1-POWER(Keep,AE39)) -> 70 | AL39: =Smax*(1-POWER(Keep,AF39)) -> 105 | AM39: =Smax*(1-POWER(Keep,AG39)) -> 105 | AN39: =Smax*(1-POWER(Keep,AH39)) -> 105 | AO39: =Smax*(1-POWER(Keep,AI39)) -> 105 | AP39: =Smax*(1-POWER(Keep,AJ39)) -> 105 | AQ39: =IF(D39=1,Cash0+SUM(AK39:AP39)-Cost_r*AJ39+A39*AP39,-1000000000) -> 2605
A40: =Credit_M -> 20 | B40: 7 | C40: 3 | D40: =IF($F$7="",1,0) -> 1 | E40: =IF($D$7<>"",$D$7,IF(1<C40,1,0)) -> 1 | F40: =IF($E$7<>"",$E$7,IF(2<C40,1,0)) -> 1 | G40: =IF($F$7<>"",$F$7,IF(3<C40,1,0)) -> 0 | H40: =IF($G$7<>"",$G$7,IF(4<C40,1,0)) -> 0 | I40: =IF($H$7<>"",$H$7,IF(5<C40,1,0)) -> 0 | J40: =IF($I$7<>"",$I$7,IF(6<C40,1,0)) -> 0 | K40: =SUM($E40:E40) -> 1 | L40: =SUM($E40:F40) -> 2 | M40: =SUM($E40:G40) -> 2 | N40: =SUM($E40:H40) -> 2 | O40: =SUM($E40:I40) -> 2 | P40: =SUM($E40:J40) -> 2 | Q40: =IF(1>=C40,POWER(Keep,K40-INDEX(K40:P40,C40)),0) -> 0 | R40: =IF(2>=C40,POWER(Keep,L40-INDEX(K40:P40,C40)),0) -> 0 | S40: =IF(3>=C40,POWER(Keep,M40-INDEX(K40:P40,C40)),0) -> 1 | T40: =IF(4>=C40,POWER(Keep,N40-INDEX(K40:P40,C40)),0) -> 1 | U40: =IF(5>=C40,POWER(Keep,O40-INDEX(K40:P40,C40)),0) -> 1 | V40: =IF(6>=C40,POWER(Keep,P40-INDEX(K40:P40,C40)),0) -> 1 | W40: =SUM(Q40:V40)+A40*POWER(Keep,P40-INDEX(K40:P40,C40)) -> 24 | X40: =MIN(1,MAX(0,LN(Cost_r/(Slope0*W40))/LN(Keep)-INDEX(K40:P40,C40))) -> 1 | Y40: =IF(1=C40,X40,E40) -> 1 | Z40: =IF(2=C40,X40,F40) -> 1 | AA40: =IF(3=C40,X40,G40) -> 1 | AB40: =IF(4=C40,X40,H40) -> 0 | AC40: =IF(5=C40,X40,I40) -> 0 | AD40: =IF(6=C40,X40,J40) -> 0 | AE40: =SUM($Y40:Y40) -> 1 | AF40: =SUM($Y40:Z40) -> 2 | AG40: =SUM($Y40:AA40) -> 3 | AH40: =SUM($Y40:AB40) -> 3 | AI40: =SUM($Y40:AC40) -> 3 | AJ40: =SUM($Y40:AD40) -> 3 | AK40: =Smax*(1-POWER(Keep,AE40)) -> 70 | AL40: =Smax*(1-POWER(Keep,AF40)) -> 105 | AM40: =Smax*(1-POWER(Keep,AG40)) -> 122.5 | AN40: =Smax*(1-POWER(Keep,AH40)) -> 122.5 | AO40: =Smax*(1-POWER(Keep,AI40)) -> 122.5 | AP40: =Smax*(1-POWER(Keep,AJ40)) -> 122.5 | AQ40: =IF(D40=1,Cash0+SUM(AK40:AP40)-Cost_r*AJ40+A40*AP40,-1000000000) -> 2905
A41: =Credit_M -> 20 | B41: 7 | C41: 4 | D41: =IF($G$7="",1,0) -> 1 | E41: =IF($D$7<>"",$D$7,IF(1<C41,1,0)) -> 1 | F41: =IF($E$7<>"",$E$7,IF(2<C41,1,0)) -> 1 | G41: =IF($F$7<>"",$F$7,IF(3<C41,1,0)) -> 1 | H41: =IF($G$7<>"",$G$7,IF(4<C41,1,0)) -> 0 | I41: =IF($H$7<>"",$H$7,IF(5<C41,1,0)) -> 0 | J41: =IF($I$7<>"",$I$7,IF(6<C41,1,0)) -> 0 | K41: =SUM($E41:E41) -> 1 | L41: =SUM($E41:F41) -> 2 | M41: =SUM($E41:G41) -> 3 | N41: =SUM($E41:H41) -> 3 | O41: =SUM($E41:I41) -> 3 | P41: =SUM($E41:J41) -> 3 | Q41: =IF(1>=C41,POWER(Keep,K41-INDEX(K41:P41,C41)),0) -> 0 | R41: =IF(2>=C41,POWER(Keep,L41-INDEX(K41:P41,C41)),0) -> 0 | S41: =IF(3>=C41,POWER(Keep,M41-INDEX(K41:P41,C41)),0) -> 0 | T41: =IF(4>=C41,POWER(Keep,N41-INDEX(K41:P41,C41)),0) -> 1 | U41: =IF(5>=C41,POWER(Keep,O41-INDEX(K41:P41,C41)),0) -> 1 | V41: =IF(6>=C41,POWER(Keep,P41-INDEX(K41:P41,C41)),0) -> 1 | W41: =SUM(Q41:V41)+A41*POWER(Keep,P41-INDEX(K41:P41,C41)) -> 23 | X41: =MIN(1,MAX(0,LN(Cost_r/(Slope0*W41))/LN(Keep)-INDEX(K41:P41,C41))) -> 1 | Y41: =IF(1=C41,X41,E41) -> 1 | Z41: =IF(2=C41,X41,F41) -> 1 | AA41: =IF(3=C41,X41,G41) -> 1 | AB41: =IF(4=C41,X41,H41) -> 1 | AC41: =IF(5=C41,X41,I41) -> 0 | AD41: =IF(6=C41,X41,J41) -> 0 | AE41: =SUM($Y41:Y41) -> 1 | AF41: =SUM($Y41:Z41) -> 2 | AG41: =SUM($Y41:AA41) -> 3 | AH41: =SUM($Y41:AB41) -> 4 | AI41: =SUM($Y41:AC41) -> 4 | AJ41: =SUM($Y41:AD41) -> 4 | AK41: =Smax*(1-POWER(Keep,AE41)) -> 70 | AL41: =Smax*(1-POWER(Keep,AF41)) -> 105 | AM41: =Smax*(1-POWER(Keep,AG41)) -> 122.5 | AN41: =Smax*(1-POWER(Keep,AH41)) -> 131.25 | AO41: =Smax*(1-POWER(Keep,AI41)) -> 131.25 | AP41: =Smax*(1-POWER(Keep,AJ41)) -> 131.25 | AQ41: =IF(D41=1,Cash0+SUM(AK41:AP41)-Cost_r*AJ41+A41*AP41,-1000000000) -> 2986.25
A42: =Credit_M -> 20 | B42: 7 | C42: 5 | D42: =IF($H$7="",1,0) -> 0 | E42: =IF($D$7<>"",$D$7,IF(1<C42,1,0)) -> 1 | F42: =IF($E$7<>"",$E$7,IF(2<C42,1,0)) -> 1 | G42: =IF($F$7<>"",$F$7,IF(3<C42,1,0)) -> 1 | H42: =IF($G$7<>"",$G$7,IF(4<C42,1,0)) -> 1 | I42: =IF($H$7<>"",$H$7,IF(5<C42,1,0)) -> 0 | J42: =IF($I$7<>"",$I$7,IF(6<C42,1,0)) -> 0 | K42: =SUM($E42:E42) -> 1 | L42: =SUM($E42:F42) -> 2 | M42: =SUM($E42:G42) -> 3 | N42: =SUM($E42:H42) -> 4 | O42: =SUM($E42:I42) -> 4 | P42: =SUM($E42:J42) -> 4 | Q42: =IF(1>=C42,POWER(Keep,K42-INDEX(K42:P42,C42)),0) -> 0 | R42: =IF(2>=C42,POWER(Keep,L42-INDEX(K42:P42,C42)),0) -> 0 | S42: =IF(3>=C42,POWER(Keep,M42-INDEX(K42:P42,C42)),0) -> 0 | T42: =IF(4>=C42,POWER(Keep,N42-INDEX(K42:P42,C42)),0) -> 0 | U42: =IF(5>=C42,POWER(Keep,O42-INDEX(K42:P42,C42)),0) -> 1 | V42: =IF(6>=C42,POWER(Keep,P42-INDEX(K42:P42,C42)),0) -> 1 | W42: =SUM(Q42:V42)+A42*POWER(Keep,P42-INDEX(K42:P42,C42)) -> 22 | X42: =MIN(1,MAX(0,LN(Cost_r/(Slope0*W42))/LN(Keep)-INDEX(K42:P42,C42))) -> 0.15305767 | Y42: =IF(1=C42,X42,E42) -> 1 | Z42: =IF(2=C42,X42,F42) -> 1 | AA42: =IF(3=C42,X42,G42) -> 1 | AB42: =IF(4=C42,X42,H42) -> 1 | AC42: =IF(5=C42,X42,I42) -> 0.15305767 | AD42: =IF(6=C42,X42,J42) -> 0 | AE42: =SUM($Y42:Y42) -> 1 | AF42: =SUM($Y42:Z42) -> 2 | AG42: =SUM($Y42:AA42) -> 3 | AH42: =SUM($Y42:AB42) -> 4 | AI42: =SUM($Y42:AC42) -> 4.1530577 | AJ42: =SUM($Y42:AD42) -> 4.1530577 | AK42: =Smax*(1-POWER(Keep,AE42)) -> 70 | AL42: =Smax*(1-POWER(Keep,AF42)) -> 105 | AM42: =Smax*(1-POWER(Keep,AG42)) -> 122.5 | AN42: =Smax*(1-POWER(Keep,AH42)) -> 131.25 | AO42: =Smax*(1-POWER(Keep,AI42)) -> 132.13075 | AP42: =Smax*(1-POWER(Keep,AJ42)) -> 132.13075 | AQ42: =IF(D42=1,Cash0+SUM(AK42:AP42)-Cost_r*AJ42+A42*AP42,-1000000000) -> -1000000000
A43: =Credit_M -> 20 | B43: 7 | C43: 6 | D43: =IF($I$7="",1,0) -> 0 | E43: =IF($D$7<>"",$D$7,IF(1<C43,1,0)) -> 1 | F43: =IF($E$7<>"",$E$7,IF(2<C43,1,0)) -> 1 | G43: =IF($F$7<>"",$F$7,IF(3<C43,1,0)) -> 1 | H43: =IF($G$7<>"",$G$7,IF(4<C43,1,0)) -> 1 | I43: =IF($H$7<>"",$H$7,IF(5<C43,1,0)) -> 0 | J43: =IF($I$7<>"",$I$7,IF(6<C43,1,0)) -> 0 | K43: =SUM($E43:E43) -> 1 | L43: =SUM($E43:F43) -> 2 | M43: =SUM($E43:G43) -> 3 | N43: =SUM($E43:H43) -> 4 | O43: =SUM($E43:I43) -> 4 | P43: =SUM($E43:J43) -> 4 | Q43: =IF(1>=C43,POWER(Keep,K43-INDEX(K43:P43,C43)),0) -> 0 | R43: =IF(2>=C43,POWER(Keep,L43-INDEX(K43:P43,C43)),0) -> 0 | S43: =IF(3>=C43,POWER(Keep,M43-INDEX(K43:P43,C43)),0) -> 0 | T43: =IF(4>=C43,POWER(Keep,N43-INDEX(K43:P43,C43)),0) -> 0 | U43: =IF(5>=C43,POWER(Keep,O43-INDEX(K43:P43,C43)),0) -> 0 | V43: =IF(6>=C43,POWER(Keep,P43-INDEX(K43:P43,C43)),0) -> 1 | W43: =SUM(Q43:V43)+A43*POWER(Keep,P43-INDEX(K43:P43,C43)) -> 21 | X43: =MIN(1,MAX(0,LN(Cost_r/(Slope0*W43))/LN(Keep)-INDEX(K43:P43,C43))) -> 0.085943471 | Y43: =IF(1=C43,X43,E43) -> 1 | Z43: =IF(2=C43,X43,F43) -> 1 | AA43: =IF(3=C43,X43,G43) -> 1 | AB43: =IF(4=C43,X43,H43) -> 1 | AC43: =IF(5=C43,X43,I43) -> 0 | AD43: =IF(6=C43,X43,J43) -> 0.085943471 | AE43: =SUM($Y43:Y43) -> 1 | AF43: =SUM($Y43:Z43) -> 2 | AG43: =SUM($Y43:AA43) -> 3 | AH43: =SUM($Y43:AB43) -> 4 | AI43: =SUM($Y43:AC43) -> 4 | AJ43: =SUM($Y43:AD43) -> 4.0859435 | AK43: =Smax*(1-POWER(Keep,AE43)) -> 70 | AL43: =Smax*(1-POWER(Keep,AF43)) -> 105 | AM43: =Smax*(1-POWER(Keep,AG43)) -> 122.5 | AN43: =Smax*(1-POWER(Keep,AH43)) -> 131.25 | AO43: =Smax*(1-POWER(Keep,AI43)) -> 131.25 | AP43: =Smax*(1-POWER(Keep,AJ43)) -> 131.75603 | AQ43: =IF(D43=1,Cash0+SUM(AK43:AP43)-Cost_r*AJ43+A43*AP43,-1000000000) -> -1000000000
A44: =Credit_M -> 20 | B44: 8 | C44: 1 | D44: =IF($D$8="",1,0) -> 1 | E44: =IF($D$8<>"",$D$8,IF(1<C44,1,0)) -> 0 | F44: =IF($E$8<>"",$E$8,IF(2<C44,1,0)) -> 0 | G44: =IF($F$8<>"",$F$8,IF(3<C44,1,0)) -> 0 | H44: =IF($G$8<>"",$G$8,IF(4<C44,1,0)) -> 0 | I44: =IF($H$8<>"",$H$8,IF(5<C44,1,0)) -> 0 | J44: =IF($I$8<>"",$I$8,IF(6<C44,1,0)) -> 1 | K44: =SUM($E44:E44) -> 0 | L44: =SUM($E44:F44) -> 0 | M44: =SUM($E44:G44) -> 0 | N44: =SUM($E44:H44) -> 0 | O44: =SUM($E44:I44) -> 0 | P44: =SUM($E44:J44) -> 1 | Q44: =IF(1>=C44,POWER(Keep,K44-INDEX(K44:P44,C44)),0) -> 1 | R44: =IF(2>=C44,POWER(Keep,L44-INDEX(K44:P44,C44)),0) -> 1 | S44: =IF(3>=C44,POWER(Keep,M44-INDEX(K44:P44,C44)),0) -> 1 | T44: =IF(4>=C44,POWER(Keep,N44-INDEX(K44:P44,C44)),0) -> 1 | U44: =IF(5>=C44,POWER(Keep,O44-INDEX(K44:P44,C44)),0) -> 1 | V44: =IF(6>=C44,POWER(Keep,P44-INDEX(K44:P44,C44)),0) -> 0.5 | W44: =SUM(Q44:V44)+A44*POWER(Keep,P44-INDEX(K44:P44,C44)) -> 15.5 | X44: =MIN(1,MAX(0,LN(Cost_r/(Slope0*W44))/LN(Keep)-INDEX(K44:P44,C44))) -> 1 | Y44: =IF(1=C44,X44,E44) -> 1 | Z44: =IF(2=C44,X44,F44) -> 0 | AA44: =IF(3=C44,X44,G44) -> 0 | AB44: =IF(4=C44,X44,H44) -> 0 | AC44: =IF(5=C44,X44,I44) -> 0 | AD44: =IF(6=C44,X44,J44) -> 1 | AE44: =SUM($Y44:Y44) -> 1 | AF44: =SUM($Y44:Z44) -> 1 | AG44: =SUM($Y44:AA44) -> 1 | AH44: =SUM($Y44:AB44) -> 1 | AI44: =SUM($Y44:AC44) -> 1 | AJ44: =SUM($Y44:AD44) -> 2 | AK44: =Smax*(1-POWER(Keep,AE44)) -> 70 | AL44: =Smax*(1-POWER(Keep,AF44)) -> 70 | AM44: =Smax*(1-POWER(Keep,AG44)) -> 70 | AN44: =Smax*(1-POWER(Keep,AH44)) -> 70 | AO44: =Smax*(1-POWER(Keep,AI44)) -> 70 | AP44: =Smax*(1-POWER(Keep,AJ44)) -> 105 | AQ44: =IF(D44=1,Cash0+SUM(AK44:AP44)-Cost_r*AJ44+A44*AP44,-1000000000) -> 2465
A45: =Credit_M -> 20 | B45: 8 | C45: 2 | D45: =IF($E$8="",1,0) -> 1 | E45: =IF($D$8<>"",$D$8,IF(1<C45,1,0)) -> 1 | F45: =IF($E$8<>"",$E$8,IF(2<C45,1,0)) -> 0 | G45: =IF($F$8<>"",$F$8,IF(3<C45,1,0)) -> 0 | H45: =IF($G$8<>"",$G$8,IF(4<C45,1,0)) -> 0 | I45: =IF($H$8<>"",$H$8,IF(5<C45,1,0)) -> 0 | J45: =IF($I$8<>"",$I$8,IF(6<C45,1,0)) -> 1 | K45: =SUM($E45:E45) -> 1 | L45: =SUM($E45:F45) -> 1 | M45: =SUM($E45:G45) -> 1 | N45: =SUM($E45:H45) -> 1 | O45: =SUM($E45:I45) -> 1 | P45: =SUM($E45:J45) -> 2 | Q45: =IF(1>=C45,POWER(Keep,K45-INDEX(K45:P45,C45)),0) -> 0 | R45: =IF(2>=C45,POWER(Keep,L45-INDEX(K45:P45,C45)),0) -> 1 | S45: =IF(3>=C45,POWER(Keep,M45-INDEX(K45:P45,C45)),0) -> 1 | T45: =IF(4>=C45,POWER(Keep,N45-INDEX(K45:P45,C45)),0) -> 1 | U45: =IF(5>=C45,POWER(Keep,O45-INDEX(K45:P45,C45)),0) -> 1 | V45: =IF(6>=C45,POWER(Keep,P45-INDEX(K45:P45,C45)),0) -> 0.5 | W45: =SUM(Q45:V45)+A45*POWER(Keep,P45-INDEX(K45:P45,C45)) -> 14.5 | X45: =MIN(1,MAX(0,LN(Cost_r/(Slope0*W45))/LN(Keep)-INDEX(K45:P45,C45))) -> 1 | Y45: =IF(1=C45,X45,E45) -> 1 | Z45: =IF(2=C45,X45,F45) -> 1 | AA45: =IF(3=C45,X45,G45) -> 0 | AB45: =IF(4=C45,X45,H45) -> 0 | AC45: =IF(5=C45,X45,I45) -> 0 | AD45: =IF(6=C45,X45,J45) -> 1 | AE45: =SUM($Y45:Y45) -> 1 | AF45: =SUM($Y45:Z45) -> 2 | AG45: =SUM($Y45:AA45) -> 2 | AH45: =SUM($Y45:AB45) -> 2 | AI45: =SUM($Y45:AC45) -> 2 | AJ45: =SUM($Y45:AD45) -> 3 | AK45: =Smax*(1-POWER(Keep,AE45)) -> 70 | AL45: =Smax*(1-POWER(Keep,AF45)) -> 105 | AM45: =Smax*(1-POWER(Keep,AG45)) -> 105 | AN45: =Smax*(1-POWER(Keep,AH45)) -> 105 | AO45: =Smax*(1-POWER(Keep,AI45)) -> 105 | AP45: =Smax*(1-POWER(Keep,AJ45)) -> 122.5 | AQ45: =IF(D45=1,Cash0+SUM(AK45:AP45)-Cost_r*AJ45+A45*AP45,-1000000000) -> 2852.5
A46: =Credit_M -> 20 | B46: 8 | C46: 3 | D46: =IF($F$8="",1,0) -> 1 | E46: =IF($D$8<>"",$D$8,IF(1<C46,1,0)) -> 1 | F46: =IF($E$8<>"",$E$8,IF(2<C46,1,0)) -> 1 | G46: =IF($F$8<>"",$F$8,IF(3<C46,1,0)) -> 0 | H46: =IF($G$8<>"",$G$8,IF(4<C46,1,0)) -> 0 | I46: =IF($H$8<>"",$H$8,IF(5<C46,1,0)) -> 0 | J46: =IF($I$8<>"",$I$8,IF(6<C46,1,0)) -> 1 | K46: =SUM($E46:E46) -> 1 | L46: =SUM($E46:F46) -> 2 | M46: =SUM($E46:G46) -> 2 | N46: =SUM($E46:H46) -> 2 | O46: =SUM($E46:I46) -> 2 | P46: =SUM($E46:J46) -> 3 | Q46: =IF(1>=C46,POWER(Keep,K46-INDEX(K46:P46,C46)),0) -> 0 | R46: =IF(2>=C46,POWER(Keep,L46-INDEX(K46:P46,C46)),0) -> 0 | S46: =IF(3>=C46,POWER(Keep,M46-INDEX(K46:P46,C46)),0) -> 1 | T46: =IF(4>=C46,POWER(Keep,N46-INDEX(K46:P46,C46)),0) -> 1 | U46: =IF(5>=C46,POWER(Keep,O46-INDEX(K46:P46,C46)),0) -> 1 | V46: =IF(6>=C46,POWER(Keep,P46-INDEX(K46:P46,C46)),0) -> 0.5 | W46: =SUM(Q46:V46)+A46*POWER(Keep,P46-INDEX(K46:P46,C46)) -> 13.5 | X46: =MIN(1,MAX(0,LN(Cost_r/(Slope0*W46))/LN(Keep)-INDEX(K46:P46,C46))) -> 1 | Y46: =IF(1=C46,X46,E46) -> 1 | Z46: =IF(2=C46,X46,F46) -> 1 | AA46: =IF(3=C46,X46,G46) -> 1 | AB46: =IF(4=C46,X46,H46) -> 0 | AC46: =IF(5=C46,X46,I46) -> 0 | AD46: =IF(6=C46,X46,J46) -> 1 | AE46: =SUM($Y46:Y46) -> 1 | AF46: =SUM($Y46:Z46) -> 2 | AG46: =SUM($Y46:AA46) -> 3 | AH46: =SUM($Y46:AB46) -> 3 | AI46: =SUM($Y46:AC46) -> 3 | AJ46: =SUM($Y46:AD46) -> 4 | AK46: =Smax*(1-POWER(Keep,AE46)) -> 70 | AL46: =Smax*(1-POWER(Keep,AF46)) -> 105 | AM46: =Smax*(1-POWER(Keep,AG46)) -> 122.5 | AN46: =Smax*(1-POWER(Keep,AH46)) -> 122.5 | AO46: =Smax*(1-POWER(Keep,AI46)) -> 122.5 | AP46: =Smax*(1-POWER(Keep,AJ46)) -> 131.25 | AQ46: =IF(D46=1,Cash0+SUM(AK46:AP46)-Cost_r*AJ46+A46*AP46,-1000000000) -> 2968.75
A47: =Credit_M -> 20 | B47: 8 | C47: 4 | D47: =IF($G$8="",1,0) -> 1 | E47: =IF($D$8<>"",$D$8,IF(1<C47,1,0)) -> 1 | F47: =IF($E$8<>"",$E$8,IF(2<C47,1,0)) -> 1 | G47: =IF($F$8<>"",$F$8,IF(3<C47,1,0)) -> 1 | H47: =IF($G$8<>"",$G$8,IF(4<C47,1,0)) -> 0 | I47: =IF($H$8<>"",$H$8,IF(5<C47,1,0)) -> 0 | J47: =IF($I$8<>"",$I$8,IF(6<C47,1,0)) -> 1 | K47: =SUM($E47:E47) -> 1 | L47: =SUM($E47:F47) -> 2 | M47: =SUM($E47:G47) -> 3 | N47: =SUM($E47:H47) -> 3 | O47: =SUM($E47:I47) -> 3 | P47: =SUM($E47:J47) -> 4 | Q47: =IF(1>=C47,POWER(Keep,K47-INDEX(K47:P47,C47)),0) -> 0 | R47: =IF(2>=C47,POWER(Keep,L47-INDEX(K47:P47,C47)),0) -> 0 | S47: =IF(3>=C47,POWER(Keep,M47-INDEX(K47:P47,C47)),0) -> 0 | T47: =IF(4>=C47,POWER(Keep,N47-INDEX(K47:P47,C47)),0) -> 1 | U47: =IF(5>=C47,POWER(Keep,O47-INDEX(K47:P47,C47)),0) -> 1 | V47: =IF(6>=C47,POWER(Keep,P47-INDEX(K47:P47,C47)),0) -> 0.5 | W47: =SUM(Q47:V47)+A47*POWER(Keep,P47-INDEX(K47:P47,C47)) -> 12.5 | X47: =MIN(1,MAX(0,LN(Cost_r/(Slope0*W47))/LN(Keep)-INDEX(K47:P47,C47))) -> 0.33748224 | Y47: =IF(1=C47,X47,E47) -> 1 | Z47: =IF(2=C47,X47,F47) -> 1 | AA47: =IF(3=C47,X47,G47) -> 1 | AB47: =IF(4=C47,X47,H47) -> 0.33748224 | AC47: =IF(5=C47,X47,I47) -> 0 | AD47: =IF(6=C47,X47,J47) -> 1 | AE47: =SUM($Y47:Y47) -> 1 | AF47: =SUM($Y47:Z47) -> 2 | AG47: =SUM($Y47:AA47) -> 3 | AH47: =SUM($Y47:AB47) -> 3.3374822 | AI47: =SUM($Y47:AC47) -> 3.3374822 | AJ47: =SUM($Y47:AD47) -> 4.3374822 | AK47: =Smax*(1-POWER(Keep,AE47)) -> 70 | AL47: =Smax*(1-POWER(Keep,AF47)) -> 105 | AM47: =Smax*(1-POWER(Keep,AG47)) -> 122.5 | AN47: =Smax*(1-POWER(Keep,AH47)) -> 126.15013 | AO47: =Smax*(1-POWER(Keep,AI47)) -> 126.15013 | AP47: =Smax*(1-POWER(Keep,AJ47)) -> 133.07506 | AQ47: =IF(D47=1,Cash0+SUM(AK47:AP47)-Cost_r*AJ47+A47*AP47,-1000000000) -> 2973.8787
A48: =Credit_M -> 20 | B48: 8 | C48: 5 | D48: =IF($H$8="",1,0) -> 0 | E48: =IF($D$8<>"",$D$8,IF(1<C48,1,0)) -> 1 | F48: =IF($E$8<>"",$E$8,IF(2<C48,1,0)) -> 1 | G48: =IF($F$8<>"",$F$8,IF(3<C48,1,0)) -> 1 | H48: =IF($G$8<>"",$G$8,IF(4<C48,1,0)) -> 1 | I48: =IF($H$8<>"",$H$8,IF(5<C48,1,0)) -> 0 | J48: =IF($I$8<>"",$I$8,IF(6<C48,1,0)) -> 1 | K48: =SUM($E48:E48) -> 1 | L48: =SUM($E48:F48) -> 2 | M48: =SUM($E48:G48) -> 3 | N48: =SUM($E48:H48) -> 4 | O48: =SUM($E48:I48) -> 4 | P48: =SUM($E48:J48) -> 5 | Q48: =IF(1>=C48,POWER(Keep,K48-INDEX(K48:P48,C48)),0) -> 0 | R48: =IF(2>=C48,POWER(Keep,L48-INDEX(K48:P48,C48)),0) -> 0 | S48: =IF(3>=C48,POWER(Keep,M48-INDEX(K48:P48,C48)),0) -> 0 | T48: =IF(4>=C48,POWER(Keep,N48-INDEX(K48:P48,C48)),0) -> 0 | U48: =IF(5>=C48,POWER(Keep,O48-INDEX(K48:P48,C48)),0) -> 1 | V48: =IF(6>=C48,POWER(Keep,P48-INDEX(K48:P48,C48)),0) -> 0.5 | W48: =SUM(Q48:V48)+A48*POWER(Keep,P48-INDEX(K48:P48,C48)) -> 11.5 | X48: =MIN(1,MAX(0,LN(Cost_r/(Slope0*W48))/LN(Keep)-INDEX(K48:P48,C48))) -> 0 | Y48: =IF(1=C48,X48,E48) -> 1 | Z48: =IF(2=C48,X48,F48) -> 1 | AA48: =IF(3=C48,X48,G48) -> 1 | AB48: =IF(4=C48,X48,H48) -> 1 | AC48: =IF(5=C48,X48,I48) -> 0 | AD48: =IF(6=C48,X48,J48) -> 1 | AE48: =SUM($Y48:Y48) -> 1 | AF48: =SUM($Y48:Z48) -> 2 | AG48: =SUM($Y48:AA48) -> 3 | AH48: =SUM($Y48:AB48) -> 4 | AI48: =SUM($Y48:AC48) -> 4 | AJ48: =SUM($Y48:AD48) -> 5 | AK48: =Smax*(1-POWER(Keep,AE48)) -> 70 | AL48: =Smax*(1-POWER(Keep,AF48)) -> 105 | AM48: =Smax*(1-POWER(Keep,AG48)) -> 122.5 | AN48: =Smax*(1-POWER(Keep,AH48)) -> 131.25 | AO48: =Smax*(1-POWER(Keep,AI48)) -> 131.25 | AP48: =Smax*(1-POWER(Keep,AJ48)) -> 135.625 | AQ48: =IF(D48=1,Cash0+SUM(AK48:AP48)-Cost_r*AJ48+A48*AP48,-1000000000) -> -1000000000
A49: =Credit_M -> 20 | B49: 8 | C49: 6 | D49: =IF($I$8="",1,0) -> 0 | E49: =IF($D$8<>"",$D$8,IF(1<C49,1,0)) -> 1 | F49: =IF($E$8<>"",$E$8,IF(2<C49,1,0)) -> 1 | G49: =IF($F$8<>"",$F$8,IF(3<C49,1,0)) -> 1 | H49: =IF($G$8<>"",$G$8,IF(4<C49,1,0)) -> 1 | I49: =IF($H$8<>"",$H$8,IF(5<C49,1,0)) -> 0 | J49: =IF($I$8<>"",$I$8,IF(6<C49,1,0)) -> 1 | K49: =SUM($E49:E49) -> 1 | L49: =SUM($E49:F49) -> 2 | M49: =SUM($E49:G49) -> 3 | N49: =SUM($E49:H49) -> 4 | O49: =SUM($E49:I49) -> 4 | P49: =SUM($E49:J49) -> 5 | Q49: =IF(1>=C49,POWER(Keep,K49-INDEX(K49:P49,C49)),0) -> 0 | R49: =IF(2>=C49,POWER(Keep,L49-INDEX(K49:P49,C49)),0) -> 0 | S49: =IF(3>=C49,POWER(Keep,M49-INDEX(K49:P49,C49)),0) -> 0 | T49: =IF(4>=C49,POWER(Keep,N49-INDEX(K49:P49,C49)),0) -> 0 | U49: =IF(5>=C49,POWER(Keep,O49-INDEX(K49:P49,C49)),0) -> 0 | V49: =IF(6>=C49,POWER(Keep,P49-INDEX(K49:P49,C49)),0) -> 1 | W49: =SUM(Q49:V49)+A49*POWER(Keep,P49-INDEX(K49:P49,C49)) -> 21 | X49: =MIN(1,MAX(0,LN(Cost_r/(Slope0*W49))/LN(Keep)-INDEX(K49:P49,C49))) -> 0 | Y49: =IF(1=C49,X49,E49) -> 1 | Z49: =IF(2=C49,X49,F49) -> 1 | AA49: =IF(3=C49,X49,G49) -> 1 | AB49: =IF(4=C49,X49,H49) -> 1 | AC49: =IF(5=C49,X49,I49) -> 0 | AD49: =IF(6=C49,X49,J49) -> 0 | AE49: =SUM($Y49:Y49) -> 1 | AF49: =SUM($Y49:Z49) -> 2 | AG49: =SUM($Y49:AA49) -> 3 | AH49: =SUM($Y49:AB49) -> 4 | AI49: =SUM($Y49:AC49) -> 4 | AJ49: =SUM($Y49:AD49) -> 4 | AK49: =Smax*(1-POWER(Keep,AE49)) -> 70 | AL49: =Smax*(1-POWER(Keep,AF49)) -> 105 | AM49: =Smax*(1-POWER(Keep,AG49)) -> 122.5 | AN49: =Smax*(1-POWER(Keep,AH49)) -> 131.25 | AO49: =Smax*(1-POWER(Keep,AI49)) -> 131.25 | AP49: =Smax*(1-POWER(Keep,AJ49)) -> 131.25 | AQ49: =IF(D49=1,Cash0+SUM(AK49:AP49)-Cost_r*AJ49+A49*AP49,-1000000000) -> -1000000000
A50: =Credit_M -> 20 | B50: 9 | C50: 1 | D50: =IF($D$9="",1,0) -> 1 | E50: =IF($D$9<>"",$D$9,IF(1<C50,1,0)) -> 0 | F50: =IF($E$9<>"",$E$9,IF(2<C50,1,0)) -> 0 | G50: =IF($F$9<>"",$F$9,IF(3<C50,1,0)) -> 0 | H50: =IF($G$9<>"",$G$9,IF(4<C50,1,0)) -> 0 | I50: =IF($H$9<>"",$H$9,IF(5<C50,1,0)) -> 1 | J50: =IF($I$9<>"",$I$9,IF(6<C50,1,0)) -> 0 | K50: =SUM($E50:E50) -> 0 | L50: =SUM($E50:F50) -> 0 | M50: =SUM($E50:G50) -> 0 | N50: =SUM($E50:H50) -> 0 | O50: =SUM($E50:I50) -> 1 | P50: =SUM($E50:J50) -> 1 | Q50: =IF(1>=C50,POWER(Keep,K50-INDEX(K50:P50,C50)),0) -> 1 | R50: =IF(2>=C50,POWER(Keep,L50-INDEX(K50:P50,C50)),0) -> 1 | S50: =IF(3>=C50,POWER(Keep,M50-INDEX(K50:P50,C50)),0) -> 1 | T50: =IF(4>=C50,POWER(Keep,N50-INDEX(K50:P50,C50)),0) -> 1 | U50: =IF(5>=C50,POWER(Keep,O50-INDEX(K50:P50,C50)),0) -> 0.5 | V50: =IF(6>=C50,POWER(Keep,P50-INDEX(K50:P50,C50)),0) -> 0.5 | W50: =SUM(Q50:V50)+A50*POWER(Keep,P50-INDEX(K50:P50,C50)) -> 15 | X50: =MIN(1,MAX(0,LN(Cost_r/(Slope0*W50))/LN(Keep)-INDEX(K50:P50,C50))) -> 1 | Y50: =IF(1=C50,X50,E50) -> 1 | Z50: =IF(2=C50,X50,F50) -> 0 | AA50: =IF(3=C50,X50,G50) -> 0 | AB50: =IF(4=C50,X50,H50) -> 0 | AC50: =IF(5=C50,X50,I50) -> 1 | AD50: =IF(6=C50,X50,J50) -> 0 | AE50: =SUM($Y50:Y50) -> 1 | AF50: =SUM($Y50:Z50) -> 1 | AG50: =SUM($Y50:AA50) -> 1 | AH50: =SUM($Y50:AB50) -> 1 | AI50: =SUM($Y50:AC50) -> 2 | AJ50: =SUM($Y50:AD50) -> 2 | AK50: =Smax*(1-POWER(Keep,AE50)) -> 70 | AL50: =Smax*(1-POWER(Keep,AF50)) -> 70 | AM50: =Smax*(1-POWER(Keep,AG50)) -> 70 | AN50: =Smax*(1-POWER(Keep,AH50)) -> 70 | AO50: =Smax*(1-POWER(Keep,AI50)) -> 105 | AP50: =Smax*(1-POWER(Keep,AJ50)) -> 105 | AQ50: =IF(D50=1,Cash0+SUM(AK50:AP50)-Cost_r*AJ50+A50*AP50,-1000000000) -> 2500
A51: =Credit_M -> 20 | B51: 9 | C51: 2 | D51: =IF($E$9="",1,0) -> 1 | E51: =IF($D$9<>"",$D$9,IF(1<C51,1,0)) -> 1 | F51: =IF($E$9<>"",$E$9,IF(2<C51,1,0)) -> 0 | G51: =IF($F$9<>"",$F$9,IF(3<C51,1,0)) -> 0 | H51: =IF($G$9<>"",$G$9,IF(4<C51,1,0)) -> 0 | I51: =IF($H$9<>"",$H$9,IF(5<C51,1,0)) -> 1 | J51: =IF($I$9<>"",$I$9,IF(6<C51,1,0)) -> 0 | K51: =SUM($E51:E51) -> 1 | L51: =SUM($E51:F51) -> 1 | M51: =SUM($E51:G51) -> 1 | N51: =SUM($E51:H51) -> 1 | O51: =SUM($E51:I51) -> 2 | P51: =SUM($E51:J51) -> 2 | Q51: =IF(1>=C51,POWER(Keep,K51-INDEX(K51:P51,C51)),0) -> 0 | R51: =IF(2>=C51,POWER(Keep,L51-INDEX(K51:P51,C51)),0) -> 1 | S51: =IF(3>=C51,POWER(Keep,M51-INDEX(K51:P51,C51)),0) -> 1 | T51: =IF(4>=C51,POWER(Keep,N51-INDEX(K51:P51,C51)),0) -> 1 | U51: =IF(5>=C51,POWER(Keep,O51-INDEX(K51:P51,C51)),0) -> 0.5 | V51: =IF(6>=C51,POWER(Keep,P51-INDEX(K51:P51,C51)),0) -> 0.5 | W51: =SUM(Q51:V51)+A51*POWER(Keep,P51-INDEX(K51:P51,C51)) -> 14 | X51: =MIN(1,MAX(0,LN(Cost_r/(Slope0*W51))/LN(Keep)-INDEX(K51:P51,C51))) -> 1 | Y51: =IF(1=C51,X51,E51) -> 1 | Z51: =IF(2=C51,X51,F51) -> 1 | AA51: =IF(3=C51,X51,G51) -> 0 | AB51: =IF(4=C51,X51,H51) -> 0 | AC51: =IF(5=C51,X51,I51) -> 1 | AD51: =IF(6=C51,X51,J51) -> 0 | AE51: =SUM($Y51:Y51) -> 1 | AF51: =SUM($Y51:Z51) -> 2 | AG51: =SUM($Y51:AA51) -> 2 | AH51: =SUM($Y51:AB51) -> 2 | AI51: =SUM($Y51:AC51) -> 3 | AJ51: =SUM($Y51:AD51) -> 3 | AK51: =Smax*(1-POWER(Keep,AE51)) -> 70 | AL51: =Smax*(1-POWER(Keep,AF51)) -> 105 | AM51: =Smax*(1-POWER(Keep,AG51)) -> 105 | AN51: =Smax*(1-POWER(Keep,AH51)) -> 105 | AO51: =Smax*(1-POWER(Keep,AI51)) -> 122.5 | AP51: =Smax*(1-POWER(Keep,AJ51)) -> 122.5 | AQ51: =IF(D51=1,Cash0+SUM(AK51:AP51)-Cost_r*AJ51+A51*AP51,-1000000000) -> 2870
A52: =Credit_M -> 20 | B52: 9 | C52: 3 | D52: =IF($F$9="",1,0) -> 1 | E52: =IF($D$9<>"",$D$9,IF(1<C52,1,0)) -> 1 | F52: =IF($E$9<>"",$E$9,IF(2<C52,1,0)) -> 1 | G52: =IF($F$9<>"",$F$9,IF(3<C52,1,0)) -> 0 | H52: =IF($G$9<>"",$G$9,IF(4<C52,1,0)) -> 0 | I52: =IF($H$9<>"",$H$9,IF(5<C52,1,0)) -> 1 | J52: =IF($I$9<>"",$I$9,IF(6<C52,1,0)) -> 0 | K52: =SUM($E52:E52) -> 1 | L52: =SUM($E52:F52) -> 2 | M52: =SUM($E52:G52) -> 2 | N52: =SUM($E52:H52) -> 2 | O52: =SUM($E52:I52) -> 3 | P52: =SUM($E52:J52) -> 3 | Q52: =IF(1>=C52,POWER(Keep,K52-INDEX(K52:P52,C52)),0) -> 0 | R52: =IF(2>=C52,POWER(Keep,L52-INDEX(K52:P52,C52)),0) -> 0 | S52: =IF(3>=C52,POWER(Keep,M52-INDEX(K52:P52,C52)),0) -> 1 | T52: =IF(4>=C52,POWER(Keep,N52-INDEX(K52:P52,C52)),0) -> 1 | U52: =IF(5>=C52,POWER(Keep,O52-INDEX(K52:P52,C52)),0) -> 0.5 | V52: =IF(6>=C52,POWER(Keep,P52-INDEX(K52:P52,C52)),0) -> 0.5 | W52: =SUM(Q52:V52)+A52*POWER(Keep,P52-INDEX(K52:P52,C52)) -> 13 | X52: =MIN(1,MAX(0,LN(Cost_r/(Slope0*W52))/LN(Keep)-INDEX(K52:P52,C52))) -> 1 | Y52: =IF(1=C52,X52,E52) -> 1 | Z52: =IF(2=C52,X52,F52) -> 1 | AA52: =IF(3=C52,X52,G52) -> 1 | AB52: =IF(4=C52,X52,H52) -> 0 | AC52: =IF(5=C52,X52,I52) -> 1 | AD52: =IF(6=C52,X52,J52) -> 0 | AE52: =SUM($Y52:Y52) -> 1 | AF52: =SUM($Y52:Z52) -> 2 | AG52: =SUM($Y52:AA52) -> 3 | AH52: =SUM($Y52:AB52) -> 3 | AI52: =SUM($Y52:AC52) -> 4 | AJ52: =SUM($Y52:AD52) -> 4 | AK52: =Smax*(1-POWER(Keep,AE52)) -> 70 | AL52: =Smax*(1-POWER(Keep,AF52)) -> 105 | AM52: =Smax*(1-POWER(Keep,AG52)) -> 122.5 | AN52: =Smax*(1-POWER(Keep,AH52)) -> 122.5 | AO52: =Smax*(1-POWER(Keep,AI52)) -> 131.25 | AP52: =Smax*(1-POWER(Keep,AJ52)) -> 131.25 | AQ52: =IF(D52=1,Cash0+SUM(AK52:AP52)-Cost_r*AJ52+A52*AP52,-1000000000) -> 2977.5
A53: =Credit_M -> 20 | B53: 9 | C53: 4 | D53: =IF($G$9="",1,0) -> 1 | E53: =IF($D$9<>"",$D$9,IF(1<C53,1,0)) -> 1 | F53: =IF($E$9<>"",$E$9,IF(2<C53,1,0)) -> 1 | G53: =IF($F$9<>"",$F$9,IF(3<C53,1,0)) -> 1 | H53: =IF($G$9<>"",$G$9,IF(4<C53,1,0)) -> 0 | I53: =IF($H$9<>"",$H$9,IF(5<C53,1,0)) -> 1 | J53: =IF($I$9<>"",$I$9,IF(6<C53,1,0)) -> 0 | K53: =SUM($E53:E53) -> 1 | L53: =SUM($E53:F53) -> 2 | M53: =SUM($E53:G53) -> 3 | N53: =SUM($E53:H53) -> 3 | O53: =SUM($E53:I53) -> 4 | P53: =SUM($E53:J53) -> 4 | Q53: =IF(1>=C53,POWER(Keep,K53-INDEX(K53:P53,C53)),0) -> 0 | R53: =IF(2>=C53,POWER(Keep,L53-INDEX(K53:P53,C53)),0) -> 0 | S53: =IF(3>=C53,POWER(Keep,M53-INDEX(K53:P53,C53)),0) -> 0 | T53: =IF(4>=C53,POWER(Keep,N53-INDEX(K53:P53,C53)),0) -> 1 | U53: =IF(5>=C53,POWER(Keep,O53-INDEX(K53:P53,C53)),0) -> 0.5 | V53: =IF(6>=C53,POWER(Keep,P53-INDEX(K53:P53,C53)),0) -> 0.5 | W53: =SUM(Q53:V53)+A53*POWER(Keep,P53-INDEX(K53:P53,C53)) -> 12 | X53: =MIN(1,MAX(0,LN(Cost_r/(Slope0*W53))/LN(Keep)-INDEX(K53:P53,C53))) -> 0.27858855 | Y53: =IF(1=C53,X53,E53) -> 1 | Z53: =IF(2=C53,X53,F53) -> 1 | AA53: =IF(3=C53,X53,G53) -> 1 | AB53: =IF(4=C53,X53,H53) -> 0.27858855 | AC53: =IF(5=C53,X53,I53) -> 1 | AD53: =IF(6=C53,X53,J53) -> 0 | AE53: =SUM($Y53:Y53) -> 1 | AF53: =SUM($Y53:Z53) -> 2 | AG53: =SUM($Y53:AA53) -> 3 | AH53: =SUM($Y53:AB53) -> 3.2785885 | AI53: =SUM($Y53:AC53) -> 4.2785885 | AJ53: =SUM($Y53:AD53) -> 4.2785885 | AK53: =Smax*(1-POWER(Keep,AE53)) -> 70 | AL53: =Smax*(1-POWER(Keep,AF53)) -> 105 | AM53: =Smax*(1-POWER(Keep,AG53)) -> 122.5 | AN53: =Smax*(1-POWER(Keep,AH53)) -> 125.57305 | AO53: =Smax*(1-POWER(Keep,AI53)) -> 132.78652 | AP53: =Smax*(1-POWER(Keep,AJ53)) -> 132.78652 | AQ53: =IF(D53=1,Cash0+SUM(AK53:AP53)-Cost_r*AJ53+A53*AP53,-1000000000) -> 2980.946
A54: =Credit_M -> 20 | B54: 9 | C54: 5 | D54: =IF($H$9="",1,0) -> 0 | E54: =IF($D$9<>"",$D$9,IF(1<C54,1,0)) -> 1 | F54: =IF($E$9<>"",$E$9,IF(2<C54,1,0)) -> 1 | G54: =IF($F$9<>"",$F$9,IF(3<C54,1,0)) -> 1 | H54: =IF($G$9<>"",$G$9,IF(4<C54,1,0)) -> 1 | I54: =IF($H$9<>"",$H$9,IF(5<C54,1,0)) -> 1 | J54: =IF($I$9<>"",$I$9,IF(6<C54,1,0)) -> 0 | K54: =SUM($E54:E54) -> 1 | L54: =SUM($E54:F54) -> 2 | M54: =SUM($E54:G54) -> 3 | N54: =SUM($E54:H54) -> 4 | O54: =SUM($E54:I54) -> 5 | P54: =SUM($E54:J54) -> 5 | Q54: =IF(1>=C54,POWER(Keep,K54-INDEX(K54:P54,C54)),0) -> 0 | R54: =IF(2>=C54,POWER(Keep,L54-INDEX(K54:P54,C54)),0) -> 0 | S54: =IF(3>=C54,POWER(Keep,M54-INDEX(K54:P54,C54)),0) -> 0 | T54: =IF(4>=C54,POWER(Keep,N54-INDEX(K54:P54,C54)),0) -> 0 | U54: =IF(5>=C54,POWER(Keep,O54-INDEX(K54:P54,C54)),0) -> 1 | V54: =IF(6>=C54,POWER(Keep,P54-INDEX(K54:P54,C54)),0) -> 1 | W54: =SUM(Q54:V54)+A54*POWER(Keep,P54-INDEX(K54:P54,C54)) -> 22 | X54: =MIN(1,MAX(0,LN(Cost_r/(Slope0*W54))/LN(Keep)-INDEX(K54:P54,C54))) -> 0 | Y54: =IF(1=C54,X54,E54) -> 1 | Z54: =IF(2=C54,X54,F54) -> 1 | AA54: =IF(3=C54,X54,G54) -> 1 | AB54: =IF(4=C54,X54,H54) -> 1 | AC54: =IF(5=C54,X54,I54) -> 0 | AD54: =IF(6=C54,X54,J54) -> 0 | AE54: =SUM($Y54:Y54) -> 1 | AF54: =SUM($Y54:Z54) -> 2 | AG54: =SUM($Y54:AA54) -> 3 | AH54: =SUM($Y54:AB54) -> 4 | AI54: =SUM($Y54:AC54) -> 4 | AJ54: =SUM($Y54:AD54) -> 4 | AK54: =Smax*(1-POWER(Keep,AE54)) -> 70 | AL54: =Smax*(1-POWER(Keep,AF54)) -> 105 | AM54: =Smax*(1-POWER(Keep,AG54)) -> 122.5 | AN54: =Smax*(1-POWER(Keep,AH54)) -> 131.25 | AO54: =Smax*(1-POWER(Keep,AI54)) -> 131.25 | AP54: =Smax*(1-POWER(Keep,AJ54)) -> 131.25 | AQ54: =IF(D54=1,Cash0+SUM(AK54:AP54)-Cost_r*AJ54+A54*AP54,-1000000000) -> -1000000000
A55: =Credit_M -> 20 | B55: 9 | C55: 6 | D55: =IF($I$9="",1,0) -> 1 | E55: =IF($D$9<>"",$D$9,IF(1<C55,1,0)) -> 1 | F55: =IF($E$9<>"",$E$9,IF(2<C55,1,0)) -> 1 | G55: =IF($F$9<>"",$F$9,IF(3<C55,1,0)) -> 1 | H55: =IF($G$9<>"",$G$9,IF(4<C55,1,0)) -> 1 | I55: =IF($H$9<>"",$H$9,IF(5<C55,1,0)) -> 1 | J55: =IF($I$9<>"",$I$9,IF(6<C55,1,0)) -> 0 | K55: =SUM($E55:E55) -> 1 | L55: =SUM($E55:F55) -> 2 | M55: =SUM($E55:G55) -> 3 | N55: =SUM($E55:H55) -> 4 | O55: =SUM($E55:I55) -> 5 | P55: =SUM($E55:J55) -> 5 | Q55: =IF(1>=C55,POWER(Keep,K55-INDEX(K55:P55,C55)),0) -> 0 | R55: =IF(2>=C55,POWER(Keep,L55-INDEX(K55:P55,C55)),0) -> 0 | S55: =IF(3>=C55,POWER(Keep,M55-INDEX(K55:P55,C55)),0) -> 0 | T55: =IF(4>=C55,POWER(Keep,N55-INDEX(K55:P55,C55)),0) -> 0 | U55: =IF(5>=C55,POWER(Keep,O55-INDEX(K55:P55,C55)),0) -> 0 | V55: =IF(6>=C55,POWER(Keep,P55-INDEX(K55:P55,C55)),0) -> 1 | W55: =SUM(Q55:V55)+A55*POWER(Keep,P55-INDEX(K55:P55,C55)) -> 21 | X55: =MIN(1,MAX(0,LN(Cost_r/(Slope0*W55))/LN(Keep)-INDEX(K55:P55,C55))) -> 0 | Y55: =IF(1=C55,X55,E55) -> 1 | Z55: =IF(2=C55,X55,F55) -> 1 | AA55: =IF(3=C55,X55,G55) -> 1 | AB55: =IF(4=C55,X55,H55) -> 1 | AC55: =IF(5=C55,X55,I55) -> 1 | AD55: =IF(6=C55,X55,J55) -> 0 | AE55: =SUM($Y55:Y55) -> 1 | AF55: =SUM($Y55:Z55) -> 2 | AG55: =SUM($Y55:AA55) -> 3 | AH55: =SUM($Y55:AB55) -> 4 | AI55: =SUM($Y55:AC55) -> 5 | AJ55: =SUM($Y55:AD55) -> 5 | AK55: =Smax*(1-POWER(Keep,AE55)) -> 70 | AL55: =Smax*(1-POWER(Keep,AF55)) -> 105 | AM55: =Smax*(1-POWER(Keep,AG55)) -> 122.5 | AN55: =Smax*(1-POWER(Keep,AH55)) -> 131.25 | AO55: =Smax*(1-POWER(Keep,AI55)) -> 135.625 | AP55: =Smax*(1-POWER(Keep,AJ55)) -> 135.625 | AQ55: =IF(D55=1,Cash0+SUM(AK55:AP55)-Cost_r*AJ55+A55*AP55,-1000000000) -> 2962.5
A56: =Credit_10 -> 10 | B56: 13 | C56: 1 | D56: =IF($D$13="",1,0) -> 1 | E56: =IF($D$13<>"",$D$13,IF(1<C56,1,0)) -> 0 | F56: =IF($E$13<>"",$E$13,IF(2<C56,1,0)) -> 0 | G56: =IF($F$13<>"",$F$13,IF(3<C56,1,0)) -> 0 | H56: =IF($G$13<>"",$G$13,IF(4<C56,1,0)) -> 0 | I56: =IF($H$13<>"",$H$13,IF(5<C56,1,0)) -> 0 | J56: =IF($I$13<>"",$I$13,IF(6<C56,1,0)) -> 0 | K56: =SUM($E56:E56) -> 0 | L56: =SUM($E56:F56) -> 0 | M56: =SUM($E56:G56) -> 0 | N56: =SUM($E56:H56) -> 0 | O56: =SUM($E56:I56) -> 0 | P56: =SUM($E56:J56) -> 0 | Q56: =IF(1>=C56,POWER(Keep,K56-INDEX(K56:P56,C56)),0) -> 1 | R56: =IF(2>=C56,POWER(Keep,L56-INDEX(K56:P56,C56)),0) -> 1 | S56: =IF(3>=C56,POWER(Keep,M56-INDEX(K56:P56,C56)),0) -> 1 | T56: =IF(4>=C56,POWER(Keep,N56-INDEX(K56:P56,C56)),0) -> 1 | U56: =IF(5>=C56,POWER(Keep,O56-INDEX(K56:P56,C56)),0) -> 1 | V56: =IF(6>=C56,POWER(Keep,P56-INDEX(K56:P56,C56)),0) -> 1 | W56: =SUM(Q56:V56)+A56*POWER(Keep,P56-INDEX(K56:P56,C56)) -> 16 | X56: =MIN(1,MAX(0,LN(Cost_r/(Slope0*W56))/LN(Keep)-INDEX(K56:P56,C56))) -> 1 | Y56: =IF(1=C56,X56,E56) -> 1 | Z56: =IF(2=C56,X56,F56) -> 0 | AA56: =IF(3=C56,X56,G56) -> 0 | AB56: =IF(4=C56,X56,H56) -> 0 | AC56: =IF(5=C56,X56,I56) -> 0 | AD56: =IF(6=C56,X56,J56) -> 0 | AE56: =SUM($Y56:Y56) -> 1 | AF56: =SUM($Y56:Z56) -> 1 | AG56: =SUM($Y56:AA56) -> 1 | AH56: =SUM($Y56:AB56) -> 1 | AI56: =SUM($Y56:AC56) -> 1 | AJ56: =SUM($Y56:AD56) -> 1 | AK56: =Smax*(1-POWER(Keep,AE56)) -> 70 | AL56: =Smax*(1-POWER(Keep,AF56)) -> 70 | AM56: =Smax*(1-POWER(Keep,AG56)) -> 70 | AN56: =Smax*(1-POWER(Keep,AH56)) -> 70 | AO56: =Smax*(1-POWER(Keep,AI56)) -> 70 | AP56: =Smax*(1-POWER(Keep,AJ56)) -> 70 | AQ56: =IF(D56=1,Cash0+SUM(AK56:AP56)-Cost_r*AJ56+A56*AP56,-1000000000) -> 1150
A57: =Credit_10 -> 10 | B57: 13 | C57: 2 | D57: =IF($E$13="",1,0) -> 1 | E57: =IF($D$13<>"",$D$13,IF(1<C57,1,0)) -> 1 | F57: =IF($E$13<>"",$E$13,IF(2<C57,1,0)) -> 0 | G57: =IF($F$13<>"",$F$13,IF(3<C57,1,0)) -> 0 | H57: =IF($G$13<>"",$G$13,IF(4<C57,1,0)) -> 0 | I57: =IF($H$13<>"",$H$13,IF(5<C57,1,0)) -> 0 | J57: =IF($I$13<>"",$I$13,IF(6<C57,1,0)) -> 0 | K57: =SUM($E57:E57) -> 1 | L57: =SUM($E57:F57) -> 1 | M57: =SUM($E57:G57) -> 1 | N57: =SUM($E57:H57) -> 1 | O57: =SUM($E57:I57) -> 1 | P57: =SUM($E57:J57) -> 1 | Q57: =IF(1>=C57,POWER(Keep,K57-INDEX(K57:P57,C57)),0) -> 0 | R57: =IF(2>=C57,POWER(Keep,L57-INDEX(K57:P57,C57)),0) -> 1 | S57: =IF(3>=C57,POWER(Keep,M57-INDEX(K57:P57,C57)),0) -> 1 | T57: =IF(4>=C57,POWER(Keep,N57-INDEX(K57:P57,C57)),0) -> 1 | U57: =IF(5>=C57,POWER(Keep,O57-INDEX(K57:P57,C57)),0) -> 1 | V57: =IF(6>=C57,POWER(Keep,P57-INDEX(K57:P57,C57)),0) -> 1 | W57: =SUM(Q57:V57)+A57*POWER(Keep,P57-INDEX(K57:P57,C57)) -> 15 | X57: =MIN(1,MAX(0,LN(Cost_r/(Slope0*W57))/LN(Keep)-INDEX(K57:P57,C57))) -> 1 | Y57: =IF(1=C57,X57,E57) -> 1 | Z57: =IF(2=C57,X57,F57) -> 1 | AA57: =IF(3=C57,X57,G57) -> 0 | AB57: =IF(4=C57,X57,H57) -> 0 | AC57: =IF(5=C57,X57,I57) -> 0 | AD57: =IF(6=C57,X57,J57) -> 0 | AE57: =SUM($Y57:Y57) -> 1 | AF57: =SUM($Y57:Z57) -> 2 | AG57: =SUM($Y57:AA57) -> 2 | AH57: =SUM($Y57:AB57) -> 2 | AI57: =SUM($Y57:AC57) -> 2 | AJ57: =SUM($Y57:AD57) -> 2 | AK57: =Smax*(1-POWER(Keep,AE57)) -> 70 | AL57: =Smax*(1-POWER(Keep,AF57)) -> 105 | AM57: =Smax*(1-POWER(Keep,AG57)) -> 105 | AN57: =Smax*(1-POWER(Keep,AH57)) -> 105 | AO57: =Smax*(1-POWER(Keep,AI57)) -> 105 | AP57: =Smax*(1-POWER(Keep,AJ57)) -> 105 | AQ57: =IF(D57=1,Cash0+SUM(AK57:AP57)-Cost_r*AJ57+A57*AP57,-1000000000) -> 1555
A58: =Credit_10 -> 10 | B58: 13 | C58: 3 | D58: =IF($F$13="",1,0) -> 1 | E58: =IF($D$13<>"",$D$13,IF(1<C58,1,0)) -> 1 | F58: =IF($E$13<>"",$E$13,IF(2<C58,1,0)) -> 1 | G58: =IF($F$13<>"",$F$13,IF(3<C58,1,0)) -> 0 | H58: =IF($G$13<>"",$G$13,IF(4<C58,1,0)) -> 0 | I58: =IF($H$13<>"",$H$13,IF(5<C58,1,0)) -> 0 | J58: =IF($I$13<>"",$I$13,IF(6<C58,1,0)) -> 0 | K58: =SUM($E58:E58) -> 1 | L58: =SUM($E58:F58) -> 2 | M58: =SUM($E58:G58) -> 2 | N58: =SUM($E58:H58) -> 2 | O58: =SUM($E58:I58) -> 2 | P58: =SUM($E58:J58) -> 2 | Q58: =IF(1>=C58,POWER(Keep,K58-INDEX(K58:P58,C58)),0) -> 0 | R58: =IF(2>=C58,POWER(Keep,L58-INDEX(K58:P58,C58)),0) -> 0 | S58: =IF(3>=C58,POWER(Keep,M58-INDEX(K58:P58,C58)),0) -> 1 | T58: =IF(4>=C58,POWER(Keep,N58-INDEX(K58:P58,C58)),0) -> 1 | U58: =IF(5>=C58,POWER(Keep,O58-INDEX(K58:P58,C58)),0) -> 1 | V58: =IF(6>=C58,POWER(Keep,P58-INDEX(K58:P58,C58)),0) -> 1 | W58: =SUM(Q58:V58)+A58*POWER(Keep,P58-INDEX(K58:P58,C58)) -> 14 | X58: =MIN(1,MAX(0,LN(Cost_r/(Slope0*W58))/LN(Keep)-INDEX(K58:P58,C58))) -> 1 | Y58: =IF(1=C58,X58,E58) -> 1 | Z58: =IF(2=C58,X58,F58) -> 1 | AA58: =IF(3=C58,X58,G58) -> 1 | AB58: =IF(4=C58,X58,H58) -> 0 | AC58: =IF(5=C58,X58,I58) -> 0 | AD58: =IF(6=C58,X58,J58) -> 0 | AE58: =SUM($Y58:Y58) -> 1 | AF58: =SUM($Y58:Z58) -> 2 | AG58: =SUM($Y58:AA58) -> 3 | AH58: =SUM($Y58:AB58) -> 3 | AI58: =SUM($Y58:AC58) -> 3 | AJ58: =SUM($Y58:AD58) -> 3 | AK58: =Smax*(1-POWER(Keep,AE58)) -> 70 | AL58: =Smax*(1-POWER(Keep,AF58)) -> 105 | AM58: =Smax*(1-POWER(Keep,AG58)) -> 122.5 | AN58: =Smax*(1-POWER(Keep,AH58)) -> 122.5 | AO58: =Smax*(1-POWER(Keep,AI58)) -> 122.5 | AP58: =Smax*(1-POWER(Keep,AJ58)) -> 122.5 | AQ58: =IF(D58=1,Cash0+SUM(AK58:AP58)-Cost_r*AJ58+A58*AP58,-1000000000) -> 1680
A59: =Credit_10 -> 10 | B59: 13 | C59: 4 | D59: =IF($G$13="",1,0) -> 1 | E59: =IF($D$13<>"",$D$13,IF(1<C59,1,0)) -> 1 | F59: =IF($E$13<>"",$E$13,IF(2<C59,1,0)) -> 1 | G59: =IF($F$13<>"",$F$13,IF(3<C59,1,0)) -> 1 | H59: =IF($G$13<>"",$G$13,IF(4<C59,1,0)) -> 0 | I59: =IF($H$13<>"",$H$13,IF(5<C59,1,0)) -> 0 | J59: =IF($I$13<>"",$I$13,IF(6<C59,1,0)) -> 0 | K59: =SUM($E59:E59) -> 1 | L59: =SUM($E59:F59) -> 2 | M59: =SUM($E59:G59) -> 3 | N59: =SUM($E59:H59) -> 3 | O59: =SUM($E59:I59) -> 3 | P59: =SUM($E59:J59) -> 3 | Q59: =IF(1>=C59,POWER(Keep,K59-INDEX(K59:P59,C59)),0) -> 0 | R59: =IF(2>=C59,POWER(Keep,L59-INDEX(K59:P59,C59)),0) -> 0 | S59: =IF(3>=C59,POWER(Keep,M59-INDEX(K59:P59,C59)),0) -> 0 | T59: =IF(4>=C59,POWER(Keep,N59-INDEX(K59:P59,C59)),0) -> 1 | U59: =IF(5>=C59,POWER(Keep,O59-INDEX(K59:P59,C59)),0) -> 1 | V59: =IF(6>=C59,POWER(Keep,P59-INDEX(K59:P59,C59)),0) -> 1 | W59: =SUM(Q59:V59)+A59*POWER(Keep,P59-INDEX(K59:P59,C59)) -> 13 | X59: =MIN(1,MAX(0,LN(Cost_r/(Slope0*W59))/LN(Keep)-INDEX(K59:P59,C59))) -> 0.39406577 | Y59: =IF(1=C59,X59,E59) -> 1 | Z59: =IF(2=C59,X59,F59) -> 1 | AA59: =IF(3=C59,X59,G59) -> 1 | AB59: =IF(4=C59,X59,H59) -> 0.39406577 | AC59: =IF(5=C59,X59,I59) -> 0 | AD59: =IF(6=C59,X59,J59) -> 0 | AE59: =SUM($Y59:Y59) -> 1 | AF59: =SUM($Y59:Z59) -> 2 | AG59: =SUM($Y59:AA59) -> 3 | AH59: =SUM($Y59:AB59) -> 3.3940658 | AI59: =SUM($Y59:AC59) -> 3.3940658 | AJ59: =SUM($Y59:AD59) -> 3.3940658 | AK59: =Smax*(1-POWER(Keep,AE59)) -> 70 | AL59: =Smax*(1-POWER(Keep,AF59)) -> 105 | AM59: =Smax*(1-POWER(Keep,AG59)) -> 122.5 | AN59: =Smax*(1-POWER(Keep,AH59)) -> 126.68282 | AO59: =Smax*(1-POWER(Keep,AI59)) -> 126.68282 | AP59: =Smax*(1-POWER(Keep,AJ59)) -> 126.68282 | AQ59: =IF(D59=1,Cash0+SUM(AK59:AP59)-Cost_r*AJ59+A59*AP59,-1000000000) -> 1687.0887
A60: =Credit_10 -> 10 | B60: 13 | C60: 5 | D60: =IF($H$13="",1,0) -> 1 | E60: =IF($D$13<>"",$D$13,IF(1<C60,1,0)) -> 1 | F60: =IF($E$13<>"",$E$13,IF(2<C60,1,0)) -> 1 | G60: =IF($F$13<>"",$F$13,IF(3<C60,1,0)) -> 1 | H60: =IF($G$13<>"",$G$13,IF(4<C60,1,0)) -> 1 | I60: =IF($H$13<>"",$H$13,IF(5<C60,1,0)) -> 0 | J60: =IF($I$13<>"",$I$13,IF(6<C60,1,0)) -> 0 | K60: =SUM($E60:E60) -> 1 | L60: =SUM($E60:F60) -> 2 | M60: =SUM($E60:G60) -> 3 | N60: =SUM($E60:H60) -> 4 | O60: =SUM($E60:I60) -> 4 | P60: =SUM($E60:J60) -> 4 | Q60: =IF(1>=C60,POWER(Keep,K60-INDEX(K60:P60,C60)),0) -> 0 | R60: =IF(2>=C60,POWER(Keep,L60-INDEX(K60:P60,C60)),0) -> 0 | S60: =IF(3>=C60,POWER(Keep,M60-INDEX(K60:P60,C60)),0) -> 0 | T60: =IF(4>=C60,POWER(Keep,N60-INDEX(K60:P60,C60)),0) -> 0 | U60: =IF(5>=C60,POWER(Keep,O60-INDEX(K60:P60,C60)),0) -> 1 | V60: =IF(6>=C60,POWER(Keep,P60-INDEX(K60:P60,C60)),0) -> 1 | W60: =SUM(Q60:V60)+A60*POWER(Keep,P60-INDEX(K60:P60,C60)) -> 12 | X60: =MIN(1,MAX(0,LN(Cost_r/(Slope0*W60))/LN(Keep)-INDEX(K60:P60,C60))) -> 0 | Y60: =IF(1=C60,X60,E60) -> 1 | Z60: =IF(2=C60,X60,F60) -> 1 | AA60: =IF(3=C60,X60,G60) -> 1 | AB60: =IF(4=C60,X60,H60) -> 1 | AC60: =IF(5=C60,X60,I60) -> 0 | AD60: =IF(6=C60,X60,J60) -> 0 | AE60: =SUM($Y60:Y60) -> 1 | AF60: =SUM($Y60:Z60) -> 2 | AG60: =SUM($Y60:AA60) -> 3 | AH60: =SUM($Y60:AB60) -> 4 | AI60: =SUM($Y60:AC60) -> 4 | AJ60: =SUM($Y60:AD60) -> 4 | AK60: =Smax*(1-POWER(Keep,AE60)) -> 70 | AL60: =Smax*(1-POWER(Keep,AF60)) -> 105 | AM60: =Smax*(1-POWER(Keep,AG60)) -> 122.5 | AN60: =Smax*(1-POWER(Keep,AH60)) -> 131.25 | AO60: =Smax*(1-POWER(Keep,AI60)) -> 131.25 | AP60: =Smax*(1-POWER(Keep,AJ60)) -> 131.25 | AQ60: =IF(D60=1,Cash0+SUM(AK60:AP60)-Cost_r*AJ60+A60*AP60,-1000000000) -> 1673.75
A61: =Credit_10 -> 10 | B61: 13 | C61: 6 | D61: =IF($I$13="",1,0) -> 1 | E61: =IF($D$13<>"",$D$13,IF(1<C61,1,0)) -> 1 | F61: =IF($E$13<>"",$E$13,IF(2<C61,1,0)) -> 1 | G61: =IF($F$13<>"",$F$13,IF(3<C61,1,0)) -> 1 | H61: =IF($G$13<>"",$G$13,IF(4<C61,1,0)) -> 1 | I61: =IF($H$13<>"",$H$13,IF(5<C61,1,0)) -> 1 | J61: =IF($I$13<>"",$I$13,IF(6<C61,1,0)) -> 0 | K61: =SUM($E61:E61) -> 1 | L61: =SUM($E61:F61) -> 2 | M61: =SUM($E61:G61) -> 3 | N61: =SUM($E61:H61) -> 4 | O61: =SUM($E61:I61) -> 5 | P61: =SUM($E61:J61) -> 5 | Q61: =IF(1>=C61,POWER(Keep,K61-INDEX(K61:P61,C61)),0) -> 0 | R61: =IF(2>=C61,POWER(Keep,L61-INDEX(K61:P61,C61)),0) -> 0 | S61: =IF(3>=C61,POWER(Keep,M61-INDEX(K61:P61,C61)),0) -> 0 | T61: =IF(4>=C61,POWER(Keep,N61-INDEX(K61:P61,C61)),0) -> 0 | U61: =IF(5>=C61,POWER(Keep,O61-INDEX(K61:P61,C61)),0) -> 0 | V61: =IF(6>=C61,POWER(Keep,P61-INDEX(K61:P61,C61)),0) -> 1 | W61: =SUM(Q61:V61)+A61*POWER(Keep,P61-INDEX(K61:P61,C61)) -> 11 | X61: =MIN(1,MAX(0,LN(Cost_r/(Slope0*W61))/LN(Keep)-INDEX(K61:P61,C61))) -> 0 | Y61: =IF(1=C61,X61,E61) -> 1 | Z61: =IF(2=C61,X61,F61) -> 1 | AA61: =IF(3=C61,X61,G61) -> 1 | AB61: =IF(4=C61,X61,H61) -> 1 | AC61: =IF(5=C61,X61,I61) -> 1 | AD61: =IF(6=C61,X61,J61) -> 0 | AE61: =SUM($Y61:Y61) -> 1 | AF61: =SUM($Y61:Z61) -> 2 | AG61: =SUM($Y61:AA61) -> 3 | AH61: =SUM($Y61:AB61) -> 4 | AI61: =SUM($Y61:AC61) -> 5 | AJ61: =SUM($Y61:AD61) -> 5 | AK61: =Smax*(1-POWER(Keep,AE61)) -> 70 | AL61: =Smax*(1-POWER(Keep,AF61)) -> 105 | AM61: =Smax*(1-POWER(Keep,AG61)) -> 122.5 | AN61: =Smax*(1-POWER(Keep,AH61)) -> 131.25 | AO61: =Smax*(1-POWER(Keep,AI61)) -> 135.625 | AP61: =Smax*(1-POWER(Keep,AJ61)) -> 135.625 | AQ61: =IF(D61=1,Cash0+SUM(AK61:AP61)-Cost_r*AJ61+A61*AP61,-1000000000) -> 1606.25
A62: =Credit_10 -> 10 | B62: 14 | C62: 1 | D62: =IF($D$14="",1,0) -> 1 | E62: =IF($D$14<>"",$D$14,IF(1<C62,1,0)) -> 0 | F62: =IF($E$14<>"",$E$14,IF(2<C62,1,0)) -> 0 | G62: =IF($F$14<>"",$F$14,IF(3<C62,1,0)) -> 0 | H62: =IF($G$14<>"",$G$14,IF(4<C62,1,0)) -> 0 | I62: =IF($H$14<>"",$H$14,IF(5<C62,1,0)) -> 0 | J62: =IF($I$14<>"",$I$14,IF(6<C62,1,0)) -> 0 | K62: =SUM($E62:E62) -> 0 | L62: =SUM($E62:F62) -> 0 | M62: =SUM($E62:G62) -> 0 | N62: =SUM($E62:H62) -> 0 | O62: =SUM($E62:I62) -> 0 | P62: =SUM($E62:J62) -> 0 | Q62: =IF(1>=C62,POWER(Keep,K62-INDEX(K62:P62,C62)),0) -> 1 | R62: =IF(2>=C62,POWER(Keep,L62-INDEX(K62:P62,C62)),0) -> 1 | S62: =IF(3>=C62,POWER(Keep,M62-INDEX(K62:P62,C62)),0) -> 1 | T62: =IF(4>=C62,POWER(Keep,N62-INDEX(K62:P62,C62)),0) -> 1 | U62: =IF(5>=C62,POWER(Keep,O62-INDEX(K62:P62,C62)),0) -> 1 | V62: =IF(6>=C62,POWER(Keep,P62-INDEX(K62:P62,C62)),0) -> 1 | W62: =SUM(Q62:V62)+A62*POWER(Keep,P62-INDEX(K62:P62,C62)) -> 16 | X62: =MIN(1,MAX(0,LN(Cost_r/(Slope0*W62))/LN(Keep)-INDEX(K62:P62,C62))) -> 1 | Y62: =IF(1=C62,X62,E62) -> 1 | Z62: =IF(2=C62,X62,F62) -> 0 | AA62: =IF(3=C62,X62,G62) -> 0 | AB62: =IF(4=C62,X62,H62) -> 0 | AC62: =IF(5=C62,X62,I62) -> 0 | AD62: =IF(6=C62,X62,J62) -> 0 | AE62: =SUM($Y62:Y62) -> 1 | AF62: =SUM($Y62:Z62) -> 1 | AG62: =SUM($Y62:AA62) -> 1 | AH62: =SUM($Y62:AB62) -> 1 | AI62: =SUM($Y62:AC62) -> 1 | AJ62: =SUM($Y62:AD62) -> 1 | AK62: =Smax*(1-POWER(Keep,AE62)) -> 70 | AL62: =Smax*(1-POWER(Keep,AF62)) -> 70 | AM62: =Smax*(1-POWER(Keep,AG62)) -> 70 | AN62: =Smax*(1-POWER(Keep,AH62)) -> 70 | AO62: =Smax*(1-POWER(Keep,AI62)) -> 70 | AP62: =Smax*(1-POWER(Keep,AJ62)) -> 70 | AQ62: =IF(D62=1,Cash0+SUM(AK62:AP62)-Cost_r*AJ62+A62*AP62,-1000000000) -> 1150
A63: =Credit_10 -> 10 | B63: 14 | C63: 2 | D63: =IF($E$14="",1,0) -> 1 | E63: =IF($D$14<>"",$D$14,IF(1<C63,1,0)) -> 1 | F63: =IF($E$14<>"",$E$14,IF(2<C63,1,0)) -> 0 | G63: =IF($F$14<>"",$F$14,IF(3<C63,1,0)) -> 0 | H63: =IF($G$14<>"",$G$14,IF(4<C63,1,0)) -> 0 | I63: =IF($H$14<>"",$H$14,IF(5<C63,1,0)) -> 0 | J63: =IF($I$14<>"",$I$14,IF(6<C63,1,0)) -> 0 | K63: =SUM($E63:E63) -> 1 | L63: =SUM($E63:F63) -> 1 | M63: =SUM($E63:G63) -> 1 | N63: =SUM($E63:H63) -> 1 | O63: =SUM($E63:I63) -> 1 | P63: =SUM($E63:J63) -> 1 | Q63: =IF(1>=C63,POWER(Keep,K63-INDEX(K63:P63,C63)),0) -> 0 | R63: =IF(2>=C63,POWER(Keep,L63-INDEX(K63:P63,C63)),0) -> 1 | S63: =IF(3>=C63,POWER(Keep,M63-INDEX(K63:P63,C63)),0) -> 1 | T63: =IF(4>=C63,POWER(Keep,N63-INDEX(K63:P63,C63)),0) -> 1 | U63: =IF(5>=C63,POWER(Keep,O63-INDEX(K63:P63,C63)),0) -> 1 | V63: =IF(6>=C63,POWER(Keep,P63-INDEX(K63:P63,C63)),0) -> 1 | W63: =SUM(Q63:V63)+A63*POWER(Keep,P63-INDEX(K63:P63,C63)) -> 15 | X63: =MIN(1,MAX(0,LN(Cost_r/(Slope0*W63))/LN(Keep)-INDEX(K63:P63,C63))) -> 1 | Y63: =IF(1=C63,X63,E63) -> 1 | Z63: =IF(2=C63,X63,F63) -> 1 | AA63: =IF(3=C63,X63,G63) -> 0 | AB63: =IF(4=C63,X63,H63) -> 0 | AC63: =IF(5=C63,X63,I63) -> 0 | AD63: =IF(6=C63,X63,J63) -> 0 | AE63: =SUM($Y63:Y63) -> 1 | AF63: =SUM($Y63:Z63) -> 2 | AG63: =SUM($Y63:AA63) -> 2 | AH63: =SUM($Y63:AB63) -> 2 | AI63: =SUM($Y63:AC63) -> 2 | AJ63: =SUM($Y63:AD63) -> 2 | AK63: =Smax*(1-POWER(Keep,AE63)) -> 70 | AL63: =Smax*(1-POWER(Keep,AF63)) -> 105 | AM63: =Smax*(1-POWER(Keep,AG63)) -> 105 | AN63: =Smax*(1-POWER(Keep,AH63)) -> 105 | AO63: =Smax*(1-POWER(Keep,AI63)) -> 105 | AP63: =Smax*(1-POWER(Keep,AJ63)) -> 105 | AQ63: =IF(D63=1,Cash0+SUM(AK63:AP63)-Cost_r*AJ63+A63*AP63,-1000000000) -> 1555
A64: =Credit_10 -> 10 | B64: 14 | C64: 3 | D64: =IF($F$14="",1,0) -> 1 | E64: =IF($D$14<>"",$D$14,IF(1<C64,1,0)) -> 1 | F64: =IF($E$14<>"",$E$14,IF(2<C64,1,0)) -> 1 | G64: =IF($F$14<>"",$F$14,IF(3<C64,1,0)) -> 0 | H64: =IF($G$14<>"",$G$14,IF(4<C64,1,0)) -> 0 | I64: =IF($H$14<>"",$H$14,IF(5<C64,1,0)) -> 0 | J64: =IF($I$14<>"",$I$14,IF(6<C64,1,0)) -> 0 | K64: =SUM($E64:E64) -> 1 | L64: =SUM($E64:F64) -> 2 | M64: =SUM($E64:G64) -> 2 | N64: =SUM($E64:H64) -> 2 | O64: =SUM($E64:I64) -> 2 | P64: =SUM($E64:J64) -> 2 | Q64: =IF(1>=C64,POWER(Keep,K64-INDEX(K64:P64,C64)),0) -> 0 | R64: =IF(2>=C64,POWER(Keep,L64-INDEX(K64:P64,C64)),0) -> 0 | S64: =IF(3>=C64,POWER(Keep,M64-INDEX(K64:P64,C64)),0) -> 1 | T64: =IF(4>=C64,POWER(Keep,N64-INDEX(K64:P64,C64)),0) -> 1 | U64: =IF(5>=C64,POWER(Keep,O64-INDEX(K64:P64,C64)),0) -> 1 | V64: =IF(6>=C64,POWER(Keep,P64-INDEX(K64:P64,C64)),0) -> 1 | W64: =SUM(Q64:V64)+A64*POWER(Keep,P64-INDEX(K64:P64,C64)) -> 14 | X64: =MIN(1,MAX(0,LN(Cost_r/(Slope0*W64))/LN(Keep)-INDEX(K64:P64,C64))) -> 1 | Y64: =IF(1=C64,X64,E64) -> 1 | Z64: =IF(2=C64,X64,F64) -> 1 | AA64: =IF(3=C64,X64,G64) -> 1 | AB64: =IF(4=C64,X64,H64) -> 0 | AC64: =IF(5=C64,X64,I64) -> 0 | AD64: =IF(6=C64,X64,J64) -> 0 | AE64: =SUM($Y64:Y64) -> 1 | AF64: =SUM($Y64:Z64) -> 2 | AG64: =SUM($Y64:AA64) -> 3 | AH64: =SUM($Y64:AB64) -> 3 | AI64: =SUM($Y64:AC64) -> 3 | AJ64: =SUM($Y64:AD64) -> 3 | AK64: =Smax*(1-POWER(Keep,AE64)) -> 70 | AL64: =Smax*(1-POWER(Keep,AF64)) -> 105 | AM64: =Smax*(1-POWER(Keep,AG64)) -> 122.5 | AN64: =Smax*(1-POWER(Keep,AH64)) -> 122.5 | AO64: =Smax*(1-POWER(Keep,AI64)) -> 122.5 | AP64: =Smax*(1-POWER(Keep,AJ64)) -> 122.5 | AQ64: =IF(D64=1,Cash0+SUM(AK64:AP64)-Cost_r*AJ64+A64*AP64,-1000000000) -> 1680
A65: =Credit_10 -> 10 | B65: 14 | C65: 4 | D65: =IF($G$14="",1,0) -> 0 | E65: =IF($D$14<>"",$D$14,IF(1<C65,1,0)) -> 1 | F65: =IF($E$14<>"",$E$14,IF(2<C65,1,0)) -> 1 | G65: =IF($F$14<>"",$F$14,IF(3<C65,1,0)) -> 1 | H65: =IF($G$14<>"",$G$14,IF(4<C65,1,0)) -> 0 | I65: =IF($H$14<>"",$H$14,IF(5<C65,1,0)) -> 0 | J65: =IF($I$14<>"",$I$14,IF(6<C65,1,0)) -> 0 | K65: =SUM($E65:E65) -> 1 | L65: =SUM($E65:F65) -> 2 | M65: =SUM($E65:G65) -> 3 | N65: =SUM($E65:H65) -> 3 | O65: =SUM($E65:I65) -> 3 | P65: =SUM($E65:J65) -> 3 | Q65: =IF(1>=C65,POWER(Keep,K65-INDEX(K65:P65,C65)),0) -> 0 | R65: =IF(2>=C65,POWER(Keep,L65-INDEX(K65:P65,C65)),0) -> 0 | S65: =IF(3>=C65,POWER(Keep,M65-INDEX(K65:P65,C65)),0) -> 0 | T65: =IF(4>=C65,POWER(Keep,N65-INDEX(K65:P65,C65)),0) -> 1 | U65: =IF(5>=C65,POWER(Keep,O65-INDEX(K65:P65,C65)),0) -> 1 | V65: =IF(6>=C65,POWER(Keep,P65-INDEX(K65:P65,C65)),0) -> 1 | W65: =SUM(Q65:V65)+A65*POWER(Keep,P65-INDEX(K65:P65,C65)) -> 13 | X65: =MIN(1,MAX(0,LN(Cost_r/(Slope0*W65))/LN(Keep)-INDEX(K65:P65,C65))) -> 0.39406577 | Y65: =IF(1=C65,X65,E65) -> 1 | Z65: =IF(2=C65,X65,F65) -> 1 | AA65: =IF(3=C65,X65,G65) -> 1 | AB65: =IF(4=C65,X65,H65) -> 0.39406577 | AC65: =IF(5=C65,X65,I65) -> 0 | AD65: =IF(6=C65,X65,J65) -> 0 | AE65: =SUM($Y65:Y65) -> 1 | AF65: =SUM($Y65:Z65) -> 2 | AG65: =SUM($Y65:AA65) -> 3 | AH65: =SUM($Y65:AB65) -> 3.3940658 | AI65: =SUM($Y65:AC65) -> 3.3940658 | AJ65: =SUM($Y65:AD65) -> 3.3940658 | AK65: =Smax*(1-POWER(Keep,AE65)) -> 70 | AL65: =Smax*(1-POWER(Keep,AF65)) -> 105 | AM65: =Smax*(1-POWER(Keep,AG65)) -> 122.5 | AN65: =Smax*(1-POWER(Keep,AH65)) -> 126.68282 | AO65: =Smax*(1-POWER(Keep,AI65)) -> 126.68282 | AP65: =Smax*(1-POWER(Keep,AJ65)) -> 126.68282 | AQ65: =IF(D65=1,Cash0+SUM(AK65:AP65)-Cost_r*AJ65+A65*AP65,-1000000000) -> -1000000000
A66: =Credit_10 -> 10 | B66: 14 | C66: 5 | D66: =IF($H$14="",1,0) -> 1 | E66: =IF($D$14<>"",$D$14,IF(1<C66,1,0)) -> 1 | F66: =IF($E$14<>"",$E$14,IF(2<C66,1,0)) -> 1 | G66: =IF($F$14<>"",$F$14,IF(3<C66,1,0)) -> 1 | H66: =IF($G$14<>"",$G$14,IF(4<C66,1,0)) -> 0 | I66: =IF($H$14<>"",$H$14,IF(5<C66,1,0)) -> 0 | J66: =IF($I$14<>"",$I$14,IF(6<C66,1,0)) -> 0 | K66: =SUM($E66:E66) -> 1 | L66: =SUM($E66:F66) -> 2 | M66: =SUM($E66:G66) -> 3 | N66: =SUM($E66:H66) -> 3 | O66: =SUM($E66:I66) -> 3 | P66: =SUM($E66:J66) -> 3 | Q66: =IF(1>=C66,POWER(Keep,K66-INDEX(K66:P66,C66)),0) -> 0 | R66: =IF(2>=C66,POWER(Keep,L66-INDEX(K66:P66,C66)),0) -> 0 | S66: =IF(3>=C66,POWER(Keep,M66-INDEX(K66:P66,C66)),0) -> 0 | T66: =IF(4>=C66,POWER(Keep,N66-INDEX(K66:P66,C66)),0) -> 0 | U66: =IF(5>=C66,POWER(Keep,O66-INDEX(K66:P66,C66)),0) -> 1 | V66: =IF(6>=C66,POWER(Keep,P66-INDEX(K66:P66,C66)),0) -> 1 | W66: =SUM(Q66:V66)+A66*POWER(Keep,P66-INDEX(K66:P66,C66)) -> 12 | X66: =MIN(1,MAX(0,LN(Cost_r/(Slope0*W66))/LN(Keep)-INDEX(K66:P66,C66))) -> 0.27858855 | Y66: =IF(1=C66,X66,E66) -> 1 | Z66: =IF(2=C66,X66,F66) -> 1 | AA66: =IF(3=C66,X66,G66) -> 1 | AB66: =IF(4=C66,X66,H66) -> 0 | AC66: =IF(5=C66,X66,I66) -> 0.27858855 | AD66: =IF(6=C66,X66,J66) -> 0 | AE66: =SUM($Y66:Y66) -> 1 | AF66: =SUM($Y66:Z66) -> 2 | AG66: =SUM($Y66:AA66) -> 3 | AH66: =SUM($Y66:AB66) -> 3 | AI66: =SUM($Y66:AC66) -> 3.2785885 | AJ66: =SUM($Y66:AD66) -> 3.2785885 | AK66: =Smax*(1-POWER(Keep,AE66)) -> 70 | AL66: =Smax*(1-POWER(Keep,AF66)) -> 105 | AM66: =Smax*(1-POWER(Keep,AG66)) -> 122.5 | AN66: =Smax*(1-POWER(Keep,AH66)) -> 122.5 | AO66: =Smax*(1-POWER(Keep,AI66)) -> 125.57305 | AP66: =Smax*(1-POWER(Keep,AJ66)) -> 125.57305 | AQ66: =IF(D66=1,Cash0+SUM(AK66:AP66)-Cost_r*AJ66+A66*AP66,-1000000000) -> 1683.446
A67: =Credit_10 -> 10 | B67: 14 | C67: 6 | D67: =IF($I$14="",1,0) -> 1 | E67: =IF($D$14<>"",$D$14,IF(1<C67,1,0)) -> 1 | F67: =IF($E$14<>"",$E$14,IF(2<C67,1,0)) -> 1 | G67: =IF($F$14<>"",$F$14,IF(3<C67,1,0)) -> 1 | H67: =IF($G$14<>"",$G$14,IF(4<C67,1,0)) -> 0 | I67: =IF($H$14<>"",$H$14,IF(5<C67,1,0)) -> 1 | J67: =IF($I$14<>"",$I$14,IF(6<C67,1,0)) -> 0 | K67: =SUM($E67:E67) -> 1 | L67: =SUM($E67:F67) -> 2 | M67: =SUM($E67:G67) -> 3 | N67: =SUM($E67:H67) -> 3 | O67: =SUM($E67:I67) -> 4 | P67: =SUM($E67:J67) -> 4 | Q67: =IF(1>=C67,POWER(Keep,K67-INDEX(K67:P67,C67)),0) -> 0 | R67: =IF(2>=C67,POWER(Keep,L67-INDEX(K67:P67,C67)),0) -> 0 | S67: =IF(3>=C67,POWER(Keep,M67-INDEX(K67:P67,C67)),0) -> 0 | T67: =IF(4>=C67,POWER(Keep,N67-INDEX(K67:P67,C67)),0) -> 0 | U67: =IF(5>=C67,POWER(Keep,O67-INDEX(K67:P67,C67)),0) -> 0 | V67: =IF(6>=C67,POWER(Keep,P67-INDEX(K67:P67,C67)),0) -> 1 | W67: =SUM(Q67:V67)+A67*POWER(Keep,P67-INDEX(K67:P67,C67)) -> 11 | X67: =MIN(1,MAX(0,LN(Cost_r/(Slope0*W67))/LN(Keep)-INDEX(K67:P67,C67))) -> 0 | Y67: =IF(1=C67,X67,E67) -> 1 | Z67: =IF(2=C67,X67,F67) -> 1 | AA67: =IF(3=C67,X67,G67) -> 1 | AB67: =IF(4=C67,X67,H67) -> 0 | AC67: =IF(5=C67,X67,I67) -> 1 | AD67: =IF(6=C67,X67,J67) -> 0 | AE67: =SUM($Y67:Y67) -> 1 | AF67: =SUM($Y67:Z67) -> 2 | AG67: =SUM($Y67:AA67) -> 3 | AH67: =SUM($Y67:AB67) -> 3 | AI67: =SUM($Y67:AC67) -> 4 | AJ67: =SUM($Y67:AD67) -> 4 | AK67: =Smax*(1-POWER(Keep,AE67)) -> 70 | AL67: =Smax*(1-POWER(Keep,AF67)) -> 105 | AM67: =Smax*(1-POWER(Keep,AG67)) -> 122.5 | AN67: =Smax*(1-POWER(Keep,AH67)) -> 122.5 | AO67: =Smax*(1-POWER(Keep,AI67)) -> 131.25 | AP67: =Smax*(1-POWER(Keep,AJ67)) -> 131.25 | AQ67: =IF(D67=1,Cash0+SUM(AK67:AP67)-Cost_r*AJ67+A67*AP67,-1000000000) -> 1665
A68: =Credit_10 -> 10 | B68: 15 | C68: 1 | D68: =IF($D$15="",1,0) -> 1 | E68: =IF($D$15<>"",$D$15,IF(1<C68,1,0)) -> 0 | F68: =IF($E$15<>"",$E$15,IF(2<C68,1,0)) -> 0 | G68: =IF($F$15<>"",$F$15,IF(3<C68,1,0)) -> 0 | H68: =IF($G$15<>"",$G$15,IF(4<C68,1,0)) -> 0 | I68: =IF($H$15<>"",$H$15,IF(5<C68,1,0)) -> 0 | J68: =IF($I$15<>"",$I$15,IF(6<C68,1,0)) -> 0 | K68: =SUM($E68:E68) -> 0 | L68: =SUM($E68:F68) -> 0 | M68: =SUM($E68:G68) -> 0 | N68: =SUM($E68:H68) -> 0 | O68: =SUM($E68:I68) -> 0 | P68: =SUM($E68:J68) -> 0 | Q68: =IF(1>=C68,POWER(Keep,K68-INDEX(K68:P68,C68)),0) -> 1 | R68: =IF(2>=C68,POWER(Keep,L68-INDEX(K68:P68,C68)),0) -> 1 | S68: =IF(3>=C68,POWER(Keep,M68-INDEX(K68:P68,C68)),0) -> 1 | T68: =IF(4>=C68,POWER(Keep,N68-INDEX(K68:P68,C68)),0) -> 1 | U68: =IF(5>=C68,POWER(Keep,O68-INDEX(K68:P68,C68)),0) -> 1 | V68: =IF(6>=C68,POWER(Keep,P68-INDEX(K68:P68,C68)),0) -> 1 | W68: =SUM(Q68:V68)+A68*POWER(Keep,P68-INDEX(K68:P68,C68)) -> 16 | X68: =MIN(1,MAX(0,LN(Cost_r/(Slope0*W68))/LN(Keep)-INDEX(K68:P68,C68))) -> 1 | Y68: =IF(1=C68,X68,E68) -> 1 | Z68: =IF(2=C68,X68,F68) -> 0 | AA68: =IF(3=C68,X68,G68) -> 0 | AB68: =IF(4=C68,X68,H68) -> 0 | AC68: =IF(5=C68,X68,I68) -> 0 | AD68: =IF(6=C68,X68,J68) -> 0 | AE68: =SUM($Y68:Y68) -> 1 | AF68: =SUM($Y68:Z68) -> 1 | AG68: =SUM($Y68:AA68) -> 1 | AH68: =SUM($Y68:AB68) -> 1 | AI68: =SUM($Y68:AC68) -> 1 | AJ68: =SUM($Y68:AD68) -> 1 | AK68: =Smax*(1-POWER(Keep,AE68)) -> 70 | AL68: =Smax*(1-POWER(Keep,AF68)) -> 70 | AM68: =Smax*(1-POWER(Keep,AG68)) -> 70 | AN68: =Smax*(1-POWER(Keep,AH68)) -> 70 | AO68: =Smax*(1-POWER(Keep,AI68)) -> 70 | AP68: =Smax*(1-POWER(Keep,AJ68)) -> 70 | AQ68: =IF(D68=1,Cash0+SUM(AK68:AP68)-Cost_r*AJ68+A68*AP68,-1000000000) -> 1150
A69: =Credit_10 -> 10 | B69: 15 | C69: 2 | D69: =IF($E$15="",1,0) -> 1 | E69: =IF($D$15<>"",$D$15,IF(1<C69,1,0)) -> 1 | F69: =IF($E$15<>"",$E$15,IF(2<C69,1,0)) -> 0 | G69: =IF($F$15<>"",$F$15,IF(3<C69,1,0)) -> 0 | H69: =IF($G$15<>"",$G$15,IF(4<C69,1,0)) -> 0 | I69: =IF($H$15<>"",$H$15,IF(5<C69,1,0)) -> 0 | J69: =IF($I$15<>"",$I$15,IF(6<C69,1,0)) -> 0 | K69: =SUM($E69:E69) -> 1 | L69: =SUM($E69:F69) -> 1 | M69: =SUM($E69:G69) -> 1 | N69: =SUM($E69:H69) -> 1 | O69: =SUM($E69:I69) -> 1 | P69: =SUM($E69:J69) -> 1 | Q69: =IF(1>=C69,POWER(Keep,K69-INDEX(K69:P69,C69)),0) -> 0 | R69: =IF(2>=C69,POWER(Keep,L69-INDEX(K69:P69,C69)),0) -> 1 | S69: =IF(3>=C69,POWER(Keep,M69-INDEX(K69:P69,C69)),0) -> 1 | T69: =IF(4>=C69,POWER(Keep,N69-INDEX(K69:P69,C69)),0) -> 1 | U69: =IF(5>=C69,POWER(Keep,O69-INDEX(K69:P69,C69)),0) -> 1 | V69: =IF(6>=C69,POWER(Keep,P69-INDEX(K69:P69,C69)),0) -> 1 | W69: =SUM(Q69:V69)+A69*POWER(Keep,P69-INDEX(K69:P69,C69)) -> 15 | X69: =MIN(1,MAX(0,LN(Cost_r/(Slope0*W69))/LN(Keep)-INDEX(K69:P69,C69))) -> 1 | Y69: =IF(1=C69,X69,E69) -> 1 | Z69: =IF(2=C69,X69,F69) -> 1 | AA69: =IF(3=C69,X69,G69) -> 0 | AB69: =IF(4=C69,X69,H69) -> 0 | AC69: =IF(5=C69,X69,I69) -> 0 | AD69: =IF(6=C69,X69,J69) -> 0 | AE69: =SUM($Y69:Y69) -> 1 | AF69: =SUM($Y69:Z69) -> 2 | AG69: =SUM($Y69:AA69) -> 2 | AH69: =SUM($Y69:AB69) -> 2 | AI69: =SUM($Y69:AC69) -> 2 | AJ69: =SUM($Y69:AD69) -> 2 | AK69: =Smax*(1-POWER(Keep,AE69)) -> 70 | AL69: =Smax*(1-POWER(Keep,AF69)) -> 105 | AM69: =Smax*(1-POWER(Keep,AG69)) -> 105 | AN69: =Smax*(1-POWER(Keep,AH69)) -> 105 | AO69: =Smax*(1-POWER(Keep,AI69)) -> 105 | AP69: =Smax*(1-POWER(Keep,AJ69)) -> 105 | AQ69: =IF(D69=1,Cash0+SUM(AK69:AP69)-Cost_r*AJ69+A69*AP69,-1000000000) -> 1555
A70: =Credit_10 -> 10 | B70: 15 | C70: 3 | D70: =IF($F$15="",1,0) -> 1 | E70: =IF($D$15<>"",$D$15,IF(1<C70,1,0)) -> 1 | F70: =IF($E$15<>"",$E$15,IF(2<C70,1,0)) -> 1 | G70: =IF($F$15<>"",$F$15,IF(3<C70,1,0)) -> 0 | H70: =IF($G$15<>"",$G$15,IF(4<C70,1,0)) -> 0 | I70: =IF($H$15<>"",$H$15,IF(5<C70,1,0)) -> 0 | J70: =IF($I$15<>"",$I$15,IF(6<C70,1,0)) -> 0 | K70: =SUM($E70:E70) -> 1 | L70: =SUM($E70:F70) -> 2 | M70: =SUM($E70:G70) -> 2 | N70: =SUM($E70:H70) -> 2 | O70: =SUM($E70:I70) -> 2 | P70: =SUM($E70:J70) -> 2 | Q70: =IF(1>=C70,POWER(Keep,K70-INDEX(K70:P70,C70)),0) -> 0 | R70: =IF(2>=C70,POWER(Keep,L70-INDEX(K70:P70,C70)),0) -> 0 | S70: =IF(3>=C70,POWER(Keep,M70-INDEX(K70:P70,C70)),0) -> 1 | T70: =IF(4>=C70,POWER(Keep,N70-INDEX(K70:P70,C70)),0) -> 1 | U70: =IF(5>=C70,POWER(Keep,O70-INDEX(K70:P70,C70)),0) -> 1 | V70: =IF(6>=C70,POWER(Keep,P70-INDEX(K70:P70,C70)),0) -> 1 | W70: =SUM(Q70:V70)+A70*POWER(Keep,P70-INDEX(K70:P70,C70)) -> 14 | X70: =MIN(1,MAX(0,LN(Cost_r/(Slope0*W70))/LN(Keep)-INDEX(K70:P70,C70))) -> 1 | Y70: =IF(1=C70,X70,E70) -> 1 | Z70: =IF(2=C70,X70,F70) -> 1 | AA70: =IF(3=C70,X70,G70) -> 1 | AB70: =IF(4=C70,X70,H70) -> 0 | AC70: =IF(5=C70,X70,I70) -> 0 | AD70: =IF(6=C70,X70,J70) -> 0 | AE70: =SUM($Y70:Y70) -> 1 | AF70: =SUM($Y70:Z70) -> 2 | AG70: =SUM($Y70:AA70) -> 3 | AH70: =SUM($Y70:AB70) -> 3 | AI70: =SUM($Y70:AC70) -> 3 | AJ70: =SUM($Y70:AD70) -> 3 | AK70: =Smax*(1-POWER(Keep,AE70)) -> 70 | AL70: =Smax*(1-POWER(Keep,AF70)) -> 105 | AM70: =Smax*(1-POWER(Keep,AG70)) -> 122.5 | AN70: =Smax*(1-POWER(Keep,AH70)) -> 122.5 | AO70: =Smax*(1-POWER(Keep,AI70)) -> 122.5 | AP70: =Smax*(1-POWER(Keep,AJ70)) -> 122.5 | AQ70: =IF(D70=1,Cash0+SUM(AK70:AP70)-Cost_r*AJ70+A70*AP70,-1000000000) -> 1680
A71: =Credit_10 -> 10 | B71: 15 | C71: 4 | D71: =IF($G$15="",1,0) -> 0 | E71: =IF($D$15<>"",$D$15,IF(1<C71,1,0)) -> 1 | F71: =IF($E$15<>"",$E$15,IF(2<C71,1,0)) -> 1 | G71: =IF($F$15<>"",$F$15,IF(3<C71,1,0)) -> 1 | H71: =IF($G$15<>"",$G$15,IF(4<C71,1,0)) -> 0 | I71: =IF($H$15<>"",$H$15,IF(5<C71,1,0)) -> 0 | J71: =IF($I$15<>"",$I$15,IF(6<C71,1,0)) -> 0 | K71: =SUM($E71:E71) -> 1 | L71: =SUM($E71:F71) -> 2 | M71: =SUM($E71:G71) -> 3 | N71: =SUM($E71:H71) -> 3 | O71: =SUM($E71:I71) -> 3 | P71: =SUM($E71:J71) -> 3 | Q71: =IF(1>=C71,POWER(Keep,K71-INDEX(K71:P71,C71)),0) -> 0 | R71: =IF(2>=C71,POWER(Keep,L71-INDEX(K71:P71,C71)),0) -> 0 | S71: =IF(3>=C71,POWER(Keep,M71-INDEX(K71:P71,C71)),0) -> 0 | T71: =IF(4>=C71,POWER(Keep,N71-INDEX(K71:P71,C71)),0) -> 1 | U71: =IF(5>=C71,POWER(Keep,O71-INDEX(K71:P71,C71)),0) -> 1 | V71: =IF(6>=C71,POWER(Keep,P71-INDEX(K71:P71,C71)),0) -> 1 | W71: =SUM(Q71:V71)+A71*POWER(Keep,P71-INDEX(K71:P71,C71)) -> 13 | X71: =MIN(1,MAX(0,LN(Cost_r/(Slope0*W71))/LN(Keep)-INDEX(K71:P71,C71))) -> 0.39406577 | Y71: =IF(1=C71,X71,E71) -> 1 | Z71: =IF(2=C71,X71,F71) -> 1 | AA71: =IF(3=C71,X71,G71) -> 1 | AB71: =IF(4=C71,X71,H71) -> 0.39406577 | AC71: =IF(5=C71,X71,I71) -> 0 | AD71: =IF(6=C71,X71,J71) -> 0 | AE71: =SUM($Y71:Y71) -> 1 | AF71: =SUM($Y71:Z71) -> 2 | AG71: =SUM($Y71:AA71) -> 3 | AH71: =SUM($Y71:AB71) -> 3.3940658 | AI71: =SUM($Y71:AC71) -> 3.3940658 | AJ71: =SUM($Y71:AD71) -> 3.3940658 | AK71: =Smax*(1-POWER(Keep,AE71)) -> 70 | AL71: =Smax*(1-POWER(Keep,AF71)) -> 105 | AM71: =Smax*(1-POWER(Keep,AG71)) -> 122.5 | AN71: =Smax*(1-POWER(Keep,AH71)) -> 126.68282 | AO71: =Smax*(1-POWER(Keep,AI71)) -> 126.68282 | AP71: =Smax*(1-POWER(Keep,AJ71)) -> 126.68282 | AQ71: =IF(D71=1,Cash0+SUM(AK71:AP71)-Cost_r*AJ71+A71*AP71,-1000000000) -> -1000000000
A72: =Credit_10 -> 10 | B72: 15 | C72: 5 | D72: =IF($H$15="",1,0) -> 0 | E72: =IF($D$15<>"",$D$15,IF(1<C72,1,0)) -> 1 | F72: =IF($E$15<>"",$E$15,IF(2<C72,1,0)) -> 1 | G72: =IF($F$15<>"",$F$15,IF(3<C72,1,0)) -> 1 | H72: =IF($G$15<>"",$G$15,IF(4<C72,1,0)) -> 0 | I72: =IF($H$15<>"",$H$15,IF(5<C72,1,0)) -> 0 | J72: =IF($I$15<>"",$I$15,IF(6<C72,1,0)) -> 0 | K72: =SUM($E72:E72) -> 1 | L72: =SUM($E72:F72) -> 2 | M72: =SUM($E72:G72) -> 3 | N72: =SUM($E72:H72) -> 3 | O72: =SUM($E72:I72) -> 3 | P72: =SUM($E72:J72) -> 3 | Q72: =IF(1>=C72,POWER(Keep,K72-INDEX(K72:P72,C72)),0) -> 0 | R72: =IF(2>=C72,POWER(Keep,L72-INDEX(K72:P72,C72)),0) -> 0 | S72: =IF(3>=C72,POWER(Keep,M72-INDEX(K72:P72,C72)),0) -> 0 | T72: =IF(4>=C72,POWER(Keep,N72-INDEX(K72:P72,C72)),0) -> 0 | U72: =IF(5>=C72,POWER(Keep,O72-INDEX(K72:P72,C72)),0) -> 1 | V72: =IF(6>=C72,POWER(Keep,P72-INDEX(K72:P72,C72)),0) -> 1 | W72: =SUM(Q72:V72)+A72*POWER(Keep,P72-INDEX(K72:P72,C72)) -> 12 | X72: =MIN(1,MAX(0,LN(Cost_r/(Slope0*W72))/LN(Keep)-INDEX(K72:P72,C72))) -> 0.27858855 | Y72: =IF(1=C72,X72,E72) -> 1 | Z72: =IF(2=C72,X72,F72) -> 1 | AA72: =IF(3=C72,X72,G72) -> 1 | AB72: =IF(4=C72,X72,H72) -> 0 | AC72: =IF(5=C72,X72,I72) -> 0.27858855 | AD72: =IF(6=C72,X72,J72) -> 0 | AE72: =SUM($Y72:Y72) -> 1 | AF72: =SUM($Y72:Z72) -> 2 | AG72: =SUM($Y72:AA72) -> 3 | AH72: =SUM($Y72:AB72) -> 3 | AI72: =SUM($Y72:AC72) -> 3.2785885 | AJ72: =SUM($Y72:AD72) -> 3.2785885 | AK72: =Smax*(1-POWER(Keep,AE72)) -> 70 | AL72: =Smax*(1-POWER(Keep,AF72)) -> 105 | AM72: =Smax*(1-POWER(Keep,AG72)) -> 122.5 | AN72: =Smax*(1-POWER(Keep,AH72)) -> 122.5 | AO72: =Smax*(1-POWER(Keep,AI72)) -> 125.57305 | AP72: =Smax*(1-POWER(Keep,AJ72)) -> 125.57305 | AQ72: =IF(D72=1,Cash0+SUM(AK72:AP72)-Cost_r*AJ72+A72*AP72,-1000000000) -> -1000000000
A73: =Credit_10 -> 10 | B73: 15 | C73: 6 | D73: =IF($I$15="",1,0) -> 1 | E73: =IF($D$15<>"",$D$15,IF(1<C73,1,0)) -> 1 | F73: =IF($E$15<>"",$E$15,IF(2<C73,1,0)) -> 1 | G73: =IF($F$15<>"",$F$15,IF(3<C73,1,0)) -> 1 | H73: =IF($G$15<>"",$G$15,IF(4<C73,1,0)) -> 0 | I73: =IF($H$15<>"",$H$15,IF(5<C73,1,0)) -> 0 | J73: =IF($I$15<>"",$I$15,IF(6<C73,1,0)) -> 0 | K73: =SUM($E73:E73) -> 1 | L73: =SUM($E73:F73) -> 2 | M73: =SUM($E73:G73) -> 3 | N73: =SUM($E73:H73) -> 3 | O73: =SUM($E73:I73) -> 3 | P73: =SUM($E73:J73) -> 3 | Q73: =IF(1>=C73,POWER(Keep,K73-INDEX(K73:P73,C73)),0) -> 0 | R73: =IF(2>=C73,POWER(Keep,L73-INDEX(K73:P73,C73)),0) -> 0 | S73: =IF(3>=C73,POWER(Keep,M73-INDEX(K73:P73,C73)),0) -> 0 | T73: =IF(4>=C73,POWER(Keep,N73-INDEX(K73:P73,C73)),0) -> 0 | U73: =IF(5>=C73,POWER(Keep,O73-INDEX(K73:P73,C73)),0) -> 0 | V73: =IF(6>=C73,POWER(Keep,P73-INDEX(K73:P73,C73)),0) -> 1 | W73: =SUM(Q73:V73)+A73*POWER(Keep,P73-INDEX(K73:P73,C73)) -> 11 | X73: =MIN(1,MAX(0,LN(Cost_r/(Slope0*W73))/LN(Keep)-INDEX(K73:P73,C73))) -> 0.15305767 | Y73: =IF(1=C73,X73,E73) -> 1 | Z73: =IF(2=C73,X73,F73) -> 1 | AA73: =IF(3=C73,X73,G73) -> 1 | AB73: =IF(4=C73,X73,H73) -> 0 | AC73: =IF(5=C73,X73,I73) -> 0 | AD73: =IF(6=C73,X73,J73) -> 0.15305767 | AE73: =SUM($Y73:Y73) -> 1 | AF73: =SUM($Y73:Z73) -> 2 | AG73: =SUM($Y73:AA73) -> 3 | AH73: =SUM($Y73:AB73) -> 3 | AI73: =SUM($Y73:AC73) -> 3 | AJ73: =SUM($Y73:AD73) -> 3.1530577 | AK73: =Smax*(1-POWER(Keep,AE73)) -> 70 | AL73: =Smax*(1-POWER(Keep,AF73)) -> 105 | AM73: =Smax*(1-POWER(Keep,AG73)) -> 122.5 | AN73: =Smax*(1-POWER(Keep,AH73)) -> 122.5 | AO73: =Smax*(1-POWER(Keep,AI73)) -> 122.5 | AP73: =Smax*(1-POWER(Keep,AJ73)) -> 124.26151 | AQ73: =IF(D73=1,Cash0+SUM(AK73:AP73)-Cost_r*AJ73+A73*AP73,-1000000000) -> 1681.0097
A74: =Credit_10 -> 10 | B74: 16 | C74: 1 | D74: =IF($D$16="",1,0) -> 1 | E74: =IF($D$16<>"",$D$16,IF(1<C74,1,0)) -> 0 | F74: =IF($E$16<>"",$E$16,IF(2<C74,1,0)) -> 0 | G74: =IF($F$16<>"",$F$16,IF(3<C74,1,0)) -> 0 | H74: =IF($G$16<>"",$G$16,IF(4<C74,1,0)) -> 0 | I74: =IF($H$16<>"",$H$16,IF(5<C74,1,0)) -> 0 | J74: =IF($I$16<>"",$I$16,IF(6<C74,1,0)) -> 0 | K74: =SUM($E74:E74) -> 0 | L74: =SUM($E74:F74) -> 0 | M74: =SUM($E74:G74) -> 0 | N74: =SUM($E74:H74) -> 0 | O74: =SUM($E74:I74) -> 0 | P74: =SUM($E74:J74) -> 0 | Q74: =IF(1>=C74,POWER(Keep,K74-INDEX(K74:P74,C74)),0) -> 1 | R74: =IF(2>=C74,POWER(Keep,L74-INDEX(K74:P74,C74)),0) -> 1 | S74: =IF(3>=C74,POWER(Keep,M74-INDEX(K74:P74,C74)),0) -> 1 | T74: =IF(4>=C74,POWER(Keep,N74-INDEX(K74:P74,C74)),0) -> 1 | U74: =IF(5>=C74,POWER(Keep,O74-INDEX(K74:P74,C74)),0) -> 1 | V74: =IF(6>=C74,POWER(Keep,P74-INDEX(K74:P74,C74)),0) -> 1 | W74: =SUM(Q74:V74)+A74*POWER(Keep,P74-INDEX(K74:P74,C74)) -> 16 | X74: =MIN(1,MAX(0,LN(Cost_r/(Slope0*W74))/LN(Keep)-INDEX(K74:P74,C74))) -> 1 | Y74: =IF(1=C74,X74,E74) -> 1 | Z74: =IF(2=C74,X74,F74) -> 0 | AA74: =IF(3=C74,X74,G74) -> 0 | AB74: =IF(4=C74,X74,H74) -> 0 | AC74: =IF(5=C74,X74,I74) -> 0 | AD74: =IF(6=C74,X74,J74) -> 0 | AE74: =SUM($Y74:Y74) -> 1 | AF74: =SUM($Y74:Z74) -> 1 | AG74: =SUM($Y74:AA74) -> 1 | AH74: =SUM($Y74:AB74) -> 1 | AI74: =SUM($Y74:AC74) -> 1 | AJ74: =SUM($Y74:AD74) -> 1 | AK74: =Smax*(1-POWER(Keep,AE74)) -> 70 | AL74: =Smax*(1-POWER(Keep,AF74)) -> 70 | AM74: =Smax*(1-POWER(Keep,AG74)) -> 70 | AN74: =Smax*(1-POWER(Keep,AH74)) -> 70 | AO74: =Smax*(1-POWER(Keep,AI74)) -> 70 | AP74: =Smax*(1-POWER(Keep,AJ74)) -> 70 | AQ74: =IF(D74=1,Cash0+SUM(AK74:AP74)-Cost_r*AJ74+A74*AP74,-1000000000) -> 1150
A75: =Credit_10 -> 10 | B75: 16 | C75: 2 | D75: =IF($E$16="",1,0) -> 1 | E75: =IF($D$16<>"",$D$16,IF(1<C75,1,0)) -> 1 | F75: =IF($E$16<>"",$E$16,IF(2<C75,1,0)) -> 0 | G75: =IF($F$16<>"",$F$16,IF(3<C75,1,0)) -> 0 | H75: =IF($G$16<>"",$G$16,IF(4<C75,1,0)) -> 0 | I75: =IF($H$16<>"",$H$16,IF(5<C75,1,0)) -> 0 | J75: =IF($I$16<>"",$I$16,IF(6<C75,1,0)) -> 0 | K75: =SUM($E75:E75) -> 1 | L75: =SUM($E75:F75) -> 1 | M75: =SUM($E75:G75) -> 1 | N75: =SUM($E75:H75) -> 1 | O75: =SUM($E75:I75) -> 1 | P75: =SUM($E75:J75) -> 1 | Q75: =IF(1>=C75,POWER(Keep,K75-INDEX(K75:P75,C75)),0) -> 0 | R75: =IF(2>=C75,POWER(Keep,L75-INDEX(K75:P75,C75)),0) -> 1 | S75: =IF(3>=C75,POWER(Keep,M75-INDEX(K75:P75,C75)),0) -> 1 | T75: =IF(4>=C75,POWER(Keep,N75-INDEX(K75:P75,C75)),0) -> 1 | U75: =IF(5>=C75,POWER(Keep,O75-INDEX(K75:P75,C75)),0) -> 1 | V75: =IF(6>=C75,POWER(Keep,P75-INDEX(K75:P75,C75)),0) -> 1 | W75: =SUM(Q75:V75)+A75*POWER(Keep,P75-INDEX(K75:P75,C75)) -> 15 | X75: =MIN(1,MAX(0,LN(Cost_r/(Slope0*W75))/LN(Keep)-INDEX(K75:P75,C75))) -> 1 | Y75: =IF(1=C75,X75,E75) -> 1 | Z75: =IF(2=C75,X75,F75) -> 1 | AA75: =IF(3=C75,X75,G75) -> 0 | AB75: =IF(4=C75,X75,H75) -> 0 | AC75: =IF(5=C75,X75,I75) -> 0 | AD75: =IF(6=C75,X75,J75) -> 0 | AE75: =SUM($Y75:Y75) -> 1 | AF75: =SUM($Y75:Z75) -> 2 | AG75: =SUM($Y75:AA75) -> 2 | AH75: =SUM($Y75:AB75) -> 2 | AI75: =SUM($Y75:AC75) -> 2 | AJ75: =SUM($Y75:AD75) -> 2 | AK75: =Smax*(1-POWER(Keep,AE75)) -> 70 | AL75: =Smax*(1-POWER(Keep,AF75)) -> 105 | AM75: =Smax*(1-POWER(Keep,AG75)) -> 105 | AN75: =Smax*(1-POWER(Keep,AH75)) -> 105 | AO75: =Smax*(1-POWER(Keep,AI75)) -> 105 | AP75: =Smax*(1-POWER(Keep,AJ75)) -> 105 | AQ75: =IF(D75=1,Cash0+SUM(AK75:AP75)-Cost_r*AJ75+A75*AP75,-1000000000) -> 1555
A76: =Credit_10 -> 10 | B76: 16 | C76: 3 | D76: =IF($F$16="",1,0) -> 1 | E76: =IF($D$16<>"",$D$16,IF(1<C76,1,0)) -> 1 | F76: =IF($E$16<>"",$E$16,IF(2<C76,1,0)) -> 1 | G76: =IF($F$16<>"",$F$16,IF(3<C76,1,0)) -> 0 | H76: =IF($G$16<>"",$G$16,IF(4<C76,1,0)) -> 0 | I76: =IF($H$16<>"",$H$16,IF(5<C76,1,0)) -> 0 | J76: =IF($I$16<>"",$I$16,IF(6<C76,1,0)) -> 0 | K76: =SUM($E76:E76) -> 1 | L76: =SUM($E76:F76) -> 2 | M76: =SUM($E76:G76) -> 2 | N76: =SUM($E76:H76) -> 2 | O76: =SUM($E76:I76) -> 2 | P76: =SUM($E76:J76) -> 2 | Q76: =IF(1>=C76,POWER(Keep,K76-INDEX(K76:P76,C76)),0) -> 0 | R76: =IF(2>=C76,POWER(Keep,L76-INDEX(K76:P76,C76)),0) -> 0 | S76: =IF(3>=C76,POWER(Keep,M76-INDEX(K76:P76,C76)),0) -> 1 | T76: =IF(4>=C76,POWER(Keep,N76-INDEX(K76:P76,C76)),0) -> 1 | U76: =IF(5>=C76,POWER(Keep,O76-INDEX(K76:P76,C76)),0) -> 1 | V76: =IF(6>=C76,POWER(Keep,P76-INDEX(K76:P76,C76)),0) -> 1 | W76: =SUM(Q76:V76)+A76*POWER(Keep,P76-INDEX(K76:P76,C76)) -> 14 | X76: =MIN(1,MAX(0,LN(Cost_r/(Slope0*W76))/LN(Keep)-INDEX(K76:P76,C76))) -> 1 | Y76: =IF(1=C76,X76,E76) -> 1 | Z76: =IF(2=C76,X76,F76) -> 1 | AA76: =IF(3=C76,X76,G76) -> 1 | AB76: =IF(4=C76,X76,H76) -> 0 | AC76: =IF(5=C76,X76,I76) -> 0 | AD76: =IF(6=C76,X76,J76) -> 0 | AE76: =SUM($Y76:Y76) -> 1 | AF76: =SUM($Y76:Z76) -> 2 | AG76: =SUM($Y76:AA76) -> 3 | AH76: =SUM($Y76:AB76) -> 3 | AI76: =SUM($Y76:AC76) -> 3 | AJ76: =SUM($Y76:AD76) -> 3 | AK76: =Smax*(1-POWER(Keep,AE76)) -> 70 | AL76: =Smax*(1-POWER(Keep,AF76)) -> 105 | AM76: =Smax*(1-POWER(Keep,AG76)) -> 122.5 | AN76: =Smax*(1-POWER(Keep,AH76)) -> 122.5 | AO76: =Smax*(1-POWER(Keep,AI76)) -> 122.5 | AP76: =Smax*(1-POWER(Keep,AJ76)) -> 122.5 | AQ76: =IF(D76=1,Cash0+SUM(AK76:AP76)-Cost_r*AJ76+A76*AP76,-1000000000) -> 1680
A77: =Credit_10 -> 10 | B77: 16 | C77: 4 | D77: =IF($G$16="",1,0) -> 0 | E77: =IF($D$16<>"",$D$16,IF(1<C77,1,0)) -> 1 | F77: =IF($E$16<>"",$E$16,IF(2<C77,1,0)) -> 1 | G77: =IF($F$16<>"",$F$16,IF(3<C77,1,0)) -> 1 | H77: =IF($G$16<>"",$G$16,IF(4<C77,1,0)) -> 0 | I77: =IF($H$16<>"",$H$16,IF(5<C77,1,0)) -> 0 | J77: =IF($I$16<>"",$I$16,IF(6<C77,1,0)) -> 0 | K77: =SUM($E77:E77) -> 1 | L77: =SUM($E77:F77) -> 2 | M77: =SUM($E77:G77) -> 3 | N77: =SUM($E77:H77) -> 3 | O77: =SUM($E77:I77) -> 3 | P77: =SUM($E77:J77) -> 3 | Q77: =IF(1>=C77,POWER(Keep,K77-INDEX(K77:P77,C77)),0) -> 0 | R77: =IF(2>=C77,POWER(Keep,L77-INDEX(K77:P77,C77)),0) -> 0 | S77: =IF(3>=C77,POWER(Keep,M77-INDEX(K77:P77,C77)),0) -> 0 | T77: =IF(4>=C77,POWER(Keep,N77-INDEX(K77:P77,C77)),0) -> 1 | U77: =IF(5>=C77,POWER(Keep,O77-INDEX(K77:P77,C77)),0) -> 1 | V77: =IF(6>=C77,POWER(Keep,P77-INDEX(K77:P77,C77)),0) -> 1 | W77: =SUM(Q77:V77)+A77*POWER(Keep,P77-INDEX(K77:P77,C77)) -> 13 | X77: =MIN(1,MAX(0,LN(Cost_r/(Slope0*W77))/LN(Keep)-INDEX(K77:P77,C77))) -> 0.39406577 | Y77: =IF(1=C77,X77,E77) -> 1 | Z77: =IF(2=C77,X77,F77) -> 1 | AA77: =IF(3=C77,X77,G77) -> 1 | AB77: =IF(4=C77,X77,H77) -> 0.39406577 | AC77: =IF(5=C77,X77,I77) -> 0 | AD77: =IF(6=C77,X77,J77) -> 0 | AE77: =SUM($Y77:Y77) -> 1 | AF77: =SUM($Y77:Z77) -> 2 | AG77: =SUM($Y77:AA77) -> 3 | AH77: =SUM($Y77:AB77) -> 3.3940658 | AI77: =SUM($Y77:AC77) -> 3.3940658 | AJ77: =SUM($Y77:AD77) -> 3.3940658 | AK77: =Smax*(1-POWER(Keep,AE77)) -> 70 | AL77: =Smax*(1-POWER(Keep,AF77)) -> 105 | AM77: =Smax*(1-POWER(Keep,AG77)) -> 122.5 | AN77: =Smax*(1-POWER(Keep,AH77)) -> 126.68282 | AO77: =Smax*(1-POWER(Keep,AI77)) -> 126.68282 | AP77: =Smax*(1-POWER(Keep,AJ77)) -> 126.68282 | AQ77: =IF(D77=1,Cash0+SUM(AK77:AP77)-Cost_r*AJ77+A77*AP77,-1000000000) -> -1000000000
A78: =Credit_10 -> 10 | B78: 16 | C78: 5 | D78: =IF($H$16="",1,0) -> 0 | E78: =IF($D$16<>"",$D$16,IF(1<C78,1,0)) -> 1 | F78: =IF($E$16<>"",$E$16,IF(2<C78,1,0)) -> 1 | G78: =IF($F$16<>"",$F$16,IF(3<C78,1,0)) -> 1 | H78: =IF($G$16<>"",$G$16,IF(4<C78,1,0)) -> 0 | I78: =IF($H$16<>"",$H$16,IF(5<C78,1,0)) -> 0 | J78: =IF($I$16<>"",$I$16,IF(6<C78,1,0)) -> 0 | K78: =SUM($E78:E78) -> 1 | L78: =SUM($E78:F78) -> 2 | M78: =SUM($E78:G78) -> 3 | N78: =SUM($E78:H78) -> 3 | O78: =SUM($E78:I78) -> 3 | P78: =SUM($E78:J78) -> 3 | Q78: =IF(1>=C78,POWER(Keep,K78-INDEX(K78:P78,C78)),0) -> 0 | R78: =IF(2>=C78,POWER(Keep,L78-INDEX(K78:P78,C78)),0) -> 0 | S78: =IF(3>=C78,POWER(Keep,M78-INDEX(K78:P78,C78)),0) -> 0 | T78: =IF(4>=C78,POWER(Keep,N78-INDEX(K78:P78,C78)),0) -> 0 | U78: =IF(5>=C78,POWER(Keep,O78-INDEX(K78:P78,C78)),0) -> 1 | V78: =IF(6>=C78,POWER(Keep,P78-INDEX(K78:P78,C78)),0) -> 1 | W78: =SUM(Q78:V78)+A78*POWER(Keep,P78-INDEX(K78:P78,C78)) -> 12 | X78: =MIN(1,MAX(0,LN(Cost_r/(Slope0*W78))/LN(Keep)-INDEX(K78:P78,C78))) -> 0.27858855 | Y78: =IF(1=C78,X78,E78) -> 1 | Z78: =IF(2=C78,X78,F78) -> 1 | AA78: =IF(3=C78,X78,G78) -> 1 | AB78: =IF(4=C78,X78,H78) -> 0 | AC78: =IF(5=C78,X78,I78) -> 0.27858855 | AD78: =IF(6=C78,X78,J78) -> 0 | AE78: =SUM($Y78:Y78) -> 1 | AF78: =SUM($Y78:Z78) -> 2 | AG78: =SUM($Y78:AA78) -> 3 | AH78: =SUM($Y78:AB78) -> 3 | AI78: =SUM($Y78:AC78) -> 3.2785885 | AJ78: =SUM($Y78:AD78) -> 3.2785885 | AK78: =Smax*(1-POWER(Keep,AE78)) -> 70 | AL78: =Smax*(1-POWER(Keep,AF78)) -> 105 | AM78: =Smax*(1-POWER(Keep,AG78)) -> 122.5 | AN78: =Smax*(1-POWER(Keep,AH78)) -> 122.5 | AO78: =Smax*(1-POWER(Keep,AI78)) -> 125.57305 | AP78: =Smax*(1-POWER(Keep,AJ78)) -> 125.57305 | AQ78: =IF(D78=1,Cash0+SUM(AK78:AP78)-Cost_r*AJ78+A78*AP78,-1000000000) -> -1000000000
A79: =Credit_10 -> 10 | B79: 16 | C79: 6 | D79: =IF($I$16="",1,0) -> 0 | E79: =IF($D$16<>"",$D$16,IF(1<C79,1,0)) -> 1 | F79: =IF($E$16<>"",$E$16,IF(2<C79,1,0)) -> 1 | G79: =IF($F$16<>"",$F$16,IF(3<C79,1,0)) -> 1 | H79: =IF($G$16<>"",$G$16,IF(4<C79,1,0)) -> 0 | I79: =IF($H$16<>"",$H$16,IF(5<C79,1,0)) -> 0 | J79: =IF($I$16<>"",$I$16,IF(6<C79,1,0)) -> 0 | K79: =SUM($E79:E79) -> 1 | L79: =SUM($E79:F79) -> 2 | M79: =SUM($E79:G79) -> 3 | N79: =SUM($E79:H79) -> 3 | O79: =SUM($E79:I79) -> 3 | P79: =SUM($E79:J79) -> 3 | Q79: =IF(1>=C79,POWER(Keep,K79-INDEX(K79:P79,C79)),0) -> 0 | R79: =IF(2>=C79,POWER(Keep,L79-INDEX(K79:P79,C79)),0) -> 0 | S79: =IF(3>=C79,POWER(Keep,M79-INDEX(K79:P79,C79)),0) -> 0 | T79: =IF(4>=C79,POWER(Keep,N79-INDEX(K79:P79,C79)),0) -> 0 | U79: =IF(5>=C79,POWER(Keep,O79-INDEX(K79:P79,C79)),0) -> 0 | V79: =IF(6>=C79,POWER(Keep,P79-INDEX(K79:P79,C79)),0) -> 1 | W79: =SUM(Q79:V79)+A79*POWER(Keep,P79-INDEX(K79:P79,C79)) -> 11 | X79: =MIN(1,MAX(0,LN(Cost_r/(Slope0*W79))/LN(Keep)-INDEX(K79:P79,C79))) -> 0.15305767 | Y79: =IF(1=C79,X79,E79) -> 1 | Z79: =IF(2=C79,X79,F79) -> 1 | AA79: =IF(3=C79,X79,G79) -> 1 | AB79: =IF(4=C79,X79,H79) -> 0 | AC79: =IF(5=C79,X79,I79) -> 0 | AD79: =IF(6=C79,X79,J79) -> 0.15305767 | AE79: =SUM($Y79:Y79) -> 1 | AF79: =SUM($Y79:Z79) -> 2 | AG79: =SUM($Y79:AA79) -> 3 | AH79: =SUM($Y79:AB79) -> 3 | AI79: =SUM($Y79:AC79) -> 3 | AJ79: =SUM($Y79:AD79) -> 3.1530577 | AK79: =Smax*(1-POWER(Keep,AE79)) -> 70 | AL79: =Smax*(1-POWER(Keep,AF79)) -> 105 | AM79: =Smax*(1-POWER(Keep,AG79)) -> 122.5 | AN79: =Smax*(1-POWER(Keep,AH79)) -> 122.5 | AO79: =Smax*(1-POWER(Keep,AI79)) -> 122.5 | AP79: =Smax*(1-POWER(Keep,AJ79)) -> 124.26151 | AQ79: =IF(D79=1,Cash0+SUM(AK79:AP79)-Cost_r*AJ79+A79*AP79,-1000000000) -> -1000000000
