Workbook

Sheet README
B1: DCT Laboratory — Vol I, Ch 13: Unified Enterprise Transformation Architecture
B2: Seed 26113 · Companion to DCT_V1_Ch13_Lab.ipynb and AXIOM Lab 1.13 (module AXIOM-13). Money in $ million.
B4: Worked Example 13.1, Is the Same Cash Promised Twice?, with the book's declarations, and the five steps of AXIOM Lab 1.13, One Company, Five Ledgers.
B5: Declarations: the inputs of Worked Example 13.1, Chapter 1's model (Online Appendix 1.B.4), Figure 13.2's cycle.
B6: Assemble: Meridian's skeleton (Chapter 9), the layers' references, contracts and buffer identity, and the compatibility checks (C1)-(C5) at each attachment in two orders (lab step 1).
B7: Couplings: Figure 13.2's three-layer cycle quarter by quarter, and an interaction-matrix editor that finds rho(M) and its split by block by power iteration (lab step 2).
B8: Wavefront: distances on the skeleton by relaxation, the ledger clocks of the digital program and of a demand shock, the feedback core, and the ancestors of a tripwire (lab step 3).
B9: Ledgers: the program month by month in three ledgers, Figure 13.1 (lab step 5).
B10: JointCheck: the sign-offs, the joint check and the buffer line, Figure 13.3 (Worked Example 13.1, Steps 1-3; lab step 4).
B11: Repairs: Table 13.6 (Step 4). Decide: the separated verdicts against the unified one (Step 5; lab step 5).
B12: Only the breach odds and the average simulated low are the engine's (the book's 100,000 paths, seed 8; a fresh stream with the lab's seed 26113). Reference_Values and Checks: the notebook engine's numbers and a PASS/FAIL comparison with this workbook's formulas.
B14: LEGEND
... B18: Cross-sheet link: green.

Sheet Declarations
A1: Declarations (Worked Example 13.1, Step 1; Table 13.1). Money in $ million.
A3: Quantity | B3: Value | C3: Source
A4: Liquidity today ($ million) | B4: 620 | C4: Table 3.1; Worked Example 13.1, Step 1
A5: The board's liquidity floor ($ million) | B5: 350 | C5: Table 5.4; at treasury (Table 9.3)
A6: Cash above the floor ($ million) | B6: =B4-B5 -> 270 | C6: Worked Example 13.1: $270 million
A7: Liquidity per index point ($ million) | B7: =B4/100 -> 6.2 | C7: Chapter 1: index 100 = $620 million
A8: Phased build: trough depth (index points) | B8: 20 | C8: Chapter 8: depth 20 instead of 28
A9: Closure size: mean ($ million) | B9: 120 | C9: Chapter 8, Worked Example 8.1
A10: Closure size: standard deviation ($ million) | B10: 50 | C10: Chapter 8, Worked Example 8.1
A11: Closure law: gamma shape, (mean / sd)^2 | B11: =(B9/B10)^2 -> 5.76 | C11: 5.76
A12: Closure law: gamma scale, sd^2 / mean | B12: =B10^2/B9 -> 20.833333 | C12: 20.83
A13: The risk office's buffer: closure percentile | B13: 0.9 | C13: Chapter 12: the 90th-percentile closure
A14: The relaxed buffer: closure percentile | B14: 0.5 | C14: Worked Example 13.1, Step 4: the median closure
A15: Standby line: cover of any closure ($ million) | B15: 100 | C15: Chapter 8
A16: The board's appetite: breach probability at most | B16: 0.05 | C16: Chapter 8
A17: Strategic-risk ceiling | B17: 75 | C17: Table 9.3
A18: Workforce capability today | B18: 58 | C18: Table 3.1
A19: Capability floor for the digital build | B19: 55 | C19: Table 9.3 (engineering, Digital)
A20: Capability lost a quarter | B20: 0.025 | C20: Chapter 10
A21: Price of a capability point ($ million) | B21: 4 | C21: Chapter 10
A22: Capability rent ($ million a year), delta x 58 x 4 quarters x price | B22: =B20*B18*4*B21 -> 23.2 | C22: Table 13.1: $23 million a year
A23: Cycle: share of a loss each layer keeps a quarter, a | B23: 0.5 | C23: Figure 13.2
A24: Cycle: share passed on to the next layer, c | B24: 0.25 | C24: Figure 13.2: 0.25 (also 0.40)
A26: Chapter 1 model (Online Appendix 1.B.4) | B26: Today | C26: Target | D26: Speed a year | E26: Trough (signed) | F26: Trough time (years)
A27: Liquidity index (today = 100) | B27: 100 | C27: 112 | D27: 0.35 | E27: -28 | F27: 2
A28: Technology platform | B28: 41 | C28: 78 | D28: 0.55 | E28: 0 | F28: 1
A29: Operational efficiency | B29: 71 | C29: 77 | D29: 0.5 | E29: -9 | F29: 1.5
A30: Strategic risk | B30: 64 | C30: 51 | D30: 0.4 | E30: 14 | F30: 1.2
A31: x(t) = target + (today - target) e^(-speed t) + trough (t / trough time) e^(1 - t / trough time), t in years; technology has no trough. The digital program's paths, as in Chapters 1, 8 and 13.

Sheet Assemble
A1: Assemble: Meridian's unified architecture on one skeleton (Theorems 13.1 and 13.2(i); Definition 13.4; Table 13.1; AXIOM Lab 1.13, step 1)
A2: Attach the layers in two orders. Integration adjoins a declaration (Definition 13.3), so the result is the same; only the step at which (C4) fails moves.
A4: Component (Table 9.1) | B4: Name | D4: Arrow from | E4: to | F4: Type (Worked Example 9.1) | G4: Endpoints resolve | I4: Constraint (Table 9.3) | J4: Scope
A5: MKT | B5: market | D5: MKT | E5: IND | F5: demand | G5: =AND(COUNTIF(Comps,D5)=1,COUNTIF(Comps,E5)=1) -> TRUE | I5: Covenant: net leverage at most 4.5x | J5: TRS
A6: GOV | B6: governance | D6: MKT | E6: DIG | F6: demand | G6: =AND(COUNTIF(Comps,D6)=1,COUNTIF(Comps,E6)=1) -> TRUE | I6: Liquidity floor of $350 million | J6: TRS
A7: MAT | B7: Advanced Materials | D7: MKT | E7: MAT | F7: demand | G7: =AND(COUNTIF(Comps,D7)=1,COUNTIF(Comps,E7)=1) -> TRUE | I7: Plant capacity | J7: IND
A8: IND | B8: Industrial Systems | D8: IND | E8: TRS | F8: cash | G8: =AND(COUNTIF(Comps,D8)=1,COUNTIF(Comps,E8)=1) -> TRUE | I8: Strategic-risk ceiling of 75 | J8: IND, DIG, MAT
A9: DIG | B9: Digital Solutions | D9: DIG | E9: TRS | F9: cash | G9: =AND(COUNTIF(Comps,D9)=1,COUNTIF(Comps,E9)=1) -> TRUE | I9: Capability of at least 55 for the digital build | J9: ENG, DIG
A10: ENG | B10: shared engineering | D10: MAT | E10: TRS | F10: cash | G10: =AND(COUNTIF(Comps,D10)=1,COUNTIF(Comps,E10)=1) -> TRUE
A11: TRS | B11: treasury | D11: TRS | E11: IND | F11: funding | G11: =AND(COUNTIF(Comps,D11)=1,COUNTIF(Comps,E11)=1) -> TRUE
D12: TRS | E12: DIG | F12: funding | G12: =AND(COUNTIF(Comps,D12)=1,COUNTIF(Comps,E12)=1) -> TRUE
D13: ENG | E13: IND | F13: capability | G13: =AND(COUNTIF(Comps,D13)=1,COUNTIF(Comps,E13)=1) -> TRUE
D14: IND | E14: ENG | F14: capability | G14: =AND(COUNTIF(Comps,D14)=1,COUNTIF(Comps,E14)=1) -> TRUE
D15: ENG | E15: DIG | F15: capability | G15: =AND(COUNTIF(Comps,D15)=1,COUNTIF(Comps,E15)=1) -> TRUE
D16: DIG | E16: ENG | F16: capability | G16: =AND(COUNTIF(Comps,D16)=1,COUNTIF(Comps,E16)=1) -> TRUE
D17: GOV | E17: TRS | F17: policy | G17: =AND(COUNTIF(Comps,D17)=1,COUNTIF(Comps,E17)=1) -> TRUE
D18: GOV | E18: DIG | F18: policy | G18: =AND(COUNTIF(Comps,D18)=1,COUNTIF(Comps,E18)=1) -> TRUE
A21: Form of capital (Table 10.1) | C21: Performance dimension (Table 11.2)
A22: Financial | C22: Financial
A23: Human | C23: Operational
A24: Intellectual | C24: Strategic
A25: Technological | C25: Human
A26: Organizational | C26: Technological
A27: Relational | C27: Innovation
A28: Strategic | C28: Governance
A29: Governance | C29: Environmental
A30: Innovation | C30: Resilience
A31: Informational | C31: Sustainability
A33: Counts | B33: Value | C33: Book
A34: Components | B34: =COUNTA(A5:A11) -> 7 | C34: Table 13.1: seven
A35: Arrows | B35: =COUNTA(D5:D18) -> 14 | C35: Worked Example 9.1: fourteen
A36: Arrows whose endpoints resolve | B36: =COUNTIF(G5:G18,TRUE()) -> 14
A37: Forms of capital | B37: =COUNTA(A22:A31) -> 10 | C37: Table 13.1: ten forms
A38: Performance dimensions | B38: =COUNTA(C22:C31) -> 10 | C38: Table 13.1: ten dimensions
A39: Capability rent ($ million a year) | B39: =Rent_year -> 23.2 | C39: Table 13.1: $23 million
A42: Layer | B42: Carrier, support, write set or buffer | C42: Component | D42: Resolves (C1) | F42: Layer | G42: References | H42: Unresolved (C1)
A43: transformation | B43: digital build: write set | C43: DIG | D43: =COUNTIF(Comps,C43)=1 -> TRUE | F43: transformation | G43: =COUNTIF(Ref_layer,"transformation") -> 3 | H43: =COUNTIFS(Ref_layer,"transformation",Ref_ok,FALSE()) -> 0
A44: transformation | B44: digital build: write set | C44: ENG | D44: =COUNTIF(Comps,C44)=1 -> TRUE | F44: capital | G44: =COUNTIF(Ref_layer,"capital") -> 4 | H44: =COUNTIFS(Ref_layer,"capital",Ref_ok,FALSE()) -> 0
A45: transformation | B45: program draw D | C45: DIG | D45: =COUNTIF(Comps,C45)=1 -> TRUE | F45: performance | G45: =COUNTIF(Ref_layer,"performance") -> 10 | H45: =COUNTIFS(Ref_layer,"performance",Ref_ok,FALSE()) -> 0
A46: capital | B46: liquidity | C46: TRS | D46: =COUNTIF(Comps,C46)=1 -> TRUE | F46: risk | G46: =COUNTIF(Ref_layer,"risk") -> 16 | H46: =COUNTIFS(Ref_layer,"risk",Ref_ok,FALSE()) -> 0
A47: capital | B47: net leverage | C47: TRS | D47: =COUNTIF(Comps,C47)=1 -> TRUE
A48: capital | B48: workforce capability | C48: ENG | D48: =COUNTIF(Comps,C48)=1 -> TRUE
A49: capital | B49: cash above the floor A | C49: TRS | D49: =COUNTIF(Comps,C49)=1 -> TRUE
A50: performance | B50: P_F | C50: TRS | D50: =COUNTIF(Comps,C50)=1 -> TRUE
A51: performance | B51: P_O | C51: IND | D51: =COUNTIF(Comps,C51)=1 -> TRUE
A52: performance | B52: P_O | C52: MAT | D52: =COUNTIF(Comps,C52)=1 -> TRUE
A53: performance | B53: P_S | C53: IND | D53: =COUNTIF(Comps,C53)=1 -> TRUE
A54: performance | B54: P_S | C54: DIG | D54: =COUNTIF(Comps,C54)=1 -> TRUE
A55: performance | B55: P_S | C55: MAT | D55: =COUNTIF(Comps,C55)=1 -> TRUE
A56: performance | B56: P_T | C56: DIG | D56: =COUNTIF(Comps,C56)=1 -> TRUE
A57: performance | B57: P_I | C57: DIG | D57: =COUNTIF(Comps,C57)=1 -> TRUE
A58: performance | B58: P_I | C58: ENG | D58: =COUNTIF(Comps,C58)=1 -> TRUE
... A75: risk | B75: closure buffer B | C75: TRS | D75: =COUNTIF(Comps,C75)=1 -> TRUE
A78: Indicator | B78: Contract (Table 5.2) | C78: Capital reads it with | D78: Performance reads it with | E78: Risk reads it with | F78: One contract (C2)
A79: liquidity | B79: treasury systems, +/-1% | C79: treasury systems, +/-1% | D79: treasury systems, +/-1% | E79: treasury systems, +/-1% | F79: =IF(AND(OR(C79="",C79=B79),OR(D79="",D79=B79),OR(E79="",E79=B79)),"one contract","CONFLICT") -> one contract
A80: net leverage | B80: audited accounts, +/-2% | C80: audited accounts, +/-2% | F80: =IF(AND(OR(C80="",C80=B80),OR(D80="",D80=B80),OR(E80="",E80=B80)),"one contract","CONFLICT") -> one contract
A81: workforce capability | B81: skills survey, +/-5 points | C81: skills survey, +/-5 points | F81: =IF(AND(OR(C81="",C81=B81),OR(D81="",D81=B81),OR(E81="",E81=B81)),"one contract","CONFLICT") -> one contract
A82: technology platform | B82: architecture audit, +/-4 points | D82: architecture audit, +/-4 points | F82: =IF(AND(OR(C82="",C82=B82),OR(D82="",D82=B82),OR(E82="",E82=B82)),"one contract","CONFLICT") -> one contract
A83: operational efficiency | B83: cost benchmarking, +/-3 points | D83: cost benchmarking, +/-3 points | F83: =IF(AND(OR(C83="",C83=B83),OR(D83="",D83=B83),OR(E83="",E83=B83)),"one contract","CONFLICT") -> one contract
A84: strategic risk | B84: risk committee, +/-6 points | D84: risk committee, +/-6 points | E84: risk committee, +/-6 points | F84: =IF(AND(OR(C84="",C84=B84),OR(D84="",D84=B84),OR(E84="",E84=B84)),"one contract","CONFLICT") -> one contract
A87: Buffer (risk layer) | B87: Funding stock it names | C87: Declared by the capital layer (C3)
A88: closure buffer B | B88: cash above the floor A | C88: =COUNTIFS(Ref_layer,"capital",Ref_name,B88)>0 -> TRUE
A91: Claims on treasury cash (C4) | B91: Layer | C91: Value ($ million)
A92: program draw D | B92: transformation | C92: =JointCheck!$K$7 -> 138.04962
A93: closure buffer B | B93: risk | C93: =JointCheck!$K$12 -> 186.86698
A94: cash above the floor A | B94: capital | C94: =Pool_cash -> 270
A96: Order 1: transformation, capital, performance, risk
A97: Step | B97: Layer attached | C97: Transformation | D97: Capital | E97: Performance | F97: Risk | G97: Unresolved references | H97: C1 | I97: C2 | J97: C3 | K97: Claims on treasury cash | L97: C4 | M97: C5: the digital build's domain | O97: C2 helper: liquidity | P97: C2 helper: net leverage | Q97: C2 helper: workforce capability | R97: C2 helper: technology platform | S97: C2 helper: operational efficiency | T97: C2 helper: strategic risk
A98: 1 | B98: transformation | C98: =IF(COUNTIF($B$98:B98,"transformation")>0,1,0) -> 1 | D98: =IF(COUNTIF($B$98:B98,"capital")>0,1,0) -> 0 | E98: =IF(COUNTIF($B$98:B98,"performance")>0,1,0) -> 0 | F98: =IF(COUNTIF($B$98:B98,"risk")>0,1,0) -> 0 | G98: =C98*$H$43+D98*$H$44+E98*$H$45+F98*$H$46 -> 0 | H98: =IF(G98=0,"pass","FAIL") -> pass | I98: =IF(SUM(O98:T98)=0,"pass","FAIL") -> pass | J98: =IF(F98=0,"pass",IF(AND(D98=1,$C$88),"pass","FAIL")) -> pass | K98: =C98*$C$92+IF(AND(F98=1,D98=1,$C$88),$C$93,0) -> 138.04962 | L98: =IF(K98<=$C$94,"pass","FAIL") -> pass | M98: =IF(C98=0,"no operator yet",IF(AND(L98="pass",Cap_today>=Cap_floor),"nonempty","empty")) -> nonempty | O98: =IF(OR(AND(IF(AND($D98=1,$C$79<>""),$C$79,"")<>"",IF(AND($E98=1,$D$79<>""),$D$79,"")<>"",IF(AND($D98=1,$C$79<>""),$C$79,"")<>IF(AND($E98=1,$D$79<>""),$D$79,"")),AND(IF(AND($D98=1,$C$79<>""),$C$79,"")<>"",IF(AND($F98=1,$E$79<>""),$E$79,"")<>"",IF(AND($D98=1,$C$79<>""),$C$79,"")<>IF(AND($F98=1,$E$79<>""),$E$79,"")),AND(IF(AND($E98=1,$D$79<>""),$D$79,"")<>"",IF(AND($F98=1,$E$79<>""),$E$79,"")<>"",IF(AND($E98=1,$D$79<>""),$D$79,"")<>IF(AND($F98=1,$E$79<>""),$E$79,""))),1,0) -> 0 | P98: =IF(OR(AND(IF(AND($D98=1,$C$80<>""),$C$80,"")<>"",IF(AND($E98=1,$D$80<>""),$D$80,"")<>"",IF(AND($D98=1,$C$80<>""),$C$80,"")<>IF(AND($E98=1,$D$80<>""),$D$80,"")),AND(IF(AND($D98=1,$C$80<>""),$C$80,"")<>"",IF(AND($F98=1,$E$80<>""),$E$80,"")<>"",IF(AND($D98=1,$C$80<>""),$C$80,"")<>IF(AND($F98=1,$E$80<>""),$E$80,"")),AND(IF(AND($E98=1,$D$80<>""),$D$80,"")<>"",IF(AND($F98=1,$E$80<>""),$E$80,"")<>"",IF(AND($E98=1,$D$80<>""),$D$80,"")<>IF(AND($F98=1,$E$80<>""),$E$80,""))),1,0) -> 0 | Q98: =IF(OR(AND(IF(AND($D98=1,$C$81<>""),$C$81,"")<>"",IF(AND($E98=1,$D$81<>""),$D$81,"")<>"",IF(AND($D98=1,$C$81<>""),$C$81,"")<>IF(AND($E98=1,$D$81<>""),$D$81,"")),AND(IF(AND($D98=1,$C$81<>""),$C$81,"")<>"",IF(AND($F98=1,$E$81<>""),$E$81,"")<>"",IF(AND($D98=1,$C$81<>""),$C$81,"")<>IF(AND($F98=1,$E$81<>""),$E$81,"")),AND(IF(AND($E98=1,$D$81<>""),$D$81,"")<>"",IF(AND($F98=1,$E$81<>""),$E$81,"")<>"",IF(AND($E98=1,$D$81<>""),$D$81,"")<>IF(AND($F98=1,$E$81<>""),$E$81,""))),1,0) -> 0 | R98: =IF(OR(AND(IF(AND($D98=1,$C$82<>""),$C$82,"")<>"",IF(AND($E98=1,$D$82<>""),$D$82,"")<>"",IF(AND($D98=1,$C$82<>""),$C$82,"")<>IF(AND($E98=1,$D$82<>""),$D$82,"")),AND(IF(AND($D98=1,$C$82<>""),$C$82,"")<>"",IF(AND($F98=1,$E$82<>""),$E$82,"")<>"",IF(AND($D98=1,$C$82<>""),$C$82,"")<>IF(AND($F98=1,$E$82<>""),$E$82,"")),AND(IF(AND($E98=1,$D$82<>""),$D$82,"")<>"",IF(AND($F98=1,$E$82<>""),$E$82,"")<>"",IF(AND($E98=1,$D$82<>""),$D$82,"")<>IF(AND($F98=1,$E$82<>""),$E$82,""))),1,0) -> 0 | S98: =IF(OR(AND(IF(AND($D98=1,$C$83<>""),$C$83,"")<>"",IF(AND($E98=1,$D$83<>""),$D$83,"")<>"",IF(AND($D98=1,$C$83<>""),$C$83,"")<>IF(AND($E98=1,$D$83<>""),$D$83,"")),AND(IF(AND($D98=1,$C$83<>""),$C$83,"")<>"",IF(AND($F98=1,$E$83<>""),$E$83,"")<>"",IF(AND($D98=1,$C$83<>""),$C$83,"")<>IF(AND($F98=1,$E$83<>""),$E$83,"")),AND(IF(AND($E98=1,$D$83<>""),$D$83,"")<>"",IF(AND($F98=1,$E$83<>""),$E$83,"")<>"",IF(AND($E98=1,$D$83<>""),$D$83,"")<>IF(AND($F98=1,$E$83<>""),$E$83,""))),1,0) -> 0 | T98: =IF(OR(AND(IF(AND($D98=1,$C$84<>""),$C$84,"")<>"",IF(AND($E98=1,$D$84<>""),$D$84,"")<>"",IF(AND($D98=1,$C$84<>""),$C$84,"")<>IF(AND($E98=1,$D$84<>""),$D$84,"")),AND(IF(AND($D98=1,$C$84<>""),$C$84,"")<>"",IF(AND($F98=1,$E$84<>""),$E$84,"")<>"",IF(AND($D98=1,$C$84<>""),$C$84,"")<>IF(AND($F98=1,$E$84<>""),$E$84,"")),AND(IF(AND($E98=1,$D$84<>""),$D$84,"")<>"",IF(AND($F98=1,$E$84<>""),$E$84,"")<>"",IF(AND($E98=1,$D$84<>""),$D$84,"")<>IF(AND($F98=1,$E$84<>""),$E$84,""))),1,0) -> 0
A99: 2 | B99: capital | C99: =IF(COUNTIF($B$98:B99,"transformation")>0,1,0) -> 1 | D99: =IF(COUNTIF($B$98:B99,"capital")>0,1,0) -> 1 | E99: =IF(COUNTIF($B$98:B99,"performance")>0,1,0) -> 0 | F99: =IF(COUNTIF($B$98:B99,"risk")>0,1,0) -> 0 | G99: =C99*$H$43+D99*$H$44+E99*$H$45+F99*$H$46 -> 0 | H99: =IF(G99=0,"pass","FAIL") -> pass | I99: =IF(SUM(O99:T99)=0,"pass","FAIL") -> pass | J99: =IF(F99=0,"pass",IF(AND(D99=1,$C$88),"pass","FAIL")) -> pass | K99: =C99*$C$92+IF(AND(F99=1,D99=1,$C$88),$C$93,0) -> 138.04962 | L99: =IF(K99<=$C$94,"pass","FAIL") -> pass | M99: =IF(C99=0,"no operator yet",IF(AND(L99="pass",Cap_today>=Cap_floor),"nonempty","empty")) -> nonempty | O99: =IF(OR(AND(IF(AND($D99=1,$C$79<>""),$C$79,"")<>"",IF(AND($E99=1,$D$79<>""),$D$79,"")<>"",IF(AND($D99=1,$C$79<>""),$C$79,"")<>IF(AND($E99=1,$D$79<>""),$D$79,"")),AND(IF(AND($D99=1,$C$79<>""),$C$79,"")<>"",IF(AND($F99=1,$E$79<>""),$E$79,"")<>"",IF(AND($D99=1,$C$79<>""),$C$79,"")<>IF(AND($F99=1,$E$79<>""),$E$79,"")),AND(IF(AND($E99=1,$D$79<>""),$D$79,"")<>"",IF(AND($F99=1,$E$79<>""),$E$79,"")<>"",IF(AND($E99=1,$D$79<>""),$D$79,"")<>IF(AND($F99=1,$E$79<>""),$E$79,""))),1,0) -> 0 | P99: =IF(OR(AND(IF(AND($D99=1,$C$80<>""),$C$80,"")<>"",IF(AND($E99=1,$D$80<>""),$D$80,"")<>"",IF(AND($D99=1,$C$80<>""),$C$80,"")<>IF(AND($E99=1,$D$80<>""),$D$80,"")),AND(IF(AND($D99=1,$C$80<>""),$C$80,"")<>"",IF(AND($F99=1,$E$80<>""),$E$80,"")<>"",IF(AND($D99=1,$C$80<>""),$C$80,"")<>IF(AND($F99=1,$E$80<>""),$E$80,"")),AND(IF(AND($E99=1,$D$80<>""),$D$80,"")<>"",IF(AND($F99=1,$E$80<>""),$E$80,"")<>"",IF(AND($E99=1,$D$80<>""),$D$80,"")<>IF(AND($F99=1,$E$80<>""),$E$80,""))),1,0) -> 0 | Q99: =IF(OR(AND(IF(AND($D99=1,$C$81<>""),$C$81,"")<>"",IF(AND($E99=1,$D$81<>""),$D$81,"")<>"",IF(AND($D99=1,$C$81<>""),$C$81,"")<>IF(AND($E99=1,$D$81<>""),$D$81,"")),AND(IF(AND($D99=1,$C$81<>""),$C$81,"")<>"",IF(AND($F99=1,$E$81<>""),$E$81,"")<>"",IF(AND($D99=1,$C$81<>""),$C$81,"")<>IF(AND($F99=1,$E$81<>""),$E$81,"")),AND(IF(AND($E99=1,$D$81<>""),$D$81,"")<>"",IF(AND($F99=1,$E$81<>""),$E$81,"")<>"",IF(AND($E99=1,$D$81<>""),$D$81,"")<>IF(AND($F99=1,$E$81<>""),$E$81,""))),1,0) -> 0 | R99: =IF(OR(AND(IF(AND($D99=1,$C$82<>""),$C$82,"")<>"",IF(AND($E99=1,$D$82<>""),$D$82,"")<>"",IF(AND($D99=1,$C$82<>""),$C$82,"")<>IF(AND($E99=1,$D$82<>""),$D$82,"")),AND(IF(AND($D99=1,$C$82<>""),$C$82,"")<>"",IF(AND($F99=1,$E$82<>""),$E$82,"")<>"",IF(AND($D99=1,$C$82<>""),$C$82,"")<>IF(AND($F99=1,$E$82<>""),$E$82,"")),AND(IF(AND($E99=1,$D$82<>""),$D$82,"")<>"",IF(AND($F99=1,$E$82<>""),$E$82,"")<>"",IF(AND($E99=1,$D$82<>""),$D$82,"")<>IF(AND($F99=1,$E$82<>""),$E$82,""))),1,0) -> 0 | S99: =IF(OR(AND(IF(AND($D99=1,$C$83<>""),$C$83,"")<>"",IF(AND($E99=1,$D$83<>""),$D$83,"")<>"",IF(AND($D99=1,$C$83<>""),$C$83,"")<>IF(AND($E99=1,$D$83<>""),$D$83,"")),AND(IF(AND($D99=1,$C$83<>""),$C$83,"")<>"",IF(AND($F99=1,$E$83<>""),$E$83,"")<>"",IF(AND($D99=1,$C$83<>""),$C$83,"")<>IF(AND($F99=1,$E$83<>""),$E$83,"")),AND(IF(AND($E99=1,$D$83<>""),$D$83,"")<>"",IF(AND($F99=1,$E$83<>""),$E$83,"")<>"",IF(AND($E99=1,$D$83<>""),$D$83,"")<>IF(AND($F99=1,$E$83<>""),$E$83,""))),1,0) -> 0 | T99: =IF(OR(AND(IF(AND($D99=1,$C$84<>""),$C$84,"")<>"",IF(AND($E99=1,$D$84<>""),$D$84,"")<>"",IF(AND($D99=1,$C$84<>""),$C$84,"")<>IF(AND($E99=1,$D$84<>""),$D$84,"")),AND(IF(AND($D99=1,$C$84<>""),$C$84,"")<>"",IF(AND($F99=1,$E$84<>""),$E$84,"")<>"",IF(AND($D99=1,$C$84<>""),$C$84,"")<>IF(AND($F99=1,$E$84<>""),$E$84,"")),AND(IF(AND($E99=1,$D$84<>""),$D$84,"")<>"",IF(AND($F99=1,$E$84<>""),$E$84,"")<>"",IF(AND($E99=1,$D$84<>""),$D$84,"")<>IF(AND($F99=1,$E$84<>""),$E$84,""))),1,0) -> 0
A100: 3 | B100: performance | C100: =IF(COUNTIF($B$98:B100,"transformation")>0,1,0) -> 1 | D100: =IF(COUNTIF($B$98:B100,"capital")>0,1,0) -> 1 | E100: =IF(COUNTIF($B$98:B100,"performance")>0,1,0) -> 1 | F100: =IF(COUNTIF($B$98:B100,"risk")>0,1,0) -> 0 | G100: =C100*$H$43+D100*$H$44+E100*$H$45+F100*$H$46 -> 0 | H100: =IF(G100=0,"pass","FAIL") -> pass | I100: =IF(SUM(O100:T100)=0,"pass","FAIL") -> pass | J100: =IF(F100=0,"pass",IF(AND(D100=1,$C$88),"pass","FAIL")) -> pass | K100: =C100*$C$92+IF(AND(F100=1,D100=1,$C$88),$C$93,0) -> 138.04962 | L100: =IF(K100<=$C$94,"pass","FAIL") -> pass | M100: =IF(C100=0,"no operator yet",IF(AND(L100="pass",Cap_today>=Cap_floor),"nonempty","empty")) -> nonempty | O100: =IF(OR(AND(IF(AND($D100=1,$C$79<>""),$C$79,"")<>"",IF(AND($E100=1,$D$79<>""),$D$79,"")<>"",IF(AND($D100=1,$C$79<>""),$C$79,"")<>IF(AND($E100=1,$D$79<>""),$D$79,"")),AND(IF(AND($D100=1,$C$79<>""),$C$79,"")<>"",IF(AND($F100=1,$E$79<>""),$E$79,"")<>"",IF(AND($D100=1,$C$79<>""),$C$79,"")<>IF(AND($F100=1,$E$79<>""),$E$79,"")),AND(IF(AND($E100=1,$D$79<>""),$D$79,"")<>"",IF(AND($F100=1,$E$79<>""),$E$79,"")<>"",IF(AND($E100=1,$D$79<>""),$D$79,"")<>IF(AND($F100=1,$E$79<>""),$E$79,""))),1,0) -> 0 | P100: =IF(OR(AND(IF(AND($D100=1,$C$80<>""),$C$80,"")<>"",IF(AND($E100=1,$D$80<>""),$D$80,"")<>"",IF(AND($D100=1,$C$80<>""),$C$80,"")<>IF(AND($E100=1,$D$80<>""),$D$80,"")),AND(IF(AND($D100=1,$C$80<>""),$C$80,"")<>"",IF(AND($F100=1,$E$80<>""),$E$80,"")<>"",IF(AND($D100=1,$C$80<>""),$C$80,"")<>IF(AND($F100=1,$E$80<>""),$E$80,"")),AND(IF(AND($E100=1,$D$80<>""),$D$80,"")<>"",IF(AND($F100=1,$E$80<>""),$E$80,"")<>"",IF(AND($E100=1,$D$80<>""),$D$80,"")<>IF(AND($F100=1,$E$80<>""),$E$80,""))),1,0) -> 0 | Q100: =IF(OR(AND(IF(AND($D100=1,$C$81<>""),$C$81,"")<>"",IF(AND($E100=1,$D$81<>""),$D$81,"")<>"",IF(AND($D100=1,$C$81<>""),$C$81,"")<>IF(AND($E100=1,$D$81<>""),$D$81,"")),AND(IF(AND($D100=1,$C$81<>""),$C$81,"")<>"",IF(AND($F100=1,$E$81<>""),$E$81,"")<>"",IF(AND($D100=1,$C$81<>""),$C$81,"")<>IF(AND($F100=1,$E$81<>""),$E$81,"")),AND(IF(AND($E100=1,$D$81<>""),$D$81,"")<>"",IF(AND($F100=1,$E$81<>""),$E$81,"")<>"",IF(AND($E100=1,$D$81<>""),$D$81,"")<>IF(AND($F100=1,$E$81<>""),$E$81,""))),1,0) -> 0 | R100: =IF(OR(AND(IF(AND($D100=1,$C$82<>""),$C$82,"")<>"",IF(AND($E100=1,$D$82<>""),$D$82,"")<>"",IF(AND($D100=1,$C$82<>""),$C$82,"")<>IF(AND($E100=1,$D$82<>""),$D$82,"")),AND(IF(AND($D100=1,$C$82<>""),$C$82,"")<>"",IF(AND($F100=1,$E$82<>""),$E$82,"")<>"",IF(AND($D100=1,$C$82<>""),$C$82,"")<>IF(AND($F100=1,$E$82<>""),$E$82,"")),AND(IF(AND($E100=1,$D$82<>""),$D$82,"")<>"",IF(AND($F100=1,$E$82<>""),$E$82,"")<>"",IF(AND($E100=1,$D$82<>""),$D$82,"")<>IF(AND($F100=1,$E$82<>""),$E$82,""))),1,0) -> 0 | S100: =IF(OR(AND(IF(AND($D100=1,$C$83<>""),$C$83,"")<>"",IF(AND($E100=1,$D$83<>""),$D$83,"")<>"",IF(AND($D100=1,$C$83<>""),$C$83,"")<>IF(AND($E100=1,$D$83<>""),$D$83,"")),AND(IF(AND($D100=1,$C$83<>""),$C$83,"")<>"",IF(AND($F100=1,$E$83<>""),$E$83,"")<>"",IF(AND($D100=1,$C$83<>""),$C$83,"")<>IF(AND($F100=1,$E$83<>""),$E$83,"")),AND(IF(AND($E100=1,$D$83<>""),$D$83,"")<>"",IF(AND($F100=1,$E$83<>""),$E$83,"")<>"",IF(AND($E100=1,$D$83<>""),$D$83,"")<>IF(AND($F100=1,$E$83<>""),$E$83,""))),1,0) -> 0 | T100: =IF(OR(AND(IF(AND($D100=1,$C$84<>""),$C$84,"")<>"",IF(AND($E100=1,$D$84<>""),$D$84,"")<>"",IF(AND($D100=1,$C$84<>""),$C$84,"")<>IF(AND($E100=1,$D$84<>""),$D$84,"")),AND(IF(AND($D100=1,$C$84<>""),$C$84,"")<>"",IF(AND($F100=1,$E$84<>""),$E$84,"")<>"",IF(AND($D100=1,$C$84<>""),$C$84,"")<>IF(AND($F100=1,$E$84<>""),$E$84,"")),AND(IF(AND($E100=1,$D$84<>""),$D$84,"")<>"",IF(AND($F100=1,$E$84<>""),$E$84,"")<>"",IF(AND($E100=1,$D$84<>""),$D$84,"")<>IF(AND($F100=1,$E$84<>""),$E$84,""))),1,0) -> 0
A101: 4 | B101: risk | C101: =IF(COUNTIF($B$98:B101,"transformation")>0,1,0) -> 1 | D101: =IF(COUNTIF($B$98:B101,"capital")>0,1,0) -> 1 | E101: =IF(COUNTIF($B$98:B101,"performance")>0,1,0) -> 1 | F101: =IF(COUNTIF($B$98:B101,"risk")>0,1,0) -> 1 | G101: =C101*$H$43+D101*$H$44+E101*$H$45+F101*$H$46 -> 0 | H101: =IF(G101=0,"pass","FAIL") -> pass | I101: =IF(SUM(O101:T101)=0,"pass","FAIL") -> pass | J101: =IF(F101=0,"pass",IF(AND(D101=1,$C$88),"pass","FAIL")) -> pass | K101: =C101*$C$92+IF(AND(F101=1,D101=1,$C$88),$C$93,0) -> 324.91659 | L101: =IF(K101<=$C$94,"pass","FAIL") -> FAIL | M101: =IF(C101=0,"no operator yet",IF(AND(L101="pass",Cap_today>=Cap_floor),"nonempty","empty")) -> empty | O101: =IF(OR(AND(IF(AND($D101=1,$C$79<>""),$C$79,"")<>"",IF(AND($E101=1,$D$79<>""),$D$79,"")<>"",IF(AND($D101=1,$C$79<>""),$C$79,"")<>IF(AND($E101=1,$D$79<>""),$D$79,"")),AND(IF(AND($D101=1,$C$79<>""),$C$79,"")<>"",IF(AND($F101=1,$E$79<>""),$E$79,"")<>"",IF(AND($D101=1,$C$79<>""),$C$79,"")<>IF(AND($F101=1,$E$79<>""),$E$79,"")),AND(IF(AND($E101=1,$D$79<>""),$D$79,"")<>"",IF(AND($F101=1,$E$79<>""),$E$79,"")<>"",IF(AND($E101=1,$D$79<>""),$D$79,"")<>IF(AND($F101=1,$E$79<>""),$E$79,""))),1,0) -> 0 | P101: =IF(OR(AND(IF(AND($D101=1,$C$80<>""),$C$80,"")<>"",IF(AND($E101=1,$D$80<>""),$D$80,"")<>"",IF(AND($D101=1,$C$80<>""),$C$80,"")<>IF(AND($E101=1,$D$80<>""),$D$80,"")),AND(IF(AND($D101=1,$C$80<>""),$C$80,"")<>"",IF(AND($F101=1,$E$80<>""),$E$80,"")<>"",IF(AND($D101=1,$C$80<>""),$C$80,"")<>IF(AND($F101=1,$E$80<>""),$E$80,"")),AND(IF(AND($E101=1,$D$80<>""),$D$80,"")<>"",IF(AND($F101=1,$E$80<>""),$E$80,"")<>"",IF(AND($E101=1,$D$80<>""),$D$80,"")<>IF(AND($F101=1,$E$80<>""),$E$80,""))),1,0) -> 0 | Q101: =IF(OR(AND(IF(AND($D101=1,$C$81<>""),$C$81,"")<>"",IF(AND($E101=1,$D$81<>""),$D$81,"")<>"",IF(AND($D101=1,$C$81<>""),$C$81,"")<>IF(AND($E101=1,$D$81<>""),$D$81,"")),AND(IF(AND($D101=1,$C$81<>""),$C$81,"")<>"",IF(AND($F101=1,$E$81<>""),$E$81,"")<>"",IF(AND($D101=1,$C$81<>""),$C$81,"")<>IF(AND($F101=1,$E$81<>""),$E$81,"")),AND(IF(AND($E101=1,$D$81<>""),$D$81,"")<>"",IF(AND($F101=1,$E$81<>""),$E$81,"")<>"",IF(AND($E101=1,$D$81<>""),$D$81,"")<>IF(AND($F101=1,$E$81<>""),$E$81,""))),1,0) -> 0 | R101: =IF(OR(AND(IF(AND($D101=1,$C$82<>""),$C$82,"")<>"",IF(AND($E101=1,$D$82<>""),$D$82,"")<>"",IF(AND($D101=1,$C$82<>""),$C$82,"")<>IF(AND($E101=1,$D$82<>""),$D$82,"")),AND(IF(AND($D101=1,$C$82<>""),$C$82,"")<>"",IF(AND($F101=1,$E$82<>""),$E$82,"")<>"",IF(AND($D101=1,$C$82<>""),$C$82,"")<>IF(AND($F101=1,$E$82<>""),$E$82,"")),AND(IF(AND($E101=1,$D$82<>""),$D$82,"")<>"",IF(AND($F101=1,$E$82<>""),$E$82,"")<>"",IF(AND($E101=1,$D$82<>""),$D$82,"")<>IF(AND($F101=1,$E$82<>""),$E$82,""))),1,0) -> 0 | S101: =IF(OR(AND(IF(AND($D101=1,$C$83<>""),$C$83,"")<>"",IF(AND($E101=1,$D$83<>""),$D$83,"")<>"",IF(AND($D101=1,$C$83<>""),$C$83,"")<>IF(AND($E101=1,$D$83<>""),$D$83,"")),AND(IF(AND($D101=1,$C$83<>""),$C$83,"")<>"",IF(AND($F101=1,$E$83<>""),$E$83,"")<>"",IF(AND($D101=1,$C$83<>""),$C$83,"")<>IF(AND($F101=1,$E$83<>""),$E$83,"")),AND(IF(AND($E101=1,$D$83<>""),$D$83,"")<>"",IF(AND($F101=1,$E$83<>""),$E$83,"")<>"",IF(AND($E101=1,$D$83<>""),$D$83,"")<>IF(AND($F101=1,$E$83<>""),$E$83,""))),1,0) -> 0 | T101: =IF(OR(AND(IF(AND($D101=1,$C$84<>""),$C$84,"")<>"",IF(AND($E101=1,$D$84<>""),$D$84,"")<>"",IF(AND($D101=1,$C$84<>""),$C$84,"")<>IF(AND($E101=1,$D$84<>""),$D$84,"")),AND(IF(AND($D101=1,$C$84<>""),$C$84,"")<>"",IF(AND($F101=1,$E$84<>""),$E$84,"")<>"",IF(AND($D101=1,$C$84<>""),$C$84,"")<>IF(AND($F101=1,$E$84<>""),$E$84,"")),AND(IF(AND($E101=1,$D$84<>""),$D$84,"")<>"",IF(AND($F101=1,$E$84<>""),$E$84,"")<>"",IF(AND($E101=1,$D$84<>""),$D$84,"")<>IF(AND($F101=1,$E$84<>""),$E$84,""))),1,0) -> 0
A104: Order 2: capital, risk, performance, transformation
A105: Step | B105: Layer attached | C105: Transformation | D105: Capital | E105: Performance | F105: Risk | G105: Unresolved references | H105: C1 | I105: C2 | J105: C3 | K105: Claims on treasury cash | L105: C4 | M105: C5: the digital build's domain | O105: C2 helper: liquidity | P105: C2 helper: net leverage | Q105: C2 helper: workforce capability | R105: C2 helper: technology platform | S105: C2 helper: operational efficiency | T105: C2 helper: strategic risk
A106: 1 | B106: capital | C106: =IF(COUNTIF($B$106:B106,"transformation")>0,1,0) -> 0 | D106: =IF(COUNTIF($B$106:B106,"capital")>0,1,0) -> 1 | E106: =IF(COUNTIF($B$106:B106,"performance")>0,1,0) -> 0 | F106: =IF(COUNTIF($B$106:B106,"risk")>0,1,0) -> 0 | G106: =C106*$H$43+D106*$H$44+E106*$H$45+F106*$H$46 -> 0 | H106: =IF(G106=0,"pass","FAIL") -> pass | I106: =IF(SUM(O106:T106)=0,"pass","FAIL") -> pass | J106: =IF(F106=0,"pass",IF(AND(D106=1,$C$88),"pass","FAIL")) -> pass | K106: =C106*$C$92+IF(AND(F106=1,D106=1,$C$88),$C$93,0) -> 0 | L106: =IF(K106<=$C$94,"pass","FAIL") -> pass | M106: =IF(C106=0,"no operator yet",IF(AND(L106="pass",Cap_today>=Cap_floor),"nonempty","empty")) -> no operator yet | O106: =IF(OR(AND(IF(AND($D106=1,$C$79<>""),$C$79,"")<>"",IF(AND($E106=1,$D$79<>""),$D$79,"")<>"",IF(AND($D106=1,$C$79<>""),$C$79,"")<>IF(AND($E106=1,$D$79<>""),$D$79,"")),AND(IF(AND($D106=1,$C$79<>""),$C$79,"")<>"",IF(AND($F106=1,$E$79<>""),$E$79,"")<>"",IF(AND($D106=1,$C$79<>""),$C$79,"")<>IF(AND($F106=1,$E$79<>""),$E$79,"")),AND(IF(AND($E106=1,$D$79<>""),$D$79,"")<>"",IF(AND($F106=1,$E$79<>""),$E$79,"")<>"",IF(AND($E106=1,$D$79<>""),$D$79,"")<>IF(AND($F106=1,$E$79<>""),$E$79,""))),1,0) -> 0 | P106: =IF(OR(AND(IF(AND($D106=1,$C$80<>""),$C$80,"")<>"",IF(AND($E106=1,$D$80<>""),$D$80,"")<>"",IF(AND($D106=1,$C$80<>""),$C$80,"")<>IF(AND($E106=1,$D$80<>""),$D$80,"")),AND(IF(AND($D106=1,$C$80<>""),$C$80,"")<>"",IF(AND($F106=1,$E$80<>""),$E$80,"")<>"",IF(AND($D106=1,$C$80<>""),$C$80,"")<>IF(AND($F106=1,$E$80<>""),$E$80,"")),AND(IF(AND($E106=1,$D$80<>""),$D$80,"")<>"",IF(AND($F106=1,$E$80<>""),$E$80,"")<>"",IF(AND($E106=1,$D$80<>""),$D$80,"")<>IF(AND($F106=1,$E$80<>""),$E$80,""))),1,0) -> 0 | Q106: =IF(OR(AND(IF(AND($D106=1,$C$81<>""),$C$81,"")<>"",IF(AND($E106=1,$D$81<>""),$D$81,"")<>"",IF(AND($D106=1,$C$81<>""),$C$81,"")<>IF(AND($E106=1,$D$81<>""),$D$81,"")),AND(IF(AND($D106=1,$C$81<>""),$C$81,"")<>"",IF(AND($F106=1,$E$81<>""),$E$81,"")<>"",IF(AND($D106=1,$C$81<>""),$C$81,"")<>IF(AND($F106=1,$E$81<>""),$E$81,"")),AND(IF(AND($E106=1,$D$81<>""),$D$81,"")<>"",IF(AND($F106=1,$E$81<>""),$E$81,"")<>"",IF(AND($E106=1,$D$81<>""),$D$81,"")<>IF(AND($F106=1,$E$81<>""),$E$81,""))),1,0) -> 0 | R106: =IF(OR(AND(IF(AND($D106=1,$C$82<>""),$C$82,"")<>"",IF(AND($E106=1,$D$82<>""),$D$82,"")<>"",IF(AND($D106=1,$C$82<>""),$C$82,"")<>IF(AND($E106=1,$D$82<>""),$D$82,"")),AND(IF(AND($D106=1,$C$82<>""),$C$82,"")<>"",IF(AND($F106=1,$E$82<>""),$E$82,"")<>"",IF(AND($D106=1,$C$82<>""),$C$82,"")<>IF(AND($F106=1,$E$82<>""),$E$82,"")),AND(IF(AND($E106=1,$D$82<>""),$D$82,"")<>"",IF(AND($F106=1,$E$82<>""),$E$82,"")<>"",IF(AND($E106=1,$D$82<>""),$D$82,"")<>IF(AND($F106=1,$E$82<>""),$E$82,""))),1,0) -> 0 | S106: =IF(OR(AND(IF(AND($D106=1,$C$83<>""),$C$83,"")<>"",IF(AND($E106=1,$D$83<>""),$D$83,"")<>"",IF(AND($D106=1,$C$83<>""),$C$83,"")<>IF(AND($E106=1,$D$83<>""),$D$83,"")),AND(IF(AND($D106=1,$C$83<>""),$C$83,"")<>"",IF(AND($F106=1,$E$83<>""),$E$83,"")<>"",IF(AND($D106=1,$C$83<>""),$C$83,"")<>IF(AND($F106=1,$E$83<>""),$E$83,"")),AND(IF(AND($E106=1,$D$83<>""),$D$83,"")<>"",IF(AND($F106=1,$E$83<>""),$E$83,"")<>"",IF(AND($E106=1,$D$83<>""),$D$83,"")<>IF(AND($F106=1,$E$83<>""),$E$83,""))),1,0) -> 0 | T106: =IF(OR(AND(IF(AND($D106=1,$C$84<>""),$C$84,"")<>"",IF(AND($E106=1,$D$84<>""),$D$84,"")<>"",IF(AND($D106=1,$C$84<>""),$C$84,"")<>IF(AND($E106=1,$D$84<>""),$D$84,"")),AND(IF(AND($D106=1,$C$84<>""),$C$84,"")<>"",IF(AND($F106=1,$E$84<>""),$E$84,"")<>"",IF(AND($D106=1,$C$84<>""),$C$84,"")<>IF(AND($F106=1,$E$84<>""),$E$84,"")),AND(IF(AND($E106=1,$D$84<>""),$D$84,"")<>"",IF(AND($F106=1,$E$84<>""),$E$84,"")<>"",IF(AND($E106=1,$D$84<>""),$D$84,"")<>IF(AND($F106=1,$E$84<>""),$E$84,""))),1,0) -> 0
A107: 2 | B107: risk | C107: =IF(COUNTIF($B$106:B107,"transformation")>0,1,0) -> 0 | D107: =IF(COUNTIF($B$106:B107,"capital")>0,1,0) -> 1 | E107: =IF(COUNTIF($B$106:B107,"performance")>0,1,0) -> 0 | F107: =IF(COUNTIF($B$106:B107,"risk")>0,1,0) -> 1 | G107: =C107*$H$43+D107*$H$44+E107*$H$45+F107*$H$46 -> 0 | H107: =IF(G107=0,"pass","FAIL") -> pass | I107: =IF(SUM(O107:T107)=0,"pass","FAIL") -> pass | J107: =IF(F107=0,"pass",IF(AND(D107=1,$C$88),"pass","FAIL")) -> pass | K107: =C107*$C$92+IF(AND(F107=1,D107=1,$C$88),$C$93,0) -> 186.86698 | L107: =IF(K107<=$C$94,"pass","FAIL") -> pass | M107: =IF(C107=0,"no operator yet",IF(AND(L107="pass",Cap_today>=Cap_floor),"nonempty","empty")) -> no operator yet | O107: =IF(OR(AND(IF(AND($D107=1,$C$79<>""),$C$79,"")<>"",IF(AND($E107=1,$D$79<>""),$D$79,"")<>"",IF(AND($D107=1,$C$79<>""),$C$79,"")<>IF(AND($E107=1,$D$79<>""),$D$79,"")),AND(IF(AND($D107=1,$C$79<>""),$C$79,"")<>"",IF(AND($F107=1,$E$79<>""),$E$79,"")<>"",IF(AND($D107=1,$C$79<>""),$C$79,"")<>IF(AND($F107=1,$E$79<>""),$E$79,"")),AND(IF(AND($E107=1,$D$79<>""),$D$79,"")<>"",IF(AND($F107=1,$E$79<>""),$E$79,"")<>"",IF(AND($E107=1,$D$79<>""),$D$79,"")<>IF(AND($F107=1,$E$79<>""),$E$79,""))),1,0) -> 0 | P107: =IF(OR(AND(IF(AND($D107=1,$C$80<>""),$C$80,"")<>"",IF(AND($E107=1,$D$80<>""),$D$80,"")<>"",IF(AND($D107=1,$C$80<>""),$C$80,"")<>IF(AND($E107=1,$D$80<>""),$D$80,"")),AND(IF(AND($D107=1,$C$80<>""),$C$80,"")<>"",IF(AND($F107=1,$E$80<>""),$E$80,"")<>"",IF(AND($D107=1,$C$80<>""),$C$80,"")<>IF(AND($F107=1,$E$80<>""),$E$80,"")),AND(IF(AND($E107=1,$D$80<>""),$D$80,"")<>"",IF(AND($F107=1,$E$80<>""),$E$80,"")<>"",IF(AND($E107=1,$D$80<>""),$D$80,"")<>IF(AND($F107=1,$E$80<>""),$E$80,""))),1,0) -> 0 | Q107: =IF(OR(AND(IF(AND($D107=1,$C$81<>""),$C$81,"")<>"",IF(AND($E107=1,$D$81<>""),$D$81,"")<>"",IF(AND($D107=1,$C$81<>""),$C$81,"")<>IF(AND($E107=1,$D$81<>""),$D$81,"")),AND(IF(AND($D107=1,$C$81<>""),$C$81,"")<>"",IF(AND($F107=1,$E$81<>""),$E$81,"")<>"",IF(AND($D107=1,$C$81<>""),$C$81,"")<>IF(AND($F107=1,$E$81<>""),$E$81,"")),AND(IF(AND($E107=1,$D$81<>""),$D$81,"")<>"",IF(AND($F107=1,$E$81<>""),$E$81,"")<>"",IF(AND($E107=1,$D$81<>""),$D$81,"")<>IF(AND($F107=1,$E$81<>""),$E$81,""))),1,0) -> 0 | R107: =IF(OR(AND(IF(AND($D107=1,$C$82<>""),$C$82,"")<>"",IF(AND($E107=1,$D$82<>""),$D$82,"")<>"",IF(AND($D107=1,$C$82<>""),$C$82,"")<>IF(AND($E107=1,$D$82<>""),$D$82,"")),AND(IF(AND($D107=1,$C$82<>""),$C$82,"")<>"",IF(AND($F107=1,$E$82<>""),$E$82,"")<>"",IF(AND($D107=1,$C$82<>""),$C$82,"")<>IF(AND($F107=1,$E$82<>""),$E$82,"")),AND(IF(AND($E107=1,$D$82<>""),$D$82,"")<>"",IF(AND($F107=1,$E$82<>""),$E$82,"")<>"",IF(AND($E107=1,$D$82<>""),$D$82,"")<>IF(AND($F107=1,$E$82<>""),$E$82,""))),1,0) -> 0 | S107: =IF(OR(AND(IF(AND($D107=1,$C$83<>""),$C$83,"")<>"",IF(AND($E107=1,$D$83<>""),$D$83,"")<>"",IF(AND($D107=1,$C$83<>""),$C$83,"")<>IF(AND($E107=1,$D$83<>""),$D$83,"")),AND(IF(AND($D107=1,$C$83<>""),$C$83,"")<>"",IF(AND($F107=1,$E$83<>""),$E$83,"")<>"",IF(AND($D107=1,$C$83<>""),$C$83,"")<>IF(AND($F107=1,$E$83<>""),$E$83,"")),AND(IF(AND($E107=1,$D$83<>""),$D$83,"")<>"",IF(AND($F107=1,$E$83<>""),$E$83,"")<>"",IF(AND($E107=1,$D$83<>""),$D$83,"")<>IF(AND($F107=1,$E$83<>""),$E$83,""))),1,0) -> 0 | T107: =IF(OR(AND(IF(AND($D107=1,$C$84<>""),$C$84,"")<>"",IF(AND($E107=1,$D$84<>""),$D$84,"")<>"",IF(AND($D107=1,$C$84<>""),$C$84,"")<>IF(AND($E107=1,$D$84<>""),$D$84,"")),AND(IF(AND($D107=1,$C$84<>""),$C$84,"")<>"",IF(AND($F107=1,$E$84<>""),$E$84,"")<>"",IF(AND($D107=1,$C$84<>""),$C$84,"")<>IF(AND($F107=1,$E$84<>""),$E$84,"")),AND(IF(AND($E107=1,$D$84<>""),$D$84,"")<>"",IF(AND($F107=1,$E$84<>""),$E$84,"")<>"",IF(AND($E107=1,$D$84<>""),$D$84,"")<>IF(AND($F107=1,$E$84<>""),$E$84,""))),1,0) -> 0
A108: 3 | B108: performance | C108: =IF(COUNTIF($B$106:B108,"transformation")>0,1,0) -> 0 | D108: =IF(COUNTIF($B$106:B108,"capital")>0,1,0) -> 1 | E108: =IF(COUNTIF($B$106:B108,"performance")>0,1,0) -> 1 | F108: =IF(COUNTIF($B$106:B108,"risk")>0,1,0) -> 1 | G108: =C108*$H$43+D108*$H$44+E108*$H$45+F108*$H$46 -> 0 | H108: =IF(G108=0,"pass","FAIL") -> pass | I108: =IF(SUM(O108:T108)=0,"pass","FAIL") -> pass | J108: =IF(F108=0,"pass",IF(AND(D108=1,$C$88),"pass","FAIL")) -> pass | K108: =C108*$C$92+IF(AND(F108=1,D108=1,$C$88),$C$93,0) -> 186.86698 | L108: =IF(K108<=$C$94,"pass","FAIL") -> pass | M108: =IF(C108=0,"no operator yet",IF(AND(L108="pass",Cap_today>=Cap_floor),"nonempty","empty")) -> no operator yet | O108: =IF(OR(AND(IF(AND($D108=1,$C$79<>""),$C$79,"")<>"",IF(AND($E108=1,$D$79<>""),$D$79,"")<>"",IF(AND($D108=1,$C$79<>""),$C$79,"")<>IF(AND($E108=1,$D$79<>""),$D$79,"")),AND(IF(AND($D108=1,$C$79<>""),$C$79,"")<>"",IF(AND($F108=1,$E$79<>""),$E$79,"")<>"",IF(AND($D108=1,$C$79<>""),$C$79,"")<>IF(AND($F108=1,$E$79<>""),$E$79,"")),AND(IF(AND($E108=1,$D$79<>""),$D$79,"")<>"",IF(AND($F108=1,$E$79<>""),$E$79,"")<>"",IF(AND($E108=1,$D$79<>""),$D$79,"")<>IF(AND($F108=1,$E$79<>""),$E$79,""))),1,0) -> 0 | P108: =IF(OR(AND(IF(AND($D108=1,$C$80<>""),$C$80,"")<>"",IF(AND($E108=1,$D$80<>""),$D$80,"")<>"",IF(AND($D108=1,$C$80<>""),$C$80,"")<>IF(AND($E108=1,$D$80<>""),$D$80,"")),AND(IF(AND($D108=1,$C$80<>""),$C$80,"")<>"",IF(AND($F108=1,$E$80<>""),$E$80,"")<>"",IF(AND($D108=1,$C$80<>""),$C$80,"")<>IF(AND($F108=1,$E$80<>""),$E$80,"")),AND(IF(AND($E108=1,$D$80<>""),$D$80,"")<>"",IF(AND($F108=1,$E$80<>""),$E$80,"")<>"",IF(AND($E108=1,$D$80<>""),$D$80,"")<>IF(AND($F108=1,$E$80<>""),$E$80,""))),1,0) -> 0 | Q108: =IF(OR(AND(IF(AND($D108=1,$C$81<>""),$C$81,"")<>"",IF(AND($E108=1,$D$81<>""),$D$81,"")<>"",IF(AND($D108=1,$C$81<>""),$C$81,"")<>IF(AND($E108=1,$D$81<>""),$D$81,"")),AND(IF(AND($D108=1,$C$81<>""),$C$81,"")<>"",IF(AND($F108=1,$E$81<>""),$E$81,"")<>"",IF(AND($D108=1,$C$81<>""),$C$81,"")<>IF(AND($F108=1,$E$81<>""),$E$81,"")),AND(IF(AND($E108=1,$D$81<>""),$D$81,"")<>"",IF(AND($F108=1,$E$81<>""),$E$81,"")<>"",IF(AND($E108=1,$D$81<>""),$D$81,"")<>IF(AND($F108=1,$E$81<>""),$E$81,""))),1,0) -> 0 | R108: =IF(OR(AND(IF(AND($D108=1,$C$82<>""),$C$82,"")<>"",IF(AND($E108=1,$D$82<>""),$D$82,"")<>"",IF(AND($D108=1,$C$82<>""),$C$82,"")<>IF(AND($E108=1,$D$82<>""),$D$82,"")),AND(IF(AND($D108=1,$C$82<>""),$C$82,"")<>"",IF(AND($F108=1,$E$82<>""),$E$82,"")<>"",IF(AND($D108=1,$C$82<>""),$C$82,"")<>IF(AND($F108=1,$E$82<>""),$E$82,"")),AND(IF(AND($E108=1,$D$82<>""),$D$82,"")<>"",IF(AND($F108=1,$E$82<>""),$E$82,"")<>"",IF(AND($E108=1,$D$82<>""),$D$82,"")<>IF(AND($F108=1,$E$82<>""),$E$82,""))),1,0) -> 0 | S108: =IF(OR(AND(IF(AND($D108=1,$C$83<>""),$C$83,"")<>"",IF(AND($E108=1,$D$83<>""),$D$83,"")<>"",IF(AND($D108=1,$C$83<>""),$C$83,"")<>IF(AND($E108=1,$D$83<>""),$D$83,"")),AND(IF(AND($D108=1,$C$83<>""),$C$83,"")<>"",IF(AND($F108=1,$E$83<>""),$E$83,"")<>"",IF(AND($D108=1,$C$83<>""),$C$83,"")<>IF(AND($F108=1,$E$83<>""),$E$83,"")),AND(IF(AND($E108=1,$D$83<>""),$D$83,"")<>"",IF(AND($F108=1,$E$83<>""),$E$83,"")<>"",IF(AND($E108=1,$D$83<>""),$D$83,"")<>IF(AND($F108=1,$E$83<>""),$E$83,""))),1,0) -> 0 | T108: =IF(OR(AND(IF(AND($D108=1,$C$84<>""),$C$84,"")<>"",IF(AND($E108=1,$D$84<>""),$D$84,"")<>"",IF(AND($D108=1,$C$84<>""),$C$84,"")<>IF(AND($E108=1,$D$84<>""),$D$84,"")),AND(IF(AND($D108=1,$C$84<>""),$C$84,"")<>"",IF(AND($F108=1,$E$84<>""),$E$84,"")<>"",IF(AND($D108=1,$C$84<>""),$C$84,"")<>IF(AND($F108=1,$E$84<>""),$E$84,"")),AND(IF(AND($E108=1,$D$84<>""),$D$84,"")<>"",IF(AND($F108=1,$E$84<>""),$E$84,"")<>"",IF(AND($E108=1,$D$84<>""),$D$84,"")<>IF(AND($F108=1,$E$84<>""),$E$84,""))),1,0) -> 0
A109: 4 | B109: transformation | C109: =IF(COUNTIF($B$106:B109,"transformation")>0,1,0) -> 1 | D109: =IF(COUNTIF($B$106:B109,"capital")>0,1,0) -> 1 | E109: =IF(COUNTIF($B$106:B109,"performance")>0,1,0) -> 1 | F109: =IF(COUNTIF($B$106:B109,"risk")>0,1,0) -> 1 | G109: =C109*$H$43+D109*$H$44+E109*$H$45+F109*$H$46 -> 0 | H109: =IF(G109=0,"pass","FAIL") -> pass | I109: =IF(SUM(O109:T109)=0,"pass","FAIL") -> pass | J109: =IF(F109=0,"pass",IF(AND(D109=1,$C$88),"pass","FAIL")) -> pass | K109: =C109*$C$92+IF(AND(F109=1,D109=1,$C$88),$C$93,0) -> 324.91659 | L109: =IF(K109<=$C$94,"pass","FAIL") -> FAIL | M109: =IF(C109=0,"no operator yet",IF(AND(L109="pass",Cap_today>=Cap_floor),"nonempty","empty")) -> empty | O109: =IF(OR(AND(IF(AND($D109=1,$C$79<>""),$C$79,"")<>"",IF(AND($E109=1,$D$79<>""),$D$79,"")<>"",IF(AND($D109=1,$C$79<>""),$C$79,"")<>IF(AND($E109=1,$D$79<>""),$D$79,"")),AND(IF(AND($D109=1,$C$79<>""),$C$79,"")<>"",IF(AND($F109=1,$E$79<>""),$E$79,"")<>"",IF(AND($D109=1,$C$79<>""),$C$79,"")<>IF(AND($F109=1,$E$79<>""),$E$79,"")),AND(IF(AND($E109=1,$D$79<>""),$D$79,"")<>"",IF(AND($F109=1,$E$79<>""),$E$79,"")<>"",IF(AND($E109=1,$D$79<>""),$D$79,"")<>IF(AND($F109=1,$E$79<>""),$E$79,""))),1,0) -> 0 | P109: =IF(OR(AND(IF(AND($D109=1,$C$80<>""),$C$80,"")<>"",IF(AND($E109=1,$D$80<>""),$D$80,"")<>"",IF(AND($D109=1,$C$80<>""),$C$80,"")<>IF(AND($E109=1,$D$80<>""),$D$80,"")),AND(IF(AND($D109=1,$C$80<>""),$C$80,"")<>"",IF(AND($F109=1,$E$80<>""),$E$80,"")<>"",IF(AND($D109=1,$C$80<>""),$C$80,"")<>IF(AND($F109=1,$E$80<>""),$E$80,"")),AND(IF(AND($E109=1,$D$80<>""),$D$80,"")<>"",IF(AND($F109=1,$E$80<>""),$E$80,"")<>"",IF(AND($E109=1,$D$80<>""),$D$80,"")<>IF(AND($F109=1,$E$80<>""),$E$80,""))),1,0) -> 0 | Q109: =IF(OR(AND(IF(AND($D109=1,$C$81<>""),$C$81,"")<>"",IF(AND($E109=1,$D$81<>""),$D$81,"")<>"",IF(AND($D109=1,$C$81<>""),$C$81,"")<>IF(AND($E109=1,$D$81<>""),$D$81,"")),AND(IF(AND($D109=1,$C$81<>""),$C$81,"")<>"",IF(AND($F109=1,$E$81<>""),$E$81,"")<>"",IF(AND($D109=1,$C$81<>""),$C$81,"")<>IF(AND($F109=1,$E$81<>""),$E$81,"")),AND(IF(AND($E109=1,$D$81<>""),$D$81,"")<>"",IF(AND($F109=1,$E$81<>""),$E$81,"")<>"",IF(AND($E109=1,$D$81<>""),$D$81,"")<>IF(AND($F109=1,$E$81<>""),$E$81,""))),1,0) -> 0 | R109: =IF(OR(AND(IF(AND($D109=1,$C$82<>""),$C$82,"")<>"",IF(AND($E109=1,$D$82<>""),$D$82,"")<>"",IF(AND($D109=1,$C$82<>""),$C$82,"")<>IF(AND($E109=1,$D$82<>""),$D$82,"")),AND(IF(AND($D109=1,$C$82<>""),$C$82,"")<>"",IF(AND($F109=1,$E$82<>""),$E$82,"")<>"",IF(AND($D109=1,$C$82<>""),$C$82,"")<>IF(AND($F109=1,$E$82<>""),$E$82,"")),AND(IF(AND($E109=1,$D$82<>""),$D$82,"")<>"",IF(AND($F109=1,$E$82<>""),$E$82,"")<>"",IF(AND($E109=1,$D$82<>""),$D$82,"")<>IF(AND($F109=1,$E$82<>""),$E$82,""))),1,0) -> 0 | S109: =IF(OR(AND(IF(AND($D109=1,$C$83<>""),$C$83,"")<>"",IF(AND($E109=1,$D$83<>""),$D$83,"")<>"",IF(AND($D109=1,$C$83<>""),$C$83,"")<>IF(AND($E109=1,$D$83<>""),$D$83,"")),AND(IF(AND($D109=1,$C$83<>""),$C$83,"")<>"",IF(AND($F109=1,$E$83<>""),$E$83,"")<>"",IF(AND($D109=1,$C$83<>""),$C$83,"")<>IF(AND($F109=1,$E$83<>""),$E$83,"")),AND(IF(AND($E109=1,$D$83<>""),$D$83,"")<>"",IF(AND($F109=1,$E$83<>""),$E$83,"")<>"",IF(AND($E109=1,$D$83<>""),$D$83,"")<>IF(AND($F109=1,$E$83<>""),$E$83,""))),1,0) -> 0 | T109: =IF(OR(AND(IF(AND($D109=1,$C$84<>""),$C$84,"")<>"",IF(AND($E109=1,$D$84<>""),$D$84,"")<>"",IF(AND($D109=1,$C$84<>""),$C$84,"")<>IF(AND($E109=1,$D$84<>""),$D$84,"")),AND(IF(AND($D109=1,$C$84<>""),$C$84,"")<>"",IF(AND($F109=1,$E$84<>""),$E$84,"")<>"",IF(AND($D109=1,$C$84<>""),$C$84,"")<>IF(AND($F109=1,$E$84<>""),$E$84,"")),AND(IF(AND($E109=1,$D$84<>""),$D$84,"")<>"",IF(AND($F109=1,$E$84<>""),$E$84,"")<>"",IF(AND($E109=1,$D$84<>""),$D$84,"")<>IF(AND($F109=1,$E$84<>""),$E$84,""))),1,0) -> 0
A113: After the last attachment | B113: Value | C113: Reading
A114: Claims on treasury cash, order 1 | B114: =K101 -> 324.91659 | C114: $325 million (Worked Example 13.1)
A115: Claims on treasury cash, order 2 | B115: =K109 -> 324.91659
A116: The same checks in both orders | B116: =AND(H101=H109,I101=I109,J101=J109,K101=K109,L101=L109,M101=M109) -> TRUE | C116: Theorem 13.2(i): order does not matter
A117: Joint check: cash less the claims | B117: =$C$94-K101 -> -54.916594 | C117: infeasible by $55 million
A118: Unresolved references, all layers | B118: =SUM(H43:H46) -> 0 | C118: (C1) holds

Sheet Couplings
A1: Wire the couplings: every layer passes, the whole fails (Theorem 13.3(ii); Figure 13.2; Online Appendix 13.B.1; AXIOM Lab 1.13, step 2)
A2: Losses propagate as l(k+1) = M l(k), rows receiving. The total impact of a unit loss is finite exactly when rho(M) < 1.
A4: Figure 13.2's cycle: M (rows receive) | B4: from capital | C4: from performance | D4: from risk | H4: Cross-layer share c | I4: rho(M) = a + c | J4: Total impact | K4: Each layer alone
A5: to capital | B5: =A_keep -> 0.5 | C5: 0 | D5: =C_pass -> 0.25 | H5: 0 | I5: =A_keep+H5 -> 0.5 | J5: =IF(I5<1,1/(1-I5),"no finite bill") -> 2 | K5: =1/(1-A_keep) -> 2
A6: to performance | B6: =C_pass -> 0.25 | C6: =A_keep -> 0.5 | D6: 0 | H6: 0.1 | I6: =A_keep+H6 -> 0.6 | J6: =IF(I6<1,1/(1-I6),"no finite bill") -> 2.5 | K6: =1/(1-A_keep) -> 2
A7: to risk | B7: 0 | C7: =C_pass -> 0.25 | D7: =A_keep -> 0.5 | H7: 0.2 | I7: =A_keep+H7 -> 0.7 | J7: =IF(I7<1,1/(1-I7),"no finite bill") -> 3.3333333 | K7: =1/(1-A_keep) -> 2
A8: Column sums | B8: =SUM(B5:B7) -> 0.75 | C8: =SUM(C5:C7) -> 0.75 | D8: =SUM(D5:D7) -> 0.75 | H8: 0.25 | I8: =A_keep+H8 -> 0.75 | J8: =IF(I8<1,1/(1-I8),"no finite bill") -> 4 | K8: =1/(1-A_keep) -> 2
H9: 0.3 | I9: =A_keep+H9 -> 0.8 | J9: =IF(I9<1,1/(1-I9),"no finite bill") -> 5 | K9: =1/(1-A_keep) -> 2
A10: Each layer's own radius, a | B10: =A_keep -> 0.5 | C10: every layer passes its own test | H10: 0.4 | I10: =A_keep+H10 -> 0.9 | J10: =IF(I10<1,1/(1-I10),"no finite bill") -> 10 | K10: =1/(1-A_keep) -> 2
A11: Each layer alone: total impact of a unit shock, 1/(1 - a) | B11: =1/(1-A_keep) -> 2 | C11: Figure 13.2: 2 | H11: 0.45 | I11: =A_keep+H11 -> 0.95 | J11: =IF(I11<1,1/(1-I11),"no finite bill") -> 20 | K11: =1/(1-A_keep) -> 2
A12: rho(M): every column sums to a + c | B12: =IF(MAX(B8:D8)-MIN(B8:D8)<0.000000000001,B8,-1) -> 0.75 | C12: Online Appendix 13.B.1 | H12: 0.5 | I12: =A_keep+H12 -> 1 | J12: =IF(I12<1,1/(1-I12),"no finite bill") -> no finite bill | K12: =1/(1-A_keep) -> 2
A13: The whole: total impact, 1/(1 - a - c) | B13: =IF(B12<1,1/(1-B12),"no finite bill") -> 4 | C13: Figure 13.2: 4 at c = 0.25 | H13: 0.6 | I13: =A_keep+H13 -> 1.1 | J13: =IF(I13<1,1/(1-I13),"no finite bill") -> no finite bill | K13: =1/(1-A_keep) -> 2
A14: Diagonal blocks' part of rho(M) | B14: =(B5+C6+D7)/3 -> 0.5 | C14: uniform Perron vectors: exactly a | P14: The editor's spectral report | Q14: Value
A15: Cross-layer blocks' part of rho(M) | B15: =(SUM(B5:D7)-(B5+C6+D7))/3 -> 0.25 | C15: exactly c: the whole difference | P15: rho(M), by power iteration | Q15: =L103 -> 0.75
A16: Cumulative bill after 200 quarters (table below) | B16: =F220 -> 4 | C16: the series sums to 1/(1 - a - c) | P16: Layer radii: capital, performance, risk | Q16: =TEXT($I$18,"0.00")&", "&TEXT($J$19,"0.00")&", "&TEXT($K$20,"0.00") -> 0.50, 0.50, 0.50
H17: Interaction-matrix editor: enter any gains | I17: from capital | J17: from performance | K17: from risk | P17: Largest layer radius | Q17: =MAX($I$18,$J$19,$K$20) -> 0.5
H18: to capital | I18: 0.5 | J18: 0 | K18: 0.25 | P18: Diagonal blocks' part of rho(M) | Q18: =(M103*$I$18*I103+N103*$J$19*J103+O103*$K$20*K103)/(M103*I103+N103*J103+O103*K103) -> 0.5
A19: Quarter | B19: Loss at capital | C19: at performance | D19: at risk | E19: This quarter | F19: Cumulative bill | H19: to performance | I19: 0.25 | J19: 0.5 | K19: 0 | P19: Cross-layer blocks' part of rho(M) | Q19: =Q15-Q18 -> 0.25
A20: 0 | B20: 1 | C20: 0 | D20: 0 | E20: =SUM(B20:D20) -> 1 | F20: =E20 -> 1 | H20: to risk | I20: 0 | J20: 0.25 | K20: 0.5 | P20: Verdict | Q20: =IF(AND(Q17<1,Q15<1),"every layer stable, the whole stable",IF(Q17<1,"every layer stable, the whole NOT","a layer fails its own test")) -> every layer stable, the whole stable
A21: 1 | B21: =A_keep*B20+C_pass*D20 -> 0.5 | C21: =C_pass*B20+A_keep*C20 -> 0.25 | D21: =C_pass*C20+A_keep*D20 -> 0 | E21: =SUM(B21:D21) -> 0.75 | F21: =F20+E21 -> 1.75 | P21: Total impact of a unit loss at capital | Q21: =IF(Q15<1,(Q25+Q26+Q27)/Q24,"no finite bill") -> 4
A22: 2 | B22: =A_keep*B21+C_pass*D21 -> 0.25 | C22: =C_pass*B21+A_keep*C21 -> 0.25 | D22: =C_pass*C21+A_keep*D21 -> 0.0625 | E22: =SUM(B22:D22) -> 0.5625 | F22: =F21+E22 -> 2.3125 | H22: Iteration | I22: v capital | J22: v performance | K22: v risk | L22: rho estimate | M22: u capital | N22: u performance | O22: u risk
A23: 3 | B23: =A_keep*B22+C_pass*D22 -> 0.140625 | C23: =C_pass*B22+A_keep*C22 -> 0.1875 | D23: =C_pass*C22+A_keep*D22 -> 0.09375 | E23: =SUM(B23:D23) -> 0.421875 | F23: =F22+E23 -> 2.734375 | H23: 0 | I23: 0.33333333 | J23: 0.33333333 | K23: 0.33333333 | L23: =($I$18+$I$19+$I$20)*I23+($J$18+$J$19+$J$20)*J23+($K$18+$K$19+$K$20)*K23 -> 0.75 | M23: 0.33333333 | N23: 0.33333333 | O23: 0.33333333 | P23: The total impact: column 1 of (I - M)^-1 by cofactors
A24: 4 | B24: =A_keep*B23+C_pass*D23 -> 0.09375 | C24: =C_pass*B23+A_keep*C23 -> 0.12890625 | D24: =C_pass*C23+A_keep*D23 -> 0.09375 | E24: =SUM(B24:D24) -> 0.31640625 | F24: =F23+E24 -> 3.0507812 | H24: 1 | I24: =($I$18*I23+$J$18*J23+$K$18*K23)/(($I$18+$I$19+$I$20)*I23+($J$18+$J$19+$J$20)*J23+($K$18+$K$19+$K$20)*K23) -> 0.33333333 | J24: =($I$19*I23+$J$19*J23+$K$19*K23)/(($I$18+$I$19+$I$20)*I23+($J$18+$J$19+$J$20)*J23+($K$18+$K$19+$K$20)*K23) -> 0.33333333 | K24: =($I$20*I23+$J$20*J23+$K$20*K23)/(($I$18+$I$19+$I$20)*I23+($J$18+$J$19+$J$20)*J23+($K$18+$K$19+$K$20)*K23) -> 0.33333333 | L24: =($I$18+$I$19+$I$20)*I24+($J$18+$J$19+$J$20)*J24+($K$18+$K$19+$K$20)*K24 -> 0.75 | M24: =(M23*$I$18+N23*$I$19+O23*$I$20)/(($I$18+$J$18+$K$18)*M23+($I$19+$J$19+$K$19)*N23+($I$20+$J$20+$K$20)*O23) -> 0.33333333 | N24: =(M23*$J$18+N23*$J$19+O23*$J$20)/(($I$18+$J$18+$K$18)*M23+($I$19+$J$19+$K$19)*N23+($I$20+$J$20+$K$20)*O23) -> 0.33333333 | O24: =(M23*$K$18+N23*$K$19+O23*$K$20)/(($I$18+$J$18+$K$18)*M23+($I$19+$J$19+$K$19)*N23+($I$20+$J$20+$K$20)*O23) -> 0.33333333 | P24: det(I - M) | Q24: =(1-$I$18)*((1-$J$19)*(1-$K$20)-(0-$K$19)*(0-$J$20))-(0-$J$18)*((0-$I$19)*(1-$K$20)-(0-$K$19)*(0-$I$20))+(0-$K$18)*((0-$I$19)*(0-$J$20)-(1-$J$19)*(0-$I$20)) -> 0.109375
A25: 5 | B25: =A_keep*B24+C_pass*D24 -> 0.0703125 | C25: =C_pass*B24+A_keep*C24 -> 0.087890625 | D25: =C_pass*C24+A_keep*D24 -> 0.079101562 | E25: =SUM(B25:D25) -> 0.23730469 | F25: =F24+E25 -> 3.2880859 | H25: 2 | I25: =($I$18*I24+$J$18*J24+$K$18*K24)/(($I$18+$I$19+$I$20)*I24+($J$18+$J$19+$J$20)*J24+($K$18+$K$19+$K$20)*K24) -> 0.33333333 | J25: =($I$19*I24+$J$19*J24+$K$19*K24)/(($I$18+$I$19+$I$20)*I24+($J$18+$J$19+$J$20)*J24+($K$18+$K$19+$K$20)*K24) -> 0.33333333 | K25: =($I$20*I24+$J$20*J24+$K$20*K24)/(($I$18+$I$19+$I$20)*I24+($J$18+$J$19+$J$20)*J24+($K$18+$K$19+$K$20)*K24) -> 0.33333333 | L25: =($I$18+$I$19+$I$20)*I25+($J$18+$J$19+$J$20)*J25+($K$18+$K$19+$K$20)*K25 -> 0.75 | M25: =(M24*$I$18+N24*$I$19+O24*$I$20)/(($I$18+$J$18+$K$18)*M24+($I$19+$J$19+$K$19)*N24+($I$20+$J$20+$K$20)*O24) -> 0.33333333 | N25: =(M24*$J$18+N24*$J$19+O24*$J$20)/(($I$18+$J$18+$K$18)*M24+($I$19+$J$19+$K$19)*N24+($I$20+$J$20+$K$20)*O24) -> 0.33333333 | O25: =(M24*$K$18+N24*$K$19+O24*$K$20)/(($I$18+$J$18+$K$18)*M24+($I$19+$J$19+$K$19)*N24+($I$20+$J$20+$K$20)*O24) -> 0.33333333 | P25: Cofactor C11 of I - M | Q25: =(1-$J$19)*(1-$K$20)-(0-$K$19)*(0-$J$20) -> 0.25
A26: 6 | B26: =A_keep*B25+C_pass*D25 -> 0.054931641 | C26: =C_pass*B25+A_keep*C25 -> 0.061523438 | D26: =C_pass*C25+A_keep*D25 -> 0.061523438 | E26: =SUM(B26:D26) -> 0.17797852 | F26: =F25+E26 -> 3.4660645 | H26: 3 | I26: =($I$18*I25+$J$18*J25+$K$18*K25)/(($I$18+$I$19+$I$20)*I25+($J$18+$J$19+$J$20)*J25+($K$18+$K$19+$K$20)*K25) -> 0.33333333 | J26: =($I$19*I25+$J$19*J25+$K$19*K25)/(($I$18+$I$19+$I$20)*I25+($J$18+$J$19+$J$20)*J25+($K$18+$K$19+$K$20)*K25) -> 0.33333333 | K26: =($I$20*I25+$J$20*J25+$K$20*K25)/(($I$18+$I$19+$I$20)*I25+($J$18+$J$19+$J$20)*J25+($K$18+$K$19+$K$20)*K25) -> 0.33333333 | L26: =($I$18+$I$19+$I$20)*I26+($J$18+$J$19+$J$20)*J26+($K$18+$K$19+$K$20)*K26 -> 0.75 | M26: =(M25*$I$18+N25*$I$19+O25*$I$20)/(($I$18+$J$18+$K$18)*M25+($I$19+$J$19+$K$19)*N25+($I$20+$J$20+$K$20)*O25) -> 0.33333333 | N26: =(M25*$J$18+N25*$J$19+O25*$J$20)/(($I$18+$J$18+$K$18)*M25+($I$19+$J$19+$K$19)*N25+($I$20+$J$20+$K$20)*O25) -> 0.33333333 | O26: =(M25*$K$18+N25*$K$19+O25*$K$20)/(($I$18+$J$18+$K$18)*M25+($I$19+$J$19+$K$19)*N25+($I$20+$J$20+$K$20)*O25) -> 0.33333333 | P26: Cofactor C12 of I - M | Q26: =-((0-$I$19)*(1-$K$20)-(0-$K$19)*(0-$I$20)) -> 0.125
A27: 7 | B27: =A_keep*B26+C_pass*D26 -> 0.04284668 | C27: =C_pass*B26+A_keep*C26 -> 0.044494629 | D27: =C_pass*C26+A_keep*D26 -> 0.046142578 | E27: =SUM(B27:D27) -> 0.13348389 | F27: =F26+E27 -> 3.5995483 | H27: 4 | I27: =($I$18*I26+$J$18*J26+$K$18*K26)/(($I$18+$I$19+$I$20)*I26+($J$18+$J$19+$J$20)*J26+($K$18+$K$19+$K$20)*K26) -> 0.33333333 | J27: =($I$19*I26+$J$19*J26+$K$19*K26)/(($I$18+$I$19+$I$20)*I26+($J$18+$J$19+$J$20)*J26+($K$18+$K$19+$K$20)*K26) -> 0.33333333 | K27: =($I$20*I26+$J$20*J26+$K$20*K26)/(($I$18+$I$19+$I$20)*I26+($J$18+$J$19+$J$20)*J26+($K$18+$K$19+$K$20)*K26) -> 0.33333333 | L27: =($I$18+$I$19+$I$20)*I27+($J$18+$J$19+$J$20)*J27+($K$18+$K$19+$K$20)*K27 -> 0.75 | M27: =(M26*$I$18+N26*$I$19+O26*$I$20)/(($I$18+$J$18+$K$18)*M26+($I$19+$J$19+$K$19)*N26+($I$20+$J$20+$K$20)*O26) -> 0.33333333 | N27: =(M26*$J$18+N26*$J$19+O26*$J$20)/(($I$18+$J$18+$K$18)*M26+($I$19+$J$19+$K$19)*N26+($I$20+$J$20+$K$20)*O26) -> 0.33333333 | O27: =(M26*$K$18+N26*$K$19+O26*$K$20)/(($I$18+$J$18+$K$18)*M26+($I$19+$J$19+$K$19)*N26+($I$20+$J$20+$K$20)*O26) -> 0.33333333 | P27: Cofactor C13 of I - M | Q27: =(0-$I$19)*(0-$J$20)-(1-$J$19)*(0-$I$20) -> 0.0625
A28: 8 | B28: =A_keep*B27+C_pass*D27 -> 0.032958984 | C28: =C_pass*B27+A_keep*C27 -> 0.032958984 | D28: =C_pass*C27+A_keep*D27 -> 0.034194946 | E28: =SUM(B28:D28) -> 0.10011292 | F28: =F27+E28 -> 3.6996613 | H28: 5 | I28: =($I$18*I27+$J$18*J27+$K$18*K27)/(($I$18+$I$19+$I$20)*I27+($J$18+$J$19+$J$20)*J27+($K$18+$K$19+$K$20)*K27) -> 0.33333333 | J28: =($I$19*I27+$J$19*J27+$K$19*K27)/(($I$18+$I$19+$I$20)*I27+($J$18+$J$19+$J$20)*J27+($K$18+$K$19+$K$20)*K27) -> 0.33333333 | K28: =($I$20*I27+$J$20*J27+$K$20*K27)/(($I$18+$I$19+$I$20)*I27+($J$18+$J$19+$J$20)*J27+($K$18+$K$19+$K$20)*K27) -> 0.33333333 | L28: =($I$18+$I$19+$I$20)*I28+($J$18+$J$19+$J$20)*J28+($K$18+$K$19+$K$20)*K28 -> 0.75 | M28: =(M27*$I$18+N27*$I$19+O27*$I$20)/(($I$18+$J$18+$K$18)*M27+($I$19+$J$19+$K$19)*N27+($I$20+$J$20+$K$20)*O27) -> 0.33333333 | N28: =(M27*$J$18+N27*$J$19+O27*$J$20)/(($I$18+$J$18+$K$18)*M27+($I$19+$J$19+$K$19)*N27+($I$20+$J$20+$K$20)*O27) -> 0.33333333 | O28: =(M27*$K$18+N27*$K$19+O27*$K$20)/(($I$18+$J$18+$K$18)*M27+($I$19+$J$19+$K$19)*N27+($I$20+$J$20+$K$20)*O27) -> 0.33333333
A29: 9 | B29: =A_keep*B28+C_pass*D28 -> 0.025028229 | C29: =C_pass*B28+A_keep*C28 -> 0.024719238 | D29: =C_pass*C28+A_keep*D28 -> 0.025337219 | E29: =SUM(B29:D29) -> 0.075084686 | F29: =F28+E29 -> 3.7747459 | H29: 6 | I29: =($I$18*I28+$J$18*J28+$K$18*K28)/(($I$18+$I$19+$I$20)*I28+($J$18+$J$19+$J$20)*J28+($K$18+$K$19+$K$20)*K28) -> 0.33333333 | J29: =($I$19*I28+$J$19*J28+$K$19*K28)/(($I$18+$I$19+$I$20)*I28+($J$18+$J$19+$J$20)*J28+($K$18+$K$19+$K$20)*K28) -> 0.33333333 | K29: =($I$20*I28+$J$20*J28+$K$20*K28)/(($I$18+$I$19+$I$20)*I28+($J$18+$J$19+$J$20)*J28+($K$18+$K$19+$K$20)*K28) -> 0.33333333 | L29: =($I$18+$I$19+$I$20)*I29+($J$18+$J$19+$J$20)*J29+($K$18+$K$19+$K$20)*K29 -> 0.75 | M29: =(M28*$I$18+N28*$I$19+O28*$I$20)/(($I$18+$J$18+$K$18)*M28+($I$19+$J$19+$K$19)*N28+($I$20+$J$20+$K$20)*O28) -> 0.33333333 | N29: =(M28*$J$18+N28*$J$19+O28*$J$20)/(($I$18+$J$18+$K$18)*M28+($I$19+$J$19+$K$19)*N28+($I$20+$J$20+$K$20)*O28) -> 0.33333333 | O29: =(M28*$K$18+N28*$K$19+O28*$K$20)/(($I$18+$J$18+$K$18)*M28+($I$19+$J$19+$K$19)*N28+($I$20+$J$20+$K$20)*O28) -> 0.33333333 | P29: Power iteration: v' = Mv / sum(Mv) and u' = u'M / sum(u'M), from equal weights. Each block's part is u_l M_ll' v_l' / u'v; the diagonal and the cross-layer parts add up to rho(M).
A30: 10 | B30: =A_keep*B29+C_pass*D29 -> 0.018848419 | C30: =C_pass*B29+A_keep*C29 -> 0.018616676 | D30: =C_pass*C29+A_keep*D29 -> 0.018848419 | E30: =SUM(B30:D30) -> 0.056313515 | F30: =F29+E30 -> 3.8310595 | H30: 7 | I30: =($I$18*I29+$J$18*J29+$K$18*K29)/(($I$18+$I$19+$I$20)*I29+($J$18+$J$19+$J$20)*J29+($K$18+$K$19+$K$20)*K29) -> 0.33333333 | J30: =($I$19*I29+$J$19*J29+$K$19*K29)/(($I$18+$I$19+$I$20)*I29+($J$18+$J$19+$J$20)*J29+($K$18+$K$19+$K$20)*K29) -> 0.33333333 | K30: =($I$20*I29+$J$20*J29+$K$20*K29)/(($I$18+$I$19+$I$20)*I29+($J$18+$J$19+$J$20)*J29+($K$18+$K$19+$K$20)*K29) -> 0.33333333 | L30: =($I$18+$I$19+$I$20)*I30+($J$18+$J$19+$J$20)*J30+($K$18+$K$19+$K$20)*K30 -> 0.75 | M30: =(M29*$I$18+N29*$I$19+O29*$I$20)/(($I$18+$J$18+$K$18)*M29+($I$19+$J$19+$K$19)*N29+($I$20+$J$20+$K$20)*O29) -> 0.33333333 | N30: =(M29*$J$18+N29*$J$19+O29*$J$20)/(($I$18+$J$18+$K$18)*M29+($I$19+$J$19+$K$19)*N29+($I$20+$J$20+$K$20)*O29) -> 0.33333333 | O30: =(M29*$K$18+N29*$K$19+O29*$K$20)/(($I$18+$J$18+$K$18)*M29+($I$19+$J$19+$K$19)*N29+($I$20+$J$20+$K$20)*O29) -> 0.33333333
A31: 11 | B31: =A_keep*B30+C_pass*D30 -> 0.014136314 | C31: =C_pass*B30+A_keep*C30 -> 0.014020443 | D31: =C_pass*C30+A_keep*D30 -> 0.014078379 | E31: =SUM(B31:D31) -> 0.042235136 | F31: =F30+E31 -> 3.8732946 | H31: 8 | I31: =($I$18*I30+$J$18*J30+$K$18*K30)/(($I$18+$I$19+$I$20)*I30+($J$18+$J$19+$J$20)*J30+($K$18+$K$19+$K$20)*K30) -> 0.33333333 | J31: =($I$19*I30+$J$19*J30+$K$19*K30)/(($I$18+$I$19+$I$20)*I30+($J$18+$J$19+$J$20)*J30+($K$18+$K$19+$K$20)*K30) -> 0.33333333 | K31: =($I$20*I30+$J$20*J30+$K$20*K30)/(($I$18+$I$19+$I$20)*I30+($J$18+$J$19+$J$20)*J30+($K$18+$K$19+$K$20)*K30) -> 0.33333333 | L31: =($I$18+$I$19+$I$20)*I31+($J$18+$J$19+$J$20)*J31+($K$18+$K$19+$K$20)*K31 -> 0.75 | M31: =(M30*$I$18+N30*$I$19+O30*$I$20)/(($I$18+$J$18+$K$18)*M30+($I$19+$J$19+$K$19)*N30+($I$20+$J$20+$K$20)*O30) -> 0.33333333 | N31: =(M30*$J$18+N30*$J$19+O30*$J$20)/(($I$18+$J$18+$K$18)*M30+($I$19+$J$19+$K$19)*N30+($I$20+$J$20+$K$20)*O30) -> 0.33333333 | O31: =(M30*$K$18+N30*$K$19+O30*$K$20)/(($I$18+$J$18+$K$18)*M30+($I$19+$J$19+$K$19)*N30+($I$20+$J$20+$K$20)*O30) -> 0.33333333
A32: 12 | B32: =A_keep*B31+C_pass*D31 -> 0.010587752 | C32: =C_pass*B31+A_keep*C31 -> 0.0105443 | D32: =C_pass*C31+A_keep*D31 -> 0.0105443 | E32: =SUM(B32:D32) -> 0.031676352 | F32: =F31+E32 -> 3.9049709 | H32: 9 | I32: =($I$18*I31+$J$18*J31+$K$18*K31)/(($I$18+$I$19+$I$20)*I31+($J$18+$J$19+$J$20)*J31+($K$18+$K$19+$K$20)*K31) -> 0.33333333 | J32: =($I$19*I31+$J$19*J31+$K$19*K31)/(($I$18+$I$19+$I$20)*I31+($J$18+$J$19+$J$20)*J31+($K$18+$K$19+$K$20)*K31) -> 0.33333333 | K32: =($I$20*I31+$J$20*J31+$K$20*K31)/(($I$18+$I$19+$I$20)*I31+($J$18+$J$19+$J$20)*J31+($K$18+$K$19+$K$20)*K31) -> 0.33333333 | L32: =($I$18+$I$19+$I$20)*I32+($J$18+$J$19+$J$20)*J32+($K$18+$K$19+$K$20)*K32 -> 0.75 | M32: =(M31*$I$18+N31*$I$19+O31*$I$20)/(($I$18+$J$18+$K$18)*M31+($I$19+$J$19+$K$19)*N31+($I$20+$J$20+$K$20)*O31) -> 0.33333333 | N32: =(M31*$J$18+N31*$J$19+O31*$J$20)/(($I$18+$J$18+$K$18)*M31+($I$19+$J$19+$K$19)*N31+($I$20+$J$20+$K$20)*O31) -> 0.33333333 | O32: =(M31*$K$18+N31*$K$19+O31*$K$20)/(($I$18+$J$18+$K$18)*M31+($I$19+$J$19+$K$19)*N31+($I$20+$J$20+$K$20)*O31) -> 0.33333333
A33: 13 | B33: =A_keep*B32+C_pass*D32 -> 0.007929951 | C33: =C_pass*B32+A_keep*C32 -> 0.007919088 | D33: =C_pass*C32+A_keep*D32 -> 0.0079082251 | E33: =SUM(B33:D33) -> 0.023757264 | F33: =F32+E33 -> 3.9287282 | H33: 10 | I33: =($I$18*I32+$J$18*J32+$K$18*K32)/(($I$18+$I$19+$I$20)*I32+($J$18+$J$19+$J$20)*J32+($K$18+$K$19+$K$20)*K32) -> 0.33333333 | J33: =($I$19*I32+$J$19*J32+$K$19*K32)/(($I$18+$I$19+$I$20)*I32+($J$18+$J$19+$J$20)*J32+($K$18+$K$19+$K$20)*K32) -> 0.33333333 | K33: =($I$20*I32+$J$20*J32+$K$20*K32)/(($I$18+$I$19+$I$20)*I32+($J$18+$J$19+$J$20)*J32+($K$18+$K$19+$K$20)*K32) -> 0.33333333 | L33: =($I$18+$I$19+$I$20)*I33+($J$18+$J$19+$J$20)*J33+($K$18+$K$19+$K$20)*K33 -> 0.75 | M33: =(M32*$I$18+N32*$I$19+O32*$I$20)/(($I$18+$J$18+$K$18)*M32+($I$19+$J$19+$K$19)*N32+($I$20+$J$20+$K$20)*O32) -> 0.33333333 | N33: =(M32*$J$18+N32*$J$19+O32*$J$20)/(($I$18+$J$18+$K$18)*M32+($I$19+$J$19+$K$19)*N32+($I$20+$J$20+$K$20)*O32) -> 0.33333333 | O33: =(M32*$K$18+N32*$K$19+O32*$K$20)/(($I$18+$J$18+$K$18)*M32+($I$19+$J$19+$K$19)*N32+($I$20+$J$20+$K$20)*O32) -> 0.33333333
A34: 14 | B34: =A_keep*B33+C_pass*D33 -> 0.0059420317 | C34: =C_pass*B33+A_keep*C33 -> 0.0059420317 | D34: =C_pass*C33+A_keep*D33 -> 0.0059338845 | E34: =SUM(B34:D34) -> 0.017817948 | F34: =F33+E34 -> 3.9465462 | H34: 11 | I34: =($I$18*I33+$J$18*J33+$K$18*K33)/(($I$18+$I$19+$I$20)*I33+($J$18+$J$19+$J$20)*J33+($K$18+$K$19+$K$20)*K33) -> 0.33333333 | J34: =($I$19*I33+$J$19*J33+$K$19*K33)/(($I$18+$I$19+$I$20)*I33+($J$18+$J$19+$J$20)*J33+($K$18+$K$19+$K$20)*K33) -> 0.33333333 | K34: =($I$20*I33+$J$20*J33+$K$20*K33)/(($I$18+$I$19+$I$20)*I33+($J$18+$J$19+$J$20)*J33+($K$18+$K$19+$K$20)*K33) -> 0.33333333 | L34: =($I$18+$I$19+$I$20)*I34+($J$18+$J$19+$J$20)*J34+($K$18+$K$19+$K$20)*K34 -> 0.75 | M34: =(M33*$I$18+N33*$I$19+O33*$I$20)/(($I$18+$J$18+$K$18)*M33+($I$19+$J$19+$K$19)*N33+($I$20+$J$20+$K$20)*O33) -> 0.33333333 | N34: =(M33*$J$18+N33*$J$19+O33*$J$20)/(($I$18+$J$18+$K$18)*M33+($I$19+$J$19+$K$19)*N33+($I$20+$J$20+$K$20)*O33) -> 0.33333333 | O34: =(M33*$K$18+N33*$K$19+O33*$K$20)/(($I$18+$J$18+$K$18)*M33+($I$19+$J$19+$K$19)*N33+($I$20+$J$20+$K$20)*O33) -> 0.33333333
A35: 15 | B35: =A_keep*B34+C_pass*D34 -> 0.004454487 | C35: =C_pass*B34+A_keep*C34 -> 0.0044565238 | D35: =C_pass*C34+A_keep*D34 -> 0.0044524502 | E35: =SUM(B35:D35) -> 0.013363461 | F35: =F34+E35 -> 3.9599096 | H35: 12 | I35: =($I$18*I34+$J$18*J34+$K$18*K34)/(($I$18+$I$19+$I$20)*I34+($J$18+$J$19+$J$20)*J34+($K$18+$K$19+$K$20)*K34) -> 0.33333333 | J35: =($I$19*I34+$J$19*J34+$K$19*K34)/(($I$18+$I$19+$I$20)*I34+($J$18+$J$19+$J$20)*J34+($K$18+$K$19+$K$20)*K34) -> 0.33333333 | K35: =($I$20*I34+$J$20*J34+$K$20*K34)/(($I$18+$I$19+$I$20)*I34+($J$18+$J$19+$J$20)*J34+($K$18+$K$19+$K$20)*K34) -> 0.33333333 | L35: =($I$18+$I$19+$I$20)*I35+($J$18+$J$19+$J$20)*J35+($K$18+$K$19+$K$20)*K35 -> 0.75 | M35: =(M34*$I$18+N34*$I$19+O34*$I$20)/(($I$18+$J$18+$K$18)*M34+($I$19+$J$19+$K$19)*N34+($I$20+$J$20+$K$20)*O34) -> 0.33333333 | N35: =(M34*$J$18+N34*$J$19+O34*$J$20)/(($I$18+$J$18+$K$18)*M34+($I$19+$J$19+$K$19)*N34+($I$20+$J$20+$K$20)*O34) -> 0.33333333 | O35: =(M34*$K$18+N34*$K$19+O34*$K$20)/(($I$18+$J$18+$K$18)*M34+($I$19+$J$19+$K$19)*N34+($I$20+$J$20+$K$20)*O34) -> 0.33333333
A36: 16 | B36: =A_keep*B35+C_pass*D35 -> 0.0033403561 | C36: =C_pass*B35+A_keep*C35 -> 0.0033418837 | D36: =C_pass*C35+A_keep*D35 -> 0.0033403561 | E36: =SUM(B36:D36) -> 0.010022596 | F36: =F35+E36 -> 3.9699322 | H36: 13 | I36: =($I$18*I35+$J$18*J35+$K$18*K35)/(($I$18+$I$19+$I$20)*I35+($J$18+$J$19+$J$20)*J35+($K$18+$K$19+$K$20)*K35) -> 0.33333333 | J36: =($I$19*I35+$J$19*J35+$K$19*K35)/(($I$18+$I$19+$I$20)*I35+($J$18+$J$19+$J$20)*J35+($K$18+$K$19+$K$20)*K35) -> 0.33333333 | K36: =($I$20*I35+$J$20*J35+$K$20*K35)/(($I$18+$I$19+$I$20)*I35+($J$18+$J$19+$J$20)*J35+($K$18+$K$19+$K$20)*K35) -> 0.33333333 | L36: =($I$18+$I$19+$I$20)*I36+($J$18+$J$19+$J$20)*J36+($K$18+$K$19+$K$20)*K36 -> 0.75 | M36: =(M35*$I$18+N35*$I$19+O35*$I$20)/(($I$18+$J$18+$K$18)*M35+($I$19+$J$19+$K$19)*N35+($I$20+$J$20+$K$20)*O35) -> 0.33333333 | N36: =(M35*$J$18+N35*$J$19+O35*$J$20)/(($I$18+$J$18+$K$18)*M35+($I$19+$J$19+$K$19)*N35+($I$20+$J$20+$K$20)*O35) -> 0.33333333 | O36: =(M35*$K$18+N35*$K$19+O35*$K$20)/(($I$18+$J$18+$K$18)*M35+($I$19+$J$19+$K$19)*N35+($I$20+$J$20+$K$20)*O35) -> 0.33333333
A37: 17 | B37: =A_keep*B36+C_pass*D36 -> 0.002505267 | C37: =C_pass*B36+A_keep*C36 -> 0.0025060308 | D37: =C_pass*C36+A_keep*D36 -> 0.0025056489 | E37: =SUM(B37:D37) -> 0.0075169468 | F37: =F36+E37 -> 3.9774492 | H37: 14 | I37: =($I$18*I36+$J$18*J36+$K$18*K36)/(($I$18+$I$19+$I$20)*I36+($J$18+$J$19+$J$20)*J36+($K$18+$K$19+$K$20)*K36) -> 0.33333333 | J37: =($I$19*I36+$J$19*J36+$K$19*K36)/(($I$18+$I$19+$I$20)*I36+($J$18+$J$19+$J$20)*J36+($K$18+$K$19+$K$20)*K36) -> 0.33333333 | K37: =($I$20*I36+$J$20*J36+$K$20*K36)/(($I$18+$I$19+$I$20)*I36+($J$18+$J$19+$J$20)*J36+($K$18+$K$19+$K$20)*K36) -> 0.33333333 | L37: =($I$18+$I$19+$I$20)*I37+($J$18+$J$19+$J$20)*J37+($K$18+$K$19+$K$20)*K37 -> 0.75 | M37: =(M36*$I$18+N36*$I$19+O36*$I$20)/(($I$18+$J$18+$K$18)*M36+($I$19+$J$19+$K$19)*N36+($I$20+$J$20+$K$20)*O36) -> 0.33333333 | N37: =(M36*$J$18+N36*$J$19+O36*$J$20)/(($I$18+$J$18+$K$18)*M36+($I$19+$J$19+$K$19)*N36+($I$20+$J$20+$K$20)*O36) -> 0.33333333 | O37: =(M36*$K$18+N36*$K$19+O36*$K$20)/(($I$18+$J$18+$K$18)*M36+($I$19+$J$19+$K$19)*N36+($I$20+$J$20+$K$20)*O36) -> 0.33333333
A38: 18 | B38: =A_keep*B37+C_pass*D37 -> 0.0018790458 | C38: =C_pass*B37+A_keep*C37 -> 0.0018793322 | D38: =C_pass*C37+A_keep*D37 -> 0.0018793322 | E38: =SUM(B38:D38) -> 0.0056377101 | F38: =F37+E38 -> 3.9830869 | H38: 15 | I38: =($I$18*I37+$J$18*J37+$K$18*K37)/(($I$18+$I$19+$I$20)*I37+($J$18+$J$19+$J$20)*J37+($K$18+$K$19+$K$20)*K37) -> 0.33333333 | J38: =($I$19*I37+$J$19*J37+$K$19*K37)/(($I$18+$I$19+$I$20)*I37+($J$18+$J$19+$J$20)*J37+($K$18+$K$19+$K$20)*K37) -> 0.33333333 | K38: =($I$20*I37+$J$20*J37+$K$20*K37)/(($I$18+$I$19+$I$20)*I37+($J$18+$J$19+$J$20)*J37+($K$18+$K$19+$K$20)*K37) -> 0.33333333 | L38: =($I$18+$I$19+$I$20)*I38+($J$18+$J$19+$J$20)*J38+($K$18+$K$19+$K$20)*K38 -> 0.75 | M38: =(M37*$I$18+N37*$I$19+O37*$I$20)/(($I$18+$J$18+$K$18)*M37+($I$19+$J$19+$K$19)*N37+($I$20+$J$20+$K$20)*O37) -> 0.33333333 | N38: =(M37*$J$18+N37*$J$19+O37*$J$20)/(($I$18+$J$18+$K$18)*M37+($I$19+$J$19+$K$19)*N37+($I$20+$J$20+$K$20)*O37) -> 0.33333333 | O38: =(M37*$K$18+N37*$K$19+O37*$K$20)/(($I$18+$J$18+$K$18)*M37+($I$19+$J$19+$K$19)*N37+($I$20+$J$20+$K$20)*O37) -> 0.33333333
A39: 19 | B39: =A_keep*B38+C_pass*D38 -> 0.0014093559 | C39: =C_pass*B38+A_keep*C38 -> 0.0014094275 | D39: =C_pass*C38+A_keep*D38 -> 0.0014094991 | E39: =SUM(B39:D39) -> 0.0042282826 | F39: =F38+E39 -> 3.9873152 | H39: 16 | I39: =($I$18*I38+$J$18*J38+$K$18*K38)/(($I$18+$I$19+$I$20)*I38+($J$18+$J$19+$J$20)*J38+($K$18+$K$19+$K$20)*K38) -> 0.33333333 | J39: =($I$19*I38+$J$19*J38+$K$19*K38)/(($I$18+$I$19+$I$20)*I38+($J$18+$J$19+$J$20)*J38+($K$18+$K$19+$K$20)*K38) -> 0.33333333 | K39: =($I$20*I38+$J$20*J38+$K$20*K38)/(($I$18+$I$19+$I$20)*I38+($J$18+$J$19+$J$20)*J38+($K$18+$K$19+$K$20)*K38) -> 0.33333333 | L39: =($I$18+$I$19+$I$20)*I39+($J$18+$J$19+$J$20)*J39+($K$18+$K$19+$K$20)*K39 -> 0.75 | M39: =(M38*$I$18+N38*$I$19+O38*$I$20)/(($I$18+$J$18+$K$18)*M38+($I$19+$J$19+$K$19)*N38+($I$20+$J$20+$K$20)*O38) -> 0.33333333 | N39: =(M38*$J$18+N38*$J$19+O38*$J$20)/(($I$18+$J$18+$K$18)*M38+($I$19+$J$19+$K$19)*N38+($I$20+$J$20+$K$20)*O38) -> 0.33333333 | O39: =(M38*$K$18+N38*$K$19+O38*$K$20)/(($I$18+$J$18+$K$18)*M38+($I$19+$J$19+$K$19)*N38+($I$20+$J$20+$K$20)*O38) -> 0.33333333
A40: 20 | B40: =A_keep*B39+C_pass*D39 -> 0.0010570527 | C40: =C_pass*B39+A_keep*C39 -> 0.0010570527 | D40: =C_pass*C39+A_keep*D39 -> 0.0010571064 | E40: =SUM(B40:D40) -> 0.0031712119 | F40: =F39+E40 -> 3.9904864 | H40: 17 | I40: =($I$18*I39+$J$18*J39+$K$18*K39)/(($I$18+$I$19+$I$20)*I39+($J$18+$J$19+$J$20)*J39+($K$18+$K$19+$K$20)*K39) -> 0.33333333 | J40: =($I$19*I39+$J$19*J39+$K$19*K39)/(($I$18+$I$19+$I$20)*I39+($J$18+$J$19+$J$20)*J39+($K$18+$K$19+$K$20)*K39) -> 0.33333333 | K40: =($I$20*I39+$J$20*J39+$K$20*K39)/(($I$18+$I$19+$I$20)*I39+($J$18+$J$19+$J$20)*J39+($K$18+$K$19+$K$20)*K39) -> 0.33333333 | L40: =($I$18+$I$19+$I$20)*I40+($J$18+$J$19+$J$20)*J40+($K$18+$K$19+$K$20)*K40 -> 0.75 | M40: =(M39*$I$18+N39*$I$19+O39*$I$20)/(($I$18+$J$18+$K$18)*M39+($I$19+$J$19+$K$19)*N39+($I$20+$J$20+$K$20)*O39) -> 0.33333333 | N40: =(M39*$J$18+N39*$J$19+O39*$J$20)/(($I$18+$J$18+$K$18)*M39+($I$19+$J$19+$K$19)*N39+($I$20+$J$20+$K$20)*O39) -> 0.33333333 | O40: =(M39*$K$18+N39*$K$19+O39*$K$20)/(($I$18+$J$18+$K$18)*M39+($I$19+$J$19+$K$19)*N39+($I$20+$J$20+$K$20)*O39) -> 0.33333333
A41: 21 | B41: =A_keep*B40+C_pass*D40 -> 0.00079280298 | C41: =C_pass*B40+A_keep*C40 -> 0.00079278956 | D41: =C_pass*C40+A_keep*D40 -> 0.00079281641 | E41: =SUM(B41:D41) -> 0.002378409 | F41: =F40+E41 -> 3.9928648 | H41: 18 | I41: =($I$18*I40+$J$18*J40+$K$18*K40)/(($I$18+$I$19+$I$20)*I40+($J$18+$J$19+$J$20)*J40+($K$18+$K$19+$K$20)*K40) -> 0.33333333 | J41: =($I$19*I40+$J$19*J40+$K$19*K40)/(($I$18+$I$19+$I$20)*I40+($J$18+$J$19+$J$20)*J40+($K$18+$K$19+$K$20)*K40) -> 0.33333333 | K41: =($I$20*I40+$J$20*J40+$K$20*K40)/(($I$18+$I$19+$I$20)*I40+($J$18+$J$19+$J$20)*J40+($K$18+$K$19+$K$20)*K40) -> 0.33333333 | L41: =($I$18+$I$19+$I$20)*I41+($J$18+$J$19+$J$20)*J41+($K$18+$K$19+$K$20)*K41 -> 0.75 | M41: =(M40*$I$18+N40*$I$19+O40*$I$20)/(($I$18+$J$18+$K$18)*M40+($I$19+$J$19+$K$19)*N40+($I$20+$J$20+$K$20)*O40) -> 0.33333333 | N41: =(M40*$J$18+N40*$J$19+O40*$J$20)/(($I$18+$J$18+$K$18)*M40+($I$19+$J$19+$K$19)*N40+($I$20+$J$20+$K$20)*O40) -> 0.33333333 | O41: =(M40*$K$18+N40*$K$19+O40*$K$20)/(($I$18+$J$18+$K$18)*M40+($I$19+$J$19+$K$19)*N40+($I$20+$J$20+$K$20)*O40) -> 0.33333333
... A103: 83 | B103: =A_keep*B102+C_pass*D102 -> 1.4222096e-11 | C103: =C_pass*B102+A_keep*C102 -> 1.4222096e-11 | D103: =C_pass*C102+A_keep*D102 -> 1.4222096e-11 | E103: =SUM(B103:D103) -> 4.2666288e-11 | F103: =F102+E103 -> 4 | H103: 80 | I103: =($I$18*I102+$J$18*J102+$K$18*K102)/(($I$18+$I$19+$I$20)*I102+($J$18+$J$19+$J$20)*J102+($K$18+$K$19+$K$20)*K102) -> 0.33333333 | J103: =($I$19*I102+$J$19*J102+$K$19*K102)/(($I$18+$I$19+$I$20)*I102+($J$18+$J$19+$J$20)*J102+($K$18+$K$19+$K$20)*K102) -> 0.33333333 | K103: =($I$20*I102+$J$20*J102+$K$20*K102)/(($I$18+$I$19+$I$20)*I102+($J$18+$J$19+$J$20)*J102+($K$18+$K$19+$K$20)*K102) -> 0.33333333 | L103: =($I$18+$I$19+$I$20)*I103+($J$18+$J$19+$J$20)*J103+($K$18+$K$19+$K$20)*K103 -> 0.75 | M103: =(M102*$I$18+N102*$I$19+O102*$I$20)/(($I$18+$J$18+$K$18)*M102+($I$19+$J$19+$K$19)*N102+($I$20+$J$20+$K$20)*O102) -> 0.33333333 | N103: =(M102*$J$18+N102*$J$19+O102*$J$20)/(($I$18+$J$18+$K$18)*M102+($I$19+$J$19+$K$19)*N102+($I$20+$J$20+$K$20)*O102) -> 0.33333333 | O103: =(M102*$K$18+N102*$K$19+O102*$K$20)/(($I$18+$J$18+$K$18)*M102+($I$19+$J$19+$K$19)*N102+($I$20+$J$20+$K$20)*O102) -> 0.33333333
A104: 84 | B104: =A_keep*B103+C_pass*D103 -> 1.0666572e-11 | C104: =C_pass*B103+A_keep*C103 -> 1.0666572e-11 | D104: =C_pass*C103+A_keep*D103 -> 1.0666572e-11 | E104: =SUM(B104:D104) -> 3.1999716e-11 | F104: =F103+E104 -> 4
A105: 85 | B105: =A_keep*B104+C_pass*D104 -> 7.999929e-12 | C105: =C_pass*B104+A_keep*C104 -> 7.999929e-12 | D105: =C_pass*C104+A_keep*D104 -> 7.999929e-12 | E105: =SUM(B105:D105) -> 2.3999787e-11 | F105: =F104+E105 -> 4
A106: 86 | B106: =A_keep*B105+C_pass*D105 -> 5.9999468e-12 | C106: =C_pass*B105+A_keep*C105 -> 5.9999468e-12 | D106: =C_pass*C105+A_keep*D105 -> 5.9999468e-12 | E106: =SUM(B106:D106) -> 1.799984e-11 | F106: =F105+E106 -> 4
A107: 87 | B107: =A_keep*B106+C_pass*D106 -> 4.4999601e-12 | C107: =C_pass*B106+A_keep*C106 -> 4.4999601e-12 | D107: =C_pass*C106+A_keep*D106 -> 4.4999601e-12 | E107: =SUM(B107:D107) -> 1.349988e-11 | F107: =F106+E107 -> 4
A108: 88 | B108: =A_keep*B107+C_pass*D107 -> 3.3749701e-12 | C108: =C_pass*B107+A_keep*C107 -> 3.3749701e-12 | D108: =C_pass*C107+A_keep*D107 -> 3.3749701e-12 | E108: =SUM(B108:D108) -> 1.012491e-11 | F108: =F107+E108 -> 4
A109: 89 | B109: =A_keep*B108+C_pass*D108 -> 2.5312275e-12 | C109: =C_pass*B108+A_keep*C108 -> 2.5312275e-12 | D109: =C_pass*C108+A_keep*D108 -> 2.5312275e-12 | E109: =SUM(B109:D109) -> 7.5936826e-12 | F109: =F108+E109 -> 4
A110: 90 | B110: =A_keep*B109+C_pass*D109 -> 1.8984207e-12 | C110: =C_pass*B109+A_keep*C109 -> 1.8984207e-12 | D110: =C_pass*C109+A_keep*D109 -> 1.8984207e-12 | E110: =SUM(B110:D110) -> 5.695262e-12 | F110: =F109+E110 -> 4
A111: 91 | B111: =A_keep*B110+C_pass*D110 -> 1.4238155e-12 | C111: =C_pass*B110+A_keep*C110 -> 1.4238155e-12 | D111: =C_pass*C110+A_keep*D110 -> 1.4238155e-12 | E111: =SUM(B111:D111) -> 4.2714465e-12 | F111: =F110+E111 -> 4
A112: 92 | B112: =A_keep*B111+C_pass*D111 -> 1.0678616e-12 | C112: =C_pass*B111+A_keep*C111 -> 1.0678616e-12 | D112: =C_pass*C111+A_keep*D111 -> 1.0678616e-12 | E112: =SUM(B112:D112) -> 3.2035849e-12 | F112: =F111+E112 -> 4
A113: 93 | B113: =A_keep*B112+C_pass*D112 -> 8.0089621e-13 | C113: =C_pass*B112+A_keep*C112 -> 8.0089621e-13 | D113: =C_pass*C112+A_keep*D112 -> 8.0089621e-13 | E113: =SUM(B113:D113) -> 2.4026886e-12 | F113: =F112+E113 -> 4
A114: 94 | B114: =A_keep*B113+C_pass*D113 -> 6.0067216e-13 | C114: =C_pass*B113+A_keep*C113 -> 6.0067216e-13 | D114: =C_pass*C113+A_keep*D113 -> 6.0067216e-13 | E114: =SUM(B114:D114) -> 1.8020165e-12 | F114: =F113+E114 -> 4
A115: 95 | B115: =A_keep*B114+C_pass*D114 -> 4.5050412e-13 | C115: =C_pass*B114+A_keep*C114 -> 4.5050412e-13 | D115: =C_pass*C114+A_keep*D114 -> 4.5050412e-13 | E115: =SUM(B115:D115) -> 1.3515124e-12 | F115: =F114+E115 -> 4
... A220: 200 | B220: =A_keep*B219+C_pass*D219 -> 3.4287153e-26 | C220: =C_pass*B219+A_keep*C219 -> 3.4287153e-26 | D220: =C_pass*C219+A_keep*D219 -> 3.4287153e-26 | E220: =SUM(B220:D220) -> 1.0286146e-25 | F220: =F219+E220 -> 4

Sheet Wavefront
A1: Follow the wavefront: the ledger clocks (Proposition 13.2; Theorem 13.4(iii); Online Appendix 13.B.3; AXIOM Lab 1.13, step 3)
A2: Distances on the skeleton by relaxation: D(u,v) = min(D(u,v), min over arrows w -> v of D(u,w) + 1). 99 means never.
A4: Arrows (row sends, column receives) | B4: =INDEX(Comps,1) -> MKT | C4: =INDEX(Comps,2) -> GOV | D4: =INDEX(Comps,3) -> MAT | E4: =INDEX(Comps,4) -> IND | F4: =INDEX(Comps,5) -> DIG | G4: =INDEX(Comps,6) -> ENG | H4: =INDEX(Comps,7) -> TRS | J4: Arrows into (row receives from column) | K4: =INDEX(Comps,1) -> MKT | L4: =INDEX(Comps,2) -> GOV | M4: =INDEX(Comps,3) -> MAT | N4: =INDEX(Comps,4) -> IND | O4: =INDEX(Comps,5) -> DIG | P4: =INDEX(Comps,6) -> ENG | Q4: =INDEX(Comps,7) -> TRS
A5: =INDEX(Comps,1) -> MKT | B5: =COUNTIFS(Arr_from,$A5,Arr_to,B$4) -> 0 | C5: =COUNTIFS(Arr_from,$A5,Arr_to,C$4) -> 0 | D5: =COUNTIFS(Arr_from,$A5,Arr_to,D$4) -> 1 | E5: =COUNTIFS(Arr_from,$A5,Arr_to,E$4) -> 1 | F5: =COUNTIFS(Arr_from,$A5,Arr_to,F$4) -> 1 | G5: =COUNTIFS(Arr_from,$A5,Arr_to,G$4) -> 0 | H5: =COUNTIFS(Arr_from,$A5,Arr_to,H$4) -> 0 | J5: =INDEX(Comps,1) -> MKT | K5: =INDEX($B$5:$H$11,1,1) -> 0 | L5: =INDEX($B$5:$H$11,2,1) -> 0 | M5: =INDEX($B$5:$H$11,3,1) -> 0 | N5: =INDEX($B$5:$H$11,4,1) -> 0 | O5: =INDEX($B$5:$H$11,5,1) -> 0 | P5: =INDEX($B$5:$H$11,6,1) -> 0 | Q5: =INDEX($B$5:$H$11,7,1) -> 0
A6: =INDEX(Comps,2) -> GOV | B6: =COUNTIFS(Arr_from,$A6,Arr_to,B$4) -> 0 | C6: =COUNTIFS(Arr_from,$A6,Arr_to,C$4) -> 0 | D6: =COUNTIFS(Arr_from,$A6,Arr_to,D$4) -> 0 | E6: =COUNTIFS(Arr_from,$A6,Arr_to,E$4) -> 0 | F6: =COUNTIFS(Arr_from,$A6,Arr_to,F$4) -> 1 | G6: =COUNTIFS(Arr_from,$A6,Arr_to,G$4) -> 0 | H6: =COUNTIFS(Arr_from,$A6,Arr_to,H$4) -> 1 | J6: =INDEX(Comps,2) -> GOV | K6: =INDEX($B$5:$H$11,1,2) -> 0 | L6: =INDEX($B$5:$H$11,2,2) -> 0 | M6: =INDEX($B$5:$H$11,3,2) -> 0 | N6: =INDEX($B$5:$H$11,4,2) -> 0 | O6: =INDEX($B$5:$H$11,5,2) -> 0 | P6: =INDEX($B$5:$H$11,6,2) -> 0 | Q6: =INDEX($B$5:$H$11,7,2) -> 0
A7: =INDEX(Comps,3) -> MAT | B7: =COUNTIFS(Arr_from,$A7,Arr_to,B$4) -> 0 | C7: =COUNTIFS(Arr_from,$A7,Arr_to,C$4) -> 0 | D7: =COUNTIFS(Arr_from,$A7,Arr_to,D$4) -> 0 | E7: =COUNTIFS(Arr_from,$A7,Arr_to,E$4) -> 0 | F7: =COUNTIFS(Arr_from,$A7,Arr_to,F$4) -> 0 | G7: =COUNTIFS(Arr_from,$A7,Arr_to,G$4) -> 0 | H7: =COUNTIFS(Arr_from,$A7,Arr_to,H$4) -> 1 | J7: =INDEX(Comps,3) -> MAT | K7: =INDEX($B$5:$H$11,1,3) -> 1 | L7: =INDEX($B$5:$H$11,2,3) -> 0 | M7: =INDEX($B$5:$H$11,3,3) -> 0 | N7: =INDEX($B$5:$H$11,4,3) -> 0 | O7: =INDEX($B$5:$H$11,5,3) -> 0 | P7: =INDEX($B$5:$H$11,6,3) -> 0 | Q7: =INDEX($B$5:$H$11,7,3) -> 0
A8: =INDEX(Comps,4) -> IND | B8: =COUNTIFS(Arr_from,$A8,Arr_to,B$4) -> 0 | C8: =COUNTIFS(Arr_from,$A8,Arr_to,C$4) -> 0 | D8: =COUNTIFS(Arr_from,$A8,Arr_to,D$4) -> 0 | E8: =COUNTIFS(Arr_from,$A8,Arr_to,E$4) -> 0 | F8: =COUNTIFS(Arr_from,$A8,Arr_to,F$4) -> 0 | G8: =COUNTIFS(Arr_from,$A8,Arr_to,G$4) -> 1 | H8: =COUNTIFS(Arr_from,$A8,Arr_to,H$4) -> 1 | J8: =INDEX(Comps,4) -> IND | K8: =INDEX($B$5:$H$11,1,4) -> 1 | L8: =INDEX($B$5:$H$11,2,4) -> 0 | M8: =INDEX($B$5:$H$11,3,4) -> 0 | N8: =INDEX($B$5:$H$11,4,4) -> 0 | O8: =INDEX($B$5:$H$11,5,4) -> 0 | P8: =INDEX($B$5:$H$11,6,4) -> 1 | Q8: =INDEX($B$5:$H$11,7,4) -> 1
A9: =INDEX(Comps,5) -> DIG | B9: =COUNTIFS(Arr_from,$A9,Arr_to,B$4) -> 0 | C9: =COUNTIFS(Arr_from,$A9,Arr_to,C$4) -> 0 | D9: =COUNTIFS(Arr_from,$A9,Arr_to,D$4) -> 0 | E9: =COUNTIFS(Arr_from,$A9,Arr_to,E$4) -> 0 | F9: =COUNTIFS(Arr_from,$A9,Arr_to,F$4) -> 0 | G9: =COUNTIFS(Arr_from,$A9,Arr_to,G$4) -> 1 | H9: =COUNTIFS(Arr_from,$A9,Arr_to,H$4) -> 1 | J9: =INDEX(Comps,5) -> DIG | K9: =INDEX($B$5:$H$11,1,5) -> 1 | L9: =INDEX($B$5:$H$11,2,5) -> 1 | M9: =INDEX($B$5:$H$11,3,5) -> 0 | N9: =INDEX($B$5:$H$11,4,5) -> 0 | O9: =INDEX($B$5:$H$11,5,5) -> 0 | P9: =INDEX($B$5:$H$11,6,5) -> 1 | Q9: =INDEX($B$5:$H$11,7,5) -> 1
A10: =INDEX(Comps,6) -> ENG | B10: =COUNTIFS(Arr_from,$A10,Arr_to,B$4) -> 0 | C10: =COUNTIFS(Arr_from,$A10,Arr_to,C$4) -> 0 | D10: =COUNTIFS(Arr_from,$A10,Arr_to,D$4) -> 0 | E10: =COUNTIFS(Arr_from,$A10,Arr_to,E$4) -> 1 | F10: =COUNTIFS(Arr_from,$A10,Arr_to,F$4) -> 1 | G10: =COUNTIFS(Arr_from,$A10,Arr_to,G$4) -> 0 | H10: =COUNTIFS(Arr_from,$A10,Arr_to,H$4) -> 0 | J10: =INDEX(Comps,6) -> ENG | K10: =INDEX($B$5:$H$11,1,6) -> 0 | L10: =INDEX($B$5:$H$11,2,6) -> 0 | M10: =INDEX($B$5:$H$11,3,6) -> 0 | N10: =INDEX($B$5:$H$11,4,6) -> 1 | O10: =INDEX($B$5:$H$11,5,6) -> 1 | P10: =INDEX($B$5:$H$11,6,6) -> 0 | Q10: =INDEX($B$5:$H$11,7,6) -> 0
A11: =INDEX(Comps,7) -> TRS | B11: =COUNTIFS(Arr_from,$A11,Arr_to,B$4) -> 0 | C11: =COUNTIFS(Arr_from,$A11,Arr_to,C$4) -> 0 | D11: =COUNTIFS(Arr_from,$A11,Arr_to,D$4) -> 0 | E11: =COUNTIFS(Arr_from,$A11,Arr_to,E$4) -> 1 | F11: =COUNTIFS(Arr_from,$A11,Arr_to,F$4) -> 1 | G11: =COUNTIFS(Arr_from,$A11,Arr_to,G$4) -> 0 | H11: =COUNTIFS(Arr_from,$A11,Arr_to,H$4) -> 0 | J11: =INDEX(Comps,7) -> TRS | K11: =INDEX($B$5:$H$11,1,7) -> 0 | L11: =INDEX($B$5:$H$11,2,7) -> 1 | M11: =INDEX($B$5:$H$11,3,7) -> 1 | N11: =INDEX($B$5:$H$11,4,7) -> 1 | O11: =INDEX($B$5:$H$11,5,7) -> 1 | P11: =INDEX($B$5:$H$11,6,7) -> 0 | Q11: =INDEX($B$5:$H$11,7,7) -> 0
A14: Distance using at most 1 arrows | B14: =INDEX(Comps,1) -> MKT | C14: =INDEX(Comps,2) -> GOV | D14: =INDEX(Comps,3) -> MAT | E14: =INDEX(Comps,4) -> IND | F14: =INDEX(Comps,5) -> DIG | G14: =INDEX(Comps,6) -> ENG | H14: =INDEX(Comps,7) -> TRS
A15: =INDEX(Comps,1) -> MKT | B15: =IF($A15=B$14,0,IF(B5>0,1,99)) -> 0 | C15: =IF($A15=C$14,0,IF(C5>0,1,99)) -> 99 | D15: =IF($A15=D$14,0,IF(D5>0,1,99)) -> 1 | E15: =IF($A15=E$14,0,IF(E5>0,1,99)) -> 1 | F15: =IF($A15=F$14,0,IF(F5>0,1,99)) -> 1 | G15: =IF($A15=G$14,0,IF(G5>0,1,99)) -> 99 | H15: =IF($A15=H$14,0,IF(H5>0,1,99)) -> 99
A16: =INDEX(Comps,2) -> GOV | B16: =IF($A16=B$14,0,IF(B6>0,1,99)) -> 99 | C16: =IF($A16=C$14,0,IF(C6>0,1,99)) -> 0 | D16: =IF($A16=D$14,0,IF(D6>0,1,99)) -> 99 | E16: =IF($A16=E$14,0,IF(E6>0,1,99)) -> 99 | F16: =IF($A16=F$14,0,IF(F6>0,1,99)) -> 1 | G16: =IF($A16=G$14,0,IF(G6>0,1,99)) -> 99 | H16: =IF($A16=H$14,0,IF(H6>0,1,99)) -> 1
A17: =INDEX(Comps,3) -> MAT | B17: =IF($A17=B$14,0,IF(B7>0,1,99)) -> 99 | C17: =IF($A17=C$14,0,IF(C7>0,1,99)) -> 99 | D17: =IF($A17=D$14,0,IF(D7>0,1,99)) -> 0 | E17: =IF($A17=E$14,0,IF(E7>0,1,99)) -> 99 | F17: =IF($A17=F$14,0,IF(F7>0,1,99)) -> 99 | G17: =IF($A17=G$14,0,IF(G7>0,1,99)) -> 99 | H17: =IF($A17=H$14,0,IF(H7>0,1,99)) -> 1
A18: =INDEX(Comps,4) -> IND | B18: =IF($A18=B$14,0,IF(B8>0,1,99)) -> 99 | C18: =IF($A18=C$14,0,IF(C8>0,1,99)) -> 99 | D18: =IF($A18=D$14,0,IF(D8>0,1,99)) -> 99 | E18: =IF($A18=E$14,0,IF(E8>0,1,99)) -> 0 | F18: =IF($A18=F$14,0,IF(F8>0,1,99)) -> 99 | G18: =IF($A18=G$14,0,IF(G8>0,1,99)) -> 1 | H18: =IF($A18=H$14,0,IF(H8>0,1,99)) -> 1
A19: =INDEX(Comps,5) -> DIG | B19: =IF($A19=B$14,0,IF(B9>0,1,99)) -> 99 | C19: =IF($A19=C$14,0,IF(C9>0,1,99)) -> 99 | D19: =IF($A19=D$14,0,IF(D9>0,1,99)) -> 99 | E19: =IF($A19=E$14,0,IF(E9>0,1,99)) -> 99 | F19: =IF($A19=F$14,0,IF(F9>0,1,99)) -> 0 | G19: =IF($A19=G$14,0,IF(G9>0,1,99)) -> 1 | H19: =IF($A19=H$14,0,IF(H9>0,1,99)) -> 1
A20: =INDEX(Comps,6) -> ENG | B20: =IF($A20=B$14,0,IF(B10>0,1,99)) -> 99 | C20: =IF($A20=C$14,0,IF(C10>0,1,99)) -> 99 | D20: =IF($A20=D$14,0,IF(D10>0,1,99)) -> 99 | E20: =IF($A20=E$14,0,IF(E10>0,1,99)) -> 1 | F20: =IF($A20=F$14,0,IF(F10>0,1,99)) -> 1 | G20: =IF($A20=G$14,0,IF(G10>0,1,99)) -> 0 | H20: =IF($A20=H$14,0,IF(H10>0,1,99)) -> 99
A21: =INDEX(Comps,7) -> TRS | B21: =IF($A21=B$14,0,IF(B11>0,1,99)) -> 99 | C21: =IF($A21=C$14,0,IF(C11>0,1,99)) -> 99 | D21: =IF($A21=D$14,0,IF(D11>0,1,99)) -> 99 | E21: =IF($A21=E$14,0,IF(E11>0,1,99)) -> 1 | F21: =IF($A21=F$14,0,IF(F11>0,1,99)) -> 1 | G21: =IF($A21=G$14,0,IF(G11>0,1,99)) -> 99 | H21: =IF($A21=H$14,0,IF(H11>0,1,99)) -> 0
A23: Distance using at most 2 arrows | B23: =INDEX(Comps,1) -> MKT | C23: =INDEX(Comps,2) -> GOV | D23: =INDEX(Comps,3) -> MAT | E23: =INDEX(Comps,4) -> IND | F23: =INDEX(Comps,5) -> DIG | G23: =INDEX(Comps,6) -> ENG | H23: =INDEX(Comps,7) -> TRS
A24: =INDEX(Comps,1) -> MKT | B24: =MIN(B15,IF(COUNTIF($K$5:$Q$5,">0")=0,99,_xlfn.MINIFS($B$15:$H$15,$K$5:$Q$5,">0")+1)) -> 0 | C24: =MIN(C15,IF(COUNTIF($K$6:$Q$6,">0")=0,99,_xlfn.MINIFS($B$15:$H$15,$K$6:$Q$6,">0")+1)) -> 99 | D24: =MIN(D15,IF(COUNTIF($K$7:$Q$7,">0")=0,99,_xlfn.MINIFS($B$15:$H$15,$K$7:$Q$7,">0")+1)) -> 1 | E24: =MIN(E15,IF(COUNTIF($K$8:$Q$8,">0")=0,99,_xlfn.MINIFS($B$15:$H$15,$K$8:$Q$8,">0")+1)) -> 1 | F24: =MIN(F15,IF(COUNTIF($K$9:$Q$9,">0")=0,99,_xlfn.MINIFS($B$15:$H$15,$K$9:$Q$9,">0")+1)) -> 1 | G24: =MIN(G15,IF(COUNTIF($K$10:$Q$10,">0")=0,99,_xlfn.MINIFS($B$15:$H$15,$K$10:$Q$10,">0")+1)) -> 2 | H24: =MIN(H15,IF(COUNTIF($K$11:$Q$11,">0")=0,99,_xlfn.MINIFS($B$15:$H$15,$K$11:$Q$11,">0")+1)) -> 2
A25: =INDEX(Comps,2) -> GOV | B25: =MIN(B16,IF(COUNTIF($K$5:$Q$5,">0")=0,99,_xlfn.MINIFS($B$16:$H$16,$K$5:$Q$5,">0")+1)) -> 99 | C25: =MIN(C16,IF(COUNTIF($K$6:$Q$6,">0")=0,99,_xlfn.MINIFS($B$16:$H$16,$K$6:$Q$6,">0")+1)) -> 0 | D25: =MIN(D16,IF(COUNTIF($K$7:$Q$7,">0")=0,99,_xlfn.MINIFS($B$16:$H$16,$K$7:$Q$7,">0")+1)) -> 99 | E25: =MIN(E16,IF(COUNTIF($K$8:$Q$8,">0")=0,99,_xlfn.MINIFS($B$16:$H$16,$K$8:$Q$8,">0")+1)) -> 2 | F25: =MIN(F16,IF(COUNTIF($K$9:$Q$9,">0")=0,99,_xlfn.MINIFS($B$16:$H$16,$K$9:$Q$9,">0")+1)) -> 1 | G25: =MIN(G16,IF(COUNTIF($K$10:$Q$10,">0")=0,99,_xlfn.MINIFS($B$16:$H$16,$K$10:$Q$10,">0")+1)) -> 2 | H25: =MIN(H16,IF(COUNTIF($K$11:$Q$11,">0")=0,99,_xlfn.MINIFS($B$16:$H$16,$K$11:$Q$11,">0")+1)) -> 1
A26: =INDEX(Comps,3) -> MAT | B26: =MIN(B17,IF(COUNTIF($K$5:$Q$5,">0")=0,99,_xlfn.MINIFS($B$17:$H$17,$K$5:$Q$5,">0")+1)) -> 99 | C26: =MIN(C17,IF(COUNTIF($K$6:$Q$6,">0")=0,99,_xlfn.MINIFS($B$17:$H$17,$K$6:$Q$6,">0")+1)) -> 99 | D26: =MIN(D17,IF(COUNTIF($K$7:$Q$7,">0")=0,99,_xlfn.MINIFS($B$17:$H$17,$K$7:$Q$7,">0")+1)) -> 0 | E26: =MIN(E17,IF(COUNTIF($K$8:$Q$8,">0")=0,99,_xlfn.MINIFS($B$17:$H$17,$K$8:$Q$8,">0")+1)) -> 2 | F26: =MIN(F17,IF(COUNTIF($K$9:$Q$9,">0")=0,99,_xlfn.MINIFS($B$17:$H$17,$K$9:$Q$9,">0")+1)) -> 2 | G26: =MIN(G17,IF(COUNTIF($K$10:$Q$10,">0")=0,99,_xlfn.MINIFS($B$17:$H$17,$K$10:$Q$10,">0")+1)) -> 99 | H26: =MIN(H17,IF(COUNTIF($K$11:$Q$11,">0")=0,99,_xlfn.MINIFS($B$17:$H$17,$K$11:$Q$11,">0")+1)) -> 1
A27: =INDEX(Comps,4) -> IND | B27: =MIN(B18,IF(COUNTIF($K$5:$Q$5,">0")=0,99,_xlfn.MINIFS($B$18:$H$18,$K$5:$Q$5,">0")+1)) -> 99 | C27: =MIN(C18,IF(COUNTIF($K$6:$Q$6,">0")=0,99,_xlfn.MINIFS($B$18:$H$18,$K$6:$Q$6,">0")+1)) -> 99 | D27: =MIN(D18,IF(COUNTIF($K$7:$Q$7,">0")=0,99,_xlfn.MINIFS($B$18:$H$18,$K$7:$Q$7,">0")+1)) -> 99 | E27: =MIN(E18,IF(COUNTIF($K$8:$Q$8,">0")=0,99,_xlfn.MINIFS($B$18:$H$18,$K$8:$Q$8,">0")+1)) -> 0 | F27: =MIN(F18,IF(COUNTIF($K$9:$Q$9,">0")=0,99,_xlfn.MINIFS($B$18:$H$18,$K$9:$Q$9,">0")+1)) -> 2 | G27: =MIN(G18,IF(COUNTIF($K$10:$Q$10,">0")=0,99,_xlfn.MINIFS($B$18:$H$18,$K$10:$Q$10,">0")+1)) -> 1 | H27: =MIN(H18,IF(COUNTIF($K$11:$Q$11,">0")=0,99,_xlfn.MINIFS($B$18:$H$18,$K$11:$Q$11,">0")+1)) -> 1
A28: =INDEX(Comps,5) -> DIG | B28: =MIN(B19,IF(COUNTIF($K$5:$Q$5,">0")=0,99,_xlfn.MINIFS($B$19:$H$19,$K$5:$Q$5,">0")+1)) -> 99 | C28: =MIN(C19,IF(COUNTIF($K$6:$Q$6,">0")=0,99,_xlfn.MINIFS($B$19:$H$19,$K$6:$Q$6,">0")+1)) -> 99 | D28: =MIN(D19,IF(COUNTIF($K$7:$Q$7,">0")=0,99,_xlfn.MINIFS($B$19:$H$19,$K$7:$Q$7,">0")+1)) -> 99 | E28: =MIN(E19,IF(COUNTIF($K$8:$Q$8,">0")=0,99,_xlfn.MINIFS($B$19:$H$19,$K$8:$Q$8,">0")+1)) -> 2 | F28: =MIN(F19,IF(COUNTIF($K$9:$Q$9,">0")=0,99,_xlfn.MINIFS($B$19:$H$19,$K$9:$Q$9,">0")+1)) -> 0 | G28: =MIN(G19,IF(COUNTIF($K$10:$Q$10,">0")=0,99,_xlfn.MINIFS($B$19:$H$19,$K$10:$Q$10,">0")+1)) -> 1 | H28: =MIN(H19,IF(COUNTIF($K$11:$Q$11,">0")=0,99,_xlfn.MINIFS($B$19:$H$19,$K$11:$Q$11,">0")+1)) -> 1
A29: =INDEX(Comps,6) -> ENG | B29: =MIN(B20,IF(COUNTIF($K$5:$Q$5,">0")=0,99,_xlfn.MINIFS($B$20:$H$20,$K$5:$Q$5,">0")+1)) -> 99 | C29: =MIN(C20,IF(COUNTIF($K$6:$Q$6,">0")=0,99,_xlfn.MINIFS($B$20:$H$20,$K$6:$Q$6,">0")+1)) -> 99 | D29: =MIN(D20,IF(COUNTIF($K$7:$Q$7,">0")=0,99,_xlfn.MINIFS($B$20:$H$20,$K$7:$Q$7,">0")+1)) -> 99 | E29: =MIN(E20,IF(COUNTIF($K$8:$Q$8,">0")=0,99,_xlfn.MINIFS($B$20:$H$20,$K$8:$Q$8,">0")+1)) -> 1 | F29: =MIN(F20,IF(COUNTIF($K$9:$Q$9,">0")=0,99,_xlfn.MINIFS($B$20:$H$20,$K$9:$Q$9,">0")+1)) -> 1 | G29: =MIN(G20,IF(COUNTIF($K$10:$Q$10,">0")=0,99,_xlfn.MINIFS($B$20:$H$20,$K$10:$Q$10,">0")+1)) -> 0 | H29: =MIN(H20,IF(COUNTIF($K$11:$Q$11,">0")=0,99,_xlfn.MINIFS($B$20:$H$20,$K$11:$Q$11,">0")+1)) -> 2
A30: =INDEX(Comps,7) -> TRS | B30: =MIN(B21,IF(COUNTIF($K$5:$Q$5,">0")=0,99,_xlfn.MINIFS($B$21:$H$21,$K$5:$Q$5,">0")+1)) -> 99 | C30: =MIN(C21,IF(COUNTIF($K$6:$Q$6,">0")=0,99,_xlfn.MINIFS($B$21:$H$21,$K$6:$Q$6,">0")+1)) -> 99 | D30: =MIN(D21,IF(COUNTIF($K$7:$Q$7,">0")=0,99,_xlfn.MINIFS($B$21:$H$21,$K$7:$Q$7,">0")+1)) -> 99 | E30: =MIN(E21,IF(COUNTIF($K$8:$Q$8,">0")=0,99,_xlfn.MINIFS($B$21:$H$21,$K$8:$Q$8,">0")+1)) -> 1 | F30: =MIN(F21,IF(COUNTIF($K$9:$Q$9,">0")=0,99,_xlfn.MINIFS($B$21:$H$21,$K$9:$Q$9,">0")+1)) -> 1 | G30: =MIN(G21,IF(COUNTIF($K$10:$Q$10,">0")=0,99,_xlfn.MINIFS($B$21:$H$21,$K$10:$Q$10,">0")+1)) -> 2 | H30: =MIN(H21,IF(COUNTIF($K$11:$Q$11,">0")=0,99,_xlfn.MINIFS($B$21:$H$21,$K$11:$Q$11,">0")+1)) -> 0
A32: Distance using at most 3 arrows | B32: =INDEX(Comps,1) -> MKT | C32: =INDEX(Comps,2) -> GOV | D32: =INDEX(Comps,3) -> MAT | E32: =INDEX(Comps,4) -> IND | F32: =INDEX(Comps,5) -> DIG | G32: =INDEX(Comps,6) -> ENG | H32: =INDEX(Comps,7) -> TRS
A33: =INDEX(Comps,1) -> MKT | B33: =MIN(B24,IF(COUNTIF($K$5:$Q$5,">0")=0,99,_xlfn.MINIFS($B$24:$H$24,$K$5:$Q$5,">0")+1)) -> 0 | C33: =MIN(C24,IF(COUNTIF($K$6:$Q$6,">0")=0,99,_xlfn.MINIFS($B$24:$H$24,$K$6:$Q$6,">0")+1)) -> 99 | D33: =MIN(D24,IF(COUNTIF($K$7:$Q$7,">0")=0,99,_xlfn.MINIFS($B$24:$H$24,$K$7:$Q$7,">0")+1)) -> 1 | E33: =MIN(E24,IF(COUNTIF($K$8:$Q$8,">0")=0,99,_xlfn.MINIFS($B$24:$H$24,$K$8:$Q$8,">0")+1)) -> 1 | F33: =MIN(F24,IF(COUNTIF($K$9:$Q$9,">0")=0,99,_xlfn.MINIFS($B$24:$H$24,$K$9:$Q$9,">0")+1)) -> 1 | G33: =MIN(G24,IF(COUNTIF($K$10:$Q$10,">0")=0,99,_xlfn.MINIFS($B$24:$H$24,$K$10:$Q$10,">0")+1)) -> 2 | H33: =MIN(H24,IF(COUNTIF($K$11:$Q$11,">0")=0,99,_xlfn.MINIFS($B$24:$H$24,$K$11:$Q$11,">0")+1)) -> 2
A34: =INDEX(Comps,2) -> GOV | B34: =MIN(B25,IF(COUNTIF($K$5:$Q$5,">0")=0,99,_xlfn.MINIFS($B$25:$H$25,$K$5:$Q$5,">0")+1)) -> 99 | C34: =MIN(C25,IF(COUNTIF($K$6:$Q$6,">0")=0,99,_xlfn.MINIFS($B$25:$H$25,$K$6:$Q$6,">0")+1)) -> 0 | D34: =MIN(D25,IF(COUNTIF($K$7:$Q$7,">0")=0,99,_xlfn.MINIFS($B$25:$H$25,$K$7:$Q$7,">0")+1)) -> 99 | E34: =MIN(E25,IF(COUNTIF($K$8:$Q$8,">0")=0,99,_xlfn.MINIFS($B$25:$H$25,$K$8:$Q$8,">0")+1)) -> 2 | F34: =MIN(F25,IF(COUNTIF($K$9:$Q$9,">0")=0,99,_xlfn.MINIFS($B$25:$H$25,$K$9:$Q$9,">0")+1)) -> 1 | G34: =MIN(G25,IF(COUNTIF($K$10:$Q$10,">0")=0,99,_xlfn.MINIFS($B$25:$H$25,$K$10:$Q$10,">0")+1)) -> 2 | H34: =MIN(H25,IF(COUNTIF($K$11:$Q$11,">0")=0,99,_xlfn.MINIFS($B$25:$H$25,$K$11:$Q$11,">0")+1)) -> 1
A35: =INDEX(Comps,3) -> MAT | B35: =MIN(B26,IF(COUNTIF($K$5:$Q$5,">0")=0,99,_xlfn.MINIFS($B$26:$H$26,$K$5:$Q$5,">0")+1)) -> 99 | C35: =MIN(C26,IF(COUNTIF($K$6:$Q$6,">0")=0,99,_xlfn.MINIFS($B$26:$H$26,$K$6:$Q$6,">0")+1)) -> 99 | D35: =MIN(D26,IF(COUNTIF($K$7:$Q$7,">0")=0,99,_xlfn.MINIFS($B$26:$H$26,$K$7:$Q$7,">0")+1)) -> 0 | E35: =MIN(E26,IF(COUNTIF($K$8:$Q$8,">0")=0,99,_xlfn.MINIFS($B$26:$H$26,$K$8:$Q$8,">0")+1)) -> 2 | F35: =MIN(F26,IF(COUNTIF($K$9:$Q$9,">0")=0,99,_xlfn.MINIFS($B$26:$H$26,$K$9:$Q$9,">0")+1)) -> 2 | G35: =MIN(G26,IF(COUNTIF($K$10:$Q$10,">0")=0,99,_xlfn.MINIFS($B$26:$H$26,$K$10:$Q$10,">0")+1)) -> 3 | H35: =MIN(H26,IF(COUNTIF($K$11:$Q$11,">0")=0,99,_xlfn.MINIFS($B$26:$H$26,$K$11:$Q$11,">0")+1)) -> 1
A36: =INDEX(Comps,4) -> IND | B36: =MIN(B27,IF(COUNTIF($K$5:$Q$5,">0")=0,99,_xlfn.MINIFS($B$27:$H$27,$K$5:$Q$5,">0")+1)) -> 99 | C36: =MIN(C27,IF(COUNTIF($K$6:$Q$6,">0")=0,99,_xlfn.MINIFS($B$27:$H$27,$K$6:$Q$6,">0")+1)) -> 99 | D36: =MIN(D27,IF(COUNTIF($K$7:$Q$7,">0")=0,99,_xlfn.MINIFS($B$27:$H$27,$K$7:$Q$7,">0")+1)) -> 99 | E36: =MIN(E27,IF(COUNTIF($K$8:$Q$8,">0")=0,99,_xlfn.MINIFS($B$27:$H$27,$K$8:$Q$8,">0")+1)) -> 0 | F36: =MIN(F27,IF(COUNTIF($K$9:$Q$9,">0")=0,99,_xlfn.MINIFS($B$27:$H$27,$K$9:$Q$9,">0")+1)) -> 2 | G36: =MIN(G27,IF(COUNTIF($K$10:$Q$10,">0")=0,99,_xlfn.MINIFS($B$27:$H$27,$K$10:$Q$10,">0")+1)) -> 1 | H36: =MIN(H27,IF(COUNTIF($K$11:$Q$11,">0")=0,99,_xlfn.MINIFS($B$27:$H$27,$K$11:$Q$11,">0")+1)) -> 1
A37: =INDEX(Comps,5) -> DIG | B37: =MIN(B28,IF(COUNTIF($K$5:$Q$5,">0")=0,99,_xlfn.MINIFS($B$28:$H$28,$K$5:$Q$5,">0")+1)) -> 99 | C37: =MIN(C28,IF(COUNTIF($K$6:$Q$6,">0")=0,99,_xlfn.MINIFS($B$28:$H$28,$K$6:$Q$6,">0")+1)) -> 99 | D37: =MIN(D28,IF(COUNTIF($K$7:$Q$7,">0")=0,99,_xlfn.MINIFS($B$28:$H$28,$K$7:$Q$7,">0")+1)) -> 99 | E37: =MIN(E28,IF(COUNTIF($K$8:$Q$8,">0")=0,99,_xlfn.MINIFS($B$28:$H$28,$K$8:$Q$8,">0")+1)) -> 2 | F37: =MIN(F28,IF(COUNTIF($K$9:$Q$9,">0")=0,99,_xlfn.MINIFS($B$28:$H$28,$K$9:$Q$9,">0")+1)) -> 0 | G37: =MIN(G28,IF(COUNTIF($K$10:$Q$10,">0")=0,99,_xlfn.MINIFS($B$28:$H$28,$K$10:$Q$10,">0")+1)) -> 1 | H37: =MIN(H28,IF(COUNTIF($K$11:$Q$11,">0")=0,99,_xlfn.MINIFS($B$28:$H$28,$K$11:$Q$11,">0")+1)) -> 1
A38: =INDEX(Comps,6) -> ENG | B38: =MIN(B29,IF(COUNTIF($K$5:$Q$5,">0")=0,99,_xlfn.MINIFS($B$29:$H$29,$K$5:$Q$5,">0")+1)) -> 99 | C38: =MIN(C29,IF(COUNTIF($K$6:$Q$6,">0")=0,99,_xlfn.MINIFS($B$29:$H$29,$K$6:$Q$6,">0")+1)) -> 99 | D38: =MIN(D29,IF(COUNTIF($K$7:$Q$7,">0")=0,99,_xlfn.MINIFS($B$29:$H$29,$K$7:$Q$7,">0")+1)) -> 99 | E38: =MIN(E29,IF(COUNTIF($K$8:$Q$8,">0")=0,99,_xlfn.MINIFS($B$29:$H$29,$K$8:$Q$8,">0")+1)) -> 1 | F38: =MIN(F29,IF(COUNTIF($K$9:$Q$9,">0")=0,99,_xlfn.MINIFS($B$29:$H$29,$K$9:$Q$9,">0")+1)) -> 1 | G38: =MIN(G29,IF(COUNTIF($K$10:$Q$10,">0")=0,99,_xlfn.MINIFS($B$29:$H$29,$K$10:$Q$10,">0")+1)) -> 0 | H38: =MIN(H29,IF(COUNTIF($K$11:$Q$11,">0")=0,99,_xlfn.MINIFS($B$29:$H$29,$K$11:$Q$11,">0")+1)) -> 2
A39: =INDEX(Comps,7) -> TRS | B39: =MIN(B30,IF(COUNTIF($K$5:$Q$5,">0")=0,99,_xlfn.MINIFS($B$30:$H$30,$K$5:$Q$5,">0")+1)) -> 99 | C39: =MIN(C30,IF(COUNTIF($K$6:$Q$6,">0")=0,99,_xlfn.MINIFS($B$30:$H$30,$K$6:$Q$6,">0")+1)) -> 99 | D39: =MIN(D30,IF(COUNTIF($K$7:$Q$7,">0")=0,99,_xlfn.MINIFS($B$30:$H$30,$K$7:$Q$7,">0")+1)) -> 99 | E39: =MIN(E30,IF(COUNTIF($K$8:$Q$8,">0")=0,99,_xlfn.MINIFS($B$30:$H$30,$K$8:$Q$8,">0")+1)) -> 1 | F39: =MIN(F30,IF(COUNTIF($K$9:$Q$9,">0")=0,99,_xlfn.MINIFS($B$30:$H$30,$K$9:$Q$9,">0")+1)) -> 1 | G39: =MIN(G30,IF(COUNTIF($K$10:$Q$10,">0")=0,99,_xlfn.MINIFS($B$30:$H$30,$K$10:$Q$10,">0")+1)) -> 2 | H39: =MIN(H30,IF(COUNTIF($K$11:$Q$11,">0")=0,99,_xlfn.MINIFS($B$30:$H$30,$K$11:$Q$11,">0")+1)) -> 0
A41: Distance using at most 4 arrows | B41: =INDEX(Comps,1) -> MKT | C41: =INDEX(Comps,2) -> GOV | D41: =INDEX(Comps,3) -> MAT | E41: =INDEX(Comps,4) -> IND | F41: =INDEX(Comps,5) -> DIG | G41: =INDEX(Comps,6) -> ENG | H41: =INDEX(Comps,7) -> TRS
A42: =INDEX(Comps,1) -> MKT | B42: =MIN(B33,IF(COUNTIF($K$5:$Q$5,">0")=0,99,_xlfn.MINIFS($B$33:$H$33,$K$5:$Q$5,">0")+1)) -> 0 | C42: =MIN(C33,IF(COUNTIF($K$6:$Q$6,">0")=0,99,_xlfn.MINIFS($B$33:$H$33,$K$6:$Q$6,">0")+1)) -> 99 | D42: =MIN(D33,IF(COUNTIF($K$7:$Q$7,">0")=0,99,_xlfn.MINIFS($B$33:$H$33,$K$7:$Q$7,">0")+1)) -> 1 | E42: =MIN(E33,IF(COUNTIF($K$8:$Q$8,">0")=0,99,_xlfn.MINIFS($B$33:$H$33,$K$8:$Q$8,">0")+1)) -> 1 | F42: =MIN(F33,IF(COUNTIF($K$9:$Q$9,">0")=0,99,_xlfn.MINIFS($B$33:$H$33,$K$9:$Q$9,">0")+1)) -> 1 | G42: =MIN(G33,IF(COUNTIF($K$10:$Q$10,">0")=0,99,_xlfn.MINIFS($B$33:$H$33,$K$10:$Q$10,">0")+1)) -> 2 | H42: =MIN(H33,IF(COUNTIF($K$11:$Q$11,">0")=0,99,_xlfn.MINIFS($B$33:$H$33,$K$11:$Q$11,">0")+1)) -> 2
A43: =INDEX(Comps,2) -> GOV | B43: =MIN(B34,IF(COUNTIF($K$5:$Q$5,">0")=0,99,_xlfn.MINIFS($B$34:$H$34,$K$5:$Q$5,">0")+1)) -> 99 | C43: =MIN(C34,IF(COUNTIF($K$6:$Q$6,">0")=0,99,_xlfn.MINIFS($B$34:$H$34,$K$6:$Q$6,">0")+1)) -> 0 | D43: =MIN(D34,IF(COUNTIF($K$7:$Q$7,">0")=0,99,_xlfn.MINIFS($B$34:$H$34,$K$7:$Q$7,">0")+1)) -> 99 | E43: =MIN(E34,IF(COUNTIF($K$8:$Q$8,">0")=0,99,_xlfn.MINIFS($B$34:$H$34,$K$8:$Q$8,">0")+1)) -> 2 | F43: =MIN(F34,IF(COUNTIF($K$9:$Q$9,">0")=0,99,_xlfn.MINIFS($B$34:$H$34,$K$9:$Q$9,">0")+1)) -> 1 | G43: =MIN(G34,IF(COUNTIF($K$10:$Q$10,">0")=0,99,_xlfn.MINIFS($B$34:$H$34,$K$10:$Q$10,">0")+1)) -> 2 | H43: =MIN(H34,IF(COUNTIF($K$11:$Q$11,">0")=0,99,_xlfn.MINIFS($B$34:$H$34,$K$11:$Q$11,">0")+1)) -> 1
A44: =INDEX(Comps,3) -> MAT | B44: =MIN(B35,IF(COUNTIF($K$5:$Q$5,">0")=0,99,_xlfn.MINIFS($B$35:$H$35,$K$5:$Q$5,">0")+1)) -> 99 | C44: =MIN(C35,IF(COUNTIF($K$6:$Q$6,">0")=0,99,_xlfn.MINIFS($B$35:$H$35,$K$6:$Q$6,">0")+1)) -> 99 | D44: =MIN(D35,IF(COUNTIF($K$7:$Q$7,">0")=0,99,_xlfn.MINIFS($B$35:$H$35,$K$7:$Q$7,">0")+1)) -> 0 | E44: =MIN(E35,IF(COUNTIF($K$8:$Q$8,">0")=0,99,_xlfn.MINIFS($B$35:$H$35,$K$8:$Q$8,">0")+1)) -> 2 | F44: =MIN(F35,IF(COUNTIF($K$9:$Q$9,">0")=0,99,_xlfn.MINIFS($B$35:$H$35,$K$9:$Q$9,">0")+1)) -> 2 | G44: =MIN(G35,IF(COUNTIF($K$10:$Q$10,">0")=0,99,_xlfn.MINIFS($B$35:$H$35,$K$10:$Q$10,">0")+1)) -> 3 | H44: =MIN(H35,IF(COUNTIF($K$11:$Q$11,">0")=0,99,_xlfn.MINIFS($B$35:$H$35,$K$11:$Q$11,">0")+1)) -> 1
A45: =INDEX(Comps,4) -> IND | B45: =MIN(B36,IF(COUNTIF($K$5:$Q$5,">0")=0,99,_xlfn.MINIFS($B$36:$H$36,$K$5:$Q$5,">0")+1)) -> 99 | C45: =MIN(C36,IF(COUNTIF($K$6:$Q$6,">0")=0,99,_xlfn.MINIFS($B$36:$H$36,$K$6:$Q$6,">0")+1)) -> 99 | D45: =MIN(D36,IF(COUNTIF($K$7:$Q$7,">0")=0,99,_xlfn.MINIFS($B$36:$H$36,$K$7:$Q$7,">0")+1)) -> 99 | E45: =MIN(E36,IF(COUNTIF($K$8:$Q$8,">0")=0,99,_xlfn.MINIFS($B$36:$H$36,$K$8:$Q$8,">0")+1)) -> 0 | F45: =MIN(F36,IF(COUNTIF($K$9:$Q$9,">0")=0,99,_xlfn.MINIFS($B$36:$H$36,$K$9:$Q$9,">0")+1)) -> 2 | G45: =MIN(G36,IF(COUNTIF($K$10:$Q$10,">0")=0,99,_xlfn.MINIFS($B$36:$H$36,$K$10:$Q$10,">0")+1)) -> 1 | H45: =MIN(H36,IF(COUNTIF($K$11:$Q$11,">0")=0,99,_xlfn.MINIFS($B$36:$H$36,$K$11:$Q$11,">0")+1)) -> 1
A46: =INDEX(Comps,5) -> DIG | B46: =MIN(B37,IF(COUNTIF($K$5:$Q$5,">0")=0,99,_xlfn.MINIFS($B$37:$H$37,$K$5:$Q$5,">0")+1)) -> 99 | C46: =MIN(C37,IF(COUNTIF($K$6:$Q$6,">0")=0,99,_xlfn.MINIFS($B$37:$H$37,$K$6:$Q$6,">0")+1)) -> 99 | D46: =MIN(D37,IF(COUNTIF($K$7:$Q$7,">0")=0,99,_xlfn.MINIFS($B$37:$H$37,$K$7:$Q$7,">0")+1)) -> 99 | E46: =MIN(E37,IF(COUNTIF($K$8:$Q$8,">0")=0,99,_xlfn.MINIFS($B$37:$H$37,$K$8:$Q$8,">0")+1)) -> 2 | F46: =MIN(F37,IF(COUNTIF($K$9:$Q$9,">0")=0,99,_xlfn.MINIFS($B$37:$H$37,$K$9:$Q$9,">0")+1)) -> 0 | G46: =MIN(G37,IF(COUNTIF($K$10:$Q$10,">0")=0,99,_xlfn.MINIFS($B$37:$H$37,$K$10:$Q$10,">0")+1)) -> 1 | H46: =MIN(H37,IF(COUNTIF($K$11:$Q$11,">0")=0,99,_xlfn.MINIFS($B$37:$H$37,$K$11:$Q$11,">0")+1)) -> 1
A47: =INDEX(Comps,6) -> ENG | B47: =MIN(B38,IF(COUNTIF($K$5:$Q$5,">0")=0,99,_xlfn.MINIFS($B$38:$H$38,$K$5:$Q$5,">0")+1)) -> 99 | C47: =MIN(C38,IF(COUNTIF($K$6:$Q$6,">0")=0,99,_xlfn.MINIFS($B$38:$H$38,$K$6:$Q$6,">0")+1)) -> 99 | D47: =MIN(D38,IF(COUNTIF($K$7:$Q$7,">0")=0,99,_xlfn.MINIFS($B$38:$H$38,$K$7:$Q$7,">0")+1)) -> 99 | E47: =MIN(E38,IF(COUNTIF($K$8:$Q$8,">0")=0,99,_xlfn.MINIFS($B$38:$H$38,$K$8:$Q$8,">0")+1)) -> 1 | F47: =MIN(F38,IF(COUNTIF($K$9:$Q$9,">0")=0,99,_xlfn.MINIFS($B$38:$H$38,$K$9:$Q$9,">0")+1)) -> 1 | G47: =MIN(G38,IF(COUNTIF($K$10:$Q$10,">0")=0,99,_xlfn.MINIFS($B$38:$H$38,$K$10:$Q$10,">0")+1)) -> 0 | H47: =MIN(H38,IF(COUNTIF($K$11:$Q$11,">0")=0,99,_xlfn.MINIFS($B$38:$H$38,$K$11:$Q$11,">0")+1)) -> 2
A48: =INDEX(Comps,7) -> TRS | B48: =MIN(B39,IF(COUNTIF($K$5:$Q$5,">0")=0,99,_xlfn.MINIFS($B$39:$H$39,$K$5:$Q$5,">0")+1)) -> 99 | C48: =MIN(C39,IF(COUNTIF($K$6:$Q$6,">0")=0,99,_xlfn.MINIFS($B$39:$H$39,$K$6:$Q$6,">0")+1)) -> 99 | D48: =MIN(D39,IF(COUNTIF($K$7:$Q$7,">0")=0,99,_xlfn.MINIFS($B$39:$H$39,$K$7:$Q$7,">0")+1)) -> 99 | E48: =MIN(E39,IF(COUNTIF($K$8:$Q$8,">0")=0,99,_xlfn.MINIFS($B$39:$H$39,$K$8:$Q$8,">0")+1)) -> 1 | F48: =MIN(F39,IF(COUNTIF($K$9:$Q$9,">0")=0,99,_xlfn.MINIFS($B$39:$H$39,$K$9:$Q$9,">0")+1)) -> 1 | G48: =MIN(G39,IF(COUNTIF($K$10:$Q$10,">0")=0,99,_xlfn.MINIFS($B$39:$H$39,$K$10:$Q$10,">0")+1)) -> 2 | H48: =MIN(H39,IF(COUNTIF($K$11:$Q$11,">0")=0,99,_xlfn.MINIFS($B$39:$H$39,$K$11:$Q$11,">0")+1)) -> 0
A50: Distance using at most 5 arrows | B50: =INDEX(Comps,1) -> MKT | C50: =INDEX(Comps,2) -> GOV | D50: =INDEX(Comps,3) -> MAT | E50: =INDEX(Comps,4) -> IND | F50: =INDEX(Comps,5) -> DIG | G50: =INDEX(Comps,6) -> ENG | H50: =INDEX(Comps,7) -> TRS
A51: =INDEX(Comps,1) -> MKT | B51: =MIN(B42,IF(COUNTIF($K$5:$Q$5,">0")=0,99,_xlfn.MINIFS($B$42:$H$42,$K$5:$Q$5,">0")+1)) -> 0 | C51: =MIN(C42,IF(COUNTIF($K$6:$Q$6,">0")=0,99,_xlfn.MINIFS($B$42:$H$42,$K$6:$Q$6,">0")+1)) -> 99 | D51: =MIN(D42,IF(COUNTIF($K$7:$Q$7,">0")=0,99,_xlfn.MINIFS($B$42:$H$42,$K$7:$Q$7,">0")+1)) -> 1 | E51: =MIN(E42,IF(COUNTIF($K$8:$Q$8,">0")=0,99,_xlfn.MINIFS($B$42:$H$42,$K$8:$Q$8,">0")+1)) -> 1 | F51: =MIN(F42,IF(COUNTIF($K$9:$Q$9,">0")=0,99,_xlfn.MINIFS($B$42:$H$42,$K$9:$Q$9,">0")+1)) -> 1 | G51: =MIN(G42,IF(COUNTIF($K$10:$Q$10,">0")=0,99,_xlfn.MINIFS($B$42:$H$42,$K$10:$Q$10,">0")+1)) -> 2 | H51: =MIN(H42,IF(COUNTIF($K$11:$Q$11,">0")=0,99,_xlfn.MINIFS($B$42:$H$42,$K$11:$Q$11,">0")+1)) -> 2
A52: =INDEX(Comps,2) -> GOV | B52: =MIN(B43,IF(COUNTIF($K$5:$Q$5,">0")=0,99,_xlfn.MINIFS($B$43:$H$43,$K$5:$Q$5,">0")+1)) -> 99 | C52: =MIN(C43,IF(COUNTIF($K$6:$Q$6,">0")=0,99,_xlfn.MINIFS($B$43:$H$43,$K$6:$Q$6,">0")+1)) -> 0 | D52: =MIN(D43,IF(COUNTIF($K$7:$Q$7,">0")=0,99,_xlfn.MINIFS($B$43:$H$43,$K$7:$Q$7,">0")+1)) -> 99 | E52: =MIN(E43,IF(COUNTIF($K$8:$Q$8,">0")=0,99,_xlfn.MINIFS($B$43:$H$43,$K$8:$Q$8,">0")+1)) -> 2 | F52: =MIN(F43,IF(COUNTIF($K$9:$Q$9,">0")=0,99,_xlfn.MINIFS($B$43:$H$43,$K$9:$Q$9,">0")+1)) -> 1 | G52: =MIN(G43,IF(COUNTIF($K$10:$Q$10,">0")=0,99,_xlfn.MINIFS($B$43:$H$43,$K$10:$Q$10,">0")+1)) -> 2 | H52: =MIN(H43,IF(COUNTIF($K$11:$Q$11,">0")=0,99,_xlfn.MINIFS($B$43:$H$43,$K$11:$Q$11,">0")+1)) -> 1
A53: =INDEX(Comps,3) -> MAT | B53: =MIN(B44,IF(COUNTIF($K$5:$Q$5,">0")=0,99,_xlfn.MINIFS($B$44:$H$44,$K$5:$Q$5,">0")+1)) -> 99 | C53: =MIN(C44,IF(COUNTIF($K$6:$Q$6,">0")=0,99,_xlfn.MINIFS($B$44:$H$44,$K$6:$Q$6,">0")+1)) -> 99 | D53: =MIN(D44,IF(COUNTIF($K$7:$Q$7,">0")=0,99,_xlfn.MINIFS($B$44:$H$44,$K$7:$Q$7,">0")+1)) -> 0 | E53: =MIN(E44,IF(COUNTIF($K$8:$Q$8,">0")=0,99,_xlfn.MINIFS($B$44:$H$44,$K$8:$Q$8,">0")+1)) -> 2 | F53: =MIN(F44,IF(COUNTIF($K$9:$Q$9,">0")=0,99,_xlfn.MINIFS($B$44:$H$44,$K$9:$Q$9,">0")+1)) -> 2 | G53: =MIN(G44,IF(COUNTIF($K$10:$Q$10,">0")=0,99,_xlfn.MINIFS($B$44:$H$44,$K$10:$Q$10,">0")+1)) -> 3 | H53: =MIN(H44,IF(COUNTIF($K$11:$Q$11,">0")=0,99,_xlfn.MINIFS($B$44:$H$44,$K$11:$Q$11,">0")+1)) -> 1
A54: =INDEX(Comps,4) -> IND | B54: =MIN(B45,IF(COUNTIF($K$5:$Q$5,">0")=0,99,_xlfn.MINIFS($B$45:$H$45,$K$5:$Q$5,">0")+1)) -> 99 | C54: =MIN(C45,IF(COUNTIF($K$6:$Q$6,">0")=0,99,_xlfn.MINIFS($B$45:$H$45,$K$6:$Q$6,">0")+1)) -> 99 | D54: =MIN(D45,IF(COUNTIF($K$7:$Q$7,">0")=0,99,_xlfn.MINIFS($B$45:$H$45,$K$7:$Q$7,">0")+1)) -> 99 | E54: =MIN(E45,IF(COUNTIF($K$8:$Q$8,">0")=0,99,_xlfn.MINIFS($B$45:$H$45,$K$8:$Q$8,">0")+1)) -> 0 | F54: =MIN(F45,IF(COUNTIF($K$9:$Q$9,">0")=0,99,_xlfn.MINIFS($B$45:$H$45,$K$9:$Q$9,">0")+1)) -> 2 | G54: =MIN(G45,IF(COUNTIF($K$10:$Q$10,">0")=0,99,_xlfn.MINIFS($B$45:$H$45,$K$10:$Q$10,">0")+1)) -> 1 | H54: =MIN(H45,IF(COUNTIF($K$11:$Q$11,">0")=0,99,_xlfn.MINIFS($B$45:$H$45,$K$11:$Q$11,">0")+1)) -> 1
A55: =INDEX(Comps,5) -> DIG | B55: =MIN(B46,IF(COUNTIF($K$5:$Q$5,">0")=0,99,_xlfn.MINIFS($B$46:$H$46,$K$5:$Q$5,">0")+1)) -> 99 | C55: =MIN(C46,IF(COUNTIF($K$6:$Q$6,">0")=0,99,_xlfn.MINIFS($B$46:$H$46,$K$6:$Q$6,">0")+1)) -> 99 | D55: =MIN(D46,IF(COUNTIF($K$7:$Q$7,">0")=0,99,_xlfn.MINIFS($B$46:$H$46,$K$7:$Q$7,">0")+1)) -> 99 | E55: =MIN(E46,IF(COUNTIF($K$8:$Q$8,">0")=0,99,_xlfn.MINIFS($B$46:$H$46,$K$8:$Q$8,">0")+1)) -> 2 | F55: =MIN(F46,IF(COUNTIF($K$9:$Q$9,">0")=0,99,_xlfn.MINIFS($B$46:$H$46,$K$9:$Q$9,">0")+1)) -> 0 | G55: =MIN(G46,IF(COUNTIF($K$10:$Q$10,">0")=0,99,_xlfn.MINIFS($B$46:$H$46,$K$10:$Q$10,">0")+1)) -> 1 | H55: =MIN(H46,IF(COUNTIF($K$11:$Q$11,">0")=0,99,_xlfn.MINIFS($B$46:$H$46,$K$11:$Q$11,">0")+1)) -> 1
A56: =INDEX(Comps,6) -> ENG | B56: =MIN(B47,IF(COUNTIF($K$5:$Q$5,">0")=0,99,_xlfn.MINIFS($B$47:$H$47,$K$5:$Q$5,">0")+1)) -> 99 | C56: =MIN(C47,IF(COUNTIF($K$6:$Q$6,">0")=0,99,_xlfn.MINIFS($B$47:$H$47,$K$6:$Q$6,">0")+1)) -> 99 | D56: =MIN(D47,IF(COUNTIF($K$7:$Q$7,">0")=0,99,_xlfn.MINIFS($B$47:$H$47,$K$7:$Q$7,">0")+1)) -> 99 | E56: =MIN(E47,IF(COUNTIF($K$8:$Q$8,">0")=0,99,_xlfn.MINIFS($B$47:$H$47,$K$8:$Q$8,">0")+1)) -> 1 | F56: =MIN(F47,IF(COUNTIF($K$9:$Q$9,">0")=0,99,_xlfn.MINIFS($B$47:$H$47,$K$9:$Q$9,">0")+1)) -> 1 | G56: =MIN(G47,IF(COUNTIF($K$10:$Q$10,">0")=0,99,_xlfn.MINIFS($B$47:$H$47,$K$10:$Q$10,">0")+1)) -> 0 | H56: =MIN(H47,IF(COUNTIF($K$11:$Q$11,">0")=0,99,_xlfn.MINIFS($B$47:$H$47,$K$11:$Q$11,">0")+1)) -> 2
A57: =INDEX(Comps,7) -> TRS | B57: =MIN(B48,IF(COUNTIF($K$5:$Q$5,">0")=0,99,_xlfn.MINIFS($B$48:$H$48,$K$5:$Q$5,">0")+1)) -> 99 | C57: =MIN(C48,IF(COUNTIF($K$6:$Q$6,">0")=0,99,_xlfn.MINIFS($B$48:$H$48,$K$6:$Q$6,">0")+1)) -> 99 | D57: =MIN(D48,IF(COUNTIF($K$7:$Q$7,">0")=0,99,_xlfn.MINIFS($B$48:$H$48,$K$7:$Q$7,">0")+1)) -> 99 | E57: =MIN(E48,IF(COUNTIF($K$8:$Q$8,">0")=0,99,_xlfn.MINIFS($B$48:$H$48,$K$8:$Q$8,">0")+1)) -> 1 | F57: =MIN(F48,IF(COUNTIF($K$9:$Q$9,">0")=0,99,_xlfn.MINIFS($B$48:$H$48,$K$9:$Q$9,">0")+1)) -> 1 | G57: =MIN(G48,IF(COUNTIF($K$10:$Q$10,">0")=0,99,_xlfn.MINIFS($B$48:$H$48,$K$10:$Q$10,">0")+1)) -> 2 | H57: =MIN(H48,IF(COUNTIF($K$11:$Q$11,">0")=0,99,_xlfn.MINIFS($B$48:$H$48,$K$11:$Q$11,">0")+1)) -> 0
A59: Distance using at most 6 arrows | B59: =INDEX(Comps,1) -> MKT | C59: =INDEX(Comps,2) -> GOV | D59: =INDEX(Comps,3) -> MAT | E59: =INDEX(Comps,4) -> IND | F59: =INDEX(Comps,5) -> DIG | G59: =INDEX(Comps,6) -> ENG | H59: =INDEX(Comps,7) -> TRS
A60: =INDEX(Comps,1) -> MKT | B60: =MIN(B51,IF(COUNTIF($K$5:$Q$5,">0")=0,99,_xlfn.MINIFS($B$51:$H$51,$K$5:$Q$5,">0")+1)) -> 0 | C60: =MIN(C51,IF(COUNTIF($K$6:$Q$6,">0")=0,99,_xlfn.MINIFS($B$51:$H$51,$K$6:$Q$6,">0")+1)) -> 99 | D60: =MIN(D51,IF(COUNTIF($K$7:$Q$7,">0")=0,99,_xlfn.MINIFS($B$51:$H$51,$K$7:$Q$7,">0")+1)) -> 1 | E60: =MIN(E51,IF(COUNTIF($K$8:$Q$8,">0")=0,99,_xlfn.MINIFS($B$51:$H$51,$K$8:$Q$8,">0")+1)) -> 1 | F60: =MIN(F51,IF(COUNTIF($K$9:$Q$9,">0")=0,99,_xlfn.MINIFS($B$51:$H$51,$K$9:$Q$9,">0")+1)) -> 1 | G60: =MIN(G51,IF(COUNTIF($K$10:$Q$10,">0")=0,99,_xlfn.MINIFS($B$51:$H$51,$K$10:$Q$10,">0")+1)) -> 2 | H60: =MIN(H51,IF(COUNTIF($K$11:$Q$11,">0")=0,99,_xlfn.MINIFS($B$51:$H$51,$K$11:$Q$11,">0")+1)) -> 2
A61: =INDEX(Comps,2) -> GOV | B61: =MIN(B52,IF(COUNTIF($K$5:$Q$5,">0")=0,99,_xlfn.MINIFS($B$52:$H$52,$K$5:$Q$5,">0")+1)) -> 99 | C61: =MIN(C52,IF(COUNTIF($K$6:$Q$6,">0")=0,99,_xlfn.MINIFS($B$52:$H$52,$K$6:$Q$6,">0")+1)) -> 0 | D61: =MIN(D52,IF(COUNTIF($K$7:$Q$7,">0")=0,99,_xlfn.MINIFS($B$52:$H$52,$K$7:$Q$7,">0")+1)) -> 99 | E61: =MIN(E52,IF(COUNTIF($K$8:$Q$8,">0")=0,99,_xlfn.MINIFS($B$52:$H$52,$K$8:$Q$8,">0")+1)) -> 2 | F61: =MIN(F52,IF(COUNTIF($K$9:$Q$9,">0")=0,99,_xlfn.MINIFS($B$52:$H$52,$K$9:$Q$9,">0")+1)) -> 1 | G61: =MIN(G52,IF(COUNTIF($K$10:$Q$10,">0")=0,99,_xlfn.MINIFS($B$52:$H$52,$K$10:$Q$10,">0")+1)) -> 2 | H61: =MIN(H52,IF(COUNTIF($K$11:$Q$11,">0")=0,99,_xlfn.MINIFS($B$52:$H$52,$K$11:$Q$11,">0")+1)) -> 1
A62: =INDEX(Comps,3) -> MAT | B62: =MIN(B53,IF(COUNTIF($K$5:$Q$5,">0")=0,99,_xlfn.MINIFS($B$53:$H$53,$K$5:$Q$5,">0")+1)) -> 99 | C62: =MIN(C53,IF(COUNTIF($K$6:$Q$6,">0")=0,99,_xlfn.MINIFS($B$53:$H$53,$K$6:$Q$6,">0")+1)) -> 99 | D62: =MIN(D53,IF(COUNTIF($K$7:$Q$7,">0")=0,99,_xlfn.MINIFS($B$53:$H$53,$K$7:$Q$7,">0")+1)) -> 0 | E62: =MIN(E53,IF(COUNTIF($K$8:$Q$8,">0")=0,99,_xlfn.MINIFS($B$53:$H$53,$K$8:$Q$8,">0")+1)) -> 2 | F62: =MIN(F53,IF(COUNTIF($K$9:$Q$9,">0")=0,99,_xlfn.MINIFS($B$53:$H$53,$K$9:$Q$9,">0")+1)) -> 2 | G62: =MIN(G53,IF(COUNTIF($K$10:$Q$10,">0")=0,99,_xlfn.MINIFS($B$53:$H$53,$K$10:$Q$10,">0")+1)) -> 3 | H62: =MIN(H53,IF(COUNTIF($K$11:$Q$11,">0")=0,99,_xlfn.MINIFS($B$53:$H$53,$K$11:$Q$11,">0")+1)) -> 1
A63: =INDEX(Comps,4) -> IND | B63: =MIN(B54,IF(COUNTIF($K$5:$Q$5,">0")=0,99,_xlfn.MINIFS($B$54:$H$54,$K$5:$Q$5,">0")+1)) -> 99 | C63: =MIN(C54,IF(COUNTIF($K$6:$Q$6,">0")=0,99,_xlfn.MINIFS($B$54:$H$54,$K$6:$Q$6,">0")+1)) -> 99 | D63: =MIN(D54,IF(COUNTIF($K$7:$Q$7,">0")=0,99,_xlfn.MINIFS($B$54:$H$54,$K$7:$Q$7,">0")+1)) -> 99 | E63: =MIN(E54,IF(COUNTIF($K$8:$Q$8,">0")=0,99,_xlfn.MINIFS($B$54:$H$54,$K$8:$Q$8,">0")+1)) -> 0 | F63: =MIN(F54,IF(COUNTIF($K$9:$Q$9,">0")=0,99,_xlfn.MINIFS($B$54:$H$54,$K$9:$Q$9,">0")+1)) -> 2 | G63: =MIN(G54,IF(COUNTIF($K$10:$Q$10,">0")=0,99,_xlfn.MINIFS($B$54:$H$54,$K$10:$Q$10,">0")+1)) -> 1 | H63: =MIN(H54,IF(COUNTIF($K$11:$Q$11,">0")=0,99,_xlfn.MINIFS($B$54:$H$54,$K$11:$Q$11,">0")+1)) -> 1
A64: =INDEX(Comps,5) -> DIG | B64: =MIN(B55,IF(COUNTIF($K$5:$Q$5,">0")=0,99,_xlfn.MINIFS($B$55:$H$55,$K$5:$Q$5,">0")+1)) -> 99 | C64: =MIN(C55,IF(COUNTIF($K$6:$Q$6,">0")=0,99,_xlfn.MINIFS($B$55:$H$55,$K$6:$Q$6,">0")+1)) -> 99 | D64: =MIN(D55,IF(COUNTIF($K$7:$Q$7,">0")=0,99,_xlfn.MINIFS($B$55:$H$55,$K$7:$Q$7,">0")+1)) -> 99 | E64: =MIN(E55,IF(COUNTIF($K$8:$Q$8,">0")=0,99,_xlfn.MINIFS($B$55:$H$55,$K$8:$Q$8,">0")+1)) -> 2 | F64: =MIN(F55,IF(COUNTIF($K$9:$Q$9,">0")=0,99,_xlfn.MINIFS($B$55:$H$55,$K$9:$Q$9,">0")+1)) -> 0 | G64: =MIN(G55,IF(COUNTIF($K$10:$Q$10,">0")=0,99,_xlfn.MINIFS($B$55:$H$55,$K$10:$Q$10,">0")+1)) -> 1 | H64: =MIN(H55,IF(COUNTIF($K$11:$Q$11,">0")=0,99,_xlfn.MINIFS($B$55:$H$55,$K$11:$Q$11,">0")+1)) -> 1
A65: =INDEX(Comps,6) -> ENG | B65: =MIN(B56,IF(COUNTIF($K$5:$Q$5,">0")=0,99,_xlfn.MINIFS($B$56:$H$56,$K$5:$Q$5,">0")+1)) -> 99 | C65: =MIN(C56,IF(COUNTIF($K$6:$Q$6,">0")=0,99,_xlfn.MINIFS($B$56:$H$56,$K$6:$Q$6,">0")+1)) -> 99 | D65: =MIN(D56,IF(COUNTIF($K$7:$Q$7,">0")=0,99,_xlfn.MINIFS($B$56:$H$56,$K$7:$Q$7,">0")+1)) -> 99 | E65: =MIN(E56,IF(COUNTIF($K$8:$Q$8,">0")=0,99,_xlfn.MINIFS($B$56:$H$56,$K$8:$Q$8,">0")+1)) -> 1 | F65: =MIN(F56,IF(COUNTIF($K$9:$Q$9,">0")=0,99,_xlfn.MINIFS($B$56:$H$56,$K$9:$Q$9,">0")+1)) -> 1 | G65: =MIN(G56,IF(COUNTIF($K$10:$Q$10,">0")=0,99,_xlfn.MINIFS($B$56:$H$56,$K$10:$Q$10,">0")+1)) -> 0 | H65: =MIN(H56,IF(COUNTIF($K$11:$Q$11,">0")=0,99,_xlfn.MINIFS($B$56:$H$56,$K$11:$Q$11,">0")+1)) -> 2
A66: =INDEX(Comps,7) -> TRS | B66: =MIN(B57,IF(COUNTIF($K$5:$Q$5,">0")=0,99,_xlfn.MINIFS($B$57:$H$57,$K$5:$Q$5,">0")+1)) -> 99 | C66: =MIN(C57,IF(COUNTIF($K$6:$Q$6,">0")=0,99,_xlfn.MINIFS($B$57:$H$57,$K$6:$Q$6,">0")+1)) -> 99 | D66: =MIN(D57,IF(COUNTIF($K$7:$Q$7,">0")=0,99,_xlfn.MINIFS($B$57:$H$57,$K$7:$Q$7,">0")+1)) -> 99 | E66: =MIN(E57,IF(COUNTIF($K$8:$Q$8,">0")=0,99,_xlfn.MINIFS($B$57:$H$57,$K$8:$Q$8,">0")+1)) -> 1 | F66: =MIN(F57,IF(COUNTIF($K$9:$Q$9,">0")=0,99,_xlfn.MINIFS($B$57:$H$57,$K$9:$Q$9,">0")+1)) -> 1 | G66: =MIN(G57,IF(COUNTIF($K$10:$Q$10,">0")=0,99,_xlfn.MINIFS($B$57:$H$57,$K$10:$Q$10,">0")+1)) -> 2 | H66: =MIN(H57,IF(COUNTIF($K$11:$Q$11,">0")=0,99,_xlfn.MINIFS($B$57:$H$57,$K$11:$Q$11,">0")+1)) -> 0
A68: Distance (final): quarters, 99 = never | B68: =INDEX(Comps,1) -> MKT | C68: =INDEX(Comps,2) -> GOV | D68: =INDEX(Comps,3) -> MAT | E68: =INDEX(Comps,4) -> IND | F68: =INDEX(Comps,5) -> DIG | G68: =INDEX(Comps,6) -> ENG | H68: =INDEX(Comps,7) -> TRS
A69: =INDEX(Comps,1) -> MKT | B69: =MIN(B60,IF(COUNTIF($K$5:$Q$5,">0")=0,99,_xlfn.MINIFS($B$60:$H$60,$K$5:$Q$5,">0")+1)) -> 0 | C69: =MIN(C60,IF(COUNTIF($K$6:$Q$6,">0")=0,99,_xlfn.MINIFS($B$60:$H$60,$K$6:$Q$6,">0")+1)) -> 99 | D69: =MIN(D60,IF(COUNTIF($K$7:$Q$7,">0")=0,99,_xlfn.MINIFS($B$60:$H$60,$K$7:$Q$7,">0")+1)) -> 1 | E69: =MIN(E60,IF(COUNTIF($K$8:$Q$8,">0")=0,99,_xlfn.MINIFS($B$60:$H$60,$K$8:$Q$8,">0")+1)) -> 1 | F69: =MIN(F60,IF(COUNTIF($K$9:$Q$9,">0")=0,99,_xlfn.MINIFS($B$60:$H$60,$K$9:$Q$9,">0")+1)) -> 1 | G69: =MIN(G60,IF(COUNTIF($K$10:$Q$10,">0")=0,99,_xlfn.MINIFS($B$60:$H$60,$K$10:$Q$10,">0")+1)) -> 2 | H69: =MIN(H60,IF(COUNTIF($K$11:$Q$11,">0")=0,99,_xlfn.MINIFS($B$60:$H$60,$K$11:$Q$11,">0")+1)) -> 2
A70: =INDEX(Comps,2) -> GOV | B70: =MIN(B61,IF(COUNTIF($K$5:$Q$5,">0")=0,99,_xlfn.MINIFS($B$61:$H$61,$K$5:$Q$5,">0")+1)) -> 99 | C70: =MIN(C61,IF(COUNTIF($K$6:$Q$6,">0")=0,99,_xlfn.MINIFS($B$61:$H$61,$K$6:$Q$6,">0")+1)) -> 0 | D70: =MIN(D61,IF(COUNTIF($K$7:$Q$7,">0")=0,99,_xlfn.MINIFS($B$61:$H$61,$K$7:$Q$7,">0")+1)) -> 99 | E70: =MIN(E61,IF(COUNTIF($K$8:$Q$8,">0")=0,99,_xlfn.MINIFS($B$61:$H$61,$K$8:$Q$8,">0")+1)) -> 2 | F70: =MIN(F61,IF(COUNTIF($K$9:$Q$9,">0")=0,99,_xlfn.MINIFS($B$61:$H$61,$K$9:$Q$9,">0")+1)) -> 1 | G70: =MIN(G61,IF(COUNTIF($K$10:$Q$10,">0")=0,99,_xlfn.MINIFS($B$61:$H$61,$K$10:$Q$10,">0")+1)) -> 2 | H70: =MIN(H61,IF(COUNTIF($K$11:$Q$11,">0")=0,99,_xlfn.MINIFS($B$61:$H$61,$K$11:$Q$11,">0")+1)) -> 1
A71: =INDEX(Comps,3) -> MAT | B71: =MIN(B62,IF(COUNTIF($K$5:$Q$5,">0")=0,99,_xlfn.MINIFS($B$62:$H$62,$K$5:$Q$5,">0")+1)) -> 99 | C71: =MIN(C62,IF(COUNTIF($K$6:$Q$6,">0")=0,99,_xlfn.MINIFS($B$62:$H$62,$K$6:$Q$6,">0")+1)) -> 99 | D71: =MIN(D62,IF(COUNTIF($K$7:$Q$7,">0")=0,99,_xlfn.MINIFS($B$62:$H$62,$K$7:$Q$7,">0")+1)) -> 0 | E71: =MIN(E62,IF(COUNTIF($K$8:$Q$8,">0")=0,99,_xlfn.MINIFS($B$62:$H$62,$K$8:$Q$8,">0")+1)) -> 2 | F71: =MIN(F62,IF(COUNTIF($K$9:$Q$9,">0")=0,99,_xlfn.MINIFS($B$62:$H$62,$K$9:$Q$9,">0")+1)) -> 2 | G71: =MIN(G62,IF(COUNTIF($K$10:$Q$10,">0")=0,99,_xlfn.MINIFS($B$62:$H$62,$K$10:$Q$10,">0")+1)) -> 3 | H71: =MIN(H62,IF(COUNTIF($K$11:$Q$11,">0")=0,99,_xlfn.MINIFS($B$62:$H$62,$K$11:$Q$11,">0")+1)) -> 1
A72: =INDEX(Comps,4) -> IND | B72: =MIN(B63,IF(COUNTIF($K$5:$Q$5,">0")=0,99,_xlfn.MINIFS($B$63:$H$63,$K$5:$Q$5,">0")+1)) -> 99 | C72: =MIN(C63,IF(COUNTIF($K$6:$Q$6,">0")=0,99,_xlfn.MINIFS($B$63:$H$63,$K$6:$Q$6,">0")+1)) -> 99 | D72: =MIN(D63,IF(COUNTIF($K$7:$Q$7,">0")=0,99,_xlfn.MINIFS($B$63:$H$63,$K$7:$Q$7,">0")+1)) -> 99 | E72: =MIN(E63,IF(COUNTIF($K$8:$Q$8,">0")=0,99,_xlfn.MINIFS($B$63:$H$63,$K$8:$Q$8,">0")+1)) -> 0 | F72: =MIN(F63,IF(COUNTIF($K$9:$Q$9,">0")=0,99,_xlfn.MINIFS($B$63:$H$63,$K$9:$Q$9,">0")+1)) -> 2 | G72: =MIN(G63,IF(COUNTIF($K$10:$Q$10,">0")=0,99,_xlfn.MINIFS($B$63:$H$63,$K$10:$Q$10,">0")+1)) -> 1 | H72: =MIN(H63,IF(COUNTIF($K$11:$Q$11,">0")=0,99,_xlfn.MINIFS($B$63:$H$63,$K$11:$Q$11,">0")+1)) -> 1
A73: =INDEX(Comps,5) -> DIG | B73: =MIN(B64,IF(COUNTIF($K$5:$Q$5,">0")=0,99,_xlfn.MINIFS($B$64:$H$64,$K$5:$Q$5,">0")+1)) -> 99 | C73: =MIN(C64,IF(COUNTIF($K$6:$Q$6,">0")=0,99,_xlfn.MINIFS($B$64:$H$64,$K$6:$Q$6,">0")+1)) -> 99 | D73: =MIN(D64,IF(COUNTIF($K$7:$Q$7,">0")=0,99,_xlfn.MINIFS($B$64:$H$64,$K$7:$Q$7,">0")+1)) -> 99 | E73: =MIN(E64,IF(COUNTIF($K$8:$Q$8,">0")=0,99,_xlfn.MINIFS($B$64:$H$64,$K$8:$Q$8,">0")+1)) -> 2 | F73: =MIN(F64,IF(COUNTIF($K$9:$Q$9,">0")=0,99,_xlfn.MINIFS($B$64:$H$64,$K$9:$Q$9,">0")+1)) -> 0 | G73: =MIN(G64,IF(COUNTIF($K$10:$Q$10,">0")=0,99,_xlfn.MINIFS($B$64:$H$64,$K$10:$Q$10,">0")+1)) -> 1 | H73: =MIN(H64,IF(COUNTIF($K$11:$Q$11,">0")=0,99,_xlfn.MINIFS($B$64:$H$64,$K$11:$Q$11,">0")+1)) -> 1
A74: =INDEX(Comps,6) -> ENG | B74: =MIN(B65,IF(COUNTIF($K$5:$Q$5,">0")=0,99,_xlfn.MINIFS($B$65:$H$65,$K$5:$Q$5,">0")+1)) -> 99 | C74: =MIN(C65,IF(COUNTIF($K$6:$Q$6,">0")=0,99,_xlfn.MINIFS($B$65:$H$65,$K$6:$Q$6,">0")+1)) -> 99 | D74: =MIN(D65,IF(COUNTIF($K$7:$Q$7,">0")=0,99,_xlfn.MINIFS($B$65:$H$65,$K$7:$Q$7,">0")+1)) -> 99 | E74: =MIN(E65,IF(COUNTIF($K$8:$Q$8,">0")=0,99,_xlfn.MINIFS($B$65:$H$65,$K$8:$Q$8,">0")+1)) -> 1 | F74: =MIN(F65,IF(COUNTIF($K$9:$Q$9,">0")=0,99,_xlfn.MINIFS($B$65:$H$65,$K$9:$Q$9,">0")+1)) -> 1 | G74: =MIN(G65,IF(COUNTIF($K$10:$Q$10,">0")=0,99,_xlfn.MINIFS($B$65:$H$65,$K$10:$Q$10,">0")+1)) -> 0 | H74: =MIN(H65,IF(COUNTIF($K$11:$Q$11,">0")=0,99,_xlfn.MINIFS($B$65:$H$65,$K$11:$Q$11,">0")+1)) -> 2
A75: =INDEX(Comps,7) -> TRS | B75: =MIN(B66,IF(COUNTIF($K$5:$Q$5,">0")=0,99,_xlfn.MINIFS($B$66:$H$66,$K$5:$Q$5,">0")+1)) -> 99 | C75: =MIN(C66,IF(COUNTIF($K$6:$Q$6,">0")=0,99,_xlfn.MINIFS($B$66:$H$66,$K$6:$Q$6,">0")+1)) -> 99 | D75: =MIN(D66,IF(COUNTIF($K$7:$Q$7,">0")=0,99,_xlfn.MINIFS($B$66:$H$66,$K$7:$Q$7,">0")+1)) -> 99 | E75: =MIN(E66,IF(COUNTIF($K$8:$Q$8,">0")=0,99,_xlfn.MINIFS($B$66:$H$66,$K$8:$Q$8,">0")+1)) -> 1 | F75: =MIN(F66,IF(COUNTIF($K$9:$Q$9,">0")=0,99,_xlfn.MINIFS($B$66:$H$66,$K$9:$Q$9,">0")+1)) -> 1 | G75: =MIN(G66,IF(COUNTIF($K$10:$Q$10,">0")=0,99,_xlfn.MINIFS($B$66:$H$66,$K$10:$Q$10,">0")+1)) -> 2 | H75: =MIN(H66,IF(COUNTIF($K$11:$Q$11,">0")=0,99,_xlfn.MINIFS($B$66:$H$66,$K$11:$Q$11,">0")+1)) -> 0
A78: Component | B78: Quarters from the digital program (Digital, engineering) | C78: Quarters from a demand shock (market) | D78: Program | E78: Shock | H78: Ledger clocks | I78: Quarters | J78: Book
A79: =INDEX(Comps,1) -> MKT | B79: =MIN(B73,B74) -> 99 | C79: =B69 -> 0 | D79: =IF(B79>=99,"never",B79) -> never | E79: =IF(C79>=99,"never",C79) -> 0 | H79: Program: treasury | I79: =INDEX($B$79:$B$85,MATCH("TRS",$A$79:$A$85,0)) -> 1 | J79: Online Appendix 13.B.3: one quarter
A80: =INDEX(Comps,2) -> GOV | B80: =MIN(C73,C74) -> 99 | C80: =C69 -> 99 | D80: =IF(B80>=99,"never",B80) -> never | E80: =IF(C80>=99,"never",C80) -> never | H80: Program: Industrial Systems | I80: =INDEX($B$79:$B$85,MATCH("IND",$A$79:$A$85,0)) -> 1 | J80: one quarter
A81: =INDEX(Comps,3) -> MAT | B81: =MIN(D73,D74) -> 99 | C81: =D69 -> 1 | D81: =IF(B81>=99,"never",B81) -> never | E81: =IF(C81>=99,"never",C81) -> 1 | H81: Program: components never reached | I81: =COUNTIF($B$79:$B$85,">=99") -> 3 | J81: Materials, the market, governance
A82: =INDEX(Comps,4) -> IND | B82: =MIN(E73,E74) -> 1 | C82: =E69 -> 1 | D82: =IF(B82>=99,"never",B82) -> 1 | E82: =IF(C82>=99,"never",C82) -> 1 | H82: Demand shock: the slowest division | I82: =MAX(INDEX($C$79:$C$85,MATCH("IND",$A$79:$A$85,0)),INDEX($C$79:$C$85,MATCH("DIG",$A$79:$A$85,0)),INDEX($C$79:$C$85,MATCH("MAT",$A$79:$A$85,0))) -> 1 | J82: the divisions after one quarter
A83: =INDEX(Comps,5) -> DIG | B83: =MIN(F73,F74) -> 0 | C83: =F69 -> 1 | D83: =IF(B83>=99,"never",B83) -> 0 | E83: =IF(C83>=99,"never",C83) -> 1 | H83: Demand shock: engineering | I83: =INDEX($C$79:$C$85,MATCH("ENG",$A$79:$A$85,0)) -> 2 | J83: two quarters
A84: =INDEX(Comps,6) -> ENG | B84: =MIN(G73,G74) -> 0 | C84: =G69 -> 2 | D84: =IF(B84>=99,"never",B84) -> 0 | E84: =IF(C84>=99,"never",C84) -> 2 | H84: Demand shock: treasury | I84: =INDEX($C$79:$C$85,MATCH("TRS",$A$79:$A$85,0)) -> 2 | J84: two quarters
A85: =INDEX(Comps,7) -> TRS | B85: =MIN(H73,H74) -> 1 | C85: =H69 -> 2 | D85: =IF(B85>=99,"never",B85) -> 1 | E85: =IF(C85>=99,"never",C85) -> 2 | H85: Digital alone: Industrial Systems | I85: =E73 -> 2 | J85: Table 11.4's floor of 2 for P_T -> P_O
A88: Ledger | B88: Readout (Tables 9.1, 9.3, 11.4, 12.2) | C88: Support 1 | D88: Support 2 | E88: Support 3 | F88: Program clock | G88: Shock clock | H88: Program | I88: Shock | J88: Engine: program | K88: Engine: shock | L88: Match
A89: capital | B89: liquidity (financial capital) | C89: TRS | F89: =MIN(IF(C89="",99,INDEX($B$79:$B$85,MATCH(C89,$A$79:$A$85,0))),IF(D89="",99,INDEX($B$79:$B$85,MATCH(D89,$A$79:$A$85,0))),IF(E89="",99,INDEX($B$79:$B$85,MATCH(E89,$A$79:$A$85,0)))) -> 1 | G89: =MIN(IF(C89="",99,INDEX($C$79:$C$85,MATCH(C89,$A$79:$A$85,0))),IF(D89="",99,INDEX($C$79:$C$85,MATCH(D89,$A$79:$A$85,0))),IF(E89="",99,INDEX($C$79:$C$85,MATCH(E89,$A$79:$A$85,0)))) -> 2 | H89: =IF(F89>=99,"never",F89) -> 1 | I89: =IF(G89>=99,"never",G89) -> 2 | J89: 1 | K89: 2 | L89: =IF(AND(F89=J89,G89=K89),1,0) -> 1
A90: capital | B90: net leverage (financial capital) | C90: TRS | F90: =MIN(IF(C90="",99,INDEX($B$79:$B$85,MATCH(C90,$A$79:$A$85,0))),IF(D90="",99,INDEX($B$79:$B$85,MATCH(D90,$A$79:$A$85,0))),IF(E90="",99,INDEX($B$79:$B$85,MATCH(E90,$A$79:$A$85,0)))) -> 1 | G90: =MIN(IF(C90="",99,INDEX($C$79:$C$85,MATCH(C90,$A$79:$A$85,0))),IF(D90="",99,INDEX($C$79:$C$85,MATCH(D90,$A$79:$A$85,0))),IF(E90="",99,INDEX($C$79:$C$85,MATCH(E90,$A$79:$A$85,0)))) -> 2 | H90: =IF(F90>=99,"never",F90) -> 1 | I90: =IF(G90>=99,"never",G90) -> 2 | J90: 1 | K90: 2 | L90: =IF(AND(F90=J90,G90=K90),1,0) -> 1
A91: capital | B91: workforce capability (human capital) | C91: ENG | F91: =MIN(IF(C91="",99,INDEX($B$79:$B$85,MATCH(C91,$A$79:$A$85,0))),IF(D91="",99,INDEX($B$79:$B$85,MATCH(D91,$A$79:$A$85,0))),IF(E91="",99,INDEX($B$79:$B$85,MATCH(E91,$A$79:$A$85,0)))) -> 0 | G91: =MIN(IF(C91="",99,INDEX($C$79:$C$85,MATCH(C91,$A$79:$A$85,0))),IF(D91="",99,INDEX($C$79:$C$85,MATCH(D91,$A$79:$A$85,0))),IF(E91="",99,INDEX($C$79:$C$85,MATCH(E91,$A$79:$A$85,0)))) -> 2 | H91: =IF(F91>=99,"never",F91) -> 0 | I91: =IF(G91>=99,"never",G91) -> 2 | J91: 0 | K91: 2 | L91: =IF(AND(F91=J91,G91=K91),1,0) -> 1
A92: performance | B92: P_F financial | C92: TRS | F92: =MIN(IF(C92="",99,INDEX($B$79:$B$85,MATCH(C92,$A$79:$A$85,0))),IF(D92="",99,INDEX($B$79:$B$85,MATCH(D92,$A$79:$A$85,0))),IF(E92="",99,INDEX($B$79:$B$85,MATCH(E92,$A$79:$A$85,0)))) -> 1 | G92: =MIN(IF(C92="",99,INDEX($C$79:$C$85,MATCH(C92,$A$79:$A$85,0))),IF(D92="",99,INDEX($C$79:$C$85,MATCH(D92,$A$79:$A$85,0))),IF(E92="",99,INDEX($C$79:$C$85,MATCH(E92,$A$79:$A$85,0)))) -> 2 | H92: =IF(F92>=99,"never",F92) -> 1 | I92: =IF(G92>=99,"never",G92) -> 2 | J92: 1 | K92: 2 | L92: =IF(AND(F92=J92,G92=K92),1,0) -> 1
A93: performance | B93: P_O operational | C93: IND | D93: MAT | F93: =MIN(IF(C93="",99,INDEX($B$79:$B$85,MATCH(C93,$A$79:$A$85,0))),IF(D93="",99,INDEX($B$79:$B$85,MATCH(D93,$A$79:$A$85,0))),IF(E93="",99,INDEX($B$79:$B$85,MATCH(E93,$A$79:$A$85,0)))) -> 1 | G93: =MIN(IF(C93="",99,INDEX($C$79:$C$85,MATCH(C93,$A$79:$A$85,0))),IF(D93="",99,INDEX($C$79:$C$85,MATCH(D93,$A$79:$A$85,0))),IF(E93="",99,INDEX($C$79:$C$85,MATCH(E93,$A$79:$A$85,0)))) -> 1 | H93: =IF(F93>=99,"never",F93) -> 1 | I93: =IF(G93>=99,"never",G93) -> 1 | J93: 1 | K93: 1 | L93: =IF(AND(F93=J93,G93=K93),1,0) -> 1
A94: performance | B94: P_S strategic | C94: IND | D94: DIG | E94: MAT | F94: =MIN(IF(C94="",99,INDEX($B$79:$B$85,MATCH(C94,$A$79:$A$85,0))),IF(D94="",99,INDEX($B$79:$B$85,MATCH(D94,$A$79:$A$85,0))),IF(E94="",99,INDEX($B$79:$B$85,MATCH(E94,$A$79:$A$85,0)))) -> 0 | G94: =MIN(IF(C94="",99,INDEX($C$79:$C$85,MATCH(C94,$A$79:$A$85,0))),IF(D94="",99,INDEX($C$79:$C$85,MATCH(D94,$A$79:$A$85,0))),IF(E94="",99,INDEX($C$79:$C$85,MATCH(E94,$A$79:$A$85,0)))) -> 1 | H94: =IF(F94>=99,"never",F94) -> 0 | I94: =IF(G94>=99,"never",G94) -> 1 | J94: 0 | K94: 1 | L94: =IF(AND(F94=J94,G94=K94),1,0) -> 1
A95: performance | B95: P_T technological | C95: DIG | F95: =MIN(IF(C95="",99,INDEX($B$79:$B$85,MATCH(C95,$A$79:$A$85,0))),IF(D95="",99,INDEX($B$79:$B$85,MATCH(D95,$A$79:$A$85,0))),IF(E95="",99,INDEX($B$79:$B$85,MATCH(E95,$A$79:$A$85,0)))) -> 0 | G95: =MIN(IF(C95="",99,INDEX($C$79:$C$85,MATCH(C95,$A$79:$A$85,0))),IF(D95="",99,INDEX($C$79:$C$85,MATCH(D95,$A$79:$A$85,0))),IF(E95="",99,INDEX($C$79:$C$85,MATCH(E95,$A$79:$A$85,0)))) -> 1 | H95: =IF(F95>=99,"never",F95) -> 0 | I95: =IF(G95>=99,"never",G95) -> 1 | J95: 0 | K95: 1 | L95: =IF(AND(F95=J95,G95=K95),1,0) -> 1
A96: performance | B96: P_I innovation | C96: DIG | D96: ENG | F96: =MIN(IF(C96="",99,INDEX($B$79:$B$85,MATCH(C96,$A$79:$A$85,0))),IF(D96="",99,INDEX($B$79:$B$85,MATCH(D96,$A$79:$A$85,0))),IF(E96="",99,INDEX($B$79:$B$85,MATCH(E96,$A$79:$A$85,0)))) -> 0 | G96: =MIN(IF(C96="",99,INDEX($C$79:$C$85,MATCH(C96,$A$79:$A$85,0))),IF(D96="",99,INDEX($C$79:$C$85,MATCH(D96,$A$79:$A$85,0))),IF(E96="",99,INDEX($C$79:$C$85,MATCH(E96,$A$79:$A$85,0)))) -> 1 | H96: =IF(F96>=99,"never",F96) -> 0 | I96: =IF(G96>=99,"never",G96) -> 1 | J96: 0 | K96: 1 | L96: =IF(AND(F96=J96,G96=K96),1,0) -> 1
A97: performance | B97: P_R resilience | C97: TRS | F97: =MIN(IF(C97="",99,INDEX($B$79:$B$85,MATCH(C97,$A$79:$A$85,0))),IF(D97="",99,INDEX($B$79:$B$85,MATCH(D97,$A$79:$A$85,0))),IF(E97="",99,INDEX($B$79:$B$85,MATCH(E97,$A$79:$A$85,0)))) -> 1 | G97: =MIN(IF(C97="",99,INDEX($C$79:$C$85,MATCH(C97,$A$79:$A$85,0))),IF(D97="",99,INDEX($C$79:$C$85,MATCH(D97,$A$79:$A$85,0))),IF(E97="",99,INDEX($C$79:$C$85,MATCH(E97,$A$79:$A$85,0)))) -> 2 | H97: =IF(F97>=99,"never",F97) -> 1 | I97: =IF(G97>=99,"never",G97) -> 2 | J97: 1 | K97: 2 | L97: =IF(AND(F97=J97,G97=K97),1,0) -> 1
A98: risk | B98: R_F financial: floor, covenant | C98: TRS | F98: =MIN(IF(C98="",99,INDEX($B$79:$B$85,MATCH(C98,$A$79:$A$85,0))),IF(D98="",99,INDEX($B$79:$B$85,MATCH(D98,$A$79:$A$85,0))),IF(E98="",99,INDEX($B$79:$B$85,MATCH(E98,$A$79:$A$85,0)))) -> 1 | G98: =MIN(IF(C98="",99,INDEX($C$79:$C$85,MATCH(C98,$A$79:$A$85,0))),IF(D98="",99,INDEX($C$79:$C$85,MATCH(D98,$A$79:$A$85,0))),IF(E98="",99,INDEX($C$79:$C$85,MATCH(E98,$A$79:$A$85,0)))) -> 2 | H98: =IF(F98>=99,"never",F98) -> 1 | I98: =IF(G98>=99,"never",G98) -> 2 | J98: 1 | K98: 2 | L98: =IF(AND(F98=J98,G98=K98),1,0) -> 1
A99: risk | B99: R_O operational | C99: IND | D99: MAT | F99: =MIN(IF(C99="",99,INDEX($B$79:$B$85,MATCH(C99,$A$79:$A$85,0))),IF(D99="",99,INDEX($B$79:$B$85,MATCH(D99,$A$79:$A$85,0))),IF(E99="",99,INDEX($B$79:$B$85,MATCH(E99,$A$79:$A$85,0)))) -> 1 | G99: =MIN(IF(C99="",99,INDEX($C$79:$C$85,MATCH(C99,$A$79:$A$85,0))),IF(D99="",99,INDEX($C$79:$C$85,MATCH(D99,$A$79:$A$85,0))),IF(E99="",99,INDEX($C$79:$C$85,MATCH(E99,$A$79:$A$85,0)))) -> 1 | H99: =IF(F99>=99,"never",F99) -> 1 | I99: =IF(G99>=99,"never",G99) -> 1 | J99: 1 | K99: 1 | L99: =IF(AND(F99=J99,G99=K99),1,0) -> 1
A100: risk | B100: R_S strategic | C100: MKT | D100: GOV | F100: =MIN(IF(C100="",99,INDEX($B$79:$B$85,MATCH(C100,$A$79:$A$85,0))),IF(D100="",99,INDEX($B$79:$B$85,MATCH(D100,$A$79:$A$85,0))),IF(E100="",99,INDEX($B$79:$B$85,MATCH(E100,$A$79:$A$85,0)))) -> 99 | G100: =MIN(IF(C100="",99,INDEX($C$79:$C$85,MATCH(C100,$A$79:$A$85,0))),IF(D100="",99,INDEX($C$79:$C$85,MATCH(D100,$A$79:$A$85,0))),IF(E100="",99,INDEX($C$79:$C$85,MATCH(E100,$A$79:$A$85,0)))) -> 0 | H100: =IF(F100>=99,"never",F100) -> never | I100: =IF(G100>=99,"never",G100) -> 0 | J100: 99 | K100: 0 | L100: =IF(AND(F100=J100,G100=K100),1,0) -> 1
A101: risk | B101: R_T technological | C101: DIG | D101: ENG | F101: =MIN(IF(C101="",99,INDEX($B$79:$B$85,MATCH(C101,$A$79:$A$85,0))),IF(D101="",99,INDEX($B$79:$B$85,MATCH(D101,$A$79:$A$85,0))),IF(E101="",99,INDEX($B$79:$B$85,MATCH(E101,$A$79:$A$85,0)))) -> 0 | G101: =MIN(IF(C101="",99,INDEX($C$79:$C$85,MATCH(C101,$A$79:$A$85,0))),IF(D101="",99,INDEX($C$79:$C$85,MATCH(D101,$A$79:$A$85,0))),IF(E101="",99,INDEX($C$79:$C$85,MATCH(E101,$A$79:$A$85,0)))) -> 1 | H101: =IF(F101>=99,"never",F101) -> 0 | I101: =IF(G101>=99,"never",G101) -> 1 | J101: 0 | K101: 1 | L101: =IF(AND(F101=J101,G101=K101),1,0) -> 1
A102: risk | B102: R_G governance | C102: GOV | F102: =MIN(IF(C102="",99,INDEX($B$79:$B$85,MATCH(C102,$A$79:$A$85,0))),IF(D102="",99,INDEX($B$79:$B$85,MATCH(D102,$A$79:$A$85,0))),IF(E102="",99,INDEX($B$79:$B$85,MATCH(E102,$A$79:$A$85,0)))) -> 99 | G102: =MIN(IF(C102="",99,INDEX($C$79:$C$85,MATCH(C102,$A$79:$A$85,0))),IF(D102="",99,INDEX($C$79:$C$85,MATCH(D102,$A$79:$A$85,0))),IF(E102="",99,INDEX($C$79:$C$85,MATCH(E102,$A$79:$A$85,0)))) -> 99 | H102: =IF(F102>=99,"never",F102) -> never | I102: =IF(G102>=99,"never",G102) -> never | J102: 99 | K102: 99 | L102: =IF(AND(F102=J102,G102=K102),1,0) -> 1
A103: risk | B103: R_L legal and regulatory | C103: GOV | D103: TRS | F103: =MIN(IF(C103="",99,INDEX($B$79:$B$85,MATCH(C103,$A$79:$A$85,0))),IF(D103="",99,INDEX($B$79:$B$85,MATCH(D103,$A$79:$A$85,0))),IF(E103="",99,INDEX($B$79:$B$85,MATCH(E103,$A$79:$A$85,0)))) -> 1 | G103: =MIN(IF(C103="",99,INDEX($C$79:$C$85,MATCH(C103,$A$79:$A$85,0))),IF(D103="",99,INDEX($C$79:$C$85,MATCH(D103,$A$79:$A$85,0))),IF(E103="",99,INDEX($C$79:$C$85,MATCH(E103,$A$79:$A$85,0)))) -> 2 | H103: =IF(F103>=99,"never",F103) -> 1 | I103: =IF(G103>=99,"never",G103) -> 2 | J103: 1 | K103: 2 | L103: =IF(AND(F103=J103,G103=K103),1,0) -> 1
A104: risk | B104: R_E environmental | C104: IND | D104: MAT | F104: =MIN(IF(C104="",99,INDEX($B$79:$B$85,MATCH(C104,$A$79:$A$85,0))),IF(D104="",99,INDEX($B$79:$B$85,MATCH(D104,$A$79:$A$85,0))),IF(E104="",99,INDEX($B$79:$B$85,MATCH(E104,$A$79:$A$85,0)))) -> 1 | G104: =MIN(IF(C104="",99,INDEX($C$79:$C$85,MATCH(C104,$A$79:$A$85,0))),IF(D104="",99,INDEX($C$79:$C$85,MATCH(D104,$A$79:$A$85,0))),IF(E104="",99,INDEX($C$79:$C$85,MATCH(E104,$A$79:$A$85,0)))) -> 1 | H104: =IF(F104>=99,"never",F104) -> 1 | I104: =IF(G104>=99,"never",G104) -> 1 | J104: 1 | K104: 1 | L104: =IF(AND(F104=J104,G104=K104),1,0) -> 1
A105: risk | B105: strategic-risk ceiling | C105: IND | D105: DIG | E105: MAT | F105: =MIN(IF(C105="",99,INDEX($B$79:$B$85,MATCH(C105,$A$79:$A$85,0))),IF(D105="",99,INDEX($B$79:$B$85,MATCH(D105,$A$79:$A$85,0))),IF(E105="",99,INDEX($B$79:$B$85,MATCH(E105,$A$79:$A$85,0)))) -> 0 | G105: =MIN(IF(C105="",99,INDEX($C$79:$C$85,MATCH(C105,$A$79:$A$85,0))),IF(D105="",99,INDEX($C$79:$C$85,MATCH(D105,$A$79:$A$85,0))),IF(E105="",99,INDEX($C$79:$C$85,MATCH(E105,$A$79:$A$85,0)))) -> 1 | H105: =IF(F105>=99,"never",F105) -> 0 | I105: =IF(G105>=99,"never",G105) -> 1 | J105: 0 | K105: 1 | L105: =IF(AND(F105=J105,G105=K105),1,0) -> 1
A106: Readouts whose two clocks match the engine | L106: =SUM(L89:L105) -> 17
A109: Mutual reach (u, w): both ways | B109: =INDEX(Comps,1) -> MKT | C109: =INDEX(Comps,2) -> GOV | D109: =INDEX(Comps,3) -> MAT | E109: =INDEX(Comps,4) -> IND | F109: =INDEX(Comps,5) -> DIG | G109: =INDEX(Comps,6) -> ENG | H109: =INDEX(Comps,7) -> TRS | I109: On a cycle
A110: =INDEX(Comps,1) -> MKT | B110: =IF(AND(0<>0,B69<99,B69<99),1,0) -> 0 | C110: =IF(AND(0<>1,C69<99,B70<99),1,0) -> 0 | D110: =IF(AND(0<>2,D69<99,B71<99),1,0) -> 0 | E110: =IF(AND(0<>3,E69<99,B72<99),1,0) -> 0 | F110: =IF(AND(0<>4,F69<99,B73<99),1,0) -> 0 | G110: =IF(AND(0<>5,G69<99,B74<99),1,0) -> 0 | H110: =IF(AND(0<>6,H69<99,B75<99),1,0) -> 0 | I110: =IF(SUM(B110:H110)>0,1,0) -> 0
A111: =INDEX(Comps,2) -> GOV | B111: =IF(AND(1<>0,B70<99,C69<99),1,0) -> 0 | C111: =IF(AND(1<>1,C70<99,C70<99),1,0) -> 0 | D111: =IF(AND(1<>2,D70<99,C71<99),1,0) -> 0 | E111: =IF(AND(1<>3,E70<99,C72<99),1,0) -> 0 | F111: =IF(AND(1<>4,F70<99,C73<99),1,0) -> 0 | G111: =IF(AND(1<>5,G70<99,C74<99),1,0) -> 0 | H111: =IF(AND(1<>6,H70<99,C75<99),1,0) -> 0 | I111: =IF(SUM(B111:H111)>0,1,0) -> 0
A112: =INDEX(Comps,3) -> MAT | B112: =IF(AND(2<>0,B71<99,D69<99),1,0) -> 0 | C112: =IF(AND(2<>1,C71<99,D70<99),1,0) -> 0 | D112: =IF(AND(2<>2,D71<99,D71<99),1,0) -> 0 | E112: =IF(AND(2<>3,E71<99,D72<99),1,0) -> 0 | F112: =IF(AND(2<>4,F71<99,D73<99),1,0) -> 0 | G112: =IF(AND(2<>5,G71<99,D74<99),1,0) -> 0 | H112: =IF(AND(2<>6,H71<99,D75<99),1,0) -> 0 | I112: =IF(SUM(B112:H112)>0,1,0) -> 0
A113: =INDEX(Comps,4) -> IND | B113: =IF(AND(3<>0,B72<99,E69<99),1,0) -> 0 | C113: =IF(AND(3<>1,C72<99,E70<99),1,0) -> 0 | D113: =IF(AND(3<>2,D72<99,E71<99),1,0) -> 0 | E113: =IF(AND(3<>3,E72<99,E72<99),1,0) -> 0 | F113: =IF(AND(3<>4,F72<99,E73<99),1,0) -> 1 | G113: =IF(AND(3<>5,G72<99,E74<99),1,0) -> 1 | H113: =IF(AND(3<>6,H72<99,E75<99),1,0) -> 1 | I113: =IF(SUM(B113:H113)>0,1,0) -> 1
A114: =INDEX(Comps,5) -> DIG | B114: =IF(AND(4<>0,B73<99,F69<99),1,0) -> 0 | C114: =IF(AND(4<>1,C73<99,F70<99),1,0) -> 0 | D114: =IF(AND(4<>2,D73<99,F71<99),1,0) -> 0 | E114: =IF(AND(4<>3,E73<99,F72<99),1,0) -> 1 | F114: =IF(AND(4<>4,F73<99,F73<99),1,0) -> 0 | G114: =IF(AND(4<>5,G73<99,F74<99),1,0) -> 1 | H114: =IF(AND(4<>6,H73<99,F75<99),1,0) -> 1 | I114: =IF(SUM(B114:H114)>0,1,0) -> 1
A115: =INDEX(Comps,6) -> ENG | B115: =IF(AND(5<>0,B74<99,G69<99),1,0) -> 0 | C115: =IF(AND(5<>1,C74<99,G70<99),1,0) -> 0 | D115: =IF(AND(5<>2,D74<99,G71<99),1,0) -> 0 | E115: =IF(AND(5<>3,E74<99,G72<99),1,0) -> 1 | F115: =IF(AND(5<>4,F74<99,G73<99),1,0) -> 1 | G115: =IF(AND(5<>5,G74<99,G74<99),1,0) -> 0 | H115: =IF(AND(5<>6,H74<99,G75<99),1,0) -> 1 | I115: =IF(SUM(B115:H115)>0,1,0) -> 1
...

Sheet Ledgers
A1: Run the program on one clock: three ledgers month by month (Proposition 13.2; Theorem 13.4; Figure 13.1; AXIOM Lab 1.13, step 5)
A2: Chapter 1's model (Declarations rows 27-30): capital (liquidity), performance (the CFO's scorecard, (L + T + E - R)/4), risk (strategic risk against the ceiling of 75, measured +/-6).
A4: Month | B4: Years | C4: Liquidity index | D4: Technology | E4: Efficiency | F4: Strategic risk | G4: Liquidity ($ million) | H4: CFO's scorecard | J4: The three clocks | K4: Value | L4: Book (Figure 13.1; Online Appendix 13.B.4)
A5: 0 | B5: =A5/12 -> 0 | C5: =Declarations!$C$27+(Declarations!$B$27-Declarations!$C$27)*EXP(-Declarations!$D$27*$B5)+Declarations!$E$27*($B5/Declarations!$F$27)*EXP(1-$B5/Declarations!$F$27) -> 100 | D5: =Declarations!$C$28+(Declarations!$B$28-Declarations!$C$28)*EXP(-Declarations!$D$28*$B5)+Declarations!$E$28*($B5/Declarations!$F$28)*EXP(1-$B5/Declarations!$F$28) -> 41 | E5: =Declarations!$C$29+(Declarations!$B$29-Declarations!$C$29)*EXP(-Declarations!$D$29*$B5)+Declarations!$E$29*($B5/Declarations!$F$29)*EXP(1-$B5/Declarations!$F$29) -> 71 | F5: =Declarations!$C$30+(Declarations!$B$30-Declarations!$C$30)*EXP(-Declarations!$D$30*$B5)+Declarations!$E$30*($B5/Declarations!$F$30)*EXP(1-$B5/Declarations!$F$30) -> 64 | G5: =Per_point*C5 -> 620 | H5: =(C5+D5+E5-F5)/4 -> 37 | J5: Scorecard today | K5: =H5 -> 37 | L5: 37.0
A6: 1 | B6: =A6/12 -> 0.083333333 | C6: =Declarations!$C$27+(Declarations!$B$27-Declarations!$C$27)*EXP(-Declarations!$D$27*$B6)+Declarations!$E$27*($B6/Declarations!$F$27)*EXP(1-$B6/Declarations!$F$27) -> 97.30304 | D6: =Declarations!$C$28+(Declarations!$B$28-Declarations!$C$28)*EXP(-Declarations!$D$28*$B6)+Declarations!$E$28*($B6/Declarations!$F$28)*EXP(1-$B6/Declarations!$F$28) -> 42.657557 | E6: =Declarations!$C$29+(Declarations!$B$29-Declarations!$C$29)*EXP(-Declarations!$D$29*$B6)+Declarations!$E$29*($B6/Declarations!$F$29)*EXP(1-$B6/Declarations!$F$29) -> 69.959171 | F6: =Declarations!$C$30+(Declarations!$B$30-Declarations!$C$30)*EXP(-Declarations!$D$30*$B6)+Declarations!$E$30*($B6/Declarations!$F$30)*EXP(1-$B6/Declarations!$F$30) -> 66.039285 | G6: =Per_point*C6 -> 603.27885 | H6: =(C6+D6+E6-F6)/4 -> 35.970121 | J6: Liquidity low ($ million) | K6: =MIN($G$5:$G$65) -> 481.95038 | L6: $482 million
A7: 2 | B7: =A7/12 -> 0.16666667 | C7: =Declarations!$C$27+(Declarations!$B$27-Declarations!$C$27)*EXP(-Declarations!$D$27*$B7)+Declarations!$E$27*($B7/Declarations!$F$27)*EXP(1-$B7/Declarations!$F$27) -> 94.844448 | D7: =Declarations!$C$28+(Declarations!$B$28-Declarations!$C$28)*EXP(-Declarations!$D$28*$B7)+Declarations!$E$28*($B7/Declarations!$F$28)*EXP(1-$B7/Declarations!$F$28) -> 44.240858 | E7: =Declarations!$C$29+(Declarations!$B$29-Declarations!$C$29)*EXP(-Declarations!$D$29*$B7)+Declarations!$E$29*($B7/Declarations!$F$29)*EXP(1-$B7/Declarations!$F$29) -> 69.047308 | F7: =Declarations!$C$30+(Declarations!$B$30-Declarations!$C$30)*EXP(-Declarations!$D$30*$B7)+Declarations!$E$30*($B7/Declarations!$F$30)*EXP(1-$B7/Declarations!$F$30) -> 67.761734 | G7: =Per_point*C7 -> 588.03558 | H7: =(C7+D7+E7-F7)/4 -> 35.09272 | J7: Month of the liquidity low | K7: =INDEX($A$5:$A$65,MATCH(K6,$G$5:$G$65,0)) -> 21 | L7: month 21
A8: 3 | B8: =A8/12 -> 0.25 | C8: =Declarations!$C$27+(Declarations!$B$27-Declarations!$C$27)*EXP(-Declarations!$D$27*$B8)+Declarations!$E$27*($B8/Declarations!$F$27)*EXP(1-$B8/Declarations!$F$27) -> 92.60931 | D8: =Declarations!$C$28+(Declarations!$B$28-Declarations!$C$28)*EXP(-Declarations!$D$28*$B8)+Declarations!$E$28*($B8/Declarations!$F$28)*EXP(1-$B8/Declarations!$F$28) -> 45.753229 | E8: =Declarations!$C$29+(Declarations!$B$29-Declarations!$C$29)*EXP(-Declarations!$D$29*$B8)+Declarations!$E$29*($B8/Declarations!$F$29)*EXP(1-$B8/Declarations!$F$29) -> 68.253555 | F8: =Declarations!$C$30+(Declarations!$B$30-Declarations!$C$30)*EXP(-Declarations!$D$30*$B8)+Declarations!$E$30*($B8/Declarations!$F$30)*EXP(1-$B8/Declarations!$F$30) -> 69.200179 | G8: =Per_point*C8 -> 574.17772 | H8: =(C8+D8+E8-F8)/4 -> 34.353979 | J8: Scorecard low | K8: =MIN($H$5:$H$65) -> 32.106467 | L8: 32.1
A9: 4 | B9: =A9/12 -> 0.33333333 | C9: =Declarations!$C$27+(Declarations!$B$27-Declarations!$C$27)*EXP(-Declarations!$D$27*$B9)+Declarations!$E$27*($B9/Declarations!$F$27)*EXP(1-$B9/Declarations!$F$27) -> 90.583531 | D9: =Declarations!$C$28+(Declarations!$B$28-Declarations!$C$28)*EXP(-Declarations!$D$28*$B9)+Declarations!$E$28*($B9/Declarations!$F$28)*EXP(1-$B9/Declarations!$F$28) -> 47.197847 | E9: =Declarations!$C$29+(Declarations!$B$29-Declarations!$C$29)*EXP(-Declarations!$D$29*$B9)+Declarations!$E$29*($B9/Declarations!$F$29)*EXP(1-$B9/Declarations!$F$29) -> 67.56785 | F9: =Declarations!$C$30+(Declarations!$B$30-Declarations!$C$30)*EXP(-Declarations!$D$30*$B9)+Declarations!$E$30*($B9/Declarations!$F$30)*EXP(1-$B9/Declarations!$F$30) -> 70.38449 | G9: =Per_point*C9 -> 561.61789 | H9: =(C9+D9+E9-F9)/4 -> 33.741185 | J9: Month of the scorecard low | K9: =INDEX($A$5:$A$65,MATCH(K8,$H$5:$H$65,0)) -> 11 | L9: month 11
A10: 5 | B10: =A10/12 -> 0.41666667 | C10: =Declarations!$C$27+(Declarations!$B$27-Declarations!$C$27)*EXP(-Declarations!$D$27*$B10)+Declarations!$E$27*($B10/Declarations!$F$27)*EXP(1-$B10/Declarations!$F$27) -> 88.753794 | D10: =Declarations!$C$28+(Declarations!$B$28-Declarations!$C$28)*EXP(-Declarations!$D$28*$B10)+Declarations!$E$28*($B10/Declarations!$F$28)*EXP(1-$B10/Declarations!$F$28) -> 48.577748 | E10: =Declarations!$C$29+(Declarations!$B$29-Declarations!$C$29)*EXP(-Declarations!$D$29*$B10)+Declarations!$E$29*($B10/Declarations!$F$29)*EXP(1-$B10/Declarations!$F$29) -> 66.980873 | F10: =Declarations!$C$30+(Declarations!$B$30-Declarations!$C$30)*EXP(-Declarations!$D$30*$B10)+Declarations!$E$30*($B10/Declarations!$F$30)*EXP(1-$B10/Declarations!$F$30) -> 71.341821 | G10: =Per_point*C10 -> 550.27352 | H10: =(C10+D10+E10-F10)/4 -> 33.242648 | J10: Month the scorecard regains today's level | K10: =_xlfn.MINIFS($A$5:$A$65,$H$5:$H$65,">="&K5,$A$5:$A$65,">"&K9) -> 29 | L10: month 29
A11: 6 | B11: =A11/12 -> 0.5 | C11: =Declarations!$C$27+(Declarations!$B$27-Declarations!$C$27)*EXP(-Declarations!$D$27*$B11)+Declarations!$E$27*($B11/Declarations!$F$27)*EXP(1-$B11/Declarations!$F$27) -> 87.107516 | D11: =Declarations!$C$28+(Declarations!$B$28-Declarations!$C$28)*EXP(-Declarations!$D$28*$B11)+Declarations!$E$28*($B11/Declarations!$F$28)*EXP(1-$B11/Declarations!$F$28) -> 49.895831 | E11: =Declarations!$C$29+(Declarations!$B$29-Declarations!$C$29)*EXP(-Declarations!$D$29*$B11)+Declarations!$E$29*($B11/Declarations!$F$29)*EXP(1-$B11/Declarations!$F$29) -> 66.483993 | F11: =Declarations!$C$30+(Declarations!$B$30-Declarations!$C$30)*EXP(-Declarations!$D$30*$B11)+Declarations!$E$30*($B11/Declarations!$F$30)*EXP(1-$B11/Declarations!$F$30) -> 72.096844 | G11: =Per_point*C11 -> 540.0666 | H11: =(C11+D11+E11-F11)/4 -> 32.847624 | J11: Scorecard in that month | K11: =INDEX($H$5:$H$65,K10+1) -> 37.18741 | L11: 37.19
A12: 7 | B12: =A12/12 -> 0.58333333 | C12: =Declarations!$C$27+(Declarations!$B$27-Declarations!$C$27)*EXP(-Declarations!$D$27*$B12)+Declarations!$E$27*($B12/Declarations!$F$27)*EXP(1-$B12/Declarations!$F$27) -> 85.632816 | D12: =Declarations!$C$28+(Declarations!$B$28-Declarations!$C$28)*EXP(-Declarations!$D$28*$B12)+Declarations!$E$28*($B12/Declarations!$F$28)*EXP(1-$B12/Declarations!$F$28) -> 51.154866 | E12: =Declarations!$C$29+(Declarations!$B$29-Declarations!$C$29)*EXP(-Declarations!$D$29*$B12)+Declarations!$E$29*($B12/Declarations!$F$29)*EXP(1-$B12/Declarations!$F$29) -> 66.069224 | F12: =Declarations!$C$30+(Declarations!$B$30-Declarations!$C$30)*EXP(-Declarations!$D$30*$B12)+Declarations!$E$30*($B12/Declarations!$F$30)*EXP(1-$B12/Declarations!$F$30) -> 72.671956 | G12: =Per_point*C12 -> 530.92346 | H12: =(C12+D12+E12-F12)/4 -> 32.546237 | J12: Strategic-risk peak | K12: =MAX($F$5:$F$65) -> 73.552064 | L12: 73.55
A13: 8 | B13: =A13/12 -> 0.66666667 | C13: =Declarations!$C$27+(Declarations!$B$27-Declarations!$C$27)*EXP(-Declarations!$D$27*$B13)+Declarations!$E$27*($B13/Declarations!$F$27)*EXP(1-$B13/Declarations!$F$27) -> 84.318474 | D13: =Declarations!$C$28+(Declarations!$B$28-Declarations!$C$28)*EXP(-Declarations!$D$28*$B13)+Declarations!$E$28*($B13/Declarations!$F$28)*EXP(1-$B13/Declarations!$F$28) -> 52.357497 | E13: =Declarations!$C$29+(Declarations!$B$29-Declarations!$C$29)*EXP(-Declarations!$D$29*$B13)+Declarations!$E$29*($B13/Declarations!$F$29)*EXP(1-$B13/Declarations!$F$29) -> 65.729176 | F13: =Declarations!$C$30+(Declarations!$B$30-Declarations!$C$30)*EXP(-Declarations!$D$30*$B13)+Declarations!$E$30*($B13/Declarations!$F$30)*EXP(1-$B13/Declarations!$F$30) -> 73.087473 | G13: =Per_point*C13 -> 522.77454 | H13: =(C13+D13+E13-F13)/4 -> 32.329418 | J13: Month of the risk peak | K13: =INDEX($A$5:$A$65,MATCH(K12,$F$5:$F$65,0)) -> 11 | L13: month 11
A14: 9 | B14: =A14/12 -> 0.75 | C14: =Declarations!$C$27+(Declarations!$B$27-Declarations!$C$27)*EXP(-Declarations!$D$27*$B14)+Declarations!$E$27*($B14/Declarations!$F$27)*EXP(1-$B14/Declarations!$F$27) -> 83.153901 | D14: =Declarations!$C$28+(Declarations!$B$28-Declarations!$C$28)*EXP(-Declarations!$D$28*$B14)+Declarations!$E$28*($B14/Declarations!$F$28)*EXP(1-$B14/Declarations!$F$28) -> 53.506252 | E14: =Declarations!$C$29+(Declarations!$B$29-Declarations!$C$29)*EXP(-Declarations!$D$29*$B14)+Declarations!$E$29*($B14/Declarations!$F$29)*EXP(1-$B14/Declarations!$F$29) -> 65.457019 | F14: =Declarations!$C$30+(Declarations!$B$30-Declarations!$C$30)*EXP(-Declarations!$D$30*$B14)+Declarations!$E$30*($B14/Declarations!$F$30)*EXP(1-$B14/Declarations!$F$30) -> 73.361812 | G14: =Per_point*C14 -> 515.55419 | H14: =(C14+D14+E14-F14)/4 -> 32.18884 | J14: The ceiling's distance at the peak | K14: =Risk_ceiling-K12 -> 1.4479365 | L14: 1.4 points, inside the +/-6 error
A15: 10 | B15: =A15/12 -> 0.83333333 | C15: =Declarations!$C$27+(Declarations!$B$27-Declarations!$C$27)*EXP(-Declarations!$D$27*$B15)+Declarations!$E$27*($B15/Declarations!$F$27)*EXP(1-$B15/Declarations!$F$27) -> 82.129102 | D15: =Declarations!$C$28+(Declarations!$B$28-Declarations!$C$28)*EXP(-Declarations!$D$28*$B15)+Declarations!$E$28*($B15/Declarations!$F$28)*EXP(1-$B15/Declarations!$F$28) -> 54.603543 | E15: =Declarations!$C$29+(Declarations!$B$29-Declarations!$C$29)*EXP(-Declarations!$D$29*$B15)+Declarations!$E$29*($B15/Declarations!$F$29)*EXP(1-$B15/Declarations!$F$29) -> 65.246439 | F15: =Declarations!$C$30+(Declarations!$B$30-Declarations!$C$30)*EXP(-Declarations!$D$30*$B15)+Declarations!$E$30*($B15/Declarations!$F$30)*EXP(1-$B15/Declarations!$F$30) -> 73.511646 | G15: =Per_point*C15 -> 509.20043 | H15: =(C15+D15+E15-F15)/4 -> 32.116859
A16: 11 | B16: =A16/12 -> 0.91666667 | C16: =Declarations!$C$27+(Declarations!$B$27-Declarations!$C$27)*EXP(-Declarations!$D$27*$B16)+Declarations!$E$27*($B16/Declarations!$F$27)*EXP(1-$B16/Declarations!$F$27) -> 81.234648 | D16: =Declarations!$C$28+(Declarations!$B$28-Declarations!$C$28)*EXP(-Declarations!$D$28*$B16)+Declarations!$E$28*($B16/Declarations!$F$28)*EXP(1-$B16/Declarations!$F$28) -> 55.651678 | E16: =Declarations!$C$29+(Declarations!$B$29-Declarations!$C$29)*EXP(-Declarations!$D$29*$B16)+Declarations!$E$29*($B16/Declarations!$F$29)*EXP(1-$B16/Declarations!$F$29) -> 65.091607 | F16: =Declarations!$C$30+(Declarations!$B$30-Declarations!$C$30)*EXP(-Declarations!$D$30*$B16)+Declarations!$E$30*($B16/Declarations!$F$30)*EXP(1-$B16/Declarations!$F$30) -> 73.552064 | G16: =Per_point*C16 -> 503.65482 | H16: =(C16+D16+E16-F16)/4 -> 32.106467 | J16: Month 11: liquidity ($ million) | K16: =INDEX($G$5:$G$65,12) -> 503.65482 | L16: a falling but ample cushion
A17: 12 | B17: =A17/12 -> 1 | C17: =Declarations!$C$27+(Declarations!$B$27-Declarations!$C$27)*EXP(-Declarations!$D$27*$B17)+Declarations!$E$27*($B17/Declarations!$F$27)*EXP(1-$B17/Declarations!$F$27) -> 80.461645 | D17: =Declarations!$C$28+(Declarations!$B$28-Declarations!$C$28)*EXP(-Declarations!$D$28*$B17)+Declarations!$E$28*($B17/Declarations!$F$28)*EXP(1-$B17/Declarations!$F$28) -> 56.652857 | E17: =Declarations!$C$29+(Declarations!$B$29-Declarations!$C$29)*EXP(-Declarations!$D$29*$B17)+Declarations!$E$29*($B17/Declarations!$F$29)*EXP(1-$B17/Declarations!$F$29) -> 64.987141 | F17: =Declarations!$C$30+(Declarations!$B$30-Declarations!$C$30)*EXP(-Declarations!$D$30*$B17)+Declarations!$E$30*($B17/Declarations!$F$30)*EXP(1-$B17/Declarations!$F$30) -> 73.496699 | G17: =Per_point*C17 -> 498.8622 | H17: =(C17+D17+E17-F17)/4 -> 32.151236 | J17: Month 11: liquidity's change over the month | K17: =INDEX($G$5:$G$65,12)-INDEX($G$5:$G$65,11) -> -5.5456158 | L17: falling
A18: 13 | B18: =A18/12 -> 1.0833333 | C18: =Declarations!$C$27+(Declarations!$B$27-Declarations!$C$27)*EXP(-Declarations!$D$27*$B18)+Declarations!$E$27*($B18/Declarations!$F$27)*EXP(1-$B18/Declarations!$F$27) -> 79.801708 | D18: =Declarations!$C$28+(Declarations!$B$28-Declarations!$C$28)*EXP(-Declarations!$D$28*$B18)+Declarations!$E$28*($B18/Declarations!$F$28)*EXP(1-$B18/Declarations!$F$28) -> 57.609184 | E18: =Declarations!$C$29+(Declarations!$B$29-Declarations!$C$29)*EXP(-Declarations!$D$29*$B18)+Declarations!$E$29*($B18/Declarations!$F$29)*EXP(1-$B18/Declarations!$F$29) -> 64.92808 | F18: =Declarations!$C$30+(Declarations!$B$30-Declarations!$C$30)*EXP(-Declarations!$D$30*$B18)+Declarations!$E$30*($B18/Declarations!$F$30)*EXP(1-$B18/Declarations!$F$30) -> 73.357862 | G18: =Per_point*C18 -> 494.77059 | H18: =(C18+D18+E18-F18)/4 -> 32.245278 | J18: Month 11: scorecard | K18: =INDEX($H$5:$H$65,12) -> 32.106467 | L18: a failing program
A19: 14 | B19: =A19/12 -> 1.1666667 | C19: =Declarations!$C$27+(Declarations!$B$27-Declarations!$C$27)*EXP(-Declarations!$D$27*$B19)+Declarations!$E$27*($B19/Declarations!$F$27)*EXP(1-$B19/Declarations!$F$27) -> 79.246932 | D19: =Declarations!$C$28+(Declarations!$B$28-Declarations!$C$28)*EXP(-Declarations!$D$28*$B19)+Declarations!$E$28*($B19/Declarations!$F$28)*EXP(1-$B19/Declarations!$F$28) -> 58.52267 | E19: =Declarations!$C$29+(Declarations!$B$29-Declarations!$C$29)*EXP(-Declarations!$D$29*$B19)+Declarations!$E$29*($B19/Declarations!$F$29)*EXP(1-$B19/Declarations!$F$29) -> 64.909847 | F19: =Declarations!$C$30+(Declarations!$B$30-Declarations!$C$30)*EXP(-Declarations!$D$30*$B19)+Declarations!$E$30*($B19/Declarations!$F$30)*EXP(1-$B19/Declarations!$F$30) -> 73.146656 | G19: =Per_point*C19 -> 491.33098 | H19: =(C19+D19+E19-F19)/4 -> 32.383198 | J19: Month 11: strategic risk | K19: =INDEX($F$5:$F$65,12) -> 73.552064 | L19: the ceiling 1.4 points away
A20: 15 | B20: =A20/12 -> 1.25 | C20: =Declarations!$C$27+(Declarations!$B$27-Declarations!$C$27)*EXP(-Declarations!$D$27*$B20)+Declarations!$E$27*($B20/Declarations!$F$27)*EXP(1-$B20/Declarations!$F$27) -> 78.789868 | D20: =Declarations!$C$28+(Declarations!$B$28-Declarations!$C$28)*EXP(-Declarations!$D$28*$B20)+Declarations!$E$28*($B20/Declarations!$F$28)*EXP(1-$B20/Declarations!$F$28) -> 59.395232 | E20: =Declarations!$C$29+(Declarations!$B$29-Declarations!$C$29)*EXP(-Declarations!$D$29*$B20)+Declarations!$E$29*($B20/Declarations!$F$29)*EXP(1-$B20/Declarations!$F$29) -> 64.928228 | F20: =Declarations!$C$30+(Declarations!$B$30-Declarations!$C$30)*EXP(-Declarations!$D$30*$B20)+Declarations!$E$30*($B20/Declarations!$F$30)*EXP(1-$B20/Declarations!$F$30) -> 72.873078 | G20: =Per_point*C20 -> 488.49718 | H20: =(C20+D20+E20-F20)/4 -> 32.560062
A21: 16 | B21: =A21/12 -> 1.3333333 | C21: =Declarations!$C$27+(Declarations!$B$27-Declarations!$C$27)*EXP(-Declarations!$D$27*$B21)+Declarations!$E$27*($B21/Declarations!$F$27)*EXP(1-$B21/Declarations!$F$27) -> 78.423499 | D21: =Declarations!$C$28+(Declarations!$B$28-Declarations!$C$28)*EXP(-Declarations!$D$28*$B21)+Declarations!$E$28*($B21/Declarations!$F$28)*EXP(1-$B21/Declarations!$F$28) -> 60.228704 | E21: =Declarations!$C$29+(Declarations!$B$29-Declarations!$C$29)*EXP(-Declarations!$D$29*$B21)+Declarations!$E$29*($B21/Declarations!$F$29)*EXP(1-$B21/Declarations!$F$29) -> 64.979345 | F21: =Declarations!$C$30+(Declarations!$B$30-Declarations!$C$30)*EXP(-Declarations!$D$30*$B21)+Declarations!$E$30*($B21/Declarations!$F$30)*EXP(1-$B21/Declarations!$F$30) -> 72.546124 | G21: =Per_point*C21 -> 486.22569 | H21: =(C21+D21+E21-F21)/4 -> 32.771356
A22: 17 | B22: =A22/12 -> 1.4166667 | C22: =Declarations!$C$27+(Declarations!$B$27-Declarations!$C$27)*EXP(-Declarations!$D$27*$B22)+Declarations!$E$27*($B22/Declarations!$F$27)*EXP(1-$B22/Declarations!$F$27) -> 78.141217 | D22: =Declarations!$C$28+(Declarations!$B$28-Declarations!$C$28)*EXP(-Declarations!$D$28*$B22)+Declarations!$E$28*($B22/Declarations!$F$28)*EXP(1-$B22/Declarations!$F$28) -> 61.024838 | E22: =Declarations!$C$29+(Declarations!$B$29-Declarations!$C$29)*EXP(-Declarations!$D$29*$B22)+Declarations!$E$29*($B22/Declarations!$F$29)*EXP(1-$B22/Declarations!$F$29) -> 65.059628 | F22: =Declarations!$C$30+(Declarations!$B$30-Declarations!$C$30)*EXP(-Declarations!$D$30*$B22)+Declarations!$E$30*($B22/Declarations!$F$30)*EXP(1-$B22/Declarations!$F$30) -> 72.173871 | G22: =Per_point*C22 -> 484.47555 | H22: =(C22+D22+E22-F22)/4 -> 33.012953
A23: 18 | B23: =A23/12 -> 1.5 | C23: =Declarations!$C$27+(Declarations!$B$27-Declarations!$C$27)*EXP(-Declarations!$D$27*$B23)+Declarations!$E$27*($B23/Declarations!$F$27)*EXP(1-$B23/Declarations!$F$27) -> 77.936802 | D23: =Declarations!$C$28+(Declarations!$B$28-Declarations!$C$28)*EXP(-Declarations!$D$28*$B23)+Declarations!$E$28*($B23/Declarations!$F$28)*EXP(1-$B23/Declarations!$F$28) -> 61.785305 | E23: =Declarations!$C$29+(Declarations!$B$29-Declarations!$C$29)*EXP(-Declarations!$D$29*$B23)+Declarations!$E$29*($B23/Declarations!$F$29)*EXP(1-$B23/Declarations!$F$29) -> 65.165801 | F23: =Declarations!$C$30+(Declarations!$B$30-Declarations!$C$30)*EXP(-Declarations!$D$30*$B23)+Declarations!$E$30*($B23/Declarations!$F$30)*EXP(1-$B23/Declarations!$F$30) -> 71.763565 | G23: =Per_point*C23 -> 483.20817 | H23: =(C23+D23+E23-F23)/4 -> 33.281086
A24: 19 | B24: =A24/12 -> 1.5833333 | C24: =Declarations!$C$27+(Declarations!$B$27-Declarations!$C$27)*EXP(-Declarations!$D$27*$B24)+Declarations!$E$27*($B24/Declarations!$F$27)*EXP(1-$B24/Declarations!$F$27) -> 77.804399 | D24: =Declarations!$C$28+(Declarations!$B$28-Declarations!$C$28)*EXP(-Declarations!$D$28*$B24)+Declarations!$E$28*($B24/Declarations!$F$28)*EXP(1-$B24/Declarations!$F$28) -> 62.511705 | E24: =Declarations!$C$29+(Declarations!$B$29-Declarations!$C$29)*EXP(-Declarations!$D$29*$B24)+Declarations!$E$29*($B24/Declarations!$F$29)*EXP(1-$B24/Declarations!$F$29) -> 65.294851 | F24: =Declarations!$C$30+(Declarations!$B$30-Declarations!$C$30)*EXP(-Declarations!$D$30*$B24)+Declarations!$E$30*($B24/Declarations!$F$30)*EXP(1-$B24/Declarations!$F$30) -> 71.321693 | G24: =Per_point*C24 -> 482.38727 | H24: =(C24+D24+E24-F24)/4 -> 33.572315
A25: 20 | B25: =A25/12 -> 1.6666667 | C25: =Declarations!$C$27+(Declarations!$B$27-Declarations!$C$27)*EXP(-Declarations!$D$27*$B25)+Declarations!$E$27*($B25/Declarations!$F$27)*EXP(1-$B25/Declarations!$F$27) -> 77.738502 | D25: =Declarations!$C$28+(Declarations!$B$28-Declarations!$C$28)*EXP(-Declarations!$D$28*$B25)+Declarations!$E$28*($B25/Declarations!$F$28)*EXP(1-$B25/Declarations!$F$28) -> 63.205563 | E25: =Declarations!$C$29+(Declarations!$B$29-Declarations!$C$29)*EXP(-Declarations!$D$29*$B25)+Declarations!$E$29*($B25/Declarations!$F$29)*EXP(1-$B25/Declarations!$F$29) -> 65.444018 | F25: =Declarations!$C$30+(Declarations!$B$30-Declarations!$C$30)*EXP(-Declarations!$D$30*$B25)+Declarations!$E$30*($B25/Declarations!$F$30)*EXP(1-$B25/Declarations!$F$30) -> 70.854053 | G25: =Per_point*C25 -> 481.97871 | H25: =(C25+D25+E25-F25)/4 -> 33.883507
A26: 21 | B26: =A26/12 -> 1.75 | C26: =Declarations!$C$27+(Declarations!$B$27-Declarations!$C$27)*EXP(-Declarations!$D$27*$B26)+Declarations!$E$27*($B26/Declarations!$F$27)*EXP(1-$B26/Declarations!$F$27) -> 77.733933 | D26: =Declarations!$C$28+(Declarations!$B$28-Declarations!$C$28)*EXP(-Declarations!$D$28*$B26)+Declarations!$E$28*($B26/Declarations!$F$28)*EXP(1-$B26/Declarations!$F$28) -> 63.868337 | E26: =Declarations!$C$29+(Declarations!$B$29-Declarations!$C$29)*EXP(-Declarations!$D$29*$B26)+Declarations!$E$29*($B26/Declarations!$F$29)*EXP(1-$B26/Declarations!$F$29) -> 65.61077 | F26: =Declarations!$C$30+(Declarations!$B$30-Declarations!$C$30)*EXP(-Declarations!$D$30*$B26)+Declarations!$E$30*($B26/Declarations!$F$30)*EXP(1-$B26/Declarations!$F$30) -> 70.365816 | G26: =Per_point*C26 -> 481.95038 | H26: =(C26+D26+E26-F26)/4 -> 34.211806
A27: 22 | B27: =A27/12 -> 1.8333333 | C27: =Declarations!$C$27+(Declarations!$B$27-Declarations!$C$27)*EXP(-Declarations!$D$27*$B27)+Declarations!$E$27*($B27/Declarations!$F$27)*EXP(1-$B27/Declarations!$F$27) -> 77.785824 | D27: =Declarations!$C$28+(Declarations!$B$28-Declarations!$C$28)*EXP(-Declarations!$D$28*$B27)+Declarations!$E$28*($B27/Declarations!$F$28)*EXP(1-$B27/Declarations!$F$28) -> 64.501419 | E27: =Declarations!$C$29+(Declarations!$B$29-Declarations!$C$29)*EXP(-Declarations!$D$29*$B27)+Declarations!$E$29*($B27/Declarations!$F$29)*EXP(1-$B27/Declarations!$F$29) -> 65.792791 | F27: =Declarations!$C$30+(Declarations!$B$30-Declarations!$C$30)*EXP(-Declarations!$D$30*$B27)+Declarations!$E$30*($B27/Declarations!$F$30)*EXP(1-$B27/Declarations!$F$30) -> 69.861583 | G27: =Per_point*C27 -> 482.27211 | H27: =(C27+D27+E27-F27)/4 -> 34.554613
A28: 23 | B28: =A28/12 -> 1.9166667 | C28: =Declarations!$C$27+(Declarations!$B$27-Declarations!$C$27)*EXP(-Declarations!$D$27*$B28)+Declarations!$E$27*($B28/Declarations!$F$27)*EXP(1-$B28/Declarations!$F$27) -> 77.889603 | D28: =Declarations!$C$28+(Declarations!$B$28-Declarations!$C$28)*EXP(-Declarations!$D$28*$B28)+Declarations!$E$28*($B28/Declarations!$F$28)*EXP(1-$B28/Declarations!$F$28) -> 65.10614 | E28: =Declarations!$C$29+(Declarations!$B$29-Declarations!$C$29)*EXP(-Declarations!$D$29*$B28)+Declarations!$E$29*($B28/Declarations!$F$29)*EXP(1-$B28/Declarations!$F$29) -> 65.987962 | F28: =Declarations!$C$30+(Declarations!$B$30-Declarations!$C$30)*EXP(-Declarations!$D$30*$B28)+Declarations!$E$30*($B28/Declarations!$F$30)*EXP(1-$B28/Declarations!$F$30) -> 69.345442 | G28: =Per_point*C28 -> 482.91554 | H28: =(C28+D28+E28-F28)/4 -> 34.909566
A29: 24 | B29: =A29/12 -> 2 | C29: =Declarations!$C$27+(Declarations!$B$27-Declarations!$C$27)*EXP(-Declarations!$D$27*$B29)+Declarations!$E$27*($B29/Declarations!$F$27)*EXP(1-$B29/Declarations!$F$27) -> 78.040976 | D29: =Declarations!$C$28+(Declarations!$B$28-Declarations!$C$28)*EXP(-Declarations!$D$28*$B29)+Declarations!$E$28*($B29/Declarations!$F$28)*EXP(1-$B29/Declarations!$F$28) -> 65.68377 | E29: =Declarations!$C$29+(Declarations!$B$29-Declarations!$C$29)*EXP(-Declarations!$D$29*$B29)+Declarations!$E$29*($B29/Declarations!$F$29)*EXP(1-$B29/Declarations!$F$29) -> 66.194348 | F29: =Declarations!$C$30+(Declarations!$B$30-Declarations!$C$30)*EXP(-Declarations!$D$30*$B29)+Declarations!$E$30*($B29/Declarations!$F$30)*EXP(1-$B29/Declarations!$F$30) -> 68.821009 | G29: =Per_point*C29 -> 483.85405 | H29: =(C29+D29+E29-F29)/4 -> 35.274521
A30: 25 | B30: =A30/12 -> 2.0833333 | C30: =Declarations!$C$27+(Declarations!$B$27-Declarations!$C$27)*EXP(-Declarations!$D$27*$B30)+Declarations!$E$27*($B30/Declarations!$F$27)*EXP(1-$B30/Declarations!$F$27) -> 78.235912 | D30: =Declarations!$C$28+(Declarations!$B$28-Declarations!$C$28)*EXP(-Declarations!$D$28*$B30)+Declarations!$E$28*($B30/Declarations!$F$28)*EXP(1-$B30/Declarations!$F$28) -> 66.235523 | E30: =Declarations!$C$29+(Declarations!$B$29-Declarations!$C$29)*EXP(-Declarations!$D$29*$B30)+Declarations!$E$29*($B30/Declarations!$F$29)*EXP(1-$B30/Declarations!$F$29) -> 66.410184 | F30: =Declarations!$C$30+(Declarations!$B$30-Declarations!$C$30)*EXP(-Declarations!$D$30*$B30)+Declarations!$E$30*($B30/Declarations!$F$30)*EXP(1-$B30/Declarations!$F$30) -> 68.291481 | G30: =Per_point*C30 -> 485.06265 | H30: =(C30+D30+E30-F30)/4 -> 35.647534
A31: 26 | B31: =A31/12 -> 2.1666667 | C31: =Declarations!$C$27+(Declarations!$B$27-Declarations!$C$27)*EXP(-Declarations!$D$27*$B31)+Declarations!$E$27*($B31/Declarations!$F$27)*EXP(1-$B31/Declarations!$F$27) -> 78.470628 | D31: =Declarations!$C$28+(Declarations!$B$28-Declarations!$C$28)*EXP(-Declarations!$D$28*$B31)+Declarations!$E$28*($B31/Declarations!$F$28)*EXP(1-$B31/Declarations!$F$28) -> 66.762558 | E31: =Declarations!$C$29+(Declarations!$B$29-Declarations!$C$29)*EXP(-Declarations!$D$29*$B31)+Declarations!$E$29*($B31/Declarations!$F$29)*EXP(1-$B31/Declarations!$F$29) -> 66.633862 | F31: =Declarations!$C$30+(Declarations!$B$30-Declarations!$C$30)*EXP(-Declarations!$D$30*$B31)+Declarations!$E$30*($B31/Declarations!$F$30)*EXP(1-$B31/Declarations!$F$30) -> 67.759667 | G31: =Per_point*C31 -> 486.51789 | H31: =(C31+D31+E31-F31)/4 -> 36.026845
... A65: 60 | B65: =A65/12 -> 5 | C65: =Declarations!$C$27+(Declarations!$B$27-Declarations!$C$27)*EXP(-Declarations!$D$27*$B65)+Declarations!$E$27*($B65/Declarations!$F$27)*EXP(1-$B65/Declarations!$F$27) -> 94.295601 | D65: =Declarations!$C$28+(Declarations!$B$28-Declarations!$C$28)*EXP(-Declarations!$D$28*$B65)+Declarations!$E$28*($B65/Declarations!$F$28)*EXP(1-$B65/Declarations!$F$28) -> 75.634669 | E65: =Declarations!$C$29+(Declarations!$B$29-Declarations!$C$29)*EXP(-Declarations!$D$29*$B65)+Declarations!$E$29*($B65/Declarations!$F$29)*EXP(1-$B65/Declarations!$F$29) -> 73.598331 | F65: =Declarations!$C$30+(Declarations!$B$30-Declarations!$C$30)*EXP(-Declarations!$D$30*$B65)+Declarations!$E$30*($B65/Declarations!$F$30)*EXP(1-$B65/Declarations!$F$30) -> 55.21775 | G65: =Per_point*C65 -> 584.63273 | H65: =(C65+D65+E65-F65)/4 -> 47.077713

Sheet JointCheck
A1: Read the sign-offs and walk the cycle as one constraint (Worked Example 13.1, Steps 1-3; Theorem 13.5(iii); Figure 13.3; AXIOM Lab 1.13, step 4)
A2: Chapter 8's plan, quarterly: liquidity = $6.2 million x Chapter 1's index. The phased build's trough is 20 deep instead of 28.
A4: Quarter | B4: Years | C4: Plan: index | D4: Plan: liquidity ($ million) | E4: Phased: index | F4: Phased: liquidity ($ million) | G4: Plan inside the buffer line | H4: Phased inside the buffer line | J4: The sign-offs and the joint check | K4: Value | L4: Book
A5: 0 | B5: =A5/4 -> 0 | C5: =Declarations!$C$27+(Declarations!$B$27-Declarations!$C$27)*EXP(-Declarations!$D$27*$B5)+Declarations!$E$27*($B5/Declarations!$F$27)*EXP(1-$B5/Declarations!$F$27) -> 100 | D5: =Per_point*C5 -> 620 | E5: =Declarations!$C$27+(Declarations!$B$27-Declarations!$C$27)*EXP(-Declarations!$D$27*$B5)+(-Depth_ph)*($B5/Declarations!$F$27)*EXP(1-$B5/Declarations!$F$27) -> 100 | F5: =Per_point*E5 -> 620 | G5: =IF(D5<$K$19,1,0) -> 0 | H5: =IF(F5<$K$19,1,0) -> 0 | J5: Cash above the floor, A | K5: =Pool_cash -> 270 | L5: $270 million
A6: 1 | B6: =A6/4 -> 0.25 | C6: =Declarations!$C$27+(Declarations!$B$27-Declarations!$C$27)*EXP(-Declarations!$D$27*$B6)+Declarations!$E$27*($B6/Declarations!$F$27)*EXP(1-$B6/Declarations!$F$27) -> 92.60931 | D6: =Per_point*C6 -> 574.17772 | E6: =Declarations!$C$27+(Declarations!$B$27-Declarations!$C$27)*EXP(-Declarations!$D$27*$B6)+(-Depth_ph)*($B6/Declarations!$F$27)*EXP(1-$B6/Declarations!$F$27) -> 95.008185 | F6: =Per_point*E6 -> 589.05075 | G6: =IF(D6<$K$19,1,0) -> 0 | H6: =IF(F6<$K$19,1,0) -> 0 | J6: The plan's lowest liquidity | K6: =MIN($D$5:$D$17) -> 481.95038 | L6: $482 million
A7: 2 | B7: =A7/4 -> 0.5 | C7: =Declarations!$C$27+(Declarations!$B$27-Declarations!$C$27)*EXP(-Declarations!$D$27*$B7)+Declarations!$E$27*($B7/Declarations!$F$27)*EXP(1-$B7/Declarations!$F$27) -> 87.107516 | D7: =Per_point*C7 -> 540.0666 | E7: =Declarations!$C$27+(Declarations!$B$27-Declarations!$C$27)*EXP(-Declarations!$D$27*$B7)+(-Depth_ph)*($B7/Declarations!$F$27)*EXP(1-$B7/Declarations!$F$27) -> 91.341516 | F7: =Per_point*E7 -> 566.3174 | G7: =IF(D7<$K$19,1,0) -> 0 | H7: =IF(F7<$K$19,1,0) -> 0 | J7: The program's deepest draw, D | K7: =Liq_today-K6 -> 138.04962 | L7: $138 million
A8: 3 | B8: =A8/4 -> 0.75 | C8: =Declarations!$C$27+(Declarations!$B$27-Declarations!$C$27)*EXP(-Declarations!$D$27*$B8)+Declarations!$E$27*($B8/Declarations!$F$27)*EXP(1-$B8/Declarations!$F$27) -> 83.153901 | D8: =Per_point*C8 -> 515.55419 | E8: =Declarations!$C$27+(Declarations!$B$27-Declarations!$C$27)*EXP(-Declarations!$D$27*$B8)+(-Depth_ph)*($B8/Declarations!$F$27)*EXP(1-$B8/Declarations!$F$27) -> 88.758639 | F8: =Per_point*E8 -> 550.30356 | G8: =IF(D8<$K$19,1,0) -> 1 | H8: =IF(F8<$K$19,1,0) -> 0 | J8: Quarter of the deepest draw | K8: =INDEX($A$5:$A$17,MATCH(K6,$D$5:$D$17,0)) -> 7 | L8: quarter 7
A9: 4 | B9: =A9/4 -> 1 | C9: =Declarations!$C$27+(Declarations!$B$27-Declarations!$C$27)*EXP(-Declarations!$D$27*$B9)+Declarations!$E$27*($B9/Declarations!$F$27)*EXP(1-$B9/Declarations!$F$27) -> 80.461645 | D9: =Per_point*C9 -> 498.8622 | E9: =Declarations!$C$27+(Declarations!$B$27-Declarations!$C$27)*EXP(-Declarations!$D$27*$B9)+(-Depth_ph)*($B9/Declarations!$F$27)*EXP(1-$B9/Declarations!$F$27) -> 87.05653 | F9: =Per_point*E9 -> 539.75049 | G9: =IF(D9<$K$19,1,0) -> 1 | H9: =IF(F9<$K$19,1,0) -> 0 | J9: Funding sign-off (CFO, transformation office): D within A | K9: =IF(K7<=K5,"pass","fail") -> pass | L9: funded
A10: 5 | B10: =A10/4 -> 1.25 | C10: =Declarations!$C$27+(Declarations!$B$27-Declarations!$C$27)*EXP(-Declarations!$D$27*$B10)+Declarations!$E$27*($B10/Declarations!$F$27)*EXP(1-$B10/Declarations!$F$27) -> 78.789868 | D10: =Per_point*C10 -> 488.49718 | E10: =Declarations!$C$27+(Declarations!$B$27-Declarations!$C$27)*EXP(-Declarations!$D$27*$B10)+(-Depth_ph)*($B10/Declarations!$F$27)*EXP(1-$B10/Declarations!$F$27) -> 86.064825 | F10: =Per_point*E10 -> 533.60192 | G10: =IF(D10<$K$19,1,0) -> 1 | H10: =IF(F10<$K$19,1,0) -> 1 | J10: Funding sign-off: spare | K10: =K5-K7 -> 131.95038 | L10: $132 million
A11: 6 | B11: =A11/4 -> 1.5 | C11: =Declarations!$C$27+(Declarations!$B$27-Declarations!$C$27)*EXP(-Declarations!$D$27*$B11)+Declarations!$E$27*($B11/Declarations!$F$27)*EXP(1-$B11/Declarations!$F$27) -> 77.936802 | D11: =Per_point*C11 -> 483.20817 | E11: =Declarations!$C$27+(Declarations!$B$27-Declarations!$C$27)*EXP(-Declarations!$D$27*$B11)+(-Depth_ph)*($B11/Declarations!$F$27)*EXP(1-$B11/Declarations!$F$27) -> 85.640954 | F11: =Per_point*E11 -> 530.97392 | G11: =IF(D11<$K$19,1,0) -> 1 | H11: =IF(F11<$K$19,1,0) -> 1 | J11: Closure: median | K11: =GAMMAINV(Med_pct,G_shape,G_scale) -> 113.13158 | L11: $113 million
A12: 7 | B12: =A12/4 -> 1.75 | C12: =Declarations!$C$27+(Declarations!$B$27-Declarations!$C$27)*EXP(-Declarations!$D$27*$B12)+Declarations!$E$27*($B12/Declarations!$F$27)*EXP(1-$B12/Declarations!$F$27) -> 77.733933 | D12: =Per_point*C12 -> 481.95038 | E12: =Declarations!$C$27+(Declarations!$B$27-Declarations!$C$27)*EXP(-Declarations!$D$27*$B12)+(-Depth_ph)*($B12/Declarations!$F$27)*EXP(1-$B12/Declarations!$F$27) -> 85.665972 | F12: =Per_point*E12 -> 531.12903 | G12: =IF(D12<$K$19,1,0) -> 1 | H12: =IF(F12<$K$19,1,0) -> 1 | J12: Closure: 90th percentile, the buffer B | K12: =GAMMAINV(Buf_pct,G_shape,G_scale) -> 186.86698 | L12: $187 million
A13: 8 | B13: =A13/4 -> 2 | C13: =Declarations!$C$27+(Declarations!$B$27-Declarations!$C$27)*EXP(-Declarations!$D$27*$B13)+Declarations!$E$27*($B13/Declarations!$F$27)*EXP(1-$B13/Declarations!$F$27) -> 78.040976 | D13: =Per_point*C13 -> 483.85405 | E13: =Declarations!$C$27+(Declarations!$B$27-Declarations!$C$27)*EXP(-Declarations!$D$27*$B13)+(-Depth_ph)*($B13/Declarations!$F$27)*EXP(1-$B13/Declarations!$F$27) -> 86.040976 | F13: =Per_point*E13 -> 533.45405 | G13: =IF(D13<$K$19,1,0) -> 1 | H13: =IF(F13<$K$19,1,0) -> 1 | J13: Buffer sign-off (CFO, CRO): B within A | K13: =IF(K12<=K5,"pass","fail") -> pass | L13: funded
A14: 9 | B14: =A14/4 -> 2.25 | C14: =Declarations!$C$27+(Declarations!$B$27-Declarations!$C$27)*EXP(-Declarations!$D$27*$B14)+Declarations!$E$27*($B14/Declarations!$F$27)*EXP(1-$B14/Declarations!$F$27) -> 78.741578 | D14: =Per_point*C14 -> 488.19778 | E14: =Declarations!$C$27+(Declarations!$B$27-Declarations!$C$27)*EXP(-Declarations!$D$27*$B14)+(-Depth_ph)*($B14/Declarations!$F$27)*EXP(1-$B14/Declarations!$F$27) -> 86.68405 | F14: =Per_point*E14 -> 537.44111 | G14: =IF(D14<$K$19,1,0) -> 1 | H14: =IF(F14<$K$19,1,0) -> 0 | J14: Buffer sign-off: spare | K14: =K5-K12 -> 83.133024 | L14: $83 million
A15: 10 | B15: =A15/4 -> 2.5 | C15: =Declarations!$C$27+(Declarations!$B$27-Declarations!$C$27)*EXP(-Declarations!$D$27*$B15)+Declarations!$E$27*($B15/Declarations!$F$27)*EXP(1-$B15/Declarations!$F$27) -> 79.739628 | D15: =Per_point*C15 -> 494.3857 | E15: =Declarations!$C$27+(Declarations!$B$27-Declarations!$C$27)*EXP(-Declarations!$D$27*$B15)+(-Depth_ph)*($B15/Declarations!$F$27)*EXP(1-$B15/Declarations!$F$27) -> 87.527636 | F15: =Per_point*E15 -> 542.67134 | G15: =IF(D15<$K$19,1,0) -> 1 | H15: =IF(F15<$K$19,1,0) -> 0 | J15: Schedule sign-off (transformation office, CRO) | K15: no constraint on the pair alone: pass | L15: within appetite, because the buffer is held
A16: 11 | B16: =A16/4 -> 2.75 | C16: =Declarations!$C$27+(Declarations!$B$27-Declarations!$C$27)*EXP(-Declarations!$D$27*$B16)+Declarations!$E$27*($B16/Declarations!$F$27)*EXP(1-$B16/Declarations!$F$27) -> 80.956121 | D16: =Per_point*C16 -> 501.92795 | E16: =Declarations!$C$27+(Declarations!$B$27-Declarations!$C$27)*EXP(-Declarations!$D$27*$B16)+(-Depth_ph)*($B16/Declarations!$F$27)*EXP(1-$B16/Declarations!$F$27) -> 88.516303 | F16: =Per_point*E16 -> 548.80108 | G16: =IF(D16<$K$19,1,0) -> 1 | H16: =IF(F16<$K$19,1,0) -> 0 | J16: Joint check: D + B | K16: =K7+K12 -> 324.91659 | L16: $325 million
A17: 12 | B17: =A17/4 -> 3 | C17: =Declarations!$C$27+(Declarations!$B$27-Declarations!$C$27)*EXP(-Declarations!$D$27*$B17)+Declarations!$E$27*($B17/Declarations!$F$27)*EXP(1-$B17/Declarations!$F$27) -> 82.326459 | D17: =Per_point*C17 -> 510.42405 | E17: =Declarations!$C$27+(Declarations!$B$27-Declarations!$C$27)*EXP(-Declarations!$D$27*$B17)+(-Depth_ph)*($B17/Declarations!$F$27)*EXP(1-$B17/Declarations!$F$27) -> 89.604827 | F17: =Per_point*E17 -> 555.54993 | G17: =IF(D17<$K$19,1,0) -> 1 | H17: =IF(F17<$K$19,1,0) -> 0 | J17: Joint check: A - (D + B) | K17: =K5-K16 -> -54.916594 | L17: infeasible by $55 million
J18: Joint check | K18: =IF(K17>=0,"feasible","infeasible") -> infeasible | L18: the same cash promised twice
J19: Buffer line: floor + B | K19: =Floor_liq+K12 -> 536.86698 | L19: $537 million
J20: Plan inside the buffer line: quarters | K20: =SUM($G$5:$G$17) -> 10 | L20: quarters 3-12
J21: Plan inside the buffer line: first quarter | K21: =_xlfn.MINIFS($A$5:$A$17,$G$5:$G$17,1) -> 3 | L21: quarter 3
J22: Plan inside the buffer line: last quarter | K22: =_xlfn.MAXIFS($A$5:$A$17,$G$5:$G$17,1) -> 12 | L22: quarter 12
J23: Plan inside the buffer line: deepest | K23: =K19-K6 -> 54.916594 | L23: 55 deep at quarter 7
J24: The phased build's lowest liquidity | K24: =MIN($F$5:$F$17) -> 530.97392 | L24: $531 million
J25: Phased inside the buffer line: first quarter | K25: =_xlfn.MINIFS($A$5:$A$17,$H$5:$H$17,1) -> 5 | L25: quarters 5-8
J26: The phased build's deepest draw | K26: =Liq_today-K24 -> 89.026083 | L26: $89 million
J27: Phased inside the buffer line: last quarter | K27: =_xlfn.MAXIFS($A$5:$A$17,$H$5:$H$17,1) -> 8
J28: Phased inside the buffer line: deepest | K28: =K19-K24 -> 5.8930592 | L28: at most 6
J30: Constraint graph of D + B <= A: nodes | K30: 3 | L30: draw, buffer, cash (Online Appendix 13.B.2)
J31: Edges: every pair shares the one scope | K31: =K30*(K30-1)/2 -> 3 | L31: a triangle
J32: Independent cycles: edges - nodes + 1 | K32: =K31-K30+1 -> 1 | L32: a cycle: bilateral checks cannot certify it

Sheet Repairs
A1: Repair it three ways: Table 13.6 (Worked Example 13.1, Step 4; Online Appendix 13.B.4)
A2: The draw is the program's deepest cash draw; the cash buffer is the closure percentile the risk office declares, less the standby line's cover.
A4: Declaration | B4: Draw | C4: Cash buffer | D4: Total claims | E4: Spare cash | F4: Joint check | G4: Ledger of the repair
A5: As signed off | B5: =JointCheck!$K$7 -> 138.04962 | C5: =JointCheck!$K$12 -> 186.86698 | D5: =B5+C5 -> 324.91659 | E5: =Pool_cash-D5 -> -54.916594 | F5: =IF(E5>=0,"passes","fails") -> fails | G5: -
A6: Buffer at the median closure | B6: =JointCheck!$K$7 -> 138.04962 | C6: =JointCheck!$K$11 -> 113.13158 | D6: =B6+C6 -> 251.18119 | E6: =Pool_cash-D6 -> 18.818807 | F6: =IF(E6>=0,"passes","fails") -> passes | G6: risk
A7: Phased build | B7: =JointCheck!$K$26 -> 89.026083 | C7: =JointCheck!$K$12 -> 186.86698 | D7: =B7+C7 -> 275.89306 | E7: =Pool_cash-D7 -> -5.8930592 | F7: =IF(E7>=0,"passes","fails") -> fails | G7: transformation
A8: Standby line | B8: =JointCheck!$K$7 -> 138.04962 | C8: =MAX(JointCheck!$K$12-Line_cover,0) -> 86.866976 | D8: =B8+C8 -> 224.91659 | E8: =Pool_cash-D8 -> 45.083406 | F8: =IF(E8>=0,"passes","fails") -> passes | G8: capital
A9: Both levers | B9: =JointCheck!$K$26 -> 89.026083 | C9: =MAX(JointCheck!$K$12-Line_cover,0) -> 86.866976 | D9: =B9+C9 -> 175.89306 | E9: =Pool_cash-D9 -> 94.106941 | F9: =IF(E9>=0,"passes","fails") -> passes | G9: transformation + capital
A11: Relaxing the buffer to the median passes only by lowering the bar: half of all closures would exceed it, and the breach odds stay at 24.6 percent (Decide).

Sheet Decide
A1: Decide in one place: the separated verdicts and the unified one (Worked Example 13.1, Step 5; Proposition 13.5; AXIOM Lab 1.13, step 5)
A2: Breach odds: the engine's simulation of Chapter 8's 100,000 paths with the book's seed 8 (Worked Example 12.1); the fresh stream uses the lab's seed 26113.
A4: Declaration | B4: Ledger of the repair | C4: Spare cash (joint check) | D4: Joint check | E4: Breach probability (engine, seed 8) | F4: Standard error (engine) | G4: Risk ledger: within the appetite | H4: Every ledger | I4: Fresh stream (engine, seed 26113)
A5: As signed off | B5: - | C5: =Repairs!E5 -> -54.916594 | D5: =IF(C5>=0,"pass","fail") -> fail | E5: 0.24622 | F5: 0.0013623352 | G5: =IF(E5<=Appetite,"pass","fail") -> fail | H5: =IF(AND(D5="pass",G5="pass"),"yes","no") -> no | I5: 0.24538
A6: Buffer at the median closure | B6: risk | C6: =Repairs!E6 -> 18.818807 | D6: =IF(C6>=0,"pass","fail") -> pass | E6: 0.24622 | F6: 0.0013623352 | G6: =IF(E6<=Appetite,"pass","fail") -> fail | H6: =IF(AND(D6="pass",G6="pass"),"yes","no") -> no | I6: 0.24538
A7: Phased build | B7: transformation | C7: =Repairs!E7 -> -5.8930592 | D7: =IF(C7>=0,"pass","fail") -> fail | E7: 0.13068 | F7: 0.0010658459 | G7: =IF(E7<=Appetite,"pass","fail") -> fail | H7: =IF(AND(D7="pass",G7="pass"),"yes","no") -> no | I7: 0.1313
A8: Standby line | B8: capital | C8: =Repairs!E8 -> 45.083406 | D8: =IF(C8>=0,"pass","fail") -> pass | E8: 0.12374 | F8: 0.0010412896 | G8: =IF(E8<=Appetite,"pass","fail") -> fail | H8: =IF(AND(D8="pass",G8="pass"),"yes","no") -> no | I8: 0.12313
A9: Both levers | B9: transformation + capital | C9: =Repairs!E9 -> 94.106941 | D9: =IF(C9>=0,"pass","fail") -> pass | E9: 0.03003 | F9: 0.00053970547 | G9: =IF(E9<=Appetite,"pass","fail") -> pass | H9: =IF(AND(D9="pass",G9="pass"),"yes","no") -> yes | I9: 0.03025
A11: Separated choices (one ledger's repair each) that pass every ledger | B11: =COUNTIF(H6:H8,"yes") -> 0 | C11: none: each repair alone fails a ledger
A12: Declarations that pass every ledger | B12: =COUNTIF(H5:H9,"yes") -> 1 | C12: only both levers
A13: The plan's planned low ($ million) | B13: =JointCheck!K6 -> 481.95038 | C13: $482 million
A14: Average of the simulated lows ($ million, engine, seed 8) | B14: 383.83151 | C14: $384 million (Worked Example 8.1)
A15: The flaw of averages: planned low less the average | B15: =B13-B14 -> 98.11887 | C15: Theorem 13.4(iv)
A17: Proposition 13.5(ii): a separated choice is the unified problem with the other ledgers' repairs ruled out, so it never does better; here it does strictly worse, because no single-ledger repair passes.

Sheet Reference_Values
A1: Checkpoint | B1: Engine value | C1: Meaning (where in the book)
A2: Components in the skeleton | B2: 7 | C2: Table 13.1: seven components
A3: Feedback core: components | B3: 4 | C3: Table 13.1: a feedback core of four
A4: Forms of capital | B4: 10 | C4: Table 13.1: ten forms
A5: Performance dimensions | B5: 10 | C5: Table 13.1: ten dimensions
A6: Capability rent, $ million a year | B6: 23.2 | C6: Table 13.1: $23 million a year
A7: Unresolved references (C1) | B7: 0 | C7: Definition 13.4: every carrier is a component
A8: Claims on treasury cash after assembly, order 1 | B8: 324.91659 | C8: (C4): $325 million on $270 million
A9: Claims on treasury cash after assembly, order 2 | B9: 324.91659 | C9: Theorem 13.2(i): the same object
A10: Cash above the floor today | B10: 270 | C10: Worked Example 13.1, Step 1: $270 million
A11: Each layer alone: total impact | B11: 2 | C11: Figure 13.2: 2
A12: Total impact, no coupling | B12: 2 | C12: Figure 13.2: 2
A13: Total impact at c = 0.25 | B13: 4 | C13: Figure 13.2: 4
... A73: Repairs that pass every ledger | B73: 1 | C73: Step 5: only both levers

Sheet Checks
A1: Checkpoint | B1: Workbook formula value | C1: Engine value | D1: |diff| | E1: Tolerance | F1: Status
A2: Components in the skeleton | B2: =Assemble!B34 -> 7 | C2: =Reference_Values!B2 -> 7 | D2: =ABS(B2-C2) -> 0 | E2: 0 | F2: =IF(D2<=E2,"PASS","FAIL") -> PASS
A3: Feedback core: components | B3: =Wavefront!B118 -> 4 | C3: =Reference_Values!B3 -> 4 | D3: =ABS(B3-C3) -> 0 | E3: 0 | F3: =IF(D3<=E3,"PASS","FAIL") -> PASS
A4: Forms of capital | B4: =Assemble!B37 -> 10 | C4: =Reference_Values!B4 -> 10 | D4: =ABS(B4-C4) -> 0 | E4: 0 | F4: =IF(D4<=E4,"PASS","FAIL") -> PASS
A5: Performance dimensions | B5: =Assemble!B38 -> 10 | C5: =Reference_Values!B5 -> 10 | D5: =ABS(B5-C5) -> 0 | E5: 0 | F5: =IF(D5<=E5,"PASS","FAIL") -> PASS
A6: Capability rent, $ million a year | B6: =Assemble!B39 -> 23.2 | C6: =Reference_Values!B6 -> 23.2 | D6: =ABS(B6-C6) -> 0 | E6: 1e-09 | F6: =IF(D6<=E6,"PASS","FAIL") -> PASS
A7: Unresolved references (C1) | B7: =Assemble!B118 -> 0 | C7: =Reference_Values!B7 -> 0 | D7: =ABS(B7-C7) -> 0 | E7: 0 | F7: =IF(D7<=E7,"PASS","FAIL") -> PASS
A8: Claims on treasury cash after assembly, order 1 | B8: =Assemble!B114 -> 324.91659 | C8: =Reference_Values!B8 -> 324.91659 | D8: =ABS(B8-C8) -> 0 | E8: 1e-09 | F8: =IF(D8<=E8,"PASS","FAIL") -> PASS
A9: Claims on treasury cash after assembly, order 2 | B9: =Assemble!B115 -> 324.91659 | C9: =Reference_Values!B9 -> 324.91659 | D9: =ABS(B9-C9) -> 0 | E9: 1e-09 | F9: =IF(D9<=E9,"PASS","FAIL") -> PASS
A10: Cash above the floor today | B10: =JointCheck!K5 -> 270 | C10: =Reference_Values!B10 -> 270 | D10: =ABS(B10-C10) -> 0 | E10: 1e-09 | F10: =IF(D10<=E10,"PASS","FAIL") -> PASS
A11: Each layer alone: total impact | B11: =Couplings!B11 -> 2 | C11: =Reference_Values!B11 -> 2 | D11: =ABS(B11-C11) -> 0 | E11: 1e-09 | F11: =IF(D11<=E11,"PASS","FAIL") -> PASS
A12: Total impact, no coupling | B12: =IF(ISNUMBER(Couplings!J5),Couplings!J5,-1) -> 2 | C12: =Reference_Values!B12 -> 2 | D12: =ABS(B12-C12) -> 0 | E12: 1e-09 | F12: =IF(D12<=E12,"PASS","FAIL") -> PASS
A13: Total impact at c = 0.25 | B13: =IF(ISNUMBER(Couplings!J8),Couplings!J8,-1) -> 4 | C13: =Reference_Values!B13 -> 4 | D13: =ABS(B13-C13) -> 0 | E13: 1e-09 | F13: =IF(D13<=E13,"PASS","FAIL") -> PASS
A14: Total impact at c = 0.40 | B14: =IF(ISNUMBER(Couplings!J10),Couplings!J10,-1) -> 10 | C14: =Reference_Values!B14 -> 10 | D14: =ABS(B14-C14) -> 0 | E14: 1e-09 | F14: =IF(D14<=E14,"PASS","FAIL") -> PASS
A15: rho(M) at c = 0.25, a + c | B15: =Couplings!B12 -> 0.75 | C15: =Reference_Values!B15 -> 0.75 | D15: =ABS(B15-C15) -> 0 | E15: 1e-09 | F15: =IF(D15<=E15,"PASS","FAIL") -> PASS
A16: rho(M) at c = 0.5 | B16: =Couplings!I12 -> 1 | C16: =Reference_Values!B16 -> 1 | D16: =ABS(B16-C16) -> 0 | E16: 1e-09 | F16: =IF(D16<=E16,"PASS","FAIL") -> PASS
A17: Cumulative bill after 200 quarters, c = 0.25 | B17: =Couplings!B16 -> 4 | C17: =Reference_Values!B17 -> 4 | D17: =ABS(B17-C17) -> 0 | E17: 1e-09 | F17: =IF(D17<=E17,"PASS","FAIL") -> PASS
A18: Cross-layer blocks' part of rho(M), c = 0.25 | B18: =Couplings!B15 -> 0.25 | C18: =Reference_Values!B18 -> 0.25 | D18: =ABS(B18-C18) -> 0 | E18: 1e-09 | F18: =IF(D18<=E18,"PASS","FAIL") -> PASS
A19: Editor: rho(M) by power iteration | B19: =Couplings!Q15 -> 0.75 | C19: =Reference_Values!B19 -> 0.75 | D19: =ABS(B19-C19) -> 0 | E19: 1e-09 | F19: =IF(D19<=E19,"PASS","FAIL") -> PASS
A20: Editor: cross-layer blocks' part | B20: =Couplings!Q19 -> 0.25 | C20: =Reference_Values!B20 -> 0.25 | D20: =ABS(B20-C20) -> 0 | E20: 1e-09 | F20: =IF(D20<=E20,"PASS","FAIL") -> PASS
A21: Editor: total impact of a unit loss | B21: =IF(ISNUMBER(Couplings!Q21),Couplings!Q21,-1) -> 4 | C21: =Reference_Values!B21 -> 4 | D21: =ABS(B21-C21) -> 0 | E21: 1e-09 | F21: =IF(D21<=E21,"PASS","FAIL") -> PASS
A22: Program: quarters to treasury | B22: =Wavefront!I79 -> 1 | C22: =Reference_Values!B22 -> 1 | D22: =ABS(B22-C22) -> 0 | E22: 0 | F22: =IF(D22<=E22,"PASS","FAIL") -> PASS
A23: Program: quarters to Industrial Systems | B23: =Wavefront!I80 -> 1 | C23: =Reference_Values!B23 -> 1 | D23: =ABS(B23-C23) -> 0 | E23: 0 | F23: =IF(D23<=E23,"PASS","FAIL") -> PASS
A24: Program: components never reached | B24: =Wavefront!I81 -> 3 | C24: =Reference_Values!B24 -> 3 | D24: =ABS(B24-C24) -> 0 | E24: 0 | F24: =IF(D24<=E24,"PASS","FAIL") -> PASS
A25: Demand shock: quarters to the divisions | B25: =Wavefront!I82 -> 1 | C25: =Reference_Values!B25 -> 1 | D25: =ABS(B25-C25) -> 0 | E25: 0 | F25: =IF(D25<=E25,"PASS","FAIL") -> PASS
A26: Demand shock: quarters to engineering | B26: =Wavefront!I83 -> 2 | C26: =Reference_Values!B26 -> 2 | D26: =ABS(B26-C26) -> 0 | E26: 0 | F26: =IF(D26<=E26,"PASS","FAIL") -> PASS
A27: Demand shock: quarters to treasury | B27: =Wavefront!I84 -> 2 | C27: =Reference_Values!B27 -> 2 | D27: =ABS(B27-C27) -> 0 | E27: 0 | F27: =IF(D27<=E27,"PASS","FAIL") -> PASS
A28: Readouts whose clocks match the engine | B28: =Wavefront!L106 -> 17 | C28: =Reference_Values!B28 -> 17 | D28: =ABS(B28-C28) -> 0 | E28: 0 | F28: =IF(D28<=E28,"PASS","FAIL") -> PASS
A29: Ancestors of treasury | B29: =Wavefront!B119 -> 7 | C29: =Reference_Values!B29 -> 7 | D29: =ABS(B29-C29) -> 0 | E29: 0 | F29: =IF(D29<=E29,"PASS","FAIL") -> PASS
A30: Ancestors of Materials | B30: =Wavefront!B120 -> 2 | C30: =Reference_Values!B30 -> 2 | D30: =ABS(B30-C30) -> 0 | E30: 0 | F30: =IF(D30<=E30,"PASS","FAIL") -> PASS
A31: Plan liquidity, quarter 1 | B31: =JointCheck!D6 -> 574.17772 | C31: =Reference_Values!B31 -> 574.17772 | D31: =ABS(B31-C31) -> 0 | E31: 1e-09 | F31: =IF(D31<=E31,"PASS","FAIL") -> PASS
A32: Plan liquidity, quarter 12 | B32: =JointCheck!D17 -> 510.42405 | C32: =Reference_Values!B32 -> 510.42405 | D32: =ABS(B32-C32) -> 0 | E32: 1e-09 | F32: =IF(D32<=E32,"PASS","FAIL") -> PASS
A33: Phased liquidity, quarter 1 | B33: =JointCheck!F6 -> 589.05075 | C33: =Reference_Values!B33 -> 589.05075 | D33: =ABS(B33-C33) -> 0 | E33: 1e-09 | F33: =IF(D33<=E33,"PASS","FAIL") -> PASS
A34: Phased liquidity, quarter 12 | B34: =JointCheck!F17 -> 555.54993 | C34: =Reference_Values!B34 -> 555.54993 | D34: =ABS(B34-C34) -> 0 | E34: 1e-09 | F34: =IF(D34<=E34,"PASS","FAIL") -> PASS
A35: Deepest draw | B35: =JointCheck!K7 -> 138.04962 | C35: =Reference_Values!B35 -> 138.04962 | D35: =ABS(B35-C35) -> 0 | E35: 1e-09 | F35: =IF(D35<=E35,"PASS","FAIL") -> PASS
A36: Quarter of the deepest draw | B36: =JointCheck!K8 -> 7 | C36: =Reference_Values!B36 -> 7 | D36: =ABS(B36-C36) -> 0 | E36: 0 | F36: =IF(D36<=E36,"PASS","FAIL") -> PASS
A37: Funding check: spare | B37: =JointCheck!K10 -> 131.95038 | C37: =Reference_Values!B37 -> 131.95038 | D37: =ABS(B37-C37) -> 0 | E37: 1e-09 | F37: =IF(D37<=E37,"PASS","FAIL") -> PASS
A38: Closure: 90th percentile | B38: =JointCheck!K12 -> 186.86698 | C38: =Reference_Values!B38 -> 186.86698 | D38: =ABS(B38-C38) -> 0 | E38: 1e-06 | F38: =IF(D38<=E38,"PASS","FAIL") -> PASS
A39: Buffer check: spare | B39: =JointCheck!K14 -> 83.133024 | C39: =Reference_Values!B39 -> 83.133024 | D39: =ABS(B39-C39) -> 0 | E39: 1e-06 | F39: =IF(D39<=E39,"PASS","FAIL") -> PASS
A40: Closure: median | B40: =JointCheck!K11 -> 113.13158 | C40: =Reference_Values!B40 -> 113.13158 | D40: =ABS(B40-C40) -> 0 | E40: 1e-06 | F40: =IF(D40<=E40,"PASS","FAIL") -> PASS
A41: Joint check: total claims | B41: =JointCheck!K16 -> 324.91659 | C41: =Reference_Values!B41 -> 324.91659 | D41: =ABS(B41-C41) -> 0 | E41: 1e-06 | F41: =IF(D41<=E41,"PASS","FAIL") -> PASS
A42: Joint check: spare | B42: =JointCheck!K17 -> -54.916594 | C42: =Reference_Values!B42 -> -54.916594 | D42: =ABS(B42-C42) -> 0 | E42: 1e-06 | F42: =IF(D42<=E42,"PASS","FAIL") -> PASS
A43: Constraint graph: independent cycles | B43: =JointCheck!K32 -> 1 | C43: =Reference_Values!B43 -> 1 | D43: =ABS(B43-C43) -> 0 | E43: 0 | F43: =IF(D43<=E43,"PASS","FAIL") -> PASS
A44: Buffer line | B44: =JointCheck!K19 -> 536.86698 | C44: =Reference_Values!B44 -> 536.86698 | D44: =ABS(B44-C44) -> 0 | E44: 1e-06 | F44: =IF(D44<=E44,"PASS","FAIL") -> PASS
A45: Plan inside the buffer line: first quarter | B45: =JointCheck!K21 -> 3 | C45: =Reference_Values!B45 -> 3 | D45: =ABS(B45-C45) -> 0 | E45: 0 | F45: =IF(D45<=E45,"PASS","FAIL") -> PASS
A46: Plan inside the buffer line: last quarter | B46: =JointCheck!K22 -> 12 | C46: =Reference_Values!B46 -> 12 | D46: =ABS(B46-C46) -> 0 | E46: 0 | F46: =IF(D46<=E46,"PASS","FAIL") -> PASS
A47: Plan inside the buffer line: deepest | B47: =JointCheck!K23 -> 54.916594 | C47: =Reference_Values!B47 -> 54.916594 | D47: =ABS(B47-C47) -> 0 | E47: 1e-06 | F47: =IF(D47<=E47,"PASS","FAIL") -> PASS
A48: Phased inside the buffer line: first quarter | B48: =JointCheck!K25 -> 5 | C48: =Reference_Values!B48 -> 5 | D48: =ABS(B48-C48) -> 0 | E48: 0 | F48: =IF(D48<=E48,"PASS","FAIL") -> PASS
A49: Phased inside the buffer line: last quarter | B49: =JointCheck!K27 -> 8 | C49: =Reference_Values!B49 -> 8 | D49: =ABS(B49-C49) -> 0 | E49: 0 | F49: =IF(D49<=E49,"PASS","FAIL") -> PASS
A50: Phased inside the buffer line: deepest | B50: =JointCheck!K28 -> 5.8930592 | C50: =Reference_Values!B50 -> 5.8930592 | D50: =ABS(B50-C50) -> 1.1368684e-13 | E50: 1e-06 | F50: =IF(D50<=E50,"PASS","FAIL") -> PASS
A51: Median buffer: total claims | B51: =Repairs!D6 -> 251.18119 | C51: =Reference_Values!B51 -> 251.18119 | D51: =ABS(B51-C51) -> 0 | E51: 1e-06 | F51: =IF(D51<=E51,"PASS","FAIL") -> PASS
A52: Median buffer: spare | B52: =Repairs!E6 -> 18.818807 | C52: =Reference_Values!B52 -> 18.818807 | D52: =ABS(B52-C52) -> 0 | E52: 1e-06 | F52: =IF(D52<=E52,"PASS","FAIL") -> PASS
A53: Phased build: draw | B53: =Repairs!B7 -> 89.026083 | C53: =Reference_Values!B53 -> 89.026083 | D53: =ABS(B53-C53) -> 0 | E53: 1e-09 | F53: =IF(D53<=E53,"PASS","FAIL") -> PASS
A54: Phased build: total claims | B54: =Repairs!D7 -> 275.89306 | C54: =Reference_Values!B54 -> 275.89306 | D54: =ABS(B54-C54) -> 0 | E54: 1e-06 | F54: =IF(D54<=E54,"PASS","FAIL") -> PASS
A55: Phased build: spare | B55: =Repairs!E7 -> -5.8930592 | C55: =Reference_Values!B55 -> -5.8930592 | D55: =ABS(B55-C55) -> 8.437695e-14 | E55: 1e-06 | F55: =IF(D55<=E55,"PASS","FAIL") -> PASS
A56: Standby line: cash buffer | B56: =Repairs!C8 -> 86.866976 | C56: =Reference_Values!B56 -> 86.866976 | D56: =ABS(B56-C56) -> 0 | E56: 1e-06 | F56: =IF(D56<=E56,"PASS","FAIL") -> PASS
A57: Standby line: total claims | B57: =Repairs!D8 -> 224.91659 | C57: =Reference_Values!B57 -> 224.91659 | D57: =ABS(B57-C57) -> 0 | E57: 1e-06 | F57: =IF(D57<=E57,"PASS","FAIL") -> PASS
A58: Standby line: spare | B58: =Repairs!E8 -> 45.083406 | C58: =Reference_Values!B58 -> 45.083406 | D58: =ABS(B58-C58) -> 0 | E58: 1e-06 | F58: =IF(D58<=E58,"PASS","FAIL") -> PASS
A59: Both levers: total claims | B59: =Repairs!D9 -> 175.89306 | C59: =Reference_Values!B59 -> 175.89306 | D59: =ABS(B59-C59) -> 0 | E59: 1e-06 | F59: =IF(D59<=E59,"PASS","FAIL") -> PASS
A60: Both levers: spare | B60: =Repairs!E9 -> 94.106941 | C60: =Reference_Values!B60 -> 94.106941 | D60: =ABS(B60-C60) -> 0 | E60: 1e-06 | F60: =IF(D60<=E60,"PASS","FAIL") -> PASS
A61: Scorecard today | B61: =Ledgers!K5 -> 37 | C61: =Reference_Values!B61 -> 37 | D61: =ABS(B61-C61) -> 0 | E61: 1e-09 | F61: =IF(D61<=E61,"PASS","FAIL") -> PASS
A62: Liquidity low, $ million | B62: =Ledgers!K6 -> 481.95038 | C62: =Reference_Values!B62 -> 481.95038 | D62: =ABS(B62-C62) -> 0 | E62: 1e-09 | F62: =IF(D62<=E62,"PASS","FAIL") -> PASS
A63: Month of the liquidity low | B63: =Ledgers!K7 -> 21 | C63: =Reference_Values!B63 -> 21 | D63: =ABS(B63-C63) -> 0 | E63: 0 | F63: =IF(D63<=E63,"PASS","FAIL") -> PASS
A64: Scorecard low | B64: =Ledgers!K8 -> 32.106467 | C64: =Reference_Values!B64 -> 32.106467 | D64: =ABS(B64-C64) -> 0 | E64: 1e-09 | F64: =IF(D64<=E64,"PASS","FAIL") -> PASS
A65: Month of the scorecard low | B65: =Ledgers!K9 -> 11 | C65: =Reference_Values!B65 -> 11 | D65: =ABS(B65-C65) -> 0 | E65: 0 | F65: =IF(D65<=E65,"PASS","FAIL") -> PASS
A66: Month the scorecard regains 37.0 | B66: =Ledgers!K10 -> 29 | C66: =Reference_Values!B66 -> 29 | D66: =ABS(B66-C66) -> 0 | E66: 0 | F66: =IF(D66<=E66,"PASS","FAIL") -> PASS
A67: Scorecard in that month | B67: =Ledgers!K11 -> 37.18741 | C67: =Reference_Values!B67 -> 37.18741 | D67: =ABS(B67-C67) -> 0 | E67: 1e-09 | F67: =IF(D67<=E67,"PASS","FAIL") -> PASS
A68: Strategic-risk peak | B68: =Ledgers!K12 -> 73.552064 | C68: =Reference_Values!B68 -> 73.552064 | D68: =ABS(B68-C68) -> 0 | E68: 1e-09 | F68: =IF(D68<=E68,"PASS","FAIL") -> PASS
A69: Month of the risk peak | B69: =Ledgers!K13 -> 11 | C69: =Reference_Values!B69 -> 11 | D69: =ABS(B69-C69) -> 0 | E69: 0 | F69: =IF(D69<=E69,"PASS","FAIL") -> PASS
A70: The ceiling's distance at the peak | B70: =Ledgers!K14 -> 1.4479365 | C70: =Reference_Values!B70 -> 1.4479365 | D70: =ABS(B70-C70) -> 0 | E70: 1e-09 | F70: =IF(D70<=E70,"PASS","FAIL") -> PASS
A71: Planned low point, $ million | B71: =Decide!B13 -> 481.95038 | C71: =Reference_Values!B71 -> 481.95038 | D71: =ABS(B71-C71) -> 0 | E71: 1e-09 | F71: =IF(D71<=E71,"PASS","FAIL") -> PASS
A72: Separated choices passing every ledger | B72: =Decide!B11 -> 0 | C72: =Reference_Values!B72 -> 0 | D72: =ABS(B72-C72) -> 0 | E72: 0 | F72: =IF(D72<=E72,"PASS","FAIL") -> PASS
A73: Repairs that pass every ledger | B73: =Decide!B12 -> 1 | C73: =Reference_Values!B73 -> 1 | D73: =ABS(B73-C73) -> 0 | E73: 0 | F73: =IF(D73<=E73,"PASS","FAIL") -> PASS
A75: All checkpoints | F75: =IF(COUNTIF(F2:F73,"PASS")=72,"ALL PASS","CHECK") -> ALL PASS
