Workbook

Sheet README
B1: DCT Laboratory — Vol II, Ch 5: Dynamic Enterprise Optimization
B2: Seed 26205 · Companion to DCT_V2_Ch05_Lab.ipynb and AXIOM Lab 2.5 (module AXIOM-05). Money in $ million.
B4: Worked Example 5.1, When Should Meridian Pay Its Shareholders?, with the book's declarations, in formulas.
B5: Declarations: the inputs of Step 1. Simulate: the CFO's rule and decisions judged year by year (Step 2).
B6: Transcribe: all 64 schedules of rounds, each with its war chest, its payouts and its value; BestPlan: the best of them, year by year (Step 3).
B7: Prices: the prices of cash and of efficiency, the binding commitments, perturbation checks and the round test (Step 4).
B8: Rates: the best plan at hurdle rates from 3 to 30 percent and the switch rates certified; Horizons: terminal values and planning windows of 1 to 20 years (Step 5).
B9: Replan: the present-biased board's yearly re-plans (Section 5.6). Stress and ShortfallKnown: each round a point short, Step 3's schedule against the war-chest rule (Step 6).
B10: Table5_3: Table 5.3 assembled from these sheets. The bisection for the switch rates, the linear-program check, the rolling windows and the figures run in the notebook.
B11: Reference_Values and Checks: the engine's numbers and a PASS/FAIL comparison with this workbook's formulas.
B13: LEGEND
B14: Input: blue on pale gold. A declaration from the book; change it to explore.
... B17: Cross-sheet link: green.

Sheet Declarations
A1: Declarations (Worked Example 5.1, Step 1). Money in $ million; efficiency in points.
A3: Quantity | B3: Value | C3: Source
A4: Hurdle rate r (a year) | B4: 0.1 | C4: The board's declaration: payouts discounted at 10 percent a year
A5: Discount factor a year, beta = 1/(1 + r) | B5: =1/(1+B4) -> 0.90909091
A6: Cost of a round | B6: 120 | C6: Volume I, Worked Example 6.1
A7: Efficiency ceiling | B7: 85 | C7: A round closes half the gap to 85
A8: Share of the remaining gap a round closes | B8: 0.5
A9: Savings per point of efficiency a year | B9: 10 | C9: S_k = 10 (e_k - 71)
A10: Today's efficiency, e_0 | B10: 71
A11: Today's cash, q_0 | B11: 620
A12: Floor on cash at every year end | B12: 350 | C12: The board's $350 million floor
A13: Cash a round needs on hand when it starts | B13: 470 | C13: So the floor holds after paying for the round
A14: End condition: cash at the end of year 6 | B14: 470 | C14: Cash for another round
A15: Life of the automated lines (years) | B15: 20 | C15: Step 5: savings valued only over the lines' life
A16: Part I's years of undiscounted credit | B16: 10 | C16: Worked Examples 2.1 and 3.1
A17: Shortfall per round in the stress scenario (points) | B17: 1 | C17: Step 6: each round a point short
A18: Present-biased board's weight on later years, b | B18: 0.9 | C18: Section 5.6: later years at 90 percent
A20: Six years, one period a year; cash earns nothing. Dynamics: e_k = e_(k-1) + z_k (85 - e_(k-1))/2; q_k = q_(k-1) - 120 z_k + S_k - p_k. A round needs q_(k-1) >= 470; every year ends with q_k >= 350; year 6 ends with q_6 >= 470.
A21: Value: sum over k of beta^k p_k + beta^6 S_6 / r, the payouts plus the year-6 savings forever (at 10 percent the perpetuity is 10 S_6, Part I's ten years of credit).

Sheet Simulate
A1: Simulate: the CFO's rule (Proposition 5.1; Worked Example 5.1, Step 2; AXIOM Lab 2.5, step 1)
A2: Pay out, every year end, whatever cash exceeds the floor; a planned round runs only if the year opens with the cash it needs. The payout leaves 350, so no round after the first can start.
A4: The CFO's rule: rounds planned for years 1 to 3
A5: Year | B5: Round planned | C5: Cash at the start | D5: Round runs | E5: Efficiency | F5: Savings | G5: Payout | H5: Year-end cash | I5: Discount factor | J5: PV of payout | K5: Breach
A6: 1 | B6: 1 | C6: =Q_zero -> 620 | D6: =IF(AND(B6=1,C6>=Pre_q-0.000000001),1,0) -> 1 | E6: =E_zero+D6*(Half_gap*(Ceiling_e-E_zero)-0) -> 78 | F6: =Val_pt*(E6-E_zero) -> 70 | G6: =MAX(0,C6-Cost_round*D6+F6-Floor_q) -> 220 | H6: =C6-Cost_round*D6+F6-G6 -> 350 | I6: =Beta_y^A6 -> 0.90909091 | J6: =G6*I6 -> 200 | K6: =IF(AND(B6=1,D6=0),"round cannot start; ","")&IF(H6<Floor_q-0.000000001,"floor breached; ","")
A7: 2 | B7: 1 | C7: =H6 -> 350 | D7: =IF(AND(B7=1,C7>=Pre_q-0.000000001),1,0) -> 0 | E7: =E6+D7*(Half_gap*(Ceiling_e-E6)-0) -> 78 | F7: =Val_pt*(E7-E_zero) -> 70 | G7: =MAX(0,C7-Cost_round*D7+F7-Floor_q) -> 70 | H7: =C7-Cost_round*D7+F7-G7 -> 350 | I7: =Beta_y^A7 -> 0.82644628 | J7: =G7*I7 -> 57.85124 | K7: =IF(AND(B7=1,D7=0),"round cannot start; ","")&IF(H7<Floor_q-0.000000001,"floor breached; ","") -> round cannot start;
A8: 3 | B8: 1 | C8: =H7 -> 350 | D8: =IF(AND(B8=1,C8>=Pre_q-0.000000001),1,0) -> 0 | E8: =E7+D8*(Half_gap*(Ceiling_e-E7)-0) -> 78 | F8: =Val_pt*(E8-E_zero) -> 70 | G8: =MAX(0,C8-Cost_round*D8+F8-Floor_q) -> 70 | H8: =C8-Cost_round*D8+F8-G8 -> 350 | I8: =Beta_y^A8 -> 0.7513148 | J8: =G8*I8 -> 52.592036 | K8: =IF(AND(B8=1,D8=0),"round cannot start; ","")&IF(H8<Floor_q-0.000000001,"floor breached; ","") -> round cannot start;
A9: 4 | B9: 0 | C9: =H8 -> 350 | D9: =IF(AND(B9=1,C9>=Pre_q-0.000000001),1,0) -> 0 | E9: =E8+D9*(Half_gap*(Ceiling_e-E8)-0) -> 78 | F9: =Val_pt*(E9-E_zero) -> 70 | G9: =MAX(0,C9-Cost_round*D9+F9-Floor_q) -> 70 | H9: =C9-Cost_round*D9+F9-G9 -> 350 | I9: =Beta_y^A9 -> 0.68301346 | J9: =G9*I9 -> 47.810942 | K9: =IF(AND(B9=1,D9=0),"round cannot start; ","")&IF(H9<Floor_q-0.000000001,"floor breached; ","")
A10: 5 | B10: 0 | C10: =H9 -> 350 | D10: =IF(AND(B10=1,C10>=Pre_q-0.000000001),1,0) -> 0 | E10: =E9+D10*(Half_gap*(Ceiling_e-E9)-0) -> 78 | F10: =Val_pt*(E10-E_zero) -> 70 | G10: =MAX(0,C10-Cost_round*D10+F10-Floor_q) -> 70 | H10: =C10-Cost_round*D10+F10-G10 -> 350 | I10: =Beta_y^A10 -> 0.62092132 | J10: =G10*I10 -> 43.464493 | K10: =IF(AND(B10=1,D10=0),"round cannot start; ","")&IF(H10<Floor_q-0.000000001,"floor breached; ","")
A11: 6 | B11: 0 | C11: =H10 -> 350 | D11: =IF(AND(B11=1,C11>=Pre_q-0.000000001),1,0) -> 0 | E11: =E10+D11*(Half_gap*(Ceiling_e-E10)-0) -> 78 | F11: =Val_pt*(E11-E_zero) -> 70 | G11: =MAX(0,C11-Cost_round*D11+F11-Floor_q) -> 70 | H11: =C11-Cost_round*D11+F11-G11 -> 350 | I11: =Beta_y^A11 -> 0.56447393 | J11: =G11*I11 -> 39.513175 | K11: =IF(AND(B11=1,D11=0),"round cannot start; ","")&IF(H11<Floor_q-0.000000001,"floor breached; ","")&IF(H11<End_q-0.000000001,"end condition missed","") -> end condition missed
A13: Rounds run | H13: =SUM(D6:D11) -> 1
A14: Planned rounds that could not start | H14: =SUMPRODUCT((B6:B11=1)*(D6:D11=0)) -> 2
A15: Year ends below the floor | H15: =COUNTIF(H6:H11,"<"&(Floor_q-0.000000001)) -> 0
A16: Cash at the end of year 6 | H16: =H11 -> 350
A17: End condition | H17: =IF(H11>=End_q-0.000000001,"kept","missed") -> missed
A18: Payouts, present value | H18: =SUM(J6:J11) -> 441.23189
A19: Savings after year 6 forever, today | H19: =I11*F11/Hurdle_r -> 395.13175
A20: Value: payouts plus savings forever (-- if the floor breaks) | H20: =IF(H15>0,"--",H18+H19) -> 836.36364
A23: Decided year by year: no round is ever worth its cost within its own year
A24: Year | B24: Round planned | C24: Cash at the start | D24: Round runs | E24: Efficiency | F24: Savings | G24: Payout | H24: Year-end cash | I24: Discount factor | J24: PV of payout | K24: Breach
A25: 1 | B25: 0 | C25: =Q_zero -> 620 | D25: =IF(AND(B25=1,C25>=Pre_q-0.000000001),1,0) -> 0 | E25: =E_zero+D25*(Half_gap*(Ceiling_e-E_zero)-0) -> 71 | F25: =Val_pt*(E25-E_zero) -> 0 | G25: =MAX(0,C25-Cost_round*D25+F25-Floor_q) -> 270 | H25: =C25-Cost_round*D25+F25-G25 -> 350 | I25: =Beta_y^A25 -> 0.90909091 | J25: =G25*I25 -> 245.45455 | K25: =IF(AND(B25=1,D25=0),"round cannot start; ","")&IF(H25<Floor_q-0.000000001,"floor breached; ","")
A26: 2 | B26: 0 | C26: =H25 -> 350 | D26: =IF(AND(B26=1,C26>=Pre_q-0.000000001),1,0) -> 0 | E26: =E25+D26*(Half_gap*(Ceiling_e-E25)-0) -> 71 | F26: =Val_pt*(E26-E_zero) -> 0 | G26: =MAX(0,C26-Cost_round*D26+F26-Floor_q) -> 0 | H26: =C26-Cost_round*D26+F26-G26 -> 350 | I26: =Beta_y^A26 -> 0.82644628 | J26: =G26*I26 -> 0 | K26: =IF(AND(B26=1,D26=0),"round cannot start; ","")&IF(H26<Floor_q-0.000000001,"floor breached; ","")
A27: 3 | B27: 0 | C27: =H26 -> 350 | D27: =IF(AND(B27=1,C27>=Pre_q-0.000000001),1,0) -> 0 | E27: =E26+D27*(Half_gap*(Ceiling_e-E26)-0) -> 71 | F27: =Val_pt*(E27-E_zero) -> 0 | G27: =MAX(0,C27-Cost_round*D27+F27-Floor_q) -> 0 | H27: =C27-Cost_round*D27+F27-G27 -> 350 | I27: =Beta_y^A27 -> 0.7513148 | J27: =G27*I27 -> 0 | K27: =IF(AND(B27=1,D27=0),"round cannot start; ","")&IF(H27<Floor_q-0.000000001,"floor breached; ","")
A28: 4 | B28: 0 | C28: =H27 -> 350 | D28: =IF(AND(B28=1,C28>=Pre_q-0.000000001),1,0) -> 0 | E28: =E27+D28*(Half_gap*(Ceiling_e-E27)-0) -> 71 | F28: =Val_pt*(E28-E_zero) -> 0 | G28: =MAX(0,C28-Cost_round*D28+F28-Floor_q) -> 0 | H28: =C28-Cost_round*D28+F28-G28 -> 350 | I28: =Beta_y^A28 -> 0.68301346 | J28: =G28*I28 -> 0 | K28: =IF(AND(B28=1,D28=0),"round cannot start; ","")&IF(H28<Floor_q-0.000000001,"floor breached; ","")
A29: 5 | B29: 0 | C29: =H28 -> 350 | D29: =IF(AND(B29=1,C29>=Pre_q-0.000000001),1,0) -> 0 | E29: =E28+D29*(Half_gap*(Ceiling_e-E28)-0) -> 71 | F29: =Val_pt*(E29-E_zero) -> 0 | G29: =MAX(0,C29-Cost_round*D29+F29-Floor_q) -> 0 | H29: =C29-Cost_round*D29+F29-G29 -> 350 | I29: =Beta_y^A29 -> 0.62092132 | J29: =G29*I29 -> 0 | K29: =IF(AND(B29=1,D29=0),"round cannot start; ","")&IF(H29<Floor_q-0.000000001,"floor breached; ","")
A30: 6 | B30: 0 | C30: =H29 -> 350 | D30: =IF(AND(B30=1,C30>=Pre_q-0.000000001),1,0) -> 0 | E30: =E29+D30*(Half_gap*(Ceiling_e-E29)-0) -> 71 | F30: =Val_pt*(E30-E_zero) -> 0 | G30: =MAX(0,C30-Cost_round*D30+F30-Floor_q) -> 0 | H30: =C30-Cost_round*D30+F30-G30 -> 350 | I30: =Beta_y^A30 -> 0.56447393 | J30: =G30*I30 -> 0 | K30: =IF(AND(B30=1,D30=0),"round cannot start; ","")&IF(H30<Floor_q-0.000000001,"floor breached; ","")&IF(H30<End_q-0.000000001,"end condition missed","") -> end condition missed
A32: Rounds run | H32: =SUM(D25:D30) -> 0
A33: Planned rounds that could not start | H33: =SUMPRODUCT((B25:B30=1)*(D25:D30=0)) -> 0
A34: Year ends below the floor | H34: =COUNTIF(H25:H30,"<"&(Floor_q-0.000000001)) -> 0
A35: Cash at the end of year 6 | H35: =H30 -> 350
A36: End condition | H36: =IF(H30>=End_q-0.000000001,"kept","missed") -> missed
A37: Payouts, present value | H37: =SUM(J25:J30) -> 245.45455
A38: Savings after year 6 forever, today | H38: =I30*F30/Hurdle_r -> 0
A39: Value: payouts plus savings forever (-- if the floor breaks) | H39: =IF(H34>0,"--",H37+H38) -> 245.45455
A42: Most savings a round adds in its own year | H42: =Val_pt*Half_gap*(Ceiling_e-E_zero) -> 70
A43: Against the cost of a round | H43: =Cost_round -> 120
A45: The value of a plan that misses the end condition is shown as if the board waived it (Table 5.3, note a).

Sheet Transcribe
A1: Transcribe and solve: all 64 schedules of rounds, each with its payout program (Theorem 5.1; Proposition 5.3(ii); AXIOM Lab 2.5, step 2)
A2: Each row is a schedule of rounds (z_k = 1: a round in year k). Its best payouts pay out, every year end, everything above the war chest R_k: R_6 = 470; R_(k-1) = max(R_k + 120 z_k - S_k, 470 if z_k = 1, 350), with no floor term for R_0.
A3: The schedule keeps every commitment exactly when today's cash covers R_0; then p_1 = q_0 - 120 z_1 + S_1 - R_1 and p_k = R_(k-1) - 120 z_k + S_k - R_k (Proposition 5.3(ii): pay as early as the commitments allow).
A4: Shortfall per round on this sheet (points) | F4: 0
AK6: Hurdle rate for the column: | AP6: 0.03 | AQ6: 0.05 | AR6: 0.08 | AS6: 0.1 | AT6: 0.12 | AU6: 0.15 | AV6: 0.2 | AW6: 0.3 | AX6: 0.018229167 | AY6: 0.036458333 | AZ6: 0.072916667 | BA6: 0.14549722 | BB6: 0.29871078
A7: # | B7: Rounds by year | C7: Rounds | D7: z1 | E7: z2 | F7: z3 | G7: z4 | H7: z5 | I7: z6 | J7: e1 | K7: e2 | L7: e3 | M7: e4 | N7: e5 | O7: e6 | P7: S1 | Q7: S2 | R7: S3 | S7: S4 | T7: S5 | U7: S6 | V7: R0 | W7: R1 | X7: R2 | Y7: R3 | Z7: R4 | AA7: R5 | AB7: R6 | AC7: Keeps every commitment | AD7: p1 | AE7: p2 | AF7: p3 | AG7: p4 | AH7: p5 | AI7: p6 | AJ7: Paid out | AK7: Payouts, PV | AL7: Value: savings forever | AM7: Value: no terminal value | AN7: Value: savings over the lines' life | AO7: Undiscounted, Part I's credit | AP7: Value at 3% | AQ7: Value at 5% | AR7: Value at 8% | AS7: Value at 10% | AT7: Value at 12% | AU7: Value at 15% | AV7: Value at 20% | AW7: Value at 30% | AX7: Value at switch rate 1 | AY7: Value at switch rate 2 | AZ7: Value at switch rate 3 | BA7: Value at switch rate 4 | BB7: Value at switch rate 5
A8: 0 | B8: =D8&E8&F8&G8&H8&I8 -> 000000 | C8: =SUM(D8:I8) -> 0 | D8: =MOD(INT($A8/32),2) -> 0 | E8: =MOD(INT($A8/16),2) -> 0 | F8: =MOD(INT($A8/8),2) -> 0 | G8: =MOD(INT($A8/4),2) -> 0 | H8: =MOD(INT($A8/2),2) -> 0 | I8: =MOD(INT($A8/1),2) -> 0 | J8: =E_zero+D8*(Half_gap*(Ceiling_e-E_zero)-$F$4) -> 71 | K8: =J8+E8*(Half_gap*(Ceiling_e-J8)-$F$4) -> 71 | L8: =K8+F8*(Half_gap*(Ceiling_e-K8)-$F$4) -> 71 | M8: =L8+G8*(Half_gap*(Ceiling_e-L8)-$F$4) -> 71 | N8: =M8+H8*(Half_gap*(Ceiling_e-M8)-$F$4) -> 71 | O8: =N8+I8*(Half_gap*(Ceiling_e-N8)-$F$4) -> 71 | P8: =Val_pt*(J8-E_zero) -> 0 | Q8: =Val_pt*(K8-E_zero) -> 0 | R8: =Val_pt*(L8-E_zero) -> 0 | S8: =Val_pt*(M8-E_zero) -> 0 | T8: =Val_pt*(N8-E_zero) -> 0 | U8: =Val_pt*(O8-E_zero) -> 0 | V8: =MAX(W8+Cost_round*D8-P8,IF(D8=1,Pre_q,0)) -> 470 | W8: =MAX(X8+Cost_round*E8-Q8,IF(E8=1,Pre_q,0),Floor_q) -> 470 | X8: =MAX(Y8+Cost_round*F8-R8,IF(F8=1,Pre_q,0),Floor_q) -> 470 | Y8: =MAX(Z8+Cost_round*G8-S8,IF(G8=1,Pre_q,0),Floor_q) -> 470 | Z8: =MAX(AA8+Cost_round*H8-T8,IF(H8=1,Pre_q,0),Floor_q) -> 470 | AA8: =MAX(AB8+Cost_round*I8-U8,IF(I8=1,Pre_q,0),Floor_q) -> 470 | AB8: =MAX(End_q,Floor_q) -> 470 | AC8: =IF(Q_zero>=V8-0.000000001,1,0) -> 1 | AD8: =IF($AC8=1,Q_zero-Cost_round*D8+P8-W8,"") -> 150 | AE8: =IF($AC8=1,W8-Cost_round*E8+Q8-X8,"") -> 0 | AF8: =IF($AC8=1,X8-Cost_round*F8+R8-Y8,"") -> 0 | AG8: =IF($AC8=1,Y8-Cost_round*G8+S8-Z8,"") -> 0 | AH8: =IF($AC8=1,Z8-Cost_round*H8+T8-AA8,"") -> 0 | AI8: =IF($AC8=1,AA8-Cost_round*I8+U8-AB8,"") -> 0 | AJ8: =IF($AC8=1,SUM(AD8:AI8),"") -> 150 | AK8: =IF($AC8=1,AD8*Beta_y^1+AE8*Beta_y^2+AF8*Beta_y^3+AG8*Beta_y^4+AH8*Beta_y^5+AI8*Beta_y^6,"") -> 136.36364 | AL8: =IF($AC8=1,AK8+Beta_y^6*U8/Hurdle_r,"") -> 136.36364 | AM8: =IF($AC8=1,AK8,"") -> 136.36364 | AN8: =IF($AC8=1,AK8+Beta_y^6*U8*(1-(1+Hurdle_r)^(-Life_yrs))/Hurdle_r,"") -> 136.36364 | AO8: =IF($AC8=1,AJ8+Credit_yrs*U8,"") -> 150 | AP8: =IF($AC8=1,$AD8/(1+AP$6)^1+$AE8/(1+AP$6)^2+$AF8/(1+AP$6)^3+$AG8/(1+AP$6)^4+$AH8/(1+AP$6)^5+$AI8/(1+AP$6)^6+$U8/AP$6/(1+AP$6)^6,"") -> 145.63107 | AQ8: =IF($AC8=1,$AD8/(1+AQ$6)^1+$AE8/(1+AQ$6)^2+$AF8/(1+AQ$6)^3+$AG8/(1+AQ$6)^4+$AH8/(1+AQ$6)^5+$AI8/(1+AQ$6)^6+$U8/AQ$6/(1+AQ$6)^6,"") -> 142.85714 | AR8: =IF($AC8=1,$AD8/(1+AR$6)^1+$AE8/(1+AR$6)^2+$AF8/(1+AR$6)^3+$AG8/(1+AR$6)^4+$AH8/(1+AR$6)^5+$AI8/(1+AR$6)^6+$U8/AR$6/(1+AR$6)^6,"") -> 138.88889 | AS8: =IF($AC8=1,$AD8/(1+AS$6)^1+$AE8/(1+AS$6)^2+$AF8/(1+AS$6)^3+$AG8/(1+AS$6)^4+$AH8/(1+AS$6)^5+$AI8/(1+AS$6)^6+$U8/AS$6/(1+AS$6)^6,"") -> 136.36364 | AT8: =IF($AC8=1,$AD8/(1+AT$6)^1+$AE8/(1+AT$6)^2+$AF8/(1+AT$6)^3+$AG8/(1+AT$6)^4+$AH8/(1+AT$6)^5+$AI8/(1+AT$6)^6+$U8/AT$6/(1+AT$6)^6,"") -> 133.92857 | AU8: =IF($AC8=1,$AD8/(1+AU$6)^1+$AE8/(1+AU$6)^2+$AF8/(1+AU$6)^3+$AG8/(1+AU$6)^4+$AH8/(1+AU$6)^5+$AI8/(1+AU$6)^6+$U8/AU$6/(1+AU$6)^6,"") -> 130.43478 | AV8: =IF($AC8=1,$AD8/(1+AV$6)^1+$AE8/(1+AV$6)^2+$AF8/(1+AV$6)^3+$AG8/(1+AV$6)^4+$AH8/(1+AV$6)^5+$AI8/(1+AV$6)^6+$U8/AV$6/(1+AV$6)^6,"") -> 125 | AW8: =IF($AC8=1,$AD8/(1+AW$6)^1+$AE8/(1+AW$6)^2+$AF8/(1+AW$6)^3+$AG8/(1+AW$6)^4+$AH8/(1+AW$6)^5+$AI8/(1+AW$6)^6+$U8/AW$6/(1+AW$6)^6,"") -> 115.38462 | ... BB8: =IF($AC8=1,$AD8/(1+BB$6)^1+$AE8/(1+BB$6)^2+$AF8/(1+BB$6)^3+$AG8/(1+BB$6)^4+$AH8/(1+BB$6)^5+$AI8/(1+BB$6)^6+$U8/BB$6/(1+BB$6)^6,"") -> 115.49916
A9: 1 | B9: =D9&E9&F9&G9&H9&I9 -> 000001 | C9: =SUM(D9:I9) -> 1 | D9: =MOD(INT($A9/32),2) -> 0 | E9: =MOD(INT($A9/16),2) -> 0 | F9: =MOD(INT($A9/8),2) -> 0 | G9: =MOD(INT($A9/4),2) -> 0 | H9: =MOD(INT($A9/2),2) -> 0 | I9: =MOD(INT($A9/1),2) -> 1 | J9: =E_zero+D9*(Half_gap*(Ceiling_e-E_zero)-$F$4) -> 71 | K9: =J9+E9*(Half_gap*(Ceiling_e-J9)-$F$4) -> 71 | L9: =K9+F9*(Half_gap*(Ceiling_e-K9)-$F$4) -> 71 | M9: =L9+G9*(Half_gap*(Ceiling_e-L9)-$F$4) -> 71 | N9: =M9+H9*(Half_gap*(Ceiling_e-M9)-$F$4) -> 71 | O9: =N9+I9*(Half_gap*(Ceiling_e-N9)-$F$4) -> 78 | P9: =Val_pt*(J9-E_zero) -> 0 | Q9: =Val_pt*(K9-E_zero) -> 0 | R9: =Val_pt*(L9-E_zero) -> 0 | S9: =Val_pt*(M9-E_zero) -> 0 | T9: =Val_pt*(N9-E_zero) -> 0 | U9: =Val_pt*(O9-E_zero) -> 70 | V9: =MAX(W9+Cost_round*D9-P9,IF(D9=1,Pre_q,0)) -> 520 | W9: =MAX(X9+Cost_round*E9-Q9,IF(E9=1,Pre_q,0),Floor_q) -> 520 | X9: =MAX(Y9+Cost_round*F9-R9,IF(F9=1,Pre_q,0),Floor_q) -> 520 | Y9: =MAX(Z9+Cost_round*G9-S9,IF(G9=1,Pre_q,0),Floor_q) -> 520 | Z9: =MAX(AA9+Cost_round*H9-T9,IF(H9=1,Pre_q,0),Floor_q) -> 520 | AA9: =MAX(AB9+Cost_round*I9-U9,IF(I9=1,Pre_q,0),Floor_q) -> 520 | AB9: =MAX(End_q,Floor_q) -> 470 | AC9: =IF(Q_zero>=V9-0.000000001,1,0) -> 1 | AD9: =IF($AC9=1,Q_zero-Cost_round*D9+P9-W9,"") -> 100 | AE9: =IF($AC9=1,W9-Cost_round*E9+Q9-X9,"") -> 0 | AF9: =IF($AC9=1,X9-Cost_round*F9+R9-Y9,"") -> 0 | AG9: =IF($AC9=1,Y9-Cost_round*G9+S9-Z9,"") -> 0 | AH9: =IF($AC9=1,Z9-Cost_round*H9+T9-AA9,"") -> 0 | AI9: =IF($AC9=1,AA9-Cost_round*I9+U9-AB9,"") -> 0 | AJ9: =IF($AC9=1,SUM(AD9:AI9),"") -> 100 | AK9: =IF($AC9=1,AD9*Beta_y^1+AE9*Beta_y^2+AF9*Beta_y^3+AG9*Beta_y^4+AH9*Beta_y^5+AI9*Beta_y^6,"") -> 90.909091 | AL9: =IF($AC9=1,AK9+Beta_y^6*U9/Hurdle_r,"") -> 486.04084 | AM9: =IF($AC9=1,AK9,"") -> 90.909091 | AN9: =IF($AC9=1,AK9+Beta_y^6*U9*(1-(1+Hurdle_r)^(-Life_yrs))/Hurdle_r,"") -> 427.30702 | AO9: =IF($AC9=1,AJ9+Credit_yrs*U9,"") -> 800 | AP9: =IF($AC9=1,$AD9/(1+AP$6)^1+$AE9/(1+AP$6)^2+$AF9/(1+AP$6)^3+$AG9/(1+AP$6)^4+$AH9/(1+AP$6)^5+$AI9/(1+AP$6)^6+$U9/AP$6/(1+AP$6)^6,"") -> 2051.2173 | AQ9: =IF($AC9=1,$AD9/(1+AQ$6)^1+$AE9/(1+AQ$6)^2+$AF9/(1+AQ$6)^3+$AG9/(1+AQ$6)^4+$AH9/(1+AQ$6)^5+$AI9/(1+AQ$6)^6+$U9/AQ$6/(1+AQ$6)^6,"") -> 1139.9397 | AR9: =IF($AC9=1,$AD9/(1+AR$6)^1+$AE9/(1+AR$6)^2+$AF9/(1+AR$6)^3+$AG9/(1+AR$6)^4+$AH9/(1+AR$6)^5+$AI9/(1+AR$6)^6+$U9/AR$6/(1+AR$6)^6,"") -> 643.99102 | AS9: =IF($AC9=1,$AD9/(1+AS$6)^1+$AE9/(1+AS$6)^2+$AF9/(1+AS$6)^3+$AG9/(1+AS$6)^4+$AH9/(1+AS$6)^5+$AI9/(1+AS$6)^6+$U9/AS$6/(1+AS$6)^6,"") -> 486.04084 | AT9: =IF($AC9=1,$AD9/(1+AT$6)^1+$AE9/(1+AT$6)^2+$AF9/(1+AT$6)^3+$AG9/(1+AT$6)^4+$AH9/(1+AT$6)^5+$AI9/(1+AT$6)^6+$U9/AT$6/(1+AT$6)^6,"") -> 384.82053 | AU9: =IF($AC9=1,$AD9/(1+AU$6)^1+$AE9/(1+AU$6)^2+$AF9/(1+AU$6)^3+$AG9/(1+AU$6)^4+$AH9/(1+AU$6)^5+$AI9/(1+AU$6)^6+$U9/AU$6/(1+AU$6)^6,"") -> 288.7094 | AV9: =IF($AC9=1,$AD9/(1+AV$6)^1+$AE9/(1+AV$6)^2+$AF9/(1+AV$6)^3+$AG9/(1+AV$6)^4+$AH9/(1+AV$6)^5+$AI9/(1+AV$6)^6+$U9/AV$6/(1+AV$6)^6,"") -> 200.54763 | AW9: =IF($AC9=1,$AD9/(1+AW$6)^1+$AE9/(1+AW$6)^2+$AF9/(1+AW$6)^3+$AG9/(1+AW$6)^4+$AH9/(1+AW$6)^5+$AI9/(1+AW$6)^6+$U9/AW$6/(1+AW$6)^6,"") -> 125.26419 | ... BB9: =IF($AC9=1,$AD9/(1+BB$6)^1+$AE9/(1+BB$6)^2+$AF9/(1+BB$6)^3+$AG9/(1+BB$6)^4+$AH9/(1+BB$6)^5+$AI9/(1+BB$6)^6+$U9/BB$6/(1+BB$6)^6,"") -> 125.83908
A10: 2 | B10: =D10&E10&F10&G10&H10&I10 -> 000010 | C10: =SUM(D10:I10) -> 1 | D10: =MOD(INT($A10/32),2) -> 0 | E10: =MOD(INT($A10/16),2) -> 0 | F10: =MOD(INT($A10/8),2) -> 0 | G10: =MOD(INT($A10/4),2) -> 0 | H10: =MOD(INT($A10/2),2) -> 1 | I10: =MOD(INT($A10/1),2) -> 0 | J10: =E_zero+D10*(Half_gap*(Ceiling_e-E_zero)-$F$4) -> 71 | K10: =J10+E10*(Half_gap*(Ceiling_e-J10)-$F$4) -> 71 | L10: =K10+F10*(Half_gap*(Ceiling_e-K10)-$F$4) -> 71 | M10: =L10+G10*(Half_gap*(Ceiling_e-L10)-$F$4) -> 71 | N10: =M10+H10*(Half_gap*(Ceiling_e-M10)-$F$4) -> 78 | O10: =N10+I10*(Half_gap*(Ceiling_e-N10)-$F$4) -> 78 | P10: =Val_pt*(J10-E_zero) -> 0 | Q10: =Val_pt*(K10-E_zero) -> 0 | R10: =Val_pt*(L10-E_zero) -> 0 | S10: =Val_pt*(M10-E_zero) -> 0 | T10: =Val_pt*(N10-E_zero) -> 70 | U10: =Val_pt*(O10-E_zero) -> 70 | V10: =MAX(W10+Cost_round*D10-P10,IF(D10=1,Pre_q,0)) -> 470 | W10: =MAX(X10+Cost_round*E10-Q10,IF(E10=1,Pre_q,0),Floor_q) -> 470 | X10: =MAX(Y10+Cost_round*F10-R10,IF(F10=1,Pre_q,0),Floor_q) -> 470 | Y10: =MAX(Z10+Cost_round*G10-S10,IF(G10=1,Pre_q,0),Floor_q) -> 470 | Z10: =MAX(AA10+Cost_round*H10-T10,IF(H10=1,Pre_q,0),Floor_q) -> 470 | AA10: =MAX(AB10+Cost_round*I10-U10,IF(I10=1,Pre_q,0),Floor_q) -> 400 | AB10: =MAX(End_q,Floor_q) -> 470 | AC10: =IF(Q_zero>=V10-0.000000001,1,0) -> 1 | AD10: =IF($AC10=1,Q_zero-Cost_round*D10+P10-W10,"") -> 150 | AE10: =IF($AC10=1,W10-Cost_round*E10+Q10-X10,"") -> 0 | AF10: =IF($AC10=1,X10-Cost_round*F10+R10-Y10,"") -> 0 | AG10: =IF($AC10=1,Y10-Cost_round*G10+S10-Z10,"") -> 0 | AH10: =IF($AC10=1,Z10-Cost_round*H10+T10-AA10,"") -> 20 | AI10: =IF($AC10=1,AA10-Cost_round*I10+U10-AB10,"") -> 0 | AJ10: =IF($AC10=1,SUM(AD10:AI10),"") -> 170 | AK10: =IF($AC10=1,AD10*Beta_y^1+AE10*Beta_y^2+AF10*Beta_y^3+AG10*Beta_y^4+AH10*Beta_y^5+AI10*Beta_y^6,"") -> 148.78206 | AL10: =IF($AC10=1,AK10+Beta_y^6*U10/Hurdle_r,"") -> 543.91381 | AM10: =IF($AC10=1,AK10,"") -> 148.78206 | AN10: =IF($AC10=1,AK10+Beta_y^6*U10*(1-(1+Hurdle_r)^(-Life_yrs))/Hurdle_r,"") -> 485.18 | AO10: =IF($AC10=1,AJ10+Credit_yrs*U10,"") -> 870 | AP10: =IF($AC10=1,$AD10/(1+AP$6)^1+$AE10/(1+AP$6)^2+$AF10/(1+AP$6)^3+$AG10/(1+AP$6)^4+$AH10/(1+AP$6)^5+$AI10/(1+AP$6)^6+$U10/AP$6/(1+AP$6)^6,"") -> 2117.0132 | AQ10: =IF($AC10=1,$AD10/(1+AQ$6)^1+$AE10/(1+AQ$6)^2+$AF10/(1+AQ$6)^3+$AG10/(1+AQ$6)^4+$AH10/(1+AQ$6)^5+$AI10/(1+AQ$6)^6+$U10/AQ$6/(1+AQ$6)^6,"") -> 1203.2292 | AR10: =IF($AC10=1,$AD10/(1+AR$6)^1+$AE10/(1+AR$6)^2+$AF10/(1+AR$6)^3+$AG10/(1+AR$6)^4+$AH10/(1+AR$6)^5+$AI10/(1+AR$6)^6+$U10/AR$6/(1+AR$6)^6,"") -> 703.89898 | AS10: =IF($AC10=1,$AD10/(1+AS$6)^1+$AE10/(1+AS$6)^2+$AF10/(1+AS$6)^3+$AG10/(1+AS$6)^4+$AH10/(1+AS$6)^5+$AI10/(1+AS$6)^6+$U10/AS$6/(1+AS$6)^6,"") -> 543.91381 | AT10: =IF($AC10=1,$AD10/(1+AT$6)^1+$AE10/(1+AT$6)^2+$AF10/(1+AT$6)^3+$AG10/(1+AT$6)^4+$AH10/(1+AT$6)^5+$AI10/(1+AT$6)^6+$U10/AT$6/(1+AT$6)^6,"") -> 440.81193 | AU10: =IF($AC10=1,$AD10/(1+AU$6)^1+$AE10/(1+AU$6)^2+$AF10/(1+AU$6)^3+$AG10/(1+AU$6)^4+$AH10/(1+AU$6)^5+$AI10/(1+AU$6)^6+$U10/AU$6/(1+AU$6)^6,"") -> 342.1312 | AV10: =IF($AC10=1,$AD10/(1+AV$6)^1+$AE10/(1+AV$6)^2+$AF10/(1+AV$6)^3+$AG10/(1+AV$6)^4+$AH10/(1+AV$6)^5+$AI10/(1+AV$6)^6+$U10/AV$6/(1+AV$6)^6,"") -> 250.25184 | AW10: =IF($AC10=1,$AD10/(1+AW$6)^1+$AE10/(1+AW$6)^2+$AF10/(1+AW$6)^3+$AG10/(1+AW$6)^4+$AH10/(1+AW$6)^5+$AI10/(1+AW$6)^6+$U10/AW$6/(1+AW$6)^6,"") -> 169.11231 | ... BB10: =IF($AC10=1,$AD10/(1+BB$6)^1+$AE10/(1+BB$6)^2+$AF10/(1+BB$6)^3+$AG10/(1+BB$6)^4+$AH10/(1+BB$6)^5+$AI10/(1+BB$6)^6+$U10/BB$6/(1+BB$6)^6,"") -> 169.75217
A11: 3 | B11: =D11&E11&F11&G11&H11&I11 -> 000011 | C11: =SUM(D11:I11) -> 2 | D11: =MOD(INT($A11/32),2) -> 0 | E11: =MOD(INT($A11/16),2) -> 0 | F11: =MOD(INT($A11/8),2) -> 0 | G11: =MOD(INT($A11/4),2) -> 0 | H11: =MOD(INT($A11/2),2) -> 1 | I11: =MOD(INT($A11/1),2) -> 1 | J11: =E_zero+D11*(Half_gap*(Ceiling_e-E_zero)-$F$4) -> 71 | K11: =J11+E11*(Half_gap*(Ceiling_e-J11)-$F$4) -> 71 | L11: =K11+F11*(Half_gap*(Ceiling_e-K11)-$F$4) -> 71 | M11: =L11+G11*(Half_gap*(Ceiling_e-L11)-$F$4) -> 71 | N11: =M11+H11*(Half_gap*(Ceiling_e-M11)-$F$4) -> 78 | O11: =N11+I11*(Half_gap*(Ceiling_e-N11)-$F$4) -> 81.5 | P11: =Val_pt*(J11-E_zero) -> 0 | Q11: =Val_pt*(K11-E_zero) -> 0 | R11: =Val_pt*(L11-E_zero) -> 0 | S11: =Val_pt*(M11-E_zero) -> 0 | T11: =Val_pt*(N11-E_zero) -> 70 | U11: =Val_pt*(O11-E_zero) -> 105 | V11: =MAX(W11+Cost_round*D11-P11,IF(D11=1,Pre_q,0)) -> 535 | W11: =MAX(X11+Cost_round*E11-Q11,IF(E11=1,Pre_q,0),Floor_q) -> 535 | X11: =MAX(Y11+Cost_round*F11-R11,IF(F11=1,Pre_q,0),Floor_q) -> 535 | Y11: =MAX(Z11+Cost_round*G11-S11,IF(G11=1,Pre_q,0),Floor_q) -> 535 | Z11: =MAX(AA11+Cost_round*H11-T11,IF(H11=1,Pre_q,0),Floor_q) -> 535 | AA11: =MAX(AB11+Cost_round*I11-U11,IF(I11=1,Pre_q,0),Floor_q) -> 485 | AB11: =MAX(End_q,Floor_q) -> 470 | AC11: =IF(Q_zero>=V11-0.000000001,1,0) -> 1 | AD11: =IF($AC11=1,Q_zero-Cost_round*D11+P11-W11,"") -> 85 | AE11: =IF($AC11=1,W11-Cost_round*E11+Q11-X11,"") -> 0 | AF11: =IF($AC11=1,X11-Cost_round*F11+R11-Y11,"") -> 0 | AG11: =IF($AC11=1,Y11-Cost_round*G11+S11-Z11,"") -> 0 | AH11: =IF($AC11=1,Z11-Cost_round*H11+T11-AA11,"") -> 0 | AI11: =IF($AC11=1,AA11-Cost_round*I11+U11-AB11,"") -> 0 | AJ11: =IF($AC11=1,SUM(AD11:AI11),"") -> 85 | AK11: =IF($AC11=1,AD11*Beta_y^1+AE11*Beta_y^2+AF11*Beta_y^3+AG11*Beta_y^4+AH11*Beta_y^5+AI11*Beta_y^6,"") -> 77.272727 | AL11: =IF($AC11=1,AK11+Beta_y^6*U11/Hurdle_r,"") -> 669.97035 | AM11: =IF($AC11=1,AK11,"") -> 77.272727 | AN11: =IF($AC11=1,AK11+Beta_y^6*U11*(1-(1+Hurdle_r)^(-Life_yrs))/Hurdle_r,"") -> 581.86963 | AO11: =IF($AC11=1,AJ11+Credit_yrs*U11,"") -> 1135 | AP11: =IF($AC11=1,$AD11/(1+AP$6)^1+$AE11/(1+AP$6)^2+$AF11/(1+AP$6)^3+$AG11/(1+AP$6)^4+$AH11/(1+AP$6)^5+$AI11/(1+AP$6)^6+$U11/AP$6/(1+AP$6)^6,"") -> 3013.7192 | AQ11: =IF($AC11=1,$AD11/(1+AQ$6)^1+$AE11/(1+AQ$6)^2+$AF11/(1+AQ$6)^3+$AG11/(1+AQ$6)^4+$AH11/(1+AQ$6)^5+$AI11/(1+AQ$6)^6+$U11/AQ$6/(1+AQ$6)^6,"") -> 1648.0047 | AR11: =IF($AC11=1,$AD11/(1+AR$6)^1+$AE11/(1+AR$6)^2+$AF11/(1+AR$6)^3+$AG11/(1+AR$6)^4+$AH11/(1+AR$6)^5+$AI11/(1+AR$6)^6+$U11/AR$6/(1+AR$6)^6,"") -> 905.80134 | AS11: =IF($AC11=1,$AD11/(1+AS$6)^1+$AE11/(1+AS$6)^2+$AF11/(1+AS$6)^3+$AG11/(1+AS$6)^4+$AH11/(1+AS$6)^5+$AI11/(1+AS$6)^6+$U11/AS$6/(1+AS$6)^6,"") -> 669.97035 | AT11: =IF($AC11=1,$AD11/(1+AT$6)^1+$AE11/(1+AT$6)^2+$AF11/(1+AT$6)^3+$AG11/(1+AT$6)^4+$AH11/(1+AT$6)^5+$AI11/(1+AT$6)^6+$U11/AT$6/(1+AT$6)^6,"") -> 519.19509 | AU11: =IF($AC11=1,$AD11/(1+AU$6)^1+$AE11/(1+AU$6)^2+$AF11/(1+AU$6)^3+$AG11/(1+AU$6)^4+$AH11/(1+AU$6)^5+$AI11/(1+AU$6)^6+$U11/AU$6/(1+AU$6)^6,"") -> 376.54236 | AV11: =IF($AC11=1,$AD11/(1+AV$6)^1+$AE11/(1+AV$6)^2+$AF11/(1+AV$6)^3+$AG11/(1+AV$6)^4+$AH11/(1+AV$6)^5+$AI11/(1+AV$6)^6+$U11/AV$6/(1+AV$6)^6,"") -> 246.65477 | AW11: =IF($AC11=1,$AD11/(1+AW$6)^1+$AE11/(1+AW$6)^2+$AF11/(1+AW$6)^3+$AG11/(1+AW$6)^4+$AH11/(1+AW$6)^5+$AI11/(1+AW$6)^6+$U11/AW$6/(1+AW$6)^6,"") -> 137.89629 | ... BB11: =IF($AC11=1,$AD11/(1+BB$6)^1+$AE11/(1+BB$6)^2+$AF11/(1+BB$6)^3+$AG11/(1+BB$6)^4+$AH11/(1+BB$6)^5+$AI11/(1+BB$6)^6+$U11/BB$6/(1+BB$6)^6,"") -> 138.70898
A12: 4 | B12: =D12&E12&F12&G12&H12&I12 -> 000100 | C12: =SUM(D12:I12) -> 1 | D12: =MOD(INT($A12/32),2) -> 0 | E12: =MOD(INT($A12/16),2) -> 0 | F12: =MOD(INT($A12/8),2) -> 0 | G12: =MOD(INT($A12/4),2) -> 1 | H12: =MOD(INT($A12/2),2) -> 0 | I12: =MOD(INT($A12/1),2) -> 0 | J12: =E_zero+D12*(Half_gap*(Ceiling_e-E_zero)-$F$4) -> 71 | K12: =J12+E12*(Half_gap*(Ceiling_e-J12)-$F$4) -> 71 | L12: =K12+F12*(Half_gap*(Ceiling_e-K12)-$F$4) -> 71 | M12: =L12+G12*(Half_gap*(Ceiling_e-L12)-$F$4) -> 78 | N12: =M12+H12*(Half_gap*(Ceiling_e-M12)-$F$4) -> 78 | O12: =N12+I12*(Half_gap*(Ceiling_e-N12)-$F$4) -> 78 | P12: =Val_pt*(J12-E_zero) -> 0 | Q12: =Val_pt*(K12-E_zero) -> 0 | R12: =Val_pt*(L12-E_zero) -> 0 | S12: =Val_pt*(M12-E_zero) -> 70 | T12: =Val_pt*(N12-E_zero) -> 70 | U12: =Val_pt*(O12-E_zero) -> 70 | V12: =MAX(W12+Cost_round*D12-P12,IF(D12=1,Pre_q,0)) -> 470 | W12: =MAX(X12+Cost_round*E12-Q12,IF(E12=1,Pre_q,0),Floor_q) -> 470 | X12: =MAX(Y12+Cost_round*F12-R12,IF(F12=1,Pre_q,0),Floor_q) -> 470 | Y12: =MAX(Z12+Cost_round*G12-S12,IF(G12=1,Pre_q,0),Floor_q) -> 470 | Z12: =MAX(AA12+Cost_round*H12-T12,IF(H12=1,Pre_q,0),Floor_q) -> 350 | AA12: =MAX(AB12+Cost_round*I12-U12,IF(I12=1,Pre_q,0),Floor_q) -> 400 | AB12: =MAX(End_q,Floor_q) -> 470 | AC12: =IF(Q_zero>=V12-0.000000001,1,0) -> 1 | AD12: =IF($AC12=1,Q_zero-Cost_round*D12+P12-W12,"") -> 150 | AE12: =IF($AC12=1,W12-Cost_round*E12+Q12-X12,"") -> 0 | AF12: =IF($AC12=1,X12-Cost_round*F12+R12-Y12,"") -> 0 | AG12: =IF($AC12=1,Y12-Cost_round*G12+S12-Z12,"") -> 70 | AH12: =IF($AC12=1,Z12-Cost_round*H12+T12-AA12,"") -> 20 | AI12: =IF($AC12=1,AA12-Cost_round*I12+U12-AB12,"") -> 0 | AJ12: =IF($AC12=1,SUM(AD12:AI12),"") -> 240 | AK12: =IF($AC12=1,AD12*Beta_y^1+AE12*Beta_y^2+AF12*Beta_y^3+AG12*Beta_y^4+AH12*Beta_y^5+AI12*Beta_y^6,"") -> 196.593 | AL12: =IF($AC12=1,AK12+Beta_y^6*U12/Hurdle_r,"") -> 591.72476 | AM12: =IF($AC12=1,AK12,"") -> 196.593 | AN12: =IF($AC12=1,AK12+Beta_y^6*U12*(1-(1+Hurdle_r)^(-Life_yrs))/Hurdle_r,"") -> 532.99094 | AO12: =IF($AC12=1,AJ12+Credit_yrs*U12,"") -> 940 | AP12: =IF($AC12=1,$AD12/(1+AP$6)^1+$AE12/(1+AP$6)^2+$AF12/(1+AP$6)^3+$AG12/(1+AP$6)^4+$AH12/(1+AP$6)^5+$AI12/(1+AP$6)^6+$U12/AP$6/(1+AP$6)^6,"") -> 2179.2073 | AQ12: =IF($AC12=1,$AD12/(1+AQ$6)^1+$AE12/(1+AQ$6)^2+$AF12/(1+AQ$6)^3+$AG12/(1+AQ$6)^4+$AH12/(1+AQ$6)^5+$AI12/(1+AQ$6)^6+$U12/AQ$6/(1+AQ$6)^6,"") -> 1260.8184 | AR12: =IF($AC12=1,$AD12/(1+AR$6)^1+$AE12/(1+AR$6)^2+$AF12/(1+AR$6)^3+$AG12/(1+AR$6)^4+$AH12/(1+AR$6)^5+$AI12/(1+AR$6)^6+$U12/AR$6/(1+AR$6)^6,"") -> 755.35107 | AS12: =IF($AC12=1,$AD12/(1+AS$6)^1+$AE12/(1+AS$6)^2+$AF12/(1+AS$6)^3+$AG12/(1+AS$6)^4+$AH12/(1+AS$6)^5+$AI12/(1+AS$6)^6+$U12/AS$6/(1+AS$6)^6,"") -> 591.72476 | AT12: =IF($AC12=1,$AD12/(1+AT$6)^1+$AE12/(1+AT$6)^2+$AF12/(1+AT$6)^3+$AG12/(1+AT$6)^4+$AH12/(1+AT$6)^5+$AI12/(1+AT$6)^6+$U12/AT$6/(1+AT$6)^6,"") -> 485.29819 | AU12: =IF($AC12=1,$AD12/(1+AU$6)^1+$AE12/(1+AU$6)^2+$AF12/(1+AU$6)^3+$AG12/(1+AU$6)^4+$AH12/(1+AU$6)^5+$AI12/(1+AU$6)^6+$U12/AU$6/(1+AU$6)^6,"") -> 382.15392 | AV12: =IF($AC12=1,$AD12/(1+AV$6)^1+$AE12/(1+AV$6)^2+$AF12/(1+AV$6)^3+$AG12/(1+AV$6)^4+$AH12/(1+AV$6)^5+$AI12/(1+AV$6)^6+$U12/AV$6/(1+AV$6)^6,"") -> 284.00956 | AW12: =IF($AC12=1,$AD12/(1+AW$6)^1+$AE12/(1+AW$6)^2+$AF12/(1+AW$6)^3+$AG12/(1+AW$6)^4+$AH12/(1+AW$6)^5+$AI12/(1+AW$6)^6+$U12/AW$6/(1+AW$6)^6,"") -> 193.62126 | ... BB12: =IF($AC12=1,$AD12/(1+BB$6)^1+$AE12/(1+BB$6)^2+$AF12/(1+BB$6)^3+$AG12/(1+BB$6)^4+$AH12/(1+BB$6)^5+$AI12/(1+BB$6)^6+$U12/BB$6/(1+BB$6)^6,"") -> 194.35858
A13: 5 | B13: =D13&E13&F13&G13&H13&I13 -> 000101 | C13: =SUM(D13:I13) -> 2 | D13: =MOD(INT($A13/32),2) -> 0 | E13: =MOD(INT($A13/16),2) -> 0 | F13: =MOD(INT($A13/8),2) -> 0 | G13: =MOD(INT($A13/4),2) -> 1 | H13: =MOD(INT($A13/2),2) -> 0 | I13: =MOD(INT($A13/1),2) -> 1 | J13: =E_zero+D13*(Half_gap*(Ceiling_e-E_zero)-$F$4) -> 71 | K13: =J13+E13*(Half_gap*(Ceiling_e-J13)-$F$4) -> 71 | L13: =K13+F13*(Half_gap*(Ceiling_e-K13)-$F$4) -> 71 | M13: =L13+G13*(Half_gap*(Ceiling_e-L13)-$F$4) -> 78 | N13: =M13+H13*(Half_gap*(Ceiling_e-M13)-$F$4) -> 78 | O13: =N13+I13*(Half_gap*(Ceiling_e-N13)-$F$4) -> 81.5 | P13: =Val_pt*(J13-E_zero) -> 0 | Q13: =Val_pt*(K13-E_zero) -> 0 | R13: =Val_pt*(L13-E_zero) -> 0 | S13: =Val_pt*(M13-E_zero) -> 70 | T13: =Val_pt*(N13-E_zero) -> 70 | U13: =Val_pt*(O13-E_zero) -> 105 | V13: =MAX(W13+Cost_round*D13-P13,IF(D13=1,Pre_q,0)) -> 470 | W13: =MAX(X13+Cost_round*E13-Q13,IF(E13=1,Pre_q,0),Floor_q) -> 470 | X13: =MAX(Y13+Cost_round*F13-R13,IF(F13=1,Pre_q,0),Floor_q) -> 470 | Y13: =MAX(Z13+Cost_round*G13-S13,IF(G13=1,Pre_q,0),Floor_q) -> 470 | Z13: =MAX(AA13+Cost_round*H13-T13,IF(H13=1,Pre_q,0),Floor_q) -> 415 | AA13: =MAX(AB13+Cost_round*I13-U13,IF(I13=1,Pre_q,0),Floor_q) -> 485 | AB13: =MAX(End_q,Floor_q) -> 470 | AC13: =IF(Q_zero>=V13-0.000000001,1,0) -> 1 | AD13: =IF($AC13=1,Q_zero-Cost_round*D13+P13-W13,"") -> 150 | AE13: =IF($AC13=1,W13-Cost_round*E13+Q13-X13,"") -> 0 | AF13: =IF($AC13=1,X13-Cost_round*F13+R13-Y13,"") -> 0 | AG13: =IF($AC13=1,Y13-Cost_round*G13+S13-Z13,"") -> 5 | AH13: =IF($AC13=1,Z13-Cost_round*H13+T13-AA13,"") -> 0 | AI13: =IF($AC13=1,AA13-Cost_round*I13+U13-AB13,"") -> 0 | AJ13: =IF($AC13=1,SUM(AD13:AI13),"") -> 155 | AK13: =IF($AC13=1,AD13*Beta_y^1+AE13*Beta_y^2+AF13*Beta_y^3+AG13*Beta_y^4+AH13*Beta_y^5+AI13*Beta_y^6,"") -> 139.7787 | AL13: =IF($AC13=1,AK13+Beta_y^6*U13/Hurdle_r,"") -> 732.47633 | AM13: =IF($AC13=1,AK13,"") -> 139.7787 | AN13: =IF($AC13=1,AK13+Beta_y^6*U13*(1-(1+Hurdle_r)^(-Life_yrs))/Hurdle_r,"") -> 644.3756 | AO13: =IF($AC13=1,AJ13+Credit_yrs*U13,"") -> 1205 | AP13: =IF($AC13=1,$AD13/(1+AP$6)^1+$AE13/(1+AP$6)^2+$AF13/(1+AP$6)^3+$AG13/(1+AP$6)^4+$AH13/(1+AP$6)^5+$AI13/(1+AP$6)^6+$U13/AP$6/(1+AP$6)^6,"") -> 3081.2684 | AQ13: =IF($AC13=1,$AD13/(1+AQ$6)^1+$AE13/(1+AQ$6)^2+$AF13/(1+AQ$6)^3+$AG13/(1+AQ$6)^4+$AH13/(1+AQ$6)^5+$AI13/(1+AQ$6)^6+$U13/AQ$6/(1+AQ$6)^6,"") -> 1714.023 | AR13: =IF($AC13=1,$AD13/(1+AR$6)^1+$AE13/(1+AR$6)^2+$AF13/(1+AR$6)^3+$AG13/(1+AR$6)^4+$AH13/(1+AR$6)^5+$AI13/(1+AR$6)^6+$U13/AR$6/(1+AR$6)^6,"") -> 969.66167 | AS13: =IF($AC13=1,$AD13/(1+AS$6)^1+$AE13/(1+AS$6)^2+$AF13/(1+AS$6)^3+$AG13/(1+AS$6)^4+$AH13/(1+AS$6)^5+$AI13/(1+AS$6)^6+$U13/AS$6/(1+AS$6)^6,"") -> 732.47633 | AT13: =IF($AC13=1,$AD13/(1+AT$6)^1+$AE13/(1+AT$6)^2+$AF13/(1+AT$6)^3+$AG13/(1+AT$6)^4+$AH13/(1+AT$6)^5+$AI13/(1+AT$6)^6+$U13/AT$6/(1+AT$6)^6,"") -> 580.40839 | AU13: =IF($AC13=1,$AD13/(1+AU$6)^1+$AE13/(1+AU$6)^2+$AF13/(1+AU$6)^3+$AG13/(1+AU$6)^4+$AH13/(1+AU$6)^5+$AI13/(1+AU$6)^6+$U13/AU$6/(1+AU$6)^6,"") -> 435.92287 | AV13: =IF($AC13=1,$AD13/(1+AV$6)^1+$AE13/(1+AV$6)^2+$AF13/(1+AV$6)^3+$AG13/(1+AV$6)^4+$AH13/(1+AV$6)^5+$AI13/(1+AV$6)^6+$U13/AV$6/(1+AV$6)^6,"") -> 303.2327 | AW13: =IF($AC13=1,$AD13/(1+AW$6)^1+$AE13/(1+AW$6)^2+$AF13/(1+AW$6)^3+$AG13/(1+AW$6)^4+$AH13/(1+AW$6)^5+$AI13/(1+AW$6)^6+$U13/AW$6/(1+AW$6)^6,"") -> 189.64693 | ... BB13: =IF($AC13=1,$AD13/(1+BB$6)^1+$AE13/(1+BB$6)^2+$AF13/(1+BB$6)^3+$AG13/(1+BB$6)^4+$AH13/(1+BB$6)^5+$AI13/(1+BB$6)^6+$U13/BB$6/(1+BB$6)^6,"") -> 190.51622
A14: 6 | B14: =D14&E14&F14&G14&H14&I14 -> 000110 | C14: =SUM(D14:I14) -> 2 | D14: =MOD(INT($A14/32),2) -> 0 | E14: =MOD(INT($A14/16),2) -> 0 | F14: =MOD(INT($A14/8),2) -> 0 | G14: =MOD(INT($A14/4),2) -> 1 | H14: =MOD(INT($A14/2),2) -> 1 | I14: =MOD(INT($A14/1),2) -> 0 | J14: =E_zero+D14*(Half_gap*(Ceiling_e-E_zero)-$F$4) -> 71 | K14: =J14+E14*(Half_gap*(Ceiling_e-J14)-$F$4) -> 71 | L14: =K14+F14*(Half_gap*(Ceiling_e-K14)-$F$4) -> 71 | M14: =L14+G14*(Half_gap*(Ceiling_e-L14)-$F$4) -> 78 | N14: =M14+H14*(Half_gap*(Ceiling_e-M14)-$F$4) -> 81.5 | O14: =N14+I14*(Half_gap*(Ceiling_e-N14)-$F$4) -> 81.5 | P14: =Val_pt*(J14-E_zero) -> 0 | Q14: =Val_pt*(K14-E_zero) -> 0 | R14: =Val_pt*(L14-E_zero) -> 0 | S14: =Val_pt*(M14-E_zero) -> 70 | T14: =Val_pt*(N14-E_zero) -> 105 | U14: =Val_pt*(O14-E_zero) -> 105 | V14: =MAX(W14+Cost_round*D14-P14,IF(D14=1,Pre_q,0)) -> 520 | W14: =MAX(X14+Cost_round*E14-Q14,IF(E14=1,Pre_q,0),Floor_q) -> 520 | X14: =MAX(Y14+Cost_round*F14-R14,IF(F14=1,Pre_q,0),Floor_q) -> 520 | Y14: =MAX(Z14+Cost_round*G14-S14,IF(G14=1,Pre_q,0),Floor_q) -> 520 | Z14: =MAX(AA14+Cost_round*H14-T14,IF(H14=1,Pre_q,0),Floor_q) -> 470 | AA14: =MAX(AB14+Cost_round*I14-U14,IF(I14=1,Pre_q,0),Floor_q) -> 365 | AB14: =MAX(End_q,Floor_q) -> 470 | AC14: =IF(Q_zero>=V14-0.000000001,1,0) -> 1 | AD14: =IF($AC14=1,Q_zero-Cost_round*D14+P14-W14,"") -> 100 | AE14: =IF($AC14=1,W14-Cost_round*E14+Q14-X14,"") -> 0 | AF14: =IF($AC14=1,X14-Cost_round*F14+R14-Y14,"") -> 0 | AG14: =IF($AC14=1,Y14-Cost_round*G14+S14-Z14,"") -> 0 | AH14: =IF($AC14=1,Z14-Cost_round*H14+T14-AA14,"") -> 90 | AI14: =IF($AC14=1,AA14-Cost_round*I14+U14-AB14,"") -> 0 | AJ14: =IF($AC14=1,SUM(AD14:AI14),"") -> 190 | AK14: =IF($AC14=1,AD14*Beta_y^1+AE14*Beta_y^2+AF14*Beta_y^3+AG14*Beta_y^4+AH14*Beta_y^5+AI14*Beta_y^6,"") -> 146.79201 | AL14: =IF($AC14=1,AK14+Beta_y^6*U14/Hurdle_r,"") -> 739.48964 | AM14: =IF($AC14=1,AK14,"") -> 146.79201 | AN14: =IF($AC14=1,AK14+Beta_y^6*U14*(1-(1+Hurdle_r)^(-Life_yrs))/Hurdle_r,"") -> 651.38891 | AO14: =IF($AC14=1,AJ14+Credit_yrs*U14,"") -> 1240 | AP14: =IF($AC14=1,$AD14/(1+AP$6)^1+$AE14/(1+AP$6)^2+$AF14/(1+AP$6)^3+$AG14/(1+AP$6)^4+$AH14/(1+AP$6)^5+$AI14/(1+AP$6)^6+$U14/AP$6/(1+AP$6)^6,"") -> 3105.9171 | AQ14: =IF($AC14=1,$AD14/(1+AQ$6)^1+$AE14/(1+AQ$6)^2+$AF14/(1+AQ$6)^3+$AG14/(1+AQ$6)^4+$AH14/(1+AQ$6)^5+$AI14/(1+AQ$6)^6+$U14/AQ$6/(1+AQ$6)^6,"") -> 1732.8078 | AR14: =IF($AC14=1,$AD14/(1+AR$6)^1+$AE14/(1+AR$6)^2+$AF14/(1+AR$6)^3+$AG14/(1+AR$6)^4+$AH14/(1+AR$6)^5+$AI14/(1+AR$6)^6+$U14/AR$6/(1+AR$6)^6,"") -> 980.94272 | AS14: =IF($AC14=1,$AD14/(1+AS$6)^1+$AE14/(1+AS$6)^2+$AF14/(1+AS$6)^3+$AG14/(1+AS$6)^4+$AH14/(1+AS$6)^5+$AI14/(1+AS$6)^6+$U14/AS$6/(1+AS$6)^6,"") -> 739.48964 | AT14: =IF($AC14=1,$AD14/(1+AT$6)^1+$AE14/(1+AT$6)^2+$AF14/(1+AT$6)^3+$AG14/(1+AT$6)^4+$AH14/(1+AT$6)^5+$AI14/(1+AT$6)^6+$U14/AT$6/(1+AT$6)^6,"") -> 583.65636 | AU14: =IF($AC14=1,$AD14/(1+AU$6)^1+$AE14/(1+AU$6)^2+$AF14/(1+AU$6)^3+$AG14/(1+AU$6)^4+$AH14/(1+AU$6)^5+$AI14/(1+AU$6)^6+$U14/AU$6/(1+AU$6)^6,"") -> 434.33175 | AV14: =IF($AC14=1,$AD14/(1+AV$6)^1+$AE14/(1+AV$6)^2+$AF14/(1+AV$6)^3+$AG14/(1+AV$6)^4+$AH14/(1+AV$6)^5+$AI14/(1+AV$6)^6+$U14/AV$6/(1+AV$6)^6,"") -> 295.32375 | AW14: =IF($AC14=1,$AD14/(1+AW$6)^1+$AE14/(1+AW$6)^2+$AF14/(1+AW$6)^3+$AG14/(1+AW$6)^4+$AH14/(1+AW$6)^5+$AI14/(1+AW$6)^6+$U14/AW$6/(1+AW$6)^6,"") -> 173.67437 | ... BB14: =IF($AC14=1,$AD14/(1+BB$6)^1+$AE14/(1+BB$6)^2+$AF14/(1+BB$6)^3+$AG14/(1+BB$6)^4+$AH14/(1+BB$6)^5+$AI14/(1+BB$6)^6+$U14/BB$6/(1+BB$6)^6,"") -> 174.61907
A15: 7 | B15: =D15&E15&F15&G15&H15&I15 -> 000111 | C15: =SUM(D15:I15) -> 3 | D15: =MOD(INT($A15/32),2) -> 0 | E15: =MOD(INT($A15/16),2) -> 0 | F15: =MOD(INT($A15/8),2) -> 0 | G15: =MOD(INT($A15/4),2) -> 1 | H15: =MOD(INT($A15/2),2) -> 1 | I15: =MOD(INT($A15/1),2) -> 1 | J15: =E_zero+D15*(Half_gap*(Ceiling_e-E_zero)-$F$4) -> 71 | K15: =J15+E15*(Half_gap*(Ceiling_e-J15)-$F$4) -> 71 | L15: =K15+F15*(Half_gap*(Ceiling_e-K15)-$F$4) -> 71 | M15: =L15+G15*(Half_gap*(Ceiling_e-L15)-$F$4) -> 78 | N15: =M15+H15*(Half_gap*(Ceiling_e-M15)-$F$4) -> 81.5 | O15: =N15+I15*(Half_gap*(Ceiling_e-N15)-$F$4) -> 83.25 | P15: =Val_pt*(J15-E_zero) -> 0 | Q15: =Val_pt*(K15-E_zero) -> 0 | R15: =Val_pt*(L15-E_zero) -> 0 | S15: =Val_pt*(M15-E_zero) -> 70 | T15: =Val_pt*(N15-E_zero) -> 105 | U15: =Val_pt*(O15-E_zero) -> 122.5 | V15: =MAX(W15+Cost_round*D15-P15,IF(D15=1,Pre_q,0)) -> 535 | W15: =MAX(X15+Cost_round*E15-Q15,IF(E15=1,Pre_q,0),Floor_q) -> 535 | X15: =MAX(Y15+Cost_round*F15-R15,IF(F15=1,Pre_q,0),Floor_q) -> 535 | Y15: =MAX(Z15+Cost_round*G15-S15,IF(G15=1,Pre_q,0),Floor_q) -> 535 | Z15: =MAX(AA15+Cost_round*H15-T15,IF(H15=1,Pre_q,0),Floor_q) -> 485 | AA15: =MAX(AB15+Cost_round*I15-U15,IF(I15=1,Pre_q,0),Floor_q) -> 470 | AB15: =MAX(End_q,Floor_q) -> 470 | AC15: =IF(Q_zero>=V15-0.000000001,1,0) -> 1 | AD15: =IF($AC15=1,Q_zero-Cost_round*D15+P15-W15,"") -> 85 | AE15: =IF($AC15=1,W15-Cost_round*E15+Q15-X15,"") -> 0 | AF15: =IF($AC15=1,X15-Cost_round*F15+R15-Y15,"") -> 0 | AG15: =IF($AC15=1,Y15-Cost_round*G15+S15-Z15,"") -> 0 | AH15: =IF($AC15=1,Z15-Cost_round*H15+T15-AA15,"") -> 0 | AI15: =IF($AC15=1,AA15-Cost_round*I15+U15-AB15,"") -> 2.5 | AJ15: =IF($AC15=1,SUM(AD15:AI15),"") -> 87.5 | AK15: =IF($AC15=1,AD15*Beta_y^1+AE15*Beta_y^2+AF15*Beta_y^3+AG15*Beta_y^4+AH15*Beta_y^5+AI15*Beta_y^6,"") -> 78.683912 | AL15: =IF($AC15=1,AK15+Beta_y^6*U15/Hurdle_r,"") -> 770.16448 | AM15: =IF($AC15=1,AK15,"") -> 78.683912 | AN15: =IF($AC15=1,AK15+Beta_y^6*U15*(1-(1+Hurdle_r)^(-Life_yrs))/Hurdle_r,"") -> 667.3803 | AO15: =IF($AC15=1,AJ15+Credit_yrs*U15,"") -> 1312.5 | AP15: =IF($AC15=1,$AD15/(1+AP$6)^1+$AE15/(1+AP$6)^2+$AF15/(1+AP$6)^3+$AG15/(1+AP$6)^4+$AH15/(1+AP$6)^5+$AI15/(1+AP$6)^6+$U15/AP$6/(1+AP$6)^6,"") -> 3504.3454 | AQ15: =IF($AC15=1,$AD15/(1+AQ$6)^1+$AE15/(1+AQ$6)^2+$AF15/(1+AQ$6)^3+$AG15/(1+AQ$6)^4+$AH15/(1+AQ$6)^5+$AI15/(1+AQ$6)^6+$U15/AQ$6/(1+AQ$6)^6,"") -> 1911.0456 | AR15: =IF($AC15=1,$AD15/(1+AR$6)^1+$AE15/(1+AR$6)^2+$AF15/(1+AR$6)^3+$AG15/(1+AR$6)^4+$AH15/(1+AR$6)^5+$AI15/(1+AR$6)^6+$U15/AR$6/(1+AR$6)^6,"") -> 1045.2264 | AS15: =IF($AC15=1,$AD15/(1+AS$6)^1+$AE15/(1+AS$6)^2+$AF15/(1+AS$6)^3+$AG15/(1+AS$6)^4+$AH15/(1+AS$6)^5+$AI15/(1+AS$6)^6+$U15/AS$6/(1+AS$6)^6,"") -> 770.16448 | AT15: =IF($AC15=1,$AD15/(1+AT$6)^1+$AE15/(1+AT$6)^2+$AF15/(1+AT$6)^3+$AG15/(1+AT$6)^4+$AH15/(1+AT$6)^5+$AI15/(1+AT$6)^6+$U15/AT$6/(1+AT$6)^6,"") -> 594.34537 | AU15: =IF($AC15=1,$AD15/(1+AU$6)^1+$AE15/(1+AU$6)^2+$AF15/(1+AU$6)^3+$AG15/(1+AU$6)^4+$AH15/(1+AU$6)^5+$AI15/(1+AU$6)^6+$U15/AU$6/(1+AU$6)^6,"") -> 428.0614 | AV15: =IF($AC15=1,$AD15/(1+AV$6)^1+$AE15/(1+AV$6)^2+$AF15/(1+AV$6)^3+$AG15/(1+AV$6)^4+$AH15/(1+AV$6)^5+$AI15/(1+AV$6)^6+$U15/AV$6/(1+AV$6)^6,"") -> 276.79559 | AW15: =IF($AC15=1,$AD15/(1+AW$6)^1+$AE15/(1+AW$6)^2+$AF15/(1+AW$6)^3+$AG15/(1+AW$6)^4+$AH15/(1+AW$6)^5+$AI15/(1+AW$6)^6+$U15/AW$6/(1+AW$6)^6,"") -> 150.49951 | ... BB15: =IF($AC15=1,$AD15/(1+BB$6)^1+$AE15/(1+BB$6)^2+$AF15/(1+BB$6)^3+$AG15/(1+BB$6)^4+$AH15/(1+BB$6)^5+$AI15/(1+BB$6)^6+$U15/BB$6/(1+BB$6)^6,"") -> 151.43993
A16: 8 | B16: =D16&E16&F16&G16&H16&I16 -> 001000 | C16: =SUM(D16:I16) -> 1 | D16: =MOD(INT($A16/32),2) -> 0 | E16: =MOD(INT($A16/16),2) -> 0 | F16: =MOD(INT($A16/8),2) -> 1 | G16: =MOD(INT($A16/4),2) -> 0 | H16: =MOD(INT($A16/2),2) -> 0 | I16: =MOD(INT($A16/1),2) -> 0 | J16: =E_zero+D16*(Half_gap*(Ceiling_e-E_zero)-$F$4) -> 71 | K16: =J16+E16*(Half_gap*(Ceiling_e-J16)-$F$4) -> 71 | L16: =K16+F16*(Half_gap*(Ceiling_e-K16)-$F$4) -> 78 | M16: =L16+G16*(Half_gap*(Ceiling_e-L16)-$F$4) -> 78 | N16: =M16+H16*(Half_gap*(Ceiling_e-M16)-$F$4) -> 78 | O16: =N16+I16*(Half_gap*(Ceiling_e-N16)-$F$4) -> 78 | P16: =Val_pt*(J16-E_zero) -> 0 | Q16: =Val_pt*(K16-E_zero) -> 0 | R16: =Val_pt*(L16-E_zero) -> 70 | S16: =Val_pt*(M16-E_zero) -> 70 | T16: =Val_pt*(N16-E_zero) -> 70 | U16: =Val_pt*(O16-E_zero) -> 70 | V16: =MAX(W16+Cost_round*D16-P16,IF(D16=1,Pre_q,0)) -> 470 | W16: =MAX(X16+Cost_round*E16-Q16,IF(E16=1,Pre_q,0),Floor_q) -> 470 | X16: =MAX(Y16+Cost_round*F16-R16,IF(F16=1,Pre_q,0),Floor_q) -> 470 | Y16: =MAX(Z16+Cost_round*G16-S16,IF(G16=1,Pre_q,0),Floor_q) -> 350 | Z16: =MAX(AA16+Cost_round*H16-T16,IF(H16=1,Pre_q,0),Floor_q) -> 350 | AA16: =MAX(AB16+Cost_round*I16-U16,IF(I16=1,Pre_q,0),Floor_q) -> 400 | AB16: =MAX(End_q,Floor_q) -> 470 | AC16: =IF(Q_zero>=V16-0.000000001,1,0) -> 1 | AD16: =IF($AC16=1,Q_zero-Cost_round*D16+P16-W16,"") -> 150 | AE16: =IF($AC16=1,W16-Cost_round*E16+Q16-X16,"") -> 0 | AF16: =IF($AC16=1,X16-Cost_round*F16+R16-Y16,"") -> 70 | AG16: =IF($AC16=1,Y16-Cost_round*G16+S16-Z16,"") -> 70 | AH16: =IF($AC16=1,Z16-Cost_round*H16+T16-AA16,"") -> 20 | AI16: =IF($AC16=1,AA16-Cost_round*I16+U16-AB16,"") -> 0 | AJ16: =IF($AC16=1,SUM(AD16:AI16),"") -> 310 | AK16: =IF($AC16=1,AD16*Beta_y^1+AE16*Beta_y^2+AF16*Beta_y^3+AG16*Beta_y^4+AH16*Beta_y^5+AI16*Beta_y^6,"") -> 249.18504 | AL16: =IF($AC16=1,AK16+Beta_y^6*U16/Hurdle_r,"") -> 644.31679 | AM16: =IF($AC16=1,AK16,"") -> 249.18504 | AN16: =IF($AC16=1,AK16+Beta_y^6*U16*(1-(1+Hurdle_r)^(-Life_yrs))/Hurdle_r,"") -> 585.58297 | AO16: =IF($AC16=1,AJ16+Credit_yrs*U16,"") -> 1010 | AP16: =IF($AC16=1,$AD16/(1+AP$6)^1+$AE16/(1+AP$6)^2+$AF16/(1+AP$6)^3+$AG16/(1+AP$6)^4+$AH16/(1+AP$6)^5+$AI16/(1+AP$6)^6+$U16/AP$6/(1+AP$6)^6,"") -> 2243.2672 | AQ16: =IF($AC16=1,$AD16/(1+AQ$6)^1+$AE16/(1+AQ$6)^2+$AF16/(1+AQ$6)^3+$AG16/(1+AQ$6)^4+$AH16/(1+AQ$6)^5+$AI16/(1+AQ$6)^6+$U16/AQ$6/(1+AQ$6)^6,"") -> 1321.287 | AR16: =IF($AC16=1,$AD16/(1+AR$6)^1+$AE16/(1+AR$6)^2+$AF16/(1+AR$6)^3+$AG16/(1+AR$6)^4+$AH16/(1+AR$6)^5+$AI16/(1+AR$6)^6+$U16/AR$6/(1+AR$6)^6,"") -> 810.91932 | AS16: =IF($AC16=1,$AD16/(1+AS$6)^1+$AE16/(1+AS$6)^2+$AF16/(1+AS$6)^3+$AG16/(1+AS$6)^4+$AH16/(1+AS$6)^5+$AI16/(1+AS$6)^6+$U16/AS$6/(1+AS$6)^6,"") -> 644.31679 | AT16: =IF($AC16=1,$AD16/(1+AT$6)^1+$AE16/(1+AT$6)^2+$AF16/(1+AT$6)^3+$AG16/(1+AT$6)^4+$AH16/(1+AT$6)^5+$AI16/(1+AT$6)^6+$U16/AT$6/(1+AT$6)^6,"") -> 535.12281 | AU16: =IF($AC16=1,$AD16/(1+AU$6)^1+$AE16/(1+AU$6)^2+$AF16/(1+AU$6)^3+$AG16/(1+AU$6)^4+$AH16/(1+AU$6)^5+$AI16/(1+AU$6)^6+$U16/AU$6/(1+AU$6)^6,"") -> 428.18006 | AV16: =IF($AC16=1,$AD16/(1+AV$6)^1+$AE16/(1+AV$6)^2+$AF16/(1+AV$6)^3+$AG16/(1+AV$6)^4+$AH16/(1+AV$6)^5+$AI16/(1+AV$6)^6+$U16/AV$6/(1+AV$6)^6,"") -> 324.51882 | AW16: =IF($AC16=1,$AD16/(1+AW$6)^1+$AE16/(1+AW$6)^2+$AF16/(1+AW$6)^3+$AG16/(1+AW$6)^4+$AH16/(1+AW$6)^5+$AI16/(1+AW$6)^6+$U16/AW$6/(1+AW$6)^6,"") -> 225.48289 | ... BB16: =IF($AC16=1,$AD16/(1+BB$6)^1+$AE16/(1+BB$6)^2+$AF16/(1+BB$6)^3+$AG16/(1+BB$6)^4+$AH16/(1+BB$6)^5+$AI16/(1+BB$6)^6+$U16/BB$6/(1+BB$6)^6,"") -> 226.31519
A17: 9 | B17: =D17&E17&F17&G17&H17&I17 -> 001001 | C17: =SUM(D17:I17) -> 2 | D17: =MOD(INT($A17/32),2) -> 0 | E17: =MOD(INT($A17/16),2) -> 0 | F17: =MOD(INT($A17/8),2) -> 1 | G17: =MOD(INT($A17/4),2) -> 0 | H17: =MOD(INT($A17/2),2) -> 0 | I17: =MOD(INT($A17/1),2) -> 1 | J17: =E_zero+D17*(Half_gap*(Ceiling_e-E_zero)-$F$4) -> 71 | K17: =J17+E17*(Half_gap*(Ceiling_e-J17)-$F$4) -> 71 | L17: =K17+F17*(Half_gap*(Ceiling_e-K17)-$F$4) -> 78 | M17: =L17+G17*(Half_gap*(Ceiling_e-L17)-$F$4) -> 78 | N17: =M17+H17*(Half_gap*(Ceiling_e-M17)-$F$4) -> 78 | O17: =N17+I17*(Half_gap*(Ceiling_e-N17)-$F$4) -> 81.5 | P17: =Val_pt*(J17-E_zero) -> 0 | Q17: =Val_pt*(K17-E_zero) -> 0 | R17: =Val_pt*(L17-E_zero) -> 70 | S17: =Val_pt*(M17-E_zero) -> 70 | T17: =Val_pt*(N17-E_zero) -> 70 | U17: =Val_pt*(O17-E_zero) -> 105 | V17: =MAX(W17+Cost_round*D17-P17,IF(D17=1,Pre_q,0)) -> 470 | W17: =MAX(X17+Cost_round*E17-Q17,IF(E17=1,Pre_q,0),Floor_q) -> 470 | X17: =MAX(Y17+Cost_round*F17-R17,IF(F17=1,Pre_q,0),Floor_q) -> 470 | Y17: =MAX(Z17+Cost_round*G17-S17,IF(G17=1,Pre_q,0),Floor_q) -> 350 | Z17: =MAX(AA17+Cost_round*H17-T17,IF(H17=1,Pre_q,0),Floor_q) -> 415 | AA17: =MAX(AB17+Cost_round*I17-U17,IF(I17=1,Pre_q,0),Floor_q) -> 485 | AB17: =MAX(End_q,Floor_q) -> 470 | AC17: =IF(Q_zero>=V17-0.000000001,1,0) -> 1 | AD17: =IF($AC17=1,Q_zero-Cost_round*D17+P17-W17,"") -> 150 | AE17: =IF($AC17=1,W17-Cost_round*E17+Q17-X17,"") -> 0 | AF17: =IF($AC17=1,X17-Cost_round*F17+R17-Y17,"") -> 70 | AG17: =IF($AC17=1,Y17-Cost_round*G17+S17-Z17,"") -> 5 | AH17: =IF($AC17=1,Z17-Cost_round*H17+T17-AA17,"") -> 0 | AI17: =IF($AC17=1,AA17-Cost_round*I17+U17-AB17,"") -> 0 | AJ17: =IF($AC17=1,SUM(AD17:AI17),"") -> 225 | AK17: =IF($AC17=1,AD17*Beta_y^1+AE17*Beta_y^2+AF17*Beta_y^3+AG17*Beta_y^4+AH17*Beta_y^5+AI17*Beta_y^6,"") -> 192.37074 | AL17: =IF($AC17=1,AK17+Beta_y^6*U17/Hurdle_r,"") -> 785.06837 | AM17: =IF($AC17=1,AK17,"") -> 192.37074 | AN17: =IF($AC17=1,AK17+Beta_y^6*U17*(1-(1+Hurdle_r)^(-Life_yrs))/Hurdle_r,"") -> 696.96764 | AO17: =IF($AC17=1,AJ17+Credit_yrs*U17,"") -> 1275 | AP17: =IF($AC17=1,$AD17/(1+AP$6)^1+$AE17/(1+AP$6)^2+$AF17/(1+AP$6)^3+$AG17/(1+AP$6)^4+$AH17/(1+AP$6)^5+$AI17/(1+AP$6)^6+$U17/AP$6/(1+AP$6)^6,"") -> 3145.3283 | AQ17: =IF($AC17=1,$AD17/(1+AQ$6)^1+$AE17/(1+AQ$6)^2+$AF17/(1+AQ$6)^3+$AG17/(1+AQ$6)^4+$AH17/(1+AQ$6)^5+$AI17/(1+AQ$6)^6+$U17/AQ$6/(1+AQ$6)^6,"") -> 1774.4916 | AR17: =IF($AC17=1,$AD17/(1+AR$6)^1+$AE17/(1+AR$6)^2+$AF17/(1+AR$6)^3+$AG17/(1+AR$6)^4+$AH17/(1+AR$6)^5+$AI17/(1+AR$6)^6+$U17/AR$6/(1+AR$6)^6,"") -> 1025.2299 | AS17: =IF($AC17=1,$AD17/(1+AS$6)^1+$AE17/(1+AS$6)^2+$AF17/(1+AS$6)^3+$AG17/(1+AS$6)^4+$AH17/(1+AS$6)^5+$AI17/(1+AS$6)^6+$U17/AS$6/(1+AS$6)^6,"") -> 785.06837 | AT17: =IF($AC17=1,$AD17/(1+AT$6)^1+$AE17/(1+AT$6)^2+$AF17/(1+AT$6)^3+$AG17/(1+AT$6)^4+$AH17/(1+AT$6)^5+$AI17/(1+AT$6)^6+$U17/AT$6/(1+AT$6)^6,"") -> 630.23301 | AU17: =IF($AC17=1,$AD17/(1+AU$6)^1+$AE17/(1+AU$6)^2+$AF17/(1+AU$6)^3+$AG17/(1+AU$6)^4+$AH17/(1+AU$6)^5+$AI17/(1+AU$6)^6+$U17/AU$6/(1+AU$6)^6,"") -> 481.949 | AV17: =IF($AC17=1,$AD17/(1+AV$6)^1+$AE17/(1+AV$6)^2+$AF17/(1+AV$6)^3+$AG17/(1+AV$6)^4+$AH17/(1+AV$6)^5+$AI17/(1+AV$6)^6+$U17/AV$6/(1+AV$6)^6,"") -> 343.74196 | AW17: =IF($AC17=1,$AD17/(1+AW$6)^1+$AE17/(1+AW$6)^2+$AF17/(1+AW$6)^3+$AG17/(1+AW$6)^4+$AH17/(1+AW$6)^5+$AI17/(1+AW$6)^6+$U17/AW$6/(1+AW$6)^6,"") -> 221.50856 | ... BB17: =IF($AC17=1,$AD17/(1+BB$6)^1+$AE17/(1+BB$6)^2+$AF17/(1+BB$6)^3+$AG17/(1+BB$6)^4+$AH17/(1+BB$6)^5+$AI17/(1+BB$6)^6+$U17/BB$6/(1+BB$6)^6,"") -> 222.47283
A18: 10 | B18: =D18&E18&F18&G18&H18&I18 -> 001010 | C18: =SUM(D18:I18) -> 2 | D18: =MOD(INT($A18/32),2) -> 0 | E18: =MOD(INT($A18/16),2) -> 0 | F18: =MOD(INT($A18/8),2) -> 1 | G18: =MOD(INT($A18/4),2) -> 0 | H18: =MOD(INT($A18/2),2) -> 1 | I18: =MOD(INT($A18/1),2) -> 0 | J18: =E_zero+D18*(Half_gap*(Ceiling_e-E_zero)-$F$4) -> 71 | K18: =J18+E18*(Half_gap*(Ceiling_e-J18)-$F$4) -> 71 | L18: =K18+F18*(Half_gap*(Ceiling_e-K18)-$F$4) -> 78 | M18: =L18+G18*(Half_gap*(Ceiling_e-L18)-$F$4) -> 78 | N18: =M18+H18*(Half_gap*(Ceiling_e-M18)-$F$4) -> 81.5 | O18: =N18+I18*(Half_gap*(Ceiling_e-N18)-$F$4) -> 81.5 | P18: =Val_pt*(J18-E_zero) -> 0 | Q18: =Val_pt*(K18-E_zero) -> 0 | R18: =Val_pt*(L18-E_zero) -> 70 | S18: =Val_pt*(M18-E_zero) -> 70 | T18: =Val_pt*(N18-E_zero) -> 105 | U18: =Val_pt*(O18-E_zero) -> 105 | V18: =MAX(W18+Cost_round*D18-P18,IF(D18=1,Pre_q,0)) -> 470 | W18: =MAX(X18+Cost_round*E18-Q18,IF(E18=1,Pre_q,0),Floor_q) -> 470 | X18: =MAX(Y18+Cost_round*F18-R18,IF(F18=1,Pre_q,0),Floor_q) -> 470 | Y18: =MAX(Z18+Cost_round*G18-S18,IF(G18=1,Pre_q,0),Floor_q) -> 400 | Z18: =MAX(AA18+Cost_round*H18-T18,IF(H18=1,Pre_q,0),Floor_q) -> 470 | AA18: =MAX(AB18+Cost_round*I18-U18,IF(I18=1,Pre_q,0),Floor_q) -> 365 | AB18: =MAX(End_q,Floor_q) -> 470 | AC18: =IF(Q_zero>=V18-0.000000001,1,0) -> 1 | AD18: =IF($AC18=1,Q_zero-Cost_round*D18+P18-W18,"") -> 150 | AE18: =IF($AC18=1,W18-Cost_round*E18+Q18-X18,"") -> 0 | AF18: =IF($AC18=1,X18-Cost_round*F18+R18-Y18,"") -> 20 | AG18: =IF($AC18=1,Y18-Cost_round*G18+S18-Z18,"") -> 0 | AH18: =IF($AC18=1,Z18-Cost_round*H18+T18-AA18,"") -> 90 | AI18: =IF($AC18=1,AA18-Cost_round*I18+U18-AB18,"") -> 0 | AJ18: =IF($AC18=1,SUM(AD18:AI18),"") -> 260 | AK18: =IF($AC18=1,AD18*Beta_y^1+AE18*Beta_y^2+AF18*Beta_y^3+AG18*Beta_y^4+AH18*Beta_y^5+AI18*Beta_y^6,"") -> 207.27285 | AL18: =IF($AC18=1,AK18+Beta_y^6*U18/Hurdle_r,"") -> 799.97048 | AM18: =IF($AC18=1,AK18,"") -> 207.27285 | AN18: =IF($AC18=1,AK18+Beta_y^6*U18*(1-(1+Hurdle_r)^(-Life_yrs))/Hurdle_r,"") -> 711.86975 | AO18: =IF($AC18=1,AJ18+Credit_yrs*U18,"") -> 1310 | AP18: =IF($AC18=1,$AD18/(1+AP$6)^1+$AE18/(1+AP$6)^2+$AF18/(1+AP$6)^3+$AG18/(1+AP$6)^4+$AH18/(1+AP$6)^5+$AI18/(1+AP$6)^6+$U18/AP$6/(1+AP$6)^6,"") -> 3172.7636 | AQ18: =IF($AC18=1,$AD18/(1+AQ$6)^1+$AE18/(1+AQ$6)^2+$AF18/(1+AQ$6)^3+$AG18/(1+AQ$6)^4+$AH18/(1+AQ$6)^5+$AI18/(1+AQ$6)^6+$U18/AQ$6/(1+AQ$6)^6,"") -> 1797.7036 | AR18: =IF($AC18=1,$AD18/(1+AR$6)^1+$AE18/(1+AR$6)^2+$AF18/(1+AR$6)^3+$AG18/(1+AR$6)^4+$AH18/(1+AR$6)^5+$AI18/(1+AR$6)^6+$U18/AR$6/(1+AR$6)^6,"") -> 1043.1157 | AS18: =IF($AC18=1,$AD18/(1+AS$6)^1+$AE18/(1+AS$6)^2+$AF18/(1+AS$6)^3+$AG18/(1+AS$6)^4+$AH18/(1+AS$6)^5+$AI18/(1+AS$6)^6+$U18/AS$6/(1+AS$6)^6,"") -> 799.97048 | AT18: =IF($AC18=1,$AD18/(1+AT$6)^1+$AE18/(1+AT$6)^2+$AF18/(1+AT$6)^3+$AG18/(1+AT$6)^4+$AH18/(1+AT$6)^5+$AI18/(1+AT$6)^6+$U18/AT$6/(1+AT$6)^6,"") -> 642.53482 | AU18: =IF($AC18=1,$AD18/(1+AU$6)^1+$AE18/(1+AU$6)^2+$AF18/(1+AU$6)^3+$AG18/(1+AU$6)^4+$AH18/(1+AU$6)^5+$AI18/(1+AU$6)^6+$U18/AU$6/(1+AU$6)^6,"") -> 490.96033 | AV18: =IF($AC18=1,$AD18/(1+AV$6)^1+$AE18/(1+AV$6)^2+$AF18/(1+AV$6)^3+$AG18/(1+AV$6)^4+$AH18/(1+AV$6)^5+$AI18/(1+AV$6)^6+$U18/AV$6/(1+AV$6)^6,"") -> 348.56449 | AW18: =IF($AC18=1,$AD18/(1+AW$6)^1+$AE18/(1+AW$6)^2+$AF18/(1+AW$6)^3+$AG18/(1+AW$6)^4+$AH18/(1+AW$6)^5+$AI18/(1+AW$6)^6+$U18/AW$6/(1+AW$6)^6,"") -> 221.23923 | ... BB18: =IF($AC18=1,$AD18/(1+BB$6)^1+$AE18/(1+BB$6)^2+$AF18/(1+BB$6)^3+$AG18/(1+BB$6)^4+$AH18/(1+BB$6)^5+$AI18/(1+BB$6)^6+$U18/BB$6/(1+BB$6)^6,"") -> 222.24925
A19: 11 | B19: =D19&E19&F19&G19&H19&I19 -> 001011 | C19: =SUM(D19:I19) -> 3 | D19: =MOD(INT($A19/32),2) -> 0 | E19: =MOD(INT($A19/16),2) -> 0 | F19: =MOD(INT($A19/8),2) -> 1 | G19: =MOD(INT($A19/4),2) -> 0 | H19: =MOD(INT($A19/2),2) -> 1 | I19: =MOD(INT($A19/1),2) -> 1 | J19: =E_zero+D19*(Half_gap*(Ceiling_e-E_zero)-$F$4) -> 71 | K19: =J19+E19*(Half_gap*(Ceiling_e-J19)-$F$4) -> 71 | L19: =K19+F19*(Half_gap*(Ceiling_e-K19)-$F$4) -> 78 | M19: =L19+G19*(Half_gap*(Ceiling_e-L19)-$F$4) -> 78 | N19: =M19+H19*(Half_gap*(Ceiling_e-M19)-$F$4) -> 81.5 | O19: =N19+I19*(Half_gap*(Ceiling_e-N19)-$F$4) -> 83.25 | P19: =Val_pt*(J19-E_zero) -> 0 | Q19: =Val_pt*(K19-E_zero) -> 0 | R19: =Val_pt*(L19-E_zero) -> 70 | S19: =Val_pt*(M19-E_zero) -> 70 | T19: =Val_pt*(N19-E_zero) -> 105 | U19: =Val_pt*(O19-E_zero) -> 122.5 | V19: =MAX(W19+Cost_round*D19-P19,IF(D19=1,Pre_q,0)) -> 470 | W19: =MAX(X19+Cost_round*E19-Q19,IF(E19=1,Pre_q,0),Floor_q) -> 470 | X19: =MAX(Y19+Cost_round*F19-R19,IF(F19=1,Pre_q,0),Floor_q) -> 470 | Y19: =MAX(Z19+Cost_round*G19-S19,IF(G19=1,Pre_q,0),Floor_q) -> 415 | Z19: =MAX(AA19+Cost_round*H19-T19,IF(H19=1,Pre_q,0),Floor_q) -> 485 | AA19: =MAX(AB19+Cost_round*I19-U19,IF(I19=1,Pre_q,0),Floor_q) -> 470 | AB19: =MAX(End_q,Floor_q) -> 470 | AC19: =IF(Q_zero>=V19-0.000000001,1,0) -> 1 | AD19: =IF($AC19=1,Q_zero-Cost_round*D19+P19-W19,"") -> 150 | AE19: =IF($AC19=1,W19-Cost_round*E19+Q19-X19,"") -> 0 | AF19: =IF($AC19=1,X19-Cost_round*F19+R19-Y19,"") -> 5 | AG19: =IF($AC19=1,Y19-Cost_round*G19+S19-Z19,"") -> 0 | AH19: =IF($AC19=1,Z19-Cost_round*H19+T19-AA19,"") -> 0 | AI19: =IF($AC19=1,AA19-Cost_round*I19+U19-AB19,"") -> 2.5 | AJ19: =IF($AC19=1,SUM(AD19:AI19),"") -> 157.5 | AK19: =IF($AC19=1,AD19*Beta_y^1+AE19*Beta_y^2+AF19*Beta_y^3+AG19*Beta_y^4+AH19*Beta_y^5+AI19*Beta_y^6,"") -> 141.5314 | AL19: =IF($AC19=1,AK19+Beta_y^6*U19/Hurdle_r,"") -> 833.01196 | AM19: =IF($AC19=1,AK19,"") -> 141.5314 | AN19: =IF($AC19=1,AK19+Beta_y^6*U19*(1-(1+Hurdle_r)^(-Life_yrs))/Hurdle_r,"") -> 730.22778 | AO19: =IF($AC19=1,AJ19+Credit_yrs*U19,"") -> 1382.5 | AP19: =IF($AC19=1,$AD19/(1+AP$6)^1+$AE19/(1+AP$6)^2+$AF19/(1+AP$6)^3+$AG19/(1+AP$6)^4+$AH19/(1+AP$6)^5+$AI19/(1+AP$6)^6+$U19/AP$6/(1+AP$6)^6,"") -> 3572.0279 | AQ19: =IF($AC19=1,$AD19/(1+AQ$6)^1+$AE19/(1+AQ$6)^2+$AF19/(1+AQ$6)^3+$AG19/(1+AQ$6)^4+$AH19/(1+AQ$6)^5+$AI19/(1+AQ$6)^6+$U19/AQ$6/(1+AQ$6)^6,"") -> 1977.2696 | AR19: =IF($AC19=1,$AD19/(1+AR$6)^1+$AE19/(1+AR$6)^2+$AF19/(1+AR$6)^3+$AG19/(1+AR$6)^4+$AH19/(1+AR$6)^5+$AI19/(1+AR$6)^6+$U19/AR$6/(1+AR$6)^6,"") -> 1109.3807 | AS19: =IF($AC19=1,$AD19/(1+AS$6)^1+$AE19/(1+AS$6)^2+$AF19/(1+AS$6)^3+$AG19/(1+AS$6)^4+$AH19/(1+AS$6)^5+$AI19/(1+AS$6)^6+$U19/AS$6/(1+AS$6)^6,"") -> 833.01196 | AT19: =IF($AC19=1,$AD19/(1+AT$6)^1+$AE19/(1+AT$6)^2+$AF19/(1+AT$6)^3+$AG19/(1+AT$6)^4+$AH19/(1+AT$6)^5+$AI19/(1+AT$6)^6+$U19/AT$6/(1+AT$6)^6,"") -> 655.93999 | AU19: =IF($AC19=1,$AD19/(1+AU$6)^1+$AE19/(1+AU$6)^2+$AF19/(1+AU$6)^3+$AG19/(1+AU$6)^4+$AH19/(1+AU$6)^5+$AI19/(1+AU$6)^6+$U19/AU$6/(1+AU$6)^6,"") -> 487.87072 | AV19: =IF($AC19=1,$AD19/(1+AV$6)^1+$AE19/(1+AV$6)^2+$AF19/(1+AV$6)^3+$AG19/(1+AV$6)^4+$AH19/(1+AV$6)^5+$AI19/(1+AV$6)^6+$U19/AV$6/(1+AV$6)^6,"") -> 333.85577 | AW19: =IF($AC19=1,$AD19/(1+AW$6)^1+$AE19/(1+AW$6)^2+$AF19/(1+AW$6)^3+$AG19/(1+AW$6)^4+$AH19/(1+AW$6)^5+$AI19/(1+AW$6)^6+$U19/AW$6/(1+AW$6)^6,"") -> 202.77534 | ... BB19: =IF($AC19=1,$AD19/(1+BB$6)^1+$AE19/(1+BB$6)^2+$AF19/(1+BB$6)^3+$AG19/(1+BB$6)^4+$AH19/(1+BB$6)^5+$AI19/(1+BB$6)^6+$U19/BB$6/(1+BB$6)^6,"") -> 203.77218
... A71: 63 | B71: =D71&E71&F71&G71&H71&I71 -> 111111 | C71: =SUM(D71:I71) -> 6 | D71: =MOD(INT($A71/32),2) -> 1 | E71: =MOD(INT($A71/16),2) -> 1 | F71: =MOD(INT($A71/8),2) -> 1 | G71: =MOD(INT($A71/4),2) -> 1 | H71: =MOD(INT($A71/2),2) -> 1 | I71: =MOD(INT($A71/1),2) -> 1 | J71: =E_zero+D71*(Half_gap*(Ceiling_e-E_zero)-$F$4) -> 78 | K71: =J71+E71*(Half_gap*(Ceiling_e-J71)-$F$4) -> 81.5 | L71: =K71+F71*(Half_gap*(Ceiling_e-K71)-$F$4) -> 83.25 | M71: =L71+G71*(Half_gap*(Ceiling_e-L71)-$F$4) -> 84.125 | N71: =M71+H71*(Half_gap*(Ceiling_e-M71)-$F$4) -> 84.5625 | O71: =N71+I71*(Half_gap*(Ceiling_e-N71)-$F$4) -> 84.78125 | P71: =Val_pt*(J71-E_zero) -> 70 | Q71: =Val_pt*(K71-E_zero) -> 105 | R71: =Val_pt*(L71-E_zero) -> 122.5 | S71: =Val_pt*(M71-E_zero) -> 131.25 | T71: =Val_pt*(N71-E_zero) -> 135.625 | U71: =Val_pt*(O71-E_zero) -> 137.8125 | V71: =MAX(W71+Cost_round*D71-P71,IF(D71=1,Pre_q,0)) -> 535 | W71: =MAX(X71+Cost_round*E71-Q71,IF(E71=1,Pre_q,0),Floor_q) -> 485 | X71: =MAX(Y71+Cost_round*F71-R71,IF(F71=1,Pre_q,0),Floor_q) -> 470 | Y71: =MAX(Z71+Cost_round*G71-S71,IF(G71=1,Pre_q,0),Floor_q) -> 470 | Z71: =MAX(AA71+Cost_round*H71-T71,IF(H71=1,Pre_q,0),Floor_q) -> 470 | AA71: =MAX(AB71+Cost_round*I71-U71,IF(I71=1,Pre_q,0),Floor_q) -> 470 | AB71: =MAX(End_q,Floor_q) -> 470 | AC71: =IF(Q_zero>=V71-0.000000001,1,0) -> 1 | AD71: =IF($AC71=1,Q_zero-Cost_round*D71+P71-W71,"") -> 85 | AE71: =IF($AC71=1,W71-Cost_round*E71+Q71-X71,"") -> 0 | AF71: =IF($AC71=1,X71-Cost_round*F71+R71-Y71,"") -> 2.5 | AG71: =IF($AC71=1,Y71-Cost_round*G71+S71-Z71,"") -> 11.25 | AH71: =IF($AC71=1,Z71-Cost_round*H71+T71-AA71,"") -> 15.625 | AI71: =IF($AC71=1,AA71-Cost_round*I71+U71-AB71,"") -> 17.8125 | AJ71: =IF($AC71=1,SUM(AD71:AI71),"") -> 132.1875 | AK71: =IF($AC71=1,AD71*Beta_y^1+AE71*Beta_y^2+AF71*Beta_y^3+AG71*Beta_y^4+AH71*Beta_y^5+AI71*Beta_y^6,"") -> 106.5915 | AL71: =IF($AC71=1,AK71+Beta_y^6*U71/Hurdle_r,"") -> 884.50714 | AM71: =IF($AC71=1,AK71,"") -> 106.5915 | AN71: =IF($AC71=1,AK71+Beta_y^6*U71*(1-(1+Hurdle_r)^(-Life_yrs))/Hurdle_r,"") -> 768.87494 | AO71: =IF($AC71=1,AJ71+Credit_yrs*U71,"") -> 1510.3125 | AP71: =IF($AC71=1,$AD71/(1+AP$6)^1+$AE71/(1+AP$6)^2+$AF71/(1+AP$6)^3+$AG71/(1+AP$6)^4+$AH71/(1+AP$6)^5+$AI71/(1+AP$6)^6+$U71/AP$6/(1+AP$6)^6,"") -> 3970.3969 | AQ71: =IF($AC71=1,$AD71/(1+AQ$6)^1+$AE71/(1+AQ$6)^2+$AF71/(1+AQ$6)^3+$AG71/(1+AQ$6)^4+$AH71/(1+AQ$6)^5+$AI71/(1+AQ$6)^6+$U71/AQ$6/(1+AQ$6)^6,"") -> 2174.6581 | AR71: =IF($AC71=1,$AD71/(1+AR$6)^1+$AE71/(1+AR$6)^2+$AF71/(1+AR$6)^3+$AG71/(1+AR$6)^4+$AH71/(1+AR$6)^5+$AI71/(1+AR$6)^6+$U71/AR$6/(1+AR$6)^6,"") -> 1196.382 | AS71: =IF($AC71=1,$AD71/(1+AS$6)^1+$AE71/(1+AS$6)^2+$AF71/(1+AS$6)^3+$AG71/(1+AS$6)^4+$AH71/(1+AS$6)^5+$AI71/(1+AS$6)^6+$U71/AS$6/(1+AS$6)^6,"") -> 884.50714 | AT71: =IF($AC71=1,$AD71/(1+AT$6)^1+$AE71/(1+AT$6)^2+$AF71/(1+AT$6)^3+$AG71/(1+AT$6)^4+$AH71/(1+AT$6)^5+$AI71/(1+AT$6)^6+$U71/AT$6/(1+AT$6)^6,"") -> 684.54648 | AU71: =IF($AC71=1,$AD71/(1+AU$6)^1+$AE71/(1+AU$6)^2+$AF71/(1+AU$6)^3+$AG71/(1+AU$6)^4+$AH71/(1+AU$6)^5+$AI71/(1+AU$6)^6+$U71/AU$6/(1+AU$6)^6,"") -> 494.65926 | AV71: =IF($AC71=1,$AD71/(1+AV$6)^1+$AE71/(1+AV$6)^2+$AF71/(1+AV$6)^3+$AG71/(1+AV$6)^4+$AH71/(1+AV$6)^5+$AI71/(1+AV$6)^6+$U71/AV$6/(1+AV$6)^6,"") -> 320.71578 | AW71: =IF($AC71=1,$AD71/(1+AW$6)^1+$AE71/(1+AW$6)^2+$AF71/(1+AW$6)^3+$AG71/(1+AW$6)^4+$AH71/(1+AW$6)^5+$AI71/(1+AW$6)^6+$U71/AW$6/(1+AW$6)^6,"") -> 173.53163 | ... BB71: =IF($AC71=1,$AD71/(1+BB$6)^1+$AE71/(1+BB$6)^2+$AF71/(1+BB$6)^3+$AG71/(1+BB$6)^4+$AH71/(1+BB$6)^5+$AI71/(1+BB$6)^6+$U71/BB$6/(1+BB$6)^6,"") -> 174.64003

Sheet BestPlan
A1: Transcribe and solve: the best plan pays out above a war chest (Worked Example 5.1, Step 3)
A2: The best of the 64 schedules on Transcribe, by MAX; its year-end cash equals its war chest every year: everything above it is paid out at once.
A4: Best value: payouts plus the savings after year 6 forever | H4: =MAX(Transcribe!$AL$8:$AL$71) -> 1021.9325
A5: Its row among the 64 schedules | H5: =MATCH(H4,Transcribe!$AL$8:$AL$71,0) -> 57
A6: Rounds by year (1 = a round) | H6: =INDEX(Transcribe!$B$8:$B$71,H5) -> 111000
A7: Number of rounds | H7: =INDEX(Transcribe!$C$8:$C$71,H5) -> 3
A8: Schedules that keep every commitment | H8: =SUM(Transcribe!$AC$8:$AC$71) -> 64
A10: Year | B10: Round | C10: Efficiency | D10: Savings | E10: War chest | F10: Payout | G10: Year-end cash | H10: Discount factor | I10: PV of payout
A11: 0 | C11: =E_zero -> 71 | E11: =INDEX(Transcribe!$V$8:$V$71,$H$5) -> 535 | G11: =Q_zero -> 620
A12: 1 | B12: =INDEX(Transcribe!$D$8:$D$71,$H$5) -> 1 | C12: =INDEX(Transcribe!$J$8:$J$71,$H$5) -> 78 | D12: =INDEX(Transcribe!$P$8:$P$71,$H$5) -> 70 | E12: =INDEX(Transcribe!$W$8:$W$71,$H$5) -> 485 | F12: =INDEX(Transcribe!$AD$8:$AD$71,$H$5) -> 85 | G12: =G11-Cost_round*B12+D12-F12 -> 485 | H12: =Beta_y^A12 -> 0.90909091 | I12: =F12*H12 -> 77.272727
A13: 2 | B13: =INDEX(Transcribe!$E$8:$E$71,$H$5) -> 1 | C13: =INDEX(Transcribe!$K$8:$K$71,$H$5) -> 81.5 | D13: =INDEX(Transcribe!$Q$8:$Q$71,$H$5) -> 105 | E13: =INDEX(Transcribe!$X$8:$X$71,$H$5) -> 470 | F13: =INDEX(Transcribe!$AE$8:$AE$71,$H$5) -> 0 | G13: =G12-Cost_round*B13+D13-F13 -> 470 | H13: =Beta_y^A13 -> 0.82644628 | I13: =F13*H13 -> 0
A14: 3 | B14: =INDEX(Transcribe!$F$8:$F$71,$H$5) -> 1 | C14: =INDEX(Transcribe!$L$8:$L$71,$H$5) -> 83.25 | D14: =INDEX(Transcribe!$R$8:$R$71,$H$5) -> 122.5 | E14: =INDEX(Transcribe!$Y$8:$Y$71,$H$5) -> 350 | F14: =INDEX(Transcribe!$AF$8:$AF$71,$H$5) -> 122.5 | G14: =G13-Cost_round*B14+D14-F14 -> 350 | H14: =Beta_y^A14 -> 0.7513148 | I14: =F14*H14 -> 92.036063
A15: 4 | B15: =INDEX(Transcribe!$G$8:$G$71,$H$5) -> 0 | C15: =INDEX(Transcribe!$M$8:$M$71,$H$5) -> 83.25 | D15: =INDEX(Transcribe!$S$8:$S$71,$H$5) -> 122.5 | E15: =INDEX(Transcribe!$Z$8:$Z$71,$H$5) -> 350 | F15: =INDEX(Transcribe!$AG$8:$AG$71,$H$5) -> 122.5 | G15: =G14-Cost_round*B15+D15-F15 -> 350 | H15: =Beta_y^A15 -> 0.68301346 | I15: =F15*H15 -> 83.669148
A16: 5 | B16: =INDEX(Transcribe!$H$8:$H$71,$H$5) -> 0 | C16: =INDEX(Transcribe!$N$8:$N$71,$H$5) -> 83.25 | D16: =INDEX(Transcribe!$T$8:$T$71,$H$5) -> 122.5 | E16: =INDEX(Transcribe!$AA$8:$AA$71,$H$5) -> 350 | F16: =INDEX(Transcribe!$AH$8:$AH$71,$H$5) -> 122.5 | G16: =G15-Cost_round*B16+D16-F16 -> 350 | H16: =Beta_y^A16 -> 0.62092132 | I16: =F16*H16 -> 76.062862
A17: 6 | B17: =INDEX(Transcribe!$I$8:$I$71,$H$5) -> 0 | C17: =INDEX(Transcribe!$O$8:$O$71,$H$5) -> 83.25 | D17: =INDEX(Transcribe!$U$8:$U$71,$H$5) -> 122.5 | E17: =INDEX(Transcribe!$AB$8:$AB$71,$H$5) -> 470 | F17: =INDEX(Transcribe!$AI$8:$AI$71,$H$5) -> 2.5 | G17: =G16-Cost_round*B17+D17-F17 -> 470 | H17: =Beta_y^A17 -> 0.56447393 | I17: =F17*H17 -> 1.4111848
A19: Payouts, present value | H19: =SUM(I12:I17) -> 330.45199
A20: Savings after year 6, forever, valued at year 6 | H20: =D17/Hurdle_r -> 1225
A21: ... and today | H21: =H17*D17/Hurdle_r -> 691.48056
A22: Value | H22: =H19+H21 -> 1021.9325
A23: Total paid out | H23: =SUM(F12:F17) -> 455
A24: The same total paid at the end of year 6, with the savings forever | H24: =H17*H23+H21 -> 948.3162
A25: Front-loading the payouts is worth | H25: =H22-H24 -> 73.616347
A26: The CFO's rule (end condition waived) is worth less by | H26: =H22-Simulate!H20 -> 185.56891
A27: Year-end cash equals the war chest every year | H27: =IF(SUMPRODUCT(ABS(G12:G17-E12:E17))<0.000000001,"yes","no") -> yes

Sheet Prices
A1: Price: the multipliers of the dynamics, for cash and for efficiency (Theorem 5.1(iii); Figure 5.1; AXIOM Lab 2.5, step 3)
A2: Cash: a dollar arriving in year k is paid out at once, worth beta^k, unless the war chest at the end of year k-1 is set by the carry (R_k + 120 z_k - S_k): then it shrinks that war chest and is paid a year earlier, worth lambda_(k-1).
A3: A binding bound on q_k costs lambda_k - lambda_(k+1) a dollar (the end condition: lambda_6). Efficiency: mu_6 = 10 lambda_6 + 10 beta^6/r; mu_k = 10 lambda_k + (1 - z_(k+1)/2) mu_(k+1).
A5: Year k | B5: Round z_k | C5: Savings S_k | D5: War chest R_(k-1) | E5: Carry R_k + 120 z_k - S_k | F5: Round's cash | G5: Floor | H5: R_(k-1) set by | I5: Price of cash lambda_k | J5: beta^k | K5: Bound on q_k | L5: Bound | M5: Price of the bound | N5: Price of a point mu_k | O5: mu_k in year-k dollars
A6: 1 | B6: =BestPlan!B12 -> 1 | C6: =BestPlan!D12 -> 70 | D6: =BestPlan!E11 -> 535 | E6: =BestPlan!E12+Cost_round*B6-C6 -> 535 | F6: =IF(B6=1,Pre_q,0) -> 470 | G6: 0 | H6: =IF(E6>MAX(F6,G6)+0.000000001,"carry",IF(F6>=G6,"round's cash","floor")) -> carry | I6: =Beta_y^A6 -> 0.90909091 | J6: =Beta_y^A6 -> 0.90909091 | K6: =MAX(Floor_q,IF(B7=1,Pre_q,0)) -> 470 | L6: =IF(ABS(BestPlan!G12-K6)<0.000000001,"binding","slack") -> slack | M6: =IF(L6="binding",I6-I7,0) -> 0 | N6: =Val_pt*I6+(1-Half_gap*B7)*N7 -> 34.297521 | O6: =N6/J6 -> 37.727273
A7: 2 | B7: =BestPlan!B13 -> 1 | C7: =BestPlan!D13 -> 105 | D7: =BestPlan!E12 -> 485 | E7: =BestPlan!E13+Cost_round*B7-C7 -> 485 | F7: =IF(B7=1,Pre_q,0) -> 470 | G7: =Floor_q -> 350 | H7: =IF(E7>MAX(F7,G7)+0.000000001,"carry",IF(F7>=G7,"round's cash","floor")) -> carry | I7: =IF(H7="carry",I6,Beta_y^A7) -> 0.90909091 | J7: =Beta_y^A7 -> 0.82644628 | K7: =MAX(Floor_q,IF(B8=1,Pre_q,0)) -> 470 | L7: =IF(ABS(BestPlan!G13-K7)<0.000000001,"binding","slack") -> binding | M7: =IF(L7="binding",I7-I8,0) -> 0.15777611 | N7: =Val_pt*I7+(1-Half_gap*B8)*N8 -> 50.413223 | O7: =N7/J7 -> 61
A8: 3 | B8: =BestPlan!B14 -> 1 | C8: =BestPlan!D14 -> 122.5 | D8: =BestPlan!E13 -> 470 | E8: =BestPlan!E14+Cost_round*B8-C8 -> 347.5 | F8: =IF(B8=1,Pre_q,0) -> 470 | G8: =Floor_q -> 350 | H8: =IF(E8>MAX(F8,G8)+0.000000001,"carry",IF(F8>=G8,"round's cash","floor")) -> round's cash | I8: =IF(H8="carry",I7,Beta_y^A8) -> 0.7513148 | J8: =Beta_y^A8 -> 0.7513148 | K8: =MAX(Floor_q,IF(B9=1,Pre_q,0)) -> 350 | L8: =IF(ABS(BestPlan!G14-K8)<0.000000001,"binding","slack") -> binding | M8: =IF(L8="binding",I8-I9,0) -> 0.068301346 | N8: =Val_pt*I8+(1-Half_gap*B9)*N9 -> 82.644628 | O8: =N8/J8 -> 110
A9: 4 | B9: =BestPlan!B15 -> 0 | C9: =BestPlan!D15 -> 122.5 | D9: =BestPlan!E14 -> 350 | E9: =BestPlan!E15+Cost_round*B9-C9 -> 227.5 | F9: =IF(B9=1,Pre_q,0) -> 0 | G9: =Floor_q -> 350 | H9: =IF(E9>MAX(F9,G9)+0.000000001,"carry",IF(F9>=G9,"round's cash","floor")) -> floor | I9: =IF(H9="carry",I8,Beta_y^A9) -> 0.68301346 | J9: =Beta_y^A9 -> 0.68301346 | K9: =MAX(Floor_q,IF(B10=1,Pre_q,0)) -> 350 | L9: =IF(ABS(BestPlan!G15-K9)<0.000000001,"binding","slack") -> binding | M9: =IF(L9="binding",I9-I10,0) -> 0.062092132 | N9: =Val_pt*I9+(1-Half_gap*B10)*N10 -> 75.13148 | O9: =N9/J9 -> 110
A10: 5 | B10: =BestPlan!B16 -> 0 | C10: =BestPlan!D16 -> 122.5 | D10: =BestPlan!E15 -> 350 | E10: =BestPlan!E16+Cost_round*B10-C10 -> 227.5 | F10: =IF(B10=1,Pre_q,0) -> 0 | G10: =Floor_q -> 350 | H10: =IF(E10>MAX(F10,G10)+0.000000001,"carry",IF(F10>=G10,"round's cash","floor")) -> floor | I10: =IF(H10="carry",I9,Beta_y^A10) -> 0.62092132 | J10: =Beta_y^A10 -> 0.62092132 | K10: =MAX(Floor_q,IF(B11=1,Pre_q,0)) -> 350 | L10: =IF(ABS(BestPlan!G16-K10)<0.000000001,"binding","slack") -> binding | M10: =IF(L10="binding",I10-I11,0) -> 0.056447393 | N10: =Val_pt*I10+(1-Half_gap*B11)*N11 -> 68.301346 | O10: =N10/J10 -> 110
A11: 6 | B11: =BestPlan!B17 -> 0 | C11: =BestPlan!D17 -> 122.5 | D11: =BestPlan!E16 -> 350 | E11: =BestPlan!E17+Cost_round*B11-C11 -> 347.5 | F11: =IF(B11=1,Pre_q,0) -> 0 | G11: =Floor_q -> 350 | H11: =IF(E11>MAX(F11,G11)+0.000000001,"carry",IF(F11>=G11,"round's cash","floor")) -> floor | I11: =IF(H11="carry",I10,Beta_y^A11) -> 0.56447393 | J11: =Beta_y^A11 -> 0.56447393 | K11: =MAX(End_q,Floor_q) -> 470 | L11: =IF(ABS(BestPlan!G17-K11)<0.000000001,"binding","slack") -> binding | M11: =IF(L11="binding",I11,0) -> 0.56447393 | N11: =Val_pt*I11+Val_pt*Beta_y^6/Hurdle_r -> 62.092132 | O11: =N11/J11 -> 110
A13: Cost today of the end condition's cash above the floor | H13: =(End_q-Floor_q)*M11 -> 67.736872
A14: Price of the third round's precondition (bound on q_2) | H14: =M7 -> 0.15777611
A16: Check the prices by perturbing the instance (the rounds held fixed; payouts re-optimized): one more dollar of cash in a year, or 0.01 point more efficiency in a year
A17: Perturbation | B17: Year | C17: Kind | D17: Size | E17: e1 | F17: e2 | G17: e3 | H17: e4 | I17: e5 | J17: e6 | K17: cash in 1 | L17: cash in 2 | M17: cash in 3 | N17: cash in 4 | O17: cash in 5 | P17: cash in 6 | Q17: R0 | R17: R1 | S17: R2 | T17: R3 | U17: R4 | V17: R5 | W17: R6 | X17: Keeps every commitment | Y17: p1 | Z17: p2 | AA17: p3 | AB17: p4 | AC17: p5 | AD17: p6 | AE17: Value | AF17: Price by perturbation | AG17: Price from the program | AH17: |difference|
A18: Best plan | B18: 0 | C18: base | D18: 0 | E18: =IF(AND($C18="efficiency",1>=$B18),IF(1=$B18,BestPlan!$C$12+$D18,E_zero+BestPlan!$B$12*(Half_gap*(Ceiling_e-E_zero)-Transcribe!$F$4)),BestPlan!$C$12) -> 78 | F18: =IF(AND($C18="efficiency",2>=$B18),IF(2=$B18,BestPlan!$C$13+$D18,E18+BestPlan!$B$13*(Half_gap*(Ceiling_e-E18)-Transcribe!$F$4)),BestPlan!$C$13) -> 81.5 | G18: =IF(AND($C18="efficiency",3>=$B18),IF(3=$B18,BestPlan!$C$14+$D18,F18+BestPlan!$B$14*(Half_gap*(Ceiling_e-F18)-Transcribe!$F$4)),BestPlan!$C$14) -> 83.25 | H18: =IF(AND($C18="efficiency",4>=$B18),IF(4=$B18,BestPlan!$C$15+$D18,G18+BestPlan!$B$15*(Half_gap*(Ceiling_e-G18)-Transcribe!$F$4)),BestPlan!$C$15) -> 83.25 | I18: =IF(AND($C18="efficiency",5>=$B18),IF(5=$B18,BestPlan!$C$16+$D18,H18+BestPlan!$B$16*(Half_gap*(Ceiling_e-H18)-Transcribe!$F$4)),BestPlan!$C$16) -> 83.25 | J18: =IF(AND($C18="efficiency",6>=$B18),IF(6=$B18,BestPlan!$C$17+$D18,I18+BestPlan!$B$17*(Half_gap*(Ceiling_e-I18)-Transcribe!$F$4)),BestPlan!$C$17) -> 83.25 | K18: =Val_pt*(E18-E_zero)+IF(AND($C18="cash",$B18=1),$D18,0) -> 70 | L18: =Val_pt*(F18-E_zero)+IF(AND($C18="cash",$B18=2),$D18,0) -> 105 | M18: =Val_pt*(G18-E_zero)+IF(AND($C18="cash",$B18=3),$D18,0) -> 122.5 | N18: =Val_pt*(H18-E_zero)+IF(AND($C18="cash",$B18=4),$D18,0) -> 122.5 | O18: =Val_pt*(I18-E_zero)+IF(AND($C18="cash",$B18=5),$D18,0) -> 122.5 | P18: =Val_pt*(J18-E_zero)+IF(AND($C18="cash",$B18=6),$D18,0) -> 122.5 | Q18: =MAX(R18+Cost_round*BestPlan!$B$12-K18,IF(BestPlan!$B$12=1,Pre_q,0)) -> 535 | R18: =MAX(S18+Cost_round*BestPlan!$B$13-L18,IF(BestPlan!$B$13=1,Pre_q,0),Floor_q) -> 485 | S18: =MAX(T18+Cost_round*BestPlan!$B$14-M18,IF(BestPlan!$B$14=1,Pre_q,0),Floor_q) -> 470 | T18: =MAX(U18+Cost_round*BestPlan!$B$15-N18,IF(BestPlan!$B$15=1,Pre_q,0),Floor_q) -> 350 | U18: =MAX(V18+Cost_round*BestPlan!$B$16-O18,IF(BestPlan!$B$16=1,Pre_q,0),Floor_q) -> 350 | V18: =MAX(W18+Cost_round*BestPlan!$B$17-P18,IF(BestPlan!$B$17=1,Pre_q,0),Floor_q) -> 350 | W18: =MAX(End_q,Floor_q) -> 470 | X18: =IF(Q_zero>=Q18-0.000000001,1,0) -> 1 | Y18: =Q_zero-Cost_round*BestPlan!$B$12+K18-R18 -> 85 | Z18: =R18-Cost_round*BestPlan!$B$13+L18-S18 -> 0 | AA18: =S18-Cost_round*BestPlan!$B$14+M18-T18 -> 122.5 | AB18: =T18-Cost_round*BestPlan!$B$15+N18-U18 -> 122.5 | AC18: =U18-Cost_round*BestPlan!$B$16+O18-V18 -> 122.5 | AD18: =V18-Cost_round*BestPlan!$B$17+P18-W18 -> 2.5 | AE18: =Y18*Beta_y^1+Z18*Beta_y^2+AA18*Beta_y^3+AB18*Beta_y^4+AC18*Beta_y^5+AD18*Beta_y^6+Beta_y^6*Val_pt*(J18-E_zero)/Hurdle_r -> 1021.9325
A19: $1 more cash, year 1 | B19: 1 | C19: cash | D19: 1 | E19: =IF(AND($C19="efficiency",1>=$B19),IF(1=$B19,BestPlan!$C$12+$D19,E_zero+BestPlan!$B$12*(Half_gap*(Ceiling_e-E_zero)-Transcribe!$F$4)),BestPlan!$C$12) -> 78 | F19: =IF(AND($C19="efficiency",2>=$B19),IF(2=$B19,BestPlan!$C$13+$D19,E19+BestPlan!$B$13*(Half_gap*(Ceiling_e-E19)-Transcribe!$F$4)),BestPlan!$C$13) -> 81.5 | G19: =IF(AND($C19="efficiency",3>=$B19),IF(3=$B19,BestPlan!$C$14+$D19,F19+BestPlan!$B$14*(Half_gap*(Ceiling_e-F19)-Transcribe!$F$4)),BestPlan!$C$14) -> 83.25 | H19: =IF(AND($C19="efficiency",4>=$B19),IF(4=$B19,BestPlan!$C$15+$D19,G19+BestPlan!$B$15*(Half_gap*(Ceiling_e-G19)-Transcribe!$F$4)),BestPlan!$C$15) -> 83.25 | I19: =IF(AND($C19="efficiency",5>=$B19),IF(5=$B19,BestPlan!$C$16+$D19,H19+BestPlan!$B$16*(Half_gap*(Ceiling_e-H19)-Transcribe!$F$4)),BestPlan!$C$16) -> 83.25 | J19: =IF(AND($C19="efficiency",6>=$B19),IF(6=$B19,BestPlan!$C$17+$D19,I19+BestPlan!$B$17*(Half_gap*(Ceiling_e-I19)-Transcribe!$F$4)),BestPlan!$C$17) -> 83.25 | K19: =Val_pt*(E19-E_zero)+IF(AND($C19="cash",$B19=1),$D19,0) -> 71 | L19: =Val_pt*(F19-E_zero)+IF(AND($C19="cash",$B19=2),$D19,0) -> 105 | M19: =Val_pt*(G19-E_zero)+IF(AND($C19="cash",$B19=3),$D19,0) -> 122.5 | N19: =Val_pt*(H19-E_zero)+IF(AND($C19="cash",$B19=4),$D19,0) -> 122.5 | O19: =Val_pt*(I19-E_zero)+IF(AND($C19="cash",$B19=5),$D19,0) -> 122.5 | P19: =Val_pt*(J19-E_zero)+IF(AND($C19="cash",$B19=6),$D19,0) -> 122.5 | Q19: =MAX(R19+Cost_round*BestPlan!$B$12-K19,IF(BestPlan!$B$12=1,Pre_q,0)) -> 534 | R19: =MAX(S19+Cost_round*BestPlan!$B$13-L19,IF(BestPlan!$B$13=1,Pre_q,0),Floor_q) -> 485 | S19: =MAX(T19+Cost_round*BestPlan!$B$14-M19,IF(BestPlan!$B$14=1,Pre_q,0),Floor_q) -> 470 | T19: =MAX(U19+Cost_round*BestPlan!$B$15-N19,IF(BestPlan!$B$15=1,Pre_q,0),Floor_q) -> 350 | U19: =MAX(V19+Cost_round*BestPlan!$B$16-O19,IF(BestPlan!$B$16=1,Pre_q,0),Floor_q) -> 350 | V19: =MAX(W19+Cost_round*BestPlan!$B$17-P19,IF(BestPlan!$B$17=1,Pre_q,0),Floor_q) -> 350 | W19: =MAX(End_q,Floor_q) -> 470 | X19: =IF(Q_zero>=Q19-0.000000001,1,0) -> 1 | Y19: =Q_zero-Cost_round*BestPlan!$B$12+K19-R19 -> 86 | Z19: =R19-Cost_round*BestPlan!$B$13+L19-S19 -> 0 | AA19: =S19-Cost_round*BestPlan!$B$14+M19-T19 -> 122.5 | AB19: =T19-Cost_round*BestPlan!$B$15+N19-U19 -> 122.5 | AC19: =U19-Cost_round*BestPlan!$B$16+O19-V19 -> 122.5 | AD19: =V19-Cost_round*BestPlan!$B$17+P19-W19 -> 2.5 | AE19: =Y19*Beta_y^1+Z19*Beta_y^2+AA19*Beta_y^3+AB19*Beta_y^4+AC19*Beta_y^5+AD19*Beta_y^6+Beta_y^6*Val_pt*(J19-E_zero)/Hurdle_r -> 1022.8416 | AF19: =(AE19-$AE$18)/$D19 -> 0.90909091 | AG19: =I6 -> 0.90909091 | AH19: =ABS(AF19-AG19) -> 1.4466206e-13
A20: $1 more cash, year 2 | B20: 2 | C20: cash | D20: 1 | E20: =IF(AND($C20="efficiency",1>=$B20),IF(1=$B20,BestPlan!$C$12+$D20,E_zero+BestPlan!$B$12*(Half_gap*(Ceiling_e-E_zero)-Transcribe!$F$4)),BestPlan!$C$12) -> 78 | F20: =IF(AND($C20="efficiency",2>=$B20),IF(2=$B20,BestPlan!$C$13+$D20,E20+BestPlan!$B$13*(Half_gap*(Ceiling_e-E20)-Transcribe!$F$4)),BestPlan!$C$13) -> 81.5 | G20: =IF(AND($C20="efficiency",3>=$B20),IF(3=$B20,BestPlan!$C$14+$D20,F20+BestPlan!$B$14*(Half_gap*(Ceiling_e-F20)-Transcribe!$F$4)),BestPlan!$C$14) -> 83.25 | H20: =IF(AND($C20="efficiency",4>=$B20),IF(4=$B20,BestPlan!$C$15+$D20,G20+BestPlan!$B$15*(Half_gap*(Ceiling_e-G20)-Transcribe!$F$4)),BestPlan!$C$15) -> 83.25 | I20: =IF(AND($C20="efficiency",5>=$B20),IF(5=$B20,BestPlan!$C$16+$D20,H20+BestPlan!$B$16*(Half_gap*(Ceiling_e-H20)-Transcribe!$F$4)),BestPlan!$C$16) -> 83.25 | J20: =IF(AND($C20="efficiency",6>=$B20),IF(6=$B20,BestPlan!$C$17+$D20,I20+BestPlan!$B$17*(Half_gap*(Ceiling_e-I20)-Transcribe!$F$4)),BestPlan!$C$17) -> 83.25 | K20: =Val_pt*(E20-E_zero)+IF(AND($C20="cash",$B20=1),$D20,0) -> 70 | L20: =Val_pt*(F20-E_zero)+IF(AND($C20="cash",$B20=2),$D20,0) -> 106 | M20: =Val_pt*(G20-E_zero)+IF(AND($C20="cash",$B20=3),$D20,0) -> 122.5 | N20: =Val_pt*(H20-E_zero)+IF(AND($C20="cash",$B20=4),$D20,0) -> 122.5 | O20: =Val_pt*(I20-E_zero)+IF(AND($C20="cash",$B20=5),$D20,0) -> 122.5 | P20: =Val_pt*(J20-E_zero)+IF(AND($C20="cash",$B20=6),$D20,0) -> 122.5 | Q20: =MAX(R20+Cost_round*BestPlan!$B$12-K20,IF(BestPlan!$B$12=1,Pre_q,0)) -> 534 | R20: =MAX(S20+Cost_round*BestPlan!$B$13-L20,IF(BestPlan!$B$13=1,Pre_q,0),Floor_q) -> 484 | S20: =MAX(T20+Cost_round*BestPlan!$B$14-M20,IF(BestPlan!$B$14=1,Pre_q,0),Floor_q) -> 470 | T20: =MAX(U20+Cost_round*BestPlan!$B$15-N20,IF(BestPlan!$B$15=1,Pre_q,0),Floor_q) -> 350 | U20: =MAX(V20+Cost_round*BestPlan!$B$16-O20,IF(BestPlan!$B$16=1,Pre_q,0),Floor_q) -> 350 | V20: =MAX(W20+Cost_round*BestPlan!$B$17-P20,IF(BestPlan!$B$17=1,Pre_q,0),Floor_q) -> 350 | W20: =MAX(End_q,Floor_q) -> 470 | X20: =IF(Q_zero>=Q20-0.000000001,1,0) -> 1 | Y20: =Q_zero-Cost_round*BestPlan!$B$12+K20-R20 -> 86 | Z20: =R20-Cost_round*BestPlan!$B$13+L20-S20 -> 0 | AA20: =S20-Cost_round*BestPlan!$B$14+M20-T20 -> 122.5 | AB20: =T20-Cost_round*BestPlan!$B$15+N20-U20 -> 122.5 | AC20: =U20-Cost_round*BestPlan!$B$16+O20-V20 -> 122.5 | AD20: =V20-Cost_round*BestPlan!$B$17+P20-W20 -> 2.5 | AE20: =Y20*Beta_y^1+Z20*Beta_y^2+AA20*Beta_y^3+AB20*Beta_y^4+AC20*Beta_y^5+AD20*Beta_y^6+Beta_y^6*Val_pt*(J20-E_zero)/Hurdle_r -> 1022.8416 | AF20: =(AE20-$AE$18)/$D20 -> 0.90909091 | AG20: =I7 -> 0.90909091 | AH20: =ABS(AF20-AG20) -> 1.4466206e-13
A21: $1 more cash, year 3 | B21: 3 | C21: cash | D21: 1 | E21: =IF(AND($C21="efficiency",1>=$B21),IF(1=$B21,BestPlan!$C$12+$D21,E_zero+BestPlan!$B$12*(Half_gap*(Ceiling_e-E_zero)-Transcribe!$F$4)),BestPlan!$C$12) -> 78 | F21: =IF(AND($C21="efficiency",2>=$B21),IF(2=$B21,BestPlan!$C$13+$D21,E21+BestPlan!$B$13*(Half_gap*(Ceiling_e-E21)-Transcribe!$F$4)),BestPlan!$C$13) -> 81.5 | G21: =IF(AND($C21="efficiency",3>=$B21),IF(3=$B21,BestPlan!$C$14+$D21,F21+BestPlan!$B$14*(Half_gap*(Ceiling_e-F21)-Transcribe!$F$4)),BestPlan!$C$14) -> 83.25 | H21: =IF(AND($C21="efficiency",4>=$B21),IF(4=$B21,BestPlan!$C$15+$D21,G21+BestPlan!$B$15*(Half_gap*(Ceiling_e-G21)-Transcribe!$F$4)),BestPlan!$C$15) -> 83.25 | I21: =IF(AND($C21="efficiency",5>=$B21),IF(5=$B21,BestPlan!$C$16+$D21,H21+BestPlan!$B$16*(Half_gap*(Ceiling_e-H21)-Transcribe!$F$4)),BestPlan!$C$16) -> 83.25 | J21: =IF(AND($C21="efficiency",6>=$B21),IF(6=$B21,BestPlan!$C$17+$D21,I21+BestPlan!$B$17*(Half_gap*(Ceiling_e-I21)-Transcribe!$F$4)),BestPlan!$C$17) -> 83.25 | K21: =Val_pt*(E21-E_zero)+IF(AND($C21="cash",$B21=1),$D21,0) -> 70 | L21: =Val_pt*(F21-E_zero)+IF(AND($C21="cash",$B21=2),$D21,0) -> 105 | M21: =Val_pt*(G21-E_zero)+IF(AND($C21="cash",$B21=3),$D21,0) -> 123.5 | N21: =Val_pt*(H21-E_zero)+IF(AND($C21="cash",$B21=4),$D21,0) -> 122.5 | O21: =Val_pt*(I21-E_zero)+IF(AND($C21="cash",$B21=5),$D21,0) -> 122.5 | P21: =Val_pt*(J21-E_zero)+IF(AND($C21="cash",$B21=6),$D21,0) -> 122.5 | Q21: =MAX(R21+Cost_round*BestPlan!$B$12-K21,IF(BestPlan!$B$12=1,Pre_q,0)) -> 535 | R21: =MAX(S21+Cost_round*BestPlan!$B$13-L21,IF(BestPlan!$B$13=1,Pre_q,0),Floor_q) -> 485 | S21: =MAX(T21+Cost_round*BestPlan!$B$14-M21,IF(BestPlan!$B$14=1,Pre_q,0),Floor_q) -> 470 | T21: =MAX(U21+Cost_round*BestPlan!$B$15-N21,IF(BestPlan!$B$15=1,Pre_q,0),Floor_q) -> 350 | U21: =MAX(V21+Cost_round*BestPlan!$B$16-O21,IF(BestPlan!$B$16=1,Pre_q,0),Floor_q) -> 350 | V21: =MAX(W21+Cost_round*BestPlan!$B$17-P21,IF(BestPlan!$B$17=1,Pre_q,0),Floor_q) -> 350 | W21: =MAX(End_q,Floor_q) -> 470 | X21: =IF(Q_zero>=Q21-0.000000001,1,0) -> 1 | Y21: =Q_zero-Cost_round*BestPlan!$B$12+K21-R21 -> 85 | Z21: =R21-Cost_round*BestPlan!$B$13+L21-S21 -> 0 | AA21: =S21-Cost_round*BestPlan!$B$14+M21-T21 -> 123.5 | AB21: =T21-Cost_round*BestPlan!$B$15+N21-U21 -> 122.5 | AC21: =U21-Cost_round*BestPlan!$B$16+O21-V21 -> 122.5 | AD21: =V21-Cost_round*BestPlan!$B$17+P21-W21 -> 2.5 | AE21: =Y21*Beta_y^1+Z21*Beta_y^2+AA21*Beta_y^3+AB21*Beta_y^4+AC21*Beta_y^5+AD21*Beta_y^6+Beta_y^6*Val_pt*(J21-E_zero)/Hurdle_r -> 1022.6839 | AF21: =(AE21-$AE$18)/$D21 -> 0.7513148 | AG21: =I8 -> 0.7513148 | AH21: =ABS(AF21-AG21) -> 1.0913492e-13
A22: $1 more cash, year 4 | B22: 4 | C22: cash | D22: 1 | E22: =IF(AND($C22="efficiency",1>=$B22),IF(1=$B22,BestPlan!$C$12+$D22,E_zero+BestPlan!$B$12*(Half_gap*(Ceiling_e-E_zero)-Transcribe!$F$4)),BestPlan!$C$12) -> 78 | F22: =IF(AND($C22="efficiency",2>=$B22),IF(2=$B22,BestPlan!$C$13+$D22,E22+BestPlan!$B$13*(Half_gap*(Ceiling_e-E22)-Transcribe!$F$4)),BestPlan!$C$13) -> 81.5 | G22: =IF(AND($C22="efficiency",3>=$B22),IF(3=$B22,BestPlan!$C$14+$D22,F22+BestPlan!$B$14*(Half_gap*(Ceiling_e-F22)-Transcribe!$F$4)),BestPlan!$C$14) -> 83.25 | H22: =IF(AND($C22="efficiency",4>=$B22),IF(4=$B22,BestPlan!$C$15+$D22,G22+BestPlan!$B$15*(Half_gap*(Ceiling_e-G22)-Transcribe!$F$4)),BestPlan!$C$15) -> 83.25 | I22: =IF(AND($C22="efficiency",5>=$B22),IF(5=$B22,BestPlan!$C$16+$D22,H22+BestPlan!$B$16*(Half_gap*(Ceiling_e-H22)-Transcribe!$F$4)),BestPlan!$C$16) -> 83.25 | J22: =IF(AND($C22="efficiency",6>=$B22),IF(6=$B22,BestPlan!$C$17+$D22,I22+BestPlan!$B$17*(Half_gap*(Ceiling_e-I22)-Transcribe!$F$4)),BestPlan!$C$17) -> 83.25 | K22: =Val_pt*(E22-E_zero)+IF(AND($C22="cash",$B22=1),$D22,0) -> 70 | L22: =Val_pt*(F22-E_zero)+IF(AND($C22="cash",$B22=2),$D22,0) -> 105 | M22: =Val_pt*(G22-E_zero)+IF(AND($C22="cash",$B22=3),$D22,0) -> 122.5 | N22: =Val_pt*(H22-E_zero)+IF(AND($C22="cash",$B22=4),$D22,0) -> 123.5 | O22: =Val_pt*(I22-E_zero)+IF(AND($C22="cash",$B22=5),$D22,0) -> 122.5 | P22: =Val_pt*(J22-E_zero)+IF(AND($C22="cash",$B22=6),$D22,0) -> 122.5 | Q22: =MAX(R22+Cost_round*BestPlan!$B$12-K22,IF(BestPlan!$B$12=1,Pre_q,0)) -> 535 | R22: =MAX(S22+Cost_round*BestPlan!$B$13-L22,IF(BestPlan!$B$13=1,Pre_q,0),Floor_q) -> 485 | S22: =MAX(T22+Cost_round*BestPlan!$B$14-M22,IF(BestPlan!$B$14=1,Pre_q,0),Floor_q) -> 470 | T22: =MAX(U22+Cost_round*BestPlan!$B$15-N22,IF(BestPlan!$B$15=1,Pre_q,0),Floor_q) -> 350 | U22: =MAX(V22+Cost_round*BestPlan!$B$16-O22,IF(BestPlan!$B$16=1,Pre_q,0),Floor_q) -> 350 | V22: =MAX(W22+Cost_round*BestPlan!$B$17-P22,IF(BestPlan!$B$17=1,Pre_q,0),Floor_q) -> 350 | W22: =MAX(End_q,Floor_q) -> 470 | X22: =IF(Q_zero>=Q22-0.000000001,1,0) -> 1 | Y22: =Q_zero-Cost_round*BestPlan!$B$12+K22-R22 -> 85 | Z22: =R22-Cost_round*BestPlan!$B$13+L22-S22 -> 0 | AA22: =S22-Cost_round*BestPlan!$B$14+M22-T22 -> 122.5 | AB22: =T22-Cost_round*BestPlan!$B$15+N22-U22 -> 123.5 | AC22: =U22-Cost_round*BestPlan!$B$16+O22-V22 -> 122.5 | AD22: =V22-Cost_round*BestPlan!$B$17+P22-W22 -> 2.5 | AE22: =Y22*Beta_y^1+Z22*Beta_y^2+AA22*Beta_y^3+AB22*Beta_y^4+AC22*Beta_y^5+AD22*Beta_y^6+Beta_y^6*Val_pt*(J22-E_zero)/Hurdle_r -> 1022.6156 | AF22: =(AE22-$AE$18)/$D22 -> 0.68301346 | AG22: =I9 -> 0.68301346 | AH22: =ABS(AF22-AG22) -> 9.9253938e-14
A23: $1 more cash, year 5 | B23: 5 | C23: cash | D23: 1 | E23: =IF(AND($C23="efficiency",1>=$B23),IF(1=$B23,BestPlan!$C$12+$D23,E_zero+BestPlan!$B$12*(Half_gap*(Ceiling_e-E_zero)-Transcribe!$F$4)),BestPlan!$C$12) -> 78 | F23: =IF(AND($C23="efficiency",2>=$B23),IF(2=$B23,BestPlan!$C$13+$D23,E23+BestPlan!$B$13*(Half_gap*(Ceiling_e-E23)-Transcribe!$F$4)),BestPlan!$C$13) -> 81.5 | G23: =IF(AND($C23="efficiency",3>=$B23),IF(3=$B23,BestPlan!$C$14+$D23,F23+BestPlan!$B$14*(Half_gap*(Ceiling_e-F23)-Transcribe!$F$4)),BestPlan!$C$14) -> 83.25 | H23: =IF(AND($C23="efficiency",4>=$B23),IF(4=$B23,BestPlan!$C$15+$D23,G23+BestPlan!$B$15*(Half_gap*(Ceiling_e-G23)-Transcribe!$F$4)),BestPlan!$C$15) -> 83.25 | I23: =IF(AND($C23="efficiency",5>=$B23),IF(5=$B23,BestPlan!$C$16+$D23,H23+BestPlan!$B$16*(Half_gap*(Ceiling_e-H23)-Transcribe!$F$4)),BestPlan!$C$16) -> 83.25 | J23: =IF(AND($C23="efficiency",6>=$B23),IF(6=$B23,BestPlan!$C$17+$D23,I23+BestPlan!$B$17*(Half_gap*(Ceiling_e-I23)-Transcribe!$F$4)),BestPlan!$C$17) -> 83.25 | K23: =Val_pt*(E23-E_zero)+IF(AND($C23="cash",$B23=1),$D23,0) -> 70 | L23: =Val_pt*(F23-E_zero)+IF(AND($C23="cash",$B23=2),$D23,0) -> 105 | M23: =Val_pt*(G23-E_zero)+IF(AND($C23="cash",$B23=3),$D23,0) -> 122.5 | N23: =Val_pt*(H23-E_zero)+IF(AND($C23="cash",$B23=4),$D23,0) -> 122.5 | O23: =Val_pt*(I23-E_zero)+IF(AND($C23="cash",$B23=5),$D23,0) -> 123.5 | P23: =Val_pt*(J23-E_zero)+IF(AND($C23="cash",$B23=6),$D23,0) -> 122.5 | Q23: =MAX(R23+Cost_round*BestPlan!$B$12-K23,IF(BestPlan!$B$12=1,Pre_q,0)) -> 535 | R23: =MAX(S23+Cost_round*BestPlan!$B$13-L23,IF(BestPlan!$B$13=1,Pre_q,0),Floor_q) -> 485 | S23: =MAX(T23+Cost_round*BestPlan!$B$14-M23,IF(BestPlan!$B$14=1,Pre_q,0),Floor_q) -> 470 | T23: =MAX(U23+Cost_round*BestPlan!$B$15-N23,IF(BestPlan!$B$15=1,Pre_q,0),Floor_q) -> 350 | U23: =MAX(V23+Cost_round*BestPlan!$B$16-O23,IF(BestPlan!$B$16=1,Pre_q,0),Floor_q) -> 350 | V23: =MAX(W23+Cost_round*BestPlan!$B$17-P23,IF(BestPlan!$B$17=1,Pre_q,0),Floor_q) -> 350 | W23: =MAX(End_q,Floor_q) -> 470 | X23: =IF(Q_zero>=Q23-0.000000001,1,0) -> 1 | Y23: =Q_zero-Cost_round*BestPlan!$B$12+K23-R23 -> 85 | Z23: =R23-Cost_round*BestPlan!$B$13+L23-S23 -> 0 | AA23: =S23-Cost_round*BestPlan!$B$14+M23-T23 -> 122.5 | AB23: =T23-Cost_round*BestPlan!$B$15+N23-U23 -> 122.5 | AC23: =U23-Cost_round*BestPlan!$B$16+O23-V23 -> 123.5 | AD23: =V23-Cost_round*BestPlan!$B$17+P23-W23 -> 2.5 | AE23: =Y23*Beta_y^1+Z23*Beta_y^2+AA23*Beta_y^3+AB23*Beta_y^4+AC23*Beta_y^5+AD23*Beta_y^6+Beta_y^6*Val_pt*(J23-E_zero)/Hurdle_r -> 1022.5535 | AF23: =(AE23-$AE$18)/$D23 -> 0.62092132 | AG23: =I10 -> 0.62092132 | AH23: =ABS(AF23-AG23) -> 9.015011e-14
A24: $1 more cash, year 6 | B24: 6 | C24: cash | D24: 1 | E24: =IF(AND($C24="efficiency",1>=$B24),IF(1=$B24,BestPlan!$C$12+$D24,E_zero+BestPlan!$B$12*(Half_gap*(Ceiling_e-E_zero)-Transcribe!$F$4)),BestPlan!$C$12) -> 78 | F24: =IF(AND($C24="efficiency",2>=$B24),IF(2=$B24,BestPlan!$C$13+$D24,E24+BestPlan!$B$13*(Half_gap*(Ceiling_e-E24)-Transcribe!$F$4)),BestPlan!$C$13) -> 81.5 | G24: =IF(AND($C24="efficiency",3>=$B24),IF(3=$B24,BestPlan!$C$14+$D24,F24+BestPlan!$B$14*(Half_gap*(Ceiling_e-F24)-Transcribe!$F$4)),BestPlan!$C$14) -> 83.25 | H24: =IF(AND($C24="efficiency",4>=$B24),IF(4=$B24,BestPlan!$C$15+$D24,G24+BestPlan!$B$15*(Half_gap*(Ceiling_e-G24)-Transcribe!$F$4)),BestPlan!$C$15) -> 83.25 | I24: =IF(AND($C24="efficiency",5>=$B24),IF(5=$B24,BestPlan!$C$16+$D24,H24+BestPlan!$B$16*(Half_gap*(Ceiling_e-H24)-Transcribe!$F$4)),BestPlan!$C$16) -> 83.25 | J24: =IF(AND($C24="efficiency",6>=$B24),IF(6=$B24,BestPlan!$C$17+$D24,I24+BestPlan!$B$17*(Half_gap*(Ceiling_e-I24)-Transcribe!$F$4)),BestPlan!$C$17) -> 83.25 | K24: =Val_pt*(E24-E_zero)+IF(AND($C24="cash",$B24=1),$D24,0) -> 70 | L24: =Val_pt*(F24-E_zero)+IF(AND($C24="cash",$B24=2),$D24,0) -> 105 | M24: =Val_pt*(G24-E_zero)+IF(AND($C24="cash",$B24=3),$D24,0) -> 122.5 | N24: =Val_pt*(H24-E_zero)+IF(AND($C24="cash",$B24=4),$D24,0) -> 122.5 | O24: =Val_pt*(I24-E_zero)+IF(AND($C24="cash",$B24=5),$D24,0) -> 122.5 | P24: =Val_pt*(J24-E_zero)+IF(AND($C24="cash",$B24=6),$D24,0) -> 123.5 | Q24: =MAX(R24+Cost_round*BestPlan!$B$12-K24,IF(BestPlan!$B$12=1,Pre_q,0)) -> 535 | R24: =MAX(S24+Cost_round*BestPlan!$B$13-L24,IF(BestPlan!$B$13=1,Pre_q,0),Floor_q) -> 485 | S24: =MAX(T24+Cost_round*BestPlan!$B$14-M24,IF(BestPlan!$B$14=1,Pre_q,0),Floor_q) -> 470 | T24: =MAX(U24+Cost_round*BestPlan!$B$15-N24,IF(BestPlan!$B$15=1,Pre_q,0),Floor_q) -> 350 | U24: =MAX(V24+Cost_round*BestPlan!$B$16-O24,IF(BestPlan!$B$16=1,Pre_q,0),Floor_q) -> 350 | V24: =MAX(W24+Cost_round*BestPlan!$B$17-P24,IF(BestPlan!$B$17=1,Pre_q,0),Floor_q) -> 350 | W24: =MAX(End_q,Floor_q) -> 470 | X24: =IF(Q_zero>=Q24-0.000000001,1,0) -> 1 | Y24: =Q_zero-Cost_round*BestPlan!$B$12+K24-R24 -> 85 | Z24: =R24-Cost_round*BestPlan!$B$13+L24-S24 -> 0 | AA24: =S24-Cost_round*BestPlan!$B$14+M24-T24 -> 122.5 | AB24: =T24-Cost_round*BestPlan!$B$15+N24-U24 -> 122.5 | AC24: =U24-Cost_round*BestPlan!$B$16+O24-V24 -> 122.5 | AD24: =V24-Cost_round*BestPlan!$B$17+P24-W24 -> 3.5 | AE24: =Y24*Beta_y^1+Z24*Beta_y^2+AA24*Beta_y^3+AB24*Beta_y^4+AC24*Beta_y^5+AD24*Beta_y^6+Beta_y^6*Val_pt*(J24-E_zero)/Hurdle_r -> 1022.497 | AF24: =(AE24-$AE$18)/$D24 -> 0.56447393 | AG24: =I11 -> 0.56447393 | AH24: =ABS(AF24-AG24) -> 4.0634163e-14
A25: 0.01 point more efficiency, year 1 | B25: 1 | C25: efficiency | D25: 0.01 | E25: =IF(AND($C25="efficiency",1>=$B25),IF(1=$B25,BestPlan!$C$12+$D25,E_zero+BestPlan!$B$12*(Half_gap*(Ceiling_e-E_zero)-Transcribe!$F$4)),BestPlan!$C$12) -> 78.01 | F25: =IF(AND($C25="efficiency",2>=$B25),IF(2=$B25,BestPlan!$C$13+$D25,E25+BestPlan!$B$13*(Half_gap*(Ceiling_e-E25)-Transcribe!$F$4)),BestPlan!$C$13) -> 81.505 | G25: =IF(AND($C25="efficiency",3>=$B25),IF(3=$B25,BestPlan!$C$14+$D25,F25+BestPlan!$B$14*(Half_gap*(Ceiling_e-F25)-Transcribe!$F$4)),BestPlan!$C$14) -> 83.2525 | H25: =IF(AND($C25="efficiency",4>=$B25),IF(4=$B25,BestPlan!$C$15+$D25,G25+BestPlan!$B$15*(Half_gap*(Ceiling_e-G25)-Transcribe!$F$4)),BestPlan!$C$15) -> 83.2525 | I25: =IF(AND($C25="efficiency",5>=$B25),IF(5=$B25,BestPlan!$C$16+$D25,H25+BestPlan!$B$16*(Half_gap*(Ceiling_e-H25)-Transcribe!$F$4)),BestPlan!$C$16) -> 83.2525 | J25: =IF(AND($C25="efficiency",6>=$B25),IF(6=$B25,BestPlan!$C$17+$D25,I25+BestPlan!$B$17*(Half_gap*(Ceiling_e-I25)-Transcribe!$F$4)),BestPlan!$C$17) -> 83.2525 | K25: =Val_pt*(E25-E_zero)+IF(AND($C25="cash",$B25=1),$D25,0) -> 70.1 | L25: =Val_pt*(F25-E_zero)+IF(AND($C25="cash",$B25=2),$D25,0) -> 105.05 | M25: =Val_pt*(G25-E_zero)+IF(AND($C25="cash",$B25=3),$D25,0) -> 122.525 | N25: =Val_pt*(H25-E_zero)+IF(AND($C25="cash",$B25=4),$D25,0) -> 122.525 | O25: =Val_pt*(I25-E_zero)+IF(AND($C25="cash",$B25=5),$D25,0) -> 122.525 | P25: =Val_pt*(J25-E_zero)+IF(AND($C25="cash",$B25=6),$D25,0) -> 122.525 | Q25: =MAX(R25+Cost_round*BestPlan!$B$12-K25,IF(BestPlan!$B$12=1,Pre_q,0)) -> 534.85 | R25: =MAX(S25+Cost_round*BestPlan!$B$13-L25,IF(BestPlan!$B$13=1,Pre_q,0),Floor_q) -> 484.95 | S25: =MAX(T25+Cost_round*BestPlan!$B$14-M25,IF(BestPlan!$B$14=1,Pre_q,0),Floor_q) -> 470 | T25: =MAX(U25+Cost_round*BestPlan!$B$15-N25,IF(BestPlan!$B$15=1,Pre_q,0),Floor_q) -> 350 | U25: =MAX(V25+Cost_round*BestPlan!$B$16-O25,IF(BestPlan!$B$16=1,Pre_q,0),Floor_q) -> 350 | V25: =MAX(W25+Cost_round*BestPlan!$B$17-P25,IF(BestPlan!$B$17=1,Pre_q,0),Floor_q) -> 350 | W25: =MAX(End_q,Floor_q) -> 470 | X25: =IF(Q_zero>=Q25-0.000000001,1,0) -> 1 | Y25: =Q_zero-Cost_round*BestPlan!$B$12+K25-R25 -> 85.15 | Z25: =R25-Cost_round*BestPlan!$B$13+L25-S25 -> 0 | AA25: =S25-Cost_round*BestPlan!$B$14+M25-T25 -> 122.525 | AB25: =T25-Cost_round*BestPlan!$B$15+N25-U25 -> 122.525 | AC25: =U25-Cost_round*BestPlan!$B$16+O25-V25 -> 122.525 | AD25: =V25-Cost_round*BestPlan!$B$17+P25-W25 -> 2.525 | AE25: =Y25*Beta_y^1+Z25*Beta_y^2+AA25*Beta_y^3+AB25*Beta_y^4+AC25*Beta_y^5+AD25*Beta_y^6+Beta_y^6*Val_pt*(J25-E_zero)/Hurdle_r -> 1022.2755 | AF25: =(AE25-$AE$18)/$D25 -> 34.297521 | AG25: =N6 -> 34.297521 | AH25: =ABS(AF25-AG25) -> 2.7057467e-11
A26: 0.01 point more efficiency, year 2 | B26: 2 | C26: efficiency | D26: 0.01 | E26: =IF(AND($C26="efficiency",1>=$B26),IF(1=$B26,BestPlan!$C$12+$D26,E_zero+BestPlan!$B$12*(Half_gap*(Ceiling_e-E_zero)-Transcribe!$F$4)),BestPlan!$C$12) -> 78 | F26: =IF(AND($C26="efficiency",2>=$B26),IF(2=$B26,BestPlan!$C$13+$D26,E26+BestPlan!$B$13*(Half_gap*(Ceiling_e-E26)-Transcribe!$F$4)),BestPlan!$C$13) -> 81.51 | G26: =IF(AND($C26="efficiency",3>=$B26),IF(3=$B26,BestPlan!$C$14+$D26,F26+BestPlan!$B$14*(Half_gap*(Ceiling_e-F26)-Transcribe!$F$4)),BestPlan!$C$14) -> 83.255 | H26: =IF(AND($C26="efficiency",4>=$B26),IF(4=$B26,BestPlan!$C$15+$D26,G26+BestPlan!$B$15*(Half_gap*(Ceiling_e-G26)-Transcribe!$F$4)),BestPlan!$C$15) -> 83.255 | I26: =IF(AND($C26="efficiency",5>=$B26),IF(5=$B26,BestPlan!$C$16+$D26,H26+BestPlan!$B$16*(Half_gap*(Ceiling_e-H26)-Transcribe!$F$4)),BestPlan!$C$16) -> 83.255 | J26: =IF(AND($C26="efficiency",6>=$B26),IF(6=$B26,BestPlan!$C$17+$D26,I26+BestPlan!$B$17*(Half_gap*(Ceiling_e-I26)-Transcribe!$F$4)),BestPlan!$C$17) -> 83.255 | K26: =Val_pt*(E26-E_zero)+IF(AND($C26="cash",$B26=1),$D26,0) -> 70 | L26: =Val_pt*(F26-E_zero)+IF(AND($C26="cash",$B26=2),$D26,0) -> 105.1 | M26: =Val_pt*(G26-E_zero)+IF(AND($C26="cash",$B26=3),$D26,0) -> 122.55 | N26: =Val_pt*(H26-E_zero)+IF(AND($C26="cash",$B26=4),$D26,0) -> 122.55 | O26: =Val_pt*(I26-E_zero)+IF(AND($C26="cash",$B26=5),$D26,0) -> 122.55 | P26: =Val_pt*(J26-E_zero)+IF(AND($C26="cash",$B26=6),$D26,0) -> 122.55 | Q26: =MAX(R26+Cost_round*BestPlan!$B$12-K26,IF(BestPlan!$B$12=1,Pre_q,0)) -> 534.9 | R26: =MAX(S26+Cost_round*BestPlan!$B$13-L26,IF(BestPlan!$B$13=1,Pre_q,0),Floor_q) -> 484.9 | S26: =MAX(T26+Cost_round*BestPlan!$B$14-M26,IF(BestPlan!$B$14=1,Pre_q,0),Floor_q) -> 470 | T26: =MAX(U26+Cost_round*BestPlan!$B$15-N26,IF(BestPlan!$B$15=1,Pre_q,0),Floor_q) -> 350 | U26: =MAX(V26+Cost_round*BestPlan!$B$16-O26,IF(BestPlan!$B$16=1,Pre_q,0),Floor_q) -> 350 | V26: =MAX(W26+Cost_round*BestPlan!$B$17-P26,IF(BestPlan!$B$17=1,Pre_q,0),Floor_q) -> 350 | W26: =MAX(End_q,Floor_q) -> 470 | X26: =IF(Q_zero>=Q26-0.000000001,1,0) -> 1 | Y26: =Q_zero-Cost_round*BestPlan!$B$12+K26-R26 -> 85.1 | Z26: =R26-Cost_round*BestPlan!$B$13+L26-S26 -> 0 | AA26: =S26-Cost_round*BestPlan!$B$14+M26-T26 -> 122.55 | AB26: =T26-Cost_round*BestPlan!$B$15+N26-U26 -> 122.55 | AC26: =U26-Cost_round*BestPlan!$B$16+O26-V26 -> 122.55 | AD26: =V26-Cost_round*BestPlan!$B$17+P26-W26 -> 2.55 | AE26: =Y26*Beta_y^1+Z26*Beta_y^2+AA26*Beta_y^3+AB26*Beta_y^4+AC26*Beta_y^5+AD26*Beta_y^6+Beta_y^6*Val_pt*(J26-E_zero)/Hurdle_r -> 1022.4367 | AF26: =(AE26-$AE$18)/$D26 -> 50.413223 | AG26: =N7 -> 50.413223 | AH26: =ABS(AF26-AG26) -> 3.75735e-11
A27: 0.01 point more efficiency, year 3 | B27: 3 | C27: efficiency | D27: 0.01 | E27: =IF(AND($C27="efficiency",1>=$B27),IF(1=$B27,BestPlan!$C$12+$D27,E_zero+BestPlan!$B$12*(Half_gap*(Ceiling_e-E_zero)-Transcribe!$F$4)),BestPlan!$C$12) -> 78 | F27: =IF(AND($C27="efficiency",2>=$B27),IF(2=$B27,BestPlan!$C$13+$D27,E27+BestPlan!$B$13*(Half_gap*(Ceiling_e-E27)-Transcribe!$F$4)),BestPlan!$C$13) -> 81.5 | G27: =IF(AND($C27="efficiency",3>=$B27),IF(3=$B27,BestPlan!$C$14+$D27,F27+BestPlan!$B$14*(Half_gap*(Ceiling_e-F27)-Transcribe!$F$4)),BestPlan!$C$14) -> 83.26 | H27: =IF(AND($C27="efficiency",4>=$B27),IF(4=$B27,BestPlan!$C$15+$D27,G27+BestPlan!$B$15*(Half_gap*(Ceiling_e-G27)-Transcribe!$F$4)),BestPlan!$C$15) -> 83.26 | I27: =IF(AND($C27="efficiency",5>=$B27),IF(5=$B27,BestPlan!$C$16+$D27,H27+BestPlan!$B$16*(Half_gap*(Ceiling_e-H27)-Transcribe!$F$4)),BestPlan!$C$16) -> 83.26 | J27: =IF(AND($C27="efficiency",6>=$B27),IF(6=$B27,BestPlan!$C$17+$D27,I27+BestPlan!$B$17*(Half_gap*(Ceiling_e-I27)-Transcribe!$F$4)),BestPlan!$C$17) -> 83.26 | K27: =Val_pt*(E27-E_zero)+IF(AND($C27="cash",$B27=1),$D27,0) -> 70 | L27: =Val_pt*(F27-E_zero)+IF(AND($C27="cash",$B27=2),$D27,0) -> 105 | M27: =Val_pt*(G27-E_zero)+IF(AND($C27="cash",$B27=3),$D27,0) -> 122.6 | N27: =Val_pt*(H27-E_zero)+IF(AND($C27="cash",$B27=4),$D27,0) -> 122.6 | O27: =Val_pt*(I27-E_zero)+IF(AND($C27="cash",$B27=5),$D27,0) -> 122.6 | P27: =Val_pt*(J27-E_zero)+IF(AND($C27="cash",$B27=6),$D27,0) -> 122.6 | Q27: =MAX(R27+Cost_round*BestPlan!$B$12-K27,IF(BestPlan!$B$12=1,Pre_q,0)) -> 535 | R27: =MAX(S27+Cost_round*BestPlan!$B$13-L27,IF(BestPlan!$B$13=1,Pre_q,0),Floor_q) -> 485 | S27: =MAX(T27+Cost_round*BestPlan!$B$14-M27,IF(BestPlan!$B$14=1,Pre_q,0),Floor_q) -> 470 | T27: =MAX(U27+Cost_round*BestPlan!$B$15-N27,IF(BestPlan!$B$15=1,Pre_q,0),Floor_q) -> 350 | U27: =MAX(V27+Cost_round*BestPlan!$B$16-O27,IF(BestPlan!$B$16=1,Pre_q,0),Floor_q) -> 350 | V27: =MAX(W27+Cost_round*BestPlan!$B$17-P27,IF(BestPlan!$B$17=1,Pre_q,0),Floor_q) -> 350 | W27: =MAX(End_q,Floor_q) -> 470 | X27: =IF(Q_zero>=Q27-0.000000001,1,0) -> 1 | Y27: =Q_zero-Cost_round*BestPlan!$B$12+K27-R27 -> 85 | Z27: =R27-Cost_round*BestPlan!$B$13+L27-S27 -> 0 | AA27: =S27-Cost_round*BestPlan!$B$14+M27-T27 -> 122.6 | AB27: =T27-Cost_round*BestPlan!$B$15+N27-U27 -> 122.6 | AC27: =U27-Cost_round*BestPlan!$B$16+O27-V27 -> 122.6 | AD27: =V27-Cost_round*BestPlan!$B$17+P27-W27 -> 2.6 | AE27: =Y27*Beta_y^1+Z27*Beta_y^2+AA27*Beta_y^3+AB27*Beta_y^4+AC27*Beta_y^5+AD27*Beta_y^6+Beta_y^6*Val_pt*(J27-E_zero)/Hurdle_r -> 1022.759 | AF27: =(AE27-$AE$18)/$D27 -> 82.644628 | AG27: =N8 -> 82.644628 | AH27: =ABS(AF27-AG27) -> 3.2329694e-11
A28: 0.01 point more efficiency, year 4 | B28: 4 | C28: efficiency | D28: 0.01 | E28: =IF(AND($C28="efficiency",1>=$B28),IF(1=$B28,BestPlan!$C$12+$D28,E_zero+BestPlan!$B$12*(Half_gap*(Ceiling_e-E_zero)-Transcribe!$F$4)),BestPlan!$C$12) -> 78 | F28: =IF(AND($C28="efficiency",2>=$B28),IF(2=$B28,BestPlan!$C$13+$D28,E28+BestPlan!$B$13*(Half_gap*(Ceiling_e-E28)-Transcribe!$F$4)),BestPlan!$C$13) -> 81.5 | G28: =IF(AND($C28="efficiency",3>=$B28),IF(3=$B28,BestPlan!$C$14+$D28,F28+BestPlan!$B$14*(Half_gap*(Ceiling_e-F28)-Transcribe!$F$4)),BestPlan!$C$14) -> 83.25 | H28: =IF(AND($C28="efficiency",4>=$B28),IF(4=$B28,BestPlan!$C$15+$D28,G28+BestPlan!$B$15*(Half_gap*(Ceiling_e-G28)-Transcribe!$F$4)),BestPlan!$C$15) -> 83.26 | I28: =IF(AND($C28="efficiency",5>=$B28),IF(5=$B28,BestPlan!$C$16+$D28,H28+BestPlan!$B$16*(Half_gap*(Ceiling_e-H28)-Transcribe!$F$4)),BestPlan!$C$16) -> 83.26 | J28: =IF(AND($C28="efficiency",6>=$B28),IF(6=$B28,BestPlan!$C$17+$D28,I28+BestPlan!$B$17*(Half_gap*(Ceiling_e-I28)-Transcribe!$F$4)),BestPlan!$C$17) -> 83.26 | K28: =Val_pt*(E28-E_zero)+IF(AND($C28="cash",$B28=1),$D28,0) -> 70 | L28: =Val_pt*(F28-E_zero)+IF(AND($C28="cash",$B28=2),$D28,0) -> 105 | M28: =Val_pt*(G28-E_zero)+IF(AND($C28="cash",$B28=3),$D28,0) -> 122.5 | N28: =Val_pt*(H28-E_zero)+IF(AND($C28="cash",$B28=4),$D28,0) -> 122.6 | O28: =Val_pt*(I28-E_zero)+IF(AND($C28="cash",$B28=5),$D28,0) -> 122.6 | P28: =Val_pt*(J28-E_zero)+IF(AND($C28="cash",$B28=6),$D28,0) -> 122.6 | Q28: =MAX(R28+Cost_round*BestPlan!$B$12-K28,IF(BestPlan!$B$12=1,Pre_q,0)) -> 535 | R28: =MAX(S28+Cost_round*BestPlan!$B$13-L28,IF(BestPlan!$B$13=1,Pre_q,0),Floor_q) -> 485 | S28: =MAX(T28+Cost_round*BestPlan!$B$14-M28,IF(BestPlan!$B$14=1,Pre_q,0),Floor_q) -> 470 | T28: =MAX(U28+Cost_round*BestPlan!$B$15-N28,IF(BestPlan!$B$15=1,Pre_q,0),Floor_q) -> 350 | U28: =MAX(V28+Cost_round*BestPlan!$B$16-O28,IF(BestPlan!$B$16=1,Pre_q,0),Floor_q) -> 350 | V28: =MAX(W28+Cost_round*BestPlan!$B$17-P28,IF(BestPlan!$B$17=1,Pre_q,0),Floor_q) -> 350 | W28: =MAX(End_q,Floor_q) -> 470 | X28: =IF(Q_zero>=Q28-0.000000001,1,0) -> 1 | Y28: =Q_zero-Cost_round*BestPlan!$B$12+K28-R28 -> 85 | Z28: =R28-Cost_round*BestPlan!$B$13+L28-S28 -> 0 | AA28: =S28-Cost_round*BestPlan!$B$14+M28-T28 -> 122.5 | AB28: =T28-Cost_round*BestPlan!$B$15+N28-U28 -> 122.6 | AC28: =U28-Cost_round*BestPlan!$B$16+O28-V28 -> 122.6 | AD28: =V28-Cost_round*BestPlan!$B$17+P28-W28 -> 2.6 | AE28: =Y28*Beta_y^1+Z28*Beta_y^2+AA28*Beta_y^3+AB28*Beta_y^4+AC28*Beta_y^5+AD28*Beta_y^6+Beta_y^6*Val_pt*(J28-E_zero)/Hurdle_r -> 1022.6839 | AF28: =(AE28-$AE$18)/$D28 -> 75.13148 | AG28: =N9 -> 75.13148 | AH28: =ABS(AF28-AG28) -> 2.3192115e-11
A29: 0.01 point more efficiency, year 5 | B29: 5 | C29: efficiency | D29: 0.01 | E29: =IF(AND($C29="efficiency",1>=$B29),IF(1=$B29,BestPlan!$C$12+$D29,E_zero+BestPlan!$B$12*(Half_gap*(Ceiling_e-E_zero)-Transcribe!$F$4)),BestPlan!$C$12) -> 78 | F29: =IF(AND($C29="efficiency",2>=$B29),IF(2=$B29,BestPlan!$C$13+$D29,E29+BestPlan!$B$13*(Half_gap*(Ceiling_e-E29)-Transcribe!$F$4)),BestPlan!$C$13) -> 81.5 | G29: =IF(AND($C29="efficiency",3>=$B29),IF(3=$B29,BestPlan!$C$14+$D29,F29+BestPlan!$B$14*(Half_gap*(Ceiling_e-F29)-Transcribe!$F$4)),BestPlan!$C$14) -> 83.25 | H29: =IF(AND($C29="efficiency",4>=$B29),IF(4=$B29,BestPlan!$C$15+$D29,G29+BestPlan!$B$15*(Half_gap*(Ceiling_e-G29)-Transcribe!$F$4)),BestPlan!$C$15) -> 83.25 | I29: =IF(AND($C29="efficiency",5>=$B29),IF(5=$B29,BestPlan!$C$16+$D29,H29+BestPlan!$B$16*(Half_gap*(Ceiling_e-H29)-Transcribe!$F$4)),BestPlan!$C$16) -> 83.26 | J29: =IF(AND($C29="efficiency",6>=$B29),IF(6=$B29,BestPlan!$C$17+$D29,I29+BestPlan!$B$17*(Half_gap*(Ceiling_e-I29)-Transcribe!$F$4)),BestPlan!$C$17) -> 83.26 | K29: =Val_pt*(E29-E_zero)+IF(AND($C29="cash",$B29=1),$D29,0) -> 70 | L29: =Val_pt*(F29-E_zero)+IF(AND($C29="cash",$B29=2),$D29,0) -> 105 | M29: =Val_pt*(G29-E_zero)+IF(AND($C29="cash",$B29=3),$D29,0) -> 122.5 | N29: =Val_pt*(H29-E_zero)+IF(AND($C29="cash",$B29=4),$D29,0) -> 122.5 | O29: =Val_pt*(I29-E_zero)+IF(AND($C29="cash",$B29=5),$D29,0) -> 122.6 | P29: =Val_pt*(J29-E_zero)+IF(AND($C29="cash",$B29=6),$D29,0) -> 122.6 | Q29: =MAX(R29+Cost_round*BestPlan!$B$12-K29,IF(BestPlan!$B$12=1,Pre_q,0)) -> 535 | R29: =MAX(S29+Cost_round*BestPlan!$B$13-L29,IF(BestPlan!$B$13=1,Pre_q,0),Floor_q) -> 485 | S29: =MAX(T29+Cost_round*BestPlan!$B$14-M29,IF(BestPlan!$B$14=1,Pre_q,0),Floor_q) -> 470 | T29: =MAX(U29+Cost_round*BestPlan!$B$15-N29,IF(BestPlan!$B$15=1,Pre_q,0),Floor_q) -> 350 | U29: =MAX(V29+Cost_round*BestPlan!$B$16-O29,IF(BestPlan!$B$16=1,Pre_q,0),Floor_q) -> 350 | V29: =MAX(W29+Cost_round*BestPlan!$B$17-P29,IF(BestPlan!$B$17=1,Pre_q,0),Floor_q) -> 350 | W29: =MAX(End_q,Floor_q) -> 470 | X29: =IF(Q_zero>=Q29-0.000000001,1,0) -> 1 | Y29: =Q_zero-Cost_round*BestPlan!$B$12+K29-R29 -> 85 | Z29: =R29-Cost_round*BestPlan!$B$13+L29-S29 -> 0 | AA29: =S29-Cost_round*BestPlan!$B$14+M29-T29 -> 122.5 | AB29: =T29-Cost_round*BestPlan!$B$15+N29-U29 -> 122.5 | AC29: =U29-Cost_round*BestPlan!$B$16+O29-V29 -> 122.6 | AD29: =V29-Cost_round*BestPlan!$B$17+P29-W29 -> 2.6 | AE29: =Y29*Beta_y^1+Z29*Beta_y^2+AA29*Beta_y^3+AB29*Beta_y^4+AC29*Beta_y^5+AD29*Beta_y^6+Beta_y^6*Val_pt*(J29-E_zero)/Hurdle_r -> 1022.6156 | AF29: =(AE29-$AE$18)/$D29 -> 68.301346 | AG29: =N10 -> 68.301346 | AH29: =ABS(AF29-AG29) -> 2.4186875e-11
A30: 0.01 point more efficiency, year 6 | B30: 6 | C30: efficiency | D30: 0.01 | E30: =IF(AND($C30="efficiency",1>=$B30),IF(1=$B30,BestPlan!$C$12+$D30,E_zero+BestPlan!$B$12*(Half_gap*(Ceiling_e-E_zero)-Transcribe!$F$4)),BestPlan!$C$12) -> 78 | F30: =IF(AND($C30="efficiency",2>=$B30),IF(2=$B30,BestPlan!$C$13+$D30,E30+BestPlan!$B$13*(Half_gap*(Ceiling_e-E30)-Transcribe!$F$4)),BestPlan!$C$13) -> 81.5 | G30: =IF(AND($C30="efficiency",3>=$B30),IF(3=$B30,BestPlan!$C$14+$D30,F30+BestPlan!$B$14*(Half_gap*(Ceiling_e-F30)-Transcribe!$F$4)),BestPlan!$C$14) -> 83.25 | H30: =IF(AND($C30="efficiency",4>=$B30),IF(4=$B30,BestPlan!$C$15+$D30,G30+BestPlan!$B$15*(Half_gap*(Ceiling_e-G30)-Transcribe!$F$4)),BestPlan!$C$15) -> 83.25 | I30: =IF(AND($C30="efficiency",5>=$B30),IF(5=$B30,BestPlan!$C$16+$D30,H30+BestPlan!$B$16*(Half_gap*(Ceiling_e-H30)-Transcribe!$F$4)),BestPlan!$C$16) -> 83.25 | J30: =IF(AND($C30="efficiency",6>=$B30),IF(6=$B30,BestPlan!$C$17+$D30,I30+BestPlan!$B$17*(Half_gap*(Ceiling_e-I30)-Transcribe!$F$4)),BestPlan!$C$17) -> 83.26 | K30: =Val_pt*(E30-E_zero)+IF(AND($C30="cash",$B30=1),$D30,0) -> 70 | L30: =Val_pt*(F30-E_zero)+IF(AND($C30="cash",$B30=2),$D30,0) -> 105 | M30: =Val_pt*(G30-E_zero)+IF(AND($C30="cash",$B30=3),$D30,0) -> 122.5 | N30: =Val_pt*(H30-E_zero)+IF(AND($C30="cash",$B30=4),$D30,0) -> 122.5 | O30: =Val_pt*(I30-E_zero)+IF(AND($C30="cash",$B30=5),$D30,0) -> 122.5 | P30: =Val_pt*(J30-E_zero)+IF(AND($C30="cash",$B30=6),$D30,0) -> 122.6 | Q30: =MAX(R30+Cost_round*BestPlan!$B$12-K30,IF(BestPlan!$B$12=1,Pre_q,0)) -> 535 | R30: =MAX(S30+Cost_round*BestPlan!$B$13-L30,IF(BestPlan!$B$13=1,Pre_q,0),Floor_q) -> 485 | S30: =MAX(T30+Cost_round*BestPlan!$B$14-M30,IF(BestPlan!$B$14=1,Pre_q,0),Floor_q) -> 470 | T30: =MAX(U30+Cost_round*BestPlan!$B$15-N30,IF(BestPlan!$B$15=1,Pre_q,0),Floor_q) -> 350 | U30: =MAX(V30+Cost_round*BestPlan!$B$16-O30,IF(BestPlan!$B$16=1,Pre_q,0),Floor_q) -> 350 | V30: =MAX(W30+Cost_round*BestPlan!$B$17-P30,IF(BestPlan!$B$17=1,Pre_q,0),Floor_q) -> 350 | W30: =MAX(End_q,Floor_q) -> 470 | X30: =IF(Q_zero>=Q30-0.000000001,1,0) -> 1 | Y30: =Q_zero-Cost_round*BestPlan!$B$12+K30-R30 -> 85 | Z30: =R30-Cost_round*BestPlan!$B$13+L30-S30 -> 0 | AA30: =S30-Cost_round*BestPlan!$B$14+M30-T30 -> 122.5 | AB30: =T30-Cost_round*BestPlan!$B$15+N30-U30 -> 122.5 | AC30: =U30-Cost_round*BestPlan!$B$16+O30-V30 -> 122.5 | AD30: =V30-Cost_round*BestPlan!$B$17+P30-W30 -> 2.6 | AE30: =Y30*Beta_y^1+Z30*Beta_y^2+AA30*Beta_y^3+AB30*Beta_y^4+AC30*Beta_y^5+AD30*Beta_y^6+Beta_y^6*Val_pt*(J30-E_zero)/Hurdle_r -> 1022.5535 | AF30: =(AE30-$AE$18)/$D30 -> 62.092132 | AG30: =N11 -> 62.092132 | AH30: =ABS(AF30-AG30) -> 2.5089264e-11
A31: Largest difference between the prices and the perturbations | AH31: =MAX(AH19:AH30) -> 3.75735e-11
A33: The round test (Worked Example 5.1, Step 4): the n-th round pays when the savings it adds, valued at the hurdle rate, cover the $120 million it needs
A34: Round n | B34: Gap before the round | C34: Savings it adds a year | D34: Valued forever at r | E34: Against its cost | F34: Its yield
A35: 1 | B35: =(Ceiling_e-E_zero)*(1-Half_gap)^(A35-1) -> 14 | C35: =Val_pt*Half_gap*B35 -> 70 | D35: =C35/Hurdle_r -> 700 | E35: =IF(D35>=Cost_round,"pays","does not pay") -> pays | F35: =C35/Cost_round -> 0.58333333
A36: 2 | B36: =(Ceiling_e-E_zero)*(1-Half_gap)^(A36-1) -> 7 | C36: =Val_pt*Half_gap*B36 -> 35 | D36: =C36/Hurdle_r -> 350 | E36: =IF(D36>=Cost_round,"pays","does not pay") -> pays | F36: =C36/Cost_round -> 0.29166667
A37: 3 | B37: =(Ceiling_e-E_zero)*(1-Half_gap)^(A37-1) -> 3.5 | C37: =Val_pt*Half_gap*B37 -> 17.5 | D37: =C37/Hurdle_r -> 175 | E37: =IF(D37>=Cost_round,"pays","does not pay") -> pays | F37: =C37/Cost_round -> 0.14583333
A38: 4 | B38: =(Ceiling_e-E_zero)*(1-Half_gap)^(A38-1) -> 1.75 | C38: =Val_pt*Half_gap*B38 -> 8.75 | D38: =C38/Hurdle_r -> 87.5 | E38: =IF(D38>=Cost_round,"pays","does not pay") -> does not pay | F38: =C38/Cost_round -> 0.072916667
A39: 5 | B39: =(Ceiling_e-E_zero)*(1-Half_gap)^(A39-1) -> 0.875 | C39: =Val_pt*Half_gap*B39 -> 4.375 | D39: =C39/Hurdle_r -> 43.75 | E39: =IF(D39>=Cost_round,"pays","does not pay") -> does not pay | F39: =C39/Cost_round -> 0.036458333
A40: 6 | B40: =(Ceiling_e-E_zero)*(1-Half_gap)^(A40-1) -> 0.4375 | C40: =Val_pt*Half_gap*B40 -> 2.1875 | D40: =C40/Hurdle_r -> 21.875 | E40: =IF(D40>=Cost_round,"pays","does not pay") -> does not pay | F40: =C40/Cost_round -> 0.018229167

Sheet Rates
A1: Move the rate: the best plan at hurdle rates from 3 to 30 percent (Figure 5.2(b); AXIOM Lab 2.5, step 4)
A2: Each column of Transcribe values all 64 schedules at one hurdle rate (the war chests and payouts do not depend on the rate). The best plan at each rate is the MAX of its column.
A4: Hurdle rate | B4: Best value | C4: Its row | D4: Rounds by year | E4: Rounds | F4: Perpetuity in years of S_6
A5: =Transcribe!AP$6 -> 0.03 | B5: =MAX(Transcribe!$AP$8:$AP$71) -> 4011.0114 | C5: =MATCH(B5,Transcribe!$AP$8:$AP$71,0) -> 63 | D5: =INDEX(Transcribe!$B$8:$B$71,C5) -> 111110 | E5: =INDEX(Transcribe!$C$8:$C$71,C5) -> 5 | F5: =1/A5 -> 33.333333
A6: =Transcribe!AQ$6 -> 0.05 | B6: =MAX(Transcribe!$AQ$8:$AQ$71) -> 2261.1398 | C6: =MATCH(B6,Transcribe!$AQ$8:$AQ$71,0) -> 61 | D6: =INDEX(Transcribe!$B$8:$B$71,C6) -> 111100 | E6: =INDEX(Transcribe!$C$8:$C$71,C6) -> 4 | F6: =1/A6 -> 20
A7: =Transcribe!AR$6 -> 0.08 | B7: =MAX(Transcribe!$AR$8:$AR$71) -> 1315.8834 | C7: =MATCH(B7,Transcribe!$AR$8:$AR$71,0) -> 57 | D7: =INDEX(Transcribe!$B$8:$B$71,C7) -> 111000 | E7: =INDEX(Transcribe!$C$8:$C$71,C7) -> 3 | F7: =1/A7 -> 12.5
A8: =Transcribe!AS$6 -> 0.1 | B8: =MAX(Transcribe!$AS$8:$AS$71) -> 1021.9325 | C8: =MATCH(B8,Transcribe!$AS$8:$AS$71,0) -> 57 | D8: =INDEX(Transcribe!$B$8:$B$71,C8) -> 111000 | E8: =INDEX(Transcribe!$C$8:$C$71,C8) -> 3 | F8: =1/A8 -> 10
A9: =Transcribe!AT$6 -> 0.12 | B9: =MAX(Transcribe!$AT$8:$AT$71) -> 828.89921 | C9: =MATCH(B9,Transcribe!$AT$8:$AT$71,0) -> 57 | D9: =INDEX(Transcribe!$B$8:$B$71,C9) -> 111000 | E9: =INDEX(Transcribe!$C$8:$C$71,C9) -> 3 | F9: =1/A9 -> 8.3333333
A10: =Transcribe!AU$6 -> 0.15 | B10: =MAX(Transcribe!$AU$8:$AU$71) -> 642.80013 | C10: =MATCH(B10,Transcribe!$AU$8:$AU$71,0) -> 49 | D10: =INDEX(Transcribe!$B$8:$B$71,C10) -> 110000 | E10: =INDEX(Transcribe!$C$8:$C$71,C10) -> 2 | F10: =1/A10 -> 6.6666667
A11: =Transcribe!AV$6 -> 0.2 | B11: =MAX(Transcribe!$AV$8:$AV$71) -> 479.64088 | C11: =MATCH(B11,Transcribe!$AV$8:$AV$71,0) -> 49 | D11: =INDEX(Transcribe!$B$8:$B$71,C11) -> 110000 | E11: =INDEX(Transcribe!$C$8:$C$71,C11) -> 2 | F11: =1/A11 -> 5
A12: =Transcribe!AW$6 -> 0.3 | B12: =MAX(Transcribe!$AW$8:$AW$71) -> 320.74916 | C12: =MATCH(B12,Transcribe!$AW$8:$AW$71,0) -> 33 | D12: =INDEX(Transcribe!$B$8:$B$71,C12) -> 100000 | E12: =INDEX(Transcribe!$C$8:$C$71,C12) -> 1 | F12: =1/A12 -> 3.3333333
A14: Payouts of the best plan at 5 percent, years 1 to 6
B15: =INDEX(Transcribe!$AD$8:$AD$71,$C$6) -> 85 | C15: =INDEX(Transcribe!$AE$8:$AE$71,$C$6) -> 0 | D15: =INDEX(Transcribe!$AF$8:$AF$71,$C$6) -> 2.5 | E15: =INDEX(Transcribe!$AG$8:$AG$71,$C$6) -> 131.25 | F15: =INDEX(Transcribe!$AH$8:$AH$71,$C$6) -> 131.25 | G15: =INDEX(Transcribe!$AI$8:$AI$71,$C$6) -> 11.25
A18: Switch | B18: Rate (engine bisection) | C18: Rounds below the rate | D18: Best plan with that many rounds | E18: Best plan with one round fewer | F18: |difference| | G18: Best of all 64 | H18: The round's yield | I18: Rate - yield
A19: round 6 | B19: =Transcribe!AX$6 -> 0.018229167 | C19: 6 | D19: =_xlfn.MAXIFS(Transcribe!$AX$8:$AX$71,Transcribe!$C$8:$C$71,C19) -> 6909.9887 | E19: =_xlfn.MAXIFS(Transcribe!$AX$8:$AX$71,Transcribe!$C$8:$C$71,C19-1) -> 6909.9887 | F19: =ABS(D19-E19) -> 1.0013537e-09 | G19: =MAX(Transcribe!$AX$8:$AX$71) -> 6909.9887 | H19: =Prices!C40/Cost_round -> 0.018229167 | I19: =B19-H19 -> -1.6648835e-13
A20: round 5 | B20: =Transcribe!AY$6 -> 0.036458333 | C20: 5 | D20: =_xlfn.MAXIFS(Transcribe!$AY$8:$AY$71,Transcribe!$C$8:$C$71,C20) -> 3220.7637 | E20: =_xlfn.MAXIFS(Transcribe!$AY$8:$AY$71,Transcribe!$C$8:$C$71,C20-1) -> 3220.7637 | F20: =ABS(D20-E20) -> 1.0004442e-09 | G20: =MAX(Transcribe!$AY$8:$AY$71) -> 3220.7637 | H20: =Prices!C39/Cost_round -> 0.036458333 | I20: =B20-H20 -> -3.5079578e-13
A21: round 4 | B21: =Transcribe!AZ$6 -> 0.072916667 | C21: 4 | D21: =_xlfn.MAXIFS(Transcribe!$AZ$8:$AZ$71,Transcribe!$C$8:$C$71,C21) -> 1459.9676 | E21: =_xlfn.MAXIFS(Transcribe!$AZ$8:$AZ$71,Transcribe!$C$8:$C$71,C21-1) -> 1459.9676 | F21: =ABS(D21-E21) -> 9.9998942e-10 | G21: =MAX(Transcribe!$AZ$8:$AZ$71) -> 1459.9676 | H21: =Prices!C38/Cost_round -> 0.072916667 | I21: =B21-H21 -> -7.5046913e-13
A22: round 3 | B22: =Transcribe!BA$6 -> 0.14549722 | C22: 3 | D22: =_xlfn.MAXIFS(Transcribe!$BA$8:$BA$71,Transcribe!$C$8:$C$71,C22) -> 663.21735 | E22: =_xlfn.MAXIFS(Transcribe!$BA$8:$BA$71,Transcribe!$C$8:$C$71,C22-1) -> 663.21735 | F22: =ABS(D22-E22) -> 1.0002168e-09 | G22: =MAX(Transcribe!$BA$8:$BA$71) -> 663.21735 | H22: =Prices!C37/Cost_round -> 0.14583333 | I22: =B22-H22 -> -0.00033610897
A23: round 2 | B23: =Transcribe!BB$6 -> 0.29871078 | C23: 2 | D23: =_xlfn.MAXIFS(Transcribe!$BB$8:$BB$71,Transcribe!$C$8:$C$71,C23) -> 321.71719 | E23: =_xlfn.MAXIFS(Transcribe!$BB$8:$BB$71,Transcribe!$C$8:$C$71,C23-1) -> 321.71719 | F23: =ABS(D23-E23) -> 1.0001031e-09 | G23: =MAX(Transcribe!$BB$8:$BB$71) -> 321.71719 | H23: =Prices!C36/Cost_round -> 0.29166667 | I23: =B23-H23 -> 0.0070441138
A25: At each switch rate the best plan with n rounds and the best with n - 1 are worth the same, and no plan is worth more: the engine's bisection is certified by formulas. From the fourth round on the switch rate is exactly the round's yield; for the second and third the end condition's cash moves the switch.

Sheet Horizons
A1: Move the horizon: terminal values and planning windows (Theorem 5.2; Figure 5.2(a); AXIOM Lab 2.5, step 4)
A3: Terminal value, six-year plan (all 64 schedules) | B3: Best by its own criterion | C3: Its row | D3: Rounds by year | E3: Worth with the savings forever
A4: Savings valued forever (the board's declaration) | B4: =MAX(Transcribe!$AL$8:$AL$71) -> 1021.9325 | C4: =MATCH(B4,Transcribe!$AL$8:$AL$71,0) -> 57 | D4: =INDEX(Transcribe!$B$8:$B$71,C4) -> 111000 | E4: =INDEX(Transcribe!$AL$8:$AL$71,C4) -> 1021.9325
A5: No terminal value | B5: =MAX(Transcribe!$AM$8:$AM$71) -> 384.17334 | C5: =MATCH(B5,Transcribe!$AM$8:$AM$71,0) -> 49 | D5: =INDEX(Transcribe!$B$8:$B$71,C5) -> 110000 | E5: =INDEX(Transcribe!$AL$8:$AL$71,C5) -> 976.87096
A6: Savings over the twenty-year life of the lines | B6: =MAX(Transcribe!$AN$8:$AN$71) -> 919.14837 | C6: =MATCH(B6,Transcribe!$AN$8:$AN$71,0) -> 57 | D6: =INDEX(Transcribe!$B$8:$B$71,C6) -> 111000 | E6: =INDEX(Transcribe!$AL$8:$AL$71,C6) -> 1021.9325
A7: Undiscounted, Part I's ten years of credit | B7: =MAX(Transcribe!$AO$8:$AO$71) -> 1680 | C7: =MATCH(B7,Transcribe!$AO$8:$AO$71,0) -> 57 | D7: =INDEX(Transcribe!$B$8:$B$71,C7) -> 111000 | E7: =INDEX(Transcribe!$AL$8:$AL$71,C7) -> 1021.9325
A9: Planning without a terminal value loses, with the savings valued forever | E9: =E4-E5 -> 45.061587
A10: The perpetuity S_6/r in years of S_6: at the board's rate, and at 5 percent | D10: =1/Hurdle_r -> 10 | E10: =1/0.05 -> 20
A12: Planning windows of T years at the board's rate, the end condition at each window's end: the best number of rounds (the rows below compare rounds in the first n years, n = 0 to 4)
A13: Window T (years) | B13: Best value, no terminal value | C13: Rounds, no terminal value | D13: Best value, savings forever | E13: Rounds, savings forever
A14: 1 | B14: =_xlfn.MAXIFS($BM$40:$BM$133,$A$40:$A$133,A14) -> 136.36364 | C14: =_xlfn.MINIFS($B$40:$B$133,$A$40:$A$133,A14,$BM$40:$BM$133,">="&(B14-0.000000001)) -> 0 | D14: =_xlfn.MAXIFS($BN$40:$BN$133,$A$40:$A$133,A14) -> 727.27273 | E14: =_xlfn.MINIFS($B$40:$B$133,$A$40:$A$133,A14,$BN$40:$BN$133,">="&(D14-0.000000001)) -> 1
A15: 2 | B15: =_xlfn.MAXIFS($BM$40:$BM$133,$A$40:$A$133,A15) -> 154.54545 | C15: =_xlfn.MINIFS($B$40:$B$133,$A$40:$A$133,A15,$BM$40:$BM$133,">="&(B15-0.000000001)) -> 1 | D15: =_xlfn.MAXIFS($BN$40:$BN$133,$A$40:$A$133,A15) -> 945.04132 | E15: =_xlfn.MINIFS($B$40:$B$133,$A$40:$A$133,A15,$BN$40:$BN$133,">="&(D15-0.000000001)) -> 2
A16: 3 | B16: =_xlfn.MAXIFS($BM$40:$BM$133,$A$40:$A$133,A16) -> 216.52893 | C16: =_xlfn.MINIFS($B$40:$B$133,$A$40:$A$133,A16,$BM$40:$BM$133,">="&(B16-0.000000001)) -> 1 | D16: =_xlfn.MAXIFS($BN$40:$BN$133,$A$40:$A$133,A16) -> 999.51165 | E16: =_xlfn.MINIFS($B$40:$B$133,$A$40:$A$133,A16,$BN$40:$BN$133,">="&(D16-0.000000001)) -> 3
A17: 4 | B17: =_xlfn.MAXIFS($BM$40:$BM$133,$A$40:$A$133,A17) -> 272.87754 | C17: =_xlfn.MINIFS($B$40:$B$133,$A$40:$A$133,A17,$BM$40:$BM$133,">="&(B17-0.000000001)) -> 1 | D17: =_xlfn.MAXIFS($BN$40:$BN$133,$A$40:$A$133,A17) -> 1007.7078 | E17: =_xlfn.MINIFS($B$40:$B$133,$A$40:$A$133,A17,$BN$40:$BN$133,">="&(D17-0.000000001)) -> 3
A18: 5 | B18: =_xlfn.MAXIFS($BM$40:$BM$133,$A$40:$A$133,A18) -> 324.10354 | C18: =_xlfn.MINIFS($B$40:$B$133,$A$40:$A$133,A18,$BM$40:$BM$133,">="&(B18-0.000000001)) -> 1 | D18: =_xlfn.MAXIFS($BN$40:$BN$133,$A$40:$A$133,A18) -> 1015.1589 | E18: =_xlfn.MINIFS($B$40:$B$133,$A$40:$A$133,A18,$BN$40:$BN$133,">="&(D18-0.000000001)) -> 3
A19: 6 | B19: =_xlfn.MAXIFS($BM$40:$BM$133,$A$40:$A$133,A19) -> 384.17334 | C19: =_xlfn.MINIFS($B$40:$B$133,$A$40:$A$133,A19,$BM$40:$BM$133,">="&(B19-0.000000001)) -> 2 | D19: =_xlfn.MAXIFS($BN$40:$BN$133,$A$40:$A$133,A19) -> 1021.9325 | E19: =_xlfn.MINIFS($B$40:$B$133,$A$40:$A$133,A19,$BN$40:$BN$133,">="&(D19-0.000000001)) -> 3
A20: 7 | B20: =_xlfn.MAXIFS($BM$40:$BM$133,$A$40:$A$133,A20) -> 444.28981 | C20: =_xlfn.MINIFS($B$40:$B$133,$A$40:$A$133,A20,$BM$40:$BM$133,">="&(B20-0.000000001)) -> 2 | D20: =_xlfn.MAXIFS($BN$40:$BN$133,$A$40:$A$133,A20) -> 1028.0904 | E20: =_xlfn.MINIFS($B$40:$B$133,$A$40:$A$133,A20,$BN$40:$BN$133,">="&(D20-0.000000001)) -> 3
A21: 8 | B21: =_xlfn.MAXIFS($BM$40:$BM$133,$A$40:$A$133,A21) -> 498.94115 | C21: =_xlfn.MINIFS($B$40:$B$133,$A$40:$A$133,A21,$BM$40:$BM$133,">="&(B21-0.000000001)) -> 2 | D21: =_xlfn.MAXIFS($BN$40:$BN$133,$A$40:$A$133,A21) -> 1033.6885 | E21: =_xlfn.MINIFS($B$40:$B$133,$A$40:$A$133,A21,$BN$40:$BN$133,">="&(D21-0.000000001)) -> 3
A22: 9 | B22: =_xlfn.MAXIFS($BM$40:$BM$133,$A$40:$A$133,A22) -> 548.62419 | C22: =_xlfn.MINIFS($B$40:$B$133,$A$40:$A$133,A22,$BM$40:$BM$133,">="&(B22-0.000000001)) -> 2 | D22: =_xlfn.MAXIFS($BN$40:$BN$133,$A$40:$A$133,A22) -> 1038.7777 | E22: =_xlfn.MINIFS($B$40:$B$133,$A$40:$A$133,A22,$BN$40:$BN$133,">="&(D22-0.000000001)) -> 3
A23: 10 | B23: =_xlfn.MAXIFS($BM$40:$BM$133,$A$40:$A$133,A23) -> 593.79058 | C23: =_xlfn.MINIFS($B$40:$B$133,$A$40:$A$133,A23,$BM$40:$BM$133,">="&(B23-0.000000001)) -> 2 | D23: =_xlfn.MAXIFS($BN$40:$BN$133,$A$40:$A$133,A23) -> 1043.4042 | E23: =_xlfn.MINIFS($B$40:$B$133,$A$40:$A$133,A23,$BN$40:$BN$133,">="&(D23-0.000000001)) -> 3
A24: 11 | B24: =_xlfn.MAXIFS($BM$40:$BM$133,$A$40:$A$133,A24) -> 634.85094 | C24: =_xlfn.MINIFS($B$40:$B$133,$A$40:$A$133,A24,$BM$40:$BM$133,">="&(B24-0.000000001)) -> 2 | D24: =_xlfn.MAXIFS($BN$40:$BN$133,$A$40:$A$133,A24) -> 1047.6102 | E24: =_xlfn.MINIFS($B$40:$B$133,$A$40:$A$133,A24,$BN$40:$BN$133,">="&(D24-0.000000001)) -> 3
A25: 12 | B25: =_xlfn.MAXIFS($BM$40:$BM$133,$A$40:$A$133,A25) -> 672.17854 | C25: =_xlfn.MINIFS($B$40:$B$133,$A$40:$A$133,A25,$BM$40:$BM$133,">="&(B25-0.000000001)) -> 2 | D25: =_xlfn.MAXIFS($BN$40:$BN$133,$A$40:$A$133,A25) -> 1051.4337 | E25: =_xlfn.MINIFS($B$40:$B$133,$A$40:$A$133,A25,$BN$40:$BN$133,">="&(D25-0.000000001)) -> 3
... A33: 20 | B33: =_xlfn.MAXIFS($BM$40:$BM$133,$A$40:$A$133,A33) -> 889.74374 | C33: =_xlfn.MINIFS($B$40:$B$133,$A$40:$A$133,A33,$BM$40:$BM$133,">="&(B33-0.000000001)) -> 3 | D33: =_xlfn.MAXIFS($BN$40:$BN$133,$A$40:$A$133,A33) -> 1071.8322 | E33: =_xlfn.MINIFS($B$40:$B$133,$A$40:$A$133,A33,$BN$40:$BN$133,">="&(D33-0.000000001)) -> 3
A35: Shortest window whose best plan runs a third round: no terminal value | E35: =_xlfn.MINIFS(A14:A33,C14:C33,">=3") -> 15
A36: Shortest window whose best plan runs a third round: savings valued forever | E36: =_xlfn.MINIFS(A14:A33,E14:E33,">=3") -> 3
A37: The notebook's full enumeration confirms that the best rounds come in the first years for windows of up to twelve years (Online Appendix 5.B.3: ten); years beyond a window show 0.
A38: Discount factor | AS38: =Beta_y^1 -> 0.90909091 | AT38: =Beta_y^2 -> 0.82644628 | AU38: =Beta_y^3 -> 0.7513148 | AV38: =Beta_y^4 -> 0.68301346 | AW38: =Beta_y^5 -> 0.62092132 | AX38: =Beta_y^6 -> 0.56447393 | AY38: =Beta_y^7 -> 0.51315812 | AZ38: =Beta_y^8 -> 0.46650738 | BA38: =Beta_y^9 -> 0.42409762 | BB38: =Beta_y^10 -> 0.38554329 | BC38: =Beta_y^11 -> 0.3504939 | BD38: =Beta_y^12 -> 0.31863082 | BE38: =Beta_y^13 -> 0.28966438 | BF38: =Beta_y^14 -> 0.26333125 | BG38: =Beta_y^15 -> 0.23939205 | BH38: =Beta_y^16 -> 0.21762914 | BI38: =Beta_y^17 -> 0.19784467 | BJ38: =Beta_y^18 -> 0.17985879 | BK38: =Beta_y^19 -> 0.16350799 | BL38: =Beta_y^20 -> 0.14864363
A39: T | B39: n | C39: S1 | D39: S2 | E39: S3 | F39: S4 | G39: S5 | H39: S6 | I39: S7 | J39: S8 | K39: S9 | L39: S10 | M39: S11 | N39: S12 | O39: S13 | P39: S14 | Q39: S15 | R39: S16 | S39: S17 | T39: S18 | U39: S19 | V39: S20 | W39: R0 | X39: R1 | Y39: R2 | Z39: R3 | AA39: R4 | AB39: R5 | AC39: R6 | AD39: R7 | AE39: R8 | AF39: R9 | AG39: R10 | AH39: R11 | AI39: R12 | AJ39: R13 | AK39: R14 | AL39: R15 | AM39: R16 | AN39: R17 | AO39: R18 | AP39: R19 | AQ39: R20 | AR39: Keeps every commitment | AS39: p1 | AT39: p2 | AU39: p3 | AV39: p4 | AW39: p5 | AX39: p6 | AY39: p7 | AZ39: p8 | BA39: p9 | BB39: p10 | BC39: p11 | BD39: p12 | BE39: p13 | BF39: p14 | BG39: p15 | BH39: p16 | BI39: p17 | BJ39: p18 | BK39: p19 | BL39: p20 | BM39: Value, no terminal value | BN39: Value, savings forever
A40: 1 | B40: 0 | C40: =IF(1>$A40,0,Val_pt*(Ceiling_e-E_zero)*(1-(1-Half_gap)^MIN(1,$B40))) -> 0 | D40: =IF(2>$A40,0,Val_pt*(Ceiling_e-E_zero)*(1-(1-Half_gap)^MIN(2,$B40))) -> 0 | E40: =IF(3>$A40,0,Val_pt*(Ceiling_e-E_zero)*(1-(1-Half_gap)^MIN(3,$B40))) -> 0 | F40: =IF(4>$A40,0,Val_pt*(Ceiling_e-E_zero)*(1-(1-Half_gap)^MIN(4,$B40))) -> 0 | G40: =IF(5>$A40,0,Val_pt*(Ceiling_e-E_zero)*(1-(1-Half_gap)^MIN(5,$B40))) -> 0 | H40: =IF(6>$A40,0,Val_pt*(Ceiling_e-E_zero)*(1-(1-Half_gap)^MIN(6,$B40))) -> 0 | I40: =IF(7>$A40,0,Val_pt*(Ceiling_e-E_zero)*(1-(1-Half_gap)^MIN(7,$B40))) -> 0 | J40: =IF(8>$A40,0,Val_pt*(Ceiling_e-E_zero)*(1-(1-Half_gap)^MIN(8,$B40))) -> 0 | K40: =IF(9>$A40,0,Val_pt*(Ceiling_e-E_zero)*(1-(1-Half_gap)^MIN(9,$B40))) -> 0 | L40: =IF(10>$A40,0,Val_pt*(Ceiling_e-E_zero)*(1-(1-Half_gap)^MIN(10,$B40))) -> 0 | M40: =IF(11>$A40,0,Val_pt*(Ceiling_e-E_zero)*(1-(1-Half_gap)^MIN(11,$B40))) -> 0 | N40: =IF(12>$A40,0,Val_pt*(Ceiling_e-E_zero)*(1-(1-Half_gap)^MIN(12,$B40))) -> 0 | O40: =IF(13>$A40,0,Val_pt*(Ceiling_e-E_zero)*(1-(1-Half_gap)^MIN(13,$B40))) -> 0 | P40: =IF(14>$A40,0,Val_pt*(Ceiling_e-E_zero)*(1-(1-Half_gap)^MIN(14,$B40))) -> 0 | Q40: =IF(15>$A40,0,Val_pt*(Ceiling_e-E_zero)*(1-(1-Half_gap)^MIN(15,$B40))) -> 0 | R40: =IF(16>$A40,0,Val_pt*(Ceiling_e-E_zero)*(1-(1-Half_gap)^MIN(16,$B40))) -> 0 | S40: =IF(17>$A40,0,Val_pt*(Ceiling_e-E_zero)*(1-(1-Half_gap)^MIN(17,$B40))) -> 0 | T40: =IF(18>$A40,0,Val_pt*(Ceiling_e-E_zero)*(1-(1-Half_gap)^MIN(18,$B40))) -> 0 | U40: =IF(19>$A40,0,Val_pt*(Ceiling_e-E_zero)*(1-(1-Half_gap)^MIN(19,$B40))) -> 0 | V40: =IF(20>$A40,0,Val_pt*(Ceiling_e-E_zero)*(1-(1-Half_gap)^MIN(20,$B40))) -> 0 | W40: =IF(0>$A40,0,IF(0=$A40,MAX(End_q,Floor_q),MAX(X40+Cost_round*IF(1<=$B40,1,0)-C40,IF(1<=$B40,1,0)*Pre_q))) -> 470 | X40: =IF(1>$A40,0,IF(1=$A40,MAX(End_q,Floor_q),MAX(Y40+Cost_round*IF(2<=$B40,1,0)-D40,IF(2<=$B40,1,0)*Pre_q,Floor_q))) -> 470 | Y40: =IF(2>$A40,0,IF(2=$A40,MAX(End_q,Floor_q),MAX(Z40+Cost_round*IF(3<=$B40,1,0)-E40,IF(3<=$B40,1,0)*Pre_q,Floor_q))) -> 0 | Z40: =IF(3>$A40,0,IF(3=$A40,MAX(End_q,Floor_q),MAX(AA40+Cost_round*IF(4<=$B40,1,0)-F40,IF(4<=$B40,1,0)*Pre_q,Floor_q))) -> 0 | AA40: =IF(4>$A40,0,IF(4=$A40,MAX(End_q,Floor_q),MAX(AB40+Cost_round*IF(5<=$B40,1,0)-G40,IF(5<=$B40,1,0)*Pre_q,Floor_q))) -> 0 | AB40: =IF(5>$A40,0,IF(5=$A40,MAX(End_q,Floor_q),MAX(AC40+Cost_round*IF(6<=$B40,1,0)-H40,IF(6<=$B40,1,0)*Pre_q,Floor_q))) -> 0 | AC40: =IF(6>$A40,0,IF(6=$A40,MAX(End_q,Floor_q),MAX(AD40+Cost_round*IF(7<=$B40,1,0)-I40,IF(7<=$B40,1,0)*Pre_q,Floor_q))) -> 0 | AD40: =IF(7>$A40,0,IF(7=$A40,MAX(End_q,Floor_q),MAX(AE40+Cost_round*IF(8<=$B40,1,0)-J40,IF(8<=$B40,1,0)*Pre_q,Floor_q))) -> 0 | AE40: =IF(8>$A40,0,IF(8=$A40,MAX(End_q,Floor_q),MAX(AF40+Cost_round*IF(9<=$B40,1,0)-K40,IF(9<=$B40,1,0)*Pre_q,Floor_q))) -> 0 | AF40: =IF(9>$A40,0,IF(9=$A40,MAX(End_q,Floor_q),MAX(AG40+Cost_round*IF(10<=$B40,1,0)-L40,IF(10<=$B40,1,0)*Pre_q,Floor_q))) -> 0 | AG40: =IF(10>$A40,0,IF(10=$A40,MAX(End_q,Floor_q),MAX(AH40+Cost_round*IF(11<=$B40,1,0)-M40,IF(11<=$B40,1,0)*Pre_q,Floor_q))) -> 0 | AH40: =IF(11>$A40,0,IF(11=$A40,MAX(End_q,Floor_q),MAX(AI40+Cost_round*IF(12<=$B40,1,0)-N40,IF(12<=$B40,1,0)*Pre_q,Floor_q))) -> 0 | AI40: =IF(12>$A40,0,IF(12=$A40,MAX(End_q,Floor_q),MAX(AJ40+Cost_round*IF(13<=$B40,1,0)-O40,IF(13<=$B40,1,0)*Pre_q,Floor_q))) -> 0 | AJ40: =IF(13>$A40,0,IF(13=$A40,MAX(End_q,Floor_q),MAX(AK40+Cost_round*IF(14<=$B40,1,0)-P40,IF(14<=$B40,1,0)*Pre_q,Floor_q))) -> 0 | AK40: =IF(14>$A40,0,IF(14=$A40,MAX(End_q,Floor_q),MAX(AL40+Cost_round*IF(15<=$B40,1,0)-Q40,IF(15<=$B40,1,0)*Pre_q,Floor_q))) -> 0 | AL40: =IF(15>$A40,0,IF(15=$A40,MAX(End_q,Floor_q),MAX(AM40+Cost_round*IF(16<=$B40,1,0)-R40,IF(16<=$B40,1,0)*Pre_q,Floor_q))) -> 0 | AM40: =IF(16>$A40,0,IF(16=$A40,MAX(End_q,Floor_q),MAX(AN40+Cost_round*IF(17<=$B40,1,0)-S40,IF(17<=$B40,1,0)*Pre_q,Floor_q))) -> 0 | AN40: =IF(17>$A40,0,IF(17=$A40,MAX(End_q,Floor_q),MAX(AO40+Cost_round*IF(18<=$B40,1,0)-T40,IF(18<=$B40,1,0)*Pre_q,Floor_q))) -> 0 | AO40: =IF(18>$A40,0,IF(18=$A40,MAX(End_q,Floor_q),MAX(AP40+Cost_round*IF(19<=$B40,1,0)-U40,IF(19<=$B40,1,0)*Pre_q,Floor_q))) -> 0 | AP40: =IF(19>$A40,0,IF(19=$A40,MAX(End_q,Floor_q),MAX(AQ40+Cost_round*IF(20<=$B40,1,0)-V40,IF(20<=$B40,1,0)*Pre_q,Floor_q))) -> 0 | AQ40: =IF(20>$A40,0,MAX(End_q,Floor_q)) -> 0 | AR40: =IF(Q_zero>=W40-0.000000001,1,0) -> 1 | AS40: =IF(1>$A40,0,Q_zero-Cost_round*IF(1<=$B40,1,0)+C40-X40) -> 150 | AT40: =IF(2>$A40,0,X40-Cost_round*IF(2<=$B40,1,0)+D40-Y40) -> 0 | AU40: =IF(3>$A40,0,Y40-Cost_round*IF(3<=$B40,1,0)+E40-Z40) -> 0 | AV40: =IF(4>$A40,0,Z40-Cost_round*IF(4<=$B40,1,0)+F40-AA40) -> 0 | AW40: =IF(5>$A40,0,AA40-Cost_round*IF(5<=$B40,1,0)+G40-AB40) -> 0 | AX40: =IF(6>$A40,0,AB40-Cost_round*IF(6<=$B40,1,0)+H40-AC40) -> 0 | AY40: =IF(7>$A40,0,AC40-Cost_round*IF(7<=$B40,1,0)+I40-AD40) -> 0 | AZ40: =IF(8>$A40,0,AD40-Cost_round*IF(8<=$B40,1,0)+J40-AE40) -> 0 | BA40: =IF(9>$A40,0,AE40-Cost_round*IF(9<=$B40,1,0)+K40-AF40) -> 0 | BB40: =IF(10>$A40,0,AF40-Cost_round*IF(10<=$B40,1,0)+L40-AG40) -> 0 | BC40: =IF(11>$A40,0,AG40-Cost_round*IF(11<=$B40,1,0)+M40-AH40) -> 0 | BD40: =IF(12>$A40,0,AH40-Cost_round*IF(12<=$B40,1,0)+N40-AI40) -> 0 | BE40: =IF(13>$A40,0,AI40-Cost_round*IF(13<=$B40,1,0)+O40-AJ40) -> 0 | BF40: =IF(14>$A40,0,AJ40-Cost_round*IF(14<=$B40,1,0)+P40-AK40) -> 0 | BG40: =IF(15>$A40,0,AK40-Cost_round*IF(15<=$B40,1,0)+Q40-AL40) -> 0 | BH40: =IF(16>$A40,0,AL40-Cost_round*IF(16<=$B40,1,0)+R40-AM40) -> 0 | BI40: =IF(17>$A40,0,AM40-Cost_round*IF(17<=$B40,1,0)+S40-AN40) -> 0 | BJ40: =IF(18>$A40,0,AN40-Cost_round*IF(18<=$B40,1,0)+T40-AO40) -> 0 | BK40: =IF(19>$A40,0,AO40-Cost_round*IF(19<=$B40,1,0)+U40-AP40) -> 0 | BL40: =IF(20>$A40,0,AP40-Cost_round*IF(20<=$B40,1,0)+V40-AQ40) -> 0 | BM40: =IF($AR40=1,SUMPRODUCT(AS40:BL40,$AS$38:$BL$38),"") -> 136.36364 | BN40: =IF($AR40=1,BM40+INDEX($AS$38:$BL$38,$A40)*INDEX(C40:V40,$A40)/Hurdle_r,"") -> 136.36364
A41: 1 | B41: 1 | C41: =IF(1>$A41,0,Val_pt*(Ceiling_e-E_zero)*(1-(1-Half_gap)^MIN(1,$B41))) -> 70 | D41: =IF(2>$A41,0,Val_pt*(Ceiling_e-E_zero)*(1-(1-Half_gap)^MIN(2,$B41))) -> 0 | E41: =IF(3>$A41,0,Val_pt*(Ceiling_e-E_zero)*(1-(1-Half_gap)^MIN(3,$B41))) -> 0 | F41: =IF(4>$A41,0,Val_pt*(Ceiling_e-E_zero)*(1-(1-Half_gap)^MIN(4,$B41))) -> 0 | G41: =IF(5>$A41,0,Val_pt*(Ceiling_e-E_zero)*(1-(1-Half_gap)^MIN(5,$B41))) -> 0 | H41: =IF(6>$A41,0,Val_pt*(Ceiling_e-E_zero)*(1-(1-Half_gap)^MIN(6,$B41))) -> 0 | I41: =IF(7>$A41,0,Val_pt*(Ceiling_e-E_zero)*(1-(1-Half_gap)^MIN(7,$B41))) -> 0 | J41: =IF(8>$A41,0,Val_pt*(Ceiling_e-E_zero)*(1-(1-Half_gap)^MIN(8,$B41))) -> 0 | K41: =IF(9>$A41,0,Val_pt*(Ceiling_e-E_zero)*(1-(1-Half_gap)^MIN(9,$B41))) -> 0 | L41: =IF(10>$A41,0,Val_pt*(Ceiling_e-E_zero)*(1-(1-Half_gap)^MIN(10,$B41))) -> 0 | M41: =IF(11>$A41,0,Val_pt*(Ceiling_e-E_zero)*(1-(1-Half_gap)^MIN(11,$B41))) -> 0 | N41: =IF(12>$A41,0,Val_pt*(Ceiling_e-E_zero)*(1-(1-Half_gap)^MIN(12,$B41))) -> 0 | O41: =IF(13>$A41,0,Val_pt*(Ceiling_e-E_zero)*(1-(1-Half_gap)^MIN(13,$B41))) -> 0 | P41: =IF(14>$A41,0,Val_pt*(Ceiling_e-E_zero)*(1-(1-Half_gap)^MIN(14,$B41))) -> 0 | Q41: =IF(15>$A41,0,Val_pt*(Ceiling_e-E_zero)*(1-(1-Half_gap)^MIN(15,$B41))) -> 0 | R41: =IF(16>$A41,0,Val_pt*(Ceiling_e-E_zero)*(1-(1-Half_gap)^MIN(16,$B41))) -> 0 | S41: =IF(17>$A41,0,Val_pt*(Ceiling_e-E_zero)*(1-(1-Half_gap)^MIN(17,$B41))) -> 0 | T41: =IF(18>$A41,0,Val_pt*(Ceiling_e-E_zero)*(1-(1-Half_gap)^MIN(18,$B41))) -> 0 | U41: =IF(19>$A41,0,Val_pt*(Ceiling_e-E_zero)*(1-(1-Half_gap)^MIN(19,$B41))) -> 0 | V41: =IF(20>$A41,0,Val_pt*(Ceiling_e-E_zero)*(1-(1-Half_gap)^MIN(20,$B41))) -> 0 | W41: =IF(0>$A41,0,IF(0=$A41,MAX(End_q,Floor_q),MAX(X41+Cost_round*IF(1<=$B41,1,0)-C41,IF(1<=$B41,1,0)*Pre_q))) -> 520 | X41: =IF(1>$A41,0,IF(1=$A41,MAX(End_q,Floor_q),MAX(Y41+Cost_round*IF(2<=$B41,1,0)-D41,IF(2<=$B41,1,0)*Pre_q,Floor_q))) -> 470 | Y41: =IF(2>$A41,0,IF(2=$A41,MAX(End_q,Floor_q),MAX(Z41+Cost_round*IF(3<=$B41,1,0)-E41,IF(3<=$B41,1,0)*Pre_q,Floor_q))) -> 0 | Z41: =IF(3>$A41,0,IF(3=$A41,MAX(End_q,Floor_q),MAX(AA41+Cost_round*IF(4<=$B41,1,0)-F41,IF(4<=$B41,1,0)*Pre_q,Floor_q))) -> 0 | AA41: =IF(4>$A41,0,IF(4=$A41,MAX(End_q,Floor_q),MAX(AB41+Cost_round*IF(5<=$B41,1,0)-G41,IF(5<=$B41,1,0)*Pre_q,Floor_q))) -> 0 | AB41: =IF(5>$A41,0,IF(5=$A41,MAX(End_q,Floor_q),MAX(AC41+Cost_round*IF(6<=$B41,1,0)-H41,IF(6<=$B41,1,0)*Pre_q,Floor_q))) -> 0 | AC41: =IF(6>$A41,0,IF(6=$A41,MAX(End_q,Floor_q),MAX(AD41+Cost_round*IF(7<=$B41,1,0)-I41,IF(7<=$B41,1,0)*Pre_q,Floor_q))) -> 0 | AD41: =IF(7>$A41,0,IF(7=$A41,MAX(End_q,Floor_q),MAX(AE41+Cost_round*IF(8<=$B41,1,0)-J41,IF(8<=$B41,1,0)*Pre_q,Floor_q))) -> 0 | AE41: =IF(8>$A41,0,IF(8=$A41,MAX(End_q,Floor_q),MAX(AF41+Cost_round*IF(9<=$B41,1,0)-K41,IF(9<=$B41,1,0)*Pre_q,Floor_q))) -> 0 | AF41: =IF(9>$A41,0,IF(9=$A41,MAX(End_q,Floor_q),MAX(AG41+Cost_round*IF(10<=$B41,1,0)-L41,IF(10<=$B41,1,0)*Pre_q,Floor_q))) -> 0 | AG41: =IF(10>$A41,0,IF(10=$A41,MAX(End_q,Floor_q),MAX(AH41+Cost_round*IF(11<=$B41,1,0)-M41,IF(11<=$B41,1,0)*Pre_q,Floor_q))) -> 0 | AH41: =IF(11>$A41,0,IF(11=$A41,MAX(End_q,Floor_q),MAX(AI41+Cost_round*IF(12<=$B41,1,0)-N41,IF(12<=$B41,1,0)*Pre_q,Floor_q))) -> 0 | AI41: =IF(12>$A41,0,IF(12=$A41,MAX(End_q,Floor_q),MAX(AJ41+Cost_round*IF(13<=$B41,1,0)-O41,IF(13<=$B41,1,0)*Pre_q,Floor_q))) -> 0 | AJ41: =IF(13>$A41,0,IF(13=$A41,MAX(End_q,Floor_q),MAX(AK41+Cost_round*IF(14<=$B41,1,0)-P41,IF(14<=$B41,1,0)*Pre_q,Floor_q))) -> 0 | AK41: =IF(14>$A41,0,IF(14=$A41,MAX(End_q,Floor_q),MAX(AL41+Cost_round*IF(15<=$B41,1,0)-Q41,IF(15<=$B41,1,0)*Pre_q,Floor_q))) -> 0 | AL41: =IF(15>$A41,0,IF(15=$A41,MAX(End_q,Floor_q),MAX(AM41+Cost_round*IF(16<=$B41,1,0)-R41,IF(16<=$B41,1,0)*Pre_q,Floor_q))) -> 0 | AM41: =IF(16>$A41,0,IF(16=$A41,MAX(End_q,Floor_q),MAX(AN41+Cost_round*IF(17<=$B41,1,0)-S41,IF(17<=$B41,1,0)*Pre_q,Floor_q))) -> 0 | AN41: =IF(17>$A41,0,IF(17=$A41,MAX(End_q,Floor_q),MAX(AO41+Cost_round*IF(18<=$B41,1,0)-T41,IF(18<=$B41,1,0)*Pre_q,Floor_q))) -> 0 | AO41: =IF(18>$A41,0,IF(18=$A41,MAX(End_q,Floor_q),MAX(AP41+Cost_round*IF(19<=$B41,1,0)-U41,IF(19<=$B41,1,0)*Pre_q,Floor_q))) -> 0 | AP41: =IF(19>$A41,0,IF(19=$A41,MAX(End_q,Floor_q),MAX(AQ41+Cost_round*IF(20<=$B41,1,0)-V41,IF(20<=$B41,1,0)*Pre_q,Floor_q))) -> 0 | AQ41: =IF(20>$A41,0,MAX(End_q,Floor_q)) -> 0 | AR41: =IF(Q_zero>=W41-0.000000001,1,0) -> 1 | AS41: =IF(1>$A41,0,Q_zero-Cost_round*IF(1<=$B41,1,0)+C41-X41) -> 100 | AT41: =IF(2>$A41,0,X41-Cost_round*IF(2<=$B41,1,0)+D41-Y41) -> 0 | AU41: =IF(3>$A41,0,Y41-Cost_round*IF(3<=$B41,1,0)+E41-Z41) -> 0 | AV41: =IF(4>$A41,0,Z41-Cost_round*IF(4<=$B41,1,0)+F41-AA41) -> 0 | AW41: =IF(5>$A41,0,AA41-Cost_round*IF(5<=$B41,1,0)+G41-AB41) -> 0 | AX41: =IF(6>$A41,0,AB41-Cost_round*IF(6<=$B41,1,0)+H41-AC41) -> 0 | AY41: =IF(7>$A41,0,AC41-Cost_round*IF(7<=$B41,1,0)+I41-AD41) -> 0 | AZ41: =IF(8>$A41,0,AD41-Cost_round*IF(8<=$B41,1,0)+J41-AE41) -> 0 | BA41: =IF(9>$A41,0,AE41-Cost_round*IF(9<=$B41,1,0)+K41-AF41) -> 0 | BB41: =IF(10>$A41,0,AF41-Cost_round*IF(10<=$B41,1,0)+L41-AG41) -> 0 | BC41: =IF(11>$A41,0,AG41-Cost_round*IF(11<=$B41,1,0)+M41-AH41) -> 0 | BD41: =IF(12>$A41,0,AH41-Cost_round*IF(12<=$B41,1,0)+N41-AI41) -> 0 | BE41: =IF(13>$A41,0,AI41-Cost_round*IF(13<=$B41,1,0)+O41-AJ41) -> 0 | BF41: =IF(14>$A41,0,AJ41-Cost_round*IF(14<=$B41,1,0)+P41-AK41) -> 0 | BG41: =IF(15>$A41,0,AK41-Cost_round*IF(15<=$B41,1,0)+Q41-AL41) -> 0 | BH41: =IF(16>$A41,0,AL41-Cost_round*IF(16<=$B41,1,0)+R41-AM41) -> 0 | BI41: =IF(17>$A41,0,AM41-Cost_round*IF(17<=$B41,1,0)+S41-AN41) -> 0 | BJ41: =IF(18>$A41,0,AN41-Cost_round*IF(18<=$B41,1,0)+T41-AO41) -> 0 | BK41: =IF(19>$A41,0,AO41-Cost_round*IF(19<=$B41,1,0)+U41-AP41) -> 0 | BL41: =IF(20>$A41,0,AP41-Cost_round*IF(20<=$B41,1,0)+V41-AQ41) -> 0 | BM41: =IF($AR41=1,SUMPRODUCT(AS41:BL41,$AS$38:$BL$38),"") -> 90.909091 | BN41: =IF($AR41=1,BM41+INDEX($AS$38:$BL$38,$A41)*INDEX(C41:V41,$A41)/Hurdle_r,"") -> 727.27273
A42: 2 | B42: 0 | C42: =IF(1>$A42,0,Val_pt*(Ceiling_e-E_zero)*(1-(1-Half_gap)^MIN(1,$B42))) -> 0 | D42: =IF(2>$A42,0,Val_pt*(Ceiling_e-E_zero)*(1-(1-Half_gap)^MIN(2,$B42))) -> 0 | E42: =IF(3>$A42,0,Val_pt*(Ceiling_e-E_zero)*(1-(1-Half_gap)^MIN(3,$B42))) -> 0 | F42: =IF(4>$A42,0,Val_pt*(Ceiling_e-E_zero)*(1-(1-Half_gap)^MIN(4,$B42))) -> 0 | G42: =IF(5>$A42,0,Val_pt*(Ceiling_e-E_zero)*(1-(1-Half_gap)^MIN(5,$B42))) -> 0 | H42: =IF(6>$A42,0,Val_pt*(Ceiling_e-E_zero)*(1-(1-Half_gap)^MIN(6,$B42))) -> 0 | I42: =IF(7>$A42,0,Val_pt*(Ceiling_e-E_zero)*(1-(1-Half_gap)^MIN(7,$B42))) -> 0 | J42: =IF(8>$A42,0,Val_pt*(Ceiling_e-E_zero)*(1-(1-Half_gap)^MIN(8,$B42))) -> 0 | K42: =IF(9>$A42,0,Val_pt*(Ceiling_e-E_zero)*(1-(1-Half_gap)^MIN(9,$B42))) -> 0 | L42: =IF(10>$A42,0,Val_pt*(Ceiling_e-E_zero)*(1-(1-Half_gap)^MIN(10,$B42))) -> 0 | M42: =IF(11>$A42,0,Val_pt*(Ceiling_e-E_zero)*(1-(1-Half_gap)^MIN(11,$B42))) -> 0 | N42: =IF(12>$A42,0,Val_pt*(Ceiling_e-E_zero)*(1-(1-Half_gap)^MIN(12,$B42))) -> 0 | O42: =IF(13>$A42,0,Val_pt*(Ceiling_e-E_zero)*(1-(1-Half_gap)^MIN(13,$B42))) -> 0 | P42: =IF(14>$A42,0,Val_pt*(Ceiling_e-E_zero)*(1-(1-Half_gap)^MIN(14,$B42))) -> 0 | Q42: =IF(15>$A42,0,Val_pt*(Ceiling_e-E_zero)*(1-(1-Half_gap)^MIN(15,$B42))) -> 0 | R42: =IF(16>$A42,0,Val_pt*(Ceiling_e-E_zero)*(1-(1-Half_gap)^MIN(16,$B42))) -> 0 | S42: =IF(17>$A42,0,Val_pt*(Ceiling_e-E_zero)*(1-(1-Half_gap)^MIN(17,$B42))) -> 0 | T42: =IF(18>$A42,0,Val_pt*(Ceiling_e-E_zero)*(1-(1-Half_gap)^MIN(18,$B42))) -> 0 | U42: =IF(19>$A42,0,Val_pt*(Ceiling_e-E_zero)*(1-(1-Half_gap)^MIN(19,$B42))) -> 0 | V42: =IF(20>$A42,0,Val_pt*(Ceiling_e-E_zero)*(1-(1-Half_gap)^MIN(20,$B42))) -> 0 | W42: =IF(0>$A42,0,IF(0=$A42,MAX(End_q,Floor_q),MAX(X42+Cost_round*IF(1<=$B42,1,0)-C42,IF(1<=$B42,1,0)*Pre_q))) -> 470 | X42: =IF(1>$A42,0,IF(1=$A42,MAX(End_q,Floor_q),MAX(Y42+Cost_round*IF(2<=$B42,1,0)-D42,IF(2<=$B42,1,0)*Pre_q,Floor_q))) -> 470 | Y42: =IF(2>$A42,0,IF(2=$A42,MAX(End_q,Floor_q),MAX(Z42+Cost_round*IF(3<=$B42,1,0)-E42,IF(3<=$B42,1,0)*Pre_q,Floor_q))) -> 470 | Z42: =IF(3>$A42,0,IF(3=$A42,MAX(End_q,Floor_q),MAX(AA42+Cost_round*IF(4<=$B42,1,0)-F42,IF(4<=$B42,1,0)*Pre_q,Floor_q))) -> 0 | AA42: =IF(4>$A42,0,IF(4=$A42,MAX(End_q,Floor_q),MAX(AB42+Cost_round*IF(5<=$B42,1,0)-G42,IF(5<=$B42,1,0)*Pre_q,Floor_q))) -> 0 | AB42: =IF(5>$A42,0,IF(5=$A42,MAX(End_q,Floor_q),MAX(AC42+Cost_round*IF(6<=$B42,1,0)-H42,IF(6<=$B42,1,0)*Pre_q,Floor_q))) -> 0 | AC42: =IF(6>$A42,0,IF(6=$A42,MAX(End_q,Floor_q),MAX(AD42+Cost_round*IF(7<=$B42,1,0)-I42,IF(7<=$B42,1,0)*Pre_q,Floor_q))) -> 0 | AD42: =IF(7>$A42,0,IF(7=$A42,MAX(End_q,Floor_q),MAX(AE42+Cost_round*IF(8<=$B42,1,0)-J42,IF(8<=$B42,1,0)*Pre_q,Floor_q))) -> 0 | AE42: =IF(8>$A42,0,IF(8=$A42,MAX(End_q,Floor_q),MAX(AF42+Cost_round*IF(9<=$B42,1,0)-K42,IF(9<=$B42,1,0)*Pre_q,Floor_q))) -> 0 | AF42: =IF(9>$A42,0,IF(9=$A42,MAX(End_q,Floor_q),MAX(AG42+Cost_round*IF(10<=$B42,1,0)-L42,IF(10<=$B42,1,0)*Pre_q,Floor_q))) -> 0 | AG42: =IF(10>$A42,0,IF(10=$A42,MAX(End_q,Floor_q),MAX(AH42+Cost_round*IF(11<=$B42,1,0)-M42,IF(11<=$B42,1,0)*Pre_q,Floor_q))) -> 0 | AH42: =IF(11>$A42,0,IF(11=$A42,MAX(End_q,Floor_q),MAX(AI42+Cost_round*IF(12<=$B42,1,0)-N42,IF(12<=$B42,1,0)*Pre_q,Floor_q))) -> 0 | AI42: =IF(12>$A42,0,IF(12=$A42,MAX(End_q,Floor_q),MAX(AJ42+Cost_round*IF(13<=$B42,1,0)-O42,IF(13<=$B42,1,0)*Pre_q,Floor_q))) -> 0 | AJ42: =IF(13>$A42,0,IF(13=$A42,MAX(End_q,Floor_q),MAX(AK42+Cost_round*IF(14<=$B42,1,0)-P42,IF(14<=$B42,1,0)*Pre_q,Floor_q))) -> 0 | AK42: =IF(14>$A42,0,IF(14=$A42,MAX(End_q,Floor_q),MAX(AL42+Cost_round*IF(15<=$B42,1,0)-Q42,IF(15<=$B42,1,0)*Pre_q,Floor_q))) -> 0 | AL42: =IF(15>$A42,0,IF(15=$A42,MAX(End_q,Floor_q),MAX(AM42+Cost_round*IF(16<=$B42,1,0)-R42,IF(16<=$B42,1,0)*Pre_q,Floor_q))) -> 0 | AM42: =IF(16>$A42,0,IF(16=$A42,MAX(End_q,Floor_q),MAX(AN42+Cost_round*IF(17<=$B42,1,0)-S42,IF(17<=$B42,1,0)*Pre_q,Floor_q))) -> 0 | AN42: =IF(17>$A42,0,IF(17=$A42,MAX(End_q,Floor_q),MAX(AO42+Cost_round*IF(18<=$B42,1,0)-T42,IF(18<=$B42,1,0)*Pre_q,Floor_q))) -> 0 | AO42: =IF(18>$A42,0,IF(18=$A42,MAX(End_q,Floor_q),MAX(AP42+Cost_round*IF(19<=$B42,1,0)-U42,IF(19<=$B42,1,0)*Pre_q,Floor_q))) -> 0 | AP42: =IF(19>$A42,0,IF(19=$A42,MAX(End_q,Floor_q),MAX(AQ42+Cost_round*IF(20<=$B42,1,0)-V42,IF(20<=$B42,1,0)*Pre_q,Floor_q))) -> 0 | AQ42: =IF(20>$A42,0,MAX(End_q,Floor_q)) -> 0 | AR42: =IF(Q_zero>=W42-0.000000001,1,0) -> 1 | AS42: =IF(1>$A42,0,Q_zero-Cost_round*IF(1<=$B42,1,0)+C42-X42) -> 150 | AT42: =IF(2>$A42,0,X42-Cost_round*IF(2<=$B42,1,0)+D42-Y42) -> 0 | AU42: =IF(3>$A42,0,Y42-Cost_round*IF(3<=$B42,1,0)+E42-Z42) -> 0 | AV42: =IF(4>$A42,0,Z42-Cost_round*IF(4<=$B42,1,0)+F42-AA42) -> 0 | AW42: =IF(5>$A42,0,AA42-Cost_round*IF(5<=$B42,1,0)+G42-AB42) -> 0 | AX42: =IF(6>$A42,0,AB42-Cost_round*IF(6<=$B42,1,0)+H42-AC42) -> 0 | AY42: =IF(7>$A42,0,AC42-Cost_round*IF(7<=$B42,1,0)+I42-AD42) -> 0 | AZ42: =IF(8>$A42,0,AD42-Cost_round*IF(8<=$B42,1,0)+J42-AE42) -> 0 | BA42: =IF(9>$A42,0,AE42-Cost_round*IF(9<=$B42,1,0)+K42-AF42) -> 0 | BB42: =IF(10>$A42,0,AF42-Cost_round*IF(10<=$B42,1,0)+L42-AG42) -> 0 | BC42: =IF(11>$A42,0,AG42-Cost_round*IF(11<=$B42,1,0)+M42-AH42) -> 0 | BD42: =IF(12>$A42,0,AH42-Cost_round*IF(12<=$B42,1,0)+N42-AI42) -> 0 | BE42: =IF(13>$A42,0,AI42-Cost_round*IF(13<=$B42,1,0)+O42-AJ42) -> 0 | BF42: =IF(14>$A42,0,AJ42-Cost_round*IF(14<=$B42,1,0)+P42-AK42) -> 0 | BG42: =IF(15>$A42,0,AK42-Cost_round*IF(15<=$B42,1,0)+Q42-AL42) -> 0 | BH42: =IF(16>$A42,0,AL42-Cost_round*IF(16<=$B42,1,0)+R42-AM42) -> 0 | BI42: =IF(17>$A42,0,AM42-Cost_round*IF(17<=$B42,1,0)+S42-AN42) -> 0 | BJ42: =IF(18>$A42,0,AN42-Cost_round*IF(18<=$B42,1,0)+T42-AO42) -> 0 | BK42: =IF(19>$A42,0,AO42-Cost_round*IF(19<=$B42,1,0)+U42-AP42) -> 0 | BL42: =IF(20>$A42,0,AP42-Cost_round*IF(20<=$B42,1,0)+V42-AQ42) -> 0 | BM42: =IF($AR42=1,SUMPRODUCT(AS42:BL42,$AS$38:$BL$38),"") -> 136.36364 | BN42: =IF($AR42=1,BM42+INDEX($AS$38:$BL$38,$A42)*INDEX(C42:V42,$A42)/Hurdle_r,"") -> 136.36364
A43: 2 | B43: 1 | C43: =IF(1>$A43,0,Val_pt*(Ceiling_e-E_zero)*(1-(1-Half_gap)^MIN(1,$B43))) -> 70 | D43: =IF(2>$A43,0,Val_pt*(Ceiling_e-E_zero)*(1-(1-Half_gap)^MIN(2,$B43))) -> 70 | E43: =IF(3>$A43,0,Val_pt*(Ceiling_e-E_zero)*(1-(1-Half_gap)^MIN(3,$B43))) -> 0 | F43: =IF(4>$A43,0,Val_pt*(Ceiling_e-E_zero)*(1-(1-Half_gap)^MIN(4,$B43))) -> 0 | G43: =IF(5>$A43,0,Val_pt*(Ceiling_e-E_zero)*(1-(1-Half_gap)^MIN(5,$B43))) -> 0 | H43: =IF(6>$A43,0,Val_pt*(Ceiling_e-E_zero)*(1-(1-Half_gap)^MIN(6,$B43))) -> 0 | I43: =IF(7>$A43,0,Val_pt*(Ceiling_e-E_zero)*(1-(1-Half_gap)^MIN(7,$B43))) -> 0 | J43: =IF(8>$A43,0,Val_pt*(Ceiling_e-E_zero)*(1-(1-Half_gap)^MIN(8,$B43))) -> 0 | K43: =IF(9>$A43,0,Val_pt*(Ceiling_e-E_zero)*(1-(1-Half_gap)^MIN(9,$B43))) -> 0 | L43: =IF(10>$A43,0,Val_pt*(Ceiling_e-E_zero)*(1-(1-Half_gap)^MIN(10,$B43))) -> 0 | M43: =IF(11>$A43,0,Val_pt*(Ceiling_e-E_zero)*(1-(1-Half_gap)^MIN(11,$B43))) -> 0 | N43: =IF(12>$A43,0,Val_pt*(Ceiling_e-E_zero)*(1-(1-Half_gap)^MIN(12,$B43))) -> 0 | O43: =IF(13>$A43,0,Val_pt*(Ceiling_e-E_zero)*(1-(1-Half_gap)^MIN(13,$B43))) -> 0 | P43: =IF(14>$A43,0,Val_pt*(Ceiling_e-E_zero)*(1-(1-Half_gap)^MIN(14,$B43))) -> 0 | Q43: =IF(15>$A43,0,Val_pt*(Ceiling_e-E_zero)*(1-(1-Half_gap)^MIN(15,$B43))) -> 0 | R43: =IF(16>$A43,0,Val_pt*(Ceiling_e-E_zero)*(1-(1-Half_gap)^MIN(16,$B43))) -> 0 | S43: =IF(17>$A43,0,Val_pt*(Ceiling_e-E_zero)*(1-(1-Half_gap)^MIN(17,$B43))) -> 0 | T43: =IF(18>$A43,0,Val_pt*(Ceiling_e-E_zero)*(1-(1-Half_gap)^MIN(18,$B43))) -> 0 | U43: =IF(19>$A43,0,Val_pt*(Ceiling_e-E_zero)*(1-(1-Half_gap)^MIN(19,$B43))) -> 0 | V43: =IF(20>$A43,0,Val_pt*(Ceiling_e-E_zero)*(1-(1-Half_gap)^MIN(20,$B43))) -> 0 | W43: =IF(0>$A43,0,IF(0=$A43,MAX(End_q,Floor_q),MAX(X43+Cost_round*IF(1<=$B43,1,0)-C43,IF(1<=$B43,1,0)*Pre_q))) -> 470 | X43: =IF(1>$A43,0,IF(1=$A43,MAX(End_q,Floor_q),MAX(Y43+Cost_round*IF(2<=$B43,1,0)-D43,IF(2<=$B43,1,0)*Pre_q,Floor_q))) -> 400 | Y43: =IF(2>$A43,0,IF(2=$A43,MAX(End_q,Floor_q),MAX(Z43+Cost_round*IF(3<=$B43,1,0)-E43,IF(3<=$B43,1,0)*Pre_q,Floor_q))) -> 470 | Z43: =IF(3>$A43,0,IF(3=$A43,MAX(End_q,Floor_q),MAX(AA43+Cost_round*IF(4<=$B43,1,0)-F43,IF(4<=$B43,1,0)*Pre_q,Floor_q))) -> 0 | AA43: =IF(4>$A43,0,IF(4=$A43,MAX(End_q,Floor_q),MAX(AB43+Cost_round*IF(5<=$B43,1,0)-G43,IF(5<=$B43,1,0)*Pre_q,Floor_q))) -> 0 | AB43: =IF(5>$A43,0,IF(5=$A43,MAX(End_q,Floor_q),MAX(AC43+Cost_round*IF(6<=$B43,1,0)-H43,IF(6<=$B43,1,0)*Pre_q,Floor_q))) -> 0 | AC43: =IF(6>$A43,0,IF(6=$A43,MAX(End_q,Floor_q),MAX(AD43+Cost_round*IF(7<=$B43,1,0)-I43,IF(7<=$B43,1,0)*Pre_q,Floor_q))) -> 0 | AD43: =IF(7>$A43,0,IF(7=$A43,MAX(End_q,Floor_q),MAX(AE43+Cost_round*IF(8<=$B43,1,0)-J43,IF(8<=$B43,1,0)*Pre_q,Floor_q))) -> 0 | AE43: =IF(8>$A43,0,IF(8=$A43,MAX(End_q,Floor_q),MAX(AF43+Cost_round*IF(9<=$B43,1,0)-K43,IF(9<=$B43,1,0)*Pre_q,Floor_q))) -> 0 | AF43: =IF(9>$A43,0,IF(9=$A43,MAX(End_q,Floor_q),MAX(AG43+Cost_round*IF(10<=$B43,1,0)-L43,IF(10<=$B43,1,0)*Pre_q,Floor_q))) -> 0 | AG43: =IF(10>$A43,0,IF(10=$A43,MAX(End_q,Floor_q),MAX(AH43+Cost_round*IF(11<=$B43,1,0)-M43,IF(11<=$B43,1,0)*Pre_q,Floor_q))) -> 0 | AH43: =IF(11>$A43,0,IF(11=$A43,MAX(End_q,Floor_q),MAX(AI43+Cost_round*IF(12<=$B43,1,0)-N43,IF(12<=$B43,1,0)*Pre_q,Floor_q))) -> 0 | AI43: =IF(12>$A43,0,IF(12=$A43,MAX(End_q,Floor_q),MAX(AJ43+Cost_round*IF(13<=$B43,1,0)-O43,IF(13<=$B43,1,0)*Pre_q,Floor_q))) -> 0 | AJ43: =IF(13>$A43,0,IF(13=$A43,MAX(End_q,Floor_q),MAX(AK43+Cost_round*IF(14<=$B43,1,0)-P43,IF(14<=$B43,1,0)*Pre_q,Floor_q))) -> 0 | AK43: =IF(14>$A43,0,IF(14=$A43,MAX(End_q,Floor_q),MAX(AL43+Cost_round*IF(15<=$B43,1,0)-Q43,IF(15<=$B43,1,0)*Pre_q,Floor_q))) -> 0 | AL43: =IF(15>$A43,0,IF(15=$A43,MAX(End_q,Floor_q),MAX(AM43+Cost_round*IF(16<=$B43,1,0)-R43,IF(16<=$B43,1,0)*Pre_q,Floor_q))) -> 0 | AM43: =IF(16>$A43,0,IF(16=$A43,MAX(End_q,Floor_q),MAX(AN43+Cost_round*IF(17<=$B43,1,0)-S43,IF(17<=$B43,1,0)*Pre_q,Floor_q))) -> 0 | AN43: =IF(17>$A43,0,IF(17=$A43,MAX(End_q,Floor_q),MAX(AO43+Cost_round*IF(18<=$B43,1,0)-T43,IF(18<=$B43,1,0)*Pre_q,Floor_q))) -> 0 | AO43: =IF(18>$A43,0,IF(18=$A43,MAX(End_q,Floor_q),MAX(AP43+Cost_round*IF(19<=$B43,1,0)-U43,IF(19<=$B43,1,0)*Pre_q,Floor_q))) -> 0 | AP43: =IF(19>$A43,0,IF(19=$A43,MAX(End_q,Floor_q),MAX(AQ43+Cost_round*IF(20<=$B43,1,0)-V43,IF(20<=$B43,1,0)*Pre_q,Floor_q))) -> 0 | AQ43: =IF(20>$A43,0,MAX(End_q,Floor_q)) -> 0 | AR43: =IF(Q_zero>=W43-0.000000001,1,0) -> 1 | AS43: =IF(1>$A43,0,Q_zero-Cost_round*IF(1<=$B43,1,0)+C43-X43) -> 170 | AT43: =IF(2>$A43,0,X43-Cost_round*IF(2<=$B43,1,0)+D43-Y43) -> 0 | AU43: =IF(3>$A43,0,Y43-Cost_round*IF(3<=$B43,1,0)+E43-Z43) -> 0 | AV43: =IF(4>$A43,0,Z43-Cost_round*IF(4<=$B43,1,0)+F43-AA43) -> 0 | AW43: =IF(5>$A43,0,AA43-Cost_round*IF(5<=$B43,1,0)+G43-AB43) -> 0 | AX43: =IF(6>$A43,0,AB43-Cost_round*IF(6<=$B43,1,0)+H43-AC43) -> 0 | AY43: =IF(7>$A43,0,AC43-Cost_round*IF(7<=$B43,1,0)+I43-AD43) -> 0 | AZ43: =IF(8>$A43,0,AD43-Cost_round*IF(8<=$B43,1,0)+J43-AE43) -> 0 | BA43: =IF(9>$A43,0,AE43-Cost_round*IF(9<=$B43,1,0)+K43-AF43) -> 0 | BB43: =IF(10>$A43,0,AF43-Cost_round*IF(10<=$B43,1,0)+L43-AG43) -> 0 | BC43: =IF(11>$A43,0,AG43-Cost_round*IF(11<=$B43,1,0)+M43-AH43) -> 0 | BD43: =IF(12>$A43,0,AH43-Cost_round*IF(12<=$B43,1,0)+N43-AI43) -> 0 | BE43: =IF(13>$A43,0,AI43-Cost_round*IF(13<=$B43,1,0)+O43-AJ43) -> 0 | BF43: =IF(14>$A43,0,AJ43-Cost_round*IF(14<=$B43,1,0)+P43-AK43) -> 0 | BG43: =IF(15>$A43,0,AK43-Cost_round*IF(15<=$B43,1,0)+Q43-AL43) -> 0 | BH43: =IF(16>$A43,0,AL43-Cost_round*IF(16<=$B43,1,0)+R43-AM43) -> 0 | BI43: =IF(17>$A43,0,AM43-Cost_round*IF(17<=$B43,1,0)+S43-AN43) -> 0 | BJ43: =IF(18>$A43,0,AN43-Cost_round*IF(18<=$B43,1,0)+T43-AO43) -> 0 | BK43: =IF(19>$A43,0,AO43-Cost_round*IF(19<=$B43,1,0)+U43-AP43) -> 0 | BL43: =IF(20>$A43,0,AP43-Cost_round*IF(20<=$B43,1,0)+V43-AQ43) -> 0 | BM43: =IF($AR43=1,SUMPRODUCT(AS43:BL43,$AS$38:$BL$38),"") -> 154.54545 | BN43: =IF($AR43=1,BM43+INDEX($AS$38:$BL$38,$A43)*INDEX(C43:V43,$A43)/Hurdle_r,"") -> 733.05785
A44: 2 | B44: 2 | C44: =IF(1>$A44,0,Val_pt*(Ceiling_e-E_zero)*(1-(1-Half_gap)^MIN(1,$B44))) -> 70 | D44: =IF(2>$A44,0,Val_pt*(Ceiling_e-E_zero)*(1-(1-Half_gap)^MIN(2,$B44))) -> 105 | E44: =IF(3>$A44,0,Val_pt*(Ceiling_e-E_zero)*(1-(1-Half_gap)^MIN(3,$B44))) -> 0 | F44: =IF(4>$A44,0,Val_pt*(Ceiling_e-E_zero)*(1-(1-Half_gap)^MIN(4,$B44))) -> 0 | G44: =IF(5>$A44,0,Val_pt*(Ceiling_e-E_zero)*(1-(1-Half_gap)^MIN(5,$B44))) -> 0 | H44: =IF(6>$A44,0,Val_pt*(Ceiling_e-E_zero)*(1-(1-Half_gap)^MIN(6,$B44))) -> 0 | I44: =IF(7>$A44,0,Val_pt*(Ceiling_e-E_zero)*(1-(1-Half_gap)^MIN(7,$B44))) -> 0 | J44: =IF(8>$A44,0,Val_pt*(Ceiling_e-E_zero)*(1-(1-Half_gap)^MIN(8,$B44))) -> 0 | K44: =IF(9>$A44,0,Val_pt*(Ceiling_e-E_zero)*(1-(1-Half_gap)^MIN(9,$B44))) -> 0 | L44: =IF(10>$A44,0,Val_pt*(Ceiling_e-E_zero)*(1-(1-Half_gap)^MIN(10,$B44))) -> 0 | M44: =IF(11>$A44,0,Val_pt*(Ceiling_e-E_zero)*(1-(1-Half_gap)^MIN(11,$B44))) -> 0 | N44: =IF(12>$A44,0,Val_pt*(Ceiling_e-E_zero)*(1-(1-Half_gap)^MIN(12,$B44))) -> 0 | O44: =IF(13>$A44,0,Val_pt*(Ceiling_e-E_zero)*(1-(1-Half_gap)^MIN(13,$B44))) -> 0 | P44: =IF(14>$A44,0,Val_pt*(Ceiling_e-E_zero)*(1-(1-Half_gap)^MIN(14,$B44))) -> 0 | Q44: =IF(15>$A44,0,Val_pt*(Ceiling_e-E_zero)*(1-(1-Half_gap)^MIN(15,$B44))) -> 0 | R44: =IF(16>$A44,0,Val_pt*(Ceiling_e-E_zero)*(1-(1-Half_gap)^MIN(16,$B44))) -> 0 | S44: =IF(17>$A44,0,Val_pt*(Ceiling_e-E_zero)*(1-(1-Half_gap)^MIN(17,$B44))) -> 0 | T44: =IF(18>$A44,0,Val_pt*(Ceiling_e-E_zero)*(1-(1-Half_gap)^MIN(18,$B44))) -> 0 | U44: =IF(19>$A44,0,Val_pt*(Ceiling_e-E_zero)*(1-(1-Half_gap)^MIN(19,$B44))) -> 0 | V44: =IF(20>$A44,0,Val_pt*(Ceiling_e-E_zero)*(1-(1-Half_gap)^MIN(20,$B44))) -> 0 | W44: =IF(0>$A44,0,IF(0=$A44,MAX(End_q,Floor_q),MAX(X44+Cost_round*IF(1<=$B44,1,0)-C44,IF(1<=$B44,1,0)*Pre_q))) -> 535 | X44: =IF(1>$A44,0,IF(1=$A44,MAX(End_q,Floor_q),MAX(Y44+Cost_round*IF(2<=$B44,1,0)-D44,IF(2<=$B44,1,0)*Pre_q,Floor_q))) -> 485 | Y44: =IF(2>$A44,0,IF(2=$A44,MAX(End_q,Floor_q),MAX(Z44+Cost_round*IF(3<=$B44,1,0)-E44,IF(3<=$B44,1,0)*Pre_q,Floor_q))) -> 470 | Z44: =IF(3>$A44,0,IF(3=$A44,MAX(End_q,Floor_q),MAX(AA44+Cost_round*IF(4<=$B44,1,0)-F44,IF(4<=$B44,1,0)*Pre_q,Floor_q))) -> 0 | AA44: =IF(4>$A44,0,IF(4=$A44,MAX(End_q,Floor_q),MAX(AB44+Cost_round*IF(5<=$B44,1,0)-G44,IF(5<=$B44,1,0)*Pre_q,Floor_q))) -> 0 | AB44: =IF(5>$A44,0,IF(5=$A44,MAX(End_q,Floor_q),MAX(AC44+Cost_round*IF(6<=$B44,1,0)-H44,IF(6<=$B44,1,0)*Pre_q,Floor_q))) -> 0 | AC44: =IF(6>$A44,0,IF(6=$A44,MAX(End_q,Floor_q),MAX(AD44+Cost_round*IF(7<=$B44,1,0)-I44,IF(7<=$B44,1,0)*Pre_q,Floor_q))) -> 0 | AD44: =IF(7>$A44,0,IF(7=$A44,MAX(End_q,Floor_q),MAX(AE44+Cost_round*IF(8<=$B44,1,0)-J44,IF(8<=$B44,1,0)*Pre_q,Floor_q))) -> 0 | AE44: =IF(8>$A44,0,IF(8=$A44,MAX(End_q,Floor_q),MAX(AF44+Cost_round*IF(9<=$B44,1,0)-K44,IF(9<=$B44,1,0)*Pre_q,Floor_q))) -> 0 | AF44: =IF(9>$A44,0,IF(9=$A44,MAX(End_q,Floor_q),MAX(AG44+Cost_round*IF(10<=$B44,1,0)-L44,IF(10<=$B44,1,0)*Pre_q,Floor_q))) -> 0 | AG44: =IF(10>$A44,0,IF(10=$A44,MAX(End_q,Floor_q),MAX(AH44+Cost_round*IF(11<=$B44,1,0)-M44,IF(11<=$B44,1,0)*Pre_q,Floor_q))) -> 0 | AH44: =IF(11>$A44,0,IF(11=$A44,MAX(End_q,Floor_q),MAX(AI44+Cost_round*IF(12<=$B44,1,0)-N44,IF(12<=$B44,1,0)*Pre_q,Floor_q))) -> 0 | AI44: =IF(12>$A44,0,IF(12=$A44,MAX(End_q,Floor_q),MAX(AJ44+Cost_round*IF(13<=$B44,1,0)-O44,IF(13<=$B44,1,0)*Pre_q,Floor_q))) -> 0 | AJ44: =IF(13>$A44,0,IF(13=$A44,MAX(End_q,Floor_q),MAX(AK44+Cost_round*IF(14<=$B44,1,0)-P44,IF(14<=$B44,1,0)*Pre_q,Floor_q))) -> 0 | AK44: =IF(14>$A44,0,IF(14=$A44,MAX(End_q,Floor_q),MAX(AL44+Cost_round*IF(15<=$B44,1,0)-Q44,IF(15<=$B44,1,0)*Pre_q,Floor_q))) -> 0 | AL44: =IF(15>$A44,0,IF(15=$A44,MAX(End_q,Floor_q),MAX(AM44+Cost_round*IF(16<=$B44,1,0)-R44,IF(16<=$B44,1,0)*Pre_q,Floor_q))) -> 0 | AM44: =IF(16>$A44,0,IF(16=$A44,MAX(End_q,Floor_q),MAX(AN44+Cost_round*IF(17<=$B44,1,0)-S44,IF(17<=$B44,1,0)*Pre_q,Floor_q))) -> 0 | AN44: =IF(17>$A44,0,IF(17=$A44,MAX(End_q,Floor_q),MAX(AO44+Cost_round*IF(18<=$B44,1,0)-T44,IF(18<=$B44,1,0)*Pre_q,Floor_q))) -> 0 | AO44: =IF(18>$A44,0,IF(18=$A44,MAX(End_q,Floor_q),MAX(AP44+Cost_round*IF(19<=$B44,1,0)-U44,IF(19<=$B44,1,0)*Pre_q,Floor_q))) -> 0 | AP44: =IF(19>$A44,0,IF(19=$A44,MAX(End_q,Floor_q),MAX(AQ44+Cost_round*IF(20<=$B44,1,0)-V44,IF(20<=$B44,1,0)*Pre_q,Floor_q))) -> 0 | AQ44: =IF(20>$A44,0,MAX(End_q,Floor_q)) -> 0 | AR44: =IF(Q_zero>=W44-0.000000001,1,0) -> 1 | AS44: =IF(1>$A44,0,Q_zero-Cost_round*IF(1<=$B44,1,0)+C44-X44) -> 85 | AT44: =IF(2>$A44,0,X44-Cost_round*IF(2<=$B44,1,0)+D44-Y44) -> 0 | AU44: =IF(3>$A44,0,Y44-Cost_round*IF(3<=$B44,1,0)+E44-Z44) -> 0 | AV44: =IF(4>$A44,0,Z44-Cost_round*IF(4<=$B44,1,0)+F44-AA44) -> 0 | AW44: =IF(5>$A44,0,AA44-Cost_round*IF(5<=$B44,1,0)+G44-AB44) -> 0 | AX44: =IF(6>$A44,0,AB44-Cost_round*IF(6<=$B44,1,0)+H44-AC44) -> 0 | AY44: =IF(7>$A44,0,AC44-Cost_round*IF(7<=$B44,1,0)+I44-AD44) -> 0 | AZ44: =IF(8>$A44,0,AD44-Cost_round*IF(8<=$B44,1,0)+J44-AE44) -> 0 | BA44: =IF(9>$A44,0,AE44-Cost_round*IF(9<=$B44,1,0)+K44-AF44) -> 0 | BB44: =IF(10>$A44,0,AF44-Cost_round*IF(10<=$B44,1,0)+L44-AG44) -> 0 | BC44: =IF(11>$A44,0,AG44-Cost_round*IF(11<=$B44,1,0)+M44-AH44) -> 0 | BD44: =IF(12>$A44,0,AH44-Cost_round*IF(12<=$B44,1,0)+N44-AI44) -> 0 | BE44: =IF(13>$A44,0,AI44-Cost_round*IF(13<=$B44,1,0)+O44-AJ44) -> 0 | BF44: =IF(14>$A44,0,AJ44-Cost_round*IF(14<=$B44,1,0)+P44-AK44) -> 0 | BG44: =IF(15>$A44,0,AK44-Cost_round*IF(15<=$B44,1,0)+Q44-AL44) -> 0 | BH44: =IF(16>$A44,0,AL44-Cost_round*IF(16<=$B44,1,0)+R44-AM44) -> 0 | BI44: =IF(17>$A44,0,AM44-Cost_round*IF(17<=$B44,1,0)+S44-AN44) -> 0 | BJ44: =IF(18>$A44,0,AN44-Cost_round*IF(18<=$B44,1,0)+T44-AO44) -> 0 | BK44: =IF(19>$A44,0,AO44-Cost_round*IF(19<=$B44,1,0)+U44-AP44) -> 0 | BL44: =IF(20>$A44,0,AP44-Cost_round*IF(20<=$B44,1,0)+V44-AQ44) -> 0 | BM44: =IF($AR44=1,SUMPRODUCT(AS44:BL44,$AS$38:$BL$38),"") -> 77.272727 | BN44: =IF($AR44=1,BM44+INDEX($AS$38:$BL$38,$A44)*INDEX(C44:V44,$A44)/Hurdle_r,"") -> 945.04132
A45: 3 | B45: 0 | C45: =IF(1>$A45,0,Val_pt*(Ceiling_e-E_zero)*(1-(1-Half_gap)^MIN(1,$B45))) -> 0 | D45: =IF(2>$A45,0,Val_pt*(Ceiling_e-E_zero)*(1-(1-Half_gap)^MIN(2,$B45))) -> 0 | E45: =IF(3>$A45,0,Val_pt*(Ceiling_e-E_zero)*(1-(1-Half_gap)^MIN(3,$B45))) -> 0 | F45: =IF(4>$A45,0,Val_pt*(Ceiling_e-E_zero)*(1-(1-Half_gap)^MIN(4,$B45))) -> 0 | G45: =IF(5>$A45,0,Val_pt*(Ceiling_e-E_zero)*(1-(1-Half_gap)^MIN(5,$B45))) -> 0 | H45: =IF(6>$A45,0,Val_pt*(Ceiling_e-E_zero)*(1-(1-Half_gap)^MIN(6,$B45))) -> 0 | I45: =IF(7>$A45,0,Val_pt*(Ceiling_e-E_zero)*(1-(1-Half_gap)^MIN(7,$B45))) -> 0 | J45: =IF(8>$A45,0,Val_pt*(Ceiling_e-E_zero)*(1-(1-Half_gap)^MIN(8,$B45))) -> 0 | K45: =IF(9>$A45,0,Val_pt*(Ceiling_e-E_zero)*(1-(1-Half_gap)^MIN(9,$B45))) -> 0 | L45: =IF(10>$A45,0,Val_pt*(Ceiling_e-E_zero)*(1-(1-Half_gap)^MIN(10,$B45))) -> 0 | M45: =IF(11>$A45,0,Val_pt*(Ceiling_e-E_zero)*(1-(1-Half_gap)^MIN(11,$B45))) -> 0 | N45: =IF(12>$A45,0,Val_pt*(Ceiling_e-E_zero)*(1-(1-Half_gap)^MIN(12,$B45))) -> 0 | O45: =IF(13>$A45,0,Val_pt*(Ceiling_e-E_zero)*(1-(1-Half_gap)^MIN(13,$B45))) -> 0 | P45: =IF(14>$A45,0,Val_pt*(Ceiling_e-E_zero)*(1-(1-Half_gap)^MIN(14,$B45))) -> 0 | Q45: =IF(15>$A45,0,Val_pt*(Ceiling_e-E_zero)*(1-(1-Half_gap)^MIN(15,$B45))) -> 0 | R45: =IF(16>$A45,0,Val_pt*(Ceiling_e-E_zero)*(1-(1-Half_gap)^MIN(16,$B45))) -> 0 | S45: =IF(17>$A45,0,Val_pt*(Ceiling_e-E_zero)*(1-(1-Half_gap)^MIN(17,$B45))) -> 0 | T45: =IF(18>$A45,0,Val_pt*(Ceiling_e-E_zero)*(1-(1-Half_gap)^MIN(18,$B45))) -> 0 | U45: =IF(19>$A45,0,Val_pt*(Ceiling_e-E_zero)*(1-(1-Half_gap)^MIN(19,$B45))) -> 0 | V45: =IF(20>$A45,0,Val_pt*(Ceiling_e-E_zero)*(1-(1-Half_gap)^MIN(20,$B45))) -> 0 | W45: =IF(0>$A45,0,IF(0=$A45,MAX(End_q,Floor_q),MAX(X45+Cost_round*IF(1<=$B45,1,0)-C45,IF(1<=$B45,1,0)*Pre_q))) -> 470 | X45: =IF(1>$A45,0,IF(1=$A45,MAX(End_q,Floor_q),MAX(Y45+Cost_round*IF(2<=$B45,1,0)-D45,IF(2<=$B45,1,0)*Pre_q,Floor_q))) -> 470 | Y45: =IF(2>$A45,0,IF(2=$A45,MAX(End_q,Floor_q),MAX(Z45+Cost_round*IF(3<=$B45,1,0)-E45,IF(3<=$B45,1,0)*Pre_q,Floor_q))) -> 470 | Z45: =IF(3>$A45,0,IF(3=$A45,MAX(End_q,Floor_q),MAX(AA45+Cost_round*IF(4<=$B45,1,0)-F45,IF(4<=$B45,1,0)*Pre_q,Floor_q))) -> 470 | AA45: =IF(4>$A45,0,IF(4=$A45,MAX(End_q,Floor_q),MAX(AB45+Cost_round*IF(5<=$B45,1,0)-G45,IF(5<=$B45,1,0)*Pre_q,Floor_q))) -> 0 | AB45: =IF(5>$A45,0,IF(5=$A45,MAX(End_q,Floor_q),MAX(AC45+Cost_round*IF(6<=$B45,1,0)-H45,IF(6<=$B45,1,0)*Pre_q,Floor_q))) -> 0 | AC45: =IF(6>$A45,0,IF(6=$A45,MAX(End_q,Floor_q),MAX(AD45+Cost_round*IF(7<=$B45,1,0)-I45,IF(7<=$B45,1,0)*Pre_q,Floor_q))) -> 0 | AD45: =IF(7>$A45,0,IF(7=$A45,MAX(End_q,Floor_q),MAX(AE45+Cost_round*IF(8<=$B45,1,0)-J45,IF(8<=$B45,1,0)*Pre_q,Floor_q))) -> 0 | AE45: =IF(8>$A45,0,IF(8=$A45,MAX(End_q,Floor_q),MAX(AF45+Cost_round*IF(9<=$B45,1,0)-K45,IF(9<=$B45,1,0)*Pre_q,Floor_q))) -> 0 | AF45: =IF(9>$A45,0,IF(9=$A45,MAX(End_q,Floor_q),MAX(AG45+Cost_round*IF(10<=$B45,1,0)-L45,IF(10<=$B45,1,0)*Pre_q,Floor_q))) -> 0 | AG45: =IF(10>$A45,0,IF(10=$A45,MAX(End_q,Floor_q),MAX(AH45+Cost_round*IF(11<=$B45,1,0)-M45,IF(11<=$B45,1,0)*Pre_q,Floor_q))) -> 0 | AH45: =IF(11>$A45,0,IF(11=$A45,MAX(End_q,Floor_q),MAX(AI45+Cost_round*IF(12<=$B45,1,0)-N45,IF(12<=$B45,1,0)*Pre_q,Floor_q))) -> 0 | AI45: =IF(12>$A45,0,IF(12=$A45,MAX(End_q,Floor_q),MAX(AJ45+Cost_round*IF(13<=$B45,1,0)-O45,IF(13<=$B45,1,0)*Pre_q,Floor_q))) -> 0 | AJ45: =IF(13>$A45,0,IF(13=$A45,MAX(End_q,Floor_q),MAX(AK45+Cost_round*IF(14<=$B45,1,0)-P45,IF(14<=$B45,1,0)*Pre_q,Floor_q))) -> 0 | AK45: =IF(14>$A45,0,IF(14=$A45,MAX(End_q,Floor_q),MAX(AL45+Cost_round*IF(15<=$B45,1,0)-Q45,IF(15<=$B45,1,0)*Pre_q,Floor_q))) -> 0 | AL45: =IF(15>$A45,0,IF(15=$A45,MAX(End_q,Floor_q),MAX(AM45+Cost_round*IF(16<=$B45,1,0)-R45,IF(16<=$B45,1,0)*Pre_q,Floor_q))) -> 0 | AM45: =IF(16>$A45,0,IF(16=$A45,MAX(End_q,Floor_q),MAX(AN45+Cost_round*IF(17<=$B45,1,0)-S45,IF(17<=$B45,1,0)*Pre_q,Floor_q))) -> 0 | AN45: =IF(17>$A45,0,IF(17=$A45,MAX(End_q,Floor_q),MAX(AO45+Cost_round*IF(18<=$B45,1,0)-T45,IF(18<=$B45,1,0)*Pre_q,Floor_q))) -> 0 | AO45: =IF(18>$A45,0,IF(18=$A45,MAX(End_q,Floor_q),MAX(AP45+Cost_round*IF(19<=$B45,1,0)-U45,IF(19<=$B45,1,0)*Pre_q,Floor_q))) -> 0 | AP45: =IF(19>$A45,0,IF(19=$A45,MAX(End_q,Floor_q),MAX(AQ45+Cost_round*IF(20<=$B45,1,0)-V45,IF(20<=$B45,1,0)*Pre_q,Floor_q))) -> 0 | AQ45: =IF(20>$A45,0,MAX(End_q,Floor_q)) -> 0 | AR45: =IF(Q_zero>=W45-0.000000001,1,0) -> 1 | AS45: =IF(1>$A45,0,Q_zero-Cost_round*IF(1<=$B45,1,0)+C45-X45) -> 150 | AT45: =IF(2>$A45,0,X45-Cost_round*IF(2<=$B45,1,0)+D45-Y45) -> 0 | AU45: =IF(3>$A45,0,Y45-Cost_round*IF(3<=$B45,1,0)+E45-Z45) -> 0 | AV45: =IF(4>$A45,0,Z45-Cost_round*IF(4<=$B45,1,0)+F45-AA45) -> 0 | AW45: =IF(5>$A45,0,AA45-Cost_round*IF(5<=$B45,1,0)+G45-AB45) -> 0 | AX45: =IF(6>$A45,0,AB45-Cost_round*IF(6<=$B45,1,0)+H45-AC45) -> 0 | AY45: =IF(7>$A45,0,AC45-Cost_round*IF(7<=$B45,1,0)+I45-AD45) -> 0 | AZ45: =IF(8>$A45,0,AD45-Cost_round*IF(8<=$B45,1,0)+J45-AE45) -> 0 | BA45: =IF(9>$A45,0,AE45-Cost_round*IF(9<=$B45,1,0)+K45-AF45) -> 0 | BB45: =IF(10>$A45,0,AF45-Cost_round*IF(10<=$B45,1,0)+L45-AG45) -> 0 | BC45: =IF(11>$A45,0,AG45-Cost_round*IF(11<=$B45,1,0)+M45-AH45) -> 0 | BD45: =IF(12>$A45,0,AH45-Cost_round*IF(12<=$B45,1,0)+N45-AI45) -> 0 | BE45: =IF(13>$A45,0,AI45-Cost_round*IF(13<=$B45,1,0)+O45-AJ45) -> 0 | BF45: =IF(14>$A45,0,AJ45-Cost_round*IF(14<=$B45,1,0)+P45-AK45) -> 0 | BG45: =IF(15>$A45,0,AK45-Cost_round*IF(15<=$B45,1,0)+Q45-AL45) -> 0 | BH45: =IF(16>$A45,0,AL45-Cost_round*IF(16<=$B45,1,0)+R45-AM45) -> 0 | BI45: =IF(17>$A45,0,AM45-Cost_round*IF(17<=$B45,1,0)+S45-AN45) -> 0 | BJ45: =IF(18>$A45,0,AN45-Cost_round*IF(18<=$B45,1,0)+T45-AO45) -> 0 | BK45: =IF(19>$A45,0,AO45-Cost_round*IF(19<=$B45,1,0)+U45-AP45) -> 0 | BL45: =IF(20>$A45,0,AP45-Cost_round*IF(20<=$B45,1,0)+V45-AQ45) -> 0 | BM45: =IF($AR45=1,SUMPRODUCT(AS45:BL45,$AS$38:$BL$38),"") -> 136.36364 | BN45: =IF($AR45=1,BM45+INDEX($AS$38:$BL$38,$A45)*INDEX(C45:V45,$A45)/Hurdle_r,"") -> 136.36364
A46: 3 | B46: 1 | C46: =IF(1>$A46,0,Val_pt*(Ceiling_e-E_zero)*(1-(1-Half_gap)^MIN(1,$B46))) -> 70 | D46: =IF(2>$A46,0,Val_pt*(Ceiling_e-E_zero)*(1-(1-Half_gap)^MIN(2,$B46))) -> 70 | E46: =IF(3>$A46,0,Val_pt*(Ceiling_e-E_zero)*(1-(1-Half_gap)^MIN(3,$B46))) -> 70 | F46: =IF(4>$A46,0,Val_pt*(Ceiling_e-E_zero)*(1-(1-Half_gap)^MIN(4,$B46))) -> 0 | G46: =IF(5>$A46,0,Val_pt*(Ceiling_e-E_zero)*(1-(1-Half_gap)^MIN(5,$B46))) -> 0 | H46: =IF(6>$A46,0,Val_pt*(Ceiling_e-E_zero)*(1-(1-Half_gap)^MIN(6,$B46))) -> 0 | I46: =IF(7>$A46,0,Val_pt*(Ceiling_e-E_zero)*(1-(1-Half_gap)^MIN(7,$B46))) -> 0 | J46: =IF(8>$A46,0,Val_pt*(Ceiling_e-E_zero)*(1-(1-Half_gap)^MIN(8,$B46))) -> 0 | K46: =IF(9>$A46,0,Val_pt*(Ceiling_e-E_zero)*(1-(1-Half_gap)^MIN(9,$B46))) -> 0 | L46: =IF(10>$A46,0,Val_pt*(Ceiling_e-E_zero)*(1-(1-Half_gap)^MIN(10,$B46))) -> 0 | M46: =IF(11>$A46,0,Val_pt*(Ceiling_e-E_zero)*(1-(1-Half_gap)^MIN(11,$B46))) -> 0 | N46: =IF(12>$A46,0,Val_pt*(Ceiling_e-E_zero)*(1-(1-Half_gap)^MIN(12,$B46))) -> 0 | O46: =IF(13>$A46,0,Val_pt*(Ceiling_e-E_zero)*(1-(1-Half_gap)^MIN(13,$B46))) -> 0 | P46: =IF(14>$A46,0,Val_pt*(Ceiling_e-E_zero)*(1-(1-Half_gap)^MIN(14,$B46))) -> 0 | Q46: =IF(15>$A46,0,Val_pt*(Ceiling_e-E_zero)*(1-(1-Half_gap)^MIN(15,$B46))) -> 0 | R46: =IF(16>$A46,0,Val_pt*(Ceiling_e-E_zero)*(1-(1-Half_gap)^MIN(16,$B46))) -> 0 | S46: =IF(17>$A46,0,Val_pt*(Ceiling_e-E_zero)*(1-(1-Half_gap)^MIN(17,$B46))) -> 0 | T46: =IF(18>$A46,0,Val_pt*(Ceiling_e-E_zero)*(1-(1-Half_gap)^MIN(18,$B46))) -> 0 | U46: =IF(19>$A46,0,Val_pt*(Ceiling_e-E_zero)*(1-(1-Half_gap)^MIN(19,$B46))) -> 0 | V46: =IF(20>$A46,0,Val_pt*(Ceiling_e-E_zero)*(1-(1-Half_gap)^MIN(20,$B46))) -> 0 | W46: =IF(0>$A46,0,IF(0=$A46,MAX(End_q,Floor_q),MAX(X46+Cost_round*IF(1<=$B46,1,0)-C46,IF(1<=$B46,1,0)*Pre_q))) -> 470 | X46: =IF(1>$A46,0,IF(1=$A46,MAX(End_q,Floor_q),MAX(Y46+Cost_round*IF(2<=$B46,1,0)-D46,IF(2<=$B46,1,0)*Pre_q,Floor_q))) -> 350 | Y46: =IF(2>$A46,0,IF(2=$A46,MAX(End_q,Floor_q),MAX(Z46+Cost_round*IF(3<=$B46,1,0)-E46,IF(3<=$B46,1,0)*Pre_q,Floor_q))) -> 400 | Z46: =IF(3>$A46,0,IF(3=$A46,MAX(End_q,Floor_q),MAX(AA46+Cost_round*IF(4<=$B46,1,0)-F46,IF(4<=$B46,1,0)*Pre_q,Floor_q))) -> 470 | AA46: =IF(4>$A46,0,IF(4=$A46,MAX(End_q,Floor_q),MAX(AB46+Cost_round*IF(5<=$B46,1,0)-G46,IF(5<=$B46,1,0)*Pre_q,Floor_q))) -> 0 | AB46: =IF(5>$A46,0,IF(5=$A46,MAX(End_q,Floor_q),MAX(AC46+Cost_round*IF(6<=$B46,1,0)-H46,IF(6<=$B46,1,0)*Pre_q,Floor_q))) -> 0 | AC46: =IF(6>$A46,0,IF(6=$A46,MAX(End_q,Floor_q),MAX(AD46+Cost_round*IF(7<=$B46,1,0)-I46,IF(7<=$B46,1,0)*Pre_q,Floor_q))) -> 0 | AD46: =IF(7>$A46,0,IF(7=$A46,MAX(End_q,Floor_q),MAX(AE46+Cost_round*IF(8<=$B46,1,0)-J46,IF(8<=$B46,1,0)*Pre_q,Floor_q))) -> 0 | AE46: =IF(8>$A46,0,IF(8=$A46,MAX(End_q,Floor_q),MAX(AF46+Cost_round*IF(9<=$B46,1,0)-K46,IF(9<=$B46,1,0)*Pre_q,Floor_q))) -> 0 | AF46: =IF(9>$A46,0,IF(9=$A46,MAX(End_q,Floor_q),MAX(AG46+Cost_round*IF(10<=$B46,1,0)-L46,IF(10<=$B46,1,0)*Pre_q,Floor_q))) -> 0 | AG46: =IF(10>$A46,0,IF(10=$A46,MAX(End_q,Floor_q),MAX(AH46+Cost_round*IF(11<=$B46,1,0)-M46,IF(11<=$B46,1,0)*Pre_q,Floor_q))) -> 0 | AH46: =IF(11>$A46,0,IF(11=$A46,MAX(End_q,Floor_q),MAX(AI46+Cost_round*IF(12<=$B46,1,0)-N46,IF(12<=$B46,1,0)*Pre_q,Floor_q))) -> 0 | AI46: =IF(12>$A46,0,IF(12=$A46,MAX(End_q,Floor_q),MAX(AJ46+Cost_round*IF(13<=$B46,1,0)-O46,IF(13<=$B46,1,0)*Pre_q,Floor_q))) -> 0 | AJ46: =IF(13>$A46,0,IF(13=$A46,MAX(End_q,Floor_q),MAX(AK46+Cost_round*IF(14<=$B46,1,0)-P46,IF(14<=$B46,1,0)*Pre_q,Floor_q))) -> 0 | AK46: =IF(14>$A46,0,IF(14=$A46,MAX(End_q,Floor_q),MAX(AL46+Cost_round*IF(15<=$B46,1,0)-Q46,IF(15<=$B46,1,0)*Pre_q,Floor_q))) -> 0 | AL46: =IF(15>$A46,0,IF(15=$A46,MAX(End_q,Floor_q),MAX(AM46+Cost_round*IF(16<=$B46,1,0)-R46,IF(16<=$B46,1,0)*Pre_q,Floor_q))) -> 0 | AM46: =IF(16>$A46,0,IF(16=$A46,MAX(End_q,Floor_q),MAX(AN46+Cost_round*IF(17<=$B46,1,0)-S46,IF(17<=$B46,1,0)*Pre_q,Floor_q))) -> 0 | AN46: =IF(17>$A46,0,IF(17=$A46,MAX(End_q,Floor_q),MAX(AO46+Cost_round*IF(18<=$B46,1,0)-T46,IF(18<=$B46,1,0)*Pre_q,Floor_q))) -> 0 | AO46: =IF(18>$A46,0,IF(18=$A46,MAX(End_q,Floor_q),MAX(AP46+Cost_round*IF(19<=$B46,1,0)-U46,IF(19<=$B46,1,0)*Pre_q,Floor_q))) -> 0 | AP46: =IF(19>$A46,0,IF(19=$A46,MAX(End_q,Floor_q),MAX(AQ46+Cost_round*IF(20<=$B46,1,0)-V46,IF(20<=$B46,1,0)*Pre_q,Floor_q))) -> 0 | AQ46: =IF(20>$A46,0,MAX(End_q,Floor_q)) -> 0 | AR46: =IF(Q_zero>=W46-0.000000001,1,0) -> 1 | AS46: =IF(1>$A46,0,Q_zero-Cost_round*IF(1<=$B46,1,0)+C46-X46) -> 220 | AT46: =IF(2>$A46,0,X46-Cost_round*IF(2<=$B46,1,0)+D46-Y46) -> 20 | AU46: =IF(3>$A46,0,Y46-Cost_round*IF(3<=$B46,1,0)+E46-Z46) -> 0 | AV46: =IF(4>$A46,0,Z46-Cost_round*IF(4<=$B46,1,0)+F46-AA46) -> 0 | AW46: =IF(5>$A46,0,AA46-Cost_round*IF(5<=$B46,1,0)+G46-AB46) -> 0 | AX46: =IF(6>$A46,0,AB46-Cost_round*IF(6<=$B46,1,0)+H46-AC46) -> 0 | AY46: =IF(7>$A46,0,AC46-Cost_round*IF(7<=$B46,1,0)+I46-AD46) -> 0 | AZ46: =IF(8>$A46,0,AD46-Cost_round*IF(8<=$B46,1,0)+J46-AE46) -> 0 | BA46: =IF(9>$A46,0,AE46-Cost_round*IF(9<=$B46,1,0)+K46-AF46) -> 0 | BB46: =IF(10>$A46,0,AF46-Cost_round*IF(10<=$B46,1,0)+L46-AG46) -> 0 | BC46: =IF(11>$A46,0,AG46-Cost_round*IF(11<=$B46,1,0)+M46-AH46) -> 0 | BD46: =IF(12>$A46,0,AH46-Cost_round*IF(12<=$B46,1,0)+N46-AI46) -> 0 | BE46: =IF(13>$A46,0,AI46-Cost_round*IF(13<=$B46,1,0)+O46-AJ46) -> 0 | BF46: =IF(14>$A46,0,AJ46-Cost_round*IF(14<=$B46,1,0)+P46-AK46) -> 0 | BG46: =IF(15>$A46,0,AK46-Cost_round*IF(15<=$B46,1,0)+Q46-AL46) -> 0 | BH46: =IF(16>$A46,0,AL46-Cost_round*IF(16<=$B46,1,0)+R46-AM46) -> 0 | BI46: =IF(17>$A46,0,AM46-Cost_round*IF(17<=$B46,1,0)+S46-AN46) -> 0 | BJ46: =IF(18>$A46,0,AN46-Cost_round*IF(18<=$B46,1,0)+T46-AO46) -> 0 | BK46: =IF(19>$A46,0,AO46-Cost_round*IF(19<=$B46,1,0)+U46-AP46) -> 0 | BL46: =IF(20>$A46,0,AP46-Cost_round*IF(20<=$B46,1,0)+V46-AQ46) -> 0 | BM46: =IF($AR46=1,SUMPRODUCT(AS46:BL46,$AS$38:$BL$38),"") -> 216.52893 | BN46: =IF($AR46=1,BM46+INDEX($AS$38:$BL$38,$A46)*INDEX(C46:V46,$A46)/Hurdle_r,"") -> 742.44929
A47: 3 | B47: 2 | C47: =IF(1>$A47,0,Val_pt*(Ceiling_e-E_zero)*(1-(1-Half_gap)^MIN(1,$B47))) -> 70 | D47: =IF(2>$A47,0,Val_pt*(Ceiling_e-E_zero)*(1-(1-Half_gap)^MIN(2,$B47))) -> 105 | E47: =IF(3>$A47,0,Val_pt*(Ceiling_e-E_zero)*(1-(1-Half_gap)^MIN(3,$B47))) -> 105 | F47: =IF(4>$A47,0,Val_pt*(Ceiling_e-E_zero)*(1-(1-Half_gap)^MIN(4,$B47))) -> 0 | G47: =IF(5>$A47,0,Val_pt*(Ceiling_e-E_zero)*(1-(1-Half_gap)^MIN(5,$B47))) -> 0 | H47: =IF(6>$A47,0,Val_pt*(Ceiling_e-E_zero)*(1-(1-Half_gap)^MIN(6,$B47))) -> 0 | I47: =IF(7>$A47,0,Val_pt*(Ceiling_e-E_zero)*(1-(1-Half_gap)^MIN(7,$B47))) -> 0 | J47: =IF(8>$A47,0,Val_pt*(Ceiling_e-E_zero)*(1-(1-Half_gap)^MIN(8,$B47))) -> 0 | K47: =IF(9>$A47,0,Val_pt*(Ceiling_e-E_zero)*(1-(1-Half_gap)^MIN(9,$B47))) -> 0 | L47: =IF(10>$A47,0,Val_pt*(Ceiling_e-E_zero)*(1-(1-Half_gap)^MIN(10,$B47))) -> 0 | M47: =IF(11>$A47,0,Val_pt*(Ceiling_e-E_zero)*(1-(1-Half_gap)^MIN(11,$B47))) -> 0 | N47: =IF(12>$A47,0,Val_pt*(Ceiling_e-E_zero)*(1-(1-Half_gap)^MIN(12,$B47))) -> 0 | O47: =IF(13>$A47,0,Val_pt*(Ceiling_e-E_zero)*(1-(1-Half_gap)^MIN(13,$B47))) -> 0 | P47: =IF(14>$A47,0,Val_pt*(Ceiling_e-E_zero)*(1-(1-Half_gap)^MIN(14,$B47))) -> 0 | Q47: =IF(15>$A47,0,Val_pt*(Ceiling_e-E_zero)*(1-(1-Half_gap)^MIN(15,$B47))) -> 0 | R47: =IF(16>$A47,0,Val_pt*(Ceiling_e-E_zero)*(1-(1-Half_gap)^MIN(16,$B47))) -> 0 | S47: =IF(17>$A47,0,Val_pt*(Ceiling_e-E_zero)*(1-(1-Half_gap)^MIN(17,$B47))) -> 0 | T47: =IF(18>$A47,0,Val_pt*(Ceiling_e-E_zero)*(1-(1-Half_gap)^MIN(18,$B47))) -> 0 | U47: =IF(19>$A47,0,Val_pt*(Ceiling_e-E_zero)*(1-(1-Half_gap)^MIN(19,$B47))) -> 0 | V47: =IF(20>$A47,0,Val_pt*(Ceiling_e-E_zero)*(1-(1-Half_gap)^MIN(20,$B47))) -> 0 | W47: =IF(0>$A47,0,IF(0=$A47,MAX(End_q,Floor_q),MAX(X47+Cost_round*IF(1<=$B47,1,0)-C47,IF(1<=$B47,1,0)*Pre_q))) -> 520 | X47: =IF(1>$A47,0,IF(1=$A47,MAX(End_q,Floor_q),MAX(Y47+Cost_round*IF(2<=$B47,1,0)-D47,IF(2<=$B47,1,0)*Pre_q,Floor_q))) -> 470 | Y47: =IF(2>$A47,0,IF(2=$A47,MAX(End_q,Floor_q),MAX(Z47+Cost_round*IF(3<=$B47,1,0)-E47,IF(3<=$B47,1,0)*Pre_q,Floor_q))) -> 365 | Z47: =IF(3>$A47,0,IF(3=$A47,MAX(End_q,Floor_q),MAX(AA47+Cost_round*IF(4<=$B47,1,0)-F47,IF(4<=$B47,1,0)*Pre_q,Floor_q))) -> 470 | AA47: =IF(4>$A47,0,IF(4=$A47,MAX(End_q,Floor_q),MAX(AB47+Cost_round*IF(5<=$B47,1,0)-G47,IF(5<=$B47,1,0)*Pre_q,Floor_q))) -> 0 | AB47: =IF(5>$A47,0,IF(5=$A47,MAX(End_q,Floor_q),MAX(AC47+Cost_round*IF(6<=$B47,1,0)-H47,IF(6<=$B47,1,0)*Pre_q,Floor_q))) -> 0 | AC47: =IF(6>$A47,0,IF(6=$A47,MAX(End_q,Floor_q),MAX(AD47+Cost_round*IF(7<=$B47,1,0)-I47,IF(7<=$B47,1,0)*Pre_q,Floor_q))) -> 0 | AD47: =IF(7>$A47,0,IF(7=$A47,MAX(End_q,Floor_q),MAX(AE47+Cost_round*IF(8<=$B47,1,0)-J47,IF(8<=$B47,1,0)*Pre_q,Floor_q))) -> 0 | AE47: =IF(8>$A47,0,IF(8=$A47,MAX(End_q,Floor_q),MAX(AF47+Cost_round*IF(9<=$B47,1,0)-K47,IF(9<=$B47,1,0)*Pre_q,Floor_q))) -> 0 | AF47: =IF(9>$A47,0,IF(9=$A47,MAX(End_q,Floor_q),MAX(AG47+Cost_round*IF(10<=$B47,1,0)-L47,IF(10<=$B47,1,0)*Pre_q,Floor_q))) -> 0 | AG47: =IF(10>$A47,0,IF(10=$A47,MAX(End_q,Floor_q),MAX(AH47+Cost_round*IF(11<=$B47,1,0)-M47,IF(11<=$B47,1,0)*Pre_q,Floor_q))) -> 0 | AH47: =IF(11>$A47,0,IF(11=$A47,MAX(End_q,Floor_q),MAX(AI47+Cost_round*IF(12<=$B47,1,0)-N47,IF(12<=$B47,1,0)*Pre_q,Floor_q))) -> 0 | AI47: =IF(12>$A47,0,IF(12=$A47,MAX(End_q,Floor_q),MAX(AJ47+Cost_round*IF(13<=$B47,1,0)-O47,IF(13<=$B47,1,0)*Pre_q,Floor_q))) -> 0 | AJ47: =IF(13>$A47,0,IF(13=$A47,MAX(End_q,Floor_q),MAX(AK47+Cost_round*IF(14<=$B47,1,0)-P47,IF(14<=$B47,1,0)*Pre_q,Floor_q))) -> 0 | AK47: =IF(14>$A47,0,IF(14=$A47,MAX(End_q,Floor_q),MAX(AL47+Cost_round*IF(15<=$B47,1,0)-Q47,IF(15<=$B47,1,0)*Pre_q,Floor_q))) -> 0 | AL47: =IF(15>$A47,0,IF(15=$A47,MAX(End_q,Floor_q),MAX(AM47+Cost_round*IF(16<=$B47,1,0)-R47,IF(16<=$B47,1,0)*Pre_q,Floor_q))) -> 0 | AM47: =IF(16>$A47,0,IF(16=$A47,MAX(End_q,Floor_q),MAX(AN47+Cost_round*IF(17<=$B47,1,0)-S47,IF(17<=$B47,1,0)*Pre_q,Floor_q))) -> 0 | AN47: =IF(17>$A47,0,IF(17=$A47,MAX(End_q,Floor_q),MAX(AO47+Cost_round*IF(18<=$B47,1,0)-T47,IF(18<=$B47,1,0)*Pre_q,Floor_q))) -> 0 | AO47: =IF(18>$A47,0,IF(18=$A47,MAX(End_q,Floor_q),MAX(AP47+Cost_round*IF(19<=$B47,1,0)-U47,IF(19<=$B47,1,0)*Pre_q,Floor_q))) -> 0 | AP47: =IF(19>$A47,0,IF(19=$A47,MAX(End_q,Floor_q),MAX(AQ47+Cost_round*IF(20<=$B47,1,0)-V47,IF(20<=$B47,1,0)*Pre_q,Floor_q))) -> 0 | AQ47: =IF(20>$A47,0,MAX(End_q,Floor_q)) -> 0 | AR47: =IF(Q_zero>=W47-0.000000001,1,0) -> 1 | AS47: =IF(1>$A47,0,Q_zero-Cost_round*IF(1<=$B47,1,0)+C47-X47) -> 100 | AT47: =IF(2>$A47,0,X47-Cost_round*IF(2<=$B47,1,0)+D47-Y47) -> 90 | AU47: =IF(3>$A47,0,Y47-Cost_round*IF(3<=$B47,1,0)+E47-Z47) -> 0 | AV47: =IF(4>$A47,0,Z47-Cost_round*IF(4<=$B47,1,0)+F47-AA47) -> 0 | AW47: =IF(5>$A47,0,AA47-Cost_round*IF(5<=$B47,1,0)+G47-AB47) -> 0 | AX47: =IF(6>$A47,0,AB47-Cost_round*IF(6<=$B47,1,0)+H47-AC47) -> 0 | AY47: =IF(7>$A47,0,AC47-Cost_round*IF(7<=$B47,1,0)+I47-AD47) -> 0 | AZ47: =IF(8>$A47,0,AD47-Cost_round*IF(8<=$B47,1,0)+J47-AE47) -> 0 | BA47: =IF(9>$A47,0,AE47-Cost_round*IF(9<=$B47,1,0)+K47-AF47) -> 0 | BB47: =IF(10>$A47,0,AF47-Cost_round*IF(10<=$B47,1,0)+L47-AG47) -> 0 | BC47: =IF(11>$A47,0,AG47-Cost_round*IF(11<=$B47,1,0)+M47-AH47) -> 0 | BD47: =IF(12>$A47,0,AH47-Cost_round*IF(12<=$B47,1,0)+N47-AI47) -> 0 | BE47: =IF(13>$A47,0,AI47-Cost_round*IF(13<=$B47,1,0)+O47-AJ47) -> 0 | BF47: =IF(14>$A47,0,AJ47-Cost_round*IF(14<=$B47,1,0)+P47-AK47) -> 0 | BG47: =IF(15>$A47,0,AK47-Cost_round*IF(15<=$B47,1,0)+Q47-AL47) -> 0 | BH47: =IF(16>$A47,0,AL47-Cost_round*IF(16<=$B47,1,0)+R47-AM47) -> 0 | BI47: =IF(17>$A47,0,AM47-Cost_round*IF(17<=$B47,1,0)+S47-AN47) -> 0 | BJ47: =IF(18>$A47,0,AN47-Cost_round*IF(18<=$B47,1,0)+T47-AO47) -> 0 | BK47: =IF(19>$A47,0,AO47-Cost_round*IF(19<=$B47,1,0)+U47-AP47) -> 0 | BL47: =IF(20>$A47,0,AP47-Cost_round*IF(20<=$B47,1,0)+V47-AQ47) -> 0 | BM47: =IF($AR47=1,SUMPRODUCT(AS47:BL47,$AS$38:$BL$38),"") -> 165.28926 | BN47: =IF($AR47=1,BM47+INDEX($AS$38:$BL$38,$A47)*INDEX(C47:V47,$A47)/Hurdle_r,"") -> 954.1698
A48: 3 | B48: 3 | C48: =IF(1>$A48,0,Val_pt*(Ceiling_e-E_zero)*(1-(1-Half_gap)^MIN(1,$B48))) -> 70 | D48: =IF(2>$A48,0,Val_pt*(Ceiling_e-E_zero)*(1-(1-Half_gap)^MIN(2,$B48))) -> 105 | E48: =IF(3>$A48,0,Val_pt*(Ceiling_e-E_zero)*(1-(1-Half_gap)^MIN(3,$B48))) -> 122.5 | F48: =IF(4>$A48,0,Val_pt*(Ceiling_e-E_zero)*(1-(1-Half_gap)^MIN(4,$B48))) -> 0 | G48: =IF(5>$A48,0,Val_pt*(Ceiling_e-E_zero)*(1-(1-Half_gap)^MIN(5,$B48))) -> 0 | H48: =IF(6>$A48,0,Val_pt*(Ceiling_e-E_zero)*(1-(1-Half_gap)^MIN(6,$B48))) -> 0 | I48: =IF(7>$A48,0,Val_pt*(Ceiling_e-E_zero)*(1-(1-Half_gap)^MIN(7,$B48))) -> 0 | J48: =IF(8>$A48,0,Val_pt*(Ceiling_e-E_zero)*(1-(1-Half_gap)^MIN(8,$B48))) -> 0 | K48: =IF(9>$A48,0,Val_pt*(Ceiling_e-E_zero)*(1-(1-Half_gap)^MIN(9,$B48))) -> 0 | L48: =IF(10>$A48,0,Val_pt*(Ceiling_e-E_zero)*(1-(1-Half_gap)^MIN(10,$B48))) -> 0 | M48: =IF(11>$A48,0,Val_pt*(Ceiling_e-E_zero)*(1-(1-Half_gap)^MIN(11,$B48))) -> 0 | N48: =IF(12>$A48,0,Val_pt*(Ceiling_e-E_zero)*(1-(1-Half_gap)^MIN(12,$B48))) -> 0 | O48: =IF(13>$A48,0,Val_pt*(Ceiling_e-E_zero)*(1-(1-Half_gap)^MIN(13,$B48))) -> 0 | P48: =IF(14>$A48,0,Val_pt*(Ceiling_e-E_zero)*(1-(1-Half_gap)^MIN(14,$B48))) -> 0 | Q48: =IF(15>$A48,0,Val_pt*(Ceiling_e-E_zero)*(1-(1-Half_gap)^MIN(15,$B48))) -> 0 | R48: =IF(16>$A48,0,Val_pt*(Ceiling_e-E_zero)*(1-(1-Half_gap)^MIN(16,$B48))) -> 0 | S48: =IF(17>$A48,0,Val_pt*(Ceiling_e-E_zero)*(1-(1-Half_gap)^MIN(17,$B48))) -> 0 | T48: =IF(18>$A48,0,Val_pt*(Ceiling_e-E_zero)*(1-(1-Half_gap)^MIN(18,$B48))) -> 0 | U48: =IF(19>$A48,0,Val_pt*(Ceiling_e-E_zero)*(1-(1-Half_gap)^MIN(19,$B48))) -> 0 | V48: =IF(20>$A48,0,Val_pt*(Ceiling_e-E_zero)*(1-(1-Half_gap)^MIN(20,$B48))) -> 0 | W48: =IF(0>$A48,0,IF(0=$A48,MAX(End_q,Floor_q),MAX(X48+Cost_round*IF(1<=$B48,1,0)-C48,IF(1<=$B48,1,0)*Pre_q))) -> 535 | X48: =IF(1>$A48,0,IF(1=$A48,MAX(End_q,Floor_q),MAX(Y48+Cost_round*IF(2<=$B48,1,0)-D48,IF(2<=$B48,1,0)*Pre_q,Floor_q))) -> 485 | Y48: =IF(2>$A48,0,IF(2=$A48,MAX(End_q,Floor_q),MAX(Z48+Cost_round*IF(3<=$B48,1,0)-E48,IF(3<=$B48,1,0)*Pre_q,Floor_q))) -> 470 | Z48: =IF(3>$A48,0,IF(3=$A48,MAX(End_q,Floor_q),MAX(AA48+Cost_round*IF(4<=$B48,1,0)-F48,IF(4<=$B48,1,0)*Pre_q,Floor_q))) -> 470 | AA48: =IF(4>$A48,0,IF(4=$A48,MAX(End_q,Floor_q),MAX(AB48+Cost_round*IF(5<=$B48,1,0)-G48,IF(5<=$B48,1,0)*Pre_q,Floor_q))) -> 0 | AB48: =IF(5>$A48,0,IF(5=$A48,MAX(End_q,Floor_q),MAX(AC48+Cost_round*IF(6<=$B48,1,0)-H48,IF(6<=$B48,1,0)*Pre_q,Floor_q))) -> 0 | AC48: =IF(6>$A48,0,IF(6=$A48,MAX(End_q,Floor_q),MAX(AD48+Cost_round*IF(7<=$B48,1,0)-I48,IF(7<=$B48,1,0)*Pre_q,Floor_q))) -> 0 | AD48: =IF(7>$A48,0,IF(7=$A48,MAX(End_q,Floor_q),MAX(AE48+Cost_round*IF(8<=$B48,1,0)-J48,IF(8<=$B48,1,0)*Pre_q,Floor_q))) -> 0 | AE48: =IF(8>$A48,0,IF(8=$A48,MAX(End_q,Floor_q),MAX(AF48+Cost_round*IF(9<=$B48,1,0)-K48,IF(9<=$B48,1,0)*Pre_q,Floor_q))) -> 0 | AF48: =IF(9>$A48,0,IF(9=$A48,MAX(End_q,Floor_q),MAX(AG48+Cost_round*IF(10<=$B48,1,0)-L48,IF(10<=$B48,1,0)*Pre_q,Floor_q))) -> 0 | AG48: =IF(10>$A48,0,IF(10=$A48,MAX(End_q,Floor_q),MAX(AH48+Cost_round*IF(11<=$B48,1,0)-M48,IF(11<=$B48,1,0)*Pre_q,Floor_q))) -> 0 | AH48: =IF(11>$A48,0,IF(11=$A48,MAX(End_q,Floor_q),MAX(AI48+Cost_round*IF(12<=$B48,1,0)-N48,IF(12<=$B48,1,0)*Pre_q,Floor_q))) -> 0 | AI48: =IF(12>$A48,0,IF(12=$A48,MAX(End_q,Floor_q),MAX(AJ48+Cost_round*IF(13<=$B48,1,0)-O48,IF(13<=$B48,1,0)*Pre_q,Floor_q))) -> 0 | AJ48: =IF(13>$A48,0,IF(13=$A48,MAX(End_q,Floor_q),MAX(AK48+Cost_round*IF(14<=$B48,1,0)-P48,IF(14<=$B48,1,0)*Pre_q,Floor_q))) -> 0 | AK48: =IF(14>$A48,0,IF(14=$A48,MAX(End_q,Floor_q),MAX(AL48+Cost_round*IF(15<=$B48,1,0)-Q48,IF(15<=$B48,1,0)*Pre_q,Floor_q))) -> 0 | AL48: =IF(15>$A48,0,IF(15=$A48,MAX(End_q,Floor_q),MAX(AM48+Cost_round*IF(16<=$B48,1,0)-R48,IF(16<=$B48,1,0)*Pre_q,Floor_q))) -> 0 | AM48: =IF(16>$A48,0,IF(16=$A48,MAX(End_q,Floor_q),MAX(AN48+Cost_round*IF(17<=$B48,1,0)-S48,IF(17<=$B48,1,0)*Pre_q,Floor_q))) -> 0 | AN48: =IF(17>$A48,0,IF(17=$A48,MAX(End_q,Floor_q),MAX(AO48+Cost_round*IF(18<=$B48,1,0)-T48,IF(18<=$B48,1,0)*Pre_q,Floor_q))) -> 0 | AO48: =IF(18>$A48,0,IF(18=$A48,MAX(End_q,Floor_q),MAX(AP48+Cost_round*IF(19<=$B48,1,0)-U48,IF(19<=$B48,1,0)*Pre_q,Floor_q))) -> 0 | AP48: =IF(19>$A48,0,IF(19=$A48,MAX(End_q,Floor_q),MAX(AQ48+Cost_round*IF(20<=$B48,1,0)-V48,IF(20<=$B48,1,0)*Pre_q,Floor_q))) -> 0 | AQ48: =IF(20>$A48,0,MAX(End_q,Floor_q)) -> 0 | AR48: =IF(Q_zero>=W48-0.000000001,1,0) -> 1 | AS48: =IF(1>$A48,0,Q_zero-Cost_round*IF(1<=$B48,1,0)+C48-X48) -> 85 | AT48: =IF(2>$A48,0,X48-Cost_round*IF(2<=$B48,1,0)+D48-Y48) -> 0 | AU48: =IF(3>$A48,0,Y48-Cost_round*IF(3<=$B48,1,0)+E48-Z48) -> 2.5 | AV48: =IF(4>$A48,0,Z48-Cost_round*IF(4<=$B48,1,0)+F48-AA48) -> 0 | AW48: =IF(5>$A48,0,AA48-Cost_round*IF(5<=$B48,1,0)+G48-AB48) -> 0 | AX48: =IF(6>$A48,0,AB48-Cost_round*IF(6<=$B48,1,0)+H48-AC48) -> 0 | AY48: =IF(7>$A48,0,AC48-Cost_round*IF(7<=$B48,1,0)+I48-AD48) -> 0 | AZ48: =IF(8>$A48,0,AD48-Cost_round*IF(8<=$B48,1,0)+J48-AE48) -> 0 | BA48: =IF(9>$A48,0,AE48-Cost_round*IF(9<=$B48,1,0)+K48-AF48) -> 0 | BB48: =IF(10>$A48,0,AF48-Cost_round*IF(10<=$B48,1,0)+L48-AG48) -> 0 | BC48: =IF(11>$A48,0,AG48-Cost_round*IF(11<=$B48,1,0)+M48-AH48) -> 0 | BD48: =IF(12>$A48,0,AH48-Cost_round*IF(12<=$B48,1,0)+N48-AI48) -> 0 | BE48: =IF(13>$A48,0,AI48-Cost_round*IF(13<=$B48,1,0)+O48-AJ48) -> 0 | BF48: =IF(14>$A48,0,AJ48-Cost_round*IF(14<=$B48,1,0)+P48-AK48) -> 0 | BG48: =IF(15>$A48,0,AK48-Cost_round*IF(15<=$B48,1,0)+Q48-AL48) -> 0 | BH48: =IF(16>$A48,0,AL48-Cost_round*IF(16<=$B48,1,0)+R48-AM48) -> 0 | BI48: =IF(17>$A48,0,AM48-Cost_round*IF(17<=$B48,1,0)+S48-AN48) -> 0 | BJ48: =IF(18>$A48,0,AN48-Cost_round*IF(18<=$B48,1,0)+T48-AO48) -> 0 | BK48: =IF(19>$A48,0,AO48-Cost_round*IF(19<=$B48,1,0)+U48-AP48) -> 0 | BL48: =IF(20>$A48,0,AP48-Cost_round*IF(20<=$B48,1,0)+V48-AQ48) -> 0 | BM48: =IF($AR48=1,SUMPRODUCT(AS48:BL48,$AS$38:$BL$38),"") -> 79.151014 | BN48: =IF($AR48=1,BM48+INDEX($AS$38:$BL$38,$A48)*INDEX(C48:V48,$A48)/Hurdle_r,"") -> 999.51165
A49: 4 | B49: 0 | C49: =IF(1>$A49,0,Val_pt*(Ceiling_e-E_zero)*(1-(1-Half_gap)^MIN(1,$B49))) -> 0 | D49: =IF(2>$A49,0,Val_pt*(Ceiling_e-E_zero)*(1-(1-Half_gap)^MIN(2,$B49))) -> 0 | E49: =IF(3>$A49,0,Val_pt*(Ceiling_e-E_zero)*(1-(1-Half_gap)^MIN(3,$B49))) -> 0 | F49: =IF(4>$A49,0,Val_pt*(Ceiling_e-E_zero)*(1-(1-Half_gap)^MIN(4,$B49))) -> 0 | G49: =IF(5>$A49,0,Val_pt*(Ceiling_e-E_zero)*(1-(1-Half_gap)^MIN(5,$B49))) -> 0 | H49: =IF(6>$A49,0,Val_pt*(Ceiling_e-E_zero)*(1-(1-Half_gap)^MIN(6,$B49))) -> 0 | I49: =IF(7>$A49,0,Val_pt*(Ceiling_e-E_zero)*(1-(1-Half_gap)^MIN(7,$B49))) -> 0 | J49: =IF(8>$A49,0,Val_pt*(Ceiling_e-E_zero)*(1-(1-Half_gap)^MIN(8,$B49))) -> 0 | K49: =IF(9>$A49,0,Val_pt*(Ceiling_e-E_zero)*(1-(1-Half_gap)^MIN(9,$B49))) -> 0 | L49: =IF(10>$A49,0,Val_pt*(Ceiling_e-E_zero)*(1-(1-Half_gap)^MIN(10,$B49))) -> 0 | M49: =IF(11>$A49,0,Val_pt*(Ceiling_e-E_zero)*(1-(1-Half_gap)^MIN(11,$B49))) -> 0 | N49: =IF(12>$A49,0,Val_pt*(Ceiling_e-E_zero)*(1-(1-Half_gap)^MIN(12,$B49))) -> 0 | O49: =IF(13>$A49,0,Val_pt*(Ceiling_e-E_zero)*(1-(1-Half_gap)^MIN(13,$B49))) -> 0 | P49: =IF(14>$A49,0,Val_pt*(Ceiling_e-E_zero)*(1-(1-Half_gap)^MIN(14,$B49))) -> 0 | Q49: =IF(15>$A49,0,Val_pt*(Ceiling_e-E_zero)*(1-(1-Half_gap)^MIN(15,$B49))) -> 0 | R49: =IF(16>$A49,0,Val_pt*(Ceiling_e-E_zero)*(1-(1-Half_gap)^MIN(16,$B49))) -> 0 | S49: =IF(17>$A49,0,Val_pt*(Ceiling_e-E_zero)*(1-(1-Half_gap)^MIN(17,$B49))) -> 0 | T49: =IF(18>$A49,0,Val_pt*(Ceiling_e-E_zero)*(1-(1-Half_gap)^MIN(18,$B49))) -> 0 | U49: =IF(19>$A49,0,Val_pt*(Ceiling_e-E_zero)*(1-(1-Half_gap)^MIN(19,$B49))) -> 0 | V49: =IF(20>$A49,0,Val_pt*(Ceiling_e-E_zero)*(1-(1-Half_gap)^MIN(20,$B49))) -> 0 | W49: =IF(0>$A49,0,IF(0=$A49,MAX(End_q,Floor_q),MAX(X49+Cost_round*IF(1<=$B49,1,0)-C49,IF(1<=$B49,1,0)*Pre_q))) -> 470 | X49: =IF(1>$A49,0,IF(1=$A49,MAX(End_q,Floor_q),MAX(Y49+Cost_round*IF(2<=$B49,1,0)-D49,IF(2<=$B49,1,0)*Pre_q,Floor_q))) -> 470 | Y49: =IF(2>$A49,0,IF(2=$A49,MAX(End_q,Floor_q),MAX(Z49+Cost_round*IF(3<=$B49,1,0)-E49,IF(3<=$B49,1,0)*Pre_q,Floor_q))) -> 470 | Z49: =IF(3>$A49,0,IF(3=$A49,MAX(End_q,Floor_q),MAX(AA49+Cost_round*IF(4<=$B49,1,0)-F49,IF(4<=$B49,1,0)*Pre_q,Floor_q))) -> 470 | AA49: =IF(4>$A49,0,IF(4=$A49,MAX(End_q,Floor_q),MAX(AB49+Cost_round*IF(5<=$B49,1,0)-G49,IF(5<=$B49,1,0)*Pre_q,Floor_q))) -> 470 | AB49: =IF(5>$A49,0,IF(5=$A49,MAX(End_q,Floor_q),MAX(AC49+Cost_round*IF(6<=$B49,1,0)-H49,IF(6<=$B49,1,0)*Pre_q,Floor_q))) -> 0 | AC49: =IF(6>$A49,0,IF(6=$A49,MAX(End_q,Floor_q),MAX(AD49+Cost_round*IF(7<=$B49,1,0)-I49,IF(7<=$B49,1,0)*Pre_q,Floor_q))) -> 0 | AD49: =IF(7>$A49,0,IF(7=$A49,MAX(End_q,Floor_q),MAX(AE49+Cost_round*IF(8<=$B49,1,0)-J49,IF(8<=$B49,1,0)*Pre_q,Floor_q))) -> 0 | AE49: =IF(8>$A49,0,IF(8=$A49,MAX(End_q,Floor_q),MAX(AF49+Cost_round*IF(9<=$B49,1,0)-K49,IF(9<=$B49,1,0)*Pre_q,Floor_q))) -> 0 | AF49: =IF(9>$A49,0,IF(9=$A49,MAX(End_q,Floor_q),MAX(AG49+Cost_round*IF(10<=$B49,1,0)-L49,IF(10<=$B49,1,0)*Pre_q,Floor_q))) -> 0 | AG49: =IF(10>$A49,0,IF(10=$A49,MAX(End_q,Floor_q),MAX(AH49+Cost_round*IF(11<=$B49,1,0)-M49,IF(11<=$B49,1,0)*Pre_q,Floor_q))) -> 0 | AH49: =IF(11>$A49,0,IF(11=$A49,MAX(End_q,Floor_q),MAX(AI49+Cost_round*IF(12<=$B49,1,0)-N49,IF(12<=$B49,1,0)*Pre_q,Floor_q))) -> 0 | AI49: =IF(12>$A49,0,IF(12=$A49,MAX(End_q,Floor_q),MAX(AJ49+Cost_round*IF(13<=$B49,1,0)-O49,IF(13<=$B49,1,0)*Pre_q,Floor_q))) -> 0 | AJ49: =IF(13>$A49,0,IF(13=$A49,MAX(End_q,Floor_q),MAX(AK49+Cost_round*IF(14<=$B49,1,0)-P49,IF(14<=$B49,1,0)*Pre_q,Floor_q))) -> 0 | AK49: =IF(14>$A49,0,IF(14=$A49,MAX(End_q,Floor_q),MAX(AL49+Cost_round*IF(15<=$B49,1,0)-Q49,IF(15<=$B49,1,0)*Pre_q,Floor_q))) -> 0 | AL49: =IF(15>$A49,0,IF(15=$A49,MAX(End_q,Floor_q),MAX(AM49+Cost_round*IF(16<=$B49,1,0)-R49,IF(16<=$B49,1,0)*Pre_q,Floor_q))) -> 0 | AM49: =IF(16>$A49,0,IF(16=$A49,MAX(End_q,Floor_q),MAX(AN49+Cost_round*IF(17<=$B49,1,0)-S49,IF(17<=$B49,1,0)*Pre_q,Floor_q))) -> 0 | AN49: =IF(17>$A49,0,IF(17=$A49,MAX(End_q,Floor_q),MAX(AO49+Cost_round*IF(18<=$B49,1,0)-T49,IF(18<=$B49,1,0)*Pre_q,Floor_q))) -> 0 | AO49: =IF(18>$A49,0,IF(18=$A49,MAX(End_q,Floor_q),MAX(AP49+Cost_round*IF(19<=$B49,1,0)-U49,IF(19<=$B49,1,0)*Pre_q,Floor_q))) -> 0 | AP49: =IF(19>$A49,0,IF(19=$A49,MAX(End_q,Floor_q),MAX(AQ49+Cost_round*IF(20<=$B49,1,0)-V49,IF(20<=$B49,1,0)*Pre_q,Floor_q))) -> 0 | AQ49: =IF(20>$A49,0,MAX(End_q,Floor_q)) -> 0 | AR49: =IF(Q_zero>=W49-0.000000001,1,0) -> 1 | AS49: =IF(1>$A49,0,Q_zero-Cost_round*IF(1<=$B49,1,0)+C49-X49) -> 150 | AT49: =IF(2>$A49,0,X49-Cost_round*IF(2<=$B49,1,0)+D49-Y49) -> 0 | AU49: =IF(3>$A49,0,Y49-Cost_round*IF(3<=$B49,1,0)+E49-Z49) -> 0 | AV49: =IF(4>$A49,0,Z49-Cost_round*IF(4<=$B49,1,0)+F49-AA49) -> 0 | AW49: =IF(5>$A49,0,AA49-Cost_round*IF(5<=$B49,1,0)+G49-AB49) -> 0 | AX49: =IF(6>$A49,0,AB49-Cost_round*IF(6<=$B49,1,0)+H49-AC49) -> 0 | AY49: =IF(7>$A49,0,AC49-Cost_round*IF(7<=$B49,1,0)+I49-AD49) -> 0 | AZ49: =IF(8>$A49,0,AD49-Cost_round*IF(8<=$B49,1,0)+J49-AE49) -> 0 | BA49: =IF(9>$A49,0,AE49-Cost_round*IF(9<=$B49,1,0)+K49-AF49) -> 0 | BB49: =IF(10>$A49,0,AF49-Cost_round*IF(10<=$B49,1,0)+L49-AG49) -> 0 | BC49: =IF(11>$A49,0,AG49-Cost_round*IF(11<=$B49,1,0)+M49-AH49) -> 0 | BD49: =IF(12>$A49,0,AH49-Cost_round*IF(12<=$B49,1,0)+N49-AI49) -> 0 | BE49: =IF(13>$A49,0,AI49-Cost_round*IF(13<=$B49,1,0)+O49-AJ49) -> 0 | BF49: =IF(14>$A49,0,AJ49-Cost_round*IF(14<=$B49,1,0)+P49-AK49) -> 0 | BG49: =IF(15>$A49,0,AK49-Cost_round*IF(15<=$B49,1,0)+Q49-AL49) -> 0 | BH49: =IF(16>$A49,0,AL49-Cost_round*IF(16<=$B49,1,0)+R49-AM49) -> 0 | BI49: =IF(17>$A49,0,AM49-Cost_round*IF(17<=$B49,1,0)+S49-AN49) -> 0 | BJ49: =IF(18>$A49,0,AN49-Cost_round*IF(18<=$B49,1,0)+T49-AO49) -> 0 | BK49: =IF(19>$A49,0,AO49-Cost_round*IF(19<=$B49,1,0)+U49-AP49) -> 0 | BL49: =IF(20>$A49,0,AP49-Cost_round*IF(20<=$B49,1,0)+V49-AQ49) -> 0 | BM49: =IF($AR49=1,SUMPRODUCT(AS49:BL49,$AS$38:$BL$38),"") -> 136.36364 | BN49: =IF($AR49=1,BM49+INDEX($AS$38:$BL$38,$A49)*INDEX(C49:V49,$A49)/Hurdle_r,"") -> 136.36364
A50: 4 | B50: 1 | C50: =IF(1>$A50,0,Val_pt*(Ceiling_e-E_zero)*(1-(1-Half_gap)^MIN(1,$B50))) -> 70 | D50: =IF(2>$A50,0,Val_pt*(Ceiling_e-E_zero)*(1-(1-Half_gap)^MIN(2,$B50))) -> 70 | E50: =IF(3>$A50,0,Val_pt*(Ceiling_e-E_zero)*(1-(1-Half_gap)^MIN(3,$B50))) -> 70 | F50: =IF(4>$A50,0,Val_pt*(Ceiling_e-E_zero)*(1-(1-Half_gap)^MIN(4,$B50))) -> 70 | G50: =IF(5>$A50,0,Val_pt*(Ceiling_e-E_zero)*(1-(1-Half_gap)^MIN(5,$B50))) -> 0 | H50: =IF(6>$A50,0,Val_pt*(Ceiling_e-E_zero)*(1-(1-Half_gap)^MIN(6,$B50))) -> 0 | I50: =IF(7>$A50,0,Val_pt*(Ceiling_e-E_zero)*(1-(1-Half_gap)^MIN(7,$B50))) -> 0 | J50: =IF(8>$A50,0,Val_pt*(Ceiling_e-E_zero)*(1-(1-Half_gap)^MIN(8,$B50))) -> 0 | K50: =IF(9>$A50,0,Val_pt*(Ceiling_e-E_zero)*(1-(1-Half_gap)^MIN(9,$B50))) -> 0 | L50: =IF(10>$A50,0,Val_pt*(Ceiling_e-E_zero)*(1-(1-Half_gap)^MIN(10,$B50))) -> 0 | M50: =IF(11>$A50,0,Val_pt*(Ceiling_e-E_zero)*(1-(1-Half_gap)^MIN(11,$B50))) -> 0 | N50: =IF(12>$A50,0,Val_pt*(Ceiling_e-E_zero)*(1-(1-Half_gap)^MIN(12,$B50))) -> 0 | O50: =IF(13>$A50,0,Val_pt*(Ceiling_e-E_zero)*(1-(1-Half_gap)^MIN(13,$B50))) -> 0 | P50: =IF(14>$A50,0,Val_pt*(Ceiling_e-E_zero)*(1-(1-Half_gap)^MIN(14,$B50))) -> 0 | Q50: =IF(15>$A50,0,Val_pt*(Ceiling_e-E_zero)*(1-(1-Half_gap)^MIN(15,$B50))) -> 0 | R50: =IF(16>$A50,0,Val_pt*(Ceiling_e-E_zero)*(1-(1-Half_gap)^MIN(16,$B50))) -> 0 | S50: =IF(17>$A50,0,Val_pt*(Ceiling_e-E_zero)*(1-(1-Half_gap)^MIN(17,$B50))) -> 0 | T50: =IF(18>$A50,0,Val_pt*(Ceiling_e-E_zero)*(1-(1-Half_gap)^MIN(18,$B50))) -> 0 | U50: =IF(19>$A50,0,Val_pt*(Ceiling_e-E_zero)*(1-(1-Half_gap)^MIN(19,$B50))) -> 0 | V50: =IF(20>$A50,0,Val_pt*(Ceiling_e-E_zero)*(1-(1-Half_gap)^MIN(20,$B50))) -> 0 | W50: =IF(0>$A50,0,IF(0=$A50,MAX(End_q,Floor_q),MAX(X50+Cost_round*IF(1<=$B50,1,0)-C50,IF(1<=$B50,1,0)*Pre_q))) -> 470 | X50: =IF(1>$A50,0,IF(1=$A50,MAX(End_q,Floor_q),MAX(Y50+Cost_round*IF(2<=$B50,1,0)-D50,IF(2<=$B50,1,0)*Pre_q,Floor_q))) -> 350 | Y50: =IF(2>$A50,0,IF(2=$A50,MAX(End_q,Floor_q),MAX(Z50+Cost_round*IF(3<=$B50,1,0)-E50,IF(3<=$B50,1,0)*Pre_q,Floor_q))) -> 350 | Z50: =IF(3>$A50,0,IF(3=$A50,MAX(End_q,Floor_q),MAX(AA50+Cost_round*IF(4<=$B50,1,0)-F50,IF(4<=$B50,1,0)*Pre_q,Floor_q))) -> 400 | AA50: =IF(4>$A50,0,IF(4=$A50,MAX(End_q,Floor_q),MAX(AB50+Cost_round*IF(5<=$B50,1,0)-G50,IF(5<=$B50,1,0)*Pre_q,Floor_q))) -> 470 | AB50: =IF(5>$A50,0,IF(5=$A50,MAX(End_q,Floor_q),MAX(AC50+Cost_round*IF(6<=$B50,1,0)-H50,IF(6<=$B50,1,0)*Pre_q,Floor_q))) -> 0 | AC50: =IF(6>$A50,0,IF(6=$A50,MAX(End_q,Floor_q),MAX(AD50+Cost_round*IF(7<=$B50,1,0)-I50,IF(7<=$B50,1,0)*Pre_q,Floor_q))) -> 0 | AD50: =IF(7>$A50,0,IF(7=$A50,MAX(End_q,Floor_q),MAX(AE50+Cost_round*IF(8<=$B50,1,0)-J50,IF(8<=$B50,1,0)*Pre_q,Floor_q))) -> 0 | AE50: =IF(8>$A50,0,IF(8=$A50,MAX(End_q,Floor_q),MAX(AF50+Cost_round*IF(9<=$B50,1,0)-K50,IF(9<=$B50,1,0)*Pre_q,Floor_q))) -> 0 | AF50: =IF(9>$A50,0,IF(9=$A50,MAX(End_q,Floor_q),MAX(AG50+Cost_round*IF(10<=$B50,1,0)-L50,IF(10<=$B50,1,0)*Pre_q,Floor_q))) -> 0 | AG50: =IF(10>$A50,0,IF(10=$A50,MAX(End_q,Floor_q),MAX(AH50+Cost_round*IF(11<=$B50,1,0)-M50,IF(11<=$B50,1,0)*Pre_q,Floor_q))) -> 0 | AH50: =IF(11>$A50,0,IF(11=$A50,MAX(End_q,Floor_q),MAX(AI50+Cost_round*IF(12<=$B50,1,0)-N50,IF(12<=$B50,1,0)*Pre_q,Floor_q))) -> 0 | AI50: =IF(12>$A50,0,IF(12=$A50,MAX(End_q,Floor_q),MAX(AJ50+Cost_round*IF(13<=$B50,1,0)-O50,IF(13<=$B50,1,0)*Pre_q,Floor_q))) -> 0 | AJ50: =IF(13>$A50,0,IF(13=$A50,MAX(End_q,Floor_q),MAX(AK50+Cost_round*IF(14<=$B50,1,0)-P50,IF(14<=$B50,1,0)*Pre_q,Floor_q))) -> 0 | AK50: =IF(14>$A50,0,IF(14=$A50,MAX(End_q,Floor_q),MAX(AL50+Cost_round*IF(15<=$B50,1,0)-Q50,IF(15<=$B50,1,0)*Pre_q,Floor_q))) -> 0 | AL50: =IF(15>$A50,0,IF(15=$A50,MAX(End_q,Floor_q),MAX(AM50+Cost_round*IF(16<=$B50,1,0)-R50,IF(16<=$B50,1,0)*Pre_q,Floor_q))) -> 0 | AM50: =IF(16>$A50,0,IF(16=$A50,MAX(End_q,Floor_q),MAX(AN50+Cost_round*IF(17<=$B50,1,0)-S50,IF(17<=$B50,1,0)*Pre_q,Floor_q))) -> 0 | AN50: =IF(17>$A50,0,IF(17=$A50,MAX(End_q,Floor_q),MAX(AO50+Cost_round*IF(18<=$B50,1,0)-T50,IF(18<=$B50,1,0)*Pre_q,Floor_q))) -> 0 | AO50: =IF(18>$A50,0,IF(18=$A50,MAX(End_q,Floor_q),MAX(AP50+Cost_round*IF(19<=$B50,1,0)-U50,IF(19<=$B50,1,0)*Pre_q,Floor_q))) -> 0 | AP50: =IF(19>$A50,0,IF(19=$A50,MAX(End_q,Floor_q),MAX(AQ50+Cost_round*IF(20<=$B50,1,0)-V50,IF(20<=$B50,1,0)*Pre_q,Floor_q))) -> 0 | AQ50: =IF(20>$A50,0,MAX(End_q,Floor_q)) -> 0 | AR50: =IF(Q_zero>=W50-0.000000001,1,0) -> 1 | AS50: =IF(1>$A50,0,Q_zero-Cost_round*IF(1<=$B50,1,0)+C50-X50) -> 220 | AT50: =IF(2>$A50,0,X50-Cost_round*IF(2<=$B50,1,0)+D50-Y50) -> 70 | AU50: =IF(3>$A50,0,Y50-Cost_round*IF(3<=$B50,1,0)+E50-Z50) -> 20 | AV50: =IF(4>$A50,0,Z50-Cost_round*IF(4<=$B50,1,0)+F50-AA50) -> 0 | AW50: =IF(5>$A50,0,AA50-Cost_round*IF(5<=$B50,1,0)+G50-AB50) -> 0 | AX50: =IF(6>$A50,0,AB50-Cost_round*IF(6<=$B50,1,0)+H50-AC50) -> 0 | AY50: =IF(7>$A50,0,AC50-Cost_round*IF(7<=$B50,1,0)+I50-AD50) -> 0 | AZ50: =IF(8>$A50,0,AD50-Cost_round*IF(8<=$B50,1,0)+J50-AE50) -> 0 | BA50: =IF(9>$A50,0,AE50-Cost_round*IF(9<=$B50,1,0)+K50-AF50) -> 0 | BB50: =IF(10>$A50,0,AF50-Cost_round*IF(10<=$B50,1,0)+L50-AG50) -> 0 | BC50: =IF(11>$A50,0,AG50-Cost_round*IF(11<=$B50,1,0)+M50-AH50) -> 0 | BD50: =IF(12>$A50,0,AH50-Cost_round*IF(12<=$B50,1,0)+N50-AI50) -> 0 | BE50: =IF(13>$A50,0,AI50-Cost_round*IF(13<=$B50,1,0)+O50-AJ50) -> 0 | BF50: =IF(14>$A50,0,AJ50-Cost_round*IF(14<=$B50,1,0)+P50-AK50) -> 0 | BG50: =IF(15>$A50,0,AK50-Cost_round*IF(15<=$B50,1,0)+Q50-AL50) -> 0 | BH50: =IF(16>$A50,0,AL50-Cost_round*IF(16<=$B50,1,0)+R50-AM50) -> 0 | BI50: =IF(17>$A50,0,AM50-Cost_round*IF(17<=$B50,1,0)+S50-AN50) -> 0 | BJ50: =IF(18>$A50,0,AN50-Cost_round*IF(18<=$B50,1,0)+T50-AO50) -> 0 | BK50: =IF(19>$A50,0,AO50-Cost_round*IF(19<=$B50,1,0)+U50-AP50) -> 0 | BL50: =IF(20>$A50,0,AP50-Cost_round*IF(20<=$B50,1,0)+V50-AQ50) -> 0 | BM50: =IF($AR50=1,SUMPRODUCT(AS50:BL50,$AS$38:$BL$38),"") -> 272.87754 | BN50: =IF($AR50=1,BM50+INDEX($AS$38:$BL$38,$A50)*INDEX(C50:V50,$A50)/Hurdle_r,"") -> 750.98695
A51: 4 | B51: 2 | C51: =IF(1>$A51,0,Val_pt*(Ceiling_e-E_zero)*(1-(1-Half_gap)^MIN(1,$B51))) -> 70 | D51: =IF(2>$A51,0,Val_pt*(Ceiling_e-E_zero)*(1-(1-Half_gap)^MIN(2,$B51))) -> 105 | E51: =IF(3>$A51,0,Val_pt*(Ceiling_e-E_zero)*(1-(1-Half_gap)^MIN(3,$B51))) -> 105 | F51: =IF(4>$A51,0,Val_pt*(Ceiling_e-E_zero)*(1-(1-Half_gap)^MIN(4,$B51))) -> 105 | G51: =IF(5>$A51,0,Val_pt*(Ceiling_e-E_zero)*(1-(1-Half_gap)^MIN(5,$B51))) -> 0 | H51: =IF(6>$A51,0,Val_pt*(Ceiling_e-E_zero)*(1-(1-Half_gap)^MIN(6,$B51))) -> 0 | I51: =IF(7>$A51,0,Val_pt*(Ceiling_e-E_zero)*(1-(1-Half_gap)^MIN(7,$B51))) -> 0 | J51: =IF(8>$A51,0,Val_pt*(Ceiling_e-E_zero)*(1-(1-Half_gap)^MIN(8,$B51))) -> 0 | K51: =IF(9>$A51,0,Val_pt*(Ceiling_e-E_zero)*(1-(1-Half_gap)^MIN(9,$B51))) -> 0 | L51: =IF(10>$A51,0,Val_pt*(Ceiling_e-E_zero)*(1-(1-Half_gap)^MIN(10,$B51))) -> 0 | M51: =IF(11>$A51,0,Val_pt*(Ceiling_e-E_zero)*(1-(1-Half_gap)^MIN(11,$B51))) -> 0 | N51: =IF(12>$A51,0,Val_pt*(Ceiling_e-E_zero)*(1-(1-Half_gap)^MIN(12,$B51))) -> 0 | O51: =IF(13>$A51,0,Val_pt*(Ceiling_e-E_zero)*(1-(1-Half_gap)^MIN(13,$B51))) -> 0 | P51: =IF(14>$A51,0,Val_pt*(Ceiling_e-E_zero)*(1-(1-Half_gap)^MIN(14,$B51))) -> 0 | Q51: =IF(15>$A51,0,Val_pt*(Ceiling_e-E_zero)*(1-(1-Half_gap)^MIN(15,$B51))) -> 0 | R51: =IF(16>$A51,0,Val_pt*(Ceiling_e-E_zero)*(1-(1-Half_gap)^MIN(16,$B51))) -> 0 | S51: =IF(17>$A51,0,Val_pt*(Ceiling_e-E_zero)*(1-(1-Half_gap)^MIN(17,$B51))) -> 0 | T51: =IF(18>$A51,0,Val_pt*(Ceiling_e-E_zero)*(1-(1-Half_gap)^MIN(18,$B51))) -> 0 | U51: =IF(19>$A51,0,Val_pt*(Ceiling_e-E_zero)*(1-(1-Half_gap)^MIN(19,$B51))) -> 0 | V51: =IF(20>$A51,0,Val_pt*(Ceiling_e-E_zero)*(1-(1-Half_gap)^MIN(20,$B51))) -> 0 | W51: =IF(0>$A51,0,IF(0=$A51,MAX(End_q,Floor_q),MAX(X51+Cost_round*IF(1<=$B51,1,0)-C51,IF(1<=$B51,1,0)*Pre_q))) -> 520 | X51: =IF(1>$A51,0,IF(1=$A51,MAX(End_q,Floor_q),MAX(Y51+Cost_round*IF(2<=$B51,1,0)-D51,IF(2<=$B51,1,0)*Pre_q,Floor_q))) -> 470 | Y51: =IF(2>$A51,0,IF(2=$A51,MAX(End_q,Floor_q),MAX(Z51+Cost_round*IF(3<=$B51,1,0)-E51,IF(3<=$B51,1,0)*Pre_q,Floor_q))) -> 350 | Z51: =IF(3>$A51,0,IF(3=$A51,MAX(End_q,Floor_q),MAX(AA51+Cost_round*IF(4<=$B51,1,0)-F51,IF(4<=$B51,1,0)*Pre_q,Floor_q))) -> 365 | AA51: =IF(4>$A51,0,IF(4=$A51,MAX(End_q,Floor_q),MAX(AB51+Cost_round*IF(5<=$B51,1,0)-G51,IF(5<=$B51,1,0)*Pre_q,Floor_q))) -> 470 | AB51: =IF(5>$A51,0,IF(5=$A51,MAX(End_q,Floor_q),MAX(AC51+Cost_round*IF(6<=$B51,1,0)-H51,IF(6<=$B51,1,0)*Pre_q,Floor_q))) -> 0 | AC51: =IF(6>$A51,0,IF(6=$A51,MAX(End_q,Floor_q),MAX(AD51+Cost_round*IF(7<=$B51,1,0)-I51,IF(7<=$B51,1,0)*Pre_q,Floor_q))) -> 0 | AD51: =IF(7>$A51,0,IF(7=$A51,MAX(End_q,Floor_q),MAX(AE51+Cost_round*IF(8<=$B51,1,0)-J51,IF(8<=$B51,1,0)*Pre_q,Floor_q))) -> 0 | AE51: =IF(8>$A51,0,IF(8=$A51,MAX(End_q,Floor_q),MAX(AF51+Cost_round*IF(9<=$B51,1,0)-K51,IF(9<=$B51,1,0)*Pre_q,Floor_q))) -> 0 | AF51: =IF(9>$A51,0,IF(9=$A51,MAX(End_q,Floor_q),MAX(AG51+Cost_round*IF(10<=$B51,1,0)-L51,IF(10<=$B51,1,0)*Pre_q,Floor_q))) -> 0 | AG51: =IF(10>$A51,0,IF(10=$A51,MAX(End_q,Floor_q),MAX(AH51+Cost_round*IF(11<=$B51,1,0)-M51,IF(11<=$B51,1,0)*Pre_q,Floor_q))) -> 0 | AH51: =IF(11>$A51,0,IF(11=$A51,MAX(End_q,Floor_q),MAX(AI51+Cost_round*IF(12<=$B51,1,0)-N51,IF(12<=$B51,1,0)*Pre_q,Floor_q))) -> 0 | AI51: =IF(12>$A51,0,IF(12=$A51,MAX(End_q,Floor_q),MAX(AJ51+Cost_round*IF(13<=$B51,1,0)-O51,IF(13<=$B51,1,0)*Pre_q,Floor_q))) -> 0 | AJ51: =IF(13>$A51,0,IF(13=$A51,MAX(End_q,Floor_q),MAX(AK51+Cost_round*IF(14<=$B51,1,0)-P51,IF(14<=$B51,1,0)*Pre_q,Floor_q))) -> 0 | AK51: =IF(14>$A51,0,IF(14=$A51,MAX(End_q,Floor_q),MAX(AL51+Cost_round*IF(15<=$B51,1,0)-Q51,IF(15<=$B51,1,0)*Pre_q,Floor_q))) -> 0 | AL51: =IF(15>$A51,0,IF(15=$A51,MAX(End_q,Floor_q),MAX(AM51+Cost_round*IF(16<=$B51,1,0)-R51,IF(16<=$B51,1,0)*Pre_q,Floor_q))) -> 0 | AM51: =IF(16>$A51,0,IF(16=$A51,MAX(End_q,Floor_q),MAX(AN51+Cost_round*IF(17<=$B51,1,0)-S51,IF(17<=$B51,1,0)*Pre_q,Floor_q))) -> 0 | AN51: =IF(17>$A51,0,IF(17=$A51,MAX(End_q,Floor_q),MAX(AO51+Cost_round*IF(18<=$B51,1,0)-T51,IF(18<=$B51,1,0)*Pre_q,Floor_q))) -> 0 | AO51: =IF(18>$A51,0,IF(18=$A51,MAX(End_q,Floor_q),MAX(AP51+Cost_round*IF(19<=$B51,1,0)-U51,IF(19<=$B51,1,0)*Pre_q,Floor_q))) -> 0 | AP51: =IF(19>$A51,0,IF(19=$A51,MAX(End_q,Floor_q),MAX(AQ51+Cost_round*IF(20<=$B51,1,0)-V51,IF(20<=$B51,1,0)*Pre_q,Floor_q))) -> 0 | AQ51: =IF(20>$A51,0,MAX(End_q,Floor_q)) -> 0 | AR51: =IF(Q_zero>=W51-0.000000001,1,0) -> 1 | AS51: =IF(1>$A51,0,Q_zero-Cost_round*IF(1<=$B51,1,0)+C51-X51) -> 100 | AT51: =IF(2>$A51,0,X51-Cost_round*IF(2<=$B51,1,0)+D51-Y51) -> 105 | AU51: =IF(3>$A51,0,Y51-Cost_round*IF(3<=$B51,1,0)+E51-Z51) -> 90 | AV51: =IF(4>$A51,0,Z51-Cost_round*IF(4<=$B51,1,0)+F51-AA51) -> 0 | AW51: =IF(5>$A51,0,AA51-Cost_round*IF(5<=$B51,1,0)+G51-AB51) -> 0 | AX51: =IF(6>$A51,0,AB51-Cost_round*IF(6<=$B51,1,0)+H51-AC51) -> 0 | AY51: =IF(7>$A51,0,AC51-Cost_round*IF(7<=$B51,1,0)+I51-AD51) -> 0 | AZ51: =IF(8>$A51,0,AD51-Cost_round*IF(8<=$B51,1,0)+J51-AE51) -> 0 | BA51: =IF(9>$A51,0,AE51-Cost_round*IF(9<=$B51,1,0)+K51-AF51) -> 0 | BB51: =IF(10>$A51,0,AF51-Cost_round*IF(10<=$B51,1,0)+L51-AG51) -> 0 | BC51: =IF(11>$A51,0,AG51-Cost_round*IF(11<=$B51,1,0)+M51-AH51) -> 0 | BD51: =IF(12>$A51,0,AH51-Cost_round*IF(12<=$B51,1,0)+N51-AI51) -> 0 | BE51: =IF(13>$A51,0,AI51-Cost_round*IF(13<=$B51,1,0)+O51-AJ51) -> 0 | BF51: =IF(14>$A51,0,AJ51-Cost_round*IF(14<=$B51,1,0)+P51-AK51) -> 0 | BG51: =IF(15>$A51,0,AK51-Cost_round*IF(15<=$B51,1,0)+Q51-AL51) -> 0 | BH51: =IF(16>$A51,0,AL51-Cost_round*IF(16<=$B51,1,0)+R51-AM51) -> 0 | BI51: =IF(17>$A51,0,AM51-Cost_round*IF(17<=$B51,1,0)+S51-AN51) -> 0 | BJ51: =IF(18>$A51,0,AN51-Cost_round*IF(18<=$B51,1,0)+T51-AO51) -> 0 | BK51: =IF(19>$A51,0,AO51-Cost_round*IF(19<=$B51,1,0)+U51-AP51) -> 0 | BL51: =IF(20>$A51,0,AP51-Cost_round*IF(20<=$B51,1,0)+V51-AQ51) -> 0 | BM51: =IF($AR51=1,SUMPRODUCT(AS51:BL51,$AS$38:$BL$38),"") -> 245.30428 | BN51: =IF($AR51=1,BM51+INDEX($AS$38:$BL$38,$A51)*INDEX(C51:V51,$A51)/Hurdle_r,"") -> 962.46841
... A133: 20 | B133: 4 | C133: =IF(1>$A133,0,Val_pt*(Ceiling_e-E_zero)*(1-(1-Half_gap)^MIN(1,$B133))) -> 70 | D133: =IF(2>$A133,0,Val_pt*(Ceiling_e-E_zero)*(1-(1-Half_gap)^MIN(2,$B133))) -> 105 | E133: =IF(3>$A133,0,Val_pt*(Ceiling_e-E_zero)*(1-(1-Half_gap)^MIN(3,$B133))) -> 122.5 | F133: =IF(4>$A133,0,Val_pt*(Ceiling_e-E_zero)*(1-(1-Half_gap)^MIN(4,$B133))) -> 131.25 | G133: =IF(5>$A133,0,Val_pt*(Ceiling_e-E_zero)*(1-(1-Half_gap)^MIN(5,$B133))) -> 131.25 | H133: =IF(6>$A133,0,Val_pt*(Ceiling_e-E_zero)*(1-(1-Half_gap)^MIN(6,$B133))) -> 131.25 | I133: =IF(7>$A133,0,Val_pt*(Ceiling_e-E_zero)*(1-(1-Half_gap)^MIN(7,$B133))) -> 131.25 | J133: =IF(8>$A133,0,Val_pt*(Ceiling_e-E_zero)*(1-(1-Half_gap)^MIN(8,$B133))) -> 131.25 | K133: =IF(9>$A133,0,Val_pt*(Ceiling_e-E_zero)*(1-(1-Half_gap)^MIN(9,$B133))) -> 131.25 | L133: =IF(10>$A133,0,Val_pt*(Ceiling_e-E_zero)*(1-(1-Half_gap)^MIN(10,$B133))) -> 131.25 | M133: =IF(11>$A133,0,Val_pt*(Ceiling_e-E_zero)*(1-(1-Half_gap)^MIN(11,$B133))) -> 131.25 | N133: =IF(12>$A133,0,Val_pt*(Ceiling_e-E_zero)*(1-(1-Half_gap)^MIN(12,$B133))) -> 131.25 | O133: =IF(13>$A133,0,Val_pt*(Ceiling_e-E_zero)*(1-(1-Half_gap)^MIN(13,$B133))) -> 131.25 | P133: =IF(14>$A133,0,Val_pt*(Ceiling_e-E_zero)*(1-(1-Half_gap)^MIN(14,$B133))) -> 131.25 | Q133: =IF(15>$A133,0,Val_pt*(Ceiling_e-E_zero)*(1-(1-Half_gap)^MIN(15,$B133))) -> 131.25 | R133: =IF(16>$A133,0,Val_pt*(Ceiling_e-E_zero)*(1-(1-Half_gap)^MIN(16,$B133))) -> 131.25 | S133: =IF(17>$A133,0,Val_pt*(Ceiling_e-E_zero)*(1-(1-Half_gap)^MIN(17,$B133))) -> 131.25 | T133: =IF(18>$A133,0,Val_pt*(Ceiling_e-E_zero)*(1-(1-Half_gap)^MIN(18,$B133))) -> 131.25 | U133: =IF(19>$A133,0,Val_pt*(Ceiling_e-E_zero)*(1-(1-Half_gap)^MIN(19,$B133))) -> 131.25 | V133: =IF(20>$A133,0,Val_pt*(Ceiling_e-E_zero)*(1-(1-Half_gap)^MIN(20,$B133))) -> 131.25 | W133: =IF(0>$A133,0,IF(0=$A133,MAX(End_q,Floor_q),MAX(X133+Cost_round*IF(1<=$B133,1,0)-C133,IF(1<=$B133,1,0)*Pre_q))) -> 535 | X133: =IF(1>$A133,0,IF(1=$A133,MAX(End_q,Floor_q),MAX(Y133+Cost_round*IF(2<=$B133,1,0)-D133,IF(2<=$B133,1,0)*Pre_q,Floor_q))) -> 485 | Y133: =IF(2>$A133,0,IF(2=$A133,MAX(End_q,Floor_q),MAX(Z133+Cost_round*IF(3<=$B133,1,0)-E133,IF(3<=$B133,1,0)*Pre_q,Floor_q))) -> 470 | Z133: =IF(3>$A133,0,IF(3=$A133,MAX(End_q,Floor_q),MAX(AA133+Cost_round*IF(4<=$B133,1,0)-F133,IF(4<=$B133,1,0)*Pre_q,Floor_q))) -> 470 | AA133: =IF(4>$A133,0,IF(4=$A133,MAX(End_q,Floor_q),MAX(AB133+Cost_round*IF(5<=$B133,1,0)-G133,IF(5<=$B133,1,0)*Pre_q,Floor_q))) -> 350 | AB133: =IF(5>$A133,0,IF(5=$A133,MAX(End_q,Floor_q),MAX(AC133+Cost_round*IF(6<=$B133,1,0)-H133,IF(6<=$B133,1,0)*Pre_q,Floor_q))) -> 350 | AC133: =IF(6>$A133,0,IF(6=$A133,MAX(End_q,Floor_q),MAX(AD133+Cost_round*IF(7<=$B133,1,0)-I133,IF(7<=$B133,1,0)*Pre_q,Floor_q))) -> 350 | AD133: =IF(7>$A133,0,IF(7=$A133,MAX(End_q,Floor_q),MAX(AE133+Cost_round*IF(8<=$B133,1,0)-J133,IF(8<=$B133,1,0)*Pre_q,Floor_q))) -> 350 | AE133: =IF(8>$A133,0,IF(8=$A133,MAX(End_q,Floor_q),MAX(AF133+Cost_round*IF(9<=$B133,1,0)-K133,IF(9<=$B133,1,0)*Pre_q,Floor_q))) -> 350 | AF133: =IF(9>$A133,0,IF(9=$A133,MAX(End_q,Floor_q),MAX(AG133+Cost_round*IF(10<=$B133,1,0)-L133,IF(10<=$B133,1,0)*Pre_q,Floor_q))) -> 350 | AG133: =IF(10>$A133,0,IF(10=$A133,MAX(End_q,Floor_q),MAX(AH133+Cost_round*IF(11<=$B133,1,0)-M133,IF(11<=$B133,1,0)*Pre_q,Floor_q))) -> 350 | AH133: =IF(11>$A133,0,IF(11=$A133,MAX(End_q,Floor_q),MAX(AI133+Cost_round*IF(12<=$B133,1,0)-N133,IF(12<=$B133,1,0)*Pre_q,Floor_q))) -> 350 | AI133: =IF(12>$A133,0,IF(12=$A133,MAX(End_q,Floor_q),MAX(AJ133+Cost_round*IF(13<=$B133,1,0)-O133,IF(13<=$B133,1,0)*Pre_q,Floor_q))) -> 350 | AJ133: =IF(13>$A133,0,IF(13=$A133,MAX(End_q,Floor_q),MAX(AK133+Cost_round*IF(14<=$B133,1,0)-P133,IF(14<=$B133,1,0)*Pre_q,Floor_q))) -> 350 | AK133: =IF(14>$A133,0,IF(14=$A133,MAX(End_q,Floor_q),MAX(AL133+Cost_round*IF(15<=$B133,1,0)-Q133,IF(15<=$B133,1,0)*Pre_q,Floor_q))) -> 350 | AL133: =IF(15>$A133,0,IF(15=$A133,MAX(End_q,Floor_q),MAX(AM133+Cost_round*IF(16<=$B133,1,0)-R133,IF(16<=$B133,1,0)*Pre_q,Floor_q))) -> 350 | AM133: =IF(16>$A133,0,IF(16=$A133,MAX(End_q,Floor_q),MAX(AN133+Cost_round*IF(17<=$B133,1,0)-S133,IF(17<=$B133,1,0)*Pre_q,Floor_q))) -> 350 | AN133: =IF(17>$A133,0,IF(17=$A133,MAX(End_q,Floor_q),MAX(AO133+Cost_round*IF(18<=$B133,1,0)-T133,IF(18<=$B133,1,0)*Pre_q,Floor_q))) -> 350 | AO133: =IF(18>$A133,0,IF(18=$A133,MAX(End_q,Floor_q),MAX(AP133+Cost_round*IF(19<=$B133,1,0)-U133,IF(19<=$B133,1,0)*Pre_q,Floor_q))) -> 350 | AP133: =IF(19>$A133,0,IF(19=$A133,MAX(End_q,Floor_q),MAX(AQ133+Cost_round*IF(20<=$B133,1,0)-V133,IF(20<=$B133,1,0)*Pre_q,Floor_q))) -> 350 | AQ133: =IF(20>$A133,0,MAX(End_q,Floor_q)) -> 470 | AR133: =IF(Q_zero>=W133-0.000000001,1,0) -> 1 | AS133: =IF(1>$A133,0,Q_zero-Cost_round*IF(1<=$B133,1,0)+C133-X133) -> 85 | AT133: =IF(2>$A133,0,X133-Cost_round*IF(2<=$B133,1,0)+D133-Y133) -> 0 | AU133: =IF(3>$A133,0,Y133-Cost_round*IF(3<=$B133,1,0)+E133-Z133) -> 2.5 | AV133: =IF(4>$A133,0,Z133-Cost_round*IF(4<=$B133,1,0)+F133-AA133) -> 131.25 | AW133: =IF(5>$A133,0,AA133-Cost_round*IF(5<=$B133,1,0)+G133-AB133) -> 131.25 | AX133: =IF(6>$A133,0,AB133-Cost_round*IF(6<=$B133,1,0)+H133-AC133) -> 131.25 | AY133: =IF(7>$A133,0,AC133-Cost_round*IF(7<=$B133,1,0)+I133-AD133) -> 131.25 | AZ133: =IF(8>$A133,0,AD133-Cost_round*IF(8<=$B133,1,0)+J133-AE133) -> 131.25 | BA133: =IF(9>$A133,0,AE133-Cost_round*IF(9<=$B133,1,0)+K133-AF133) -> 131.25 | BB133: =IF(10>$A133,0,AF133-Cost_round*IF(10<=$B133,1,0)+L133-AG133) -> 131.25 | BC133: =IF(11>$A133,0,AG133-Cost_round*IF(11<=$B133,1,0)+M133-AH133) -> 131.25 | BD133: =IF(12>$A133,0,AH133-Cost_round*IF(12<=$B133,1,0)+N133-AI133) -> 131.25 | BE133: =IF(13>$A133,0,AI133-Cost_round*IF(13<=$B133,1,0)+O133-AJ133) -> 131.25 | BF133: =IF(14>$A133,0,AJ133-Cost_round*IF(14<=$B133,1,0)+P133-AK133) -> 131.25 | BG133: =IF(15>$A133,0,AK133-Cost_round*IF(15<=$B133,1,0)+Q133-AL133) -> 131.25 | BH133: =IF(16>$A133,0,AL133-Cost_round*IF(16<=$B133,1,0)+R133-AM133) -> 131.25 | BI133: =IF(17>$A133,0,AM133-Cost_round*IF(17<=$B133,1,0)+S133-AN133) -> 131.25 | BJ133: =IF(18>$A133,0,AN133-Cost_round*IF(18<=$B133,1,0)+T133-AO133) -> 131.25 | BK133: =IF(19>$A133,0,AO133-Cost_round*IF(19<=$B133,1,0)+U133-AP133) -> 131.25 | BL133: =IF(20>$A133,0,AP133-Cost_round*IF(20<=$B133,1,0)+V133-AQ133) -> 11.25 | BM133: =IF($AR133=1,SUMPRODUCT(AS133:BL133,$AS$38:$BL$38),"") -> 852.31969 | BN133: =IF($AR133=1,BM133+INDEX($AS$38:$BL$38,$A133)*INDEX(C133:V133,$A133)/Hurdle_r,"") -> 1047.4145

Sheet Replan
A1: Re-plan: a present-biased board re-plans every year (Section 5.6; Theorem 5.3(iv); Table 5.3)
A2: At the start of each year the board weighs that year's payout 1 and the payout i years later b x beta^i (b on Declarations), compares every schedule of the remaining years from the cash and efficiency reached, and carries out the first year of the best (the first if tied).
A3: With b = 1 the weights are exponential and the board carries out the plan it approved (Theorem 5.3(iii)). Shareholders discount at the hurdle rate throughout.
A5: Year | B5: Cash at the start | C5: Efficiency at the start | D5: Plan made: rounds in the remaining years | E5: Its number | F5: Round this year | G5: Efficiency | H5: Savings | I5: Payout | J5: Year-end cash | K5: Discount factor | L5: PV of payout
A6: 1 | B6: =Q_zero -> 620 | C6: =E_zero -> 71 | D6: =INDEX($B$24:$B$87,E6+1) -> 111000 | E6: =_xlfn.MINIFS($A$24:$A$87,$AI$24:$AI$87,">="&(MAX($AI$24:$AI$87)-0.000000001)) -> 56 | F6: =INDEX($C$24:$C$87,E6+1) -> 1 | G6: =C6+F6*(Half_gap*(Ceiling_e-C6)) -> 78 | H6: =Val_pt*(G6-E_zero) -> 70 | I6: =INDEX($AC$24:$AC$87,E6+1) -> 85 | J6: =B6-Cost_round*F6+H6-I6 -> 485 | K6: =Beta_y^A6 -> 0.90909091 | L6: =I6*K6 -> 77.272727
A7: 2 | B7: =J6 -> 485 | C7: =G6 -> 78 | D7: =INDEX($B$92:$B$123,E7+1) -> 10100 | E7: =_xlfn.MINIFS($A$92:$A$123,$AI$92:$AI$123,">="&(MAX($AI$92:$AI$123)-0.000000001)) -> 20 | F7: =INDEX($C$92:$C$123,E7+1) -> 1 | G7: =C7+F7*(Half_gap*(Ceiling_e-C7)) -> 81.5 | H7: =Val_pt*(G7-E_zero) -> 105 | I7: =INDEX($AC$92:$AC$123,E7+1) -> 105 | J7: =B7-Cost_round*F7+H7-I7 -> 365 | K7: =Beta_y^A7 -> 0.82644628 | L7: =I7*K7 -> 86.77686
A8: 3 | B8: =J7 -> 365 | C8: =G7 -> 81.5 | D8: =INDEX($B$128:$B$143,E8+1) -> 0010 | E8: =_xlfn.MINIFS($A$128:$A$143,$AI$128:$AI$143,">="&(MAX($AI$128:$AI$143)-0.000000001)) -> 2 | F8: =INDEX($C$128:$C$143,E8+1) -> 0 | G8: =C8+F8*(Half_gap*(Ceiling_e-C8)) -> 81.5 | H8: =Val_pt*(G8-E_zero) -> 105 | I8: =INDEX($AC$128:$AC$143,E8+1) -> 105 | J8: =B8-Cost_round*F8+H8-I8 -> 365 | K8: =Beta_y^A8 -> 0.7513148 | L8: =I8*K8 -> 78.888054
A9: 4 | B9: =J8 -> 365 | C9: =G8 -> 81.5 | D9: =INDEX($B$148:$B$155,E9+1) -> 001 | E9: =_xlfn.MINIFS($A$148:$A$155,$AI$148:$AI$155,">="&(MAX($AI$148:$AI$155)-0.000000001)) -> 1 | F9: =INDEX($C$148:$C$155,E9+1) -> 0 | G9: =C9+F9*(Half_gap*(Ceiling_e-C9)) -> 81.5 | H9: =Val_pt*(G9-E_zero) -> 105 | I9: =INDEX($AC$148:$AC$155,E9+1) -> 105 | J9: =B9-Cost_round*F9+H9-I9 -> 365 | K9: =Beta_y^A9 -> 0.68301346 | L9: =I9*K9 -> 71.716413
A10: 5 | B10: =J9 -> 365 | C10: =G9 -> 81.5 | D10: =INDEX($B$160:$B$163,E10+1) -> 01 | E10: =_xlfn.MINIFS($A$160:$A$163,$AI$160:$AI$163,">="&(MAX($AI$160:$AI$163)-0.000000001)) -> 1 | F10: =INDEX($C$160:$C$163,E10+1) -> 0 | G10: =C10+F10*(Half_gap*(Ceiling_e-C10)) -> 81.5 | H10: =Val_pt*(G10-E_zero) -> 105 | I10: =INDEX($AC$160:$AC$163,E10+1) -> 0 | J10: =B10-Cost_round*F10+H10-I10 -> 470 | K10: =Beta_y^A10 -> 0.62092132 | L10: =I10*K10 -> 0
A11: 6 | B11: =J10 -> 470 | C11: =G10 -> 81.5 | D11: =INDEX($B$168:$B$169,E11+1) -> 1 | E11: =_xlfn.MINIFS($A$168:$A$169,$AI$168:$AI$169,">="&(MAX($AI$168:$AI$169)-0.000000001)) -> 1 | F11: =INDEX($C$168:$C$169,E11+1) -> 1 | G11: =C11+F11*(Half_gap*(Ceiling_e-C11)) -> 83.25 | H11: =Val_pt*(G11-E_zero) -> 122.5 | I11: =INDEX($AC$168:$AC$169,E11+1) -> 2.5 | J11: =B11-Cost_round*F11+H11-I11 -> 470 | K11: =Beta_y^A11 -> 0.56447393 | L11: =I11*K11 -> 1.4111848
A13: Rounds carried out, by year | D13: =F6&F7&F8&F9&F10&F11 -> 110001
A14: Payouts, present value | D14: =SUM(L6:L11) -> 316.06524
A15: Savings after year 6 forever, today | D15: =K11*H11/Hurdle_r -> 691.48056
A16: Value to shareholders | D16: =D14+D15 -> 1007.5458
A17: Less than the best plan | D17: =BestPlan!H22-D16 -> 14.386747
A18: Commitments | D18: =IF(AND(MIN(J6:J11)>=Floor_q-0.000000001,J11>=End_q-0.000000001,SUMPRODUCT((F6:F11=1)*(B6:B11<Pre_q-0.000000001))=0),"kept","breached") -> kept
A22: Start of year 1: the 64 schedules of the remaining 6 years, from the cash and efficiency reached
A23: # | B23: Rounds | C23: z1 | D23: z2 | E23: z3 | F23: z4 | G23: z5 | H23: z6 | I23: e1 | J23: e2 | K23: e3 | L23: e4 | M23: e5 | N23: e6 | O23: S1 | P23: S2 | Q23: S3 | R23: S4 | S23: S5 | T23: S6 | U23: R0 | V23: R1 | W23: R2 | X23: R3 | Y23: R4 | Z23: R5 | AA23: R6 | AB23: Keeps every commitment | AC23: p1 | AD23: p2 | AE23: p3 | AF23: p4 | AG23: p5 | AH23: p6 | AI23: The board's score
A24: 0 | B24: =""&C24&D24&E24&F24&G24&H24 -> 000000 | C24: =MOD(INT($A24/32),2) -> 0 | D24: =MOD(INT($A24/16),2) -> 0 | E24: =MOD(INT($A24/8),2) -> 0 | F24: =MOD(INT($A24/4),2) -> 0 | G24: =MOD(INT($A24/2),2) -> 0 | H24: =MOD(INT($A24/1),2) -> 0 | I24: =$C$6+C24*(Half_gap*(Ceiling_e-$C$6)) -> 71 | J24: =I24+D24*(Half_gap*(Ceiling_e-I24)) -> 71 | K24: =J24+E24*(Half_gap*(Ceiling_e-J24)) -> 71 | L24: =K24+F24*(Half_gap*(Ceiling_e-K24)) -> 71 | M24: =L24+G24*(Half_gap*(Ceiling_e-L24)) -> 71 | N24: =M24+H24*(Half_gap*(Ceiling_e-M24)) -> 71 | O24: =Val_pt*(I24-E_zero) -> 0 | P24: =Val_pt*(J24-E_zero) -> 0 | Q24: =Val_pt*(K24-E_zero) -> 0 | R24: =Val_pt*(L24-E_zero) -> 0 | S24: =Val_pt*(M24-E_zero) -> 0 | T24: =Val_pt*(N24-E_zero) -> 0 | U24: =MAX(V24+Cost_round*C24-O24,IF(C24=1,Pre_q,0)) -> 470 | V24: =MAX(W24+Cost_round*D24-P24,IF(D24=1,Pre_q,0),Floor_q) -> 470 | W24: =MAX(X24+Cost_round*E24-Q24,IF(E24=1,Pre_q,0),Floor_q) -> 470 | X24: =MAX(Y24+Cost_round*F24-R24,IF(F24=1,Pre_q,0),Floor_q) -> 470 | Y24: =MAX(Z24+Cost_round*G24-S24,IF(G24=1,Pre_q,0),Floor_q) -> 470 | Z24: =MAX(AA24+Cost_round*H24-T24,IF(H24=1,Pre_q,0),Floor_q) -> 470 | AA24: =MAX(End_q,Floor_q) -> 470 | AB24: =IF($B$6>=U24-0.000000001,1,0) -> 1 | AC24: =IF($AB24=1,$B$6-Cost_round*C24+O24-V24,"") -> 150 | AD24: =IF($AB24=1,V24-Cost_round*D24+P24-W24,"") -> 0 | AE24: =IF($AB24=1,W24-Cost_round*E24+Q24-X24,"") -> 0 | AF24: =IF($AB24=1,X24-Cost_round*F24+R24-Y24,"") -> 0 | AG24: =IF($AB24=1,Y24-Cost_round*G24+S24-Z24,"") -> 0 | AH24: =IF($AB24=1,Z24-Cost_round*H24+T24-AA24,"") -> 0 | AI24: =IF($AB24=1,AC24*1+AD24*Bias_b*Beta_y^1+AE24*Bias_b*Beta_y^2+AF24*Bias_b*Beta_y^3+AG24*Bias_b*Beta_y^4+AH24*Bias_b*Beta_y^5+Bias_b*Beta_y^5*T24/Hurdle_r,"") -> 150
