Workbook

Sheet README
B1: DCT Laboratory — Vol I, Ch 11: Enterprise Performance Architecture
B2: Seed 26111 · Companion to DCT_V1_Ch11_Lab.ipynb and AXIOM Lab 1.11 (module AXIOM-11). Readings in index points; money in $ million.
B4: Worked Example 11.1, Who Really Chose Digital?, with the book's declarations, and the five steps of AXIOM Lab 1.11, Auditing Meridian's Scorecard.
B5: Declarations: the CFO's scorecard (Worked Example 1.1) and the Chapter 1 model's parameters (Online Appendix 1.B.4).
B6: Paths: the four readings of each option and the scorecard, month by month for five years (Figure 11.3; Online Appendix 11.B.6).
B7: Dashboard: Table 11.2's ten dimensions, Meridian's six with supports, indicators and bands, Proposition 11.1's twin, and Section 11.8's sustainability line (lab step 1).
B8: Dependencies: Table 11.4's lag floors recomputed from Chapter 9's fourteen arrows (Theorem 11.3(i)).
B9: Weights: dominance, the tie 1.6 points of weight away, the weight sweep, and the shares of weightings (Theorem 11.2(ii); Figure 11.1; Online Appendix 11.B.2; lab step 2).
B10: Yardsticks: best-to-worst and percentage scales, their effective weights, and two other reference groups (Theorem 11.2(iii); Online Appendix 11.B.3; lab step 3).
B11: Ratios: the rate-and-mix bridge for Theorem 11.5's two divisions and Table 11.5's bank, a mix bench, target cascades and roll-ups (lab step 4).
B12: Frontier: the indivisible programs and Figure 11.2's exchange rate (Theorem 11.4; lab step 5).
B13: Window: the annual reviews and the J-curve's evaluation window (Theorem 11.3(iii); Online Appendix 11.B.1; lab step 5).
... B21: Cross-sheet link: green.

Sheet Declarations
A1: Declarations (Worked Example 11.1, the situation; Worked Example 1.1; the Chapter 1 model of Online Appendix 1.B.4). Readings in index points; liquidity indexed to today = 100 ($620 million).
A3: Reading | B3: Today (Chapter 3) | C3: Weight in the CFO's scorecard | D3: Sign (lower risk is better) | E3: Measurement error (Table 5.2) | F3: Tag (Table 5.2)
A4: Liquidity | B4: 100 | C4: 0.25 | D4: 1 | E4: +/-1% | F4: ECA: capital
A5: Technology | B5: 41 | C5: 0.25 | D5: 1 | E5: +/-4 | F5: ECA: capital
A6: Efficiency | B6: 71 | C6: 0.25 | D6: 1 | E6: +/-3 | F6: EPA: performance
A7: Strategic risk | B7: 64 | C7: 0.25 | D7: -1 | E7: +/-6 | F7: ERRA: risk
A8: Today's score, the weights times (L, T, E, -R) | B8: =SUMPRODUCT(B4:B7,C4:C7,D4:D7) -> 37 | C8: Worked Example 1.1: (100 + 41 + 71 - 64)/4 = 37.0
A9: $ million a liquidity index point | B9: 6.2 | C9: Today = 100 = $620 million
A10: The restructuring's sale closes (years) | B10: 1 | C10: The jump J applies from t = 1
A13: Option | B13: Reading | C13: Target | D13: Speed k a year | E13: Trough sigma D | F13: Trough time tau (years) | G13: Jump J at the sale | H13: Start x(0)
A14: Digital | B14: Liquidity | C14: 112 | D14: 0.35 | E14: -28 | F14: 2 | G14: 0 | H14: =$B$4 -> 100
A15: Digital | B15: Technology | C15: 78 | D15: 0.55 | E15: 0 | G15: 0 | H15: =$B$5 -> 41
A16: Digital | B16: Efficiency | C16: 77 | D16: 0.5 | E16: -9 | F16: 1.5 | G16: 0 | H16: =$B$6 -> 71
A17: Digital | B17: Strategic risk | C17: 51 | D17: 0.4 | E17: 14 | F17: 1.2 | G17: 0 | H17: =$B$7 -> 64
A18: Restructuring | B18: Liquidity | C18: 104 | D18: 0.3 | E18: 0 | G18: 18 | H18: =$B$4 -> 100
A19: Restructuring | B19: Technology | C19: 38 | D19: 0.25 | E19: 0 | G19: 0 | H19: =$B$5 -> 41
A20: Restructuring | B20: Efficiency | C20: 74 | D20: 0.45 | E20: 0 | G20: 0 | H20: =$B$6 -> 71
A21: Restructuring | B21: Strategic risk | C21: 56 | D21: 0.35 | E21: 0 | G21: -8 | H21: =$B$7 -> 64
A22: Turnaround | B22: Liquidity | C22: 106 | D22: 0.45 | E22: 0 | G22: 0 | H22: =$B$4 -> 100
A23: Turnaround | B23: Technology | C23: 33 | D23: 0.2 | E23: 0 | G23: 0 | H23: =$B$5 -> 41
A24: Turnaround | B24: Efficiency | C24: 79 | D24: 0.6 | E24: 0 | G24: 0 | H24: =$B$6 -> 71
A25: Turnaround | B25: Strategic risk | C25: 67 | D25: 0.3 | E25: 0 | G25: 0 | H25: =$B$7 -> 64
A27: Online Appendix 1.B.4: x(t) = target + (x(0) - target) e^(-k t) + sigma D (t / tau) e^(1 - t / tau) + J 1{t >= 1}, t in years. A trough of zero needs no trough time; blank cells are zero.

Sheet Paths
A1: The Chapter 1 model month by month: four readings for each option and the CFO's scorecard (Worked Example 11.1, Step 4; Figure 11.3; Online Appendix 11.B.6)
A2: Each reading follows Online Appendix 1.B.4's model with the parameters on Declarations; the score is the weights times (L, T, E, -R). Flags: 1 when the statement is true that month.
X3: Reading the paths | Y3: Value | Z3: Book
A4: Month | B4: t (years) | C4: Digital: liquidity | D4: Digital: technology | E4: Digital: efficiency | F4: Digital: strategic risk | G4: Restructuring: liquidity | H4: Restructuring: technology | I4: Restructuring: efficiency | J4: Restructuring: strategic risk | K4: Turnaround: liquidity | L4: Turnaround: technology | M4: Turnaround: efficiency | N4: Turnaround: strategic risk | O4: Score: digital | P4: Score: restructuring | Q4: Score: turnaround | R4: Digital below today's score | S4: Digital ahead of the turnaround | T4: Digital ahead of restructuring | U4: Digital's rank | V4: |Restructuring - turnaround| | X4: Digital's low | Y4: =MIN($O$5:$O$65) -> 32.106467 | Z4: 32.11 at month 11
A5: 0 | B5: =A5/12 -> 0 | C5: =Declarations!$C$14+(Declarations!$H$14-Declarations!$C$14)*EXP(-Declarations!$D$14*$B5)+IF(Declarations!$E$14=0,0,Declarations!$E$14*($B5/Declarations!$F$14)*EXP(1-$B5/Declarations!$F$14))+Declarations!$G$14*IF($B5>=Sale_t,1,0) -> 100 | D5: =Declarations!$C$15+(Declarations!$H$15-Declarations!$C$15)*EXP(-Declarations!$D$15*$B5)+IF(Declarations!$E$15=0,0,Declarations!$E$15*($B5/Declarations!$F$15)*EXP(1-$B5/Declarations!$F$15))+Declarations!$G$15*IF($B5>=Sale_t,1,0) -> 41 | E5: =Declarations!$C$16+(Declarations!$H$16-Declarations!$C$16)*EXP(-Declarations!$D$16*$B5)+IF(Declarations!$E$16=0,0,Declarations!$E$16*($B5/Declarations!$F$16)*EXP(1-$B5/Declarations!$F$16))+Declarations!$G$16*IF($B5>=Sale_t,1,0) -> 71 | F5: =Declarations!$C$17+(Declarations!$H$17-Declarations!$C$17)*EXP(-Declarations!$D$17*$B5)+IF(Declarations!$E$17=0,0,Declarations!$E$17*($B5/Declarations!$F$17)*EXP(1-$B5/Declarations!$F$17))+Declarations!$G$17*IF($B5>=Sale_t,1,0) -> 64 | G5: =Declarations!$C$18+(Declarations!$H$18-Declarations!$C$18)*EXP(-Declarations!$D$18*$B5)+IF(Declarations!$E$18=0,0,Declarations!$E$18*($B5/Declarations!$F$18)*EXP(1-$B5/Declarations!$F$18))+Declarations!$G$18*IF($B5>=Sale_t,1,0) -> 100 | H5: =Declarations!$C$19+(Declarations!$H$19-Declarations!$C$19)*EXP(-Declarations!$D$19*$B5)+IF(Declarations!$E$19=0,0,Declarations!$E$19*($B5/Declarations!$F$19)*EXP(1-$B5/Declarations!$F$19))+Declarations!$G$19*IF($B5>=Sale_t,1,0) -> 41 | I5: =Declarations!$C$20+(Declarations!$H$20-Declarations!$C$20)*EXP(-Declarations!$D$20*$B5)+IF(Declarations!$E$20=0,0,Declarations!$E$20*($B5/Declarations!$F$20)*EXP(1-$B5/Declarations!$F$20))+Declarations!$G$20*IF($B5>=Sale_t,1,0) -> 71 | J5: =Declarations!$C$21+(Declarations!$H$21-Declarations!$C$21)*EXP(-Declarations!$D$21*$B5)+IF(Declarations!$E$21=0,0,Declarations!$E$21*($B5/Declarations!$F$21)*EXP(1-$B5/Declarations!$F$21))+Declarations!$G$21*IF($B5>=Sale_t,1,0) -> 64 | K5: =Declarations!$C$22+(Declarations!$H$22-Declarations!$C$22)*EXP(-Declarations!$D$22*$B5)+IF(Declarations!$E$22=0,0,Declarations!$E$22*($B5/Declarations!$F$22)*EXP(1-$B5/Declarations!$F$22))+Declarations!$G$22*IF($B5>=Sale_t,1,0) -> 100 | L5: =Declarations!$C$23+(Declarations!$H$23-Declarations!$C$23)*EXP(-Declarations!$D$23*$B5)+IF(Declarations!$E$23=0,0,Declarations!$E$23*($B5/Declarations!$F$23)*EXP(1-$B5/Declarations!$F$23))+Declarations!$G$23*IF($B5>=Sale_t,1,0) -> 41 | M5: =Declarations!$C$24+(Declarations!$H$24-Declarations!$C$24)*EXP(-Declarations!$D$24*$B5)+IF(Declarations!$E$24=0,0,Declarations!$E$24*($B5/Declarations!$F$24)*EXP(1-$B5/Declarations!$F$24))+Declarations!$G$24*IF($B5>=Sale_t,1,0) -> 71 | N5: =Declarations!$C$25+(Declarations!$H$25-Declarations!$C$25)*EXP(-Declarations!$D$25*$B5)+IF(Declarations!$E$25=0,0,Declarations!$E$25*($B5/Declarations!$F$25)*EXP(1-$B5/Declarations!$F$25))+Declarations!$G$25*IF($B5>=Sale_t,1,0) -> 64 | O5: =W_L*S_L*C5+W_T*S_T*D5+W_E*S_E*E5+W_R*S_R*F5 -> 37 | P5: =W_L*S_L*G5+W_T*S_T*H5+W_E*S_E*I5+W_R*S_R*J5 -> 37 | Q5: =W_L*S_L*K5+W_T*S_T*L5+W_E*S_E*M5+W_R*S_R*N5 -> 37 | R5: =IF(O5<Score_today,1,0) -> 0 | S5: =IF(O5>Q5,1,0) -> 0 | T5: =IF(O5>P5,1,0) -> 0 | U5: =1+IF(P5>O5,1,0)+IF(Q5>O5,1,0) -> 1 | V5: =ABS(P5-Q5) -> 0 | X5: Month of digital's low | Y5: =INDEX($A$5:$A$65,MATCH(Y4,$O$5:$O$65,0)) -> 11
A6: 1 | B6: =A6/12 -> 0.083333333 | C6: =Declarations!$C$14+(Declarations!$H$14-Declarations!$C$14)*EXP(-Declarations!$D$14*$B6)+IF(Declarations!$E$14=0,0,Declarations!$E$14*($B6/Declarations!$F$14)*EXP(1-$B6/Declarations!$F$14))+Declarations!$G$14*IF($B6>=Sale_t,1,0) -> 97.30304 | D6: =Declarations!$C$15+(Declarations!$H$15-Declarations!$C$15)*EXP(-Declarations!$D$15*$B6)+IF(Declarations!$E$15=0,0,Declarations!$E$15*($B6/Declarations!$F$15)*EXP(1-$B6/Declarations!$F$15))+Declarations!$G$15*IF($B6>=Sale_t,1,0) -> 42.657557 | E6: =Declarations!$C$16+(Declarations!$H$16-Declarations!$C$16)*EXP(-Declarations!$D$16*$B6)+IF(Declarations!$E$16=0,0,Declarations!$E$16*($B6/Declarations!$F$16)*EXP(1-$B6/Declarations!$F$16))+Declarations!$G$16*IF($B6>=Sale_t,1,0) -> 69.959171 | F6: =Declarations!$C$17+(Declarations!$H$17-Declarations!$C$17)*EXP(-Declarations!$D$17*$B6)+IF(Declarations!$E$17=0,0,Declarations!$E$17*($B6/Declarations!$F$17)*EXP(1-$B6/Declarations!$F$17))+Declarations!$G$17*IF($B6>=Sale_t,1,0) -> 66.039285 | G6: =Declarations!$C$18+(Declarations!$H$18-Declarations!$C$18)*EXP(-Declarations!$D$18*$B6)+IF(Declarations!$E$18=0,0,Declarations!$E$18*($B6/Declarations!$F$18)*EXP(1-$B6/Declarations!$F$18))+Declarations!$G$18*IF($B6>=Sale_t,1,0) -> 100.09876 | H6: =Declarations!$C$19+(Declarations!$H$19-Declarations!$C$19)*EXP(-Declarations!$D$19*$B6)+IF(Declarations!$E$19=0,0,Declarations!$E$19*($B6/Declarations!$F$19)*EXP(1-$B6/Declarations!$F$19))+Declarations!$G$19*IF($B6>=Sale_t,1,0) -> 40.938147 | I6: =Declarations!$C$20+(Declarations!$H$20-Declarations!$C$20)*EXP(-Declarations!$D$20*$B6)+IF(Declarations!$E$20=0,0,Declarations!$E$20*($B6/Declarations!$F$20)*EXP(1-$B6/Declarations!$F$20))+Declarations!$G$20*IF($B6>=Sale_t,1,0) -> 71.110417 | J6: =Declarations!$C$21+(Declarations!$H$21-Declarations!$C$21)*EXP(-Declarations!$D$21*$B6)+IF(Declarations!$E$21=0,0,Declarations!$E$21*($B6/Declarations!$F$21)*EXP(1-$B6/Declarations!$F$21))+Declarations!$G$21*IF($B6>=Sale_t,1,0) -> 63.770037 | K6: =Declarations!$C$22+(Declarations!$H$22-Declarations!$C$22)*EXP(-Declarations!$D$22*$B6)+IF(Declarations!$E$22=0,0,Declarations!$E$22*($B6/Declarations!$F$22)*EXP(1-$B6/Declarations!$F$22))+Declarations!$G$22*IF($B6>=Sale_t,1,0) -> 100.22083 | L6: =Declarations!$C$23+(Declarations!$H$23-Declarations!$C$23)*EXP(-Declarations!$D$23*$B6)+IF(Declarations!$E$23=0,0,Declarations!$E$23*($B6/Declarations!$F$23)*EXP(1-$B6/Declarations!$F$23))+Declarations!$G$23*IF($B6>=Sale_t,1,0) -> 40.867772 | M6: =Declarations!$C$24+(Declarations!$H$24-Declarations!$C$24)*EXP(-Declarations!$D$24*$B6)+IF(Declarations!$E$24=0,0,Declarations!$E$24*($B6/Declarations!$F$24)*EXP(1-$B6/Declarations!$F$24))+Declarations!$G$24*IF($B6>=Sale_t,1,0) -> 71.390165 | N6: =Declarations!$C$25+(Declarations!$H$25-Declarations!$C$25)*EXP(-Declarations!$D$25*$B6)+IF(Declarations!$E$25=0,0,Declarations!$E$25*($B6/Declarations!$F$25)*EXP(1-$B6/Declarations!$F$25))+Declarations!$G$25*IF($B6>=Sale_t,1,0) -> 64.07407 | O6: =W_L*S_L*C6+W_T*S_T*D6+W_E*S_E*E6+W_R*S_R*F6 -> 35.970121 | P6: =W_L*S_L*G6+W_T*S_T*H6+W_E*S_E*I6+W_R*S_R*J6 -> 37.094322 | Q6: =W_L*S_L*K6+W_T*S_T*L6+W_E*S_E*M6+W_R*S_R*N6 -> 37.101175 | R6: =IF(O6<Score_today,1,0) -> 1 | S6: =IF(O6>Q6,1,0) -> 0 | T6: =IF(O6>P6,1,0) -> 0 | U6: =1+IF(P6>O6,1,0)+IF(Q6>O6,1,0) -> 3 | V6: =ABS(P6-Q6) -> 0.0068531058 | X6: Last month digital is below today's score | Y6: =_xlfn.MAXIFS($A$5:$A$65,$R$5:$R$65,1) -> 28 | Z6: month 28
A7: 2 | B7: =A7/12 -> 0.16666667 | C7: =Declarations!$C$14+(Declarations!$H$14-Declarations!$C$14)*EXP(-Declarations!$D$14*$B7)+IF(Declarations!$E$14=0,0,Declarations!$E$14*($B7/Declarations!$F$14)*EXP(1-$B7/Declarations!$F$14))+Declarations!$G$14*IF($B7>=Sale_t,1,0) -> 94.844448 | D7: =Declarations!$C$15+(Declarations!$H$15-Declarations!$C$15)*EXP(-Declarations!$D$15*$B7)+IF(Declarations!$E$15=0,0,Declarations!$E$15*($B7/Declarations!$F$15)*EXP(1-$B7/Declarations!$F$15))+Declarations!$G$15*IF($B7>=Sale_t,1,0) -> 44.240858 | E7: =Declarations!$C$16+(Declarations!$H$16-Declarations!$C$16)*EXP(-Declarations!$D$16*$B7)+IF(Declarations!$E$16=0,0,Declarations!$E$16*($B7/Declarations!$F$16)*EXP(1-$B7/Declarations!$F$16))+Declarations!$G$16*IF($B7>=Sale_t,1,0) -> 69.047308 | F7: =Declarations!$C$17+(Declarations!$H$17-Declarations!$C$17)*EXP(-Declarations!$D$17*$B7)+IF(Declarations!$E$17=0,0,Declarations!$E$17*($B7/Declarations!$F$17)*EXP(1-$B7/Declarations!$F$17))+Declarations!$G$17*IF($B7>=Sale_t,1,0) -> 67.761734 | G7: =Declarations!$C$18+(Declarations!$H$18-Declarations!$C$18)*EXP(-Declarations!$D$18*$B7)+IF(Declarations!$E$18=0,0,Declarations!$E$18*($B7/Declarations!$F$18)*EXP(1-$B7/Declarations!$F$18))+Declarations!$G$18*IF($B7>=Sale_t,1,0) -> 100.19508 | H7: =Declarations!$C$19+(Declarations!$H$19-Declarations!$C$19)*EXP(-Declarations!$D$19*$B7)+IF(Declarations!$E$19=0,0,Declarations!$E$19*($B7/Declarations!$F$19)*EXP(1-$B7/Declarations!$F$19))+Declarations!$G$19*IF($B7>=Sale_t,1,0) -> 40.877568 | I7: =Declarations!$C$20+(Declarations!$H$20-Declarations!$C$20)*EXP(-Declarations!$D$20*$B7)+IF(Declarations!$E$20=0,0,Declarations!$E$20*($B7/Declarations!$F$20)*EXP(1-$B7/Declarations!$F$20))+Declarations!$G$20*IF($B7>=Sale_t,1,0) -> 71.21677 | J7: =Declarations!$C$21+(Declarations!$H$21-Declarations!$C$21)*EXP(-Declarations!$D$21*$B7)+IF(Declarations!$E$21=0,0,Declarations!$E$21*($B7/Declarations!$F$21)*EXP(1-$B7/Declarations!$F$21))+Declarations!$G$21*IF($B7>=Sale_t,1,0) -> 63.546684 | K7: =Declarations!$C$22+(Declarations!$H$22-Declarations!$C$22)*EXP(-Declarations!$D$22*$B7)+IF(Declarations!$E$22=0,0,Declarations!$E$22*($B7/Declarations!$F$22)*EXP(1-$B7/Declarations!$F$22))+Declarations!$G$22*IF($B7>=Sale_t,1,0) -> 100.43354 | L7: =Declarations!$C$23+(Declarations!$H$23-Declarations!$C$23)*EXP(-Declarations!$D$23*$B7)+IF(Declarations!$E$23=0,0,Declarations!$E$23*($B7/Declarations!$F$23)*EXP(1-$B7/Declarations!$F$23))+Declarations!$G$23*IF($B7>=Sale_t,1,0) -> 40.737729 | M7: =Declarations!$C$24+(Declarations!$H$24-Declarations!$C$24)*EXP(-Declarations!$D$24*$B7)+IF(Declarations!$E$24=0,0,Declarations!$E$24*($B7/Declarations!$F$24)*EXP(1-$B7/Declarations!$F$24))+Declarations!$G$24*IF($B7>=Sale_t,1,0) -> 71.761301 | N7: =Declarations!$C$25+(Declarations!$H$25-Declarations!$C$25)*EXP(-Declarations!$D$25*$B7)+IF(Declarations!$E$25=0,0,Declarations!$E$25*($B7/Declarations!$F$25)*EXP(1-$B7/Declarations!$F$25))+Declarations!$G$25*IF($B7>=Sale_t,1,0) -> 64.146312 | O7: =W_L*S_L*C7+W_T*S_T*D7+W_E*S_E*E7+W_R*S_R*F7 -> 35.09272 | P7: =W_L*S_L*G7+W_T*S_T*H7+W_E*S_E*I7+W_R*S_R*J7 -> 37.185684 | Q7: =W_L*S_L*K7+W_T*S_T*L7+W_E*S_E*M7+W_R*S_R*N7 -> 37.196564 | R7: =IF(O7<Score_today,1,0) -> 1 | S7: =IF(O7>Q7,1,0) -> 0 | T7: =IF(O7>P7,1,0) -> 0 | U7: =1+IF(P7>O7,1,0)+IF(Q7>O7,1,0) -> 3 | V7: =ABS(P7-Q7) -> 0.01088005 | X7: Month digital regains today's score | Y7: =Y6+1 -> 29 | Z7: month 29
A8: 3 | B8: =A8/12 -> 0.25 | C8: =Declarations!$C$14+(Declarations!$H$14-Declarations!$C$14)*EXP(-Declarations!$D$14*$B8)+IF(Declarations!$E$14=0,0,Declarations!$E$14*($B8/Declarations!$F$14)*EXP(1-$B8/Declarations!$F$14))+Declarations!$G$14*IF($B8>=Sale_t,1,0) -> 92.60931 | D8: =Declarations!$C$15+(Declarations!$H$15-Declarations!$C$15)*EXP(-Declarations!$D$15*$B8)+IF(Declarations!$E$15=0,0,Declarations!$E$15*($B8/Declarations!$F$15)*EXP(1-$B8/Declarations!$F$15))+Declarations!$G$15*IF($B8>=Sale_t,1,0) -> 45.753229 | E8: =Declarations!$C$16+(Declarations!$H$16-Declarations!$C$16)*EXP(-Declarations!$D$16*$B8)+IF(Declarations!$E$16=0,0,Declarations!$E$16*($B8/Declarations!$F$16)*EXP(1-$B8/Declarations!$F$16))+Declarations!$G$16*IF($B8>=Sale_t,1,0) -> 68.253555 | F8: =Declarations!$C$17+(Declarations!$H$17-Declarations!$C$17)*EXP(-Declarations!$D$17*$B8)+IF(Declarations!$E$17=0,0,Declarations!$E$17*($B8/Declarations!$F$17)*EXP(1-$B8/Declarations!$F$17))+Declarations!$G$17*IF($B8>=Sale_t,1,0) -> 69.200179 | G8: =Declarations!$C$18+(Declarations!$H$18-Declarations!$C$18)*EXP(-Declarations!$D$18*$B8)+IF(Declarations!$E$18=0,0,Declarations!$E$18*($B8/Declarations!$F$18)*EXP(1-$B8/Declarations!$F$18))+Declarations!$G$18*IF($B8>=Sale_t,1,0) -> 100.28903 | H8: =Declarations!$C$19+(Declarations!$H$19-Declarations!$C$19)*EXP(-Declarations!$D$19*$B8)+IF(Declarations!$E$19=0,0,Declarations!$E$19*($B8/Declarations!$F$19)*EXP(1-$B8/Declarations!$F$19))+Declarations!$G$19*IF($B8>=Sale_t,1,0) -> 40.818239 | I8: =Declarations!$C$20+(Declarations!$H$20-Declarations!$C$20)*EXP(-Declarations!$D$20*$B8)+IF(Declarations!$E$20=0,0,Declarations!$E$20*($B8/Declarations!$F$20)*EXP(1-$B8/Declarations!$F$20))+Declarations!$G$20*IF($B8>=Sale_t,1,0) -> 71.319208 | J8: =Declarations!$C$21+(Declarations!$H$21-Declarations!$C$21)*EXP(-Declarations!$D$21*$B8)+IF(Declarations!$E$21=0,0,Declarations!$E$21*($B8/Declarations!$F$21)*EXP(1-$B8/Declarations!$F$21))+Declarations!$G$21*IF($B8>=Sale_t,1,0) -> 63.329751 | K8: =Declarations!$C$22+(Declarations!$H$22-Declarations!$C$22)*EXP(-Declarations!$D$22*$B8)+IF(Declarations!$E$22=0,0,Declarations!$E$22*($B8/Declarations!$F$22)*EXP(1-$B8/Declarations!$F$22))+Declarations!$G$22*IF($B8>=Sale_t,1,0) -> 100.63842 | L8: =Declarations!$C$23+(Declarations!$H$23-Declarations!$C$23)*EXP(-Declarations!$D$23*$B8)+IF(Declarations!$E$23=0,0,Declarations!$E$23*($B8/Declarations!$F$23)*EXP(1-$B8/Declarations!$F$23))+Declarations!$G$23*IF($B8>=Sale_t,1,0) -> 40.609835 | M8: =Declarations!$C$24+(Declarations!$H$24-Declarations!$C$24)*EXP(-Declarations!$D$24*$B8)+IF(Declarations!$E$24=0,0,Declarations!$E$24*($B8/Declarations!$F$24)*EXP(1-$B8/Declarations!$F$24))+Declarations!$G$24*IF($B8>=Sale_t,1,0) -> 72.114336 | N8: =Declarations!$C$25+(Declarations!$H$25-Declarations!$C$25)*EXP(-Declarations!$D$25*$B8)+IF(Declarations!$E$25=0,0,Declarations!$E$25*($B8/Declarations!$F$25)*EXP(1-$B8/Declarations!$F$25))+Declarations!$G$25*IF($B8>=Sale_t,1,0) -> 64.21677 | O8: =W_L*S_L*C8+W_T*S_T*D8+W_E*S_E*E8+W_R*S_R*F8 -> 34.353979 | P8: =W_L*S_L*G8+W_T*S_T*H8+W_E*S_E*I8+W_R*S_R*J8 -> 37.274181 | Q8: =W_L*S_L*K8+W_T*S_T*L8+W_E*S_E*M8+W_R*S_R*N8 -> 37.286454 | R8: =IF(O8<Score_today,1,0) -> 1 | S8: =IF(O8>Q8,1,0) -> 0 | T8: =IF(O8>P8,1,0) -> 0 | U8: =1+IF(P8>O8,1,0)+IF(Q8>O8,1,0) -> 3 | V8: =ABS(P8-Q8) -> 0.012273933 | X8: Digital's score that month | Y8: =INDEX($O$5:$O$65,Y7+1) -> 37.18741 | Z8: 37.19
A9: 4 | B9: =A9/12 -> 0.33333333 | C9: =Declarations!$C$14+(Declarations!$H$14-Declarations!$C$14)*EXP(-Declarations!$D$14*$B9)+IF(Declarations!$E$14=0,0,Declarations!$E$14*($B9/Declarations!$F$14)*EXP(1-$B9/Declarations!$F$14))+Declarations!$G$14*IF($B9>=Sale_t,1,0) -> 90.583531 | D9: =Declarations!$C$15+(Declarations!$H$15-Declarations!$C$15)*EXP(-Declarations!$D$15*$B9)+IF(Declarations!$E$15=0,0,Declarations!$E$15*($B9/Declarations!$F$15)*EXP(1-$B9/Declarations!$F$15))+Declarations!$G$15*IF($B9>=Sale_t,1,0) -> 47.197847 | E9: =Declarations!$C$16+(Declarations!$H$16-Declarations!$C$16)*EXP(-Declarations!$D$16*$B9)+IF(Declarations!$E$16=0,0,Declarations!$E$16*($B9/Declarations!$F$16)*EXP(1-$B9/Declarations!$F$16))+Declarations!$G$16*IF($B9>=Sale_t,1,0) -> 67.56785 | F9: =Declarations!$C$17+(Declarations!$H$17-Declarations!$C$17)*EXP(-Declarations!$D$17*$B9)+IF(Declarations!$E$17=0,0,Declarations!$E$17*($B9/Declarations!$F$17)*EXP(1-$B9/Declarations!$F$17))+Declarations!$G$17*IF($B9>=Sale_t,1,0) -> 70.38449 | G9: =Declarations!$C$18+(Declarations!$H$18-Declarations!$C$18)*EXP(-Declarations!$D$18*$B9)+IF(Declarations!$E$18=0,0,Declarations!$E$18*($B9/Declarations!$F$18)*EXP(1-$B9/Declarations!$F$18))+Declarations!$G$18*IF($B9>=Sale_t,1,0) -> 100.38065 | H9: =Declarations!$C$19+(Declarations!$H$19-Declarations!$C$19)*EXP(-Declarations!$D$19*$B9)+IF(Declarations!$E$19=0,0,Declarations!$E$19*($B9/Declarations!$F$19)*EXP(1-$B9/Declarations!$F$19))+Declarations!$G$19*IF($B9>=Sale_t,1,0) -> 40.760133 | I9: =Declarations!$C$20+(Declarations!$H$20-Declarations!$C$20)*EXP(-Declarations!$D$20*$B9)+IF(Declarations!$E$20=0,0,Declarations!$E$20*($B9/Declarations!$F$20)*EXP(1-$B9/Declarations!$F$20))+Declarations!$G$20*IF($B9>=Sale_t,1,0) -> 71.417876 | J9: =Declarations!$C$21+(Declarations!$H$21-Declarations!$C$21)*EXP(-Declarations!$D$21*$B9)+IF(Declarations!$E$21=0,0,Declarations!$E$21*($B9/Declarations!$F$21)*EXP(1-$B9/Declarations!$F$21))+Declarations!$G$21*IF($B9>=Sale_t,1,0) -> 63.119054 | K9: =Declarations!$C$22+(Declarations!$H$22-Declarations!$C$22)*EXP(-Declarations!$D$22*$B9)+IF(Declarations!$E$22=0,0,Declarations!$E$22*($B9/Declarations!$F$22)*EXP(1-$B9/Declarations!$F$22))+Declarations!$G$22*IF($B9>=Sale_t,1,0) -> 100.83575 | L9: =Declarations!$C$23+(Declarations!$H$23-Declarations!$C$23)*EXP(-Declarations!$D$23*$B9)+IF(Declarations!$E$23=0,0,Declarations!$E$23*($B9/Declarations!$F$23)*EXP(1-$B9/Declarations!$F$23))+Declarations!$G$23*IF($B9>=Sale_t,1,0) -> 40.484056 | M9: =Declarations!$C$24+(Declarations!$H$24-Declarations!$C$24)*EXP(-Declarations!$D$24*$B9)+IF(Declarations!$E$24=0,0,Declarations!$E$24*($B9/Declarations!$F$24)*EXP(1-$B9/Declarations!$F$24))+Declarations!$G$24*IF($B9>=Sale_t,1,0) -> 72.450154 | N9: =Declarations!$C$25+(Declarations!$H$25-Declarations!$C$25)*EXP(-Declarations!$D$25*$B9)+IF(Declarations!$E$25=0,0,Declarations!$E$25*($B9/Declarations!$F$25)*EXP(1-$B9/Declarations!$F$25))+Declarations!$G$25*IF($B9>=Sale_t,1,0) -> 64.285488 | O9: =W_L*S_L*C9+W_T*S_T*D9+W_E*S_E*E9+W_R*S_R*F9 -> 33.741185 | P9: =W_L*S_L*G9+W_T*S_T*H9+W_E*S_E*I9+W_R*S_R*J9 -> 37.359901 | Q9: =W_L*S_L*K9+W_T*S_T*L9+W_E*S_E*M9+W_R*S_R*N9 -> 37.371119 | R9: =IF(O9<Score_today,1,0) -> 1 | S9: =IF(O9>Q9,1,0) -> 0 | T9: =IF(O9>P9,1,0) -> 0 | U9: =1+IF(P9>O9,1,0)+IF(Q9>O9,1,0) -> 3 | V9: =ABS(P9-Q9) -> 0.011217194 | X9: Month digital passes the turnaround | Y9: =INDEX($A$5:$A$65,MATCH(1,$S$5:$S$65,0)) -> 33 | Z9: month 33
A10: 5 | B10: =A10/12 -> 0.41666667 | C10: =Declarations!$C$14+(Declarations!$H$14-Declarations!$C$14)*EXP(-Declarations!$D$14*$B10)+IF(Declarations!$E$14=0,0,Declarations!$E$14*($B10/Declarations!$F$14)*EXP(1-$B10/Declarations!$F$14))+Declarations!$G$14*IF($B10>=Sale_t,1,0) -> 88.753794 | D10: =Declarations!$C$15+(Declarations!$H$15-Declarations!$C$15)*EXP(-Declarations!$D$15*$B10)+IF(Declarations!$E$15=0,0,Declarations!$E$15*($B10/Declarations!$F$15)*EXP(1-$B10/Declarations!$F$15))+Declarations!$G$15*IF($B10>=Sale_t,1,0) -> 48.577748 | E10: =Declarations!$C$16+(Declarations!$H$16-Declarations!$C$16)*EXP(-Declarations!$D$16*$B10)+IF(Declarations!$E$16=0,0,Declarations!$E$16*($B10/Declarations!$F$16)*EXP(1-$B10/Declarations!$F$16))+Declarations!$G$16*IF($B10>=Sale_t,1,0) -> 66.980873 | F10: =Declarations!$C$17+(Declarations!$H$17-Declarations!$C$17)*EXP(-Declarations!$D$17*$B10)+IF(Declarations!$E$17=0,0,Declarations!$E$17*($B10/Declarations!$F$17)*EXP(1-$B10/Declarations!$F$17))+Declarations!$G$17*IF($B10>=Sale_t,1,0) -> 71.341821 | G10: =Declarations!$C$18+(Declarations!$H$18-Declarations!$C$18)*EXP(-Declarations!$D$18*$B10)+IF(Declarations!$E$18=0,0,Declarations!$E$18*($B10/Declarations!$F$18)*EXP(1-$B10/Declarations!$F$18))+Declarations!$G$18*IF($B10>=Sale_t,1,0) -> 100.47001 | H10: =Declarations!$C$19+(Declarations!$H$19-Declarations!$C$19)*EXP(-Declarations!$D$19*$B10)+IF(Declarations!$E$19=0,0,Declarations!$E$19*($B10/Declarations!$F$19)*EXP(1-$B10/Declarations!$F$19))+Declarations!$G$19*IF($B10>=Sale_t,1,0) -> 40.703225 | I10: =Declarations!$C$20+(Declarations!$H$20-Declarations!$C$20)*EXP(-Declarations!$D$20*$B10)+IF(Declarations!$E$20=0,0,Declarations!$E$20*($B10/Declarations!$F$20)*EXP(1-$B10/Declarations!$F$20))+Declarations!$G$20*IF($B10>=Sale_t,1,0) -> 71.512913 | J10: =Declarations!$C$21+(Declarations!$H$21-Declarations!$C$21)*EXP(-Declarations!$D$21*$B10)+IF(Declarations!$E$21=0,0,Declarations!$E$21*($B10/Declarations!$F$21)*EXP(1-$B10/Declarations!$F$21))+Declarations!$G$21*IF($B10>=Sale_t,1,0) -> 62.914414 | K10: =Declarations!$C$22+(Declarations!$H$22-Declarations!$C$22)*EXP(-Declarations!$D$22*$B10)+IF(Declarations!$E$22=0,0,Declarations!$E$22*($B10/Declarations!$F$22)*EXP(1-$B10/Declarations!$F$22))+Declarations!$G$22*IF($B10>=Sale_t,1,0) -> 101.02583 | L10: =Declarations!$C$23+(Declarations!$H$23-Declarations!$C$23)*EXP(-Declarations!$D$23*$B10)+IF(Declarations!$E$23=0,0,Declarations!$E$23*($B10/Declarations!$F$23)*EXP(1-$B10/Declarations!$F$23))+Declarations!$G$23*IF($B10>=Sale_t,1,0) -> 40.360355 | M10: =Declarations!$C$24+(Declarations!$H$24-Declarations!$C$24)*EXP(-Declarations!$D$24*$B10)+IF(Declarations!$E$24=0,0,Declarations!$E$24*($B10/Declarations!$F$24)*EXP(1-$B10/Declarations!$F$24))+Declarations!$G$24*IF($B10>=Sale_t,1,0) -> 72.769594 | N10: =Declarations!$C$25+(Declarations!$H$25-Declarations!$C$25)*EXP(-Declarations!$D$25*$B10)+IF(Declarations!$E$25=0,0,Declarations!$E$25*($B10/Declarations!$F$25)*EXP(1-$B10/Declarations!$F$25))+Declarations!$G$25*IF($B10>=Sale_t,1,0) -> 64.352509 | O10: =W_L*S_L*C10+W_T*S_T*D10+W_E*S_E*E10+W_R*S_R*F10 -> 33.242648 | P10: =W_L*S_L*G10+W_T*S_T*H10+W_E*S_E*I10+W_R*S_R*J10 -> 37.442934 | Q10: =W_L*S_L*K10+W_T*S_T*L10+W_E*S_E*M10+W_R*S_R*N10 -> 37.450816 | R10: =IF(O10<Score_today,1,0) -> 1 | S10: =IF(O10>Q10,1,0) -> 0 | T10: =IF(O10>P10,1,0) -> 0 | U10: =1+IF(P10>O10,1,0)+IF(Q10>O10,1,0) -> 3 | V10: =ABS(P10-Q10) -> 0.0078821577 | X10: Digital's score that month | Y10: =INDEX($O$5:$O$65,Y9+1) -> 38.742683 | Z10: 38.74
A11: 6 | B11: =A11/12 -> 0.5 | C11: =Declarations!$C$14+(Declarations!$H$14-Declarations!$C$14)*EXP(-Declarations!$D$14*$B11)+IF(Declarations!$E$14=0,0,Declarations!$E$14*($B11/Declarations!$F$14)*EXP(1-$B11/Declarations!$F$14))+Declarations!$G$14*IF($B11>=Sale_t,1,0) -> 87.107516 | D11: =Declarations!$C$15+(Declarations!$H$15-Declarations!$C$15)*EXP(-Declarations!$D$15*$B11)+IF(Declarations!$E$15=0,0,Declarations!$E$15*($B11/Declarations!$F$15)*EXP(1-$B11/Declarations!$F$15))+Declarations!$G$15*IF($B11>=Sale_t,1,0) -> 49.895831 | E11: =Declarations!$C$16+(Declarations!$H$16-Declarations!$C$16)*EXP(-Declarations!$D$16*$B11)+IF(Declarations!$E$16=0,0,Declarations!$E$16*($B11/Declarations!$F$16)*EXP(1-$B11/Declarations!$F$16))+Declarations!$G$16*IF($B11>=Sale_t,1,0) -> 66.483993 | F11: =Declarations!$C$17+(Declarations!$H$17-Declarations!$C$17)*EXP(-Declarations!$D$17*$B11)+IF(Declarations!$E$17=0,0,Declarations!$E$17*($B11/Declarations!$F$17)*EXP(1-$B11/Declarations!$F$17))+Declarations!$G$17*IF($B11>=Sale_t,1,0) -> 72.096844 | G11: =Declarations!$C$18+(Declarations!$H$18-Declarations!$C$18)*EXP(-Declarations!$D$18*$B11)+IF(Declarations!$E$18=0,0,Declarations!$E$18*($B11/Declarations!$F$18)*EXP(1-$B11/Declarations!$F$18))+Declarations!$G$18*IF($B11>=Sale_t,1,0) -> 100.55717 | H11: =Declarations!$C$19+(Declarations!$H$19-Declarations!$C$19)*EXP(-Declarations!$D$19*$B11)+IF(Declarations!$E$19=0,0,Declarations!$E$19*($B11/Declarations!$F$19)*EXP(1-$B11/Declarations!$F$19))+Declarations!$G$19*IF($B11>=Sale_t,1,0) -> 40.647491 | I11: =Declarations!$C$20+(Declarations!$H$20-Declarations!$C$20)*EXP(-Declarations!$D$20*$B11)+IF(Declarations!$E$20=0,0,Declarations!$E$20*($B11/Declarations!$F$20)*EXP(1-$B11/Declarations!$F$20))+Declarations!$G$20*IF($B11>=Sale_t,1,0) -> 71.604451 | J11: =Declarations!$C$21+(Declarations!$H$21-Declarations!$C$21)*EXP(-Declarations!$D$21*$B11)+IF(Declarations!$E$21=0,0,Declarations!$E$21*($B11/Declarations!$F$21)*EXP(1-$B11/Declarations!$F$21))+Declarations!$G$21*IF($B11>=Sale_t,1,0) -> 62.715656 | K11: =Declarations!$C$22+(Declarations!$H$22-Declarations!$C$22)*EXP(-Declarations!$D$22*$B11)+IF(Declarations!$E$22=0,0,Declarations!$E$22*($B11/Declarations!$F$22)*EXP(1-$B11/Declarations!$F$22))+Declarations!$G$22*IF($B11>=Sale_t,1,0) -> 101.2089 | L11: =Declarations!$C$23+(Declarations!$H$23-Declarations!$C$23)*EXP(-Declarations!$D$23*$B11)+IF(Declarations!$E$23=0,0,Declarations!$E$23*($B11/Declarations!$F$23)*EXP(1-$B11/Declarations!$F$23))+Declarations!$G$23*IF($B11>=Sale_t,1,0) -> 40.238699 | M11: =Declarations!$C$24+(Declarations!$H$24-Declarations!$C$24)*EXP(-Declarations!$D$24*$B11)+IF(Declarations!$E$24=0,0,Declarations!$E$24*($B11/Declarations!$F$24)*EXP(1-$B11/Declarations!$F$24))+Declarations!$G$24*IF($B11>=Sale_t,1,0) -> 73.073454 | N11: =Declarations!$C$25+(Declarations!$H$25-Declarations!$C$25)*EXP(-Declarations!$D$25*$B11)+IF(Declarations!$E$25=0,0,Declarations!$E$25*($B11/Declarations!$F$25)*EXP(1-$B11/Declarations!$F$25))+Declarations!$G$25*IF($B11>=Sale_t,1,0) -> 64.417876 | O11: =W_L*S_L*C11+W_T*S_T*D11+W_E*S_E*E11+W_R*S_R*F11 -> 32.847624 | P11: =W_L*S_L*G11+W_T*S_T*H11+W_E*S_E*I11+W_R*S_R*J11 -> 37.523363 | Q11: =W_L*S_L*K11+W_T*S_T*L11+W_E*S_E*M11+W_R*S_R*N11 -> 37.525795 | R11: =IF(O11<Score_today,1,0) -> 1 | S11: =IF(O11>Q11,1,0) -> 0 | T11: =IF(O11>P11,1,0) -> 0 | U11: =1+IF(P11>O11,1,0)+IF(Q11>O11,1,0) -> 3 | V11: =ABS(P11-Q11) -> 0.002431554 | X11: The turnaround's score that month | Y11: =INDEX($Q$5:$Q$65,Y9+1) -> 38.413313 | Z11: 38.41
A12: 7 | B12: =A12/12 -> 0.58333333 | C12: =Declarations!$C$14+(Declarations!$H$14-Declarations!$C$14)*EXP(-Declarations!$D$14*$B12)+IF(Declarations!$E$14=0,0,Declarations!$E$14*($B12/Declarations!$F$14)*EXP(1-$B12/Declarations!$F$14))+Declarations!$G$14*IF($B12>=Sale_t,1,0) -> 85.632816 | D12: =Declarations!$C$15+(Declarations!$H$15-Declarations!$C$15)*EXP(-Declarations!$D$15*$B12)+IF(Declarations!$E$15=0,0,Declarations!$E$15*($B12/Declarations!$F$15)*EXP(1-$B12/Declarations!$F$15))+Declarations!$G$15*IF($B12>=Sale_t,1,0) -> 51.154866 | E12: =Declarations!$C$16+(Declarations!$H$16-Declarations!$C$16)*EXP(-Declarations!$D$16*$B12)+IF(Declarations!$E$16=0,0,Declarations!$E$16*($B12/Declarations!$F$16)*EXP(1-$B12/Declarations!$F$16))+Declarations!$G$16*IF($B12>=Sale_t,1,0) -> 66.069224 | F12: =Declarations!$C$17+(Declarations!$H$17-Declarations!$C$17)*EXP(-Declarations!$D$17*$B12)+IF(Declarations!$E$17=0,0,Declarations!$E$17*($B12/Declarations!$F$17)*EXP(1-$B12/Declarations!$F$17))+Declarations!$G$17*IF($B12>=Sale_t,1,0) -> 72.671956 | G12: =Declarations!$C$18+(Declarations!$H$18-Declarations!$C$18)*EXP(-Declarations!$D$18*$B12)+IF(Declarations!$E$18=0,0,Declarations!$E$18*($B12/Declarations!$F$18)*EXP(1-$B12/Declarations!$F$18))+Declarations!$G$18*IF($B12>=Sale_t,1,0) -> 100.64217 | H12: =Declarations!$C$19+(Declarations!$H$19-Declarations!$C$19)*EXP(-Declarations!$D$19*$B12)+IF(Declarations!$E$19=0,0,Declarations!$E$19*($B12/Declarations!$F$19)*EXP(1-$B12/Declarations!$F$19))+Declarations!$G$19*IF($B12>=Sale_t,1,0) -> 40.592905 | I12: =Declarations!$C$20+(Declarations!$H$20-Declarations!$C$20)*EXP(-Declarations!$D$20*$B12)+IF(Declarations!$E$20=0,0,Declarations!$E$20*($B12/Declarations!$F$20)*EXP(1-$B12/Declarations!$F$20))+Declarations!$G$20*IF($B12>=Sale_t,1,0) -> 71.692621 | J12: =Declarations!$C$21+(Declarations!$H$21-Declarations!$C$21)*EXP(-Declarations!$D$21*$B12)+IF(Declarations!$E$21=0,0,Declarations!$E$21*($B12/Declarations!$F$21)*EXP(1-$B12/Declarations!$F$21))+Declarations!$G$21*IF($B12>=Sale_t,1,0) -> 62.522612 | K12: =Declarations!$C$22+(Declarations!$H$22-Declarations!$C$22)*EXP(-Declarations!$D$22*$B12)+IF(Declarations!$E$22=0,0,Declarations!$E$22*($B12/Declarations!$F$22)*EXP(1-$B12/Declarations!$F$22))+Declarations!$G$22*IF($B12>=Sale_t,1,0) -> 101.38524 | L12: =Declarations!$C$23+(Declarations!$H$23-Declarations!$C$23)*EXP(-Declarations!$D$23*$B12)+IF(Declarations!$E$23=0,0,Declarations!$E$23*($B12/Declarations!$F$23)*EXP(1-$B12/Declarations!$F$23))+Declarations!$G$23*IF($B12>=Sale_t,1,0) -> 40.119054 | M12: =Declarations!$C$24+(Declarations!$H$24-Declarations!$C$24)*EXP(-Declarations!$D$24*$B12)+IF(Declarations!$E$24=0,0,Declarations!$E$24*($B12/Declarations!$F$24)*EXP(1-$B12/Declarations!$F$24))+Declarations!$G$24*IF($B12>=Sale_t,1,0) -> 73.362495 | N12: =Declarations!$C$25+(Declarations!$H$25-Declarations!$C$25)*EXP(-Declarations!$D$25*$B12)+IF(Declarations!$E$25=0,0,Declarations!$E$25*($B12/Declarations!$F$25)*EXP(1-$B12/Declarations!$F$25))+Declarations!$G$25*IF($B12>=Sale_t,1,0) -> 64.481629 | O12: =W_L*S_L*C12+W_T*S_T*D12+W_E*S_E*E12+W_R*S_R*F12 -> 32.546237 | P12: =W_L*S_L*G12+W_T*S_T*H12+W_E*S_E*I12+W_R*S_R*J12 -> 37.601272 | Q12: =W_L*S_L*K12+W_T*S_T*L12+W_E*S_E*M12+W_R*S_R*N12 -> 37.596291 | R12: =IF(O12<Score_today,1,0) -> 1 | S12: =IF(O12>Q12,1,0) -> 0 | T12: =IF(O12>P12,1,0) -> 0 | U12: =1+IF(P12>O12,1,0)+IF(Q12>O12,1,0) -> 3 | V12: =ABS(P12-Q12) -> 0.0049809863 | X12: Month digital passes restructuring | Y12: =INDEX($A$5:$A$65,MATCH(1,$T$5:$T$65,0)) -> 56 | Z12: month 56
A13: 8 | B13: =A13/12 -> 0.66666667 | C13: =Declarations!$C$14+(Declarations!$H$14-Declarations!$C$14)*EXP(-Declarations!$D$14*$B13)+IF(Declarations!$E$14=0,0,Declarations!$E$14*($B13/Declarations!$F$14)*EXP(1-$B13/Declarations!$F$14))+Declarations!$G$14*IF($B13>=Sale_t,1,0) -> 84.318474 | D13: =Declarations!$C$15+(Declarations!$H$15-Declarations!$C$15)*EXP(-Declarations!$D$15*$B13)+IF(Declarations!$E$15=0,0,Declarations!$E$15*($B13/Declarations!$F$15)*EXP(1-$B13/Declarations!$F$15))+Declarations!$G$15*IF($B13>=Sale_t,1,0) -> 52.357497 | E13: =Declarations!$C$16+(Declarations!$H$16-Declarations!$C$16)*EXP(-Declarations!$D$16*$B13)+IF(Declarations!$E$16=0,0,Declarations!$E$16*($B13/Declarations!$F$16)*EXP(1-$B13/Declarations!$F$16))+Declarations!$G$16*IF($B13>=Sale_t,1,0) -> 65.729176 | F13: =Declarations!$C$17+(Declarations!$H$17-Declarations!$C$17)*EXP(-Declarations!$D$17*$B13)+IF(Declarations!$E$17=0,0,Declarations!$E$17*($B13/Declarations!$F$17)*EXP(1-$B13/Declarations!$F$17))+Declarations!$G$17*IF($B13>=Sale_t,1,0) -> 73.087473 | G13: =Declarations!$C$18+(Declarations!$H$18-Declarations!$C$18)*EXP(-Declarations!$D$18*$B13)+IF(Declarations!$E$18=0,0,Declarations!$E$18*($B13/Declarations!$F$18)*EXP(1-$B13/Declarations!$F$18))+Declarations!$G$18*IF($B13>=Sale_t,1,0) -> 100.72508 | H13: =Declarations!$C$19+(Declarations!$H$19-Declarations!$C$19)*EXP(-Declarations!$D$19*$B13)+IF(Declarations!$E$19=0,0,Declarations!$E$19*($B13/Declarations!$F$19)*EXP(1-$B13/Declarations!$F$19))+Declarations!$G$19*IF($B13>=Sale_t,1,0) -> 40.539445 | I13: =Declarations!$C$20+(Declarations!$H$20-Declarations!$C$20)*EXP(-Declarations!$D$20*$B13)+IF(Declarations!$E$20=0,0,Declarations!$E$20*($B13/Declarations!$F$20)*EXP(1-$B13/Declarations!$F$20))+Declarations!$G$20*IF($B13>=Sale_t,1,0) -> 71.777545 | J13: =Declarations!$C$21+(Declarations!$H$21-Declarations!$C$21)*EXP(-Declarations!$D$21*$B13)+IF(Declarations!$E$21=0,0,Declarations!$E$21*($B13/Declarations!$F$21)*EXP(1-$B13/Declarations!$F$21))+Declarations!$G$21*IF($B13>=Sale_t,1,0) -> 62.335117 | K13: =Declarations!$C$22+(Declarations!$H$22-Declarations!$C$22)*EXP(-Declarations!$D$22*$B13)+IF(Declarations!$E$22=0,0,Declarations!$E$22*($B13/Declarations!$F$22)*EXP(1-$B13/Declarations!$F$22))+Declarations!$G$22*IF($B13>=Sale_t,1,0) -> 101.55509 | L13: =Declarations!$C$23+(Declarations!$H$23-Declarations!$C$23)*EXP(-Declarations!$D$23*$B13)+IF(Declarations!$E$23=0,0,Declarations!$E$23*($B13/Declarations!$F$23)*EXP(1-$B13/Declarations!$F$23))+Declarations!$G$23*IF($B13>=Sale_t,1,0) -> 40.001387 | M13: =Declarations!$C$24+(Declarations!$H$24-Declarations!$C$24)*EXP(-Declarations!$D$24*$B13)+IF(Declarations!$E$24=0,0,Declarations!$E$24*($B13/Declarations!$F$24)*EXP(1-$B13/Declarations!$F$24))+Declarations!$G$24*IF($B13>=Sale_t,1,0) -> 73.63744 | N13: =Declarations!$C$25+(Declarations!$H$25-Declarations!$C$25)*EXP(-Declarations!$D$25*$B13)+IF(Declarations!$E$25=0,0,Declarations!$E$25*($B13/Declarations!$F$25)*EXP(1-$B13/Declarations!$F$25))+Declarations!$G$25*IF($B13>=Sale_t,1,0) -> 64.543808 | O13: =W_L*S_L*C13+W_T*S_T*D13+W_E*S_E*E13+W_R*S_R*F13 -> 32.329418 | P13: =W_L*S_L*G13+W_T*S_T*H13+W_E*S_E*I13+W_R*S_R*J13 -> 37.676738 | Q13: =W_L*S_L*K13+W_T*S_T*L13+W_E*S_E*M13+W_R*S_R*N13 -> 37.662527 | R13: =IF(O13<Score_today,1,0) -> 1 | S13: =IF(O13>Q13,1,0) -> 0 | T13: =IF(O13>P13,1,0) -> 0 | U13: =1+IF(P13>O13,1,0)+IF(Q13>O13,1,0) -> 3 | V13: =ABS(P13-Q13) -> 0.014210463 | X13: Digital's score that month | Y13: =INDEX($O$5:$O$65,Y12+1) -> 46.145379 | Z13: 46.15
A14: 9 | B14: =A14/12 -> 0.75 | C14: =Declarations!$C$14+(Declarations!$H$14-Declarations!$C$14)*EXP(-Declarations!$D$14*$B14)+IF(Declarations!$E$14=0,0,Declarations!$E$14*($B14/Declarations!$F$14)*EXP(1-$B14/Declarations!$F$14))+Declarations!$G$14*IF($B14>=Sale_t,1,0) -> 83.153901 | D14: =Declarations!$C$15+(Declarations!$H$15-Declarations!$C$15)*EXP(-Declarations!$D$15*$B14)+IF(Declarations!$E$15=0,0,Declarations!$E$15*($B14/Declarations!$F$15)*EXP(1-$B14/Declarations!$F$15))+Declarations!$G$15*IF($B14>=Sale_t,1,0) -> 53.506252 | E14: =Declarations!$C$16+(Declarations!$H$16-Declarations!$C$16)*EXP(-Declarations!$D$16*$B14)+IF(Declarations!$E$16=0,0,Declarations!$E$16*($B14/Declarations!$F$16)*EXP(1-$B14/Declarations!$F$16))+Declarations!$G$16*IF($B14>=Sale_t,1,0) -> 65.457019 | F14: =Declarations!$C$17+(Declarations!$H$17-Declarations!$C$17)*EXP(-Declarations!$D$17*$B14)+IF(Declarations!$E$17=0,0,Declarations!$E$17*($B14/Declarations!$F$17)*EXP(1-$B14/Declarations!$F$17))+Declarations!$G$17*IF($B14>=Sale_t,1,0) -> 73.361812 | G14: =Declarations!$C$18+(Declarations!$H$18-Declarations!$C$18)*EXP(-Declarations!$D$18*$B14)+IF(Declarations!$E$18=0,0,Declarations!$E$18*($B14/Declarations!$F$18)*EXP(1-$B14/Declarations!$F$18))+Declarations!$G$18*IF($B14>=Sale_t,1,0) -> 100.80594 | H14: =Declarations!$C$19+(Declarations!$H$19-Declarations!$C$19)*EXP(-Declarations!$D$19*$B14)+IF(Declarations!$E$19=0,0,Declarations!$E$19*($B14/Declarations!$F$19)*EXP(1-$B14/Declarations!$F$19))+Declarations!$G$19*IF($B14>=Sale_t,1,0) -> 40.487087 | I14: =Declarations!$C$20+(Declarations!$H$20-Declarations!$C$20)*EXP(-Declarations!$D$20*$B14)+IF(Declarations!$E$20=0,0,Declarations!$E$20*($B14/Declarations!$F$20)*EXP(1-$B14/Declarations!$F$20))+Declarations!$G$20*IF($B14>=Sale_t,1,0) -> 71.859344 | J14: =Declarations!$C$21+(Declarations!$H$21-Declarations!$C$21)*EXP(-Declarations!$D$21*$B14)+IF(Declarations!$E$21=0,0,Declarations!$E$21*($B14/Declarations!$F$21)*EXP(1-$B14/Declarations!$F$21))+Declarations!$G$21*IF($B14>=Sale_t,1,0) -> 62.153011 | K14: =Declarations!$C$22+(Declarations!$H$22-Declarations!$C$22)*EXP(-Declarations!$D$22*$B14)+IF(Declarations!$E$22=0,0,Declarations!$E$22*($B14/Declarations!$F$22)*EXP(1-$B14/Declarations!$F$22))+Declarations!$G$22*IF($B14>=Sale_t,1,0) -> 101.71869 | L14: =Declarations!$C$23+(Declarations!$H$23-Declarations!$C$23)*EXP(-Declarations!$D$23*$B14)+IF(Declarations!$E$23=0,0,Declarations!$E$23*($B14/Declarations!$F$23)*EXP(1-$B14/Declarations!$F$23))+Declarations!$G$23*IF($B14>=Sale_t,1,0) -> 39.885664 | M14: =Declarations!$C$24+(Declarations!$H$24-Declarations!$C$24)*EXP(-Declarations!$D$24*$B14)+IF(Declarations!$E$24=0,0,Declarations!$E$24*($B14/Declarations!$F$24)*EXP(1-$B14/Declarations!$F$24))+Declarations!$G$24*IF($B14>=Sale_t,1,0) -> 73.898975 | N14: =Declarations!$C$25+(Declarations!$H$25-Declarations!$C$25)*EXP(-Declarations!$D$25*$B14)+IF(Declarations!$E$25=0,0,Declarations!$E$25*($B14/Declarations!$F$25)*EXP(1-$B14/Declarations!$F$25))+Declarations!$G$25*IF($B14>=Sale_t,1,0) -> 64.604451 | O14: =W_L*S_L*C14+W_T*S_T*D14+W_E*S_E*E14+W_R*S_R*F14 -> 32.18884 | P14: =W_L*S_L*G14+W_T*S_T*H14+W_E*S_E*I14+W_R*S_R*J14 -> 37.749839 | Q14: =W_L*S_L*K14+W_T*S_T*L14+W_E*S_E*M14+W_R*S_R*N14 -> 37.724719 | R14: =IF(O14<Score_today,1,0) -> 1 | S14: =IF(O14>Q14,1,0) -> 0 | T14: =IF(O14>P14,1,0) -> 0 | U14: =1+IF(P14>O14,1,0)+IF(Q14>O14,1,0) -> 3 | V14: =ABS(P14-Q14) -> 0.025120058 | X14: Restructuring's score that month | Y14: =INDEX($P$5:$P$65,Y12+1) -> 46.004558
A15: 10 | B15: =A15/12 -> 0.83333333 | C15: =Declarations!$C$14+(Declarations!$H$14-Declarations!$C$14)*EXP(-Declarations!$D$14*$B15)+IF(Declarations!$E$14=0,0,Declarations!$E$14*($B15/Declarations!$F$14)*EXP(1-$B15/Declarations!$F$14))+Declarations!$G$14*IF($B15>=Sale_t,1,0) -> 82.129102 | D15: =Declarations!$C$15+(Declarations!$H$15-Declarations!$C$15)*EXP(-Declarations!$D$15*$B15)+IF(Declarations!$E$15=0,0,Declarations!$E$15*($B15/Declarations!$F$15)*EXP(1-$B15/Declarations!$F$15))+Declarations!$G$15*IF($B15>=Sale_t,1,0) -> 54.603543 | E15: =Declarations!$C$16+(Declarations!$H$16-Declarations!$C$16)*EXP(-Declarations!$D$16*$B15)+IF(Declarations!$E$16=0,0,Declarations!$E$16*($B15/Declarations!$F$16)*EXP(1-$B15/Declarations!$F$16))+Declarations!$G$16*IF($B15>=Sale_t,1,0) -> 65.246439 | F15: =Declarations!$C$17+(Declarations!$H$17-Declarations!$C$17)*EXP(-Declarations!$D$17*$B15)+IF(Declarations!$E$17=0,0,Declarations!$E$17*($B15/Declarations!$F$17)*EXP(1-$B15/Declarations!$F$17))+Declarations!$G$17*IF($B15>=Sale_t,1,0) -> 73.511646 | G15: =Declarations!$C$18+(Declarations!$H$18-Declarations!$C$18)*EXP(-Declarations!$D$18*$B15)+IF(Declarations!$E$18=0,0,Declarations!$E$18*($B15/Declarations!$F$18)*EXP(1-$B15/Declarations!$F$18))+Declarations!$G$18*IF($B15>=Sale_t,1,0) -> 100.8848 | H15: =Declarations!$C$19+(Declarations!$H$19-Declarations!$C$19)*EXP(-Declarations!$D$19*$B15)+IF(Declarations!$E$19=0,0,Declarations!$E$19*($B15/Declarations!$F$19)*EXP(1-$B15/Declarations!$F$19))+Declarations!$G$19*IF($B15>=Sale_t,1,0) -> 40.435809 | I15: =Declarations!$C$20+(Declarations!$H$20-Declarations!$C$20)*EXP(-Declarations!$D$20*$B15)+IF(Declarations!$E$20=0,0,Declarations!$E$20*($B15/Declarations!$F$20)*EXP(1-$B15/Declarations!$F$20))+Declarations!$G$20*IF($B15>=Sale_t,1,0) -> 71.938132 | J15: =Declarations!$C$21+(Declarations!$H$21-Declarations!$C$21)*EXP(-Declarations!$D$21*$B15)+IF(Declarations!$E$21=0,0,Declarations!$E$21*($B15/Declarations!$F$21)*EXP(1-$B15/Declarations!$F$21))+Declarations!$G$21*IF($B15>=Sale_t,1,0) -> 61.97614 | K15: =Declarations!$C$22+(Declarations!$H$22-Declarations!$C$22)*EXP(-Declarations!$D$22*$B15)+IF(Declarations!$E$22=0,0,Declarations!$E$22*($B15/Declarations!$F$22)*EXP(1-$B15/Declarations!$F$22))+Declarations!$G$22*IF($B15>=Sale_t,1,0) -> 101.87626 | L15: =Declarations!$C$23+(Declarations!$H$23-Declarations!$C$23)*EXP(-Declarations!$D$23*$B15)+IF(Declarations!$E$23=0,0,Declarations!$E$23*($B15/Declarations!$F$23)*EXP(1-$B15/Declarations!$F$23))+Declarations!$G$23*IF($B15>=Sale_t,1,0) -> 39.771854 | M15: =Declarations!$C$24+(Declarations!$H$24-Declarations!$C$24)*EXP(-Declarations!$D$24*$B15)+IF(Declarations!$E$24=0,0,Declarations!$E$24*($B15/Declarations!$F$24)*EXP(1-$B15/Declarations!$F$24))+Declarations!$G$24*IF($B15>=Sale_t,1,0) -> 74.147755 | N15: =Declarations!$C$25+(Declarations!$H$25-Declarations!$C$25)*EXP(-Declarations!$D$25*$B15)+IF(Declarations!$E$25=0,0,Declarations!$E$25*($B15/Declarations!$F$25)*EXP(1-$B15/Declarations!$F$25))+Declarations!$G$25*IF($B15>=Sale_t,1,0) -> 64.663598 | O15: =W_L*S_L*C15+W_T*S_T*D15+W_E*S_E*E15+W_R*S_R*F15 -> 32.116859 | P15: =W_L*S_L*G15+W_T*S_T*H15+W_E*S_E*I15+W_R*S_R*J15 -> 37.82065 | Q15: =W_L*S_L*K15+W_T*S_T*L15+W_E*S_E*M15+W_R*S_R*N15 -> 37.783069 | R15: =IF(O15<Score_today,1,0) -> 1 | S15: =IF(O15>Q15,1,0) -> 0 | T15: =IF(O15>P15,1,0) -> 0 | U15: =1+IF(P15>O15,1,0)+IF(Q15>O15,1,0) -> 3 | V15: =ABS(P15-Q15) -> 0.037580717 | X15: Restructuring's jump when the sale closes (month 12 less month 11) | Y15: =P17-P16 -> 6.5664434 | Z15: +6.57
A16: 11 | B16: =A16/12 -> 0.91666667 | C16: =Declarations!$C$14+(Declarations!$H$14-Declarations!$C$14)*EXP(-Declarations!$D$14*$B16)+IF(Declarations!$E$14=0,0,Declarations!$E$14*($B16/Declarations!$F$14)*EXP(1-$B16/Declarations!$F$14))+Declarations!$G$14*IF($B16>=Sale_t,1,0) -> 81.234648 | D16: =Declarations!$C$15+(Declarations!$H$15-Declarations!$C$15)*EXP(-Declarations!$D$15*$B16)+IF(Declarations!$E$15=0,0,Declarations!$E$15*($B16/Declarations!$F$15)*EXP(1-$B16/Declarations!$F$15))+Declarations!$G$15*IF($B16>=Sale_t,1,0) -> 55.651678 | E16: =Declarations!$C$16+(Declarations!$H$16-Declarations!$C$16)*EXP(-Declarations!$D$16*$B16)+IF(Declarations!$E$16=0,0,Declarations!$E$16*($B16/Declarations!$F$16)*EXP(1-$B16/Declarations!$F$16))+Declarations!$G$16*IF($B16>=Sale_t,1,0) -> 65.091607 | F16: =Declarations!$C$17+(Declarations!$H$17-Declarations!$C$17)*EXP(-Declarations!$D$17*$B16)+IF(Declarations!$E$17=0,0,Declarations!$E$17*($B16/Declarations!$F$17)*EXP(1-$B16/Declarations!$F$17))+Declarations!$G$17*IF($B16>=Sale_t,1,0) -> 73.552064 | G16: =Declarations!$C$18+(Declarations!$H$18-Declarations!$C$18)*EXP(-Declarations!$D$18*$B16)+IF(Declarations!$E$18=0,0,Declarations!$E$18*($B16/Declarations!$F$18)*EXP(1-$B16/Declarations!$F$18))+Declarations!$G$18*IF($B16>=Sale_t,1,0) -> 100.96171 | H16: =Declarations!$C$19+(Declarations!$H$19-Declarations!$C$19)*EXP(-Declarations!$D$19*$B16)+IF(Declarations!$E$19=0,0,Declarations!$E$19*($B16/Declarations!$F$19)*EXP(1-$B16/Declarations!$F$19))+Declarations!$G$19*IF($B16>=Sale_t,1,0) -> 40.385588 | I16: =Declarations!$C$20+(Declarations!$H$20-Declarations!$C$20)*EXP(-Declarations!$D$20*$B16)+IF(Declarations!$E$20=0,0,Declarations!$E$20*($B16/Declarations!$F$20)*EXP(1-$B16/Declarations!$F$20))+Declarations!$G$20*IF($B16>=Sale_t,1,0) -> 72.01402 | J16: =Declarations!$C$21+(Declarations!$H$21-Declarations!$C$21)*EXP(-Declarations!$D$21*$B16)+IF(Declarations!$E$21=0,0,Declarations!$E$21*($B16/Declarations!$F$21)*EXP(1-$B16/Declarations!$F$21))+Declarations!$G$21*IF($B16>=Sale_t,1,0) -> 61.804353 | K16: =Declarations!$C$22+(Declarations!$H$22-Declarations!$C$22)*EXP(-Declarations!$D$22*$B16)+IF(Declarations!$E$22=0,0,Declarations!$E$22*($B16/Declarations!$F$22)*EXP(1-$B16/Declarations!$F$22))+Declarations!$G$22*IF($B16>=Sale_t,1,0) -> 102.02804 | L16: =Declarations!$C$23+(Declarations!$H$23-Declarations!$C$23)*EXP(-Declarations!$D$23*$B16)+IF(Declarations!$E$23=0,0,Declarations!$E$23*($B16/Declarations!$F$23)*EXP(1-$B16/Declarations!$F$23))+Declarations!$G$23*IF($B16>=Sale_t,1,0) -> 39.659925 | M16: =Declarations!$C$24+(Declarations!$H$24-Declarations!$C$24)*EXP(-Declarations!$D$24*$B16)+IF(Declarations!$E$24=0,0,Declarations!$E$24*($B16/Declarations!$F$24)*EXP(1-$B16/Declarations!$F$24))+Declarations!$G$24*IF($B16>=Sale_t,1,0) -> 74.384402 | N16: =Declarations!$C$25+(Declarations!$H$25-Declarations!$C$25)*EXP(-Declarations!$D$25*$B16)+IF(Declarations!$E$25=0,0,Declarations!$E$25*($B16/Declarations!$F$25)*EXP(1-$B16/Declarations!$F$25))+Declarations!$G$25*IF($B16>=Sale_t,1,0) -> 64.721284 | O16: =W_L*S_L*C16+W_T*S_T*D16+W_E*S_E*E16+W_R*S_R*F16 -> 32.106467 | P16: =W_L*S_L*G16+W_T*S_T*H16+W_E*S_E*I16+W_R*S_R*J16 -> 37.889242 | Q16: =W_L*S_L*K16+W_T*S_T*L16+W_E*S_E*M16+W_R*S_R*N16 -> 37.837771 | R16: =IF(O16<Score_today,1,0) -> 1 | S16: =IF(O16>Q16,1,0) -> 0 | T16: =IF(O16>P16,1,0) -> 0 | U16: =1+IF(P16>O16,1,0)+IF(Q16>O16,1,0) -> 3 | V16: =ABS(P16-Q16) -> 0.05147074 | X16: Largest gap, restructuring and turnaround, before the sale | Y16: =MAX(V5:V16) -> 0.05147074 | Z16: less than 0.1 point
A17: 12 | B17: =A17/12 -> 1 | C17: =Declarations!$C$14+(Declarations!$H$14-Declarations!$C$14)*EXP(-Declarations!$D$14*$B17)+IF(Declarations!$E$14=0,0,Declarations!$E$14*($B17/Declarations!$F$14)*EXP(1-$B17/Declarations!$F$14))+Declarations!$G$14*IF($B17>=Sale_t,1,0) -> 80.461645 | D17: =Declarations!$C$15+(Declarations!$H$15-Declarations!$C$15)*EXP(-Declarations!$D$15*$B17)+IF(Declarations!$E$15=0,0,Declarations!$E$15*($B17/Declarations!$F$15)*EXP(1-$B17/Declarations!$F$15))+Declarations!$G$15*IF($B17>=Sale_t,1,0) -> 56.652857 | E17: =Declarations!$C$16+(Declarations!$H$16-Declarations!$C$16)*EXP(-Declarations!$D$16*$B17)+IF(Declarations!$E$16=0,0,Declarations!$E$16*($B17/Declarations!$F$16)*EXP(1-$B17/Declarations!$F$16))+Declarations!$G$16*IF($B17>=Sale_t,1,0) -> 64.987141 | F17: =Declarations!$C$17+(Declarations!$H$17-Declarations!$C$17)*EXP(-Declarations!$D$17*$B17)+IF(Declarations!$E$17=0,0,Declarations!$E$17*($B17/Declarations!$F$17)*EXP(1-$B17/Declarations!$F$17))+Declarations!$G$17*IF($B17>=Sale_t,1,0) -> 73.496699 | G17: =Declarations!$C$18+(Declarations!$H$18-Declarations!$C$18)*EXP(-Declarations!$D$18*$B17)+IF(Declarations!$E$18=0,0,Declarations!$E$18*($B17/Declarations!$F$18)*EXP(1-$B17/Declarations!$F$18))+Declarations!$G$18*IF($B17>=Sale_t,1,0) -> 119.03673 | H17: =Declarations!$C$19+(Declarations!$H$19-Declarations!$C$19)*EXP(-Declarations!$D$19*$B17)+IF(Declarations!$E$19=0,0,Declarations!$E$19*($B17/Declarations!$F$19)*EXP(1-$B17/Declarations!$F$19))+Declarations!$G$19*IF($B17>=Sale_t,1,0) -> 40.336402 | I17: =Declarations!$C$20+(Declarations!$H$20-Declarations!$C$20)*EXP(-Declarations!$D$20*$B17)+IF(Declarations!$E$20=0,0,Declarations!$E$20*($B17/Declarations!$F$20)*EXP(1-$B17/Declarations!$F$20))+Declarations!$G$20*IF($B17>=Sale_t,1,0) -> 72.087116 | J17: =Declarations!$C$21+(Declarations!$H$21-Declarations!$C$21)*EXP(-Declarations!$D$21*$B17)+IF(Declarations!$E$21=0,0,Declarations!$E$21*($B17/Declarations!$F$21)*EXP(1-$B17/Declarations!$F$21))+Declarations!$G$21*IF($B17>=Sale_t,1,0) -> 53.637505 | K17: =Declarations!$C$22+(Declarations!$H$22-Declarations!$C$22)*EXP(-Declarations!$D$22*$B17)+IF(Declarations!$E$22=0,0,Declarations!$E$22*($B17/Declarations!$F$22)*EXP(1-$B17/Declarations!$F$22))+Declarations!$G$22*IF($B17>=Sale_t,1,0) -> 102.17423 | L17: =Declarations!$C$23+(Declarations!$H$23-Declarations!$C$23)*EXP(-Declarations!$D$23*$B17)+IF(Declarations!$E$23=0,0,Declarations!$E$23*($B17/Declarations!$F$23)*EXP(1-$B17/Declarations!$F$23))+Declarations!$G$23*IF($B17>=Sale_t,1,0) -> 39.549846 | M17: =Declarations!$C$24+(Declarations!$H$24-Declarations!$C$24)*EXP(-Declarations!$D$24*$B17)+IF(Declarations!$E$24=0,0,Declarations!$E$24*($B17/Declarations!$F$24)*EXP(1-$B17/Declarations!$F$24))+Declarations!$G$24*IF($B17>=Sale_t,1,0) -> 74.609507 | N17: =Declarations!$C$25+(Declarations!$H$25-Declarations!$C$25)*EXP(-Declarations!$D$25*$B17)+IF(Declarations!$E$25=0,0,Declarations!$E$25*($B17/Declarations!$F$25)*EXP(1-$B17/Declarations!$F$25))+Declarations!$G$25*IF($B17>=Sale_t,1,0) -> 64.777545 | O17: =W_L*S_L*C17+W_T*S_T*D17+W_E*S_E*E17+W_R*S_R*F17 -> 32.151236 | P17: =W_L*S_L*G17+W_T*S_T*H17+W_E*S_E*I17+W_R*S_R*J17 -> 44.455685 | Q17: =W_L*S_L*K17+W_T*S_T*L17+W_E*S_E*M17+W_R*S_R*N17 -> 37.88901 | R17: =IF(O17<Score_today,1,0) -> 1 | S17: =IF(O17>Q17,1,0) -> 0 | T17: =IF(O17>P17,1,0) -> 0 | U17: =1+IF(P17>O17,1,0)+IF(Q17>O17,1,0) -> 3 | V17: =ABS(P17-Q17) -> 6.5666754
A18: 13 | B18: =A18/12 -> 1.0833333 | C18: =Declarations!$C$14+(Declarations!$H$14-Declarations!$C$14)*EXP(-Declarations!$D$14*$B18)+IF(Declarations!$E$14=0,0,Declarations!$E$14*($B18/Declarations!$F$14)*EXP(1-$B18/Declarations!$F$14))+Declarations!$G$14*IF($B18>=Sale_t,1,0) -> 79.801708 | D18: =Declarations!$C$15+(Declarations!$H$15-Declarations!$C$15)*EXP(-Declarations!$D$15*$B18)+IF(Declarations!$E$15=0,0,Declarations!$E$15*($B18/Declarations!$F$15)*EXP(1-$B18/Declarations!$F$15))+Declarations!$G$15*IF($B18>=Sale_t,1,0) -> 57.609184 | E18: =Declarations!$C$16+(Declarations!$H$16-Declarations!$C$16)*EXP(-Declarations!$D$16*$B18)+IF(Declarations!$E$16=0,0,Declarations!$E$16*($B18/Declarations!$F$16)*EXP(1-$B18/Declarations!$F$16))+Declarations!$G$16*IF($B18>=Sale_t,1,0) -> 64.92808 | F18: =Declarations!$C$17+(Declarations!$H$17-Declarations!$C$17)*EXP(-Declarations!$D$17*$B18)+IF(Declarations!$E$17=0,0,Declarations!$E$17*($B18/Declarations!$F$17)*EXP(1-$B18/Declarations!$F$17))+Declarations!$G$17*IF($B18>=Sale_t,1,0) -> 73.357862 | G18: =Declarations!$C$18+(Declarations!$H$18-Declarations!$C$18)*EXP(-Declarations!$D$18*$B18)+IF(Declarations!$E$18=0,0,Declarations!$E$18*($B18/Declarations!$F$18)*EXP(1-$B18/Declarations!$F$18))+Declarations!$G$18*IF($B18>=Sale_t,1,0) -> 119.10989 | H18: =Declarations!$C$19+(Declarations!$H$19-Declarations!$C$19)*EXP(-Declarations!$D$19*$B18)+IF(Declarations!$E$19=0,0,Declarations!$E$19*($B18/Declarations!$F$19)*EXP(1-$B18/Declarations!$F$19))+Declarations!$G$19*IF($B18>=Sale_t,1,0) -> 40.288231 | I18: =Declarations!$C$20+(Declarations!$H$20-Declarations!$C$20)*EXP(-Declarations!$D$20*$B18)+IF(Declarations!$E$20=0,0,Declarations!$E$20*($B18/Declarations!$F$20)*EXP(1-$B18/Declarations!$F$20))+Declarations!$G$20*IF($B18>=Sale_t,1,0) -> 72.15752 | J18: =Declarations!$C$21+(Declarations!$H$21-Declarations!$C$21)*EXP(-Declarations!$D$21*$B18)+IF(Declarations!$E$21=0,0,Declarations!$E$21*($B18/Declarations!$F$21)*EXP(1-$B18/Declarations!$F$21))+Declarations!$G$21*IF($B18>=Sale_t,1,0) -> 53.475452 | K18: =Declarations!$C$22+(Declarations!$H$22-Declarations!$C$22)*EXP(-Declarations!$D$22*$B18)+IF(Declarations!$E$22=0,0,Declarations!$E$22*($B18/Declarations!$F$22)*EXP(1-$B18/Declarations!$F$22))+Declarations!$G$22*IF($B18>=Sale_t,1,0) -> 102.31504 | L18: =Declarations!$C$23+(Declarations!$H$23-Declarations!$C$23)*EXP(-Declarations!$D$23*$B18)+IF(Declarations!$E$23=0,0,Declarations!$E$23*($B18/Declarations!$F$23)*EXP(1-$B18/Declarations!$F$23))+Declarations!$G$23*IF($B18>=Sale_t,1,0) -> 39.441587 | M18: =Declarations!$C$24+(Declarations!$H$24-Declarations!$C$24)*EXP(-Declarations!$D$24*$B18)+IF(Declarations!$E$24=0,0,Declarations!$E$24*($B18/Declarations!$F$24)*EXP(1-$B18/Declarations!$F$24))+Declarations!$G$24*IF($B18>=Sale_t,1,0) -> 74.823634 | N18: =Declarations!$C$25+(Declarations!$H$25-Declarations!$C$25)*EXP(-Declarations!$D$25*$B18)+IF(Declarations!$E$25=0,0,Declarations!$E$25*($B18/Declarations!$F$25)*EXP(1-$B18/Declarations!$F$25))+Declarations!$G$25*IF($B18>=Sale_t,1,0) -> 64.832418 | O18: =W_L*S_L*C18+W_T*S_T*D18+W_E*S_E*E18+W_R*S_R*F18 -> 32.245278 | P18: =W_L*S_L*G18+W_T*S_T*H18+W_E*S_E*I18+W_R*S_R*J18 -> 44.520047 | Q18: =W_L*S_L*K18+W_T*S_T*L18+W_E*S_E*M18+W_R*S_R*N18 -> 37.936961 | R18: =IF(O18<Score_today,1,0) -> 1 | S18: =IF(O18>Q18,1,0) -> 0 | T18: =IF(O18>P18,1,0) -> 0 | U18: =1+IF(P18>O18,1,0)+IF(Q18>O18,1,0) -> 3 | V18: =ABS(P18-Q18) -> 6.5830866
A19: 14 | B19: =A19/12 -> 1.1666667 | C19: =Declarations!$C$14+(Declarations!$H$14-Declarations!$C$14)*EXP(-Declarations!$D$14*$B19)+IF(Declarations!$E$14=0,0,Declarations!$E$14*($B19/Declarations!$F$14)*EXP(1-$B19/Declarations!$F$14))+Declarations!$G$14*IF($B19>=Sale_t,1,0) -> 79.246932 | D19: =Declarations!$C$15+(Declarations!$H$15-Declarations!$C$15)*EXP(-Declarations!$D$15*$B19)+IF(Declarations!$E$15=0,0,Declarations!$E$15*($B19/Declarations!$F$15)*EXP(1-$B19/Declarations!$F$15))+Declarations!$G$15*IF($B19>=Sale_t,1,0) -> 58.52267 | E19: =Declarations!$C$16+(Declarations!$H$16-Declarations!$C$16)*EXP(-Declarations!$D$16*$B19)+IF(Declarations!$E$16=0,0,Declarations!$E$16*($B19/Declarations!$F$16)*EXP(1-$B19/Declarations!$F$16))+Declarations!$G$16*IF($B19>=Sale_t,1,0) -> 64.909847 | F19: =Declarations!$C$17+(Declarations!$H$17-Declarations!$C$17)*EXP(-Declarations!$D$17*$B19)+IF(Declarations!$E$17=0,0,Declarations!$E$17*($B19/Declarations!$F$17)*EXP(1-$B19/Declarations!$F$17))+Declarations!$G$17*IF($B19>=Sale_t,1,0) -> 73.146656 | G19: =Declarations!$C$18+(Declarations!$H$18-Declarations!$C$18)*EXP(-Declarations!$D$18*$B19)+IF(Declarations!$E$18=0,0,Declarations!$E$18*($B19/Declarations!$F$18)*EXP(1-$B19/Declarations!$F$18))+Declarations!$G$18*IF($B19>=Sale_t,1,0) -> 119.18125 | H19: =Declarations!$C$19+(Declarations!$H$19-Declarations!$C$19)*EXP(-Declarations!$D$19*$B19)+IF(Declarations!$E$19=0,0,Declarations!$E$19*($B19/Declarations!$F$19)*EXP(1-$B19/Declarations!$F$19))+Declarations!$G$19*IF($B19>=Sale_t,1,0) -> 40.241053 | I19: =Declarations!$C$20+(Declarations!$H$20-Declarations!$C$20)*EXP(-Declarations!$D$20*$B19)+IF(Declarations!$E$20=0,0,Declarations!$E$20*($B19/Declarations!$F$20)*EXP(1-$B19/Declarations!$F$20))+Declarations!$G$20*IF($B19>=Sale_t,1,0) -> 72.225334 | J19: =Declarations!$C$21+(Declarations!$H$21-Declarations!$C$21)*EXP(-Declarations!$D$21*$B19)+IF(Declarations!$E$21=0,0,Declarations!$E$21*($B19/Declarations!$F$21)*EXP(1-$B19/Declarations!$F$21))+Declarations!$G$21*IF($B19>=Sale_t,1,0) -> 53.318058 | K19: =Declarations!$C$22+(Declarations!$H$22-Declarations!$C$22)*EXP(-Declarations!$D$22*$B19)+IF(Declarations!$E$22=0,0,Declarations!$E$22*($B19/Declarations!$F$22)*EXP(1-$B19/Declarations!$F$22))+Declarations!$G$22*IF($B19>=Sale_t,1,0) -> 102.45067 | L19: =Declarations!$C$23+(Declarations!$H$23-Declarations!$C$23)*EXP(-Declarations!$D$23*$B19)+IF(Declarations!$E$23=0,0,Declarations!$E$23*($B19/Declarations!$F$23)*EXP(1-$B19/Declarations!$F$23))+Declarations!$G$23*IF($B19>=Sale_t,1,0) -> 39.335117 | M19: =Declarations!$C$24+(Declarations!$H$24-Declarations!$C$24)*EXP(-Declarations!$D$24*$B19)+IF(Declarations!$E$24=0,0,Declarations!$E$24*($B19/Declarations!$F$24)*EXP(1-$B19/Declarations!$F$24))+Declarations!$G$24*IF($B19>=Sale_t,1,0) -> 75.027318 | N19: =Declarations!$C$25+(Declarations!$H$25-Declarations!$C$25)*EXP(-Declarations!$D$25*$B19)+IF(Declarations!$E$25=0,0,Declarations!$E$25*($B19/Declarations!$F$25)*EXP(1-$B19/Declarations!$F$25))+Declarations!$G$25*IF($B19>=Sale_t,1,0) -> 64.885936 | O19: =W_L*S_L*C19+W_T*S_T*D19+W_E*S_E*E19+W_R*S_R*F19 -> 32.383198 | P19: =W_L*S_L*G19+W_T*S_T*H19+W_E*S_E*I19+W_R*S_R*J19 -> 44.582394 | Q19: =W_L*S_L*K19+W_T*S_T*L19+W_E*S_E*M19+W_R*S_R*N19 -> 37.981792 | R19: =IF(O19<Score_today,1,0) -> 1 | S19: =IF(O19>Q19,1,0) -> 0 | T19: =IF(O19>P19,1,0) -> 0 | U19: =1+IF(P19>O19,1,0)+IF(Q19>O19,1,0) -> 3 | V19: =ABS(P19-Q19) -> 6.6006025
A20: 15 | B20: =A20/12 -> 1.25 | C20: =Declarations!$C$14+(Declarations!$H$14-Declarations!$C$14)*EXP(-Declarations!$D$14*$B20)+IF(Declarations!$E$14=0,0,Declarations!$E$14*($B20/Declarations!$F$14)*EXP(1-$B20/Declarations!$F$14))+Declarations!$G$14*IF($B20>=Sale_t,1,0) -> 78.789868 | D20: =Declarations!$C$15+(Declarations!$H$15-Declarations!$C$15)*EXP(-Declarations!$D$15*$B20)+IF(Declarations!$E$15=0,0,Declarations!$E$15*($B20/Declarations!$F$15)*EXP(1-$B20/Declarations!$F$15))+Declarations!$G$15*IF($B20>=Sale_t,1,0) -> 59.395232 | E20: =Declarations!$C$16+(Declarations!$H$16-Declarations!$C$16)*EXP(-Declarations!$D$16*$B20)+IF(Declarations!$E$16=0,0,Declarations!$E$16*($B20/Declarations!$F$16)*EXP(1-$B20/Declarations!$F$16))+Declarations!$G$16*IF($B20>=Sale_t,1,0) -> 64.928228 | F20: =Declarations!$C$17+(Declarations!$H$17-Declarations!$C$17)*EXP(-Declarations!$D$17*$B20)+IF(Declarations!$E$17=0,0,Declarations!$E$17*($B20/Declarations!$F$17)*EXP(1-$B20/Declarations!$F$17))+Declarations!$G$17*IF($B20>=Sale_t,1,0) -> 72.873078 | G20: =Declarations!$C$18+(Declarations!$H$18-Declarations!$C$18)*EXP(-Declarations!$D$18*$B20)+IF(Declarations!$E$18=0,0,Declarations!$E$18*($B20/Declarations!$F$18)*EXP(1-$B20/Declarations!$F$18))+Declarations!$G$18*IF($B20>=Sale_t,1,0) -> 119.25084 | H20: =Declarations!$C$19+(Declarations!$H$19-Declarations!$C$19)*EXP(-Declarations!$D$19*$B20)+IF(Declarations!$E$19=0,0,Declarations!$E$19*($B20/Declarations!$F$19)*EXP(1-$B20/Declarations!$F$19))+Declarations!$G$19*IF($B20>=Sale_t,1,0) -> 40.194847 | I20: =Declarations!$C$20+(Declarations!$H$20-Declarations!$C$20)*EXP(-Declarations!$D$20*$B20)+IF(Declarations!$E$20=0,0,Declarations!$E$20*($B20/Declarations!$F$20)*EXP(1-$B20/Declarations!$F$20))+Declarations!$G$20*IF($B20>=Sale_t,1,0) -> 72.290652 | J20: =Declarations!$C$21+(Declarations!$H$21-Declarations!$C$21)*EXP(-Declarations!$D$21*$B20)+IF(Declarations!$E$21=0,0,Declarations!$E$21*($B20/Declarations!$F$21)*EXP(1-$B20/Declarations!$F$21))+Declarations!$G$21*IF($B20>=Sale_t,1,0) -> 53.165188 | K20: =Declarations!$C$22+(Declarations!$H$22-Declarations!$C$22)*EXP(-Declarations!$D$22*$B20)+IF(Declarations!$E$22=0,0,Declarations!$E$22*($B20/Declarations!$F$22)*EXP(1-$B20/Declarations!$F$22))+Declarations!$G$22*IF($B20>=Sale_t,1,0) -> 102.5813 | L20: =Declarations!$C$23+(Declarations!$H$23-Declarations!$C$23)*EXP(-Declarations!$D$23*$B20)+IF(Declarations!$E$23=0,0,Declarations!$E$23*($B20/Declarations!$F$23)*EXP(1-$B20/Declarations!$F$23))+Declarations!$G$23*IF($B20>=Sale_t,1,0) -> 39.230406 | M20: =Declarations!$C$24+(Declarations!$H$24-Declarations!$C$24)*EXP(-Declarations!$D$24*$B20)+IF(Declarations!$E$24=0,0,Declarations!$E$24*($B20/Declarations!$F$24)*EXP(1-$B20/Declarations!$F$24))+Declarations!$G$24*IF($B20>=Sale_t,1,0) -> 75.221068 | N20: =Declarations!$C$25+(Declarations!$H$25-Declarations!$C$25)*EXP(-Declarations!$D$25*$B20)+IF(Declarations!$E$25=0,0,Declarations!$E$25*($B20/Declarations!$F$25)*EXP(1-$B20/Declarations!$F$25))+Declarations!$G$25*IF($B20>=Sale_t,1,0) -> 64.938132 | O20: =W_L*S_L*C20+W_T*S_T*D20+W_E*S_E*E20+W_R*S_R*F20 -> 32.560062 | P20: =W_L*S_L*G20+W_T*S_T*H20+W_E*S_E*I20+W_R*S_R*J20 -> 44.642788 | Q20: =W_L*S_L*K20+W_T*S_T*L20+W_E*S_E*M20+W_R*S_R*N20 -> 38.023661 | R20: =IF(O20<Score_today,1,0) -> 1 | S20: =IF(O20>Q20,1,0) -> 0 | T20: =IF(O20>P20,1,0) -> 0 | U20: =1+IF(P20>O20,1,0)+IF(Q20>O20,1,0) -> 3 | V20: =ABS(P20-Q20) -> 6.6191271
A21: 16 | B21: =A21/12 -> 1.3333333 | C21: =Declarations!$C$14+(Declarations!$H$14-Declarations!$C$14)*EXP(-Declarations!$D$14*$B21)+IF(Declarations!$E$14=0,0,Declarations!$E$14*($B21/Declarations!$F$14)*EXP(1-$B21/Declarations!$F$14))+Declarations!$G$14*IF($B21>=Sale_t,1,0) -> 78.423499 | D21: =Declarations!$C$15+(Declarations!$H$15-Declarations!$C$15)*EXP(-Declarations!$D$15*$B21)+IF(Declarations!$E$15=0,0,Declarations!$E$15*($B21/Declarations!$F$15)*EXP(1-$B21/Declarations!$F$15))+Declarations!$G$15*IF($B21>=Sale_t,1,0) -> 60.228704 | E21: =Declarations!$C$16+(Declarations!$H$16-Declarations!$C$16)*EXP(-Declarations!$D$16*$B21)+IF(Declarations!$E$16=0,0,Declarations!$E$16*($B21/Declarations!$F$16)*EXP(1-$B21/Declarations!$F$16))+Declarations!$G$16*IF($B21>=Sale_t,1,0) -> 64.979345 | F21: =Declarations!$C$17+(Declarations!$H$17-Declarations!$C$17)*EXP(-Declarations!$D$17*$B21)+IF(Declarations!$E$17=0,0,Declarations!$E$17*($B21/Declarations!$F$17)*EXP(1-$B21/Declarations!$F$17))+Declarations!$G$17*IF($B21>=Sale_t,1,0) -> 72.546124 | G21: =Declarations!$C$18+(Declarations!$H$18-Declarations!$C$18)*EXP(-Declarations!$D$18*$B21)+IF(Declarations!$E$18=0,0,Declarations!$E$18*($B21/Declarations!$F$18)*EXP(1-$B21/Declarations!$F$18))+Declarations!$G$18*IF($B21>=Sale_t,1,0) -> 119.31872 | H21: =Declarations!$C$19+(Declarations!$H$19-Declarations!$C$19)*EXP(-Declarations!$D$19*$B21)+IF(Declarations!$E$19=0,0,Declarations!$E$19*($B21/Declarations!$F$19)*EXP(1-$B21/Declarations!$F$19))+Declarations!$G$19*IF($B21>=Sale_t,1,0) -> 40.149594 | I21: =Declarations!$C$20+(Declarations!$H$20-Declarations!$C$20)*EXP(-Declarations!$D$20*$B21)+IF(Declarations!$E$20=0,0,Declarations!$E$20*($B21/Declarations!$F$20)*EXP(1-$B21/Declarations!$F$20))+Declarations!$G$20*IF($B21>=Sale_t,1,0) -> 72.353565 | J21: =Declarations!$C$21+(Declarations!$H$21-Declarations!$C$21)*EXP(-Declarations!$D$21*$B21)+IF(Declarations!$E$21=0,0,Declarations!$E$21*($B21/Declarations!$F$21)*EXP(1-$B21/Declarations!$F$21))+Declarations!$G$21*IF($B21>=Sale_t,1,0) -> 53.016713 | K21: =Declarations!$C$22+(Declarations!$H$22-Declarations!$C$22)*EXP(-Declarations!$D$22*$B21)+IF(Declarations!$E$22=0,0,Declarations!$E$22*($B21/Declarations!$F$22)*EXP(1-$B21/Declarations!$F$22))+Declarations!$G$22*IF($B21>=Sale_t,1,0) -> 102.70713 | L21: =Declarations!$C$23+(Declarations!$H$23-Declarations!$C$23)*EXP(-Declarations!$D$23*$B21)+IF(Declarations!$E$23=0,0,Declarations!$E$23*($B21/Declarations!$F$23)*EXP(1-$B21/Declarations!$F$23))+Declarations!$G$23*IF($B21>=Sale_t,1,0) -> 39.127427 | M21: =Declarations!$C$24+(Declarations!$H$24-Declarations!$C$24)*EXP(-Declarations!$D$24*$B21)+IF(Declarations!$E$24=0,0,Declarations!$E$24*($B21/Declarations!$F$24)*EXP(1-$B21/Declarations!$F$24))+Declarations!$G$24*IF($B21>=Sale_t,1,0) -> 75.405368 | N21: =Declarations!$C$25+(Declarations!$H$25-Declarations!$C$25)*EXP(-Declarations!$D$25*$B21)+IF(Declarations!$E$25=0,0,Declarations!$E$25*($B21/Declarations!$F$25)*EXP(1-$B21/Declarations!$F$25))+Declarations!$G$25*IF($B21>=Sale_t,1,0) -> 64.98904 | O21: =W_L*S_L*C21+W_T*S_T*D21+W_E*S_E*E21+W_R*S_R*F21 -> 32.771356 | P21: =W_L*S_L*G21+W_T*S_T*H21+W_E*S_E*I21+W_R*S_R*J21 -> 44.701292 | Q21: =W_L*S_L*K21+W_T*S_T*L21+W_E*S_E*M21+W_R*S_R*N21 -> 38.062721 | R21: =IF(O21<Score_today,1,0) -> 1 | S21: =IF(O21>Q21,1,0) -> 0 | T21: =IF(O21>P21,1,0) -> 0 | U21: =1+IF(P21>O21,1,0)+IF(Q21>O21,1,0) -> 3 | V21: =ABS(P21-Q21) -> 6.6385702
A22: 17 | B22: =A22/12 -> 1.4166667 | C22: =Declarations!$C$14+(Declarations!$H$14-Declarations!$C$14)*EXP(-Declarations!$D$14*$B22)+IF(Declarations!$E$14=0,0,Declarations!$E$14*($B22/Declarations!$F$14)*EXP(1-$B22/Declarations!$F$14))+Declarations!$G$14*IF($B22>=Sale_t,1,0) -> 78.141217 | D22: =Declarations!$C$15+(Declarations!$H$15-Declarations!$C$15)*EXP(-Declarations!$D$15*$B22)+IF(Declarations!$E$15=0,0,Declarations!$E$15*($B22/Declarations!$F$15)*EXP(1-$B22/Declarations!$F$15))+Declarations!$G$15*IF($B22>=Sale_t,1,0) -> 61.024838 | E22: =Declarations!$C$16+(Declarations!$H$16-Declarations!$C$16)*EXP(-Declarations!$D$16*$B22)+IF(Declarations!$E$16=0,0,Declarations!$E$16*($B22/Declarations!$F$16)*EXP(1-$B22/Declarations!$F$16))+Declarations!$G$16*IF($B22>=Sale_t,1,0) -> 65.059628 | F22: =Declarations!$C$17+(Declarations!$H$17-Declarations!$C$17)*EXP(-Declarations!$D$17*$B22)+IF(Declarations!$E$17=0,0,Declarations!$E$17*($B22/Declarations!$F$17)*EXP(1-$B22/Declarations!$F$17))+Declarations!$G$17*IF($B22>=Sale_t,1,0) -> 72.173871 | G22: =Declarations!$C$18+(Declarations!$H$18-Declarations!$C$18)*EXP(-Declarations!$D$18*$B22)+IF(Declarations!$E$18=0,0,Declarations!$E$18*($B22/Declarations!$F$18)*EXP(1-$B22/Declarations!$F$18))+Declarations!$G$18*IF($B22>=Sale_t,1,0) -> 119.38492 | H22: =Declarations!$C$19+(Declarations!$H$19-Declarations!$C$19)*EXP(-Declarations!$D$19*$B22)+IF(Declarations!$E$19=0,0,Declarations!$E$19*($B22/Declarations!$F$19)*EXP(1-$B22/Declarations!$F$19))+Declarations!$G$19*IF($B22>=Sale_t,1,0) -> 40.105274 | I22: =Declarations!$C$20+(Declarations!$H$20-Declarations!$C$20)*EXP(-Declarations!$D$20*$B22)+IF(Declarations!$E$20=0,0,Declarations!$E$20*($B22/Declarations!$F$20)*EXP(1-$B22/Declarations!$F$20))+Declarations!$G$20*IF($B22>=Sale_t,1,0) -> 72.414163 | J22: =Declarations!$C$21+(Declarations!$H$21-Declarations!$C$21)*EXP(-Declarations!$D$21*$B22)+IF(Declarations!$E$21=0,0,Declarations!$E$21*($B22/Declarations!$F$21)*EXP(1-$B22/Declarations!$F$21))+Declarations!$G$21*IF($B22>=Sale_t,1,0) -> 52.872505 | K22: =Declarations!$C$22+(Declarations!$H$22-Declarations!$C$22)*EXP(-Declarations!$D$22*$B22)+IF(Declarations!$E$22=0,0,Declarations!$E$22*($B22/Declarations!$F$22)*EXP(1-$B22/Declarations!$F$22))+Declarations!$G$22*IF($B22>=Sale_t,1,0) -> 102.82833 | L22: =Declarations!$C$23+(Declarations!$H$23-Declarations!$C$23)*EXP(-Declarations!$D$23*$B22)+IF(Declarations!$E$23=0,0,Declarations!$E$23*($B22/Declarations!$F$23)*EXP(1-$B22/Declarations!$F$23))+Declarations!$G$23*IF($B22>=Sale_t,1,0) -> 39.026149 | M22: =Declarations!$C$24+(Declarations!$H$24-Declarations!$C$24)*EXP(-Declarations!$D$24*$B22)+IF(Declarations!$E$24=0,0,Declarations!$E$24*($B22/Declarations!$F$24)*EXP(1-$B22/Declarations!$F$24))+Declarations!$G$24*IF($B22>=Sale_t,1,0) -> 75.580681 | N22: =Declarations!$C$25+(Declarations!$H$25-Declarations!$C$25)*EXP(-Declarations!$D$25*$B22)+IF(Declarations!$E$25=0,0,Declarations!$E$25*($B22/Declarations!$F$25)*EXP(1-$B22/Declarations!$F$25))+Declarations!$G$25*IF($B22>=Sale_t,1,0) -> 65.038691 | O22: =W_L*S_L*C22+W_T*S_T*D22+W_E*S_E*E22+W_R*S_R*F22 -> 33.012953 | P22: =W_L*S_L*G22+W_T*S_T*H22+W_E*S_E*I22+W_R*S_R*J22 -> 44.757963 | Q22: =W_L*S_L*K22+W_T*S_T*L22+W_E*S_E*M22+W_R*S_R*N22 -> 38.099116 | R22: =IF(O22<Score_today,1,0) -> 1 | S22: =IF(O22>Q22,1,0) -> 0 | T22: =IF(O22>P22,1,0) -> 0 | U22: =1+IF(P22>O22,1,0)+IF(Q22>O22,1,0) -> 3 | V22: =ABS(P22-Q22) -> 6.6588469
A23: 18 | B23: =A23/12 -> 1.5 | C23: =Declarations!$C$14+(Declarations!$H$14-Declarations!$C$14)*EXP(-Declarations!$D$14*$B23)+IF(Declarations!$E$14=0,0,Declarations!$E$14*($B23/Declarations!$F$14)*EXP(1-$B23/Declarations!$F$14))+Declarations!$G$14*IF($B23>=Sale_t,1,0) -> 77.936802 | D23: =Declarations!$C$15+(Declarations!$H$15-Declarations!$C$15)*EXP(-Declarations!$D$15*$B23)+IF(Declarations!$E$15=0,0,Declarations!$E$15*($B23/Declarations!$F$15)*EXP(1-$B23/Declarations!$F$15))+Declarations!$G$15*IF($B23>=Sale_t,1,0) -> 61.785305 | E23: =Declarations!$C$16+(Declarations!$H$16-Declarations!$C$16)*EXP(-Declarations!$D$16*$B23)+IF(Declarations!$E$16=0,0,Declarations!$E$16*($B23/Declarations!$F$16)*EXP(1-$B23/Declarations!$F$16))+Declarations!$G$16*IF($B23>=Sale_t,1,0) -> 65.165801 | F23: =Declarations!$C$17+(Declarations!$H$17-Declarations!$C$17)*EXP(-Declarations!$D$17*$B23)+IF(Declarations!$E$17=0,0,Declarations!$E$17*($B23/Declarations!$F$17)*EXP(1-$B23/Declarations!$F$17))+Declarations!$G$17*IF($B23>=Sale_t,1,0) -> 71.763565 | G23: =Declarations!$C$18+(Declarations!$H$18-Declarations!$C$18)*EXP(-Declarations!$D$18*$B23)+IF(Declarations!$E$18=0,0,Declarations!$E$18*($B23/Declarations!$F$18)*EXP(1-$B23/Declarations!$F$18))+Declarations!$G$18*IF($B23>=Sale_t,1,0) -> 119.44949 | H23: =Declarations!$C$19+(Declarations!$H$19-Declarations!$C$19)*EXP(-Declarations!$D$19*$B23)+IF(Declarations!$E$19=0,0,Declarations!$E$19*($B23/Declarations!$F$19)*EXP(1-$B23/Declarations!$F$19))+Declarations!$G$19*IF($B23>=Sale_t,1,0) -> 40.061868 | I23: =Declarations!$C$20+(Declarations!$H$20-Declarations!$C$20)*EXP(-Declarations!$D$20*$B23)+IF(Declarations!$E$20=0,0,Declarations!$E$20*($B23/Declarations!$F$20)*EXP(1-$B23/Declarations!$F$20))+Declarations!$G$20*IF($B23>=Sale_t,1,0) -> 72.472531 | J23: =Declarations!$C$21+(Declarations!$H$21-Declarations!$C$21)*EXP(-Declarations!$D$21*$B23)+IF(Declarations!$E$21=0,0,Declarations!$E$21*($B23/Declarations!$F$21)*EXP(1-$B23/Declarations!$F$21))+Declarations!$G$21*IF($B23>=Sale_t,1,0) -> 52.732443 | K23: =Declarations!$C$22+(Declarations!$H$22-Declarations!$C$22)*EXP(-Declarations!$D$22*$B23)+IF(Declarations!$E$22=0,0,Declarations!$E$22*($B23/Declarations!$F$22)*EXP(1-$B23/Declarations!$F$22))+Declarations!$G$22*IF($B23>=Sale_t,1,0) -> 102.94506 | L23: =Declarations!$C$23+(Declarations!$H$23-Declarations!$C$23)*EXP(-Declarations!$D$23*$B23)+IF(Declarations!$E$23=0,0,Declarations!$E$23*($B23/Declarations!$F$23)*EXP(1-$B23/Declarations!$F$23))+Declarations!$G$23*IF($B23>=Sale_t,1,0) -> 38.926546 | M23: =Declarations!$C$24+(Declarations!$H$24-Declarations!$C$24)*EXP(-Declarations!$D$24*$B23)+IF(Declarations!$E$24=0,0,Declarations!$E$24*($B23/Declarations!$F$24)*EXP(1-$B23/Declarations!$F$24))+Declarations!$G$24*IF($B23>=Sale_t,1,0) -> 75.747443 | N23: =Declarations!$C$25+(Declarations!$H$25-Declarations!$C$25)*EXP(-Declarations!$D$25*$B23)+IF(Declarations!$E$25=0,0,Declarations!$E$25*($B23/Declarations!$F$25)*EXP(1-$B23/Declarations!$F$25))+Declarations!$G$25*IF($B23>=Sale_t,1,0) -> 65.087116 | O23: =W_L*S_L*C23+W_T*S_T*D23+W_E*S_E*E23+W_R*S_R*F23 -> 33.281086 | P23: =W_L*S_L*G23+W_T*S_T*H23+W_E*S_E*I23+W_R*S_R*J23 -> 44.812861 | Q23: =W_L*S_L*K23+W_T*S_T*L23+W_E*S_E*M23+W_R*S_R*N23 -> 38.132984 | R23: =IF(O23<Score_today,1,0) -> 1 | S23: =IF(O23>Q23,1,0) -> 0 | T23: =IF(O23>P23,1,0) -> 0 | U23: =1+IF(P23>O23,1,0)+IF(Q23>O23,1,0) -> 3 | V23: =ABS(P23-Q23) -> 6.6798772
A24: 19 | B24: =A24/12 -> 1.5833333 | C24: =Declarations!$C$14+(Declarations!$H$14-Declarations!$C$14)*EXP(-Declarations!$D$14*$B24)+IF(Declarations!$E$14=0,0,Declarations!$E$14*($B24/Declarations!$F$14)*EXP(1-$B24/Declarations!$F$14))+Declarations!$G$14*IF($B24>=Sale_t,1,0) -> 77.804399 | D24: =Declarations!$C$15+(Declarations!$H$15-Declarations!$C$15)*EXP(-Declarations!$D$15*$B24)+IF(Declarations!$E$15=0,0,Declarations!$E$15*($B24/Declarations!$F$15)*EXP(1-$B24/Declarations!$F$15))+Declarations!$G$15*IF($B24>=Sale_t,1,0) -> 62.511705 | E24: =Declarations!$C$16+(Declarations!$H$16-Declarations!$C$16)*EXP(-Declarations!$D$16*$B24)+IF(Declarations!$E$16=0,0,Declarations!$E$16*($B24/Declarations!$F$16)*EXP(1-$B24/Declarations!$F$16))+Declarations!$G$16*IF($B24>=Sale_t,1,0) -> 65.294851 | F24: =Declarations!$C$17+(Declarations!$H$17-Declarations!$C$17)*EXP(-Declarations!$D$17*$B24)+IF(Declarations!$E$17=0,0,Declarations!$E$17*($B24/Declarations!$F$17)*EXP(1-$B24/Declarations!$F$17))+Declarations!$G$17*IF($B24>=Sale_t,1,0) -> 71.321693 | G24: =Declarations!$C$18+(Declarations!$H$18-Declarations!$C$18)*EXP(-Declarations!$D$18*$B24)+IF(Declarations!$E$18=0,0,Declarations!$E$18*($B24/Declarations!$F$18)*EXP(1-$B24/Declarations!$F$18))+Declarations!$G$18*IF($B24>=Sale_t,1,0) -> 119.51246 | H24: =Declarations!$C$19+(Declarations!$H$19-Declarations!$C$19)*EXP(-Declarations!$D$19*$B24)+IF(Declarations!$E$19=0,0,Declarations!$E$19*($B24/Declarations!$F$19)*EXP(1-$B24/Declarations!$F$19))+Declarations!$G$19*IF($B24>=Sale_t,1,0) -> 40.019357 | I24: =Declarations!$C$20+(Declarations!$H$20-Declarations!$C$20)*EXP(-Declarations!$D$20*$B24)+IF(Declarations!$E$20=0,0,Declarations!$E$20*($B24/Declarations!$F$20)*EXP(1-$B24/Declarations!$F$20))+Declarations!$G$20*IF($B24>=Sale_t,1,0) -> 72.52875 | J24: =Declarations!$C$21+(Declarations!$H$21-Declarations!$C$21)*EXP(-Declarations!$D$21*$B24)+IF(Declarations!$E$21=0,0,Declarations!$E$21*($B24/Declarations!$F$21)*EXP(1-$B24/Declarations!$F$21))+Declarations!$G$21*IF($B24>=Sale_t,1,0) -> 52.596407 | K24: =Declarations!$C$22+(Declarations!$H$22-Declarations!$C$22)*EXP(-Declarations!$D$22*$B24)+IF(Declarations!$E$22=0,0,Declarations!$E$22*($B24/Declarations!$F$22)*EXP(1-$B24/Declarations!$F$22))+Declarations!$G$22*IF($B24>=Sale_t,1,0) -> 103.0575 | L24: =Declarations!$C$23+(Declarations!$H$23-Declarations!$C$23)*EXP(-Declarations!$D$23*$B24)+IF(Declarations!$E$23=0,0,Declarations!$E$23*($B24/Declarations!$F$23)*EXP(1-$B24/Declarations!$F$23))+Declarations!$G$23*IF($B24>=Sale_t,1,0) -> 38.828589 | M24: =Declarations!$C$24+(Declarations!$H$24-Declarations!$C$24)*EXP(-Declarations!$D$24*$B24)+IF(Declarations!$E$24=0,0,Declarations!$E$24*($B24/Declarations!$F$24)*EXP(1-$B24/Declarations!$F$24))+Declarations!$G$24*IF($B24>=Sale_t,1,0) -> 75.906072 | N24: =Declarations!$C$25+(Declarations!$H$25-Declarations!$C$25)*EXP(-Declarations!$D$25*$B24)+IF(Declarations!$E$25=0,0,Declarations!$E$25*($B24/Declarations!$F$25)*EXP(1-$B24/Declarations!$F$25))+Declarations!$G$25*IF($B24>=Sale_t,1,0) -> 65.134345 | O24: =W_L*S_L*C24+W_T*S_T*D24+W_E*S_E*E24+W_R*S_R*F24 -> 33.572315 | P24: =W_L*S_L*G24+W_T*S_T*H24+W_E*S_E*I24+W_R*S_R*J24 -> 44.86604 | Q24: =W_L*S_L*K24+W_T*S_T*L24+W_E*S_E*M24+W_R*S_R*N24 -> 38.164454 | R24: =IF(O24<Score_today,1,0) -> 1 | S24: =IF(O24>Q24,1,0) -> 0 | T24: =IF(O24>P24,1,0) -> 0 | U24: =1+IF(P24>O24,1,0)+IF(Q24>O24,1,0) -> 3 | V24: =ABS(P24-Q24) -> 6.701586
A25: 20 | B25: =A25/12 -> 1.6666667 | C25: =Declarations!$C$14+(Declarations!$H$14-Declarations!$C$14)*EXP(-Declarations!$D$14*$B25)+IF(Declarations!$E$14=0,0,Declarations!$E$14*($B25/Declarations!$F$14)*EXP(1-$B25/Declarations!$F$14))+Declarations!$G$14*IF($B25>=Sale_t,1,0) -> 77.738502 | D25: =Declarations!$C$15+(Declarations!$H$15-Declarations!$C$15)*EXP(-Declarations!$D$15*$B25)+IF(Declarations!$E$15=0,0,Declarations!$E$15*($B25/Declarations!$F$15)*EXP(1-$B25/Declarations!$F$15))+Declarations!$G$15*IF($B25>=Sale_t,1,0) -> 63.205563 | E25: =Declarations!$C$16+(Declarations!$H$16-Declarations!$C$16)*EXP(-Declarations!$D$16*$B25)+IF(Declarations!$E$16=0,0,Declarations!$E$16*($B25/Declarations!$F$16)*EXP(1-$B25/Declarations!$F$16))+Declarations!$G$16*IF($B25>=Sale_t,1,0) -> 65.444018 | F25: =Declarations!$C$17+(Declarations!$H$17-Declarations!$C$17)*EXP(-Declarations!$D$17*$B25)+IF(Declarations!$E$17=0,0,Declarations!$E$17*($B25/Declarations!$F$17)*EXP(1-$B25/Declarations!$F$17))+Declarations!$G$17*IF($B25>=Sale_t,1,0) -> 70.854053 | G25: =Declarations!$C$18+(Declarations!$H$18-Declarations!$C$18)*EXP(-Declarations!$D$18*$B25)+IF(Declarations!$E$18=0,0,Declarations!$E$18*($B25/Declarations!$F$18)*EXP(1-$B25/Declarations!$F$18))+Declarations!$G$18*IF($B25>=Sale_t,1,0) -> 119.57388 | H25: =Declarations!$C$19+(Declarations!$H$19-Declarations!$C$19)*EXP(-Declarations!$D$19*$B25)+IF(Declarations!$E$19=0,0,Declarations!$E$19*($B25/Declarations!$F$19)*EXP(1-$B25/Declarations!$F$19))+Declarations!$G$19*IF($B25>=Sale_t,1,0) -> 39.977722 | I25: =Declarations!$C$20+(Declarations!$H$20-Declarations!$C$20)*EXP(-Declarations!$D$20*$B25)+IF(Declarations!$E$20=0,0,Declarations!$E$20*($B25/Declarations!$F$20)*EXP(1-$B25/Declarations!$F$20))+Declarations!$G$20*IF($B25>=Sale_t,1,0) -> 72.5829 | J25: =Declarations!$C$21+(Declarations!$H$21-Declarations!$C$21)*EXP(-Declarations!$D$21*$B25)+IF(Declarations!$E$21=0,0,Declarations!$E$21*($B25/Declarations!$F$21)*EXP(1-$B25/Declarations!$F$21))+Declarations!$G$21*IF($B25>=Sale_t,1,0) -> 52.464281 | K25: =Declarations!$C$22+(Declarations!$H$22-Declarations!$C$22)*EXP(-Declarations!$D$22*$B25)+IF(Declarations!$E$22=0,0,Declarations!$E$22*($B25/Declarations!$F$22)*EXP(1-$B25/Declarations!$F$22))+Declarations!$G$22*IF($B25>=Sale_t,1,0) -> 103.1658 | L25: =Declarations!$C$23+(Declarations!$H$23-Declarations!$C$23)*EXP(-Declarations!$D$23*$B25)+IF(Declarations!$E$23=0,0,Declarations!$E$23*($B25/Declarations!$F$23)*EXP(1-$B25/Declarations!$F$23))+Declarations!$G$23*IF($B25>=Sale_t,1,0) -> 38.73225 | M25: =Declarations!$C$24+(Declarations!$H$24-Declarations!$C$24)*EXP(-Declarations!$D$24*$B25)+IF(Declarations!$E$24=0,0,Declarations!$E$24*($B25/Declarations!$F$24)*EXP(1-$B25/Declarations!$F$24))+Declarations!$G$24*IF($B25>=Sale_t,1,0) -> 76.056964 | N25: =Declarations!$C$25+(Declarations!$H$25-Declarations!$C$25)*EXP(-Declarations!$D$25*$B25)+IF(Declarations!$E$25=0,0,Declarations!$E$25*($B25/Declarations!$F$25)*EXP(1-$B25/Declarations!$F$25))+Declarations!$G$25*IF($B25>=Sale_t,1,0) -> 65.180408 | O25: =W_L*S_L*C25+W_T*S_T*D25+W_E*S_E*E25+W_R*S_R*F25 -> 33.883507 | P25: =W_L*S_L*G25+W_T*S_T*H25+W_E*S_E*I25+W_R*S_R*J25 -> 44.917555 | Q25: =W_L*S_L*K25+W_T*S_T*L25+W_E*S_E*M25+W_R*S_R*N25 -> 38.193652 | R25: =IF(O25<Score_today,1,0) -> 1 | S25: =IF(O25>Q25,1,0) -> 0 | T25: =IF(O25>P25,1,0) -> 0 | U25: =1+IF(P25>O25,1,0)+IF(Q25>O25,1,0) -> 3 | V25: =ABS(P25-Q25) -> 6.7239027
A26: 21 | B26: =A26/12 -> 1.75 | C26: =Declarations!$C$14+(Declarations!$H$14-Declarations!$C$14)*EXP(-Declarations!$D$14*$B26)+IF(Declarations!$E$14=0,0,Declarations!$E$14*($B26/Declarations!$F$14)*EXP(1-$B26/Declarations!$F$14))+Declarations!$G$14*IF($B26>=Sale_t,1,0) -> 77.733933 | D26: =Declarations!$C$15+(Declarations!$H$15-Declarations!$C$15)*EXP(-Declarations!$D$15*$B26)+IF(Declarations!$E$15=0,0,Declarations!$E$15*($B26/Declarations!$F$15)*EXP(1-$B26/Declarations!$F$15))+Declarations!$G$15*IF($B26>=Sale_t,1,0) -> 63.868337 | E26: =Declarations!$C$16+(Declarations!$H$16-Declarations!$C$16)*EXP(-Declarations!$D$16*$B26)+IF(Declarations!$E$16=0,0,Declarations!$E$16*($B26/Declarations!$F$16)*EXP(1-$B26/Declarations!$F$16))+Declarations!$G$16*IF($B26>=Sale_t,1,0) -> 65.61077 | F26: =Declarations!$C$17+(Declarations!$H$17-Declarations!$C$17)*EXP(-Declarations!$D$17*$B26)+IF(Declarations!$E$17=0,0,Declarations!$E$17*($B26/Declarations!$F$17)*EXP(1-$B26/Declarations!$F$17))+Declarations!$G$17*IF($B26>=Sale_t,1,0) -> 70.365816 | G26: =Declarations!$C$18+(Declarations!$H$18-Declarations!$C$18)*EXP(-Declarations!$D$18*$B26)+IF(Declarations!$E$18=0,0,Declarations!$E$18*($B26/Declarations!$F$18)*EXP(1-$B26/Declarations!$F$18))+Declarations!$G$18*IF($B26>=Sale_t,1,0) -> 119.63378 | H26: =Declarations!$C$19+(Declarations!$H$19-Declarations!$C$19)*EXP(-Declarations!$D$19*$B26)+IF(Declarations!$E$19=0,0,Declarations!$E$19*($B26/Declarations!$F$19)*EXP(1-$B26/Declarations!$F$19))+Declarations!$G$19*IF($B26>=Sale_t,1,0) -> 39.936946 | I26: =Declarations!$C$20+(Declarations!$H$20-Declarations!$C$20)*EXP(-Declarations!$D$20*$B26)+IF(Declarations!$E$20=0,0,Declarations!$E$20*($B26/Declarations!$F$20)*EXP(1-$B26/Declarations!$F$20))+Declarations!$G$20*IF($B26>=Sale_t,1,0) -> 72.635058 | J26: =Declarations!$C$21+(Declarations!$H$21-Declarations!$C$21)*EXP(-Declarations!$D$21*$B26)+IF(Declarations!$E$21=0,0,Declarations!$E$21*($B26/Declarations!$F$21)*EXP(1-$B26/Declarations!$F$21))+Declarations!$G$21*IF($B26>=Sale_t,1,0) -> 52.335954 | K26: =Declarations!$C$22+(Declarations!$H$22-Declarations!$C$22)*EXP(-Declarations!$D$22*$B26)+IF(Declarations!$E$22=0,0,Declarations!$E$22*($B26/Declarations!$F$22)*EXP(1-$B26/Declarations!$F$22))+Declarations!$G$22*IF($B26>=Sale_t,1,0) -> 103.27012 | L26: =Declarations!$C$23+(Declarations!$H$23-Declarations!$C$23)*EXP(-Declarations!$D$23*$B26)+IF(Declarations!$E$23=0,0,Declarations!$E$23*($B26/Declarations!$F$23)*EXP(1-$B26/Declarations!$F$23))+Declarations!$G$23*IF($B26>=Sale_t,1,0) -> 38.637505 | M26: =Declarations!$C$24+(Declarations!$H$24-Declarations!$C$24)*EXP(-Declarations!$D$24*$B26)+IF(Declarations!$E$24=0,0,Declarations!$E$24*($B26/Declarations!$F$24)*EXP(1-$B26/Declarations!$F$24))+Declarations!$G$24*IF($B26>=Sale_t,1,0) -> 76.200498 | N26: =Declarations!$C$25+(Declarations!$H$25-Declarations!$C$25)*EXP(-Declarations!$D$25*$B26)+IF(Declarations!$E$25=0,0,Declarations!$E$25*($B26/Declarations!$F$25)*EXP(1-$B26/Declarations!$F$25))+Declarations!$G$25*IF($B26>=Sale_t,1,0) -> 65.225334 | O26: =W_L*S_L*C26+W_T*S_T*D26+W_E*S_E*E26+W_R*S_R*F26 -> 34.211806 | P26: =W_L*S_L*G26+W_T*S_T*H26+W_E*S_E*I26+W_R*S_R*J26 -> 44.967457 | Q26: =W_L*S_L*K26+W_T*S_T*L26+W_E*S_E*M26+W_R*S_R*N26 -> 38.220696 | R26: =IF(O26<Score_today,1,0) -> 1 | S26: =IF(O26>Q26,1,0) -> 0 | T26: =IF(O26>P26,1,0) -> 0 | U26: =1+IF(P26>O26,1,0)+IF(Q26>O26,1,0) -> 3 | V26: =ABS(P26-Q26) -> 6.7467611
A27: 22 | B27: =A27/12 -> 1.8333333 | C27: =Declarations!$C$14+(Declarations!$H$14-Declarations!$C$14)*EXP(-Declarations!$D$14*$B27)+IF(Declarations!$E$14=0,0,Declarations!$E$14*($B27/Declarations!$F$14)*EXP(1-$B27/Declarations!$F$14))+Declarations!$G$14*IF($B27>=Sale_t,1,0) -> 77.785824 | D27: =Declarations!$C$15+(Declarations!$H$15-Declarations!$C$15)*EXP(-Declarations!$D$15*$B27)+IF(Declarations!$E$15=0,0,Declarations!$E$15*($B27/Declarations!$F$15)*EXP(1-$B27/Declarations!$F$15))+Declarations!$G$15*IF($B27>=Sale_t,1,0) -> 64.501419 | E27: =Declarations!$C$16+(Declarations!$H$16-Declarations!$C$16)*EXP(-Declarations!$D$16*$B27)+IF(Declarations!$E$16=0,0,Declarations!$E$16*($B27/Declarations!$F$16)*EXP(1-$B27/Declarations!$F$16))+Declarations!$G$16*IF($B27>=Sale_t,1,0) -> 65.792791 | F27: =Declarations!$C$17+(Declarations!$H$17-Declarations!$C$17)*EXP(-Declarations!$D$17*$B27)+IF(Declarations!$E$17=0,0,Declarations!$E$17*($B27/Declarations!$F$17)*EXP(1-$B27/Declarations!$F$17))+Declarations!$G$17*IF($B27>=Sale_t,1,0) -> 69.861583 | G27: =Declarations!$C$18+(Declarations!$H$18-Declarations!$C$18)*EXP(-Declarations!$D$18*$B27)+IF(Declarations!$E$18=0,0,Declarations!$E$18*($B27/Declarations!$F$18)*EXP(1-$B27/Declarations!$F$18))+Declarations!$G$18*IF($B27>=Sale_t,1,0) -> 119.6922 | H27: =Declarations!$C$19+(Declarations!$H$19-Declarations!$C$19)*EXP(-Declarations!$D$19*$B27)+IF(Declarations!$E$19=0,0,Declarations!$E$19*($B27/Declarations!$F$19)*EXP(1-$B27/Declarations!$F$19))+Declarations!$G$19*IF($B27>=Sale_t,1,0) -> 39.89701 | I27: =Declarations!$C$20+(Declarations!$H$20-Declarations!$C$20)*EXP(-Declarations!$D$20*$B27)+IF(Declarations!$E$20=0,0,Declarations!$E$20*($B27/Declarations!$F$20)*EXP(1-$B27/Declarations!$F$20))+Declarations!$G$20*IF($B27>=Sale_t,1,0) -> 72.685295 | J27: =Declarations!$C$21+(Declarations!$H$21-Declarations!$C$21)*EXP(-Declarations!$D$21*$B27)+IF(Declarations!$E$21=0,0,Declarations!$E$21*($B27/Declarations!$F$21)*EXP(1-$B27/Declarations!$F$21))+Declarations!$G$21*IF($B27>=Sale_t,1,0) -> 52.211315 | K27: =Declarations!$C$22+(Declarations!$H$22-Declarations!$C$22)*EXP(-Declarations!$D$22*$B27)+IF(Declarations!$E$22=0,0,Declarations!$E$22*($B27/Declarations!$F$22)*EXP(1-$B27/Declarations!$F$22))+Declarations!$G$22*IF($B27>=Sale_t,1,0) -> 103.37059 | L27: =Declarations!$C$23+(Declarations!$H$23-Declarations!$C$23)*EXP(-Declarations!$D$23*$B27)+IF(Declarations!$E$23=0,0,Declarations!$E$23*($B27/Declarations!$F$23)*EXP(1-$B27/Declarations!$F$23))+Declarations!$G$23*IF($B27>=Sale_t,1,0) -> 38.544325 | M27: =Declarations!$C$24+(Declarations!$H$24-Declarations!$C$24)*EXP(-Declarations!$D$24*$B27)+IF(Declarations!$E$24=0,0,Declarations!$E$24*($B27/Declarations!$F$24)*EXP(1-$B27/Declarations!$F$24))+Declarations!$G$24*IF($B27>=Sale_t,1,0) -> 76.337031 | N27: =Declarations!$C$25+(Declarations!$H$25-Declarations!$C$25)*EXP(-Declarations!$D$25*$B27)+IF(Declarations!$E$25=0,0,Declarations!$E$25*($B27/Declarations!$F$25)*EXP(1-$B27/Declarations!$F$25))+Declarations!$G$25*IF($B27>=Sale_t,1,0) -> 65.269151 | O27: =W_L*S_L*C27+W_T*S_T*D27+W_E*S_E*E27+W_R*S_R*F27 -> 34.554613 | P27: =W_L*S_L*G27+W_T*S_T*H27+W_E*S_E*I27+W_R*S_R*J27 -> 45.015798 | Q27: =W_L*S_L*K27+W_T*S_T*L27+W_E*S_E*M27+W_R*S_R*N27 -> 38.245699 | R27: =IF(O27<Score_today,1,0) -> 1 | S27: =IF(O27>Q27,1,0) -> 0 | T27: =IF(O27>P27,1,0) -> 0 | U27: =1+IF(P27>O27,1,0)+IF(Q27>O27,1,0) -> 3 | V27: =ABS(P27-Q27) -> 6.7700988
A28: 23 | B28: =A28/12 -> 1.9166667 | C28: =Declarations!$C$14+(Declarations!$H$14-Declarations!$C$14)*EXP(-Declarations!$D$14*$B28)+IF(Declarations!$E$14=0,0,Declarations!$E$14*($B28/Declarations!$F$14)*EXP(1-$B28/Declarations!$F$14))+Declarations!$G$14*IF($B28>=Sale_t,1,0) -> 77.889603 | D28: =Declarations!$C$15+(Declarations!$H$15-Declarations!$C$15)*EXP(-Declarations!$D$15*$B28)+IF(Declarations!$E$15=0,0,Declarations!$E$15*($B28/Declarations!$F$15)*EXP(1-$B28/Declarations!$F$15))+Declarations!$G$15*IF($B28>=Sale_t,1,0) -> 65.10614 | E28: =Declarations!$C$16+(Declarations!$H$16-Declarations!$C$16)*EXP(-Declarations!$D$16*$B28)+IF(Declarations!$E$16=0,0,Declarations!$E$16*($B28/Declarations!$F$16)*EXP(1-$B28/Declarations!$F$16))+Declarations!$G$16*IF($B28>=Sale_t,1,0) -> 65.987962 | F28: =Declarations!$C$17+(Declarations!$H$17-Declarations!$C$17)*EXP(-Declarations!$D$17*$B28)+IF(Declarations!$E$17=0,0,Declarations!$E$17*($B28/Declarations!$F$17)*EXP(1-$B28/Declarations!$F$17))+Declarations!$G$17*IF($B28>=Sale_t,1,0) -> 69.345442 | G28: =Declarations!$C$18+(Declarations!$H$18-Declarations!$C$18)*EXP(-Declarations!$D$18*$B28)+IF(Declarations!$E$18=0,0,Declarations!$E$18*($B28/Declarations!$F$18)*EXP(1-$B28/Declarations!$F$18))+Declarations!$G$18*IF($B28>=Sale_t,1,0) -> 119.74918 | H28: =Declarations!$C$19+(Declarations!$H$19-Declarations!$C$19)*EXP(-Declarations!$D$19*$B28)+IF(Declarations!$E$19=0,0,Declarations!$E$19*($B28/Declarations!$F$19)*EXP(1-$B28/Declarations!$F$19))+Declarations!$G$19*IF($B28>=Sale_t,1,0) -> 39.857898 | I28: =Declarations!$C$20+(Declarations!$H$20-Declarations!$C$20)*EXP(-Declarations!$D$20*$B28)+IF(Declarations!$E$20=0,0,Declarations!$E$20*($B28/Declarations!$F$20)*EXP(1-$B28/Declarations!$F$20))+Declarations!$G$20*IF($B28>=Sale_t,1,0) -> 72.733684 | J28: =Declarations!$C$21+(Declarations!$H$21-Declarations!$C$21)*EXP(-Declarations!$D$21*$B28)+IF(Declarations!$E$21=0,0,Declarations!$E$21*($B28/Declarations!$F$21)*EXP(1-$B28/Declarations!$F$21))+Declarations!$G$21*IF($B28>=Sale_t,1,0) -> 52.090259 | K28: =Declarations!$C$22+(Declarations!$H$22-Declarations!$C$22)*EXP(-Declarations!$D$22*$B28)+IF(Declarations!$E$22=0,0,Declarations!$E$22*($B28/Declarations!$F$22)*EXP(1-$B28/Declarations!$F$22))+Declarations!$G$22*IF($B28>=Sale_t,1,0) -> 103.46737 | L28: =Declarations!$C$23+(Declarations!$H$23-Declarations!$C$23)*EXP(-Declarations!$D$23*$B28)+IF(Declarations!$E$23=0,0,Declarations!$E$23*($B28/Declarations!$F$23)*EXP(1-$B28/Declarations!$F$23))+Declarations!$G$23*IF($B28>=Sale_t,1,0) -> 38.452685 | M28: =Declarations!$C$24+(Declarations!$H$24-Declarations!$C$24)*EXP(-Declarations!$D$24*$B28)+IF(Declarations!$E$24=0,0,Declarations!$E$24*($B28/Declarations!$F$24)*EXP(1-$B28/Declarations!$F$24))+Declarations!$G$24*IF($B28>=Sale_t,1,0) -> 76.466906 | N28: =Declarations!$C$25+(Declarations!$H$25-Declarations!$C$25)*EXP(-Declarations!$D$25*$B28)+IF(Declarations!$E$25=0,0,Declarations!$E$25*($B28/Declarations!$F$25)*EXP(1-$B28/Declarations!$F$25))+Declarations!$G$25*IF($B28>=Sale_t,1,0) -> 65.311885 | O28: =W_L*S_L*C28+W_T*S_T*D28+W_E*S_E*E28+W_R*S_R*F28 -> 34.909566 | P28: =W_L*S_L*G28+W_T*S_T*H28+W_E*S_E*I28+W_R*S_R*J28 -> 45.062626 | Q28: =W_L*S_L*K28+W_T*S_T*L28+W_E*S_E*M28+W_R*S_R*N28 -> 38.268768 | R28: =IF(O28<Score_today,1,0) -> 1 | S28: =IF(O28>Q28,1,0) -> 0 | T28: =IF(O28>P28,1,0) -> 0 | U28: =1+IF(P28>O28,1,0)+IF(Q28>O28,1,0) -> 3 | V28: =ABS(P28-Q28) -> 6.7938576
... A65: 60 | B65: =A65/12 -> 5 | C65: =Declarations!$C$14+(Declarations!$H$14-Declarations!$C$14)*EXP(-Declarations!$D$14*$B65)+IF(Declarations!$E$14=0,0,Declarations!$E$14*($B65/Declarations!$F$14)*EXP(1-$B65/Declarations!$F$14))+Declarations!$G$14*IF($B65>=Sale_t,1,0) -> 94.295601 | D65: =Declarations!$C$15+(Declarations!$H$15-Declarations!$C$15)*EXP(-Declarations!$D$15*$B65)+IF(Declarations!$E$15=0,0,Declarations!$E$15*($B65/Declarations!$F$15)*EXP(1-$B65/Declarations!$F$15))+Declarations!$G$15*IF($B65>=Sale_t,1,0) -> 75.634669 | E65: =Declarations!$C$16+(Declarations!$H$16-Declarations!$C$16)*EXP(-Declarations!$D$16*$B65)+IF(Declarations!$E$16=0,0,Declarations!$E$16*($B65/Declarations!$F$16)*EXP(1-$B65/Declarations!$F$16))+Declarations!$G$16*IF($B65>=Sale_t,1,0) -> 73.598331 | F65: =Declarations!$C$17+(Declarations!$H$17-Declarations!$C$17)*EXP(-Declarations!$D$17*$B65)+IF(Declarations!$E$17=0,0,Declarations!$E$17*($B65/Declarations!$F$17)*EXP(1-$B65/Declarations!$F$17))+Declarations!$G$17*IF($B65>=Sale_t,1,0) -> 55.21775 | G65: =Declarations!$C$18+(Declarations!$H$18-Declarations!$C$18)*EXP(-Declarations!$D$18*$B65)+IF(Declarations!$E$18=0,0,Declarations!$E$18*($B65/Declarations!$F$18)*EXP(1-$B65/Declarations!$F$18))+Declarations!$G$18*IF($B65>=Sale_t,1,0) -> 121.10748 | H65: =Declarations!$C$19+(Declarations!$H$19-Declarations!$C$19)*EXP(-Declarations!$D$19*$B65)+IF(Declarations!$E$19=0,0,Declarations!$E$19*($B65/Declarations!$F$19)*EXP(1-$B65/Declarations!$F$19))+Declarations!$G$19*IF($B65>=Sale_t,1,0) -> 38.859514 | I65: =Declarations!$C$20+(Declarations!$H$20-Declarations!$C$20)*EXP(-Declarations!$D$20*$B65)+IF(Declarations!$E$20=0,0,Declarations!$E$20*($B65/Declarations!$F$20)*EXP(1-$B65/Declarations!$F$20))+Declarations!$G$20*IF($B65>=Sale_t,1,0) -> 73.683802 | J65: =Declarations!$C$21+(Declarations!$H$21-Declarations!$C$21)*EXP(-Declarations!$D$21*$B65)+IF(Declarations!$E$21=0,0,Declarations!$E$21*($B65/Declarations!$F$21)*EXP(1-$B65/Declarations!$F$21))+Declarations!$G$21*IF($B65>=Sale_t,1,0) -> 49.390192 | K65: =Declarations!$C$22+(Declarations!$H$22-Declarations!$C$22)*EXP(-Declarations!$D$22*$B65)+IF(Declarations!$E$22=0,0,Declarations!$E$22*($B65/Declarations!$F$22)*EXP(1-$B65/Declarations!$F$22))+Declarations!$G$22*IF($B65>=Sale_t,1,0) -> 105.3676 | L65: =Declarations!$C$23+(Declarations!$H$23-Declarations!$C$23)*EXP(-Declarations!$D$23*$B65)+IF(Declarations!$E$23=0,0,Declarations!$E$23*($B65/Declarations!$F$23)*EXP(1-$B65/Declarations!$F$23))+Declarations!$G$23*IF($B65>=Sale_t,1,0) -> 35.943036 | M65: =Declarations!$C$24+(Declarations!$H$24-Declarations!$C$24)*EXP(-Declarations!$D$24*$B65)+IF(Declarations!$E$24=0,0,Declarations!$E$24*($B65/Declarations!$F$24)*EXP(1-$B65/Declarations!$F$24))+Declarations!$G$24*IF($B65>=Sale_t,1,0) -> 78.601703 | N65: =Declarations!$C$25+(Declarations!$H$25-Declarations!$C$25)*EXP(-Declarations!$D$25*$B65)+IF(Declarations!$E$25=0,0,Declarations!$E$25*($B65/Declarations!$F$25)*EXP(1-$B65/Declarations!$F$25))+Declarations!$G$25*IF($B65>=Sale_t,1,0) -> 66.33061 | O65: =W_L*S_L*C65+W_T*S_T*D65+W_E*S_E*E65+W_R*S_R*F65 -> 47.077713 | P65: =W_L*S_L*G65+W_T*S_T*H65+W_E*S_E*I65+W_R*S_R*J65 -> 46.065151 | Q65: =W_L*S_L*K65+W_T*S_T*L65+W_E*S_E*M65+W_R*S_R*N65 -> 38.395434 | R65: =IF(O65<Score_today,1,0) -> 0 | S65: =IF(O65>Q65,1,0) -> 1 | T65: =IF(O65>P65,1,0) -> 1 | U65: =1+IF(P65>O65,1,0)+IF(Q65>O65,1,0) -> 1 | V65: =ABS(P65-Q65) -> 7.6697176

Sheet Dashboard
A1: Build the dashboard: Table 11.2's dimensions, Meridian's six with their supports and indicators, and the sustainability line (AXIOM Lab 1.11, step 1; Tables 11.2 and 11.4; Section 11.8)
A3: Symbol | B3: Dimension (Table 11.2) | C3: What it measures per period | D3: Sample indicators
A4: P_F | B4: Financial | C4: earnings, cash, returns on capital | D4: margin, ROIC, free cash flow
A5: P_O | B5: Operational | C5: throughput, quality, delivery, cost | D5: equipment effectiveness, defects
A6: P_S | B6: Strategic | C6: position gained: share, options | D6: share change, win rate
A7: P_H | B7: Human | C7: capability applied and grown | D7: output per employee, retention
A8: P_T | B8: Technological | C8: platform uptime and speed of change | D8: availability, cycle time
A9: P_I | B9: Innovation | C9: validated novelty shipped | D9: new-product revenue share
A10: P_G | B10: Governance | C10: quality of decisions and controls | D10: audit findings, incidents
A11: P_E | B11: Environmental | C11: footprint per unit of output | D11: intensity metrics
A12: P_R | B12: Resilience | C12: shock absorption, shown or ready | D12: recovery half-life, buffer days
A13: P_ESG | B13: Sustainability | C13: the above, without depleting capital | D13: Definition 11.11
A14: Dimensions of the performance vector (Equation 11.2) | D14: =COUNTA(A4:A13) -> 10
A16: Meridian's dimension (Table 11.4) | B16: Support on Chapter 9's architecture | C16: Indicator (Table 5.2) | D16: Today | E16: Error | F16: Band today: low | G16: Band today: high | H16: Unit
A17: P_F financial | B17: treasury | C17: ROIC (x6) | D17: 8.3 | E17: 0.4 | F17: =D17-E17 -> 7.9 | G17: =D17+E17 -> 8.7 | H17: percent; error in percentage points
A18: P_O operational | B18: Industrial Systems, Materials | C18: operational efficiency (x5) | D18: 71 | E18: 3 | F18: =D18-E18 -> 68 | G18: =D18+E18 -> 74 | H18: index
A19: P_S strategic | B19: the three divisions | C19: market share (x8) | D19: 19 | E19: 0.8 | F19: =D19-E19 -> 18.2 | G19: =D19+E19 -> 19.8 | H19: percent; error in percentage points
A20: P_T technological | B20: Digital | C20: none declared | H20: blind until an indicator reads Digital
A21: P_I innovation | B21: Digital, engineering | C21: none declared | H21: blind until an indicator reads Digital and engineering
A22: P_R resilience | B22: treasury | C22: liquidity above the board's floor (x1) | D22: =B33-B34 -> 270 | E22: =0.01*B33 -> 6.2 | F22: =D22-E22 -> 263.8 | G22: =D22+E22 -> 276.2 | H22: $ million; liquidity error +/-1% (Definition 11.12: a buffer margin)
A23: Dimensions without a declared indicator (blind by construction, Section 11.4) | D23: =COUNTIF(C17:C22,"none declared") -> 2
A25: The CFO's scorecard reads | B25: Tag (Table 5.2)
A26: Liquidity | B26: =Declarations!F4 -> ECA: capital
A27: Technology | B27: =Declarations!F5 -> ECA: capital
A28: Efficiency | B28: =Declarations!F6 -> EPA: performance
A29: Strategic risk | B29: =Declarations!F7 -> ERRA: risk
A30: Performance readings among the four | B30: =SUMPRODUCT(--(LEFT(B26:B29,3)="EPA")) -> 1
A32: Proposition 11.1 (Online Appendix 11.B): the same EBITDA, different resilience | B32: Value | C32: Reading
A33: Meridian's liquidity ($ million) | B33: 620 | C33: Table 3.1
A34: The board's liquidity floor ($ million) | B34: 350 | C34: Table 5.4
A35: Revenue ($ million) | B35: 4200 | C35: Chapter 1
A36: EBITDA margin | B36: 0.118
A37: EBITDA ($ million) | B37: =B35*B36 -> 495.6 | C37: about $496 million
A38: A twin's liquidity, same EBITDA ($ million) | B38: 450
A39: A shock that drains ($ million) | B39: 150
A40: Meridian after the shock ($ million) | B40: =B33-B39 -> 470 | C40: above the floor
A41: The twin after the shock ($ million) | B41: =B38-B39 -> 300 | C41: below the floor
A42: Meridian against the floor | B42: =IF(B40>=B34,"above","below") -> above
A43: The twin against the floor | B43: =IF(B41>=B34,"above","below") -> below
A45: Section 11.8: the sustainability line (Worked Example 10.1's rent) | B45: Value | C45: Reading
A46: Capability lost a quarter to attrition, delta | B46: 0.025 | C46: Worked Example 10.1
A47: Workforce capability held | B47: 58
A48: Price of a capability point ($ million) | B48: 4 | C48: the buyer's discount, $20m for 5 points
A49: Floor for the digital build | B49: 55
A50: Rent, points a quarter, delta x 58 | B50: =B46*B47 -> 1.45 | C50: 1.45
A51: Rent, $ million a year | B51: =4*B50*B48 -> 23.2 | C51: about $23 million a year
A53: Quarter with no rent | B53: Capability
A54: 0 | B54: =$B$47*(1-$B$46)^A54 -> 58
A55: 1 | B55: =$B$47*(1-$B$46)^A55 -> 56.55
A56: 2 | B56: =$B$47*(1-$B$46)^A56 -> 55.13625
A57: 3 | B57: =$B$47*(1-$B$46)^A57 -> 53.757844
A58: 4 | B58: =$B$47*(1-$B$46)^A58 -> 52.413898
A59: First quarter below the floor of 55 | B59: =COUNTIF(B54:B58,">="&B49) -> 3 | C59: Skipping the rent adds it to reported EBITDA while capability falls below 55 within three quarters: performance borrowed from a stock (Definition 11.11).

Sheet Dependencies
A1: Table 11.4's lag floors from Chapter 9's architecture: distances between the supports (Theorem 11.3(i); AXIOM Lab 1.11, step 1)
A2: The fewest arrows from one component to another is the fewest quarters in which a shock can travel between them; 99 means no path. Distances by repeated min-plus squaring: D2 = D1 * D1, D4, D8.
A3: From | B3: To | C3: Arrow (Chapter 9)
A4: MKT | B4: IND | C4: demand
A5: MKT | B5: DIG | C5: demand
A6: MKT | B6: MAT | C6: demand
A7: IND | B7: TRS | C7: cash
A8: DIG | B8: TRS | C8: cash
A9: MAT | B9: TRS | C9: cash
A10: TRS | B10: IND | C10: funding
A11: TRS | B11: DIG | C11: funding
A12: ENG | B12: IND | C12: capability
A13: IND | B13: ENG | C13: capability
A14: ENG | B14: DIG | C14: capability
... A17: GOV | B17: DIG | C17: policy
A20: Arrows (from row to column) | B20: MKT | C20: GOV | D20: MAT | E20: IND | F20: DIG | G20: ENG | H20: TRS
A21: MKT | B21: =COUNTIFS($A$4:$A$17,$A21,$B$4:$B$17,B$20) -> 0 | C21: =COUNTIFS($A$4:$A$17,$A21,$B$4:$B$17,C$20) -> 0 | D21: =COUNTIFS($A$4:$A$17,$A21,$B$4:$B$17,D$20) -> 1 | E21: =COUNTIFS($A$4:$A$17,$A21,$B$4:$B$17,E$20) -> 1 | F21: =COUNTIFS($A$4:$A$17,$A21,$B$4:$B$17,F$20) -> 1 | G21: =COUNTIFS($A$4:$A$17,$A21,$B$4:$B$17,G$20) -> 0 | H21: =COUNTIFS($A$4:$A$17,$A21,$B$4:$B$17,H$20) -> 0
A22: GOV | B22: =COUNTIFS($A$4:$A$17,$A22,$B$4:$B$17,B$20) -> 0 | C22: =COUNTIFS($A$4:$A$17,$A22,$B$4:$B$17,C$20) -> 0 | D22: =COUNTIFS($A$4:$A$17,$A22,$B$4:$B$17,D$20) -> 0 | E22: =COUNTIFS($A$4:$A$17,$A22,$B$4:$B$17,E$20) -> 0 | F22: =COUNTIFS($A$4:$A$17,$A22,$B$4:$B$17,F$20) -> 1 | G22: =COUNTIFS($A$4:$A$17,$A22,$B$4:$B$17,G$20) -> 0 | H22: =COUNTIFS($A$4:$A$17,$A22,$B$4:$B$17,H$20) -> 1
A23: MAT | B23: =COUNTIFS($A$4:$A$17,$A23,$B$4:$B$17,B$20) -> 0 | C23: =COUNTIFS($A$4:$A$17,$A23,$B$4:$B$17,C$20) -> 0 | D23: =COUNTIFS($A$4:$A$17,$A23,$B$4:$B$17,D$20) -> 0 | E23: =COUNTIFS($A$4:$A$17,$A23,$B$4:$B$17,E$20) -> 0 | F23: =COUNTIFS($A$4:$A$17,$A23,$B$4:$B$17,F$20) -> 0 | G23: =COUNTIFS($A$4:$A$17,$A23,$B$4:$B$17,G$20) -> 0 | H23: =COUNTIFS($A$4:$A$17,$A23,$B$4:$B$17,H$20) -> 1
A24: IND | B24: =COUNTIFS($A$4:$A$17,$A24,$B$4:$B$17,B$20) -> 0 | C24: =COUNTIFS($A$4:$A$17,$A24,$B$4:$B$17,C$20) -> 0 | D24: =COUNTIFS($A$4:$A$17,$A24,$B$4:$B$17,D$20) -> 0 | E24: =COUNTIFS($A$4:$A$17,$A24,$B$4:$B$17,E$20) -> 0 | F24: =COUNTIFS($A$4:$A$17,$A24,$B$4:$B$17,F$20) -> 0 | G24: =COUNTIFS($A$4:$A$17,$A24,$B$4:$B$17,G$20) -> 1 | H24: =COUNTIFS($A$4:$A$17,$A24,$B$4:$B$17,H$20) -> 1
A25: DIG | B25: =COUNTIFS($A$4:$A$17,$A25,$B$4:$B$17,B$20) -> 0 | C25: =COUNTIFS($A$4:$A$17,$A25,$B$4:$B$17,C$20) -> 0 | D25: =COUNTIFS($A$4:$A$17,$A25,$B$4:$B$17,D$20) -> 0 | E25: =COUNTIFS($A$4:$A$17,$A25,$B$4:$B$17,E$20) -> 0 | F25: =COUNTIFS($A$4:$A$17,$A25,$B$4:$B$17,F$20) -> 0 | G25: =COUNTIFS($A$4:$A$17,$A25,$B$4:$B$17,G$20) -> 1 | H25: =COUNTIFS($A$4:$A$17,$A25,$B$4:$B$17,H$20) -> 1
A26: ENG | B26: =COUNTIFS($A$4:$A$17,$A26,$B$4:$B$17,B$20) -> 0 | C26: =COUNTIFS($A$4:$A$17,$A26,$B$4:$B$17,C$20) -> 0 | D26: =COUNTIFS($A$4:$A$17,$A26,$B$4:$B$17,D$20) -> 0 | E26: =COUNTIFS($A$4:$A$17,$A26,$B$4:$B$17,E$20) -> 1 | F26: =COUNTIFS($A$4:$A$17,$A26,$B$4:$B$17,F$20) -> 1 | G26: =COUNTIFS($A$4:$A$17,$A26,$B$4:$B$17,G$20) -> 0 | H26: =COUNTIFS($A$4:$A$17,$A26,$B$4:$B$17,H$20) -> 0
A27: TRS | B27: =COUNTIFS($A$4:$A$17,$A27,$B$4:$B$17,B$20) -> 0 | C27: =COUNTIFS($A$4:$A$17,$A27,$B$4:$B$17,C$20) -> 0 | D27: =COUNTIFS($A$4:$A$17,$A27,$B$4:$B$17,D$20) -> 0 | E27: =COUNTIFS($A$4:$A$17,$A27,$B$4:$B$17,E$20) -> 1 | F27: =COUNTIFS($A$4:$A$17,$A27,$B$4:$B$17,F$20) -> 1 | G27: =COUNTIFS($A$4:$A$17,$A27,$B$4:$B$17,G$20) -> 0 | H27: =COUNTIFS($A$4:$A$17,$A27,$B$4:$B$17,H$20) -> 0
A30: D1: one arrow | B30: MKT | C30: GOV | D30: MAT | E30: IND | F30: DIG | G30: ENG | H30: TRS
A31: MKT | B31: =IF($A31=B$30,0,IF(B21>0,1,99)) -> 0 | C31: =IF($A31=C$30,0,IF(C21>0,1,99)) -> 99 | D31: =IF($A31=D$30,0,IF(D21>0,1,99)) -> 1 | E31: =IF($A31=E$30,0,IF(E21>0,1,99)) -> 1 | F31: =IF($A31=F$30,0,IF(F21>0,1,99)) -> 1 | G31: =IF($A31=G$30,0,IF(G21>0,1,99)) -> 99 | H31: =IF($A31=H$30,0,IF(H21>0,1,99)) -> 99
A32: GOV | B32: =IF($A32=B$30,0,IF(B22>0,1,99)) -> 99 | C32: =IF($A32=C$30,0,IF(C22>0,1,99)) -> 0 | D32: =IF($A32=D$30,0,IF(D22>0,1,99)) -> 99 | E32: =IF($A32=E$30,0,IF(E22>0,1,99)) -> 99 | F32: =IF($A32=F$30,0,IF(F22>0,1,99)) -> 1 | G32: =IF($A32=G$30,0,IF(G22>0,1,99)) -> 99 | H32: =IF($A32=H$30,0,IF(H22>0,1,99)) -> 1
A33: MAT | B33: =IF($A33=B$30,0,IF(B23>0,1,99)) -> 99 | C33: =IF($A33=C$30,0,IF(C23>0,1,99)) -> 99 | D33: =IF($A33=D$30,0,IF(D23>0,1,99)) -> 0 | E33: =IF($A33=E$30,0,IF(E23>0,1,99)) -> 99 | F33: =IF($A33=F$30,0,IF(F23>0,1,99)) -> 99 | G33: =IF($A33=G$30,0,IF(G23>0,1,99)) -> 99 | H33: =IF($A33=H$30,0,IF(H23>0,1,99)) -> 1
A34: IND | B34: =IF($A34=B$30,0,IF(B24>0,1,99)) -> 99 | C34: =IF($A34=C$30,0,IF(C24>0,1,99)) -> 99 | D34: =IF($A34=D$30,0,IF(D24>0,1,99)) -> 99 | E34: =IF($A34=E$30,0,IF(E24>0,1,99)) -> 0 | F34: =IF($A34=F$30,0,IF(F24>0,1,99)) -> 99 | G34: =IF($A34=G$30,0,IF(G24>0,1,99)) -> 1 | H34: =IF($A34=H$30,0,IF(H24>0,1,99)) -> 1
A35: DIG | B35: =IF($A35=B$30,0,IF(B25>0,1,99)) -> 99 | C35: =IF($A35=C$30,0,IF(C25>0,1,99)) -> 99 | D35: =IF($A35=D$30,0,IF(D25>0,1,99)) -> 99 | E35: =IF($A35=E$30,0,IF(E25>0,1,99)) -> 99 | F35: =IF($A35=F$30,0,IF(F25>0,1,99)) -> 0 | G35: =IF($A35=G$30,0,IF(G25>0,1,99)) -> 1 | H35: =IF($A35=H$30,0,IF(H25>0,1,99)) -> 1
A36: ENG | B36: =IF($A36=B$30,0,IF(B26>0,1,99)) -> 99 | C36: =IF($A36=C$30,0,IF(C26>0,1,99)) -> 99 | D36: =IF($A36=D$30,0,IF(D26>0,1,99)) -> 99 | E36: =IF($A36=E$30,0,IF(E26>0,1,99)) -> 1 | F36: =IF($A36=F$30,0,IF(F26>0,1,99)) -> 1 | G36: =IF($A36=G$30,0,IF(G26>0,1,99)) -> 0 | H36: =IF($A36=H$30,0,IF(H26>0,1,99)) -> 99
A37: TRS | B37: =IF($A37=B$30,0,IF(B27>0,1,99)) -> 99 | C37: =IF($A37=C$30,0,IF(C27>0,1,99)) -> 99 | D37: =IF($A37=D$30,0,IF(D27>0,1,99)) -> 99 | E37: =IF($A37=E$30,0,IF(E27>0,1,99)) -> 1 | F37: =IF($A37=F$30,0,IF(F27>0,1,99)) -> 1 | G37: =IF($A37=G$30,0,IF(G27>0,1,99)) -> 99 | H37: =IF($A37=H$30,0,IF(H27>0,1,99)) -> 0
A40: D2: at most 2 arrows | B40: MKT | C40: GOV | D40: MAT | E40: IND | F40: DIG | G40: ENG | H40: TRS
A41: MKT | B41: =MIN(99,B31+B31,C31+B32,D31+B33,E31+B34,F31+B35,G31+B36,H31+B37) -> 0 | C41: =MIN(99,B31+C31,C31+C32,D31+C33,E31+C34,F31+C35,G31+C36,H31+C37) -> 99 | D41: =MIN(99,B31+D31,C31+D32,D31+D33,E31+D34,F31+D35,G31+D36,H31+D37) -> 1 | E41: =MIN(99,B31+E31,C31+E32,D31+E33,E31+E34,F31+E35,G31+E36,H31+E37) -> 1 | F41: =MIN(99,B31+F31,C31+F32,D31+F33,E31+F34,F31+F35,G31+F36,H31+F37) -> 1 | G41: =MIN(99,B31+G31,C31+G32,D31+G33,E31+G34,F31+G35,G31+G36,H31+G37) -> 2 | H41: =MIN(99,B31+H31,C31+H32,D31+H33,E31+H34,F31+H35,G31+H36,H31+H37) -> 2
A42: GOV | B42: =MIN(99,B32+B31,C32+B32,D32+B33,E32+B34,F32+B35,G32+B36,H32+B37) -> 99 | C42: =MIN(99,B32+C31,C32+C32,D32+C33,E32+C34,F32+C35,G32+C36,H32+C37) -> 0 | D42: =MIN(99,B32+D31,C32+D32,D32+D33,E32+D34,F32+D35,G32+D36,H32+D37) -> 99 | E42: =MIN(99,B32+E31,C32+E32,D32+E33,E32+E34,F32+E35,G32+E36,H32+E37) -> 2 | F42: =MIN(99,B32+F31,C32+F32,D32+F33,E32+F34,F32+F35,G32+F36,H32+F37) -> 1 | G42: =MIN(99,B32+G31,C32+G32,D32+G33,E32+G34,F32+G35,G32+G36,H32+G37) -> 2 | H42: =MIN(99,B32+H31,C32+H32,D32+H33,E32+H34,F32+H35,G32+H36,H32+H37) -> 1
A43: MAT | B43: =MIN(99,B33+B31,C33+B32,D33+B33,E33+B34,F33+B35,G33+B36,H33+B37) -> 99 | C43: =MIN(99,B33+C31,C33+C32,D33+C33,E33+C34,F33+C35,G33+C36,H33+C37) -> 99 | D43: =MIN(99,B33+D31,C33+D32,D33+D33,E33+D34,F33+D35,G33+D36,H33+D37) -> 0 | E43: =MIN(99,B33+E31,C33+E32,D33+E33,E33+E34,F33+E35,G33+E36,H33+E37) -> 2 | F43: =MIN(99,B33+F31,C33+F32,D33+F33,E33+F34,F33+F35,G33+F36,H33+F37) -> 2 | G43: =MIN(99,B33+G31,C33+G32,D33+G33,E33+G34,F33+G35,G33+G36,H33+G37) -> 99 | H43: =MIN(99,B33+H31,C33+H32,D33+H33,E33+H34,F33+H35,G33+H36,H33+H37) -> 1
A44: IND | B44: =MIN(99,B34+B31,C34+B32,D34+B33,E34+B34,F34+B35,G34+B36,H34+B37) -> 99 | C44: =MIN(99,B34+C31,C34+C32,D34+C33,E34+C34,F34+C35,G34+C36,H34+C37) -> 99 | D44: =MIN(99,B34+D31,C34+D32,D34+D33,E34+D34,F34+D35,G34+D36,H34+D37) -> 99 | E44: =MIN(99,B34+E31,C34+E32,D34+E33,E34+E34,F34+E35,G34+E36,H34+E37) -> 0 | F44: =MIN(99,B34+F31,C34+F32,D34+F33,E34+F34,F34+F35,G34+F36,H34+F37) -> 2 | G44: =MIN(99,B34+G31,C34+G32,D34+G33,E34+G34,F34+G35,G34+G36,H34+G37) -> 1 | H44: =MIN(99,B34+H31,C34+H32,D34+H33,E34+H34,F34+H35,G34+H36,H34+H37) -> 1
A45: DIG | B45: =MIN(99,B35+B31,C35+B32,D35+B33,E35+B34,F35+B35,G35+B36,H35+B37) -> 99 | C45: =MIN(99,B35+C31,C35+C32,D35+C33,E35+C34,F35+C35,G35+C36,H35+C37) -> 99 | D45: =MIN(99,B35+D31,C35+D32,D35+D33,E35+D34,F35+D35,G35+D36,H35+D37) -> 99 | E45: =MIN(99,B35+E31,C35+E32,D35+E33,E35+E34,F35+E35,G35+E36,H35+E37) -> 2 | F45: =MIN(99,B35+F31,C35+F32,D35+F33,E35+F34,F35+F35,G35+F36,H35+F37) -> 0 | G45: =MIN(99,B35+G31,C35+G32,D35+G33,E35+G34,F35+G35,G35+G36,H35+G37) -> 1 | H45: =MIN(99,B35+H31,C35+H32,D35+H33,E35+H34,F35+H35,G35+H36,H35+H37) -> 1
A46: ENG | B46: =MIN(99,B36+B31,C36+B32,D36+B33,E36+B34,F36+B35,G36+B36,H36+B37) -> 99 | C46: =MIN(99,B36+C31,C36+C32,D36+C33,E36+C34,F36+C35,G36+C36,H36+C37) -> 99 | D46: =MIN(99,B36+D31,C36+D32,D36+D33,E36+D34,F36+D35,G36+D36,H36+D37) -> 99 | E46: =MIN(99,B36+E31,C36+E32,D36+E33,E36+E34,F36+E35,G36+E36,H36+E37) -> 1 | F46: =MIN(99,B36+F31,C36+F32,D36+F33,E36+F34,F36+F35,G36+F36,H36+F37) -> 1 | G46: =MIN(99,B36+G31,C36+G32,D36+G33,E36+G34,F36+G35,G36+G36,H36+G37) -> 0 | H46: =MIN(99,B36+H31,C36+H32,D36+H33,E36+H34,F36+H35,G36+H36,H36+H37) -> 2
A47: TRS | B47: =MIN(99,B37+B31,C37+B32,D37+B33,E37+B34,F37+B35,G37+B36,H37+B37) -> 99 | C47: =MIN(99,B37+C31,C37+C32,D37+C33,E37+C34,F37+C35,G37+C36,H37+C37) -> 99 | D47: =MIN(99,B37+D31,C37+D32,D37+D33,E37+D34,F37+D35,G37+D36,H37+D37) -> 99 | E47: =MIN(99,B37+E31,C37+E32,D37+E33,E37+E34,F37+E35,G37+E36,H37+E37) -> 1 | F47: =MIN(99,B37+F31,C37+F32,D37+F33,E37+F34,F37+F35,G37+F36,H37+F37) -> 1 | G47: =MIN(99,B37+G31,C37+G32,D37+G33,E37+G34,F37+G35,G37+G36,H37+G37) -> 2 | H47: =MIN(99,B37+H31,C37+H32,D37+H33,E37+H34,F37+H35,G37+H36,H37+H37) -> 0
A50: D4: at most 4 arrows | B50: MKT | C50: GOV | D50: MAT | E50: IND | F50: DIG | G50: ENG | H50: TRS
A51: MKT | B51: =MIN(99,B41+B41,C41+B42,D41+B43,E41+B44,F41+B45,G41+B46,H41+B47) -> 0 | C51: =MIN(99,B41+C41,C41+C42,D41+C43,E41+C44,F41+C45,G41+C46,H41+C47) -> 99 | D51: =MIN(99,B41+D41,C41+D42,D41+D43,E41+D44,F41+D45,G41+D46,H41+D47) -> 1 | E51: =MIN(99,B41+E41,C41+E42,D41+E43,E41+E44,F41+E45,G41+E46,H41+E47) -> 1 | F51: =MIN(99,B41+F41,C41+F42,D41+F43,E41+F44,F41+F45,G41+F46,H41+F47) -> 1 | G51: =MIN(99,B41+G41,C41+G42,D41+G43,E41+G44,F41+G45,G41+G46,H41+G47) -> 2 | H51: =MIN(99,B41+H41,C41+H42,D41+H43,E41+H44,F41+H45,G41+H46,H41+H47) -> 2
A52: GOV | B52: =MIN(99,B42+B41,C42+B42,D42+B43,E42+B44,F42+B45,G42+B46,H42+B47) -> 99 | C52: =MIN(99,B42+C41,C42+C42,D42+C43,E42+C44,F42+C45,G42+C46,H42+C47) -> 0 | D52: =MIN(99,B42+D41,C42+D42,D42+D43,E42+D44,F42+D45,G42+D46,H42+D47) -> 99 | E52: =MIN(99,B42+E41,C42+E42,D42+E43,E42+E44,F42+E45,G42+E46,H42+E47) -> 2 | F52: =MIN(99,B42+F41,C42+F42,D42+F43,E42+F44,F42+F45,G42+F46,H42+F47) -> 1 | G52: =MIN(99,B42+G41,C42+G42,D42+G43,E42+G44,F42+G45,G42+G46,H42+G47) -> 2 | H52: =MIN(99,B42+H41,C42+H42,D42+H43,E42+H44,F42+H45,G42+H46,H42+H47) -> 1
A53: MAT | B53: =MIN(99,B43+B41,C43+B42,D43+B43,E43+B44,F43+B45,G43+B46,H43+B47) -> 99 | C53: =MIN(99,B43+C41,C43+C42,D43+C43,E43+C44,F43+C45,G43+C46,H43+C47) -> 99 | D53: =MIN(99,B43+D41,C43+D42,D43+D43,E43+D44,F43+D45,G43+D46,H43+D47) -> 0 | E53: =MIN(99,B43+E41,C43+E42,D43+E43,E43+E44,F43+E45,G43+E46,H43+E47) -> 2 | F53: =MIN(99,B43+F41,C43+F42,D43+F43,E43+F44,F43+F45,G43+F46,H43+F47) -> 2 | G53: =MIN(99,B43+G41,C43+G42,D43+G43,E43+G44,F43+G45,G43+G46,H43+G47) -> 3 | H53: =MIN(99,B43+H41,C43+H42,D43+H43,E43+H44,F43+H45,G43+H46,H43+H47) -> 1
A54: IND | B54: =MIN(99,B44+B41,C44+B42,D44+B43,E44+B44,F44+B45,G44+B46,H44+B47) -> 99 | C54: =MIN(99,B44+C41,C44+C42,D44+C43,E44+C44,F44+C45,G44+C46,H44+C47) -> 99 | D54: =MIN(99,B44+D41,C44+D42,D44+D43,E44+D44,F44+D45,G44+D46,H44+D47) -> 99 | E54: =MIN(99,B44+E41,C44+E42,D44+E43,E44+E44,F44+E45,G44+E46,H44+E47) -> 0 | F54: =MIN(99,B44+F41,C44+F42,D44+F43,E44+F44,F44+F45,G44+F46,H44+F47) -> 2 | G54: =MIN(99,B44+G41,C44+G42,D44+G43,E44+G44,F44+G45,G44+G46,H44+G47) -> 1 | H54: =MIN(99,B44+H41,C44+H42,D44+H43,E44+H44,F44+H45,G44+H46,H44+H47) -> 1
A55: DIG | B55: =MIN(99,B45+B41,C45+B42,D45+B43,E45+B44,F45+B45,G45+B46,H45+B47) -> 99 | C55: =MIN(99,B45+C41,C45+C42,D45+C43,E45+C44,F45+C45,G45+C46,H45+C47) -> 99 | D55: =MIN(99,B45+D41,C45+D42,D45+D43,E45+D44,F45+D45,G45+D46,H45+D47) -> 99 | E55: =MIN(99,B45+E41,C45+E42,D45+E43,E45+E44,F45+E45,G45+E46,H45+E47) -> 2 | F55: =MIN(99,B45+F41,C45+F42,D45+F43,E45+F44,F45+F45,G45+F46,H45+F47) -> 0 | G55: =MIN(99,B45+G41,C45+G42,D45+G43,E45+G44,F45+G45,G45+G46,H45+G47) -> 1 | H55: =MIN(99,B45+H41,C45+H42,D45+H43,E45+H44,F45+H45,G45+H46,H45+H47) -> 1
A56: ENG | B56: =MIN(99,B46+B41,C46+B42,D46+B43,E46+B44,F46+B45,G46+B46,H46+B47) -> 99 | C56: =MIN(99,B46+C41,C46+C42,D46+C43,E46+C44,F46+C45,G46+C46,H46+C47) -> 99 | D56: =MIN(99,B46+D41,C46+D42,D46+D43,E46+D44,F46+D45,G46+D46,H46+D47) -> 99 | E56: =MIN(99,B46+E41,C46+E42,D46+E43,E46+E44,F46+E45,G46+E46,H46+E47) -> 1 | F56: =MIN(99,B46+F41,C46+F42,D46+F43,E46+F44,F46+F45,G46+F46,H46+F47) -> 1 | G56: =MIN(99,B46+G41,C46+G42,D46+G43,E46+G44,F46+G45,G46+G46,H46+G47) -> 0 | H56: =MIN(99,B46+H41,C46+H42,D46+H43,E46+H44,F46+H45,G46+H46,H46+H47) -> 2
A57: TRS | B57: =MIN(99,B47+B41,C47+B42,D47+B43,E47+B44,F47+B45,G47+B46,H47+B47) -> 99 | C57: =MIN(99,B47+C41,C47+C42,D47+C43,E47+C44,F47+C45,G47+C46,H47+C47) -> 99 | D57: =MIN(99,B47+D41,C47+D42,D47+D43,E47+D44,F47+D45,G47+D46,H47+D47) -> 99 | E57: =MIN(99,B47+E41,C47+E42,D47+E43,E47+E44,F47+E45,G47+E46,H47+E47) -> 1 | F57: =MIN(99,B47+F41,C47+F42,D47+F43,E47+F44,F47+F45,G47+F46,H47+F47) -> 1 | G57: =MIN(99,B47+G41,C47+G42,D47+G43,E47+G44,F47+G45,G47+G46,H47+G47) -> 2 | H57: =MIN(99,B47+H41,C47+H42,D47+H43,E47+H44,F47+H45,G47+H46,H47+H47) -> 0
A60: D8: at most 8 arrows | B60: MKT | C60: GOV | D60: MAT | E60: IND | F60: DIG | G60: ENG | H60: TRS
A61: MKT | B61: =MIN(99,B51+B51,C51+B52,D51+B53,E51+B54,F51+B55,G51+B56,H51+B57) -> 0 | C61: =MIN(99,B51+C51,C51+C52,D51+C53,E51+C54,F51+C55,G51+C56,H51+C57) -> 99 | D61: =MIN(99,B51+D51,C51+D52,D51+D53,E51+D54,F51+D55,G51+D56,H51+D57) -> 1 | E61: =MIN(99,B51+E51,C51+E52,D51+E53,E51+E54,F51+E55,G51+E56,H51+E57) -> 1 | F61: =MIN(99,B51+F51,C51+F52,D51+F53,E51+F54,F51+F55,G51+F56,H51+F57) -> 1 | G61: =MIN(99,B51+G51,C51+G52,D51+G53,E51+G54,F51+G55,G51+G56,H51+G57) -> 2 | H61: =MIN(99,B51+H51,C51+H52,D51+H53,E51+H54,F51+H55,G51+H56,H51+H57) -> 2
A62: GOV | B62: =MIN(99,B52+B51,C52+B52,D52+B53,E52+B54,F52+B55,G52+B56,H52+B57) -> 99 | C62: =MIN(99,B52+C51,C52+C52,D52+C53,E52+C54,F52+C55,G52+C56,H52+C57) -> 0 | D62: =MIN(99,B52+D51,C52+D52,D52+D53,E52+D54,F52+D55,G52+D56,H52+D57) -> 99 | E62: =MIN(99,B52+E51,C52+E52,D52+E53,E52+E54,F52+E55,G52+E56,H52+E57) -> 2 | F62: =MIN(99,B52+F51,C52+F52,D52+F53,E52+F54,F52+F55,G52+F56,H52+F57) -> 1 | G62: =MIN(99,B52+G51,C52+G52,D52+G53,E52+G54,F52+G55,G52+G56,H52+G57) -> 2 | H62: =MIN(99,B52+H51,C52+H52,D52+H53,E52+H54,F52+H55,G52+H56,H52+H57) -> 1
A63: MAT | B63: =MIN(99,B53+B51,C53+B52,D53+B53,E53+B54,F53+B55,G53+B56,H53+B57) -> 99 | C63: =MIN(99,B53+C51,C53+C52,D53+C53,E53+C54,F53+C55,G53+C56,H53+C57) -> 99 | D63: =MIN(99,B53+D51,C53+D52,D53+D53,E53+D54,F53+D55,G53+D56,H53+D57) -> 0 | E63: =MIN(99,B53+E51,C53+E52,D53+E53,E53+E54,F53+E55,G53+E56,H53+E57) -> 2 | F63: =MIN(99,B53+F51,C53+F52,D53+F53,E53+F54,F53+F55,G53+F56,H53+F57) -> 2 | G63: =MIN(99,B53+G51,C53+G52,D53+G53,E53+G54,F53+G55,G53+G56,H53+G57) -> 3 | H63: =MIN(99,B53+H51,C53+H52,D53+H53,E53+H54,F53+H55,G53+H56,H53+H57) -> 1
A64: IND | B64: =MIN(99,B54+B51,C54+B52,D54+B53,E54+B54,F54+B55,G54+B56,H54+B57) -> 99 | C64: =MIN(99,B54+C51,C54+C52,D54+C53,E54+C54,F54+C55,G54+C56,H54+C57) -> 99 | D64: =MIN(99,B54+D51,C54+D52,D54+D53,E54+D54,F54+D55,G54+D56,H54+D57) -> 99 | E64: =MIN(99,B54+E51,C54+E52,D54+E53,E54+E54,F54+E55,G54+E56,H54+E57) -> 0 | F64: =MIN(99,B54+F51,C54+F52,D54+F53,E54+F54,F54+F55,G54+F56,H54+F57) -> 2 | G64: =MIN(99,B54+G51,C54+G52,D54+G53,E54+G54,F54+G55,G54+G56,H54+G57) -> 1 | H64: =MIN(99,B54+H51,C54+H52,D54+H53,E54+H54,F54+H55,G54+H56,H54+H57) -> 1
A65: DIG | B65: =MIN(99,B55+B51,C55+B52,D55+B53,E55+B54,F55+B55,G55+B56,H55+B57) -> 99 | C65: =MIN(99,B55+C51,C55+C52,D55+C53,E55+C54,F55+C55,G55+C56,H55+C57) -> 99 | D65: =MIN(99,B55+D51,C55+D52,D55+D53,E55+D54,F55+D55,G55+D56,H55+D57) -> 99 | E65: =MIN(99,B55+E51,C55+E52,D55+E53,E55+E54,F55+E55,G55+E56,H55+E57) -> 2 | F65: =MIN(99,B55+F51,C55+F52,D55+F53,E55+F54,F55+F55,G55+F56,H55+F57) -> 0 | G65: =MIN(99,B55+G51,C55+G52,D55+G53,E55+G54,F55+G55,G55+G56,H55+G57) -> 1 | H65: =MIN(99,B55+H51,C55+H52,D55+H53,E55+H54,F55+H55,G55+H56,H55+H57) -> 1
A66: ENG | B66: =MIN(99,B56+B51,C56+B52,D56+B53,E56+B54,F56+B55,G56+B56,H56+B57) -> 99 | C66: =MIN(99,B56+C51,C56+C52,D56+C53,E56+C54,F56+C55,G56+C56,H56+C57) -> 99 | D66: =MIN(99,B56+D51,C56+D52,D56+D53,E56+D54,F56+D55,G56+D56,H56+D57) -> 99 | E66: =MIN(99,B56+E51,C56+E52,D56+E53,E56+E54,F56+E55,G56+E56,H56+E57) -> 1 | F66: =MIN(99,B56+F51,C56+F52,D56+F53,E56+F54,F56+F55,G56+F56,H56+F57) -> 1 | G66: =MIN(99,B56+G51,C56+G52,D56+G53,E56+G54,F56+G55,G56+G56,H56+G57) -> 0 | H66: =MIN(99,B56+H51,C56+H52,D56+H53,E56+H54,F56+H55,G56+H56,H56+H57) -> 2
A67: TRS | B67: =MIN(99,B57+B51,C57+B52,D57+B53,E57+B54,F57+B55,G57+B56,H57+B57) -> 99 | C67: =MIN(99,B57+C51,C57+C52,D57+C53,E57+C54,F57+C55,G57+C56,H57+C57) -> 99 | D67: =MIN(99,B57+D51,C57+D52,D57+D53,E57+D54,F57+D55,G57+D56,H57+D57) -> 99 | E67: =MIN(99,B57+E51,C57+E52,D57+E53,E57+E54,F57+E55,G57+E56,H57+E57) -> 1 | F67: =MIN(99,B57+F51,C57+F52,D57+F53,E57+F54,F57+F55,G57+F56,H57+F57) -> 1 | G67: =MIN(99,B57+G51,C57+G52,D57+G53,E57+G54,F57+G55,G57+G56,H57+G57) -> 2 | H67: =MIN(99,B57+H51,C57+H52,D57+H53,E57+H54,F57+H55,G57+H56,H57+H57) -> 0
A70: Dimension | B70: Support (Table 11.4)
A71: P_F financial | B71: TRS
A72: P_O operational | B72: IND, MAT
A73: P_S strategic | B73: IND, DIG, MAT
A74: P_T technological | B74: DIG
A75: P_I innovation | B75: DIG, ENG
A76: P_R resilience | B76: TRS
A78: Lag floor (quarters): distance from the row's support to the column's | B78: P_F | C78: P_O | D78: P_S | E78: P_T | F78: P_I | G78: P_R
A79: P_F | B79: =MIN(H67) -> 0 | C79: =MIN(E67,D67) -> 1 | D79: =MIN(E67,F67,D67) -> 1 | E79: =MIN(F67) -> 1 | F79: =MIN(F67,G67) -> 1 | G79: =MIN(H67) -> 0
A80: P_O | B80: =MIN(H64,H63) -> 1 | C80: =MIN(E64,D64,E63,D63) -> 0 | D80: =MIN(E64,F64,D64,E63,F63,D63) -> 0 | E80: =MIN(F64,F63) -> 2 | F80: =MIN(F64,G64,F63,G63) -> 1 | G80: =MIN(H64,H63) -> 1
A81: P_S | B81: =MIN(H64,H65,H63) -> 1 | C81: =MIN(E64,D64,E65,D65,E63,D63) -> 0 | D81: =MIN(E64,F64,D64,E65,F65,D65,E63,F63,D63) -> 0 | E81: =MIN(F64,F65,F63) -> 0 | F81: =MIN(F64,G64,F65,G65,F63,G63) -> 0 | G81: =MIN(H64,H65,H63) -> 1
A82: P_T | B82: =MIN(H65) -> 1 | C82: =MIN(E65,D65) -> 2 | D82: =MIN(E65,F65,D65) -> 0 | E82: =MIN(F65) -> 0 | F82: =MIN(F65,G65) -> 0 | G82: =MIN(H65) -> 1
A83: P_I | B83: =MIN(H65,H66) -> 1 | C83: =MIN(E65,D65,E66,D66) -> 1 | D83: =MIN(E65,F65,D65,E66,F66,D66) -> 0 | E83: =MIN(F65,F66) -> 0 | F83: =MIN(F65,G65,F66,G66) -> 0 | G83: =MIN(H65,H66) -> 1
A84: P_R | B84: =MIN(H67) -> 0 | C84: =MIN(E67,D67) -> 1 | D84: =MIN(E67,F67,D67) -> 1 | E84: =MIN(F67) -> 1 | F84: =MIN(F67,G67) -> 1 | G84: =MIN(H67) -> 0
A86: Table 11.4 as printed: the declared lag floors (blank: no material effect declared) | B86: P_F | C86: P_O | D86: P_S | E86: P_T | F86: P_I | G86: P_R
A87: P_F | B87: --- | C87: 1 | D87: 1 | E87: 1 | F87: 1 | G87: 0
A88: P_O | B88: 1 | C88: --- | D88: 0 | G88: 1
A89: P_S | B89: 1 | D89: --- | F89: 0
A90: P_T | B90: 1 | C90: 2 | D90: 0 | E90: --- | F90: 0 | G90: 1
A91: P_I | B91: 1 | D91: 0 | E91: 0 | F91: ---
A92: P_R | B92: 0 | C92: 1 | G92: ---
A95: Declared sign of the medium-run effect | B95: P_F | C95: P_O | D95: P_S | E95: P_T | F95: P_I | G95: P_R
A96: P_F | B96: --- | C96: + | D96: + | E96: + | F96: + | G96: +
A97: P_O | B97: + | C97: --- | D97: + | G97: +
A98: P_S | B98: + | D98: --- | F98: +
A99: P_T | B99: + | C99: + | D99: + | E99: --- | F99: + | G99: +
A100: P_I | B100: + | D100: + | E100: + | F100: ---
A101: P_R | B101: - | C101: - | G101: ---
A103: Declared floor equal to the computed distance (1 = yes)
A104: P_F | B104: =IF(ISNUMBER(B87),IF(B87=B79,1,0),"") | C104: =IF(ISNUMBER(C87),IF(C87=C79,1,0),"") -> 1 | D104: =IF(ISNUMBER(D87),IF(D87=D79,1,0),"") -> 1 | E104: =IF(ISNUMBER(E87),IF(E87=E79,1,0),"") -> 1 | F104: =IF(ISNUMBER(F87),IF(F87=F79,1,0),"") -> 1 | G104: =IF(ISNUMBER(G87),IF(G87=G79,1,0),"") -> 1
A105: P_O | B105: =IF(ISNUMBER(B88),IF(B88=B80,1,0),"") -> 1 | C105: =IF(ISNUMBER(C88),IF(C88=C80,1,0),"") | D105: =IF(ISNUMBER(D88),IF(D88=D80,1,0),"") -> 1 | E105: =IF(ISNUMBER(E88),IF(E88=E80,1,0),"") | F105: =IF(ISNUMBER(F88),IF(F88=F80,1,0),"") | G105: =IF(ISNUMBER(G88),IF(G88=G80,1,0),"") -> 1
A106: P_S | B106: =IF(ISNUMBER(B89),IF(B89=B81,1,0),"") -> 1 | C106: =IF(ISNUMBER(C89),IF(C89=C81,1,0),"") | D106: =IF(ISNUMBER(D89),IF(D89=D81,1,0),"") | E106: =IF(ISNUMBER(E89),IF(E89=E81,1,0),"") | F106: =IF(ISNUMBER(F89),IF(F89=F81,1,0),"") -> 1 | G106: =IF(ISNUMBER(G89),IF(G89=G81,1,0),"")
A107: P_T | B107: =IF(ISNUMBER(B90),IF(B90=B82,1,0),"") -> 1 | C107: =IF(ISNUMBER(C90),IF(C90=C82,1,0),"") -> 1 | D107: =IF(ISNUMBER(D90),IF(D90=D82,1,0),"") -> 1 | E107: =IF(ISNUMBER(E90),IF(E90=E82,1,0),"") | F107: =IF(ISNUMBER(F90),IF(F90=F82,1,0),"") -> 1 | G107: =IF(ISNUMBER(G90),IF(G90=G82,1,0),"") -> 1
A108: P_I | B108: =IF(ISNUMBER(B91),IF(B91=B83,1,0),"") -> 1 | C108: =IF(ISNUMBER(C91),IF(C91=C83,1,0),"") | D108: =IF(ISNUMBER(D91),IF(D91=D83,1,0),"") -> 1 | E108: =IF(ISNUMBER(E91),IF(E91=E83,1,0),"") -> 1 | F108: =IF(ISNUMBER(F91),IF(F91=F83,1,0),"") | G108: =IF(ISNUMBER(G91),IF(G91=G83,1,0),"")
A109: P_R | B109: =IF(ISNUMBER(B92),IF(B92=B84,1,0),"") -> 1 | C109: =IF(ISNUMBER(C92),IF(C92=C84,1,0),"") -> 1 | D109: =IF(ISNUMBER(D92),IF(D92=D84,1,0),"") | E109: =IF(ISNUMBER(E92),IF(E92=E84,1,0),"") | F109: =IF(ISNUMBER(F92),IF(F92=F84,1,0),"") | G109: =IF(ISNUMBER(G92),IF(G92=G84,1,0),"")
A111: Declared lag floors | B111: =COUNT(B87:G92) -> 20 | C111: Table 11.4: 20 entries
A112: Declared lag floors equal to the distances | B112: =SUM(B104:G109) -> 20 | C112: all of them
A113: Digital to Industrial Systems (quarters) | B113: =E65 -> 2 | C113: nothing done in Digital reaches Industrial Systems' operations in less than two quarters
A114: Digital to Materials (99: no path) | B114: =D65 -> 99 | C114: no path leads from Digital to Materials at all

Sheet Weights
A1: Check for dominance and sweep the weights (Worked Example 11.1, Steps 1-2; Theorem 11.2(ii); Figure 11.1; Online Appendix 11.B.2; AXIOM Lab 1.11, step 2)
A4: Year 5 (month 60) | B4: Liquidity | C4: Technology | D4: Efficiency | E4: Strategic risk | F4: Score
A5: Digital | B5: =Paths!C65 -> 94.295601 | C5: =Paths!D65 -> 75.634669 | D5: =Paths!E65 -> 73.598331 | E5: =Paths!F65 -> 55.21775 | F5: =W_L*S_L*B5+W_T*S_T*C5+W_E*S_E*D5+W_R*S_R*E5 -> 47.077713
A6: Restructuring | B6: =Paths!G65 -> 121.10748 | C6: =Paths!H65 -> 38.859514 | D6: =Paths!I65 -> 73.683802 | E6: =Paths!J65 -> 49.390192 | F6: =W_L*S_L*B6+W_T*S_T*C6+W_E*S_E*D6+W_R*S_R*E6 -> 46.065151
A7: Turnaround | B7: =Paths!K65 -> 105.3676 | C7: =Paths!L65 -> 35.943036 | D7: =Paths!M65 -> 78.601703 | E7: =Paths!N65 -> 66.33061 | F7: =W_L*S_L*B7+W_T*S_T*C7+W_E*S_E*D7+W_R*S_R*E7 -> 38.395434
A8: Today | B8: =Today_L -> 100 | C8: =Today_T -> 41 | D8: =Today_E -> 71 | E8: =Today_R -> 64 | F8: =Score_today -> 37
A10: Signed (strategic risk reversed) | B10: Liquidity | C10: Technology | D10: Efficiency | E10: Strategic risk
A11: Digital | B11: =B5*S_L -> 94.295601 | C11: =C5*S_T -> 75.634669 | D11: =D5*S_E -> 73.598331 | E11: =E5*S_R -> -55.21775
A12: Restructuring | B12: =B6*S_L -> 121.10748 | C12: =C6*S_T -> 38.859514 | D12: =D6*S_E -> 73.683802 | E12: =E6*S_R -> -49.390192
A13: Turnaround | B13: =B7*S_L -> 105.3676 | C13: =C7*S_T -> 35.943036 | D13: =D7*S_E -> 78.601703 | E13: =E7*S_R -> -66.33061
A15: Does the first option dominate the second? (Step 1) | B15: At least as good, of 4 | C15: Better, of 4 | D15: Dominates
A16: Digital over restructuring | B16: =SUMPRODUCT(--(B11:E11>=B12:E12)) -> 1 | C16: =SUMPRODUCT(--(B11:E11>B12:E12)) -> 1 | D16: =IF(AND(B16=4,C16>=1),1,0) -> 0
A17: Digital over turnaround | B17: =SUMPRODUCT(--(B11:E11>=B13:E13)) -> 2 | C17: =SUMPRODUCT(--(B11:E11>B13:E13)) -> 2 | D17: =IF(AND(B17=4,C17>=1),1,0) -> 0
A18: Restructuring over digital | B18: =SUMPRODUCT(--(B12:E12>=B11:E11)) -> 3 | C18: =SUMPRODUCT(--(B12:E12>B11:E11)) -> 3 | D18: =IF(AND(B18=4,C18>=1),1,0) -> 0
A19: Restructuring over turnaround | B19: =SUMPRODUCT(--(B12:E12>=B13:E13)) -> 3 | C19: =SUMPRODUCT(--(B12:E12>B13:E13)) -> 3 | D19: =IF(AND(B19=4,C19>=1),1,0) -> 0
A20: Turnaround over digital | B20: =SUMPRODUCT(--(B13:E13>=B11:E11)) -> 2 | C20: =SUMPRODUCT(--(B13:E13>B11:E11)) -> 2 | D20: =IF(AND(B20=4,C20>=1),1,0) -> 0
A21: Turnaround over restructuring | B21: =SUMPRODUCT(--(B13:E13>=B12:E12)) -> 1 | C21: =SUMPRODUCT(--(B13:E13>B12:E12)) -> 1 | D21: =IF(AND(B21=4,C21>=1),1,0) -> 0
A22: Pairs in which one option dominates another | D22: =SUM(D16:D21) -> 0
A24: Digital less restructuring, d (signed) | B24: Liquidity | C24: Technology | D24: Efficiency | E24: Strategic risk
B25: =B11-B12 -> -26.811878 | C25: =C11-C12 -> 36.775155 | D25: =D11-D12 -> -0.085471354 | E25: =E11-E12 -> -5.827558
A27: Digital's technology lead | B27: =C25 -> 36.775155 | C27: 36.8
A28: Restructuring's liquidity lead | B28: =-B25 -> 26.811878 | C28: 26.8
A29: Restructuring's strategic-risk lead | B29: =-E25 -> 5.827558 | C29: 5.8
A30: Restructuring's efficiency lead | B30: =-D25 -> 0.085471354 | C30: 0.1; inside efficiency's +/-3 error
A31: Digital's lead at equal weights, w . d | B31: =W_L*B25+W_T*C25+W_E*D25+W_R*E25 -> 1.0125619 | C31: 1.01
A32: Lead lost per point of weight moved from technology to liquidity | B32: =(C25-B25)/100 -> 0.63587033 | C32: 0.64
A33: Weight moved at the tie, t* = w . d / (d_T - d_L) | B33: =B31/(C25-B25) -> 0.015924031
A34: Points of weight moved at the tie | B34: =100*B33 -> 1.5924031 | C34: 1.6
A35: Tie: weight on liquidity (%) | B35: =100*(W_L+B33) -> 26.592403 | C35: 26.6
A36: Tie: weight on technology (%) | B36: =100*(W_T-B33) -> 23.407597 | C36: 23.4
A37: Tie moving weight from technology to strategic risk (points) | B37: =100*B31/(C25-E25) -> 2.3767545 | C37: 2.4
A38: Tie moving weight from technology to efficiency (points) | B38: =100*B31/(C25-D25) -> 2.7470013 | C38: 2.7
A39: Largest change of the lead per point of weight moved, (max d - min d)/100 | B39: =(MAX(B25:E25)-MIN(B25:E25))/100 -> 0.63587033 | C39: Online Appendix 11.B.2
A40: So no change of weights smaller than (points) can tie | B40: =B31/B39 -> 1.5924031 | C40: the move from technology to liquidity
A42: Points moved from technology to liquidity | B42: Weight on liquidity | C42: Weight on technology | D42: Weight on efficiency | E42: Weight on strategic risk | F42: Digital | G42: Restructuring | H42: Turnaround | I42: First
A43: 0 | B43: =W_L+A43/100 -> 0.25 | C43: =W_T-A43/100 -> 0.25 | D43: =W_E -> 0.25 | E43: =W_R -> 0.25 | F43: =$B43*$B$11+$C43*$C$11+$D43*$D$11+$E43*$E$11 -> 47.077713 | G43: =$B43*$B$12+$C43*$C$12+$D43*$D$12+$E43*$E$12 -> 46.065151 | H43: =$B43*$B$13+$C43*$C$13+$D43*$D$13+$E43*$E$13 -> 38.395434 | I43: =INDEX($F$42:$H$42,MATCH(MAX(F43:H43),F43:H43,0)) -> Digital
A44: 0.5 | B44: =W_L+A44/100 -> 0.255 | C44: =W_T-A44/100 -> 0.245 | D44: =W_E -> 0.25 | E44: =W_R -> 0.25 | F44: =$B44*$B$11+$C44*$C$11+$D44*$D$11+$E44*$E$11 -> 47.171018 | G44: =$B44*$B$12+$C44*$C$12+$D44*$D$12+$E44*$E$12 -> 46.476391 | H44: =$B44*$B$13+$C44*$C$13+$D44*$D$13+$E44*$E$13 -> 38.742556 | I44: =INDEX($F$42:$H$42,MATCH(MAX(F44:H44),F44:H44,0)) -> Digital
A45: 1 | B45: =W_L+A45/100 -> 0.26 | C45: =W_T-A45/100 -> 0.24 | D45: =W_E -> 0.25 | E45: =W_R -> 0.25 | F45: =$B45*$B$11+$C45*$C$11+$D45*$D$11+$E45*$E$11 -> 47.264322 | G45: =$B45*$B$12+$C45*$C$12+$D45*$D$12+$E45*$E$12 -> 46.887631 | H45: =$B45*$B$13+$C45*$C$13+$D45*$D$13+$E45*$E$13 -> 39.089679 | I45: =INDEX($F$42:$H$42,MATCH(MAX(F45:H45),F45:H45,0)) -> Digital
A46: 1.5 | B46: =W_L+A46/100 -> 0.265 | C46: =W_T-A46/100 -> 0.235 | D46: =W_E -> 0.25 | E46: =W_R -> 0.25 | F46: =$B46*$B$11+$C46*$C$11+$D46*$D$11+$E46*$E$11 -> 47.357627 | G46: =$B46*$B$12+$C46*$C$12+$D46*$D$12+$E46*$E$12 -> 47.298871 | H46: =$B46*$B$13+$C46*$C$13+$D46*$D$13+$E46*$E$13 -> 39.436802 | I46: =INDEX($F$42:$H$42,MATCH(MAX(F46:H46),F46:H46,0)) -> Digital
A47: =B34 -> 1.5924031 | B47: =W_L+A47/100 -> 0.26592403 | C47: =W_T-A47/100 -> 0.23407597 | D47: =W_E -> 0.25 | E47: =W_R -> 0.25 | F47: =$B47*$B$11+$C47*$C$11+$D47*$D$11+$E47*$E$11 -> 47.37487 | G47: =$B47*$B$12+$C47*$C$12+$D47*$D$12+$E47*$E$12 -> 47.37487 | H47: =$B47*$B$13+$C47*$C$13+$D47*$D$13+$E47*$E$13 -> 39.500953 | I47: =INDEX($F$42:$H$42,MATCH(MAX(F47:H47),F47:H47,0)) -> Digital
A48: 2 | B48: =W_L+A48/100 -> 0.27 | C48: =W_T-A48/100 -> 0.23 | D48: =W_E -> 0.25 | E48: =W_R -> 0.25 | F48: =$B48*$B$11+$C48*$C$11+$D48*$D$11+$E48*$E$11 -> 47.450932 | G48: =$B48*$B$12+$C48*$C$12+$D48*$D$12+$E48*$E$12 -> 47.71011 | H48: =$B48*$B$13+$C48*$C$13+$D48*$D$13+$E48*$E$13 -> 39.783925 | I48: =INDEX($F$42:$H$42,MATCH(MAX(F48:H48),F48:H48,0)) -> Restructuring
A49: 2.5 | B49: =W_L+A49/100 -> 0.275 | C49: =W_T-A49/100 -> 0.225 | D49: =W_E -> 0.25 | E49: =W_R -> 0.25 | F49: =$B49*$B$11+$C49*$C$11+$D49*$D$11+$E49*$E$11 -> 47.544236 | G49: =$B49*$B$12+$C49*$C$12+$D49*$D$12+$E49*$E$12 -> 48.12135 | H49: =$B49*$B$13+$C49*$C$13+$D49*$D$13+$E49*$E$13 -> 40.131048 | I49: =INDEX($F$42:$H$42,MATCH(MAX(F49:H49),F49:H49,0)) -> Restructuring
A50: 3 | B50: =W_L+A50/100 -> 0.28 | C50: =W_T-A50/100 -> 0.22 | D50: =W_E -> 0.25 | E50: =W_R -> 0.25 | F50: =$B50*$B$11+$C50*$C$11+$D50*$D$11+$E50*$E$11 -> 47.637541 | G50: =$B50*$B$12+$C50*$C$12+$D50*$D$12+$E50*$E$12 -> 48.53259 | H50: =$B50*$B$13+$C50*$C$13+$D50*$D$13+$E50*$E$13 -> 40.478171 | I50: =INDEX($F$42:$H$42,MATCH(MAX(F50:H50),F50:H50,0)) -> Restructuring
A51: 4 | B51: =W_L+A51/100 -> 0.29 | C51: =W_T-A51/100 -> 0.21 | D51: =W_E -> 0.25 | E51: =W_R -> 0.25 | F51: =$B51*$B$11+$C51*$C$11+$D51*$D$11+$E51*$E$11 -> 47.82415 | G51: =$B51*$B$12+$C51*$C$12+$D51*$D$12+$E51*$E$12 -> 49.35507 | H51: =$B51*$B$13+$C51*$C$13+$D51*$D$13+$E51*$E$13 -> 41.172416 | I51: =INDEX($F$42:$H$42,MATCH(MAX(F51:H51),F51:H51,0)) -> Restructuring
A52: 5 | B52: =W_L+A52/100 -> 0.3 | C52: =W_T-A52/100 -> 0.2 | D52: =W_E -> 0.25 | E52: =W_R -> 0.25 | F52: =$B52*$B$11+$C52*$C$11+$D52*$D$11+$E52*$E$11 -> 48.01076 | G52: =$B52*$B$12+$C52*$C$12+$D52*$D$12+$E52*$E$12 -> 50.177549 | H52: =$B52*$B$13+$C52*$C$13+$D52*$D$13+$E52*$E$13 -> 41.866662 | I52: =INDEX($F$42:$H$42,MATCH(MAX(F52:H52),F52:H52,0)) -> Restructuring
A54: Row 47 is the tie (1.59 points): the two leaders score the same there. Theorem 11.2(ii): between options that do not dominate each other, the weights choose.
A56: Weightings uniform on the simplex (Online Appendix 11.B.6) | B56: Share ranking first | C56: Reading
A57: Digital | B57: 0.493745 | C57: 49.4%
A58: Restructuring | B58: 0.492915 | C58: 49.3%
A59: Turnaround | B59: 0.01334 | C59: 1.3%
A60: Turnaround first: least weight on efficiency | B60: 0.68371651 | C60: at least 68 percent
A61: Turnaround first: most weight on technology | B61: 0.1310938 | C61: at most 13 percent
A62: Engine values: 200,000 weightings drawn in the notebook with seed 26111, as in the book. The count measures how much of the space of weights each option wins; it is not a probability that either is better.

Sheet Yardsticks
A1: Change the yardstick and the reference group (Worked Example 11.1, Step 3; Theorem 11.2(iii); Online Appendix 11.B.3; AXIOM Lab 1.11, step 3)
A3: Signed readings, Year 5 | B3: Liquidity | C3: Technology | D3: Efficiency | E3: Strategic risk
A4: Digital | B4: =Weights!B11 -> 94.295601 | C4: =Weights!C11 -> 75.634669 | D4: =Weights!D11 -> 73.598331 | E4: =Weights!E11 -> -55.21775
A5: Restructuring | B5: =Weights!B12 -> 121.10748 | C5: =Weights!C12 -> 38.859514 | D5: =Weights!D12 -> 73.683802 | E5: =Weights!E12 -> -49.390192
A6: Turnaround | B6: =Weights!B13 -> 105.3676 | C6: =Weights!C13 -> 35.943036 | D6: =Weights!D13 -> 78.601703 | E6: =Weights!E13 -> -66.33061
A7: Today | B7: =Today_L*S_L -> 100 | C7: =Today_T*S_T -> 41 | D7: =Today_E*S_E -> 71 | E7: =Today_R*S_R -> -64
A9: Best option 100, worst 0: the three options (the book's) | B9: Liquidity | C9: Technology | D9: Efficiency | E9: Strategic risk | F9: Score, equal weights
A10: Worst of the reference group | B10: =MIN(B$4:B$6) -> 94.295601 | C10: =MIN(C$4:C$6) -> 35.943036 | D10: =MIN(D$4:D$6) -> 73.598331 | E10: =MIN(E$4:E$6) -> -66.33061
A11: Best of the reference group | B11: =MAX(B$4:B$6) -> 121.10748 | C11: =MAX(C$4:C$6) -> 75.634669 | D11: =MAX(D$4:D$6) -> 78.601703 | E11: =MAX(E$4:E$6) -> -49.390192
A12: Spread | B12: =B11-B10 -> 26.811878 | C12: =C11-C10 -> 39.691634 | D12: =D11-D10 -> 5.0033725 | E12: =E11-E10 -> 16.940418
A13: Digital | B13: =100*(B4-B$10)/B$12 -> 0 | C13: =100*(C4-C$10)/C$12 -> 100 | D13: =100*(D4-D$10)/D$12 -> 0 | E13: =100*(E4-E$10)/E$12 -> 65.59968 | F13: =W_L*B13+W_T*C13+W_E*D13+W_R*E13 -> 41.39992
A14: Restructuring | B14: =100*(B5-B$10)/B$12 -> 100 | C14: =100*(C5-C$10)/C$12 -> 7.3478428 | D14: =100*(D5-D$10)/D$12 -> 1.7082749 | E14: =100*(E5-E$10)/E$12 -> 100 | F14: =W_L*B14+W_T*C14+W_E*D14+W_R*E14 -> 52.264029
A15: Turnaround | B15: =100*(B6-B$10)/B$12 -> 41.295143 | C15: =100*(C6-C$10)/C$12 -> 0 | D15: =100*(D6-D$10)/D$12 -> 100 | E15: =100*(E6-E$10)/E$12 -> 0 | F15: =W_L*B15+W_T*C15+W_E*D15+W_R*E15 -> 35.323786
A16: First | F16: =INDEX(A13:A15,MATCH(MAX(F13:F15),F13:F15,0)) -> Restructuring
A17: Effective weights, as shares: (w / spread) / sum | B17: =(W_L/B12)/(W_L/$B12+W_T/$C12+W_E/$D12+W_R/$E12) -> 0.11604991 | C17: =(W_T/C12)/(W_L/$B12+W_T/$C12+W_E/$D12+W_R/$E12) -> 0.078392239 | D17: =(W_E/D12)/(W_L/$B12+W_T/$C12+W_E/$D12+W_R/$E12) -> 0.62188375 | E17: =(W_R/E12)/(W_L/$B12+W_T/$C12+W_E/$D12+W_R/$E12) -> 0.1836741
A20: Rescaled strategic-risk difference (restructuring's lead) | B20: =E14-E13 -> 34.40032 | C20: 34
A21: Rescaled technology lead (digital's) | B21: =C13-C14 -> 92.652157 | C21: 93
A22: Rescaled liquidity deficit (digital's) | B22: =B14-B13 -> 100 | C22: 100
A24: Percentage improvement on today | B24: Liquidity | C24: Technology | D24: Efficiency | E24: Strategic risk | F24: Score, equal weights
A25: Digital | B25: =100*(Weights!B5-Today_L)/Today_L*S_L -> -5.7043985 | C25: =100*(Weights!C5-Today_T)/Today_T*S_T -> 84.474803 | D25: =100*(Weights!D5-Today_E)/Today_E*S_E -> 3.6596211 | E25: =100*(Weights!E5-Today_R)/Today_R*S_R -> 13.722266 | F25: =W_L*B25+W_T*C25+W_E*D25+W_R*E25 -> 24.038073
A26: Restructuring | B26: =100*(Weights!B6-Today_L)/Today_L*S_L -> 21.107479 | C26: =100*(Weights!C6-Today_T)/Today_T*S_T -> -5.2206966 | D26: =100*(Weights!D6-Today_E)/Today_E*S_E -> 3.7800033 | E26: =100*(Weights!E6-Today_R)/Today_R*S_R -> 22.827826 | F26: =W_L*B26+W_T*C26+W_E*D26+W_R*E26 -> 10.623653
A27: Turnaround | B27: =100*(Weights!B7-Today_L)/Today_L*S_L -> 5.3676047 | C27: =100*(Weights!C7-Today_T)/Today_T*S_T -> -12.33406 | D27: =100*(Weights!D7-Today_E)/Today_E*S_E -> 10.706625 | E27: =100*(Weights!E7-Today_R)/Today_R*S_R -> -3.6415774 | F27: =W_L*B27+W_T*C27+W_E*D27+W_R*E27 -> 0.024648044
A28: First | F28: =INDEX(A25:A27,MATCH(MAX(F25:F27),F25:F27,0)) -> Digital
A29: Effective weights, as shares: (w / today) / sum | B29: =(W_L/Today_L)/(W_L/Today_L+W_T/Today_T+W_E/Today_E+W_R/Today_R) -> 0.15600685 | C29: =(W_T/Today_T)/(W_L/Today_L+W_T/Today_T+W_E/Today_E+W_R/Today_R) -> 0.3805045 | D29: =(W_E/Today_E)/(W_L/Today_L+W_T/Today_T+W_E/Today_E+W_R/Today_R) -> 0.21972795 | E29: =(W_R/Today_R)/(W_L/Today_L+W_T/Today_T+W_E/Today_E+W_R/Today_R) -> 0.2437607
A30: Digital's lead on this scale (points) | B30: =F25-F26 -> 13.41442 | C30: by 13 points
A31: Technology's gain on today under digital (%) | B31: =C25 -> 84.474803 | C31: 84 percent
A33: Theorem 11.2(iii)'s example | B33: Dimension 1 | C33: Dimension 2 | D33: Score
A34: Weights | B34: 1 | C34: 1
A35: Option A | B35: 3 | C35: 1 | D35: =B34*B35+C34*C35 -> 4
A36: Option B | B36: 1 | C36: 2 | D36: =B34*B36+C34*C36 -> 3
A37: Rescaling a | B37: 1 | C37: 3
A38: Option A after the rescaling | D38: =B34*B37*B35+C34*C37*C35 -> 6
A39: Option B after the rescaling | D39: =B34*B37*B36+C34*C37*C36 -> 7
A41: Best 100, worst 0 against the options and today's company (computed) | B41: Liquidity | C41: Technology | D41: Efficiency | E41: Strategic risk | F41: Score, equal weights
A42: Worst of the reference group | B42: =MIN(B$4:B$7) -> 94.295601 | C42: =MIN(C$4:C$7) -> 35.943036 | D42: =MIN(D$4:D$7) -> 71 | E42: =MIN(E$4:E$7) -> -66.33061
A43: Best of the reference group | B43: =MAX(B$4:B$7) -> 121.10748 | C43: =MAX(C$4:C$7) -> 75.634669 | D43: =MAX(D$4:D$7) -> 78.601703 | E43: =MAX(E$4:E$7) -> -49.390192
A44: Spread | B44: =B43-B42 -> 26.811878 | C44: =C43-C42 -> 39.691634 | D44: =D43-D42 -> 7.6017035 | E44: =E43-E42 -> 16.940418
A45: Digital | B45: =100*(B4-B$42)/B$44 -> 0 | C45: =100*(C4-C$42)/C$44 -> 100 | D45: =100*(D4-D$42)/D$44 -> 34.180904 | E45: =100*(E4-E$42)/E$44 -> 65.59968 | F45: =W_L*B45+W_T*C45+W_E*D45+W_R*E45 -> 49.945146
A46: Restructuring | B46: =100*(B5-B$42)/B$44 -> 100 | C46: =100*(C5-C$42)/C$44 -> 7.3478428 | D46: =100*(D5-D$42)/D$44 -> 35.305275 | E46: =100*(E5-E$42)/E$44 -> 100 | F46: =W_L*B46+W_T*C46+W_E*D46+W_R*E46 -> 60.66328
A47: Turnaround | B47: =100*(B6-B$42)/B$44 -> 41.295143 | C47: =100*(C6-C$42)/C$44 -> 0 | D47: =100*(D6-D$42)/D$44 -> 100 | E47: =100*(E6-E$42)/E$44 -> 0 | F47: =W_L*B47+W_T*C47+W_E*D47+W_R*E47 -> 35.323786
A48: First | F48: =INDEX(A45:A47,MATCH(MAX(F45:F47),F45:F47,0)) -> Restructuring
A49: Effective weights, as shares: (w / spread) / sum | B49: =(W_L/B44)/(W_L/$B44+W_T/$C44+W_E/$D44+W_R/$E44) -> 0.14737722 | C49: =(W_T/C44)/(W_L/$B44+W_T/$C44+W_E/$D44+W_R/$E44) -> 0.09955398 | D49: =(W_E/D44)/(W_L/$B44+W_T/$C44+W_E/$D44+W_R/$E44) -> 0.51981245 | E49: =(W_R/E44)/(W_L/$B44+W_T/$C44+W_E/$D44+W_R/$E44) -> 0.23325635
A52: Best 100, worst 0 against the two leaders alone (computed) | B52: Liquidity | C52: Technology | D52: Efficiency | E52: Strategic risk | F52: Score, equal weights
A53: Worst of the reference group | B53: =MIN(B$4:B$5) -> 94.295601 | C53: =MIN(C$4:C$5) -> 38.859514 | D53: =MIN(D$4:D$5) -> 73.598331 | E53: =MIN(E$4:E$5) -> -55.21775
A54: Best of the reference group | B54: =MAX(B$4:B$5) -> 121.10748 | C54: =MAX(C$4:C$5) -> 75.634669 | D54: =MAX(D$4:D$5) -> 73.683802 | E54: =MAX(E$4:E$5) -> -49.390192
A55: Spread | B55: =B54-B53 -> 26.811878 | C55: =C54-C53 -> 36.775155 | D55: =D54-D53 -> 0.085471354 | E55: =E54-E53 -> 5.827558
A56: Digital | B56: =100*(B4-B$53)/B$55 -> 0 | C56: =100*(C4-C$53)/C$55 -> 100 | D56: =100*(D4-D$53)/D$55 -> 0 | E56: =100*(E4-E$53)/E$55 -> 0 | F56: =W_L*B56+W_T*C56+W_E*D56+W_R*E56 -> 25
A57: Restructuring | B57: =100*(B5-B$53)/B$55 -> 100 | C57: =100*(C5-C$53)/C$55 -> 0 | D57: =100*(D5-D$53)/D$55 -> 100 | E57: =100*(E5-E$53)/E$55 -> 100 | F57: =W_L*B57+W_T*C57+W_E*D57+W_R*E57 -> 75
A58: First | F58: =INDEX(A56:A57,MATCH(MAX(F56:F57),F56:F57,0)) -> Restructuring
A59: Effective weights, as shares: (w / spread) / sum | B59: =(W_L/B55)/(W_L/$B55+W_T/$C55+W_E/$D55+W_R/$E55) -> 0.003124763 | C59: =(W_T/C55)/(W_L/$B55+W_T/$C55+W_E/$D55+W_R/$E55) -> 0.0022781893 | D59: =(W_E/D55)/(W_L/$B55+W_T/$C55+W_E/$D55+W_R/$E55) -> 0.9802204 | E59: =(W_R/E55)/(W_L/$B55+W_T/$C55+W_E/$D55+W_R/$E55) -> 0.01437665
A62: The two lower blocks switch the reference group, as the lab's normalization panel does; they are computed from the book's Year-5 readings. Against the two leaders, efficiency's 0.09-point gap, inside its +/-3 error, carries 98 percent of the effective weight.

Sheet Ratios
A1: Roll up a ratio: rate and mix (Theorem 11.5; Table 11.5; Online Appendix 11.B.5; AXIOM Lab 1.11, step 4)
A2: Group ratio R = sum of the divisional ratios weighted by their shares of the denominator; R' - R = rate effect sum s'(r' - r) + mix effect sum (s' - s) r (Theorem 11.5(i)).
A4: Theorem 11.5(i): two divisions (margin) | B4: Last year: profit | C4: Last year: revenue | D4: This year: profit | E4: This year: revenue | F4: Ratio last year | G4: Ratio this year | H4: Share last year | I4: Share this year
A5: Division 1 | B5: 40 | C5: 200 | D5: 22 | E5: 100 | F5: =B5/C5 -> 0.2 | G5: =D5/E5 -> 0.22 | H5: =C5/SUM($C$5:$C$6) -> 0.66666667 | I5: =E5/SUM($E$5:$E$6) -> 0.33333333
A6: Division 2 | B6: 15 | C6: 100 | D6: 32 | E6: 200 | F6: =B6/C6 -> 0.15 | G6: =D6/E6 -> 0.16 | H6: =C6/SUM($C$5:$C$6) -> 0.33333333 | I6: =E6/SUM($E$5:$E$6) -> 0.66666667
A7: Group ratio last year (%), pooled | B7: =100*SUM(B5:B6)/SUM(C5:C6) -> 18.333333 | C7: Theorem 11.5(i): 18.3 to 18.0 percent; rate +0.0133, mix -0.0167
A8: Group ratio this year (%), pooled | B8: =100*SUM(D5:D6)/SUM(E5:E6) -> 18
A9: Rate effect (points) | B9: =100*(I5*(G5-F5)+I6*(G6-F6)) -> 1.3333333
A10: Mix effect (points) | B10: =100*((I5-H5)*F5+(I6-H6)*F6) -> -1.6666667
A11: Rate plus mix less the change (should be 0) | B11: =B9+B10-(B8-B7) -> -1.3322676e-15
A12: Unweighted average of the divisional ratios, last year (%) | B12: =100*AVERAGE(F5:F6) -> 17.5
A13: Unweighted average of the divisional ratios, this year (%) | B13: =100*AVERAGE(G5:G6) -> 19
A16: Table 11.5: the bank (cost-income ratio, lower is better) | B16: Last year: costs | C16: Last year: income | D16: This year: costs | E16: This year: income | F16: Ratio last year | G16: Ratio this year | H16: Share last year | I16: Share this year
A17: Retail | B17: 160 | C17: 200 | D17: 78 | E17: 100 | F17: =B17/C17 -> 0.8 | G17: =D17/E17 -> 0.78 | H17: =C17/SUM($C$17:$C$18) -> 0.66666667 | I17: =E17/SUM($E$17:$E$18) -> 0.33333333
A18: Markets | B18: 85 | C18: 100 | D18: 168 | E18: 200 | F18: =B18/C18 -> 0.85 | G18: =D18/E18 -> 0.84 | H18: =C18/SUM($C$17:$C$18) -> 0.33333333 | I18: =E18/SUM($E$17:$E$18) -> 0.66666667
A19: Group ratio last year (%), pooled | B19: =100*SUM(B17:B18)/SUM(C17:C18) -> 81.666667 | C19: Table 11.5: 81.7 to 82.0 percent; rate -1.3 points, mix +1.7; Online Appendix 11.B.5
A20: Group ratio this year (%), pooled | B20: =100*SUM(D17:D18)/SUM(E17:E18) -> 82
A21: Rate effect (points) | B21: =100*(I17*(G17-F17)+I18*(G18-F18)) -> -1.3333333
A22: Mix effect (points) | B22: =100*((I17-H17)*F17+(I18-H18)*F18) -> 1.6666667
A23: Rate plus mix less the change (should be 0) | B23: =B21+B22-(B20-B19) -> 3.3306691e-15
A24: Unweighted average of the divisional ratios, last year (%) | B24: =100*AVERAGE(F17:F18) -> 82.5
A25: Unweighted average of the divisional ratios, this year (%) | B25: =100*AVERAGE(G17:G18) -> 81
A28: Mix bench: share of revenue in division 1 (this year's margins held) | B28: Group margin at last year's margins (%) | C28: Group margin at this year's margins (%) | D28: Below last year's group margin?
A29: 0 | B29: =100*(A29*$F$5+(1-A29)*$F$6) -> 15 | C29: =100*(A29*$G$5+(1-A29)*$G$6) -> 16 | D29: =IF(C29<$B$7,"yes","no") -> yes
A30: 0.05 | B30: =100*(A30*$F$5+(1-A30)*$F$6) -> 15.25 | C30: =100*(A30*$G$5+(1-A30)*$G$6) -> 16.3 | D30: =IF(C30<$B$7,"yes","no") -> yes
A31: 0.1 | B31: =100*(A31*$F$5+(1-A31)*$F$6) -> 15.5 | C31: =100*(A31*$G$5+(1-A31)*$G$6) -> 16.6 | D31: =IF(C31<$B$7,"yes","no") -> yes
A32: 0.15 | B32: =100*(A32*$F$5+(1-A32)*$F$6) -> 15.75 | C32: =100*(A32*$G$5+(1-A32)*$G$6) -> 16.9 | D32: =IF(C32<$B$7,"yes","no") -> yes
A33: 0.2 | B33: =100*(A33*$F$5+(1-A33)*$F$6) -> 16 | C33: =100*(A33*$G$5+(1-A33)*$G$6) -> 17.2 | D33: =IF(C33<$B$7,"yes","no") -> yes
A34: 0.25 | B34: =100*(A34*$F$5+(1-A34)*$F$6) -> 16.25 | C34: =100*(A34*$G$5+(1-A34)*$G$6) -> 17.5 | D34: =IF(C34<$B$7,"yes","no") -> yes
A35: 0.3 | B35: =100*(A35*$F$5+(1-A35)*$F$6) -> 16.5 | C35: =100*(A35*$G$5+(1-A35)*$G$6) -> 17.8 | D35: =IF(C35<$B$7,"yes","no") -> yes
A36: 0.35 | B36: =100*(A36*$F$5+(1-A36)*$F$6) -> 16.75 | C36: =100*(A36*$G$5+(1-A36)*$G$6) -> 18.1 | D36: =IF(C36<$B$7,"yes","no") -> yes
A37: 0.4 | B37: =100*(A37*$F$5+(1-A37)*$F$6) -> 17 | C37: =100*(A37*$G$5+(1-A37)*$G$6) -> 18.4 | D37: =IF(C37<$B$7,"yes","no") -> no
A38: 0.45 | B38: =100*(A38*$F$5+(1-A38)*$F$6) -> 17.25 | C38: =100*(A38*$G$5+(1-A38)*$G$6) -> 18.7 | D38: =IF(C38<$B$7,"yes","no") -> no
A39: 0.5 | B39: =100*(A39*$F$5+(1-A39)*$F$6) -> 17.5 | C39: =100*(A39*$G$5+(1-A39)*$G$6) -> 19 | D39: =IF(C39<$B$7,"yes","no") -> no
A40: 0.55 | B40: =100*(A40*$F$5+(1-A40)*$F$6) -> 17.75 | C40: =100*(A40*$G$5+(1-A40)*$G$6) -> 19.3 | D40: =IF(C40<$B$7,"yes","no") -> no
... A49: 1 | B49: =100*(A49*$F$5+(1-A49)*$F$6) -> 20 | C49: =100*(A49*$G$5+(1-A49)*$G$6) -> 22 | D49: =IF(C49<$B$7,"yes","no") -> no
A51: Share below which this year's group margin is under last year's (computed) | B51: =(B7/100-G6)/(G5-G6) -> 0.38888889 | C51: division 1 keeps one third
A53: Theorem 11.5(ii): capacity shared by three units | B53: 10
A54: Target of each unit | B54: 4 | C54: the same for the three
A55: Any two targets together | B55: =2*B54 -> 8 | C55: every pair fits
A56: All three together | B56: =3*B54 -> 12 | C56: together they do not
A57: Pairwise agreement, joint feasibility | B57: =IF(B55<=B53,"pairs fit","pairs fail")&"; "&IF(B56<=B53,"jointly feasible","jointly infeasible") -> pairs fit; jointly infeasible | C57: a joint review of the cycle is required
A59: Theorem 11.5(iii): group ratio with equal revenue (%) | B59: =100*AVERAGE(F5:F6) -> 17.5 | C59: same divisional ratios, 20% and 15%
A60: ... when division 1's revenue doubles (%) | B60: =100*(2*F5+F6)/3 -> 18.333333 | C60: a ratio rolls up only with its denominators

Sheet Frontier
A1: Walk the frontier (Theorem 11.4; Proposition 11.2; Figure 11.2; Online Appendix 11.B.4; AXIOM Lab 1.11, step 5)
A3: Indivisible program (Theorem 11.4(iii)) | B3: Margin gain (points) | C3: Resilience gain (months) | D3: Programs that dominate it
A4: Resilience program | B4: 0 | C4: 10 | D4: =SUMPRODUCT(($B$4:$B$6>=B4)*($C$4:$C$6>=C4)*((($B$4:$B$6>B4)+($C$4:$C$6>C4))>0)) -> 0
A5: Balanced program | B5: 4 | C5: 4 | D5: =SUMPRODUCT(($B$4:$B$6>=B5)*($C$4:$C$6>=C5)*((($B$4:$B$6>B5)+($C$4:$C$6>C5))>0)) -> 0
A6: Margin program | B6: 10 | C6: 0 | D6: =SUMPRODUCT(($B$4:$B$6>=B6)*($C$4:$C$6>=C6)*((($B$4:$B$6>B6)+($C$4:$C$6>C6))>0)) -> 0
A7: Pareto-optimal programs (dominated by none) | D7: =COUNTIF(D4:D6,0) -> 3
A9: Weight on margin, w1 (w2 = 1 - w1) | B9: Resilience program | C9: Balanced program | D9: Margin program | E9: Ranked first
A10: 0.01 | B10: =$A10*$B$4+(1-$A10)*$C$4 -> 9.9 | C10: =$A10*$B$5+(1-$A10)*$C$5 -> 4 | D10: =$A10*$B$6+(1-$A10)*$C$6 -> 0.1 | E10: =MATCH(MAX(B10:D10),B10:D10,0) -> 1
A11: 0.02 | B11: =$A11*$B$4+(1-$A11)*$C$4 -> 9.8 | C11: =$A11*$B$5+(1-$A11)*$C$5 -> 4 | D11: =$A11*$B$6+(1-$A11)*$C$6 -> 0.2 | E11: =MATCH(MAX(B11:D11),B11:D11,0) -> 1
A12: 0.03 | B12: =$A12*$B$4+(1-$A12)*$C$4 -> 9.7 | C12: =$A12*$B$5+(1-$A12)*$C$5 -> 4 | D12: =$A12*$B$6+(1-$A12)*$C$6 -> 0.3 | E12: =MATCH(MAX(B12:D12),B12:D12,0) -> 1
A13: 0.04 | B13: =$A13*$B$4+(1-$A13)*$C$4 -> 9.6 | C13: =$A13*$B$5+(1-$A13)*$C$5 -> 4 | D13: =$A13*$B$6+(1-$A13)*$C$6 -> 0.4 | E13: =MATCH(MAX(B13:D13),B13:D13,0) -> 1
A14: 0.05 | B14: =$A14*$B$4+(1-$A14)*$C$4 -> 9.5 | C14: =$A14*$B$5+(1-$A14)*$C$5 -> 4 | D14: =$A14*$B$6+(1-$A14)*$C$6 -> 0.5 | E14: =MATCH(MAX(B14:D14),B14:D14,0) -> 1
A15: 0.06 | B15: =$A15*$B$4+(1-$A15)*$C$4 -> 9.4 | C15: =$A15*$B$5+(1-$A15)*$C$5 -> 4 | D15: =$A15*$B$6+(1-$A15)*$C$6 -> 0.6 | E15: =MATCH(MAX(B15:D15),B15:D15,0) -> 1
A16: 0.07 | B16: =$A16*$B$4+(1-$A16)*$C$4 -> 9.3 | C16: =$A16*$B$5+(1-$A16)*$C$5 -> 4 | D16: =$A16*$B$6+(1-$A16)*$C$6 -> 0.7 | E16: =MATCH(MAX(B16:D16),B16:D16,0) -> 1
A17: 0.08 | B17: =$A17*$B$4+(1-$A17)*$C$4 -> 9.2 | C17: =$A17*$B$5+(1-$A17)*$C$5 -> 4 | D17: =$A17*$B$6+(1-$A17)*$C$6 -> 0.8 | E17: =MATCH(MAX(B17:D17),B17:D17,0) -> 1
A18: 0.09 | B18: =$A18*$B$4+(1-$A18)*$C$4 -> 9.1 | C18: =$A18*$B$5+(1-$A18)*$C$5 -> 4 | D18: =$A18*$B$6+(1-$A18)*$C$6 -> 0.9 | E18: =MATCH(MAX(B18:D18),B18:D18,0) -> 1
A19: 0.1 | B19: =$A19*$B$4+(1-$A19)*$C$4 -> 9 | C19: =$A19*$B$5+(1-$A19)*$C$5 -> 4 | D19: =$A19*$B$6+(1-$A19)*$C$6 -> 1 | E19: =MATCH(MAX(B19:D19),B19:D19,0) -> 1
A20: 0.11 | B20: =$A20*$B$4+(1-$A20)*$C$4 -> 8.9 | C20: =$A20*$B$5+(1-$A20)*$C$5 -> 4 | D20: =$A20*$B$6+(1-$A20)*$C$6 -> 1.1 | E20: =MATCH(MAX(B20:D20),B20:D20,0) -> 1
A21: 0.12 | B21: =$A21*$B$4+(1-$A21)*$C$4 -> 8.8 | C21: =$A21*$B$5+(1-$A21)*$C$5 -> 4 | D21: =$A21*$B$6+(1-$A21)*$C$6 -> 1.2 | E21: =MATCH(MAX(B21:D21),B21:D21,0) -> 1
... A108: 0.99 | B108: =$A108*$B$4+(1-$A108)*$C$4 -> 0.1 | C108: =$A108*$B$5+(1-$A108)*$C$5 -> 4 | D108: =$A108*$B$6+(1-$A108)*$C$6 -> 9.9 | E108: =MATCH(MAX(B108:D108),B108:D108,0) -> 3
A110: Positive weightings (of 99) that rank the balanced program first | B110: =COUNTIF(E10:E108,2) -> 0 | C110: never: max(10 w1, 10 w2) >= 5 > 4
A112: Online Appendix 11.B.4: programs (0, m), (a, a), (m, 0) | B112: a | C112: m | D112: Equal-weight score of (a, a) | E112: Of an end program | F112: Verdict
A113: Balanced program (4, 4) | B113: 4 | C113: 10 | D113: =B113 -> 4 | E113: =C113/2 -> 5 | F113: =IF(2*B113>C113,"first at equal weights",IF(2*B113=C113,"ties at equal weights","never first")) -> never first
A114: Balanced program (5, 5) | B114: 5 | C114: 10 | D114: =B114 -> 5 | E114: =C114/2 -> 5 | F114: =IF(2*B114>C114,"first at equal weights",IF(2*B114=C114,"ties at equal weights","never first")) -> ties at equal weights
A115: Balanced program (6, 6) | B115: 6 | C115: 10 | D115: =B115 -> 6 | E115: =C115/2 -> 5 | F115: =IF(2*B115>C115,"first at equal weights",IF(2*B115=C115,"ties at equal weights","never first")) -> first at equal weights
A117: Figure 11.2, left: the frontier (m / MX)^2 + (r / RY)^2 = 1 | B117: Value | C117: Reading
A118: Largest margin MX (%) | B118: 16
A119: Largest liquidity cover RY (months) | B119: 12
A120: Operating point: margin (%) | B120: 9
A121: Operating point: cover (months) | B121: 6
A122: (m / MX)^2 + (r / RY)^2 at the operating point | B122: =(B120/B118)^2+(B121/B119)^2 -> 0.56640625 | C122: below 1: inside, both can improve (Proposition 11.2)
A123: Factor that takes both to the frontier | B123: =1/SQRT(B122) -> 1.3287277
A124: Frontier point: margin (%) | B124: =B123*B120 -> 11.958549
A125: Frontier point: cover (months) | B125: =B123*B121 -> 7.9723661
A126: Slope of the frontier there, -(RY^2 m) / (MX^2 r) | B126: =-(B119^2*B124)/(B118^2*B125) -> -0.84375 | C126: Theorem 11.4(iv): -w1/w2
A127: Months of cover a point of margin costs | B127: =-B126 -> 0.84375 | C127: 0.84

Sheet Window
A1: Move the window: annual reviews and the J-curve's evaluation window (Worked Example 11.1, Step 4; Theorem 11.3(iii); Equation 11.3; Online Appendix 11.B.1; AXIOM Lab 1.11, step 5)
A3: Annual review | B3: Month | C3: Digital | D3: Restructuring | E3: Turnaround | F3: First | G3: Digital's rank
A4: Year 1 | B4: 12 | C4: =INDEX(Paths!$O$5:$O$65,B4+1) -> 32.151236 | D4: =INDEX(Paths!$P$5:$P$65,B4+1) -> 44.455685 | E4: =INDEX(Paths!$Q$5:$Q$65,B4+1) -> 37.88901 | F4: =INDEX($C$3:$E$3,MATCH(MAX(C4:E4),C4:E4,0)) -> Restructuring | G4: =INDEX(Paths!$U$5:$U$65,B4+1) -> 3
A5: Year 2 | B5: 24 | C5: =INDEX(Paths!$O$5:$O$65,B5+1) -> 35.274521 | D5: =INDEX(Paths!$P$5:$P$65,B5+1) -> 45.107989 | E5: =INDEX(Paths!$Q$5:$Q$65,B5+1) -> 38.290006 | F5: =INDEX($C$3:$E$3,MATCH(MAX(C5:E5),C5:E5,0)) -> Restructuring | G5: =INDEX(Paths!$U$5:$U$65,B5+1) -> 3
A6: Year 3 | B6: 36 | C6: =INDEX(Paths!$O$5:$O$65,B6+1) -> 39.88373 | D6: =INDEX(Paths!$P$5:$P$65,B6+1) -> 45.5534 | E6: =INDEX(Paths!$Q$5:$Q$65,B6+1) -> 38.433092 | F6: =INDEX($C$3:$E$3,MATCH(MAX(C6:E6),C6:E6,0)) -> Restructuring | G6: =INDEX(Paths!$U$5:$U$65,B6+1) -> 2
A7: Year 4 | B7: 48 | C7: =INDEX(Paths!$O$5:$O$65,B7+1) -> 43.961208 | D7: =INDEX(Paths!$P$5:$P$65,B7+1) -> 45.857547 | E7: =INDEX(Paths!$Q$5:$Q$65,B7+1) -> 38.445169 | F7: =INDEX($C$3:$E$3,MATCH(MAX(C7:E7),C7:E7,0)) -> Restructuring | G7: =INDEX(Paths!$U$5:$U$65,B7+1) -> 2
A8: Year 5 | B8: 60 | C8: =INDEX(Paths!$O$5:$O$65,B8+1) -> 47.077713 | D8: =INDEX(Paths!$P$5:$P$65,B8+1) -> 46.065151 | E8: =INDEX(Paths!$Q$5:$Q$65,B8+1) -> 38.395434 | F8: =INDEX($C$3:$E$3,MATCH(MAX(C8:E8),C8:E8,0)) -> Digital | G8: =INDEX(Paths!$U$5:$U$65,B8+1) -> 1
A9: Years 1 and 2 rank digital last, Years 3 and 4 second; only a five-year window ranks it first. The month-by-month paths and the months of Figure 11.3 are on Paths.
A11: Online Appendix 11.B.1: a program that costs c u now and gains Delta, decaying at delta | B11: Value | C11: Reading
A12: Cost now, c u | B12: 10
A13: First period's gain, Delta = gamma b u | B13: 3
A14: Window without decay, 1 + c u / Delta (Equation 11.3) | B14: =1+B12/B13 -> 4.3333333 | C14: 4.3 periods
A16: Decay a period, delta | B16: c delta / (gamma b) | C16: Pays back over some window? | D16: Window: 1 + ln(1/(1 - x)) / ln(1/(1 - delta)) | E16: Cumulative, H = 1 | F16: Cumulative, H = 2 | G16: Cumulative, H = 3 | H16: Cumulative, H = 4 | I16: Cumulative, H = 5 | J16: Cumulative, H = 6 | K16: Cumulative, H = 7 | L16: Cumulative, H = 8 | M16: Cumulative, H = 9 | N16: Cumulative, H = 10 | O16: Cumulative, H = 11 | P16: Cumulative, H = 12 | Q16: First window with a gain | R16: Windows with a gain (H up to 12)
A17: 0 | B17: =$B$12*A17/$B$13 -> 0 | C17: =IF(B17<1-0.000000000001,"yes","never") -> yes | D17: =IF(A17=0,$B$14,IF(B17<1-0.000000000001,1+LN(1/(1-B17))/LN(1/(1-A17)),"never")) -> 4.3333333 | E17: =IF($A17=0,-$B$12+$B$13*(1-1),-$B$12+$B$13*(1-(1-$A17)^(1-1))/$A17) -> -10 | F17: =IF($A17=0,-$B$12+$B$13*(2-1),-$B$12+$B$13*(1-(1-$A17)^(2-1))/$A17) -> -7 | G17: =IF($A17=0,-$B$12+$B$13*(3-1),-$B$12+$B$13*(1-(1-$A17)^(3-1))/$A17) -> -4 | H17: =IF($A17=0,-$B$12+$B$13*(4-1),-$B$12+$B$13*(1-(1-$A17)^(4-1))/$A17) -> -1 | I17: =IF($A17=0,-$B$12+$B$13*(5-1),-$B$12+$B$13*(1-(1-$A17)^(5-1))/$A17) -> 2 | J17: =IF($A17=0,-$B$12+$B$13*(6-1),-$B$12+$B$13*(1-(1-$A17)^(6-1))/$A17) -> 5 | K17: =IF($A17=0,-$B$12+$B$13*(7-1),-$B$12+$B$13*(1-(1-$A17)^(7-1))/$A17) -> 8 | L17: =IF($A17=0,-$B$12+$B$13*(8-1),-$B$12+$B$13*(1-(1-$A17)^(8-1))/$A17) -> 11 | M17: =IF($A17=0,-$B$12+$B$13*(9-1),-$B$12+$B$13*(1-(1-$A17)^(9-1))/$A17) -> 14 | N17: =IF($A17=0,-$B$12+$B$13*(10-1),-$B$12+$B$13*(1-(1-$A17)^(10-1))/$A17) -> 17 | O17: =IF($A17=0,-$B$12+$B$13*(11-1),-$B$12+$B$13*(1-(1-$A17)^(11-1))/$A17) -> 20 | P17: =IF($A17=0,-$B$12+$B$13*(12-1),-$B$12+$B$13*(1-(1-$A17)^(12-1))/$A17) -> 23 | Q17: =IF(R17=0,"never",COUNTIF(E17:P17,"<=1E-9")+1) -> 5 | R17: =COUNTIF(E17:P17,">1E-6") -> 8
A18: 0.1 | B18: =$B$12*A18/$B$13 -> 0.33333333 | C18: =IF(B18<1-0.000000000001,"yes","never") -> yes | D18: =IF(A18=0,$B$14,IF(B18<1-0.000000000001,1+LN(1/(1-B18))/LN(1/(1-A18)),"never")) -> 4.8483592 | E18: =IF($A18=0,-$B$12+$B$13*(1-1),-$B$12+$B$13*(1-(1-$A18)^(1-1))/$A18) -> -10 | F18: =IF($A18=0,-$B$12+$B$13*(2-1),-$B$12+$B$13*(1-(1-$A18)^(2-1))/$A18) -> -7 | G18: =IF($A18=0,-$B$12+$B$13*(3-1),-$B$12+$B$13*(1-(1-$A18)^(3-1))/$A18) -> -4.3 | H18: =IF($A18=0,-$B$12+$B$13*(4-1),-$B$12+$B$13*(1-(1-$A18)^(4-1))/$A18) -> -1.87 | I18: =IF($A18=0,-$B$12+$B$13*(5-1),-$B$12+$B$13*(1-(1-$A18)^(5-1))/$A18) -> 0.317 | J18: =IF($A18=0,-$B$12+$B$13*(6-1),-$B$12+$B$13*(1-(1-$A18)^(6-1))/$A18) -> 2.2853 | K18: =IF($A18=0,-$B$12+$B$13*(7-1),-$B$12+$B$13*(1-(1-$A18)^(7-1))/$A18) -> 4.05677 | L18: =IF($A18=0,-$B$12+$B$13*(8-1),-$B$12+$B$13*(1-(1-$A18)^(8-1))/$A18) -> 5.651093 | M18: =IF($A18=0,-$B$12+$B$13*(9-1),-$B$12+$B$13*(1-(1-$A18)^(9-1))/$A18) -> 7.0859837 | N18: =IF($A18=0,-$B$12+$B$13*(10-1),-$B$12+$B$13*(1-(1-$A18)^(10-1))/$A18) -> 8.3773853 | O18: =IF($A18=0,-$B$12+$B$13*(11-1),-$B$12+$B$13*(1-(1-$A18)^(11-1))/$A18) -> 9.5396468 | P18: =IF($A18=0,-$B$12+$B$13*(12-1),-$B$12+$B$13*(1-(1-$A18)^(12-1))/$A18) -> 10.585682 | Q18: =IF(R18=0,"never",COUNTIF(E18:P18,"<=1E-9")+1) -> 5 | R18: =COUNTIF(E18:P18,">1E-6") -> 8
A19: 0.2 | B19: =$B$12*A19/$B$13 -> 0.66666667 | C19: =IF(B19<1-0.000000000001,"yes","never") -> yes | D19: =IF(A19=0,$B$14,IF(B19<1-0.000000000001,1+LN(1/(1-B19))/LN(1/(1-A19)),"never")) -> 5.9233432 | E19: =IF($A19=0,-$B$12+$B$13*(1-1),-$B$12+$B$13*(1-(1-$A19)^(1-1))/$A19) -> -10 | F19: =IF($A19=0,-$B$12+$B$13*(2-1),-$B$12+$B$13*(1-(1-$A19)^(2-1))/$A19) -> -7 | G19: =IF($A19=0,-$B$12+$B$13*(3-1),-$B$12+$B$13*(1-(1-$A19)^(3-1))/$A19) -> -4.6 | H19: =IF($A19=0,-$B$12+$B$13*(4-1),-$B$12+$B$13*(1-(1-$A19)^(4-1))/$A19) -> -2.68 | I19: =IF($A19=0,-$B$12+$B$13*(5-1),-$B$12+$B$13*(1-(1-$A19)^(5-1))/$A19) -> -1.144 | J19: =IF($A19=0,-$B$12+$B$13*(6-1),-$B$12+$B$13*(1-(1-$A19)^(6-1))/$A19) -> 0.0848 | K19: =IF($A19=0,-$B$12+$B$13*(7-1),-$B$12+$B$13*(1-(1-$A19)^(7-1))/$A19) -> 1.06784 | L19: =IF($A19=0,-$B$12+$B$13*(8-1),-$B$12+$B$13*(1-(1-$A19)^(8-1))/$A19) -> 1.854272 | M19: =IF($A19=0,-$B$12+$B$13*(9-1),-$B$12+$B$13*(1-(1-$A19)^(9-1))/$A19) -> 2.4834176 | N19: =IF($A19=0,-$B$12+$B$13*(10-1),-$B$12+$B$13*(1-(1-$A19)^(10-1))/$A19) -> 2.9867341 | O19: =IF($A19=0,-$B$12+$B$13*(11-1),-$B$12+$B$13*(1-(1-$A19)^(11-1))/$A19) -> 3.3893873 | P19: =IF($A19=0,-$B$12+$B$13*(12-1),-$B$12+$B$13*(1-(1-$A19)^(12-1))/$A19) -> 3.7115098 | Q19: =IF(R19=0,"never",COUNTIF(E19:P19,"<=1E-9")+1) -> 6 | R19: =COUNTIF(E19:P19,">1E-6") -> 7
A20: 0.3 | B20: =$B$12*A20/$B$13 -> 1 | C20: =IF(B20<1-0.000000000001,"yes","never") -> never | D20: =IF(A20=0,$B$14,IF(B20<1-0.000000000001,1+LN(1/(1-B20))/LN(1/(1-A20)),"never")) -> never | E20: =IF($A20=0,-$B$12+$B$13*(1-1),-$B$12+$B$13*(1-(1-$A20)^(1-1))/$A20) -> -10 | F20: =IF($A20=0,-$B$12+$B$13*(2-1),-$B$12+$B$13*(1-(1-$A20)^(2-1))/$A20) -> -7 | G20: =IF($A20=0,-$B$12+$B$13*(3-1),-$B$12+$B$13*(1-(1-$A20)^(3-1))/$A20) -> -4.9 | H20: =IF($A20=0,-$B$12+$B$13*(4-1),-$B$12+$B$13*(1-(1-$A20)^(4-1))/$A20) -> -3.43 | I20: =IF($A20=0,-$B$12+$B$13*(5-1),-$B$12+$B$13*(1-(1-$A20)^(5-1))/$A20) -> -2.401 | J20: =IF($A20=0,-$B$12+$B$13*(6-1),-$B$12+$B$13*(1-(1-$A20)^(6-1))/$A20) -> -1.6807 | K20: =IF($A20=0,-$B$12+$B$13*(7-1),-$B$12+$B$13*(1-(1-$A20)^(7-1))/$A20) -> -1.17649 | L20: =IF($A20=0,-$B$12+$B$13*(8-1),-$B$12+$B$13*(1-(1-$A20)^(8-1))/$A20) -> -0.823543 | M20: =IF($A20=0,-$B$12+$B$13*(9-1),-$B$12+$B$13*(1-(1-$A20)^(9-1))/$A20) -> -0.5764801 | N20: =IF($A20=0,-$B$12+$B$13*(10-1),-$B$12+$B$13*(1-(1-$A20)^(10-1))/$A20) -> -0.40353607 | O20: =IF($A20=0,-$B$12+$B$13*(11-1),-$B$12+$B$13*(1-(1-$A20)^(11-1))/$A20) -> -0.28247525 | P20: =IF($A20=0,-$B$12+$B$13*(12-1),-$B$12+$B$13*(1-(1-$A20)^(12-1))/$A20) -> -0.19773267 | Q20: =IF(R20=0,"never",COUNTIF(E20:P20,"<=1E-9")+1) -> never | R20: =COUNTIF(E20:P20,">1E-6") -> 0
A22: A window shorter than the payback window reports a sound program as a loss: correctly for the window, wrongly for the program. At 30 percent decay the benefit fades before it repays the cost.

Sheet Apparatus
A1: Declare the apparatus: Table 11.6 and a gate (Worked Example 11.1, Step 5; Tables 11.3 and 11.6)
A3: Table 11.6: declaration (equal weights, index points, Year 5 unless stated) | B3: Digital | C3: Restructuring | D3: Turnaround | E3: First
A4: The CFO's scorecard | B4: =Weights!F5 -> 47.077713 | C4: =Weights!F6 -> 46.065151 | D4: =Weights!F7 -> 38.395434 | E4: =INDEX($B$3:$D$3,MATCH(MAX(B4:D4),B4:D4,0)) -> Digital
A5: 2 points of weight moved from technology to liquidity | B5: =Weights!F48 -> 47.450932 | C5: =Weights!G48 -> 47.71011 | D5: =Weights!H48 -> 39.783925 | E5: =INDEX($B$3:$D$3,MATCH(MAX(B5:D5),B5:D5,0)) -> Restructuring
A6: Best option 100, worst 0 | B6: =Yardsticks!F13 -> 41.39992 | C6: =Yardsticks!F14 -> 52.264029 | D6: =Yardsticks!F15 -> 35.323786 | E6: =INDEX($B$3:$D$3,MATCH(MAX(B6:D6),B6:D6,0)) -> Restructuring
A7: Percentage improvement on today | B7: =Yardsticks!F25 -> 24.038073 | C7: =Yardsticks!F26 -> 10.623653 | D7: =Yardsticks!F27 -> 0.024648044 | E7: =INDEX($B$3:$D$3,MATCH(MAX(B7:D7),B7:D7,0)) -> Digital
A8: Review at Year 1 | B8: =Window!C4 -> 32.151236 | C8: =Window!D4 -> 44.455685 | D8: =Window!E4 -> 37.88901 | E8: =INDEX($B$3:$D$3,MATCH(MAX(B8:D8),B8:D8,0)) -> Restructuring
A9: Review at Year 3 | B9: =Window!C6 -> 39.88373 | C9: =Window!D6 -> 45.5534 | D9: =Window!E6 -> 38.433092 | E9: =INDEX($B$3:$D$3,MATCH(MAX(B9:D9),B9:D9,0)) -> Restructuring
A11: Declarations that rank digital first | B11: =COUNTIF(E4:E9,"Digital") -> 2
A12: Declarations that rank restructuring first | B12: =COUNTIF(E4:E9,"Restructuring") -> 4
A13: Each declaration is a legitimate choice; none is a fact about the options. Declare the weights (1.6 points from a tie), the yardstick and its reference group, the rule and any gates, and the review window (at least five years for the digital program).
A15: Table 11.3: aggregation rule | B15: Compensation | C15: A zero on one dimension | D15: Reads as
A16: Weighted average | B16: full, at fixed rates | C16: is absorbed | D16: a portfolio of scores
A17: Weighted geometric mean | B17: at a price that soars near zero | C17: zeroes the index | D17: balance demanded
A18: Minimum | B18: none | C18: sets the index | D18: the weakest link governs
A19: Lexicographic | B19: none across priority tiers | C19: fails its tier | D19: gates, then scores
A21: A gate on the board's risk appetite (Worked Example 11.1, For discussion) | B21: P(breach) | C21: Verdict
A22: The board's appetite: at most this chance of breaching the $350 million floor | B22: 0.05
A23: Digital program as planned (Worked Example 8.1; seed 8) | B23: 0.24622 | C23: =IF(B23<=$B$22,"passes: scored","fails its tier: not scored") -> fails its tier: not scored
A24: With the standby line and the phased build (seed 8) | B24: 0.03003 | C24: =IF(B24<=$B$22,"passes: scored","fails its tier: not scored") -> passes: scored
A25: Versions of the digital program that pass the gate | B25: =SUMPRODUCT(--(LEFT(C23:C24,6)="passes")) -> 1
A26: Engine values: 100,000 paths of Worked Example 8.1's uncertainty model, drawn in the notebook with random seed 8 as in the book (24.6 and 3.0 percent). A weight would let technology buy back the breach risk at a fixed rate; the lexicographic gate of Table 11.3 does not.

Sheet Reference_Values
A1: Checkpoint | B1: Engine value | C1: Meaning (where in the book)
A2: Today's score | B2: 37 | C2: Worked Example 1.1: 37.0
A3: Year 5: digital liquidity | B3: 94.295601 | C3: Online Appendix 11.B.6
A4: Year 5: digital technology | B4: 75.634669 | C4: Table 1.9: 75.6
A5: Year 5: digital efficiency | B5: 73.598331 | C5: Online Appendix 11.B.6
A6: Year 5: digital strategic risk | B6: 55.21775 | C6: Online Appendix 11.B.6
A7: Year 5: restructuring liquidity | B7: 121.10748 | C7: Online Appendix 11.B.6
A8: Year 5: restructuring technology | B8: 38.859514 | C8: Online Appendix 11.B.6
A9: Year 5: restructuring efficiency | B9: 73.683802 | C9: Online Appendix 11.B.6
A10: Year 5: restructuring strategic risk | B10: 49.390192 | C10: Online Appendix 11.B.6
A11: Year 5: turnaround liquidity | B11: 105.3676 | C11: Online Appendix 11.B.6
A12: Year 5: turnaround technology | B12: 35.943036 | C12: Online Appendix 11.B.6
A13: Year 5: turnaround efficiency | B13: 78.601703 | C13: Online Appendix 11.B.6
... A126: Gate: versions of the digital program that pass | B126: 1 | C126: 24.6% fails, 3.0% passes (seed 8)

Sheet Checks
A1: Checkpoint | B1: Workbook formula value | C1: Engine value | D1: |diff| | E1: Tolerance | F1: Status
A2: Today's score | B2: =Score_today -> 37 | C2: =Reference_Values!B2 -> 37 | D2: =ABS(B2-C2) -> 0 | E2: 1e-09 | F2: =IF(D2<=E2,"PASS","FAIL") -> PASS
A3: Year 5: digital liquidity | B3: =Weights!B5 -> 94.295601 | C3: =Reference_Values!B3 -> 94.295601 | D3: =ABS(B3-C3) -> 0 | E3: 1e-09 | F3: =IF(D3<=E3,"PASS","FAIL") -> PASS
A4: Year 5: digital technology | B4: =Weights!C5 -> 75.634669 | C4: =Reference_Values!B4 -> 75.634669 | D4: =ABS(B4-C4) -> 0 | E4: 1e-09 | F4: =IF(D4<=E4,"PASS","FAIL") -> PASS
A5: Year 5: digital efficiency | B5: =Weights!D5 -> 73.598331 | C5: =Reference_Values!B5 -> 73.598331 | D5: =ABS(B5-C5) -> 0 | E5: 1e-09 | F5: =IF(D5<=E5,"PASS","FAIL") -> PASS
A6: Year 5: digital strategic risk | B6: =Weights!E5 -> 55.21775 | C6: =Reference_Values!B6 -> 55.21775 | D6: =ABS(B6-C6) -> 0 | E6: 1e-09 | F6: =IF(D6<=E6,"PASS","FAIL") -> PASS
A7: Year 5: restructuring liquidity | B7: =Weights!B6 -> 121.10748 | C7: =Reference_Values!B7 -> 121.10748 | D7: =ABS(B7-C7) -> 0 | E7: 1e-09 | F7: =IF(D7<=E7,"PASS","FAIL") -> PASS
A8: Year 5: restructuring technology | B8: =Weights!C6 -> 38.859514 | C8: =Reference_Values!B8 -> 38.859514 | D8: =ABS(B8-C8) -> 0 | E8: 1e-09 | F8: =IF(D8<=E8,"PASS","FAIL") -> PASS
A9: Year 5: restructuring efficiency | B9: =Weights!D6 -> 73.683802 | C9: =Reference_Values!B9 -> 73.683802 | D9: =ABS(B9-C9) -> 0 | E9: 1e-09 | F9: =IF(D9<=E9,"PASS","FAIL") -> PASS
A10: Year 5: restructuring strategic risk | B10: =Weights!E6 -> 49.390192 | C10: =Reference_Values!B10 -> 49.390192 | D10: =ABS(B10-C10) -> 0 | E10: 1e-09 | F10: =IF(D10<=E10,"PASS","FAIL") -> PASS
A11: Year 5: turnaround liquidity | B11: =Weights!B7 -> 105.3676 | C11: =Reference_Values!B11 -> 105.3676 | D11: =ABS(B11-C11) -> 0 | E11: 1e-09 | F11: =IF(D11<=E11,"PASS","FAIL") -> PASS
A12: Year 5: turnaround technology | B12: =Weights!C7 -> 35.943036 | C12: =Reference_Values!B12 -> 35.943036 | D12: =ABS(B12-C12) -> 0 | E12: 1e-09 | F12: =IF(D12<=E12,"PASS","FAIL") -> PASS
A13: Year 5: turnaround efficiency | B13: =Weights!D7 -> 78.601703 | C13: =Reference_Values!B13 -> 78.601703 | D13: =ABS(B13-C13) -> 0 | E13: 1e-09 | F13: =IF(D13<=E13,"PASS","FAIL") -> PASS
A14: Year 5: turnaround strategic risk | B14: =Weights!E7 -> 66.33061 | C14: =Reference_Values!B14 -> 66.33061 | D14: =ABS(B14-C14) -> 0 | E14: 1e-09 | F14: =IF(D14<=E14,"PASS","FAIL") -> PASS
A15: Year 5 score: digital | B15: =Weights!F5 -> 47.077713 | C15: =Reference_Values!B15 -> 47.077713 | D15: =ABS(B15-C15) -> 0 | E15: 1e-09 | F15: =IF(D15<=E15,"PASS","FAIL") -> PASS
A16: Year 5 score: restructuring | B16: =Weights!F6 -> 46.065151 | C16: =Reference_Values!B16 -> 46.065151 | D16: =ABS(B16-C16) -> 0 | E16: 1e-09 | F16: =IF(D16<=E16,"PASS","FAIL") -> PASS
A17: Year 5 score: turnaround | B17: =Weights!F7 -> 38.395434 | C17: =Reference_Values!B17 -> 38.395434 | D17: =ABS(B17-C17) -> 0 | E17: 1e-09 | F17: =IF(D17<=E17,"PASS","FAIL") -> PASS
A18: Pairs in which one option dominates another | B18: =Weights!D22 -> 0 | C18: =Reference_Values!B18 -> 0 | D18: =ABS(B18-C18) -> 0 | E18: 0 | F18: =IF(D18<=E18,"PASS","FAIL") -> PASS
A19: Digital's technology lead | B19: =Weights!B27 -> 36.775155 | C19: =Reference_Values!B19 -> 36.775155 | D19: =ABS(B19-C19) -> 0 | E19: 1e-09 | F19: =IF(D19<=E19,"PASS","FAIL") -> PASS
A20: Restructuring's liquidity lead | B20: =Weights!B28 -> 26.811878 | C20: =Reference_Values!B20 -> 26.811878 | D20: =ABS(B20-C20) -> 0 | E20: 1e-09 | F20: =IF(D20<=E20,"PASS","FAIL") -> PASS
A21: Restructuring's strategic-risk lead | B21: =Weights!B29 -> 5.827558 | C21: =Reference_Values!B21 -> 5.827558 | D21: =ABS(B21-C21) -> 0 | E21: 1e-09 | F21: =IF(D21<=E21,"PASS","FAIL") -> PASS
A22: Restructuring's efficiency lead | B22: =Weights!B30 -> 0.085471354 | C22: =Reference_Values!B22 -> 0.085471354 | D22: =ABS(B22-C22) -> 0 | E22: 1e-09 | F22: =IF(D22<=E22,"PASS","FAIL") -> PASS
A23: Digital's lead at equal weights | B23: =Weights!B31 -> 1.0125619 | C23: =Reference_Values!B23 -> 1.0125619 | D23: =ABS(B23-C23) -> 0 | E23: 1e-09 | F23: =IF(D23<=E23,"PASS","FAIL") -> PASS
A24: Lead lost per point of weight moved | B24: =Weights!B32 -> 0.63587033 | C24: =Reference_Values!B24 -> 0.63587033 | D24: =ABS(B24-C24) -> 0 | E24: 1e-09 | F24: =IF(D24<=E24,"PASS","FAIL") -> PASS
A25: Points of weight moved at the tie | B25: =Weights!B34 -> 1.5924031 | C25: =Reference_Values!B25 -> 1.5924031 | D25: =ABS(B25-C25) -> 0 | E25: 1e-09 | F25: =IF(D25<=E25,"PASS","FAIL") -> PASS
A26: Tie: weight on liquidity (%) | B26: =Weights!B35 -> 26.592403 | C26: =Reference_Values!B26 -> 26.592403 | D26: =ABS(B26-C26) -> 0 | E26: 1e-09 | F26: =IF(D26<=E26,"PASS","FAIL") -> PASS
A27: Tie: weight on technology (%) | B27: =Weights!B36 -> 23.407597 | C27: =Reference_Values!B27 -> 23.407597 | D27: =ABS(B27-C27) -> 0 | E27: 1e-09 | F27: =IF(D27<=E27,"PASS","FAIL") -> PASS
A28: 2 points moved: digital | B28: =Weights!F48 -> 47.450932 | C28: =Reference_Values!B28 -> 47.450932 | D28: =ABS(B28-C28) -> 0 | E28: 1e-09 | F28: =IF(D28<=E28,"PASS","FAIL") -> PASS
A29: 2 points moved: restructuring | B29: =Weights!G48 -> 47.71011 | C29: =Reference_Values!B29 -> 47.71011 | D29: =ABS(B29-C29) -> 0 | E29: 1e-09 | F29: =IF(D29<=E29,"PASS","FAIL") -> PASS
A30: 2 points moved: turnaround | B30: =Weights!H48 -> 39.783925 | C30: =Reference_Values!B30 -> 39.783925 | D30: =ABS(B30-C30) -> 0 | E30: 1e-09 | F30: =IF(D30<=E30,"PASS","FAIL") -> PASS
A31: Tie moving weight to strategic risk (points) | B31: =Weights!B37 -> 2.3767545 | C31: =Reference_Values!B31 -> 2.3767545 | D31: =ABS(B31-C31) -> 0 | E31: 1e-09 | F31: =IF(D31<=E31,"PASS","FAIL") -> PASS
A32: Tie moving weight to efficiency (points) | B32: =Weights!B38 -> 2.7470013 | C32: =Reference_Values!B32 -> 2.7470013 | D32: =ABS(B32-C32) -> 0 | E32: 1e-09 | F32: =IF(D32<=E32,"PASS","FAIL") -> PASS
A33: Smallest weight change that can tie (points) | B33: =Weights!B40 -> 1.5924031 | C33: =Reference_Values!B33 -> 1.5924031 | D33: =ABS(B33-C33) -> 0 | E33: 1e-09 | F33: =IF(D33<=E33,"PASS","FAIL") -> PASS
A34: Best 100, worst 0: digital | B34: =Yardsticks!F13 -> 41.39992 | C34: =Reference_Values!B34 -> 41.39992 | D34: =ABS(B34-C34) -> 0 | E34: 1e-09 | F34: =IF(D34<=E34,"PASS","FAIL") -> PASS
A35: Best 100, worst 0: restructuring | B35: =Yardsticks!F14 -> 52.264029 | C35: =Reference_Values!B35 -> 52.264029 | D35: =ABS(B35-C35) -> 0 | E35: 1e-09 | F35: =IF(D35<=E35,"PASS","FAIL") -> PASS
A36: Best 100, worst 0: turnaround | B36: =Yardsticks!F15 -> 35.323786 | C36: =Reference_Values!B36 -> 35.323786 | D36: =ABS(B36-C36) -> 0 | E36: 1e-09 | F36: =IF(D36<=E36,"PASS","FAIL") -> PASS
A37: Spread of liquidity across the options | B37: =Yardsticks!B12 -> 26.811878 | C37: =Reference_Values!B37 -> 26.811878 | D37: =ABS(B37-C37) -> 0 | E37: 1e-09 | F37: =IF(D37<=E37,"PASS","FAIL") -> PASS
A38: Spread of technology across the options | B38: =Yardsticks!C12 -> 39.691634 | C38: =Reference_Values!B38 -> 39.691634 | D38: =ABS(B38-C38) -> 0 | E38: 1e-09 | F38: =IF(D38<=E38,"PASS","FAIL") -> PASS
A39: Spread of efficiency across the options | B39: =Yardsticks!D12 -> 5.0033725 | C39: =Reference_Values!B39 -> 5.0033725 | D39: =ABS(B39-C39) -> 0 | E39: 1e-09 | F39: =IF(D39<=E39,"PASS","FAIL") -> PASS
A40: Spread of strategic risk across the options | B40: =Yardsticks!E12 -> 16.940418 | C40: =Reference_Values!B40 -> 16.940418 | D40: =ABS(B40-C40) -> 0 | E40: 1e-09 | F40: =IF(D40<=E40,"PASS","FAIL") -> PASS
A41: Rescaled strategic-risk difference | B41: =Yardsticks!B20 -> 34.40032 | C41: =Reference_Values!B41 -> 34.40032 | D41: =ABS(B41-C41) -> 0 | E41: 1e-09 | F41: =IF(D41<=E41,"PASS","FAIL") -> PASS
A42: Rescaled technology lead | B42: =Yardsticks!B21 -> 92.652157 | C42: =Reference_Values!B42 -> 92.652157 | D42: =ABS(B42-C42) -> 0 | E42: 1e-09 | F42: =IF(D42<=E42,"PASS","FAIL") -> PASS
A43: Rescaled liquidity deficit | B43: =Yardsticks!B22 -> 100 | C43: =Reference_Values!B43 -> 100 | D43: =ABS(B43-C43) -> 0 | E43: 1e-09 | F43: =IF(D43<=E43,"PASS","FAIL") -> PASS
A44: Percentage on today: digital | B44: =Yardsticks!F25 -> 24.038073 | C44: =Reference_Values!B44 -> 24.038073 | D44: =ABS(B44-C44) -> 0 | E44: 1e-09 | F44: =IF(D44<=E44,"PASS","FAIL") -> PASS
A45: Percentage on today: restructuring | B45: =Yardsticks!F26 -> 10.623653 | C45: =Reference_Values!B45 -> 10.623653 | D45: =ABS(B45-C45) -> 0 | E45: 1e-09 | F45: =IF(D45<=E45,"PASS","FAIL") -> PASS
A46: Percentage on today: turnaround | B46: =Yardsticks!F27 -> 0.024648044 | C46: =Reference_Values!B46 -> 0.024648044 | D46: =ABS(B46-C46) -> 0 | E46: 1e-09 | F46: =IF(D46<=E46,"PASS","FAIL") -> PASS
A47: Technology's gain on today under digital (%) | B47: =Yardsticks!B31 -> 84.474803 | C47: =Reference_Values!B47 -> 84.474803 | D47: =ABS(B47-C47) -> 0 | E47: 1e-09 | F47: =IF(D47<=E47,"PASS","FAIL") -> PASS
A48: Percentage scale: digital's lead | B48: =Yardsticks!B30 -> 13.41442 | C48: =Reference_Values!B48 -> 13.41442 | D48: =ABS(B48-C48) -> 0 | E48: 1e-09 | F48: =IF(D48<=E48,"PASS","FAIL") -> PASS
A49: Effective weight, best-worst: liquidity (%) | B49: =100*Yardsticks!B17 -> 11.604991 | C49: =Reference_Values!B49 -> 11.604991 | D49: =ABS(B49-C49) -> 0 | E49: 1e-09 | F49: =IF(D49<=E49,"PASS","FAIL") -> PASS
A50: Effective weight, best-worst: technology (%) | B50: =100*Yardsticks!C17 -> 7.8392239 | C50: =Reference_Values!B50 -> 7.8392239 | D50: =ABS(B50-C50) -> 0 | E50: 1e-09 | F50: =IF(D50<=E50,"PASS","FAIL") -> PASS
A51: Effective weight, best-worst: efficiency (%) | B51: =100*Yardsticks!D17 -> 62.188375 | C51: =Reference_Values!B51 -> 62.188375 | D51: =ABS(B51-C51) -> 0 | E51: 1e-09 | F51: =IF(D51<=E51,"PASS","FAIL") -> PASS
A52: Effective weight, best-worst: strategic risk (%) | B52: =100*Yardsticks!E17 -> 18.36741 | C52: =Reference_Values!B52 -> 18.36741 | D52: =ABS(B52-C52) -> 0 | E52: 1e-09 | F52: =IF(D52<=E52,"PASS","FAIL") -> PASS
A53: Effective weight, percentage: liquidity (%) | B53: =100*Yardsticks!B29 -> 15.600685 | C53: =Reference_Values!B53 -> 15.600685 | D53: =ABS(B53-C53) -> 0 | E53: 1e-09 | F53: =IF(D53<=E53,"PASS","FAIL") -> PASS
A54: Effective weight, percentage: technology (%) | B54: =100*Yardsticks!C29 -> 38.05045 | C54: =Reference_Values!B54 -> 38.05045 | D54: =ABS(B54-C54) -> 0 | E54: 1e-09 | F54: =IF(D54<=E54,"PASS","FAIL") -> PASS
A55: Effective weight, percentage: efficiency (%) | B55: =100*Yardsticks!D29 -> 21.972795 | C55: =Reference_Values!B55 -> 21.972795 | D55: =ABS(B55-C55) -> 0 | E55: 1e-09 | F55: =IF(D55<=E55,"PASS","FAIL") -> PASS
A56: Effective weight, percentage: strategic risk (%) | B56: =100*Yardsticks!E29 -> 24.37607 | C56: =Reference_Values!B56 -> 24.37607 | D56: =ABS(B56-C56) -> 0 | E56: 1e-09 | F56: =IF(D56<=E56,"PASS","FAIL") -> PASS
A57: Theorem 11.2(iii): A after rescaling | B57: =Yardsticks!D38 -> 6 | C57: =Reference_Values!B57 -> 6 | D57: =ABS(B57-C57) -> 0 | E57: 0 | F57: =IF(D57<=E57,"PASS","FAIL") -> PASS
A58: Theorem 11.2(iii): B after rescaling | B58: =Yardsticks!D39 -> 7 | C58: =Reference_Values!B58 -> 7 | D58: =ABS(B58-C58) -> 0 | E58: 0 | F58: =IF(D58<=E58,"PASS","FAIL") -> PASS
A59: Reference group with today: digital | B59: =Yardsticks!F45 -> 49.945146 | C59: =Reference_Values!B59 -> 49.945146 | D59: =ABS(B59-C59) -> 0 | E59: 1e-09 | F59: =IF(D59<=E59,"PASS","FAIL") -> PASS
A60: Reference group with today: restructuring | B60: =Yardsticks!F46 -> 60.66328 | C60: =Reference_Values!B60 -> 60.66328 | D60: =ABS(B60-C60) -> 0 | E60: 1e-09 | F60: =IF(D60<=E60,"PASS","FAIL") -> PASS
A61: Two leaders alone: digital | B61: =Yardsticks!F56 -> 25 | C61: =Reference_Values!B61 -> 25 | D61: =ABS(B61-C61) -> 0 | E61: 1e-09 | F61: =IF(D61<=E61,"PASS","FAIL") -> PASS
A62: Two leaders alone: restructuring | B62: =Yardsticks!F57 -> 75 | C62: =Reference_Values!B62 -> 75 | D62: =ABS(B62-C62) -> 0 | E62: 1e-09 | F62: =IF(D62<=E62,"PASS","FAIL") -> PASS
A63: Two leaders alone: effective weight on efficiency | B63: =Yardsticks!D59 -> 0.9802204 | C63: =Reference_Values!B63 -> 0.9802204 | D63: =ABS(B63-C63) -> 0 | E63: 1e-09 | F63: =IF(D63<=E63,"PASS","FAIL") -> PASS
A64: Two divisions: group margin before (%) | B64: =Ratios!B7 -> 18.333333 | C64: =Reference_Values!B64 -> 18.333333 | D64: =ABS(B64-C64) -> 0 | E64: 1e-09 | F64: =IF(D64<=E64,"PASS","FAIL") -> PASS
A65: Two divisions: group margin after (%) | B65: =Ratios!B8 -> 18 | C65: =Reference_Values!B65 -> 18 | D65: =ABS(B65-C65) -> 0 | E65: 1e-09 | F65: =IF(D65<=E65,"PASS","FAIL") -> PASS
A66: Two divisions: rate effect (points) | B66: =Ratios!B9 -> 1.3333333 | C66: =Reference_Values!B66 -> 1.3333333 | D66: =ABS(B66-C66) -> 0 | E66: 1e-09 | F66: =IF(D66<=E66,"PASS","FAIL") -> PASS
A67: Two divisions: mix effect (points) | B67: =Ratios!B10 -> -1.6666667 | C67: =Reference_Values!B67 -> -1.6666667 | D67: =ABS(B67-C67) -> 0 | E67: 1e-09 | F67: =IF(D67<=E67,"PASS","FAIL") -> PASS
A68: Bank: group cost-income before (%) | B68: =Ratios!B19 -> 81.666667 | C68: =Reference_Values!B68 -> 81.666667 | D68: =ABS(B68-C68) -> 0 | E68: 1e-09 | F68: =IF(D68<=E68,"PASS","FAIL") -> PASS
A69: Bank: group cost-income after (%) | B69: =Ratios!B20 -> 82 | C69: =Reference_Values!B69 -> 82 | D69: =ABS(B69-C69) -> 0 | E69: 1e-09 | F69: =IF(D69<=E69,"PASS","FAIL") -> PASS
A70: Bank: rate effect (points) | B70: =Ratios!B21 -> -1.3333333 | C70: =Reference_Values!B70 -> -1.3333333 | D70: =ABS(B70-C70) -> 0 | E70: 1e-09 | F70: =IF(D70<=E70,"PASS","FAIL") -> PASS
A71: Bank: mix effect (points) | B71: =Ratios!B22 -> 1.6666667 | C71: =Reference_Values!B71 -> 1.6666667 | D71: =ABS(B71-C71) -> 0 | E71: 1e-09 | F71: =IF(D71<=E71,"PASS","FAIL") -> PASS
A72: Bank: unweighted average before (%) | B72: =Ratios!B24 -> 82.5 | C72: =Reference_Values!B72 -> 82.5 | D72: =ABS(B72-C72) -> 0 | E72: 1e-09 | F72: =IF(D72<=E72,"PASS","FAIL") -> PASS
A73: Bank: unweighted average after (%) | B73: =Ratios!B25 -> 81 | C73: =Reference_Values!B73 -> 81 | D73: =ABS(B73-C73) -> 0 | E73: 1e-09 | F73: =IF(D73<=E73,"PASS","FAIL") -> PASS
A74: Mix bench: share below which the group falls | B74: =Ratios!B51 -> 0.38888889 | C74: =Reference_Values!B74 -> 0.38888889 | D74: =ABS(B74-C74) -> 0 | E74: 1e-09 | F74: =IF(D74<=E74,"PASS","FAIL") -> PASS
A75: Shared capacity: three targets together | B75: =Ratios!B56 -> 12 | C75: =Reference_Values!B75 -> 12 | D75: =ABS(B75-C75) -> 0 | E75: 0 | F75: =IF(D75<=E75,"PASS","FAIL") -> PASS
A76: Indivisible programs: weightings ranking (4, 4) first | B76: =Frontier!B110 -> 0 | C76: =Reference_Values!B76 -> 0 | D76: =ABS(B76-C76) -> 0 | E76: 0 | F76: =IF(D76<=E76,"PASS","FAIL") -> PASS
A77: Indivisible programs: Pareto-optimal programs | B77: =Frontier!D7 -> 3 | C77: =Reference_Values!B77 -> 3 | D77: =ABS(B77-C77) -> 0 | E77: 0 | F77: =IF(D77<=E77,"PASS","FAIL") -> PASS
A78: Frontier: months of cover a margin point | B78: =Frontier!B127 -> 0.84375 | C78: =Reference_Values!B78 -> 0.84375 | D78: =ABS(B78-C78) -> 0 | E78: 1e-09 | F78: =IF(D78<=E78,"PASS","FAIL") -> PASS
A79: Frontier point: margin (%) | B79: =Frontier!B124 -> 11.958549 | C79: =Reference_Values!B79 -> 11.958549 | D79: =ABS(B79-C79) -> 0 | E79: 1e-09 | F79: =IF(D79<=E79,"PASS","FAIL") -> PASS
A80: Digital's low | B80: =Paths!Y4 -> 32.106467 | C80: =Reference_Values!B80 -> 32.106467 | D80: =ABS(B80-C80) -> 0 | E80: 1e-09 | F80: =IF(D80<=E80,"PASS","FAIL") -> PASS
A81: Month of digital's low | B81: =Paths!Y5 -> 11 | C81: =Reference_Values!B81 -> 11 | D81: =ABS(B81-C81) -> 0 | E81: 0 | F81: =IF(D81<=E81,"PASS","FAIL") -> PASS
A82: Month digital regains today's score | B82: =Paths!Y7 -> 29 | C82: =Reference_Values!B82 -> 29 | D82: =ABS(B82-C82) -> 0 | E82: 0 | F82: =IF(D82<=E82,"PASS","FAIL") -> PASS
A83: Digital at month 29 | B83: =Paths!Y8 -> 37.18741 | C83: =Reference_Values!B83 -> 37.18741 | D83: =ABS(B83-C83) -> 0 | E83: 1e-09 | F83: =IF(D83<=E83,"PASS","FAIL") -> PASS
A84: Month digital passes the turnaround | B84: =Paths!Y9 -> 33 | C84: =Reference_Values!B84 -> 33 | D84: =ABS(B84-C84) -> 0 | E84: 0 | F84: =IF(D84<=E84,"PASS","FAIL") -> PASS
A85: Digital at month 33 | B85: =Paths!Y10 -> 38.742683 | C85: =Reference_Values!B85 -> 38.742683 | D85: =ABS(B85-C85) -> 0 | E85: 1e-09 | F85: =IF(D85<=E85,"PASS","FAIL") -> PASS
A86: Turnaround at month 33 | B86: =Paths!Y11 -> 38.413313 | C86: =Reference_Values!B86 -> 38.413313 | D86: =ABS(B86-C86) -> 0 | E86: 1e-09 | F86: =IF(D86<=E86,"PASS","FAIL") -> PASS
A87: Month digital passes restructuring | B87: =Paths!Y12 -> 56 | C87: =Reference_Values!B87 -> 56 | D87: =ABS(B87-C87) -> 0 | E87: 0 | F87: =IF(D87<=E87,"PASS","FAIL") -> PASS
A88: Digital at month 56 | B88: =Paths!Y13 -> 46.145379 | C88: =Reference_Values!B88 -> 46.145379 | D88: =ABS(B88-C88) -> 0 | E88: 1e-09 | F88: =IF(D88<=E88,"PASS","FAIL") -> PASS
A89: Restructuring at month 56 | B89: =Paths!Y14 -> 46.004558 | C89: =Reference_Values!B89 -> 46.004558 | D89: =ABS(B89-C89) -> 0 | E89: 1e-09 | F89: =IF(D89<=E89,"PASS","FAIL") -> PASS
A90: Year 1 review: digital | B90: =Window!C4 -> 32.151236 | C90: =Reference_Values!B90 -> 32.151236 | D90: =ABS(B90-C90) -> 0 | E90: 1e-09 | F90: =IF(D90<=E90,"PASS","FAIL") -> PASS
A91: Year 1 review: restructuring | B91: =Window!D4 -> 44.455685 | C91: =Reference_Values!B91 -> 44.455685 | D91: =ABS(B91-C91) -> 0 | E91: 1e-09 | F91: =IF(D91<=E91,"PASS","FAIL") -> PASS
A92: Year 1 review: turnaround | B92: =Window!E4 -> 37.88901 | C92: =Reference_Values!B92 -> 37.88901 | D92: =ABS(B92-C92) -> 0 | E92: 1e-09 | F92: =IF(D92<=E92,"PASS","FAIL") -> PASS
A93: Year 2 review: digital | B93: =Window!C5 -> 35.274521 | C93: =Reference_Values!B93 -> 35.274521 | D93: =ABS(B93-C93) -> 0 | E93: 1e-09 | F93: =IF(D93<=E93,"PASS","FAIL") -> PASS
A94: Year 2 review: restructuring | B94: =Window!D5 -> 45.107989 | C94: =Reference_Values!B94 -> 45.107989 | D94: =ABS(B94-C94) -> 0 | E94: 1e-09 | F94: =IF(D94<=E94,"PASS","FAIL") -> PASS
A95: Year 2 review: turnaround | B95: =Window!E5 -> 38.290006 | C95: =Reference_Values!B95 -> 38.290006 | D95: =ABS(B95-C95) -> 0 | E95: 1e-09 | F95: =IF(D95<=E95,"PASS","FAIL") -> PASS
A96: Year 3 review: digital | B96: =Window!C6 -> 39.88373 | C96: =Reference_Values!B96 -> 39.88373 | D96: =ABS(B96-C96) -> 0 | E96: 1e-09 | F96: =IF(D96<=E96,"PASS","FAIL") -> PASS
A97: Year 3 review: restructuring | B97: =Window!D6 -> 45.5534 | C97: =Reference_Values!B97 -> 45.5534 | D97: =ABS(B97-C97) -> 0 | E97: 1e-09 | F97: =IF(D97<=E97,"PASS","FAIL") -> PASS
A98: Year 3 review: turnaround | B98: =Window!E6 -> 38.433092 | C98: =Reference_Values!B98 -> 38.433092 | D98: =ABS(B98-C98) -> 0 | E98: 1e-09 | F98: =IF(D98<=E98,"PASS","FAIL") -> PASS
A99: Year 4 review: digital | B99: =Window!C7 -> 43.961208 | C99: =Reference_Values!B99 -> 43.961208 | D99: =ABS(B99-C99) -> 0 | E99: 1e-09 | F99: =IF(D99<=E99,"PASS","FAIL") -> PASS
A100: Year 4 review: restructuring | B100: =Window!D7 -> 45.857547 | C100: =Reference_Values!B100 -> 45.857547 | D100: =ABS(B100-C100) -> 0 | E100: 1e-09 | F100: =IF(D100<=E100,"PASS","FAIL") -> PASS
...
