Workbook

Sheet README
B1: DCT Laboratory — Vol I, Ch 6: Enterprise Transformation Operators
B2: Seed 26106 · Companion to DCT_V1_Ch06_Lab.ipynb and AXIOM Lab 1.6 (module AXIOM-06). Money in $ million.
B4: Worked Example 6.1, Strategy or Trade? Meridian's Automation Playbook, with the book's declarations, and the five steps of AXIOM Lab 1.6, Sequencing Meridian's Moves.
B5: Declarations: Meridian today (Table 3.1), the board's floor (Table 5.4), the automation round (Worked Example 6.1), the sale (Worked Example 3.1), the digital build (Worked Example 1.1, computed with the Chapter 1 model), and the target.
B6: Operators: each move's domain and effect from today, Figure 6.1's states, and why the sale is a family of two (Definitions 6.1-6.4; Proposition 6.1; Theorem 6.1; lab step 1).
B7: Policy: the bank's rule of Online Appendix Example 6.B.1, a family made a closed-loop system (Theorem 6.1(iii)).
B8: Programs: all sixteen two-move sequences, seam by seam, and Section 6.5's sale, two rounds, then the build (Theorem 6.2(iii); Proposition 6.5; Figure 6.3; lab step 2).
B9: Playbook: the automation round year by year, savings paid out, recycled and short of plan, with Table 6.4, the nested domains and the sustainable core (Equation 6.2; Theorem 6.3; Figure 6.2; lab step 3).
B10: Reachability: every program of up to four moves, the reachable sets R_k to closure, targets and a cushion you can change, and complete goals with tolerances (Theorem 6.4; Remark 6.B.3; lab step 4).
B11: Stability: the drift bound and its worst case, and the playbook's steady states short of plan (Theorem 6.5; Equation 6.4; Figure 6.4; Remark 6.B.2; Worked Example 6.1, Step 4; lab step 5).
B12: Every result is a formula of the declarations. Reference_Values and Checks: the notebook engine's numbers and a PASS/FAIL comparison with this workbook's formulas.
B14: LEGEND
... B18: Cross-sheet link: green.

Sheet Declarations
A1: Declarations (Worked Example 6.1, Step 1; Worked Example 3.1; Figure 6.3). Money in $ million; indices from 0 to 100.
A3: Quantity | B3: Value | C3: Source
A4: Liquidity today | B4: 620 | C4: Table 3.1
A5: Technology platform today (index) | B5: 41 | C5: Table 3.1
A6: Workforce capability today (index) | B6: 58 | C6: Table 3.1
A7: Operational efficiency today (index) | B7: 71 | C7: Table 3.1
A8: The board's liquidity floor | B8: 350 | C8: Table 5.4
A10: Automation round: cost | B10: 120 | C10: Worked Example 6.1
A11: Automation round: the plants' technical ceiling on efficiency | B11: 85 | C11: Worked Example 6.1
A12: Automation round: share of the gap to the ceiling closed | B12: 0.5 | C12: Worked Example 6.1: half of the gap
A13: Workforce capability needed to staff the automated lines | B13: 55 | C13: Worked Example 6.1, Step 1
A14: Workforce capability added by a round's retraining | B14: 1 | C14: Worked Example 6.1
A15: Value of an efficiency point gained over today, a year | B15: 10 | C15: Worked Example 6.1: $10 million a year in lower costs
A16: Liquidity a round needs: floor + cost | B16: =B8+B10 -> 470 | C16: Worked Example 6.1, Step 1: $470 million, so the floor holds after the round
A18: Sale of part of Industrial Systems, engineers leave: net proceeds | B18: 112 | C18: Worked Example 3.1
A19: Sale, engineers kept: net proceeds | B19: 92 | C19: Worked Example 3.1: $20 million less
A20: Share of the technology position the unit takes | B20: 0.1 | C20: Worked Example 3.1
A21: Workforce capability lost if the engineers leave | B21: 5 | C21: Worked Example 3.1
A23: Digital build: liquidity change over five years | B23: =(G37-B37)*Liq_today/100 -> -35.367271 | C23: Worked Example 1.1; Table 1.9: computed below with the Chapter 1 model
A24: Digital build: technology change over five years (points) | B24: =G38-B38 -> 34.634669 | C24: Worked Example 1.1; Table 1.9
A25: Digital build: efficiency change over five years (points) | B25: =G39-B39 -> 2.598331 | C25: Worked Example 1.1; Table 1.9
A26: Digital build: low point below its starting liquidity | B26: =(100-B50)*Liq_today/100 -> 138.08206 | C26: Worked Example 1.1: cash bottoms around month 21
A27: Liquidity the build needs: floor + its low point | B27: =B8+B26 -> 488.08206 | C27: $488 million, so the floor holds at the build's low point
A28: Technology target | B28: 70 | C28: Figure 6.3: at least 70, with every constraint met
A29: Efficiency target | B29: 80 | C29: Figure 6.3: at least 80
A31: Move codes on the other sheets: 1 = S, sell, engineers leave; 2 = S*, sell, engineers kept; 3 = D, digital build; 4 = A, automation round.
A32: Domains: S and S* need the unit unsold; D needs the platform unbuilt, workforce capability of at least 55, and liquidity of at least floor + its low point, so the floor holds on the way; A needs workforce capability of at least 55 and liquidity of at least floor + cost.
A34: The digital build: Worked Example 1.1's program in the Chapter 1 model (Equation 1.B.1; Table 1.B.1, digital row). Liquidity is indexed to today = 100 = $620 million; the five-year changes add to the state the build starts from.
A36: Reading | B36: Start | C36: Target | D36: Rate k | E36: Dip depth | F36: Dip timing tau (years) | G36: Year 5 | H36: Change
A37: Liquidity (index) | B37: 100 | C37: 112 | D37: 0.35 | E37: -28 | F37: 2 | G37: =C37+(B37-C37)*EXP(-D37*5)+E37*(5/F37)*EXP(1-5/F37) -> 94.295601 | H37: =G37-B37 -> -5.7043985
A38: Technology platform | B38: 41 | C38: 78 | D38: 0.55 | E38: 0 | F38: 1 | G38: =C38+(B38-C38)*EXP(-D38*5)+E38*(5/F38)*EXP(1-5/F38) -> 75.634669 | H38: =G38-B38 -> 34.634669
A39: Operational efficiency | B39: 71 | C39: 77 | D39: 0.5 | E39: -9 | F39: 1.5 | G39: =C39+(B39-C39)*EXP(-D39*5)+E39*(5/F39)*EXP(1-5/F39) -> 73.598331 | H39: =G39-B39 -> 2.598331
A41: Low point of the liquidity index: Newton's method on its slope, from year 1.5
A42: Iteration | B42: Year t | C42: Slope | D42: Curvature
A43: 0 | B43: 1.5 | C43: =-$D$37*($B$37-$C$37)*EXP(-$D$37*B43)+($E$37/$F$37)*EXP(1-B43/$F$37)*(1-B43/$F$37) -> -2.0095564 | D43: =$D$37^2*($B$37-$C$37)*EXP(-$D$37*B43)+($E$37/$F$37^2)*EXP(1-B43/$F$37)*(B43/$F$37-2) -> 10.365636
A44: 1 | B44: =B43-C43/D43 -> 1.6938672 | C44: =-$D$37*($B$37-$C$37)*EXP(-$D$37*B44)+($E$37/$F$37)*EXP(1-B44/$F$37)*(1-B44/$F$37) -> -0.17583497 | D44: =$D$37^2*($B$37-$C$37)*EXP(-$D$37*B44)+($E$37/$F$37^2)*EXP(1-B44/$F$37)*(B44/$F$37-2) -> 8.5939652
A45: 2 | B45: =B44-C44/D44 -> 1.7143274 | C45: =-$D$37*($B$37-$C$37)*EXP(-$D$37*B45)+($E$37/$F$37)*EXP(1-B45/$F$37)*(1-B45/$F$37) -> -0.0017696753 | D45: =$D$37^2*($B$37-$C$37)*EXP(-$D$37*B45)+($E$37/$F$37^2)*EXP(1-B45/$F$37)*(B45/$F$37-2) -> 8.4214176
A46: 3 | B46: =B45-C45/D45 -> 1.7145376 | C46: =-$D$37*($B$37-$C$37)*EXP(-$D$37*B46)+($E$37/$F$37)*EXP(1-B46/$F$37)*(1-B46/$F$37) -> -1.8477513e-07 | D46: =$D$37^2*($B$37-$C$37)*EXP(-$D$37*B46)+($E$37/$F$37^2)*EXP(1-B46/$F$37)*(B46/$F$37-2) -> 8.419659
A47: 4 | B47: =B46-C46/D46 -> 1.7145376 | C47: =-$D$37*($B$37-$C$37)*EXP(-$D$37*B47)+($E$37/$F$37)*EXP(1-B47/$F$37)*(1-B47/$F$37) -> 0 | D47: =$D$37^2*($B$37-$C$37)*EXP(-$D$37*B47)+($E$37/$F$37^2)*EXP(1-B47/$F$37)*(B47/$F$37-2) -> 8.4196589
A48: 5 | B48: =B47-C47/D47 -> 1.7145376 | C48: =-$D$37*($B$37-$C$37)*EXP(-$D$37*B48)+($E$37/$F$37)*EXP(1-B48/$F$37)*(1-B48/$F$37) -> 0 | D48: =$D$37^2*($B$37-$C$37)*EXP(-$D$37*B48)+($E$37/$F$37^2)*EXP(1-B48/$F$37)*(B48/$F$37-2) -> 8.4196589
A49: Month of the low point | B49: =B48*12 -> 20.574451 | C49: Worked Example 1.1: around month 21
A50: Liquidity index at the low point | B50: =$C$37+($B$37-$C$37)*EXP(-$D$37*B48)+$E$37*(B48/$F$37)*EXP(1-B48/$F$37) -> 77.7287

Sheet Operators
A1: Forge the operators: domains and effects from today's state (Definitions 6.1-6.4; Figure 6.1; AXIOM Lab 1.6, step 1)
B3: Liquidity | C3: Technology | D3: Workforce | E3: Efficiency | F3: Unit sold (1 = yes) | G3: Platform built (1 = yes)
A4: Meridian today | B4: =Liq_today -> 620 | C4: =Tech_today -> 41 | D4: =W_today -> 58 | E4: =Eff_today -> 71 | F4: 0 | G4: 0
A6: Move | B6: Liquidity after | C6: Technology after | D6: Workforce after | E6: Efficiency after | F6: In the domain today (1 = yes) | G6: Domain (preconditions) | H6: Why not
A7: S, sell, engineers leave (code 1) | B7: =IF(F7=1,CHOOSE(1,$B$4+Proc_S,$B$4+Proc_Sk,$B$4+D_dL,$B$4-Cost_A),"no result") -> 732 | C7: =IF(F7=1,CHOOSE(1,(1-Tech_share)*$C$4,(1-Tech_share)*$C$4,$C$4+D_dT,$C$4),"no result") -> 36.9 | D7: =IF(F7=1,CHOOSE(1,$D$4-W_lost,$D$4,$D$4,$D$4+W_gain),"no result") -> 53 | E7: =IF(F7=1,CHOOSE(1,$E$4,$E$4,$E$4+D_dE,$E$4+Close_A*(Ceil_E-$E$4)),"no result") -> 71 | F7: =IF(1<=2,1-$F$4,IF(1=3,IF(AND($G$4=0,$D$4>=W_min,$B$4-D_dip>=Floor_q),1,0),IF(AND($D$4>=W_min,$B$4>=Pre_A),1,0))) -> 1 | G7: ="the unit unsold" -> the unit unsold | H7: =IF($F$4=1,"the unit is already sold","")
A8: S*, sell, engineers kept (code 2) | B8: =IF(F8=1,CHOOSE(2,$B$4+Proc_S,$B$4+Proc_Sk,$B$4+D_dL,$B$4-Cost_A),"no result") -> 712 | C8: =IF(F8=1,CHOOSE(2,(1-Tech_share)*$C$4,(1-Tech_share)*$C$4,$C$4+D_dT,$C$4),"no result") -> 36.9 | D8: =IF(F8=1,CHOOSE(2,$D$4-W_lost,$D$4,$D$4,$D$4+W_gain),"no result") -> 58 | E8: =IF(F8=1,CHOOSE(2,$E$4,$E$4,$E$4+D_dE,$E$4+Close_A*(Ceil_E-$E$4)),"no result") -> 71 | F8: =IF(2<=2,1-$F$4,IF(2=3,IF(AND($G$4=0,$D$4>=W_min,$B$4-D_dip>=Floor_q),1,0),IF(AND($D$4>=W_min,$B$4>=Pre_A),1,0))) -> 1 | G8: ="the unit unsold" -> the unit unsold | H8: =IF($F$4=1,"the unit is already sold","")
A9: D, digital build (code 3) | B9: =IF(F9=1,CHOOSE(3,$B$4+Proc_S,$B$4+Proc_Sk,$B$4+D_dL,$B$4-Cost_A),"no result") -> 584.63273 | C9: =IF(F9=1,CHOOSE(3,(1-Tech_share)*$C$4,(1-Tech_share)*$C$4,$C$4+D_dT,$C$4),"no result") -> 75.634669 | D9: =IF(F9=1,CHOOSE(3,$D$4-W_lost,$D$4,$D$4,$D$4+W_gain),"no result") -> 58 | E9: =IF(F9=1,CHOOSE(3,$E$4,$E$4,$E$4+D_dE,$E$4+Close_A*(Ceil_E-$E$4)),"no result") -> 73.598331 | F9: =IF(3<=2,1-$F$4,IF(3=3,IF(AND($G$4=0,$D$4>=W_min,$B$4-D_dip>=Floor_q),1,0),IF(AND($D$4>=W_min,$B$4>=Pre_A),1,0))) -> 1 | G9: ="not built, workforce >= "&TEXT(W_min,"0")&", liquidity >= $"&TEXT(Pre_D,"0")&"m" -> not built, workforce >= 55, liquidity >= $488m | H9: =IF($G$4=1,"the platform is already built",IF($D$4<W_min,"workforce below "&TEXT(W_min,"0"),IF($B$4-D_dip<Floor_q,"its low point $"&TEXT($B$4-D_dip,"0")&"m is below the floor","")))
A10: A, automation round (code 4) | B10: =IF(F10=1,CHOOSE(4,$B$4+Proc_S,$B$4+Proc_Sk,$B$4+D_dL,$B$4-Cost_A),"no result") -> 500 | C10: =IF(F10=1,CHOOSE(4,(1-Tech_share)*$C$4,(1-Tech_share)*$C$4,$C$4+D_dT,$C$4),"no result") -> 41 | D10: =IF(F10=1,CHOOSE(4,$D$4-W_lost,$D$4,$D$4,$D$4+W_gain),"no result") -> 59 | E10: =IF(F10=1,CHOOSE(4,$E$4,$E$4,$E$4+D_dE,$E$4+Close_A*(Ceil_E-$E$4)),"no result") -> 78 | F10: =IF(4<=2,1-$F$4,IF(4=3,IF(AND($G$4=0,$D$4>=W_min,$B$4-D_dip>=Floor_q),1,0),IF(AND($D$4>=W_min,$B$4>=Pre_A),1,0))) -> 1 | G10: ="workforce >= "&TEXT(W_min,"0")&", liquidity >= $"&TEXT(Pre_A,"0")&"m" -> workforce >= 55, liquidity >= $470m | H10: =IF($D$4<W_min,"workforce below "&TEXT(W_min,"0"),IF($B$4<Pre_A,"liquidity below $"&TEXT(Pre_A,"0")&"m",""))
A11: Moves that can be taken today | F11: =SUM(F7:F10) -> 4
A12: The digital build's low point from today | B12: =B4-D_dip -> 481.91794 | C12: =IF(B12>=Floor_q,"$"&TEXT(B12-Floor_q,"0")&" million above the floor: the build can start today","below the floor: outside its domain the build has no result (Definition 6.3)") -> $132 million above the floor: the build can start today
A14: The round on Figure 6.1's plane | B14: Liquidity | C14: Efficiency | D14: In the domain (1 = yes) | E14: Liquidity after | F14: Efficiency after
A15: Meridian today | B15: 620 | C15: 71 | D15: =IF(AND(B15>=Pre_A,W_today>=W_min),1,0) -> 1 | E15: =IF(D15=1,B15-Cost_A,"no result") -> 500 | F15: =IF(D15=1,C15+Close_A*(Ceil_E-C15),"no result") -> 78
A16: a state in the domain | B16: 860 | C16: 67.5 | D16: =IF(AND(B16>=Pre_A,W_today>=W_min),1,0) -> 1 | E16: =IF(D16=1,B16-Cost_A,"no result") -> 740 | F16: =IF(D16=1,C16+Close_A*(Ceil_E-C16),"no result") -> 76.25
A17: a state in the domain | B17: 800 | C17: 81 | D17: =IF(AND(B17>=Pre_A,W_today>=W_min),1,0) -> 1 | E17: =IF(D17=1,B17-Cost_A,"no result") -> 680 | F17: =IF(D17=1,C17+Close_A*(Ceil_E-C17),"no result") -> 83
A18: a feasible state outside | B18: 410 | C18: 66.5 | D18: =IF(AND(B18>=Pre_A,W_today>=W_min),1,0) -> 0 | E18: =IF(D18=1,B18-Cost_A,"no result") -> no result | F18: =IF(D18=1,C18+Close_A*(Ceil_E-C18),"no result") -> no result
A19: Range: liquidity at least the floor, and efficiency (e + 85)/2, which stays below the ceiling of 85 whenever e does: the round can approach the ceiling but never deliver it.
A21: Record of 'sell part of Industrial Systems' (Proposition 6.1) | B21: Liquidity after | C21: Workforce after | D21: Same start?
A22: today, then the sale with the engineers leaving | B22: =CHOOSE(1,$B$4+Proc_S,$B$4+Proc_Sk,$B$4+D_dL,$B$4-Cost_A) -> 732 | C22: =CHOOSE(1,$D$4-W_lost,$D$4,$D$4,$D$4+W_gain) -> 53 | D22: yes
A23: today, then the sale keeping the engineers | B23: =CHOOSE(2,$B$4+Proc_S,$B$4+Proc_Sk,$B$4+D_dL,$B$4-Cost_A) -> 712 | C23: =CHOOSE(2,$D$4-W_lost,$D$4,$D$4,$D$4+W_gain) -> 58 | D23: yes
A24: Different outcomes from one start | B24: =IF(OR(B22<>B23,C22<>C23),2,1) -> 2
A25: One operator? | B25: =IF(B24=1,"yes","no: a family of two, one per decision about the engineers") -> no: a family of two, one per decision about the engineers
A27: Theorem 6.1(ii): the sale's proceeds rest on a buyer paying the assumed price, an assumption about the environment, not a commitment (Table 6.1: a buyer at the assumed price).

Sheet Policy
A1: A policy turns a family into a system: the bank's rule (Theorem 6.1(iii); Online Appendix Example 6.B.1)
A2: The family T_u(q, t) = (q - u, t + 0.05u) on the domain q - u >= 300; the rule u(q) = share x (q - 300) leaves the closed loop q' = (1 - share) q + share x 300, a contraction with L = 1 - share.
A3: Declaration | B3: Value | H3: Result | I3: Value
A4: Liquidity today ($ million) | B4: 900 | H4: Liquidity after one year | I4: =B13 -> 600
A5: Regulatory floor ($ million) | B5: 300 | H5: after two years | I5: =B14 -> 450
A6: Technology index today | B6: 41 | H6: after three years | I6: =B15 -> 375
A7: Technology points per $1 million invested | B7: 0.05 | H7: after four years | I7: =B16 -> 337.5
A8: The rule: share of the liquidity above the floor invested each year | B8: 0.5 | H8: Technology after one year | I8: =D13 -> 56
H9: after two years | I9: =D14 -> 63.5
H10: Total invested over 40 years (the initial slack) | I10: =SUM(C12:C52) -> 600
A11: Year | B11: Liquidity | C11: Invested u | D11: Technology | E11: Closed form: floor + (q0 - floor)(1 - share)^k | F11: In the domain (q - u >= floor) | H11: Technology after 40 years (limit 41 + 0.05 x 600 = 71) | I11: =D52 -> 71
A12: 0 | B12: =B4 -> 900 | C12: 0 | D12: =B6 -> 41 | E12: =$B$5+($B$4-$B$5)*(1-$B$8)^A12 -> 900
A13: 1 | B13: =B12-C13 -> 600 | C13: =$B$8*(B12-$B$5) -> 300 | D13: =D12+$B$7*C13 -> 56 | E13: =$B$5+($B$4-$B$5)*(1-$B$8)^A13 -> 600 | F13: =IF(B12-C13>=$B$5,1,0) -> 1
A14: 2 | B14: =B13-C14 -> 450 | C14: =$B$8*(B13-$B$5) -> 150 | D14: =D13+$B$7*C14 -> 63.5 | E14: =$B$5+($B$4-$B$5)*(1-$B$8)^A14 -> 450 | F14: =IF(B13-C14>=$B$5,1,0) -> 1
A15: 3 | B15: =B14-C15 -> 375 | C15: =$B$8*(B14-$B$5) -> 75 | D15: =D14+$B$7*C15 -> 67.25 | E15: =$B$5+($B$4-$B$5)*(1-$B$8)^A15 -> 375 | F15: =IF(B14-C15>=$B$5,1,0) -> 1
A16: 4 | B16: =B15-C16 -> 337.5 | C16: =$B$8*(B15-$B$5) -> 37.5 | D16: =D15+$B$7*C16 -> 69.125 | E16: =$B$5+($B$4-$B$5)*(1-$B$8)^A16 -> 337.5 | F16: =IF(B15-C16>=$B$5,1,0) -> 1
A17: 5 | B17: =B16-C17 -> 318.75 | C17: =$B$8*(B16-$B$5) -> 18.75 | D17: =D16+$B$7*C17 -> 70.0625 | E17: =$B$5+($B$4-$B$5)*(1-$B$8)^A17 -> 318.75 | F17: =IF(B16-C17>=$B$5,1,0) -> 1
A18: 6 | B18: =B17-C18 -> 309.375 | C18: =$B$8*(B17-$B$5) -> 9.375 | D18: =D17+$B$7*C18 -> 70.53125 | E18: =$B$5+($B$4-$B$5)*(1-$B$8)^A18 -> 309.375 | F18: =IF(B17-C18>=$B$5,1,0) -> 1
A19: 7 | B19: =B18-C19 -> 304.6875 | C19: =$B$8*(B18-$B$5) -> 4.6875 | D19: =D18+$B$7*C19 -> 70.765625 | E19: =$B$5+($B$4-$B$5)*(1-$B$8)^A19 -> 304.6875 | F19: =IF(B18-C19>=$B$5,1,0) -> 1
A20: 8 | B20: =B19-C20 -> 302.34375 | C20: =$B$8*(B19-$B$5) -> 2.34375 | D20: =D19+$B$7*C20 -> 70.882812 | E20: =$B$5+($B$4-$B$5)*(1-$B$8)^A20 -> 302.34375 | F20: =IF(B19-C20>=$B$5,1,0) -> 1
A21: 9 | B21: =B20-C21 -> 301.17188 | C21: =$B$8*(B20-$B$5) -> 1.171875 | D21: =D20+$B$7*C21 -> 70.941406 | E21: =$B$5+($B$4-$B$5)*(1-$B$8)^A21 -> 301.17188 | F21: =IF(B20-C21>=$B$5,1,0) -> 1
A22: 10 | B22: =B21-C22 -> 300.58594 | C22: =$B$8*(B21-$B$5) -> 0.5859375 | D22: =D21+$B$7*C22 -> 70.970703 | E22: =$B$5+($B$4-$B$5)*(1-$B$8)^A22 -> 300.58594 | F22: =IF(B21-C22>=$B$5,1,0) -> 1
A23: 11 | B23: =B22-C23 -> 300.29297 | C23: =$B$8*(B22-$B$5) -> 0.29296875 | D23: =D22+$B$7*C23 -> 70.985352 | E23: =$B$5+($B$4-$B$5)*(1-$B$8)^A23 -> 300.29297 | F23: =IF(B22-C23>=$B$5,1,0) -> 1
A24: 12 | B24: =B23-C24 -> 300.14648 | C24: =$B$8*(B23-$B$5) -> 0.14648438 | D24: =D23+$B$7*C24 -> 70.992676 | E24: =$B$5+($B$4-$B$5)*(1-$B$8)^A24 -> 300.14648 | F24: =IF(B23-C24>=$B$5,1,0) -> 1
... A52: 40 | B52: =B51-C52 -> 300 | C52: =$B$8*(B51-$B$5) -> 5.4569682e-10 | D52: =D51+$B$7*C52 -> 71 | E52: =$B$5+($B$4-$B$5)*(1-$B$8)^A52 -> 300 | F52: =IF(B51-C52>=$B$5,1,0) -> 1

Sheet Programs
A1: Compose programs: every two-move sequence from today, seam by seam (Theorem 6.2(iii); Proposition 6.5; Figure 6.3; AXIOM Lab 1.6, step 2)
A2: A program runs only if each step's result lies in the next step's domain (Definition 6.5). Codes: 1 = S, 2 = S*, 3 = D, 4 = A. A second sale or a second build is never possible. Grey: the state a move would produce if its preconditions were ignored; it has no result.
B3: Liquidity | C3: Technology | D3: Workforce | E3: Efficiency | F3: Unit sold | G3: Built
A4: Meridian today | B4: =Liq_today -> 620 | C4: =Tech_today -> 41 | D4: =W_today -> 58 | E4: =Eff_today -> 71 | F4: =Operators!F4 -> 0 | G4: =Operators!G4 -> 0
A6: First move | B6: Second move | C6: Code 1 | D6: Code 2 | E6: Step 1 runs | F6: Liquidity 1 | G6: Technology 1 | H6: Workforce 1 | I6: Efficiency 1 | J6: Sold 1 | K6: Step 2 runs | L6: Liquidity 2 | M6: Technology 2 | N6: Workforce 2 | O6: Efficiency 2 | P6: Sold 2 | Q6: Target met (technology and efficiency) | R6: Headroom over the floor | S6: Built 1 | T6: Built 2
A7: S | B7: S | C7: 1 | D7: 1 | E7: =IF(C7<=2,1-$F$4,IF(C7=3,IF(AND($G$4=0,$D$4>=W_min,$B$4-D_dip>=Floor_q),1,0),IF(AND($D$4>=W_min,$B$4>=Pre_A),1,0))) -> 1 | F7: =CHOOSE(C7,$B$4+Proc_S,$B$4+Proc_Sk,$B$4+D_dL,$B$4-Cost_A) -> 732 | G7: =CHOOSE(C7,(1-Tech_share)*$C$4,(1-Tech_share)*$C$4,$C$4+D_dT,$C$4) -> 36.9 | H7: =CHOOSE(C7,$D$4-W_lost,$D$4,$D$4,$D$4+W_gain) -> 53 | I7: =CHOOSE(C7,$E$4,$E$4,$E$4+D_dE,$E$4+Close_A*(Ceil_E-$E$4)) -> 71 | J7: =CHOOSE(C7,1,1,$F$4,$F$4) -> 1 | K7: =E7*IF(D7<=2,1-J7,IF(D7=3,IF(AND(S7=0,H7>=W_min,F7-D_dip>=Floor_q),1,0),IF(AND(H7>=W_min,F7>=Pre_A),1,0))) -> 0 | L7: =CHOOSE(D7,F7+Proc_S,F7+Proc_Sk,F7+D_dL,F7-Cost_A) -> 844 | M7: =CHOOSE(D7,(1-Tech_share)*G7,(1-Tech_share)*G7,G7+D_dT,G7) -> 33.21 | N7: =CHOOSE(D7,H7-W_lost,H7,H7,H7+W_gain) -> 48 | O7: =CHOOSE(D7,I7,I7,I7+D_dE,I7+Close_A*(Ceil_E-I7)) -> 71 | P7: =CHOOSE(D7,1,1,J7,J7) -> 1 | Q7: =IF(K7=1,IF(AND(M7>=Target_T,O7>=Target_E,L7>=Floor_q),1,0),0) -> 0 | R7: =IF(K7=1,L7-Floor_q,"") | S7: =CHOOSE(C7,$G$4,$G$4,1,$G$4) -> 0 | T7: =CHOOSE(D7,S7,S7,1,S7) -> 0
A8: S | B8: S* | C8: 1 | D8: 2 | E8: =IF(C8<=2,1-$F$4,IF(C8=3,IF(AND($G$4=0,$D$4>=W_min,$B$4-D_dip>=Floor_q),1,0),IF(AND($D$4>=W_min,$B$4>=Pre_A),1,0))) -> 1 | F8: =CHOOSE(C8,$B$4+Proc_S,$B$4+Proc_Sk,$B$4+D_dL,$B$4-Cost_A) -> 732 | G8: =CHOOSE(C8,(1-Tech_share)*$C$4,(1-Tech_share)*$C$4,$C$4+D_dT,$C$4) -> 36.9 | H8: =CHOOSE(C8,$D$4-W_lost,$D$4,$D$4,$D$4+W_gain) -> 53 | I8: =CHOOSE(C8,$E$4,$E$4,$E$4+D_dE,$E$4+Close_A*(Ceil_E-$E$4)) -> 71 | J8: =CHOOSE(C8,1,1,$F$4,$F$4) -> 1 | K8: =E8*IF(D8<=2,1-J8,IF(D8=3,IF(AND(S8=0,H8>=W_min,F8-D_dip>=Floor_q),1,0),IF(AND(H8>=W_min,F8>=Pre_A),1,0))) -> 0 | L8: =CHOOSE(D8,F8+Proc_S,F8+Proc_Sk,F8+D_dL,F8-Cost_A) -> 824 | M8: =CHOOSE(D8,(1-Tech_share)*G8,(1-Tech_share)*G8,G8+D_dT,G8) -> 33.21 | N8: =CHOOSE(D8,H8-W_lost,H8,H8,H8+W_gain) -> 53 | O8: =CHOOSE(D8,I8,I8,I8+D_dE,I8+Close_A*(Ceil_E-I8)) -> 71 | P8: =CHOOSE(D8,1,1,J8,J8) -> 1 | Q8: =IF(K8=1,IF(AND(M8>=Target_T,O8>=Target_E,L8>=Floor_q),1,0),0) -> 0 | R8: =IF(K8=1,L8-Floor_q,"") | S8: =CHOOSE(C8,$G$4,$G$4,1,$G$4) -> 0 | T8: =CHOOSE(D8,S8,S8,1,S8) -> 0
A9: S | B9: D | C9: 1 | D9: 3 | E9: =IF(C9<=2,1-$F$4,IF(C9=3,IF(AND($G$4=0,$D$4>=W_min,$B$4-D_dip>=Floor_q),1,0),IF(AND($D$4>=W_min,$B$4>=Pre_A),1,0))) -> 1 | F9: =CHOOSE(C9,$B$4+Proc_S,$B$4+Proc_Sk,$B$4+D_dL,$B$4-Cost_A) -> 732 | G9: =CHOOSE(C9,(1-Tech_share)*$C$4,(1-Tech_share)*$C$4,$C$4+D_dT,$C$4) -> 36.9 | H9: =CHOOSE(C9,$D$4-W_lost,$D$4,$D$4,$D$4+W_gain) -> 53 | I9: =CHOOSE(C9,$E$4,$E$4,$E$4+D_dE,$E$4+Close_A*(Ceil_E-$E$4)) -> 71 | J9: =CHOOSE(C9,1,1,$F$4,$F$4) -> 1 | K9: =E9*IF(D9<=2,1-J9,IF(D9=3,IF(AND(S9=0,H9>=W_min,F9-D_dip>=Floor_q),1,0),IF(AND(H9>=W_min,F9>=Pre_A),1,0))) -> 0 | L9: =CHOOSE(D9,F9+Proc_S,F9+Proc_Sk,F9+D_dL,F9-Cost_A) -> 696.63273 | M9: =CHOOSE(D9,(1-Tech_share)*G9,(1-Tech_share)*G9,G9+D_dT,G9) -> 71.534669 | N9: =CHOOSE(D9,H9-W_lost,H9,H9,H9+W_gain) -> 53 | O9: =CHOOSE(D9,I9,I9,I9+D_dE,I9+Close_A*(Ceil_E-I9)) -> 73.598331 | P9: =CHOOSE(D9,1,1,J9,J9) -> 1 | Q9: =IF(K9=1,IF(AND(M9>=Target_T,O9>=Target_E,L9>=Floor_q),1,0),0) -> 0 | R9: =IF(K9=1,L9-Floor_q,"") | S9: =CHOOSE(C9,$G$4,$G$4,1,$G$4) -> 0 | T9: =CHOOSE(D9,S9,S9,1,S9) -> 1
A10: S | B10: A | C10: 1 | D10: 4 | E10: =IF(C10<=2,1-$F$4,IF(C10=3,IF(AND($G$4=0,$D$4>=W_min,$B$4-D_dip>=Floor_q),1,0),IF(AND($D$4>=W_min,$B$4>=Pre_A),1,0))) -> 1 | F10: =CHOOSE(C10,$B$4+Proc_S,$B$4+Proc_Sk,$B$4+D_dL,$B$4-Cost_A) -> 732 | G10: =CHOOSE(C10,(1-Tech_share)*$C$4,(1-Tech_share)*$C$4,$C$4+D_dT,$C$4) -> 36.9 | H10: =CHOOSE(C10,$D$4-W_lost,$D$4,$D$4,$D$4+W_gain) -> 53 | I10: =CHOOSE(C10,$E$4,$E$4,$E$4+D_dE,$E$4+Close_A*(Ceil_E-$E$4)) -> 71 | J10: =CHOOSE(C10,1,1,$F$4,$F$4) -> 1 | K10: =E10*IF(D10<=2,1-J10,IF(D10=3,IF(AND(S10=0,H10>=W_min,F10-D_dip>=Floor_q),1,0),IF(AND(H10>=W_min,F10>=Pre_A),1,0))) -> 0 | L10: =CHOOSE(D10,F10+Proc_S,F10+Proc_Sk,F10+D_dL,F10-Cost_A) -> 612 | M10: =CHOOSE(D10,(1-Tech_share)*G10,(1-Tech_share)*G10,G10+D_dT,G10) -> 36.9 | N10: =CHOOSE(D10,H10-W_lost,H10,H10,H10+W_gain) -> 54 | O10: =CHOOSE(D10,I10,I10,I10+D_dE,I10+Close_A*(Ceil_E-I10)) -> 78 | P10: =CHOOSE(D10,1,1,J10,J10) -> 1 | Q10: =IF(K10=1,IF(AND(M10>=Target_T,O10>=Target_E,L10>=Floor_q),1,0),0) -> 0 | R10: =IF(K10=1,L10-Floor_q,"") | S10: =CHOOSE(C10,$G$4,$G$4,1,$G$4) -> 0 | T10: =CHOOSE(D10,S10,S10,1,S10) -> 0
A11: S* | B11: S | C11: 2 | D11: 1 | E11: =IF(C11<=2,1-$F$4,IF(C11=3,IF(AND($G$4=0,$D$4>=W_min,$B$4-D_dip>=Floor_q),1,0),IF(AND($D$4>=W_min,$B$4>=Pre_A),1,0))) -> 1 | F11: =CHOOSE(C11,$B$4+Proc_S,$B$4+Proc_Sk,$B$4+D_dL,$B$4-Cost_A) -> 712 | G11: =CHOOSE(C11,(1-Tech_share)*$C$4,(1-Tech_share)*$C$4,$C$4+D_dT,$C$4) -> 36.9 | H11: =CHOOSE(C11,$D$4-W_lost,$D$4,$D$4,$D$4+W_gain) -> 58 | I11: =CHOOSE(C11,$E$4,$E$4,$E$4+D_dE,$E$4+Close_A*(Ceil_E-$E$4)) -> 71 | J11: =CHOOSE(C11,1,1,$F$4,$F$4) -> 1 | K11: =E11*IF(D11<=2,1-J11,IF(D11=3,IF(AND(S11=0,H11>=W_min,F11-D_dip>=Floor_q),1,0),IF(AND(H11>=W_min,F11>=Pre_A),1,0))) -> 0 | L11: =CHOOSE(D11,F11+Proc_S,F11+Proc_Sk,F11+D_dL,F11-Cost_A) -> 824 | M11: =CHOOSE(D11,(1-Tech_share)*G11,(1-Tech_share)*G11,G11+D_dT,G11) -> 33.21 | N11: =CHOOSE(D11,H11-W_lost,H11,H11,H11+W_gain) -> 53 | O11: =CHOOSE(D11,I11,I11,I11+D_dE,I11+Close_A*(Ceil_E-I11)) -> 71 | P11: =CHOOSE(D11,1,1,J11,J11) -> 1 | Q11: =IF(K11=1,IF(AND(M11>=Target_T,O11>=Target_E,L11>=Floor_q),1,0),0) -> 0 | R11: =IF(K11=1,L11-Floor_q,"") | S11: =CHOOSE(C11,$G$4,$G$4,1,$G$4) -> 0 | T11: =CHOOSE(D11,S11,S11,1,S11) -> 0
A12: S* | B12: S* | C12: 2 | D12: 2 | E12: =IF(C12<=2,1-$F$4,IF(C12=3,IF(AND($G$4=0,$D$4>=W_min,$B$4-D_dip>=Floor_q),1,0),IF(AND($D$4>=W_min,$B$4>=Pre_A),1,0))) -> 1 | F12: =CHOOSE(C12,$B$4+Proc_S,$B$4+Proc_Sk,$B$4+D_dL,$B$4-Cost_A) -> 712 | G12: =CHOOSE(C12,(1-Tech_share)*$C$4,(1-Tech_share)*$C$4,$C$4+D_dT,$C$4) -> 36.9 | H12: =CHOOSE(C12,$D$4-W_lost,$D$4,$D$4,$D$4+W_gain) -> 58 | I12: =CHOOSE(C12,$E$4,$E$4,$E$4+D_dE,$E$4+Close_A*(Ceil_E-$E$4)) -> 71 | J12: =CHOOSE(C12,1,1,$F$4,$F$4) -> 1 | K12: =E12*IF(D12<=2,1-J12,IF(D12=3,IF(AND(S12=0,H12>=W_min,F12-D_dip>=Floor_q),1,0),IF(AND(H12>=W_min,F12>=Pre_A),1,0))) -> 0 | L12: =CHOOSE(D12,F12+Proc_S,F12+Proc_Sk,F12+D_dL,F12-Cost_A) -> 804 | M12: =CHOOSE(D12,(1-Tech_share)*G12,(1-Tech_share)*G12,G12+D_dT,G12) -> 33.21 | N12: =CHOOSE(D12,H12-W_lost,H12,H12,H12+W_gain) -> 58 | O12: =CHOOSE(D12,I12,I12,I12+D_dE,I12+Close_A*(Ceil_E-I12)) -> 71 | P12: =CHOOSE(D12,1,1,J12,J12) -> 1 | Q12: =IF(K12=1,IF(AND(M12>=Target_T,O12>=Target_E,L12>=Floor_q),1,0),0) -> 0 | R12: =IF(K12=1,L12-Floor_q,"") | S12: =CHOOSE(C12,$G$4,$G$4,1,$G$4) -> 0 | T12: =CHOOSE(D12,S12,S12,1,S12) -> 0
A13: S* | B13: D | C13: 2 | D13: 3 | E13: =IF(C13<=2,1-$F$4,IF(C13=3,IF(AND($G$4=0,$D$4>=W_min,$B$4-D_dip>=Floor_q),1,0),IF(AND($D$4>=W_min,$B$4>=Pre_A),1,0))) -> 1 | F13: =CHOOSE(C13,$B$4+Proc_S,$B$4+Proc_Sk,$B$4+D_dL,$B$4-Cost_A) -> 712 | G13: =CHOOSE(C13,(1-Tech_share)*$C$4,(1-Tech_share)*$C$4,$C$4+D_dT,$C$4) -> 36.9 | H13: =CHOOSE(C13,$D$4-W_lost,$D$4,$D$4,$D$4+W_gain) -> 58 | I13: =CHOOSE(C13,$E$4,$E$4,$E$4+D_dE,$E$4+Close_A*(Ceil_E-$E$4)) -> 71 | J13: =CHOOSE(C13,1,1,$F$4,$F$4) -> 1 | K13: =E13*IF(D13<=2,1-J13,IF(D13=3,IF(AND(S13=0,H13>=W_min,F13-D_dip>=Floor_q),1,0),IF(AND(H13>=W_min,F13>=Pre_A),1,0))) -> 1 | L13: =CHOOSE(D13,F13+Proc_S,F13+Proc_Sk,F13+D_dL,F13-Cost_A) -> 676.63273 | M13: =CHOOSE(D13,(1-Tech_share)*G13,(1-Tech_share)*G13,G13+D_dT,G13) -> 71.534669 | N13: =CHOOSE(D13,H13-W_lost,H13,H13,H13+W_gain) -> 58 | O13: =CHOOSE(D13,I13,I13,I13+D_dE,I13+Close_A*(Ceil_E-I13)) -> 73.598331 | P13: =CHOOSE(D13,1,1,J13,J13) -> 1 | Q13: =IF(K13=1,IF(AND(M13>=Target_T,O13>=Target_E,L13>=Floor_q),1,0),0) -> 0 | R13: =IF(K13=1,L13-Floor_q,"") -> 326.63273 | S13: =CHOOSE(C13,$G$4,$G$4,1,$G$4) -> 0 | T13: =CHOOSE(D13,S13,S13,1,S13) -> 1
A14: S* | B14: A | C14: 2 | D14: 4 | E14: =IF(C14<=2,1-$F$4,IF(C14=3,IF(AND($G$4=0,$D$4>=W_min,$B$4-D_dip>=Floor_q),1,0),IF(AND($D$4>=W_min,$B$4>=Pre_A),1,0))) -> 1 | F14: =CHOOSE(C14,$B$4+Proc_S,$B$4+Proc_Sk,$B$4+D_dL,$B$4-Cost_A) -> 712 | G14: =CHOOSE(C14,(1-Tech_share)*$C$4,(1-Tech_share)*$C$4,$C$4+D_dT,$C$4) -> 36.9 | H14: =CHOOSE(C14,$D$4-W_lost,$D$4,$D$4,$D$4+W_gain) -> 58 | I14: =CHOOSE(C14,$E$4,$E$4,$E$4+D_dE,$E$4+Close_A*(Ceil_E-$E$4)) -> 71 | J14: =CHOOSE(C14,1,1,$F$4,$F$4) -> 1 | K14: =E14*IF(D14<=2,1-J14,IF(D14=3,IF(AND(S14=0,H14>=W_min,F14-D_dip>=Floor_q),1,0),IF(AND(H14>=W_min,F14>=Pre_A),1,0))) -> 1 | L14: =CHOOSE(D14,F14+Proc_S,F14+Proc_Sk,F14+D_dL,F14-Cost_A) -> 592 | M14: =CHOOSE(D14,(1-Tech_share)*G14,(1-Tech_share)*G14,G14+D_dT,G14) -> 36.9 | N14: =CHOOSE(D14,H14-W_lost,H14,H14,H14+W_gain) -> 59 | O14: =CHOOSE(D14,I14,I14,I14+D_dE,I14+Close_A*(Ceil_E-I14)) -> 78 | P14: =CHOOSE(D14,1,1,J14,J14) -> 1 | Q14: =IF(K14=1,IF(AND(M14>=Target_T,O14>=Target_E,L14>=Floor_q),1,0),0) -> 0 | R14: =IF(K14=1,L14-Floor_q,"") -> 242 | S14: =CHOOSE(C14,$G$4,$G$4,1,$G$4) -> 0 | T14: =CHOOSE(D14,S14,S14,1,S14) -> 0
A15: D | B15: S | C15: 3 | D15: 1 | E15: =IF(C15<=2,1-$F$4,IF(C15=3,IF(AND($G$4=0,$D$4>=W_min,$B$4-D_dip>=Floor_q),1,0),IF(AND($D$4>=W_min,$B$4>=Pre_A),1,0))) -> 1 | F15: =CHOOSE(C15,$B$4+Proc_S,$B$4+Proc_Sk,$B$4+D_dL,$B$4-Cost_A) -> 584.63273 | G15: =CHOOSE(C15,(1-Tech_share)*$C$4,(1-Tech_share)*$C$4,$C$4+D_dT,$C$4) -> 75.634669 | H15: =CHOOSE(C15,$D$4-W_lost,$D$4,$D$4,$D$4+W_gain) -> 58 | I15: =CHOOSE(C15,$E$4,$E$4,$E$4+D_dE,$E$4+Close_A*(Ceil_E-$E$4)) -> 73.598331 | J15: =CHOOSE(C15,1,1,$F$4,$F$4) -> 0 | K15: =E15*IF(D15<=2,1-J15,IF(D15=3,IF(AND(S15=0,H15>=W_min,F15-D_dip>=Floor_q),1,0),IF(AND(H15>=W_min,F15>=Pre_A),1,0))) -> 1 | L15: =CHOOSE(D15,F15+Proc_S,F15+Proc_Sk,F15+D_dL,F15-Cost_A) -> 696.63273 | M15: =CHOOSE(D15,(1-Tech_share)*G15,(1-Tech_share)*G15,G15+D_dT,G15) -> 68.071202 | N15: =CHOOSE(D15,H15-W_lost,H15,H15,H15+W_gain) -> 53 | O15: =CHOOSE(D15,I15,I15,I15+D_dE,I15+Close_A*(Ceil_E-I15)) -> 73.598331 | P15: =CHOOSE(D15,1,1,J15,J15) -> 1 | Q15: =IF(K15=1,IF(AND(M15>=Target_T,O15>=Target_E,L15>=Floor_q),1,0),0) -> 0 | R15: =IF(K15=1,L15-Floor_q,"") -> 346.63273 | S15: =CHOOSE(C15,$G$4,$G$4,1,$G$4) -> 1 | T15: =CHOOSE(D15,S15,S15,1,S15) -> 1
A16: D | B16: S* | C16: 3 | D16: 2 | E16: =IF(C16<=2,1-$F$4,IF(C16=3,IF(AND($G$4=0,$D$4>=W_min,$B$4-D_dip>=Floor_q),1,0),IF(AND($D$4>=W_min,$B$4>=Pre_A),1,0))) -> 1 | F16: =CHOOSE(C16,$B$4+Proc_S,$B$4+Proc_Sk,$B$4+D_dL,$B$4-Cost_A) -> 584.63273 | G16: =CHOOSE(C16,(1-Tech_share)*$C$4,(1-Tech_share)*$C$4,$C$4+D_dT,$C$4) -> 75.634669 | H16: =CHOOSE(C16,$D$4-W_lost,$D$4,$D$4,$D$4+W_gain) -> 58 | I16: =CHOOSE(C16,$E$4,$E$4,$E$4+D_dE,$E$4+Close_A*(Ceil_E-$E$4)) -> 73.598331 | J16: =CHOOSE(C16,1,1,$F$4,$F$4) -> 0 | K16: =E16*IF(D16<=2,1-J16,IF(D16=3,IF(AND(S16=0,H16>=W_min,F16-D_dip>=Floor_q),1,0),IF(AND(H16>=W_min,F16>=Pre_A),1,0))) -> 1 | L16: =CHOOSE(D16,F16+Proc_S,F16+Proc_Sk,F16+D_dL,F16-Cost_A) -> 676.63273 | M16: =CHOOSE(D16,(1-Tech_share)*G16,(1-Tech_share)*G16,G16+D_dT,G16) -> 68.071202 | N16: =CHOOSE(D16,H16-W_lost,H16,H16,H16+W_gain) -> 58 | O16: =CHOOSE(D16,I16,I16,I16+D_dE,I16+Close_A*(Ceil_E-I16)) -> 73.598331 | P16: =CHOOSE(D16,1,1,J16,J16) -> 1 | Q16: =IF(K16=1,IF(AND(M16>=Target_T,O16>=Target_E,L16>=Floor_q),1,0),0) -> 0 | R16: =IF(K16=1,L16-Floor_q,"") -> 326.63273 | S16: =CHOOSE(C16,$G$4,$G$4,1,$G$4) -> 1 | T16: =CHOOSE(D16,S16,S16,1,S16) -> 1
A17: D | B17: D | C17: 3 | D17: 3 | E17: =IF(C17<=2,1-$F$4,IF(C17=3,IF(AND($G$4=0,$D$4>=W_min,$B$4-D_dip>=Floor_q),1,0),IF(AND($D$4>=W_min,$B$4>=Pre_A),1,0))) -> 1 | F17: =CHOOSE(C17,$B$4+Proc_S,$B$4+Proc_Sk,$B$4+D_dL,$B$4-Cost_A) -> 584.63273 | G17: =CHOOSE(C17,(1-Tech_share)*$C$4,(1-Tech_share)*$C$4,$C$4+D_dT,$C$4) -> 75.634669 | H17: =CHOOSE(C17,$D$4-W_lost,$D$4,$D$4,$D$4+W_gain) -> 58 | I17: =CHOOSE(C17,$E$4,$E$4,$E$4+D_dE,$E$4+Close_A*(Ceil_E-$E$4)) -> 73.598331 | J17: =CHOOSE(C17,1,1,$F$4,$F$4) -> 0 | K17: =E17*IF(D17<=2,1-J17,IF(D17=3,IF(AND(S17=0,H17>=W_min,F17-D_dip>=Floor_q),1,0),IF(AND(H17>=W_min,F17>=Pre_A),1,0))) -> 0 | L17: =CHOOSE(D17,F17+Proc_S,F17+Proc_Sk,F17+D_dL,F17-Cost_A) -> 549.26546 | M17: =CHOOSE(D17,(1-Tech_share)*G17,(1-Tech_share)*G17,G17+D_dT,G17) -> 110.26934 | N17: =CHOOSE(D17,H17-W_lost,H17,H17,H17+W_gain) -> 58 | O17: =CHOOSE(D17,I17,I17,I17+D_dE,I17+Close_A*(Ceil_E-I17)) -> 76.196662 | P17: =CHOOSE(D17,1,1,J17,J17) -> 0 | Q17: =IF(K17=1,IF(AND(M17>=Target_T,O17>=Target_E,L17>=Floor_q),1,0),0) -> 0 | R17: =IF(K17=1,L17-Floor_q,"") | S17: =CHOOSE(C17,$G$4,$G$4,1,$G$4) -> 1 | T17: =CHOOSE(D17,S17,S17,1,S17) -> 1
A18: D | B18: A | C18: 3 | D18: 4 | E18: =IF(C18<=2,1-$F$4,IF(C18=3,IF(AND($G$4=0,$D$4>=W_min,$B$4-D_dip>=Floor_q),1,0),IF(AND($D$4>=W_min,$B$4>=Pre_A),1,0))) -> 1 | F18: =CHOOSE(C18,$B$4+Proc_S,$B$4+Proc_Sk,$B$4+D_dL,$B$4-Cost_A) -> 584.63273 | G18: =CHOOSE(C18,(1-Tech_share)*$C$4,(1-Tech_share)*$C$4,$C$4+D_dT,$C$4) -> 75.634669 | H18: =CHOOSE(C18,$D$4-W_lost,$D$4,$D$4,$D$4+W_gain) -> 58 | I18: =CHOOSE(C18,$E$4,$E$4,$E$4+D_dE,$E$4+Close_A*(Ceil_E-$E$4)) -> 73.598331 | J18: =CHOOSE(C18,1,1,$F$4,$F$4) -> 0 | K18: =E18*IF(D18<=2,1-J18,IF(D18=3,IF(AND(S18=0,H18>=W_min,F18-D_dip>=Floor_q),1,0),IF(AND(H18>=W_min,F18>=Pre_A),1,0))) -> 1 | L18: =CHOOSE(D18,F18+Proc_S,F18+Proc_Sk,F18+D_dL,F18-Cost_A) -> 464.63273 | M18: =CHOOSE(D18,(1-Tech_share)*G18,(1-Tech_share)*G18,G18+D_dT,G18) -> 75.634669 | N18: =CHOOSE(D18,H18-W_lost,H18,H18,H18+W_gain) -> 59 | O18: =CHOOSE(D18,I18,I18,I18+D_dE,I18+Close_A*(Ceil_E-I18)) -> 79.299165 | P18: =CHOOSE(D18,1,1,J18,J18) -> 0 | Q18: =IF(K18=1,IF(AND(M18>=Target_T,O18>=Target_E,L18>=Floor_q),1,0),0) -> 0 | R18: =IF(K18=1,L18-Floor_q,"") -> 114.63273 | S18: =CHOOSE(C18,$G$4,$G$4,1,$G$4) -> 1 | T18: =CHOOSE(D18,S18,S18,1,S18) -> 1
... A22: A | B22: A | C22: 4 | D22: 4 | E22: =IF(C22<=2,1-$F$4,IF(C22=3,IF(AND($G$4=0,$D$4>=W_min,$B$4-D_dip>=Floor_q),1,0),IF(AND($D$4>=W_min,$B$4>=Pre_A),1,0))) -> 1 | F22: =CHOOSE(C22,$B$4+Proc_S,$B$4+Proc_Sk,$B$4+D_dL,$B$4-Cost_A) -> 500 | G22: =CHOOSE(C22,(1-Tech_share)*$C$4,(1-Tech_share)*$C$4,$C$4+D_dT,$C$4) -> 41 | H22: =CHOOSE(C22,$D$4-W_lost,$D$4,$D$4,$D$4+W_gain) -> 59 | I22: =CHOOSE(C22,$E$4,$E$4,$E$4+D_dE,$E$4+Close_A*(Ceil_E-$E$4)) -> 78 | J22: =CHOOSE(C22,1,1,$F$4,$F$4) -> 0 | K22: =E22*IF(D22<=2,1-J22,IF(D22=3,IF(AND(S22=0,H22>=W_min,F22-D_dip>=Floor_q),1,0),IF(AND(H22>=W_min,F22>=Pre_A),1,0))) -> 1 | L22: =CHOOSE(D22,F22+Proc_S,F22+Proc_Sk,F22+D_dL,F22-Cost_A) -> 380 | M22: =CHOOSE(D22,(1-Tech_share)*G22,(1-Tech_share)*G22,G22+D_dT,G22) -> 41 | N22: =CHOOSE(D22,H22-W_lost,H22,H22,H22+W_gain) -> 60 | O22: =CHOOSE(D22,I22,I22,I22+D_dE,I22+Close_A*(Ceil_E-I22)) -> 81.5 | P22: =CHOOSE(D22,1,1,J22,J22) -> 0 | Q22: =IF(K22=1,IF(AND(M22>=Target_T,O22>=Target_E,L22>=Floor_q),1,0),0) -> 0 | R22: =IF(K22=1,L22-Floor_q,"") -> 30 | S22: =CHOOSE(C22,$G$4,$G$4,1,$G$4) -> 0 | T22: =CHOOSE(D22,S22,S22,1,S22) -> 0
A25: Two-move programs that pass every seam | B25: =SUM(K7:K22) -> 9
A26: Programs that reach the target (technology >= 70 and efficiency >= 80) | B26: =SUM(Q7:Q22) -> 1 | C26: Automate, then build: the round's efficiency gain comes first and the build adds its own; built first, the round closes half of a smaller gap (Section 6.6; Theorem 6.2(iii)).
A27: Its liquidity | B27: =SUMIFS(L7:L22,Q7:Q22,1) -> 464.63273
A28: Its technology | B28: =SUMIFS(M7:M22,Q7:Q22,1) -> 75.634669
A29: Its headroom over the floor at the build's low point | B29: =SUMIFS(F7:F22,Q7:Q22,1)-D_dip-Floor_q -> 11.917941
A30: Its efficiency | B30: =SUMIFS(O7:O22,Q7:Q22,1) -> 80.598331
A31: The other order, D then A: efficiency | B31: =O18 -> 79.299165
A32: Section 6.5: sell keeping the engineers, two automation rounds, then the build (Proposition 6.5) | B32: Liquidity | C32: Technology | D32: Workforce | E32: Efficiency
A33: Today | B33: =B4 -> 620 | C33: =C4 -> 41 | D33: =D4 -> 58 | E33: =E4 -> 71
A34: After the sale, engineers kept | B34: =B33+Proc_Sk -> 712 | C34: =(1-Tech_share)*C33 -> 36.9 | D34: =D33 -> 58 | E34: =E33 -> 71
A35: After one automation round | B35: =B34-Cost_A -> 592 | C35: =C34 -> 36.9 | D35: =D34+W_gain -> 59 | E35: =E34+Close_A*(Ceil_E-E34) -> 78
A36: After a second round | B36: =B35-Cost_A -> 472 | C36: =C35 -> 36.9 | D36: =D35+W_gain -> 60 | E36: =E35+Close_A*(Ceil_E-E35) -> 81.5
A37: After the build (floor ignored) | B37: =B36+D_dL -> 436.63273 | C37: =C36+D_dT -> 71.534669 | D37: =D36 -> 60 | E37: =E36+D_dE -> 84.098331
A38: The build's low point on the way | B38: =B36-D_dip -> 333.91794
A39: Below the floor at the low point by | B39: =Floor_q-B38 -> 16.082059
A40: Above the floor at the end by | B40: =B37-Floor_q -> 86.632729
A41: A step that is not feasibility-preserving: no arithmetic on the end points certifies the path (Proposition 6.5).

Sheet Playbook
A1: Test the playbook: one automation round a year, savings paid out, recycled, or short of plan (Worked Example 6.1, Steps 2-4; Table 6.4; Equation 6.2; Theorem 6.3; AXIOM Lab 1.6, step 3)
A2: Round k is taken at the start of year k if liquidity is at least $470 million and workforce capability at least 55; its cost and the year's savings land by the year's end. Columns run every round, as if no precondition bound; 'Round k runs' applies Equation 6.2.
A3: Case | B3: Savings paid out | C3: Recycled, as designed | D3: Recycled, 1-point shortfall | E3: Recycled, 2-point shortfall
A4: Share of the savings kept in liquidity | B4: 0 | C4: 1 | D4: 1 | E4: 1
A5: Efficiency shortfall a round (points) | B5: 0 | C5: 0 | D5: 1 | E5: 2
A7: Rounds that run, of 40 | B7: =SUM(B34:B73) -> 2 | C7: =SUM(J34:J73) -> 40 | D7: =SUM(R34:R73) -> 40 | E7: =SUM(Z34:Z73) -> 4
A8: The round whose precondition fails | B8: =IF(B7=40,"none in 40 years",B7+1) -> 3 | C8: =IF(C7=40,"none in 40 years",C7+1) -> none in 40 years | D8: =IF(D7=40,"none in 40 years",D7+1) -> none in 40 years | E8: =IF(E7=40,"none in 40 years",E7+1) -> 5
A9: First year the savings exceed the round's cost | B9: =IF(COUNTIF(D34:D73,">"&Cost_A)=0,"never",_xlfn.MINIFS($A$34:$A$73,D34:D73,">"&Cost_A)) -> never | C9: =IF(COUNTIF(L34:L73,">"&Cost_A)=0,"never",_xlfn.MINIFS($A$34:$A$73,L34:L73,">"&Cost_A)) -> 3 | D9: =IF(COUNTIF(T34:T73,">"&Cost_A)=0,"never",_xlfn.MINIFS($A$34:$A$73,T34:T73,">"&Cost_A)) -> never | E9: =IF(COUNTIF(AB34:AB73,">"&Cost_A)=0,"never",_xlfn.MINIFS($A$34:$A$73,AB34:AB73,">"&Cost_A)) -> never
A10: Lowest liquidity at a year end while the playbook runs | B10: =_xlfn.MINIFS(F34:F73,B34:B73,1) -> 380 | C10: =_xlfn.MINIFS(N34:N73,J34:J73,1) -> 555 | D10: =_xlfn.MINIFS(V34:V73,R34:R73,1) -> 500 | E10: =_xlfn.MINIFS(AD34:AD73,Z34:Z73,1) -> 446.25
A11: Liquidity at the end of year 40, had every round run | B11: =F73 -> -4180 | C11: =N73 -> 1280 | D11: =V73 -> 500 | E11: =AD73 -> -280
A12: Savings less the round's cost in year 40, had every round run | B12: =E73 -> -120 | C12: =M73 -> 20 | D12: =U73 -> -1.0913936e-10 | E12: =AC73 -> -20
A13: Liquidity today that lets all 40 rounds run | B13: =I73 -> 5150 | C13: =Q73 -> 535 | D13: =Y73 -> 590 | E13: =AG73 -> 1350
A14: Increase from round 39 to round 40 | B14: =I73-I72 -> 120 | C14: =Q73-Q72 -> 0 | D14: =Y73-Y72 -> 2.1827873e-10 | E14: =AG73-AG72 -> 20
A15: Sustainable core: empty, or the liquidity today it starts from | B15: =IF(B14>0.000001,"empty","from "&TEXT(B13,"0.00")) -> empty | C15: =IF(C14>0.000001,"empty","from "&TEXT(C13,"0.00")) -> from 535.00 | D15: =IF(D14>0.000001,"empty","from "&TEXT(D13,"0.00")) -> from 590.00 | E15: =IF(E14>0.000001,"empty","from "&TEXT(E13,"0.00")) -> empty
A16: Meridian's margin over the liquidity 40 rounds need | B16: =Liq_today-B13 -> -4530 | C16: =Liq_today-C13 -> 85 | D16: =Liq_today-D13 -> 30 | E16: =Liq_today-E13 -> -730
A18: Table 6.4: recycled, as designed | B18: 0 | C18: 1 | D18: 2 | E18: 3 | F18: 4 | G18: 5 | H18: 6
A19: Efficiency (index) | B19: =K33 -> 71 | C19: =K34 -> 78 | D19: =K35 -> 81.5 | E19: =K36 -> 83.25 | F19: =K37 -> 84.125 | G19: =K38 -> 84.5625 | H19: =K39 -> 84.78125
A20: Savings this year | B20: -- | C20: =L34 -> 70 | D20: =L35 -> 105 | E20: =L36 -> 122.5 | F20: =L37 -> 131.25 | G20: =L38 -> 135.625 | H20: =L39 -> 137.8125
A21: Savings less the round's cost | B21: -- | C21: =M34 -> -50 | D21: =M35 -> -15 | E21: =M36 -> 2.5 | F21: =M37 -> 11.25 | G21: =M38 -> 15.625 | H21: =M39 -> 17.8125
A22: Liquidity at year end | B22: =N33 -> 620 | C22: =N34 -> 570 | D22: =N35 -> 555 | E22: =N36 -> 557.5 | F22: =N37 -> 568.75 | G22: =N38 -> 584.375 | H22: =N39 -> 602.1875
A24: Liquidity today that lets k rounds run (Equation 6.2) | B24: k = 1 | C24: k = 2 | D24: k = 3 | E24: k = 4 | F24: k = 5 | G24: k = 6 | H24: k = 7 | I24: k = 8 | J24: k = 9 | K24: k = 10
A25: Savings paid out | B25: =I34 -> 470 | C25: =I35 -> 590 | D25: =I36 -> 710 | E25: =I37 -> 830 | F25: =I38 -> 950 | G25: =I39 -> 1070 | H25: =I40 -> 1190 | I25: =I41 -> 1310 | J25: =I42 -> 1430 | K25: =I43 -> 1550
A26: Recycled, as designed | B26: =Q34 -> 470 | C26: =Q35 -> 520 | D26: =Q36 -> 535 | E26: =Q37 -> 535 | F26: =Q38 -> 535 | G26: =Q39 -> 535 | H26: =Q40 -> 535 | I26: =Q41 -> 535 | J26: =Q42 -> 535 | K26: =Q43 -> 535
A27: Recycled, 1-point shortfall | B27: =Y34 -> 470 | C27: =Y35 -> 530 | D27: =Y36 -> 560 | E27: =Y37 -> 575 | F27: =Y38 -> 582.5 | G27: =Y39 -> 586.25 | H27: =Y40 -> 588.125 | I27: =Y41 -> 589.0625 | J27: =Y42 -> 589.53125 | K27: =Y43 -> 589.76562
A28: Recycled, 2-point shortfall | B28: =AG34 -> 470 | C28: =AG35 -> 540 | D28: =AG36 -> 585 | E28: =AG37 -> 617.5 | F28: =AG38 -> 643.75 | G28: =AG39 -> 666.875 | H28: =AG40 -> 688.4375 | I28: =AG41 -> 709.21875 | J28: =AG42 -> 729.60938 | K28: =AG43 -> 749.80469
A29: Paid out: 470 + 120(k - 1), rising without bound, so no starting liquidity supports every round and the sustainable core is empty. Recycled: the requirement settles at $535 million after round 3.
A32: Year | B32: Savings paid out: round k runs | C32: Efficiency | D32: Savings | E32: Savings less cost | F32: Liquidity at year end | G32: Workforce | H32: Drop below today | I32: Liquidity today round k needs | J32: Recycled, as designed: round k runs | K32: Efficiency | L32: Savings | M32: Savings less cost | N32: Liquidity at year end | O32: Workforce | P32: Drop below today | Q32: Liquidity today round k needs | R32: Recycled, 1-point shortfall: round k runs | S32: Efficiency | T32: Savings | U32: Savings less cost | V32: Liquidity at year end | W32: Workforce | X32: Drop below today | Y32: Liquidity today round k needs | Z32: Recycled, 2-point shortfall: round k runs | AA32: Efficiency | AB32: Savings | AC32: Savings less cost | AD32: Liquidity at year end | AE32: Workforce | AF32: Drop below today | AG32: Liquidity today round k needs
A33: 0 | B33: 1 | C33: =Eff_today -> 71 | F33: =Liq_today -> 620 | G33: =W_today -> 58 | H33: =Liq_today-F33 -> 0 | J33: 1 | K33: =Eff_today -> 71 | N33: =Liq_today -> 620 | O33: =W_today -> 58 | P33: =Liq_today-N33 -> 0 | R33: 1 | S33: =Eff_today -> 71 | V33: =Liq_today -> 620 | W33: =W_today -> 58 | X33: =Liq_today-V33 -> 0 | Z33: 1 | AA33: =Eff_today -> 71 | AD33: =Liq_today -> 620 | AE33: =W_today -> 58 | AF33: =Liq_today-AD33 -> 0
A34: 1 | B34: =IF(AND(B33=1,F33>=Pre_A,G33>=W_min),1,0) -> 1 | C34: =C33+Close_A*(Ceil_E-C33)-$B$5 -> 78 | D34: =$B$4*Value_pt*(C34-Eff_today) -> 0 | E34: =D34-Cost_A -> -120 | F34: =F33+E34 -> 500 | G34: =G33+W_gain -> 59 | H34: =Liq_today-F34 -> 120 | I34: =Pre_A+MAX(H33:H33) -> 470 | J34: =IF(AND(J33=1,N33>=Pre_A,O33>=W_min),1,0) -> 1 | K34: =K33+Close_A*(Ceil_E-K33)-$C$5 -> 78 | L34: =$C$4*Value_pt*(K34-Eff_today) -> 70 | M34: =L34-Cost_A -> -50 | N34: =N33+M34 -> 570 | O34: =O33+W_gain -> 59 | P34: =Liq_today-N34 -> 50 | Q34: =Pre_A+MAX(P33:P33) -> 470 | R34: =IF(AND(R33=1,V33>=Pre_A,W33>=W_min),1,0) -> 1 | S34: =S33+Close_A*(Ceil_E-S33)-$D$5 -> 77 | T34: =$D$4*Value_pt*(S34-Eff_today) -> 60 | U34: =T34-Cost_A -> -60 | V34: =V33+U34 -> 560 | W34: =W33+W_gain -> 59 | X34: =Liq_today-V34 -> 60 | Y34: =Pre_A+MAX(X33:X33) -> 470 | Z34: =IF(AND(Z33=1,AD33>=Pre_A,AE33>=W_min),1,0) -> 1 | AA34: =AA33+Close_A*(Ceil_E-AA33)-$E$5 -> 76 | AB34: =$E$4*Value_pt*(AA34-Eff_today) -> 50 | AC34: =AB34-Cost_A -> -70 | AD34: =AD33+AC34 -> 550 | AE34: =AE33+W_gain -> 59 | AF34: =Liq_today-AD34 -> 70 | AG34: =Pre_A+MAX(AF33:AF33) -> 470
A35: 2 | B35: =IF(AND(B34=1,F34>=Pre_A,G34>=W_min),1,0) -> 1 | C35: =C34+Close_A*(Ceil_E-C34)-$B$5 -> 81.5 | D35: =$B$4*Value_pt*(C35-Eff_today) -> 0 | E35: =D35-Cost_A -> -120 | F35: =F34+E35 -> 380 | G35: =G34+W_gain -> 60 | H35: =Liq_today-F35 -> 240 | I35: =Pre_A+MAX(H33:H34) -> 590 | J35: =IF(AND(J34=1,N34>=Pre_A,O34>=W_min),1,0) -> 1 | K35: =K34+Close_A*(Ceil_E-K34)-$C$5 -> 81.5 | L35: =$C$4*Value_pt*(K35-Eff_today) -> 105 | M35: =L35-Cost_A -> -15 | N35: =N34+M35 -> 555 | O35: =O34+W_gain -> 60 | P35: =Liq_today-N35 -> 65 | Q35: =Pre_A+MAX(P33:P34) -> 520 | R35: =IF(AND(R34=1,V34>=Pre_A,W34>=W_min),1,0) -> 1 | S35: =S34+Close_A*(Ceil_E-S34)-$D$5 -> 80 | T35: =$D$4*Value_pt*(S35-Eff_today) -> 90 | U35: =T35-Cost_A -> -30 | V35: =V34+U35 -> 530 | W35: =W34+W_gain -> 60 | X35: =Liq_today-V35 -> 90 | Y35: =Pre_A+MAX(X33:X34) -> 530 | Z35: =IF(AND(Z34=1,AD34>=Pre_A,AE34>=W_min),1,0) -> 1 | AA35: =AA34+Close_A*(Ceil_E-AA34)-$E$5 -> 78.5 | AB35: =$E$4*Value_pt*(AA35-Eff_today) -> 75 | AC35: =AB35-Cost_A -> -45 | AD35: =AD34+AC35 -> 505 | AE35: =AE34+W_gain -> 60 | AF35: =Liq_today-AD35 -> 115 | AG35: =Pre_A+MAX(AF33:AF34) -> 540
A36: 3 | B36: =IF(AND(B35=1,F35>=Pre_A,G35>=W_min),1,0) -> 0 | C36: =C35+Close_A*(Ceil_E-C35)-$B$5 -> 83.25 | D36: =$B$4*Value_pt*(C36-Eff_today) -> 0 | E36: =D36-Cost_A -> -120 | F36: =F35+E36 -> 260 | G36: =G35+W_gain -> 61 | H36: =Liq_today-F36 -> 360 | I36: =Pre_A+MAX(H33:H35) -> 710 | J36: =IF(AND(J35=1,N35>=Pre_A,O35>=W_min),1,0) -> 1 | K36: =K35+Close_A*(Ceil_E-K35)-$C$5 -> 83.25 | L36: =$C$4*Value_pt*(K36-Eff_today) -> 122.5 | M36: =L36-Cost_A -> 2.5 | N36: =N35+M36 -> 557.5 | O36: =O35+W_gain -> 61 | P36: =Liq_today-N36 -> 62.5 | Q36: =Pre_A+MAX(P33:P35) -> 535 | R36: =IF(AND(R35=1,V35>=Pre_A,W35>=W_min),1,0) -> 1 | S36: =S35+Close_A*(Ceil_E-S35)-$D$5 -> 81.5 | T36: =$D$4*Value_pt*(S36-Eff_today) -> 105 | U36: =T36-Cost_A -> -15 | V36: =V35+U36 -> 515 | W36: =W35+W_gain -> 61 | X36: =Liq_today-V36 -> 105 | Y36: =Pre_A+MAX(X33:X35) -> 560 | Z36: =IF(AND(Z35=1,AD35>=Pre_A,AE35>=W_min),1,0) -> 1 | AA36: =AA35+Close_A*(Ceil_E-AA35)-$E$5 -> 79.75 | AB36: =$E$4*Value_pt*(AA36-Eff_today) -> 87.5 | AC36: =AB36-Cost_A -> -32.5 | AD36: =AD35+AC36 -> 472.5 | AE36: =AE35+W_gain -> 61 | AF36: =Liq_today-AD36 -> 147.5 | AG36: =Pre_A+MAX(AF33:AF35) -> 585
A37: 4 | B37: =IF(AND(B36=1,F36>=Pre_A,G36>=W_min),1,0) -> 0 | C37: =C36+Close_A*(Ceil_E-C36)-$B$5 -> 84.125 | D37: =$B$4*Value_pt*(C37-Eff_today) -> 0 | E37: =D37-Cost_A -> -120 | F37: =F36+E37 -> 140 | G37: =G36+W_gain -> 62 | H37: =Liq_today-F37 -> 480 | I37: =Pre_A+MAX(H33:H36) -> 830 | J37: =IF(AND(J36=1,N36>=Pre_A,O36>=W_min),1,0) -> 1 | K37: =K36+Close_A*(Ceil_E-K36)-$C$5 -> 84.125 | L37: =$C$4*Value_pt*(K37-Eff_today) -> 131.25 | M37: =L37-Cost_A -> 11.25 | N37: =N36+M37 -> 568.75 | O37: =O36+W_gain -> 62 | P37: =Liq_today-N37 -> 51.25 | Q37: =Pre_A+MAX(P33:P36) -> 535 | R37: =IF(AND(R36=1,V36>=Pre_A,W36>=W_min),1,0) -> 1 | S37: =S36+Close_A*(Ceil_E-S36)-$D$5 -> 82.25 | T37: =$D$4*Value_pt*(S37-Eff_today) -> 112.5 | U37: =T37-Cost_A -> -7.5 | V37: =V36+U37 -> 507.5 | W37: =W36+W_gain -> 62 | X37: =Liq_today-V37 -> 112.5 | Y37: =Pre_A+MAX(X33:X36) -> 575 | Z37: =IF(AND(Z36=1,AD36>=Pre_A,AE36>=W_min),1,0) -> 1 | AA37: =AA36+Close_A*(Ceil_E-AA36)-$E$5 -> 80.375 | AB37: =$E$4*Value_pt*(AA37-Eff_today) -> 93.75 | AC37: =AB37-Cost_A -> -26.25 | AD37: =AD36+AC37 -> 446.25 | AE37: =AE36+W_gain -> 62 | AF37: =Liq_today-AD37 -> 173.75 | AG37: =Pre_A+MAX(AF33:AF36) -> 617.5
A38: 5 | B38: =IF(AND(B37=1,F37>=Pre_A,G37>=W_min),1,0) -> 0 | C38: =C37+Close_A*(Ceil_E-C37)-$B$5 -> 84.5625 | D38: =$B$4*Value_pt*(C38-Eff_today) -> 0 | E38: =D38-Cost_A -> -120 | F38: =F37+E38 -> 20 | G38: =G37+W_gain -> 63 | H38: =Liq_today-F38 -> 600 | I38: =Pre_A+MAX(H33:H37) -> 950 | J38: =IF(AND(J37=1,N37>=Pre_A,O37>=W_min),1,0) -> 1 | K38: =K37+Close_A*(Ceil_E-K37)-$C$5 -> 84.5625 | L38: =$C$4*Value_pt*(K38-Eff_today) -> 135.625 | M38: =L38-Cost_A -> 15.625 | N38: =N37+M38 -> 584.375 | O38: =O37+W_gain -> 63 | P38: =Liq_today-N38 -> 35.625 | Q38: =Pre_A+MAX(P33:P37) -> 535 | R38: =IF(AND(R37=1,V37>=Pre_A,W37>=W_min),1,0) -> 1 | S38: =S37+Close_A*(Ceil_E-S37)-$D$5 -> 82.625 | T38: =$D$4*Value_pt*(S38-Eff_today) -> 116.25 | U38: =T38-Cost_A -> -3.75 | V38: =V37+U38 -> 503.75 | W38: =W37+W_gain -> 63 | X38: =Liq_today-V38 -> 116.25 | Y38: =Pre_A+MAX(X33:X37) -> 582.5 | Z38: =IF(AND(Z37=1,AD37>=Pre_A,AE37>=W_min),1,0) -> 0 | AA38: =AA37+Close_A*(Ceil_E-AA37)-$E$5 -> 80.6875 | AB38: =$E$4*Value_pt*(AA38-Eff_today) -> 96.875 | AC38: =AB38-Cost_A -> -23.125 | AD38: =AD37+AC38 -> 423.125 | AE38: =AE37+W_gain -> 63 | AF38: =Liq_today-AD38 -> 196.875 | AG38: =Pre_A+MAX(AF33:AF37) -> 643.75
A39: 6 | B39: =IF(AND(B38=1,F38>=Pre_A,G38>=W_min),1,0) -> 0 | C39: =C38+Close_A*(Ceil_E-C38)-$B$5 -> 84.78125 | D39: =$B$4*Value_pt*(C39-Eff_today) -> 0 | E39: =D39-Cost_A -> -120 | F39: =F38+E39 -> -100 | G39: =G38+W_gain -> 64 | H39: =Liq_today-F39 -> 720 | I39: =Pre_A+MAX(H33:H38) -> 1070 | J39: =IF(AND(J38=1,N38>=Pre_A,O38>=W_min),1,0) -> 1 | K39: =K38+Close_A*(Ceil_E-K38)-$C$5 -> 84.78125 | L39: =$C$4*Value_pt*(K39-Eff_today) -> 137.8125 | M39: =L39-Cost_A -> 17.8125 | N39: =N38+M39 -> 602.1875 | O39: =O38+W_gain -> 64 | P39: =Liq_today-N39 -> 17.8125 | Q39: =Pre_A+MAX(P33:P38) -> 535 | R39: =IF(AND(R38=1,V38>=Pre_A,W38>=W_min),1,0) -> 1 | S39: =S38+Close_A*(Ceil_E-S38)-$D$5 -> 82.8125 | T39: =$D$4*Value_pt*(S39-Eff_today) -> 118.125 | U39: =T39-Cost_A -> -1.875 | V39: =V38+U39 -> 501.875 | W39: =W38+W_gain -> 64 | X39: =Liq_today-V39 -> 118.125 | Y39: =Pre_A+MAX(X33:X38) -> 586.25 | Z39: =IF(AND(Z38=1,AD38>=Pre_A,AE38>=W_min),1,0) -> 0 | AA39: =AA38+Close_A*(Ceil_E-AA38)-$E$5 -> 80.84375 | AB39: =$E$4*Value_pt*(AA39-Eff_today) -> 98.4375 | AC39: =AB39-Cost_A -> -21.5625 | AD39: =AD38+AC39 -> 401.5625 | AE39: =AE38+W_gain -> 64 | AF39: =Liq_today-AD39 -> 218.4375 | AG39: =Pre_A+MAX(AF33:AF38) -> 666.875
A40: 7 | B40: =IF(AND(B39=1,F39>=Pre_A,G39>=W_min),1,0) -> 0 | C40: =C39+Close_A*(Ceil_E-C39)-$B$5 -> 84.890625 | D40: =$B$4*Value_pt*(C40-Eff_today) -> 0 | E40: =D40-Cost_A -> -120 | F40: =F39+E40 -> -220 | G40: =G39+W_gain -> 65 | H40: =Liq_today-F40 -> 840 | I40: =Pre_A+MAX(H33:H39) -> 1190 | J40: =IF(AND(J39=1,N39>=Pre_A,O39>=W_min),1,0) -> 1 | K40: =K39+Close_A*(Ceil_E-K39)-$C$5 -> 84.890625 | L40: =$C$4*Value_pt*(K40-Eff_today) -> 138.90625 | M40: =L40-Cost_A -> 18.90625 | N40: =N39+M40 -> 621.09375 | O40: =O39+W_gain -> 65 | P40: =Liq_today-N40 -> -1.09375 | Q40: =Pre_A+MAX(P33:P39) -> 535 | R40: =IF(AND(R39=1,V39>=Pre_A,W39>=W_min),1,0) -> 1 | S40: =S39+Close_A*(Ceil_E-S39)-$D$5 -> 82.90625 | T40: =$D$4*Value_pt*(S40-Eff_today) -> 119.0625 | U40: =T40-Cost_A -> -0.9375 | V40: =V39+U40 -> 500.9375 | W40: =W39+W_gain -> 65 | X40: =Liq_today-V40 -> 119.0625 | Y40: =Pre_A+MAX(X33:X39) -> 588.125 | Z40: =IF(AND(Z39=1,AD39>=Pre_A,AE39>=W_min),1,0) -> 0 | AA40: =AA39+Close_A*(Ceil_E-AA39)-$E$5 -> 80.921875 | AB40: =$E$4*Value_pt*(AA40-Eff_today) -> 99.21875 | AC40: =AB40-Cost_A -> -20.78125 | AD40: =AD39+AC40 -> 380.78125 | AE40: =AE39+W_gain -> 65 | AF40: =Liq_today-AD40 -> 239.21875 | AG40: =Pre_A+MAX(AF33:AF39) -> 688.4375
A41: 8 | B41: =IF(AND(B40=1,F40>=Pre_A,G40>=W_min),1,0) -> 0 | C41: =C40+Close_A*(Ceil_E-C40)-$B$5 -> 84.945312 | D41: =$B$4*Value_pt*(C41-Eff_today) -> 0 | E41: =D41-Cost_A -> -120 | F41: =F40+E41 -> -340 | G41: =G40+W_gain -> 66 | H41: =Liq_today-F41 -> 960 | I41: =Pre_A+MAX(H33:H40) -> 1310 | J41: =IF(AND(J40=1,N40>=Pre_A,O40>=W_min),1,0) -> 1 | K41: =K40+Close_A*(Ceil_E-K40)-$C$5 -> 84.945312 | L41: =$C$4*Value_pt*(K41-Eff_today) -> 139.45312 | M41: =L41-Cost_A -> 19.453125 | N41: =N40+M41 -> 640.54688 | O41: =O40+W_gain -> 66 | P41: =Liq_today-N41 -> -20.546875 | Q41: =Pre_A+MAX(P33:P40) -> 535 | R41: =IF(AND(R40=1,V40>=Pre_A,W40>=W_min),1,0) -> 1 | S41: =S40+Close_A*(Ceil_E-S40)-$D$5 -> 82.953125 | T41: =$D$4*Value_pt*(S41-Eff_today) -> 119.53125 | U41: =T41-Cost_A -> -0.46875 | V41: =V40+U41 -> 500.46875 | W41: =W40+W_gain -> 66 | X41: =Liq_today-V41 -> 119.53125 | Y41: =Pre_A+MAX(X33:X40) -> 589.0625 | Z41: =IF(AND(Z40=1,AD40>=Pre_A,AE40>=W_min),1,0) -> 0 | AA41: =AA40+Close_A*(Ceil_E-AA40)-$E$5 -> 80.960938 | AB41: =$E$4*Value_pt*(AA41-Eff_today) -> 99.609375 | AC41: =AB41-Cost_A -> -20.390625 | AD41: =AD40+AC41 -> 360.39062 | AE41: =AE40+W_gain -> 66 | AF41: =Liq_today-AD41 -> 259.60938 | AG41: =Pre_A+MAX(AF33:AF40) -> 709.21875
A42: 9 | B42: =IF(AND(B41=1,F41>=Pre_A,G41>=W_min),1,0) -> 0 | C42: =C41+Close_A*(Ceil_E-C41)-$B$5 -> 84.972656 | D42: =$B$4*Value_pt*(C42-Eff_today) -> 0 | E42: =D42-Cost_A -> -120 | F42: =F41+E42 -> -460 | G42: =G41+W_gain -> 67 | H42: =Liq_today-F42 -> 1080 | I42: =Pre_A+MAX(H33:H41) -> 1430 | J42: =IF(AND(J41=1,N41>=Pre_A,O41>=W_min),1,0) -> 1 | K42: =K41+Close_A*(Ceil_E-K41)-$C$5 -> 84.972656 | L42: =$C$4*Value_pt*(K42-Eff_today) -> 139.72656 | M42: =L42-Cost_A -> 19.726562 | N42: =N41+M42 -> 660.27344 | O42: =O41+W_gain -> 67 | P42: =Liq_today-N42 -> -40.273438 | Q42: =Pre_A+MAX(P33:P41) -> 535 | R42: =IF(AND(R41=1,V41>=Pre_A,W41>=W_min),1,0) -> 1 | S42: =S41+Close_A*(Ceil_E-S41)-$D$5 -> 82.976562 | T42: =$D$4*Value_pt*(S42-Eff_today) -> 119.76562 | U42: =T42-Cost_A -> -0.234375 | V42: =V41+U42 -> 500.23438 | W42: =W41+W_gain -> 67 | X42: =Liq_today-V42 -> 119.76562 | Y42: =Pre_A+MAX(X33:X41) -> 589.53125 | Z42: =IF(AND(Z41=1,AD41>=Pre_A,AE41>=W_min),1,0) -> 0 | AA42: =AA41+Close_A*(Ceil_E-AA41)-$E$5 -> 80.980469 | AB42: =$E$4*Value_pt*(AA42-Eff_today) -> 99.804688 | AC42: =AB42-Cost_A -> -20.195312 | AD42: =AD41+AC42 -> 340.19531 | AE42: =AE41+W_gain -> 67 | AF42: =Liq_today-AD42 -> 279.80469 | AG42: =Pre_A+MAX(AF33:AF41) -> 729.60938
A43: 10 | B43: =IF(AND(B42=1,F42>=Pre_A,G42>=W_min),1,0) -> 0 | C43: =C42+Close_A*(Ceil_E-C42)-$B$5 -> 84.986328 | D43: =$B$4*Value_pt*(C43-Eff_today) -> 0 | E43: =D43-Cost_A -> -120 | F43: =F42+E43 -> -580 | G43: =G42+W_gain -> 68 | H43: =Liq_today-F43 -> 1200 | I43: =Pre_A+MAX(H33:H42) -> 1550 | J43: =IF(AND(J42=1,N42>=Pre_A,O42>=W_min),1,0) -> 1 | K43: =K42+Close_A*(Ceil_E-K42)-$C$5 -> 84.986328 | L43: =$C$4*Value_pt*(K43-Eff_today) -> 139.86328 | M43: =L43-Cost_A -> 19.863281 | N43: =N42+M43 -> 680.13672 | O43: =O42+W_gain -> 68 | P43: =Liq_today-N43 -> -60.136719 | Q43: =Pre_A+MAX(P33:P42) -> 535 | R43: =IF(AND(R42=1,V42>=Pre_A,W42>=W_min),1,0) -> 1 | S43: =S42+Close_A*(Ceil_E-S42)-$D$5 -> 82.988281 | T43: =$D$4*Value_pt*(S43-Eff_today) -> 119.88281 | U43: =T43-Cost_A -> -0.1171875 | V43: =V42+U43 -> 500.11719 | W43: =W42+W_gain -> 68 | X43: =Liq_today-V43 -> 119.88281 | Y43: =Pre_A+MAX(X33:X42) -> 589.76562 | Z43: =IF(AND(Z42=1,AD42>=Pre_A,AE42>=W_min),1,0) -> 0 | AA43: =AA42+Close_A*(Ceil_E-AA42)-$E$5 -> 80.990234 | AB43: =$E$4*Value_pt*(AA43-Eff_today) -> 99.902344 | AC43: =AB43-Cost_A -> -20.097656 | AD43: =AD42+AC43 -> 320.09766 | AE43: =AE42+W_gain -> 68 | AF43: =Liq_today-AD43 -> 299.90234 | AG43: =Pre_A+MAX(AF33:AF42) -> 749.80469
A44: 11 | B44: =IF(AND(B43=1,F43>=Pre_A,G43>=W_min),1,0) -> 0 | C44: =C43+Close_A*(Ceil_E-C43)-$B$5 -> 84.993164 | D44: =$B$4*Value_pt*(C44-Eff_today) -> 0 | E44: =D44-Cost_A -> -120 | F44: =F43+E44 -> -700 | G44: =G43+W_gain -> 69 | H44: =Liq_today-F44 -> 1320 | I44: =Pre_A+MAX(H33:H43) -> 1670 | J44: =IF(AND(J43=1,N43>=Pre_A,O43>=W_min),1,0) -> 1 | K44: =K43+Close_A*(Ceil_E-K43)-$C$5 -> 84.993164 | L44: =$C$4*Value_pt*(K44-Eff_today) -> 139.93164 | M44: =L44-Cost_A -> 19.931641 | N44: =N43+M44 -> 700.06836 | O44: =O43+W_gain -> 69 | P44: =Liq_today-N44 -> -80.068359 | Q44: =Pre_A+MAX(P33:P43) -> 535 | R44: =IF(AND(R43=1,V43>=Pre_A,W43>=W_min),1,0) -> 1 | S44: =S43+Close_A*(Ceil_E-S43)-$D$5 -> 82.994141 | T44: =$D$4*Value_pt*(S44-Eff_today) -> 119.94141 | U44: =T44-Cost_A -> -0.05859375 | V44: =V43+U44 -> 500.05859 | W44: =W43+W_gain -> 69 | X44: =Liq_today-V44 -> 119.94141 | Y44: =Pre_A+MAX(X33:X43) -> 589.88281 | Z44: =IF(AND(Z43=1,AD43>=Pre_A,AE43>=W_min),1,0) -> 0 | AA44: =AA43+Close_A*(Ceil_E-AA43)-$E$5 -> 80.995117 | AB44: =$E$4*Value_pt*(AA44-Eff_today) -> 99.951172 | AC44: =AB44-Cost_A -> -20.048828 | AD44: =AD43+AC44 -> 300.04883 | AE44: =AE43+W_gain -> 69 | AF44: =Liq_today-AD44 -> 319.95117 | AG44: =Pre_A+MAX(AF33:AF43) -> 769.90234
A45: 12 | B45: =IF(AND(B44=1,F44>=Pre_A,G44>=W_min),1,0) -> 0 | C45: =C44+Close_A*(Ceil_E-C44)-$B$5 -> 84.996582 | D45: =$B$4*Value_pt*(C45-Eff_today) -> 0 | E45: =D45-Cost_A -> -120 | F45: =F44+E45 -> -820 | G45: =G44+W_gain -> 70 | H45: =Liq_today-F45 -> 1440 | I45: =Pre_A+MAX(H33:H44) -> 1790 | J45: =IF(AND(J44=1,N44>=Pre_A,O44>=W_min),1,0) -> 1 | K45: =K44+Close_A*(Ceil_E-K44)-$C$5 -> 84.996582 | L45: =$C$4*Value_pt*(K45-Eff_today) -> 139.96582 | M45: =L45-Cost_A -> 19.96582 | N45: =N44+M45 -> 720.03418 | O45: =O44+W_gain -> 70 | P45: =Liq_today-N45 -> -100.03418 | Q45: =Pre_A+MAX(P33:P44) -> 535 | R45: =IF(AND(R44=1,V44>=Pre_A,W44>=W_min),1,0) -> 1 | S45: =S44+Close_A*(Ceil_E-S44)-$D$5 -> 82.99707 | T45: =$D$4*Value_pt*(S45-Eff_today) -> 119.9707 | U45: =T45-Cost_A -> -0.029296875 | V45: =V44+U45 -> 500.0293 | W45: =W44+W_gain -> 70 | X45: =Liq_today-V45 -> 119.9707 | Y45: =Pre_A+MAX(X33:X44) -> 589.94141 | Z45: =IF(AND(Z44=1,AD44>=Pre_A,AE44>=W_min),1,0) -> 0 | AA45: =AA44+Close_A*(Ceil_E-AA44)-$E$5 -> 80.997559 | AB45: =$E$4*Value_pt*(AA45-Eff_today) -> 99.975586 | AC45: =AB45-Cost_A -> -20.024414 | AD45: =AD44+AC45 -> 280.02441 | AE45: =AE44+W_gain -> 70 | AF45: =Liq_today-AD45 -> 339.97559 | AG45: =Pre_A+MAX(AF33:AF44) -> 789.95117
A46: 13 | B46: =IF(AND(B45=1,F45>=Pre_A,G45>=W_min),1,0) -> 0 | C46: =C45+Close_A*(Ceil_E-C45)-$B$5 -> 84.998291 | D46: =$B$4*Value_pt*(C46-Eff_today) -> 0 | E46: =D46-Cost_A -> -120 | F46: =F45+E46 -> -940 | G46: =G45+W_gain -> 71 | H46: =Liq_today-F46 -> 1560 | I46: =Pre_A+MAX(H33:H45) -> 1910 | J46: =IF(AND(J45=1,N45>=Pre_A,O45>=W_min),1,0) -> 1 | K46: =K45+Close_A*(Ceil_E-K45)-$C$5 -> 84.998291 | L46: =$C$4*Value_pt*(K46-Eff_today) -> 139.98291 | M46: =L46-Cost_A -> 19.98291 | N46: =N45+M46 -> 740.01709 | O46: =O45+W_gain -> 71 | P46: =Liq_today-N46 -> -120.01709 | Q46: =Pre_A+MAX(P33:P45) -> 535 | R46: =IF(AND(R45=1,V45>=Pre_A,W45>=W_min),1,0) -> 1 | S46: =S45+Close_A*(Ceil_E-S45)-$D$5 -> 82.998535 | T46: =$D$4*Value_pt*(S46-Eff_today) -> 119.98535 | U46: =T46-Cost_A -> -0.014648438 | V46: =V45+U46 -> 500.01465 | W46: =W45+W_gain -> 71 | X46: =Liq_today-V46 -> 119.98535 | Y46: =Pre_A+MAX(X33:X45) -> 589.9707 | Z46: =IF(AND(Z45=1,AD45>=Pre_A,AE45>=W_min),1,0) -> 0 | AA46: =AA45+Close_A*(Ceil_E-AA45)-$E$5 -> 80.998779 | AB46: =$E$4*Value_pt*(AA46-Eff_today) -> 99.987793 | AC46: =AB46-Cost_A -> -20.012207 | AD46: =AD45+AC46 -> 260.01221 | AE46: =AE45+W_gain -> 71 | AF46: =Liq_today-AD46 -> 359.98779 | AG46: =Pre_A+MAX(AF33:AF45) -> 809.97559
A47: 14 | B47: =IF(AND(B46=1,F46>=Pre_A,G46>=W_min),1,0) -> 0 | C47: =C46+Close_A*(Ceil_E-C46)-$B$5 -> 84.999146 | D47: =$B$4*Value_pt*(C47-Eff_today) -> 0 | E47: =D47-Cost_A -> -120 | F47: =F46+E47 -> -1060 | G47: =G46+W_gain -> 72 | H47: =Liq_today-F47 -> 1680 | I47: =Pre_A+MAX(H33:H46) -> 2030 | J47: =IF(AND(J46=1,N46>=Pre_A,O46>=W_min),1,0) -> 1 | K47: =K46+Close_A*(Ceil_E-K46)-$C$5 -> 84.999146 | L47: =$C$4*Value_pt*(K47-Eff_today) -> 139.99146 | M47: =L47-Cost_A -> 19.991455 | N47: =N46+M47 -> 760.00854 | O47: =O46+W_gain -> 72 | P47: =Liq_today-N47 -> -140.00854 | Q47: =Pre_A+MAX(P33:P46) -> 535 | R47: =IF(AND(R46=1,V46>=Pre_A,W46>=W_min),1,0) -> 1 | S47: =S46+Close_A*(Ceil_E-S46)-$D$5 -> 82.999268 | T47: =$D$4*Value_pt*(S47-Eff_today) -> 119.99268 | U47: =T47-Cost_A -> -0.0073242188 | V47: =V46+U47 -> 500.00732 | W47: =W46+W_gain -> 72 | X47: =Liq_today-V47 -> 119.99268 | Y47: =Pre_A+MAX(X33:X46) -> 589.98535 | Z47: =IF(AND(Z46=1,AD46>=Pre_A,AE46>=W_min),1,0) -> 0 | AA47: =AA46+Close_A*(Ceil_E-AA46)-$E$5 -> 80.99939 | AB47: =$E$4*Value_pt*(AA47-Eff_today) -> 99.993896 | AC47: =AB47-Cost_A -> -20.006104 | AD47: =AD46+AC47 -> 240.0061 | AE47: =AE46+W_gain -> 72 | AF47: =Liq_today-AD47 -> 379.9939 | AG47: =Pre_A+MAX(AF33:AF46) -> 829.98779
A48: 15 | B48: =IF(AND(B47=1,F47>=Pre_A,G47>=W_min),1,0) -> 0 | C48: =C47+Close_A*(Ceil_E-C47)-$B$5 -> 84.999573 | D48: =$B$4*Value_pt*(C48-Eff_today) -> 0 | E48: =D48-Cost_A -> -120 | F48: =F47+E48 -> -1180 | G48: =G47+W_gain -> 73 | H48: =Liq_today-F48 -> 1800 | I48: =Pre_A+MAX(H33:H47) -> 2150 | J48: =IF(AND(J47=1,N47>=Pre_A,O47>=W_min),1,0) -> 1 | K48: =K47+Close_A*(Ceil_E-K47)-$C$5 -> 84.999573 | L48: =$C$4*Value_pt*(K48-Eff_today) -> 139.99573 | M48: =L48-Cost_A -> 19.995728 | N48: =N47+M48 -> 780.00427 | O48: =O47+W_gain -> 73 | P48: =Liq_today-N48 -> -160.00427 | Q48: =Pre_A+MAX(P33:P47) -> 535 | R48: =IF(AND(R47=1,V47>=Pre_A,W47>=W_min),1,0) -> 1 | S48: =S47+Close_A*(Ceil_E-S47)-$D$5 -> 82.999634 | T48: =$D$4*Value_pt*(S48-Eff_today) -> 119.99634 | U48: =T48-Cost_A -> -0.0036621094 | V48: =V47+U48 -> 500.00366 | W48: =W47+W_gain -> 73 | X48: =Liq_today-V48 -> 119.99634 | Y48: =Pre_A+MAX(X33:X47) -> 589.99268 | Z48: =IF(AND(Z47=1,AD47>=Pre_A,AE47>=W_min),1,0) -> 0 | AA48: =AA47+Close_A*(Ceil_E-AA47)-$E$5 -> 80.999695 | AB48: =$E$4*Value_pt*(AA48-Eff_today) -> 99.996948 | AC48: =AB48-Cost_A -> -20.003052 | AD48: =AD47+AC48 -> 220.00305 | AE48: =AE47+W_gain -> 73 | AF48: =Liq_today-AD48 -> 399.99695 | AG48: =Pre_A+MAX(AF33:AF47) -> 849.9939
A49: 16 | B49: =IF(AND(B48=1,F48>=Pre_A,G48>=W_min),1,0) -> 0 | C49: =C48+Close_A*(Ceil_E-C48)-$B$5 -> 84.999786 | D49: =$B$4*Value_pt*(C49-Eff_today) -> 0 | E49: =D49-Cost_A -> -120 | F49: =F48+E49 -> -1300 | G49: =G48+W_gain -> 74 | H49: =Liq_today-F49 -> 1920 | I49: =Pre_A+MAX(H33:H48) -> 2270 | J49: =IF(AND(J48=1,N48>=Pre_A,O48>=W_min),1,0) -> 1 | K49: =K48+Close_A*(Ceil_E-K48)-$C$5 -> 84.999786 | L49: =$C$4*Value_pt*(K49-Eff_today) -> 139.99786 | M49: =L49-Cost_A -> 19.997864 | N49: =N48+M49 -> 800.00214 | O49: =O48+W_gain -> 74 | P49: =Liq_today-N49 -> -180.00214 | Q49: =Pre_A+MAX(P33:P48) -> 535 | R49: =IF(AND(R48=1,V48>=Pre_A,W48>=W_min),1,0) -> 1 | S49: =S48+Close_A*(Ceil_E-S48)-$D$5 -> 82.999817 | T49: =$D$4*Value_pt*(S49-Eff_today) -> 119.99817 | U49: =T49-Cost_A -> -0.0018310547 | V49: =V48+U49 -> 500.00183 | W49: =W48+W_gain -> 74 | X49: =Liq_today-V49 -> 119.99817 | Y49: =Pre_A+MAX(X33:X48) -> 589.99634 | Z49: =IF(AND(Z48=1,AD48>=Pre_A,AE48>=W_min),1,0) -> 0 | AA49: =AA48+Close_A*(Ceil_E-AA48)-$E$5 -> 80.999847 | AB49: =$E$4*Value_pt*(AA49-Eff_today) -> 99.998474 | AC49: =AB49-Cost_A -> -20.001526 | AD49: =AD48+AC49 -> 200.00153 | AE49: =AE48+W_gain -> 74 | AF49: =Liq_today-AD49 -> 419.99847 | AG49: =Pre_A+MAX(AF33:AF48) -> 869.99695
A50: 17 | B50: =IF(AND(B49=1,F49>=Pre_A,G49>=W_min),1,0) -> 0 | C50: =C49+Close_A*(Ceil_E-C49)-$B$5 -> 84.999893 | D50: =$B$4*Value_pt*(C50-Eff_today) -> 0 | E50: =D50-Cost_A -> -120 | F50: =F49+E50 -> -1420 | G50: =G49+W_gain -> 75 | H50: =Liq_today-F50 -> 2040 | I50: =Pre_A+MAX(H33:H49) -> 2390 | J50: =IF(AND(J49=1,N49>=Pre_A,O49>=W_min),1,0) -> 1 | K50: =K49+Close_A*(Ceil_E-K49)-$C$5 -> 84.999893 | L50: =$C$4*Value_pt*(K50-Eff_today) -> 139.99893 | M50: =L50-Cost_A -> 19.998932 | N50: =N49+M50 -> 820.00107 | O50: =O49+W_gain -> 75 | P50: =Liq_today-N50 -> -200.00107 | Q50: =Pre_A+MAX(P33:P49) -> 535 | R50: =IF(AND(R49=1,V49>=Pre_A,W49>=W_min),1,0) -> 1 | S50: =S49+Close_A*(Ceil_E-S49)-$D$5 -> 82.999908 | T50: =$D$4*Value_pt*(S50-Eff_today) -> 119.99908 | U50: =T50-Cost_A -> -0.00091552734 | V50: =V49+U50 -> 500.00092 | W50: =W49+W_gain -> 75 | X50: =Liq_today-V50 -> 119.99908 | Y50: =Pre_A+MAX(X33:X49) -> 589.99817 | Z50: =IF(AND(Z49=1,AD49>=Pre_A,AE49>=W_min),1,0) -> 0 | AA50: =AA49+Close_A*(Ceil_E-AA49)-$E$5 -> 80.999924 | AB50: =$E$4*Value_pt*(AA50-Eff_today) -> 99.999237 | AC50: =AB50-Cost_A -> -20.000763 | AD50: =AD49+AC50 -> 180.00076 | AE50: =AE49+W_gain -> 75 | AF50: =Liq_today-AD50 -> 439.99924 | AG50: =Pre_A+MAX(AF33:AF49) -> 889.99847
A51: 18 | B51: =IF(AND(B50=1,F50>=Pre_A,G50>=W_min),1,0) -> 0 | C51: =C50+Close_A*(Ceil_E-C50)-$B$5 -> 84.999947 | D51: =$B$4*Value_pt*(C51-Eff_today) -> 0 | E51: =D51-Cost_A -> -120 | F51: =F50+E51 -> -1540 | G51: =G50+W_gain -> 76 | H51: =Liq_today-F51 -> 2160 | I51: =Pre_A+MAX(H33:H50) -> 2510 | J51: =IF(AND(J50=1,N50>=Pre_A,O50>=W_min),1,0) -> 1 | K51: =K50+Close_A*(Ceil_E-K50)-$C$5 -> 84.999947 | L51: =$C$4*Value_pt*(K51-Eff_today) -> 139.99947 | M51: =L51-Cost_A -> 19.999466 | N51: =N50+M51 -> 840.00053 | O51: =O50+W_gain -> 76 | P51: =Liq_today-N51 -> -220.00053 | Q51: =Pre_A+MAX(P33:P50) -> 535 | R51: =IF(AND(R50=1,V50>=Pre_A,W50>=W_min),1,0) -> 1 | S51: =S50+Close_A*(Ceil_E-S50)-$D$5 -> 82.999954 | T51: =$D$4*Value_pt*(S51-Eff_today) -> 119.99954 | U51: =T51-Cost_A -> -0.00045776367 | V51: =V50+U51 -> 500.00046 | W51: =W50+W_gain -> 76 | X51: =Liq_today-V51 -> 119.99954 | Y51: =Pre_A+MAX(X33:X50) -> 589.99908 | Z51: =IF(AND(Z50=1,AD50>=Pre_A,AE50>=W_min),1,0) -> 0 | AA51: =AA50+Close_A*(Ceil_E-AA50)-$E$5 -> 80.999962 | AB51: =$E$4*Value_pt*(AA51-Eff_today) -> 99.999619 | AC51: =AB51-Cost_A -> -20.000381 | AD51: =AD50+AC51 -> 160.00038 | AE51: =AE50+W_gain -> 76 | AF51: =Liq_today-AD51 -> 459.99962 | AG51: =Pre_A+MAX(AF33:AF50) -> 909.99924
A52: 19 | B52: =IF(AND(B51=1,F51>=Pre_A,G51>=W_min),1,0) -> 0 | C52: =C51+Close_A*(Ceil_E-C51)-$B$5 -> 84.999973 | D52: =$B$4*Value_pt*(C52-Eff_today) -> 0 | E52: =D52-Cost_A -> -120 | F52: =F51+E52 -> -1660 | G52: =G51+W_gain -> 77 | H52: =Liq_today-F52 -> 2280 | I52: =Pre_A+MAX(H33:H51) -> 2630 | J52: =IF(AND(J51=1,N51>=Pre_A,O51>=W_min),1,0) -> 1 | K52: =K51+Close_A*(Ceil_E-K51)-$C$5 -> 84.999973 | L52: =$C$4*Value_pt*(K52-Eff_today) -> 139.99973 | M52: =L52-Cost_A -> 19.999733 | N52: =N51+M52 -> 860.00027 | O52: =O51+W_gain -> 77 | P52: =Liq_today-N52 -> -240.00027 | Q52: =Pre_A+MAX(P33:P51) -> 535 | R52: =IF(AND(R51=1,V51>=Pre_A,W51>=W_min),1,0) -> 1 | S52: =S51+Close_A*(Ceil_E-S51)-$D$5 -> 82.999977 | T52: =$D$4*Value_pt*(S52-Eff_today) -> 119.99977 | U52: =T52-Cost_A -> -0.00022888184 | V52: =V51+U52 -> 500.00023 | W52: =W51+W_gain -> 77 | X52: =Liq_today-V52 -> 119.99977 | Y52: =Pre_A+MAX(X33:X51) -> 589.99954 | Z52: =IF(AND(Z51=1,AD51>=Pre_A,AE51>=W_min),1,0) -> 0 | AA52: =AA51+Close_A*(Ceil_E-AA51)-$E$5 -> 80.999981 | AB52: =$E$4*Value_pt*(AA52-Eff_today) -> 99.999809 | AC52: =AB52-Cost_A -> -20.000191 | AD52: =AD51+AC52 -> 140.00019 | AE52: =AE51+W_gain -> 77 | AF52: =Liq_today-AD52 -> 479.99981 | AG52: =Pre_A+MAX(AF33:AF51) -> 929.99962
A53: 20 | B53: =IF(AND(B52=1,F52>=Pre_A,G52>=W_min),1,0) -> 0 | C53: =C52+Close_A*(Ceil_E-C52)-$B$5 -> 84.999987 | D53: =$B$4*Value_pt*(C53-Eff_today) -> 0 | E53: =D53-Cost_A -> -120 | F53: =F52+E53 -> -1780 | G53: =G52+W_gain -> 78 | H53: =Liq_today-F53 -> 2400 | I53: =Pre_A+MAX(H33:H52) -> 2750 | J53: =IF(AND(J52=1,N52>=Pre_A,O52>=W_min),1,0) -> 1 | K53: =K52+Close_A*(Ceil_E-K52)-$C$5 -> 84.999987 | L53: =$C$4*Value_pt*(K53-Eff_today) -> 139.99987 | M53: =L53-Cost_A -> 19.999866 | N53: =N52+M53 -> 880.00013 | O53: =O52+W_gain -> 78 | P53: =Liq_today-N53 -> -260.00013 | Q53: =Pre_A+MAX(P33:P52) -> 535 | R53: =IF(AND(R52=1,V52>=Pre_A,W52>=W_min),1,0) -> 1 | S53: =S52+Close_A*(Ceil_E-S52)-$D$5 -> 82.999989 | T53: =$D$4*Value_pt*(S53-Eff_today) -> 119.99989 | U53: =T53-Cost_A -> -0.00011444092 | V53: =V52+U53 -> 500.00011 | W53: =W52+W_gain -> 78 | X53: =Liq_today-V53 -> 119.99989 | Y53: =Pre_A+MAX(X33:X52) -> 589.99977 | Z53: =IF(AND(Z52=1,AD52>=Pre_A,AE52>=W_min),1,0) -> 0 | AA53: =AA52+Close_A*(Ceil_E-AA52)-$E$5 -> 80.99999 | AB53: =$E$4*Value_pt*(AA53-Eff_today) -> 99.999905 | AC53: =AB53-Cost_A -> -20.000095 | AD53: =AD52+AC53 -> 120.0001 | AE53: =AE52+W_gain -> 78 | AF53: =Liq_today-AD53 -> 499.9999 | AG53: =Pre_A+MAX(AF33:AF52) -> 949.99981
A54: 21 | B54: =IF(AND(B53=1,F53>=Pre_A,G53>=W_min),1,0) -> 0 | C54: =C53+Close_A*(Ceil_E-C53)-$B$5 -> 84.999993 | D54: =$B$4*Value_pt*(C54-Eff_today) -> 0 | E54: =D54-Cost_A -> -120 | F54: =F53+E54 -> -1900 | G54: =G53+W_gain -> 79 | H54: =Liq_today-F54 -> 2520 | I54: =Pre_A+MAX(H33:H53) -> 2870 | J54: =IF(AND(J53=1,N53>=Pre_A,O53>=W_min),1,0) -> 1 | K54: =K53+Close_A*(Ceil_E-K53)-$C$5 -> 84.999993 | L54: =$C$4*Value_pt*(K54-Eff_today) -> 139.99993 | M54: =L54-Cost_A -> 19.999933 | N54: =N53+M54 -> 900.00007 | O54: =O53+W_gain -> 79 | P54: =Liq_today-N54 -> -280.00007 | Q54: =Pre_A+MAX(P33:P53) -> 535 | R54: =IF(AND(R53=1,V53>=Pre_A,W53>=W_min),1,0) -> 1 | S54: =S53+Close_A*(Ceil_E-S53)-$D$5 -> 82.999994 | T54: =$D$4*Value_pt*(S54-Eff_today) -> 119.99994 | U54: =T54-Cost_A -> -5.7220459e-05 | V54: =V53+U54 -> 500.00006 | W54: =W53+W_gain -> 79 | X54: =Liq_today-V54 -> 119.99994 | Y54: =Pre_A+MAX(X33:X53) -> 589.99989 | Z54: =IF(AND(Z53=1,AD53>=Pre_A,AE53>=W_min),1,0) -> 0 | AA54: =AA53+Close_A*(Ceil_E-AA53)-$E$5 -> 80.999995 | AB54: =$E$4*Value_pt*(AA54-Eff_today) -> 99.999952 | AC54: =AB54-Cost_A -> -20.000048 | AD54: =AD53+AC54 -> 100.00005 | AE54: =AE53+W_gain -> 79 | AF54: =Liq_today-AD54 -> 519.99995 | AG54: =Pre_A+MAX(AF33:AF53) -> 969.9999
A55: 22 | B55: =IF(AND(B54=1,F54>=Pre_A,G54>=W_min),1,0) -> 0 | C55: =C54+Close_A*(Ceil_E-C54)-$B$5 -> 84.999997 | D55: =$B$4*Value_pt*(C55-Eff_today) -> 0 | E55: =D55-Cost_A -> -120 | F55: =F54+E55 -> -2020 | G55: =G54+W_gain -> 80 | H55: =Liq_today-F55 -> 2640 | I55: =Pre_A+MAX(H33:H54) -> 2990 | J55: =IF(AND(J54=1,N54>=Pre_A,O54>=W_min),1,0) -> 1 | K55: =K54+Close_A*(Ceil_E-K54)-$C$5 -> 84.999997 | L55: =$C$4*Value_pt*(K55-Eff_today) -> 139.99997 | M55: =L55-Cost_A -> 19.999967 | N55: =N54+M55 -> 920.00003 | O55: =O54+W_gain -> 80 | P55: =Liq_today-N55 -> -300.00003 | Q55: =Pre_A+MAX(P33:P54) -> 535 | R55: =IF(AND(R54=1,V54>=Pre_A,W54>=W_min),1,0) -> 1 | S55: =S54+Close_A*(Ceil_E-S54)-$D$5 -> 82.999997 | T55: =$D$4*Value_pt*(S55-Eff_today) -> 119.99997 | U55: =T55-Cost_A -> -2.8610229e-05 | V55: =V54+U55 -> 500.00003 | W55: =W54+W_gain -> 80 | X55: =Liq_today-V55 -> 119.99997 | Y55: =Pre_A+MAX(X33:X54) -> 589.99994 | Z55: =IF(AND(Z54=1,AD54>=Pre_A,AE54>=W_min),1,0) -> 0 | AA55: =AA54+Close_A*(Ceil_E-AA54)-$E$5 -> 80.999998 | AB55: =$E$4*Value_pt*(AA55-Eff_today) -> 99.999976 | AC55: =AB55-Cost_A -> -20.000024 | AD55: =AD54+AC55 -> 80.000024 | AE55: =AE54+W_gain -> 80 | AF55: =Liq_today-AD55 -> 539.99998 | AG55: =Pre_A+MAX(AF33:AF54) -> 989.99995
A56: 23 | B56: =IF(AND(B55=1,F55>=Pre_A,G55>=W_min),1,0) -> 0 | C56: =C55+Close_A*(Ceil_E-C55)-$B$5 -> 84.999998 | D56: =$B$4*Value_pt*(C56-Eff_today) -> 0 | E56: =D56-Cost_A -> -120 | F56: =F55+E56 -> -2140 | G56: =G55+W_gain -> 81 | H56: =Liq_today-F56 -> 2760 | I56: =Pre_A+MAX(H33:H55) -> 3110 | J56: =IF(AND(J55=1,N55>=Pre_A,O55>=W_min),1,0) -> 1 | K56: =K55+Close_A*(Ceil_E-K55)-$C$5 -> 84.999998 | L56: =$C$4*Value_pt*(K56-Eff_today) -> 139.99998 | M56: =L56-Cost_A -> 19.999983 | N56: =N55+M56 -> 940.00002 | O56: =O55+W_gain -> 81 | P56: =Liq_today-N56 -> -320.00002 | Q56: =Pre_A+MAX(P33:P55) -> 535 | R56: =IF(AND(R55=1,V55>=Pre_A,W55>=W_min),1,0) -> 1 | S56: =S55+Close_A*(Ceil_E-S55)-$D$5 -> 82.999999 | T56: =$D$4*Value_pt*(S56-Eff_today) -> 119.99999 | U56: =T56-Cost_A -> -1.4305115e-05 | V56: =V55+U56 -> 500.00001 | W56: =W55+W_gain -> 81 | X56: =Liq_today-V56 -> 119.99999 | Y56: =Pre_A+MAX(X33:X55) -> 589.99997 | Z56: =IF(AND(Z55=1,AD55>=Pre_A,AE55>=W_min),1,0) -> 0 | AA56: =AA55+Close_A*(Ceil_E-AA55)-$E$5 -> 80.999999 | AB56: =$E$4*Value_pt*(AA56-Eff_today) -> 99.999988 | AC56: =AB56-Cost_A -> -20.000012 | AD56: =AD55+AC56 -> 60.000012 | AE56: =AE55+W_gain -> 81 | AF56: =Liq_today-AD56 -> 559.99999 | AG56: =Pre_A+MAX(AF33:AF55) -> 1010
A57: 24 | B57: =IF(AND(B56=1,F56>=Pre_A,G56>=W_min),1,0) -> 0 | C57: =C56+Close_A*(Ceil_E-C56)-$B$5 -> 84.999999 | D57: =$B$4*Value_pt*(C57-Eff_today) -> 0 | E57: =D57-Cost_A -> -120 | F57: =F56+E57 -> -2260 | G57: =G56+W_gain -> 82 | H57: =Liq_today-F57 -> 2880 | I57: =Pre_A+MAX(H33:H56) -> 3230 | J57: =IF(AND(J56=1,N56>=Pre_A,O56>=W_min),1,0) -> 1 | K57: =K56+Close_A*(Ceil_E-K56)-$C$5 -> 84.999999 | L57: =$C$4*Value_pt*(K57-Eff_today) -> 139.99999 | M57: =L57-Cost_A -> 19.999992 | N57: =N56+M57 -> 960.00001 | O57: =O56+W_gain -> 82 | P57: =Liq_today-N57 -> -340.00001 | Q57: =Pre_A+MAX(P33:P56) -> 535 | R57: =IF(AND(R56=1,V56>=Pre_A,W56>=W_min),1,0) -> 1 | S57: =S56+Close_A*(Ceil_E-S56)-$D$5 -> 82.999999 | T57: =$D$4*Value_pt*(S57-Eff_today) -> 119.99999 | U57: =T57-Cost_A -> -7.1525574e-06 | V57: =V56+U57 -> 500.00001 | W57: =W56+W_gain -> 82 | X57: =Liq_today-V57 -> 119.99999 | Y57: =Pre_A+MAX(X33:X56) -> 589.99999 | Z57: =IF(AND(Z56=1,AD56>=Pre_A,AE56>=W_min),1,0) -> 0 | AA57: =AA56+Close_A*(Ceil_E-AA56)-$E$5 -> 80.999999 | AB57: =$E$4*Value_pt*(AA57-Eff_today) -> 99.999994 | AC57: =AB57-Cost_A -> -20.000006 | AD57: =AD56+AC57 -> 40.000006 | AE57: =AE56+W_gain -> 82 | AF57: =Liq_today-AD57 -> 579.99999 | AG57: =Pre_A+MAX(AF33:AF56) -> 1030
A58: 25 | B58: =IF(AND(B57=1,F57>=Pre_A,G57>=W_min),1,0) -> 0 | C58: =C57+Close_A*(Ceil_E-C57)-$B$5 -> 85 | D58: =$B$4*Value_pt*(C58-Eff_today) -> 0 | E58: =D58-Cost_A -> -120 | F58: =F57+E58 -> -2380 | G58: =G57+W_gain -> 83 | H58: =Liq_today-F58 -> 3000 | I58: =Pre_A+MAX(H33:H57) -> 3350 | J58: =IF(AND(J57=1,N57>=Pre_A,O57>=W_min),1,0) -> 1 | K58: =K57+Close_A*(Ceil_E-K57)-$C$5 -> 85 | L58: =$C$4*Value_pt*(K58-Eff_today) -> 140 | M58: =L58-Cost_A -> 19.999996 | N58: =N57+M58 -> 980 | O58: =O57+W_gain -> 83 | P58: =Liq_today-N58 -> -360 | Q58: =Pre_A+MAX(P33:P57) -> 535 | R58: =IF(AND(R57=1,V57>=Pre_A,W57>=W_min),1,0) -> 1 | S58: =S57+Close_A*(Ceil_E-S57)-$D$5 -> 83 | T58: =$D$4*Value_pt*(S58-Eff_today) -> 120 | U58: =T58-Cost_A -> -3.5762787e-06 | V58: =V57+U58 -> 500 | W58: =W57+W_gain -> 83 | X58: =Liq_today-V58 -> 120 | Y58: =Pre_A+MAX(X33:X57) -> 589.99999 | Z58: =IF(AND(Z57=1,AD57>=Pre_A,AE57>=W_min),1,0) -> 0 | AA58: =AA57+Close_A*(Ceil_E-AA57)-$E$5 -> 81 | AB58: =$E$4*Value_pt*(AA58-Eff_today) -> 99.999997 | AC58: =AB58-Cost_A -> -20.000003 | AD58: =AD57+AC58 -> 20.000003 | AE58: =AE57+W_gain -> 83 | AF58: =Liq_today-AD58 -> 600 | AG58: =Pre_A+MAX(AF33:AF57) -> 1050
A59: 26 | B59: =IF(AND(B58=1,F58>=Pre_A,G58>=W_min),1,0) -> 0 | C59: =C58+Close_A*(Ceil_E-C58)-$B$5 -> 85 | D59: =$B$4*Value_pt*(C59-Eff_today) -> 0 | E59: =D59-Cost_A -> -120 | F59: =F58+E59 -> -2500 | G59: =G58+W_gain -> 84 | H59: =Liq_today-F59 -> 3120 | I59: =Pre_A+MAX(H33:H58) -> 3470 | J59: =IF(AND(J58=1,N58>=Pre_A,O58>=W_min),1,0) -> 1 | K59: =K58+Close_A*(Ceil_E-K58)-$C$5 -> 85 | L59: =$C$4*Value_pt*(K59-Eff_today) -> 140 | M59: =L59-Cost_A -> 19.999998 | N59: =N58+M59 -> 1000 | O59: =O58+W_gain -> 84 | P59: =Liq_today-N59 -> -380 | Q59: =Pre_A+MAX(P33:P58) -> 535 | R59: =IF(AND(R58=1,V58>=Pre_A,W58>=W_min),1,0) -> 1 | S59: =S58+Close_A*(Ceil_E-S58)-$D$5 -> 83 | T59: =$D$4*Value_pt*(S59-Eff_today) -> 120 | U59: =T59-Cost_A -> -1.7881393e-06 | V59: =V58+U59 -> 500 | W59: =W58+W_gain -> 84 | X59: =Liq_today-V59 -> 120 | Y59: =Pre_A+MAX(X33:X58) -> 590 | Z59: =IF(AND(Z58=1,AD58>=Pre_A,AE58>=W_min),1,0) -> 0 | AA59: =AA58+Close_A*(Ceil_E-AA58)-$E$5 -> 81 | AB59: =$E$4*Value_pt*(AA59-Eff_today) -> 99.999999 | AC59: =AB59-Cost_A -> -20.000001 | AD59: =AD58+AC59 -> 1.4901161e-06 | AE59: =AE58+W_gain -> 84 | AF59: =Liq_today-AD59 -> 620 | AG59: =Pre_A+MAX(AF33:AF58) -> 1070
A60: 27 | B60: =IF(AND(B59=1,F59>=Pre_A,G59>=W_min),1,0) -> 0 | C60: =C59+Close_A*(Ceil_E-C59)-$B$5 -> 85 | D60: =$B$4*Value_pt*(C60-Eff_today) -> 0 | E60: =D60-Cost_A -> -120 | F60: =F59+E60 -> -2620 | G60: =G59+W_gain -> 85 | H60: =Liq_today-F60 -> 3240 | I60: =Pre_A+MAX(H33:H59) -> 3590 | J60: =IF(AND(J59=1,N59>=Pre_A,O59>=W_min),1,0) -> 1 | K60: =K59+Close_A*(Ceil_E-K59)-$C$5 -> 85 | L60: =$C$4*Value_pt*(K60-Eff_today) -> 140 | M60: =L60-Cost_A -> 19.999999 | N60: =N59+M60 -> 1020 | O60: =O59+W_gain -> 85 | P60: =Liq_today-N60 -> -400 | Q60: =Pre_A+MAX(P33:P59) -> 535 | R60: =IF(AND(R59=1,V59>=Pre_A,W59>=W_min),1,0) -> 1 | S60: =S59+Close_A*(Ceil_E-S59)-$D$5 -> 83 | T60: =$D$4*Value_pt*(S60-Eff_today) -> 120 | U60: =T60-Cost_A -> -8.9406967e-07 | V60: =V59+U60 -> 500 | W60: =W59+W_gain -> 85 | X60: =Liq_today-V60 -> 120 | Y60: =Pre_A+MAX(X33:X59) -> 590 | Z60: =IF(AND(Z59=1,AD59>=Pre_A,AE59>=W_min),1,0) -> 0 | AA60: =AA59+Close_A*(Ceil_E-AA59)-$E$5 -> 81 | AB60: =$E$4*Value_pt*(AA60-Eff_today) -> 99.999999 | AC60: =AB60-Cost_A -> -20.000001 | AD60: =AD59+AC60 -> -19.999999 | AE60: =AE59+W_gain -> 85 | AF60: =Liq_today-AD60 -> 640 | AG60: =Pre_A+MAX(AF33:AF59) -> 1090
A61: 28 | B61: =IF(AND(B60=1,F60>=Pre_A,G60>=W_min),1,0) -> 0 | C61: =C60+Close_A*(Ceil_E-C60)-$B$5 -> 85 | D61: =$B$4*Value_pt*(C61-Eff_today) -> 0 | E61: =D61-Cost_A -> -120 | F61: =F60+E61 -> -2740 | G61: =G60+W_gain -> 86 | H61: =Liq_today-F61 -> 3360 | I61: =Pre_A+MAX(H33:H60) -> 3710 | J61: =IF(AND(J60=1,N60>=Pre_A,O60>=W_min),1,0) -> 1 | K61: =K60+Close_A*(Ceil_E-K60)-$C$5 -> 85 | L61: =$C$4*Value_pt*(K61-Eff_today) -> 140 | M61: =L61-Cost_A -> 19.999999 | N61: =N60+M61 -> 1040 | O61: =O60+W_gain -> 86 | P61: =Liq_today-N61 -> -420 | Q61: =Pre_A+MAX(P33:P60) -> 535 | R61: =IF(AND(R60=1,V60>=Pre_A,W60>=W_min),1,0) -> 1 | S61: =S60+Close_A*(Ceil_E-S60)-$D$5 -> 83 | T61: =$D$4*Value_pt*(S61-Eff_today) -> 120 | U61: =T61-Cost_A -> -4.4703484e-07 | V61: =V60+U61 -> 500 | W61: =W60+W_gain -> 86 | X61: =Liq_today-V61 -> 120 | Y61: =Pre_A+MAX(X33:X60) -> 590 | Z61: =IF(AND(Z60=1,AD60>=Pre_A,AE60>=W_min),1,0) -> 0 | AA61: =AA60+Close_A*(Ceil_E-AA60)-$E$5 -> 81 | AB61: =$E$4*Value_pt*(AA61-Eff_today) -> 100 | AC61: =AB61-Cost_A -> -20 | AD61: =AD60+AC61 -> -40 | AE61: =AE60+W_gain -> 86 | AF61: =Liq_today-AD61 -> 660 | AG61: =Pre_A+MAX(AF33:AF60) -> 1110
A62: 29 | B62: =IF(AND(B61=1,F61>=Pre_A,G61>=W_min),1,0) -> 0 | C62: =C61+Close_A*(Ceil_E-C61)-$B$5 -> 85 | D62: =$B$4*Value_pt*(C62-Eff_today) -> 0 | E62: =D62-Cost_A -> -120 | F62: =F61+E62 -> -2860 | G62: =G61+W_gain -> 87 | H62: =Liq_today-F62 -> 3480 | I62: =Pre_A+MAX(H33:H61) -> 3830 | J62: =IF(AND(J61=1,N61>=Pre_A,O61>=W_min),1,0) -> 1 | K62: =K61+Close_A*(Ceil_E-K61)-$C$5 -> 85 | L62: =$C$4*Value_pt*(K62-Eff_today) -> 140 | M62: =L62-Cost_A -> 20 | N62: =N61+M62 -> 1060 | O62: =O61+W_gain -> 87 | P62: =Liq_today-N62 -> -440 | Q62: =Pre_A+MAX(P33:P61) -> 535 | R62: =IF(AND(R61=1,V61>=Pre_A,W61>=W_min),1,0) -> 1 | S62: =S61+Close_A*(Ceil_E-S61)-$D$5 -> 83 | T62: =$D$4*Value_pt*(S62-Eff_today) -> 120 | U62: =T62-Cost_A -> -2.2351742e-07 | V62: =V61+U62 -> 500 | W62: =W61+W_gain -> 87 | X62: =Liq_today-V62 -> 120 | Y62: =Pre_A+MAX(X33:X61) -> 590 | Z62: =IF(AND(Z61=1,AD61>=Pre_A,AE61>=W_min),1,0) -> 0 | AA62: =AA61+Close_A*(Ceil_E-AA61)-$E$5 -> 81 | AB62: =$E$4*Value_pt*(AA62-Eff_today) -> 100 | AC62: =AB62-Cost_A -> -20 | AD62: =AD61+AC62 -> -60 | AE62: =AE61+W_gain -> 87 | AF62: =Liq_today-AD62 -> 680 | AG62: =Pre_A+MAX(AF33:AF61) -> 1130
A63: 30 | B63: =IF(AND(B62=1,F62>=Pre_A,G62>=W_min),1,0) -> 0 | C63: =C62+Close_A*(Ceil_E-C62)-$B$5 -> 85 | D63: =$B$4*Value_pt*(C63-Eff_today) -> 0 | E63: =D63-Cost_A -> -120 | F63: =F62+E63 -> -2980 | G63: =G62+W_gain -> 88 | H63: =Liq_today-F63 -> 3600 | I63: =Pre_A+MAX(H33:H62) -> 3950 | J63: =IF(AND(J62=1,N62>=Pre_A,O62>=W_min),1,0) -> 1 | K63: =K62+Close_A*(Ceil_E-K62)-$C$5 -> 85 | L63: =$C$4*Value_pt*(K63-Eff_today) -> 140 | M63: =L63-Cost_A -> 20 | N63: =N62+M63 -> 1080 | O63: =O62+W_gain -> 88 | P63: =Liq_today-N63 -> -460 | Q63: =Pre_A+MAX(P33:P62) -> 535 | R63: =IF(AND(R62=1,V62>=Pre_A,W62>=W_min),1,0) -> 1 | S63: =S62+Close_A*(Ceil_E-S62)-$D$5 -> 83 | T63: =$D$4*Value_pt*(S63-Eff_today) -> 120 | U63: =T63-Cost_A -> -1.1175871e-07 | V63: =V62+U63 -> 500 | W63: =W62+W_gain -> 88 | X63: =Liq_today-V63 -> 120 | Y63: =Pre_A+MAX(X33:X62) -> 590 | Z63: =IF(AND(Z62=1,AD62>=Pre_A,AE62>=W_min),1,0) -> 0 | AA63: =AA62+Close_A*(Ceil_E-AA62)-$E$5 -> 81 | AB63: =$E$4*Value_pt*(AA63-Eff_today) -> 100 | AC63: =AB63-Cost_A -> -20 | AD63: =AD62+AC63 -> -80 | AE63: =AE62+W_gain -> 88 | AF63: =Liq_today-AD63 -> 700 | AG63: =Pre_A+MAX(AF33:AF62) -> 1150
A64: 31 | B64: =IF(AND(B63=1,F63>=Pre_A,G63>=W_min),1,0) -> 0 | C64: =C63+Close_A*(Ceil_E-C63)-$B$5 -> 85 | D64: =$B$4*Value_pt*(C64-Eff_today) -> 0 | E64: =D64-Cost_A -> -120 | F64: =F63+E64 -> -3100 | G64: =G63+W_gain -> 89 | H64: =Liq_today-F64 -> 3720 | I64: =Pre_A+MAX(H33:H63) -> 4070 | J64: =IF(AND(J63=1,N63>=Pre_A,O63>=W_min),1,0) -> 1 | K64: =K63+Close_A*(Ceil_E-K63)-$C$5 -> 85 | L64: =$C$4*Value_pt*(K64-Eff_today) -> 140 | M64: =L64-Cost_A -> 20 | N64: =N63+M64 -> 1100 | O64: =O63+W_gain -> 89 | P64: =Liq_today-N64 -> -480 | Q64: =Pre_A+MAX(P33:P63) -> 535 | R64: =IF(AND(R63=1,V63>=Pre_A,W63>=W_min),1,0) -> 1 | S64: =S63+Close_A*(Ceil_E-S63)-$D$5 -> 83 | T64: =$D$4*Value_pt*(S64-Eff_today) -> 120 | U64: =T64-Cost_A -> -5.5879354e-08 | V64: =V63+U64 -> 500 | W64: =W63+W_gain -> 89 | X64: =Liq_today-V64 -> 120 | Y64: =Pre_A+MAX(X33:X63) -> 590 | Z64: =IF(AND(Z63=1,AD63>=Pre_A,AE63>=W_min),1,0) -> 0 | AA64: =AA63+Close_A*(Ceil_E-AA63)-$E$5 -> 81 | AB64: =$E$4*Value_pt*(AA64-Eff_today) -> 100 | AC64: =AB64-Cost_A -> -20 | AD64: =AD63+AC64 -> -100 | AE64: =AE63+W_gain -> 89 | AF64: =Liq_today-AD64 -> 720 | AG64: =Pre_A+MAX(AF33:AF63) -> 1170
A65: 32 | B65: =IF(AND(B64=1,F64>=Pre_A,G64>=W_min),1,0) -> 0 | C65: =C64+Close_A*(Ceil_E-C64)-$B$5 -> 85 | D65: =$B$4*Value_pt*(C65-Eff_today) -> 0 | E65: =D65-Cost_A -> -120 | F65: =F64+E65 -> -3220 | G65: =G64+W_gain -> 90 | H65: =Liq_today-F65 -> 3840 | I65: =Pre_A+MAX(H33:H64) -> 4190 | J65: =IF(AND(J64=1,N64>=Pre_A,O64>=W_min),1,0) -> 1 | K65: =K64+Close_A*(Ceil_E-K64)-$C$5 -> 85 | L65: =$C$4*Value_pt*(K65-Eff_today) -> 140 | M65: =L65-Cost_A -> 20 | N65: =N64+M65 -> 1120 | O65: =O64+W_gain -> 90 | P65: =Liq_today-N65 -> -500 | Q65: =Pre_A+MAX(P33:P64) -> 535 | R65: =IF(AND(R64=1,V64>=Pre_A,W64>=W_min),1,0) -> 1 | S65: =S64+Close_A*(Ceil_E-S64)-$D$5 -> 83 | T65: =$D$4*Value_pt*(S65-Eff_today) -> 120 | U65: =T65-Cost_A -> -2.7939677e-08 | V65: =V64+U65 -> 500 | W65: =W64+W_gain -> 90 | X65: =Liq_today-V65 -> 120 | Y65: =Pre_A+MAX(X33:X64) -> 590 | Z65: =IF(AND(Z64=1,AD64>=Pre_A,AE64>=W_min),1,0) -> 0 | AA65: =AA64+Close_A*(Ceil_E-AA64)-$E$5 -> 81 | AB65: =$E$4*Value_pt*(AA65-Eff_today) -> 100 | AC65: =AB65-Cost_A -> -20 | AD65: =AD64+AC65 -> -120 | AE65: =AE64+W_gain -> 90 | AF65: =Liq_today-AD65 -> 740 | AG65: =Pre_A+MAX(AF33:AF64) -> 1190
A66: 33 | B66: =IF(AND(B65=1,F65>=Pre_A,G65>=W_min),1,0) -> 0 | C66: =C65+Close_A*(Ceil_E-C65)-$B$5 -> 85 | D66: =$B$4*Value_pt*(C66-Eff_today) -> 0 | E66: =D66-Cost_A -> -120 | F66: =F65+E66 -> -3340 | G66: =G65+W_gain -> 91 | H66: =Liq_today-F66 -> 3960 | I66: =Pre_A+MAX(H33:H65) -> 4310 | J66: =IF(AND(J65=1,N65>=Pre_A,O65>=W_min),1,0) -> 1 | K66: =K65+Close_A*(Ceil_E-K65)-$C$5 -> 85 | L66: =$C$4*Value_pt*(K66-Eff_today) -> 140 | M66: =L66-Cost_A -> 20 | N66: =N65+M66 -> 1140 | O66: =O65+W_gain -> 91 | P66: =Liq_today-N66 -> -520 | Q66: =Pre_A+MAX(P33:P65) -> 535 | R66: =IF(AND(R65=1,V65>=Pre_A,W65>=W_min),1,0) -> 1 | S66: =S65+Close_A*(Ceil_E-S65)-$D$5 -> 83 | T66: =$D$4*Value_pt*(S66-Eff_today) -> 120 | U66: =T66-Cost_A -> -1.3969839e-08 | V66: =V65+U66 -> 500 | W66: =W65+W_gain -> 91 | X66: =Liq_today-V66 -> 120 | Y66: =Pre_A+MAX(X33:X65) -> 590 | Z66: =IF(AND(Z65=1,AD65>=Pre_A,AE65>=W_min),1,0) -> 0 | AA66: =AA65+Close_A*(Ceil_E-AA65)-$E$5 -> 81 | AB66: =$E$4*Value_pt*(AA66-Eff_today) -> 100 | AC66: =AB66-Cost_A -> -20 | AD66: =AD65+AC66 -> -140 | AE66: =AE65+W_gain -> 91 | AF66: =Liq_today-AD66 -> 760 | AG66: =Pre_A+MAX(AF33:AF65) -> 1210
A67: 34 | B67: =IF(AND(B66=1,F66>=Pre_A,G66>=W_min),1,0) -> 0 | C67: =C66+Close_A*(Ceil_E-C66)-$B$5 -> 85 | D67: =$B$4*Value_pt*(C67-Eff_today) -> 0 | E67: =D67-Cost_A -> -120 | F67: =F66+E67 -> -3460 | G67: =G66+W_gain -> 92 | H67: =Liq_today-F67 -> 4080 | I67: =Pre_A+MAX(H33:H66) -> 4430 | J67: =IF(AND(J66=1,N66>=Pre_A,O66>=W_min),1,0) -> 1 | K67: =K66+Close_A*(Ceil_E-K66)-$C$5 -> 85 | L67: =$C$4*Value_pt*(K67-Eff_today) -> 140 | M67: =L67-Cost_A -> 20 | N67: =N66+M67 -> 1160 | O67: =O66+W_gain -> 92 | P67: =Liq_today-N67 -> -540 | Q67: =Pre_A+MAX(P33:P66) -> 535 | R67: =IF(AND(R66=1,V66>=Pre_A,W66>=W_min),1,0) -> 1 | S67: =S66+Close_A*(Ceil_E-S66)-$D$5 -> 83 | T67: =$D$4*Value_pt*(S67-Eff_today) -> 120 | U67: =T67-Cost_A -> -6.9849193e-09 | V67: =V66+U67 -> 500 | W67: =W66+W_gain -> 92 | X67: =Liq_today-V67 -> 120 | Y67: =Pre_A+MAX(X33:X66) -> 590 | Z67: =IF(AND(Z66=1,AD66>=Pre_A,AE66>=W_min),1,0) -> 0 | AA67: =AA66+Close_A*(Ceil_E-AA66)-$E$5 -> 81 | AB67: =$E$4*Value_pt*(AA67-Eff_today) -> 100 | AC67: =AB67-Cost_A -> -20 | AD67: =AD66+AC67 -> -160 | AE67: =AE66+W_gain -> 92 | AF67: =Liq_today-AD67 -> 780 | AG67: =Pre_A+MAX(AF33:AF66) -> 1230
A68: 35 | B68: =IF(AND(B67=1,F67>=Pre_A,G67>=W_min),1,0) -> 0 | C68: =C67+Close_A*(Ceil_E-C67)-$B$5 -> 85 | D68: =$B$4*Value_pt*(C68-Eff_today) -> 0 | E68: =D68-Cost_A -> -120 | F68: =F67+E68 -> -3580 | G68: =G67+W_gain -> 93 | H68: =Liq_today-F68 -> 4200 | I68: =Pre_A+MAX(H33:H67) -> 4550 | J68: =IF(AND(J67=1,N67>=Pre_A,O67>=W_min),1,0) -> 1 | K68: =K67+Close_A*(Ceil_E-K67)-$C$5 -> 85 | L68: =$C$4*Value_pt*(K68-Eff_today) -> 140 | M68: =L68-Cost_A -> 20 | N68: =N67+M68 -> 1180 | O68: =O67+W_gain -> 93 | P68: =Liq_today-N68 -> -560 | Q68: =Pre_A+MAX(P33:P67) -> 535 | R68: =IF(AND(R67=1,V67>=Pre_A,W67>=W_min),1,0) -> 1 | S68: =S67+Close_A*(Ceil_E-S67)-$D$5 -> 83 | T68: =$D$4*Value_pt*(S68-Eff_today) -> 120 | U68: =T68-Cost_A -> -3.4924597e-09 | V68: =V67+U68 -> 500 | W68: =W67+W_gain -> 93 | X68: =Liq_today-V68 -> 120 | Y68: =Pre_A+MAX(X33:X67) -> 590 | Z68: =IF(AND(Z67=1,AD67>=Pre_A,AE67>=W_min),1,0) -> 0 | AA68: =AA67+Close_A*(Ceil_E-AA67)-$E$5 -> 81 | AB68: =$E$4*Value_pt*(AA68-Eff_today) -> 100 | AC68: =AB68-Cost_A -> -20 | AD68: =AD67+AC68 -> -180 | AE68: =AE67+W_gain -> 93 | AF68: =Liq_today-AD68 -> 800 | AG68: =Pre_A+MAX(AF33:AF67) -> 1250
A69: 36 | B69: =IF(AND(B68=1,F68>=Pre_A,G68>=W_min),1,0) -> 0 | C69: =C68+Close_A*(Ceil_E-C68)-$B$5 -> 85 | D69: =$B$4*Value_pt*(C69-Eff_today) -> 0 | E69: =D69-Cost_A -> -120 | F69: =F68+E69 -> -3700 | G69: =G68+W_gain -> 94 | H69: =Liq_today-F69 -> 4320 | I69: =Pre_A+MAX(H33:H68) -> 4670 | J69: =IF(AND(J68=1,N68>=Pre_A,O68>=W_min),1,0) -> 1 | K69: =K68+Close_A*(Ceil_E-K68)-$C$5 -> 85 | L69: =$C$4*Value_pt*(K69-Eff_today) -> 140 | M69: =L69-Cost_A -> 20 | N69: =N68+M69 -> 1200 | O69: =O68+W_gain -> 94 | P69: =Liq_today-N69 -> -580 | Q69: =Pre_A+MAX(P33:P68) -> 535 | R69: =IF(AND(R68=1,V68>=Pre_A,W68>=W_min),1,0) -> 1 | S69: =S68+Close_A*(Ceil_E-S68)-$D$5 -> 83 | T69: =$D$4*Value_pt*(S69-Eff_today) -> 120 | U69: =T69-Cost_A -> -1.7462298e-09 | V69: =V68+U69 -> 500 | W69: =W68+W_gain -> 94 | X69: =Liq_today-V69 -> 120 | Y69: =Pre_A+MAX(X33:X68) -> 590 | Z69: =IF(AND(Z68=1,AD68>=Pre_A,AE68>=W_min),1,0) -> 0 | AA69: =AA68+Close_A*(Ceil_E-AA68)-$E$5 -> 81 | AB69: =$E$4*Value_pt*(AA69-Eff_today) -> 100 | AC69: =AB69-Cost_A -> -20 | AD69: =AD68+AC69 -> -200 | AE69: =AE68+W_gain -> 94 | AF69: =Liq_today-AD69 -> 820 | AG69: =Pre_A+MAX(AF33:AF68) -> 1270
A70: 37 | B70: =IF(AND(B69=1,F69>=Pre_A,G69>=W_min),1,0) -> 0 | C70: =C69+Close_A*(Ceil_E-C69)-$B$5 -> 85 | D70: =$B$4*Value_pt*(C70-Eff_today) -> 0 | E70: =D70-Cost_A -> -120 | F70: =F69+E70 -> -3820 | G70: =G69+W_gain -> 95 | H70: =Liq_today-F70 -> 4440 | I70: =Pre_A+MAX(H33:H69) -> 4790 | J70: =IF(AND(J69=1,N69>=Pre_A,O69>=W_min),1,0) -> 1 | K70: =K69+Close_A*(Ceil_E-K69)-$C$5 -> 85 | L70: =$C$4*Value_pt*(K70-Eff_today) -> 140 | M70: =L70-Cost_A -> 20 | N70: =N69+M70 -> 1220 | O70: =O69+W_gain -> 95 | P70: =Liq_today-N70 -> -600 | Q70: =Pre_A+MAX(P33:P69) -> 535 | R70: =IF(AND(R69=1,V69>=Pre_A,W69>=W_min),1,0) -> 1 | S70: =S69+Close_A*(Ceil_E-S69)-$D$5 -> 83 | T70: =$D$4*Value_pt*(S70-Eff_today) -> 120 | U70: =T70-Cost_A -> -8.7311491e-10 | V70: =V69+U70 -> 500 | W70: =W69+W_gain -> 95 | X70: =Liq_today-V70 -> 120 | Y70: =Pre_A+MAX(X33:X69) -> 590 | Z70: =IF(AND(Z69=1,AD69>=Pre_A,AE69>=W_min),1,0) -> 0 | AA70: =AA69+Close_A*(Ceil_E-AA69)-$E$5 -> 81 | AB70: =$E$4*Value_pt*(AA70-Eff_today) -> 100 | AC70: =AB70-Cost_A -> -20 | AD70: =AD69+AC70 -> -220 | AE70: =AE69+W_gain -> 95 | AF70: =Liq_today-AD70 -> 840 | AG70: =Pre_A+MAX(AF33:AF69) -> 1290
A71: 38 | B71: =IF(AND(B70=1,F70>=Pre_A,G70>=W_min),1,0) -> 0 | C71: =C70+Close_A*(Ceil_E-C70)-$B$5 -> 85 | D71: =$B$4*Value_pt*(C71-Eff_today) -> 0 | E71: =D71-Cost_A -> -120 | F71: =F70+E71 -> -3940 | G71: =G70+W_gain -> 96 | H71: =Liq_today-F71 -> 4560 | I71: =Pre_A+MAX(H33:H70) -> 4910 | J71: =IF(AND(J70=1,N70>=Pre_A,O70>=W_min),1,0) -> 1 | K71: =K70+Close_A*(Ceil_E-K70)-$C$5 -> 85 | L71: =$C$4*Value_pt*(K71-Eff_today) -> 140 | M71: =L71-Cost_A -> 20 | N71: =N70+M71 -> 1240 | O71: =O70+W_gain -> 96 | P71: =Liq_today-N71 -> -620 | Q71: =Pre_A+MAX(P33:P70) -> 535 | R71: =IF(AND(R70=1,V70>=Pre_A,W70>=W_min),1,0) -> 1 | S71: =S70+Close_A*(Ceil_E-S70)-$D$5 -> 83 | T71: =$D$4*Value_pt*(S71-Eff_today) -> 120 | U71: =T71-Cost_A -> -4.3655746e-10 | V71: =V70+U71 -> 500 | W71: =W70+W_gain -> 96 | X71: =Liq_today-V71 -> 120 | Y71: =Pre_A+MAX(X33:X70) -> 590 | Z71: =IF(AND(Z70=1,AD70>=Pre_A,AE70>=W_min),1,0) -> 0 | AA71: =AA70+Close_A*(Ceil_E-AA70)-$E$5 -> 81 | AB71: =$E$4*Value_pt*(AA71-Eff_today) -> 100 | AC71: =AB71-Cost_A -> -20 | AD71: =AD70+AC71 -> -240 | AE71: =AE70+W_gain -> 96 | AF71: =Liq_today-AD71 -> 860 | AG71: =Pre_A+MAX(AF33:AF70) -> 1310
A72: 39 | B72: =IF(AND(B71=1,F71>=Pre_A,G71>=W_min),1,0) -> 0 | C72: =C71+Close_A*(Ceil_E-C71)-$B$5 -> 85 | D72: =$B$4*Value_pt*(C72-Eff_today) -> 0 | E72: =D72-Cost_A -> -120 | F72: =F71+E72 -> -4060 | G72: =G71+W_gain -> 97 | H72: =Liq_today-F72 -> 4680 | I72: =Pre_A+MAX(H33:H71) -> 5030 | J72: =IF(AND(J71=1,N71>=Pre_A,O71>=W_min),1,0) -> 1 | K72: =K71+Close_A*(Ceil_E-K71)-$C$5 -> 85 | L72: =$C$4*Value_pt*(K72-Eff_today) -> 140 | M72: =L72-Cost_A -> 20 | N72: =N71+M72 -> 1260 | O72: =O71+W_gain -> 97 | P72: =Liq_today-N72 -> -640 | Q72: =Pre_A+MAX(P33:P71) -> 535 | R72: =IF(AND(R71=1,V71>=Pre_A,W71>=W_min),1,0) -> 1 | S72: =S71+Close_A*(Ceil_E-S71)-$D$5 -> 83 | T72: =$D$4*Value_pt*(S72-Eff_today) -> 120 | U72: =T72-Cost_A -> -2.1827873e-10 | V72: =V71+U72 -> 500 | W72: =W71+W_gain -> 97 | X72: =Liq_today-V72 -> 120 | Y72: =Pre_A+MAX(X33:X71) -> 590 | Z72: =IF(AND(Z71=1,AD71>=Pre_A,AE71>=W_min),1,0) -> 0 | AA72: =AA71+Close_A*(Ceil_E-AA71)-$E$5 -> 81 | AB72: =$E$4*Value_pt*(AA72-Eff_today) -> 100 | AC72: =AB72-Cost_A -> -20 | AD72: =AD71+AC72 -> -260 | AE72: =AE71+W_gain -> 97 | AF72: =Liq_today-AD72 -> 880 | AG72: =Pre_A+MAX(AF33:AF71) -> 1330
A73: 40 | B73: =IF(AND(B72=1,F72>=Pre_A,G72>=W_min),1,0) -> 0 | C73: =C72+Close_A*(Ceil_E-C72)-$B$5 -> 85 | D73: =$B$4*Value_pt*(C73-Eff_today) -> 0 | E73: =D73-Cost_A -> -120 | F73: =F72+E73 -> -4180 | G73: =G72+W_gain -> 98 | H73: =Liq_today-F73 -> 4800 | I73: =Pre_A+MAX(H33:H72) -> 5150 | J73: =IF(AND(J72=1,N72>=Pre_A,O72>=W_min),1,0) -> 1 | K73: =K72+Close_A*(Ceil_E-K72)-$C$5 -> 85 | L73: =$C$4*Value_pt*(K73-Eff_today) -> 140 | M73: =L73-Cost_A -> 20 | N73: =N72+M73 -> 1280 | O73: =O72+W_gain -> 98 | P73: =Liq_today-N73 -> -660 | Q73: =Pre_A+MAX(P33:P72) -> 535 | R73: =IF(AND(R72=1,V72>=Pre_A,W72>=W_min),1,0) -> 1 | S73: =S72+Close_A*(Ceil_E-S72)-$D$5 -> 83 | T73: =$D$4*Value_pt*(S73-Eff_today) -> 120 | U73: =T73-Cost_A -> -1.0913936e-10 | V73: =V72+U73 -> 500 | W73: =W72+W_gain -> 98 | X73: =Liq_today-V73 -> 120 | Y73: =Pre_A+MAX(X33:X72) -> 590 | Z73: =IF(AND(Z72=1,AD72>=Pre_A,AE72>=W_min),1,0) -> 0 | AA73: =AA72+Close_A*(Ceil_E-AA72)-$E$5 -> 81 | AB73: =$E$4*Value_pt*(AA73-Eff_today) -> 100 | AC73: =AB73-Cost_A -> -20 | AD73: =AD72+AC73 -> -280 | AE73: =AE72+W_gain -> 98 | AF73: =Liq_today-AD73 -> 900 | AG73: =Pre_A+MAX(AF33:AF72) -> 1350

Sheet Reachability
A1: Explore reachability: every program of up to four moves, grown breadth first (Theorem 6.4; Online Appendix Remark 6.B.3; AXIOM Lab 1.6, step 4)
A2: R_k: the states reached by programs of at most k moves (Definition 6.9). A row is a new state when its program runs and no earlier row reached the same state; grey rows do not run. Change the targets and the cushion to tighten or loosen the goal.
A3: Goal | B3: Value
A4: Technology target | B4: =Target_T -> 70
A5: Cushion over the floor required ($ million) | B5: 0
A6: Efficiency target | B6: =Target_E -> 80
A7: Depth k | B7: 0 | C7: 1 | D7: 2 | E7: 3 | F7: 4
A8: States in R_k | B8: =SUMPRODUCT(($B$35:$B$375<=0)*($R$35:$R$375=1)) -> 1 | C8: =SUMPRODUCT(($B$35:$B$375<=1)*($R$35:$R$375=1)) -> 5 | D8: =SUMPRODUCT(($B$35:$B$375<=2)*($R$35:$R$375=1)) -> 13 | E8: =SUMPRODUCT(($B$35:$B$375<=3)*($R$35:$R$375=1)) -> 21 | F8: =SUMPRODUCT(($B$35:$B$375<=4)*($R$35:$R$375=1)) -> 28
A9: Programs of length k that run | B9: =SUMIFS($L$35:$L$375,$B$35:$B$375,0) -> 1 | C9: =SUMIFS($L$35:$L$375,$B$35:$B$375,1) -> 4 | D9: =SUMIFS($L$35:$L$375,$B$35:$B$375,2) -> 9 | E9: =SUMIFS($L$35:$L$375,$B$35:$B$375,3) -> 12 | F9: =SUMIFS($L$35:$L$375,$B$35:$B$375,4) -> 11
A10: Highest technology in R_k | B10: =_xlfn.MAXIFS($N$35:$N$375,$L$35:$L$375,1,$B$35:$B$375,"<="&0) -> 41 | C10: =_xlfn.MAXIFS($N$35:$N$375,$L$35:$L$375,1,$B$35:$B$375,"<="&1) -> 75.634669 | D10: =_xlfn.MAXIFS($N$35:$N$375,$L$35:$L$375,1,$B$35:$B$375,"<="&2) -> 75.634669 | E10: =_xlfn.MAXIFS($N$35:$N$375,$L$35:$L$375,1,$B$35:$B$375,"<="&3) -> 75.634669 | F10: =_xlfn.MAXIFS($N$35:$N$375,$L$35:$L$375,1,$B$35:$B$375,"<="&4) -> 75.634669
A12: Programs of five moves that run (closure: R_5 = R_4 when zero) | B12: =SUM($T$35:$T$375) -> 0
A13: First depth at which the goal is met | B13: =IF(COUNTIFS($L$35:$L$375,1,$N$35:$N$375,">="&($B$4-0.000000001),$P$35:$P$375,">="&($B$6-0.000000001),$M$35:$M$375,">="&(Floor_q+$B$5-0.000000001))=0,"not reachable",_xlfn.MINIFS($B$35:$B$375,$L$35:$L$375,1,$N$35:$N$375,">="&($B$4-0.000000001),$P$35:$P$375,">="&($B$6-0.000000001),$M$35:$M$375,">="&(Floor_q+$B$5-0.000000001))) -> 2
A14: Programs that meet the goal | B14: =COUNTIFS($L$35:$L$375,1,$N$35:$N$375,">="&($B$4-0.000000001),$P$35:$P$375,">="&($B$6-0.000000001),$M$35:$M$375,">="&(Floor_q+$B$5-0.000000001)) -> 7
A15: Distinct states that meet the goal | B15: =SUMPRODUCT(($R$35:$R$375=1)*($N$35:$N$375>=$B$4-0.000000001)*($P$35:$P$375>=$B$6-0.000000001)*($M$35:$M$375>=Floor_q+$B$5-0.000000001)) -> 5
A16: Liquidity of the best state that meets the goal | B16: =IF(B14=0,"none",_xlfn.MAXIFS($M$35:$M$375,$L$35:$L$375,1,$N$35:$N$375,">="&($B$4-0.000000001),$P$35:$P$375,">="&($B$6-0.000000001),$M$35:$M$375,">="&(Floor_q+$B$5-0.000000001))) -> 556.63273
A17: Largest cushion with which the target stays reachable | B17: =_xlfn.MAXIFS($M$35:$M$375,$L$35:$L$375,1,$N$35:$N$375,">="&($B$4-0.000000001),$P$35:$P$375,">="&($B$6-0.000000001))-Floor_q -> 206.63273
A18: Highest technology the repertoire can reach | B18: =_xlfn.MAXIFS($N$35:$N$375,$L$35:$L$375,1) -> 75.634669
A19: Technology levels it can reach: distinct values | B19: =IF(COUNTIFS($L$35:$L$375,1,$N$35:$N$375,">="&36.85,$N$35:$N$375,"<"&36.95)>0,36.9,"") -> 36.9 | C19: =IF(COUNTIFS($L$35:$L$375,1,$N$35:$N$375,">="&40.95,$N$35:$N$375,"<"&41.05)>0,41,"") -> 41 | D19: =IF(COUNTIFS($L$35:$L$375,1,$N$35:$N$375,">="&68.05,$N$35:$N$375,"<"&68.15)>0,68.1,"") -> 68.1 | E19: =IF(COUNTIFS($L$35:$L$375,1,$N$35:$N$375,">="&71.45,$N$35:$N$375,"<"&71.55)>0,71.5,"") -> 71.5 | F19: =IF(COUNTIFS($L$35:$L$375,1,$N$35:$N$375,">="&75.55,$N$35:$N$375,"<"&75.65)>0,75.6,"") -> 75.6
A21: Complete goal: efficiency within eps of the ceiling of 85 (Remark 6.B.3) | B21: Tolerance eps | C21: Rounds needed | D21: Efficiency then | E21: One round fewer
A22: recycled rounds: efficiency 85 - 14 x 0.5^k never reaches 85 | B22: 2 | C22: =ROUNDUP(LN((Ceil_E-Eff_today)/B22)/LN(1/(1-Close_A)),0) -> 3 | D22: =Ceil_E-(Ceil_E-Eff_today)*(1-Close_A)^C22 -> 83.25 | E22: =Ceil_E-(Ceil_E-Eff_today)*(1-Close_A)^(C22-1) -> 81.5
A23: recycled rounds: efficiency 85 - 14 x 0.5^k never reaches 85 | B23: 1 | C23: =ROUNDUP(LN((Ceil_E-Eff_today)/B23)/LN(1/(1-Close_A)),0) -> 4 | D23: =Ceil_E-(Ceil_E-Eff_today)*(1-Close_A)^C23 -> 84.125 | E23: =Ceil_E-(Ceil_E-Eff_today)*(1-Close_A)^(C23-1) -> 83.25
A24: recycled rounds: efficiency 85 - 14 x 0.5^k never reaches 85 | B24: 0.5 | C24: =ROUNDUP(LN((Ceil_E-Eff_today)/B24)/LN(1/(1-Close_A)),0) -> 5 | D24: =Ceil_E-(Ceil_E-Eff_today)*(1-Close_A)^C24 -> 84.5625 | E24: =Ceil_E-(Ceil_E-Eff_today)*(1-Close_A)^(C24-1) -> 84.125
A25: recycled rounds: efficiency 85 - 14 x 0.5^k never reaches 85 | B25: 0.25 | C25: =ROUNDUP(LN((Ceil_E-Eff_today)/B25)/LN(1/(1-Close_A)),0) -> 6 | D25: =Ceil_E-(Ceil_E-Eff_today)*(1-Close_A)^C25 -> 84.78125 | E25: =Ceil_E-(Ceil_E-Eff_today)*(1-Close_A)^(C25-1) -> 84.5625
A26: recycled rounds: efficiency 85 - 14 x 0.5^k never reaches 85 | B26: 0.1 | C26: =ROUNDUP(LN((Ceil_E-Eff_today)/B26)/LN(1/(1-Close_A)),0) -> 8 | D26: =Ceil_E-(Ceil_E-Eff_today)*(1-Close_A)^C26 -> 84.945312 | E26: =Ceil_E-(Ceil_E-Eff_today)*(1-Close_A)^(C26-1) -> 84.890625
A27: Extra rounds when the tolerance halves, log 2 / log(1/L) | C27: =LN(2)/LN(1/(1-Close_A)) -> 1
A29: Theorem 6.4(iii): T x = x/2 from 1; the target {0} itself is never reached | B29: Tolerance eps | C29: Steps to [0, eps] | D29: x then
A30: steps until x is within eps of 0 | B30: 0.1 | C30: =ROUNDUP(LOG(1/B30,2),0) -> 4 | D30: =0.5^C30 -> 0.0625
A31: steps until x is within eps of 0 | B31: 0.01 | C31: =ROUNDUP(LOG(1/B31,2),0) -> 7 | D31: =0.5^C31 -> 0.0078125
A32: steps until x is within eps of 0 | B32: 0.001 | C32: =ROUNDUP(LOG(1/B32,2),0) -> 10 | D32: =0.5^C32 -> 0.0009765625
A34: Program (word) | B34: Depth | C34: Parent row | D34: Move code | E34: Parent runs | F34: Parent liquidity | G34: Parent technology | H34: Parent workforce | I34: Parent efficiency | J34: Parent sold | K34: Move possible | L34: Program runs | M34: Liquidity | N34: Technology | O34: Workforce | P34: Efficiency | Q34: Sold | R34: New state | S34: Meets the goal | T34: Moves that can follow (depth 4) | U34: Parent built | V34: Built
A35: today | B35: 0 | L35: 1 | M35: =Liq_today -> 620 | N35: =Tech_today -> 41 | O35: =W_today -> 58 | P35: =Eff_today -> 71 | Q35: =Operators!F4 -> 0 | R35: 1 | S35: =IF(AND(L35=1,N35>=$B$4-0.000000001,P35>=$B$6-0.000000001,M35>=Floor_q+$B$5-0.000000001),1,0) -> 0 | V35: =Operators!G4 -> 0
A36: S | B36: 1 | C36: 35 | D36: 1 | E36: =L35 -> 1 | F36: =M35 -> 620 | G36: =N35 -> 41 | H36: =O35 -> 58 | I36: =P35 -> 71 | J36: =Q35 -> 0 | K36: =IF(D36<=2,1-J36,IF(D36=3,IF(AND(U36=0,H36>=W_min,F36-D_dip>=Floor_q),1,0),IF(AND(H36>=W_min,F36>=Pre_A),1,0))) -> 1 | L36: =E36*K36 -> 1 | M36: =CHOOSE(D36,F36+Proc_S,F36+Proc_Sk,F36+D_dL,F36-Cost_A) -> 732 | N36: =CHOOSE(D36,(1-Tech_share)*G36,(1-Tech_share)*G36,G36+D_dT,G36) -> 36.9 | O36: =CHOOSE(D36,H36-W_lost,H36,H36,H36+W_gain) -> 53 | P36: =CHOOSE(D36,I36,I36,I36+D_dE,I36+Close_A*(Ceil_E-I36)) -> 71 | Q36: =CHOOSE(D36,1,1,J36,J36) -> 1 | R36: =IF(L36=1,IF(SUMPRODUCT(($L$35:$L$35=1)*(ABS($M$35:$M$35-M36)<0.000001)*(ABS($N$35:$N$35-N36)<0.000001)*($O$35:$O$35=O36)*(ABS($P$35:$P$35-P36)<0.000001)*($Q$35:$Q$35=Q36)*($V$35:$V$35=V36))=0,1,0),0) -> 1 | S36: =IF(AND(L36=1,N36>=$B$4-0.000000001,P36>=$B$6-0.000000001,M36>=Floor_q+$B$5-0.000000001),1,0) -> 0 | U36: =V35 -> 0 | V36: =CHOOSE(D36,U36,U36,1,U36) -> 0
A37: S* | B37: 1 | C37: 35 | D37: 2 | E37: =L35 -> 1 | F37: =M35 -> 620 | G37: =N35 -> 41 | H37: =O35 -> 58 | I37: =P35 -> 71 | J37: =Q35 -> 0 | K37: =IF(D37<=2,1-J37,IF(D37=3,IF(AND(U37=0,H37>=W_min,F37-D_dip>=Floor_q),1,0),IF(AND(H37>=W_min,F37>=Pre_A),1,0))) -> 1 | L37: =E37*K37 -> 1 | M37: =CHOOSE(D37,F37+Proc_S,F37+Proc_Sk,F37+D_dL,F37-Cost_A) -> 712 | N37: =CHOOSE(D37,(1-Tech_share)*G37,(1-Tech_share)*G37,G37+D_dT,G37) -> 36.9 | O37: =CHOOSE(D37,H37-W_lost,H37,H37,H37+W_gain) -> 58 | P37: =CHOOSE(D37,I37,I37,I37+D_dE,I37+Close_A*(Ceil_E-I37)) -> 71 | Q37: =CHOOSE(D37,1,1,J37,J37) -> 1 | R37: =IF(L37=1,IF(SUMPRODUCT(($L$35:$L$36=1)*(ABS($M$35:$M$36-M37)<0.000001)*(ABS($N$35:$N$36-N37)<0.000001)*($O$35:$O$36=O37)*(ABS($P$35:$P$36-P37)<0.000001)*($Q$35:$Q$36=Q37)*($V$35:$V$36=V37))=0,1,0),0) -> 1 | S37: =IF(AND(L37=1,N37>=$B$4-0.000000001,P37>=$B$6-0.000000001,M37>=Floor_q+$B$5-0.000000001),1,0) -> 0 | U37: =V35 -> 0 | V37: =CHOOSE(D37,U37,U37,1,U37) -> 0
A38: D | B38: 1 | C38: 35 | D38: 3 | E38: =L35 -> 1 | F38: =M35 -> 620 | G38: =N35 -> 41 | H38: =O35 -> 58 | I38: =P35 -> 71 | J38: =Q35 -> 0 | K38: =IF(D38<=2,1-J38,IF(D38=3,IF(AND(U38=0,H38>=W_min,F38-D_dip>=Floor_q),1,0),IF(AND(H38>=W_min,F38>=Pre_A),1,0))) -> 1 | L38: =E38*K38 -> 1 | M38: =CHOOSE(D38,F38+Proc_S,F38+Proc_Sk,F38+D_dL,F38-Cost_A) -> 584.63273 | N38: =CHOOSE(D38,(1-Tech_share)*G38,(1-Tech_share)*G38,G38+D_dT,G38) -> 75.634669 | O38: =CHOOSE(D38,H38-W_lost,H38,H38,H38+W_gain) -> 58 | P38: =CHOOSE(D38,I38,I38,I38+D_dE,I38+Close_A*(Ceil_E-I38)) -> 73.598331 | Q38: =CHOOSE(D38,1,1,J38,J38) -> 0 | R38: =IF(L38=1,IF(SUMPRODUCT(($L$35:$L$37=1)*(ABS($M$35:$M$37-M38)<0.000001)*(ABS($N$35:$N$37-N38)<0.000001)*($O$35:$O$37=O38)*(ABS($P$35:$P$37-P38)<0.000001)*($Q$35:$Q$37=Q38)*($V$35:$V$37=V38))=0,1,0),0) -> 1 | S38: =IF(AND(L38=1,N38>=$B$4-0.000000001,P38>=$B$6-0.000000001,M38>=Floor_q+$B$5-0.000000001),1,0) -> 0 | U38: =V35 -> 0 | V38: =CHOOSE(D38,U38,U38,1,U38) -> 1
A39: A | B39: 1 | C39: 35 | D39: 4 | E39: =L35 -> 1 | F39: =M35 -> 620 | G39: =N35 -> 41 | H39: =O35 -> 58 | I39: =P35 -> 71 | J39: =Q35 -> 0 | K39: =IF(D39<=2,1-J39,IF(D39=3,IF(AND(U39=0,H39>=W_min,F39-D_dip>=Floor_q),1,0),IF(AND(H39>=W_min,F39>=Pre_A),1,0))) -> 1 | L39: =E39*K39 -> 1 | M39: =CHOOSE(D39,F39+Proc_S,F39+Proc_Sk,F39+D_dL,F39-Cost_A) -> 500 | N39: =CHOOSE(D39,(1-Tech_share)*G39,(1-Tech_share)*G39,G39+D_dT,G39) -> 41 | O39: =CHOOSE(D39,H39-W_lost,H39,H39,H39+W_gain) -> 59 | P39: =CHOOSE(D39,I39,I39,I39+D_dE,I39+Close_A*(Ceil_E-I39)) -> 78 | Q39: =CHOOSE(D39,1,1,J39,J39) -> 0 | R39: =IF(L39=1,IF(SUMPRODUCT(($L$35:$L$38=1)*(ABS($M$35:$M$38-M39)<0.000001)*(ABS($N$35:$N$38-N39)<0.000001)*($O$35:$O$38=O39)*(ABS($P$35:$P$38-P39)<0.000001)*($Q$35:$Q$38=Q39)*($V$35:$V$38=V39))=0,1,0),0) -> 1 | S39: =IF(AND(L39=1,N39>=$B$4-0.000000001,P39>=$B$6-0.000000001,M39>=Floor_q+$B$5-0.000000001),1,0) -> 0 | U39: =V35 -> 0 | V39: =CHOOSE(D39,U39,U39,1,U39) -> 0
A40: S S | B40: 2 | C40: 36 | D40: 1 | E40: =L36 -> 1 | F40: =M36 -> 732 | G40: =N36 -> 36.9 | H40: =O36 -> 53 | I40: =P36 -> 71 | J40: =Q36 -> 1 | K40: =IF(D40<=2,1-J40,IF(D40=3,IF(AND(U40=0,H40>=W_min,F40-D_dip>=Floor_q),1,0),IF(AND(H40>=W_min,F40>=Pre_A),1,0))) -> 0 | L40: =E40*K40 -> 0 | M40: =CHOOSE(D40,F40+Proc_S,F40+Proc_Sk,F40+D_dL,F40-Cost_A) -> 844 | N40: =CHOOSE(D40,(1-Tech_share)*G40,(1-Tech_share)*G40,G40+D_dT,G40) -> 33.21 | O40: =CHOOSE(D40,H40-W_lost,H40,H40,H40+W_gain) -> 48 | P40: =CHOOSE(D40,I40,I40,I40+D_dE,I40+Close_A*(Ceil_E-I40)) -> 71 | Q40: =CHOOSE(D40,1,1,J40,J40) -> 1 | R40: =IF(L40=1,IF(SUMPRODUCT(($L$35:$L$39=1)*(ABS($M$35:$M$39-M40)<0.000001)*(ABS($N$35:$N$39-N40)<0.000001)*($O$35:$O$39=O40)*(ABS($P$35:$P$39-P40)<0.000001)*($Q$35:$Q$39=Q40)*($V$35:$V$39=V40))=0,1,0),0) -> 0 | S40: =IF(AND(L40=1,N40>=$B$4-0.000000001,P40>=$B$6-0.000000001,M40>=Floor_q+$B$5-0.000000001),1,0) -> 0 | U40: =V36 -> 0 | V40: =CHOOSE(D40,U40,U40,1,U40) -> 0
A41: S S* | B41: 2 | C41: 36 | D41: 2 | E41: =L36 -> 1 | F41: =M36 -> 732 | G41: =N36 -> 36.9 | H41: =O36 -> 53 | I41: =P36 -> 71 | J41: =Q36 -> 1 | K41: =IF(D41<=2,1-J41,IF(D41=3,IF(AND(U41=0,H41>=W_min,F41-D_dip>=Floor_q),1,0),IF(AND(H41>=W_min,F41>=Pre_A),1,0))) -> 0 | L41: =E41*K41 -> 0 | M41: =CHOOSE(D41,F41+Proc_S,F41+Proc_Sk,F41+D_dL,F41-Cost_A) -> 824 | N41: =CHOOSE(D41,(1-Tech_share)*G41,(1-Tech_share)*G41,G41+D_dT,G41) -> 33.21 | O41: =CHOOSE(D41,H41-W_lost,H41,H41,H41+W_gain) -> 53 | P41: =CHOOSE(D41,I41,I41,I41+D_dE,I41+Close_A*(Ceil_E-I41)) -> 71 | Q41: =CHOOSE(D41,1,1,J41,J41) -> 1 | R41: =IF(L41=1,IF(SUMPRODUCT(($L$35:$L$40=1)*(ABS($M$35:$M$40-M41)<0.000001)*(ABS($N$35:$N$40-N41)<0.000001)*($O$35:$O$40=O41)*(ABS($P$35:$P$40-P41)<0.000001)*($Q$35:$Q$40=Q41)*($V$35:$V$40=V41))=0,1,0),0) -> 0 | S41: =IF(AND(L41=1,N41>=$B$4-0.000000001,P41>=$B$6-0.000000001,M41>=Floor_q+$B$5-0.000000001),1,0) -> 0 | U41: =V36 -> 0 | V41: =CHOOSE(D41,U41,U41,1,U41) -> 0
A42: S D | B42: 2 | C42: 36 | D42: 3 | E42: =L36 -> 1 | F42: =M36 -> 732 | G42: =N36 -> 36.9 | H42: =O36 -> 53 | I42: =P36 -> 71 | J42: =Q36 -> 1 | K42: =IF(D42<=2,1-J42,IF(D42=3,IF(AND(U42=0,H42>=W_min,F42-D_dip>=Floor_q),1,0),IF(AND(H42>=W_min,F42>=Pre_A),1,0))) -> 0 | L42: =E42*K42 -> 0 | M42: =CHOOSE(D42,F42+Proc_S,F42+Proc_Sk,F42+D_dL,F42-Cost_A) -> 696.63273 | N42: =CHOOSE(D42,(1-Tech_share)*G42,(1-Tech_share)*G42,G42+D_dT,G42) -> 71.534669 | O42: =CHOOSE(D42,H42-W_lost,H42,H42,H42+W_gain) -> 53 | P42: =CHOOSE(D42,I42,I42,I42+D_dE,I42+Close_A*(Ceil_E-I42)) -> 73.598331 | Q42: =CHOOSE(D42,1,1,J42,J42) -> 1 | R42: =IF(L42=1,IF(SUMPRODUCT(($L$35:$L$41=1)*(ABS($M$35:$M$41-M42)<0.000001)*(ABS($N$35:$N$41-N42)<0.000001)*($O$35:$O$41=O42)*(ABS($P$35:$P$41-P42)<0.000001)*($Q$35:$Q$41=Q42)*($V$35:$V$41=V42))=0,1,0),0) -> 0 | S42: =IF(AND(L42=1,N42>=$B$4-0.000000001,P42>=$B$6-0.000000001,M42>=Floor_q+$B$5-0.000000001),1,0) -> 0 | U42: =V36 -> 0 | V42: =CHOOSE(D42,U42,U42,1,U42) -> 1
A43: S A | B43: 2 | C43: 36 | D43: 4 | E43: =L36 -> 1 | F43: =M36 -> 732 | G43: =N36 -> 36.9 | H43: =O36 -> 53 | I43: =P36 -> 71 | J43: =Q36 -> 1 | K43: =IF(D43<=2,1-J43,IF(D43=3,IF(AND(U43=0,H43>=W_min,F43-D_dip>=Floor_q),1,0),IF(AND(H43>=W_min,F43>=Pre_A),1,0))) -> 0 | L43: =E43*K43 -> 0 | M43: =CHOOSE(D43,F43+Proc_S,F43+Proc_Sk,F43+D_dL,F43-Cost_A) -> 612 | N43: =CHOOSE(D43,(1-Tech_share)*G43,(1-Tech_share)*G43,G43+D_dT,G43) -> 36.9 | O43: =CHOOSE(D43,H43-W_lost,H43,H43,H43+W_gain) -> 54 | P43: =CHOOSE(D43,I43,I43,I43+D_dE,I43+Close_A*(Ceil_E-I43)) -> 78 | Q43: =CHOOSE(D43,1,1,J43,J43) -> 1 | R43: =IF(L43=1,IF(SUMPRODUCT(($L$35:$L$42=1)*(ABS($M$35:$M$42-M43)<0.000001)*(ABS($N$35:$N$42-N43)<0.000001)*($O$35:$O$42=O43)*(ABS($P$35:$P$42-P43)<0.000001)*($Q$35:$Q$42=Q43)*($V$35:$V$42=V43))=0,1,0),0) -> 0 | S43: =IF(AND(L43=1,N43>=$B$4-0.000000001,P43>=$B$6-0.000000001,M43>=Floor_q+$B$5-0.000000001),1,0) -> 0 | U43: =V36 -> 0 | V43: =CHOOSE(D43,U43,U43,1,U43) -> 0
A44: S* S | B44: 2 | C44: 37 | D44: 1 | E44: =L37 -> 1 | F44: =M37 -> 712 | G44: =N37 -> 36.9 | H44: =O37 -> 58 | I44: =P37 -> 71 | J44: =Q37 -> 1 | K44: =IF(D44<=2,1-J44,IF(D44=3,IF(AND(U44=0,H44>=W_min,F44-D_dip>=Floor_q),1,0),IF(AND(H44>=W_min,F44>=Pre_A),1,0))) -> 0 | L44: =E44*K44 -> 0 | M44: =CHOOSE(D44,F44+Proc_S,F44+Proc_Sk,F44+D_dL,F44-Cost_A) -> 824 | N44: =CHOOSE(D44,(1-Tech_share)*G44,(1-Tech_share)*G44,G44+D_dT,G44) -> 33.21 | O44: =CHOOSE(D44,H44-W_lost,H44,H44,H44+W_gain) -> 53 | P44: =CHOOSE(D44,I44,I44,I44+D_dE,I44+Close_A*(Ceil_E-I44)) -> 71 | Q44: =CHOOSE(D44,1,1,J44,J44) -> 1 | R44: =IF(L44=1,IF(SUMPRODUCT(($L$35:$L$43=1)*(ABS($M$35:$M$43-M44)<0.000001)*(ABS($N$35:$N$43-N44)<0.000001)*($O$35:$O$43=O44)*(ABS($P$35:$P$43-P44)<0.000001)*($Q$35:$Q$43=Q44)*($V$35:$V$43=V44))=0,1,0),0) -> 0 | S44: =IF(AND(L44=1,N44>=$B$4-0.000000001,P44>=$B$6-0.000000001,M44>=Floor_q+$B$5-0.000000001),1,0) -> 0 | U44: =V37 -> 0 | V44: =CHOOSE(D44,U44,U44,1,U44) -> 0
A45: S* S* | B45: 2 | C45: 37 | D45: 2 | E45: =L37 -> 1 | F45: =M37 -> 712 | G45: =N37 -> 36.9 | H45: =O37 -> 58 | I45: =P37 -> 71 | J45: =Q37 -> 1 | K45: =IF(D45<=2,1-J45,IF(D45=3,IF(AND(U45=0,H45>=W_min,F45-D_dip>=Floor_q),1,0),IF(AND(H45>=W_min,F45>=Pre_A),1,0))) -> 0 | L45: =E45*K45 -> 0 | M45: =CHOOSE(D45,F45+Proc_S,F45+Proc_Sk,F45+D_dL,F45-Cost_A) -> 804 | N45: =CHOOSE(D45,(1-Tech_share)*G45,(1-Tech_share)*G45,G45+D_dT,G45) -> 33.21 | O45: =CHOOSE(D45,H45-W_lost,H45,H45,H45+W_gain) -> 58 | P45: =CHOOSE(D45,I45,I45,I45+D_dE,I45+Close_A*(Ceil_E-I45)) -> 71 | Q45: =CHOOSE(D45,1,1,J45,J45) -> 1 | R45: =IF(L45=1,IF(SUMPRODUCT(($L$35:$L$44=1)*(ABS($M$35:$M$44-M45)<0.000001)*(ABS($N$35:$N$44-N45)<0.000001)*($O$35:$O$44=O45)*(ABS($P$35:$P$44-P45)<0.000001)*($Q$35:$Q$44=Q45)*($V$35:$V$44=V45))=0,1,0),0) -> 0 | S45: =IF(AND(L45=1,N45>=$B$4-0.000000001,P45>=$B$6-0.000000001,M45>=Floor_q+$B$5-0.000000001),1,0) -> 0 | U45: =V37 -> 0 | V45: =CHOOSE(D45,U45,U45,1,U45) -> 0
A46: S* D | B46: 2 | C46: 37 | D46: 3 | E46: =L37 -> 1 | F46: =M37 -> 712 | G46: =N37 -> 36.9 | H46: =O37 -> 58 | I46: =P37 -> 71 | J46: =Q37 -> 1 | K46: =IF(D46<=2,1-J46,IF(D46=3,IF(AND(U46=0,H46>=W_min,F46-D_dip>=Floor_q),1,0),IF(AND(H46>=W_min,F46>=Pre_A),1,0))) -> 1 | L46: =E46*K46 -> 1 | M46: =CHOOSE(D46,F46+Proc_S,F46+Proc_Sk,F46+D_dL,F46-Cost_A) -> 676.63273 | N46: =CHOOSE(D46,(1-Tech_share)*G46,(1-Tech_share)*G46,G46+D_dT,G46) -> 71.534669 | O46: =CHOOSE(D46,H46-W_lost,H46,H46,H46+W_gain) -> 58 | P46: =CHOOSE(D46,I46,I46,I46+D_dE,I46+Close_A*(Ceil_E-I46)) -> 73.598331 | Q46: =CHOOSE(D46,1,1,J46,J46) -> 1 | R46: =IF(L46=1,IF(SUMPRODUCT(($L$35:$L$45=1)*(ABS($M$35:$M$45-M46)<0.000001)*(ABS($N$35:$N$45-N46)<0.000001)*($O$35:$O$45=O46)*(ABS($P$35:$P$45-P46)<0.000001)*($Q$35:$Q$45=Q46)*($V$35:$V$45=V46))=0,1,0),0) -> 1 | S46: =IF(AND(L46=1,N46>=$B$4-0.000000001,P46>=$B$6-0.000000001,M46>=Floor_q+$B$5-0.000000001),1,0) -> 0 | U46: =V37 -> 0 | V46: =CHOOSE(D46,U46,U46,1,U46) -> 1
A47: S* A | B47: 2 | C47: 37 | D47: 4 | E47: =L37 -> 1 | F47: =M37 -> 712 | G47: =N37 -> 36.9 | H47: =O37 -> 58 | I47: =P37 -> 71 | J47: =Q37 -> 1 | K47: =IF(D47<=2,1-J47,IF(D47=3,IF(AND(U47=0,H47>=W_min,F47-D_dip>=Floor_q),1,0),IF(AND(H47>=W_min,F47>=Pre_A),1,0))) -> 1 | L47: =E47*K47 -> 1 | M47: =CHOOSE(D47,F47+Proc_S,F47+Proc_Sk,F47+D_dL,F47-Cost_A) -> 592 | N47: =CHOOSE(D47,(1-Tech_share)*G47,(1-Tech_share)*G47,G47+D_dT,G47) -> 36.9 | O47: =CHOOSE(D47,H47-W_lost,H47,H47,H47+W_gain) -> 59 | P47: =CHOOSE(D47,I47,I47,I47+D_dE,I47+Close_A*(Ceil_E-I47)) -> 78 | Q47: =CHOOSE(D47,1,1,J47,J47) -> 1 | R47: =IF(L47=1,IF(SUMPRODUCT(($L$35:$L$46=1)*(ABS($M$35:$M$46-M47)<0.000001)*(ABS($N$35:$N$46-N47)<0.000001)*($O$35:$O$46=O47)*(ABS($P$35:$P$46-P47)<0.000001)*($Q$35:$Q$46=Q47)*($V$35:$V$46=V47))=0,1,0),0) -> 1 | S47: =IF(AND(L47=1,N47>=$B$4-0.000000001,P47>=$B$6-0.000000001,M47>=Floor_q+$B$5-0.000000001),1,0) -> 0 | U47: =V37 -> 0 | V47: =CHOOSE(D47,U47,U47,1,U47) -> 0
A48: D S | B48: 2 | C48: 38 | D48: 1 | E48: =L38 -> 1 | F48: =M38 -> 584.63273 | G48: =N38 -> 75.634669 | H48: =O38 -> 58 | I48: =P38 -> 73.598331 | J48: =Q38 -> 0 | K48: =IF(D48<=2,1-J48,IF(D48=3,IF(AND(U48=0,H48>=W_min,F48-D_dip>=Floor_q),1,0),IF(AND(H48>=W_min,F48>=Pre_A),1,0))) -> 1 | L48: =E48*K48 -> 1 | M48: =CHOOSE(D48,F48+Proc_S,F48+Proc_Sk,F48+D_dL,F48-Cost_A) -> 696.63273 | N48: =CHOOSE(D48,(1-Tech_share)*G48,(1-Tech_share)*G48,G48+D_dT,G48) -> 68.071202 | O48: =CHOOSE(D48,H48-W_lost,H48,H48,H48+W_gain) -> 53 | P48: =CHOOSE(D48,I48,I48,I48+D_dE,I48+Close_A*(Ceil_E-I48)) -> 73.598331 | Q48: =CHOOSE(D48,1,1,J48,J48) -> 1 | R48: =IF(L48=1,IF(SUMPRODUCT(($L$35:$L$47=1)*(ABS($M$35:$M$47-M48)<0.000001)*(ABS($N$35:$N$47-N48)<0.000001)*($O$35:$O$47=O48)*(ABS($P$35:$P$47-P48)<0.000001)*($Q$35:$Q$47=Q48)*($V$35:$V$47=V48))=0,1,0),0) -> 1 | S48: =IF(AND(L48=1,N48>=$B$4-0.000000001,P48>=$B$6-0.000000001,M48>=Floor_q+$B$5-0.000000001),1,0) -> 0 | U48: =V38 -> 1 | V48: =CHOOSE(D48,U48,U48,1,U48) -> 1
A49: D S* | B49: 2 | C49: 38 | D49: 2 | E49: =L38 -> 1 | F49: =M38 -> 584.63273 | G49: =N38 -> 75.634669 | H49: =O38 -> 58 | I49: =P38 -> 73.598331 | J49: =Q38 -> 0 | K49: =IF(D49<=2,1-J49,IF(D49=3,IF(AND(U49=0,H49>=W_min,F49-D_dip>=Floor_q),1,0),IF(AND(H49>=W_min,F49>=Pre_A),1,0))) -> 1 | L49: =E49*K49 -> 1 | M49: =CHOOSE(D49,F49+Proc_S,F49+Proc_Sk,F49+D_dL,F49-Cost_A) -> 676.63273 | N49: =CHOOSE(D49,(1-Tech_share)*G49,(1-Tech_share)*G49,G49+D_dT,G49) -> 68.071202 | O49: =CHOOSE(D49,H49-W_lost,H49,H49,H49+W_gain) -> 58 | P49: =CHOOSE(D49,I49,I49,I49+D_dE,I49+Close_A*(Ceil_E-I49)) -> 73.598331 | Q49: =CHOOSE(D49,1,1,J49,J49) -> 1 | R49: =IF(L49=1,IF(SUMPRODUCT(($L$35:$L$48=1)*(ABS($M$35:$M$48-M49)<0.000001)*(ABS($N$35:$N$48-N49)<0.000001)*($O$35:$O$48=O49)*(ABS($P$35:$P$48-P49)<0.000001)*($Q$35:$Q$48=Q49)*($V$35:$V$48=V49))=0,1,0),0) -> 1 | S49: =IF(AND(L49=1,N49>=$B$4-0.000000001,P49>=$B$6-0.000000001,M49>=Floor_q+$B$5-0.000000001),1,0) -> 0 | U49: =V38 -> 1 | V49: =CHOOSE(D49,U49,U49,1,U49) -> 1
A50: D D | B50: 2 | C50: 38 | D50: 3 | E50: =L38 -> 1 | F50: =M38 -> 584.63273 | G50: =N38 -> 75.634669 | H50: =O38 -> 58 | I50: =P38 -> 73.598331 | J50: =Q38 -> 0 | K50: =IF(D50<=2,1-J50,IF(D50=3,IF(AND(U50=0,H50>=W_min,F50-D_dip>=Floor_q),1,0),IF(AND(H50>=W_min,F50>=Pre_A),1,0))) -> 0 | L50: =E50*K50 -> 0 | M50: =CHOOSE(D50,F50+Proc_S,F50+Proc_Sk,F50+D_dL,F50-Cost_A) -> 549.26546 | N50: =CHOOSE(D50,(1-Tech_share)*G50,(1-Tech_share)*G50,G50+D_dT,G50) -> 110.26934 | O50: =CHOOSE(D50,H50-W_lost,H50,H50,H50+W_gain) -> 58 | P50: =CHOOSE(D50,I50,I50,I50+D_dE,I50+Close_A*(Ceil_E-I50)) -> 76.196662 | Q50: =CHOOSE(D50,1,1,J50,J50) -> 0 | R50: =IF(L50=1,IF(SUMPRODUCT(($L$35:$L$49=1)*(ABS($M$35:$M$49-M50)<0.000001)*(ABS($N$35:$N$49-N50)<0.000001)*($O$35:$O$49=O50)*(ABS($P$35:$P$49-P50)<0.000001)*($Q$35:$Q$49=Q50)*($V$35:$V$49=V50))=0,1,0),0) -> 0 | S50: =IF(AND(L50=1,N50>=$B$4-0.000000001,P50>=$B$6-0.000000001,M50>=Floor_q+$B$5-0.000000001),1,0) -> 0 | U50: =V38 -> 1 | V50: =CHOOSE(D50,U50,U50,1,U50) -> 1
A51: D A | B51: 2 | C51: 38 | D51: 4 | E51: =L38 -> 1 | F51: =M38 -> 584.63273 | G51: =N38 -> 75.634669 | H51: =O38 -> 58 | I51: =P38 -> 73.598331 | J51: =Q38 -> 0 | K51: =IF(D51<=2,1-J51,IF(D51=3,IF(AND(U51=0,H51>=W_min,F51-D_dip>=Floor_q),1,0),IF(AND(H51>=W_min,F51>=Pre_A),1,0))) -> 1 | L51: =E51*K51 -> 1 | M51: =CHOOSE(D51,F51+Proc_S,F51+Proc_Sk,F51+D_dL,F51-Cost_A) -> 464.63273 | N51: =CHOOSE(D51,(1-Tech_share)*G51,(1-Tech_share)*G51,G51+D_dT,G51) -> 75.634669 | O51: =CHOOSE(D51,H51-W_lost,H51,H51,H51+W_gain) -> 59 | P51: =CHOOSE(D51,I51,I51,I51+D_dE,I51+Close_A*(Ceil_E-I51)) -> 79.299165 | Q51: =CHOOSE(D51,1,1,J51,J51) -> 0 | R51: =IF(L51=1,IF(SUMPRODUCT(($L$35:$L$50=1)*(ABS($M$35:$M$50-M51)<0.000001)*(ABS($N$35:$N$50-N51)<0.000001)*($O$35:$O$50=O51)*(ABS($P$35:$P$50-P51)<0.000001)*($Q$35:$Q$50=Q51)*($V$35:$V$50=V51))=0,1,0),0) -> 1 | S51: =IF(AND(L51=1,N51>=$B$4-0.000000001,P51>=$B$6-0.000000001,M51>=Floor_q+$B$5-0.000000001),1,0) -> 0 | U51: =V38 -> 1 | V51: =CHOOSE(D51,U51,U51,1,U51) -> 1
A52: A S | B52: 2 | C52: 39 | D52: 1 | E52: =L39 -> 1 | F52: =M39 -> 500 | G52: =N39 -> 41 | H52: =O39 -> 59 | I52: =P39 -> 78 | J52: =Q39 -> 0 | K52: =IF(D52<=2,1-J52,IF(D52=3,IF(AND(U52=0,H52>=W_min,F52-D_dip>=Floor_q),1,0),IF(AND(H52>=W_min,F52>=Pre_A),1,0))) -> 1 | L52: =E52*K52 -> 1 | M52: =CHOOSE(D52,F52+Proc_S,F52+Proc_Sk,F52+D_dL,F52-Cost_A) -> 612 | N52: =CHOOSE(D52,(1-Tech_share)*G52,(1-Tech_share)*G52,G52+D_dT,G52) -> 36.9 | O52: =CHOOSE(D52,H52-W_lost,H52,H52,H52+W_gain) -> 54 | P52: =CHOOSE(D52,I52,I52,I52+D_dE,I52+Close_A*(Ceil_E-I52)) -> 78 | Q52: =CHOOSE(D52,1,1,J52,J52) -> 1 | R52: =IF(L52=1,IF(SUMPRODUCT(($L$35:$L$51=1)*(ABS($M$35:$M$51-M52)<0.000001)*(ABS($N$35:$N$51-N52)<0.000001)*($O$35:$O$51=O52)*(ABS($P$35:$P$51-P52)<0.000001)*($Q$35:$Q$51=Q52)*($V$35:$V$51=V52))=0,1,0),0) -> 1 | S52: =IF(AND(L52=1,N52>=$B$4-0.000000001,P52>=$B$6-0.000000001,M52>=Floor_q+$B$5-0.000000001),1,0) -> 0 | U52: =V39 -> 0 | V52: =CHOOSE(D52,U52,U52,1,U52) -> 0
A53: A S* | B53: 2 | C53: 39 | D53: 2 | E53: =L39 -> 1 | F53: =M39 -> 500 | G53: =N39 -> 41 | H53: =O39 -> 59 | I53: =P39 -> 78 | J53: =Q39 -> 0 | K53: =IF(D53<=2,1-J53,IF(D53=3,IF(AND(U53=0,H53>=W_min,F53-D_dip>=Floor_q),1,0),IF(AND(H53>=W_min,F53>=Pre_A),1,0))) -> 1 | L53: =E53*K53 -> 1 | M53: =CHOOSE(D53,F53+Proc_S,F53+Proc_Sk,F53+D_dL,F53-Cost_A) -> 592 | N53: =CHOOSE(D53,(1-Tech_share)*G53,(1-Tech_share)*G53,G53+D_dT,G53) -> 36.9 | O53: =CHOOSE(D53,H53-W_lost,H53,H53,H53+W_gain) -> 59 | P53: =CHOOSE(D53,I53,I53,I53+D_dE,I53+Close_A*(Ceil_E-I53)) -> 78 | Q53: =CHOOSE(D53,1,1,J53,J53) -> 1 | R53: =IF(L53=1,IF(SUMPRODUCT(($L$35:$L$52=1)*(ABS($M$35:$M$52-M53)<0.000001)*(ABS($N$35:$N$52-N53)<0.000001)*($O$35:$O$52=O53)*(ABS($P$35:$P$52-P53)<0.000001)*($Q$35:$Q$52=Q53)*($V$35:$V$52=V53))=0,1,0),0) -> 0 | S53: =IF(AND(L53=1,N53>=$B$4-0.000000001,P53>=$B$6-0.000000001,M53>=Floor_q+$B$5-0.000000001),1,0) -> 0 | U53: =V39 -> 0 | V53: =CHOOSE(D53,U53,U53,1,U53) -> 0
A54: A D | B54: 2 | C54: 39 | D54: 3 | E54: =L39 -> 1 | F54: =M39 -> 500 | G54: =N39 -> 41 | H54: =O39 -> 59 | I54: =P39 -> 78 | J54: =Q39 -> 0 | K54: =IF(D54<=2,1-J54,IF(D54=3,IF(AND(U54=0,H54>=W_min,F54-D_dip>=Floor_q),1,0),IF(AND(H54>=W_min,F54>=Pre_A),1,0))) -> 1 | L54: =E54*K54 -> 1 | M54: =CHOOSE(D54,F54+Proc_S,F54+Proc_Sk,F54+D_dL,F54-Cost_A) -> 464.63273 | N54: =CHOOSE(D54,(1-Tech_share)*G54,(1-Tech_share)*G54,G54+D_dT,G54) -> 75.634669 | O54: =CHOOSE(D54,H54-W_lost,H54,H54,H54+W_gain) -> 59 | P54: =CHOOSE(D54,I54,I54,I54+D_dE,I54+Close_A*(Ceil_E-I54)) -> 80.598331 | Q54: =CHOOSE(D54,1,1,J54,J54) -> 0 | R54: =IF(L54=1,IF(SUMPRODUCT(($L$35:$L$53=1)*(ABS($M$35:$M$53-M54)<0.000001)*(ABS($N$35:$N$53-N54)<0.000001)*($O$35:$O$53=O54)*(ABS($P$35:$P$53-P54)<0.000001)*($Q$35:$Q$53=Q54)*($V$35:$V$53=V54))=0,1,0),0) -> 1 | S54: =IF(AND(L54=1,N54>=$B$4-0.000000001,P54>=$B$6-0.000000001,M54>=Floor_q+$B$5-0.000000001),1,0) -> 1 | U54: =V39 -> 0 | V54: =CHOOSE(D54,U54,U54,1,U54) -> 1
A55: A A | B55: 2 | C55: 39 | D55: 4 | E55: =L39 -> 1 | F55: =M39 -> 500 | G55: =N39 -> 41 | H55: =O39 -> 59 | I55: =P39 -> 78 | J55: =Q39 -> 0 | K55: =IF(D55<=2,1-J55,IF(D55=3,IF(AND(U55=0,H55>=W_min,F55-D_dip>=Floor_q),1,0),IF(AND(H55>=W_min,F55>=Pre_A),1,0))) -> 1 | L55: =E55*K55 -> 1 | M55: =CHOOSE(D55,F55+Proc_S,F55+Proc_Sk,F55+D_dL,F55-Cost_A) -> 380 | N55: =CHOOSE(D55,(1-Tech_share)*G55,(1-Tech_share)*G55,G55+D_dT,G55) -> 41 | O55: =CHOOSE(D55,H55-W_lost,H55,H55,H55+W_gain) -> 60 | P55: =CHOOSE(D55,I55,I55,I55+D_dE,I55+Close_A*(Ceil_E-I55)) -> 81.5 | Q55: =CHOOSE(D55,1,1,J55,J55) -> 0 | R55: =IF(L55=1,IF(SUMPRODUCT(($L$35:$L$54=1)*(ABS($M$35:$M$54-M55)<0.000001)*(ABS($N$35:$N$54-N55)<0.000001)*($O$35:$O$54=O55)*(ABS($P$35:$P$54-P55)<0.000001)*($Q$35:$Q$54=Q55)*($V$35:$V$54=V55))=0,1,0),0) -> 1 | S55: =IF(AND(L55=1,N55>=$B$4-0.000000001,P55>=$B$6-0.000000001,M55>=Floor_q+$B$5-0.000000001),1,0) -> 0 | U55: =V39 -> 0 | V55: =CHOOSE(D55,U55,U55,1,U55) -> 0
A56: S S S | B56: 3 | C56: 40 | D56: 1 | E56: =L40 -> 0 | F56: =M40 -> 844 | G56: =N40 -> 33.21 | H56: =O40 -> 48 | I56: =P40 -> 71 | J56: =Q40 -> 1 | K56: =IF(D56<=2,1-J56,IF(D56=3,IF(AND(U56=0,H56>=W_min,F56-D_dip>=Floor_q),1,0),IF(AND(H56>=W_min,F56>=Pre_A),1,0))) -> 0 | L56: =E56*K56 -> 0 | M56: =CHOOSE(D56,F56+Proc_S,F56+Proc_Sk,F56+D_dL,F56-Cost_A) -> 956 | N56: =CHOOSE(D56,(1-Tech_share)*G56,(1-Tech_share)*G56,G56+D_dT,G56) -> 29.889 | O56: =CHOOSE(D56,H56-W_lost,H56,H56,H56+W_gain) -> 43 | P56: =CHOOSE(D56,I56,I56,I56+D_dE,I56+Close_A*(Ceil_E-I56)) -> 71 | Q56: =CHOOSE(D56,1,1,J56,J56) -> 1 | R56: =IF(L56=1,IF(SUMPRODUCT(($L$35:$L$55=1)*(ABS($M$35:$M$55-M56)<0.000001)*(ABS($N$35:$N$55-N56)<0.000001)*($O$35:$O$55=O56)*(ABS($P$35:$P$55-P56)<0.000001)*($Q$35:$Q$55=Q56)*($V$35:$V$55=V56))=0,1,0),0) -> 0 | S56: =IF(AND(L56=1,N56>=$B$4-0.000000001,P56>=$B$6-0.000000001,M56>=Floor_q+$B$5-0.000000001),1,0) -> 0 | U56: =V40 -> 0 | V56: =CHOOSE(D56,U56,U56,1,U56) -> 0
A57: S S S* | B57: 3 | C57: 40 | D57: 2 | E57: =L40 -> 0 | F57: =M40 -> 844 | G57: =N40 -> 33.21 | H57: =O40 -> 48 | I57: =P40 -> 71 | J57: =Q40 -> 1 | K57: =IF(D57<=2,1-J57,IF(D57=3,IF(AND(U57=0,H57>=W_min,F57-D_dip>=Floor_q),1,0),IF(AND(H57>=W_min,F57>=Pre_A),1,0))) -> 0 | L57: =E57*K57 -> 0 | M57: =CHOOSE(D57,F57+Proc_S,F57+Proc_Sk,F57+D_dL,F57-Cost_A) -> 936 | N57: =CHOOSE(D57,(1-Tech_share)*G57,(1-Tech_share)*G57,G57+D_dT,G57) -> 29.889 | O57: =CHOOSE(D57,H57-W_lost,H57,H57,H57+W_gain) -> 48 | P57: =CHOOSE(D57,I57,I57,I57+D_dE,I57+Close_A*(Ceil_E-I57)) -> 71 | Q57: =CHOOSE(D57,1,1,J57,J57) -> 1 | R57: =IF(L57=1,IF(SUMPRODUCT(($L$35:$L$56=1)*(ABS($M$35:$M$56-M57)<0.000001)*(ABS($N$35:$N$56-N57)<0.000001)*($O$35:$O$56=O57)*(ABS($P$35:$P$56-P57)<0.000001)*($Q$35:$Q$56=Q57)*($V$35:$V$56=V57))=0,1,0),0) -> 0 | S57: =IF(AND(L57=1,N57>=$B$4-0.000000001,P57>=$B$6-0.000000001,M57>=Floor_q+$B$5-0.000000001),1,0) -> 0 | U57: =V40 -> 0 | V57: =CHOOSE(D57,U57,U57,1,U57) -> 0
A58: S S D | B58: 3 | C58: 40 | D58: 3 | E58: =L40 -> 0 | F58: =M40 -> 844 | G58: =N40 -> 33.21 | H58: =O40 -> 48 | I58: =P40 -> 71 | J58: =Q40 -> 1 | K58: =IF(D58<=2,1-J58,IF(D58=3,IF(AND(U58=0,H58>=W_min,F58-D_dip>=Floor_q),1,0),IF(AND(H58>=W_min,F58>=Pre_A),1,0))) -> 0 | L58: =E58*K58 -> 0 | M58: =CHOOSE(D58,F58+Proc_S,F58+Proc_Sk,F58+D_dL,F58-Cost_A) -> 808.63273 | N58: =CHOOSE(D58,(1-Tech_share)*G58,(1-Tech_share)*G58,G58+D_dT,G58) -> 67.844669 | O58: =CHOOSE(D58,H58-W_lost,H58,H58,H58+W_gain) -> 48 | P58: =CHOOSE(D58,I58,I58,I58+D_dE,I58+Close_A*(Ceil_E-I58)) -> 73.598331 | Q58: =CHOOSE(D58,1,1,J58,J58) -> 1 | R58: =IF(L58=1,IF(SUMPRODUCT(($L$35:$L$57=1)*(ABS($M$35:$M$57-M58)<0.000001)*(ABS($N$35:$N$57-N58)<0.000001)*($O$35:$O$57=O58)*(ABS($P$35:$P$57-P58)<0.000001)*($Q$35:$Q$57=Q58)*($V$35:$V$57=V58))=0,1,0),0) -> 0 | S58: =IF(AND(L58=1,N58>=$B$4-0.000000001,P58>=$B$6-0.000000001,M58>=Floor_q+$B$5-0.000000001),1,0) -> 0 | U58: =V40 -> 0 | V58: =CHOOSE(D58,U58,U58,1,U58) -> 1
A59: S S A | B59: 3 | C59: 40 | D59: 4 | E59: =L40 -> 0 | F59: =M40 -> 844 | G59: =N40 -> 33.21 | H59: =O40 -> 48 | I59: =P40 -> 71 | J59: =Q40 -> 1 | K59: =IF(D59<=2,1-J59,IF(D59=3,IF(AND(U59=0,H59>=W_min,F59-D_dip>=Floor_q),1,0),IF(AND(H59>=W_min,F59>=Pre_A),1,0))) -> 0 | L59: =E59*K59 -> 0 | M59: =CHOOSE(D59,F59+Proc_S,F59+Proc_Sk,F59+D_dL,F59-Cost_A) -> 724 | N59: =CHOOSE(D59,(1-Tech_share)*G59,(1-Tech_share)*G59,G59+D_dT,G59) -> 33.21 | O59: =CHOOSE(D59,H59-W_lost,H59,H59,H59+W_gain) -> 49 | P59: =CHOOSE(D59,I59,I59,I59+D_dE,I59+Close_A*(Ceil_E-I59)) -> 78 | Q59: =CHOOSE(D59,1,1,J59,J59) -> 1 | R59: =IF(L59=1,IF(SUMPRODUCT(($L$35:$L$58=1)*(ABS($M$35:$M$58-M59)<0.000001)*(ABS($N$35:$N$58-N59)<0.000001)*($O$35:$O$58=O59)*(ABS($P$35:$P$58-P59)<0.000001)*($Q$35:$Q$58=Q59)*($V$35:$V$58=V59))=0,1,0),0) -> 0 | S59: =IF(AND(L59=1,N59>=$B$4-0.000000001,P59>=$B$6-0.000000001,M59>=Floor_q+$B$5-0.000000001),1,0) -> 0 | U59: =V40 -> 0 | V59: =CHOOSE(D59,U59,U59,1,U59) -> 0
A60: S S* S | B60: 3 | C60: 41 | D60: 1 | E60: =L41 -> 0 | F60: =M41 -> 824 | G60: =N41 -> 33.21 | H60: =O41 -> 53 | I60: =P41 -> 71 | J60: =Q41 -> 1 | K60: =IF(D60<=2,1-J60,IF(D60=3,IF(AND(U60=0,H60>=W_min,F60-D_dip>=Floor_q),1,0),IF(AND(H60>=W_min,F60>=Pre_A),1,0))) -> 0 | L60: =E60*K60 -> 0 | M60: =CHOOSE(D60,F60+Proc_S,F60+Proc_Sk,F60+D_dL,F60-Cost_A) -> 936 | N60: =CHOOSE(D60,(1-Tech_share)*G60,(1-Tech_share)*G60,G60+D_dT,G60) -> 29.889 | O60: =CHOOSE(D60,H60-W_lost,H60,H60,H60+W_gain) -> 48 | P60: =CHOOSE(D60,I60,I60,I60+D_dE,I60+Close_A*(Ceil_E-I60)) -> 71 | Q60: =CHOOSE(D60,1,1,J60,J60) -> 1 | R60: =IF(L60=1,IF(SUMPRODUCT(($L$35:$L$59=1)*(ABS($M$35:$M$59-M60)<0.000001)*(ABS($N$35:$N$59-N60)<0.000001)*($O$35:$O$59=O60)*(ABS($P$35:$P$59-P60)<0.000001)*($Q$35:$Q$59=Q60)*($V$35:$V$59=V60))=0,1,0),0) -> 0 | S60: =IF(AND(L60=1,N60>=$B$4-0.000000001,P60>=$B$6-0.000000001,M60>=Floor_q+$B$5-0.000000001),1,0) -> 0 | U60: =V41 -> 0 | V60: =CHOOSE(D60,U60,U60,1,U60) -> 0
A61: S S* S* | B61: 3 | C61: 41 | D61: 2 | E61: =L41 -> 0 | F61: =M41 -> 824 | G61: =N41 -> 33.21 | H61: =O41 -> 53 | I61: =P41 -> 71 | J61: =Q41 -> 1 | K61: =IF(D61<=2,1-J61,IF(D61=3,IF(AND(U61=0,H61>=W_min,F61-D_dip>=Floor_q),1,0),IF(AND(H61>=W_min,F61>=Pre_A),1,0))) -> 0 | L61: =E61*K61 -> 0 | M61: =CHOOSE(D61,F61+Proc_S,F61+Proc_Sk,F61+D_dL,F61-Cost_A) -> 916 | N61: =CHOOSE(D61,(1-Tech_share)*G61,(1-Tech_share)*G61,G61+D_dT,G61) -> 29.889 | O61: =CHOOSE(D61,H61-W_lost,H61,H61,H61+W_gain) -> 53 | P61: =CHOOSE(D61,I61,I61,I61+D_dE,I61+Close_A*(Ceil_E-I61)) -> 71 | Q61: =CHOOSE(D61,1,1,J61,J61) -> 1 | R61: =IF(L61=1,IF(SUMPRODUCT(($L$35:$L$60=1)*(ABS($M$35:$M$60-M61)<0.000001)*(ABS($N$35:$N$60-N61)<0.000001)*($O$35:$O$60=O61)*(ABS($P$35:$P$60-P61)<0.000001)*($Q$35:$Q$60=Q61)*($V$35:$V$60=V61))=0,1,0),0) -> 0 | S61: =IF(AND(L61=1,N61>=$B$4-0.000000001,P61>=$B$6-0.000000001,M61>=Floor_q+$B$5-0.000000001),1,0) -> 0 | U61: =V41 -> 0 | V61: =CHOOSE(D61,U61,U61,1,U61) -> 0
A62: S S* D | B62: 3 | C62: 41 | D62: 3 | E62: =L41 -> 0 | F62: =M41 -> 824 | G62: =N41 -> 33.21 | H62: =O41 -> 53 | I62: =P41 -> 71 | J62: =Q41 -> 1 | K62: =IF(D62<=2,1-J62,IF(D62=3,IF(AND(U62=0,H62>=W_min,F62-D_dip>=Floor_q),1,0),IF(AND(H62>=W_min,F62>=Pre_A),1,0))) -> 0 | L62: =E62*K62 -> 0 | M62: =CHOOSE(D62,F62+Proc_S,F62+Proc_Sk,F62+D_dL,F62-Cost_A) -> 788.63273 | N62: =CHOOSE(D62,(1-Tech_share)*G62,(1-Tech_share)*G62,G62+D_dT,G62) -> 67.844669 | O62: =CHOOSE(D62,H62-W_lost,H62,H62,H62+W_gain) -> 53 | P62: =CHOOSE(D62,I62,I62,I62+D_dE,I62+Close_A*(Ceil_E-I62)) -> 73.598331 | Q62: =CHOOSE(D62,1,1,J62,J62) -> 1 | R62: =IF(L62=1,IF(SUMPRODUCT(($L$35:$L$61=1)*(ABS($M$35:$M$61-M62)<0.000001)*(ABS($N$35:$N$61-N62)<0.000001)*($O$35:$O$61=O62)*(ABS($P$35:$P$61-P62)<0.000001)*($Q$35:$Q$61=Q62)*($V$35:$V$61=V62))=0,1,0),0) -> 0 | S62: =IF(AND(L62=1,N62>=$B$4-0.000000001,P62>=$B$6-0.000000001,M62>=Floor_q+$B$5-0.000000001),1,0) -> 0 | U62: =V41 -> 0 | V62: =CHOOSE(D62,U62,U62,1,U62) -> 1
A63: S S* A | B63: 3 | C63: 41 | D63: 4 | E63: =L41 -> 0 | F63: =M41 -> 824 | G63: =N41 -> 33.21 | H63: =O41 -> 53 | I63: =P41 -> 71 | J63: =Q41 -> 1 | K63: =IF(D63<=2,1-J63,IF(D63=3,IF(AND(U63=0,H63>=W_min,F63-D_dip>=Floor_q),1,0),IF(AND(H63>=W_min,F63>=Pre_A),1,0))) -> 0 | L63: =E63*K63 -> 0 | M63: =CHOOSE(D63,F63+Proc_S,F63+Proc_Sk,F63+D_dL,F63-Cost_A) -> 704 | N63: =CHOOSE(D63,(1-Tech_share)*G63,(1-Tech_share)*G63,G63+D_dT,G63) -> 33.21 | O63: =CHOOSE(D63,H63-W_lost,H63,H63,H63+W_gain) -> 54 | P63: =CHOOSE(D63,I63,I63,I63+D_dE,I63+Close_A*(Ceil_E-I63)) -> 78 | Q63: =CHOOSE(D63,1,1,J63,J63) -> 1 | R63: =IF(L63=1,IF(SUMPRODUCT(($L$35:$L$62=1)*(ABS($M$35:$M$62-M63)<0.000001)*(ABS($N$35:$N$62-N63)<0.000001)*($O$35:$O$62=O63)*(ABS($P$35:$P$62-P63)<0.000001)*($Q$35:$Q$62=Q63)*($V$35:$V$62=V63))=0,1,0),0) -> 0 | S63: =IF(AND(L63=1,N63>=$B$4-0.000000001,P63>=$B$6-0.000000001,M63>=Floor_q+$B$5-0.000000001),1,0) -> 0 | U63: =V41 -> 0 | V63: =CHOOSE(D63,U63,U63,1,U63) -> 0
A64: S D S | B64: 3 | C64: 42 | D64: 1 | E64: =L42 -> 0 | F64: =M42 -> 696.63273 | G64: =N42 -> 71.534669 | H64: =O42 -> 53 | I64: =P42 -> 73.598331 | J64: =Q42 -> 1 | K64: =IF(D64<=2,1-J64,IF(D64=3,IF(AND(U64=0,H64>=W_min,F64-D_dip>=Floor_q),1,0),IF(AND(H64>=W_min,F64>=Pre_A),1,0))) -> 0 | L64: =E64*K64 -> 0 | M64: =CHOOSE(D64,F64+Proc_S,F64+Proc_Sk,F64+D_dL,F64-Cost_A) -> 808.63273 | N64: =CHOOSE(D64,(1-Tech_share)*G64,(1-Tech_share)*G64,G64+D_dT,G64) -> 64.381202 | O64: =CHOOSE(D64,H64-W_lost,H64,H64,H64+W_gain) -> 48 | P64: =CHOOSE(D64,I64,I64,I64+D_dE,I64+Close_A*(Ceil_E-I64)) -> 73.598331 | Q64: =CHOOSE(D64,1,1,J64,J64) -> 1 | R64: =IF(L64=1,IF(SUMPRODUCT(($L$35:$L$63=1)*(ABS($M$35:$M$63-M64)<0.000001)*(ABS($N$35:$N$63-N64)<0.000001)*($O$35:$O$63=O64)*(ABS($P$35:$P$63-P64)<0.000001)*($Q$35:$Q$63=Q64)*($V$35:$V$63=V64))=0,1,0),0) -> 0 | S64: =IF(AND(L64=1,N64>=$B$4-0.000000001,P64>=$B$6-0.000000001,M64>=Floor_q+$B$5-0.000000001),1,0) -> 0 | U64: =V42 -> 1 | V64: =CHOOSE(D64,U64,U64,1,U64) -> 1
A65: S D S* | B65: 3 | C65: 42 | D65: 2 | E65: =L42 -> 0 | F65: =M42 -> 696.63273 | G65: =N42 -> 71.534669 | H65: =O42 -> 53 | I65: =P42 -> 73.598331 | J65: =Q42 -> 1 | K65: =IF(D65<=2,1-J65,IF(D65=3,IF(AND(U65=0,H65>=W_min,F65-D_dip>=Floor_q),1,0),IF(AND(H65>=W_min,F65>=Pre_A),1,0))) -> 0 | L65: =E65*K65 -> 0 | M65: =CHOOSE(D65,F65+Proc_S,F65+Proc_Sk,F65+D_dL,F65-Cost_A) -> 788.63273 | N65: =CHOOSE(D65,(1-Tech_share)*G65,(1-Tech_share)*G65,G65+D_dT,G65) -> 64.381202 | O65: =CHOOSE(D65,H65-W_lost,H65,H65,H65+W_gain) -> 53 | P65: =CHOOSE(D65,I65,I65,I65+D_dE,I65+Close_A*(Ceil_E-I65)) -> 73.598331 | Q65: =CHOOSE(D65,1,1,J65,J65) -> 1 | R65: =IF(L65=1,IF(SUMPRODUCT(($L$35:$L$64=1)*(ABS($M$35:$M$64-M65)<0.000001)*(ABS($N$35:$N$64-N65)<0.000001)*($O$35:$O$64=O65)*(ABS($P$35:$P$64-P65)<0.000001)*($Q$35:$Q$64=Q65)*($V$35:$V$64=V65))=0,1,0),0) -> 0 | S65: =IF(AND(L65=1,N65>=$B$4-0.000000001,P65>=$B$6-0.000000001,M65>=Floor_q+$B$5-0.000000001),1,0) -> 0 | U65: =V42 -> 1 | V65: =CHOOSE(D65,U65,U65,1,U65) -> 1
A66: S D D | B66: 3 | C66: 42 | D66: 3 | E66: =L42 -> 0 | F66: =M42 -> 696.63273 | G66: =N42 -> 71.534669 | H66: =O42 -> 53 | I66: =P42 -> 73.598331 | J66: =Q42 -> 1 | K66: =IF(D66<=2,1-J66,IF(D66=3,IF(AND(U66=0,H66>=W_min,F66-D_dip>=Floor_q),1,0),IF(AND(H66>=W_min,F66>=Pre_A),1,0))) -> 0 | L66: =E66*K66 -> 0 | M66: =CHOOSE(D66,F66+Proc_S,F66+Proc_Sk,F66+D_dL,F66-Cost_A) -> 661.26546 | N66: =CHOOSE(D66,(1-Tech_share)*G66,(1-Tech_share)*G66,G66+D_dT,G66) -> 106.16934 | O66: =CHOOSE(D66,H66-W_lost,H66,H66,H66+W_gain) -> 53 | P66: =CHOOSE(D66,I66,I66,I66+D_dE,I66+Close_A*(Ceil_E-I66)) -> 76.196662 | Q66: =CHOOSE(D66,1,1,J66,J66) -> 1 | R66: =IF(L66=1,IF(SUMPRODUCT(($L$35:$L$65=1)*(ABS($M$35:$M$65-M66)<0.000001)*(ABS($N$35:$N$65-N66)<0.000001)*($O$35:$O$65=O66)*(ABS($P$35:$P$65-P66)<0.000001)*($Q$35:$Q$65=Q66)*($V$35:$V$65=V66))=0,1,0),0) -> 0 | S66: =IF(AND(L66=1,N66>=$B$4-0.000000001,P66>=$B$6-0.000000001,M66>=Floor_q+$B$5-0.000000001),1,0) -> 0 | U66: =V42 -> 1 | V66: =CHOOSE(D66,U66,U66,1,U66) -> 1
A67: S D A | B67: 3 | C67: 42 | D67: 4 | E67: =L42 -> 0 | F67: =M42 -> 696.63273 | G67: =N42 -> 71.534669 | H67: =O42 -> 53 | I67: =P42 -> 73.598331 | J67: =Q42 -> 1 | K67: =IF(D67<=2,1-J67,IF(D67=3,IF(AND(U67=0,H67>=W_min,F67-D_dip>=Floor_q),1,0),IF(AND(H67>=W_min,F67>=Pre_A),1,0))) -> 0 | L67: =E67*K67 -> 0 | M67: =CHOOSE(D67,F67+Proc_S,F67+Proc_Sk,F67+D_dL,F67-Cost_A) -> 576.63273 | N67: =CHOOSE(D67,(1-Tech_share)*G67,(1-Tech_share)*G67,G67+D_dT,G67) -> 71.534669 | O67: =CHOOSE(D67,H67-W_lost,H67,H67,H67+W_gain) -> 54 | P67: =CHOOSE(D67,I67,I67,I67+D_dE,I67+Close_A*(Ceil_E-I67)) -> 79.299165 | Q67: =CHOOSE(D67,1,1,J67,J67) -> 1 | R67: =IF(L67=1,IF(SUMPRODUCT(($L$35:$L$66=1)*(ABS($M$35:$M$66-M67)<0.000001)*(ABS($N$35:$N$66-N67)<0.000001)*($O$35:$O$66=O67)*(ABS($P$35:$P$66-P67)<0.000001)*($Q$35:$Q$66=Q67)*($V$35:$V$66=V67))=0,1,0),0) -> 0 | S67: =IF(AND(L67=1,N67>=$B$4-0.000000001,P67>=$B$6-0.000000001,M67>=Floor_q+$B$5-0.000000001),1,0) -> 0 | U67: =V42 -> 1 | V67: =CHOOSE(D67,U67,U67,1,U67) -> 1
A68: S A S | B68: 3 | C68: 43 | D68: 1 | E68: =L43 -> 0 | F68: =M43 -> 612 | G68: =N43 -> 36.9 | H68: =O43 -> 54 | I68: =P43 -> 78 | J68: =Q43 -> 1 | K68: =IF(D68<=2,1-J68,IF(D68=3,IF(AND(U68=0,H68>=W_min,F68-D_dip>=Floor_q),1,0),IF(AND(H68>=W_min,F68>=Pre_A),1,0))) -> 0 | L68: =E68*K68 -> 0 | M68: =CHOOSE(D68,F68+Proc_S,F68+Proc_Sk,F68+D_dL,F68-Cost_A) -> 724 | N68: =CHOOSE(D68,(1-Tech_share)*G68,(1-Tech_share)*G68,G68+D_dT,G68) -> 33.21 | O68: =CHOOSE(D68,H68-W_lost,H68,H68,H68+W_gain) -> 49 | P68: =CHOOSE(D68,I68,I68,I68+D_dE,I68+Close_A*(Ceil_E-I68)) -> 78 | Q68: =CHOOSE(D68,1,1,J68,J68) -> 1 | R68: =IF(L68=1,IF(SUMPRODUCT(($L$35:$L$67=1)*(ABS($M$35:$M$67-M68)<0.000001)*(ABS($N$35:$N$67-N68)<0.000001)*($O$35:$O$67=O68)*(ABS($P$35:$P$67-P68)<0.000001)*($Q$35:$Q$67=Q68)*($V$35:$V$67=V68))=0,1,0),0) -> 0 | S68: =IF(AND(L68=1,N68>=$B$4-0.000000001,P68>=$B$6-0.000000001,M68>=Floor_q+$B$5-0.000000001),1,0) -> 0 | U68: =V43 -> 0 | V68: =CHOOSE(D68,U68,U68,1,U68) -> 0
A69: S A S* | B69: 3 | C69: 43 | D69: 2 | E69: =L43 -> 0 | F69: =M43 -> 612 | G69: =N43 -> 36.9 | H69: =O43 -> 54 | I69: =P43 -> 78 | J69: =Q43 -> 1 | K69: =IF(D69<=2,1-J69,IF(D69=3,IF(AND(U69=0,H69>=W_min,F69-D_dip>=Floor_q),1,0),IF(AND(H69>=W_min,F69>=Pre_A),1,0))) -> 0 | L69: =E69*K69 -> 0 | M69: =CHOOSE(D69,F69+Proc_S,F69+Proc_Sk,F69+D_dL,F69-Cost_A) -> 704 | N69: =CHOOSE(D69,(1-Tech_share)*G69,(1-Tech_share)*G69,G69+D_dT,G69) -> 33.21 | O69: =CHOOSE(D69,H69-W_lost,H69,H69,H69+W_gain) -> 54 | P69: =CHOOSE(D69,I69,I69,I69+D_dE,I69+Close_A*(Ceil_E-I69)) -> 78 | Q69: =CHOOSE(D69,1,1,J69,J69) -> 1 | R69: =IF(L69=1,IF(SUMPRODUCT(($L$35:$L$68=1)*(ABS($M$35:$M$68-M69)<0.000001)*(ABS($N$35:$N$68-N69)<0.000001)*($O$35:$O$68=O69)*(ABS($P$35:$P$68-P69)<0.000001)*($Q$35:$Q$68=Q69)*($V$35:$V$68=V69))=0,1,0),0) -> 0 | S69: =IF(AND(L69=1,N69>=$B$4-0.000000001,P69>=$B$6-0.000000001,M69>=Floor_q+$B$5-0.000000001),1,0) -> 0 | U69: =V43 -> 0 | V69: =CHOOSE(D69,U69,U69,1,U69) -> 0
A70: S A D | B70: 3 | C70: 43 | D70: 3 | E70: =L43 -> 0 | F70: =M43 -> 612 | G70: =N43 -> 36.9 | H70: =O43 -> 54 | I70: =P43 -> 78 | J70: =Q43 -> 1 | K70: =IF(D70<=2,1-J70,IF(D70=3,IF(AND(U70=0,H70>=W_min,F70-D_dip>=Floor_q),1,0),IF(AND(H70>=W_min,F70>=Pre_A),1,0))) -> 0 | L70: =E70*K70 -> 0 | M70: =CHOOSE(D70,F70+Proc_S,F70+Proc_Sk,F70+D_dL,F70-Cost_A) -> 576.63273 | N70: =CHOOSE(D70,(1-Tech_share)*G70,(1-Tech_share)*G70,G70+D_dT,G70) -> 71.534669 | O70: =CHOOSE(D70,H70-W_lost,H70,H70,H70+W_gain) -> 54 | P70: =CHOOSE(D70,I70,I70,I70+D_dE,I70+Close_A*(Ceil_E-I70)) -> 80.598331 | Q70: =CHOOSE(D70,1,1,J70,J70) -> 1 | R70: =IF(L70=1,IF(SUMPRODUCT(($L$35:$L$69=1)*(ABS($M$35:$M$69-M70)<0.000001)*(ABS($N$35:$N$69-N70)<0.000001)*($O$35:$O$69=O70)*(ABS($P$35:$P$69-P70)<0.000001)*($Q$35:$Q$69=Q70)*($V$35:$V$69=V70))=0,1,0),0) -> 0 | S70: =IF(AND(L70=1,N70>=$B$4-0.000000001,P70>=$B$6-0.000000001,M70>=Floor_q+$B$5-0.000000001),1,0) -> 0 | U70: =V43 -> 0 | V70: =CHOOSE(D70,U70,U70,1,U70) -> 1
A71: S A A | B71: 3 | C71: 43 | D71: 4 | E71: =L43 -> 0 | F71: =M43 -> 612 | G71: =N43 -> 36.9 | H71: =O43 -> 54 | I71: =P43 -> 78 | J71: =Q43 -> 1 | K71: =IF(D71<=2,1-J71,IF(D71=3,IF(AND(U71=0,H71>=W_min,F71-D_dip>=Floor_q),1,0),IF(AND(H71>=W_min,F71>=Pre_A),1,0))) -> 0 | L71: =E71*K71 -> 0 | M71: =CHOOSE(D71,F71+Proc_S,F71+Proc_Sk,F71+D_dL,F71-Cost_A) -> 492 | N71: =CHOOSE(D71,(1-Tech_share)*G71,(1-Tech_share)*G71,G71+D_dT,G71) -> 36.9 | O71: =CHOOSE(D71,H71-W_lost,H71,H71,H71+W_gain) -> 55 | P71: =CHOOSE(D71,I71,I71,I71+D_dE,I71+Close_A*(Ceil_E-I71)) -> 81.5 | Q71: =CHOOSE(D71,1,1,J71,J71) -> 1 | R71: =IF(L71=1,IF(SUMPRODUCT(($L$35:$L$70=1)*(ABS($M$35:$M$70-M71)<0.000001)*(ABS($N$35:$N$70-N71)<0.000001)*($O$35:$O$70=O71)*(ABS($P$35:$P$70-P71)<0.000001)*($Q$35:$Q$70=Q71)*($V$35:$V$70=V71))=0,1,0),0) -> 0 | S71: =IF(AND(L71=1,N71>=$B$4-0.000000001,P71>=$B$6-0.000000001,M71>=Floor_q+$B$5-0.000000001),1,0) -> 0 | U71: =V43 -> 0 | V71: =CHOOSE(D71,U71,U71,1,U71) -> 0
A72: S* S S | B72: 3 | C72: 44 | D72: 1 | E72: =L44 -> 0 | F72: =M44 -> 824 | G72: =N44 -> 33.21 | H72: =O44 -> 53 | I72: =P44 -> 71 | J72: =Q44 -> 1 | K72: =IF(D72<=2,1-J72,IF(D72=3,IF(AND(U72=0,H72>=W_min,F72-D_dip>=Floor_q),1,0),IF(AND(H72>=W_min,F72>=Pre_A),1,0))) -> 0 | L72: =E72*K72 -> 0 | M72: =CHOOSE(D72,F72+Proc_S,F72+Proc_Sk,F72+D_dL,F72-Cost_A) -> 936 | N72: =CHOOSE(D72,(1-Tech_share)*G72,(1-Tech_share)*G72,G72+D_dT,G72) -> 29.889 | O72: =CHOOSE(D72,H72-W_lost,H72,H72,H72+W_gain) -> 48 | P72: =CHOOSE(D72,I72,I72,I72+D_dE,I72+Close_A*(Ceil_E-I72)) -> 71 | Q72: =CHOOSE(D72,1,1,J72,J72) -> 1 | R72: =IF(L72=1,IF(SUMPRODUCT(($L$35:$L$71=1)*(ABS($M$35:$M$71-M72)<0.000001)*(ABS($N$35:$N$71-N72)<0.000001)*($O$35:$O$71=O72)*(ABS($P$35:$P$71-P72)<0.000001)*($Q$35:$Q$71=Q72)*($V$35:$V$71=V72))=0,1,0),0) -> 0 | S72: =IF(AND(L72=1,N72>=$B$4-0.000000001,P72>=$B$6-0.000000001,M72>=Floor_q+$B$5-0.000000001),1,0) -> 0 | U72: =V44 -> 0 | V72: =CHOOSE(D72,U72,U72,1,U72) -> 0
A73: S* S S* | B73: 3 | C73: 44 | D73: 2 | E73: =L44 -> 0 | F73: =M44 -> 824 | G73: =N44 -> 33.21 | H73: =O44 -> 53 | I73: =P44 -> 71 | J73: =Q44 -> 1 | K73: =IF(D73<=2,1-J73,IF(D73=3,IF(AND(U73=0,H73>=W_min,F73-D_dip>=Floor_q),1,0),IF(AND(H73>=W_min,F73>=Pre_A),1,0))) -> 0 | L73: =E73*K73 -> 0 | M73: =CHOOSE(D73,F73+Proc_S,F73+Proc_Sk,F73+D_dL,F73-Cost_A) -> 916 | N73: =CHOOSE(D73,(1-Tech_share)*G73,(1-Tech_share)*G73,G73+D_dT,G73) -> 29.889 | O73: =CHOOSE(D73,H73-W_lost,H73,H73,H73+W_gain) -> 53 | P73: =CHOOSE(D73,I73,I73,I73+D_dE,I73+Close_A*(Ceil_E-I73)) -> 71 | Q73: =CHOOSE(D73,1,1,J73,J73) -> 1 | R73: =IF(L73=1,IF(SUMPRODUCT(($L$35:$L$72=1)*(ABS($M$35:$M$72-M73)<0.000001)*(ABS($N$35:$N$72-N73)<0.000001)*($O$35:$O$72=O73)*(ABS($P$35:$P$72-P73)<0.000001)*($Q$35:$Q$72=Q73)*($V$35:$V$72=V73))=0,1,0),0) -> 0 | S73: =IF(AND(L73=1,N73>=$B$4-0.000000001,P73>=$B$6-0.000000001,M73>=Floor_q+$B$5-0.000000001),1,0) -> 0 | U73: =V44 -> 0 | V73: =CHOOSE(D73,U73,U73,1,U73) -> 0
A74: S* S D | B74: 3 | C74: 44 | D74: 3 | E74: =L44 -> 0 | F74: =M44 -> 824 | G74: =N44 -> 33.21 | H74: =O44 -> 53 | I74: =P44 -> 71 | J74: =Q44 -> 1 | K74: =IF(D74<=2,1-J74,IF(D74=3,IF(AND(U74=0,H74>=W_min,F74-D_dip>=Floor_q),1,0),IF(AND(H74>=W_min,F74>=Pre_A),1,0))) -> 0 | L74: =E74*K74 -> 0 | M74: =CHOOSE(D74,F74+Proc_S,F74+Proc_Sk,F74+D_dL,F74-Cost_A) -> 788.63273 | N74: =CHOOSE(D74,(1-Tech_share)*G74,(1-Tech_share)*G74,G74+D_dT,G74) -> 67.844669 | O74: =CHOOSE(D74,H74-W_lost,H74,H74,H74+W_gain) -> 53 | P74: =CHOOSE(D74,I74,I74,I74+D_dE,I74+Close_A*(Ceil_E-I74)) -> 73.598331 | Q74: =CHOOSE(D74,1,1,J74,J74) -> 1 | R74: =IF(L74=1,IF(SUMPRODUCT(($L$35:$L$73=1)*(ABS($M$35:$M$73-M74)<0.000001)*(ABS($N$35:$N$73-N74)<0.000001)*($O$35:$O$73=O74)*(ABS($P$35:$P$73-P74)<0.000001)*($Q$35:$Q$73=Q74)*($V$35:$V$73=V74))=0,1,0),0) -> 0 | S74: =IF(AND(L74=1,N74>=$B$4-0.000000001,P74>=$B$6-0.000000001,M74>=Floor_q+$B$5-0.000000001),1,0) -> 0 | U74: =V44 -> 0 | V74: =CHOOSE(D74,U74,U74,1,U74) -> 1
A75: S* S A | B75: 3 | C75: 44 | D75: 4 | E75: =L44 -> 0 | F75: =M44 -> 824 | G75: =N44 -> 33.21 | H75: =O44 -> 53 | I75: =P44 -> 71 | J75: =Q44 -> 1 | K75: =IF(D75<=2,1-J75,IF(D75=3,IF(AND(U75=0,H75>=W_min,F75-D_dip>=Floor_q),1,0),IF(AND(H75>=W_min,F75>=Pre_A),1,0))) -> 0 | L75: =E75*K75 -> 0 | M75: =CHOOSE(D75,F75+Proc_S,F75+Proc_Sk,F75+D_dL,F75-Cost_A) -> 704 | N75: =CHOOSE(D75,(1-Tech_share)*G75,(1-Tech_share)*G75,G75+D_dT,G75) -> 33.21 | O75: =CHOOSE(D75,H75-W_lost,H75,H75,H75+W_gain) -> 54 | P75: =CHOOSE(D75,I75,I75,I75+D_dE,I75+Close_A*(Ceil_E-I75)) -> 78 | Q75: =CHOOSE(D75,1,1,J75,J75) -> 1 | R75: =IF(L75=1,IF(SUMPRODUCT(($L$35:$L$74=1)*(ABS($M$35:$M$74-M75)<0.000001)*(ABS($N$35:$N$74-N75)<0.000001)*($O$35:$O$74=O75)*(ABS($P$35:$P$74-P75)<0.000001)*($Q$35:$Q$74=Q75)*($V$35:$V$74=V75))=0,1,0),0) -> 0 | S75: =IF(AND(L75=1,N75>=$B$4-0.000000001,P75>=$B$6-0.000000001,M75>=Floor_q+$B$5-0.000000001),1,0) -> 0 | U75: =V44 -> 0 | V75: =CHOOSE(D75,U75,U75,1,U75) -> 0
A76: S* S* S | B76: 3 | C76: 45 | D76: 1 | E76: =L45 -> 0 | F76: =M45 -> 804 | G76: =N45 -> 33.21 | H76: =O45 -> 58 | I76: =P45 -> 71 | J76: =Q45 -> 1 | K76: =IF(D76<=2,1-J76,IF(D76=3,IF(AND(U76=0,H76>=W_min,F76-D_dip>=Floor_q),1,0),IF(AND(H76>=W_min,F76>=Pre_A),1,0))) -> 0 | L76: =E76*K76 -> 0 | M76: =CHOOSE(D76,F76+Proc_S,F76+Proc_Sk,F76+D_dL,F76-Cost_A) -> 916 | N76: =CHOOSE(D76,(1-Tech_share)*G76,(1-Tech_share)*G76,G76+D_dT,G76) -> 29.889 | O76: =CHOOSE(D76,H76-W_lost,H76,H76,H76+W_gain) -> 53 | P76: =CHOOSE(D76,I76,I76,I76+D_dE,I76+Close_A*(Ceil_E-I76)) -> 71 | Q76: =CHOOSE(D76,1,1,J76,J76) -> 1 | R76: =IF(L76=1,IF(SUMPRODUCT(($L$35:$L$75=1)*(ABS($M$35:$M$75-M76)<0.000001)*(ABS($N$35:$N$75-N76)<0.000001)*($O$35:$O$75=O76)*(ABS($P$35:$P$75-P76)<0.000001)*($Q$35:$Q$75=Q76)*($V$35:$V$75=V76))=0,1,0),0) -> 0 | S76: =IF(AND(L76=1,N76>=$B$4-0.000000001,P76>=$B$6-0.000000001,M76>=Floor_q+$B$5-0.000000001),1,0) -> 0 | U76: =V45 -> 0 | V76: =CHOOSE(D76,U76,U76,1,U76) -> 0
A77: S* S* S* | B77: 3 | C77: 45 | D77: 2 | E77: =L45 -> 0 | F77: =M45 -> 804 | G77: =N45 -> 33.21 | H77: =O45 -> 58 | I77: =P45 -> 71 | J77: =Q45 -> 1 | K77: =IF(D77<=2,1-J77,IF(D77=3,IF(AND(U77=0,H77>=W_min,F77-D_dip>=Floor_q),1,0),IF(AND(H77>=W_min,F77>=Pre_A),1,0))) -> 0 | L77: =E77*K77 -> 0 | M77: =CHOOSE(D77,F77+Proc_S,F77+Proc_Sk,F77+D_dL,F77-Cost_A) -> 896 | N77: =CHOOSE(D77,(1-Tech_share)*G77,(1-Tech_share)*G77,G77+D_dT,G77) -> 29.889 | O77: =CHOOSE(D77,H77-W_lost,H77,H77,H77+W_gain) -> 58 | P77: =CHOOSE(D77,I77,I77,I77+D_dE,I77+Close_A*(Ceil_E-I77)) -> 71 | Q77: =CHOOSE(D77,1,1,J77,J77) -> 1 | R77: =IF(L77=1,IF(SUMPRODUCT(($L$35:$L$76=1)*(ABS($M$35:$M$76-M77)<0.000001)*(ABS($N$35:$N$76-N77)<0.000001)*($O$35:$O$76=O77)*(ABS($P$35:$P$76-P77)<0.000001)*($Q$35:$Q$76=Q77)*($V$35:$V$76=V77))=0,1,0),0) -> 0 | S77: =IF(AND(L77=1,N77>=$B$4-0.000000001,P77>=$B$6-0.000000001,M77>=Floor_q+$B$5-0.000000001),1,0) -> 0 | U77: =V45 -> 0 | V77: =CHOOSE(D77,U77,U77,1,U77) -> 0
A78: S* S* D | B78: 3 | C78: 45 | D78: 3 | E78: =L45 -> 0 | F78: =M45 -> 804 | G78: =N45 -> 33.21 | H78: =O45 -> 58 | I78: =P45 -> 71 | J78: =Q45 -> 1 | K78: =IF(D78<=2,1-J78,IF(D78=3,IF(AND(U78=0,H78>=W_min,F78-D_dip>=Floor_q),1,0),IF(AND(H78>=W_min,F78>=Pre_A),1,0))) -> 1 | L78: =E78*K78 -> 0 | M78: =CHOOSE(D78,F78+Proc_S,F78+Proc_Sk,F78+D_dL,F78-Cost_A) -> 768.63273 | N78: =CHOOSE(D78,(1-Tech_share)*G78,(1-Tech_share)*G78,G78+D_dT,G78) -> 67.844669 | O78: =CHOOSE(D78,H78-W_lost,H78,H78,H78+W_gain) -> 58 | P78: =CHOOSE(D78,I78,I78,I78+D_dE,I78+Close_A*(Ceil_E-I78)) -> 73.598331 | Q78: =CHOOSE(D78,1,1,J78,J78) -> 1 | R78: =IF(L78=1,IF(SUMPRODUCT(($L$35:$L$77=1)*(ABS($M$35:$M$77-M78)<0.000001)*(ABS($N$35:$N$77-N78)<0.000001)*($O$35:$O$77=O78)*(ABS($P$35:$P$77-P78)<0.000001)*($Q$35:$Q$77=Q78)*($V$35:$V$77=V78))=0,1,0),0) -> 0 | S78: =IF(AND(L78=1,N78>=$B$4-0.000000001,P78>=$B$6-0.000000001,M78>=Floor_q+$B$5-0.000000001),1,0) -> 0 | U78: =V45 -> 0 | V78: =CHOOSE(D78,U78,U78,1,U78) -> 1
A79: S* S* A | B79: 3 | C79: 45 | D79: 4 | E79: =L45 -> 0 | F79: =M45 -> 804 | G79: =N45 -> 33.21 | H79: =O45 -> 58 | I79: =P45 -> 71 | J79: =Q45 -> 1 | K79: =IF(D79<=2,1-J79,IF(D79=3,IF(AND(U79=0,H79>=W_min,F79-D_dip>=Floor_q),1,0),IF(AND(H79>=W_min,F79>=Pre_A),1,0))) -> 1 | L79: =E79*K79 -> 0 | M79: =CHOOSE(D79,F79+Proc_S,F79+Proc_Sk,F79+D_dL,F79-Cost_A) -> 684 | N79: =CHOOSE(D79,(1-Tech_share)*G79,(1-Tech_share)*G79,G79+D_dT,G79) -> 33.21 | O79: =CHOOSE(D79,H79-W_lost,H79,H79,H79+W_gain) -> 59 | P79: =CHOOSE(D79,I79,I79,I79+D_dE,I79+Close_A*(Ceil_E-I79)) -> 78 | Q79: =CHOOSE(D79,1,1,J79,J79) -> 1 | R79: =IF(L79=1,IF(SUMPRODUCT(($L$35:$L$78=1)*(ABS($M$35:$M$78-M79)<0.000001)*(ABS($N$35:$N$78-N79)<0.000001)*($O$35:$O$78=O79)*(ABS($P$35:$P$78-P79)<0.000001)*($Q$35:$Q$78=Q79)*($V$35:$V$78=V79))=0,1,0),0) -> 0 | S79: =IF(AND(L79=1,N79>=$B$4-0.000000001,P79>=$B$6-0.000000001,M79>=Floor_q+$B$5-0.000000001),1,0) -> 0 | U79: =V45 -> 0 | V79: =CHOOSE(D79,U79,U79,1,U79) -> 0
A80: S* D S | B80: 3 | C80: 46 | D80: 1 | E80: =L46 -> 1 | F80: =M46 -> 676.63273 | G80: =N46 -> 71.534669 | H80: =O46 -> 58 | I80: =P46 -> 73.598331 | J80: =Q46 -> 1 | K80: =IF(D80<=2,1-J80,IF(D80=3,IF(AND(U80=0,H80>=W_min,F80-D_dip>=Floor_q),1,0),IF(AND(H80>=W_min,F80>=Pre_A),1,0))) -> 0 | L80: =E80*K80 -> 0 | M80: =CHOOSE(D80,F80+Proc_S,F80+Proc_Sk,F80+D_dL,F80-Cost_A) -> 788.63273 | N80: =CHOOSE(D80,(1-Tech_share)*G80,(1-Tech_share)*G80,G80+D_dT,G80) -> 64.381202 | O80: =CHOOSE(D80,H80-W_lost,H80,H80,H80+W_gain) -> 53 | P80: =CHOOSE(D80,I80,I80,I80+D_dE,I80+Close_A*(Ceil_E-I80)) -> 73.598331 | Q80: =CHOOSE(D80,1,1,J80,J80) -> 1 | R80: =IF(L80=1,IF(SUMPRODUCT(($L$35:$L$79=1)*(ABS($M$35:$M$79-M80)<0.000001)*(ABS($N$35:$N$79-N80)<0.000001)*($O$35:$O$79=O80)*(ABS($P$35:$P$79-P80)<0.000001)*($Q$35:$Q$79=Q80)*($V$35:$V$79=V80))=0,1,0),0) -> 0 | S80: =IF(AND(L80=1,N80>=$B$4-0.000000001,P80>=$B$6-0.000000001,M80>=Floor_q+$B$5-0.000000001),1,0) -> 0 | U80: =V46 -> 1 | V80: =CHOOSE(D80,U80,U80,1,U80) -> 1
A81: S* D S* | B81: 3 | C81: 46 | D81: 2 | E81: =L46 -> 1 | F81: =M46 -> 676.63273 | G81: =N46 -> 71.534669 | H81: =O46 -> 58 | I81: =P46 -> 73.598331 | J81: =Q46 -> 1 | K81: =IF(D81<=2,1-J81,IF(D81=3,IF(AND(U81=0,H81>=W_min,F81-D_dip>=Floor_q),1,0),IF(AND(H81>=W_min,F81>=Pre_A),1,0))) -> 0 | L81: =E81*K81 -> 0 | M81: =CHOOSE(D81,F81+Proc_S,F81+Proc_Sk,F81+D_dL,F81-Cost_A) -> 768.63273 | N81: =CHOOSE(D81,(1-Tech_share)*G81,(1-Tech_share)*G81,G81+D_dT,G81) -> 64.381202 | O81: =CHOOSE(D81,H81-W_lost,H81,H81,H81+W_gain) -> 58 | P81: =CHOOSE(D81,I81,I81,I81+D_dE,I81+Close_A*(Ceil_E-I81)) -> 73.598331 | Q81: =CHOOSE(D81,1,1,J81,J81) -> 1 | R81: =IF(L81=1,IF(SUMPRODUCT(($L$35:$L$80=1)*(ABS($M$35:$M$80-M81)<0.000001)*(ABS($N$35:$N$80-N81)<0.000001)*($O$35:$O$80=O81)*(ABS($P$35:$P$80-P81)<0.000001)*($Q$35:$Q$80=Q81)*($V$35:$V$80=V81))=0,1,0),0) -> 0 | S81: =IF(AND(L81=1,N81>=$B$4-0.000000001,P81>=$B$6-0.000000001,M81>=Floor_q+$B$5-0.000000001),1,0) -> 0 | U81: =V46 -> 1 | V81: =CHOOSE(D81,U81,U81,1,U81) -> 1
A82: S* D D | B82: 3 | C82: 46 | D82: 3 | E82: =L46 -> 1 | F82: =M46 -> 676.63273 | G82: =N46 -> 71.534669 | H82: =O46 -> 58 | I82: =P46 -> 73.598331 | J82: =Q46 -> 1 | K82: =IF(D82<=2,1-J82,IF(D82=3,IF(AND(U82=0,H82>=W_min,F82-D_dip>=Floor_q),1,0),IF(AND(H82>=W_min,F82>=Pre_A),1,0))) -> 0 | L82: =E82*K82 -> 0 | M82: =CHOOSE(D82,F82+Proc_S,F82+Proc_Sk,F82+D_dL,F82-Cost_A) -> 641.26546 | N82: =CHOOSE(D82,(1-Tech_share)*G82,(1-Tech_share)*G82,G82+D_dT,G82) -> 106.16934 | O82: =CHOOSE(D82,H82-W_lost,H82,H82,H82+W_gain) -> 58 | P82: =CHOOSE(D82,I82,I82,I82+D_dE,I82+Close_A*(Ceil_E-I82)) -> 76.196662 | Q82: =CHOOSE(D82,1,1,J82,J82) -> 1 | R82: =IF(L82=1,IF(SUMPRODUCT(($L$35:$L$81=1)*(ABS($M$35:$M$81-M82)<0.000001)*(ABS($N$35:$N$81-N82)<0.000001)*($O$35:$O$81=O82)*(ABS($P$35:$P$81-P82)<0.000001)*($Q$35:$Q$81=Q82)*($V$35:$V$81=V82))=0,1,0),0) -> 0 | S82: =IF(AND(L82=1,N82>=$B$4-0.000000001,P82>=$B$6-0.000000001,M82>=Floor_q+$B$5-0.000000001),1,0) -> 0 | U82: =V46 -> 1 | V82: =CHOOSE(D82,U82,U82,1,U82) -> 1
A83: S* D A | B83: 3 | C83: 46 | D83: 4 | E83: =L46 -> 1 | F83: =M46 -> 676.63273 | G83: =N46 -> 71.534669 | H83: =O46 -> 58 | I83: =P46 -> 73.598331 | J83: =Q46 -> 1 | K83: =IF(D83<=2,1-J83,IF(D83=3,IF(AND(U83=0,H83>=W_min,F83-D_dip>=Floor_q),1,0),IF(AND(H83>=W_min,F83>=Pre_A),1,0))) -> 1 | L83: =E83*K83 -> 1 | M83: =CHOOSE(D83,F83+Proc_S,F83+Proc_Sk,F83+D_dL,F83-Cost_A) -> 556.63273 | N83: =CHOOSE(D83,(1-Tech_share)*G83,(1-Tech_share)*G83,G83+D_dT,G83) -> 71.534669 | O83: =CHOOSE(D83,H83-W_lost,H83,H83,H83+W_gain) -> 59 | P83: =CHOOSE(D83,I83,I83,I83+D_dE,I83+Close_A*(Ceil_E-I83)) -> 79.299165 | Q83: =CHOOSE(D83,1,1,J83,J83) -> 1 | R83: =IF(L83=1,IF(SUMPRODUCT(($L$35:$L$82=1)*(ABS($M$35:$M$82-M83)<0.000001)*(ABS($N$35:$N$82-N83)<0.000001)*($O$35:$O$82=O83)*(ABS($P$35:$P$82-P83)<0.000001)*($Q$35:$Q$82=Q83)*($V$35:$V$82=V83))=0,1,0),0) -> 1 | S83: =IF(AND(L83=1,N83>=$B$4-0.000000001,P83>=$B$6-0.000000001,M83>=Floor_q+$B$5-0.000000001),1,0) -> 0 | U83: =V46 -> 1 | V83: =CHOOSE(D83,U83,U83,1,U83) -> 1
A84: S* A S | B84: 3 | C84: 47 | D84: 1 | E84: =L47 -> 1 | F84: =M47 -> 592 | G84: =N47 -> 36.9 | H84: =O47 -> 59 | I84: =P47 -> 78 | J84: =Q47 -> 1 | K84: =IF(D84<=2,1-J84,IF(D84=3,IF(AND(U84=0,H84>=W_min,F84-D_dip>=Floor_q),1,0),IF(AND(H84>=W_min,F84>=Pre_A),1,0))) -> 0 | L84: =E84*K84 -> 0 | M84: =CHOOSE(D84,F84+Proc_S,F84+Proc_Sk,F84+D_dL,F84-Cost_A) -> 704 | N84: =CHOOSE(D84,(1-Tech_share)*G84,(1-Tech_share)*G84,G84+D_dT,G84) -> 33.21 | O84: =CHOOSE(D84,H84-W_lost,H84,H84,H84+W_gain) -> 54 | P84: =CHOOSE(D84,I84,I84,I84+D_dE,I84+Close_A*(Ceil_E-I84)) -> 78 | Q84: =CHOOSE(D84,1,1,J84,J84) -> 1 | R84: =IF(L84=1,IF(SUMPRODUCT(($L$35:$L$83=1)*(ABS($M$35:$M$83-M84)<0.000001)*(ABS($N$35:$N$83-N84)<0.000001)*($O$35:$O$83=O84)*(ABS($P$35:$P$83-P84)<0.000001)*($Q$35:$Q$83=Q84)*($V$35:$V$83=V84))=0,1,0),0) -> 0 | S84: =IF(AND(L84=1,N84>=$B$4-0.000000001,P84>=$B$6-0.000000001,M84>=Floor_q+$B$5-0.000000001),1,0) -> 0 | U84: =V47 -> 0 | V84: =CHOOSE(D84,U84,U84,1,U84) -> 0
A85: S* A S* | B85: 3 | C85: 47 | D85: 2 | E85: =L47 -> 1 | F85: =M47 -> 592 | G85: =N47 -> 36.9 | H85: =O47 -> 59 | I85: =P47 -> 78 | J85: =Q47 -> 1 | K85: =IF(D85<=2,1-J85,IF(D85=3,IF(AND(U85=0,H85>=W_min,F85-D_dip>=Floor_q),1,0),IF(AND(H85>=W_min,F85>=Pre_A),1,0))) -> 0 | L85: =E85*K85 -> 0 | M85: =CHOOSE(D85,F85+Proc_S,F85+Proc_Sk,F85+D_dL,F85-Cost_A) -> 684 | N85: =CHOOSE(D85,(1-Tech_share)*G85,(1-Tech_share)*G85,G85+D_dT,G85) -> 33.21 | O85: =CHOOSE(D85,H85-W_lost,H85,H85,H85+W_gain) -> 59 | P85: =CHOOSE(D85,I85,I85,I85+D_dE,I85+Close_A*(Ceil_E-I85)) -> 78 | Q85: =CHOOSE(D85,1,1,J85,J85) -> 1 | R85: =IF(L85=1,IF(SUMPRODUCT(($L$35:$L$84=1)*(ABS($M$35:$M$84-M85)<0.000001)*(ABS($N$35:$N$84-N85)<0.000001)*($O$35:$O$84=O85)*(ABS($P$35:$P$84-P85)<0.000001)*($Q$35:$Q$84=Q85)*($V$35:$V$84=V85))=0,1,0),0) -> 0 | S85: =IF(AND(L85=1,N85>=$B$4-0.000000001,P85>=$B$6-0.000000001,M85>=Floor_q+$B$5-0.000000001),1,0) -> 0 | U85: =V47 -> 0 | V85: =CHOOSE(D85,U85,U85,1,U85) -> 0
A86: S* A D | B86: 3 | C86: 47 | D86: 3 | E86: =L47 -> 1 | F86: =M47 -> 592 | G86: =N47 -> 36.9 | H86: =O47 -> 59 | I86: =P47 -> 78 | J86: =Q47 -> 1 | K86: =IF(D86<=2,1-J86,IF(D86=3,IF(AND(U86=0,H86>=W_min,F86-D_dip>=Floor_q),1,0),IF(AND(H86>=W_min,F86>=Pre_A),1,0))) -> 1 | L86: =E86*K86 -> 1 | M86: =CHOOSE(D86,F86+Proc_S,F86+Proc_Sk,F86+D_dL,F86-Cost_A) -> 556.63273 | N86: =CHOOSE(D86,(1-Tech_share)*G86,(1-Tech_share)*G86,G86+D_dT,G86) -> 71.534669 | O86: =CHOOSE(D86,H86-W_lost,H86,H86,H86+W_gain) -> 59 | P86: =CHOOSE(D86,I86,I86,I86+D_dE,I86+Close_A*(Ceil_E-I86)) -> 80.598331 | Q86: =CHOOSE(D86,1,1,J86,J86) -> 1 | R86: =IF(L86=1,IF(SUMPRODUCT(($L$35:$L$85=1)*(ABS($M$35:$M$85-M86)<0.000001)*(ABS($N$35:$N$85-N86)<0.000001)*($O$35:$O$85=O86)*(ABS($P$35:$P$85-P86)<0.000001)*($Q$35:$Q$85=Q86)*($V$35:$V$85=V86))=0,1,0),0) -> 1 | S86: =IF(AND(L86=1,N86>=$B$4-0.000000001,P86>=$B$6-0.000000001,M86>=Floor_q+$B$5-0.000000001),1,0) -> 1 | U86: =V47 -> 0 | V86: =CHOOSE(D86,U86,U86,1,U86) -> 1
A87: S* A A | B87: 3 | C87: 47 | D87: 4 | E87: =L47 -> 1 | F87: =M47 -> 592 | G87: =N47 -> 36.9 | H87: =O47 -> 59 | I87: =P47 -> 78 | J87: =Q47 -> 1 | K87: =IF(D87<=2,1-J87,IF(D87=3,IF(AND(U87=0,H87>=W_min,F87-D_dip>=Floor_q),1,0),IF(AND(H87>=W_min,F87>=Pre_A),1,0))) -> 1 | L87: =E87*K87 -> 1 | M87: =CHOOSE(D87,F87+Proc_S,F87+Proc_Sk,F87+D_dL,F87-Cost_A) -> 472 | N87: =CHOOSE(D87,(1-Tech_share)*G87,(1-Tech_share)*G87,G87+D_dT,G87) -> 36.9 | O87: =CHOOSE(D87,H87-W_lost,H87,H87,H87+W_gain) -> 60 | P87: =CHOOSE(D87,I87,I87,I87+D_dE,I87+Close_A*(Ceil_E-I87)) -> 81.5 | Q87: =CHOOSE(D87,1,1,J87,J87) -> 1 | R87: =IF(L87=1,IF(SUMPRODUCT(($L$35:$L$86=1)*(ABS($M$35:$M$86-M87)<0.000001)*(ABS($N$35:$N$86-N87)<0.000001)*($O$35:$O$86=O87)*(ABS($P$35:$P$86-P87)<0.000001)*($Q$35:$Q$86=Q87)*($V$35:$V$86=V87))=0,1,0),0) -> 1 | S87: =IF(AND(L87=1,N87>=$B$4-0.000000001,P87>=$B$6-0.000000001,M87>=Floor_q+$B$5-0.000000001),1,0) -> 0 | U87: =V47 -> 0 | V87: =CHOOSE(D87,U87,U87,1,U87) -> 0
A88: D S S | B88: 3 | C88: 48 | D88: 1 | E88: =L48 -> 1 | F88: =M48 -> 696.63273 | G88: =N48 -> 68.071202 | H88: =O48 -> 53 | I88: =P48 -> 73.598331 | J88: =Q48 -> 1 | K88: =IF(D88<=2,1-J88,IF(D88=3,IF(AND(U88=0,H88>=W_min,F88-D_dip>=Floor_q),1,0),IF(AND(H88>=W_min,F88>=Pre_A),1,0))) -> 0 | L88: =E88*K88 -> 0 | M88: =CHOOSE(D88,F88+Proc_S,F88+Proc_Sk,F88+D_dL,F88-Cost_A) -> 808.63273 | N88: =CHOOSE(D88,(1-Tech_share)*G88,(1-Tech_share)*G88,G88+D_dT,G88) -> 61.264082 | O88: =CHOOSE(D88,H88-W_lost,H88,H88,H88+W_gain) -> 48 | P88: =CHOOSE(D88,I88,I88,I88+D_dE,I88+Close_A*(Ceil_E-I88)) -> 73.598331 | Q88: =CHOOSE(D88,1,1,J88,J88) -> 1 | R88: =IF(L88=1,IF(SUMPRODUCT(($L$35:$L$87=1)*(ABS($M$35:$M$87-M88)<0.000001)*(ABS($N$35:$N$87-N88)<0.000001)*($O$35:$O$87=O88)*(ABS($P$35:$P$87-P88)<0.000001)*($Q$35:$Q$87=Q88)*($V$35:$V$87=V88))=0,1,0),0) -> 0 | S88: =IF(AND(L88=1,N88>=$B$4-0.000000001,P88>=$B$6-0.000000001,M88>=Floor_q+$B$5-0.000000001),1,0) -> 0 | U88: =V48 -> 1 | V88: =CHOOSE(D88,U88,U88,1,U88) -> 1
A89: D S S* | B89: 3 | C89: 48 | D89: 2 | E89: =L48 -> 1 | F89: =M48 -> 696.63273 | G89: =N48 -> 68.071202 | H89: =O48 -> 53 | I89: =P48 -> 73.598331 | J89: =Q48 -> 1 | K89: =IF(D89<=2,1-J89,IF(D89=3,IF(AND(U89=0,H89>=W_min,F89-D_dip>=Floor_q),1,0),IF(AND(H89>=W_min,F89>=Pre_A),1,0))) -> 0 | L89: =E89*K89 -> 0 | M89: =CHOOSE(D89,F89+Proc_S,F89+Proc_Sk,F89+D_dL,F89-Cost_A) -> 788.63273 | N89: =CHOOSE(D89,(1-Tech_share)*G89,(1-Tech_share)*G89,G89+D_dT,G89) -> 61.264082 | O89: =CHOOSE(D89,H89-W_lost,H89,H89,H89+W_gain) -> 53 | P89: =CHOOSE(D89,I89,I89,I89+D_dE,I89+Close_A*(Ceil_E-I89)) -> 73.598331 | Q89: =CHOOSE(D89,1,1,J89,J89) -> 1 | R89: =IF(L89=1,IF(SUMPRODUCT(($L$35:$L$88=1)*(ABS($M$35:$M$88-M89)<0.000001)*(ABS($N$35:$N$88-N89)<0.000001)*($O$35:$O$88=O89)*(ABS($P$35:$P$88-P89)<0.000001)*($Q$35:$Q$88=Q89)*($V$35:$V$88=V89))=0,1,0),0) -> 0 | S89: =IF(AND(L89=1,N89>=$B$4-0.000000001,P89>=$B$6-0.000000001,M89>=Floor_q+$B$5-0.000000001),1,0) -> 0 | U89: =V48 -> 1 | V89: =CHOOSE(D89,U89,U89,1,U89) -> 1
A90: D S D | B90: 3 | C90: 48 | D90: 3 | E90: =L48 -> 1 | F90: =M48 -> 696.63273 | G90: =N48 -> 68.071202 | H90: =O48 -> 53 | I90: =P48 -> 73.598331 | J90: =Q48 -> 1 | K90: =IF(D90<=2,1-J90,IF(D90=3,IF(AND(U90=0,H90>=W_min,F90-D_dip>=Floor_q),1,0),IF(AND(H90>=W_min,F90>=Pre_A),1,0))) -> 0 | L90: =E90*K90 -> 0 | M90: =CHOOSE(D90,F90+Proc_S,F90+Proc_Sk,F90+D_dL,F90-Cost_A) -> 661.26546 | N90: =CHOOSE(D90,(1-Tech_share)*G90,(1-Tech_share)*G90,G90+D_dT,G90) -> 102.70587 | O90: =CHOOSE(D90,H90-W_lost,H90,H90,H90+W_gain) -> 53 | P90: =CHOOSE(D90,I90,I90,I90+D_dE,I90+Close_A*(Ceil_E-I90)) -> 76.196662 | Q90: =CHOOSE(D90,1,1,J90,J90) -> 1 | R90: =IF(L90=1,IF(SUMPRODUCT(($L$35:$L$89=1)*(ABS($M$35:$M$89-M90)<0.000001)*(ABS($N$35:$N$89-N90)<0.000001)*($O$35:$O$89=O90)*(ABS($P$35:$P$89-P90)<0.000001)*($Q$35:$Q$89=Q90)*($V$35:$V$89=V90))=0,1,0),0) -> 0 | S90: =IF(AND(L90=1,N90>=$B$4-0.000000001,P90>=$B$6-0.000000001,M90>=Floor_q+$B$5-0.000000001),1,0) -> 0 | U90: =V48 -> 1 | V90: =CHOOSE(D90,U90,U90,1,U90) -> 1
A91: D S A | B91: 3 | C91: 48 | D91: 4 | E91: =L48 -> 1 | F91: =M48 -> 696.63273 | G91: =N48 -> 68.071202 | H91: =O48 -> 53 | I91: =P48 -> 73.598331 | J91: =Q48 -> 1 | K91: =IF(D91<=2,1-J91,IF(D91=3,IF(AND(U91=0,H91>=W_min,F91-D_dip>=Floor_q),1,0),IF(AND(H91>=W_min,F91>=Pre_A),1,0))) -> 0 | L91: =E91*K91 -> 0 | M91: =CHOOSE(D91,F91+Proc_S,F91+Proc_Sk,F91+D_dL,F91-Cost_A) -> 576.63273 | N91: =CHOOSE(D91,(1-Tech_share)*G91,(1-Tech_share)*G91,G91+D_dT,G91) -> 68.071202 | O91: =CHOOSE(D91,H91-W_lost,H91,H91,H91+W_gain) -> 54 | P91: =CHOOSE(D91,I91,I91,I91+D_dE,I91+Close_A*(Ceil_E-I91)) -> 79.299165 | Q91: =CHOOSE(D91,1,1,J91,J91) -> 1 | R91: =IF(L91=1,IF(SUMPRODUCT(($L$35:$L$90=1)*(ABS($M$35:$M$90-M91)<0.000001)*(ABS($N$35:$N$90-N91)<0.000001)*($O$35:$O$90=O91)*(ABS($P$35:$P$90-P91)<0.000001)*($Q$35:$Q$90=Q91)*($V$35:$V$90=V91))=0,1,0),0) -> 0 | S91: =IF(AND(L91=1,N91>=$B$4-0.000000001,P91>=$B$6-0.000000001,M91>=Floor_q+$B$5-0.000000001),1,0) -> 0 | U91: =V48 -> 1 | V91: =CHOOSE(D91,U91,U91,1,U91) -> 1
A92: D S* S | B92: 3 | C92: 49 | D92: 1 | E92: =L49 -> 1 | F92: =M49 -> 676.63273 | G92: =N49 -> 68.071202 | H92: =O49 -> 58 | I92: =P49 -> 73.598331 | J92: =Q49 -> 1 | K92: =IF(D92<=2,1-J92,IF(D92=3,IF(AND(U92=0,H92>=W_min,F92-D_dip>=Floor_q),1,0),IF(AND(H92>=W_min,F92>=Pre_A),1,0))) -> 0 | L92: =E92*K92 -> 0 | M92: =CHOOSE(D92,F92+Proc_S,F92+Proc_Sk,F92+D_dL,F92-Cost_A) -> 788.63273 | N92: =CHOOSE(D92,(1-Tech_share)*G92,(1-Tech_share)*G92,G92+D_dT,G92) -> 61.264082 | O92: =CHOOSE(D92,H92-W_lost,H92,H92,H92+W_gain) -> 53 | P92: =CHOOSE(D92,I92,I92,I92+D_dE,I92+Close_A*(Ceil_E-I92)) -> 73.598331 | Q92: =CHOOSE(D92,1,1,J92,J92) -> 1 | R92: =IF(L92=1,IF(SUMPRODUCT(($L$35:$L$91=1)*(ABS($M$35:$M$91-M92)<0.000001)*(ABS($N$35:$N$91-N92)<0.000001)*($O$35:$O$91=O92)*(ABS($P$35:$P$91-P92)<0.000001)*($Q$35:$Q$91=Q92)*($V$35:$V$91=V92))=0,1,0),0) -> 0 | S92: =IF(AND(L92=1,N92>=$B$4-0.000000001,P92>=$B$6-0.000000001,M92>=Floor_q+$B$5-0.000000001),1,0) -> 0 | U92: =V49 -> 1 | V92: =CHOOSE(D92,U92,U92,1,U92) -> 1
A93: D S* S* | B93: 3 | C93: 49 | D93: 2 | E93: =L49 -> 1 | F93: =M49 -> 676.63273 | G93: =N49 -> 68.071202 | H93: =O49 -> 58 | I93: =P49 -> 73.598331 | J93: =Q49 -> 1 | K93: =IF(D93<=2,1-J93,IF(D93=3,IF(AND(U93=0,H93>=W_min,F93-D_dip>=Floor_q),1,0),IF(AND(H93>=W_min,F93>=Pre_A),1,0))) -> 0 | L93: =E93*K93 -> 0 | M93: =CHOOSE(D93,F93+Proc_S,F93+Proc_Sk,F93+D_dL,F93-Cost_A) -> 768.63273 | N93: =CHOOSE(D93,(1-Tech_share)*G93,(1-Tech_share)*G93,G93+D_dT,G93) -> 61.264082 | O93: =CHOOSE(D93,H93-W_lost,H93,H93,H93+W_gain) -> 58 | P93: =CHOOSE(D93,I93,I93,I93+D_dE,I93+Close_A*(Ceil_E-I93)) -> 73.598331 | Q93: =CHOOSE(D93,1,1,J93,J93) -> 1 | R93: =IF(L93=1,IF(SUMPRODUCT(($L$35:$L$92=1)*(ABS($M$35:$M$92-M93)<0.000001)*(ABS($N$35:$N$92-N93)<0.000001)*($O$35:$O$92=O93)*(ABS($P$35:$P$92-P93)<0.000001)*($Q$35:$Q$92=Q93)*($V$35:$V$92=V93))=0,1,0),0) -> 0 | S93: =IF(AND(L93=1,N93>=$B$4-0.000000001,P93>=$B$6-0.000000001,M93>=Floor_q+$B$5-0.000000001),1,0) -> 0 | U93: =V49 -> 1 | V93: =CHOOSE(D93,U93,U93,1,U93) -> 1
A94: D S* D | B94: 3 | C94: 49 | D94: 3 | E94: =L49 -> 1 | F94: =M49 -> 676.63273 | G94: =N49 -> 68.071202 | H94: =O49 -> 58 | I94: =P49 -> 73.598331 | J94: =Q49 -> 1 | K94: =IF(D94<=2,1-J94,IF(D94=3,IF(AND(U94=0,H94>=W_min,F94-D_dip>=Floor_q),1,0),IF(AND(H94>=W_min,F94>=Pre_A),1,0))) -> 0 | L94: =E94*K94 -> 0 | M94: =CHOOSE(D94,F94+Proc_S,F94+Proc_Sk,F94+D_dL,F94-Cost_A) -> 641.26546 | N94: =CHOOSE(D94,(1-Tech_share)*G94,(1-Tech_share)*G94,G94+D_dT,G94) -> 102.70587 | O94: =CHOOSE(D94,H94-W_lost,H94,H94,H94+W_gain) -> 58 | P94: =CHOOSE(D94,I94,I94,I94+D_dE,I94+Close_A*(Ceil_E-I94)) -> 76.196662 | Q94: =CHOOSE(D94,1,1,J94,J94) -> 1 | R94: =IF(L94=1,IF(SUMPRODUCT(($L$35:$L$93=1)*(ABS($M$35:$M$93-M94)<0.000001)*(ABS($N$35:$N$93-N94)<0.000001)*($O$35:$O$93=O94)*(ABS($P$35:$P$93-P94)<0.000001)*($Q$35:$Q$93=Q94)*($V$35:$V$93=V94))=0,1,0),0) -> 0 | S94: =IF(AND(L94=1,N94>=$B$4-0.000000001,P94>=$B$6-0.000000001,M94>=Floor_q+$B$5-0.000000001),1,0) -> 0 | U94: =V49 -> 1 | V94: =CHOOSE(D94,U94,U94,1,U94) -> 1
A95: D S* A | B95: 3 | C95: 49 | D95: 4 | E95: =L49 -> 1 | F95: =M49 -> 676.63273 | G95: =N49 -> 68.071202 | H95: =O49 -> 58 | I95: =P49 -> 73.598331 | J95: =Q49 -> 1 | K95: =IF(D95<=2,1-J95,IF(D95=3,IF(AND(U95=0,H95>=W_min,F95-D_dip>=Floor_q),1,0),IF(AND(H95>=W_min,F95>=Pre_A),1,0))) -> 1 | L95: =E95*K95 -> 1 | M95: =CHOOSE(D95,F95+Proc_S,F95+Proc_Sk,F95+D_dL,F95-Cost_A) -> 556.63273 | N95: =CHOOSE(D95,(1-Tech_share)*G95,(1-Tech_share)*G95,G95+D_dT,G95) -> 68.071202 | O95: =CHOOSE(D95,H95-W_lost,H95,H95,H95+W_gain) -> 59 | P95: =CHOOSE(D95,I95,I95,I95+D_dE,I95+Close_A*(Ceil_E-I95)) -> 79.299165 | Q95: =CHOOSE(D95,1,1,J95,J95) -> 1 | R95: =IF(L95=1,IF(SUMPRODUCT(($L$35:$L$94=1)*(ABS($M$35:$M$94-M95)<0.000001)*(ABS($N$35:$N$94-N95)<0.000001)*($O$35:$O$94=O95)*(ABS($P$35:$P$94-P95)<0.000001)*($Q$35:$Q$94=Q95)*($V$35:$V$94=V95))=0,1,0),0) -> 1 | S95: =IF(AND(L95=1,N95>=$B$4-0.000000001,P95>=$B$6-0.000000001,M95>=Floor_q+$B$5-0.000000001),1,0) -> 0 | U95: =V49 -> 1 | V95: =CHOOSE(D95,U95,U95,1,U95) -> 1
A96: D D S | B96: 3 | C96: 50 | D96: 1 | E96: =L50 -> 0 | F96: =M50 -> 549.26546 | G96: =N50 -> 110.26934 | H96: =O50 -> 58 | I96: =P50 -> 76.196662 | J96: =Q50 -> 0 | K96: =IF(D96<=2,1-J96,IF(D96=3,IF(AND(U96=0,H96>=W_min,F96-D_dip>=Floor_q),1,0),IF(AND(H96>=W_min,F96>=Pre_A),1,0))) -> 1 | L96: =E96*K96 -> 0 | M96: =CHOOSE(D96,F96+Proc_S,F96+Proc_Sk,F96+D_dL,F96-Cost_A) -> 661.26546 | N96: =CHOOSE(D96,(1-Tech_share)*G96,(1-Tech_share)*G96,G96+D_dT,G96) -> 99.242404 | O96: =CHOOSE(D96,H96-W_lost,H96,H96,H96+W_gain) -> 53 | P96: =CHOOSE(D96,I96,I96,I96+D_dE,I96+Close_A*(Ceil_E-I96)) -> 76.196662 | Q96: =CHOOSE(D96,1,1,J96,J96) -> 1 | R96: =IF(L96=1,IF(SUMPRODUCT(($L$35:$L$95=1)*(ABS($M$35:$M$95-M96)<0.000001)*(ABS($N$35:$N$95-N96)<0.000001)*($O$35:$O$95=O96)*(ABS($P$35:$P$95-P96)<0.000001)*($Q$35:$Q$95=Q96)*($V$35:$V$95=V96))=0,1,0),0) -> 0 | S96: =IF(AND(L96=1,N96>=$B$4-0.000000001,P96>=$B$6-0.000000001,M96>=Floor_q+$B$5-0.000000001),1,0) -> 0 | U96: =V50 -> 1 | V96: =CHOOSE(D96,U96,U96,1,U96) -> 1
A97: D D S* | B97: 3 | C97: 50 | D97: 2 | E97: =L50 -> 0 | F97: =M50 -> 549.26546 | G97: =N50 -> 110.26934 | H97: =O50 -> 58 | I97: =P50 -> 76.196662 | J97: =Q50 -> 0 | K97: =IF(D97<=2,1-J97,IF(D97=3,IF(AND(U97=0,H97>=W_min,F97-D_dip>=Floor_q),1,0),IF(AND(H97>=W_min,F97>=Pre_A),1,0))) -> 1 | L97: =E97*K97 -> 0 | M97: =CHOOSE(D97,F97+Proc_S,F97+Proc_Sk,F97+D_dL,F97-Cost_A) -> 641.26546 | N97: =CHOOSE(D97,(1-Tech_share)*G97,(1-Tech_share)*G97,G97+D_dT,G97) -> 99.242404 | O97: =CHOOSE(D97,H97-W_lost,H97,H97,H97+W_gain) -> 58 | P97: =CHOOSE(D97,I97,I97,I97+D_dE,I97+Close_A*(Ceil_E-I97)) -> 76.196662 | Q97: =CHOOSE(D97,1,1,J97,J97) -> 1 | R97: =IF(L97=1,IF(SUMPRODUCT(($L$35:$L$96=1)*(ABS($M$35:$M$96-M97)<0.000001)*(ABS($N$35:$N$96-N97)<0.000001)*($O$35:$O$96=O97)*(ABS($P$35:$P$96-P97)<0.000001)*($Q$35:$Q$96=Q97)*($V$35:$V$96=V97))=0,1,0),0) -> 0 | S97: =IF(AND(L97=1,N97>=$B$4-0.000000001,P97>=$B$6-0.000000001,M97>=Floor_q+$B$5-0.000000001),1,0) -> 0 | U97: =V50 -> 1 | V97: =CHOOSE(D97,U97,U97,1,U97) -> 1
A98: D D D | B98: 3 | C98: 50 | D98: 3 | E98: =L50 -> 0 | F98: =M50 -> 549.26546 | G98: =N50 -> 110.26934 | H98: =O50 -> 58 | I98: =P50 -> 76.196662 | J98: =Q50 -> 0 | K98: =IF(D98<=2,1-J98,IF(D98=3,IF(AND(U98=0,H98>=W_min,F98-D_dip>=Floor_q),1,0),IF(AND(H98>=W_min,F98>=Pre_A),1,0))) -> 0 | L98: =E98*K98 -> 0 | M98: =CHOOSE(D98,F98+Proc_S,F98+Proc_Sk,F98+D_dL,F98-Cost_A) -> 513.89819 | N98: =CHOOSE(D98,(1-Tech_share)*G98,(1-Tech_share)*G98,G98+D_dT,G98) -> 144.90401 | O98: =CHOOSE(D98,H98-W_lost,H98,H98,H98+W_gain) -> 58 | P98: =CHOOSE(D98,I98,I98,I98+D_dE,I98+Close_A*(Ceil_E-I98)) -> 78.794993 | Q98: =CHOOSE(D98,1,1,J98,J98) -> 0 | R98: =IF(L98=1,IF(SUMPRODUCT(($L$35:$L$97=1)*(ABS($M$35:$M$97-M98)<0.000001)*(ABS($N$35:$N$97-N98)<0.000001)*($O$35:$O$97=O98)*(ABS($P$35:$P$97-P98)<0.000001)*($Q$35:$Q$97=Q98)*($V$35:$V$97=V98))=0,1,0),0) -> 0 | S98: =IF(AND(L98=1,N98>=$B$4-0.000000001,P98>=$B$6-0.000000001,M98>=Floor_q+$B$5-0.000000001),1,0) -> 0 | U98: =V50 -> 1 | V98: =CHOOSE(D98,U98,U98,1,U98) -> 1
A99: D D A | B99: 3 | C99: 50 | D99: 4 | E99: =L50 -> 0 | F99: =M50 -> 549.26546 | G99: =N50 -> 110.26934 | H99: =O50 -> 58 | I99: =P50 -> 76.196662 | J99: =Q50 -> 0 | K99: =IF(D99<=2,1-J99,IF(D99=3,IF(AND(U99=0,H99>=W_min,F99-D_dip>=Floor_q),1,0),IF(AND(H99>=W_min,F99>=Pre_A),1,0))) -> 1 | L99: =E99*K99 -> 0 | M99: =CHOOSE(D99,F99+Proc_S,F99+Proc_Sk,F99+D_dL,F99-Cost_A) -> 429.26546 | N99: =CHOOSE(D99,(1-Tech_share)*G99,(1-Tech_share)*G99,G99+D_dT,G99) -> 110.26934 | O99: =CHOOSE(D99,H99-W_lost,H99,H99,H99+W_gain) -> 59 | P99: =CHOOSE(D99,I99,I99,I99+D_dE,I99+Close_A*(Ceil_E-I99)) -> 80.598331 | Q99: =CHOOSE(D99,1,1,J99,J99) -> 0 | R99: =IF(L99=1,IF(SUMPRODUCT(($L$35:$L$98=1)*(ABS($M$35:$M$98-M99)<0.000001)*(ABS($N$35:$N$98-N99)<0.000001)*($O$35:$O$98=O99)*(ABS($P$35:$P$98-P99)<0.000001)*($Q$35:$Q$98=Q99)*($V$35:$V$98=V99))=0,1,0),0) -> 0 | S99: =IF(AND(L99=1,N99>=$B$4-0.000000001,P99>=$B$6-0.000000001,M99>=Floor_q+$B$5-0.000000001),1,0) -> 0 | U99: =V50 -> 1 | V99: =CHOOSE(D99,U99,U99,1,U99) -> 1
A100: D A S | B100: 3 | C100: 51 | D100: 1 | E100: =L51 -> 1 | F100: =M51 -> 464.63273 | G100: =N51 -> 75.634669 | H100: =O51 -> 59 | I100: =P51 -> 79.299165 | J100: =Q51 -> 0 | K100: =IF(D100<=2,1-J100,IF(D100=3,IF(AND(U100=0,H100>=W_min,F100-D_dip>=Floor_q),1,0),IF(AND(H100>=W_min,F100>=Pre_A),1,0))) -> 1 | L100: =E100*K100 -> 1 | M100: =CHOOSE(D100,F100+Proc_S,F100+Proc_Sk,F100+D_dL,F100-Cost_A) -> 576.63273 | N100: =CHOOSE(D100,(1-Tech_share)*G100,(1-Tech_share)*G100,G100+D_dT,G100) -> 68.071202 | O100: =CHOOSE(D100,H100-W_lost,H100,H100,H100+W_gain) -> 54 | P100: =CHOOSE(D100,I100,I100,I100+D_dE,I100+Close_A*(Ceil_E-I100)) -> 79.299165 | Q100: =CHOOSE(D100,1,1,J100,J100) -> 1 | R100: =IF(L100=1,IF(SUMPRODUCT(($L$35:$L$99=1)*(ABS($M$35:$M$99-M100)<0.000001)*(ABS($N$35:$N$99-N100)<0.000001)*($O$35:$O$99=O100)*(ABS($P$35:$P$99-P100)<0.000001)*($Q$35:$Q$99=Q100)*($V$35:$V$99=V100))=0,1,0),0) -> 1 | S100: =IF(AND(L100=1,N100>=$B$4-0.000000001,P100>=$B$6-0.000000001,M100>=Floor_q+$B$5-0.000000001),1,0) -> 0 | U100: =V51 -> 1 | V100: =CHOOSE(D100,U100,U100,1,U100) -> 1
A101: D A S* | B101: 3 | C101: 51 | D101: 2 | E101: =L51 -> 1 | F101: =M51 -> 464.63273 | G101: =N51 -> 75.634669 | H101: =O51 -> 59 | I101: =P51 -> 79.299165 | J101: =Q51 -> 0 | K101: =IF(D101<=2,1-J101,IF(D101=3,IF(AND(U101=0,H101>=W_min,F101-D_dip>=Floor_q),1,0),IF(AND(H101>=W_min,F101>=Pre_A),1,0))) -> 1 | L101: =E101*K101 -> 1 | M101: =CHOOSE(D101,F101+Proc_S,F101+Proc_Sk,F101+D_dL,F101-Cost_A) -> 556.63273 | N101: =CHOOSE(D101,(1-Tech_share)*G101,(1-Tech_share)*G101,G101+D_dT,G101) -> 68.071202 | O101: =CHOOSE(D101,H101-W_lost,H101,H101,H101+W_gain) -> 59 | P101: =CHOOSE(D101,I101,I101,I101+D_dE,I101+Close_A*(Ceil_E-I101)) -> 79.299165 | Q101: =CHOOSE(D101,1,1,J101,J101) -> 1 | R101: =IF(L101=1,IF(SUMPRODUCT(($L$35:$L$100=1)*(ABS($M$35:$M$100-M101)<0.000001)*(ABS($N$35:$N$100-N101)<0.000001)*($O$35:$O$100=O101)*(ABS($P$35:$P$100-P101)<0.000001)*($Q$35:$Q$100=Q101)*($V$35:$V$100=V101))=0,1,0),0) -> 0 | S101: =IF(AND(L101=1,N101>=$B$4-0.000000001,P101>=$B$6-0.000000001,M101>=Floor_q+$B$5-0.000000001),1,0) -> 0 | U101: =V51 -> 1 | V101: =CHOOSE(D101,U101,U101,1,U101) -> 1
A102: D A D | B102: 3 | C102: 51 | D102: 3 | E102: =L51 -> 1 | F102: =M51 -> 464.63273 | G102: =N51 -> 75.634669 | H102: =O51 -> 59 | I102: =P51 -> 79.299165 | J102: =Q51 -> 0 | K102: =IF(D102<=2,1-J102,IF(D102=3,IF(AND(U102=0,H102>=W_min,F102-D_dip>=Floor_q),1,0),IF(AND(H102>=W_min,F102>=Pre_A),1,0))) -> 0 | L102: =E102*K102 -> 0 | M102: =CHOOSE(D102,F102+Proc_S,F102+Proc_Sk,F102+D_dL,F102-Cost_A) -> 429.26546 | N102: =CHOOSE(D102,(1-Tech_share)*G102,(1-Tech_share)*G102,G102+D_dT,G102) -> 110.26934 | O102: =CHOOSE(D102,H102-W_lost,H102,H102,H102+W_gain) -> 59 | P102: =CHOOSE(D102,I102,I102,I102+D_dE,I102+Close_A*(Ceil_E-I102)) -> 81.897496 | Q102: =CHOOSE(D102,1,1,J102,J102) -> 0 | R102: =IF(L102=1,IF(SUMPRODUCT(($L$35:$L$101=1)*(ABS($M$35:$M$101-M102)<0.000001)*(ABS($N$35:$N$101-N102)<0.000001)*($O$35:$O$101=O102)*(ABS($P$35:$P$101-P102)<0.000001)*($Q$35:$Q$101=Q102)*($V$35:$V$101=V102))=0,1,0),0) -> 0 | S102: =IF(AND(L102=1,N102>=$B$4-0.000000001,P102>=$B$6-0.000000001,M102>=Floor_q+$B$5-0.000000001),1,0) -> 0 | U102: =V51 -> 1 | V102: =CHOOSE(D102,U102,U102,1,U102) -> 1
A103: D A A | B103: 3 | C103: 51 | D103: 4 | E103: =L51 -> 1 | F103: =M51 -> 464.63273 | G103: =N51 -> 75.634669 | H103: =O51 -> 59 | I103: =P51 -> 79.299165 | J103: =Q51 -> 0 | K103: =IF(D103<=2,1-J103,IF(D103=3,IF(AND(U103=0,H103>=W_min,F103-D_dip>=Floor_q),1,0),IF(AND(H103>=W_min,F103>=Pre_A),1,0))) -> 0 | L103: =E103*K103 -> 0 | M103: =CHOOSE(D103,F103+Proc_S,F103+Proc_Sk,F103+D_dL,F103-Cost_A) -> 344.63273 | N103: =CHOOSE(D103,(1-Tech_share)*G103,(1-Tech_share)*G103,G103+D_dT,G103) -> 75.634669 | O103: =CHOOSE(D103,H103-W_lost,H103,H103,H103+W_gain) -> 60 | P103: =CHOOSE(D103,I103,I103,I103+D_dE,I103+Close_A*(Ceil_E-I103)) -> 82.149583 | Q103: =CHOOSE(D103,1,1,J103,J103) -> 0 | R103: =IF(L103=1,IF(SUMPRODUCT(($L$35:$L$102=1)*(ABS($M$35:$M$102-M103)<0.000001)*(ABS($N$35:$N$102-N103)<0.000001)*($O$35:$O$102=O103)*(ABS($P$35:$P$102-P103)<0.000001)*($Q$35:$Q$102=Q103)*($V$35:$V$102=V103))=0,1,0),0) -> 0 | S103: =IF(AND(L103=1,N103>=$B$4-0.000000001,P103>=$B$6-0.000000001,M103>=Floor_q+$B$5-0.000000001),1,0) -> 0 | U103: =V51 -> 1 | V103: =CHOOSE(D103,U103,U103,1,U103) -> 1
A104: A S S | B104: 3 | C104: 52 | D104: 1 | E104: =L52 -> 1 | F104: =M52 -> 612 | G104: =N52 -> 36.9 | H104: =O52 -> 54 | I104: =P52 -> 78 | J104: =Q52 -> 1 | K104: =IF(D104<=2,1-J104,IF(D104=3,IF(AND(U104=0,H104>=W_min,F104-D_dip>=Floor_q),1,0),IF(AND(H104>=W_min,F104>=Pre_A),1,0))) -> 0 | L104: =E104*K104 -> 0 | M104: =CHOOSE(D104,F104+Proc_S,F104+Proc_Sk,F104+D_dL,F104-Cost_A) -> 724 | N104: =CHOOSE(D104,(1-Tech_share)*G104,(1-Tech_share)*G104,G104+D_dT,G104) -> 33.21 | O104: =CHOOSE(D104,H104-W_lost,H104,H104,H104+W_gain) -> 49 | P104: =CHOOSE(D104,I104,I104,I104+D_dE,I104+Close_A*(Ceil_E-I104)) -> 78 | Q104: =CHOOSE(D104,1,1,J104,J104) -> 1 | R104: =IF(L104=1,IF(SUMPRODUCT(($L$35:$L$103=1)*(ABS($M$35:$M$103-M104)<0.000001)*(ABS($N$35:$N$103-N104)<0.000001)*($O$35:$O$103=O104)*(ABS($P$35:$P$103-P104)<0.000001)*($Q$35:$Q$103=Q104)*($V$35:$V$103=V104))=0,1,0),0) -> 0 | S104: =IF(AND(L104=1,N104>=$B$4-0.000000001,P104>=$B$6-0.000000001,M104>=Floor_q+$B$5-0.000000001),1,0) -> 0 | U104: =V52 -> 0 | V104: =CHOOSE(D104,U104,U104,1,U104) -> 0
...

Sheet Stability
A1: Stress the execution: drift and its bound, and the playbook short of plan (Theorem 6.5; Equation 6.4; Figure 6.4; Remark 6.B.2; Worked Example 6.1, Step 4; AXIOM Lab 1.6, step 5)
A2: Each step falls short of the design by eps (percent of plan); the executed path stays within eps (1 + L + ... + L^(k-1)) of the designed one, never more than eps/(1 - L) when L < 1.
A3: Declaration | B3: Value
A4: Shortfall a quarter, eps (percent of plan) | B4: 1
A5: Sensitivity factors L: consolidating, neutral, amplifying | B5: 0.8 | C5: 1 | D5: 1.2
A8: Quarter k | B8: Drift, L = 0.8 (recursion) | C8: Drift, L = 1.0 (recursion) | D8: Drift, L = 1.2 (recursion) | E8: Equation 6.4, L = 0.8 | F8: Equation 6.4, L = 1.0 | G8: Equation 6.4, L = 1.2 | H8: Executed, design held at 100, L = 0.8 | I8: Executed, design held at 100, L = 1.0 | J8: Executed, design held at 100, L = 1.2 | K8: Gap from the design, L = 0.8 | L8: Gap from the design, L = 1.0 | M8: Gap from the design, L = 1.2
A9: 0 | B9: 0 | C9: 0 | D9: 0 | E9: =IF($B$5=1,$B$4*A9,$B$4*($B$5^A9-1)/($B$5-1)) -> 0 | F9: =IF($C$5=1,$B$4*A9,$B$4*($C$5^A9-1)/($C$5-1)) -> 0 | G9: =IF($D$5=1,$B$4*A9,$B$4*($D$5^A9-1)/($D$5-1)) -> 0 | H9: 100 | I9: 100 | J9: 100 | K9: =100-H9 -> 0 | L9: =100-I9 -> 0 | M9: =100-J9 -> 0
A10: 1 | B10: =$B$5*B9+$B$4 -> 1 | C10: =$C$5*C9+$B$4 -> 1 | D10: =$D$5*D9+$B$4 -> 1 | E10: =IF($B$5=1,$B$4*A10,$B$4*($B$5^A10-1)/($B$5-1)) -> 1 | F10: =IF($C$5=1,$B$4*A10,$B$4*($C$5^A10-1)/($C$5-1)) -> 1 | G10: =IF($D$5=1,$B$4*A10,$B$4*($D$5^A10-1)/($D$5-1)) -> 1 | H10: =$B$5*H9+100*(1-$B$5)-$B$4 -> 99 | I10: =$C$5*I9+100*(1-$C$5)-$B$4 -> 99 | J10: =$D$5*J9+100*(1-$D$5)-$B$4 -> 99 | K10: =100-H10 -> 1 | L10: =100-I10 -> 1 | M10: =100-J10 -> 1
A11: 2 | B11: =$B$5*B10+$B$4 -> 1.8 | C11: =$C$5*C10+$B$4 -> 2 | D11: =$D$5*D10+$B$4 -> 2.2 | E11: =IF($B$5=1,$B$4*A11,$B$4*($B$5^A11-1)/($B$5-1)) -> 1.8 | F11: =IF($C$5=1,$B$4*A11,$B$4*($C$5^A11-1)/($C$5-1)) -> 2 | G11: =IF($D$5=1,$B$4*A11,$B$4*($D$5^A11-1)/($D$5-1)) -> 2.2 | H11: =$B$5*H10+100*(1-$B$5)-$B$4 -> 98.2 | I11: =$C$5*I10+100*(1-$C$5)-$B$4 -> 98 | J11: =$D$5*J10+100*(1-$D$5)-$B$4 -> 97.8 | K11: =100-H11 -> 1.8 | L11: =100-I11 -> 2 | M11: =100-J11 -> 2.2
A12: 3 | B12: =$B$5*B11+$B$4 -> 2.44 | C12: =$C$5*C11+$B$4 -> 3 | D12: =$D$5*D11+$B$4 -> 3.64 | E12: =IF($B$5=1,$B$4*A12,$B$4*($B$5^A12-1)/($B$5-1)) -> 2.44 | F12: =IF($C$5=1,$B$4*A12,$B$4*($C$5^A12-1)/($C$5-1)) -> 3 | G12: =IF($D$5=1,$B$4*A12,$B$4*($D$5^A12-1)/($D$5-1)) -> 3.64 | H12: =$B$5*H11+100*(1-$B$5)-$B$4 -> 97.56 | I12: =$C$5*I11+100*(1-$C$5)-$B$4 -> 97 | J12: =$D$5*J11+100*(1-$D$5)-$B$4 -> 96.36 | K12: =100-H12 -> 2.44 | L12: =100-I12 -> 3 | M12: =100-J12 -> 3.64
A13: 4 | B13: =$B$5*B12+$B$4 -> 2.952 | C13: =$C$5*C12+$B$4 -> 4 | D13: =$D$5*D12+$B$4 -> 5.368 | E13: =IF($B$5=1,$B$4*A13,$B$4*($B$5^A13-1)/($B$5-1)) -> 2.952 | F13: =IF($C$5=1,$B$4*A13,$B$4*($C$5^A13-1)/($C$5-1)) -> 4 | G13: =IF($D$5=1,$B$4*A13,$B$4*($D$5^A13-1)/($D$5-1)) -> 5.368 | H13: =$B$5*H12+100*(1-$B$5)-$B$4 -> 97.048 | I13: =$C$5*I12+100*(1-$C$5)-$B$4 -> 96 | J13: =$D$5*J12+100*(1-$D$5)-$B$4 -> 94.632 | K13: =100-H13 -> 2.952 | L13: =100-I13 -> 4 | M13: =100-J13 -> 5.368
A14: 5 | B14: =$B$5*B13+$B$4 -> 3.3616 | C14: =$C$5*C13+$B$4 -> 5 | D14: =$D$5*D13+$B$4 -> 7.4416 | E14: =IF($B$5=1,$B$4*A14,$B$4*($B$5^A14-1)/($B$5-1)) -> 3.3616 | F14: =IF($C$5=1,$B$4*A14,$B$4*($C$5^A14-1)/($C$5-1)) -> 5 | G14: =IF($D$5=1,$B$4*A14,$B$4*($D$5^A14-1)/($D$5-1)) -> 7.4416 | H14: =$B$5*H13+100*(1-$B$5)-$B$4 -> 96.6384 | I14: =$C$5*I13+100*(1-$C$5)-$B$4 -> 95 | J14: =$D$5*J13+100*(1-$D$5)-$B$4 -> 92.5584 | K14: =100-H14 -> 3.3616 | L14: =100-I14 -> 5 | M14: =100-J14 -> 7.4416
A15: 6 | B15: =$B$5*B14+$B$4 -> 3.68928 | C15: =$C$5*C14+$B$4 -> 6 | D15: =$D$5*D14+$B$4 -> 9.92992 | E15: =IF($B$5=1,$B$4*A15,$B$4*($B$5^A15-1)/($B$5-1)) -> 3.68928 | F15: =IF($C$5=1,$B$4*A15,$B$4*($C$5^A15-1)/($C$5-1)) -> 6 | G15: =IF($D$5=1,$B$4*A15,$B$4*($D$5^A15-1)/($D$5-1)) -> 9.92992 | H15: =$B$5*H14+100*(1-$B$5)-$B$4 -> 96.31072 | I15: =$C$5*I14+100*(1-$C$5)-$B$4 -> 94 | J15: =$D$5*J14+100*(1-$D$5)-$B$4 -> 90.07008 | K15: =100-H15 -> 3.68928 | L15: =100-I15 -> 6 | M15: =100-J15 -> 9.92992
A16: 7 | B16: =$B$5*B15+$B$4 -> 3.951424 | C16: =$C$5*C15+$B$4 -> 7 | D16: =$D$5*D15+$B$4 -> 12.915904 | E16: =IF($B$5=1,$B$4*A16,$B$4*($B$5^A16-1)/($B$5-1)) -> 3.951424 | F16: =IF($C$5=1,$B$4*A16,$B$4*($C$5^A16-1)/($C$5-1)) -> 7 | G16: =IF($D$5=1,$B$4*A16,$B$4*($D$5^A16-1)/($D$5-1)) -> 12.915904 | H16: =$B$5*H15+100*(1-$B$5)-$B$4 -> 96.048576 | I16: =$C$5*I15+100*(1-$C$5)-$B$4 -> 93 | J16: =$D$5*J15+100*(1-$D$5)-$B$4 -> 87.084096 | K16: =100-H16 -> 3.951424 | L16: =100-I16 -> 7 | M16: =100-J16 -> 12.915904
A17: 8 | B17: =$B$5*B16+$B$4 -> 4.1611392 | C17: =$C$5*C16+$B$4 -> 8 | D17: =$D$5*D16+$B$4 -> 16.499085 | E17: =IF($B$5=1,$B$4*A17,$B$4*($B$5^A17-1)/($B$5-1)) -> 4.1611392 | F17: =IF($C$5=1,$B$4*A17,$B$4*($C$5^A17-1)/($C$5-1)) -> 8 | G17: =IF($D$5=1,$B$4*A17,$B$4*($D$5^A17-1)/($D$5-1)) -> 16.499085 | H17: =$B$5*H16+100*(1-$B$5)-$B$4 -> 95.838861 | I17: =$C$5*I16+100*(1-$C$5)-$B$4 -> 92 | J17: =$D$5*J16+100*(1-$D$5)-$B$4 -> 83.500915 | K17: =100-H17 -> 4.1611392 | L17: =100-I17 -> 8 | M17: =100-J17 -> 16.499085
A18: 9 | B18: =$B$5*B17+$B$4 -> 4.3289114 | C18: =$C$5*C17+$B$4 -> 9 | D18: =$D$5*D17+$B$4 -> 20.798902 | E18: =IF($B$5=1,$B$4*A18,$B$4*($B$5^A18-1)/($B$5-1)) -> 4.3289114 | F18: =IF($C$5=1,$B$4*A18,$B$4*($C$5^A18-1)/($C$5-1)) -> 9 | G18: =IF($D$5=1,$B$4*A18,$B$4*($D$5^A18-1)/($D$5-1)) -> 20.798902 | H18: =$B$5*H17+100*(1-$B$5)-$B$4 -> 95.671089 | I18: =$C$5*I17+100*(1-$C$5)-$B$4 -> 91 | J18: =$D$5*J17+100*(1-$D$5)-$B$4 -> 79.201098 | K18: =100-H18 -> 4.3289114 | L18: =100-I18 -> 9 | M18: =100-J18 -> 20.798902
A19: 10 | B19: =$B$5*B18+$B$4 -> 4.4631291 | C19: =$C$5*C18+$B$4 -> 10 | D19: =$D$5*D18+$B$4 -> 25.958682 | E19: =IF($B$5=1,$B$4*A19,$B$4*($B$5^A19-1)/($B$5-1)) -> 4.4631291 | F19: =IF($C$5=1,$B$4*A19,$B$4*($C$5^A19-1)/($C$5-1)) -> 10 | G19: =IF($D$5=1,$B$4*A19,$B$4*($D$5^A19-1)/($D$5-1)) -> 25.958682 | H19: =$B$5*H18+100*(1-$B$5)-$B$4 -> 95.536871 | I19: =$C$5*I18+100*(1-$C$5)-$B$4 -> 90 | J19: =$D$5*J18+100*(1-$D$5)-$B$4 -> 74.041318 | K19: =100-H19 -> 4.4631291 | L19: =100-I19 -> 10 | M19: =100-J19 -> 25.958682
A20: 11 | B20: =$B$5*B19+$B$4 -> 4.5705033 | C20: =$C$5*C19+$B$4 -> 11 | D20: =$D$5*D19+$B$4 -> 32.150419 | E20: =IF($B$5=1,$B$4*A20,$B$4*($B$5^A20-1)/($B$5-1)) -> 4.5705033 | F20: =IF($C$5=1,$B$4*A20,$B$4*($C$5^A20-1)/($C$5-1)) -> 11 | G20: =IF($D$5=1,$B$4*A20,$B$4*($D$5^A20-1)/($D$5-1)) -> 32.150419 | H20: =$B$5*H19+100*(1-$B$5)-$B$4 -> 95.429497 | I20: =$C$5*I19+100*(1-$C$5)-$B$4 -> 89 | J20: =$D$5*J19+100*(1-$D$5)-$B$4 -> 67.849581 | K20: =100-H20 -> 4.5705033 | L20: =100-I20 -> 11 | M20: =100-J20 -> 32.150419
A21: 12 | B21: =$B$5*B20+$B$4 -> 4.6564026 | C21: =$C$5*C20+$B$4 -> 12 | D21: =$D$5*D20+$B$4 -> 39.580502 | E21: =IF($B$5=1,$B$4*A21,$B$4*($B$5^A21-1)/($B$5-1)) -> 4.6564026 | F21: =IF($C$5=1,$B$4*A21,$B$4*($C$5^A21-1)/($C$5-1)) -> 12 | G21: =IF($D$5=1,$B$4*A21,$B$4*($D$5^A21-1)/($D$5-1)) -> 39.580502 | H21: =$B$5*H20+100*(1-$B$5)-$B$4 -> 95.343597 | I21: =$C$5*I20+100*(1-$C$5)-$B$4 -> 88 | J21: =$D$5*J20+100*(1-$D$5)-$B$4 -> 60.419498 | K21: =100-H21 -> 4.6564026 | L21: =100-I21 -> 12 | M21: =100-J21 -> 39.580502
A23: After 12 quarters | B23: L = 0.8 | C23: L = 1.0 | D23: L = 1.2
A24: Drift (Equation 6.4) | B24: =E21 -> 4.6564026 | C24: =F21 -> 12 | D24: =G21 -> 39.580502
A25: Bound less the worst case (Remark 6.B.2: the bound is attained) | B25: =E21-K21 -> 2.1316282e-14 | C25: =F21-L21 -> 0 | D25: =G21-M21 -> -2.1316282e-13
A26: An error of 1 in the starting state (Theorem 6.5(i)): L^12 | B26: =B5^12 -> 0.068719477 | C26: =C5^12 -> 1 | D26: =D5^12 -> 8.9161004
A27: Bound under contraction, eps/(1 - L), at L = 0.8 | B27: =$B$4/(1-B5) -> 5
A28: Precision an amplifying program needs, relative to a consolidating one | B28: =D24/B24 -> 8.5002319
A30: Worked Example 6.1, Step 4: shortfall a round (points) | B30: 1 point | C30: 2 points
A31: Shortfall s (Playbook inputs) | B31: =Playbook!D5 -> 1 | C31: =Playbook!E5 -> 2
A32: Efficiency step's factor L = 1 - share of the gap closed | B32: =1-Close_A -> 0.5 | C32: =1-Close_A -> 0.5
A33: Steady efficiency: 85 - s/(1 - L) | B33: =Ceil_E-B31/(1-B32) -> 83 | C33: =Ceil_E-C31/(1-C32) -> 81
A34: Shift of the steady state, s/(1 - L) (Theorem 6.5(iii)) | B34: =B31/(1-B32) -> 2 | C34: =C31/(1-C32) -> 4
A35: Savings at the steady state | B35: =Value_pt*(B33-Eff_today) -> 120 | C35: =Value_pt*(C33-Eff_today) -> 100
A36: Savings less the round's cost at the steady state | B36: =B35-Cost_A -> 0 | C36: =C35-Cost_A -> -20
A37: 1 point: liquidity at the end of year 40 | B37: =Playbook!D11 -> 500
A38: 1 point: headroom over the $470 million precondition | B38: =B37-Pre_A -> 30
A39: 2 points: the round whose precondition fails | C39: =Playbook!E8 -> 5
A41: Designed less executed liquidity, 1 point (the account keeps every shortfall) | B41: Year 1 | C41: Year 2 | D41: Year 3 | E41: Year 4 | F41: Year 5 | G41: Year 6 | H41: Year 7 | I41: Year 8 | J41: Year 9 | K41: Year 10
A42: Gap ($ million) | B42: =Playbook!N34-Playbook!V34 -> 10 | C42: =Playbook!N35-Playbook!V35 -> 25 | D42: =Playbook!N36-Playbook!V36 -> 42.5 | E42: =Playbook!N37-Playbook!V37 -> 61.25 | F42: =Playbook!N38-Playbook!V38 -> 80.625 | G42: =Playbook!N39-Playbook!V39 -> 100.3125 | H42: =Playbook!N40-Playbook!V40 -> 120.15625 | I42: =Playbook!N41-Playbook!V41 -> 140.07812 | J42: =Playbook!N42-Playbook!V42 -> 160.03906 | K42: =Playbook!N43-Playbook!V43 -> 180.01953
A43: Efficiency forgives the shortfall (L = 0.5); liquidity keeps it: the gap grows by close to $20 million a year.

Sheet Reference_Values
A1: Checkpoint | B1: Engine value | C1: Meaning (where in the book)
A2: Liquidity a round needs | B2: 470 | C2: Worked Example 6.1, Step 1: $470 million
A3: Moves possible from today | B3: 4 | C3: Section 6.6: all four first moves
A4: One round from today: liquidity | B4: 500 | C4: Figure 6.1: $500 million
A5: One round from today: efficiency | B5: 78 | C5: Figure 6.1: 78
A6: Digital build first: its low point | B6: 481.91794 | C6: Section 6.6: $482 million, above the floor
A7: Sell, engineers leave: liquidity | B7: 732 | C7: Figure 6.3: $732 million
A8: Sell, engineers leave: technology | B8: 36.9 | C8: Figure 6.3: 36.9
A9: Sell, engineers leave: workforce | B9: 53 | C9: Figure 6.3: 53, a dead end
A10: Sell, engineers kept: liquidity | B10: 712 | C10: Figure 6.3: $712 million
A11: Two-move programs that pass every seam | B11: 9 | C11: Figure 6.3: nine sequences run
A12: Two-move programs reaching the target | B12: 1 | C12: Section 6.6: exactly one, automate then build
A13: A then D: liquidity | B13: 464.63273 | C13: Figure 6.3: $465 million
... A95: Digital build: efficiency change over five years | B95: 2.598331 | C95: Table 1.9: +2.6

Sheet Checks
A1: Checkpoint | B1: Workbook formula value | C1: Engine value | D1: |diff| | E1: Tolerance | F1: Status
A2: Liquidity a round needs | B2: =Pre_A -> 470 | C2: =Reference_Values!B2 -> 470 | D2: =ABS(B2-C2) -> 0 | E2: 1e-09 | F2: =IF(D2<=E2,"PASS","FAIL") -> PASS
A3: Moves possible from today | B3: =Operators!F11 -> 4 | C3: =Reference_Values!B3 -> 4 | D3: =ABS(B3-C3) -> 0 | E3: 0 | F3: =IF(D3<=E3,"PASS","FAIL") -> PASS
A4: One round from today: liquidity | B4: =Operators!B10 -> 500 | C4: =Reference_Values!B4 -> 500 | D4: =ABS(B4-C4) -> 0 | E4: 1e-09 | F4: =IF(D4<=E4,"PASS","FAIL") -> PASS
A5: One round from today: efficiency | B5: =Operators!E10 -> 78 | C5: =Reference_Values!B5 -> 78 | D5: =ABS(B5-C5) -> 0 | E5: 1e-09 | F5: =IF(D5<=E5,"PASS","FAIL") -> PASS
A6: Digital build first: its low point | B6: =Operators!B12 -> 481.91794 | C6: =Reference_Values!B6 -> 481.91794 | D6: =ABS(B6-C6) -> 0 | E6: 1e-06 | F6: =IF(D6<=E6,"PASS","FAIL") -> PASS
A7: Sell, engineers leave: liquidity | B7: =Operators!B7 -> 732 | C7: =Reference_Values!B7 -> 732 | D7: =ABS(B7-C7) -> 0 | E7: 1e-09 | F7: =IF(D7<=E7,"PASS","FAIL") -> PASS
A8: Sell, engineers leave: technology | B8: =Operators!C7 -> 36.9 | C8: =Reference_Values!B8 -> 36.9 | D8: =ABS(B8-C8) -> 0 | E8: 1e-09 | F8: =IF(D8<=E8,"PASS","FAIL") -> PASS
A9: Sell, engineers leave: workforce | B9: =Operators!D7 -> 53 | C9: =Reference_Values!B9 -> 53 | D9: =ABS(B9-C9) -> 0 | E9: 1e-09 | F9: =IF(D9<=E9,"PASS","FAIL") -> PASS
A10: Sell, engineers kept: liquidity | B10: =Operators!B8 -> 712 | C10: =Reference_Values!B10 -> 712 | D10: =ABS(B10-C10) -> 0 | E10: 1e-09 | F10: =IF(D10<=E10,"PASS","FAIL") -> PASS
A11: Two-move programs that pass every seam | B11: =Programs!B25 -> 9 | C11: =Reference_Values!B11 -> 9 | D11: =ABS(B11-C11) -> 0 | E11: 0 | F11: =IF(D11<=E11,"PASS","FAIL") -> PASS
A12: Two-move programs reaching the target | B12: =Programs!B26 -> 1 | C12: =Reference_Values!B12 -> 1 | D12: =ABS(B12-C12) -> 0 | E12: 0 | F12: =IF(D12<=E12,"PASS","FAIL") -> PASS
A13: A then D: liquidity | B13: =Programs!B27 -> 464.63273 | C13: =Reference_Values!B13 -> 464.63273 | D13: =ABS(B13-C13) -> 0 | E13: 1e-06 | F13: =IF(D13<=E13,"PASS","FAIL") -> PASS
A14: A then D: technology | B14: =Programs!B28 -> 75.634669 | C14: =Reference_Values!B14 -> 75.634669 | D14: =ABS(B14-C14) -> 0 | E14: 1e-06 | F14: =IF(D14<=E14,"PASS","FAIL") -> PASS
A15: A then D: headroom at the build's low point | B15: =Programs!B29 -> 11.917941 | C15: =Reference_Values!B15 -> 11.917941 | D15: =ABS(B15-C15) -> 0 | E15: 1e-06 | F15: =IF(D15<=E15,"PASS","FAIL") -> PASS
A16: A then S: liquidity | B16: =Programs!L19 -> 612 | C16: =Reference_Values!B16 -> 612 | D16: =ABS(B16-C16) -> 0 | E16: 1e-09 | F16: =IF(D16<=E16,"PASS","FAIL") -> PASS
A17: A then S: workforce | B17: =Programs!N19 -> 54 | C17: =Reference_Values!B17 -> 54 | D17: =ABS(B17-C17) -> 0 | E17: 1e-09 | F17: =IF(D17<=E17,"PASS","FAIL") -> PASS
A18: A then S*: liquidity | B18: =Programs!L20 -> 592 | C18: =Reference_Values!B18 -> 592 | D18: =ABS(B18-C18) -> 0 | E18: 1e-09 | F18: =IF(D18<=E18,"PASS","FAIL") -> PASS
A19: A then A: liquidity | B19: =Programs!L22 -> 380 | C19: =Reference_Values!B19 -> 380 | D19: =ABS(B19-C19) -> 0 | E19: 1e-09 | F19: =IF(D19<=E19,"PASS","FAIL") -> PASS
A20: A then D: efficiency | B20: =Programs!B30 -> 80.598331 | C20: =Reference_Values!B20 -> 80.598331 | D20: =ABS(B20-C20) -> 0 | E20: 1e-06 | F20: =IF(D20<=E20,"PASS","FAIL") -> PASS
A21: S*, A, A, then D: end liquidity (floor ignored) | B21: =Programs!B37 -> 436.63273 | C21: =Reference_Values!B21 -> 436.63273 | D21: =ABS(B21-C21) -> 0 | E21: 1e-06 | F21: =IF(D21<=E21,"PASS","FAIL") -> PASS
A22: S*, A, A, then D: the build's low point | B22: =Programs!B38 -> 333.91794 | C22: =Reference_Values!B22 -> 333.91794 | D22: =ABS(B22-C22) -> 0 | E22: 1e-06 | F22: =IF(D22<=E22,"PASS","FAIL") -> PASS
A23: Paid out: liquidity after round 2 | B23: =Playbook!F35 -> 380 | C23: =Reference_Values!B23 -> 380 | D23: =ABS(B23-C23) -> 0 | E23: 1e-09 | F23: =IF(D23<=E23,"PASS","FAIL") -> PASS
A24: Paid out: rounds that run | B24: =Playbook!B7 -> 2 | C24: =Reference_Values!B24 -> 2 | D24: =ABS(B24-C24) -> 0 | E24: 0 | F24: =IF(D24<=E24,"PASS","FAIL") -> PASS
A25: Paid out: extra liquidity each round needs | B25: =Playbook!I35-Playbook!I34 -> 120 | C25: =Reference_Values!B25 -> 120 | D25: =ABS(B25-C25) -> 0 | E25: 1e-09 | F25: =IF(D25<=E25,"PASS","FAIL") -> PASS
A26: Table 6.4: efficiency, year 1 | B26: =Playbook!C19 -> 78 | C26: =Reference_Values!B26 -> 78 | D26: =ABS(B26-C26) -> 0 | E26: 1e-09 | F26: =IF(D26<=E26,"PASS","FAIL") -> PASS
A27: Table 6.4: efficiency, year 2 | B27: =Playbook!D19 -> 81.5 | C27: =Reference_Values!B27 -> 81.5 | D27: =ABS(B27-C27) -> 0 | E27: 1e-09 | F27: =IF(D27<=E27,"PASS","FAIL") -> PASS
A28: Table 6.4: efficiency, year 3 | B28: =Playbook!E19 -> 83.25 | C28: =Reference_Values!B28 -> 83.25 | D28: =ABS(B28-C28) -> 0 | E28: 1e-09 | F28: =IF(D28<=E28,"PASS","FAIL") -> PASS
A29: Table 6.4: efficiency, year 4 | B29: =Playbook!F19 -> 84.125 | C29: =Reference_Values!B29 -> 84.125 | D29: =ABS(B29-C29) -> 0 | E29: 1e-09 | F29: =IF(D29<=E29,"PASS","FAIL") -> PASS
A30: Table 6.4: efficiency, year 5 | B30: =Playbook!G19 -> 84.5625 | C30: =Reference_Values!B30 -> 84.5625 | D30: =ABS(B30-C30) -> 0 | E30: 1e-09 | F30: =IF(D30<=E30,"PASS","FAIL") -> PASS
A31: Table 6.4: efficiency, year 6 | B31: =Playbook!H19 -> 84.78125 | C31: =Reference_Values!B31 -> 84.78125 | D31: =ABS(B31-C31) -> 0 | E31: 1e-09 | F31: =IF(D31<=E31,"PASS","FAIL") -> PASS
A32: Table 6.4: savings, year 1 | B32: =Playbook!C20 -> 70 | C32: =Reference_Values!B32 -> 70 | D32: =ABS(B32-C32) -> 0 | E32: 1e-09 | F32: =IF(D32<=E32,"PASS","FAIL") -> PASS
A33: Table 6.4: savings, year 2 | B33: =Playbook!D20 -> 105 | C33: =Reference_Values!B33 -> 105 | D33: =ABS(B33-C33) -> 0 | E33: 1e-09 | F33: =IF(D33<=E33,"PASS","FAIL") -> PASS
A34: Table 6.4: savings, year 3 | B34: =Playbook!E20 -> 122.5 | C34: =Reference_Values!B34 -> 122.5 | D34: =ABS(B34-C34) -> 0 | E34: 1e-09 | F34: =IF(D34<=E34,"PASS","FAIL") -> PASS
A35: Table 6.4: savings, year 4 | B35: =Playbook!F20 -> 131.25 | C35: =Reference_Values!B35 -> 131.25 | D35: =ABS(B35-C35) -> 0 | E35: 1e-09 | F35: =IF(D35<=E35,"PASS","FAIL") -> PASS
A36: Table 6.4: savings, year 5 | B36: =Playbook!G20 -> 135.625 | C36: =Reference_Values!B36 -> 135.625 | D36: =ABS(B36-C36) -> 0 | E36: 1e-09 | F36: =IF(D36<=E36,"PASS","FAIL") -> PASS
A37: Table 6.4: savings, year 6 | B37: =Playbook!H20 -> 137.8125 | C37: =Reference_Values!B37 -> 137.8125 | D37: =ABS(B37-C37) -> 0 | E37: 1e-09 | F37: =IF(D37<=E37,"PASS","FAIL") -> PASS
A38: Table 6.4: savings less cost, year 1 | B38: =Playbook!C21 -> -50 | C38: =Reference_Values!B38 -> -50 | D38: =ABS(B38-C38) -> 0 | E38: 1e-09 | F38: =IF(D38<=E38,"PASS","FAIL") -> PASS
A39: Table 6.4: savings less cost, year 2 | B39: =Playbook!D21 -> -15 | C39: =Reference_Values!B39 -> -15 | D39: =ABS(B39-C39) -> 0 | E39: 1e-09 | F39: =IF(D39<=E39,"PASS","FAIL") -> PASS
A40: Table 6.4: savings less cost, year 3 | B40: =Playbook!E21 -> 2.5 | C40: =Reference_Values!B40 -> 2.5 | D40: =ABS(B40-C40) -> 0 | E40: 1e-09 | F40: =IF(D40<=E40,"PASS","FAIL") -> PASS
A41: Table 6.4: savings less cost, year 4 | B41: =Playbook!F21 -> 11.25 | C41: =Reference_Values!B41 -> 11.25 | D41: =ABS(B41-C41) -> 0 | E41: 1e-09 | F41: =IF(D41<=E41,"PASS","FAIL") -> PASS
A42: Table 6.4: savings less cost, year 5 | B42: =Playbook!G21 -> 15.625 | C42: =Reference_Values!B42 -> 15.625 | D42: =ABS(B42-C42) -> 0 | E42: 1e-09 | F42: =IF(D42<=E42,"PASS","FAIL") -> PASS
A43: Table 6.4: savings less cost, year 6 | B43: =Playbook!H21 -> 17.8125 | C43: =Reference_Values!B43 -> 17.8125 | D43: =ABS(B43-C43) -> 0 | E43: 1e-09 | F43: =IF(D43<=E43,"PASS","FAIL") -> PASS
A44: Table 6.4: liquidity, year 1 | B44: =Playbook!C22 -> 570 | C44: =Reference_Values!B44 -> 570 | D44: =ABS(B44-C44) -> 0 | E44: 1e-09 | F44: =IF(D44<=E44,"PASS","FAIL") -> PASS
A45: Table 6.4: liquidity, year 2 | B45: =Playbook!D22 -> 555 | C45: =Reference_Values!B45 -> 555 | D45: =ABS(B45-C45) -> 0 | E45: 1e-09 | F45: =IF(D45<=E45,"PASS","FAIL") -> PASS
A46: Table 6.4: liquidity, year 3 | B46: =Playbook!E22 -> 557.5 | C46: =Reference_Values!B46 -> 557.5 | D46: =ABS(B46-C46) -> 0 | E46: 1e-09 | F46: =IF(D46<=E46,"PASS","FAIL") -> PASS
A47: Table 6.4: liquidity, year 4 | B47: =Playbook!F22 -> 568.75 | C47: =Reference_Values!B47 -> 568.75 | D47: =ABS(B47-C47) -> 0 | E47: 1e-09 | F47: =IF(D47<=E47,"PASS","FAIL") -> PASS
A48: Table 6.4: liquidity, year 5 | B48: =Playbook!G22 -> 584.375 | C48: =Reference_Values!B48 -> 584.375 | D48: =ABS(B48-C48) -> 0 | E48: 1e-09 | F48: =IF(D48<=E48,"PASS","FAIL") -> PASS
A49: Table 6.4: liquidity, year 6 | B49: =Playbook!H22 -> 602.1875 | C49: =Reference_Values!B49 -> 602.1875 | D49: =ABS(B49-C49) -> 0 | E49: 1e-09 | F49: =IF(D49<=E49,"PASS","FAIL") -> PASS
A50: Recycled: first year savings exceed the cost | B50: =Playbook!C9 -> 3 | C50: =Reference_Values!B50 -> 3 | D50: =ABS(B50-C50) -> 0 | E50: 0 | F50: =IF(D50<=E50,"PASS","FAIL") -> PASS
A51: Recycled: lowest liquidity | B51: =Playbook!C10 -> 555 | C51: =Reference_Values!B51 -> 555 | D51: =ABS(B51-C51) -> 0 | E51: 1e-09 | F51: =IF(D51<=E51,"PASS","FAIL") -> PASS
A52: Recycled: yearly rise of liquidity in year 40 | B52: =Playbook!C12 -> 20 | C52: =Reference_Values!B52 -> 20 | D52: =ABS(B52-C52) -> 0 | E52: 1e-09 | F52: =IF(D52<=E52,"PASS","FAIL") -> PASS
A53: Core threshold at today's efficiency | B53: =Playbook!C13 -> 535 | C53: =Reference_Values!B53 -> 535 | D53: =ABS(B53-C53) -> 0 | E53: 1e-09 | F53: =IF(D53<=E53,"PASS","FAIL") -> PASS
A54: Meridian's margin inside the core | B54: =Playbook!C16 -> 85 | C54: =Reference_Values!B54 -> 85 | D54: =ABS(B54-C54) -> 0 | E54: 1e-09 | F54: =IF(D54<=E54,"PASS","FAIL") -> PASS
A55: 1-point shortfall: steady efficiency | B55: =Stability!B33 -> 83 | C55: =Reference_Values!B55 -> 83 | D55: =ABS(B55-C55) -> 0 | E55: 1e-09 | F55: =IF(D55<=E55,"PASS","FAIL") -> PASS
A56: Steady-state shift bound | B56: =Stability!B34 -> 2 | C56: =Reference_Values!B56 -> 2 | D56: =ABS(B56-C56) -> 0 | E56: 1e-09 | F56: =IF(D56<=E56,"PASS","FAIL") -> PASS
A57: 1-point shortfall: savings top out | B57: =Stability!B35 -> 120 | C57: =Reference_Values!B57 -> 120 | D57: =ABS(B57-C57) -> 0 | E57: 1e-09 | F57: =IF(D57<=E57,"PASS","FAIL") -> PASS
A58: 1-point shortfall: liquidity in the long run | B58: =Stability!B37 -> 500 | C58: =Reference_Values!B58 -> 500 | D58: =ABS(B58-C58) -> 1.0913936e-10 | E58: 1e-06 | F58: =IF(D58<=E58,"PASS","FAIL") -> PASS
A59: 1-point shortfall: headroom | B59: =Stability!B38 -> 30 | C59: =Reference_Values!B59 -> 30 | D59: =ABS(B59-C59) -> 1.0913936e-10 | E59: 1e-06 | F59: =IF(D59<=E59,"PASS","FAIL") -> PASS
A60: 2-point shortfall: savings top out | B60: =Stability!C35 -> 100 | C60: =Reference_Values!B60 -> 100 | D60: =ABS(B60-C60) -> 0 | E60: 1e-09 | F60: =IF(D60<=E60,"PASS","FAIL") -> PASS
A61: 2-point shortfall: round that fails | B61: =Stability!C39 -> 5 | C61: =Reference_Values!B61 -> 5 | D61: =ABS(B61-C61) -> 0 | E61: 0 | F61: =IF(D61<=E61,"PASS","FAIL") -> PASS
A62: Drift bound at L = 0.8 | B62: =Stability!B27 -> 5 | C62: =Reference_Values!B62 -> 5 | D62: =ABS(B62-C62) -> 0 | E62: 1e-09 | F62: =IF(D62<=E62,"PASS","FAIL") -> PASS
A63: Drift after 12 quarters, L = 0.8 | B63: =Stability!B24 -> 4.6564026 | C63: =Reference_Values!B63 -> 4.6564026 | D63: =ABS(B63-C63) -> 0 | E63: 1e-09 | F63: =IF(D63<=E63,"PASS","FAIL") -> PASS
A64: Drift after 12 quarters, L = 1.0 | B64: =Stability!C24 -> 12 | C64: =Reference_Values!B64 -> 12 | D64: =ABS(B64-C64) -> 0 | E64: 1e-09 | F64: =IF(D64<=E64,"PASS","FAIL") -> PASS
A65: Drift after 12 quarters, L = 1.2 | B65: =Stability!D24 -> 39.580502 | C65: =Reference_Values!B65 -> 39.580502 | D65: =ABS(B65-C65) -> 0 | E65: 1e-09 | F65: =IF(D65<=E65,"PASS","FAIL") -> PASS
A66: Bound less the worst case, L = 1.2 | B66: =Stability!D25 -> -2.1316282e-13 | C66: =Reference_Values!B66 -> -2.1316282e-13 | D66: =ABS(B66-C66) -> 0 | E66: 1e-09 | F66: =IF(D66<=E66,"PASS","FAIL") -> PASS
A67: Bank: liquidity after one year | B67: =Policy!I4 -> 600 | C67: =Reference_Values!B67 -> 600 | D67: =ABS(B67-C67) -> 0 | E67: 1e-09 | F67: =IF(D67<=E67,"PASS","FAIL") -> PASS
A68: Bank: liquidity after two years | B68: =Policy!I5 -> 450 | C68: =Reference_Values!B68 -> 450 | D68: =ABS(B68-C68) -> 0 | E68: 1e-09 | F68: =IF(D68<=E68,"PASS","FAIL") -> PASS
A69: Bank: liquidity after three years | B69: =Policy!I6 -> 375 | C69: =Reference_Values!B69 -> 375 | D69: =ABS(B69-C69) -> 0 | E69: 1e-09 | F69: =IF(D69<=E69,"PASS","FAIL") -> PASS
A70: Bank: liquidity after four years | B70: =Policy!I7 -> 337.5 | C70: =Reference_Values!B70 -> 337.5 | D70: =ABS(B70-C70) -> 0 | E70: 1e-09 | F70: =IF(D70<=E70,"PASS","FAIL") -> PASS
A71: Bank: technology after one year | B71: =Policy!I8 -> 56 | C71: =Reference_Values!B71 -> 56 | D71: =ABS(B71-C71) -> 0 | E71: 1e-09 | F71: =IF(D71<=E71,"PASS","FAIL") -> PASS
A72: Bank: technology after two years | B72: =Policy!I9 -> 63.5 | C72: =Reference_Values!B72 -> 63.5 | D72: =ABS(B72-C72) -> 0 | E72: 1e-09 | F72: =IF(D72<=E72,"PASS","FAIL") -> PASS
A73: Bank: total invested over 40 years | B73: =Policy!I10 -> 600 | C73: =Reference_Values!B73 -> 600 | D73: =ABS(B73-C73) -> 0 | E73: 1e-09 | F73: =IF(D73<=E73,"PASS","FAIL") -> PASS
A74: Bank: technology after 40 years | B74: =Policy!I11 -> 71 | C74: =Reference_Values!B74 -> 71 | D74: =ABS(B74-C74) -> 0 | E74: 1e-09 | F74: =IF(D74<=E74,"PASS","FAIL") -> PASS
A75: States in R_1 | B75: =Reachability!C8 -> 5 | C75: =Reference_Values!B75 -> 5 | D75: =ABS(B75-C75) -> 0 | E75: 0 | F75: =IF(D75<=E75,"PASS","FAIL") -> PASS
A76: States in R_2 | B76: =Reachability!D8 -> 13 | C76: =Reference_Values!B76 -> 13 | D76: =ABS(B76-C76) -> 0 | E76: 0 | F76: =IF(D76<=E76,"PASS","FAIL") -> PASS
A77: States in R_3 | B77: =Reachability!E8 -> 21 | C77: =Reference_Values!B77 -> 21 | D77: =ABS(B77-C77) -> 0 | E77: 0 | F77: =IF(D77<=E77,"PASS","FAIL") -> PASS
A78: States in R_4 | B78: =Reachability!F8 -> 28 | C78: =Reference_Values!B78 -> 28 | D78: =ABS(B78-C78) -> 0 | E78: 0 | F78: =IF(D78<=E78,"PASS","FAIL") -> PASS
A79: Programs of length 1 that run | B79: =Reachability!C9 -> 4 | C79: =Reference_Values!B79 -> 4 | D79: =ABS(B79-C79) -> 0 | E79: 0 | F79: =IF(D79<=E79,"PASS","FAIL") -> PASS
A80: Programs of length 2 that run | B80: =Reachability!D9 -> 9 | C80: =Reference_Values!B80 -> 9 | D80: =ABS(B80-C80) -> 0 | E80: 0 | F80: =IF(D80<=E80,"PASS","FAIL") -> PASS
A81: Programs of length 3 that run | B81: =Reachability!E9 -> 12 | C81: =Reference_Values!B81 -> 12 | D81: =ABS(B81-C81) -> 0 | E81: 0 | F81: =IF(D81<=E81,"PASS","FAIL") -> PASS
A82: Programs of length 4 that run | B82: =Reachability!F9 -> 11 | C82: =Reference_Values!B82 -> 11 | D82: =ABS(B82-C82) -> 0 | E82: 0 | F82: =IF(D82<=E82,"PASS","FAIL") -> PASS
A83: Programs of five moves that run | B83: =Reachability!B12 -> 0 | C83: =Reference_Values!B83 -> 0 | D83: =ABS(B83-C83) -> 0 | E83: 0 | F83: =IF(D83<=E83,"PASS","FAIL") -> PASS
A84: First depth meeting the target | B84: =Reachability!B13 -> 2 | C84: =Reference_Values!B84 -> 2 | D84: =ABS(B84-C84) -> 0 | E84: 0 | F84: =IF(D84<=E84,"PASS","FAIL") -> PASS
A85: Largest cushion with which the target stays reachable | B85: =Reachability!B17 -> 206.63273 | C85: =Reference_Values!B85 -> 206.63273 | D85: =ABS(B85-C85) -> 0 | E85: 1e-06 | F85: =IF(D85<=E85,"PASS","FAIL") -> PASS
A86: Highest technology the repertoire can reach | B86: =Reachability!B18 -> 75.634669 | C86: =Reference_Values!B86 -> 75.634669 | D86: =ABS(B86-C86) -> 0 | E86: 1e-06 | F86: =IF(D86<=E86,"PASS","FAIL") -> PASS
A87: Rounds to come within 1 point of the ceiling | B87: =Reachability!C23 -> 4 | C87: =Reference_Values!B87 -> 4 | D87: =ABS(B87-C87) -> 0 | E87: 0 | F87: =IF(D87<=E87,"PASS","FAIL") -> PASS
A88: D then A: efficiency | B88: =Programs!B31 -> 79.299165 | C88: =Reference_Values!B88 -> 79.299165 | D88: =ABS(B88-C88) -> 0 | E88: 1e-06 | F88: =IF(D88<=E88,"PASS","FAIL") -> PASS
A89: S*, A, A: liquidity before the build | B89: =Programs!B36 -> 472 | C89: =Reference_Values!B89 -> 472 | D89: =ABS(B89-C89) -> 0 | E89: 1e-09 | F89: =IF(D89<=E89,"PASS","FAIL") -> PASS
A90: Digital build: low point below its start | B90: =D_dip -> 138.08206 | C90: =Reference_Values!B90 -> 138.08206 | D90: =ABS(B90-C90) -> 0 | E90: 1e-06 | F90: =IF(D90<=E90,"PASS","FAIL") -> PASS
A91: Digital build: month of the low point | B91: =Declarations!B49 -> 20.574451 | C91: =Reference_Values!B91 -> 20.574451 | D91: =ABS(B91-C91) -> 2.9385686e-07 | E91: 1e-06 | F91: =IF(D91<=E91,"PASS","FAIL") -> PASS
A92: Liquidity the build needs | B92: =Pre_D -> 488.08206 | C92: =Reference_Values!B92 -> 488.08206 | D92: =ABS(B92-C92) -> 0 | E92: 1e-06 | F92: =IF(D92<=E92,"PASS","FAIL") -> PASS
A93: Digital build: liquidity change over five years | B93: =D_dL -> -35.367271 | C93: =Reference_Values!B93 -> -35.367271 | D93: =ABS(B93-C93) -> 0 | E93: 1e-06 | F93: =IF(D93<=E93,"PASS","FAIL") -> PASS
A94: Digital build: technology change over five years | B94: =D_dT -> 34.634669 | C94: =Reference_Values!B94 -> 34.634669 | D94: =ABS(B94-C94) -> 0 | E94: 1e-06 | F94: =IF(D94<=E94,"PASS","FAIL") -> PASS
A95: Digital build: efficiency change over five years | B95: =D_dE -> 2.598331 | C95: =Reference_Values!B95 -> 2.598331 | D95: =ABS(B95-C95) -> 0 | E95: 1e-06 | F95: =IF(D95<=E95,"PASS","FAIL") -> PASS
A97: All checkpoints | F97: =IF(COUNTIF(F2:F95,"PASS")=94,"ALL PASS","CHECK") -> ALL PASS
