Workbook

Sheet README
B1: DCT Laboratory — Vol I, Ch 9: Enterprise State Architecture
B2: Seed 26109 · Companion to DCT_V1_Ch09_Lab.ipynb and AXIOM Lab 1.9 (module AXIOM-09). Money in $ million.
B4: Worked Example 9.1, How Fast Can a Demand Shock Reach the Covenant?, with the book's declarations, and the five steps of AXIOM Lab 1.9, Wiring Meridian.
B5: Declarations: the seven components, the fourteen typed arrows and the constraints with their scopes (Tables 9.1-9.3; Figure 9.1). Change an arrow or a scope and every sheet recalculates.
B6: Wiring: the adjacency matrix, the interface check, the counts, density and cycle measure (lab step 1).
B7: Core: routes of each length, reachability, the strongly connected components, the causal layers, the loops inside the core, and Online Appendix 9.B.1's offsetting channels (lab step 2).
B8: Shock: Table 9.7's distances and shortest routes, the wavefront, the path counter, and a positive linear company whose arrows can be switched off (lab step 3).
B9: Paths: every simple path from the market to treasury and every cut of one, two or three arrows.
B10: SummaryMap: the two-box map and the causal map, with the connections each invents (lab step 4).
B11: Constraints: the constraint graph, its cycle measure and its joint review; the planning rules and the carve-out timetable by the cycle test; the strategic-risk peak on the digital plan (lab step 5).
B12: Metrics: the complexity panel (Table 9.5) and the validation checklist (Table 9.4). WhatIf: treasury funds Materials.
B13: Engine values (green) are the sensitivities the notebook drew with the lab's seed and the paths it enumerated. Reference_Values and Checks: the notebook engine's numbers and a PASS/FAIL comparison.
... B19: Cross-sheet link: green.

Sheet Declarations
A1: Declarations (Worked Example 9.1, Step 1; Tables 9.1-9.3). Money in $ million; the model runs in quarters.
A3: Component | B3: Name | C3: Org chart (two-box map) | D3: Interface: readings it exposes | E3: Source
A4: MKT | B4: Market | C4: market | D4: demand | E4: named by the arrow's type
A5: GOV | B5: Governance | C5: center | D5: policy | E5: named by the arrow's type
A6: MAT | B6: Materials | C6: divisions | D6: cash and EBITDA | E6: Step 1: the divisions report cash and EBITDA along the cash arrows
A7: IND | B7: Industrial Systems | C7: divisions | D7: cash and EBITDA; capability | E7: named by the arrow's type
A8: DIG | B8: Digital | C8: divisions | D8: cash and EBITDA; capability | E8: named by the arrow's type
A9: ENG | B9: Shared engineering | C9: center | D9: workforce-capability index | E9: Table 9.1: engineering exposes the workforce-capability index
A10: TRS | B10: Treasury | C10: center | D10: funding capacity | E10: Table 9.1: treasury exposes funding capacity
A12: Arrow | B12: From | C12: To | D12: Type | E12: Class (Table 9.2) | F12: Reading carried | G12: Source exposes it (1 = yes)
A13: 1 | B13: MKT | C13: IND | D13: demand | E13: =VLOOKUP(D13,$A$30:$C$34,2,FALSE()) -> dynamic | F13: =IF(D13="capability",IF(B13="ENG","workforce-capability index","capability"),VLOOKUP(D13,$A$30:$C$34,3,FALSE())) -> demand | G13: =IF(ISNUMBER(SEARCH("; "&F13&";","; "&VLOOKUP(B13,$A$4:$D$10,4,FALSE())&";")),1,0) -> 1
A14: 2 | B14: MKT | C14: DIG | D14: demand | E14: =VLOOKUP(D14,$A$30:$C$34,2,FALSE()) -> dynamic | F14: =IF(D14="capability",IF(B14="ENG","workforce-capability index","capability"),VLOOKUP(D14,$A$30:$C$34,3,FALSE())) -> demand | G14: =IF(ISNUMBER(SEARCH("; "&F14&";","; "&VLOOKUP(B14,$A$4:$D$10,4,FALSE())&";")),1,0) -> 1
A15: 3 | B15: MKT | C15: MAT | D15: demand | E15: =VLOOKUP(D15,$A$30:$C$34,2,FALSE()) -> dynamic | F15: =IF(D15="capability",IF(B15="ENG","workforce-capability index","capability"),VLOOKUP(D15,$A$30:$C$34,3,FALSE())) -> demand | G15: =IF(ISNUMBER(SEARCH("; "&F15&";","; "&VLOOKUP(B15,$A$4:$D$10,4,FALSE())&";")),1,0) -> 1
A16: 4 | B16: IND | C16: TRS | D16: cash | E16: =VLOOKUP(D16,$A$30:$C$34,2,FALSE()) -> resource flow | F16: =IF(D16="capability",IF(B16="ENG","workforce-capability index","capability"),VLOOKUP(D16,$A$30:$C$34,3,FALSE())) -> cash and EBITDA | G16: =IF(ISNUMBER(SEARCH("; "&F16&";","; "&VLOOKUP(B16,$A$4:$D$10,4,FALSE())&";")),1,0) -> 1
A17: 5 | B17: DIG | C17: TRS | D17: cash | E17: =VLOOKUP(D17,$A$30:$C$34,2,FALSE()) -> resource flow | F17: =IF(D17="capability",IF(B17="ENG","workforce-capability index","capability"),VLOOKUP(D17,$A$30:$C$34,3,FALSE())) -> cash and EBITDA | G17: =IF(ISNUMBER(SEARCH("; "&F17&";","; "&VLOOKUP(B17,$A$4:$D$10,4,FALSE())&";")),1,0) -> 1
A18: 6 | B18: MAT | C18: TRS | D18: cash | E18: =VLOOKUP(D18,$A$30:$C$34,2,FALSE()) -> resource flow | F18: =IF(D18="capability",IF(B18="ENG","workforce-capability index","capability"),VLOOKUP(D18,$A$30:$C$34,3,FALSE())) -> cash and EBITDA | G18: =IF(ISNUMBER(SEARCH("; "&F18&";","; "&VLOOKUP(B18,$A$4:$D$10,4,FALSE())&";")),1,0) -> 1
A19: 7 | B19: TRS | C19: IND | D19: funding | E19: =VLOOKUP(D19,$A$30:$C$34,2,FALSE()) -> resource flow | F19: =IF(D19="capability",IF(B19="ENG","workforce-capability index","capability"),VLOOKUP(D19,$A$30:$C$34,3,FALSE())) -> funding capacity | G19: =IF(ISNUMBER(SEARCH("; "&F19&";","; "&VLOOKUP(B19,$A$4:$D$10,4,FALSE())&";")),1,0) -> 1
A20: 8 | B20: TRS | C20: DIG | D20: funding | E20: =VLOOKUP(D20,$A$30:$C$34,2,FALSE()) -> resource flow | F20: =IF(D20="capability",IF(B20="ENG","workforce-capability index","capability"),VLOOKUP(D20,$A$30:$C$34,3,FALSE())) -> funding capacity | G20: =IF(ISNUMBER(SEARCH("; "&F20&";","; "&VLOOKUP(B20,$A$4:$D$10,4,FALSE())&";")),1,0) -> 1
A21: 9 | B21: ENG | C21: IND | D21: capability | E21: =VLOOKUP(D21,$A$30:$C$34,2,FALSE()) -> resource flow | F21: =IF(D21="capability",IF(B21="ENG","workforce-capability index","capability"),VLOOKUP(D21,$A$30:$C$34,3,FALSE())) -> workforce-capability index | G21: =IF(ISNUMBER(SEARCH("; "&F21&";","; "&VLOOKUP(B21,$A$4:$D$10,4,FALSE())&";")),1,0) -> 1
A22: 10 | B22: IND | C22: ENG | D22: capability | E22: =VLOOKUP(D22,$A$30:$C$34,2,FALSE()) -> resource flow | F22: =IF(D22="capability",IF(B22="ENG","workforce-capability index","capability"),VLOOKUP(D22,$A$30:$C$34,3,FALSE())) -> capability | G22: =IF(ISNUMBER(SEARCH("; "&F22&";","; "&VLOOKUP(B22,$A$4:$D$10,4,FALSE())&";")),1,0) -> 1
A23: 11 | B23: ENG | C23: DIG | D23: capability | E23: =VLOOKUP(D23,$A$30:$C$34,2,FALSE()) -> resource flow | F23: =IF(D23="capability",IF(B23="ENG","workforce-capability index","capability"),VLOOKUP(D23,$A$30:$C$34,3,FALSE())) -> workforce-capability index | G23: =IF(ISNUMBER(SEARCH("; "&F23&";","; "&VLOOKUP(B23,$A$4:$D$10,4,FALSE())&";")),1,0) -> 1
A24: 12 | B24: DIG | C24: ENG | D24: capability | E24: =VLOOKUP(D24,$A$30:$C$34,2,FALSE()) -> resource flow | F24: =IF(D24="capability",IF(B24="ENG","workforce-capability index","capability"),VLOOKUP(D24,$A$30:$C$34,3,FALSE())) -> capability | G24: =IF(ISNUMBER(SEARCH("; "&F24&";","; "&VLOOKUP(B24,$A$4:$D$10,4,FALSE())&";")),1,0) -> 1
... A26: 14 | B26: GOV | C26: DIG | D26: policy | E26: =VLOOKUP(D26,$A$30:$C$34,2,FALSE()) -> informational | F26: =IF(D26="capability",IF(B26="ENG","workforce-capability index","capability"),VLOOKUP(D26,$A$30:$C$34,3,FALSE())) -> policy | G26: =IF(ISNUMBER(SEARCH("; "&F26&";","; "&VLOOKUP(B26,$A$4:$D$10,4,FALSE())&";")),1,0) -> 1
A29: Arrow type | B29: Class (Table 9.2) | C29: Reading carried
A30: demand | B30: dynamic | C30: demand
A31: cash | B31: resource flow | C31: cash and EBITDA
A32: funding | B32: resource flow | C32: funding capacity
A33: capability | B33: resource flow | C33: capability | D33: Capability arrows from engineering carry the workforce-capability index (Table 9.1).
A34: policy | B34: informational | C34: policy
A35: Constraint (Table 9.3) | B35: MKT | C35: GOV | D35: MAT | E35: IND | F35: DIG | G35: ENG | H35: TRS | I35: Components in scope | J35: Class (Table 9.3) | K35: Limit | L35: Who can change it
A36: Loan covenant: net leverage at most 4.5x EBITDA | B36: 0 | C36: 0 | D36: 0 | E36: 0 | F36: 0 | G36: 0 | H36: 1 | I36: =SUM(B36:H36) -> 1 | J36: =IF(I36=1,"local",IF(I36=2,"pairwise coupling","group coupling")) -> local | K36: 4.5 | L36: only the lenders (Table 5.4)
A37: Liquidity floor: at least $350 million | B37: 0 | C37: 0 | D37: 0 | E37: 0 | F37: 0 | G37: 0 | H37: 1 | I37: =SUM(B37:H37) -> 1 | J37: =IF(I37=1,"local",IF(I37=2,"pairwise coupling","group coupling")) -> local | K37: 350 | L37: the board: a revisable policy
A38: Plant capacity | B38: 0 | C38: 0 | D38: 0 | E38: 1 | F38: 0 | G38: 0 | H38: 0 | I38: =SUM(B38:H38) -> 1 | J38: =IF(I38=1,"local",IF(I38=2,"pairwise coupling","group coupling")) -> local | L38: a physical limit (Table 5.4)
A39: Strategic-risk ceiling | B39: 0 | C39: 0 | D39: 1 | E39: 1 | F39: 1 | G39: 0 | H39: 0 | I39: =SUM(B39:H39) -> 3 | J39: =IF(I39=1,"local",IF(I39=2,"pairwise coupling","group coupling")) -> group coupling | K39: 75 | L39: the board: a revisable policy
A40: Workforce capability for the digital build | B40: 0 | C40: 0 | D40: 0 | E40: 0 | F40: 1 | G40: 1 | H40: 0 | I40: =SUM(B40:H40) -> 2 | J40: =IF(I40=1,"local",IF(I40=2,"pairwise coupling","group coupling")) -> pairwise coupling | K40: 55 | L40: the digital build (Worked Example 3.1)
A41: Index bounds are local too (Table 9.3); local constraints add no link to the constraint graph.
A43: Declared value | B43: Value | C43: Source
A44: Strategic-risk ceiling | B44: 75 | C44: Table 5.4: a board policy
A45: Risk committee's measurement error (+/-) | B45: 6 | C45: Table 5.2
A46: Strategic risk today | B46: 64 | C46: Table 3.1
A47: Digital plan: target for strategic risk | B47: 51 | C47: Table 1.B.1 (Equation 1.B.1)
A48: Digital plan: speed a year | B48: 0.4 | C48: Table 1.B.1
A49: Digital plan: trough depth (temporary strain) | B49: 14 | C49: Table 1.B.1
A50: Digital plan: trough time, years | B50: 1.2 | C50: Table 1.B.1
A52: Strategic risk on the digital plan: x(t) = target + (today - target) e^(-speed t) + depth (t / trough time) e^(1 - t / trough time), t in years (Chapter 1, Equation 1.B.1).

Sheet Wiring
A1: Declare the architecture: the dependency graph and its counts (Worked Example 9.1, Step 1; Definitions 9.1-9.3; AXIOM Lab 1.9, step 1)
A2: Rows send, columns receive: A = 1 where an arrow runs from the row's component to the column's. Everything below recalculates from the arrow list on Declarations.
A4: Adjacency A (Figure 9.1)
A5: from \ to | B5: MKT | C5: GOV | D5: MAT | E5: IND | F5: DIG | G5: ENG | H5: TRS | I5: out-degree | K5: Quantity | L5: Value | M5: Reading
A6: MKT | B6: =IF(COUNTIFS(Arr_from,$A6,Arr_to,B$5)>0,1,0) -> 0 | C6: =IF(COUNTIFS(Arr_from,$A6,Arr_to,C$5)>0,1,0) -> 0 | D6: =IF(COUNTIFS(Arr_from,$A6,Arr_to,D$5)>0,1,0) -> 1 | E6: =IF(COUNTIFS(Arr_from,$A6,Arr_to,E$5)>0,1,0) -> 1 | F6: =IF(COUNTIFS(Arr_from,$A6,Arr_to,F$5)>0,1,0) -> 1 | G6: =IF(COUNTIFS(Arr_from,$A6,Arr_to,G$5)>0,1,0) -> 0 | H6: =IF(COUNTIFS(Arr_from,$A6,Arr_to,H$5)>0,1,0) -> 0 | I6: =SUM($B$6:$H$6) -> 3 | K6: Components |V| | L6: =COUNTA(Comp) -> 7 | M6: Table 9.1: seven
A7: GOV | B7: =IF(COUNTIFS(Arr_from,$A7,Arr_to,B$5)>0,1,0) -> 0 | C7: =IF(COUNTIFS(Arr_from,$A7,Arr_to,C$5)>0,1,0) -> 0 | D7: =IF(COUNTIFS(Arr_from,$A7,Arr_to,D$5)>0,1,0) -> 0 | E7: =IF(COUNTIFS(Arr_from,$A7,Arr_to,E$5)>0,1,0) -> 0 | F7: =IF(COUNTIFS(Arr_from,$A7,Arr_to,F$5)>0,1,0) -> 1 | G7: =IF(COUNTIFS(Arr_from,$A7,Arr_to,G$5)>0,1,0) -> 0 | H7: =IF(COUNTIFS(Arr_from,$A7,Arr_to,H$5)>0,1,0) -> 1 | I7: =SUM($B$7:$H$7) -> 2 | K7: Arrows |E| | L7: =SUM($B$6:$H$12) -> 14 | M7: Figure 9.1: fourteen
A8: MAT | B8: =IF(COUNTIFS(Arr_from,$A8,Arr_to,B$5)>0,1,0) -> 0 | C8: =IF(COUNTIFS(Arr_from,$A8,Arr_to,C$5)>0,1,0) -> 0 | D8: =IF(COUNTIFS(Arr_from,$A8,Arr_to,D$5)>0,1,0) -> 0 | E8: =IF(COUNTIFS(Arr_from,$A8,Arr_to,E$5)>0,1,0) -> 0 | F8: =IF(COUNTIFS(Arr_from,$A8,Arr_to,F$5)>0,1,0) -> 0 | G8: =IF(COUNTIFS(Arr_from,$A8,Arr_to,G$5)>0,1,0) -> 0 | H8: =IF(COUNTIFS(Arr_from,$A8,Arr_to,H$5)>0,1,0) -> 1 | I8: =SUM($B$8:$H$8) -> 1 | K8: Possible arrows |V|(|V| - 1) | L8: =L6*(L6-1) -> 42
A9: IND | B9: =IF(COUNTIFS(Arr_from,$A9,Arr_to,B$5)>0,1,0) -> 0 | C9: =IF(COUNTIFS(Arr_from,$A9,Arr_to,C$5)>0,1,0) -> 0 | D9: =IF(COUNTIFS(Arr_from,$A9,Arr_to,D$5)>0,1,0) -> 0 | E9: =IF(COUNTIFS(Arr_from,$A9,Arr_to,E$5)>0,1,0) -> 0 | F9: =IF(COUNTIFS(Arr_from,$A9,Arr_to,F$5)>0,1,0) -> 0 | G9: =IF(COUNTIFS(Arr_from,$A9,Arr_to,G$5)>0,1,0) -> 1 | H9: =IF(COUNTIFS(Arr_from,$A9,Arr_to,H$5)>0,1,0) -> 1 | I9: =SUM($B$9:$H$9) -> 2 | K9: Density |E| / (|V|(|V| - 1)) | L9: =L7/L8 -> 0.33333333 | M9: Section 9.8: 14/42 = 0.33
A10: DIG | B10: =IF(COUNTIFS(Arr_from,$A10,Arr_to,B$5)>0,1,0) -> 0 | C10: =IF(COUNTIFS(Arr_from,$A10,Arr_to,C$5)>0,1,0) -> 0 | D10: =IF(COUNTIFS(Arr_from,$A10,Arr_to,D$5)>0,1,0) -> 0 | E10: =IF(COUNTIFS(Arr_from,$A10,Arr_to,E$5)>0,1,0) -> 0 | F10: =IF(COUNTIFS(Arr_from,$A10,Arr_to,F$5)>0,1,0) -> 0 | G10: =IF(COUNTIFS(Arr_from,$A10,Arr_to,G$5)>0,1,0) -> 1 | H10: =IF(COUNTIFS(Arr_from,$A10,Arr_to,H$5)>0,1,0) -> 1 | I10: =SUM($B$10:$H$10) -> 2 | K10: Two-way relationships | L10: =SUMPRODUCT($B$6:$H$12,$B$18:$H$24)/2 -> 4 | M10: cash and funding with treasury; capability
A11: ENG | B11: =IF(COUNTIFS(Arr_from,$A11,Arr_to,B$5)>0,1,0) -> 0 | C11: =IF(COUNTIFS(Arr_from,$A11,Arr_to,C$5)>0,1,0) -> 0 | D11: =IF(COUNTIFS(Arr_from,$A11,Arr_to,D$5)>0,1,0) -> 0 | E11: =IF(COUNTIFS(Arr_from,$A11,Arr_to,E$5)>0,1,0) -> 1 | F11: =IF(COUNTIFS(Arr_from,$A11,Arr_to,F$5)>0,1,0) -> 1 | G11: =IF(COUNTIFS(Arr_from,$A11,Arr_to,G$5)>0,1,0) -> 0 | H11: =IF(COUNTIFS(Arr_from,$A11,Arr_to,H$5)>0,1,0) -> 0 | I11: =SUM($B$11:$H$11) -> 2 | K11: Pairs joined, directions ignored | L11: =L7-L10 -> 10
A12: TRS | B12: =IF(COUNTIFS(Arr_from,$A12,Arr_to,B$5)>0,1,0) -> 0 | C12: =IF(COUNTIFS(Arr_from,$A12,Arr_to,C$5)>0,1,0) -> 0 | D12: =IF(COUNTIFS(Arr_from,$A12,Arr_to,D$5)>0,1,0) -> 0 | E12: =IF(COUNTIFS(Arr_from,$A12,Arr_to,E$5)>0,1,0) -> 1 | F12: =IF(COUNTIFS(Arr_from,$A12,Arr_to,F$5)>0,1,0) -> 1 | G12: =IF(COUNTIFS(Arr_from,$A12,Arr_to,G$5)>0,1,0) -> 0 | H12: =IF(COUNTIFS(Arr_from,$A12,Arr_to,H$5)>0,1,0) -> 0 | I12: =SUM($B$12:$H$12) -> 2 | K12: Separate pieces p, directions ignored | L12: =SUMPRODUCT(1/I73:I79) -> 1 | M12: one piece
A13: in-degree | B13: =SUM($B$6:$B$12) -> 0 | C13: =SUM($C$6:$C$12) -> 0 | D13: =SUM($D$6:$D$12) -> 1 | E13: =SUM($E$6:$E$12) -> 3 | F13: =SUM($F$6:$F$12) -> 4 | G13: =SUM($G$6:$G$12) -> 2 | H13: =SUM($H$6:$H$12) -> 4 | K13: Cycle measure beta = |E| - |V| + p | L13: =L7-L6+L12 -> 8 | M13: Section 9.8: 14 - 7 + 1 = 8
K14: loops from the two-way relationships | L14: =L10 -> 4 | M14: Online Appendix 9.B.7: four
K15: loops with directions ignored | L15: =L11-L6+L12 -> 4 | M15: and the remaining four
A16: A transposed (the same arrows, columns sending) | K16: Missing arrows: claims of independence | L16: =L8-L7 -> 28
A17: to \ from | B17: MKT | C17: GOV | D17: MAT | E17: IND | F17: DIG | G17: ENG | H17: TRS | K17: Arrows into the market | L17: =B13 -> 0 | M17: nothing Meridian does moves its demand
A18: MKT | B18: =$B$6 -> 0 | C18: =$B$7 -> 0 | D18: =$B$8 -> 0 | E18: =$B$9 -> 0 | F18: =$B$10 -> 0 | G18: =$B$11 -> 0 | H18: =$B$12 -> 0 | K18: Arrows into governance | L18: =C13 -> 0
A19: GOV | B19: =$C$6 -> 0 | C19: =$C$7 -> 0 | D19: =$C$8 -> 0 | E19: =$C$9 -> 0 | F19: =$C$10 -> 0 | G19: =$C$11 -> 0 | H19: =$C$12 -> 0 | K19: Funding arrows into Materials | L19: =COUNTIFS(Arr_to,"MAT",Arr_type,"funding") -> 0 | M19: Materials funds itself
A20: MAT | B20: =$D$6 -> 1 | C20: =$D$7 -> 0 | D20: =$D$8 -> 0 | E20: =$D$9 -> 0 | F20: =$D$10 -> 0 | G20: =$D$11 -> 0 | H20: =$D$12 -> 0 | K20: Arrows interface-backed | L20: =SUM(Declarations!$G$13:$G$26) -> 14 | M20: every one: the components assemble
A21: IND | B21: =$E$6 -> 1 | C21: =$E$7 -> 0 | D21: =$E$8 -> 0 | E21: =$E$9 -> 0 | F21: =$E$10 -> 0 | G21: =$E$11 -> 1 | H21: =$E$12 -> 1 | K21: Demand arrows | L21: =COUNTIF(Arr_type,"demand") -> 3 | M21: market to each division
A22: DIG | B22: =$F$6 -> 1 | C22: =$F$7 -> 1 | D22: =$F$8 -> 0 | E22: =$F$9 -> 0 | F22: =$F$10 -> 0 | G22: =$F$11 -> 1 | H22: =$F$12 -> 1 | K22: Cash arrows | L22: =COUNTIF(Arr_type,"cash") -> 3 | M22: each division to treasury
A23: ENG | B23: =$G$6 -> 0 | C23: =$G$7 -> 0 | D23: =$G$8 -> 0 | E23: =$G$9 -> 1 | F23: =$G$10 -> 1 | G23: =$G$11 -> 0 | H23: =$G$12 -> 0 | K23: Funding arrows | L23: =COUNTIF(Arr_type,"funding") -> 2 | M23: treasury to IND and DIG
A24: TRS | B24: =$H$6 -> 0 | C24: =$H$7 -> 1 | D24: =$H$8 -> 1 | E24: =$H$9 -> 1 | F24: =$H$10 -> 1 | G24: =$H$11 -> 0 | H24: =$H$12 -> 0 | K24: Capability arrows | L24: =COUNTIF(Arr_type,"capability") -> 4 | M24: both ways, engineering with IND and DIG
K25: Policy arrows | L25: =COUNTIF(Arr_type,"policy") -> 2 | M25: governance to treasury and Digital
A27: Joined in either direction, SIGN(A + transposed): directions ignored
B28: MKT | C28: GOV | D28: MAT | E28: IND | F28: DIG | G28: ENG | H28: TRS
A29: MKT | B29: =SIGN($B$6+$B$18) -> 0 | C29: =SIGN($C$6+$C$18) -> 0 | D29: =SIGN($D$6+$D$18) -> 1 | E29: =SIGN($E$6+$E$18) -> 1 | F29: =SIGN($F$6+$F$18) -> 1 | G29: =SIGN($G$6+$G$18) -> 0 | H29: =SIGN($H$6+$H$18) -> 0
A30: GOV | B30: =SIGN($B$7+$B$19) -> 0 | C30: =SIGN($C$7+$C$19) -> 0 | D30: =SIGN($D$7+$D$19) -> 0 | E30: =SIGN($E$7+$E$19) -> 0 | F30: =SIGN($F$7+$F$19) -> 1 | G30: =SIGN($G$7+$G$19) -> 0 | H30: =SIGN($H$7+$H$19) -> 1
A31: MAT | B31: =SIGN($B$8+$B$20) -> 1 | C31: =SIGN($C$8+$C$20) -> 0 | D31: =SIGN($D$8+$D$20) -> 0 | E31: =SIGN($E$8+$E$20) -> 0 | F31: =SIGN($F$8+$F$20) -> 0 | G31: =SIGN($G$8+$G$20) -> 0 | H31: =SIGN($H$8+$H$20) -> 1
A32: IND | B32: =SIGN($B$9+$B$21) -> 1 | C32: =SIGN($C$9+$C$21) -> 0 | D32: =SIGN($D$9+$D$21) -> 0 | E32: =SIGN($E$9+$E$21) -> 0 | F32: =SIGN($F$9+$F$21) -> 0 | G32: =SIGN($G$9+$G$21) -> 1 | H32: =SIGN($H$9+$H$21) -> 1
A33: DIG | B33: =SIGN($B$10+$B$22) -> 1 | C33: =SIGN($C$10+$C$22) -> 1 | D33: =SIGN($D$10+$D$22) -> 0 | E33: =SIGN($E$10+$E$22) -> 0 | F33: =SIGN($F$10+$F$22) -> 0 | G33: =SIGN($G$10+$G$22) -> 1 | H33: =SIGN($H$10+$H$22) -> 1
A34: ENG | B34: =SIGN($B$11+$B$23) -> 0 | C34: =SIGN($C$11+$C$23) -> 0 | D34: =SIGN($D$11+$D$23) -> 0 | E34: =SIGN($E$11+$E$23) -> 1 | F34: =SIGN($F$11+$F$23) -> 1 | G34: =SIGN($G$11+$G$23) -> 0 | H34: =SIGN($H$11+$H$23) -> 0
A35: TRS | B35: =SIGN($B$12+$B$24) -> 0 | C35: =SIGN($C$12+$C$24) -> 1 | D35: =SIGN($D$12+$D$24) -> 1 | E35: =SIGN($E$12+$E$24) -> 1 | F35: =SIGN($F$12+$F$24) -> 1 | G35: =SIGN($G$12+$G$24) -> 0 | H35: =SIGN($H$12+$H$24) -> 0
A38: I + U: a component joined to itself and its neighbors
B39: MKT | C39: GOV | D39: MAT | E39: IND | F39: DIG | G39: ENG | H39: TRS
A40: MKT | B40: 1 | C40: =$C$29 -> 0 | D40: =$D$29 -> 1 | E40: =$E$29 -> 1 | F40: =$F$29 -> 1 | G40: =$G$29 -> 0 | H40: =$H$29 -> 0
A41: GOV | B41: =$B$30 -> 0 | C41: 1 | D41: =$D$30 -> 0 | E41: =$E$30 -> 0 | F41: =$F$30 -> 1 | G41: =$G$30 -> 0 | H41: =$H$30 -> 1
A42: MAT | B42: =$B$31 -> 1 | C42: =$C$31 -> 0 | D42: 1 | E42: =$E$31 -> 0 | F42: =$F$31 -> 0 | G42: =$G$31 -> 0 | H42: =$H$31 -> 1
A43: IND | B43: =$B$32 -> 1 | C43: =$C$32 -> 0 | D43: =$D$32 -> 0 | E43: 1 | F43: =$F$32 -> 0 | G43: =$G$32 -> 1 | H43: =$H$32 -> 1
A44: DIG | B44: =$B$33 -> 1 | C44: =$C$33 -> 1 | D44: =$D$33 -> 0 | E44: =$E$33 -> 0 | F44: 1 | G44: =$G$33 -> 1 | H44: =$H$33 -> 1
A45: ENG | B45: =$B$34 -> 0 | C45: =$C$34 -> 0 | D45: =$D$34 -> 0 | E45: =$E$34 -> 1 | F45: =$F$34 -> 1 | G45: 1 | H45: =$H$34 -> 0
A46: TRS | B46: =$B$35 -> 0 | C46: =$C$35 -> 1 | D46: =$D$35 -> 1 | E46: =$E$35 -> 1 | F46: =$F$35 -> 1 | G46: =$G$35 -> 0 | H46: 1
A49: (I + U)^2, as 0 or 1: within two links
B50: MKT | C50: GOV | D50: MAT | E50: IND | F50: DIG | G50: ENG | H50: TRS
A51: MKT | B51: =SIGN($B$40*$B$40+$C$40*$B$41+$D$40*$B$42+$E$40*$B$43+$F$40*$B$44+$G$40*$B$45+$H$40*$B$46) -> 1 | C51: =SIGN($B$40*$C$40+$C$40*$C$41+$D$40*$C$42+$E$40*$C$43+$F$40*$C$44+$G$40*$C$45+$H$40*$C$46) -> 1 | D51: =SIGN($B$40*$D$40+$C$40*$D$41+$D$40*$D$42+$E$40*$D$43+$F$40*$D$44+$G$40*$D$45+$H$40*$D$46) -> 1 | E51: =SIGN($B$40*$E$40+$C$40*$E$41+$D$40*$E$42+$E$40*$E$43+$F$40*$E$44+$G$40*$E$45+$H$40*$E$46) -> 1 | F51: =SIGN($B$40*$F$40+$C$40*$F$41+$D$40*$F$42+$E$40*$F$43+$F$40*$F$44+$G$40*$F$45+$H$40*$F$46) -> 1 | G51: =SIGN($B$40*$G$40+$C$40*$G$41+$D$40*$G$42+$E$40*$G$43+$F$40*$G$44+$G$40*$G$45+$H$40*$G$46) -> 1 | H51: =SIGN($B$40*$H$40+$C$40*$H$41+$D$40*$H$42+$E$40*$H$43+$F$40*$H$44+$G$40*$H$45+$H$40*$H$46) -> 1
A52: GOV | B52: =SIGN($B$41*$B$40+$C$41*$B$41+$D$41*$B$42+$E$41*$B$43+$F$41*$B$44+$G$41*$B$45+$H$41*$B$46) -> 1 | C52: =SIGN($B$41*$C$40+$C$41*$C$41+$D$41*$C$42+$E$41*$C$43+$F$41*$C$44+$G$41*$C$45+$H$41*$C$46) -> 1 | D52: =SIGN($B$41*$D$40+$C$41*$D$41+$D$41*$D$42+$E$41*$D$43+$F$41*$D$44+$G$41*$D$45+$H$41*$D$46) -> 1 | E52: =SIGN($B$41*$E$40+$C$41*$E$41+$D$41*$E$42+$E$41*$E$43+$F$41*$E$44+$G$41*$E$45+$H$41*$E$46) -> 1 | F52: =SIGN($B$41*$F$40+$C$41*$F$41+$D$41*$F$42+$E$41*$F$43+$F$41*$F$44+$G$41*$F$45+$H$41*$F$46) -> 1 | G52: =SIGN($B$41*$G$40+$C$41*$G$41+$D$41*$G$42+$E$41*$G$43+$F$41*$G$44+$G$41*$G$45+$H$41*$G$46) -> 1 | H52: =SIGN($B$41*$H$40+$C$41*$H$41+$D$41*$H$42+$E$41*$H$43+$F$41*$H$44+$G$41*$H$45+$H$41*$H$46) -> 1
A53: MAT | B53: =SIGN($B$42*$B$40+$C$42*$B$41+$D$42*$B$42+$E$42*$B$43+$F$42*$B$44+$G$42*$B$45+$H$42*$B$46) -> 1 | C53: =SIGN($B$42*$C$40+$C$42*$C$41+$D$42*$C$42+$E$42*$C$43+$F$42*$C$44+$G$42*$C$45+$H$42*$C$46) -> 1 | D53: =SIGN($B$42*$D$40+$C$42*$D$41+$D$42*$D$42+$E$42*$D$43+$F$42*$D$44+$G$42*$D$45+$H$42*$D$46) -> 1 | E53: =SIGN($B$42*$E$40+$C$42*$E$41+$D$42*$E$42+$E$42*$E$43+$F$42*$E$44+$G$42*$E$45+$H$42*$E$46) -> 1 | F53: =SIGN($B$42*$F$40+$C$42*$F$41+$D$42*$F$42+$E$42*$F$43+$F$42*$F$44+$G$42*$F$45+$H$42*$F$46) -> 1 | G53: =SIGN($B$42*$G$40+$C$42*$G$41+$D$42*$G$42+$E$42*$G$43+$F$42*$G$44+$G$42*$G$45+$H$42*$G$46) -> 0 | H53: =SIGN($B$42*$H$40+$C$42*$H$41+$D$42*$H$42+$E$42*$H$43+$F$42*$H$44+$G$42*$H$45+$H$42*$H$46) -> 1
A54: IND | B54: =SIGN($B$43*$B$40+$C$43*$B$41+$D$43*$B$42+$E$43*$B$43+$F$43*$B$44+$G$43*$B$45+$H$43*$B$46) -> 1 | C54: =SIGN($B$43*$C$40+$C$43*$C$41+$D$43*$C$42+$E$43*$C$43+$F$43*$C$44+$G$43*$C$45+$H$43*$C$46) -> 1 | D54: =SIGN($B$43*$D$40+$C$43*$D$41+$D$43*$D$42+$E$43*$D$43+$F$43*$D$44+$G$43*$D$45+$H$43*$D$46) -> 1 | E54: =SIGN($B$43*$E$40+$C$43*$E$41+$D$43*$E$42+$E$43*$E$43+$F$43*$E$44+$G$43*$E$45+$H$43*$E$46) -> 1 | F54: =SIGN($B$43*$F$40+$C$43*$F$41+$D$43*$F$42+$E$43*$F$43+$F$43*$F$44+$G$43*$F$45+$H$43*$F$46) -> 1 | G54: =SIGN($B$43*$G$40+$C$43*$G$41+$D$43*$G$42+$E$43*$G$43+$F$43*$G$44+$G$43*$G$45+$H$43*$G$46) -> 1 | H54: =SIGN($B$43*$H$40+$C$43*$H$41+$D$43*$H$42+$E$43*$H$43+$F$43*$H$44+$G$43*$H$45+$H$43*$H$46) -> 1
A55: DIG | B55: =SIGN($B$44*$B$40+$C$44*$B$41+$D$44*$B$42+$E$44*$B$43+$F$44*$B$44+$G$44*$B$45+$H$44*$B$46) -> 1 | C55: =SIGN($B$44*$C$40+$C$44*$C$41+$D$44*$C$42+$E$44*$C$43+$F$44*$C$44+$G$44*$C$45+$H$44*$C$46) -> 1 | D55: =SIGN($B$44*$D$40+$C$44*$D$41+$D$44*$D$42+$E$44*$D$43+$F$44*$D$44+$G$44*$D$45+$H$44*$D$46) -> 1 | E55: =SIGN($B$44*$E$40+$C$44*$E$41+$D$44*$E$42+$E$44*$E$43+$F$44*$E$44+$G$44*$E$45+$H$44*$E$46) -> 1 | F55: =SIGN($B$44*$F$40+$C$44*$F$41+$D$44*$F$42+$E$44*$F$43+$F$44*$F$44+$G$44*$F$45+$H$44*$F$46) -> 1 | G55: =SIGN($B$44*$G$40+$C$44*$G$41+$D$44*$G$42+$E$44*$G$43+$F$44*$G$44+$G$44*$G$45+$H$44*$G$46) -> 1 | H55: =SIGN($B$44*$H$40+$C$44*$H$41+$D$44*$H$42+$E$44*$H$43+$F$44*$H$44+$G$44*$H$45+$H$44*$H$46) -> 1
A56: ENG | B56: =SIGN($B$45*$B$40+$C$45*$B$41+$D$45*$B$42+$E$45*$B$43+$F$45*$B$44+$G$45*$B$45+$H$45*$B$46) -> 1 | C56: =SIGN($B$45*$C$40+$C$45*$C$41+$D$45*$C$42+$E$45*$C$43+$F$45*$C$44+$G$45*$C$45+$H$45*$C$46) -> 1 | D56: =SIGN($B$45*$D$40+$C$45*$D$41+$D$45*$D$42+$E$45*$D$43+$F$45*$D$44+$G$45*$D$45+$H$45*$D$46) -> 0 | E56: =SIGN($B$45*$E$40+$C$45*$E$41+$D$45*$E$42+$E$45*$E$43+$F$45*$E$44+$G$45*$E$45+$H$45*$E$46) -> 1 | F56: =SIGN($B$45*$F$40+$C$45*$F$41+$D$45*$F$42+$E$45*$F$43+$F$45*$F$44+$G$45*$F$45+$H$45*$F$46) -> 1 | G56: =SIGN($B$45*$G$40+$C$45*$G$41+$D$45*$G$42+$E$45*$G$43+$F$45*$G$44+$G$45*$G$45+$H$45*$G$46) -> 1 | H56: =SIGN($B$45*$H$40+$C$45*$H$41+$D$45*$H$42+$E$45*$H$43+$F$45*$H$44+$G$45*$H$45+$H$45*$H$46) -> 1
A57: TRS | B57: =SIGN($B$46*$B$40+$C$46*$B$41+$D$46*$B$42+$E$46*$B$43+$F$46*$B$44+$G$46*$B$45+$H$46*$B$46) -> 1 | C57: =SIGN($B$46*$C$40+$C$46*$C$41+$D$46*$C$42+$E$46*$C$43+$F$46*$C$44+$G$46*$C$45+$H$46*$C$46) -> 1 | D57: =SIGN($B$46*$D$40+$C$46*$D$41+$D$46*$D$42+$E$46*$D$43+$F$46*$D$44+$G$46*$D$45+$H$46*$D$46) -> 1 | E57: =SIGN($B$46*$E$40+$C$46*$E$41+$D$46*$E$42+$E$46*$E$43+$F$46*$E$44+$G$46*$E$45+$H$46*$E$46) -> 1 | F57: =SIGN($B$46*$F$40+$C$46*$F$41+$D$46*$F$42+$E$46*$F$43+$F$46*$F$44+$G$46*$F$45+$H$46*$F$46) -> 1 | G57: =SIGN($B$46*$G$40+$C$46*$G$41+$D$46*$G$42+$E$46*$G$43+$F$46*$G$44+$G$46*$G$45+$H$46*$G$46) -> 1 | H57: =SIGN($B$46*$H$40+$C$46*$H$41+$D$46*$H$42+$E$46*$H$43+$F$46*$H$44+$G$46*$H$45+$H$46*$H$46) -> 1
A60: (I + U)^4, as 0 or 1: within four links
B61: MKT | C61: GOV | D61: MAT | E61: IND | F61: DIG | G61: ENG | H61: TRS
A62: MKT | B62: =SIGN($B$51*$B$51+$C$51*$B$52+$D$51*$B$53+$E$51*$B$54+$F$51*$B$55+$G$51*$B$56+$H$51*$B$57) -> 1 | C62: =SIGN($B$51*$C$51+$C$51*$C$52+$D$51*$C$53+$E$51*$C$54+$F$51*$C$55+$G$51*$C$56+$H$51*$C$57) -> 1 | D62: =SIGN($B$51*$D$51+$C$51*$D$52+$D$51*$D$53+$E$51*$D$54+$F$51*$D$55+$G$51*$D$56+$H$51*$D$57) -> 1 | E62: =SIGN($B$51*$E$51+$C$51*$E$52+$D$51*$E$53+$E$51*$E$54+$F$51*$E$55+$G$51*$E$56+$H$51*$E$57) -> 1 | F62: =SIGN($B$51*$F$51+$C$51*$F$52+$D$51*$F$53+$E$51*$F$54+$F$51*$F$55+$G$51*$F$56+$H$51*$F$57) -> 1 | G62: =SIGN($B$51*$G$51+$C$51*$G$52+$D$51*$G$53+$E$51*$G$54+$F$51*$G$55+$G$51*$G$56+$H$51*$G$57) -> 1 | H62: =SIGN($B$51*$H$51+$C$51*$H$52+$D$51*$H$53+$E$51*$H$54+$F$51*$H$55+$G$51*$H$56+$H$51*$H$57) -> 1
A63: GOV | B63: =SIGN($B$52*$B$51+$C$52*$B$52+$D$52*$B$53+$E$52*$B$54+$F$52*$B$55+$G$52*$B$56+$H$52*$B$57) -> 1 | C63: =SIGN($B$52*$C$51+$C$52*$C$52+$D$52*$C$53+$E$52*$C$54+$F$52*$C$55+$G$52*$C$56+$H$52*$C$57) -> 1 | D63: =SIGN($B$52*$D$51+$C$52*$D$52+$D$52*$D$53+$E$52*$D$54+$F$52*$D$55+$G$52*$D$56+$H$52*$D$57) -> 1 | E63: =SIGN($B$52*$E$51+$C$52*$E$52+$D$52*$E$53+$E$52*$E$54+$F$52*$E$55+$G$52*$E$56+$H$52*$E$57) -> 1 | F63: =SIGN($B$52*$F$51+$C$52*$F$52+$D$52*$F$53+$E$52*$F$54+$F$52*$F$55+$G$52*$F$56+$H$52*$F$57) -> 1 | G63: =SIGN($B$52*$G$51+$C$52*$G$52+$D$52*$G$53+$E$52*$G$54+$F$52*$G$55+$G$52*$G$56+$H$52*$G$57) -> 1 | H63: =SIGN($B$52*$H$51+$C$52*$H$52+$D$52*$H$53+$E$52*$H$54+$F$52*$H$55+$G$52*$H$56+$H$52*$H$57) -> 1
A64: MAT | B64: =SIGN($B$53*$B$51+$C$53*$B$52+$D$53*$B$53+$E$53*$B$54+$F$53*$B$55+$G$53*$B$56+$H$53*$B$57) -> 1 | C64: =SIGN($B$53*$C$51+$C$53*$C$52+$D$53*$C$53+$E$53*$C$54+$F$53*$C$55+$G$53*$C$56+$H$53*$C$57) -> 1 | D64: =SIGN($B$53*$D$51+$C$53*$D$52+$D$53*$D$53+$E$53*$D$54+$F$53*$D$55+$G$53*$D$56+$H$53*$D$57) -> 1 | E64: =SIGN($B$53*$E$51+$C$53*$E$52+$D$53*$E$53+$E$53*$E$54+$F$53*$E$55+$G$53*$E$56+$H$53*$E$57) -> 1 | F64: =SIGN($B$53*$F$51+$C$53*$F$52+$D$53*$F$53+$E$53*$F$54+$F$53*$F$55+$G$53*$F$56+$H$53*$F$57) -> 1 | G64: =SIGN($B$53*$G$51+$C$53*$G$52+$D$53*$G$53+$E$53*$G$54+$F$53*$G$55+$G$53*$G$56+$H$53*$G$57) -> 1 | H64: =SIGN($B$53*$H$51+$C$53*$H$52+$D$53*$H$53+$E$53*$H$54+$F$53*$H$55+$G$53*$H$56+$H$53*$H$57) -> 1
A65: IND | B65: =SIGN($B$54*$B$51+$C$54*$B$52+$D$54*$B$53+$E$54*$B$54+$F$54*$B$55+$G$54*$B$56+$H$54*$B$57) -> 1 | C65: =SIGN($B$54*$C$51+$C$54*$C$52+$D$54*$C$53+$E$54*$C$54+$F$54*$C$55+$G$54*$C$56+$H$54*$C$57) -> 1 | D65: =SIGN($B$54*$D$51+$C$54*$D$52+$D$54*$D$53+$E$54*$D$54+$F$54*$D$55+$G$54*$D$56+$H$54*$D$57) -> 1 | E65: =SIGN($B$54*$E$51+$C$54*$E$52+$D$54*$E$53+$E$54*$E$54+$F$54*$E$55+$G$54*$E$56+$H$54*$E$57) -> 1 | F65: =SIGN($B$54*$F$51+$C$54*$F$52+$D$54*$F$53+$E$54*$F$54+$F$54*$F$55+$G$54*$F$56+$H$54*$F$57) -> 1 | G65: =SIGN($B$54*$G$51+$C$54*$G$52+$D$54*$G$53+$E$54*$G$54+$F$54*$G$55+$G$54*$G$56+$H$54*$G$57) -> 1 | H65: =SIGN($B$54*$H$51+$C$54*$H$52+$D$54*$H$53+$E$54*$H$54+$F$54*$H$55+$G$54*$H$56+$H$54*$H$57) -> 1
A66: DIG | B66: =SIGN($B$55*$B$51+$C$55*$B$52+$D$55*$B$53+$E$55*$B$54+$F$55*$B$55+$G$55*$B$56+$H$55*$B$57) -> 1 | C66: =SIGN($B$55*$C$51+$C$55*$C$52+$D$55*$C$53+$E$55*$C$54+$F$55*$C$55+$G$55*$C$56+$H$55*$C$57) -> 1 | D66: =SIGN($B$55*$D$51+$C$55*$D$52+$D$55*$D$53+$E$55*$D$54+$F$55*$D$55+$G$55*$D$56+$H$55*$D$57) -> 1 | E66: =SIGN($B$55*$E$51+$C$55*$E$52+$D$55*$E$53+$E$55*$E$54+$F$55*$E$55+$G$55*$E$56+$H$55*$E$57) -> 1 | F66: =SIGN($B$55*$F$51+$C$55*$F$52+$D$55*$F$53+$E$55*$F$54+$F$55*$F$55+$G$55*$F$56+$H$55*$F$57) -> 1 | G66: =SIGN($B$55*$G$51+$C$55*$G$52+$D$55*$G$53+$E$55*$G$54+$F$55*$G$55+$G$55*$G$56+$H$55*$G$57) -> 1 | H66: =SIGN($B$55*$H$51+$C$55*$H$52+$D$55*$H$53+$E$55*$H$54+$F$55*$H$55+$G$55*$H$56+$H$55*$H$57) -> 1
A67: ENG | B67: =SIGN($B$56*$B$51+$C$56*$B$52+$D$56*$B$53+$E$56*$B$54+$F$56*$B$55+$G$56*$B$56+$H$56*$B$57) -> 1 | C67: =SIGN($B$56*$C$51+$C$56*$C$52+$D$56*$C$53+$E$56*$C$54+$F$56*$C$55+$G$56*$C$56+$H$56*$C$57) -> 1 | D67: =SIGN($B$56*$D$51+$C$56*$D$52+$D$56*$D$53+$E$56*$D$54+$F$56*$D$55+$G$56*$D$56+$H$56*$D$57) -> 1 | E67: =SIGN($B$56*$E$51+$C$56*$E$52+$D$56*$E$53+$E$56*$E$54+$F$56*$E$55+$G$56*$E$56+$H$56*$E$57) -> 1 | F67: =SIGN($B$56*$F$51+$C$56*$F$52+$D$56*$F$53+$E$56*$F$54+$F$56*$F$55+$G$56*$F$56+$H$56*$F$57) -> 1 | G67: =SIGN($B$56*$G$51+$C$56*$G$52+$D$56*$G$53+$E$56*$G$54+$F$56*$G$55+$G$56*$G$56+$H$56*$G$57) -> 1 | H67: =SIGN($B$56*$H$51+$C$56*$H$52+$D$56*$H$53+$E$56*$H$54+$F$56*$H$55+$G$56*$H$56+$H$56*$H$57) -> 1
A68: TRS | B68: =SIGN($B$57*$B$51+$C$57*$B$52+$D$57*$B$53+$E$57*$B$54+$F$57*$B$55+$G$57*$B$56+$H$57*$B$57) -> 1 | C68: =SIGN($B$57*$C$51+$C$57*$C$52+$D$57*$C$53+$E$57*$C$54+$F$57*$C$55+$G$57*$C$56+$H$57*$C$57) -> 1 | D68: =SIGN($B$57*$D$51+$C$57*$D$52+$D$57*$D$53+$E$57*$D$54+$F$57*$D$55+$G$57*$D$56+$H$57*$D$57) -> 1 | E68: =SIGN($B$57*$E$51+$C$57*$E$52+$D$57*$E$53+$E$57*$E$54+$F$57*$E$55+$G$57*$E$56+$H$57*$E$57) -> 1 | F68: =SIGN($B$57*$F$51+$C$57*$F$52+$D$57*$F$53+$E$57*$F$54+$F$57*$F$55+$G$57*$F$56+$H$57*$F$57) -> 1 | G68: =SIGN($B$57*$G$51+$C$57*$G$52+$D$57*$G$53+$E$57*$G$54+$F$57*$G$55+$G$57*$G$56+$H$57*$G$57) -> 1 | H68: =SIGN($B$57*$H$51+$C$57*$H$52+$D$57*$H$53+$E$57*$H$54+$F$57*$H$55+$G$57*$H$56+$H$57*$H$57) -> 1
A71: (I + U)^8, as 0 or 1: in the same piece when directions are ignored
B72: MKT | C72: GOV | D72: MAT | E72: IND | F72: DIG | G72: ENG | H72: TRS | I72: piece size
A73: MKT | B73: =SIGN($B$62*$B$62+$C$62*$B$63+$D$62*$B$64+$E$62*$B$65+$F$62*$B$66+$G$62*$B$67+$H$62*$B$68) -> 1 | C73: =SIGN($B$62*$C$62+$C$62*$C$63+$D$62*$C$64+$E$62*$C$65+$F$62*$C$66+$G$62*$C$67+$H$62*$C$68) -> 1 | D73: =SIGN($B$62*$D$62+$C$62*$D$63+$D$62*$D$64+$E$62*$D$65+$F$62*$D$66+$G$62*$D$67+$H$62*$D$68) -> 1 | E73: =SIGN($B$62*$E$62+$C$62*$E$63+$D$62*$E$64+$E$62*$E$65+$F$62*$E$66+$G$62*$E$67+$H$62*$E$68) -> 1 | F73: =SIGN($B$62*$F$62+$C$62*$F$63+$D$62*$F$64+$E$62*$F$65+$F$62*$F$66+$G$62*$F$67+$H$62*$F$68) -> 1 | G73: =SIGN($B$62*$G$62+$C$62*$G$63+$D$62*$G$64+$E$62*$G$65+$F$62*$G$66+$G$62*$G$67+$H$62*$G$68) -> 1 | H73: =SIGN($B$62*$H$62+$C$62*$H$63+$D$62*$H$64+$E$62*$H$65+$F$62*$H$66+$G$62*$H$67+$H$62*$H$68) -> 1 | I73: =SUM($B$73:$H$73) -> 7
A74: GOV | B74: =SIGN($B$63*$B$62+$C$63*$B$63+$D$63*$B$64+$E$63*$B$65+$F$63*$B$66+$G$63*$B$67+$H$63*$B$68) -> 1 | C74: =SIGN($B$63*$C$62+$C$63*$C$63+$D$63*$C$64+$E$63*$C$65+$F$63*$C$66+$G$63*$C$67+$H$63*$C$68) -> 1 | D74: =SIGN($B$63*$D$62+$C$63*$D$63+$D$63*$D$64+$E$63*$D$65+$F$63*$D$66+$G$63*$D$67+$H$63*$D$68) -> 1 | E74: =SIGN($B$63*$E$62+$C$63*$E$63+$D$63*$E$64+$E$63*$E$65+$F$63*$E$66+$G$63*$E$67+$H$63*$E$68) -> 1 | F74: =SIGN($B$63*$F$62+$C$63*$F$63+$D$63*$F$64+$E$63*$F$65+$F$63*$F$66+$G$63*$F$67+$H$63*$F$68) -> 1 | G74: =SIGN($B$63*$G$62+$C$63*$G$63+$D$63*$G$64+$E$63*$G$65+$F$63*$G$66+$G$63*$G$67+$H$63*$G$68) -> 1 | H74: =SIGN($B$63*$H$62+$C$63*$H$63+$D$63*$H$64+$E$63*$H$65+$F$63*$H$66+$G$63*$H$67+$H$63*$H$68) -> 1 | I74: =SUM($B$74:$H$74) -> 7
A75: MAT | B75: =SIGN($B$64*$B$62+$C$64*$B$63+$D$64*$B$64+$E$64*$B$65+$F$64*$B$66+$G$64*$B$67+$H$64*$B$68) -> 1 | C75: =SIGN($B$64*$C$62+$C$64*$C$63+$D$64*$C$64+$E$64*$C$65+$F$64*$C$66+$G$64*$C$67+$H$64*$C$68) -> 1 | D75: =SIGN($B$64*$D$62+$C$64*$D$63+$D$64*$D$64+$E$64*$D$65+$F$64*$D$66+$G$64*$D$67+$H$64*$D$68) -> 1 | E75: =SIGN($B$64*$E$62+$C$64*$E$63+$D$64*$E$64+$E$64*$E$65+$F$64*$E$66+$G$64*$E$67+$H$64*$E$68) -> 1 | F75: =SIGN($B$64*$F$62+$C$64*$F$63+$D$64*$F$64+$E$64*$F$65+$F$64*$F$66+$G$64*$F$67+$H$64*$F$68) -> 1 | G75: =SIGN($B$64*$G$62+$C$64*$G$63+$D$64*$G$64+$E$64*$G$65+$F$64*$G$66+$G$64*$G$67+$H$64*$G$68) -> 1 | H75: =SIGN($B$64*$H$62+$C$64*$H$63+$D$64*$H$64+$E$64*$H$65+$F$64*$H$66+$G$64*$H$67+$H$64*$H$68) -> 1 | I75: =SUM($B$75:$H$75) -> 7
A76: IND | B76: =SIGN($B$65*$B$62+$C$65*$B$63+$D$65*$B$64+$E$65*$B$65+$F$65*$B$66+$G$65*$B$67+$H$65*$B$68) -> 1 | C76: =SIGN($B$65*$C$62+$C$65*$C$63+$D$65*$C$64+$E$65*$C$65+$F$65*$C$66+$G$65*$C$67+$H$65*$C$68) -> 1 | D76: =SIGN($B$65*$D$62+$C$65*$D$63+$D$65*$D$64+$E$65*$D$65+$F$65*$D$66+$G$65*$D$67+$H$65*$D$68) -> 1 | E76: =SIGN($B$65*$E$62+$C$65*$E$63+$D$65*$E$64+$E$65*$E$65+$F$65*$E$66+$G$65*$E$67+$H$65*$E$68) -> 1 | F76: =SIGN($B$65*$F$62+$C$65*$F$63+$D$65*$F$64+$E$65*$F$65+$F$65*$F$66+$G$65*$F$67+$H$65*$F$68) -> 1 | G76: =SIGN($B$65*$G$62+$C$65*$G$63+$D$65*$G$64+$E$65*$G$65+$F$65*$G$66+$G$65*$G$67+$H$65*$G$68) -> 1 | H76: =SIGN($B$65*$H$62+$C$65*$H$63+$D$65*$H$64+$E$65*$H$65+$F$65*$H$66+$G$65*$H$67+$H$65*$H$68) -> 1 | I76: =SUM($B$76:$H$76) -> 7
A77: DIG | B77: =SIGN($B$66*$B$62+$C$66*$B$63+$D$66*$B$64+$E$66*$B$65+$F$66*$B$66+$G$66*$B$67+$H$66*$B$68) -> 1 | C77: =SIGN($B$66*$C$62+$C$66*$C$63+$D$66*$C$64+$E$66*$C$65+$F$66*$C$66+$G$66*$C$67+$H$66*$C$68) -> 1 | D77: =SIGN($B$66*$D$62+$C$66*$D$63+$D$66*$D$64+$E$66*$D$65+$F$66*$D$66+$G$66*$D$67+$H$66*$D$68) -> 1 | E77: =SIGN($B$66*$E$62+$C$66*$E$63+$D$66*$E$64+$E$66*$E$65+$F$66*$E$66+$G$66*$E$67+$H$66*$E$68) -> 1 | F77: =SIGN($B$66*$F$62+$C$66*$F$63+$D$66*$F$64+$E$66*$F$65+$F$66*$F$66+$G$66*$F$67+$H$66*$F$68) -> 1 | G77: =SIGN($B$66*$G$62+$C$66*$G$63+$D$66*$G$64+$E$66*$G$65+$F$66*$G$66+$G$66*$G$67+$H$66*$G$68) -> 1 | H77: =SIGN($B$66*$H$62+$C$66*$H$63+$D$66*$H$64+$E$66*$H$65+$F$66*$H$66+$G$66*$H$67+$H$66*$H$68) -> 1 | I77: =SUM($B$77:$H$77) -> 7
A78: ENG | B78: =SIGN($B$67*$B$62+$C$67*$B$63+$D$67*$B$64+$E$67*$B$65+$F$67*$B$66+$G$67*$B$67+$H$67*$B$68) -> 1 | C78: =SIGN($B$67*$C$62+$C$67*$C$63+$D$67*$C$64+$E$67*$C$65+$F$67*$C$66+$G$67*$C$67+$H$67*$C$68) -> 1 | D78: =SIGN($B$67*$D$62+$C$67*$D$63+$D$67*$D$64+$E$67*$D$65+$F$67*$D$66+$G$67*$D$67+$H$67*$D$68) -> 1 | E78: =SIGN($B$67*$E$62+$C$67*$E$63+$D$67*$E$64+$E$67*$E$65+$F$67*$E$66+$G$67*$E$67+$H$67*$E$68) -> 1 | F78: =SIGN($B$67*$F$62+$C$67*$F$63+$D$67*$F$64+$E$67*$F$65+$F$67*$F$66+$G$67*$F$67+$H$67*$F$68) -> 1 | G78: =SIGN($B$67*$G$62+$C$67*$G$63+$D$67*$G$64+$E$67*$G$65+$F$67*$G$66+$G$67*$G$67+$H$67*$G$68) -> 1 | H78: =SIGN($B$67*$H$62+$C$67*$H$63+$D$67*$H$64+$E$67*$H$65+$F$67*$H$66+$G$67*$H$67+$H$67*$H$68) -> 1 | I78: =SUM($B$78:$H$78) -> 7
A79: TRS | B79: =SIGN($B$68*$B$62+$C$68*$B$63+$D$68*$B$64+$E$68*$B$65+$F$68*$B$66+$G$68*$B$67+$H$68*$B$68) -> 1 | C79: =SIGN($B$68*$C$62+$C$68*$C$63+$D$68*$C$64+$E$68*$C$65+$F$68*$C$66+$G$68*$C$67+$H$68*$C$68) -> 1 | D79: =SIGN($B$68*$D$62+$C$68*$D$63+$D$68*$D$64+$E$68*$D$65+$F$68*$D$66+$G$68*$D$67+$H$68*$D$68) -> 1 | E79: =SIGN($B$68*$E$62+$C$68*$E$63+$D$68*$E$64+$E$68*$E$65+$F$68*$E$66+$G$68*$E$67+$H$68*$E$68) -> 1 | F79: =SIGN($B$68*$F$62+$C$68*$F$63+$D$68*$F$64+$E$68*$F$65+$F$68*$F$66+$G$68*$F$67+$H$68*$F$68) -> 1 | G79: =SIGN($B$68*$G$62+$C$68*$G$63+$D$68*$G$64+$E$68*$G$65+$F$68*$G$66+$G$68*$G$67+$H$68*$G$68) -> 1 | H79: =SIGN($B$68*$H$62+$C$68*$H$63+$D$68*$H$64+$E$68*$H$65+$F$68*$H$66+$G$68*$H$67+$H$68*$H$68) -> 1 | I79: =SUM($B$79:$H$79) -> 7

Sheet Core
A1: Find the core: routes, reachability, strongly connected components and causal layers (Worked Example 9.1, Step 2; Theorem 9.2(iii); Proposition 9.3; AXIOM Lab 1.9, step 2)
A2: Tarjan's algorithm in the notebook; here the same answer from matrix powers: two components are strongly connected when each reaches the other.
A4: A^2: routes of 2 steps from the row to the column
B5: MKT | C5: GOV | D5: MAT | E5: IND | F5: DIG | G5: ENG | H5: TRS | M5: Result | N5: Value | O5: Reading
A6: MKT | B6: =Wiring!$B$6*Wiring!$B$6+Wiring!$C$6*Wiring!$B$7+Wiring!$D$6*Wiring!$B$8+Wiring!$E$6*Wiring!$B$9+Wiring!$F$6*Wiring!$B$10+Wiring!$G$6*Wiring!$B$11+Wiring!$H$6*Wiring!$B$12 -> 0 | C6: =Wiring!$B$6*Wiring!$C$6+Wiring!$C$6*Wiring!$C$7+Wiring!$D$6*Wiring!$C$8+Wiring!$E$6*Wiring!$C$9+Wiring!$F$6*Wiring!$C$10+Wiring!$G$6*Wiring!$C$11+Wiring!$H$6*Wiring!$C$12 -> 0 | D6: =Wiring!$B$6*Wiring!$D$6+Wiring!$C$6*Wiring!$D$7+Wiring!$D$6*Wiring!$D$8+Wiring!$E$6*Wiring!$D$9+Wiring!$F$6*Wiring!$D$10+Wiring!$G$6*Wiring!$D$11+Wiring!$H$6*Wiring!$D$12 -> 0 | E6: =Wiring!$B$6*Wiring!$E$6+Wiring!$C$6*Wiring!$E$7+Wiring!$D$6*Wiring!$E$8+Wiring!$E$6*Wiring!$E$9+Wiring!$F$6*Wiring!$E$10+Wiring!$G$6*Wiring!$E$11+Wiring!$H$6*Wiring!$E$12 -> 0 | F6: =Wiring!$B$6*Wiring!$F$6+Wiring!$C$6*Wiring!$F$7+Wiring!$D$6*Wiring!$F$8+Wiring!$E$6*Wiring!$F$9+Wiring!$F$6*Wiring!$F$10+Wiring!$G$6*Wiring!$F$11+Wiring!$H$6*Wiring!$F$12 -> 0 | G6: =Wiring!$B$6*Wiring!$G$6+Wiring!$C$6*Wiring!$G$7+Wiring!$D$6*Wiring!$G$8+Wiring!$E$6*Wiring!$G$9+Wiring!$F$6*Wiring!$G$10+Wiring!$G$6*Wiring!$G$11+Wiring!$H$6*Wiring!$G$12 -> 2 | H6: =Wiring!$B$6*Wiring!$H$6+Wiring!$C$6*Wiring!$H$7+Wiring!$D$6*Wiring!$H$8+Wiring!$E$6*Wiring!$H$9+Wiring!$F$6*Wiring!$H$10+Wiring!$G$6*Wiring!$H$11+Wiring!$H$6*Wiring!$H$12 -> 3 | M6: Feedback cores (components of more than one member) | N6: =SUMPRODUCT($K$94:$K$100/$J$94:$J$100) -> 1 | O6: one: {IND, DIG, ENG, TRS}
A7: GOV | B7: =Wiring!$B$7*Wiring!$B$6+Wiring!$C$7*Wiring!$B$7+Wiring!$D$7*Wiring!$B$8+Wiring!$E$7*Wiring!$B$9+Wiring!$F$7*Wiring!$B$10+Wiring!$G$7*Wiring!$B$11+Wiring!$H$7*Wiring!$B$12 -> 0 | C7: =Wiring!$B$7*Wiring!$C$6+Wiring!$C$7*Wiring!$C$7+Wiring!$D$7*Wiring!$C$8+Wiring!$E$7*Wiring!$C$9+Wiring!$F$7*Wiring!$C$10+Wiring!$G$7*Wiring!$C$11+Wiring!$H$7*Wiring!$C$12 -> 0 | D7: =Wiring!$B$7*Wiring!$D$6+Wiring!$C$7*Wiring!$D$7+Wiring!$D$7*Wiring!$D$8+Wiring!$E$7*Wiring!$D$9+Wiring!$F$7*Wiring!$D$10+Wiring!$G$7*Wiring!$D$11+Wiring!$H$7*Wiring!$D$12 -> 0 | E7: =Wiring!$B$7*Wiring!$E$6+Wiring!$C$7*Wiring!$E$7+Wiring!$D$7*Wiring!$E$8+Wiring!$E$7*Wiring!$E$9+Wiring!$F$7*Wiring!$E$10+Wiring!$G$7*Wiring!$E$11+Wiring!$H$7*Wiring!$E$12 -> 1 | F7: =Wiring!$B$7*Wiring!$F$6+Wiring!$C$7*Wiring!$F$7+Wiring!$D$7*Wiring!$F$8+Wiring!$E$7*Wiring!$F$9+Wiring!$F$7*Wiring!$F$10+Wiring!$G$7*Wiring!$F$11+Wiring!$H$7*Wiring!$F$12 -> 1 | G7: =Wiring!$B$7*Wiring!$G$6+Wiring!$C$7*Wiring!$G$7+Wiring!$D$7*Wiring!$G$8+Wiring!$E$7*Wiring!$G$9+Wiring!$F$7*Wiring!$G$10+Wiring!$G$7*Wiring!$G$11+Wiring!$H$7*Wiring!$G$12 -> 1 | H7: =Wiring!$B$7*Wiring!$H$6+Wiring!$C$7*Wiring!$H$7+Wiring!$D$7*Wiring!$H$8+Wiring!$E$7*Wiring!$H$9+Wiring!$F$7*Wiring!$H$10+Wiring!$G$7*Wiring!$H$11+Wiring!$H$7*Wiring!$H$12 -> 1 | M7: Members of the largest core | N7: =MAX($J$94:$J$100) -> 4 | O7: four
A8: MAT | B8: =Wiring!$B$8*Wiring!$B$6+Wiring!$C$8*Wiring!$B$7+Wiring!$D$8*Wiring!$B$8+Wiring!$E$8*Wiring!$B$9+Wiring!$F$8*Wiring!$B$10+Wiring!$G$8*Wiring!$B$11+Wiring!$H$8*Wiring!$B$12 -> 0 | C8: =Wiring!$B$8*Wiring!$C$6+Wiring!$C$8*Wiring!$C$7+Wiring!$D$8*Wiring!$C$8+Wiring!$E$8*Wiring!$C$9+Wiring!$F$8*Wiring!$C$10+Wiring!$G$8*Wiring!$C$11+Wiring!$H$8*Wiring!$C$12 -> 0 | D8: =Wiring!$B$8*Wiring!$D$6+Wiring!$C$8*Wiring!$D$7+Wiring!$D$8*Wiring!$D$8+Wiring!$E$8*Wiring!$D$9+Wiring!$F$8*Wiring!$D$10+Wiring!$G$8*Wiring!$D$11+Wiring!$H$8*Wiring!$D$12 -> 0 | E8: =Wiring!$B$8*Wiring!$E$6+Wiring!$C$8*Wiring!$E$7+Wiring!$D$8*Wiring!$E$8+Wiring!$E$8*Wiring!$E$9+Wiring!$F$8*Wiring!$E$10+Wiring!$G$8*Wiring!$E$11+Wiring!$H$8*Wiring!$E$12 -> 1 | F8: =Wiring!$B$8*Wiring!$F$6+Wiring!$C$8*Wiring!$F$7+Wiring!$D$8*Wiring!$F$8+Wiring!$E$8*Wiring!$F$9+Wiring!$F$8*Wiring!$F$10+Wiring!$G$8*Wiring!$F$11+Wiring!$H$8*Wiring!$F$12 -> 1 | G8: =Wiring!$B$8*Wiring!$G$6+Wiring!$C$8*Wiring!$G$7+Wiring!$D$8*Wiring!$G$8+Wiring!$E$8*Wiring!$G$9+Wiring!$F$8*Wiring!$G$10+Wiring!$G$8*Wiring!$G$11+Wiring!$H$8*Wiring!$G$12 -> 0 | H8: =Wiring!$B$8*Wiring!$H$6+Wiring!$C$8*Wiring!$H$7+Wiring!$D$8*Wiring!$H$8+Wiring!$E$8*Wiring!$H$9+Wiring!$F$8*Wiring!$H$10+Wiring!$G$8*Wiring!$H$11+Wiring!$H$8*Wiring!$H$12 -> 0 | M8: Components in a core | N8: =SUM($K$94:$K$100) -> 4
A9: IND | B9: =Wiring!$B$9*Wiring!$B$6+Wiring!$C$9*Wiring!$B$7+Wiring!$D$9*Wiring!$B$8+Wiring!$E$9*Wiring!$B$9+Wiring!$F$9*Wiring!$B$10+Wiring!$G$9*Wiring!$B$11+Wiring!$H$9*Wiring!$B$12 -> 0 | C9: =Wiring!$B$9*Wiring!$C$6+Wiring!$C$9*Wiring!$C$7+Wiring!$D$9*Wiring!$C$8+Wiring!$E$9*Wiring!$C$9+Wiring!$F$9*Wiring!$C$10+Wiring!$G$9*Wiring!$C$11+Wiring!$H$9*Wiring!$C$12 -> 0 | D9: =Wiring!$B$9*Wiring!$D$6+Wiring!$C$9*Wiring!$D$7+Wiring!$D$9*Wiring!$D$8+Wiring!$E$9*Wiring!$D$9+Wiring!$F$9*Wiring!$D$10+Wiring!$G$9*Wiring!$D$11+Wiring!$H$9*Wiring!$D$12 -> 0 | E9: =Wiring!$B$9*Wiring!$E$6+Wiring!$C$9*Wiring!$E$7+Wiring!$D$9*Wiring!$E$8+Wiring!$E$9*Wiring!$E$9+Wiring!$F$9*Wiring!$E$10+Wiring!$G$9*Wiring!$E$11+Wiring!$H$9*Wiring!$E$12 -> 2 | F9: =Wiring!$B$9*Wiring!$F$6+Wiring!$C$9*Wiring!$F$7+Wiring!$D$9*Wiring!$F$8+Wiring!$E$9*Wiring!$F$9+Wiring!$F$9*Wiring!$F$10+Wiring!$G$9*Wiring!$F$11+Wiring!$H$9*Wiring!$F$12 -> 2 | G9: =Wiring!$B$9*Wiring!$G$6+Wiring!$C$9*Wiring!$G$7+Wiring!$D$9*Wiring!$G$8+Wiring!$E$9*Wiring!$G$9+Wiring!$F$9*Wiring!$G$10+Wiring!$G$9*Wiring!$G$11+Wiring!$H$9*Wiring!$G$12 -> 0 | H9: =Wiring!$B$9*Wiring!$H$6+Wiring!$C$9*Wiring!$H$7+Wiring!$D$9*Wiring!$H$8+Wiring!$E$9*Wiring!$H$9+Wiring!$F$9*Wiring!$H$10+Wiring!$G$9*Wiring!$H$11+Wiring!$H$9*Wiring!$H$12 -> 0 | M9: Causal layers | N9: =MAX($H$127:$H$133) -> 3 | O9: drivers, feeder, core
A10: DIG | B10: =Wiring!$B$10*Wiring!$B$6+Wiring!$C$10*Wiring!$B$7+Wiring!$D$10*Wiring!$B$8+Wiring!$E$10*Wiring!$B$9+Wiring!$F$10*Wiring!$B$10+Wiring!$G$10*Wiring!$B$11+Wiring!$H$10*Wiring!$B$12 -> 0 | C10: =Wiring!$B$10*Wiring!$C$6+Wiring!$C$10*Wiring!$C$7+Wiring!$D$10*Wiring!$C$8+Wiring!$E$10*Wiring!$C$9+Wiring!$F$10*Wiring!$C$10+Wiring!$G$10*Wiring!$C$11+Wiring!$H$10*Wiring!$C$12 -> 0 | D10: =Wiring!$B$10*Wiring!$D$6+Wiring!$C$10*Wiring!$D$7+Wiring!$D$10*Wiring!$D$8+Wiring!$E$10*Wiring!$D$9+Wiring!$F$10*Wiring!$D$10+Wiring!$G$10*Wiring!$D$11+Wiring!$H$10*Wiring!$D$12 -> 0 | E10: =Wiring!$B$10*Wiring!$E$6+Wiring!$C$10*Wiring!$E$7+Wiring!$D$10*Wiring!$E$8+Wiring!$E$10*Wiring!$E$9+Wiring!$F$10*Wiring!$E$10+Wiring!$G$10*Wiring!$E$11+Wiring!$H$10*Wiring!$E$12 -> 2 | F10: =Wiring!$B$10*Wiring!$F$6+Wiring!$C$10*Wiring!$F$7+Wiring!$D$10*Wiring!$F$8+Wiring!$E$10*Wiring!$F$9+Wiring!$F$10*Wiring!$F$10+Wiring!$G$10*Wiring!$F$11+Wiring!$H$10*Wiring!$F$12 -> 2 | G10: =Wiring!$B$10*Wiring!$G$6+Wiring!$C$10*Wiring!$G$7+Wiring!$D$10*Wiring!$G$8+Wiring!$E$10*Wiring!$G$9+Wiring!$F$10*Wiring!$G$10+Wiring!$G$10*Wiring!$G$11+Wiring!$H$10*Wiring!$G$12 -> 0 | H10: =Wiring!$B$10*Wiring!$H$6+Wiring!$C$10*Wiring!$H$7+Wiring!$D$10*Wiring!$H$8+Wiring!$E$10*Wiring!$H$9+Wiring!$F$10*Wiring!$H$10+Wiring!$G$10*Wiring!$H$11+Wiring!$H$10*Wiring!$H$12 -> 0 | M10: Condensation depth: longest chain of one-way arrows | N10: =N9-1 -> 2 | O10: two
A11: ENG | B11: =Wiring!$B$11*Wiring!$B$6+Wiring!$C$11*Wiring!$B$7+Wiring!$D$11*Wiring!$B$8+Wiring!$E$11*Wiring!$B$9+Wiring!$F$11*Wiring!$B$10+Wiring!$G$11*Wiring!$B$11+Wiring!$H$11*Wiring!$B$12 -> 0 | C11: =Wiring!$B$11*Wiring!$C$6+Wiring!$C$11*Wiring!$C$7+Wiring!$D$11*Wiring!$C$8+Wiring!$E$11*Wiring!$C$9+Wiring!$F$11*Wiring!$C$10+Wiring!$G$11*Wiring!$C$11+Wiring!$H$11*Wiring!$C$12 -> 0 | D11: =Wiring!$B$11*Wiring!$D$6+Wiring!$C$11*Wiring!$D$7+Wiring!$D$11*Wiring!$D$8+Wiring!$E$11*Wiring!$D$9+Wiring!$F$11*Wiring!$D$10+Wiring!$G$11*Wiring!$D$11+Wiring!$H$11*Wiring!$D$12 -> 0 | E11: =Wiring!$B$11*Wiring!$E$6+Wiring!$C$11*Wiring!$E$7+Wiring!$D$11*Wiring!$E$8+Wiring!$E$11*Wiring!$E$9+Wiring!$F$11*Wiring!$E$10+Wiring!$G$11*Wiring!$E$11+Wiring!$H$11*Wiring!$E$12 -> 0 | F11: =Wiring!$B$11*Wiring!$F$6+Wiring!$C$11*Wiring!$F$7+Wiring!$D$11*Wiring!$F$8+Wiring!$E$11*Wiring!$F$9+Wiring!$F$11*Wiring!$F$10+Wiring!$G$11*Wiring!$F$11+Wiring!$H$11*Wiring!$F$12 -> 0 | G11: =Wiring!$B$11*Wiring!$G$6+Wiring!$C$11*Wiring!$G$7+Wiring!$D$11*Wiring!$G$8+Wiring!$E$11*Wiring!$G$9+Wiring!$F$11*Wiring!$G$10+Wiring!$G$11*Wiring!$G$11+Wiring!$H$11*Wiring!$G$12 -> 2 | H11: =Wiring!$B$11*Wiring!$H$6+Wiring!$C$11*Wiring!$H$7+Wiring!$D$11*Wiring!$H$8+Wiring!$E$11*Wiring!$H$9+Wiring!$F$11*Wiring!$H$10+Wiring!$G$11*Wiring!$H$11+Wiring!$H$11*Wiring!$H$12 -> 2 | M11: Layer of the market | N11: =$H$127 -> 1 | O11: a driver
A12: TRS | B12: =Wiring!$B$12*Wiring!$B$6+Wiring!$C$12*Wiring!$B$7+Wiring!$D$12*Wiring!$B$8+Wiring!$E$12*Wiring!$B$9+Wiring!$F$12*Wiring!$B$10+Wiring!$G$12*Wiring!$B$11+Wiring!$H$12*Wiring!$B$12 -> 0 | C12: =Wiring!$B$12*Wiring!$C$6+Wiring!$C$12*Wiring!$C$7+Wiring!$D$12*Wiring!$C$8+Wiring!$E$12*Wiring!$C$9+Wiring!$F$12*Wiring!$C$10+Wiring!$G$12*Wiring!$C$11+Wiring!$H$12*Wiring!$C$12 -> 0 | D12: =Wiring!$B$12*Wiring!$D$6+Wiring!$C$12*Wiring!$D$7+Wiring!$D$12*Wiring!$D$8+Wiring!$E$12*Wiring!$D$9+Wiring!$F$12*Wiring!$D$10+Wiring!$G$12*Wiring!$D$11+Wiring!$H$12*Wiring!$D$12 -> 0 | E12: =Wiring!$B$12*Wiring!$E$6+Wiring!$C$12*Wiring!$E$7+Wiring!$D$12*Wiring!$E$8+Wiring!$E$12*Wiring!$E$9+Wiring!$F$12*Wiring!$E$10+Wiring!$G$12*Wiring!$E$11+Wiring!$H$12*Wiring!$E$12 -> 0 | F12: =Wiring!$B$12*Wiring!$F$6+Wiring!$C$12*Wiring!$F$7+Wiring!$D$12*Wiring!$F$8+Wiring!$E$12*Wiring!$F$9+Wiring!$F$12*Wiring!$F$10+Wiring!$G$12*Wiring!$F$11+Wiring!$H$12*Wiring!$F$12 -> 0 | G12: =Wiring!$B$12*Wiring!$G$6+Wiring!$C$12*Wiring!$G$7+Wiring!$D$12*Wiring!$G$8+Wiring!$E$12*Wiring!$G$9+Wiring!$F$12*Wiring!$G$10+Wiring!$G$12*Wiring!$G$11+Wiring!$H$12*Wiring!$G$12 -> 2 | H12: =Wiring!$B$12*Wiring!$H$6+Wiring!$C$12*Wiring!$H$7+Wiring!$D$12*Wiring!$H$8+Wiring!$E$12*Wiring!$H$9+Wiring!$F$12*Wiring!$H$10+Wiring!$G$12*Wiring!$H$11+Wiring!$H$12*Wiring!$H$12 -> 2 | M12: Layer of governance | N12: =$H$128 -> 1 | O12: a driver
M13: Layer of Materials | N13: =$H$129 -> 2 | O13: the feeder
M14: Layer of the core | N14: =$H$133 -> 3
A15: A^3: routes of 3 steps from the row to the column | M15: Core members among the divisions | N15: =COUNTIFS(Box,"divisions",$K$94:$K$100,1) -> 2 | O15: IND and DIG
B16: MKT | C16: GOV | D16: MAT | E16: IND | F16: DIG | G16: ENG | H16: TRS | M16: Core members in the corporate center | N16: =COUNTIFS(Box,"center",$K$94:$K$100,1) -> 2 | O16: ENG and TRS
A17: MKT | B17: =$B$6*Wiring!$B$6+$C$6*Wiring!$B$7+$D$6*Wiring!$B$8+$E$6*Wiring!$B$9+$F$6*Wiring!$B$10+$G$6*Wiring!$B$11+$H$6*Wiring!$B$12 -> 0 | C17: =$B$6*Wiring!$C$6+$C$6*Wiring!$C$7+$D$6*Wiring!$C$8+$E$6*Wiring!$C$9+$F$6*Wiring!$C$10+$G$6*Wiring!$C$11+$H$6*Wiring!$C$12 -> 0 | D17: =$B$6*Wiring!$D$6+$C$6*Wiring!$D$7+$D$6*Wiring!$D$8+$E$6*Wiring!$D$9+$F$6*Wiring!$D$10+$G$6*Wiring!$D$11+$H$6*Wiring!$D$12 -> 0 | E17: =$B$6*Wiring!$E$6+$C$6*Wiring!$E$7+$D$6*Wiring!$E$8+$E$6*Wiring!$E$9+$F$6*Wiring!$E$10+$G$6*Wiring!$E$11+$H$6*Wiring!$E$12 -> 5 | F17: =$B$6*Wiring!$F$6+$C$6*Wiring!$F$7+$D$6*Wiring!$F$8+$E$6*Wiring!$F$9+$F$6*Wiring!$F$10+$G$6*Wiring!$F$11+$H$6*Wiring!$F$12 -> 5 | G17: =$B$6*Wiring!$G$6+$C$6*Wiring!$G$7+$D$6*Wiring!$G$8+$E$6*Wiring!$G$9+$F$6*Wiring!$G$10+$G$6*Wiring!$G$11+$H$6*Wiring!$G$12 -> 0 | H17: =$B$6*Wiring!$H$6+$C$6*Wiring!$H$7+$D$6*Wiring!$H$8+$E$6*Wiring!$H$9+$F$6*Wiring!$H$10+$G$6*Wiring!$H$11+$H$6*Wiring!$H$12 -> 0
A18: GOV | B18: =$B$7*Wiring!$B$6+$C$7*Wiring!$B$7+$D$7*Wiring!$B$8+$E$7*Wiring!$B$9+$F$7*Wiring!$B$10+$G$7*Wiring!$B$11+$H$7*Wiring!$B$12 -> 0 | C18: =$B$7*Wiring!$C$6+$C$7*Wiring!$C$7+$D$7*Wiring!$C$8+$E$7*Wiring!$C$9+$F$7*Wiring!$C$10+$G$7*Wiring!$C$11+$H$7*Wiring!$C$12 -> 0 | D18: =$B$7*Wiring!$D$6+$C$7*Wiring!$D$7+$D$7*Wiring!$D$8+$E$7*Wiring!$D$9+$F$7*Wiring!$D$10+$G$7*Wiring!$D$11+$H$7*Wiring!$D$12 -> 0 | E18: =$B$7*Wiring!$E$6+$C$7*Wiring!$E$7+$D$7*Wiring!$E$8+$E$7*Wiring!$E$9+$F$7*Wiring!$E$10+$G$7*Wiring!$E$11+$H$7*Wiring!$E$12 -> 2 | F18: =$B$7*Wiring!$F$6+$C$7*Wiring!$F$7+$D$7*Wiring!$F$8+$E$7*Wiring!$F$9+$F$7*Wiring!$F$10+$G$7*Wiring!$F$11+$H$7*Wiring!$F$12 -> 2 | G18: =$B$7*Wiring!$G$6+$C$7*Wiring!$G$7+$D$7*Wiring!$G$8+$E$7*Wiring!$G$9+$F$7*Wiring!$G$10+$G$7*Wiring!$G$11+$H$7*Wiring!$G$12 -> 2 | H18: =$B$7*Wiring!$H$6+$C$7*Wiring!$H$7+$D$7*Wiring!$H$8+$E$7*Wiring!$H$9+$F$7*Wiring!$H$10+$G$7*Wiring!$H$11+$H$7*Wiring!$H$12 -> 2
A19: MAT | B19: =$B$8*Wiring!$B$6+$C$8*Wiring!$B$7+$D$8*Wiring!$B$8+$E$8*Wiring!$B$9+$F$8*Wiring!$B$10+$G$8*Wiring!$B$11+$H$8*Wiring!$B$12 -> 0 | C19: =$B$8*Wiring!$C$6+$C$8*Wiring!$C$7+$D$8*Wiring!$C$8+$E$8*Wiring!$C$9+$F$8*Wiring!$C$10+$G$8*Wiring!$C$11+$H$8*Wiring!$C$12 -> 0 | D19: =$B$8*Wiring!$D$6+$C$8*Wiring!$D$7+$D$8*Wiring!$D$8+$E$8*Wiring!$D$9+$F$8*Wiring!$D$10+$G$8*Wiring!$D$11+$H$8*Wiring!$D$12 -> 0 | E19: =$B$8*Wiring!$E$6+$C$8*Wiring!$E$7+$D$8*Wiring!$E$8+$E$8*Wiring!$E$9+$F$8*Wiring!$E$10+$G$8*Wiring!$E$11+$H$8*Wiring!$E$12 -> 0 | F19: =$B$8*Wiring!$F$6+$C$8*Wiring!$F$7+$D$8*Wiring!$F$8+$E$8*Wiring!$F$9+$F$8*Wiring!$F$10+$G$8*Wiring!$F$11+$H$8*Wiring!$F$12 -> 0 | G19: =$B$8*Wiring!$G$6+$C$8*Wiring!$G$7+$D$8*Wiring!$G$8+$E$8*Wiring!$G$9+$F$8*Wiring!$G$10+$G$8*Wiring!$G$11+$H$8*Wiring!$G$12 -> 2 | H19: =$B$8*Wiring!$H$6+$C$8*Wiring!$H$7+$D$8*Wiring!$H$8+$E$8*Wiring!$H$9+$F$8*Wiring!$H$10+$G$8*Wiring!$H$11+$H$8*Wiring!$H$12 -> 2
A20: IND | B20: =$B$9*Wiring!$B$6+$C$9*Wiring!$B$7+$D$9*Wiring!$B$8+$E$9*Wiring!$B$9+$F$9*Wiring!$B$10+$G$9*Wiring!$B$11+$H$9*Wiring!$B$12 -> 0 | C20: =$B$9*Wiring!$C$6+$C$9*Wiring!$C$7+$D$9*Wiring!$C$8+$E$9*Wiring!$C$9+$F$9*Wiring!$C$10+$G$9*Wiring!$C$11+$H$9*Wiring!$C$12 -> 0 | D20: =$B$9*Wiring!$D$6+$C$9*Wiring!$D$7+$D$9*Wiring!$D$8+$E$9*Wiring!$D$9+$F$9*Wiring!$D$10+$G$9*Wiring!$D$11+$H$9*Wiring!$D$12 -> 0 | E20: =$B$9*Wiring!$E$6+$C$9*Wiring!$E$7+$D$9*Wiring!$E$8+$E$9*Wiring!$E$9+$F$9*Wiring!$E$10+$G$9*Wiring!$E$11+$H$9*Wiring!$E$12 -> 0 | F20: =$B$9*Wiring!$F$6+$C$9*Wiring!$F$7+$D$9*Wiring!$F$8+$E$9*Wiring!$F$9+$F$9*Wiring!$F$10+$G$9*Wiring!$F$11+$H$9*Wiring!$F$12 -> 0 | G20: =$B$9*Wiring!$G$6+$C$9*Wiring!$G$7+$D$9*Wiring!$G$8+$E$9*Wiring!$G$9+$F$9*Wiring!$G$10+$G$9*Wiring!$G$11+$H$9*Wiring!$G$12 -> 4 | H20: =$B$9*Wiring!$H$6+$C$9*Wiring!$H$7+$D$9*Wiring!$H$8+$E$9*Wiring!$H$9+$F$9*Wiring!$H$10+$G$9*Wiring!$H$11+$H$9*Wiring!$H$12 -> 4 | M20: Loops inside the core: every candidate on its members (Worked Example 9.1, Step 2)
A21: DIG | B21: =$B$10*Wiring!$B$6+$C$10*Wiring!$B$7+$D$10*Wiring!$B$8+$E$10*Wiring!$B$9+$F$10*Wiring!$B$10+$G$10*Wiring!$B$11+$H$10*Wiring!$B$12 -> 0 | C21: =$B$10*Wiring!$C$6+$C$10*Wiring!$C$7+$D$10*Wiring!$C$8+$E$10*Wiring!$C$9+$F$10*Wiring!$C$10+$G$10*Wiring!$C$11+$H$10*Wiring!$C$12 -> 0 | D21: =$B$10*Wiring!$D$6+$C$10*Wiring!$D$7+$D$10*Wiring!$D$8+$E$10*Wiring!$D$9+$F$10*Wiring!$D$10+$G$10*Wiring!$D$11+$H$10*Wiring!$D$12 -> 0 | E21: =$B$10*Wiring!$E$6+$C$10*Wiring!$E$7+$D$10*Wiring!$E$8+$E$10*Wiring!$E$9+$F$10*Wiring!$E$10+$G$10*Wiring!$E$11+$H$10*Wiring!$E$12 -> 0 | F21: =$B$10*Wiring!$F$6+$C$10*Wiring!$F$7+$D$10*Wiring!$F$8+$E$10*Wiring!$F$9+$F$10*Wiring!$F$10+$G$10*Wiring!$F$11+$H$10*Wiring!$F$12 -> 0 | G21: =$B$10*Wiring!$G$6+$C$10*Wiring!$G$7+$D$10*Wiring!$G$8+$E$10*Wiring!$G$9+$F$10*Wiring!$G$10+$G$10*Wiring!$G$11+$H$10*Wiring!$G$12 -> 4 | H21: =$B$10*Wiring!$H$6+$C$10*Wiring!$H$7+$D$10*Wiring!$H$8+$E$10*Wiring!$H$9+$F$10*Wiring!$H$10+$G$10*Wiring!$H$11+$H$10*Wiring!$H$12 -> 4 | M21: Component | O21: Running count of core members
A22: ENG | B22: =$B$11*Wiring!$B$6+$C$11*Wiring!$B$7+$D$11*Wiring!$B$8+$E$11*Wiring!$B$9+$F$11*Wiring!$B$10+$G$11*Wiring!$B$11+$H$11*Wiring!$B$12 -> 0 | C22: =$B$11*Wiring!$C$6+$C$11*Wiring!$C$7+$D$11*Wiring!$C$8+$E$11*Wiring!$C$9+$F$11*Wiring!$C$10+$G$11*Wiring!$C$11+$H$11*Wiring!$C$12 -> 0 | D22: =$B$11*Wiring!$D$6+$C$11*Wiring!$D$7+$D$11*Wiring!$D$8+$E$11*Wiring!$D$9+$F$11*Wiring!$D$10+$G$11*Wiring!$D$11+$H$11*Wiring!$D$12 -> 0 | E22: =$B$11*Wiring!$E$6+$C$11*Wiring!$E$7+$D$11*Wiring!$E$8+$E$11*Wiring!$E$9+$F$11*Wiring!$E$10+$G$11*Wiring!$E$11+$H$11*Wiring!$E$12 -> 4 | F22: =$B$11*Wiring!$F$6+$C$11*Wiring!$F$7+$D$11*Wiring!$F$8+$E$11*Wiring!$F$9+$F$11*Wiring!$F$10+$G$11*Wiring!$F$11+$H$11*Wiring!$F$12 -> 4 | G22: =$B$11*Wiring!$G$6+$C$11*Wiring!$G$7+$D$11*Wiring!$G$8+$E$11*Wiring!$G$9+$F$11*Wiring!$G$10+$G$11*Wiring!$G$11+$H$11*Wiring!$G$12 -> 0 | H22: =$B$11*Wiring!$H$6+$C$11*Wiring!$H$7+$D$11*Wiring!$H$8+$E$11*Wiring!$H$9+$F$11*Wiring!$H$10+$G$11*Wiring!$H$11+$H$11*Wiring!$H$12 -> 0 | M22: MKT | O22: =COUNTIF($K$94:$K$94,1)*$K$94 -> 0
A23: TRS | B23: =$B$12*Wiring!$B$6+$C$12*Wiring!$B$7+$D$12*Wiring!$B$8+$E$12*Wiring!$B$9+$F$12*Wiring!$B$10+$G$12*Wiring!$B$11+$H$12*Wiring!$B$12 -> 0 | C23: =$B$12*Wiring!$C$6+$C$12*Wiring!$C$7+$D$12*Wiring!$C$8+$E$12*Wiring!$C$9+$F$12*Wiring!$C$10+$G$12*Wiring!$C$11+$H$12*Wiring!$C$12 -> 0 | D23: =$B$12*Wiring!$D$6+$C$12*Wiring!$D$7+$D$12*Wiring!$D$8+$E$12*Wiring!$D$9+$F$12*Wiring!$D$10+$G$12*Wiring!$D$11+$H$12*Wiring!$D$12 -> 0 | E23: =$B$12*Wiring!$E$6+$C$12*Wiring!$E$7+$D$12*Wiring!$E$8+$E$12*Wiring!$E$9+$F$12*Wiring!$E$10+$G$12*Wiring!$E$11+$H$12*Wiring!$E$12 -> 4 | F23: =$B$12*Wiring!$F$6+$C$12*Wiring!$F$7+$D$12*Wiring!$F$8+$E$12*Wiring!$F$9+$F$12*Wiring!$F$10+$G$12*Wiring!$F$11+$H$12*Wiring!$F$12 -> 4 | G23: =$B$12*Wiring!$G$6+$C$12*Wiring!$G$7+$D$12*Wiring!$G$8+$E$12*Wiring!$G$9+$F$12*Wiring!$G$10+$G$12*Wiring!$G$11+$H$12*Wiring!$G$12 -> 0 | H23: =$B$12*Wiring!$H$6+$C$12*Wiring!$H$7+$D$12*Wiring!$H$8+$E$12*Wiring!$H$9+$F$12*Wiring!$H$10+$G$12*Wiring!$H$11+$H$12*Wiring!$H$12 -> 0 | M23: GOV | O23: =COUNTIF($K$94:$K$95,1)*$K$95 -> 0
M24: MAT | O24: =COUNTIF($K$94:$K$96,1)*$K$96 -> 0
M25: IND | O25: =COUNTIF($K$94:$K$97,1)*$K$97 -> 1
A26: A^4: routes of 4 steps from the row to the column | M26: DIG | O26: =COUNTIF($K$94:$K$98,1)*$K$98 -> 2
B27: MKT | C27: GOV | D27: MAT | E27: IND | F27: DIG | G27: ENG | H27: TRS | M27: ENG | O27: =COUNTIF($K$94:$K$99,1)*$K$99 -> 3
A28: MKT | B28: =$B$17*Wiring!$B$6+$C$17*Wiring!$B$7+$D$17*Wiring!$B$8+$E$17*Wiring!$B$9+$F$17*Wiring!$B$10+$G$17*Wiring!$B$11+$H$17*Wiring!$B$12 -> 0 | C28: =$B$17*Wiring!$C$6+$C$17*Wiring!$C$7+$D$17*Wiring!$C$8+$E$17*Wiring!$C$9+$F$17*Wiring!$C$10+$G$17*Wiring!$C$11+$H$17*Wiring!$C$12 -> 0 | D28: =$B$17*Wiring!$D$6+$C$17*Wiring!$D$7+$D$17*Wiring!$D$8+$E$17*Wiring!$D$9+$F$17*Wiring!$D$10+$G$17*Wiring!$D$11+$H$17*Wiring!$D$12 -> 0 | E28: =$B$17*Wiring!$E$6+$C$17*Wiring!$E$7+$D$17*Wiring!$E$8+$E$17*Wiring!$E$9+$F$17*Wiring!$E$10+$G$17*Wiring!$E$11+$H$17*Wiring!$E$12 -> 0 | F28: =$B$17*Wiring!$F$6+$C$17*Wiring!$F$7+$D$17*Wiring!$F$8+$E$17*Wiring!$F$9+$F$17*Wiring!$F$10+$G$17*Wiring!$F$11+$H$17*Wiring!$F$12 -> 0 | G28: =$B$17*Wiring!$G$6+$C$17*Wiring!$G$7+$D$17*Wiring!$G$8+$E$17*Wiring!$G$9+$F$17*Wiring!$G$10+$G$17*Wiring!$G$11+$H$17*Wiring!$G$12 -> 10 | H28: =$B$17*Wiring!$H$6+$C$17*Wiring!$H$7+$D$17*Wiring!$H$8+$E$17*Wiring!$H$9+$F$17*Wiring!$H$10+$G$17*Wiring!$H$11+$H$17*Wiring!$H$12 -> 10 | M28: TRS | O28: =COUNTIF($K$94:$K$100,1)*$K$100 -> 4
A29: GOV | B29: =$B$18*Wiring!$B$6+$C$18*Wiring!$B$7+$D$18*Wiring!$B$8+$E$18*Wiring!$B$9+$F$18*Wiring!$B$10+$G$18*Wiring!$B$11+$H$18*Wiring!$B$12 -> 0 | C29: =$B$18*Wiring!$C$6+$C$18*Wiring!$C$7+$D$18*Wiring!$C$8+$E$18*Wiring!$C$9+$F$18*Wiring!$C$10+$G$18*Wiring!$C$11+$H$18*Wiring!$C$12 -> 0 | D29: =$B$18*Wiring!$D$6+$C$18*Wiring!$D$7+$D$18*Wiring!$D$8+$E$18*Wiring!$D$9+$F$18*Wiring!$D$10+$G$18*Wiring!$D$11+$H$18*Wiring!$D$12 -> 0 | E29: =$B$18*Wiring!$E$6+$C$18*Wiring!$E$7+$D$18*Wiring!$E$8+$E$18*Wiring!$E$9+$F$18*Wiring!$E$10+$G$18*Wiring!$E$11+$H$18*Wiring!$E$12 -> 4 | F29: =$B$18*Wiring!$F$6+$C$18*Wiring!$F$7+$D$18*Wiring!$F$8+$E$18*Wiring!$F$9+$F$18*Wiring!$F$10+$G$18*Wiring!$F$11+$H$18*Wiring!$F$12 -> 4 | G29: =$B$18*Wiring!$G$6+$C$18*Wiring!$G$7+$D$18*Wiring!$G$8+$E$18*Wiring!$G$9+$F$18*Wiring!$G$10+$G$18*Wiring!$G$11+$H$18*Wiring!$G$12 -> 4 | H29: =$B$18*Wiring!$H$6+$C$18*Wiring!$H$7+$D$18*Wiring!$H$8+$E$18*Wiring!$H$9+$F$18*Wiring!$H$10+$G$18*Wiring!$H$11+$H$18*Wiring!$H$12 -> 4 | M29: k | N29: k-th member of the core
A30: MAT | B30: =$B$19*Wiring!$B$6+$C$19*Wiring!$B$7+$D$19*Wiring!$B$8+$E$19*Wiring!$B$9+$F$19*Wiring!$B$10+$G$19*Wiring!$B$11+$H$19*Wiring!$B$12 -> 0 | C30: =$B$19*Wiring!$C$6+$C$19*Wiring!$C$7+$D$19*Wiring!$C$8+$E$19*Wiring!$C$9+$F$19*Wiring!$C$10+$G$19*Wiring!$C$11+$H$19*Wiring!$C$12 -> 0 | D30: =$B$19*Wiring!$D$6+$C$19*Wiring!$D$7+$D$19*Wiring!$D$8+$E$19*Wiring!$D$9+$F$19*Wiring!$D$10+$G$19*Wiring!$D$11+$H$19*Wiring!$D$12 -> 0 | E30: =$B$19*Wiring!$E$6+$C$19*Wiring!$E$7+$D$19*Wiring!$E$8+$E$19*Wiring!$E$9+$F$19*Wiring!$E$10+$G$19*Wiring!$E$11+$H$19*Wiring!$E$12 -> 4 | F30: =$B$19*Wiring!$F$6+$C$19*Wiring!$F$7+$D$19*Wiring!$F$8+$E$19*Wiring!$F$9+$F$19*Wiring!$F$10+$G$19*Wiring!$F$11+$H$19*Wiring!$F$12 -> 4 | G30: =$B$19*Wiring!$G$6+$C$19*Wiring!$G$7+$D$19*Wiring!$G$8+$E$19*Wiring!$G$9+$F$19*Wiring!$G$10+$G$19*Wiring!$G$11+$H$19*Wiring!$G$12 -> 0 | H30: =$B$19*Wiring!$H$6+$C$19*Wiring!$H$7+$D$19*Wiring!$H$8+$E$19*Wiring!$H$9+$F$19*Wiring!$H$10+$G$19*Wiring!$H$11+$H$19*Wiring!$H$12 -> 0 | M30: 1 | N30: =INDEX($M$22:$M$28,MATCH(1,$O$22:$O$28,0)) -> IND
A31: IND | B31: =$B$20*Wiring!$B$6+$C$20*Wiring!$B$7+$D$20*Wiring!$B$8+$E$20*Wiring!$B$9+$F$20*Wiring!$B$10+$G$20*Wiring!$B$11+$H$20*Wiring!$B$12 -> 0 | C31: =$B$20*Wiring!$C$6+$C$20*Wiring!$C$7+$D$20*Wiring!$C$8+$E$20*Wiring!$C$9+$F$20*Wiring!$C$10+$G$20*Wiring!$C$11+$H$20*Wiring!$C$12 -> 0 | D31: =$B$20*Wiring!$D$6+$C$20*Wiring!$D$7+$D$20*Wiring!$D$8+$E$20*Wiring!$D$9+$F$20*Wiring!$D$10+$G$20*Wiring!$D$11+$H$20*Wiring!$D$12 -> 0 | E31: =$B$20*Wiring!$E$6+$C$20*Wiring!$E$7+$D$20*Wiring!$E$8+$E$20*Wiring!$E$9+$F$20*Wiring!$E$10+$G$20*Wiring!$E$11+$H$20*Wiring!$E$12 -> 8 | F31: =$B$20*Wiring!$F$6+$C$20*Wiring!$F$7+$D$20*Wiring!$F$8+$E$20*Wiring!$F$9+$F$20*Wiring!$F$10+$G$20*Wiring!$F$11+$H$20*Wiring!$F$12 -> 8 | G31: =$B$20*Wiring!$G$6+$C$20*Wiring!$G$7+$D$20*Wiring!$G$8+$E$20*Wiring!$G$9+$F$20*Wiring!$G$10+$G$20*Wiring!$G$11+$H$20*Wiring!$G$12 -> 0 | H31: =$B$20*Wiring!$H$6+$C$20*Wiring!$H$7+$D$20*Wiring!$H$8+$E$20*Wiring!$H$9+$F$20*Wiring!$H$10+$G$20*Wiring!$H$11+$H$20*Wiring!$H$12 -> 0 | M31: 2 | N31: =INDEX($M$22:$M$28,MATCH(2,$O$22:$O$28,0)) -> DIG
A32: DIG | B32: =$B$21*Wiring!$B$6+$C$21*Wiring!$B$7+$D$21*Wiring!$B$8+$E$21*Wiring!$B$9+$F$21*Wiring!$B$10+$G$21*Wiring!$B$11+$H$21*Wiring!$B$12 -> 0 | C32: =$B$21*Wiring!$C$6+$C$21*Wiring!$C$7+$D$21*Wiring!$C$8+$E$21*Wiring!$C$9+$F$21*Wiring!$C$10+$G$21*Wiring!$C$11+$H$21*Wiring!$C$12 -> 0 | D32: =$B$21*Wiring!$D$6+$C$21*Wiring!$D$7+$D$21*Wiring!$D$8+$E$21*Wiring!$D$9+$F$21*Wiring!$D$10+$G$21*Wiring!$D$11+$H$21*Wiring!$D$12 -> 0 | E32: =$B$21*Wiring!$E$6+$C$21*Wiring!$E$7+$D$21*Wiring!$E$8+$E$21*Wiring!$E$9+$F$21*Wiring!$E$10+$G$21*Wiring!$E$11+$H$21*Wiring!$E$12 -> 8 | F32: =$B$21*Wiring!$F$6+$C$21*Wiring!$F$7+$D$21*Wiring!$F$8+$E$21*Wiring!$F$9+$F$21*Wiring!$F$10+$G$21*Wiring!$F$11+$H$21*Wiring!$F$12 -> 8 | G32: =$B$21*Wiring!$G$6+$C$21*Wiring!$G$7+$D$21*Wiring!$G$8+$E$21*Wiring!$G$9+$F$21*Wiring!$G$10+$G$21*Wiring!$G$11+$H$21*Wiring!$G$12 -> 0 | H32: =$B$21*Wiring!$H$6+$C$21*Wiring!$H$7+$D$21*Wiring!$H$8+$E$21*Wiring!$H$9+$F$21*Wiring!$H$10+$G$21*Wiring!$H$11+$H$21*Wiring!$H$12 -> 0 | M32: 3 | N32: =INDEX($M$22:$M$28,MATCH(3,$O$22:$O$28,0)) -> ENG
A33: ENG | B33: =$B$22*Wiring!$B$6+$C$22*Wiring!$B$7+$D$22*Wiring!$B$8+$E$22*Wiring!$B$9+$F$22*Wiring!$B$10+$G$22*Wiring!$B$11+$H$22*Wiring!$B$12 -> 0 | C33: =$B$22*Wiring!$C$6+$C$22*Wiring!$C$7+$D$22*Wiring!$C$8+$E$22*Wiring!$C$9+$F$22*Wiring!$C$10+$G$22*Wiring!$C$11+$H$22*Wiring!$C$12 -> 0 | D33: =$B$22*Wiring!$D$6+$C$22*Wiring!$D$7+$D$22*Wiring!$D$8+$E$22*Wiring!$D$9+$F$22*Wiring!$D$10+$G$22*Wiring!$D$11+$H$22*Wiring!$D$12 -> 0 | E33: =$B$22*Wiring!$E$6+$C$22*Wiring!$E$7+$D$22*Wiring!$E$8+$E$22*Wiring!$E$9+$F$22*Wiring!$E$10+$G$22*Wiring!$E$11+$H$22*Wiring!$E$12 -> 0 | F33: =$B$22*Wiring!$F$6+$C$22*Wiring!$F$7+$D$22*Wiring!$F$8+$E$22*Wiring!$F$9+$F$22*Wiring!$F$10+$G$22*Wiring!$F$11+$H$22*Wiring!$F$12 -> 0 | G33: =$B$22*Wiring!$G$6+$C$22*Wiring!$G$7+$D$22*Wiring!$G$8+$E$22*Wiring!$G$9+$F$22*Wiring!$G$10+$G$22*Wiring!$G$11+$H$22*Wiring!$G$12 -> 8 | H33: =$B$22*Wiring!$H$6+$C$22*Wiring!$H$7+$D$22*Wiring!$H$8+$E$22*Wiring!$H$9+$F$22*Wiring!$H$10+$G$22*Wiring!$H$11+$H$22*Wiring!$H$12 -> 8 | M33: 4 | N33: =INDEX($M$22:$M$28,MATCH(4,$O$22:$O$28,0)) -> TRS
A34: TRS | B34: =$B$23*Wiring!$B$6+$C$23*Wiring!$B$7+$D$23*Wiring!$B$8+$E$23*Wiring!$B$9+$F$23*Wiring!$B$10+$G$23*Wiring!$B$11+$H$23*Wiring!$B$12 -> 0 | C34: =$B$23*Wiring!$C$6+$C$23*Wiring!$C$7+$D$23*Wiring!$C$8+$E$23*Wiring!$C$9+$F$23*Wiring!$C$10+$G$23*Wiring!$C$11+$H$23*Wiring!$C$12 -> 0 | D34: =$B$23*Wiring!$D$6+$C$23*Wiring!$D$7+$D$23*Wiring!$D$8+$E$23*Wiring!$D$9+$F$23*Wiring!$D$10+$G$23*Wiring!$D$11+$H$23*Wiring!$D$12 -> 0 | E34: =$B$23*Wiring!$E$6+$C$23*Wiring!$E$7+$D$23*Wiring!$E$8+$E$23*Wiring!$E$9+$F$23*Wiring!$E$10+$G$23*Wiring!$E$11+$H$23*Wiring!$E$12 -> 0 | F34: =$B$23*Wiring!$F$6+$C$23*Wiring!$F$7+$D$23*Wiring!$F$8+$E$23*Wiring!$F$9+$F$23*Wiring!$F$10+$G$23*Wiring!$F$11+$H$23*Wiring!$F$12 -> 0 | G34: =$B$23*Wiring!$G$6+$C$23*Wiring!$G$7+$D$23*Wiring!$G$8+$E$23*Wiring!$G$9+$F$23*Wiring!$G$10+$G$23*Wiring!$G$11+$H$23*Wiring!$G$12 -> 8 | H34: =$B$23*Wiring!$H$6+$C$23*Wiring!$H$7+$D$23*Wiring!$H$8+$E$23*Wiring!$H$9+$F$23*Wiring!$H$10+$G$23*Wiring!$H$11+$H$23*Wiring!$H$12 -> 8
M35: Candidate loop | N35: Kind | O35: All its arrows present
M36: =$N$30&" > "&$N$31&" > "&$N$30 -> IND > DIG > IND | N36: two-way | O36: =INDEX(Wiring!$B$6:$H$12,MATCH($N$30,Wiring!$A$6:$A$12,0),MATCH($N$31,Wiring!$B$5:$H$5,0))*INDEX(Wiring!$B$6:$H$12,MATCH($N$31,Wiring!$A$6:$A$12,0),MATCH($N$30,Wiring!$B$5:$H$5,0)) -> 0
A37: A^5: routes of 5 steps from the row to the column | M37: =$N$30&" > "&$N$32&" > "&$N$30 -> IND > ENG > IND | N37: two-way | O37: =INDEX(Wiring!$B$6:$H$12,MATCH($N$30,Wiring!$A$6:$A$12,0),MATCH($N$32,Wiring!$B$5:$H$5,0))*INDEX(Wiring!$B$6:$H$12,MATCH($N$32,Wiring!$A$6:$A$12,0),MATCH($N$30,Wiring!$B$5:$H$5,0)) -> 1
B38: MKT | C38: GOV | D38: MAT | E38: IND | F38: DIG | G38: ENG | H38: TRS | M38: =$N$30&" > "&$N$33&" > "&$N$30 -> IND > TRS > IND | N38: two-way | O38: =INDEX(Wiring!$B$6:$H$12,MATCH($N$30,Wiring!$A$6:$A$12,0),MATCH($N$33,Wiring!$B$5:$H$5,0))*INDEX(Wiring!$B$6:$H$12,MATCH($N$33,Wiring!$A$6:$A$12,0),MATCH($N$30,Wiring!$B$5:$H$5,0)) -> 1
A39: MKT | B39: =$B$28*Wiring!$B$6+$C$28*Wiring!$B$7+$D$28*Wiring!$B$8+$E$28*Wiring!$B$9+$F$28*Wiring!$B$10+$G$28*Wiring!$B$11+$H$28*Wiring!$B$12 -> 0 | C39: =$B$28*Wiring!$C$6+$C$28*Wiring!$C$7+$D$28*Wiring!$C$8+$E$28*Wiring!$C$9+$F$28*Wiring!$C$10+$G$28*Wiring!$C$11+$H$28*Wiring!$C$12 -> 0 | D39: =$B$28*Wiring!$D$6+$C$28*Wiring!$D$7+$D$28*Wiring!$D$8+$E$28*Wiring!$D$9+$F$28*Wiring!$D$10+$G$28*Wiring!$D$11+$H$28*Wiring!$D$12 -> 0 | E39: =$B$28*Wiring!$E$6+$C$28*Wiring!$E$7+$D$28*Wiring!$E$8+$E$28*Wiring!$E$9+$F$28*Wiring!$E$10+$G$28*Wiring!$E$11+$H$28*Wiring!$E$12 -> 20 | F39: =$B$28*Wiring!$F$6+$C$28*Wiring!$F$7+$D$28*Wiring!$F$8+$E$28*Wiring!$F$9+$F$28*Wiring!$F$10+$G$28*Wiring!$F$11+$H$28*Wiring!$F$12 -> 20 | G39: =$B$28*Wiring!$G$6+$C$28*Wiring!$G$7+$D$28*Wiring!$G$8+$E$28*Wiring!$G$9+$F$28*Wiring!$G$10+$G$28*Wiring!$G$11+$H$28*Wiring!$G$12 -> 0 | H39: =$B$28*Wiring!$H$6+$C$28*Wiring!$H$7+$D$28*Wiring!$H$8+$E$28*Wiring!$H$9+$F$28*Wiring!$H$10+$G$28*Wiring!$H$11+$H$28*Wiring!$H$12 -> 0 | M39: =$N$31&" > "&$N$32&" > "&$N$31 -> DIG > ENG > DIG | N39: two-way | O39: =INDEX(Wiring!$B$6:$H$12,MATCH($N$31,Wiring!$A$6:$A$12,0),MATCH($N$32,Wiring!$B$5:$H$5,0))*INDEX(Wiring!$B$6:$H$12,MATCH($N$32,Wiring!$A$6:$A$12,0),MATCH($N$31,Wiring!$B$5:$H$5,0)) -> 1
A40: GOV | B40: =$B$29*Wiring!$B$6+$C$29*Wiring!$B$7+$D$29*Wiring!$B$8+$E$29*Wiring!$B$9+$F$29*Wiring!$B$10+$G$29*Wiring!$B$11+$H$29*Wiring!$B$12 -> 0 | C40: =$B$29*Wiring!$C$6+$C$29*Wiring!$C$7+$D$29*Wiring!$C$8+$E$29*Wiring!$C$9+$F$29*Wiring!$C$10+$G$29*Wiring!$C$11+$H$29*Wiring!$C$12 -> 0 | D40: =$B$29*Wiring!$D$6+$C$29*Wiring!$D$7+$D$29*Wiring!$D$8+$E$29*Wiring!$D$9+$F$29*Wiring!$D$10+$G$29*Wiring!$D$11+$H$29*Wiring!$D$12 -> 0 | E40: =$B$29*Wiring!$E$6+$C$29*Wiring!$E$7+$D$29*Wiring!$E$8+$E$29*Wiring!$E$9+$F$29*Wiring!$E$10+$G$29*Wiring!$E$11+$H$29*Wiring!$E$12 -> 8 | F40: =$B$29*Wiring!$F$6+$C$29*Wiring!$F$7+$D$29*Wiring!$F$8+$E$29*Wiring!$F$9+$F$29*Wiring!$F$10+$G$29*Wiring!$F$11+$H$29*Wiring!$F$12 -> 8 | G40: =$B$29*Wiring!$G$6+$C$29*Wiring!$G$7+$D$29*Wiring!$G$8+$E$29*Wiring!$G$9+$F$29*Wiring!$G$10+$G$29*Wiring!$G$11+$H$29*Wiring!$G$12 -> 8 | H40: =$B$29*Wiring!$H$6+$C$29*Wiring!$H$7+$D$29*Wiring!$H$8+$E$29*Wiring!$H$9+$F$29*Wiring!$H$10+$G$29*Wiring!$H$11+$H$29*Wiring!$H$12 -> 8 | M40: =$N$31&" > "&$N$33&" > "&$N$31 -> DIG > TRS > DIG | N40: two-way | O40: =INDEX(Wiring!$B$6:$H$12,MATCH($N$31,Wiring!$A$6:$A$12,0),MATCH($N$33,Wiring!$B$5:$H$5,0))*INDEX(Wiring!$B$6:$H$12,MATCH($N$33,Wiring!$A$6:$A$12,0),MATCH($N$31,Wiring!$B$5:$H$5,0)) -> 1
A41: MAT | B41: =$B$30*Wiring!$B$6+$C$30*Wiring!$B$7+$D$30*Wiring!$B$8+$E$30*Wiring!$B$9+$F$30*Wiring!$B$10+$G$30*Wiring!$B$11+$H$30*Wiring!$B$12 -> 0 | C41: =$B$30*Wiring!$C$6+$C$30*Wiring!$C$7+$D$30*Wiring!$C$8+$E$30*Wiring!$C$9+$F$30*Wiring!$C$10+$G$30*Wiring!$C$11+$H$30*Wiring!$C$12 -> 0 | D41: =$B$30*Wiring!$D$6+$C$30*Wiring!$D$7+$D$30*Wiring!$D$8+$E$30*Wiring!$D$9+$F$30*Wiring!$D$10+$G$30*Wiring!$D$11+$H$30*Wiring!$D$12 -> 0 | E41: =$B$30*Wiring!$E$6+$C$30*Wiring!$E$7+$D$30*Wiring!$E$8+$E$30*Wiring!$E$9+$F$30*Wiring!$E$10+$G$30*Wiring!$E$11+$H$30*Wiring!$E$12 -> 0 | F41: =$B$30*Wiring!$F$6+$C$30*Wiring!$F$7+$D$30*Wiring!$F$8+$E$30*Wiring!$F$9+$F$30*Wiring!$F$10+$G$30*Wiring!$F$11+$H$30*Wiring!$F$12 -> 0 | G41: =$B$30*Wiring!$G$6+$C$30*Wiring!$G$7+$D$30*Wiring!$G$8+$E$30*Wiring!$G$9+$F$30*Wiring!$G$10+$G$30*Wiring!$G$11+$H$30*Wiring!$G$12 -> 8 | H41: =$B$30*Wiring!$H$6+$C$30*Wiring!$H$7+$D$30*Wiring!$H$8+$E$30*Wiring!$H$9+$F$30*Wiring!$H$10+$G$30*Wiring!$H$11+$H$30*Wiring!$H$12 -> 8 | M41: =$N$32&" > "&$N$33&" > "&$N$32 -> ENG > TRS > ENG | N41: two-way | O41: =INDEX(Wiring!$B$6:$H$12,MATCH($N$32,Wiring!$A$6:$A$12,0),MATCH($N$33,Wiring!$B$5:$H$5,0))*INDEX(Wiring!$B$6:$H$12,MATCH($N$33,Wiring!$A$6:$A$12,0),MATCH($N$32,Wiring!$B$5:$H$5,0)) -> 0
A42: IND | B42: =$B$31*Wiring!$B$6+$C$31*Wiring!$B$7+$D$31*Wiring!$B$8+$E$31*Wiring!$B$9+$F$31*Wiring!$B$10+$G$31*Wiring!$B$11+$H$31*Wiring!$B$12 -> 0 | C42: =$B$31*Wiring!$C$6+$C$31*Wiring!$C$7+$D$31*Wiring!$C$8+$E$31*Wiring!$C$9+$F$31*Wiring!$C$10+$G$31*Wiring!$C$11+$H$31*Wiring!$C$12 -> 0 | D42: =$B$31*Wiring!$D$6+$C$31*Wiring!$D$7+$D$31*Wiring!$D$8+$E$31*Wiring!$D$9+$F$31*Wiring!$D$10+$G$31*Wiring!$D$11+$H$31*Wiring!$D$12 -> 0 | E42: =$B$31*Wiring!$E$6+$C$31*Wiring!$E$7+$D$31*Wiring!$E$8+$E$31*Wiring!$E$9+$F$31*Wiring!$E$10+$G$31*Wiring!$E$11+$H$31*Wiring!$E$12 -> 0 | F42: =$B$31*Wiring!$F$6+$C$31*Wiring!$F$7+$D$31*Wiring!$F$8+$E$31*Wiring!$F$9+$F$31*Wiring!$F$10+$G$31*Wiring!$F$11+$H$31*Wiring!$F$12 -> 0 | G42: =$B$31*Wiring!$G$6+$C$31*Wiring!$G$7+$D$31*Wiring!$G$8+$E$31*Wiring!$G$9+$F$31*Wiring!$G$10+$G$31*Wiring!$G$11+$H$31*Wiring!$G$12 -> 16 | H42: =$B$31*Wiring!$H$6+$C$31*Wiring!$H$7+$D$31*Wiring!$H$8+$E$31*Wiring!$H$9+$F$31*Wiring!$H$10+$G$31*Wiring!$H$11+$H$31*Wiring!$H$12 -> 16 | M42: =$N$30&" > "&$N$31&" > "&$N$32&" > "&$N$30 -> IND > DIG > ENG > IND | N42: three members | O42: =INDEX(Wiring!$B$6:$H$12,MATCH($N$30,Wiring!$A$6:$A$12,0),MATCH($N$31,Wiring!$B$5:$H$5,0))*INDEX(Wiring!$B$6:$H$12,MATCH($N$31,Wiring!$A$6:$A$12,0),MATCH($N$32,Wiring!$B$5:$H$5,0))*INDEX(Wiring!$B$6:$H$12,MATCH($N$32,Wiring!$A$6:$A$12,0),MATCH($N$30,Wiring!$B$5:$H$5,0)) -> 0
A43: DIG | B43: =$B$32*Wiring!$B$6+$C$32*Wiring!$B$7+$D$32*Wiring!$B$8+$E$32*Wiring!$B$9+$F$32*Wiring!$B$10+$G$32*Wiring!$B$11+$H$32*Wiring!$B$12 -> 0 | C43: =$B$32*Wiring!$C$6+$C$32*Wiring!$C$7+$D$32*Wiring!$C$8+$E$32*Wiring!$C$9+$F$32*Wiring!$C$10+$G$32*Wiring!$C$11+$H$32*Wiring!$C$12 -> 0 | D43: =$B$32*Wiring!$D$6+$C$32*Wiring!$D$7+$D$32*Wiring!$D$8+$E$32*Wiring!$D$9+$F$32*Wiring!$D$10+$G$32*Wiring!$D$11+$H$32*Wiring!$D$12 -> 0 | E43: =$B$32*Wiring!$E$6+$C$32*Wiring!$E$7+$D$32*Wiring!$E$8+$E$32*Wiring!$E$9+$F$32*Wiring!$E$10+$G$32*Wiring!$E$11+$H$32*Wiring!$E$12 -> 0 | F43: =$B$32*Wiring!$F$6+$C$32*Wiring!$F$7+$D$32*Wiring!$F$8+$E$32*Wiring!$F$9+$F$32*Wiring!$F$10+$G$32*Wiring!$F$11+$H$32*Wiring!$F$12 -> 0 | G43: =$B$32*Wiring!$G$6+$C$32*Wiring!$G$7+$D$32*Wiring!$G$8+$E$32*Wiring!$G$9+$F$32*Wiring!$G$10+$G$32*Wiring!$G$11+$H$32*Wiring!$G$12 -> 16 | H43: =$B$32*Wiring!$H$6+$C$32*Wiring!$H$7+$D$32*Wiring!$H$8+$E$32*Wiring!$H$9+$F$32*Wiring!$H$10+$G$32*Wiring!$H$11+$H$32*Wiring!$H$12 -> 16 | M43: =$N$30&" > "&$N$31&" > "&$N$33&" > "&$N$30 -> IND > DIG > TRS > IND | N43: three members | O43: =INDEX(Wiring!$B$6:$H$12,MATCH($N$30,Wiring!$A$6:$A$12,0),MATCH($N$31,Wiring!$B$5:$H$5,0))*INDEX(Wiring!$B$6:$H$12,MATCH($N$31,Wiring!$A$6:$A$12,0),MATCH($N$33,Wiring!$B$5:$H$5,0))*INDEX(Wiring!$B$6:$H$12,MATCH($N$33,Wiring!$A$6:$A$12,0),MATCH($N$30,Wiring!$B$5:$H$5,0)) -> 0
A44: ENG | B44: =$B$33*Wiring!$B$6+$C$33*Wiring!$B$7+$D$33*Wiring!$B$8+$E$33*Wiring!$B$9+$F$33*Wiring!$B$10+$G$33*Wiring!$B$11+$H$33*Wiring!$B$12 -> 0 | C44: =$B$33*Wiring!$C$6+$C$33*Wiring!$C$7+$D$33*Wiring!$C$8+$E$33*Wiring!$C$9+$F$33*Wiring!$C$10+$G$33*Wiring!$C$11+$H$33*Wiring!$C$12 -> 0 | D44: =$B$33*Wiring!$D$6+$C$33*Wiring!$D$7+$D$33*Wiring!$D$8+$E$33*Wiring!$D$9+$F$33*Wiring!$D$10+$G$33*Wiring!$D$11+$H$33*Wiring!$D$12 -> 0 | E44: =$B$33*Wiring!$E$6+$C$33*Wiring!$E$7+$D$33*Wiring!$E$8+$E$33*Wiring!$E$9+$F$33*Wiring!$E$10+$G$33*Wiring!$E$11+$H$33*Wiring!$E$12 -> 16 | F44: =$B$33*Wiring!$F$6+$C$33*Wiring!$F$7+$D$33*Wiring!$F$8+$E$33*Wiring!$F$9+$F$33*Wiring!$F$10+$G$33*Wiring!$F$11+$H$33*Wiring!$F$12 -> 16 | G44: =$B$33*Wiring!$G$6+$C$33*Wiring!$G$7+$D$33*Wiring!$G$8+$E$33*Wiring!$G$9+$F$33*Wiring!$G$10+$G$33*Wiring!$G$11+$H$33*Wiring!$G$12 -> 0 | H44: =$B$33*Wiring!$H$6+$C$33*Wiring!$H$7+$D$33*Wiring!$H$8+$E$33*Wiring!$H$9+$F$33*Wiring!$H$10+$G$33*Wiring!$H$11+$H$33*Wiring!$H$12 -> 0 | M44: =$N$30&" > "&$N$32&" > "&$N$33&" > "&$N$30 -> IND > ENG > TRS > IND | N44: three members | O44: =INDEX(Wiring!$B$6:$H$12,MATCH($N$30,Wiring!$A$6:$A$12,0),MATCH($N$32,Wiring!$B$5:$H$5,0))*INDEX(Wiring!$B$6:$H$12,MATCH($N$32,Wiring!$A$6:$A$12,0),MATCH($N$33,Wiring!$B$5:$H$5,0))*INDEX(Wiring!$B$6:$H$12,MATCH($N$33,Wiring!$A$6:$A$12,0),MATCH($N$30,Wiring!$B$5:$H$5,0)) -> 0
A45: TRS | B45: =$B$34*Wiring!$B$6+$C$34*Wiring!$B$7+$D$34*Wiring!$B$8+$E$34*Wiring!$B$9+$F$34*Wiring!$B$10+$G$34*Wiring!$B$11+$H$34*Wiring!$B$12 -> 0 | C45: =$B$34*Wiring!$C$6+$C$34*Wiring!$C$7+$D$34*Wiring!$C$8+$E$34*Wiring!$C$9+$F$34*Wiring!$C$10+$G$34*Wiring!$C$11+$H$34*Wiring!$C$12 -> 0 | D45: =$B$34*Wiring!$D$6+$C$34*Wiring!$D$7+$D$34*Wiring!$D$8+$E$34*Wiring!$D$9+$F$34*Wiring!$D$10+$G$34*Wiring!$D$11+$H$34*Wiring!$D$12 -> 0 | E45: =$B$34*Wiring!$E$6+$C$34*Wiring!$E$7+$D$34*Wiring!$E$8+$E$34*Wiring!$E$9+$F$34*Wiring!$E$10+$G$34*Wiring!$E$11+$H$34*Wiring!$E$12 -> 16 | F45: =$B$34*Wiring!$F$6+$C$34*Wiring!$F$7+$D$34*Wiring!$F$8+$E$34*Wiring!$F$9+$F$34*Wiring!$F$10+$G$34*Wiring!$F$11+$H$34*Wiring!$F$12 -> 16 | G45: =$B$34*Wiring!$G$6+$C$34*Wiring!$G$7+$D$34*Wiring!$G$8+$E$34*Wiring!$G$9+$F$34*Wiring!$G$10+$G$34*Wiring!$G$11+$H$34*Wiring!$G$12 -> 0 | H45: =$B$34*Wiring!$H$6+$C$34*Wiring!$H$7+$D$34*Wiring!$H$8+$E$34*Wiring!$H$9+$F$34*Wiring!$H$10+$G$34*Wiring!$H$11+$H$34*Wiring!$H$12 -> 0 | M45: =$N$31&" > "&$N$32&" > "&$N$33&" > "&$N$31 -> DIG > ENG > TRS > DIG | N45: three members | O45: =INDEX(Wiring!$B$6:$H$12,MATCH($N$31,Wiring!$A$6:$A$12,0),MATCH($N$32,Wiring!$B$5:$H$5,0))*INDEX(Wiring!$B$6:$H$12,MATCH($N$32,Wiring!$A$6:$A$12,0),MATCH($N$33,Wiring!$B$5:$H$5,0))*INDEX(Wiring!$B$6:$H$12,MATCH($N$33,Wiring!$A$6:$A$12,0),MATCH($N$31,Wiring!$B$5:$H$5,0)) -> 0
M46: =$N$30&" > "&$N$32&" > "&$N$31&" > "&$N$30 -> IND > ENG > DIG > IND | N46: three members | O46: =INDEX(Wiring!$B$6:$H$12,MATCH($N$30,Wiring!$A$6:$A$12,0),MATCH($N$32,Wiring!$B$5:$H$5,0))*INDEX(Wiring!$B$6:$H$12,MATCH($N$32,Wiring!$A$6:$A$12,0),MATCH($N$31,Wiring!$B$5:$H$5,0))*INDEX(Wiring!$B$6:$H$12,MATCH($N$31,Wiring!$A$6:$A$12,0),MATCH($N$30,Wiring!$B$5:$H$5,0)) -> 0
M47: =$N$30&" > "&$N$33&" > "&$N$31&" > "&$N$30 -> IND > TRS > DIG > IND | N47: three members | O47: =INDEX(Wiring!$B$6:$H$12,MATCH($N$30,Wiring!$A$6:$A$12,0),MATCH($N$33,Wiring!$B$5:$H$5,0))*INDEX(Wiring!$B$6:$H$12,MATCH($N$33,Wiring!$A$6:$A$12,0),MATCH($N$31,Wiring!$B$5:$H$5,0))*INDEX(Wiring!$B$6:$H$12,MATCH($N$31,Wiring!$A$6:$A$12,0),MATCH($N$30,Wiring!$B$5:$H$5,0)) -> 0
A48: A^6: routes of 6 steps from the row to the column | M48: =$N$30&" > "&$N$33&" > "&$N$32&" > "&$N$30 -> IND > TRS > ENG > IND | N48: three members | O48: =INDEX(Wiring!$B$6:$H$12,MATCH($N$30,Wiring!$A$6:$A$12,0),MATCH($N$33,Wiring!$B$5:$H$5,0))*INDEX(Wiring!$B$6:$H$12,MATCH($N$33,Wiring!$A$6:$A$12,0),MATCH($N$32,Wiring!$B$5:$H$5,0))*INDEX(Wiring!$B$6:$H$12,MATCH($N$32,Wiring!$A$6:$A$12,0),MATCH($N$30,Wiring!$B$5:$H$5,0)) -> 0
B49: MKT | C49: GOV | D49: MAT | E49: IND | F49: DIG | G49: ENG | H49: TRS | M49: =$N$31&" > "&$N$33&" > "&$N$32&" > "&$N$31 -> DIG > TRS > ENG > DIG | N49: three members | O49: =INDEX(Wiring!$B$6:$H$12,MATCH($N$31,Wiring!$A$6:$A$12,0),MATCH($N$33,Wiring!$B$5:$H$5,0))*INDEX(Wiring!$B$6:$H$12,MATCH($N$33,Wiring!$A$6:$A$12,0),MATCH($N$32,Wiring!$B$5:$H$5,0))*INDEX(Wiring!$B$6:$H$12,MATCH($N$32,Wiring!$A$6:$A$12,0),MATCH($N$31,Wiring!$B$5:$H$5,0)) -> 0
A50: MKT | B50: =$B$39*Wiring!$B$6+$C$39*Wiring!$B$7+$D$39*Wiring!$B$8+$E$39*Wiring!$B$9+$F$39*Wiring!$B$10+$G$39*Wiring!$B$11+$H$39*Wiring!$B$12 -> 0 | C50: =$B$39*Wiring!$C$6+$C$39*Wiring!$C$7+$D$39*Wiring!$C$8+$E$39*Wiring!$C$9+$F$39*Wiring!$C$10+$G$39*Wiring!$C$11+$H$39*Wiring!$C$12 -> 0 | D50: =$B$39*Wiring!$D$6+$C$39*Wiring!$D$7+$D$39*Wiring!$D$8+$E$39*Wiring!$D$9+$F$39*Wiring!$D$10+$G$39*Wiring!$D$11+$H$39*Wiring!$D$12 -> 0 | E50: =$B$39*Wiring!$E$6+$C$39*Wiring!$E$7+$D$39*Wiring!$E$8+$E$39*Wiring!$E$9+$F$39*Wiring!$E$10+$G$39*Wiring!$E$11+$H$39*Wiring!$E$12 -> 0 | F50: =$B$39*Wiring!$F$6+$C$39*Wiring!$F$7+$D$39*Wiring!$F$8+$E$39*Wiring!$F$9+$F$39*Wiring!$F$10+$G$39*Wiring!$F$11+$H$39*Wiring!$F$12 -> 0 | G50: =$B$39*Wiring!$G$6+$C$39*Wiring!$G$7+$D$39*Wiring!$G$8+$E$39*Wiring!$G$9+$F$39*Wiring!$G$10+$G$39*Wiring!$G$11+$H$39*Wiring!$G$12 -> 40 | H50: =$B$39*Wiring!$H$6+$C$39*Wiring!$H$7+$D$39*Wiring!$H$8+$E$39*Wiring!$H$9+$F$39*Wiring!$H$10+$G$39*Wiring!$H$11+$H$39*Wiring!$H$12 -> 40 | M50: =$N$30&" > "&$N$31&" > "&$N$32&" > "&$N$33&" > "&$N$30 -> IND > DIG > ENG > TRS > IND | N50: four members | O50: =INDEX(Wiring!$B$6:$H$12,MATCH($N$30,Wiring!$A$6:$A$12,0),MATCH($N$31,Wiring!$B$5:$H$5,0))*INDEX(Wiring!$B$6:$H$12,MATCH($N$31,Wiring!$A$6:$A$12,0),MATCH($N$32,Wiring!$B$5:$H$5,0))*INDEX(Wiring!$B$6:$H$12,MATCH($N$32,Wiring!$A$6:$A$12,0),MATCH($N$33,Wiring!$B$5:$H$5,0))*INDEX(Wiring!$B$6:$H$12,MATCH($N$33,Wiring!$A$6:$A$12,0),MATCH($N$30,Wiring!$B$5:$H$5,0)) -> 0
A51: GOV | B51: =$B$40*Wiring!$B$6+$C$40*Wiring!$B$7+$D$40*Wiring!$B$8+$E$40*Wiring!$B$9+$F$40*Wiring!$B$10+$G$40*Wiring!$B$11+$H$40*Wiring!$B$12 -> 0 | C51: =$B$40*Wiring!$C$6+$C$40*Wiring!$C$7+$D$40*Wiring!$C$8+$E$40*Wiring!$C$9+$F$40*Wiring!$C$10+$G$40*Wiring!$C$11+$H$40*Wiring!$C$12 -> 0 | D51: =$B$40*Wiring!$D$6+$C$40*Wiring!$D$7+$D$40*Wiring!$D$8+$E$40*Wiring!$D$9+$F$40*Wiring!$D$10+$G$40*Wiring!$D$11+$H$40*Wiring!$D$12 -> 0 | E51: =$B$40*Wiring!$E$6+$C$40*Wiring!$E$7+$D$40*Wiring!$E$8+$E$40*Wiring!$E$9+$F$40*Wiring!$E$10+$G$40*Wiring!$E$11+$H$40*Wiring!$E$12 -> 16 | F51: =$B$40*Wiring!$F$6+$C$40*Wiring!$F$7+$D$40*Wiring!$F$8+$E$40*Wiring!$F$9+$F$40*Wiring!$F$10+$G$40*Wiring!$F$11+$H$40*Wiring!$F$12 -> 16 | G51: =$B$40*Wiring!$G$6+$C$40*Wiring!$G$7+$D$40*Wiring!$G$8+$E$40*Wiring!$G$9+$F$40*Wiring!$G$10+$G$40*Wiring!$G$11+$H$40*Wiring!$G$12 -> 16 | H51: =$B$40*Wiring!$H$6+$C$40*Wiring!$H$7+$D$40*Wiring!$H$8+$E$40*Wiring!$H$9+$F$40*Wiring!$H$10+$G$40*Wiring!$H$11+$H$40*Wiring!$H$12 -> 16 | M51: =$N$30&" > "&$N$31&" > "&$N$33&" > "&$N$32&" > "&$N$30 -> IND > DIG > TRS > ENG > IND | N51: four members | O51: =INDEX(Wiring!$B$6:$H$12,MATCH($N$30,Wiring!$A$6:$A$12,0),MATCH($N$31,Wiring!$B$5:$H$5,0))*INDEX(Wiring!$B$6:$H$12,MATCH($N$31,Wiring!$A$6:$A$12,0),MATCH($N$33,Wiring!$B$5:$H$5,0))*INDEX(Wiring!$B$6:$H$12,MATCH($N$33,Wiring!$A$6:$A$12,0),MATCH($N$32,Wiring!$B$5:$H$5,0))*INDEX(Wiring!$B$6:$H$12,MATCH($N$32,Wiring!$A$6:$A$12,0),MATCH($N$30,Wiring!$B$5:$H$5,0)) -> 0
A52: MAT | B52: =$B$41*Wiring!$B$6+$C$41*Wiring!$B$7+$D$41*Wiring!$B$8+$E$41*Wiring!$B$9+$F$41*Wiring!$B$10+$G$41*Wiring!$B$11+$H$41*Wiring!$B$12 -> 0 | C52: =$B$41*Wiring!$C$6+$C$41*Wiring!$C$7+$D$41*Wiring!$C$8+$E$41*Wiring!$C$9+$F$41*Wiring!$C$10+$G$41*Wiring!$C$11+$H$41*Wiring!$C$12 -> 0 | D52: =$B$41*Wiring!$D$6+$C$41*Wiring!$D$7+$D$41*Wiring!$D$8+$E$41*Wiring!$D$9+$F$41*Wiring!$D$10+$G$41*Wiring!$D$11+$H$41*Wiring!$D$12 -> 0 | E52: =$B$41*Wiring!$E$6+$C$41*Wiring!$E$7+$D$41*Wiring!$E$8+$E$41*Wiring!$E$9+$F$41*Wiring!$E$10+$G$41*Wiring!$E$11+$H$41*Wiring!$E$12 -> 16 | F52: =$B$41*Wiring!$F$6+$C$41*Wiring!$F$7+$D$41*Wiring!$F$8+$E$41*Wiring!$F$9+$F$41*Wiring!$F$10+$G$41*Wiring!$F$11+$H$41*Wiring!$F$12 -> 16 | G52: =$B$41*Wiring!$G$6+$C$41*Wiring!$G$7+$D$41*Wiring!$G$8+$E$41*Wiring!$G$9+$F$41*Wiring!$G$10+$G$41*Wiring!$G$11+$H$41*Wiring!$G$12 -> 0 | H52: =$B$41*Wiring!$H$6+$C$41*Wiring!$H$7+$D$41*Wiring!$H$8+$E$41*Wiring!$H$9+$F$41*Wiring!$H$10+$G$41*Wiring!$H$11+$H$41*Wiring!$H$12 -> 0 | M52: =$N$30&" > "&$N$32&" > "&$N$31&" > "&$N$33&" > "&$N$30 -> IND > ENG > DIG > TRS > IND | N52: four members | O52: =INDEX(Wiring!$B$6:$H$12,MATCH($N$30,Wiring!$A$6:$A$12,0),MATCH($N$32,Wiring!$B$5:$H$5,0))*INDEX(Wiring!$B$6:$H$12,MATCH($N$32,Wiring!$A$6:$A$12,0),MATCH($N$31,Wiring!$B$5:$H$5,0))*INDEX(Wiring!$B$6:$H$12,MATCH($N$31,Wiring!$A$6:$A$12,0),MATCH($N$33,Wiring!$B$5:$H$5,0))*INDEX(Wiring!$B$6:$H$12,MATCH($N$33,Wiring!$A$6:$A$12,0),MATCH($N$30,Wiring!$B$5:$H$5,0)) -> 1
A53: IND | B53: =$B$42*Wiring!$B$6+$C$42*Wiring!$B$7+$D$42*Wiring!$B$8+$E$42*Wiring!$B$9+$F$42*Wiring!$B$10+$G$42*Wiring!$B$11+$H$42*Wiring!$B$12 -> 0 | C53: =$B$42*Wiring!$C$6+$C$42*Wiring!$C$7+$D$42*Wiring!$C$8+$E$42*Wiring!$C$9+$F$42*Wiring!$C$10+$G$42*Wiring!$C$11+$H$42*Wiring!$C$12 -> 0 | D53: =$B$42*Wiring!$D$6+$C$42*Wiring!$D$7+$D$42*Wiring!$D$8+$E$42*Wiring!$D$9+$F$42*Wiring!$D$10+$G$42*Wiring!$D$11+$H$42*Wiring!$D$12 -> 0 | E53: =$B$42*Wiring!$E$6+$C$42*Wiring!$E$7+$D$42*Wiring!$E$8+$E$42*Wiring!$E$9+$F$42*Wiring!$E$10+$G$42*Wiring!$E$11+$H$42*Wiring!$E$12 -> 32 | F53: =$B$42*Wiring!$F$6+$C$42*Wiring!$F$7+$D$42*Wiring!$F$8+$E$42*Wiring!$F$9+$F$42*Wiring!$F$10+$G$42*Wiring!$F$11+$H$42*Wiring!$F$12 -> 32 | G53: =$B$42*Wiring!$G$6+$C$42*Wiring!$G$7+$D$42*Wiring!$G$8+$E$42*Wiring!$G$9+$F$42*Wiring!$G$10+$G$42*Wiring!$G$11+$H$42*Wiring!$G$12 -> 0 | H53: =$B$42*Wiring!$H$6+$C$42*Wiring!$H$7+$D$42*Wiring!$H$8+$E$42*Wiring!$H$9+$F$42*Wiring!$H$10+$G$42*Wiring!$H$11+$H$42*Wiring!$H$12 -> 0 | M53: =$N$30&" > "&$N$32&" > "&$N$33&" > "&$N$31&" > "&$N$30 -> IND > ENG > TRS > DIG > IND | N53: four members | O53: =INDEX(Wiring!$B$6:$H$12,MATCH($N$30,Wiring!$A$6:$A$12,0),MATCH($N$32,Wiring!$B$5:$H$5,0))*INDEX(Wiring!$B$6:$H$12,MATCH($N$32,Wiring!$A$6:$A$12,0),MATCH($N$33,Wiring!$B$5:$H$5,0))*INDEX(Wiring!$B$6:$H$12,MATCH($N$33,Wiring!$A$6:$A$12,0),MATCH($N$31,Wiring!$B$5:$H$5,0))*INDEX(Wiring!$B$6:$H$12,MATCH($N$31,Wiring!$A$6:$A$12,0),MATCH($N$30,Wiring!$B$5:$H$5,0)) -> 0
A54: DIG | B54: =$B$43*Wiring!$B$6+$C$43*Wiring!$B$7+$D$43*Wiring!$B$8+$E$43*Wiring!$B$9+$F$43*Wiring!$B$10+$G$43*Wiring!$B$11+$H$43*Wiring!$B$12 -> 0 | C54: =$B$43*Wiring!$C$6+$C$43*Wiring!$C$7+$D$43*Wiring!$C$8+$E$43*Wiring!$C$9+$F$43*Wiring!$C$10+$G$43*Wiring!$C$11+$H$43*Wiring!$C$12 -> 0 | D54: =$B$43*Wiring!$D$6+$C$43*Wiring!$D$7+$D$43*Wiring!$D$8+$E$43*Wiring!$D$9+$F$43*Wiring!$D$10+$G$43*Wiring!$D$11+$H$43*Wiring!$D$12 -> 0 | E54: =$B$43*Wiring!$E$6+$C$43*Wiring!$E$7+$D$43*Wiring!$E$8+$E$43*Wiring!$E$9+$F$43*Wiring!$E$10+$G$43*Wiring!$E$11+$H$43*Wiring!$E$12 -> 32 | F54: =$B$43*Wiring!$F$6+$C$43*Wiring!$F$7+$D$43*Wiring!$F$8+$E$43*Wiring!$F$9+$F$43*Wiring!$F$10+$G$43*Wiring!$F$11+$H$43*Wiring!$F$12 -> 32 | G54: =$B$43*Wiring!$G$6+$C$43*Wiring!$G$7+$D$43*Wiring!$G$8+$E$43*Wiring!$G$9+$F$43*Wiring!$G$10+$G$43*Wiring!$G$11+$H$43*Wiring!$G$12 -> 0 | H54: =$B$43*Wiring!$H$6+$C$43*Wiring!$H$7+$D$43*Wiring!$H$8+$E$43*Wiring!$H$9+$F$43*Wiring!$H$10+$G$43*Wiring!$H$11+$H$43*Wiring!$H$12 -> 0 | M54: =$N$30&" > "&$N$33&" > "&$N$31&" > "&$N$32&" > "&$N$30 -> IND > TRS > DIG > ENG > IND | N54: four members | O54: =INDEX(Wiring!$B$6:$H$12,MATCH($N$30,Wiring!$A$6:$A$12,0),MATCH($N$33,Wiring!$B$5:$H$5,0))*INDEX(Wiring!$B$6:$H$12,MATCH($N$33,Wiring!$A$6:$A$12,0),MATCH($N$31,Wiring!$B$5:$H$5,0))*INDEX(Wiring!$B$6:$H$12,MATCH($N$31,Wiring!$A$6:$A$12,0),MATCH($N$32,Wiring!$B$5:$H$5,0))*INDEX(Wiring!$B$6:$H$12,MATCH($N$32,Wiring!$A$6:$A$12,0),MATCH($N$30,Wiring!$B$5:$H$5,0)) -> 1
A55: ENG | B55: =$B$44*Wiring!$B$6+$C$44*Wiring!$B$7+$D$44*Wiring!$B$8+$E$44*Wiring!$B$9+$F$44*Wiring!$B$10+$G$44*Wiring!$B$11+$H$44*Wiring!$B$12 -> 0 | C55: =$B$44*Wiring!$C$6+$C$44*Wiring!$C$7+$D$44*Wiring!$C$8+$E$44*Wiring!$C$9+$F$44*Wiring!$C$10+$G$44*Wiring!$C$11+$H$44*Wiring!$C$12 -> 0 | D55: =$B$44*Wiring!$D$6+$C$44*Wiring!$D$7+$D$44*Wiring!$D$8+$E$44*Wiring!$D$9+$F$44*Wiring!$D$10+$G$44*Wiring!$D$11+$H$44*Wiring!$D$12 -> 0 | E55: =$B$44*Wiring!$E$6+$C$44*Wiring!$E$7+$D$44*Wiring!$E$8+$E$44*Wiring!$E$9+$F$44*Wiring!$E$10+$G$44*Wiring!$E$11+$H$44*Wiring!$E$12 -> 0 | F55: =$B$44*Wiring!$F$6+$C$44*Wiring!$F$7+$D$44*Wiring!$F$8+$E$44*Wiring!$F$9+$F$44*Wiring!$F$10+$G$44*Wiring!$F$11+$H$44*Wiring!$F$12 -> 0 | G55: =$B$44*Wiring!$G$6+$C$44*Wiring!$G$7+$D$44*Wiring!$G$8+$E$44*Wiring!$G$9+$F$44*Wiring!$G$10+$G$44*Wiring!$G$11+$H$44*Wiring!$G$12 -> 32 | H55: =$B$44*Wiring!$H$6+$C$44*Wiring!$H$7+$D$44*Wiring!$H$8+$E$44*Wiring!$H$9+$F$44*Wiring!$H$10+$G$44*Wiring!$H$11+$H$44*Wiring!$H$12 -> 32 | M55: =$N$30&" > "&$N$33&" > "&$N$32&" > "&$N$31&" > "&$N$30 -> IND > TRS > ENG > DIG > IND | N55: four members | O55: =INDEX(Wiring!$B$6:$H$12,MATCH($N$30,Wiring!$A$6:$A$12,0),MATCH($N$33,Wiring!$B$5:$H$5,0))*INDEX(Wiring!$B$6:$H$12,MATCH($N$33,Wiring!$A$6:$A$12,0),MATCH($N$32,Wiring!$B$5:$H$5,0))*INDEX(Wiring!$B$6:$H$12,MATCH($N$32,Wiring!$A$6:$A$12,0),MATCH($N$31,Wiring!$B$5:$H$5,0))*INDEX(Wiring!$B$6:$H$12,MATCH($N$31,Wiring!$A$6:$A$12,0),MATCH($N$30,Wiring!$B$5:$H$5,0)) -> 0
A56: TRS | B56: =$B$45*Wiring!$B$6+$C$45*Wiring!$B$7+$D$45*Wiring!$B$8+$E$45*Wiring!$B$9+$F$45*Wiring!$B$10+$G$45*Wiring!$B$11+$H$45*Wiring!$B$12 -> 0 | C56: =$B$45*Wiring!$C$6+$C$45*Wiring!$C$7+$D$45*Wiring!$C$8+$E$45*Wiring!$C$9+$F$45*Wiring!$C$10+$G$45*Wiring!$C$11+$H$45*Wiring!$C$12 -> 0 | D56: =$B$45*Wiring!$D$6+$C$45*Wiring!$D$7+$D$45*Wiring!$D$8+$E$45*Wiring!$D$9+$F$45*Wiring!$D$10+$G$45*Wiring!$D$11+$H$45*Wiring!$D$12 -> 0 | E56: =$B$45*Wiring!$E$6+$C$45*Wiring!$E$7+$D$45*Wiring!$E$8+$E$45*Wiring!$E$9+$F$45*Wiring!$E$10+$G$45*Wiring!$E$11+$H$45*Wiring!$E$12 -> 0 | F56: =$B$45*Wiring!$F$6+$C$45*Wiring!$F$7+$D$45*Wiring!$F$8+$E$45*Wiring!$F$9+$F$45*Wiring!$F$10+$G$45*Wiring!$F$11+$H$45*Wiring!$F$12 -> 0 | G56: =$B$45*Wiring!$G$6+$C$45*Wiring!$G$7+$D$45*Wiring!$G$8+$E$45*Wiring!$G$9+$F$45*Wiring!$G$10+$G$45*Wiring!$G$11+$H$45*Wiring!$G$12 -> 32 | H56: =$B$45*Wiring!$H$6+$C$45*Wiring!$H$7+$D$45*Wiring!$H$8+$E$45*Wiring!$H$9+$F$45*Wiring!$H$10+$G$45*Wiring!$H$11+$H$45*Wiring!$H$12 -> 32
M57: Two-way relationships in the core | N57: =SUMIF($N$36:$N$55,"two-way",$O$36:$O$55) -> 4 | O57: four
M58: Loops through three members | N58: =SUMIF($N$36:$N$55,"three members",$O$36:$O$55) -> 0 | O58: none
A59: A^7: routes of 7 steps from the row to the column | M59: Loops through all four members | N59: =SUMIF($N$36:$N$55,"four members",$O$36:$O$55) -> 2 | O59: two
B60: MKT | C60: GOV | D60: MAT | E60: IND | F60: DIG | G60: ENG | H60: TRS | M60: Directed loops in the core | N60: =SUM($N$57:$N$59) -> 6 | O60: Worked Example 9.1: six
A61: MKT | B61: =$B$50*Wiring!$B$6+$C$50*Wiring!$B$7+$D$50*Wiring!$B$8+$E$50*Wiring!$B$9+$F$50*Wiring!$B$10+$G$50*Wiring!$B$11+$H$50*Wiring!$B$12 -> 0 | C61: =$B$50*Wiring!$C$6+$C$50*Wiring!$C$7+$D$50*Wiring!$C$8+$E$50*Wiring!$C$9+$F$50*Wiring!$C$10+$G$50*Wiring!$C$11+$H$50*Wiring!$C$12 -> 0 | D61: =$B$50*Wiring!$D$6+$C$50*Wiring!$D$7+$D$50*Wiring!$D$8+$E$50*Wiring!$D$9+$F$50*Wiring!$D$10+$G$50*Wiring!$D$11+$H$50*Wiring!$D$12 -> 0 | E61: =$B$50*Wiring!$E$6+$C$50*Wiring!$E$7+$D$50*Wiring!$E$8+$E$50*Wiring!$E$9+$F$50*Wiring!$E$10+$G$50*Wiring!$E$11+$H$50*Wiring!$E$12 -> 80 | F61: =$B$50*Wiring!$F$6+$C$50*Wiring!$F$7+$D$50*Wiring!$F$8+$E$50*Wiring!$F$9+$F$50*Wiring!$F$10+$G$50*Wiring!$F$11+$H$50*Wiring!$F$12 -> 80 | G61: =$B$50*Wiring!$G$6+$C$50*Wiring!$G$7+$D$50*Wiring!$G$8+$E$50*Wiring!$G$9+$F$50*Wiring!$G$10+$G$50*Wiring!$G$11+$H$50*Wiring!$G$12 -> 0 | H61: =$B$50*Wiring!$H$6+$C$50*Wiring!$H$7+$D$50*Wiring!$H$8+$E$50*Wiring!$H$9+$F$50*Wiring!$H$10+$G$50*Wiring!$H$11+$H$50*Wiring!$H$12 -> 0
A62: GOV | B62: =$B$51*Wiring!$B$6+$C$51*Wiring!$B$7+$D$51*Wiring!$B$8+$E$51*Wiring!$B$9+$F$51*Wiring!$B$10+$G$51*Wiring!$B$11+$H$51*Wiring!$B$12 -> 0 | C62: =$B$51*Wiring!$C$6+$C$51*Wiring!$C$7+$D$51*Wiring!$C$8+$E$51*Wiring!$C$9+$F$51*Wiring!$C$10+$G$51*Wiring!$C$11+$H$51*Wiring!$C$12 -> 0 | D62: =$B$51*Wiring!$D$6+$C$51*Wiring!$D$7+$D$51*Wiring!$D$8+$E$51*Wiring!$D$9+$F$51*Wiring!$D$10+$G$51*Wiring!$D$11+$H$51*Wiring!$D$12 -> 0 | E62: =$B$51*Wiring!$E$6+$C$51*Wiring!$E$7+$D$51*Wiring!$E$8+$E$51*Wiring!$E$9+$F$51*Wiring!$E$10+$G$51*Wiring!$E$11+$H$51*Wiring!$E$12 -> 32 | F62: =$B$51*Wiring!$F$6+$C$51*Wiring!$F$7+$D$51*Wiring!$F$8+$E$51*Wiring!$F$9+$F$51*Wiring!$F$10+$G$51*Wiring!$F$11+$H$51*Wiring!$F$12 -> 32 | G62: =$B$51*Wiring!$G$6+$C$51*Wiring!$G$7+$D$51*Wiring!$G$8+$E$51*Wiring!$G$9+$F$51*Wiring!$G$10+$G$51*Wiring!$G$11+$H$51*Wiring!$G$12 -> 32 | H62: =$B$51*Wiring!$H$6+$C$51*Wiring!$H$7+$D$51*Wiring!$H$8+$E$51*Wiring!$H$9+$F$51*Wiring!$H$10+$G$51*Wiring!$H$11+$H$51*Wiring!$H$12 -> 32 | M62: Online Appendix 9.B.1: offsetting channels inside a core (a' = u, b' = -u, v' = a + b, u' = u + c v)
A63: MAT | B63: =$B$52*Wiring!$B$6+$C$52*Wiring!$B$7+$D$52*Wiring!$B$8+$E$52*Wiring!$B$9+$F$52*Wiring!$B$10+$G$52*Wiring!$B$11+$H$52*Wiring!$B$12 -> 0 | C63: =$B$52*Wiring!$C$6+$C$52*Wiring!$C$7+$D$52*Wiring!$C$8+$E$52*Wiring!$C$9+$F$52*Wiring!$C$10+$G$52*Wiring!$C$11+$H$52*Wiring!$C$12 -> 0 | D63: =$B$52*Wiring!$D$6+$C$52*Wiring!$D$7+$D$52*Wiring!$D$8+$E$52*Wiring!$D$9+$F$52*Wiring!$D$10+$G$52*Wiring!$D$11+$H$52*Wiring!$D$12 -> 0 | E63: =$B$52*Wiring!$E$6+$C$52*Wiring!$E$7+$D$52*Wiring!$E$8+$E$52*Wiring!$E$9+$F$52*Wiring!$E$10+$G$52*Wiring!$E$11+$H$52*Wiring!$E$12 -> 0 | F63: =$B$52*Wiring!$F$6+$C$52*Wiring!$F$7+$D$52*Wiring!$F$8+$E$52*Wiring!$F$9+$F$52*Wiring!$F$10+$G$52*Wiring!$F$11+$H$52*Wiring!$F$12 -> 0 | G63: =$B$52*Wiring!$G$6+$C$52*Wiring!$G$7+$D$52*Wiring!$G$8+$E$52*Wiring!$G$9+$F$52*Wiring!$G$10+$G$52*Wiring!$G$11+$H$52*Wiring!$G$12 -> 32 | H63: =$B$52*Wiring!$H$6+$C$52*Wiring!$H$7+$D$52*Wiring!$H$8+$E$52*Wiring!$H$9+$F$52*Wiring!$H$10+$G$52*Wiring!$H$11+$H$52*Wiring!$H$12 -> 32 | M63: c | N63: 0.5
A64: IND | B64: =$B$53*Wiring!$B$6+$C$53*Wiring!$B$7+$D$53*Wiring!$B$8+$E$53*Wiring!$B$9+$F$53*Wiring!$B$10+$G$53*Wiring!$B$11+$H$53*Wiring!$B$12 -> 0 | C64: =$B$53*Wiring!$C$6+$C$53*Wiring!$C$7+$D$53*Wiring!$C$8+$E$53*Wiring!$C$9+$F$53*Wiring!$C$10+$G$53*Wiring!$C$11+$H$53*Wiring!$C$12 -> 0 | D64: =$B$53*Wiring!$D$6+$C$53*Wiring!$D$7+$D$53*Wiring!$D$8+$E$53*Wiring!$D$9+$F$53*Wiring!$D$10+$G$53*Wiring!$D$11+$H$53*Wiring!$D$12 -> 0 | E64: =$B$53*Wiring!$E$6+$C$53*Wiring!$E$7+$D$53*Wiring!$E$8+$E$53*Wiring!$E$9+$F$53*Wiring!$E$10+$G$53*Wiring!$E$11+$H$53*Wiring!$E$12 -> 0 | F64: =$B$53*Wiring!$F$6+$C$53*Wiring!$F$7+$D$53*Wiring!$F$8+$E$53*Wiring!$F$9+$F$53*Wiring!$F$10+$G$53*Wiring!$F$11+$H$53*Wiring!$F$12 -> 0 | G64: =$B$53*Wiring!$G$6+$C$53*Wiring!$G$7+$D$53*Wiring!$G$8+$E$53*Wiring!$G$9+$F$53*Wiring!$G$10+$G$53*Wiring!$G$11+$H$53*Wiring!$G$12 -> 64 | H64: =$B$53*Wiring!$H$6+$C$53*Wiring!$H$7+$D$53*Wiring!$H$8+$E$53*Wiring!$H$9+$F$53*Wiring!$H$10+$G$53*Wiring!$H$11+$H$53*Wiring!$H$12 -> 64 | M64: quarter | N64: a | O64: b | P64: v | Q64: u | R64: a (rule +1) | S64: b | T64: v | U64: u | V64: |change in v| | W64: u (profit +1) | X64: v
A65: DIG | B65: =$B$54*Wiring!$B$6+$C$54*Wiring!$B$7+$D$54*Wiring!$B$8+$E$54*Wiring!$B$9+$F$54*Wiring!$B$10+$G$54*Wiring!$B$11+$H$54*Wiring!$B$12 -> 0 | C65: =$B$54*Wiring!$C$6+$C$54*Wiring!$C$7+$D$54*Wiring!$C$8+$E$54*Wiring!$C$9+$F$54*Wiring!$C$10+$G$54*Wiring!$C$11+$H$54*Wiring!$C$12 -> 0 | D65: =$B$54*Wiring!$D$6+$C$54*Wiring!$D$7+$D$54*Wiring!$D$8+$E$54*Wiring!$D$9+$F$54*Wiring!$D$10+$G$54*Wiring!$D$11+$H$54*Wiring!$D$12 -> 0 | E65: =$B$54*Wiring!$E$6+$C$54*Wiring!$E$7+$D$54*Wiring!$E$8+$E$54*Wiring!$E$9+$F$54*Wiring!$E$10+$G$54*Wiring!$E$11+$H$54*Wiring!$E$12 -> 0 | F65: =$B$54*Wiring!$F$6+$C$54*Wiring!$F$7+$D$54*Wiring!$F$8+$E$54*Wiring!$F$9+$F$54*Wiring!$F$10+$G$54*Wiring!$F$11+$H$54*Wiring!$F$12 -> 0 | G65: =$B$54*Wiring!$G$6+$C$54*Wiring!$G$7+$D$54*Wiring!$G$8+$E$54*Wiring!$G$9+$F$54*Wiring!$G$10+$G$54*Wiring!$G$11+$H$54*Wiring!$G$12 -> 64 | H65: =$B$54*Wiring!$H$6+$C$54*Wiring!$H$7+$D$54*Wiring!$H$8+$E$54*Wiring!$H$9+$F$54*Wiring!$H$10+$G$54*Wiring!$H$11+$H$54*Wiring!$H$12 -> 64 | M65: 0 | N65: 1 | O65: 2 | P65: 3 | Q65: 4 | R65: 1 | S65: 2 | T65: 3 | U65: 5 | V65: =ABS(T65-P65) -> 0 | W65: =Q65 -> 4 | X65: =P65+1 -> 4
A66: ENG | B66: =$B$55*Wiring!$B$6+$C$55*Wiring!$B$7+$D$55*Wiring!$B$8+$E$55*Wiring!$B$9+$F$55*Wiring!$B$10+$G$55*Wiring!$B$11+$H$55*Wiring!$B$12 -> 0 | C66: =$B$55*Wiring!$C$6+$C$55*Wiring!$C$7+$D$55*Wiring!$C$8+$E$55*Wiring!$C$9+$F$55*Wiring!$C$10+$G$55*Wiring!$C$11+$H$55*Wiring!$C$12 -> 0 | D66: =$B$55*Wiring!$D$6+$C$55*Wiring!$D$7+$D$55*Wiring!$D$8+$E$55*Wiring!$D$9+$F$55*Wiring!$D$10+$G$55*Wiring!$D$11+$H$55*Wiring!$D$12 -> 0 | E66: =$B$55*Wiring!$E$6+$C$55*Wiring!$E$7+$D$55*Wiring!$E$8+$E$55*Wiring!$E$9+$F$55*Wiring!$E$10+$G$55*Wiring!$E$11+$H$55*Wiring!$E$12 -> 64 | F66: =$B$55*Wiring!$F$6+$C$55*Wiring!$F$7+$D$55*Wiring!$F$8+$E$55*Wiring!$F$9+$F$55*Wiring!$F$10+$G$55*Wiring!$F$11+$H$55*Wiring!$F$12 -> 64 | G66: =$B$55*Wiring!$G$6+$C$55*Wiring!$G$7+$D$55*Wiring!$G$8+$E$55*Wiring!$G$9+$F$55*Wiring!$G$10+$G$55*Wiring!$G$11+$H$55*Wiring!$G$12 -> 0 | H66: =$B$55*Wiring!$H$6+$C$55*Wiring!$H$7+$D$55*Wiring!$H$8+$E$55*Wiring!$H$9+$F$55*Wiring!$H$10+$G$55*Wiring!$H$11+$H$55*Wiring!$H$12 -> 0 | M66: 1 | N66: =Q65 -> 4 | O66: =-Q65 -> -4 | P66: =N65+O65 -> 3 | Q66: =Q65+$N$63*P65 -> 5.5 | R66: =U65 -> 5 | S66: =-U65 -> -5 | T66: =R65+S65 -> 3 | U66: =U65+$N$63*T65 -> 6.5 | V66: =ABS(T66-P66) -> 0 | W66: =W65+$N$63*X65 -> 6
A67: TRS | B67: =$B$56*Wiring!$B$6+$C$56*Wiring!$B$7+$D$56*Wiring!$B$8+$E$56*Wiring!$B$9+$F$56*Wiring!$B$10+$G$56*Wiring!$B$11+$H$56*Wiring!$B$12 -> 0 | C67: =$B$56*Wiring!$C$6+$C$56*Wiring!$C$7+$D$56*Wiring!$C$8+$E$56*Wiring!$C$9+$F$56*Wiring!$C$10+$G$56*Wiring!$C$11+$H$56*Wiring!$C$12 -> 0 | D67: =$B$56*Wiring!$D$6+$C$56*Wiring!$D$7+$D$56*Wiring!$D$8+$E$56*Wiring!$D$9+$F$56*Wiring!$D$10+$G$56*Wiring!$D$11+$H$56*Wiring!$D$12 -> 0 | E67: =$B$56*Wiring!$E$6+$C$56*Wiring!$E$7+$D$56*Wiring!$E$8+$E$56*Wiring!$E$9+$F$56*Wiring!$E$10+$G$56*Wiring!$E$11+$H$56*Wiring!$E$12 -> 64 | F67: =$B$56*Wiring!$F$6+$C$56*Wiring!$F$7+$D$56*Wiring!$F$8+$E$56*Wiring!$F$9+$F$56*Wiring!$F$10+$G$56*Wiring!$F$11+$H$56*Wiring!$F$12 -> 64 | G67: =$B$56*Wiring!$G$6+$C$56*Wiring!$G$7+$D$56*Wiring!$G$8+$E$56*Wiring!$G$9+$F$56*Wiring!$G$10+$G$56*Wiring!$G$11+$H$56*Wiring!$G$12 -> 0 | H67: =$B$56*Wiring!$H$6+$C$56*Wiring!$H$7+$D$56*Wiring!$H$8+$E$56*Wiring!$H$9+$F$56*Wiring!$H$10+$G$56*Wiring!$H$11+$H$56*Wiring!$H$12 -> 0 | M67: 2 | N67: =Q66 -> 5.5 | O67: =-Q66 -> -5.5 | P67: =N66+O66 -> 0 | Q67: =Q66+$N$63*P66 -> 7 | R67: =U66 -> 6.5 | S67: =-U66 -> -6.5 | T67: =R66+S66 -> 0 | U67: =U66+$N$63*T66 -> 8 | V67: =ABS(T67-P67) -> 0
M68: 3 | N68: =Q67 -> 7 | O68: =-Q67 -> -7 | P68: =N67+O67 -> 0 | Q68: =Q67+$N$63*P67 -> 7 | R68: =U67 -> 8 | S68: =-U67 -> -8 | T68: =R67+S67 -> 0 | U68: =U67+$N$63*T67 -> 8 | V68: =ABS(T68-P68) -> 0
M69: 4 | N69: =Q68 -> 7 | O69: =-Q68 -> -7 | P69: =N68+O68 -> 0 | Q69: =Q68+$N$63*P68 -> 7 | R69: =U68 -> 8 | S69: =-U68 -> -8 | T69: =R68+S68 -> 0 | U69: =U68+$N$63*T68 -> 8 | V69: =ABS(T69-P69) -> 0
A70: A^8: routes of 8 steps from the row to the column | M70: 5 | N70: =Q69 -> 7 | O70: =-Q69 -> -7 | P70: =N69+O69 -> 0 | Q70: =Q69+$N$63*P69 -> 7 | R70: =U69 -> 8 | S70: =-U69 -> -8 | T70: =R69+S69 -> 0 | U70: =U69+$N$63*T69 -> 8 | V70: =ABS(T70-P70) -> 0
B71: MKT | C71: GOV | D71: MAT | E71: IND | F71: DIG | G71: ENG | H71: TRS | M71: 6 | N71: =Q70 -> 7 | O71: =-Q70 -> -7 | P71: =N70+O70 -> 0 | Q71: =Q70+$N$63*P70 -> 7 | R71: =U70 -> 8 | S71: =-U70 -> -8 | T71: =R70+S70 -> 0 | U71: =U70+$N$63*T70 -> 8 | V71: =ABS(T71-P71) -> 0
A72: MKT | B72: =$B$61*Wiring!$B$6+$C$61*Wiring!$B$7+$D$61*Wiring!$B$8+$E$61*Wiring!$B$9+$F$61*Wiring!$B$10+$G$61*Wiring!$B$11+$H$61*Wiring!$B$12 -> 0 | C72: =$B$61*Wiring!$C$6+$C$61*Wiring!$C$7+$D$61*Wiring!$C$8+$E$61*Wiring!$C$9+$F$61*Wiring!$C$10+$G$61*Wiring!$C$11+$H$61*Wiring!$C$12 -> 0 | D72: =$B$61*Wiring!$D$6+$C$61*Wiring!$D$7+$D$61*Wiring!$D$8+$E$61*Wiring!$D$9+$F$61*Wiring!$D$10+$G$61*Wiring!$D$11+$H$61*Wiring!$D$12 -> 0 | E72: =$B$61*Wiring!$E$6+$C$61*Wiring!$E$7+$D$61*Wiring!$E$8+$E$61*Wiring!$E$9+$F$61*Wiring!$E$10+$G$61*Wiring!$E$11+$H$61*Wiring!$E$12 -> 0 | F72: =$B$61*Wiring!$F$6+$C$61*Wiring!$F$7+$D$61*Wiring!$F$8+$E$61*Wiring!$F$9+$F$61*Wiring!$F$10+$G$61*Wiring!$F$11+$H$61*Wiring!$F$12 -> 0 | G72: =$B$61*Wiring!$G$6+$C$61*Wiring!$G$7+$D$61*Wiring!$G$8+$E$61*Wiring!$G$9+$F$61*Wiring!$G$10+$G$61*Wiring!$G$11+$H$61*Wiring!$G$12 -> 160 | H72: =$B$61*Wiring!$H$6+$C$61*Wiring!$H$7+$D$61*Wiring!$H$8+$E$61*Wiring!$H$9+$F$61*Wiring!$H$10+$G$61*Wiring!$H$11+$H$61*Wiring!$H$12 -> 160 | M72: 7 | N72: =Q71 -> 7 | O72: =-Q71 -> -7 | P72: =N71+O71 -> 0 | Q72: =Q71+$N$63*P71 -> 7 | R72: =U71 -> 8 | S72: =-U71 -> -8 | T72: =R71+S71 -> 0 | U72: =U71+$N$63*T71 -> 8 | V72: =ABS(T72-P72) -> 0
A73: GOV | B73: =$B$62*Wiring!$B$6+$C$62*Wiring!$B$7+$D$62*Wiring!$B$8+$E$62*Wiring!$B$9+$F$62*Wiring!$B$10+$G$62*Wiring!$B$11+$H$62*Wiring!$B$12 -> 0 | C73: =$B$62*Wiring!$C$6+$C$62*Wiring!$C$7+$D$62*Wiring!$C$8+$E$62*Wiring!$C$9+$F$62*Wiring!$C$10+$G$62*Wiring!$C$11+$H$62*Wiring!$C$12 -> 0 | D73: =$B$62*Wiring!$D$6+$C$62*Wiring!$D$7+$D$62*Wiring!$D$8+$E$62*Wiring!$D$9+$F$62*Wiring!$D$10+$G$62*Wiring!$D$11+$H$62*Wiring!$D$12 -> 0 | E73: =$B$62*Wiring!$E$6+$C$62*Wiring!$E$7+$D$62*Wiring!$E$8+$E$62*Wiring!$E$9+$F$62*Wiring!$E$10+$G$62*Wiring!$E$11+$H$62*Wiring!$E$12 -> 64 | F73: =$B$62*Wiring!$F$6+$C$62*Wiring!$F$7+$D$62*Wiring!$F$8+$E$62*Wiring!$F$9+$F$62*Wiring!$F$10+$G$62*Wiring!$F$11+$H$62*Wiring!$F$12 -> 64 | G73: =$B$62*Wiring!$G$6+$C$62*Wiring!$G$7+$D$62*Wiring!$G$8+$E$62*Wiring!$G$9+$F$62*Wiring!$G$10+$G$62*Wiring!$G$11+$H$62*Wiring!$G$12 -> 64 | H73: =$B$62*Wiring!$H$6+$C$62*Wiring!$H$7+$D$62*Wiring!$H$8+$E$62*Wiring!$H$9+$F$62*Wiring!$H$10+$G$62*Wiring!$H$11+$H$62*Wiring!$H$12 -> 64 | M73: 8 | N73: =Q72 -> 7 | O73: =-Q72 -> -7 | P73: =N72+O72 -> 0 | Q73: =Q72+$N$63*P72 -> 7 | R73: =U72 -> 8 | S73: =-U72 -> -8 | T73: =R72+S72 -> 0 | U73: =U72+$N$63*T72 -> 8 | V73: =ABS(T73-P73) -> 0
A74: MAT | B74: =$B$63*Wiring!$B$6+$C$63*Wiring!$B$7+$D$63*Wiring!$B$8+$E$63*Wiring!$B$9+$F$63*Wiring!$B$10+$G$63*Wiring!$B$11+$H$63*Wiring!$B$12 -> 0 | C74: =$B$63*Wiring!$C$6+$C$63*Wiring!$C$7+$D$63*Wiring!$C$8+$E$63*Wiring!$C$9+$F$63*Wiring!$C$10+$G$63*Wiring!$C$11+$H$63*Wiring!$C$12 -> 0 | D74: =$B$63*Wiring!$D$6+$C$63*Wiring!$D$7+$D$63*Wiring!$D$8+$E$63*Wiring!$D$9+$F$63*Wiring!$D$10+$G$63*Wiring!$D$11+$H$63*Wiring!$D$12 -> 0 | E74: =$B$63*Wiring!$E$6+$C$63*Wiring!$E$7+$D$63*Wiring!$E$8+$E$63*Wiring!$E$9+$F$63*Wiring!$E$10+$G$63*Wiring!$E$11+$H$63*Wiring!$E$12 -> 64 | F74: =$B$63*Wiring!$F$6+$C$63*Wiring!$F$7+$D$63*Wiring!$F$8+$E$63*Wiring!$F$9+$F$63*Wiring!$F$10+$G$63*Wiring!$F$11+$H$63*Wiring!$F$12 -> 64 | G74: =$B$63*Wiring!$G$6+$C$63*Wiring!$G$7+$D$63*Wiring!$G$8+$E$63*Wiring!$G$9+$F$63*Wiring!$G$10+$G$63*Wiring!$G$11+$H$63*Wiring!$G$12 -> 0 | H74: =$B$63*Wiring!$H$6+$C$63*Wiring!$H$7+$D$63*Wiring!$H$8+$E$63*Wiring!$H$9+$F$63*Wiring!$H$10+$G$63*Wiring!$H$11+$H$63*Wiring!$H$12 -> 0 | M74: 9 | N74: =Q73 -> 7 | O74: =-Q73 -> -7 | P74: =N73+O73 -> 0 | Q74: =Q73+$N$63*P73 -> 7 | R74: =U73 -> 8 | S74: =-U73 -> -8 | T74: =R73+S73 -> 0 | U74: =U73+$N$63*T73 -> 8 | V74: =ABS(T74-P74) -> 0
A75: IND | B75: =$B$64*Wiring!$B$6+$C$64*Wiring!$B$7+$D$64*Wiring!$B$8+$E$64*Wiring!$B$9+$F$64*Wiring!$B$10+$G$64*Wiring!$B$11+$H$64*Wiring!$B$12 -> 0 | C75: =$B$64*Wiring!$C$6+$C$64*Wiring!$C$7+$D$64*Wiring!$C$8+$E$64*Wiring!$C$9+$F$64*Wiring!$C$10+$G$64*Wiring!$C$11+$H$64*Wiring!$C$12 -> 0 | D75: =$B$64*Wiring!$D$6+$C$64*Wiring!$D$7+$D$64*Wiring!$D$8+$E$64*Wiring!$D$9+$F$64*Wiring!$D$10+$G$64*Wiring!$D$11+$H$64*Wiring!$D$12 -> 0 | E75: =$B$64*Wiring!$E$6+$C$64*Wiring!$E$7+$D$64*Wiring!$E$8+$E$64*Wiring!$E$9+$F$64*Wiring!$E$10+$G$64*Wiring!$E$11+$H$64*Wiring!$E$12 -> 128 | F75: =$B$64*Wiring!$F$6+$C$64*Wiring!$F$7+$D$64*Wiring!$F$8+$E$64*Wiring!$F$9+$F$64*Wiring!$F$10+$G$64*Wiring!$F$11+$H$64*Wiring!$F$12 -> 128 | G75: =$B$64*Wiring!$G$6+$C$64*Wiring!$G$7+$D$64*Wiring!$G$8+$E$64*Wiring!$G$9+$F$64*Wiring!$G$10+$G$64*Wiring!$G$11+$H$64*Wiring!$G$12 -> 0 | H75: =$B$64*Wiring!$H$6+$C$64*Wiring!$H$7+$D$64*Wiring!$H$8+$E$64*Wiring!$H$9+$F$64*Wiring!$H$10+$G$64*Wiring!$H$11+$H$64*Wiring!$H$12 -> 0 | M75: 10 | N75: =Q74 -> 7 | O75: =-Q74 -> -7 | P75: =N74+O74 -> 0 | Q75: =Q74+$N$63*P74 -> 7 | R75: =U74 -> 8 | S75: =-U74 -> -8 | T75: =R74+S74 -> 0 | U75: =U74+$N$63*T74 -> 8 | V75: =ABS(T75-P75) -> 0
A76: DIG | B76: =$B$65*Wiring!$B$6+$C$65*Wiring!$B$7+$D$65*Wiring!$B$8+$E$65*Wiring!$B$9+$F$65*Wiring!$B$10+$G$65*Wiring!$B$11+$H$65*Wiring!$B$12 -> 0 | C76: =$B$65*Wiring!$C$6+$C$65*Wiring!$C$7+$D$65*Wiring!$C$8+$E$65*Wiring!$C$9+$F$65*Wiring!$C$10+$G$65*Wiring!$C$11+$H$65*Wiring!$C$12 -> 0 | D76: =$B$65*Wiring!$D$6+$C$65*Wiring!$D$7+$D$65*Wiring!$D$8+$E$65*Wiring!$D$9+$F$65*Wiring!$D$10+$G$65*Wiring!$D$11+$H$65*Wiring!$D$12 -> 0 | E76: =$B$65*Wiring!$E$6+$C$65*Wiring!$E$7+$D$65*Wiring!$E$8+$E$65*Wiring!$E$9+$F$65*Wiring!$E$10+$G$65*Wiring!$E$11+$H$65*Wiring!$E$12 -> 128 | F76: =$B$65*Wiring!$F$6+$C$65*Wiring!$F$7+$D$65*Wiring!$F$8+$E$65*Wiring!$F$9+$F$65*Wiring!$F$10+$G$65*Wiring!$F$11+$H$65*Wiring!$F$12 -> 128 | G76: =$B$65*Wiring!$G$6+$C$65*Wiring!$G$7+$D$65*Wiring!$G$8+$E$65*Wiring!$G$9+$F$65*Wiring!$G$10+$G$65*Wiring!$G$11+$H$65*Wiring!$G$12 -> 0 | H76: =$B$65*Wiring!$H$6+$C$65*Wiring!$H$7+$D$65*Wiring!$H$8+$E$65*Wiring!$H$9+$F$65*Wiring!$H$10+$G$65*Wiring!$H$11+$H$65*Wiring!$H$12 -> 0 | M76: 11 | N76: =Q75 -> 7 | O76: =-Q75 -> -7 | P76: =N75+O75 -> 0 | Q76: =Q75+$N$63*P75 -> 7 | R76: =U75 -> 8 | S76: =-U75 -> -8 | T76: =R75+S75 -> 0 | U76: =U75+$N$63*T75 -> 8 | V76: =ABS(T76-P76) -> 0
A77: ENG | B77: =$B$66*Wiring!$B$6+$C$66*Wiring!$B$7+$D$66*Wiring!$B$8+$E$66*Wiring!$B$9+$F$66*Wiring!$B$10+$G$66*Wiring!$B$11+$H$66*Wiring!$B$12 -> 0 | C77: =$B$66*Wiring!$C$6+$C$66*Wiring!$C$7+$D$66*Wiring!$C$8+$E$66*Wiring!$C$9+$F$66*Wiring!$C$10+$G$66*Wiring!$C$11+$H$66*Wiring!$C$12 -> 0 | D77: =$B$66*Wiring!$D$6+$C$66*Wiring!$D$7+$D$66*Wiring!$D$8+$E$66*Wiring!$D$9+$F$66*Wiring!$D$10+$G$66*Wiring!$D$11+$H$66*Wiring!$D$12 -> 0 | E77: =$B$66*Wiring!$E$6+$C$66*Wiring!$E$7+$D$66*Wiring!$E$8+$E$66*Wiring!$E$9+$F$66*Wiring!$E$10+$G$66*Wiring!$E$11+$H$66*Wiring!$E$12 -> 0 | F77: =$B$66*Wiring!$F$6+$C$66*Wiring!$F$7+$D$66*Wiring!$F$8+$E$66*Wiring!$F$9+$F$66*Wiring!$F$10+$G$66*Wiring!$F$11+$H$66*Wiring!$F$12 -> 0 | G77: =$B$66*Wiring!$G$6+$C$66*Wiring!$G$7+$D$66*Wiring!$G$8+$E$66*Wiring!$G$9+$F$66*Wiring!$G$10+$G$66*Wiring!$G$11+$H$66*Wiring!$G$12 -> 128 | H77: =$B$66*Wiring!$H$6+$C$66*Wiring!$H$7+$D$66*Wiring!$H$8+$E$66*Wiring!$H$9+$F$66*Wiring!$H$10+$G$66*Wiring!$H$11+$H$66*Wiring!$H$12 -> 128 | M77: 12 | N77: =Q76 -> 7 | O77: =-Q76 -> -7 | P77: =N76+O76 -> 0 | Q77: =Q76+$N$63*P76 -> 7 | R77: =U76 -> 8 | S77: =-U76 -> -8 | T77: =R76+S76 -> 0 | U77: =U76+$N$63*T76 -> 8 | V77: =ABS(T77-P77) -> 0
A78: TRS | B78: =$B$67*Wiring!$B$6+$C$67*Wiring!$B$7+$D$67*Wiring!$B$8+$E$67*Wiring!$B$9+$F$67*Wiring!$B$10+$G$67*Wiring!$B$11+$H$67*Wiring!$B$12 -> 0 | C78: =$B$67*Wiring!$C$6+$C$67*Wiring!$C$7+$D$67*Wiring!$C$8+$E$67*Wiring!$C$9+$F$67*Wiring!$C$10+$G$67*Wiring!$C$11+$H$67*Wiring!$C$12 -> 0 | D78: =$B$67*Wiring!$D$6+$C$67*Wiring!$D$7+$D$67*Wiring!$D$8+$E$67*Wiring!$D$9+$F$67*Wiring!$D$10+$G$67*Wiring!$D$11+$H$67*Wiring!$D$12 -> 0 | E78: =$B$67*Wiring!$E$6+$C$67*Wiring!$E$7+$D$67*Wiring!$E$8+$E$67*Wiring!$E$9+$F$67*Wiring!$E$10+$G$67*Wiring!$E$11+$H$67*Wiring!$E$12 -> 0 | F78: =$B$67*Wiring!$F$6+$C$67*Wiring!$F$7+$D$67*Wiring!$F$8+$E$67*Wiring!$F$9+$F$67*Wiring!$F$10+$G$67*Wiring!$F$11+$H$67*Wiring!$F$12 -> 0 | G78: =$B$67*Wiring!$G$6+$C$67*Wiring!$G$7+$D$67*Wiring!$G$8+$E$67*Wiring!$G$9+$F$67*Wiring!$G$10+$G$67*Wiring!$G$11+$H$67*Wiring!$G$12 -> 128 | H78: =$B$67*Wiring!$H$6+$C$67*Wiring!$H$7+$D$67*Wiring!$H$8+$E$67*Wiring!$H$9+$F$67*Wiring!$H$10+$G$67*Wiring!$H$11+$H$67*Wiring!$H$12 -> 128
M79: Largest change in consolidated profit after the rule rises by 1 | N79: =MAX(V65:V77) -> 0 | O79: none, ever
M80: Rise in next quarter's rule after consolidated profit rises by 1 | N80: =W66-Q66 -> 0.5 | O80: c
A81: Reachability: 1 if some route of 1 to 7 steps leads from the row to the column
B82: MKT | C82: GOV | D82: MAT | E82: IND | F82: DIG | G82: ENG | H82: TRS
A83: MKT | B83: =SIGN(Wiring!$B$6+$B$6+$B$17+$B$28+$B$39+$B$50+$B$61) -> 0 | C83: =SIGN(Wiring!$C$6+$C$6+$C$17+$C$28+$C$39+$C$50+$C$61) -> 0 | D83: =SIGN(Wiring!$D$6+$D$6+$D$17+$D$28+$D$39+$D$50+$D$61) -> 1 | E83: =SIGN(Wiring!$E$6+$E$6+$E$17+$E$28+$E$39+$E$50+$E$61) -> 1 | F83: =SIGN(Wiring!$F$6+$F$6+$F$17+$F$28+$F$39+$F$50+$F$61) -> 1 | G83: =SIGN(Wiring!$G$6+$G$6+$G$17+$G$28+$G$39+$G$50+$G$61) -> 1 | H83: =SIGN(Wiring!$H$6+$H$6+$H$17+$H$28+$H$39+$H$50+$H$61) -> 1
A84: GOV | B84: =SIGN(Wiring!$B$7+$B$7+$B$18+$B$29+$B$40+$B$51+$B$62) -> 0 | C84: =SIGN(Wiring!$C$7+$C$7+$C$18+$C$29+$C$40+$C$51+$C$62) -> 0 | D84: =SIGN(Wiring!$D$7+$D$7+$D$18+$D$29+$D$40+$D$51+$D$62) -> 0 | E84: =SIGN(Wiring!$E$7+$E$7+$E$18+$E$29+$E$40+$E$51+$E$62) -> 1 | F84: =SIGN(Wiring!$F$7+$F$7+$F$18+$F$29+$F$40+$F$51+$F$62) -> 1 | G84: =SIGN(Wiring!$G$7+$G$7+$G$18+$G$29+$G$40+$G$51+$G$62) -> 1 | H84: =SIGN(Wiring!$H$7+$H$7+$H$18+$H$29+$H$40+$H$51+$H$62) -> 1
A85: MAT | B85: =SIGN(Wiring!$B$8+$B$8+$B$19+$B$30+$B$41+$B$52+$B$63) -> 0 | C85: =SIGN(Wiring!$C$8+$C$8+$C$19+$C$30+$C$41+$C$52+$C$63) -> 0 | D85: =SIGN(Wiring!$D$8+$D$8+$D$19+$D$30+$D$41+$D$52+$D$63) -> 0 | E85: =SIGN(Wiring!$E$8+$E$8+$E$19+$E$30+$E$41+$E$52+$E$63) -> 1 | F85: =SIGN(Wiring!$F$8+$F$8+$F$19+$F$30+$F$41+$F$52+$F$63) -> 1 | G85: =SIGN(Wiring!$G$8+$G$8+$G$19+$G$30+$G$41+$G$52+$G$63) -> 1 | H85: =SIGN(Wiring!$H$8+$H$8+$H$19+$H$30+$H$41+$H$52+$H$63) -> 1
A86: IND | B86: =SIGN(Wiring!$B$9+$B$9+$B$20+$B$31+$B$42+$B$53+$B$64) -> 0 | C86: =SIGN(Wiring!$C$9+$C$9+$C$20+$C$31+$C$42+$C$53+$C$64) -> 0 | D86: =SIGN(Wiring!$D$9+$D$9+$D$20+$D$31+$D$42+$D$53+$D$64) -> 0 | E86: =SIGN(Wiring!$E$9+$E$9+$E$20+$E$31+$E$42+$E$53+$E$64) -> 1 | F86: =SIGN(Wiring!$F$9+$F$9+$F$20+$F$31+$F$42+$F$53+$F$64) -> 1 | G86: =SIGN(Wiring!$G$9+$G$9+$G$20+$G$31+$G$42+$G$53+$G$64) -> 1 | H86: =SIGN(Wiring!$H$9+$H$9+$H$20+$H$31+$H$42+$H$53+$H$64) -> 1
A87: DIG | B87: =SIGN(Wiring!$B$10+$B$10+$B$21+$B$32+$B$43+$B$54+$B$65) -> 0 | C87: =SIGN(Wiring!$C$10+$C$10+$C$21+$C$32+$C$43+$C$54+$C$65) -> 0 | D87: =SIGN(Wiring!$D$10+$D$10+$D$21+$D$32+$D$43+$D$54+$D$65) -> 0 | E87: =SIGN(Wiring!$E$10+$E$10+$E$21+$E$32+$E$43+$E$54+$E$65) -> 1 | F87: =SIGN(Wiring!$F$10+$F$10+$F$21+$F$32+$F$43+$F$54+$F$65) -> 1 | G87: =SIGN(Wiring!$G$10+$G$10+$G$21+$G$32+$G$43+$G$54+$G$65) -> 1 | H87: =SIGN(Wiring!$H$10+$H$10+$H$21+$H$32+$H$43+$H$54+$H$65) -> 1
A88: ENG | B88: =SIGN(Wiring!$B$11+$B$11+$B$22+$B$33+$B$44+$B$55+$B$66) -> 0 | C88: =SIGN(Wiring!$C$11+$C$11+$C$22+$C$33+$C$44+$C$55+$C$66) -> 0 | D88: =SIGN(Wiring!$D$11+$D$11+$D$22+$D$33+$D$44+$D$55+$D$66) -> 0 | E88: =SIGN(Wiring!$E$11+$E$11+$E$22+$E$33+$E$44+$E$55+$E$66) -> 1 | F88: =SIGN(Wiring!$F$11+$F$11+$F$22+$F$33+$F$44+$F$55+$F$66) -> 1 | G88: =SIGN(Wiring!$G$11+$G$11+$G$22+$G$33+$G$44+$G$55+$G$66) -> 1 | H88: =SIGN(Wiring!$H$11+$H$11+$H$22+$H$33+$H$44+$H$55+$H$66) -> 1
A89: TRS | B89: =SIGN(Wiring!$B$12+$B$12+$B$23+$B$34+$B$45+$B$56+$B$67) -> 0 | C89: =SIGN(Wiring!$C$12+$C$12+$C$23+$C$34+$C$45+$C$56+$C$67) -> 0 | D89: =SIGN(Wiring!$D$12+$D$12+$D$23+$D$34+$D$45+$D$56+$D$67) -> 0 | E89: =SIGN(Wiring!$E$12+$E$12+$E$23+$E$34+$E$45+$E$56+$E$67) -> 1 | F89: =SIGN(Wiring!$F$12+$F$12+$F$23+$F$34+$F$45+$F$56+$F$67) -> 1 | G89: =SIGN(Wiring!$G$12+$G$12+$G$23+$G$34+$G$45+$G$56+$G$67) -> 1 | H89: =SIGN(Wiring!$H$12+$H$12+$H$23+$H$34+$H$45+$H$56+$H$67) -> 1
A92: Strongly connected: 1 if the row and the column reach each other (Definition 9.5)
B93: MKT | C93: GOV | D93: MAT | E93: IND | F93: DIG | G93: ENG | H93: TRS | J93: component size | K93: in a core
A94: MKT | B94: 1 | C94: =$C$83*$B$84 -> 0 | D94: =$D$83*$B$85 -> 0 | E94: =$E$83*$B$86 -> 0 | F94: =$F$83*$B$87 -> 0 | G94: =$G$83*$B$88 -> 0 | H94: =$H$83*$B$89 -> 0 | J94: =SUM($B$94:$H$94) -> 1 | K94: =IF(J94>1,1,0) -> 0
A95: GOV | B95: =$B$84*$C$83 -> 0 | C95: 1 | D95: =$D$84*$C$85 -> 0 | E95: =$E$84*$C$86 -> 0 | F95: =$F$84*$C$87 -> 0 | G95: =$G$84*$C$88 -> 0 | H95: =$H$84*$C$89 -> 0 | J95: =SUM($B$95:$H$95) -> 1 | K95: =IF(J95>1,1,0) -> 0
A96: MAT | B96: =$B$85*$D$83 -> 0 | C96: =$C$85*$D$84 -> 0 | D96: 1 | E96: =$E$85*$D$86 -> 0 | F96: =$F$85*$D$87 -> 0 | G96: =$G$85*$D$88 -> 0 | H96: =$H$85*$D$89 -> 0 | J96: =SUM($B$96:$H$96) -> 1 | K96: =IF(J96>1,1,0) -> 0
A97: IND | B97: =$B$86*$E$83 -> 0 | C97: =$C$86*$E$84 -> 0 | D97: =$D$86*$E$85 -> 0 | E97: 1 | F97: =$F$86*$E$87 -> 1 | G97: =$G$86*$E$88 -> 1 | H97: =$H$86*$E$89 -> 1 | J97: =SUM($B$97:$H$97) -> 4 | K97: =IF(J97>1,1,0) -> 1
A98: DIG | B98: =$B$87*$F$83 -> 0 | C98: =$C$87*$F$84 -> 0 | D98: =$D$87*$F$85 -> 0 | E98: =$E$87*$F$86 -> 1 | F98: 1 | G98: =$G$87*$F$88 -> 1 | H98: =$H$87*$F$89 -> 1 | J98: =SUM($B$98:$H$98) -> 4 | K98: =IF(J98>1,1,0) -> 1
A99: ENG | B99: =$B$88*$G$83 -> 0 | C99: =$C$88*$G$84 -> 0 | D99: =$D$88*$G$85 -> 0 | E99: =$E$88*$G$86 -> 1 | F99: =$F$88*$G$87 -> 1 | G99: 1 | H99: =$H$88*$G$89 -> 1 | J99: =SUM($B$99:$H$99) -> 4 | K99: =IF(J99>1,1,0) -> 1
A100: TRS | B100: =$B$89*$H$83 -> 0 | C100: =$C$89*$H$84 -> 0 | D100: =$D$89*$H$85 -> 0 | E100: =$E$89*$H$86 -> 1 | F100: =$F$89*$H$87 -> 1 | G100: =$G$89*$H$88 -> 1 | H100: 1 | J100: =SUM($B$100:$H$100) -> 4 | K100: =IF(J100>1,1,0) -> 1
A103: A x strongly connected: arrows from the row into the column's component
B104: MKT | C104: GOV | D104: MAT | E104: IND | F104: DIG | G104: ENG | H104: TRS
A105: MKT | B105: =Wiring!$B$6*$B$94+Wiring!$C$6*$B$95+Wiring!$D$6*$B$96+Wiring!$E$6*$B$97+Wiring!$F$6*$B$98+Wiring!$G$6*$B$99+Wiring!$H$6*$B$100 -> 0 | C105: =Wiring!$B$6*$C$94+Wiring!$C$6*$C$95+Wiring!$D$6*$C$96+Wiring!$E$6*$C$97+Wiring!$F$6*$C$98+Wiring!$G$6*$C$99+Wiring!$H$6*$C$100 -> 0 | D105: =Wiring!$B$6*$D$94+Wiring!$C$6*$D$95+Wiring!$D$6*$D$96+Wiring!$E$6*$D$97+Wiring!$F$6*$D$98+Wiring!$G$6*$D$99+Wiring!$H$6*$D$100 -> 1 | E105: =Wiring!$B$6*$E$94+Wiring!$C$6*$E$95+Wiring!$D$6*$E$96+Wiring!$E$6*$E$97+Wiring!$F$6*$E$98+Wiring!$G$6*$E$99+Wiring!$H$6*$E$100 -> 2 | F105: =Wiring!$B$6*$F$94+Wiring!$C$6*$F$95+Wiring!$D$6*$F$96+Wiring!$E$6*$F$97+Wiring!$F$6*$F$98+Wiring!$G$6*$F$99+Wiring!$H$6*$F$100 -> 2 | G105: =Wiring!$B$6*$G$94+Wiring!$C$6*$G$95+Wiring!$D$6*$G$96+Wiring!$E$6*$G$97+Wiring!$F$6*$G$98+Wiring!$G$6*$G$99+Wiring!$H$6*$G$100 -> 2 | H105: =Wiring!$B$6*$H$94+Wiring!$C$6*$H$95+Wiring!$D$6*$H$96+Wiring!$E$6*$H$97+Wiring!$F$6*$H$98+Wiring!$G$6*$H$99+Wiring!$H$6*$H$100 -> 2
...

Sheet Shock
A1: Put floors under arrival times and send a shock (Worked Example 9.1, Step 3; Theorem 9.2; Table 9.7; Online Appendix 9.B.2; AXIOM Lab 1.9, step 3)
A2: A demand shock to the market can change a component no sooner than its distance, the fewest arrows from the market: a floor, not a forecast.
A5: Component | B5: Distance from the market | C5: Reached at all
A6: MKT | B6: 0 | C6: =IF(ISNUMBER(B6),1,0) -> 1 | F6: Reached after one quarter | G6: =C43 -> 3 | H6: the three divisions
A7: GOV | B7: =IF(Wiring!$C$6>0,1,IF(Core!$C$6>0,2,IF(Core!$C$17>0,3,IF(Core!$C$28>0,4,IF(Core!$C$39>0,5,IF(Core!$C$50>0,6,"never")))))) -> never | C7: =IF(ISNUMBER(B7),1,0) -> 0 | F7: Reached after two quarters | G7: =D43 -> 5 | H7: and engineering and treasury
A8: MAT | B8: =IF(Wiring!$D$6>0,1,IF(Core!$D$6>0,2,IF(Core!$D$17>0,3,IF(Core!$D$28>0,4,IF(Core!$D$39>0,5,IF(Core!$D$50>0,6,"never")))))) -> 1 | C8: =IF(ISNUMBER(B8),1,0) -> 1 | F8: Reached after three quarters | G8: =E43 -> 5 | H8: no one else
A9: IND | B9: =IF(Wiring!$E$6>0,1,IF(Core!$E$6>0,2,IF(Core!$E$17>0,3,IF(Core!$E$28>0,4,IF(Core!$E$39>0,5,IF(Core!$E$50>0,6,"never")))))) -> 1 | C9: =IF(ISNUMBER(B9),1,0) -> 1 | F9: Never reached | G9: =COUNTIF($B$6:$B$12,"never") -> 1 | H9: governance: no path
A10: DIG | B10: =IF(Wiring!$F$6>0,1,IF(Core!$F$6>0,2,IF(Core!$F$17>0,3,IF(Core!$F$28>0,4,IF(Core!$F$39>0,5,IF(Core!$F$50>0,6,"never")))))) -> 1 | C10: =IF(ISNUMBER(B10),1,0) -> 1 | F10: Routes of two steps | G10: =B48 -> 3 | H10: Section 9.8: 3
A11: ENG | B11: =IF(Wiring!$G$6>0,1,IF(Core!$G$6>0,2,IF(Core!$G$17>0,3,IF(Core!$G$28>0,4,IF(Core!$G$39>0,5,IF(Core!$G$50>0,6,"never")))))) -> 2 | C11: =IF(ISNUMBER(B11),1,0) -> 1 | F11: Routes of four steps | G11: =B50 -> 10 | H11: Section 9.8: 10
A12: TRS | B12: =IF(Wiring!$H$6>0,1,IF(Core!$H$6>0,2,IF(Core!$H$17>0,3,IF(Core!$H$28>0,4,IF(Core!$H$39>0,5,IF(Core!$H$50>0,6,"never")))))) -> 2 | C12: =IF(ISNUMBER(B12),1,0) -> 1 | F12: Routes of six steps | G12: =B52 -> 40 | H12: Section 9.8: 40
F13: Routes of odd length (1, 3, 5, 7) | G13: =B47+B49+B51+B53 -> 0 | H13: none: routes alternate between two groups
A15: Component (Table 9.7) | B15: Earliest quarter | C15: A shortest route | D15: Shortest routes
A16: Industrial Systems (IND) | B16: =$B$9 -> 1 | C16: =IF(ISNUMBER($B$9),IF($B$9=1,"MKT → IND",IF($B$9=2,"MKT → "&$E$33&" → IND",IF($B$9=3,"MKT → "&INDEX($B$33:$H$33,MATCH($E$33,$B$25:$H$25,0))&" → "&$E$33&" → IND","longer"))),"no path") -> MKT → IND | D16: =IF(ISNUMBER(B16),CHOOSE(B16,Wiring!$E$6,Core!$E$6,Core!$E$17,Core!$E$28,Core!$E$39,Core!$E$50),0) -> 1
A17: Digital (DIG) | B17: =$B$10 -> 1 | C17: =IF(ISNUMBER($B$10),IF($B$10=1,"MKT → DIG",IF($B$10=2,"MKT → "&$F$33&" → DIG",IF($B$10=3,"MKT → "&INDEX($B$33:$H$33,MATCH($F$33,$B$25:$H$25,0))&" → "&$F$33&" → DIG","longer"))),"no path") -> MKT → DIG | D17: =IF(ISNUMBER(B17),CHOOSE(B17,Wiring!$F$6,Core!$F$6,Core!$F$17,Core!$F$28,Core!$F$39,Core!$F$50),0) -> 1
A18: Materials (MAT) | B18: =$B$8 -> 1 | C18: =IF(ISNUMBER($B$8),IF($B$8=1,"MKT → MAT",IF($B$8=2,"MKT → "&$D$33&" → MAT",IF($B$8=3,"MKT → "&INDEX($B$33:$H$33,MATCH($D$33,$B$25:$H$25,0))&" → "&$D$33&" → MAT","longer"))),"no path") -> MKT → MAT | D18: =IF(ISNUMBER(B18),CHOOSE(B18,Wiring!$D$6,Core!$D$6,Core!$D$17,Core!$D$28,Core!$D$39,Core!$D$50),0) -> 1
A19: Shared engineering (ENG) | B19: =$B$11 -> 2 | C19: =IF(ISNUMBER($B$11),IF($B$11=1,"MKT → ENG",IF($B$11=2,"MKT → "&$G$33&" → ENG",IF($B$11=3,"MKT → "&INDEX($B$33:$H$33,MATCH($G$33,$B$25:$H$25,0))&" → "&$G$33&" → ENG","longer"))),"no path") -> MKT → IND → ENG | D19: =IF(ISNUMBER(B19),CHOOSE(B19,Wiring!$G$6,Core!$G$6,Core!$G$17,Core!$G$28,Core!$G$39,Core!$G$50),0) -> 2
A20: Treasury (TRS), covenant | B20: =$B$12 -> 2 | C20: =IF(ISNUMBER($B$12),IF($B$12=1,"MKT → TRS",IF($B$12=2,"MKT → "&$H$33&" → TRS",IF($B$12=3,"MKT → "&INDEX($B$33:$H$33,MATCH($H$33,$B$25:$H$25,0))&" → "&$H$33&" → TRS","longer"))),"no path") -> MKT → IND → TRS | D20: =IF(ISNUMBER(B20),CHOOSE(B20,Wiring!$H$6,Core!$H$6,Core!$H$17,Core!$H$28,Core!$H$39,Core!$H$50),0) -> 3
A21: Governance (GOV) | B21: =$B$7 -> never | C21: =IF(ISNUMBER($B$7),IF($B$7=1,"MKT → GOV",IF($B$7=2,"MKT → "&$C$33&" → GOV",IF($B$7=3,"MKT → "&INDEX($B$33:$H$33,MATCH($C$33,$B$25:$H$25,0))&" → "&$C$33&" → GOV","longer"))),"no path") -> no path | D21: =IF(ISNUMBER(B21),CHOOSE(B21,Wiring!$C$6,Core!$C$6,Core!$C$17,Core!$C$28,Core!$C$39,Core!$C$50),0) -> 0
A22: The covenant is a reading of treasury: it cannot move before the second quarter-end after the shock (Theorem 9.2(ii)), and three routes of two steps lead there.
A24: A predecessor on a shortest route: 1 if the row is one step closer to the market and sends an arrow to the column
A25: from \ to | B25: MKT | C25: GOV | D25: MAT | E25: IND | F25: DIG | G25: ENG | H25: TRS
A26: IND | B26: =IF(AND(ISNUMBER($B$9),ISNUMBER($B$6)),IF(AND($B$9=$B$6-1,Wiring!$B$9=1),1,0),0) -> 0 | C26: =IF(AND(ISNUMBER($B$9),ISNUMBER($B$7)),IF(AND($B$9=$B$7-1,Wiring!$C$9=1),1,0),0) -> 0 | D26: =IF(AND(ISNUMBER($B$9),ISNUMBER($B$8)),IF(AND($B$9=$B$8-1,Wiring!$D$9=1),1,0),0) -> 0 | E26: =IF(AND(ISNUMBER($B$9),ISNUMBER($B$9)),IF(AND($B$9=$B$9-1,Wiring!$E$9=1),1,0),0) -> 0 | F26: =IF(AND(ISNUMBER($B$9),ISNUMBER($B$10)),IF(AND($B$9=$B$10-1,Wiring!$F$9=1),1,0),0) -> 0 | G26: =IF(AND(ISNUMBER($B$9),ISNUMBER($B$11)),IF(AND($B$9=$B$11-1,Wiring!$G$9=1),1,0),0) -> 1 | H26: =IF(AND(ISNUMBER($B$9),ISNUMBER($B$12)),IF(AND($B$9=$B$12-1,Wiring!$H$9=1),1,0),0) -> 1
A27: DIG | B27: =IF(AND(ISNUMBER($B$10),ISNUMBER($B$6)),IF(AND($B$10=$B$6-1,Wiring!$B$10=1),1,0),0) -> 0 | C27: =IF(AND(ISNUMBER($B$10),ISNUMBER($B$7)),IF(AND($B$10=$B$7-1,Wiring!$C$10=1),1,0),0) -> 0 | D27: =IF(AND(ISNUMBER($B$10),ISNUMBER($B$8)),IF(AND($B$10=$B$8-1,Wiring!$D$10=1),1,0),0) -> 0 | E27: =IF(AND(ISNUMBER($B$10),ISNUMBER($B$9)),IF(AND($B$10=$B$9-1,Wiring!$E$10=1),1,0),0) -> 0 | F27: =IF(AND(ISNUMBER($B$10),ISNUMBER($B$10)),IF(AND($B$10=$B$10-1,Wiring!$F$10=1),1,0),0) -> 0 | G27: =IF(AND(ISNUMBER($B$10),ISNUMBER($B$11)),IF(AND($B$10=$B$11-1,Wiring!$G$10=1),1,0),0) -> 1 | H27: =IF(AND(ISNUMBER($B$10),ISNUMBER($B$12)),IF(AND($B$10=$B$12-1,Wiring!$H$10=1),1,0),0) -> 1
A28: MAT | B28: =IF(AND(ISNUMBER($B$8),ISNUMBER($B$6)),IF(AND($B$8=$B$6-1,Wiring!$B$8=1),1,0),0) -> 0 | C28: =IF(AND(ISNUMBER($B$8),ISNUMBER($B$7)),IF(AND($B$8=$B$7-1,Wiring!$C$8=1),1,0),0) -> 0 | D28: =IF(AND(ISNUMBER($B$8),ISNUMBER($B$8)),IF(AND($B$8=$B$8-1,Wiring!$D$8=1),1,0),0) -> 0 | E28: =IF(AND(ISNUMBER($B$8),ISNUMBER($B$9)),IF(AND($B$8=$B$9-1,Wiring!$E$8=1),1,0),0) -> 0 | F28: =IF(AND(ISNUMBER($B$8),ISNUMBER($B$10)),IF(AND($B$8=$B$10-1,Wiring!$F$8=1),1,0),0) -> 0 | G28: =IF(AND(ISNUMBER($B$8),ISNUMBER($B$11)),IF(AND($B$8=$B$11-1,Wiring!$G$8=1),1,0),0) -> 0 | H28: =IF(AND(ISNUMBER($B$8),ISNUMBER($B$12)),IF(AND($B$8=$B$12-1,Wiring!$H$8=1),1,0),0) -> 1
A29: ENG | B29: =IF(AND(ISNUMBER($B$11),ISNUMBER($B$6)),IF(AND($B$11=$B$6-1,Wiring!$B$11=1),1,0),0) -> 0 | C29: =IF(AND(ISNUMBER($B$11),ISNUMBER($B$7)),IF(AND($B$11=$B$7-1,Wiring!$C$11=1),1,0),0) -> 0 | D29: =IF(AND(ISNUMBER($B$11),ISNUMBER($B$8)),IF(AND($B$11=$B$8-1,Wiring!$D$11=1),1,0),0) -> 0 | E29: =IF(AND(ISNUMBER($B$11),ISNUMBER($B$9)),IF(AND($B$11=$B$9-1,Wiring!$E$11=1),1,0),0) -> 0 | F29: =IF(AND(ISNUMBER($B$11),ISNUMBER($B$10)),IF(AND($B$11=$B$10-1,Wiring!$F$11=1),1,0),0) -> 0 | G29: =IF(AND(ISNUMBER($B$11),ISNUMBER($B$11)),IF(AND($B$11=$B$11-1,Wiring!$G$11=1),1,0),0) -> 0 | H29: =IF(AND(ISNUMBER($B$11),ISNUMBER($B$12)),IF(AND($B$11=$B$12-1,Wiring!$H$11=1),1,0),0) -> 0
A30: TRS | B30: =IF(AND(ISNUMBER($B$12),ISNUMBER($B$6)),IF(AND($B$12=$B$6-1,Wiring!$B$12=1),1,0),0) -> 0 | C30: =IF(AND(ISNUMBER($B$12),ISNUMBER($B$7)),IF(AND($B$12=$B$7-1,Wiring!$C$12=1),1,0),0) -> 0 | D30: =IF(AND(ISNUMBER($B$12),ISNUMBER($B$8)),IF(AND($B$12=$B$8-1,Wiring!$D$12=1),1,0),0) -> 0 | E30: =IF(AND(ISNUMBER($B$12),ISNUMBER($B$9)),IF(AND($B$12=$B$9-1,Wiring!$E$12=1),1,0),0) -> 0 | F30: =IF(AND(ISNUMBER($B$12),ISNUMBER($B$10)),IF(AND($B$12=$B$10-1,Wiring!$F$12=1),1,0),0) -> 0 | G30: =IF(AND(ISNUMBER($B$12),ISNUMBER($B$11)),IF(AND($B$12=$B$11-1,Wiring!$G$12=1),1,0),0) -> 0 | H30: =IF(AND(ISNUMBER($B$12),ISNUMBER($B$12)),IF(AND($B$12=$B$12-1,Wiring!$H$12=1),1,0),0) -> 0
A31: MKT | B31: =IF(AND(ISNUMBER($B$6),ISNUMBER($B$6)),IF(AND($B$6=$B$6-1,Wiring!$B$6=1),1,0),0) -> 0 | C31: =IF(AND(ISNUMBER($B$6),ISNUMBER($B$7)),IF(AND($B$6=$B$7-1,Wiring!$C$6=1),1,0),0) -> 0 | D31: =IF(AND(ISNUMBER($B$6),ISNUMBER($B$8)),IF(AND($B$6=$B$8-1,Wiring!$D$6=1),1,0),0) -> 1 | E31: =IF(AND(ISNUMBER($B$6),ISNUMBER($B$9)),IF(AND($B$6=$B$9-1,Wiring!$E$6=1),1,0),0) -> 1 | F31: =IF(AND(ISNUMBER($B$6),ISNUMBER($B$10)),IF(AND($B$6=$B$10-1,Wiring!$F$6=1),1,0),0) -> 1 | G31: =IF(AND(ISNUMBER($B$6),ISNUMBER($B$11)),IF(AND($B$6=$B$11-1,Wiring!$G$6=1),1,0),0) -> 0 | H31: =IF(AND(ISNUMBER($B$6),ISNUMBER($B$12)),IF(AND($B$6=$B$12-1,Wiring!$H$6=1),1,0),0) -> 0
A32: GOV | B32: =IF(AND(ISNUMBER($B$7),ISNUMBER($B$6)),IF(AND($B$7=$B$6-1,Wiring!$B$7=1),1,0),0) -> 0 | C32: =IF(AND(ISNUMBER($B$7),ISNUMBER($B$7)),IF(AND($B$7=$B$7-1,Wiring!$C$7=1),1,0),0) -> 0 | D32: =IF(AND(ISNUMBER($B$7),ISNUMBER($B$8)),IF(AND($B$7=$B$8-1,Wiring!$D$7=1),1,0),0) -> 0 | E32: =IF(AND(ISNUMBER($B$7),ISNUMBER($B$9)),IF(AND($B$7=$B$9-1,Wiring!$E$7=1),1,0),0) -> 0 | F32: =IF(AND(ISNUMBER($B$7),ISNUMBER($B$10)),IF(AND($B$7=$B$10-1,Wiring!$F$7=1),1,0),0) -> 0 | G32: =IF(AND(ISNUMBER($B$7),ISNUMBER($B$11)),IF(AND($B$7=$B$11-1,Wiring!$G$7=1),1,0),0) -> 0 | H32: =IF(AND(ISNUMBER($B$7),ISNUMBER($B$12)),IF(AND($B$7=$B$12-1,Wiring!$H$7=1),1,0),0) -> 0
A33: predecessor | B33: =IFERROR(INDEX($A$26:$A$32,MATCH(1,B26:B32,0)),"") | C33: =IFERROR(INDEX($A$26:$A$32,MATCH(1,C26:C32,0)),"") | D33: =IFERROR(INDEX($A$26:$A$32,MATCH(1,D26:D32,0)),"") -> MKT | E33: =IFERROR(INDEX($A$26:$A$32,MATCH(1,E26:E32,0)),"") -> MKT | F33: =IFERROR(INDEX($A$26:$A$32,MATCH(1,F26:F32,0)),"") -> MKT | G33: =IFERROR(INDEX($A$26:$A$32,MATCH(1,G26:G32,0)),"") -> IND | H33: =IFERROR(INDEX($A$26:$A$32,MATCH(1,H26:H32,0)),"") -> IND
A35: The wavefront: 1 once the shock can have reached the component (AXIOM Lab 1.9, step 3)
A36: Component | B36: quarter 0 | C36: quarter 1 | D36: quarter 2 | E36: quarter 3 | F36: quarter 4
A37: IND | B37: =IF(ISNUMBER($B$9),IF($B$9<=0,1,0),0) -> 0 | C37: =IF(ISNUMBER($B$9),IF($B$9<=1,1,0),0) -> 1 | D37: =IF(ISNUMBER($B$9),IF($B$9<=2,1,0),0) -> 1 | E37: =IF(ISNUMBER($B$9),IF($B$9<=3,1,0),0) -> 1 | F37: =IF(ISNUMBER($B$9),IF($B$9<=4,1,0),0) -> 1
A38: DIG | B38: =IF(ISNUMBER($B$10),IF($B$10<=0,1,0),0) -> 0 | C38: =IF(ISNUMBER($B$10),IF($B$10<=1,1,0),0) -> 1 | D38: =IF(ISNUMBER($B$10),IF($B$10<=2,1,0),0) -> 1 | E38: =IF(ISNUMBER($B$10),IF($B$10<=3,1,0),0) -> 1 | F38: =IF(ISNUMBER($B$10),IF($B$10<=4,1,0),0) -> 1
A39: MAT | B39: =IF(ISNUMBER($B$8),IF($B$8<=0,1,0),0) -> 0 | C39: =IF(ISNUMBER($B$8),IF($B$8<=1,1,0),0) -> 1 | D39: =IF(ISNUMBER($B$8),IF($B$8<=2,1,0),0) -> 1 | E39: =IF(ISNUMBER($B$8),IF($B$8<=3,1,0),0) -> 1 | F39: =IF(ISNUMBER($B$8),IF($B$8<=4,1,0),0) -> 1
A40: ENG | B40: =IF(ISNUMBER($B$11),IF($B$11<=0,1,0),0) -> 0 | C40: =IF(ISNUMBER($B$11),IF($B$11<=1,1,0),0) -> 0 | D40: =IF(ISNUMBER($B$11),IF($B$11<=2,1,0),0) -> 1 | E40: =IF(ISNUMBER($B$11),IF($B$11<=3,1,0),0) -> 1 | F40: =IF(ISNUMBER($B$11),IF($B$11<=4,1,0),0) -> 1
A41: TRS | B41: =IF(ISNUMBER($B$12),IF($B$12<=0,1,0),0) -> 0 | C41: =IF(ISNUMBER($B$12),IF($B$12<=1,1,0),0) -> 0 | D41: =IF(ISNUMBER($B$12),IF($B$12<=2,1,0),0) -> 1 | E41: =IF(ISNUMBER($B$12),IF($B$12<=3,1,0),0) -> 1 | F41: =IF(ISNUMBER($B$12),IF($B$12<=4,1,0),0) -> 1
A42: GOV | B42: =IF(ISNUMBER($B$7),IF($B$7<=0,1,0),0) -> 0 | C42: =IF(ISNUMBER($B$7),IF($B$7<=1,1,0),0) -> 0 | D42: =IF(ISNUMBER($B$7),IF($B$7<=2,1,0),0) -> 0 | E42: =IF(ISNUMBER($B$7),IF($B$7<=3,1,0),0) -> 0 | F42: =IF(ISNUMBER($B$7),IF($B$7<=4,1,0),0) -> 0
A43: reached | B43: =SUM(B37:B42) -> 0 | C43: =SUM(C37:C42) -> 3 | D43: =SUM(D37:D42) -> 5 | E43: =SUM(E37:E42) -> 5 | F43: =SUM(F37:F42) -> 5
A46: Route length | B46: Routes from the market to treasury
A47: 1 | B47: =Wiring!$H$6 -> 0
A48: 2 | B48: =Core!$H$6 -> 3
A49: 3 | B49: =Core!$H$17 -> 0
A50: 4 | B50: =Core!$H$28 -> 10
A51: 5 | B51: =Core!$H$39 -> 0
A52: 6 | B52: =Core!$H$50 -> 40
A53: 7 | B53: =Core!$H$61 -> 0
A54: 8 | B54: =Core!$H$72 -> 160
A57: A positive linear company (Theorem 9.2(iii)): sensitivities drawn by the notebook with the lab's seed 26109 (engine values); set an arrow's switch to 0 to weaken it away
A58: From | B58: To | C58: Sensitivity (engine) | D58: Switch (1 on, 0 off) | E58: In use
A59: =Declarations!B13 -> MKT | B59: =Declarations!C13 -> IND | C59: 0.66115678 | D59: 1 | E59: =C59*D59 -> 0.66115678
A60: =Declarations!B14 -> MKT | B60: =Declarations!C14 -> DIG | C60: 0.5352025 | D60: 1 | E60: =C60*D60 -> 0.5352025
A61: =Declarations!B15 -> MKT | B61: =Declarations!C15 -> MAT | C61: 0.54219262 | D61: 1 | E61: =C61*D61 -> 0.54219262
A62: =Declarations!B16 -> IND | B62: =Declarations!C16 -> TRS | C62: 0.49522824 | D62: 1 | E62: =C62*D62 -> 0.49522824
A63: =Declarations!B17 -> DIG | B63: =Declarations!C17 -> TRS | C63: 0.21732749 | D63: 1 | E63: =C63*D63 -> 0.21732749
A64: =Declarations!B18 -> MAT | B64: =Declarations!C18 -> TRS | C64: 0.37493918 | D64: 1 | E64: =C64*D64 -> 0.37493918
A65: =Declarations!B19 -> TRS | B65: =Declarations!C19 -> IND | C65: 0.78734021 | D65: 1 | E65: =C65*D65 -> 0.78734021
A66: =Declarations!B20 -> TRS | B66: =Declarations!C20 -> DIG | C66: 0.32290235 | D66: 1 | E66: =C66*D66 -> 0.32290235
A67: =Declarations!B21 -> ENG | B67: =Declarations!C21 -> IND | C67: 0.54850403 | D67: 1 | E67: =C67*D67 -> 0.54850403
A68: =Declarations!B22 -> IND | B68: =Declarations!C22 -> ENG | C68: 0.52252391 | D68: 1 | E68: =C68*D68 -> 0.52252391
A69: =Declarations!B23 -> ENG | B69: =Declarations!C23 -> DIG | C69: 0.41698186 | D69: 1 | E69: =C69*D69 -> 0.41698186
A70: =Declarations!B24 -> DIG | B70: =Declarations!C24 -> ENG | C70: 0.55895128 | D70: 1 | E70: =C70*D70 -> 0.55895128
... A72: =Declarations!B26 -> GOV | B72: =Declarations!C26 -> DIG | C72: 0.2134342 | D72: 1 | E72: =C72*D72 -> 0.2134342
A75: Component | B75: Carry-over (engine)
A76: MKT | B76: 0.66233825
A77: GOV | B77: 0.77619257
A78: MAT | B78: 0.30813932
A79: IND | B79: 0.79486231
A80: DIG | B80: 0.73011733
A81: ENG | B81: 0.47924867
A82: TRS | B82: 0.41209036
A85: The company's next state: row = component updated, column = component read
A86: next \ reads | B86: MKT | C86: GOV | D86: MAT | E86: IND | F86: DIG | G86: ENG | H86: TRS
A87: MKT | B87: =$B$76 -> 0.66233825 | C87: =SUMIFS($E$59:$E$72,$A$59:$A$72,C$86,$B$59:$B$72,$A87) -> 0 | D87: =SUMIFS($E$59:$E$72,$A$59:$A$72,D$86,$B$59:$B$72,$A87) -> 0 | E87: =SUMIFS($E$59:$E$72,$A$59:$A$72,E$86,$B$59:$B$72,$A87) -> 0 | F87: =SUMIFS($E$59:$E$72,$A$59:$A$72,F$86,$B$59:$B$72,$A87) -> 0 | G87: =SUMIFS($E$59:$E$72,$A$59:$A$72,G$86,$B$59:$B$72,$A87) -> 0 | H87: =SUMIFS($E$59:$E$72,$A$59:$A$72,H$86,$B$59:$B$72,$A87) -> 0
A88: GOV | B88: =SUMIFS($E$59:$E$72,$A$59:$A$72,B$86,$B$59:$B$72,$A88) -> 0 | C88: =$B$77 -> 0.77619257 | D88: =SUMIFS($E$59:$E$72,$A$59:$A$72,D$86,$B$59:$B$72,$A88) -> 0 | E88: =SUMIFS($E$59:$E$72,$A$59:$A$72,E$86,$B$59:$B$72,$A88) -> 0 | F88: =SUMIFS($E$59:$E$72,$A$59:$A$72,F$86,$B$59:$B$72,$A88) -> 0 | G88: =SUMIFS($E$59:$E$72,$A$59:$A$72,G$86,$B$59:$B$72,$A88) -> 0 | H88: =SUMIFS($E$59:$E$72,$A$59:$A$72,H$86,$B$59:$B$72,$A88) -> 0
A89: MAT | B89: =SUMIFS($E$59:$E$72,$A$59:$A$72,B$86,$B$59:$B$72,$A89) -> 0.54219262 | C89: =SUMIFS($E$59:$E$72,$A$59:$A$72,C$86,$B$59:$B$72,$A89) -> 0 | D89: =$B$78 -> 0.30813932 | E89: =SUMIFS($E$59:$E$72,$A$59:$A$72,E$86,$B$59:$B$72,$A89) -> 0 | F89: =SUMIFS($E$59:$E$72,$A$59:$A$72,F$86,$B$59:$B$72,$A89) -> 0 | G89: =SUMIFS($E$59:$E$72,$A$59:$A$72,G$86,$B$59:$B$72,$A89) -> 0 | H89: =SUMIFS($E$59:$E$72,$A$59:$A$72,H$86,$B$59:$B$72,$A89) -> 0
A90: IND | B90: =SUMIFS($E$59:$E$72,$A$59:$A$72,B$86,$B$59:$B$72,$A90) -> 0.66115678 | C90: =SUMIFS($E$59:$E$72,$A$59:$A$72,C$86,$B$59:$B$72,$A90) -> 0 | D90: =SUMIFS($E$59:$E$72,$A$59:$A$72,D$86,$B$59:$B$72,$A90) -> 0 | E90: =$B$79 -> 0.79486231 | F90: =SUMIFS($E$59:$E$72,$A$59:$A$72,F$86,$B$59:$B$72,$A90) -> 0 | G90: =SUMIFS($E$59:$E$72,$A$59:$A$72,G$86,$B$59:$B$72,$A90) -> 0.54850403 | H90: =SUMIFS($E$59:$E$72,$A$59:$A$72,H$86,$B$59:$B$72,$A90) -> 0.78734021
A91: DIG | B91: =SUMIFS($E$59:$E$72,$A$59:$A$72,B$86,$B$59:$B$72,$A91) -> 0.5352025 | C91: =SUMIFS($E$59:$E$72,$A$59:$A$72,C$86,$B$59:$B$72,$A91) -> 0.2134342 | D91: =SUMIFS($E$59:$E$72,$A$59:$A$72,D$86,$B$59:$B$72,$A91) -> 0 | E91: =SUMIFS($E$59:$E$72,$A$59:$A$72,E$86,$B$59:$B$72,$A91) -> 0 | F91: =$B$80 -> 0.73011733 | G91: =SUMIFS($E$59:$E$72,$A$59:$A$72,G$86,$B$59:$B$72,$A91) -> 0.41698186 | H91: =SUMIFS($E$59:$E$72,$A$59:$A$72,H$86,$B$59:$B$72,$A91) -> 0.32290235
A92: ENG | B92: =SUMIFS($E$59:$E$72,$A$59:$A$72,B$86,$B$59:$B$72,$A92) -> 0 | C92: =SUMIFS($E$59:$E$72,$A$59:$A$72,C$86,$B$59:$B$72,$A92) -> 0 | D92: =SUMIFS($E$59:$E$72,$A$59:$A$72,D$86,$B$59:$B$72,$A92) -> 0 | E92: =SUMIFS($E$59:$E$72,$A$59:$A$72,E$86,$B$59:$B$72,$A92) -> 0.52252391 | F92: =SUMIFS($E$59:$E$72,$A$59:$A$72,F$86,$B$59:$B$72,$A92) -> 0.55895128 | G92: =$B$81 -> 0.47924867 | H92: =SUMIFS($E$59:$E$72,$A$59:$A$72,H$86,$B$59:$B$72,$A92) -> 0
A93: TRS | B93: =SUMIFS($E$59:$E$72,$A$59:$A$72,B$86,$B$59:$B$72,$A93) -> 0 | C93: =SUMIFS($E$59:$E$72,$A$59:$A$72,C$86,$B$59:$B$72,$A93) -> 0.74736168 | D93: =SUMIFS($E$59:$E$72,$A$59:$A$72,D$86,$B$59:$B$72,$A93) -> 0.37493918 | E93: =SUMIFS($E$59:$E$72,$A$59:$A$72,E$86,$B$59:$B$72,$A93) -> 0.49522824 | F93: =SUMIFS($E$59:$E$72,$A$59:$A$72,F$86,$B$59:$B$72,$A93) -> 0.21732749 | G93: =SUMIFS($E$59:$E$72,$A$59:$A$72,G$86,$B$59:$B$72,$A93) -> 0 | H93: =$B$82 -> 0.41209036
A95: Response to a unit demand shock, quarter by quarter (x' = W x)
A97: quarter | B97: MKT | C97: GOV | D97: MAT | E97: IND | F97: DIG | G97: ENG | H97: TRS
A98: 0 | B98: =IF(B$97="MKT",1,0) -> 1 | C98: =IF(C$97="MKT",1,0) -> 0 | D98: =IF(D$97="MKT",1,0) -> 0 | E98: =IF(E$97="MKT",1,0) -> 0 | F98: =IF(F$97="MKT",1,0) -> 0 | G98: =IF(G$97="MKT",1,0) -> 0 | H98: =IF(H$97="MKT",1,0) -> 0
A99: 1 | B99: =SUMPRODUCT($B$87:$H$87,$B$98:$H$98) -> 0.66233825 | C99: =SUMPRODUCT($B$88:$H$88,$B$98:$H$98) -> 0 | D99: =SUMPRODUCT($B$89:$H$89,$B$98:$H$98) -> 0.54219262 | E99: =SUMPRODUCT($B$90:$H$90,$B$98:$H$98) -> 0.66115678 | F99: =SUMPRODUCT($B$91:$H$91,$B$98:$H$98) -> 0.5352025 | G99: =SUMPRODUCT($B$92:$H$92,$B$98:$H$98) -> 0 | H99: =SUMPRODUCT($B$93:$H$93,$B$98:$H$98) -> 0
A100: 2 | B100: =SUMPRODUCT($B$87:$H$87,$B$99:$H$99) -> 0.43869195 | C100: =SUMPRODUCT($B$88:$H$88,$B$99:$H$99) -> 0 | D100: =SUMPRODUCT($B$89:$H$89,$B$99:$H$99) -> 0.52618578 | E100: =SUMPRODUCT($B$90:$H$90,$B$99:$H$99) -> 0.96343802 | F100: =SUMPRODUCT($B$91:$H$91,$B$99:$H$99) -> 0.7452457 | G100: =SUMPRODUCT($B$92:$H$92,$B$99:$H$99) -> 0.64462235 | H100: =SUMPRODUCT($B$93:$H$93,$B$99:$H$99) -> 0.64702699
A101: 3 | B101: =SUMPRODUCT($B$87:$H$87,$B$100:$H$100) -> 0.29056246 | C101: =SUMPRODUCT($B$88:$H$88,$B$100:$H$100) -> 0 | D101: =SUMPRODUCT($B$89:$H$89,$B$100:$H$100) -> 0.39999407 | E101: =SUMPRODUCT($B$90:$H$90,$B$100:$H$100) -> 1.918853 | F101: =SUMPRODUCT($B$91:$H$91,$B$100:$H$100) -> 1.2566282 | G101: =SUMPRODUCT($B$92:$H$92,$B$100:$H$100) -> 1.2289099 | H101: =SUMPRODUCT($B$93:$H$93,$B$100:$H$100) -> 1.1030053
A102: 4 | B102: =SUMPRODUCT($B$87:$H$87,$B$101:$H$101) -> 0.19245063 | C102: =SUMPRODUCT($B$88:$H$88,$B$101:$H$101) -> 0 | D102: =SUMPRODUCT($B$89:$H$89,$B$101:$H$101) -> 0.28079472 | E102: =SUMPRODUCT($B$90:$H$90,$B$101:$H$101) -> 3.2598338 | F102: =SUMPRODUCT($B$91:$H$91,$B$101:$H$101) -> 1.9415919 | G102: =SUMPRODUCT($B$92:$H$92,$B$101:$H$101) -> 2.293994 | H102: =SUMPRODUCT($B$93:$H$93,$B$101:$H$101) -> 1.8278814
A103: 5 | B103: =SUMPRODUCT($B$87:$H$87,$B$102:$H$102) -> 0.12746741 | C103: =SUMPRODUCT($B$88:$H$88,$B$102:$H$102) -> 0 | D103: =SUMPRODUCT($B$89:$H$89,$B$102:$H$102) -> 0.19086921 | E103: =SUMPRODUCT($B$90:$H$90,$B$102:$H$102) -> 5.4157885 | F103: =SUMPRODUCT($B$91:$H$91,$B$102:$H$102) -> 3.067371 | G103: =SUMPRODUCT($B$92:$H$92,$B$102:$H$102) -> 3.8879899 | H103: =SUMPRODUCT($B$93:$H$93,$B$102:$H$102) -> 2.8948563
A104: 6 | B104: =SUMPRODUCT($B$87:$H$87,$B$103:$H$103) -> 0.084426541 | C104: =SUMPRODUCT($B$88:$H$88,$B$103:$H$103) -> 0 | D104: =SUMPRODUCT($B$89:$H$89,$B$103:$H$103) -> 0.1279262 | E104: =SUMPRODUCT($B$90:$H$90,$B$103:$H$103) -> 8.8008969 | F104: =SUMPRODUCT($B$91:$H$91,$B$103:$H$103) -> 4.8637388 | G104: =SUMPRODUCT($B$92:$H$92,$B$103:$H$103) -> 6.4077039 | H104: =SUMPRODUCT($B$93:$H$93,$B$103:$H$103) -> 4.6131821
A105: 7 | B105: =SUMPRODUCT($B$87:$H$87,$B$104:$H$104) -> 0.055918927 | C105: =SUMPRODUCT($B$88:$H$88,$B$104:$H$104) -> 0 | D105: =SUMPRODUCT($B$89:$H$89,$B$104:$H$104) -> 0.08519454 | E105: =SUMPRODUCT($B$90:$H$90,$B$104:$H$104) -> 14.198116 | F105: =SUMPRODUCT($B$91:$H$91,$B$104:$H$104) -> 7.7577889 | G105: =SUMPRODUCT($B$92:$H$92,$B$104:$H$104) -> 10.388156 | H105: =SUMPRODUCT($B$93:$H$93,$B$104:$H$104) -> 7.3644893
A106: 8 | B106: =SUMPRODUCT($B$87:$H$87,$B$105:$H$105) -> 0.037037244 | C106: =SUMPRODUCT($B$88:$H$88,$B$105:$H$105) -> 0 | D106: =SUMPRODUCT($B$89:$H$89,$B$105:$H$105) -> 0.056570618 | E106: =SUMPRODUCT($B$90:$H$90,$B$105:$H$105) -> 22.818822 | F106: =SUMPRODUCT($B$91:$H$91,$B$105:$H$105) -> 12.403707 | G106: =SUMPRODUCT($B$92:$H$92,$B$105:$H$105) -> 16.733591 | H106: =SUMPRODUCT($B$93:$H$93,$B$105:$H$105) -> 11.784066
A107: first moves at | B107: =IF(COUNTIF(B98:B106,">0")>0,COUNTIF(B98:B106,0),"never") -> 0 | C107: =IF(COUNTIF(C98:C106,">0")>0,COUNTIF(C98:C106,0),"never") -> never | D107: =IF(COUNTIF(D98:D106,">0")>0,COUNTIF(D98:D106,0),"never") -> 1 | E107: =IF(COUNTIF(E98:E106,">0")>0,COUNTIF(E98:E106,0),"never") -> 1 | F107: =IF(COUNTIF(F98:F106,">0")>0,COUNTIF(F98:F106,0),"never") -> 1 | G107: =IF(COUNTIF(G98:G106,">0")>0,COUNTIF(G98:G106,0),"never") -> 2 | H107: =IF(COUNTIF(H98:H106,">0")>0,COUNTIF(H98:H106,0),"never") -> 2
A108: distance | B108: =VLOOKUP(B$97,$A$6:$B$12,2,FALSE()) -> 0 | C108: =VLOOKUP(C$97,$A$6:$B$12,2,FALSE()) -> never | D108: =VLOOKUP(D$97,$A$6:$B$12,2,FALSE()) -> 1 | E108: =VLOOKUP(E$97,$A$6:$B$12,2,FALSE()) -> 1 | F108: =VLOOKUP(F$97,$A$6:$B$12,2,FALSE()) -> 1 | G108: =VLOOKUP(G$97,$A$6:$B$12,2,FALSE()) -> 2 | H108: =VLOOKUP(H$97,$A$6:$B$12,2,FALSE()) -> 2
A109: earlier than the distance | B109: =IF(ISNUMBER(B107),IF(ISNUMBER(B108),IF(B107<B108,1,0),1),0) -> 0 | C109: =IF(ISNUMBER(C107),IF(ISNUMBER(C108),IF(C107<C108,1,0),1),0) -> 0 | D109: =IF(ISNUMBER(D107),IF(ISNUMBER(D108),IF(D107<D108,1,0),1),0) -> 0 | E109: =IF(ISNUMBER(E107),IF(ISNUMBER(E108),IF(E107<E108,1,0),1),0) -> 0 | F109: =IF(ISNUMBER(F107),IF(ISNUMBER(F108),IF(F107<F108,1,0),1),0) -> 0 | G109: =IF(ISNUMBER(G107),IF(ISNUMBER(G108),IF(G107<G108,1,0),1),0) -> 0 | H109: =IF(ISNUMBER(H107),IF(ISNUMBER(H108),IF(H107<H108,1,0),1),0) -> 0
A110: exactly at it | B110: =IF(ISNUMBER(B107),IF(ISNUMBER(B108),IF(B107=B108,1,0),0),IF(ISNUMBER(B108),0,1)) -> 1 | C110: =IF(ISNUMBER(C107),IF(ISNUMBER(C108),IF(C107=C108,1,0),0),IF(ISNUMBER(C108),0,1)) -> 1 | D110: =IF(ISNUMBER(D107),IF(ISNUMBER(D108),IF(D107=D108,1,0),0),IF(ISNUMBER(D108),0,1)) -> 1 | E110: =IF(ISNUMBER(E107),IF(ISNUMBER(E108),IF(E107=E108,1,0),0),IF(ISNUMBER(E108),0,1)) -> 1 | F110: =IF(ISNUMBER(F107),IF(ISNUMBER(F108),IF(F107=F108,1,0),0),IF(ISNUMBER(F108),0,1)) -> 1 | G110: =IF(ISNUMBER(G107),IF(ISNUMBER(G108),IF(G107=G108,1,0),0),IF(ISNUMBER(G108),0,1)) -> 1 | H110: =IF(ISNUMBER(H107),IF(ISNUMBER(H108),IF(H107=H108,1,0),0),IF(ISNUMBER(H108),0,1)) -> 1
A113: Division | B113: Sensitivity to demand | C113: Share reaching cash | D113: Product
A114: IND | B114: =SUMIFS($E$59:$E$72,$A$59:$A$72,"MKT",$B$59:$B$72,A114) -> 0.66115678 | C114: =SUMIFS($E$59:$E$72,$A$59:$A$72,A114,$B$59:$B$72,"TRS") -> 0.49522824 | D114: =B114*C114 -> 0.32742351
A115: DIG | B115: =SUMIFS($E$59:$E$72,$A$59:$A$72,"MKT",$B$59:$B$72,A115) -> 0.5352025 | C115: =SUMIFS($E$59:$E$72,$A$59:$A$72,A115,$B$59:$B$72,"TRS") -> 0.21732749 | D115: =B115*C115 -> 0.11631422
A116: MAT | B116: =SUMIFS($E$59:$E$72,$A$59:$A$72,"MKT",$B$59:$B$72,A116) -> 0.54219262 | C116: =SUMIFS($E$59:$E$72,$A$59:$A$72,A116,$B$59:$B$72,"TRS") -> 0.37493918 | D116: =B116*C116 -> 0.20328926
A118: Route sum: what reaches treasury at quarter 2 (Online Appendix 9.B.2) | D118: =SUM(D114:D116) -> 0.64702699
A119: Treasury's response at quarter 2 | D119: =H100 -> 0.64702699 | E119: equal: a positive linear company
...

Sheet Paths
A1: Paths and cuts from the market to treasury (Worked Example 9.1, Step 3; Theorem 9.2(i); AXIOM Lab 1.9, step 3)
A2: Every ordering of intermediate components is tried: a route is a path when its components are distinct, and it exists when all its arrows do. Cuts are tested against the paths found. | H2: The paths the notebook enumerated (engine), re-verified: arrows used on each path | Q2: =Declarations!B13 -> MKT | R2: =Declarations!B14 -> MKT | S2: =Declarations!B15 -> MKT | T2: =Declarations!B16 -> IND | U2: =Declarations!B17 -> DIG | V2: =Declarations!B18 -> MAT | W2: =Declarations!B19 -> TRS | X2: =Declarations!B20 -> TRS | Y2: =Declarations!B21 -> ENG | Z2: =Declarations!B22 -> IND | AA2: =Declarations!B23 -> ENG | AB2: =Declarations!B24 -> DIG | AC2: =Declarations!B25 -> GOV | AD2: =Declarations!B26 -> GOV
Q3: =Declarations!C13 -> IND | R3: =Declarations!C14 -> DIG | S3: =Declarations!C15 -> MAT | T3: =Declarations!C16 -> TRS | U3: =Declarations!C17 -> TRS | V3: =Declarations!C18 -> TRS | W3: =Declarations!C19 -> IND | X3: =Declarations!C20 -> DIG | Y3: =Declarations!C21 -> IND | Z3: =Declarations!C22 -> ENG | AA3: =Declarations!C23 -> DIG | AB3: =Declarations!C24 -> ENG | AC3: =Declarations!C25 -> TRS | AD3: =Declarations!C26 -> DIG
A4: Steps | B4: Route | C4: All arrows present | E4: Steps | F4: Simple paths | H4: Path | I4: 1 | J4: 2 | K4: 3 | L4: 4 | M4: 5 | N4: Steps | O4: Valid | Q4: =Q2&">"&Q3 -> MKT>IND | R4: =R2&">"&R3 -> MKT>DIG | S4: =S2&">"&S3 -> MKT>MAT | T4: =T2&">"&T3 -> IND>TRS | U4: =U2&">"&U3 -> DIG>TRS | V4: =V2&">"&V3 -> MAT>TRS | W4: =W2&">"&W3 -> TRS>IND | X4: =X2&">"&X3 -> TRS>DIG | ... AD4: =AD2&">"&AD3 -> GOV>DIG
A5: 1 | B5: MKT → TRS | C5: =Wiring!$H$6 -> 0 | E5: 1 | F5: =SUMIF($A$5:$A$330,E5,$C$5:$C$330) -> 0 | H5: 1 | I5: MKT | J5: IND | K5: TRS | N5: =COUNTIF(I5:M5,"?*")-1 -> 2 | O5: =IF(SUM(Q5:AD5)=N5,1,0) -> 1 | Q5: =IF(SUMPRODUCT(($I5:$L5=Q$2)*($J5:$M5=Q$3))>0,1,0) -> 1 | R5: =IF(SUMPRODUCT(($I5:$L5=R$2)*($J5:$M5=R$3))>0,1,0) -> 0 | S5: =IF(SUMPRODUCT(($I5:$L5=S$2)*($J5:$M5=S$3))>0,1,0) -> 0 | T5: =IF(SUMPRODUCT(($I5:$L5=T$2)*($J5:$M5=T$3))>0,1,0) -> 1 | U5: =IF(SUMPRODUCT(($I5:$L5=U$2)*($J5:$M5=U$3))>0,1,0) -> 0 | V5: =IF(SUMPRODUCT(($I5:$L5=V$2)*($J5:$M5=V$3))>0,1,0) -> 0 | W5: =IF(SUMPRODUCT(($I5:$L5=W$2)*($J5:$M5=W$3))>0,1,0) -> 0 | X5: =IF(SUMPRODUCT(($I5:$L5=X$2)*($J5:$M5=X$3))>0,1,0) -> 0 | ... AD5: =IF(SUMPRODUCT(($I5:$L5=AD$2)*($J5:$M5=AD$3))>0,1,0) -> 0
A6: 2 | B6: MKT → GOV → TRS | C6: =Wiring!$C$6*Wiring!$H$7 -> 0 | E6: 2 | F6: =SUMIF($A$5:$A$330,E6,$C$5:$C$330) -> 3 | H6: 2 | I6: MKT | J6: DIG | K6: TRS | N6: =COUNTIF(I6:M6,"?*")-1 -> 2 | O6: =IF(SUM(Q6:AD6)=N6,1,0) -> 1 | Q6: =IF(SUMPRODUCT(($I6:$L6=Q$2)*($J6:$M6=Q$3))>0,1,0) -> 0 | R6: =IF(SUMPRODUCT(($I6:$L6=R$2)*($J6:$M6=R$3))>0,1,0) -> 1 | S6: =IF(SUMPRODUCT(($I6:$L6=S$2)*($J6:$M6=S$3))>0,1,0) -> 0 | T6: =IF(SUMPRODUCT(($I6:$L6=T$2)*($J6:$M6=T$3))>0,1,0) -> 0 | U6: =IF(SUMPRODUCT(($I6:$L6=U$2)*($J6:$M6=U$3))>0,1,0) -> 1 | V6: =IF(SUMPRODUCT(($I6:$L6=V$2)*($J6:$M6=V$3))>0,1,0) -> 0 | W6: =IF(SUMPRODUCT(($I6:$L6=W$2)*($J6:$M6=W$3))>0,1,0) -> 0 | X6: =IF(SUMPRODUCT(($I6:$L6=X$2)*($J6:$M6=X$3))>0,1,0) -> 0 | ... AD6: =IF(SUMPRODUCT(($I6:$L6=AD$2)*($J6:$M6=AD$3))>0,1,0) -> 0
A7: 2 | B7: MKT → MAT → TRS | C7: =Wiring!$D$6*Wiring!$H$8 -> 1 | E7: 3 | F7: =SUMIF($A$5:$A$330,E7,$C$5:$C$330) -> 0 | H7: 3 | I7: MKT | J7: MAT | K7: TRS | N7: =COUNTIF(I7:M7,"?*")-1 -> 2 | O7: =IF(SUM(Q7:AD7)=N7,1,0) -> 1 | Q7: =IF(SUMPRODUCT(($I7:$L7=Q$2)*($J7:$M7=Q$3))>0,1,0) -> 0 | R7: =IF(SUMPRODUCT(($I7:$L7=R$2)*($J7:$M7=R$3))>0,1,0) -> 0 | S7: =IF(SUMPRODUCT(($I7:$L7=S$2)*($J7:$M7=S$3))>0,1,0) -> 1 | T7: =IF(SUMPRODUCT(($I7:$L7=T$2)*($J7:$M7=T$3))>0,1,0) -> 0 | U7: =IF(SUMPRODUCT(($I7:$L7=U$2)*($J7:$M7=U$3))>0,1,0) -> 0 | V7: =IF(SUMPRODUCT(($I7:$L7=V$2)*($J7:$M7=V$3))>0,1,0) -> 1 | W7: =IF(SUMPRODUCT(($I7:$L7=W$2)*($J7:$M7=W$3))>0,1,0) -> 0 | X7: =IF(SUMPRODUCT(($I7:$L7=X$2)*($J7:$M7=X$3))>0,1,0) -> 0 | ... AD7: =IF(SUMPRODUCT(($I7:$L7=AD$2)*($J7:$M7=AD$3))>0,1,0) -> 0
A8: 2 | B8: MKT → IND → TRS | C8: =Wiring!$E$6*Wiring!$H$9 -> 1 | E8: 4 | F8: =SUMIF($A$5:$A$330,E8,$C$5:$C$330) -> 2 | H8: 4 | I8: MKT | J8: IND | K8: ENG | L8: DIG | M8: TRS | N8: =COUNTIF(I8:M8,"?*")-1 -> 4 | O8: =IF(SUM(Q8:AD8)=N8,1,0) -> 1 | Q8: =IF(SUMPRODUCT(($I8:$L8=Q$2)*($J8:$M8=Q$3))>0,1,0) -> 1 | R8: =IF(SUMPRODUCT(($I8:$L8=R$2)*($J8:$M8=R$3))>0,1,0) -> 0 | S8: =IF(SUMPRODUCT(($I8:$L8=S$2)*($J8:$M8=S$3))>0,1,0) -> 0 | T8: =IF(SUMPRODUCT(($I8:$L8=T$2)*($J8:$M8=T$3))>0,1,0) -> 0 | U8: =IF(SUMPRODUCT(($I8:$L8=U$2)*($J8:$M8=U$3))>0,1,0) -> 1 | V8: =IF(SUMPRODUCT(($I8:$L8=V$2)*($J8:$M8=V$3))>0,1,0) -> 0 | W8: =IF(SUMPRODUCT(($I8:$L8=W$2)*($J8:$M8=W$3))>0,1,0) -> 0 | X8: =IF(SUMPRODUCT(($I8:$L8=X$2)*($J8:$M8=X$3))>0,1,0) -> 0 | ... AD8: =IF(SUMPRODUCT(($I8:$L8=AD$2)*($J8:$M8=AD$3))>0,1,0) -> 0
A9: 2 | B9: MKT → DIG → TRS | C9: =Wiring!$F$6*Wiring!$H$10 -> 1 | E9: 5 | F9: =SUMIF($A$5:$A$330,E9,$C$5:$C$330) -> 0 | H9: 5 | I9: MKT | J9: DIG | K9: ENG | L9: IND | M9: TRS | N9: =COUNTIF(I9:M9,"?*")-1 -> 4 | O9: =IF(SUM(Q9:AD9)=N9,1,0) -> 1 | Q9: =IF(SUMPRODUCT(($I9:$L9=Q$2)*($J9:$M9=Q$3))>0,1,0) -> 0 | R9: =IF(SUMPRODUCT(($I9:$L9=R$2)*($J9:$M9=R$3))>0,1,0) -> 1 | S9: =IF(SUMPRODUCT(($I9:$L9=S$2)*($J9:$M9=S$3))>0,1,0) -> 0 | T9: =IF(SUMPRODUCT(($I9:$L9=T$2)*($J9:$M9=T$3))>0,1,0) -> 1 | U9: =IF(SUMPRODUCT(($I9:$L9=U$2)*($J9:$M9=U$3))>0,1,0) -> 0 | V9: =IF(SUMPRODUCT(($I9:$L9=V$2)*($J9:$M9=V$3))>0,1,0) -> 0 | W9: =IF(SUMPRODUCT(($I9:$L9=W$2)*($J9:$M9=W$3))>0,1,0) -> 0 | X9: =IF(SUMPRODUCT(($I9:$L9=X$2)*($J9:$M9=X$3))>0,1,0) -> 0 | ... AD9: =IF(SUMPRODUCT(($I9:$L9=AD$2)*($J9:$M9=AD$3))>0,1,0) -> 0
A10: 2 | B10: MKT → ENG → TRS | C10: =Wiring!$G$6*Wiring!$H$11 -> 0 | E10: 6 | F10: =SUMIF($A$5:$A$330,E10,$C$5:$C$330) -> 0
A11: 3 | B11: MKT → GOV → MAT → TRS | C11: =Wiring!$C$6*Wiring!$D$7*Wiring!$H$8 -> 0 | E11: All | F11: =SUM(F5:F10) -> 5 | P11: two-step paths using it | Q11: =SUMPRODUCT(($N$5:$N$9=2)*(Q5:Q9)) -> 1 | R11: =SUMPRODUCT(($N$5:$N$9=2)*(R5:R9)) -> 1 | S11: =SUMPRODUCT(($N$5:$N$9=2)*(S5:S9)) -> 1 | T11: =SUMPRODUCT(($N$5:$N$9=2)*(T5:T9)) -> 1 | U11: =SUMPRODUCT(($N$5:$N$9=2)*(U5:U9)) -> 1 | V11: =SUMPRODUCT(($N$5:$N$9=2)*(V5:V9)) -> 1 | W11: =SUMPRODUCT(($N$5:$N$9=2)*(W5:W9)) -> 0 | X11: =SUMPRODUCT(($N$5:$N$9=2)*(X5:X9)) -> 0 | ... AD11: =SUMPRODUCT(($N$5:$N$9=2)*(AD5:AD9)) -> 0
A12: 3 | B12: MKT → GOV → IND → TRS | C12: =Wiring!$C$6*Wiring!$E$7*Wiring!$H$9 -> 0 | P12: paths left if it alone is cut | Q12: =SUMPRODUCT(1-Q5:Q9) -> 3 | R12: =SUMPRODUCT(1-R5:R9) -> 3 | S12: =SUMPRODUCT(1-S5:S9) -> 4 | T12: =SUMPRODUCT(1-T5:T9) -> 3 | U12: =SUMPRODUCT(1-U5:U9) -> 3 | V12: =SUMPRODUCT(1-V5:V9) -> 4 | W12: =SUMPRODUCT(1-W5:W9) -> 5 | X12: =SUMPRODUCT(1-X5:X9) -> 5 | ... AD12: =SUMPRODUCT(1-AD5:AD9) -> 5
A13: 3 | B13: MKT → GOV → DIG → TRS | C13: =Wiring!$C$6*Wiring!$F$7*Wiring!$H$10 -> 0
A14: 3 | B14: MKT → GOV → ENG → TRS | C14: =Wiring!$C$6*Wiring!$G$7*Wiring!$H$11 -> 0 | E14: Simple paths from the market to treasury | F14: =F11 -> 5 | G14: Step 3: five
A15: 3 | B15: MKT → MAT → GOV → TRS | C15: =Wiring!$D$6*Wiring!$C$8*Wiring!$H$7 -> 0 | E15: of two steps | F15: =F6 -> 3 | G15: three, one through each division | P15: First arrow | Q15: Second arrow | R15: Paths left
A16: 3 | B16: MKT → MAT → IND → TRS | C16: =Wiring!$D$6*Wiring!$E$8*Wiring!$H$9 -> 0 | E16: of four steps | F16: =F8 -> 2 | G16: two, through engineering | P16: =Q$4 -> MKT>IND | Q16: =R$4 -> MKT>DIG | R16: =SUMPRODUCT((1-Q$5:Q$9)*(1-R$5:R$9)) -> 1
A17: 3 | B17: MKT → MAT → DIG → TRS | C17: =Wiring!$D$6*Wiring!$F$8*Wiring!$H$10 -> 0 | E17: Paths verified from the notebook's list | F17: =SUM(O5:O9) -> 5 | P17: =Q$4 -> MKT>IND | Q17: =S$4 -> MKT>MAT | R17: =SUMPRODUCT((1-Q$5:Q$9)*(1-S$5:S$9)) -> 2
A18: 3 | B18: MKT → MAT → ENG → TRS | C18: =Wiring!$D$6*Wiring!$G$8*Wiring!$H$11 -> 0 | E18: Arrows shared by two-step paths | F18: =COUNTIF(Q11:AD11,">1") -> 0 | G18: none | P18: =Q$4 -> MKT>IND | Q18: =T$4 -> IND>TRS | R18: =SUMPRODUCT((1-Q$5:Q$9)*(1-T$5:T$9)) -> 2
A19: 3 | B19: MKT → IND → GOV → TRS | C19: =Wiring!$E$6*Wiring!$C$9*Wiring!$H$7 -> 0 | E19: Paths sharing no arrow (two-step paths, none shared) | F19: =IF(F18=0,F6,"check") -> 3 | G19: three | P19: =Q$4 -> MKT>IND | Q19: =U$4 -> DIG>TRS | R19: =SUMPRODUCT((1-Q$5:Q$9)*(1-U$5:U$9)) -> 2
A20: 3 | B20: MKT → IND → MAT → TRS | C20: =Wiring!$E$6*Wiring!$D$9*Wiring!$H$8 -> 0 | E20: Single arrows whose cut separates | F20: =COUNTIF(Q12:AD12,0) -> 0 | G20: none | P20: =Q$4 -> MKT>IND | Q20: =V$4 -> MAT>TRS | R20: =SUMPRODUCT((1-Q$5:Q$9)*(1-V$5:V$9)) -> 2
A21: 3 | B21: MKT → IND → DIG → TRS | C21: =Wiring!$E$6*Wiring!$F$9*Wiring!$H$10 -> 0 | E21: Pairs of arrows whose cut separates | F21: =COUNTIF(R16:R106,0) -> 0 | G21: none | P21: =Q$4 -> MKT>IND | Q21: =W$4 -> TRS>IND | R21: =SUMPRODUCT((1-Q$5:Q$9)*(1-W$5:W$9)) -> 3
A22: 3 | B22: MKT → IND → ENG → TRS | C22: =Wiring!$E$6*Wiring!$G$9*Wiring!$H$11 -> 0 | E22: Paths left after cutting the three cash arrows | F22: =SUMPRODUCT((1-T$5:T$9)*(1-U$5:U$9)*(1-V$5:V$9)) -> 0 | G22: none: the cut separates | P22: =Q$4 -> MKT>IND | Q22: =X$4 -> TRS>DIG | R22: =SUMPRODUCT((1-Q$5:Q$9)*(1-X$5:X$9)) -> 3
A23: 3 | B23: MKT → DIG → GOV → TRS | C23: =Wiring!$F$6*Wiring!$C$10*Wiring!$H$7 -> 0 | E23: Paths left after cutting the three demand arrows | F23: =SUMPRODUCT((1-Q$5:Q$9)*(1-R$5:R$9)*(1-S$5:S$9)) -> 0 | G23: none: the cut separates | P23: =Q$4 -> MKT>IND | Q23: =Y$4 -> ENG>IND | R23: =SUMPRODUCT((1-Q$5:Q$9)*(1-Y$5:Y$9)) -> 2
A24: 3 | B24: MKT → DIG → MAT → TRS | C24: =Wiring!$F$6*Wiring!$D$10*Wiring!$H$8 -> 0 | E24: Fewest arrows to cut | F24: =IF(F20>0,1,IF(F21>0,2,IF(MIN(F22,F23)=0,3,"more than 3"))) -> 3 | G24: three: as many as the paths sharing no arrow | P24: =Q$4 -> MKT>IND | Q24: =Z$4 -> IND>ENG | R24: =SUMPRODUCT((1-Q$5:Q$9)*(1-Z$5:Z$9)) -> 3
A25: 3 | B25: MKT → DIG → IND → TRS | C25: =Wiring!$F$6*Wiring!$E$10*Wiring!$H$9 -> 0 | P25: =Q$4 -> MKT>IND | Q25: =AA$4 -> ENG>DIG | R25: =SUMPRODUCT((1-Q$5:Q$9)*(1-AA$5:AA$9)) -> 3
A26: 3 | B26: MKT → DIG → ENG → TRS | C26: =Wiring!$F$6*Wiring!$G$10*Wiring!$H$11 -> 0 | P26: =Q$4 -> MKT>IND | Q26: =AB$4 -> DIG>ENG | R26: =SUMPRODUCT((1-Q$5:Q$9)*(1-AB$5:AB$9)) -> 2
A27: 3 | B27: MKT → ENG → GOV → TRS | C27: =Wiring!$G$6*Wiring!$C$11*Wiring!$H$7 -> 0 | P27: =Q$4 -> MKT>IND | Q27: =AC$4 -> GOV>TRS | R27: =SUMPRODUCT((1-Q$5:Q$9)*(1-AC$5:AC$9)) -> 3
A28: 3 | B28: MKT → ENG → MAT → TRS | C28: =Wiring!$G$6*Wiring!$D$11*Wiring!$H$8 -> 0 | P28: =Q$4 -> MKT>IND | Q28: =AD$4 -> GOV>DIG | R28: =SUMPRODUCT((1-Q$5:Q$9)*(1-AD$5:AD$9)) -> 3
A29: 3 | B29: MKT → ENG → IND → TRS | C29: =Wiring!$G$6*Wiring!$E$11*Wiring!$H$9 -> 0 | P29: =R$4 -> MKT>DIG | Q29: =S$4 -> MKT>MAT | R29: =SUMPRODUCT((1-R$5:R$9)*(1-S$5:S$9)) -> 2
A30: 3 | B30: MKT → ENG → DIG → TRS | C30: =Wiring!$G$6*Wiring!$F$11*Wiring!$H$10 -> 0 | P30: =R$4 -> MKT>DIG | Q30: =T$4 -> IND>TRS | R30: =SUMPRODUCT((1-R$5:R$9)*(1-T$5:T$9)) -> 2
A31: 4 | B31: MKT → GOV → MAT → IND → TRS | C31: =Wiring!$C$6*Wiring!$D$7*Wiring!$E$8*Wiring!$H$9 -> 0 | P31: =R$4 -> MKT>DIG | Q31: =U$4 -> DIG>TRS | R31: =SUMPRODUCT((1-R$5:R$9)*(1-U$5:U$9)) -> 2
A32: 4 | B32: MKT → GOV → MAT → DIG → TRS | C32: =Wiring!$C$6*Wiring!$D$7*Wiring!$F$8*Wiring!$H$10 -> 0 | P32: =R$4 -> MKT>DIG | Q32: =V$4 -> MAT>TRS | R32: =SUMPRODUCT((1-R$5:R$9)*(1-V$5:V$9)) -> 2
A33: 4 | B33: MKT → GOV → MAT → ENG → TRS | C33: =Wiring!$C$6*Wiring!$D$7*Wiring!$G$8*Wiring!$H$11 -> 0 | P33: =R$4 -> MKT>DIG | Q33: =W$4 -> TRS>IND | R33: =SUMPRODUCT((1-R$5:R$9)*(1-W$5:W$9)) -> 3
A34: 4 | B34: MKT → GOV → IND → MAT → TRS | C34: =Wiring!$C$6*Wiring!$E$7*Wiring!$D$9*Wiring!$H$8 -> 0 | P34: =R$4 -> MKT>DIG | Q34: =X$4 -> TRS>DIG | R34: =SUMPRODUCT((1-R$5:R$9)*(1-X$5:X$9)) -> 3
A35: 4 | B35: MKT → GOV → IND → DIG → TRS | C35: =Wiring!$C$6*Wiring!$E$7*Wiring!$F$9*Wiring!$H$10 -> 0 | P35: =R$4 -> MKT>DIG | Q35: =Y$4 -> ENG>IND | R35: =SUMPRODUCT((1-R$5:R$9)*(1-Y$5:Y$9)) -> 3
A36: 4 | B36: MKT → GOV → IND → ENG → TRS | C36: =Wiring!$C$6*Wiring!$E$7*Wiring!$G$9*Wiring!$H$11 -> 0 | P36: =R$4 -> MKT>DIG | Q36: =Z$4 -> IND>ENG | R36: =SUMPRODUCT((1-R$5:R$9)*(1-Z$5:Z$9)) -> 2
A37: 4 | B37: MKT → GOV → DIG → MAT → TRS | C37: =Wiring!$C$6*Wiring!$F$7*Wiring!$D$10*Wiring!$H$8 -> 0 | P37: =R$4 -> MKT>DIG | Q37: =AA$4 -> ENG>DIG | R37: =SUMPRODUCT((1-R$5:R$9)*(1-AA$5:AA$9)) -> 2
A38: 4 | B38: MKT → GOV → DIG → IND → TRS | C38: =Wiring!$C$6*Wiring!$F$7*Wiring!$E$10*Wiring!$H$9 -> 0 | P38: =R$4 -> MKT>DIG | Q38: =AB$4 -> DIG>ENG | R38: =SUMPRODUCT((1-R$5:R$9)*(1-AB$5:AB$9)) -> 3
A39: 4 | B39: MKT → GOV → DIG → ENG → TRS | C39: =Wiring!$C$6*Wiring!$F$7*Wiring!$G$10*Wiring!$H$11 -> 0 | P39: =R$4 -> MKT>DIG | Q39: =AC$4 -> GOV>TRS | R39: =SUMPRODUCT((1-R$5:R$9)*(1-AC$5:AC$9)) -> 3
A40: 4 | B40: MKT → GOV → ENG → MAT → TRS | C40: =Wiring!$C$6*Wiring!$G$7*Wiring!$D$11*Wiring!$H$8 -> 0 | P40: =R$4 -> MKT>DIG | Q40: =AD$4 -> GOV>DIG | R40: =SUMPRODUCT((1-R$5:R$9)*(1-AD$5:AD$9)) -> 3
A41: 4 | B41: MKT → GOV → ENG → IND → TRS | C41: =Wiring!$C$6*Wiring!$G$7*Wiring!$E$11*Wiring!$H$9 -> 0 | P41: =S$4 -> MKT>MAT | Q41: =T$4 -> IND>TRS | R41: =SUMPRODUCT((1-S$5:S$9)*(1-T$5:T$9)) -> 2
A42: 4 | B42: MKT → GOV → ENG → DIG → TRS | C42: =Wiring!$C$6*Wiring!$G$7*Wiring!$F$11*Wiring!$H$10 -> 0 | P42: =S$4 -> MKT>MAT | Q42: =U$4 -> DIG>TRS | R42: =SUMPRODUCT((1-S$5:S$9)*(1-U$5:U$9)) -> 2
A43: 4 | B43: MKT → MAT → GOV → IND → TRS | C43: =Wiring!$D$6*Wiring!$C$8*Wiring!$E$7*Wiring!$H$9 -> 0 | P43: =S$4 -> MKT>MAT | Q43: =V$4 -> MAT>TRS | R43: =SUMPRODUCT((1-S$5:S$9)*(1-V$5:V$9)) -> 4
A44: 4 | B44: MKT → MAT → GOV → DIG → TRS | C44: =Wiring!$D$6*Wiring!$C$8*Wiring!$F$7*Wiring!$H$10 -> 0 | P44: =S$4 -> MKT>MAT | Q44: =W$4 -> TRS>IND | R44: =SUMPRODUCT((1-S$5:S$9)*(1-W$5:W$9)) -> 4
A45: 4 | B45: MKT → MAT → GOV → ENG → TRS | C45: =Wiring!$D$6*Wiring!$C$8*Wiring!$G$7*Wiring!$H$11 -> 0 | P45: =S$4 -> MKT>MAT | Q45: =X$4 -> TRS>DIG | R45: =SUMPRODUCT((1-S$5:S$9)*(1-X$5:X$9)) -> 4
A46: 4 | B46: MKT → MAT → IND → GOV → TRS | C46: =Wiring!$D$6*Wiring!$E$8*Wiring!$C$9*Wiring!$H$7 -> 0 | P46: =S$4 -> MKT>MAT | Q46: =Y$4 -> ENG>IND | R46: =SUMPRODUCT((1-S$5:S$9)*(1-Y$5:Y$9)) -> 3
A47: 4 | B47: MKT → MAT → IND → DIG → TRS | C47: =Wiring!$D$6*Wiring!$E$8*Wiring!$F$9*Wiring!$H$10 -> 0 | P47: =S$4 -> MKT>MAT | Q47: =Z$4 -> IND>ENG | R47: =SUMPRODUCT((1-S$5:S$9)*(1-Z$5:Z$9)) -> 3
A48: 4 | B48: MKT → MAT → IND → ENG → TRS | C48: =Wiring!$D$6*Wiring!$E$8*Wiring!$G$9*Wiring!$H$11 -> 0 | P48: =S$4 -> MKT>MAT | Q48: =AA$4 -> ENG>DIG | R48: =SUMPRODUCT((1-S$5:S$9)*(1-AA$5:AA$9)) -> 3
A49: 4 | B49: MKT → MAT → DIG → GOV → TRS | C49: =Wiring!$D$6*Wiring!$F$8*Wiring!$C$10*Wiring!$H$7 -> 0 | P49: =S$4 -> MKT>MAT | Q49: =AB$4 -> DIG>ENG | R49: =SUMPRODUCT((1-S$5:S$9)*(1-AB$5:AB$9)) -> 3
A50: 4 | B50: MKT → MAT → DIG → IND → TRS | C50: =Wiring!$D$6*Wiring!$F$8*Wiring!$E$10*Wiring!$H$9 -> 0 | P50: =S$4 -> MKT>MAT | Q50: =AC$4 -> GOV>TRS | R50: =SUMPRODUCT((1-S$5:S$9)*(1-AC$5:AC$9)) -> 4
A51: 4 | B51: MKT → MAT → DIG → ENG → TRS | C51: =Wiring!$D$6*Wiring!$F$8*Wiring!$G$10*Wiring!$H$11 -> 0 | P51: =S$4 -> MKT>MAT | Q51: =AD$4 -> GOV>DIG | R51: =SUMPRODUCT((1-S$5:S$9)*(1-AD$5:AD$9)) -> 4
A52: 4 | B52: MKT → MAT → ENG → GOV → TRS | C52: =Wiring!$D$6*Wiring!$G$8*Wiring!$C$11*Wiring!$H$7 -> 0 | P52: =T$4 -> IND>TRS | Q52: =U$4 -> DIG>TRS | R52: =SUMPRODUCT((1-T$5:T$9)*(1-U$5:U$9)) -> 1
A53: 4 | B53: MKT → MAT → ENG → IND → TRS | C53: =Wiring!$D$6*Wiring!$G$8*Wiring!$E$11*Wiring!$H$9 -> 0 | P53: =T$4 -> IND>TRS | Q53: =V$4 -> MAT>TRS | R53: =SUMPRODUCT((1-T$5:T$9)*(1-V$5:V$9)) -> 2
A54: 4 | B54: MKT → MAT → ENG → DIG → TRS | C54: =Wiring!$D$6*Wiring!$G$8*Wiring!$F$11*Wiring!$H$10 -> 0 | P54: =T$4 -> IND>TRS | Q54: =W$4 -> TRS>IND | R54: =SUMPRODUCT((1-T$5:T$9)*(1-W$5:W$9)) -> 3
A55: 4 | B55: MKT → IND → GOV → MAT → TRS | C55: =Wiring!$E$6*Wiring!$C$9*Wiring!$D$7*Wiring!$H$8 -> 0 | P55: =T$4 -> IND>TRS | Q55: =X$4 -> TRS>DIG | R55: =SUMPRODUCT((1-T$5:T$9)*(1-X$5:X$9)) -> 3
A56: 4 | B56: MKT → IND → GOV → DIG → TRS | C56: =Wiring!$E$6*Wiring!$C$9*Wiring!$F$7*Wiring!$H$10 -> 0 | P56: =T$4 -> IND>TRS | Q56: =Y$4 -> ENG>IND | R56: =SUMPRODUCT((1-T$5:T$9)*(1-Y$5:Y$9)) -> 3
A57: 4 | B57: MKT → IND → GOV → ENG → TRS | C57: =Wiring!$E$6*Wiring!$C$9*Wiring!$G$7*Wiring!$H$11 -> 0 | P57: =T$4 -> IND>TRS | Q57: =Z$4 -> IND>ENG | R57: =SUMPRODUCT((1-T$5:T$9)*(1-Z$5:Z$9)) -> 2
A58: 4 | B58: MKT → IND → MAT → GOV → TRS | C58: =Wiring!$E$6*Wiring!$D$9*Wiring!$C$8*Wiring!$H$7 -> 0 | P58: =T$4 -> IND>TRS | Q58: =AA$4 -> ENG>DIG | R58: =SUMPRODUCT((1-T$5:T$9)*(1-AA$5:AA$9)) -> 2
A59: 4 | B59: MKT → IND → MAT → DIG → TRS | C59: =Wiring!$E$6*Wiring!$D$9*Wiring!$F$8*Wiring!$H$10 -> 0 | P59: =T$4 -> IND>TRS | Q59: =AB$4 -> DIG>ENG | R59: =SUMPRODUCT((1-T$5:T$9)*(1-AB$5:AB$9)) -> 3
A60: 4 | B60: MKT → IND → MAT → ENG → TRS | C60: =Wiring!$E$6*Wiring!$D$9*Wiring!$G$8*Wiring!$H$11 -> 0 | P60: =T$4 -> IND>TRS | Q60: =AC$4 -> GOV>TRS | R60: =SUMPRODUCT((1-T$5:T$9)*(1-AC$5:AC$9)) -> 3
A61: 4 | B61: MKT → IND → DIG → GOV → TRS | C61: =Wiring!$E$6*Wiring!$F$9*Wiring!$C$10*Wiring!$H$7 -> 0 | P61: =T$4 -> IND>TRS | Q61: =AD$4 -> GOV>DIG | R61: =SUMPRODUCT((1-T$5:T$9)*(1-AD$5:AD$9)) -> 3
A62: 4 | B62: MKT → IND → DIG → MAT → TRS | C62: =Wiring!$E$6*Wiring!$F$9*Wiring!$D$10*Wiring!$H$8 -> 0 | P62: =U$4 -> DIG>TRS | Q62: =V$4 -> MAT>TRS | R62: =SUMPRODUCT((1-U$5:U$9)*(1-V$5:V$9)) -> 2
A63: 4 | B63: MKT → IND → DIG → ENG → TRS | C63: =Wiring!$E$6*Wiring!$F$9*Wiring!$G$10*Wiring!$H$11 -> 0 | P63: =U$4 -> DIG>TRS | Q63: =W$4 -> TRS>IND | R63: =SUMPRODUCT((1-U$5:U$9)*(1-W$5:W$9)) -> 3
A64: 4 | B64: MKT → IND → ENG → GOV → TRS | C64: =Wiring!$E$6*Wiring!$G$9*Wiring!$C$11*Wiring!$H$7 -> 0 | P64: =U$4 -> DIG>TRS | Q64: =X$4 -> TRS>DIG | R64: =SUMPRODUCT((1-U$5:U$9)*(1-X$5:X$9)) -> 3
A65: 4 | B65: MKT → IND → ENG → MAT → TRS | C65: =Wiring!$E$6*Wiring!$G$9*Wiring!$D$11*Wiring!$H$8 -> 0 | P65: =U$4 -> DIG>TRS | Q65: =Y$4 -> ENG>IND | R65: =SUMPRODUCT((1-U$5:U$9)*(1-Y$5:Y$9)) -> 2
A66: 4 | B66: MKT → IND → ENG → DIG → TRS | C66: =Wiring!$E$6*Wiring!$G$9*Wiring!$F$11*Wiring!$H$10 -> 1 | P66: =U$4 -> DIG>TRS | Q66: =Z$4 -> IND>ENG | R66: =SUMPRODUCT((1-U$5:U$9)*(1-Z$5:Z$9)) -> 3
A67: 4 | B67: MKT → DIG → GOV → MAT → TRS | C67: =Wiring!$F$6*Wiring!$C$10*Wiring!$D$7*Wiring!$H$8 -> 0 | P67: =U$4 -> DIG>TRS | Q67: =AA$4 -> ENG>DIG | R67: =SUMPRODUCT((1-U$5:U$9)*(1-AA$5:AA$9)) -> 3
A68: 4 | B68: MKT → DIG → GOV → IND → TRS | C68: =Wiring!$F$6*Wiring!$C$10*Wiring!$E$7*Wiring!$H$9 -> 0 | P68: =U$4 -> DIG>TRS | Q68: =AB$4 -> DIG>ENG | R68: =SUMPRODUCT((1-U$5:U$9)*(1-AB$5:AB$9)) -> 2
A69: 4 | B69: MKT → DIG → GOV → ENG → TRS | C69: =Wiring!$F$6*Wiring!$C$10*Wiring!$G$7*Wiring!$H$11 -> 0 | P69: =U$4 -> DIG>TRS | Q69: =AC$4 -> GOV>TRS | R69: =SUMPRODUCT((1-U$5:U$9)*(1-AC$5:AC$9)) -> 3
A70: 4 | B70: MKT → DIG → MAT → GOV → TRS | C70: =Wiring!$F$6*Wiring!$D$10*Wiring!$C$8*Wiring!$H$7 -> 0 | P70: =U$4 -> DIG>TRS | Q70: =AD$4 -> GOV>DIG | R70: =SUMPRODUCT((1-U$5:U$9)*(1-AD$5:AD$9)) -> 3
A71: 4 | B71: MKT → DIG → MAT → IND → TRS | C71: =Wiring!$F$6*Wiring!$D$10*Wiring!$E$8*Wiring!$H$9 -> 0 | P71: =V$4 -> MAT>TRS | Q71: =W$4 -> TRS>IND | R71: =SUMPRODUCT((1-V$5:V$9)*(1-W$5:W$9)) -> 4
A72: 4 | B72: MKT → DIG → MAT → ENG → TRS | C72: =Wiring!$F$6*Wiring!$D$10*Wiring!$G$8*Wiring!$H$11 -> 0 | P72: =V$4 -> MAT>TRS | Q72: =X$4 -> TRS>DIG | R72: =SUMPRODUCT((1-V$5:V$9)*(1-X$5:X$9)) -> 4
A73: 4 | B73: MKT → DIG → IND → GOV → TRS | C73: =Wiring!$F$6*Wiring!$E$10*Wiring!$C$9*Wiring!$H$7 -> 0 | P73: =V$4 -> MAT>TRS | Q73: =Y$4 -> ENG>IND | R73: =SUMPRODUCT((1-V$5:V$9)*(1-Y$5:Y$9)) -> 3
A74: 4 | B74: MKT → DIG → IND → MAT → TRS | C74: =Wiring!$F$6*Wiring!$E$10*Wiring!$D$9*Wiring!$H$8 -> 0 | P74: =V$4 -> MAT>TRS | Q74: =Z$4 -> IND>ENG | R74: =SUMPRODUCT((1-V$5:V$9)*(1-Z$5:Z$9)) -> 3
A75: 4 | B75: MKT → DIG → IND → ENG → TRS | C75: =Wiring!$F$6*Wiring!$E$10*Wiring!$G$9*Wiring!$H$11 -> 0 | P75: =V$4 -> MAT>TRS | Q75: =AA$4 -> ENG>DIG | R75: =SUMPRODUCT((1-V$5:V$9)*(1-AA$5:AA$9)) -> 3
A76: 4 | B76: MKT → DIG → ENG → GOV → TRS | C76: =Wiring!$F$6*Wiring!$G$10*Wiring!$C$11*Wiring!$H$7 -> 0 | P76: =V$4 -> MAT>TRS | Q76: =AB$4 -> DIG>ENG | R76: =SUMPRODUCT((1-V$5:V$9)*(1-AB$5:AB$9)) -> 3
A77: 4 | B77: MKT → DIG → ENG → MAT → TRS | C77: =Wiring!$F$6*Wiring!$G$10*Wiring!$D$11*Wiring!$H$8 -> 0 | P77: =V$4 -> MAT>TRS | Q77: =AC$4 -> GOV>TRS | R77: =SUMPRODUCT((1-V$5:V$9)*(1-AC$5:AC$9)) -> 4
A78: 4 | B78: MKT → DIG → ENG → IND → TRS | C78: =Wiring!$F$6*Wiring!$G$10*Wiring!$E$11*Wiring!$H$9 -> 1 | P78: =V$4 -> MAT>TRS | Q78: =AD$4 -> GOV>DIG | R78: =SUMPRODUCT((1-V$5:V$9)*(1-AD$5:AD$9)) -> 4
A79: 4 | B79: MKT → ENG → GOV → MAT → TRS | C79: =Wiring!$G$6*Wiring!$C$11*Wiring!$D$7*Wiring!$H$8 -> 0 | P79: =W$4 -> TRS>IND | Q79: =X$4 -> TRS>DIG | R79: =SUMPRODUCT((1-W$5:W$9)*(1-X$5:X$9)) -> 5
A80: 4 | B80: MKT → ENG → GOV → IND → TRS | C80: =Wiring!$G$6*Wiring!$C$11*Wiring!$E$7*Wiring!$H$9 -> 0 | P80: =W$4 -> TRS>IND | Q80: =Y$4 -> ENG>IND | R80: =SUMPRODUCT((1-W$5:W$9)*(1-Y$5:Y$9)) -> 4
A81: 4 | B81: MKT → ENG → GOV → DIG → TRS | C81: =Wiring!$G$6*Wiring!$C$11*Wiring!$F$7*Wiring!$H$10 -> 0 | P81: =W$4 -> TRS>IND | Q81: =Z$4 -> IND>ENG | R81: =SUMPRODUCT((1-W$5:W$9)*(1-Z$5:Z$9)) -> 4
A82: 4 | B82: MKT → ENG → MAT → GOV → TRS | C82: =Wiring!$G$6*Wiring!$D$11*Wiring!$C$8*Wiring!$H$7 -> 0 | P82: =W$4 -> TRS>IND | Q82: =AA$4 -> ENG>DIG | R82: =SUMPRODUCT((1-W$5:W$9)*(1-AA$5:AA$9)) -> 4
A83: 4 | B83: MKT → ENG → MAT → IND → TRS | C83: =Wiring!$G$6*Wiring!$D$11*Wiring!$E$8*Wiring!$H$9 -> 0 | P83: =W$4 -> TRS>IND | Q83: =AB$4 -> DIG>ENG | R83: =SUMPRODUCT((1-W$5:W$9)*(1-AB$5:AB$9)) -> 4
A84: 4 | B84: MKT → ENG → MAT → DIG → TRS | C84: =Wiring!$G$6*Wiring!$D$11*Wiring!$F$8*Wiring!$H$10 -> 0 | P84: =W$4 -> TRS>IND | Q84: =AC$4 -> GOV>TRS | R84: =SUMPRODUCT((1-W$5:W$9)*(1-AC$5:AC$9)) -> 5
A85: 4 | B85: MKT → ENG → IND → GOV → TRS | C85: =Wiring!$G$6*Wiring!$E$11*Wiring!$C$9*Wiring!$H$7 -> 0 | P85: =W$4 -> TRS>IND | Q85: =AD$4 -> GOV>DIG | R85: =SUMPRODUCT((1-W$5:W$9)*(1-AD$5:AD$9)) -> 5
A86: 4 | B86: MKT → ENG → IND → MAT → TRS | C86: =Wiring!$G$6*Wiring!$E$11*Wiring!$D$9*Wiring!$H$8 -> 0 | P86: =X$4 -> TRS>DIG | Q86: =Y$4 -> ENG>IND | R86: =SUMPRODUCT((1-X$5:X$9)*(1-Y$5:Y$9)) -> 4
A87: 4 | B87: MKT → ENG → IND → DIG → TRS | C87: =Wiring!$G$6*Wiring!$E$11*Wiring!$F$9*Wiring!$H$10 -> 0 | P87: =X$4 -> TRS>DIG | Q87: =Z$4 -> IND>ENG | R87: =SUMPRODUCT((1-X$5:X$9)*(1-Z$5:Z$9)) -> 4
A88: 4 | B88: MKT → ENG → DIG → GOV → TRS | C88: =Wiring!$G$6*Wiring!$F$11*Wiring!$C$10*Wiring!$H$7 -> 0 | P88: =X$4 -> TRS>DIG | Q88: =AA$4 -> ENG>DIG | R88: =SUMPRODUCT((1-X$5:X$9)*(1-AA$5:AA$9)) -> 4
A89: 4 | B89: MKT → ENG → DIG → MAT → TRS | C89: =Wiring!$G$6*Wiring!$F$11*Wiring!$D$10*Wiring!$H$8 -> 0 | P89: =X$4 -> TRS>DIG | Q89: =AB$4 -> DIG>ENG | R89: =SUMPRODUCT((1-X$5:X$9)*(1-AB$5:AB$9)) -> 4
A90: 4 | B90: MKT → ENG → DIG → IND → TRS | C90: =Wiring!$G$6*Wiring!$F$11*Wiring!$E$10*Wiring!$H$9 -> 0 | P90: =X$4 -> TRS>DIG | Q90: =AC$4 -> GOV>TRS | R90: =SUMPRODUCT((1-X$5:X$9)*(1-AC$5:AC$9)) -> 5
A91: 5 | B91: MKT → GOV → MAT → IND → DIG → TRS | C91: =Wiring!$C$6*Wiring!$D$7*Wiring!$E$8*Wiring!$F$9*Wiring!$H$10 -> 0 | P91: =X$4 -> TRS>DIG | Q91: =AD$4 -> GOV>DIG | R91: =SUMPRODUCT((1-X$5:X$9)*(1-AD$5:AD$9)) -> 5
A92: 5 | B92: MKT → GOV → MAT → IND → ENG → TRS | C92: =Wiring!$C$6*Wiring!$D$7*Wiring!$E$8*Wiring!$G$9*Wiring!$H$11 -> 0 | P92: =Y$4 -> ENG>IND | Q92: =Z$4 -> IND>ENG | R92: =SUMPRODUCT((1-Y$5:Y$9)*(1-Z$5:Z$9)) -> 3
A93: 5 | B93: MKT → GOV → MAT → DIG → IND → TRS | C93: =Wiring!$C$6*Wiring!$D$7*Wiring!$F$8*Wiring!$E$10*Wiring!$H$9 -> 0 | P93: =Y$4 -> ENG>IND | Q93: =AA$4 -> ENG>DIG | R93: =SUMPRODUCT((1-Y$5:Y$9)*(1-AA$5:AA$9)) -> 3
A94: 5 | B94: MKT → GOV → MAT → DIG → ENG → TRS | C94: =Wiring!$C$6*Wiring!$D$7*Wiring!$F$8*Wiring!$G$10*Wiring!$H$11 -> 0 | P94: =Y$4 -> ENG>IND | Q94: =AB$4 -> DIG>ENG | R94: =SUMPRODUCT((1-Y$5:Y$9)*(1-AB$5:AB$9)) -> 4
A95: 5 | B95: MKT → GOV → MAT → ENG → IND → TRS | C95: =Wiring!$C$6*Wiring!$D$7*Wiring!$G$8*Wiring!$E$11*Wiring!$H$9 -> 0 | P95: =Y$4 -> ENG>IND | Q95: =AC$4 -> GOV>TRS | R95: =SUMPRODUCT((1-Y$5:Y$9)*(1-AC$5:AC$9)) -> 4
A96: 5 | B96: MKT → GOV → MAT → ENG → DIG → TRS | C96: =Wiring!$C$6*Wiring!$D$7*Wiring!$G$8*Wiring!$F$11*Wiring!$H$10 -> 0 | P96: =Y$4 -> ENG>IND | Q96: =AD$4 -> GOV>DIG | R96: =SUMPRODUCT((1-Y$5:Y$9)*(1-AD$5:AD$9)) -> 4
A97: 5 | B97: MKT → GOV → IND → MAT → DIG → TRS | C97: =Wiring!$C$6*Wiring!$E$7*Wiring!$D$9*Wiring!$F$8*Wiring!$H$10 -> 0 | P97: =Z$4 -> IND>ENG | Q97: =AA$4 -> ENG>DIG | R97: =SUMPRODUCT((1-Z$5:Z$9)*(1-AA$5:AA$9)) -> 4
A98: 5 | B98: MKT → GOV → IND → MAT → ENG → TRS | C98: =Wiring!$C$6*Wiring!$E$7*Wiring!$D$9*Wiring!$G$8*Wiring!$H$11 -> 0 | P98: =Z$4 -> IND>ENG | Q98: =AB$4 -> DIG>ENG | R98: =SUMPRODUCT((1-Z$5:Z$9)*(1-AB$5:AB$9)) -> 3
A99: 5 | B99: MKT → GOV → IND → DIG → MAT → TRS | C99: =Wiring!$C$6*Wiring!$E$7*Wiring!$F$9*Wiring!$D$10*Wiring!$H$8 -> 0 | P99: =Z$4 -> IND>ENG | Q99: =AC$4 -> GOV>TRS | R99: =SUMPRODUCT((1-Z$5:Z$9)*(1-AC$5:AC$9)) -> 4
A100: 5 | B100: MKT → GOV → IND → DIG → ENG → TRS | C100: =Wiring!$C$6*Wiring!$E$7*Wiring!$F$9*Wiring!$G$10*Wiring!$H$11 -> 0 | P100: =Z$4 -> IND>ENG | Q100: =AD$4 -> GOV>DIG | R100: =SUMPRODUCT((1-Z$5:Z$9)*(1-AD$5:AD$9)) -> 4
...

Sheet SummaryMap
A1: Test the summary map: aggregation keeps real paths and can invent others (Worked Example 9.1, Step 5; Theorem 9.3; Figure 9.2; Online Appendix 9.B.3; AXIOM Lab 1.9, step 4)
A2: A connection is invented when the summary map joins the boxes of two components and no route joins the components themselves.
A4: The two-box map (the board's): market, operating divisions, corporate center | M4: The causal map: each strongly connected component one box (the core and the rest alone)
A5: Component | B5: Box | M5: Component | N5: Box
A6: MKT | B6: =INDEX(Box,1) -> market | M6: MKT | N6: =IF(Core!$K$94=1,"core","MKT") -> MKT
A7: GOV | B7: =INDEX(Box,2) -> center | M7: GOV | N7: =IF(Core!$K$95=1,"core","GOV") -> GOV
A8: MAT | B8: =INDEX(Box,3) -> divisions | M8: MAT | N8: =IF(Core!$K$96=1,"core","MAT") -> MAT
A9: IND | B9: =INDEX(Box,4) -> divisions | M9: IND | N9: =IF(Core!$K$97=1,"core","IND") -> core
A10: DIG | B10: =INDEX(Box,5) -> divisions | M10: DIG | N10: =IF(Core!$K$98=1,"core","DIG") -> core
A11: ENG | B11: =INDEX(Box,6) -> center | M11: ENG | N11: =IF(Core!$K$99=1,"core","ENG") -> core
A12: TRS | B12: =INDEX(Box,7) -> center | M12: TRS | N12: =IF(Core!$K$100=1,"core","TRS") -> core
A14: Arrow from | B14: to | C14: box from | D14: box to | M14: Arrow from | N14: to | O14: box from | P14: box to
A15: =Declarations!B13 -> MKT | B15: =Declarations!C13 -> IND | C15: =INDEX($B$6:$B$12,MATCH(A15,$A$6:$A$12,0)) -> market | D15: =INDEX($B$6:$B$12,MATCH(B15,$A$6:$A$12,0)) -> divisions | M15: =Declarations!B13 -> MKT | N15: =Declarations!C13 -> IND | O15: =INDEX($N$6:$N$12,MATCH(M15,$M$6:$M$12,0)) -> MKT | P15: =INDEX($N$6:$N$12,MATCH(N15,$M$6:$M$12,0)) -> core
A16: =Declarations!B14 -> MKT | B16: =Declarations!C14 -> DIG | C16: =INDEX($B$6:$B$12,MATCH(A16,$A$6:$A$12,0)) -> market | D16: =INDEX($B$6:$B$12,MATCH(B16,$A$6:$A$12,0)) -> divisions | M16: =Declarations!B14 -> MKT | N16: =Declarations!C14 -> DIG | O16: =INDEX($N$6:$N$12,MATCH(M16,$M$6:$M$12,0)) -> MKT | P16: =INDEX($N$6:$N$12,MATCH(N16,$M$6:$M$12,0)) -> core
A17: =Declarations!B15 -> MKT | B17: =Declarations!C15 -> MAT | C17: =INDEX($B$6:$B$12,MATCH(A17,$A$6:$A$12,0)) -> market | D17: =INDEX($B$6:$B$12,MATCH(B17,$A$6:$A$12,0)) -> divisions | M17: =Declarations!B15 -> MKT | N17: =Declarations!C15 -> MAT | O17: =INDEX($N$6:$N$12,MATCH(M17,$M$6:$M$12,0)) -> MKT | P17: =INDEX($N$6:$N$12,MATCH(N17,$M$6:$M$12,0)) -> MAT
A18: =Declarations!B16 -> IND | B18: =Declarations!C16 -> TRS | C18: =INDEX($B$6:$B$12,MATCH(A18,$A$6:$A$12,0)) -> divisions | D18: =INDEX($B$6:$B$12,MATCH(B18,$A$6:$A$12,0)) -> center | M18: =Declarations!B16 -> IND | N18: =Declarations!C16 -> TRS | O18: =INDEX($N$6:$N$12,MATCH(M18,$M$6:$M$12,0)) -> core | P18: =INDEX($N$6:$N$12,MATCH(N18,$M$6:$M$12,0)) -> core
A19: =Declarations!B17 -> DIG | B19: =Declarations!C17 -> TRS | C19: =INDEX($B$6:$B$12,MATCH(A19,$A$6:$A$12,0)) -> divisions | D19: =INDEX($B$6:$B$12,MATCH(B19,$A$6:$A$12,0)) -> center | M19: =Declarations!B17 -> DIG | N19: =Declarations!C17 -> TRS | O19: =INDEX($N$6:$N$12,MATCH(M19,$M$6:$M$12,0)) -> core | P19: =INDEX($N$6:$N$12,MATCH(N19,$M$6:$M$12,0)) -> core
A20: =Declarations!B18 -> MAT | B20: =Declarations!C18 -> TRS | C20: =INDEX($B$6:$B$12,MATCH(A20,$A$6:$A$12,0)) -> divisions | D20: =INDEX($B$6:$B$12,MATCH(B20,$A$6:$A$12,0)) -> center | M20: =Declarations!B18 -> MAT | N20: =Declarations!C18 -> TRS | O20: =INDEX($N$6:$N$12,MATCH(M20,$M$6:$M$12,0)) -> MAT | P20: =INDEX($N$6:$N$12,MATCH(N20,$M$6:$M$12,0)) -> core
A21: =Declarations!B19 -> TRS | B21: =Declarations!C19 -> IND | C21: =INDEX($B$6:$B$12,MATCH(A21,$A$6:$A$12,0)) -> center | D21: =INDEX($B$6:$B$12,MATCH(B21,$A$6:$A$12,0)) -> divisions | M21: =Declarations!B19 -> TRS | N21: =Declarations!C19 -> IND | O21: =INDEX($N$6:$N$12,MATCH(M21,$M$6:$M$12,0)) -> core | P21: =INDEX($N$6:$N$12,MATCH(N21,$M$6:$M$12,0)) -> core
A22: =Declarations!B20 -> TRS | B22: =Declarations!C20 -> DIG | C22: =INDEX($B$6:$B$12,MATCH(A22,$A$6:$A$12,0)) -> center | D22: =INDEX($B$6:$B$12,MATCH(B22,$A$6:$A$12,0)) -> divisions | M22: =Declarations!B20 -> TRS | N22: =Declarations!C20 -> DIG | O22: =INDEX($N$6:$N$12,MATCH(M22,$M$6:$M$12,0)) -> core | P22: =INDEX($N$6:$N$12,MATCH(N22,$M$6:$M$12,0)) -> core
A23: =Declarations!B21 -> ENG | B23: =Declarations!C21 -> IND | C23: =INDEX($B$6:$B$12,MATCH(A23,$A$6:$A$12,0)) -> center | D23: =INDEX($B$6:$B$12,MATCH(B23,$A$6:$A$12,0)) -> divisions | M23: =Declarations!B21 -> ENG | N23: =Declarations!C21 -> IND | O23: =INDEX($N$6:$N$12,MATCH(M23,$M$6:$M$12,0)) -> core | P23: =INDEX($N$6:$N$12,MATCH(N23,$M$6:$M$12,0)) -> core
A24: =Declarations!B22 -> IND | B24: =Declarations!C22 -> ENG | C24: =INDEX($B$6:$B$12,MATCH(A24,$A$6:$A$12,0)) -> divisions | D24: =INDEX($B$6:$B$12,MATCH(B24,$A$6:$A$12,0)) -> center | M24: =Declarations!B22 -> IND | N24: =Declarations!C22 -> ENG | O24: =INDEX($N$6:$N$12,MATCH(M24,$M$6:$M$12,0)) -> core | P24: =INDEX($N$6:$N$12,MATCH(N24,$M$6:$M$12,0)) -> core
A25: =Declarations!B23 -> ENG | B25: =Declarations!C23 -> DIG | C25: =INDEX($B$6:$B$12,MATCH(A25,$A$6:$A$12,0)) -> center | D25: =INDEX($B$6:$B$12,MATCH(B25,$A$6:$A$12,0)) -> divisions | M25: =Declarations!B23 -> ENG | N25: =Declarations!C23 -> DIG | O25: =INDEX($N$6:$N$12,MATCH(M25,$M$6:$M$12,0)) -> core | P25: =INDEX($N$6:$N$12,MATCH(N25,$M$6:$M$12,0)) -> core
A26: =Declarations!B24 -> DIG | B26: =Declarations!C24 -> ENG | C26: =INDEX($B$6:$B$12,MATCH(A26,$A$6:$A$12,0)) -> divisions | D26: =INDEX($B$6:$B$12,MATCH(B26,$A$6:$A$12,0)) -> center | M26: =Declarations!B24 -> DIG | N26: =Declarations!C24 -> ENG | O26: =INDEX($N$6:$N$12,MATCH(M26,$M$6:$M$12,0)) -> core | P26: =INDEX($N$6:$N$12,MATCH(N26,$M$6:$M$12,0)) -> core
... A28: =Declarations!B26 -> GOV | B28: =Declarations!C26 -> DIG | C28: =INDEX($B$6:$B$12,MATCH(A28,$A$6:$A$12,0)) -> center | D28: =INDEX($B$6:$B$12,MATCH(B28,$A$6:$A$12,0)) -> divisions | M28: =Declarations!B26 -> GOV | N28: =Declarations!C26 -> DIG | O28: =INDEX($N$6:$N$12,MATCH(M28,$M$6:$M$12,0)) -> GOV | P28: =INDEX($N$6:$N$12,MATCH(N28,$M$6:$M$12,0)) -> core
A30: Summary map: 1 if some arrow runs from the row's box to the column's | M30: Summary map: 1 if some arrow runs from the row's box to the column's
B31: market | C31: divisions | D31: center | N31: MKT | O31: GOV | P31: MAT | Q31: core
A32: market | B32: 0 | C32: =IF(COUNTIFS($C$15:$C$28,"market",$D$15:$D$28,"divisions")>0,1,0) -> 1 | D32: =IF(COUNTIFS($C$15:$C$28,"market",$D$15:$D$28,"center")>0,1,0) -> 0 | M32: MKT | N32: 0 | O32: =IF(COUNTIFS($O$15:$O$28,"MKT",$P$15:$P$28,"GOV")>0,1,0) -> 0 | P32: =IF(COUNTIFS($O$15:$O$28,"MKT",$P$15:$P$28,"MAT")>0,1,0) -> 1 | Q32: =IF(COUNTIFS($O$15:$O$28,"MKT",$P$15:$P$28,"core")>0,1,0) -> 1
A33: divisions | B33: =IF(COUNTIFS($C$15:$C$28,"divisions",$D$15:$D$28,"market")>0,1,0) -> 0 | C33: 0 | D33: =IF(COUNTIFS($C$15:$C$28,"divisions",$D$15:$D$28,"center")>0,1,0) -> 1 | M33: GOV | N33: =IF(COUNTIFS($O$15:$O$28,"GOV",$P$15:$P$28,"MKT")>0,1,0) -> 0 | O33: 0 | P33: =IF(COUNTIFS($O$15:$O$28,"GOV",$P$15:$P$28,"MAT")>0,1,0) -> 0 | Q33: =IF(COUNTIFS($O$15:$O$28,"GOV",$P$15:$P$28,"core")>0,1,0) -> 1
A34: center | B34: =IF(COUNTIFS($C$15:$C$28,"center",$D$15:$D$28,"market")>0,1,0) -> 0 | C34: =IF(COUNTIFS($C$15:$C$28,"center",$D$15:$D$28,"divisions")>0,1,0) -> 1 | D34: 0 | M34: MAT | N34: =IF(COUNTIFS($O$15:$O$28,"MAT",$P$15:$P$28,"MKT")>0,1,0) -> 0 | O34: =IF(COUNTIFS($O$15:$O$28,"MAT",$P$15:$P$28,"GOV")>0,1,0) -> 0 | P34: 0 | Q34: =IF(COUNTIFS($O$15:$O$28,"MAT",$P$15:$P$28,"core")>0,1,0) -> 1
M35: core | N35: =IF(COUNTIFS($O$15:$O$28,"core",$P$15:$P$28,"MKT")>0,1,0) -> 0 | O35: =IF(COUNTIFS($O$15:$O$28,"core",$P$15:$P$28,"GOV")>0,1,0) -> 0 | P35: =IF(COUNTIFS($O$15:$O$28,"core",$P$15:$P$28,"MAT")>0,1,0) -> 0 | Q35: 0
A36: two steps
B37: market | C37: divisions | D37: center | M37: two steps
A38: market | B38: =$B$32*$B$32+$C$32*$B$33+$D$32*$B$34 -> 0 | C38: =$B$32*$C$32+$C$32*$C$33+$D$32*$C$34 -> 0 | D38: =$B$32*$D$32+$C$32*$D$33+$D$32*$D$34 -> 1 | N38: MKT | O38: GOV | P38: MAT | Q38: core
A39: divisions | B39: =$B$33*$B$32+$C$33*$B$33+$D$33*$B$34 -> 0 | C39: =$B$33*$C$32+$C$33*$C$33+$D$33*$C$34 -> 1 | D39: =$B$33*$D$32+$C$33*$D$33+$D$33*$D$34 -> 0 | M39: MKT | N39: =$N$32*$N$32+$O$32*$N$33+$P$32*$N$34+$Q$32*$N$35 -> 0 | O39: =$N$32*$O$32+$O$32*$O$33+$P$32*$O$34+$Q$32*$O$35 -> 0 | P39: =$N$32*$P$32+$O$32*$P$33+$P$32*$P$34+$Q$32*$P$35 -> 0 | Q39: =$N$32*$Q$32+$O$32*$Q$33+$P$32*$Q$34+$Q$32*$Q$35 -> 1
A40: center | B40: =$B$34*$B$32+$C$34*$B$33+$D$34*$B$34 -> 0 | C40: =$B$34*$C$32+$C$34*$C$33+$D$34*$C$34 -> 0 | D40: =$B$34*$D$32+$C$34*$D$33+$D$34*$D$34 -> 1 | M40: GOV | N40: =$N$33*$N$32+$O$33*$N$33+$P$33*$N$34+$Q$33*$N$35 -> 0 | O40: =$N$33*$O$32+$O$33*$O$33+$P$33*$O$34+$Q$33*$O$35 -> 0 | P40: =$N$33*$P$32+$O$33*$P$33+$P$33*$P$34+$Q$33*$P$35 -> 0 | Q40: =$N$33*$Q$32+$O$33*$Q$33+$P$33*$Q$34+$Q$33*$Q$35 -> 0
M41: MAT | N41: =$N$34*$N$32+$O$34*$N$33+$P$34*$N$34+$Q$34*$N$35 -> 0 | O41: =$N$34*$O$32+$O$34*$O$33+$P$34*$O$34+$Q$34*$O$35 -> 0 | P41: =$N$34*$P$32+$O$34*$P$33+$P$34*$P$34+$Q$34*$P$35 -> 0 | Q41: =$N$34*$Q$32+$O$34*$Q$33+$P$34*$Q$34+$Q$34*$Q$35 -> 0
A42: three steps | M42: core | N42: =$N$35*$N$32+$O$35*$N$33+$P$35*$N$34+$Q$35*$N$35 -> 0 | O42: =$N$35*$O$32+$O$35*$O$33+$P$35*$O$34+$Q$35*$O$35 -> 0 | P42: =$N$35*$P$32+$O$35*$P$33+$P$35*$P$34+$Q$35*$P$35 -> 0 | Q42: =$N$35*$Q$32+$O$35*$Q$33+$P$35*$Q$34+$Q$35*$Q$35 -> 0
B43: market | C43: divisions | D43: center
A44: market | B44: =$B$38*$B$32+$C$38*$B$33+$D$38*$B$34 -> 0 | C44: =$B$38*$C$32+$C$38*$C$33+$D$38*$C$34 -> 1 | D44: =$B$38*$D$32+$C$38*$D$33+$D$38*$D$34 -> 0 | M44: three steps
A45: divisions | B45: =$B$39*$B$32+$C$39*$B$33+$D$39*$B$34 -> 0 | C45: =$B$39*$C$32+$C$39*$C$33+$D$39*$C$34 -> 0 | D45: =$B$39*$D$32+$C$39*$D$33+$D$39*$D$34 -> 1 | N45: MKT | O45: GOV | P45: MAT | Q45: core
A46: center | B46: =$B$40*$B$32+$C$40*$B$33+$D$40*$B$34 -> 0 | C46: =$B$40*$C$32+$C$40*$C$33+$D$40*$C$34 -> 1 | D46: =$B$40*$D$32+$C$40*$D$33+$D$40*$D$34 -> 0 | M46: MKT | N46: =$N$39*$N$32+$O$39*$N$33+$P$39*$N$34+$Q$39*$N$35 -> 0 | O46: =$N$39*$O$32+$O$39*$O$33+$P$39*$O$34+$Q$39*$O$35 -> 0 | P46: =$N$39*$P$32+$O$39*$P$33+$P$39*$P$34+$Q$39*$P$35 -> 0 | Q46: =$N$39*$Q$32+$O$39*$Q$33+$P$39*$Q$34+$Q$39*$Q$35 -> 0
M47: GOV | N47: =$N$40*$N$32+$O$40*$N$33+$P$40*$N$34+$Q$40*$N$35 -> 0 | O47: =$N$40*$O$32+$O$40*$O$33+$P$40*$O$34+$Q$40*$O$35 -> 0 | P47: =$N$40*$P$32+$O$40*$P$33+$P$40*$P$34+$Q$40*$P$35 -> 0 | Q47: =$N$40*$Q$32+$O$40*$Q$33+$P$40*$Q$34+$Q$40*$Q$35 -> 0
A48: Summary-map reach: 1 if a route of 1 to 3 steps joins the boxes | M48: MAT | N48: =$N$41*$N$32+$O$41*$N$33+$P$41*$N$34+$Q$41*$N$35 -> 0 | O48: =$N$41*$O$32+$O$41*$O$33+$P$41*$O$34+$Q$41*$O$35 -> 0 | P48: =$N$41*$P$32+$O$41*$P$33+$P$41*$P$34+$Q$41*$P$35 -> 0 | Q48: =$N$41*$Q$32+$O$41*$Q$33+$P$41*$Q$34+$Q$41*$Q$35 -> 0
B49: market | C49: divisions | D49: center | M49: core | N49: =$N$42*$N$32+$O$42*$N$33+$P$42*$N$34+$Q$42*$N$35 -> 0 | O49: =$N$42*$O$32+$O$42*$O$33+$P$42*$O$34+$Q$42*$O$35 -> 0 | P49: =$N$42*$P$32+$O$42*$P$33+$P$42*$P$34+$Q$42*$P$35 -> 0 | Q49: =$N$42*$Q$32+$O$42*$Q$33+$P$42*$Q$34+$Q$42*$Q$35 -> 0
A50: market | B50: =SIGN($B$32+$B$38+$B$44) -> 0 | C50: =SIGN($C$32+$C$38+$C$44) -> 1 | D50: =SIGN($D$32+$D$38+$D$44) -> 1
A51: divisions | B51: =SIGN($B$33+$B$39+$B$45) -> 0 | C51: =SIGN($C$33+$C$39+$C$45) -> 1 | D51: =SIGN($D$33+$D$39+$D$45) -> 1 | M51: Summary-map reach: 1 if a route of 1 to 3 steps joins the boxes
A52: center | B52: =SIGN($B$34+$B$40+$B$46) -> 0 | C52: =SIGN($C$34+$C$40+$C$46) -> 1 | D52: =SIGN($D$34+$D$40+$D$46) -> 1 | N52: MKT | O52: GOV | P52: MAT | Q52: core
M53: MKT | N53: =SIGN($N$32+$N$39+$N$46) -> 0 | O53: =SIGN($O$32+$O$39+$O$46) -> 0 | P53: =SIGN($P$32+$P$39+$P$46) -> 1 | Q53: =SIGN($Q$32+$Q$39+$Q$46) -> 1
M54: GOV | N54: =SIGN($N$33+$N$40+$N$47) -> 0 | O54: =SIGN($O$33+$O$40+$O$47) -> 0 | P54: =SIGN($P$33+$P$40+$P$47) -> 0 | Q54: =SIGN($Q$33+$Q$40+$Q$47) -> 1
M55: MAT | N55: =SIGN($N$34+$N$41+$N$48) -> 0 | O55: =SIGN($O$34+$O$41+$O$48) -> 0 | P55: =SIGN($P$34+$P$41+$P$48) -> 0 | Q55: =SIGN($Q$34+$Q$41+$Q$48) -> 1
M56: core | N56: =SIGN($N$35+$N$42+$N$49) -> 0 | O56: =SIGN($O$35+$O$42+$O$49) -> 0 | P56: =SIGN($P$35+$P$42+$P$49) -> 0 | Q56: =SIGN($Q$35+$Q$42+$Q$49) -> 0
A57: Invented: the boxes are joined on the summary map, the components are not
B58: MKT | C58: GOV | D58: MAT | E58: IND | F58: DIG | G58: ENG | H58: TRS
A59: MKT | B59: =IF(INDEX($B$6:$B$12,1)=INDEX($B$6:$B$12,1),0,INDEX($B$50:$D$52,MATCH(INDEX($B$6:$B$12,1),$A$50:$A$52,0),MATCH(INDEX($B$6:$B$12,1),$B$49:$D$49,0))*(1-Core!$B$83)) -> 0 | C59: =IF(INDEX($B$6:$B$12,1)=INDEX($B$6:$B$12,2),0,INDEX($B$50:$D$52,MATCH(INDEX($B$6:$B$12,1),$A$50:$A$52,0),MATCH(INDEX($B$6:$B$12,2),$B$49:$D$49,0))*(1-Core!$C$83)) -> 1 | D59: =IF(INDEX($B$6:$B$12,1)=INDEX($B$6:$B$12,3),0,INDEX($B$50:$D$52,MATCH(INDEX($B$6:$B$12,1),$A$50:$A$52,0),MATCH(INDEX($B$6:$B$12,3),$B$49:$D$49,0))*(1-Core!$D$83)) -> 0 | E59: =IF(INDEX($B$6:$B$12,1)=INDEX($B$6:$B$12,4),0,INDEX($B$50:$D$52,MATCH(INDEX($B$6:$B$12,1),$A$50:$A$52,0),MATCH(INDEX($B$6:$B$12,4),$B$49:$D$49,0))*(1-Core!$E$83)) -> 0 | F59: =IF(INDEX($B$6:$B$12,1)=INDEX($B$6:$B$12,5),0,INDEX($B$50:$D$52,MATCH(INDEX($B$6:$B$12,1),$A$50:$A$52,0),MATCH(INDEX($B$6:$B$12,5),$B$49:$D$49,0))*(1-Core!$F$83)) -> 0 | G59: =IF(INDEX($B$6:$B$12,1)=INDEX($B$6:$B$12,6),0,INDEX($B$50:$D$52,MATCH(INDEX($B$6:$B$12,1),$A$50:$A$52,0),MATCH(INDEX($B$6:$B$12,6),$B$49:$D$49,0))*(1-Core!$G$83)) -> 0 | H59: =IF(INDEX($B$6:$B$12,1)=INDEX($B$6:$B$12,7),0,INDEX($B$50:$D$52,MATCH(INDEX($B$6:$B$12,1),$A$50:$A$52,0),MATCH(INDEX($B$6:$B$12,7),$B$49:$D$49,0))*(1-Core!$H$83)) -> 0
A60: GOV | B60: =IF(INDEX($B$6:$B$12,2)=INDEX($B$6:$B$12,1),0,INDEX($B$50:$D$52,MATCH(INDEX($B$6:$B$12,2),$A$50:$A$52,0),MATCH(INDEX($B$6:$B$12,1),$B$49:$D$49,0))*(1-Core!$B$84)) -> 0 | C60: =IF(INDEX($B$6:$B$12,2)=INDEX($B$6:$B$12,2),0,INDEX($B$50:$D$52,MATCH(INDEX($B$6:$B$12,2),$A$50:$A$52,0),MATCH(INDEX($B$6:$B$12,2),$B$49:$D$49,0))*(1-Core!$C$84)) -> 0 | D60: =IF(INDEX($B$6:$B$12,2)=INDEX($B$6:$B$12,3),0,INDEX($B$50:$D$52,MATCH(INDEX($B$6:$B$12,2),$A$50:$A$52,0),MATCH(INDEX($B$6:$B$12,3),$B$49:$D$49,0))*(1-Core!$D$84)) -> 1 | E60: =IF(INDEX($B$6:$B$12,2)=INDEX($B$6:$B$12,4),0,INDEX($B$50:$D$52,MATCH(INDEX($B$6:$B$12,2),$A$50:$A$52,0),MATCH(INDEX($B$6:$B$12,4),$B$49:$D$49,0))*(1-Core!$E$84)) -> 0 | F60: =IF(INDEX($B$6:$B$12,2)=INDEX($B$6:$B$12,5),0,INDEX($B$50:$D$52,MATCH(INDEX($B$6:$B$12,2),$A$50:$A$52,0),MATCH(INDEX($B$6:$B$12,5),$B$49:$D$49,0))*(1-Core!$F$84)) -> 0 | G60: =IF(INDEX($B$6:$B$12,2)=INDEX($B$6:$B$12,6),0,INDEX($B$50:$D$52,MATCH(INDEX($B$6:$B$12,2),$A$50:$A$52,0),MATCH(INDEX($B$6:$B$12,6),$B$49:$D$49,0))*(1-Core!$G$84)) -> 0 | H60: =IF(INDEX($B$6:$B$12,2)=INDEX($B$6:$B$12,7),0,INDEX($B$50:$D$52,MATCH(INDEX($B$6:$B$12,2),$A$50:$A$52,0),MATCH(INDEX($B$6:$B$12,7),$B$49:$D$49,0))*(1-Core!$H$84)) -> 0
A61: MAT | B61: =IF(INDEX($B$6:$B$12,3)=INDEX($B$6:$B$12,1),0,INDEX($B$50:$D$52,MATCH(INDEX($B$6:$B$12,3),$A$50:$A$52,0),MATCH(INDEX($B$6:$B$12,1),$B$49:$D$49,0))*(1-Core!$B$85)) -> 0 | C61: =IF(INDEX($B$6:$B$12,3)=INDEX($B$6:$B$12,2),0,INDEX($B$50:$D$52,MATCH(INDEX($B$6:$B$12,3),$A$50:$A$52,0),MATCH(INDEX($B$6:$B$12,2),$B$49:$D$49,0))*(1-Core!$C$85)) -> 1 | D61: =IF(INDEX($B$6:$B$12,3)=INDEX($B$6:$B$12,3),0,INDEX($B$50:$D$52,MATCH(INDEX($B$6:$B$12,3),$A$50:$A$52,0),MATCH(INDEX($B$6:$B$12,3),$B$49:$D$49,0))*(1-Core!$D$85)) -> 0 | E61: =IF(INDEX($B$6:$B$12,3)=INDEX($B$6:$B$12,4),0,INDEX($B$50:$D$52,MATCH(INDEX($B$6:$B$12,3),$A$50:$A$52,0),MATCH(INDEX($B$6:$B$12,4),$B$49:$D$49,0))*(1-Core!$E$85)) -> 0 | F61: =IF(INDEX($B$6:$B$12,3)=INDEX($B$6:$B$12,5),0,INDEX($B$50:$D$52,MATCH(INDEX($B$6:$B$12,3),$A$50:$A$52,0),MATCH(INDEX($B$6:$B$12,5),$B$49:$D$49,0))*(1-Core!$F$85)) -> 0 | G61: =IF(INDEX($B$6:$B$12,3)=INDEX($B$6:$B$12,6),0,INDEX($B$50:$D$52,MATCH(INDEX($B$6:$B$12,3),$A$50:$A$52,0),MATCH(INDEX($B$6:$B$12,6),$B$49:$D$49,0))*(1-Core!$G$85)) -> 0 | H61: =IF(INDEX($B$6:$B$12,3)=INDEX($B$6:$B$12,7),0,INDEX($B$50:$D$52,MATCH(INDEX($B$6:$B$12,3),$A$50:$A$52,0),MATCH(INDEX($B$6:$B$12,7),$B$49:$D$49,0))*(1-Core!$H$85)) -> 0 | M61: Invented: the boxes are joined on the summary map, the components are not
A62: IND | B62: =IF(INDEX($B$6:$B$12,4)=INDEX($B$6:$B$12,1),0,INDEX($B$50:$D$52,MATCH(INDEX($B$6:$B$12,4),$A$50:$A$52,0),MATCH(INDEX($B$6:$B$12,1),$B$49:$D$49,0))*(1-Core!$B$86)) -> 0 | C62: =IF(INDEX($B$6:$B$12,4)=INDEX($B$6:$B$12,2),0,INDEX($B$50:$D$52,MATCH(INDEX($B$6:$B$12,4),$A$50:$A$52,0),MATCH(INDEX($B$6:$B$12,2),$B$49:$D$49,0))*(1-Core!$C$86)) -> 1 | D62: =IF(INDEX($B$6:$B$12,4)=INDEX($B$6:$B$12,3),0,INDEX($B$50:$D$52,MATCH(INDEX($B$6:$B$12,4),$A$50:$A$52,0),MATCH(INDEX($B$6:$B$12,3),$B$49:$D$49,0))*(1-Core!$D$86)) -> 0 | E62: =IF(INDEX($B$6:$B$12,4)=INDEX($B$6:$B$12,4),0,INDEX($B$50:$D$52,MATCH(INDEX($B$6:$B$12,4),$A$50:$A$52,0),MATCH(INDEX($B$6:$B$12,4),$B$49:$D$49,0))*(1-Core!$E$86)) -> 0 | F62: =IF(INDEX($B$6:$B$12,4)=INDEX($B$6:$B$12,5),0,INDEX($B$50:$D$52,MATCH(INDEX($B$6:$B$12,4),$A$50:$A$52,0),MATCH(INDEX($B$6:$B$12,5),$B$49:$D$49,0))*(1-Core!$F$86)) -> 0 | G62: =IF(INDEX($B$6:$B$12,4)=INDEX($B$6:$B$12,6),0,INDEX($B$50:$D$52,MATCH(INDEX($B$6:$B$12,4),$A$50:$A$52,0),MATCH(INDEX($B$6:$B$12,6),$B$49:$D$49,0))*(1-Core!$G$86)) -> 0 | H62: =IF(INDEX($B$6:$B$12,4)=INDEX($B$6:$B$12,7),0,INDEX($B$50:$D$52,MATCH(INDEX($B$6:$B$12,4),$A$50:$A$52,0),MATCH(INDEX($B$6:$B$12,7),$B$49:$D$49,0))*(1-Core!$H$86)) -> 0 | N62: MKT | O62: GOV | P62: MAT | Q62: IND | R62: DIG | S62: ENG | T62: TRS
A63: DIG | B63: =IF(INDEX($B$6:$B$12,5)=INDEX($B$6:$B$12,1),0,INDEX($B$50:$D$52,MATCH(INDEX($B$6:$B$12,5),$A$50:$A$52,0),MATCH(INDEX($B$6:$B$12,1),$B$49:$D$49,0))*(1-Core!$B$87)) -> 0 | C63: =IF(INDEX($B$6:$B$12,5)=INDEX($B$6:$B$12,2),0,INDEX($B$50:$D$52,MATCH(INDEX($B$6:$B$12,5),$A$50:$A$52,0),MATCH(INDEX($B$6:$B$12,2),$B$49:$D$49,0))*(1-Core!$C$87)) -> 1 | D63: =IF(INDEX($B$6:$B$12,5)=INDEX($B$6:$B$12,3),0,INDEX($B$50:$D$52,MATCH(INDEX($B$6:$B$12,5),$A$50:$A$52,0),MATCH(INDEX($B$6:$B$12,3),$B$49:$D$49,0))*(1-Core!$D$87)) -> 0 | E63: =IF(INDEX($B$6:$B$12,5)=INDEX($B$6:$B$12,4),0,INDEX($B$50:$D$52,MATCH(INDEX($B$6:$B$12,5),$A$50:$A$52,0),MATCH(INDEX($B$6:$B$12,4),$B$49:$D$49,0))*(1-Core!$E$87)) -> 0 | F63: =IF(INDEX($B$6:$B$12,5)=INDEX($B$6:$B$12,5),0,INDEX($B$50:$D$52,MATCH(INDEX($B$6:$B$12,5),$A$50:$A$52,0),MATCH(INDEX($B$6:$B$12,5),$B$49:$D$49,0))*(1-Core!$F$87)) -> 0 | G63: =IF(INDEX($B$6:$B$12,5)=INDEX($B$6:$B$12,6),0,INDEX($B$50:$D$52,MATCH(INDEX($B$6:$B$12,5),$A$50:$A$52,0),MATCH(INDEX($B$6:$B$12,6),$B$49:$D$49,0))*(1-Core!$G$87)) -> 0 | H63: =IF(INDEX($B$6:$B$12,5)=INDEX($B$6:$B$12,7),0,INDEX($B$50:$D$52,MATCH(INDEX($B$6:$B$12,5),$A$50:$A$52,0),MATCH(INDEX($B$6:$B$12,7),$B$49:$D$49,0))*(1-Core!$H$87)) -> 0 | M63: MKT | N63: =IF(INDEX($N$6:$N$12,1)=INDEX($N$6:$N$12,1),0,INDEX($N$53:$Q$56,MATCH(INDEX($N$6:$N$12,1),$M$53:$M$56,0),MATCH(INDEX($N$6:$N$12,1),$N$52:$Q$52,0))*(1-Core!$B$83)) -> 0 | O63: =IF(INDEX($N$6:$N$12,1)=INDEX($N$6:$N$12,2),0,INDEX($N$53:$Q$56,MATCH(INDEX($N$6:$N$12,1),$M$53:$M$56,0),MATCH(INDEX($N$6:$N$12,2),$N$52:$Q$52,0))*(1-Core!$C$83)) -> 0 | P63: =IF(INDEX($N$6:$N$12,1)=INDEX($N$6:$N$12,3),0,INDEX($N$53:$Q$56,MATCH(INDEX($N$6:$N$12,1),$M$53:$M$56,0),MATCH(INDEX($N$6:$N$12,3),$N$52:$Q$52,0))*(1-Core!$D$83)) -> 0 | Q63: =IF(INDEX($N$6:$N$12,1)=INDEX($N$6:$N$12,4),0,INDEX($N$53:$Q$56,MATCH(INDEX($N$6:$N$12,1),$M$53:$M$56,0),MATCH(INDEX($N$6:$N$12,4),$N$52:$Q$52,0))*(1-Core!$E$83)) -> 0 | R63: =IF(INDEX($N$6:$N$12,1)=INDEX($N$6:$N$12,5),0,INDEX($N$53:$Q$56,MATCH(INDEX($N$6:$N$12,1),$M$53:$M$56,0),MATCH(INDEX($N$6:$N$12,5),$N$52:$Q$52,0))*(1-Core!$F$83)) -> 0 | S63: =IF(INDEX($N$6:$N$12,1)=INDEX($N$6:$N$12,6),0,INDEX($N$53:$Q$56,MATCH(INDEX($N$6:$N$12,1),$M$53:$M$56,0),MATCH(INDEX($N$6:$N$12,6),$N$52:$Q$52,0))*(1-Core!$G$83)) -> 0 | T63: =IF(INDEX($N$6:$N$12,1)=INDEX($N$6:$N$12,7),0,INDEX($N$53:$Q$56,MATCH(INDEX($N$6:$N$12,1),$M$53:$M$56,0),MATCH(INDEX($N$6:$N$12,7),$N$52:$Q$52,0))*(1-Core!$H$83)) -> 0
A64: ENG | B64: =IF(INDEX($B$6:$B$12,6)=INDEX($B$6:$B$12,1),0,INDEX($B$50:$D$52,MATCH(INDEX($B$6:$B$12,6),$A$50:$A$52,0),MATCH(INDEX($B$6:$B$12,1),$B$49:$D$49,0))*(1-Core!$B$88)) -> 0 | C64: =IF(INDEX($B$6:$B$12,6)=INDEX($B$6:$B$12,2),0,INDEX($B$50:$D$52,MATCH(INDEX($B$6:$B$12,6),$A$50:$A$52,0),MATCH(INDEX($B$6:$B$12,2),$B$49:$D$49,0))*(1-Core!$C$88)) -> 0 | D64: =IF(INDEX($B$6:$B$12,6)=INDEX($B$6:$B$12,3),0,INDEX($B$50:$D$52,MATCH(INDEX($B$6:$B$12,6),$A$50:$A$52,0),MATCH(INDEX($B$6:$B$12,3),$B$49:$D$49,0))*(1-Core!$D$88)) -> 1 | E64: =IF(INDEX($B$6:$B$12,6)=INDEX($B$6:$B$12,4),0,INDEX($B$50:$D$52,MATCH(INDEX($B$6:$B$12,6),$A$50:$A$52,0),MATCH(INDEX($B$6:$B$12,4),$B$49:$D$49,0))*(1-Core!$E$88)) -> 0 | F64: =IF(INDEX($B$6:$B$12,6)=INDEX($B$6:$B$12,5),0,INDEX($B$50:$D$52,MATCH(INDEX($B$6:$B$12,6),$A$50:$A$52,0),MATCH(INDEX($B$6:$B$12,5),$B$49:$D$49,0))*(1-Core!$F$88)) -> 0 | G64: =IF(INDEX($B$6:$B$12,6)=INDEX($B$6:$B$12,6),0,INDEX($B$50:$D$52,MATCH(INDEX($B$6:$B$12,6),$A$50:$A$52,0),MATCH(INDEX($B$6:$B$12,6),$B$49:$D$49,0))*(1-Core!$G$88)) -> 0 | H64: =IF(INDEX($B$6:$B$12,6)=INDEX($B$6:$B$12,7),0,INDEX($B$50:$D$52,MATCH(INDEX($B$6:$B$12,6),$A$50:$A$52,0),MATCH(INDEX($B$6:$B$12,7),$B$49:$D$49,0))*(1-Core!$H$88)) -> 0 | M64: GOV | N64: =IF(INDEX($N$6:$N$12,2)=INDEX($N$6:$N$12,1),0,INDEX($N$53:$Q$56,MATCH(INDEX($N$6:$N$12,2),$M$53:$M$56,0),MATCH(INDEX($N$6:$N$12,1),$N$52:$Q$52,0))*(1-Core!$B$84)) -> 0 | O64: =IF(INDEX($N$6:$N$12,2)=INDEX($N$6:$N$12,2),0,INDEX($N$53:$Q$56,MATCH(INDEX($N$6:$N$12,2),$M$53:$M$56,0),MATCH(INDEX($N$6:$N$12,2),$N$52:$Q$52,0))*(1-Core!$C$84)) -> 0 | P64: =IF(INDEX($N$6:$N$12,2)=INDEX($N$6:$N$12,3),0,INDEX($N$53:$Q$56,MATCH(INDEX($N$6:$N$12,2),$M$53:$M$56,0),MATCH(INDEX($N$6:$N$12,3),$N$52:$Q$52,0))*(1-Core!$D$84)) -> 0 | Q64: =IF(INDEX($N$6:$N$12,2)=INDEX($N$6:$N$12,4),0,INDEX($N$53:$Q$56,MATCH(INDEX($N$6:$N$12,2),$M$53:$M$56,0),MATCH(INDEX($N$6:$N$12,4),$N$52:$Q$52,0))*(1-Core!$E$84)) -> 0 | R64: =IF(INDEX($N$6:$N$12,2)=INDEX($N$6:$N$12,5),0,INDEX($N$53:$Q$56,MATCH(INDEX($N$6:$N$12,2),$M$53:$M$56,0),MATCH(INDEX($N$6:$N$12,5),$N$52:$Q$52,0))*(1-Core!$F$84)) -> 0 | S64: =IF(INDEX($N$6:$N$12,2)=INDEX($N$6:$N$12,6),0,INDEX($N$53:$Q$56,MATCH(INDEX($N$6:$N$12,2),$M$53:$M$56,0),MATCH(INDEX($N$6:$N$12,6),$N$52:$Q$52,0))*(1-Core!$G$84)) -> 0 | T64: =IF(INDEX($N$6:$N$12,2)=INDEX($N$6:$N$12,7),0,INDEX($N$53:$Q$56,MATCH(INDEX($N$6:$N$12,2),$M$53:$M$56,0),MATCH(INDEX($N$6:$N$12,7),$N$52:$Q$52,0))*(1-Core!$H$84)) -> 0
A65: TRS | B65: =IF(INDEX($B$6:$B$12,7)=INDEX($B$6:$B$12,1),0,INDEX($B$50:$D$52,MATCH(INDEX($B$6:$B$12,7),$A$50:$A$52,0),MATCH(INDEX($B$6:$B$12,1),$B$49:$D$49,0))*(1-Core!$B$89)) -> 0 | C65: =IF(INDEX($B$6:$B$12,7)=INDEX($B$6:$B$12,2),0,INDEX($B$50:$D$52,MATCH(INDEX($B$6:$B$12,7),$A$50:$A$52,0),MATCH(INDEX($B$6:$B$12,2),$B$49:$D$49,0))*(1-Core!$C$89)) -> 0 | D65: =IF(INDEX($B$6:$B$12,7)=INDEX($B$6:$B$12,3),0,INDEX($B$50:$D$52,MATCH(INDEX($B$6:$B$12,7),$A$50:$A$52,0),MATCH(INDEX($B$6:$B$12,3),$B$49:$D$49,0))*(1-Core!$D$89)) -> 1 | E65: =IF(INDEX($B$6:$B$12,7)=INDEX($B$6:$B$12,4),0,INDEX($B$50:$D$52,MATCH(INDEX($B$6:$B$12,7),$A$50:$A$52,0),MATCH(INDEX($B$6:$B$12,4),$B$49:$D$49,0))*(1-Core!$E$89)) -> 0 | F65: =IF(INDEX($B$6:$B$12,7)=INDEX($B$6:$B$12,5),0,INDEX($B$50:$D$52,MATCH(INDEX($B$6:$B$12,7),$A$50:$A$52,0),MATCH(INDEX($B$6:$B$12,5),$B$49:$D$49,0))*(1-Core!$F$89)) -> 0 | G65: =IF(INDEX($B$6:$B$12,7)=INDEX($B$6:$B$12,6),0,INDEX($B$50:$D$52,MATCH(INDEX($B$6:$B$12,7),$A$50:$A$52,0),MATCH(INDEX($B$6:$B$12,6),$B$49:$D$49,0))*(1-Core!$G$89)) -> 0 | H65: =IF(INDEX($B$6:$B$12,7)=INDEX($B$6:$B$12,7),0,INDEX($B$50:$D$52,MATCH(INDEX($B$6:$B$12,7),$A$50:$A$52,0),MATCH(INDEX($B$6:$B$12,7),$B$49:$D$49,0))*(1-Core!$H$89)) -> 0 | M65: MAT | N65: =IF(INDEX($N$6:$N$12,3)=INDEX($N$6:$N$12,1),0,INDEX($N$53:$Q$56,MATCH(INDEX($N$6:$N$12,3),$M$53:$M$56,0),MATCH(INDEX($N$6:$N$12,1),$N$52:$Q$52,0))*(1-Core!$B$85)) -> 0 | O65: =IF(INDEX($N$6:$N$12,3)=INDEX($N$6:$N$12,2),0,INDEX($N$53:$Q$56,MATCH(INDEX($N$6:$N$12,3),$M$53:$M$56,0),MATCH(INDEX($N$6:$N$12,2),$N$52:$Q$52,0))*(1-Core!$C$85)) -> 0 | P65: =IF(INDEX($N$6:$N$12,3)=INDEX($N$6:$N$12,3),0,INDEX($N$53:$Q$56,MATCH(INDEX($N$6:$N$12,3),$M$53:$M$56,0),MATCH(INDEX($N$6:$N$12,3),$N$52:$Q$52,0))*(1-Core!$D$85)) -> 0 | Q65: =IF(INDEX($N$6:$N$12,3)=INDEX($N$6:$N$12,4),0,INDEX($N$53:$Q$56,MATCH(INDEX($N$6:$N$12,3),$M$53:$M$56,0),MATCH(INDEX($N$6:$N$12,4),$N$52:$Q$52,0))*(1-Core!$E$85)) -> 0 | R65: =IF(INDEX($N$6:$N$12,3)=INDEX($N$6:$N$12,5),0,INDEX($N$53:$Q$56,MATCH(INDEX($N$6:$N$12,3),$M$53:$M$56,0),MATCH(INDEX($N$6:$N$12,5),$N$52:$Q$52,0))*(1-Core!$F$85)) -> 0 | S65: =IF(INDEX($N$6:$N$12,3)=INDEX($N$6:$N$12,6),0,INDEX($N$53:$Q$56,MATCH(INDEX($N$6:$N$12,3),$M$53:$M$56,0),MATCH(INDEX($N$6:$N$12,6),$N$52:$Q$52,0))*(1-Core!$G$85)) -> 0 | T65: =IF(INDEX($N$6:$N$12,3)=INDEX($N$6:$N$12,7),0,INDEX($N$53:$Q$56,MATCH(INDEX($N$6:$N$12,3),$M$53:$M$56,0),MATCH(INDEX($N$6:$N$12,7),$N$52:$Q$52,0))*(1-Core!$H$85)) -> 0
M66: IND | N66: =IF(INDEX($N$6:$N$12,4)=INDEX($N$6:$N$12,1),0,INDEX($N$53:$Q$56,MATCH(INDEX($N$6:$N$12,4),$M$53:$M$56,0),MATCH(INDEX($N$6:$N$12,1),$N$52:$Q$52,0))*(1-Core!$B$86)) -> 0 | O66: =IF(INDEX($N$6:$N$12,4)=INDEX($N$6:$N$12,2),0,INDEX($N$53:$Q$56,MATCH(INDEX($N$6:$N$12,4),$M$53:$M$56,0),MATCH(INDEX($N$6:$N$12,2),$N$52:$Q$52,0))*(1-Core!$C$86)) -> 0 | P66: =IF(INDEX($N$6:$N$12,4)=INDEX($N$6:$N$12,3),0,INDEX($N$53:$Q$56,MATCH(INDEX($N$6:$N$12,4),$M$53:$M$56,0),MATCH(INDEX($N$6:$N$12,3),$N$52:$Q$52,0))*(1-Core!$D$86)) -> 0 | Q66: =IF(INDEX($N$6:$N$12,4)=INDEX($N$6:$N$12,4),0,INDEX($N$53:$Q$56,MATCH(INDEX($N$6:$N$12,4),$M$53:$M$56,0),MATCH(INDEX($N$6:$N$12,4),$N$52:$Q$52,0))*(1-Core!$E$86)) -> 0 | R66: =IF(INDEX($N$6:$N$12,4)=INDEX($N$6:$N$12,5),0,INDEX($N$53:$Q$56,MATCH(INDEX($N$6:$N$12,4),$M$53:$M$56,0),MATCH(INDEX($N$6:$N$12,5),$N$52:$Q$52,0))*(1-Core!$F$86)) -> 0 | S66: =IF(INDEX($N$6:$N$12,4)=INDEX($N$6:$N$12,6),0,INDEX($N$53:$Q$56,MATCH(INDEX($N$6:$N$12,4),$M$53:$M$56,0),MATCH(INDEX($N$6:$N$12,6),$N$52:$Q$52,0))*(1-Core!$G$86)) -> 0 | T66: =IF(INDEX($N$6:$N$12,4)=INDEX($N$6:$N$12,7),0,INDEX($N$53:$Q$56,MATCH(INDEX($N$6:$N$12,4),$M$53:$M$56,0),MATCH(INDEX($N$6:$N$12,7),$N$52:$Q$52,0))*(1-Core!$H$86)) -> 0
M67: DIG | N67: =IF(INDEX($N$6:$N$12,5)=INDEX($N$6:$N$12,1),0,INDEX($N$53:$Q$56,MATCH(INDEX($N$6:$N$12,5),$M$53:$M$56,0),MATCH(INDEX($N$6:$N$12,1),$N$52:$Q$52,0))*(1-Core!$B$87)) -> 0 | O67: =IF(INDEX($N$6:$N$12,5)=INDEX($N$6:$N$12,2),0,INDEX($N$53:$Q$56,MATCH(INDEX($N$6:$N$12,5),$M$53:$M$56,0),MATCH(INDEX($N$6:$N$12,2),$N$52:$Q$52,0))*(1-Core!$C$87)) -> 0 | P67: =IF(INDEX($N$6:$N$12,5)=INDEX($N$6:$N$12,3),0,INDEX($N$53:$Q$56,MATCH(INDEX($N$6:$N$12,5),$M$53:$M$56,0),MATCH(INDEX($N$6:$N$12,3),$N$52:$Q$52,0))*(1-Core!$D$87)) -> 0 | Q67: =IF(INDEX($N$6:$N$12,5)=INDEX($N$6:$N$12,4),0,INDEX($N$53:$Q$56,MATCH(INDEX($N$6:$N$12,5),$M$53:$M$56,0),MATCH(INDEX($N$6:$N$12,4),$N$52:$Q$52,0))*(1-Core!$E$87)) -> 0 | R67: =IF(INDEX($N$6:$N$12,5)=INDEX($N$6:$N$12,5),0,INDEX($N$53:$Q$56,MATCH(INDEX($N$6:$N$12,5),$M$53:$M$56,0),MATCH(INDEX($N$6:$N$12,5),$N$52:$Q$52,0))*(1-Core!$F$87)) -> 0 | S67: =IF(INDEX($N$6:$N$12,5)=INDEX($N$6:$N$12,6),0,INDEX($N$53:$Q$56,MATCH(INDEX($N$6:$N$12,5),$M$53:$M$56,0),MATCH(INDEX($N$6:$N$12,6),$N$52:$Q$52,0))*(1-Core!$G$87)) -> 0 | T67: =IF(INDEX($N$6:$N$12,5)=INDEX($N$6:$N$12,7),0,INDEX($N$53:$Q$56,MATCH(INDEX($N$6:$N$12,5),$M$53:$M$56,0),MATCH(INDEX($N$6:$N$12,7),$N$52:$Q$52,0))*(1-Core!$H$87)) -> 0
A68: Lost: the components are joined, their boxes are not | M68: ENG | N68: =IF(INDEX($N$6:$N$12,6)=INDEX($N$6:$N$12,1),0,INDEX($N$53:$Q$56,MATCH(INDEX($N$6:$N$12,6),$M$53:$M$56,0),MATCH(INDEX($N$6:$N$12,1),$N$52:$Q$52,0))*(1-Core!$B$88)) -> 0 | O68: =IF(INDEX($N$6:$N$12,6)=INDEX($N$6:$N$12,2),0,INDEX($N$53:$Q$56,MATCH(INDEX($N$6:$N$12,6),$M$53:$M$56,0),MATCH(INDEX($N$6:$N$12,2),$N$52:$Q$52,0))*(1-Core!$C$88)) -> 0 | P68: =IF(INDEX($N$6:$N$12,6)=INDEX($N$6:$N$12,3),0,INDEX($N$53:$Q$56,MATCH(INDEX($N$6:$N$12,6),$M$53:$M$56,0),MATCH(INDEX($N$6:$N$12,3),$N$52:$Q$52,0))*(1-Core!$D$88)) -> 0 | Q68: =IF(INDEX($N$6:$N$12,6)=INDEX($N$6:$N$12,4),0,INDEX($N$53:$Q$56,MATCH(INDEX($N$6:$N$12,6),$M$53:$M$56,0),MATCH(INDEX($N$6:$N$12,4),$N$52:$Q$52,0))*(1-Core!$E$88)) -> 0 | R68: =IF(INDEX($N$6:$N$12,6)=INDEX($N$6:$N$12,5),0,INDEX($N$53:$Q$56,MATCH(INDEX($N$6:$N$12,6),$M$53:$M$56,0),MATCH(INDEX($N$6:$N$12,5),$N$52:$Q$52,0))*(1-Core!$F$88)) -> 0 | S68: =IF(INDEX($N$6:$N$12,6)=INDEX($N$6:$N$12,6),0,INDEX($N$53:$Q$56,MATCH(INDEX($N$6:$N$12,6),$M$53:$M$56,0),MATCH(INDEX($N$6:$N$12,6),$N$52:$Q$52,0))*(1-Core!$G$88)) -> 0 | T68: =IF(INDEX($N$6:$N$12,6)=INDEX($N$6:$N$12,7),0,INDEX($N$53:$Q$56,MATCH(INDEX($N$6:$N$12,6),$M$53:$M$56,0),MATCH(INDEX($N$6:$N$12,7),$N$52:$Q$52,0))*(1-Core!$H$88)) -> 0
B69: MKT | C69: GOV | D69: MAT | E69: IND | F69: DIG | G69: ENG | H69: TRS | M69: TRS | N69: =IF(INDEX($N$6:$N$12,7)=INDEX($N$6:$N$12,1),0,INDEX($N$53:$Q$56,MATCH(INDEX($N$6:$N$12,7),$M$53:$M$56,0),MATCH(INDEX($N$6:$N$12,1),$N$52:$Q$52,0))*(1-Core!$B$89)) -> 0 | O69: =IF(INDEX($N$6:$N$12,7)=INDEX($N$6:$N$12,2),0,INDEX($N$53:$Q$56,MATCH(INDEX($N$6:$N$12,7),$M$53:$M$56,0),MATCH(INDEX($N$6:$N$12,2),$N$52:$Q$52,0))*(1-Core!$C$89)) -> 0 | P69: =IF(INDEX($N$6:$N$12,7)=INDEX($N$6:$N$12,3),0,INDEX($N$53:$Q$56,MATCH(INDEX($N$6:$N$12,7),$M$53:$M$56,0),MATCH(INDEX($N$6:$N$12,3),$N$52:$Q$52,0))*(1-Core!$D$89)) -> 0 | Q69: =IF(INDEX($N$6:$N$12,7)=INDEX($N$6:$N$12,4),0,INDEX($N$53:$Q$56,MATCH(INDEX($N$6:$N$12,7),$M$53:$M$56,0),MATCH(INDEX($N$6:$N$12,4),$N$52:$Q$52,0))*(1-Core!$E$89)) -> 0 | R69: =IF(INDEX($N$6:$N$12,7)=INDEX($N$6:$N$12,5),0,INDEX($N$53:$Q$56,MATCH(INDEX($N$6:$N$12,7),$M$53:$M$56,0),MATCH(INDEX($N$6:$N$12,5),$N$52:$Q$52,0))*(1-Core!$F$89)) -> 0 | S69: =IF(INDEX($N$6:$N$12,7)=INDEX($N$6:$N$12,6),0,INDEX($N$53:$Q$56,MATCH(INDEX($N$6:$N$12,7),$M$53:$M$56,0),MATCH(INDEX($N$6:$N$12,6),$N$52:$Q$52,0))*(1-Core!$G$89)) -> 0 | T69: =IF(INDEX($N$6:$N$12,7)=INDEX($N$6:$N$12,7),0,INDEX($N$53:$Q$56,MATCH(INDEX($N$6:$N$12,7),$M$53:$M$56,0),MATCH(INDEX($N$6:$N$12,7),$N$52:$Q$52,0))*(1-Core!$H$89)) -> 0
A70: MKT | B70: =IF(INDEX($B$6:$B$12,1)=INDEX($B$6:$B$12,1),0,Core!$B$83*(1-INDEX($B$50:$D$52,MATCH(INDEX($B$6:$B$12,1),$A$50:$A$52,0),MATCH(INDEX($B$6:$B$12,1),$B$49:$D$49,0)))) -> 0 | C70: =IF(INDEX($B$6:$B$12,1)=INDEX($B$6:$B$12,2),0,Core!$C$83*(1-INDEX($B$50:$D$52,MATCH(INDEX($B$6:$B$12,1),$A$50:$A$52,0),MATCH(INDEX($B$6:$B$12,2),$B$49:$D$49,0)))) -> 0 | D70: =IF(INDEX($B$6:$B$12,1)=INDEX($B$6:$B$12,3),0,Core!$D$83*(1-INDEX($B$50:$D$52,MATCH(INDEX($B$6:$B$12,1),$A$50:$A$52,0),MATCH(INDEX($B$6:$B$12,3),$B$49:$D$49,0)))) -> 0 | E70: =IF(INDEX($B$6:$B$12,1)=INDEX($B$6:$B$12,4),0,Core!$E$83*(1-INDEX($B$50:$D$52,MATCH(INDEX($B$6:$B$12,1),$A$50:$A$52,0),MATCH(INDEX($B$6:$B$12,4),$B$49:$D$49,0)))) -> 0 | F70: =IF(INDEX($B$6:$B$12,1)=INDEX($B$6:$B$12,5),0,Core!$F$83*(1-INDEX($B$50:$D$52,MATCH(INDEX($B$6:$B$12,1),$A$50:$A$52,0),MATCH(INDEX($B$6:$B$12,5),$B$49:$D$49,0)))) -> 0 | G70: =IF(INDEX($B$6:$B$12,1)=INDEX($B$6:$B$12,6),0,Core!$G$83*(1-INDEX($B$50:$D$52,MATCH(INDEX($B$6:$B$12,1),$A$50:$A$52,0),MATCH(INDEX($B$6:$B$12,6),$B$49:$D$49,0)))) -> 0 | H70: =IF(INDEX($B$6:$B$12,1)=INDEX($B$6:$B$12,7),0,Core!$H$83*(1-INDEX($B$50:$D$52,MATCH(INDEX($B$6:$B$12,1),$A$50:$A$52,0),MATCH(INDEX($B$6:$B$12,7),$B$49:$D$49,0)))) -> 0
A71: GOV | B71: =IF(INDEX($B$6:$B$12,2)=INDEX($B$6:$B$12,1),0,Core!$B$84*(1-INDEX($B$50:$D$52,MATCH(INDEX($B$6:$B$12,2),$A$50:$A$52,0),MATCH(INDEX($B$6:$B$12,1),$B$49:$D$49,0)))) -> 0 | C71: =IF(INDEX($B$6:$B$12,2)=INDEX($B$6:$B$12,2),0,Core!$C$84*(1-INDEX($B$50:$D$52,MATCH(INDEX($B$6:$B$12,2),$A$50:$A$52,0),MATCH(INDEX($B$6:$B$12,2),$B$49:$D$49,0)))) -> 0 | D71: =IF(INDEX($B$6:$B$12,2)=INDEX($B$6:$B$12,3),0,Core!$D$84*(1-INDEX($B$50:$D$52,MATCH(INDEX($B$6:$B$12,2),$A$50:$A$52,0),MATCH(INDEX($B$6:$B$12,3),$B$49:$D$49,0)))) -> 0 | E71: =IF(INDEX($B$6:$B$12,2)=INDEX($B$6:$B$12,4),0,Core!$E$84*(1-INDEX($B$50:$D$52,MATCH(INDEX($B$6:$B$12,2),$A$50:$A$52,0),MATCH(INDEX($B$6:$B$12,4),$B$49:$D$49,0)))) -> 0 | F71: =IF(INDEX($B$6:$B$12,2)=INDEX($B$6:$B$12,5),0,Core!$F$84*(1-INDEX($B$50:$D$52,MATCH(INDEX($B$6:$B$12,2),$A$50:$A$52,0),MATCH(INDEX($B$6:$B$12,5),$B$49:$D$49,0)))) -> 0 | G71: =IF(INDEX($B$6:$B$12,2)=INDEX($B$6:$B$12,6),0,Core!$G$84*(1-INDEX($B$50:$D$52,MATCH(INDEX($B$6:$B$12,2),$A$50:$A$52,0),MATCH(INDEX($B$6:$B$12,6),$B$49:$D$49,0)))) -> 0 | H71: =IF(INDEX($B$6:$B$12,2)=INDEX($B$6:$B$12,7),0,Core!$H$84*(1-INDEX($B$50:$D$52,MATCH(INDEX($B$6:$B$12,2),$A$50:$A$52,0),MATCH(INDEX($B$6:$B$12,7),$B$49:$D$49,0)))) -> 0
A72: MAT | B72: =IF(INDEX($B$6:$B$12,3)=INDEX($B$6:$B$12,1),0,Core!$B$85*(1-INDEX($B$50:$D$52,MATCH(INDEX($B$6:$B$12,3),$A$50:$A$52,0),MATCH(INDEX($B$6:$B$12,1),$B$49:$D$49,0)))) -> 0 | C72: =IF(INDEX($B$6:$B$12,3)=INDEX($B$6:$B$12,2),0,Core!$C$85*(1-INDEX($B$50:$D$52,MATCH(INDEX($B$6:$B$12,3),$A$50:$A$52,0),MATCH(INDEX($B$6:$B$12,2),$B$49:$D$49,0)))) -> 0 | D72: =IF(INDEX($B$6:$B$12,3)=INDEX($B$6:$B$12,3),0,Core!$D$85*(1-INDEX($B$50:$D$52,MATCH(INDEX($B$6:$B$12,3),$A$50:$A$52,0),MATCH(INDEX($B$6:$B$12,3),$B$49:$D$49,0)))) -> 0 | E72: =IF(INDEX($B$6:$B$12,3)=INDEX($B$6:$B$12,4),0,Core!$E$85*(1-INDEX($B$50:$D$52,MATCH(INDEX($B$6:$B$12,3),$A$50:$A$52,0),MATCH(INDEX($B$6:$B$12,4),$B$49:$D$49,0)))) -> 0 | F72: =IF(INDEX($B$6:$B$12,3)=INDEX($B$6:$B$12,5),0,Core!$F$85*(1-INDEX($B$50:$D$52,MATCH(INDEX($B$6:$B$12,3),$A$50:$A$52,0),MATCH(INDEX($B$6:$B$12,5),$B$49:$D$49,0)))) -> 0 | G72: =IF(INDEX($B$6:$B$12,3)=INDEX($B$6:$B$12,6),0,Core!$G$85*(1-INDEX($B$50:$D$52,MATCH(INDEX($B$6:$B$12,3),$A$50:$A$52,0),MATCH(INDEX($B$6:$B$12,6),$B$49:$D$49,0)))) -> 0 | H72: =IF(INDEX($B$6:$B$12,3)=INDEX($B$6:$B$12,7),0,Core!$H$85*(1-INDEX($B$50:$D$52,MATCH(INDEX($B$6:$B$12,3),$A$50:$A$52,0),MATCH(INDEX($B$6:$B$12,7),$B$49:$D$49,0)))) -> 0 | M72: Lost: the components are joined, their boxes are not
A73: IND | B73: =IF(INDEX($B$6:$B$12,4)=INDEX($B$6:$B$12,1),0,Core!$B$86*(1-INDEX($B$50:$D$52,MATCH(INDEX($B$6:$B$12,4),$A$50:$A$52,0),MATCH(INDEX($B$6:$B$12,1),$B$49:$D$49,0)))) -> 0 | C73: =IF(INDEX($B$6:$B$12,4)=INDEX($B$6:$B$12,2),0,Core!$C$86*(1-INDEX($B$50:$D$52,MATCH(INDEX($B$6:$B$12,4),$A$50:$A$52,0),MATCH(INDEX($B$6:$B$12,2),$B$49:$D$49,0)))) -> 0 | D73: =IF(INDEX($B$6:$B$12,4)=INDEX($B$6:$B$12,3),0,Core!$D$86*(1-INDEX($B$50:$D$52,MATCH(INDEX($B$6:$B$12,4),$A$50:$A$52,0),MATCH(INDEX($B$6:$B$12,3),$B$49:$D$49,0)))) -> 0 | E73: =IF(INDEX($B$6:$B$12,4)=INDEX($B$6:$B$12,4),0,Core!$E$86*(1-INDEX($B$50:$D$52,MATCH(INDEX($B$6:$B$12,4),$A$50:$A$52,0),MATCH(INDEX($B$6:$B$12,4),$B$49:$D$49,0)))) -> 0 | F73: =IF(INDEX($B$6:$B$12,4)=INDEX($B$6:$B$12,5),0,Core!$F$86*(1-INDEX($B$50:$D$52,MATCH(INDEX($B$6:$B$12,4),$A$50:$A$52,0),MATCH(INDEX($B$6:$B$12,5),$B$49:$D$49,0)))) -> 0 | G73: =IF(INDEX($B$6:$B$12,4)=INDEX($B$6:$B$12,6),0,Core!$G$86*(1-INDEX($B$50:$D$52,MATCH(INDEX($B$6:$B$12,4),$A$50:$A$52,0),MATCH(INDEX($B$6:$B$12,6),$B$49:$D$49,0)))) -> 0 | H73: =IF(INDEX($B$6:$B$12,4)=INDEX($B$6:$B$12,7),0,Core!$H$86*(1-INDEX($B$50:$D$52,MATCH(INDEX($B$6:$B$12,4),$A$50:$A$52,0),MATCH(INDEX($B$6:$B$12,7),$B$49:$D$49,0)))) -> 0 | N73: MKT | O73: GOV | P73: MAT | Q73: IND | R73: DIG | S73: ENG | T73: TRS
A74: DIG | B74: =IF(INDEX($B$6:$B$12,5)=INDEX($B$6:$B$12,1),0,Core!$B$87*(1-INDEX($B$50:$D$52,MATCH(INDEX($B$6:$B$12,5),$A$50:$A$52,0),MATCH(INDEX($B$6:$B$12,1),$B$49:$D$49,0)))) -> 0 | C74: =IF(INDEX($B$6:$B$12,5)=INDEX($B$6:$B$12,2),0,Core!$C$87*(1-INDEX($B$50:$D$52,MATCH(INDEX($B$6:$B$12,5),$A$50:$A$52,0),MATCH(INDEX($B$6:$B$12,2),$B$49:$D$49,0)))) -> 0 | D74: =IF(INDEX($B$6:$B$12,5)=INDEX($B$6:$B$12,3),0,Core!$D$87*(1-INDEX($B$50:$D$52,MATCH(INDEX($B$6:$B$12,5),$A$50:$A$52,0),MATCH(INDEX($B$6:$B$12,3),$B$49:$D$49,0)))) -> 0 | E74: =IF(INDEX($B$6:$B$12,5)=INDEX($B$6:$B$12,4),0,Core!$E$87*(1-INDEX($B$50:$D$52,MATCH(INDEX($B$6:$B$12,5),$A$50:$A$52,0),MATCH(INDEX($B$6:$B$12,4),$B$49:$D$49,0)))) -> 0 | F74: =IF(INDEX($B$6:$B$12,5)=INDEX($B$6:$B$12,5),0,Core!$F$87*(1-INDEX($B$50:$D$52,MATCH(INDEX($B$6:$B$12,5),$A$50:$A$52,0),MATCH(INDEX($B$6:$B$12,5),$B$49:$D$49,0)))) -> 0 | G74: =IF(INDEX($B$6:$B$12,5)=INDEX($B$6:$B$12,6),0,Core!$G$87*(1-INDEX($B$50:$D$52,MATCH(INDEX($B$6:$B$12,5),$A$50:$A$52,0),MATCH(INDEX($B$6:$B$12,6),$B$49:$D$49,0)))) -> 0 | H74: =IF(INDEX($B$6:$B$12,5)=INDEX($B$6:$B$12,7),0,Core!$H$87*(1-INDEX($B$50:$D$52,MATCH(INDEX($B$6:$B$12,5),$A$50:$A$52,0),MATCH(INDEX($B$6:$B$12,7),$B$49:$D$49,0)))) -> 0 | M74: MKT | N74: =IF(INDEX($N$6:$N$12,1)=INDEX($N$6:$N$12,1),0,Core!$B$83*(1-INDEX($N$53:$Q$56,MATCH(INDEX($N$6:$N$12,1),$M$53:$M$56,0),MATCH(INDEX($N$6:$N$12,1),$N$52:$Q$52,0)))) -> 0 | O74: =IF(INDEX($N$6:$N$12,1)=INDEX($N$6:$N$12,2),0,Core!$C$83*(1-INDEX($N$53:$Q$56,MATCH(INDEX($N$6:$N$12,1),$M$53:$M$56,0),MATCH(INDEX($N$6:$N$12,2),$N$52:$Q$52,0)))) -> 0 | P74: =IF(INDEX($N$6:$N$12,1)=INDEX($N$6:$N$12,3),0,Core!$D$83*(1-INDEX($N$53:$Q$56,MATCH(INDEX($N$6:$N$12,1),$M$53:$M$56,0),MATCH(INDEX($N$6:$N$12,3),$N$52:$Q$52,0)))) -> 0 | Q74: =IF(INDEX($N$6:$N$12,1)=INDEX($N$6:$N$12,4),0,Core!$E$83*(1-INDEX($N$53:$Q$56,MATCH(INDEX($N$6:$N$12,1),$M$53:$M$56,0),MATCH(INDEX($N$6:$N$12,4),$N$52:$Q$52,0)))) -> 0 | R74: =IF(INDEX($N$6:$N$12,1)=INDEX($N$6:$N$12,5),0,Core!$F$83*(1-INDEX($N$53:$Q$56,MATCH(INDEX($N$6:$N$12,1),$M$53:$M$56,0),MATCH(INDEX($N$6:$N$12,5),$N$52:$Q$52,0)))) -> 0 | S74: =IF(INDEX($N$6:$N$12,1)=INDEX($N$6:$N$12,6),0,Core!$G$83*(1-INDEX($N$53:$Q$56,MATCH(INDEX($N$6:$N$12,1),$M$53:$M$56,0),MATCH(INDEX($N$6:$N$12,6),$N$52:$Q$52,0)))) -> 0 | T74: =IF(INDEX($N$6:$N$12,1)=INDEX($N$6:$N$12,7),0,Core!$H$83*(1-INDEX($N$53:$Q$56,MATCH(INDEX($N$6:$N$12,1),$M$53:$M$56,0),MATCH(INDEX($N$6:$N$12,7),$N$52:$Q$52,0)))) -> 0
A75: ENG | B75: =IF(INDEX($B$6:$B$12,6)=INDEX($B$6:$B$12,1),0,Core!$B$88*(1-INDEX($B$50:$D$52,MATCH(INDEX($B$6:$B$12,6),$A$50:$A$52,0),MATCH(INDEX($B$6:$B$12,1),$B$49:$D$49,0)))) -> 0 | C75: =IF(INDEX($B$6:$B$12,6)=INDEX($B$6:$B$12,2),0,Core!$C$88*(1-INDEX($B$50:$D$52,MATCH(INDEX($B$6:$B$12,6),$A$50:$A$52,0),MATCH(INDEX($B$6:$B$12,2),$B$49:$D$49,0)))) -> 0 | D75: =IF(INDEX($B$6:$B$12,6)=INDEX($B$6:$B$12,3),0,Core!$D$88*(1-INDEX($B$50:$D$52,MATCH(INDEX($B$6:$B$12,6),$A$50:$A$52,0),MATCH(INDEX($B$6:$B$12,3),$B$49:$D$49,0)))) -> 0 | E75: =IF(INDEX($B$6:$B$12,6)=INDEX($B$6:$B$12,4),0,Core!$E$88*(1-INDEX($B$50:$D$52,MATCH(INDEX($B$6:$B$12,6),$A$50:$A$52,0),MATCH(INDEX($B$6:$B$12,4),$B$49:$D$49,0)))) -> 0 | F75: =IF(INDEX($B$6:$B$12,6)=INDEX($B$6:$B$12,5),0,Core!$F$88*(1-INDEX($B$50:$D$52,MATCH(INDEX($B$6:$B$12,6),$A$50:$A$52,0),MATCH(INDEX($B$6:$B$12,5),$B$49:$D$49,0)))) -> 0 | G75: =IF(INDEX($B$6:$B$12,6)=INDEX($B$6:$B$12,6),0,Core!$G$88*(1-INDEX($B$50:$D$52,MATCH(INDEX($B$6:$B$12,6),$A$50:$A$52,0),MATCH(INDEX($B$6:$B$12,6),$B$49:$D$49,0)))) -> 0 | H75: =IF(INDEX($B$6:$B$12,6)=INDEX($B$6:$B$12,7),0,Core!$H$88*(1-INDEX($B$50:$D$52,MATCH(INDEX($B$6:$B$12,6),$A$50:$A$52,0),MATCH(INDEX($B$6:$B$12,7),$B$49:$D$49,0)))) -> 0 | M75: GOV | N75: =IF(INDEX($N$6:$N$12,2)=INDEX($N$6:$N$12,1),0,Core!$B$84*(1-INDEX($N$53:$Q$56,MATCH(INDEX($N$6:$N$12,2),$M$53:$M$56,0),MATCH(INDEX($N$6:$N$12,1),$N$52:$Q$52,0)))) -> 0 | O75: =IF(INDEX($N$6:$N$12,2)=INDEX($N$6:$N$12,2),0,Core!$C$84*(1-INDEX($N$53:$Q$56,MATCH(INDEX($N$6:$N$12,2),$M$53:$M$56,0),MATCH(INDEX($N$6:$N$12,2),$N$52:$Q$52,0)))) -> 0 | P75: =IF(INDEX($N$6:$N$12,2)=INDEX($N$6:$N$12,3),0,Core!$D$84*(1-INDEX($N$53:$Q$56,MATCH(INDEX($N$6:$N$12,2),$M$53:$M$56,0),MATCH(INDEX($N$6:$N$12,3),$N$52:$Q$52,0)))) -> 0 | Q75: =IF(INDEX($N$6:$N$12,2)=INDEX($N$6:$N$12,4),0,Core!$E$84*(1-INDEX($N$53:$Q$56,MATCH(INDEX($N$6:$N$12,2),$M$53:$M$56,0),MATCH(INDEX($N$6:$N$12,4),$N$52:$Q$52,0)))) -> 0 | R75: =IF(INDEX($N$6:$N$12,2)=INDEX($N$6:$N$12,5),0,Core!$F$84*(1-INDEX($N$53:$Q$56,MATCH(INDEX($N$6:$N$12,2),$M$53:$M$56,0),MATCH(INDEX($N$6:$N$12,5),$N$52:$Q$52,0)))) -> 0 | S75: =IF(INDEX($N$6:$N$12,2)=INDEX($N$6:$N$12,6),0,Core!$G$84*(1-INDEX($N$53:$Q$56,MATCH(INDEX($N$6:$N$12,2),$M$53:$M$56,0),MATCH(INDEX($N$6:$N$12,6),$N$52:$Q$52,0)))) -> 0 | T75: =IF(INDEX($N$6:$N$12,2)=INDEX($N$6:$N$12,7),0,Core!$H$84*(1-INDEX($N$53:$Q$56,MATCH(INDEX($N$6:$N$12,2),$M$53:$M$56,0),MATCH(INDEX($N$6:$N$12,7),$N$52:$Q$52,0)))) -> 0
A76: TRS | B76: =IF(INDEX($B$6:$B$12,7)=INDEX($B$6:$B$12,1),0,Core!$B$89*(1-INDEX($B$50:$D$52,MATCH(INDEX($B$6:$B$12,7),$A$50:$A$52,0),MATCH(INDEX($B$6:$B$12,1),$B$49:$D$49,0)))) -> 0 | C76: =IF(INDEX($B$6:$B$12,7)=INDEX($B$6:$B$12,2),0,Core!$C$89*(1-INDEX($B$50:$D$52,MATCH(INDEX($B$6:$B$12,7),$A$50:$A$52,0),MATCH(INDEX($B$6:$B$12,2),$B$49:$D$49,0)))) -> 0 | D76: =IF(INDEX($B$6:$B$12,7)=INDEX($B$6:$B$12,3),0,Core!$D$89*(1-INDEX($B$50:$D$52,MATCH(INDEX($B$6:$B$12,7),$A$50:$A$52,0),MATCH(INDEX($B$6:$B$12,3),$B$49:$D$49,0)))) -> 0 | E76: =IF(INDEX($B$6:$B$12,7)=INDEX($B$6:$B$12,4),0,Core!$E$89*(1-INDEX($B$50:$D$52,MATCH(INDEX($B$6:$B$12,7),$A$50:$A$52,0),MATCH(INDEX($B$6:$B$12,4),$B$49:$D$49,0)))) -> 0 | F76: =IF(INDEX($B$6:$B$12,7)=INDEX($B$6:$B$12,5),0,Core!$F$89*(1-INDEX($B$50:$D$52,MATCH(INDEX($B$6:$B$12,7),$A$50:$A$52,0),MATCH(INDEX($B$6:$B$12,5),$B$49:$D$49,0)))) -> 0 | G76: =IF(INDEX($B$6:$B$12,7)=INDEX($B$6:$B$12,6),0,Core!$G$89*(1-INDEX($B$50:$D$52,MATCH(INDEX($B$6:$B$12,7),$A$50:$A$52,0),MATCH(INDEX($B$6:$B$12,6),$B$49:$D$49,0)))) -> 0 | H76: =IF(INDEX($B$6:$B$12,7)=INDEX($B$6:$B$12,7),0,Core!$H$89*(1-INDEX($B$50:$D$52,MATCH(INDEX($B$6:$B$12,7),$A$50:$A$52,0),MATCH(INDEX($B$6:$B$12,7),$B$49:$D$49,0)))) -> 0 | M76: MAT | N76: =IF(INDEX($N$6:$N$12,3)=INDEX($N$6:$N$12,1),0,Core!$B$85*(1-INDEX($N$53:$Q$56,MATCH(INDEX($N$6:$N$12,3),$M$53:$M$56,0),MATCH(INDEX($N$6:$N$12,1),$N$52:$Q$52,0)))) -> 0 | O76: =IF(INDEX($N$6:$N$12,3)=INDEX($N$6:$N$12,2),0,Core!$C$85*(1-INDEX($N$53:$Q$56,MATCH(INDEX($N$6:$N$12,3),$M$53:$M$56,0),MATCH(INDEX($N$6:$N$12,2),$N$52:$Q$52,0)))) -> 0 | P76: =IF(INDEX($N$6:$N$12,3)=INDEX($N$6:$N$12,3),0,Core!$D$85*(1-INDEX($N$53:$Q$56,MATCH(INDEX($N$6:$N$12,3),$M$53:$M$56,0),MATCH(INDEX($N$6:$N$12,3),$N$52:$Q$52,0)))) -> 0 | Q76: =IF(INDEX($N$6:$N$12,3)=INDEX($N$6:$N$12,4),0,Core!$E$85*(1-INDEX($N$53:$Q$56,MATCH(INDEX($N$6:$N$12,3),$M$53:$M$56,0),MATCH(INDEX($N$6:$N$12,4),$N$52:$Q$52,0)))) -> 0 | R76: =IF(INDEX($N$6:$N$12,3)=INDEX($N$6:$N$12,5),0,Core!$F$85*(1-INDEX($N$53:$Q$56,MATCH(INDEX($N$6:$N$12,3),$M$53:$M$56,0),MATCH(INDEX($N$6:$N$12,5),$N$52:$Q$52,0)))) -> 0 | S76: =IF(INDEX($N$6:$N$12,3)=INDEX($N$6:$N$12,6),0,Core!$G$85*(1-INDEX($N$53:$Q$56,MATCH(INDEX($N$6:$N$12,3),$M$53:$M$56,0),MATCH(INDEX($N$6:$N$12,6),$N$52:$Q$52,0)))) -> 0 | T76: =IF(INDEX($N$6:$N$12,3)=INDEX($N$6:$N$12,7),0,Core!$H$85*(1-INDEX($N$53:$Q$56,MATCH(INDEX($N$6:$N$12,3),$M$53:$M$56,0),MATCH(INDEX($N$6:$N$12,7),$N$52:$Q$52,0)))) -> 0
