Workbook

Sheet README
B1: DCT Laboratory — Vol I, Ch 15: Mathematical Formulation of Enterprise Optimization
B2: Seed 26115 · Companion to DCT_V1_Ch15_Lab.ipynb and AXIOM Lab 1.15 (module AXIOM-15). Money in $ million.
B4: Worked Example 15.1, What Does the Board's Appetite Cost?, with the book's declarations, and the five steps of AXIOM Lab 1.15, Pricing Meridian's Commitments.
B5: Declarations: the GEOP's elements, the lever prices, the commitments and Chapter 8's uncertainty.
B6: Plan: the plan quarter by quarter, the deepest draws, the certainty-equivalent mean path and Chapter 13's joint check as the robust formulation (Step 2).
B7: Quantiles: the one simulation output, from the book's 100,000 paths (seed 8): each line's critical depth at each appetite. Delay and Cost turn it into the least delay and the cost of every package.
B8: Solve: the cheapest package at 5 percent, its binding set, the equal margins and the price of the appetite (Steps 3-4). Sensitivity: the price at other values of delay.
B9: Frontier: the least cost of every appetite (floors), the offices alone, Chapter 8's package, the bank's cap, and Table 15.5 (Step 5). WeightSweep: the same frontier by weights (lab step 4).
B10: Audit: consistency, viability, the capped levers' minimal infeasible set and emptying date (lab step 2).
B11: Allocation: the lab's small allocation (its data are this workbook's declaration), its corner and multipliers (lab step 3).
B12: RollingPlans: Figure 15.1. Architecture: the price of the stability budget and a twitchy optimum.
B13: Reference_Values and Checks: the notebook engine's numbers and a PASS/FAIL comparison with this workbook's formulas.
... B19: Cross-sheet link: green.

Sheet Declarations
A1: Declarations (Worked Example 15.1, Step 1; the plan and its uncertainty are Worked Example 8.1's). Money in $ million.
A3: Quantity | B3: Value | C3: Source | D3: Name
A4: Liquidity today | B4: 620 | C4: Table 5.4; Worked Example 8.1 | D4: Liq0
A5: The board's liquidity floor | B5: 350 | C5: Table 5.4 | D5: Floor_m
A6: Cash above the floor | B6: =B4-B5 -> 270 | C6: Chapter 13's joint check: 270 | D6: Pool
A7: Liquidity per index point | B7: 6.2 | C7: Chapter 1: index 100 = $620 million | D7: Usd_pt
A8: Chapter 1's liquidity target (index) | B8: 112 | C8: Online Appendix 1.B.4 | D8: Liq_target
A9: Relaxation toward the target, a year | B9: 0.35 | C9: Online Appendix 1.B.4 | D9: Relax
A10: Depth of the program's draw, as planned (index points) | B10: 28 | C10: Chapter 1's digital program | D10: Depth0
A11: Years to the deepest draw | B11: 2 | C11: Chapter 1's digital program | D11: Tau
A12: Depth cut by a quarter of delay (index points) | B12: 4 | C12: Chapter 8's phased build: depth 20 for two quarters of delay | D12: Depth_per_q
A13: Standby-line fees a year (share of the line) | B13: 0.01 | C13: Worked Example 15.1: about 1 percent | D13: Fee_year
A14: Program length (years) | B14: 3 | C14: Twelve quarters | D14: Years
A15: Fees over the program (share of the line) | B15: =B13*B14 -> 0.03 | C15: $3 million per $100 million | D15: Fee
A16: Value of a quarter of delay | B16: 8 | C16: The transformation office: Digital Solutions' contribution | D16: Vq
A17: The board's appetite: chance of a breach in some quarter | B17: 0.05 | C17: Chapter 8; a chance constraint | D17: Appetite
A18: Revenue | B18: 4200 | C18: Chapter 1 | D18: Revenue
A19: EBITDA margin | B19: 0.118 | C19: Chapter 1 | D19: Margin
A20: EBITDA | B20: =B18*B19 -> 495.6 | C20: $495.6 million | D20: Ebitda
A21: Net leverage today (net debt / EBITDA) | B21: 3.4 | C21: Table 5.4 | D21: Lev0
A22: Net debt | B22: =B21*B20 -> 1685.04 | C22: $1,685 million | D22: Net_debt
A23: Covenant: net leverage at most | B23: 4.5 | C23: Table 5.4; the CFO | D23: Covenant
A24: Workforce capability today | B24: 58 | C24: Table 5.2 | D24: Capability
A25: Capability floor for the digital build | B25: 55 | C25: Worked Example 3.1; HR and the CTO | D25: Cap_floor
A26: Persistence of the execution and market deviation | B26: 0.6 | C26: Worked Example 8.1 | D26: A_e
A27: Surprise a quarter: standard deviation | B27: 50 | C27: Worked Example 8.1 | D27: Sd_w
A28: Funding-window closures a year | B28: 0.1 | C28: Worked Example 8.1 | D28: Lam
A29: Closure size: mean | B29: 120 | C29: Worked Example 8.1 | D29: J_mean
A30: Closure size: standard deviation | B30: 50 | C30: Worked Example 8.1 | D30: J_sd
A31: Gamma shape of a closure | B31: =(B29/B30)^2 -> 5.76 | C31: 5.76 | D31: G_shape
A32: Gamma scale of a closure | B32: =B30^2/B29 -> 20.833333 | C32: 20.83 | D32: G_scale
A33: Paths | B33: 100000 | C33: Worked Example 8.1 | D33: N_paths
A34: Random seed of the book's paths | B34: 8 | C34: Volume II, Online Appendix 1.B.4 | D34: Book_seed
A36: Decisions: the standby line l (owned by the CFO) replaces up to l of any closure; the delay phi of the platform (owned by the transformation office) sets the draw's depth at 28 - 4 phi. Objective: minimize Fee x l + Vq x phi. Commitments: the appetite (board), the covenant (CFO), the capability floor (HR, CTO).

Sheet Plan
A1: The plan, the deepest draws and the three formulations (Worked Example 15.1, Step 2; Proposition 15.7)
A2: Liquidity = $6.2 million x (Chapter 1's index less the draw D x s(t)), s(t) = (t/2) e^(1 - t/2). The mean path is the plan less the closures' expected drain (no line): the certainty equivalent.
A5: Quarter | B5: Years t | C5: Index without the draw | D5: Draw shape s(t) | E5: Plan as drawn (D = 28) | F5: Phased build (D = 20) | G5: At the cheapest package's depth | H5: Expected closures so far | I5: Mean path (plan less the drain)
A6: 0 | B6: =A6/4 -> 0 | C6: =Liq_target+(100-Liq_target)*EXP(-Relax*B6) -> 100 | D6: =(B6/Tau)*EXP(1-B6/Tau) -> 0 | E6: =Usd_pt*(C6-Depth0*D6) -> 620 | F6: =Usd_pt*(C6-(Depth0-2*Depth_per_q)*D6) -> 620 | G6: =Usd_pt*(C6-Solve!$B$8*D6) -> 620 | H6: =Lam/4*A6*J_mean -> 0 | I6: =E6-H6 -> 620
A7: 1 | B7: =A7/4 -> 0.25 | C7: =Liq_target+(100-Liq_target)*EXP(-Relax*B7) -> 101.00537 | D7: =(B7/Tau)*EXP(1-B7/Tau) -> 0.29985941 | E7: =Usd_pt*(C7-Depth0*D7) -> 574.17772 | F7: =Usd_pt*(C7-(Depth0-2*Depth_per_q)*D7) -> 589.05075 | G7: =Usd_pt*(C7-Solve!$B$8*D7) -> 579.14216 | H7: =Lam/4*A7*J_mean -> 3 | I7: =E7-H7 -> 571.17772
A8: 2 | B8: =A8/4 -> 0.5 | C8: =Liq_target+(100-Liq_target)*EXP(-Relax*B8) -> 101.92652 | D8: =(B8/Tau)*EXP(1-B8/Tau) -> 0.52925 | E8: =Usd_pt*(C8-Depth0*D8) -> 540.0666 | F8: =Usd_pt*(C8-(Depth0-2*Depth_per_q)*D8) -> 566.3174 | G8: =Usd_pt*(C8-Solve!$B$8*D8) -> 548.8288 | H8: =Lam/4*A8*J_mean -> 6 | I8: =E8-H8 -> 534.0666
A9: 3 | B9: =A9/4 -> 0.75 | C9: =Liq_target+(100-Liq_target)*EXP(-Relax*B9) -> 102.77048 | D9: =(B9/Tau)*EXP(1-B9/Tau) -> 0.70059223 | E9: =Usd_pt*(C9-Depth0*D9) -> 515.55419 | F9: =Usd_pt*(C9-(Depth0-2*Depth_per_q)*D9) -> 550.30356 | G9: =Usd_pt*(C9-Solve!$B$8*D9) -> 527.15312 | H9: =Lam/4*A9*J_mean -> 9 | I9: =E9-H9 -> 506.55419
A10: 4 | B10: =A10/4 -> 1 | C10: =Liq_target+(100-Liq_target)*EXP(-Relax*B10) -> 103.54374 | D10: =(B10/Tau)*EXP(1-B10/Tau) -> 0.82436064 | E10: =Usd_pt*(C10-Depth0*D10) -> 498.8622 | F10: =Usd_pt*(C10-(Depth0-2*Depth_per_q)*D10) -> 539.75049 | G10: =Usd_pt*(C10-Solve!$B$8*D10) -> 512.51023 | H10: =Lam/4*A10*J_mean -> 12 | I10: =E10-H10 -> 486.8622
A11: 5 | B11: =A11/4 -> 1.25 | C11: =Liq_target+(100-Liq_target)*EXP(-Relax*B11) -> 104.25222 | D11: =(B11/Tau)*EXP(1-B11/Tau) -> 0.90936963 | E11: =Usd_pt*(C11-Depth0*D11) -> 488.49718 | F11: =Usd_pt*(C11-(Depth0-2*Depth_per_q)*D11) -> 533.60192 | G11: =Usd_pt*(C11-Solve!$B$8*D11) -> 503.55261 | H11: =Lam/4*A11*J_mean -> 15 | I11: =E11-H11 -> 473.49718
A12: 6 | B12: =A12/4 -> 1.5 | C12: =Liq_target+(100-Liq_target)*EXP(-Relax*B12) -> 104.90134 | D12: =(B12/Tau)*EXP(1-B12/Tau) -> 0.96301906 | E12: =Usd_pt*(C12-Depth0*D12) -> 483.20817 | F12: =Usd_pt*(C12-(Depth0-2*Depth_per_q)*D12) -> 530.97392 | G12: =Usd_pt*(C12-Solve!$B$8*D12) -> 499.15181 | H12: =Lam/4*A12*J_mean -> 18 | I12: =E12-H12 -> 465.20817
A13: 7 | B13: =A13/4 -> 1.75 | C13: =Liq_target+(100-Liq_target)*EXP(-Relax*B13) -> 105.49607 | D13: =(B13/Tau)*EXP(1-B13/Tau) -> 0.9915049 | E13: =Usd_pt*(C13-Depth0*D13) -> 481.95038 | F13: =Usd_pt*(C13-(Depth0-2*Depth_per_q)*D13) -> 531.12903 | G13: =Usd_pt*(C13-Solve!$B$8*D13) -> 498.36563 | H13: =Lam/4*A13*J_mean -> 21 | I13: =E13-H13 -> 460.95038
A14: 8 | B14: =A14/4 -> 2 | C14: =Liq_target+(100-Liq_target)*EXP(-Relax*B14) -> 106.04098 | D14: =(B14/Tau)*EXP(1-B14/Tau) -> 1 | E14: =Usd_pt*(C14-Depth0*D14) -> 483.85405 | F14: =Usd_pt*(C14-(Depth0-2*Depth_per_q)*D14) -> 533.45405 | G14: =Usd_pt*(C14-Solve!$B$8*D14) -> 500.40995 | H14: =Lam/4*A14*J_mean -> 24 | I14: =E14-H14 -> 459.85405
A15: 9 | B15: =A15/4 -> 2.25 | C15: =Liq_target+(100-Liq_target)*EXP(-Relax*B15) -> 106.54023 | D15: =(B15/Tau)*EXP(1-B15/Tau) -> 0.99280902 | E15: =Usd_pt*(C15-Depth0*D15) -> 488.19778 | F15: =Usd_pt*(C15-(Depth0-2*Depth_per_q)*D15) -> 537.44111 | G15: =Usd_pt*(C15-Solve!$B$8*D15) -> 504.63462 | H15: =Lam/4*A15*J_mean -> 27 | I15: =E15-H15 -> 461.19778
A16: 10 | B16: =A16/4 -> 2.5 | C16: =Liq_target+(100-Liq_target)*EXP(-Relax*B16) -> 106.99766 | D16: =(B16/Tau)*EXP(1-B16/Tau) -> 0.97350098 | E16: =Usd_pt*(C16-Depth0*D16) -> 494.3857 | F16: =Usd_pt*(C16-(Depth0-2*Depth_per_q)*D16) -> 542.67134 | G16: =Usd_pt*(C16-Solve!$B$8*D16) -> 510.50287 | H16: =Lam/4*A16*J_mean -> 30 | I16: =E16-H16 -> 464.3857
A17: 11 | B17: =A17/4 -> 2.75 | C17: =Liq_target+(100-Liq_target)*EXP(-Relax*B17) -> 107.41676 | D17: =(B17/Tau)*EXP(1-B17/Tau) -> 0.94502276 | E17: =Usd_pt*(C17-Depth0*D17) -> 501.92795 | F17: =Usd_pt*(C17-(Depth0-2*Depth_per_q)*D17) -> 548.80108 | G17: =Usd_pt*(C17-Solve!$B$8*D17) -> 517.57364 | H17: =Lam/4*A17*J_mean -> 33 | I17: =E17-H17 -> 468.92795
A18: 12 | B18: =A18/4 -> 3 | C18: =Liq_target+(100-Liq_target)*EXP(-Relax*B18) -> 107.80075 | D18: =(B18/Tau)*EXP(1-B18/Tau) -> 0.90979599 | E18: =Usd_pt*(C18-Depth0*D18) -> 510.42405 | F18: =Usd_pt*(C18-(Depth0-2*Depth_per_q)*D18) -> 555.54993 | G18: =Usd_pt*(C18-Solve!$B$8*D18) -> 525.48653 | H18: =Lam/4*A18*J_mean -> 36 | I18: =E18-H18 -> 474.42405
A21: Deepest draw, plan as drawn | B21: =Liq0-MIN(E6:E18) -> 138.04962 | C21: Worked Example 8.1: 620 - 482 = 138
A22: Deepest draw, Chapter 8's phased build | B22: =Liq0-MIN(F6:F18) -> 89.026083 | C22: 89
A23: The phased build's draw is smaller by | B23: =B21-B22 -> 49.023535 | C23: $49 million
A24: Deepest draw at the cheapest package | B24: =Liq0-MIN(G6:G18) -> 121.63437 | C24: Online Appendix 15.B.4: 121.6
A25: Smaller than the plan's by | B25: =B21-B24 -> 16.41525 | C25: Step 3: $16 million
A27: Certainty equivalent: the mean path's trough | B27: =MIN(I6:I18) -> 459.85405 | C27: Step 2: $460 million, above the floor: no levers
A28: Is the mean path above the floor? | B28: =IF(B27>=Floor_m,"yes: buys nothing","no") -> yes: buys nothing
A30: 90th-percentile closure (gamma) | B30: =GAMMAINV(0.9,G_shape,G_scale) -> 186.86698 | C30: Chapter 12: 187
A31: Robust: the joint check's least line, draw + (P90 - line) <= 270 | B31: =MAX(B30-(Pool-B21),0) -> 54.916594 | C31: Step 2: a $55 million line
A32: Robust: its cost | B32: =Fee*B31 -> 1.6474978 | C32: Step 2: $1.6 million (Online Appendix 15.B.4: 1.65)
A34: Joint check at the cheapest package: draw + buffer | B34: =B24+MAX(B30-Solve!$B$5,0) -> 138.50134 | C34: Fits in the 270 above the floor
A35: Joint check, no levers: draw + buffer | B35: =B21+B30 -> 324.91659 | C35: Chapter 13: 325, the same cash promised twice

Sheet Quantiles
A1: The decision table from the book's 100,000 paths (seed 8): each line's critical depth at each appetite
A2: Engine values. For a line l, a path stays above the floor exactly when the draw's depth D is at most its critical depth. Sorted over the paths, the value at the appetite's quantile is the deepest draw that meets it (Online Appendix 15.B.4). Negative: no delay can meet the appetite with that line.
A3: Quantile index (paths allowed to breach) | B3: 1000 | C3: 1250 | D3: 1500 | E3: 1750 | F3: 2000 | G3: 2250 | H3: 2500 | I3: 2750 | J3: 3000 | K3: 3250 | L3: 3500 | M3: 3750 | N3: 4000 | O3: 4250 | P3: 4500 | Q3: 4750 | R3: 5000 | S3: 5250 | T3: 5500 | U3: 5750 | V3: 6000 | W3: 6250 | X3: 6500 | Y3: 6750 | Z3: 7000 | AA3: 7250 | AB3: 7500 | AC3: 7750 | AD3: 8000 | AE3: 8250 | AF3: 8500 | AG3: 8750 | AH3: 9000 | AI3: 9250 | AJ3: 9500 | AK3: 9750 | AL3: 10000 | AM3: 10250 | AN3: 10500 | AO3: 10750 | AP3: 11000 | AQ3: 11250 | AR3: 11500 | AS3: 11750 | AT3: 12000 | AU3: 12250 | AV3: 12500 | AW3: 12750 | AX3: 13000 | AY3: 13250 | AZ3: 13500 | BA3: 13750 | BB3: 14000 | BC3: 14250 | BD3: 14500 | BE3: 14750 | BF3: 15000 | BG3: 15250 | BH3: 15500 | BI3: 15750 | BJ3: 16000 | BK3: 16250 | BL3: 16500 | BM3: 16750 | BN3: 17000 | BO3: 17250 | BP3: 17500 | BQ3: 17750 | BR3: 18000 | BS3: 18250 | BT3: 18500 | BU3: 18750 | BV3: 19000 | BW3: 19250 | BX3: 19500 | BY3: 19750 | BZ3: 20000 | CA3: 20250 | CB3: 20500 | CC3: 20750 | CD3: 21000 | CE3: 21250 | CF3: 21500 | CG3: 21750 | CH3: 22000 | CI3: 22250 | CJ3: 22500 | CK3: 22750 | CL3: 23000 | CM3: 23250 | CN3: 23500 | CO3: 23750 | CP3: 24000 | CQ3: 24250 | CR3: 24500 | CS3: 24600 | CT3: 3003
A4: Line ($ million) | B4: 0.01 | C4: 0.0125 | D4: 0.015 | E4: 0.0175 | F4: 0.02 | G4: 0.0225 | H4: 0.025 | I4: 0.0275 | J4: 0.03 | K4: 0.0325 | L4: 0.035 | M4: 0.0375 | N4: 0.04 | O4: 0.0425 | P4: 0.045 | Q4: 0.0475 | R4: 0.05 | S4: 0.0525 | T4: 0.055 | U4: 0.0575 | V4: 0.06 | W4: 0.0625 | X4: 0.065 | Y4: 0.0675 | Z4: 0.07 | AA4: 0.0725 | AB4: 0.075 | AC4: 0.0775 | AD4: 0.08 | AE4: 0.0825 | AF4: 0.085 | AG4: 0.0875 | AH4: 0.09 | AI4: 0.0925 | AJ4: 0.095 | AK4: 0.0975 | AL4: 0.1 | AM4: 0.1025 | AN4: 0.105 | AO4: 0.1075 | AP4: 0.11 | AQ4: 0.1125 | AR4: 0.115 | AS4: 0.1175 | AT4: 0.12 | AU4: 0.1225 | AV4: 0.125 | AW4: 0.1275 | AX4: 0.13 | AY4: 0.1325 | AZ4: 0.135 | BA4: 0.1375 | BB4: 0.14 | BC4: 0.1425 | BD4: 0.145 | BE4: 0.1475 | BF4: 0.15 | BG4: 0.1525 | BH4: 0.155 | BI4: 0.1575 | BJ4: 0.16 | BK4: 0.1625 | BL4: 0.165 | BM4: 0.1675 | BN4: 0.17 | BO4: 0.1725 | BP4: 0.175 | BQ4: 0.1775 | BR4: 0.18 | BS4: 0.1825 | BT4: 0.185 | BU4: 0.1875 | BV4: 0.19 | BW4: 0.1925 | BX4: 0.195 | BY4: 0.1975 | BZ4: 0.2 | CA4: 0.2025 | CB4: 0.205 | CC4: 0.2075 | CD4: 0.21 | CE4: 0.2125 | CF4: 0.215 | CG4: 0.2175 | CH4: 0.22 | CI4: 0.2225 | CJ4: 0.225 | CK4: 0.2275 | CL4: 0.23 | CM4: 0.2325 | CN4: 0.235 | CO4: 0.2375 | CP4: 0.24 | CQ4: 0.2425 | CR4: 0.245 | CS4: 0.246 | CT4: 0.03003
A5: 0 | B5: -10.428898 | C5: -8.1975309 | D5: -6.1467259 | E5: -4.5596059 | F5: -2.9213446 | G5: -1.6168311 | H5: -0.56064135 | I5: 0.40980974 | J5: 1.5251766 | K5: 2.4512433 | L5: 3.4138825 | M5: 4.2881335 | N5: 4.9924129 | O5: 5.7406531 | P5: 6.3852114 | Q5: 6.9729905 | R5: 7.6213073 | S5: 8.2326001 | T5: 8.8090794 | U5: 9.3430054 | V5: 9.9140304 | W5: 10.389977 | X5: 10.854323 | Y5: 11.312355 | Z5: 11.787398 | AA5: 12.224687 | AB5: 12.602123 | AC5: 13.031977 | AD5: 13.458882 | AE5: 13.878716 | AF5: 14.253942 | AG5: 14.630825 | AH5: 15.043588 | AI5: 15.346347 | AJ5: 15.737983 | AK5: 16.081349 | AL5: 16.396308 | AM5: 16.700888 | AN5: 17.042457 | AO5: 17.365168 | AP5: 17.654636 | AQ5: 17.960489 | AR5: 18.265361 | AS5: 18.55838 | AT5: 18.855917 | AU5: 19.16187 | AV5: 19.432254 | AW5: 19.679805 | AX5: 19.932454 | AY5: 20.209724 | AZ5: 20.443721 | BA5: 20.660888 | BB5: 20.898265 | BC5: 21.135645 | BD5: 21.394029 | BE5: 21.619886 | BF5: 21.842499 | BG5: 22.050541 | BH5: 22.259603 | BI5: 22.467612 | BJ5: 22.660701 | BK5: 22.860596 | BL5: 23.043192 | BM5: 23.248413 | BN5: 23.459355 | BO5: 23.642021 | BP5: 23.817029 | BQ5: 24.01739 | BR5: 24.19322 | BS5: 24.370725 | BT5: 24.527411 | BU5: 24.697869 | BV5: 24.873384 | BW5: 25.048633 | BX5: 25.206091 | BY5: 25.357191 | BZ5: 25.514969 | CA5: 25.671086 | CB5: 25.81834 | CC5: 25.961262 | CD5: 26.112259 | CE5: 26.25641 | CF5: 26.39051 | CG5: 26.529321 | CH5: 26.662415 | CI5: 26.803343 | CJ5: 26.936134 | CK5: 27.064292 | CL5: 27.197502 | CM5: 27.325626 | CN5: 27.457815 | CO5: 27.578564 | CP5: 27.706134 | CQ5: 27.832592 | CR5: 27.942179 | CS5: 27.990059 | CT5: 1.5474426
A6: 5 | B6: -8.8589893 | C6: -6.7127668 | D6: -4.8394197 | E6: -3.2184509 | F6: -1.5805759 | G6: -0.37568334 | H6: 0.63248342 | I6: 1.671603 | J6: 2.6816093 | K6: 3.6294245 | L6: 4.5435081 | M6: 5.3957061 | N6: 6.08762 | O6: 6.7760686 | P6: 7.426928 | Q6: 8.0251189 | R6: 8.677322 | S6: 9.2867331 | T6: 9.8233242 | U6: 10.314963 | V6: 10.858411 | W6: 11.350467 | X6: 11.820537 | Y6: 12.290065 | Z6: 12.734725 | AA6: 13.159817 | AB6: 13.534312 | AC6: 13.938507 | AD6: 14.356096 | AE6: 14.773424 | AF6: 15.150062 | AG6: 15.505793 | AH6: 15.877098 | AI6: 16.185939 | AJ6: 16.535858 | AK6: 16.885318 | AL6: 17.198121 | AM6: 17.504279 | AN6: 17.815821 | AO6: 18.113715 | AP6: 18.398593 | AQ6: 18.690858 | AR6: 19.010513 | AS6: 19.30005 | AT6: 19.565729 | AU6: 19.852081 | AV6: 20.140192 | AW6: 20.361038 | AX6: 20.583501 | AY6: 20.831153 | AZ6: 21.087774 | BA6: 21.321789 | BB6: 21.532552 | BC6: 21.746005 | BD6: 21.957316 | BE6: 22.213204 | BF6: 22.419242 | BG6: 22.627432 | BH6: 22.823388 | BI6: 23.004762 | BJ6: 23.183709 | BK6: 23.37418 | BL6: 23.556133 | BM6: 23.739182 | BN6: 23.923849 | BO6: 24.117406 | BP6: 24.3007 | BQ6: 24.467581 | BR6: 24.639391 | BS6: 24.788162 | BT6: 24.974104 | BU6: 25.148021 | BV6: 25.304317 | BW6: 25.463435 | BX6: 25.613946 | BY6: 25.77317 | BZ6: 25.914495 | CA6: 26.051372 | CB6: 26.187214 | CC6: 26.32391 | CD6: 26.465659 | CE6: 26.604005 | CF6: 26.737255 | CG6: 26.878023 | CH6: 27.006571 | CI6: 27.131655 | CJ6: 27.248296 | CK6: 27.374733 | CL6: 27.494456 | CM6: 27.618821 | CN6: 27.74916 | CO6: 27.868557 | CP6: 27.989154 | CQ6: 28.113402 | CR6: 28.250777 | CS6: 28.299357 | CT6: 2.6936105
A7: 10 | B7: -7.4620926 | C7: -5.2164457 | D7: -3.4188031 | E7: -1.9571485 | F7: -0.45142712 | G7: 0.80801708 | H7: 1.8629889 | I7: 2.8533561 | J7: 3.8178989 | K7: 4.7793862 | L7: 5.688022 | M7: 6.4590172 | N7: 7.1975049 | O7: 7.8408326 | P7: 8.4910737 | Q7: 9.0728566 | R7: 9.6807638 | S7: 10.284728 | T7: 10.813042 | U7: 11.329219 | V7: 11.811212 | W7: 12.312591 | X7: 12.765264 | Y7: 13.246717 | Z7: 13.691167 | AA7: 14.074964 | AB7: 14.464566 | AC7: 14.839787 | AD7: 15.248533 | AE7: 15.622843 | AF7: 15.982573 | AG7: 16.331114 | AH7: 16.699261 | AI7: 17.003099 | AJ7: 17.354557 | AK7: 17.684437 | AL7: 17.971624 | AM7: 18.242656 | AN7: 18.579102 | AO7: 18.868222 | AP7: 19.147811 | AQ7: 19.433507 | AR7: 19.724056 | AS7: 19.992695 | AT7: 20.2688 | AU7: 20.5137 | AV7: 20.76829 | AW7: 21.021382 | AX7: 21.250732 | AY7: 21.466301 | AZ7: 21.703119 | BA7: 21.921302 | BB7: 22.147822 | BC7: 22.339004 | BD7: 22.540741 | BE7: 22.71921 | BF7: 22.93901 | BG7: 23.132032 | BH7: 23.326027 | BI7: 23.523627 | BJ7: 23.70278 | BK7: 23.882959 | BL7: 24.056508 | BM7: 24.237275 | BN7: 24.398646 | BO7: 24.559909 | BP7: 24.728131 | BQ7: 24.901538 | BR7: 25.081741 | BS7: 25.235136 | BT7: 25.396136 | BU7: 25.558968 | BV7: 25.694363 | BW7: 25.850091 | BX7: 26.000591 | BY7: 26.140493 | BZ7: 26.278317 | CA7: 26.40907 | CB7: 26.553572 | CC7: 26.688145 | CD7: 26.821442 | CE7: 26.949379 | CF7: 27.068952 | CG7: 27.197725 | CH7: 27.312085 | CI7: 27.444979 | CJ7: 27.567951 | CK7: 27.681298 | CL7: 27.818627 | CM7: 27.936243 | CN7: 28.043369 | CO7: 28.162256 | CP7: 28.293335 | CQ7: 28.400146 | CR7: 28.514218 | CS7: 28.557349 | CT7: 3.8281618
A8: 15 | B8: -5.9977035 | C8: -3.7998011 | D8: -2.0946811 | E8: -0.57975678 | F8: 0.79780446 | G8: 2.030654 | H8: 3.05205 | I8: 4.0967438 | J8: 4.9974674 | K8: 5.8721154 | L8: 6.8233661 | M8: 7.5778283 | N8: 8.2833495 | O8: 8.9272981 | P8: 9.5089735 | Q8: 10.133568 | R8: 10.685397 | S8: 11.267158 | T8: 11.76437 | U8: 12.300508 | V8: 12.759756 | W8: 13.257586 | X8: 13.701293 | Y8: 14.154662 | Z8: 14.5902 | AA8: 14.981629 | AB8: 15.370134 | AC8: 15.723149 | AD8: 16.128522 | AE8: 16.462179 | AF8: 16.806358 | AG8: 17.140174 | AH8: 17.489793 | AI8: 17.782517 | AJ8: 18.11778 | AK8: 18.437846 | AL8: 18.731488 | AM8: 19.025539 | AN8: 19.30663 | AO8: 19.57829 | AP8: 19.842131 | AQ8: 20.13007 | AR8: 20.385188 | AS8: 20.63598 | AT8: 20.895465 | AU8: 21.161129 | AV8: 21.394899 | AW8: 21.635947 | AX8: 21.870996 | AY8: 22.077051 | AZ8: 22.278596 | BA8: 22.497692 | BB8: 22.703526 | BC8: 22.905539 | BD8: 23.080339 | BE8: 23.266556 | BF8: 23.445896 | BG8: 23.62691 | BH8: 23.832371 | BI8: 24.017994 | BJ8: 24.188737 | BK8: 24.36579 | BL8: 24.515977 | BM8: 24.687977 | BN8: 24.840725 | BO8: 25.017853 | BP8: 25.168326 | BQ8: 25.321571 | BR8: 25.480398 | BS8: 25.639104 | BT8: 25.795511 | BU8: 25.945918 | BV8: 26.081548 | BW8: 26.216028 | BX8: 26.3562 | BY8: 26.483357 | BZ8: 26.619768 | CA8: 26.755375 | CB8: 26.896391 | CC8: 27.019241 | CD8: 27.149435 | CE8: 27.258738 | CF8: 27.396202 | CG8: 27.523972 | CH8: 27.642602 | CI8: 27.766649 | CJ8: 27.879139 | CK8: 27.98977 | CL8: 28.108204 | CM8: 28.235717 | CN8: 28.352244 | CO8: 28.462761 | CP8: 28.579045 | CQ8: 28.696526 | CR8: 28.81928 | CS8: 28.856184 | CT8: 5.0043178
A9: 20 | B9: -4.6837047 | C9: -2.4708725 | D9: -0.7207286 | E9: 0.71663083 | F9: 1.9759966 | G9: 3.1615545 | H9: 4.2856351 | I9: 5.2522873 | J9: 6.1071262 | K9: 7.0157498 | L9: 7.8980708 | M9: 8.6719557 | N9: 9.3242281 | O9: 9.9926587 | P9: 10.541698 | Q9: 11.142709 | R9: 11.725286 | S9: 12.281344 | T9: 12.752734 | U9: 13.251987 | V9: 13.711347 | W9: 14.179992 | X9: 14.623232 | Y9: 15.083375 | Z9: 15.482509 | AA9: 15.832707 | AB9: 16.228767 | AC9: 16.572401 | AD9: 16.957826 | AE9: 17.29572 | AF9: 17.636741 | AG9: 17.940447 | AH9: 18.256112 | AI9: 18.554284 | AJ9: 18.857548 | AK9: 19.162732 | AL9: 19.471773 | AM9: 19.749189 | AN9: 20.020637 | AO9: 20.287077 | AP9: 20.553823 | AQ9: 20.774655 | AR9: 21.027239 | AS9: 21.275023 | AT9: 21.516468 | AU9: 21.751309 | AV9: 21.97269 | AW9: 22.216671 | AX9: 22.432964 | AY9: 22.654583 | AZ9: 22.860596 | BA9: 23.030589 | BB9: 23.213991 | BC9: 23.418639 | BD9: 23.605551 | BE9: 23.78208 | BF9: 23.96374 | BG9: 24.130279 | BH9: 24.298143 | BI9: 24.463309 | BJ9: 24.645534 | BK9: 24.798517 | BL9: 24.970076 | BM9: 25.143532 | BN9: 25.297586 | BO9: 25.447802 | BP9: 25.608476 | BQ9: 25.744508 | BR9: 25.885645 | BS9: 26.017486 | BT9: 26.154039 | BU9: 26.278317 | BV9: 26.424268 | BW9: 26.566418 | BX9: 26.706809 | BY9: 26.841007 | BZ9: 26.970113 | CA9: 27.090968 | CB9: 27.217326 | CC9: 27.325824 | CD9: 27.459809 | CE9: 27.584491 | CF9: 27.706216 | CG9: 27.830769 | CH9: 27.942228 | CI9: 28.058855 | CJ9: 28.170724 | CK9: 28.30588 | CL9: 28.415201 | CM9: 28.526288 | CN9: 28.63596 | CO9: 28.747053 | CP9: 28.864072 | CQ9: 28.974038 | CR9: 29.087622 | CS9: 29.129193 | CT9: 6.1116362
A10: 25 | B10: -3.2017679 | C10: -1.1929082 | D10: 0.51210045 | E10: 2.0403795 | F10: 3.1409217 | G10: 4.2768229 | H10: 5.4188013 | I10: 6.413746 | J10: 7.2717097 | K10: 8.1741085 | L10: 8.9661609 | M10: 9.6969247 | N10: 10.37074 | O10: 10.980399 | P10: 11.546097 | Q10: 12.139905 | R10: 12.73204 | S10: 13.233692 | T10: 13.714837 | U10: 14.180466 | V10: 14.647295 | W10: 15.113367 | X10: 15.513389 | Y10: 15.920744 | Z10: 16.333515 | AA10: 16.679326 | AB10: 17.026125 | AC10: 17.374729 | AD10: 17.74841 | AE10: 18.071112 | AF10: 18.392063 | AG10: 18.706436 | AH10: 19.040628 | AI10: 19.326275 | AJ10: 19.599277 | AK10: 19.891539 | AL10: 20.18372 | AM10: 20.422889 | AN10: 20.668046 | AO10: 20.931954 | AP10: 21.177887 | AQ10: 21.428141 | AR10: 21.662178 | AS10: 21.883609 | AT10: 22.115108 | AU10: 22.34184 | AV10: 22.563226 | AW10: 22.753043 | AX10: 22.955322 | AY10: 23.146225 | AZ10: 23.357938 | BA10: 23.555566 | BB10: 23.730364 | BC10: 23.905163 | BD10: 24.092974 | BE10: 24.279403 | BF10: 24.442867 | BG10: 24.61182 | BH10: 24.76381 | BI10: 24.918535 | BJ10: 25.078504 | BK10: 25.231023 | BL10: 25.389346 | BM10: 25.566583 | BN10: 25.70494 | BO10: 25.847908 | BP10: 25.992875 | BQ10: 26.135494 | BR10: 26.269022 | BS10: 26.400143 | BT10: 26.527971 | BU10: 26.65777 | BV10: 26.789505 | BW10: 26.916587 | BX10: 27.040098 | BY10: 27.158107 | BZ10: 27.275633 | CA10: 27.411892 | CB10: 27.537932 | CC10: 27.650929 | CD10: 27.775527 | CE10: 27.89121 | CF10: 28.006839 | CG10: 28.118 | CH10: 28.247478 | CI10: 28.36058 | CJ10: 28.477878 | CK10: 28.590527 | CL10: 28.697527 | CM10: 28.81782 | CN10: 28.929208 | CO10: 29.037033 | CP10: 29.145603 | CQ10: 29.242129 | CR10: 29.343947 | CS10: 29.382682 | CT10: 7.2806758
A11: 30 | B11: -1.8011761 | C11: 0.014961723 | D11: 1.821427 | E11: 3.2956255 | F11: 4.3828108 | G11: 5.4579222 | H11: 6.5482783 | I11: 7.5421765 | J11: 8.3684529 | K11: 9.2776571 | L11: 10.037469 | M11: 10.742593 | N11: 11.360122 | O11: 11.966457 | P11: 12.538499 | Q11: 13.131319 | R11: 13.684965 | S11: 14.181159 | T11: 14.682351 | U11: 15.112572 | V11: 15.562709 | W11: 15.960554 | X11: 16.36965 | Y11: 16.751689 | Z11: 17.156578 | AA11: 17.501331 | AB11: 17.826701 | AC11: 18.15022 | AD11: 18.493324 | AE11: 18.838502 | AF11: 19.1197 | AG11: 19.45739 | AH11: 19.750805 | AI11: 20.043755 | AJ11: 20.305883 | AK11: 20.572523 | AL11: 20.83271 | AM11: 21.114808 | AN11: 21.360385 | AO11: 21.576985 | AP11: 21.801047 | AQ11: 22.022879 | AR11: 22.24863 | AS11: 22.458839 | AT11: 22.656976 | AU11: 22.882973 | AV11: 23.073274 | AW11: 23.280909 | AX11: 23.481945 | AY11: 23.670412 | AZ11: 23.855531 | BA11: 24.029877 | BB11: 24.228362 | BC11: 24.39558 | BD11: 24.548742 | BE11: 24.712456 | BF11: 24.87996 | BG11: 25.052169 | BH11: 25.217988 | BI11: 25.365528 | BJ11: 25.519593 | BK11: 25.665421 | BL11: 25.803549 | BM11: 25.945918 | BN11: 26.079251 | BO11: 26.216028 | BP11: 26.360723 | BQ11: 26.496392 | BR11: 26.618875 | BS11: 26.751813 | BT11: 26.894082 | BU11: 27.014578 | BV11: 27.142746 | BW11: 27.255737 | BX11: 27.37511 | BY11: 27.496201 | BZ11: 27.614668 | CA11: 27.728827 | CB11: 27.849411 | CC11: 27.954962 | CD11: 28.06916 | CE11: 28.182129 | CF11: 28.318341 | CG11: 28.426353 | CH11: 28.537957 | CI11: 28.643621 | CJ11: 28.758121 | CK11: 28.878028 | CL11: 28.986075 | CM11: 29.095197 | CN11: 29.200872 | CO11: 29.29764 | CP11: 29.391942 | CQ11: 29.497697 | CR11: 29.593552 | CS11: 29.629189 | CT11: 8.3768794
A12: 35 | B12: -0.35451338 | C12: 1.3858309 | D12: 3.1177457 | E12: 4.5264713 | F12: 5.6026464 | G12: 6.5976872 | H12: 7.6654205 | I12: 8.6072807 | J12: 9.5471067 | K12: 10.338432 | L12: 11.088493 | M12: 11.710857 | N12: 12.341926 | O12: 12.937072 | P12: 13.534125 | Q12: 14.10858 | R12: 14.61185 | S12: 15.113806 | T12: 15.598537 | U12: 15.974702 | V12: 16.398552 | W12: 16.805355 | X12: 17.202264 | Y12: 17.573636 | Z12: 17.930853 | AA12: 18.261685 | AB12: 18.611777 | AC12: 18.918593 | AD12: 19.234733 | AE12: 19.58362 | AF12: 19.860438 | AG12: 20.161962 | AH12: 20.428825 | AI12: 20.705079 | AJ12: 20.949356 | AK12: 21.212444 | AL12: 21.467959 | AM12: 21.734394 | AN12: 21.96608 | AO12: 22.193262 | AP12: 22.405186 | AQ12: 22.620775 | AR12: 22.824444 | AS12: 23.030258 | AT12: 23.202263 | AU12: 23.395904 | AV12: 23.577184 | AW12: 23.780448 | AX12: 23.968744 | AY12: 24.156159 | AZ12: 24.329482 | BA12: 24.490615 | BB12: 24.672182 | BC12: 24.828315 | BD12: 25.013657 | BE12: 25.172099 | BF12: 25.337002 | BG12: 25.48537 | BH12: 25.639104 | BI12: 25.779968 | BJ12: 25.925434 | BK12: 26.070552 | BL12: 26.198194 | BM12: 26.321944 | BN12: 26.456685 | BO12: 26.582343 | BP12: 26.710137 | BQ12: 26.837356 | BR12: 26.965303 | BS12: 27.097387 | BT12: 27.216913 | BU12: 27.338074 | BV12: 27.463362 | BW12: 27.577045 | BX12: 27.698968 | BY12: 27.819929 | BZ12: 27.932029 | CA12: 28.05082 | CB12: 28.160143 | CC12: 28.287705 | CD12: 28.389061 | CE12: 28.502696 | CF12: 28.612936 | CG12: 28.712447 | CH12: 28.828828 | CI12: 28.943911 | CJ12: 29.048455 | CK12: 29.156591 | CL12: 29.249606 | CM12: 29.348719 | CN12: 29.455617 | CO12: 29.555437 | CP12: 29.644863 | CQ12: 29.739408 | CR12: 29.842481 | CS12: 29.881021 | CT12: 9.5542854
A13: 40 | B13: 0.84604229 | C13: 2.7386597 | D13: 4.3555081 | E13: 5.6060547 | F13: 6.7608071 | G13: 7.7783116 | H13: 8.8049963 | I13: 9.6806851 | J13: 10.611446 | K13: 11.401269 | L13: 12.081808 | M13: 12.739189 | N13: 13.309707 | O13: 13.88868 | P13: 14.459524 | Q13: 15.04408 | R13: 15.573581 | S13: 15.96727 | T13: 16.429356 | U13: 16.819242 | V13: 17.239292 | W13: 17.63201 | X13: 17.961183 | Y13: 18.333007 | Z13: 18.686388 | AA13: 19.02126 | AB13: 19.35166 | AC13: 19.626263 | AD13: 19.93733 | AE13: 20.258821 | AF13: 20.545921 | AG13: 20.784034 | AH13: 21.070294 | AI13: 21.337437 | AJ13: 21.597938 | AK13: 21.815047 | AL13: 22.051941 | AM13: 22.285006 | AN13: 22.523669 | AO13: 22.74596 | AP13: 22.95412 | AQ13: 23.137527 | AR13: 23.362244 | AS13: 23.54686 | AT13: 23.725676 | AU13: 23.919638 | AV13: 24.08694 | AW13: 24.264923 | AX13: 24.440708 | AY13: 24.627457 | AZ13: 24.78573 | BA13: 24.951861 | BB13: 25.122945 | BC13: 25.271107 | BD13: 25.4385 | BE13: 25.600069 | BF13: 25.740377 | BG13: 25.889214 | BH13: 26.025392 | BI13: 26.1669 | BJ13: 26.290606 | BK13: 26.431312 | BL13: 26.571892 | BM13: 26.70047 | BN13: 26.831819 | BO13: 26.964261 | BP13: 27.082565 | BQ13: 27.199611 | BR13: 27.309294 | BS13: 27.428145 | BT13: 27.546254 | BU13: 27.65753 | BV13: 27.778069 | BW13: 27.89621 | BX13: 28.007625 | BY13: 28.12026 | BZ13: 28.246778 | CA13: 28.360659 | CB13: 28.468939 | CC13: 28.574426 | CD13: 28.673748 | CE13: 28.804222 | CF13: 28.912615 | CG13: 29.020533 | CH13: 29.121474 | CI13: 29.224627 | CJ13: 29.312698 | CK13: 29.419615 | CL13: 29.51472 | CM13: 29.608268 | CN13: 29.697982 | CO13: 29.798618 | CP13: 29.898037 | CQ13: 29.994657 | CR13: 30.087808 | CS13: 30.129234 | CT13: 10.620755
A14: 45 | B14: 1.9533922 | C14: 3.909728 | D14: 5.5530003 | E14: 6.8047313 | F14: 7.8731831 | G14: 8.9736185 | H14: 9.9103931 | I14: 10.752087 | J14: 11.61158 | K14: 12.407993 | L14: 13.102142 | M14: 13.718584 | N14: 14.274677 | O14: 14.819896 | P14: 15.335646 | Q14: 15.88223 | R14: 16.389965 | S14: 16.789717 | T14: 17.253341 | U14: 17.62902 | V14: 17.997908 | W14: 18.368037 | X14: 18.731508 | Y14: 19.10613 | Z14: 19.422612 | AA14: 19.733244 | AB14: 20.066229 | AC14: 20.323799 | AD14: 20.582129 | AE14: 20.869321 | AF14: 21.170588 | AG14: 21.424258 | AH14: 21.669738 | AI14: 21.912631 | AJ14: 22.174895 | AK14: 22.401245 | AL14: 22.61586 | AM14: 22.840088 | AN14: 23.040241 | AO14: 23.252556 | AP14: 23.461172 | AQ14: 23.656852 | AR14: 23.836763 | AS14: 24.021634 | AT14: 24.216611 | AU14: 24.38822 | AV14: 24.561773 | AW14: 24.735606 | AX14: 24.894139 | AY14: 25.064801 | AZ14: 25.218419 | BA14: 25.380737 | BB14: 25.558074 | BC14: 25.69494 | BD14: 25.844611 | BE14: 25.992654 | BF14: 26.132248 | BG14: 26.270327 | BH14: 26.405788 | BI14: 26.542242 | BJ14: 26.671675 | BK14: 26.797156 | BL14: 26.920988 | BM14: 27.04276 | BN14: 27.173265 | BO14: 27.281964 | BP14: 27.414099 | BQ14: 27.53091 | BR14: 27.645972 | BS14: 27.776772 | BT14: 27.889378 | BU14: 27.989768 | BV14: 28.103277 | BW14: 28.217051 | BX14: 28.331438 | BY14: 28.439572 | BZ14: 28.543287 | CA14: 28.649883 | CB14: 28.768205 | CC14: 28.881233 | CD14: 28.98428 | CE14: 29.092588 | CF14: 29.193618 | CG14: 29.287882 | CH14: 29.383886 | CI14: 29.4852 | CJ14: 29.584418 | CK14: 29.672925 | CL14: 29.773906 | CM14: 29.872209 | CN14: 29.963957 | CO14: 30.055882 | CP14: 30.15133 | CQ14: 30.23844 | CR14: 30.320761 | CS14: 30.355913 | CT14: 11.625358
A15: 50 | B15: 3.1821207 | C15: 5.1341257 | D15: 6.6995752 | E15: 7.8941042 | F15: 9.0600608 | G15: 10.061229 | H15: 10.992817 | I15: 11.846807 | J15: 12.661727 | K15: 13.3633 | L15: 14.090583 | M15: 14.653339 | N15: 15.206647 | O15: 15.712756 | P15: 16.222545 | Q15: 16.717763 | R15: 17.196095 | S15: 17.576054 | T15: 18.001074 | U15: 18.366233 | V15: 18.753686 | W15: 19.097675 | X15: 19.459438 | Y15: 19.803793 | Z15: 20.139724 | AA15: 20.412862 | AB15: 20.696101 | AC15: 20.994049 | AD15: 21.252239 | AE15: 21.482346 | AF15: 21.748018 | AG15: 22.005057 | AH15: 22.249506 | AI15: 22.473672 | AJ15: 22.700788 | AK15: 22.916121 | AL15: 23.121795 | AM15: 23.324729 | AN15: 23.530399 | AO15: 23.727259 | AP15: 23.929929 | AQ15: 24.120081 | AR15: 24.318917 | AS15: 24.49162 | AT15: 24.660942 | AU15: 24.816501 | AV15: 24.995225 | AW15: 25.160767 | AX15: 25.331109 | AY15: 25.484343 | AZ15: 25.640672 | BA15: 25.781998 | BB15: 25.932904 | BC15: 26.074214 | BD15: 26.213748 | BE15: 26.357306 | BF15: 26.495048 | BG15: 26.622896 | BH15: 26.760166 | BI15: 26.895561 | BJ15: 27.0174 | BK15: 27.143311 | BL15: 27.254523 | BM15: 27.385066 | BN15: 27.50561 | BO15: 27.616446 | BP15: 27.736385 | BQ15: 27.852682 | BR15: 27.966609 | BS15: 28.079239 | BT15: 28.19634 | BU15: 28.321957 | BV15: 28.425419 | BW15: 28.537129 | BX15: 28.643621 | BY15: 28.754963 | BZ15: 28.859008 | CA15: 28.966437 | CB15: 29.067988 | CC15: 29.167623 | CD15: 29.261762 | CE15: 29.351037 | CF15: 29.461284 | CG15: 29.554673 | CH15: 29.645448 | CI15: 29.735962 | CJ15: 29.837641 | CK15: 29.936154 | CL15: 30.029911 | CM15: 30.127923 | CN15: 30.213258 | CO15: 30.289951 | CP15: 30.375635 | CQ15: 30.463968 | CR15: 30.553487 | CS15: 30.590835 | CT15: 12.665393
A16: 55 | B16: 4.4268588 | C16: 6.3128749 | D16: 7.8256163 | E16: 9.0325851 | F16: 10.152809 | G16: 11.14879 | H16: 12.019769 | I16: 12.835696 | J16: 13.636454 | K16: 14.334096 | L16: 14.986506 | M16: 15.541431 | N16: 16.100603 | O16: 16.581595 | P16: 17.056024 | Q16: 17.518384 | R16: 17.951515 | S16: 18.32115 | T16: 18.705128 | U16: 19.097263 | V16: 19.458712 | W16: 19.799354 | X16: 20.148477 | Y16: 20.444634 | Z16: 20.740393 | AA16: 21.050535 | AB16: 21.337453 | AC16: 21.576778 | AD16: 21.850185 | AE16: 22.087586 | AF16: 22.317418 | AG16: 22.558732 | AH16: 22.785182 | AI16: 23.021312 | AJ16: 23.215089 | AK16: 23.408605 | AL16: 23.615629 | AM16: 23.814114 | AN16: 24.010005 | AO16: 24.194838 | AP16: 24.376549 | AQ16: 24.549902 | AR16: 24.730212 | AS16: 24.906983 | AT16: 25.08123 | AU16: 25.252446 | AV16: 25.421205 | AW16: 25.57717 | AX16: 25.713292 | AY16: 25.872568 | AZ16: 26.013152 | BA16: 26.159746 | BB16: 26.288267 | BC16: 26.427699 | BD16: 26.561934 | BE16: 26.687127 | BF16: 26.829089 | BG16: 26.95237 | BH16: 27.090167 | BI16: 27.213634 | BJ16: 27.329637 | BK16: 27.458667 | BL16: 27.577045 | BM16: 27.696444 | BN16: 27.828842 | BO16: 27.939314 | BP16: 28.046391 | BQ16: 28.160451 | BR16: 28.292743 | BS16: 28.393315 | BT16: 28.504228 | BU16: 28.612569 | BV16: 28.716091 | BW16: 28.835106 | BX16: 28.944995 | BY16: 29.053269 | BZ16: 29.154232 | CA16: 29.249606 | CB16: 29.345174 | CC16: 29.453976 | CD16: 29.544641 | CE16: 29.634114 | CF16: 29.720598 | CG16: 29.816588 | CH16: 29.913105 | CI16: 30.004173 | CJ16: 30.098666 | CK16: 30.182842 | CL16: 30.265465 | CM16: 30.352031 | CN16: 30.436328 | CO16: 30.524762 | CP16: 30.609394 | CQ16: 30.690389 | CR16: 30.773975 | CS16: 30.809956 | CT16: 13.649299
... A85: 400 | B85: 19.827608 | C85: 20.574445 | D85: 21.230334 | E85: 21.778141 | F85: 22.256328 | G85: 22.684328 | H85: 23.05701 | I85: 23.419515 | J85: 23.725676 | K85: 24.041667 | L85: 24.349259 | M85: 24.605478 | N85: 24.856075 | O85: 25.116243 | P85: 25.351449 | Q85: 25.578589 | R85: 25.781569 | S85: 25.98247 | T85: 26.163908 | U85: 26.344006 | V85: 26.517224 | W85: 26.699145 | X85: 26.875398 | Y85: 27.025731 | Z85: 27.182078 | AA85: 27.329704 | AB85: 27.492836 | AC85: 27.636453 | AD85: 27.786149 | AE85: 27.919033 | AF85: 28.052907 | AG85: 28.192798 | AH85: 28.339244 | AI85: 28.460476 | AJ85: 28.588337 | AK85: 28.713684 | AL85: 28.847785 | AM85: 28.97453 | AN85: 29.090721 | AO85: 29.20885 | AP85: 29.308103 | AQ85: 29.420841 | AR85: 29.534378 | AS85: 29.64005 | AT85: 29.744437 | AU85: 29.865003 | AV85: 29.965334 | AW85: 30.068155 | AX85: 30.166729 | AY85: 30.256101 | AZ85: 30.350484 | BA85: 30.444159 | BB85: 30.536562 | BC85: 30.627623 | BD85: 30.716168 | BE85: 30.79833 | BF85: 30.894832 | BG85: 30.982573 | BH85: 31.062176 | BI85: 31.145788 | BJ85: 31.232821 | BK85: 31.312531 | BL85: 31.390263 | BM85: 31.475537 | BN85: 31.556151 | BO85: 31.628961 | BP85: 31.706783 | BQ85: 31.792946 | BR85: 31.872191 | BS85: 31.955717 | BT85: 32.03212 | BU85: 32.109986 | BV85: 32.184184 | BW85: 32.255141 | BX85: 32.326509 | BY85: 32.396269 | BZ85: 32.47766 | CA85: 32.549948 | CB85: 32.617763 | CC85: 32.681997 | CD85: 32.747033 | CE85: 32.815102 | CF85: 32.886377 | CG85: 32.952964 | CH85: 33.019641 | CI85: 33.092465 | CJ85: 33.155847 | CK85: 33.210313 | CL85: 33.273206 | CM85: 33.347037 | CN85: 33.413948 | CO85: 33.482951 | CP85: 33.55019 | CQ85: 33.616955 | CR85: 33.681944 | CS85: 33.70648 | CT85: 23.732449

Sheet Delay
A1: The least delay that meets each appetite with each line (quarters): (28 - the critical depth) / 4
A2: Blank where no delay can meet the appetite with that line. Depth = 28 - 4 x delay, never below 0.
A4: Line ($ million) | B4: =Quantiles!B4 -> 0.01 | C4: =Quantiles!C4 -> 0.0125 | D4: =Quantiles!D4 -> 0.015 | E4: =Quantiles!E4 -> 0.0175 | F4: =Quantiles!F4 -> 0.02 | G4: =Quantiles!G4 -> 0.0225 | H4: =Quantiles!H4 -> 0.025 | I4: =Quantiles!I4 -> 0.0275 | ... CT4: =Quantiles!CT4 -> 0.03003
A5: =Quantiles!A5 -> 0 | B5: =IF(Quantiles!B5<0,"",(Depth0-MIN(Depth0,Quantiles!B5))/Depth_per_q) | C5: =IF(Quantiles!C5<0,"",(Depth0-MIN(Depth0,Quantiles!C5))/Depth_per_q) | D5: =IF(Quantiles!D5<0,"",(Depth0-MIN(Depth0,Quantiles!D5))/Depth_per_q) | E5: =IF(Quantiles!E5<0,"",(Depth0-MIN(Depth0,Quantiles!E5))/Depth_per_q) | F5: =IF(Quantiles!F5<0,"",(Depth0-MIN(Depth0,Quantiles!F5))/Depth_per_q) | G5: =IF(Quantiles!G5<0,"",(Depth0-MIN(Depth0,Quantiles!G5))/Depth_per_q) | H5: =IF(Quantiles!H5<0,"",(Depth0-MIN(Depth0,Quantiles!H5))/Depth_per_q) | I5: =IF(Quantiles!I5<0,"",(Depth0-MIN(Depth0,Quantiles!I5))/Depth_per_q) -> 6.8975476 | ... CT5: =IF(Quantiles!CT5<0,"",(Depth0-MIN(Depth0,Quantiles!CT5))/Depth_per_q) -> 6.6131394
A6: =Quantiles!A6 -> 5 | B6: =IF(Quantiles!B6<0,"",(Depth0-MIN(Depth0,Quantiles!B6))/Depth_per_q) | C6: =IF(Quantiles!C6<0,"",(Depth0-MIN(Depth0,Quantiles!C6))/Depth_per_q) | D6: =IF(Quantiles!D6<0,"",(Depth0-MIN(Depth0,Quantiles!D6))/Depth_per_q) | E6: =IF(Quantiles!E6<0,"",(Depth0-MIN(Depth0,Quantiles!E6))/Depth_per_q) | F6: =IF(Quantiles!F6<0,"",(Depth0-MIN(Depth0,Quantiles!F6))/Depth_per_q) | G6: =IF(Quantiles!G6<0,"",(Depth0-MIN(Depth0,Quantiles!G6))/Depth_per_q) | H6: =IF(Quantiles!H6<0,"",(Depth0-MIN(Depth0,Quantiles!H6))/Depth_per_q) -> 6.8418791 | I6: =IF(Quantiles!I6<0,"",(Depth0-MIN(Depth0,Quantiles!I6))/Depth_per_q) -> 6.5820992 | ... CT6: =IF(Quantiles!CT6<0,"",(Depth0-MIN(Depth0,Quantiles!CT6))/Depth_per_q) -> 6.3265974
A7: =Quantiles!A7 -> 10 | B7: =IF(Quantiles!B7<0,"",(Depth0-MIN(Depth0,Quantiles!B7))/Depth_per_q) | C7: =IF(Quantiles!C7<0,"",(Depth0-MIN(Depth0,Quantiles!C7))/Depth_per_q) | D7: =IF(Quantiles!D7<0,"",(Depth0-MIN(Depth0,Quantiles!D7))/Depth_per_q) | E7: =IF(Quantiles!E7<0,"",(Depth0-MIN(Depth0,Quantiles!E7))/Depth_per_q) | F7: =IF(Quantiles!F7<0,"",(Depth0-MIN(Depth0,Quantiles!F7))/Depth_per_q) | G7: =IF(Quantiles!G7<0,"",(Depth0-MIN(Depth0,Quantiles!G7))/Depth_per_q) -> 6.7979957 | H7: =IF(Quantiles!H7<0,"",(Depth0-MIN(Depth0,Quantiles!H7))/Depth_per_q) -> 6.5342528 | I7: =IF(Quantiles!I7<0,"",(Depth0-MIN(Depth0,Quantiles!I7))/Depth_per_q) -> 6.286661 | ... CT7: =IF(Quantiles!CT7<0,"",(Depth0-MIN(Depth0,Quantiles!CT7))/Depth_per_q) -> 6.0429595
A8: =Quantiles!A8 -> 15 | B8: =IF(Quantiles!B8<0,"",(Depth0-MIN(Depth0,Quantiles!B8))/Depth_per_q) | C8: =IF(Quantiles!C8<0,"",(Depth0-MIN(Depth0,Quantiles!C8))/Depth_per_q) | D8: =IF(Quantiles!D8<0,"",(Depth0-MIN(Depth0,Quantiles!D8))/Depth_per_q) | E8: =IF(Quantiles!E8<0,"",(Depth0-MIN(Depth0,Quantiles!E8))/Depth_per_q) | F8: =IF(Quantiles!F8<0,"",(Depth0-MIN(Depth0,Quantiles!F8))/Depth_per_q) -> 6.8005489 | G8: =IF(Quantiles!G8<0,"",(Depth0-MIN(Depth0,Quantiles!G8))/Depth_per_q) -> 6.4923365 | H8: =IF(Quantiles!H8<0,"",(Depth0-MIN(Depth0,Quantiles!H8))/Depth_per_q) -> 6.2369875 | I8: =IF(Quantiles!I8<0,"",(Depth0-MIN(Depth0,Quantiles!I8))/Depth_per_q) -> 5.975814 | ... CT8: =IF(Quantiles!CT8<0,"",(Depth0-MIN(Depth0,Quantiles!CT8))/Depth_per_q) -> 5.7489205
A9: =Quantiles!A9 -> 20 | B9: =IF(Quantiles!B9<0,"",(Depth0-MIN(Depth0,Quantiles!B9))/Depth_per_q) | C9: =IF(Quantiles!C9<0,"",(Depth0-MIN(Depth0,Quantiles!C9))/Depth_per_q) | D9: =IF(Quantiles!D9<0,"",(Depth0-MIN(Depth0,Quantiles!D9))/Depth_per_q) | E9: =IF(Quantiles!E9<0,"",(Depth0-MIN(Depth0,Quantiles!E9))/Depth_per_q) -> 6.8208423 | F9: =IF(Quantiles!F9<0,"",(Depth0-MIN(Depth0,Quantiles!F9))/Depth_per_q) -> 6.5060009 | G9: =IF(Quantiles!G9<0,"",(Depth0-MIN(Depth0,Quantiles!G9))/Depth_per_q) -> 6.2096114 | H9: =IF(Quantiles!H9<0,"",(Depth0-MIN(Depth0,Quantiles!H9))/Depth_per_q) -> 5.9285912 | I9: =IF(Quantiles!I9<0,"",(Depth0-MIN(Depth0,Quantiles!I9))/Depth_per_q) -> 5.6869282 | ... CT9: =IF(Quantiles!CT9<0,"",(Depth0-MIN(Depth0,Quantiles!CT9))/Depth_per_q) -> 5.472091
A10: =Quantiles!A10 -> 25 | B10: =IF(Quantiles!B10<0,"",(Depth0-MIN(Depth0,Quantiles!B10))/Depth_per_q) | C10: =IF(Quantiles!C10<0,"",(Depth0-MIN(Depth0,Quantiles!C10))/Depth_per_q) | D10: =IF(Quantiles!D10<0,"",(Depth0-MIN(Depth0,Quantiles!D10))/Depth_per_q) -> 6.8719749 | E10: =IF(Quantiles!E10<0,"",(Depth0-MIN(Depth0,Quantiles!E10))/Depth_per_q) -> 6.4899051 | F10: =IF(Quantiles!F10<0,"",(Depth0-MIN(Depth0,Quantiles!F10))/Depth_per_q) -> 6.2147696 | G10: =IF(Quantiles!G10<0,"",(Depth0-MIN(Depth0,Quantiles!G10))/Depth_per_q) -> 5.9307943 | H10: =IF(Quantiles!H10<0,"",(Depth0-MIN(Depth0,Quantiles!H10))/Depth_per_q) -> 5.6452997 | I10: =IF(Quantiles!I10<0,"",(Depth0-MIN(Depth0,Quantiles!I10))/Depth_per_q) -> 5.3965635 | ... CT10: =IF(Quantiles!CT10<0,"",(Depth0-MIN(Depth0,Quantiles!CT10))/Depth_per_q) -> 5.179831
A11: =Quantiles!A11 -> 30 | B11: =IF(Quantiles!B11<0,"",(Depth0-MIN(Depth0,Quantiles!B11))/Depth_per_q) | C11: =IF(Quantiles!C11<0,"",(Depth0-MIN(Depth0,Quantiles!C11))/Depth_per_q) -> 6.9962596 | D11: =IF(Quantiles!D11<0,"",(Depth0-MIN(Depth0,Quantiles!D11))/Depth_per_q) -> 6.5446432 | E11: =IF(Quantiles!E11<0,"",(Depth0-MIN(Depth0,Quantiles!E11))/Depth_per_q) -> 6.1760936 | F11: =IF(Quantiles!F11<0,"",(Depth0-MIN(Depth0,Quantiles!F11))/Depth_per_q) -> 5.9042973 | G11: =IF(Quantiles!G11<0,"",(Depth0-MIN(Depth0,Quantiles!G11))/Depth_per_q) -> 5.6355195 | H11: =IF(Quantiles!H11<0,"",(Depth0-MIN(Depth0,Quantiles!H11))/Depth_per_q) -> 5.3629304 | I11: =IF(Quantiles!I11<0,"",(Depth0-MIN(Depth0,Quantiles!I11))/Depth_per_q) -> 5.1144559 | ... CT11: =IF(Quantiles!CT11<0,"",(Depth0-MIN(Depth0,Quantiles!CT11))/Depth_per_q) -> 4.9057801
A12: =Quantiles!A12 -> 35 | B12: =IF(Quantiles!B12<0,"",(Depth0-MIN(Depth0,Quantiles!B12))/Depth_per_q) | C12: =IF(Quantiles!C12<0,"",(Depth0-MIN(Depth0,Quantiles!C12))/Depth_per_q) -> 6.6535423 | D12: =IF(Quantiles!D12<0,"",(Depth0-MIN(Depth0,Quantiles!D12))/Depth_per_q) -> 6.2205636 | E12: =IF(Quantiles!E12<0,"",(Depth0-MIN(Depth0,Quantiles!E12))/Depth_per_q) -> 5.8683822 | F12: =IF(Quantiles!F12<0,"",(Depth0-MIN(Depth0,Quantiles!F12))/Depth_per_q) -> 5.5993384 | G12: =IF(Quantiles!G12<0,"",(Depth0-MIN(Depth0,Quantiles!G12))/Depth_per_q) -> 5.3505782 | H12: =IF(Quantiles!H12<0,"",(Depth0-MIN(Depth0,Quantiles!H12))/Depth_per_q) -> 5.0836449 | I12: =IF(Quantiles!I12<0,"",(Depth0-MIN(Depth0,Quantiles!I12))/Depth_per_q) -> 4.8481798 | ... CT12: =IF(Quantiles!CT12<0,"",(Depth0-MIN(Depth0,Quantiles!CT12))/Depth_per_q) -> 4.6114286
A13: =Quantiles!A13 -> 40 | B13: =IF(Quantiles!B13<0,"",(Depth0-MIN(Depth0,Quantiles!B13))/Depth_per_q) -> 6.7884894 | C13: =IF(Quantiles!C13<0,"",(Depth0-MIN(Depth0,Quantiles!C13))/Depth_per_q) -> 6.3153351 | D13: =IF(Quantiles!D13<0,"",(Depth0-MIN(Depth0,Quantiles!D13))/Depth_per_q) -> 5.911123 | E13: =IF(Quantiles!E13<0,"",(Depth0-MIN(Depth0,Quantiles!E13))/Depth_per_q) -> 5.5984863 | F13: =IF(Quantiles!F13<0,"",(Depth0-MIN(Depth0,Quantiles!F13))/Depth_per_q) -> 5.3097982 | G13: =IF(Quantiles!G13<0,"",(Depth0-MIN(Depth0,Quantiles!G13))/Depth_per_q) -> 5.0554221 | H13: =IF(Quantiles!H13<0,"",(Depth0-MIN(Depth0,Quantiles!H13))/Depth_per_q) -> 4.7987509 | I13: =IF(Quantiles!I13<0,"",(Depth0-MIN(Depth0,Quantiles!I13))/Depth_per_q) -> 4.5798287 | ... CT13: =IF(Quantiles!CT13<0,"",(Depth0-MIN(Depth0,Quantiles!CT13))/Depth_per_q) -> 4.3448112
A14: =Quantiles!A14 -> 45 | B14: =IF(Quantiles!B14<0,"",(Depth0-MIN(Depth0,Quantiles!B14))/Depth_per_q) -> 6.511652 | C14: =IF(Quantiles!C14<0,"",(Depth0-MIN(Depth0,Quantiles!C14))/Depth_per_q) -> 6.022568 | D14: =IF(Quantiles!D14<0,"",(Depth0-MIN(Depth0,Quantiles!D14))/Depth_per_q) -> 5.6117499 | E14: =IF(Quantiles!E14<0,"",(Depth0-MIN(Depth0,Quantiles!E14))/Depth_per_q) -> 5.2988172 | F14: =IF(Quantiles!F14<0,"",(Depth0-MIN(Depth0,Quantiles!F14))/Depth_per_q) -> 5.0317042 | G14: =IF(Quantiles!G14<0,"",(Depth0-MIN(Depth0,Quantiles!G14))/Depth_per_q) -> 4.7565954 | H14: =IF(Quantiles!H14<0,"",(Depth0-MIN(Depth0,Quantiles!H14))/Depth_per_q) -> 4.5224017 | I14: =IF(Quantiles!I14<0,"",(Depth0-MIN(Depth0,Quantiles!I14))/Depth_per_q) -> 4.3119783 | ... CT14: =IF(Quantiles!CT14<0,"",(Depth0-MIN(Depth0,Quantiles!CT14))/Depth_per_q) -> 4.0936604
A15: =Quantiles!A15 -> 50 | B15: =IF(Quantiles!B15<0,"",(Depth0-MIN(Depth0,Quantiles!B15))/Depth_per_q) -> 6.2044698 | C15: =IF(Quantiles!C15<0,"",(Depth0-MIN(Depth0,Quantiles!C15))/Depth_per_q) -> 5.7164686 | D15: =IF(Quantiles!D15<0,"",(Depth0-MIN(Depth0,Quantiles!D15))/Depth_per_q) -> 5.3251062 | E15: =IF(Quantiles!E15<0,"",(Depth0-MIN(Depth0,Quantiles!E15))/Depth_per_q) -> 5.026474 | F15: =IF(Quantiles!F15<0,"",(Depth0-MIN(Depth0,Quantiles!F15))/Depth_per_q) -> 4.7349848 | G15: =IF(Quantiles!G15<0,"",(Depth0-MIN(Depth0,Quantiles!G15))/Depth_per_q) -> 4.4846926 | H15: =IF(Quantiles!H15<0,"",(Depth0-MIN(Depth0,Quantiles!H15))/Depth_per_q) -> 4.2517959 | I15: =IF(Quantiles!I15<0,"",(Depth0-MIN(Depth0,Quantiles!I15))/Depth_per_q) -> 4.0382982 | ... CT15: =IF(Quantiles!CT15<0,"",(Depth0-MIN(Depth0,Quantiles!CT15))/Depth_per_q) -> 3.8336516
A16: =Quantiles!A16 -> 55 | B16: =IF(Quantiles!B16<0,"",(Depth0-MIN(Depth0,Quantiles!B16))/Depth_per_q) -> 5.8932853 | C16: =IF(Quantiles!C16<0,"",(Depth0-MIN(Depth0,Quantiles!C16))/Depth_per_q) -> 5.4217813 | D16: =IF(Quantiles!D16<0,"",(Depth0-MIN(Depth0,Quantiles!D16))/Depth_per_q) -> 5.0435959 | E16: =IF(Quantiles!E16<0,"",(Depth0-MIN(Depth0,Quantiles!E16))/Depth_per_q) -> 4.7418537 | F16: =IF(Quantiles!F16<0,"",(Depth0-MIN(Depth0,Quantiles!F16))/Depth_per_q) -> 4.4617978 | G16: =IF(Quantiles!G16<0,"",(Depth0-MIN(Depth0,Quantiles!G16))/Depth_per_q) -> 4.2128024 | H16: =IF(Quantiles!H16<0,"",(Depth0-MIN(Depth0,Quantiles!H16))/Depth_per_q) -> 3.9950578 | I16: =IF(Quantiles!I16<0,"",(Depth0-MIN(Depth0,Quantiles!I16))/Depth_per_q) -> 3.7910761 | ... CT16: =IF(Quantiles!CT16<0,"",(Depth0-MIN(Depth0,Quantiles!CT16))/Depth_per_q) -> 3.5876753
... A85: =Quantiles!A85 -> 400 | B85: =IF(Quantiles!B85<0,"",(Depth0-MIN(Depth0,Quantiles!B85))/Depth_per_q) -> 2.0430981 | C85: =IF(Quantiles!C85<0,"",(Depth0-MIN(Depth0,Quantiles!C85))/Depth_per_q) -> 1.8563889 | D85: =IF(Quantiles!D85<0,"",(Depth0-MIN(Depth0,Quantiles!D85))/Depth_per_q) -> 1.6924166 | E85: =IF(Quantiles!E85<0,"",(Depth0-MIN(Depth0,Quantiles!E85))/Depth_per_q) -> 1.5554648 | F85: =IF(Quantiles!F85<0,"",(Depth0-MIN(Depth0,Quantiles!F85))/Depth_per_q) -> 1.435918 | G85: =IF(Quantiles!G85<0,"",(Depth0-MIN(Depth0,Quantiles!G85))/Depth_per_q) -> 1.3289179 | H85: =IF(Quantiles!H85<0,"",(Depth0-MIN(Depth0,Quantiles!H85))/Depth_per_q) -> 1.2357476 | I85: =IF(Quantiles!I85<0,"",(Depth0-MIN(Depth0,Quantiles!I85))/Depth_per_q) -> 1.1451212 | ... CT85: =IF(Quantiles!CT85<0,"",(Depth0-MIN(Depth0,Quantiles!CT85))/Depth_per_q) -> 1.0668877

Sheet Cost
A1: The cost of that package: Fee x line + Vq x delay ($ million)
A2: Fees of 3 percent of the line over the program; $8 million a quarter of delay (Worked Example 15.1).
A4: Line ($ million) | B4: =Quantiles!B4 -> 0.01 | C4: =Quantiles!C4 -> 0.0125 | D4: =Quantiles!D4 -> 0.015 | E4: =Quantiles!E4 -> 0.0175 | F4: =Quantiles!F4 -> 0.02 | G4: =Quantiles!G4 -> 0.0225 | H4: =Quantiles!H4 -> 0.025 | I4: =Quantiles!I4 -> 0.0275 | ... CT4: =Quantiles!CT4 -> 0.03003
A5: =Quantiles!A5 -> 0 | B5: =IF(Delay!B5="","",Fee*$A5+Vq*Delay!B5) | C5: =IF(Delay!C5="","",Fee*$A5+Vq*Delay!C5) | D5: =IF(Delay!D5="","",Fee*$A5+Vq*Delay!D5) | E5: =IF(Delay!E5="","",Fee*$A5+Vq*Delay!E5) | F5: =IF(Delay!F5="","",Fee*$A5+Vq*Delay!F5) | G5: =IF(Delay!G5="","",Fee*$A5+Vq*Delay!G5) | H5: =IF(Delay!H5="","",Fee*$A5+Vq*Delay!H5) | I5: =IF(Delay!I5="","",Fee*$A5+Vq*Delay!I5) -> 55.180381 | ... CT5: =IF(Delay!CT5="","",Fee*$A5+Vq*Delay!CT5) -> 52.905115
A6: =Quantiles!A6 -> 5 | B6: =IF(Delay!B6="","",Fee*$A6+Vq*Delay!B6) | C6: =IF(Delay!C6="","",Fee*$A6+Vq*Delay!C6) | D6: =IF(Delay!D6="","",Fee*$A6+Vq*Delay!D6) | E6: =IF(Delay!E6="","",Fee*$A6+Vq*Delay!E6) | F6: =IF(Delay!F6="","",Fee*$A6+Vq*Delay!F6) | G6: =IF(Delay!G6="","",Fee*$A6+Vq*Delay!G6) | H6: =IF(Delay!H6="","",Fee*$A6+Vq*Delay!H6) -> 54.885033 | I6: =IF(Delay!I6="","",Fee*$A6+Vq*Delay!I6) -> 52.806794 | ... CT6: =IF(Delay!CT6="","",Fee*$A6+Vq*Delay!CT6) -> 50.762779
A7: =Quantiles!A7 -> 10 | B7: =IF(Delay!B7="","",Fee*$A7+Vq*Delay!B7) | C7: =IF(Delay!C7="","",Fee*$A7+Vq*Delay!C7) | D7: =IF(Delay!D7="","",Fee*$A7+Vq*Delay!D7) | E7: =IF(Delay!E7="","",Fee*$A7+Vq*Delay!E7) | F7: =IF(Delay!F7="","",Fee*$A7+Vq*Delay!F7) | G7: =IF(Delay!G7="","",Fee*$A7+Vq*Delay!G7) -> 54.683966 | H7: =IF(Delay!H7="","",Fee*$A7+Vq*Delay!H7) -> 52.574022 | I7: =IF(Delay!I7="","",Fee*$A7+Vq*Delay!I7) -> 50.593288 | ... CT7: =IF(Delay!CT7="","",Fee*$A7+Vq*Delay!CT7) -> 48.643676
A8: =Quantiles!A8 -> 15 | B8: =IF(Delay!B8="","",Fee*$A8+Vq*Delay!B8) | C8: =IF(Delay!C8="","",Fee*$A8+Vq*Delay!C8) | D8: =IF(Delay!D8="","",Fee*$A8+Vq*Delay!D8) | E8: =IF(Delay!E8="","",Fee*$A8+Vq*Delay!E8) | F8: =IF(Delay!F8="","",Fee*$A8+Vq*Delay!F8) -> 54.854391 | G8: =IF(Delay!G8="","",Fee*$A8+Vq*Delay!G8) -> 52.388692 | H8: =IF(Delay!H8="","",Fee*$A8+Vq*Delay!H8) -> 50.3459 | I8: =IF(Delay!I8="","",Fee*$A8+Vq*Delay!I8) -> 48.256512 | ... CT8: =IF(Delay!CT8="","",Fee*$A8+Vq*Delay!CT8) -> 46.441364
A9: =Quantiles!A9 -> 20 | B9: =IF(Delay!B9="","",Fee*$A9+Vq*Delay!B9) | C9: =IF(Delay!C9="","",Fee*$A9+Vq*Delay!C9) | D9: =IF(Delay!D9="","",Fee*$A9+Vq*Delay!D9) | E9: =IF(Delay!E9="","",Fee*$A9+Vq*Delay!E9) -> 55.166738 | F9: =IF(Delay!F9="","",Fee*$A9+Vq*Delay!F9) -> 52.648007 | G9: =IF(Delay!G9="","",Fee*$A9+Vq*Delay!G9) -> 50.276891 | H9: =IF(Delay!H9="","",Fee*$A9+Vq*Delay!H9) -> 48.02873 | I9: =IF(Delay!I9="","",Fee*$A9+Vq*Delay!I9) -> 46.095425 | ... CT9: =IF(Delay!CT9="","",Fee*$A9+Vq*Delay!CT9) -> 44.376728
A10: =Quantiles!A10 -> 25 | B10: =IF(Delay!B10="","",Fee*$A10+Vq*Delay!B10) | C10: =IF(Delay!C10="","",Fee*$A10+Vq*Delay!C10) | D10: =IF(Delay!D10="","",Fee*$A10+Vq*Delay!D10) -> 55.725799 | E10: =IF(Delay!E10="","",Fee*$A10+Vq*Delay!E10) -> 52.669241 | F10: =IF(Delay!F10="","",Fee*$A10+Vq*Delay!F10) -> 50.468157 | G10: =IF(Delay!G10="","",Fee*$A10+Vq*Delay!G10) -> 48.196354 | H10: =IF(Delay!H10="","",Fee*$A10+Vq*Delay!H10) -> 45.912397 | I10: =IF(Delay!I10="","",Fee*$A10+Vq*Delay!I10) -> 43.922508 | ... CT10: =IF(Delay!CT10="","",Fee*$A10+Vq*Delay!CT10) -> 42.188648
A11: =Quantiles!A11 -> 30 | B11: =IF(Delay!B11="","",Fee*$A11+Vq*Delay!B11) | C11: =IF(Delay!C11="","",Fee*$A11+Vq*Delay!C11) -> 56.870077 | D11: =IF(Delay!D11="","",Fee*$A11+Vq*Delay!D11) -> 53.257146 | E11: =IF(Delay!E11="","",Fee*$A11+Vq*Delay!E11) -> 50.308749 | F11: =IF(Delay!F11="","",Fee*$A11+Vq*Delay!F11) -> 48.134378 | G11: =IF(Delay!G11="","",Fee*$A11+Vq*Delay!G11) -> 45.984156 | H11: =IF(Delay!H11="","",Fee*$A11+Vq*Delay!H11) -> 43.803443 | I11: =IF(Delay!I11="","",Fee*$A11+Vq*Delay!I11) -> 41.815647 | ... CT11: =IF(Delay!CT11="","",Fee*$A11+Vq*Delay!CT11) -> 40.146241
A12: =Quantiles!A12 -> 35 | B12: =IF(Delay!B12="","",Fee*$A12+Vq*Delay!B12) | C12: =IF(Delay!C12="","",Fee*$A12+Vq*Delay!C12) -> 54.278338 | D12: =IF(Delay!D12="","",Fee*$A12+Vq*Delay!D12) -> 50.814509 | E12: =IF(Delay!E12="","",Fee*$A12+Vq*Delay!E12) -> 47.997057 | F12: =IF(Delay!F12="","",Fee*$A12+Vq*Delay!F12) -> 45.844707 | G12: =IF(Delay!G12="","",Fee*$A12+Vq*Delay!G12) -> 43.854626 | H12: =IF(Delay!H12="","",Fee*$A12+Vq*Delay!H12) -> 41.719159 | I12: =IF(Delay!I12="","",Fee*$A12+Vq*Delay!I12) -> 39.835439 | ... CT12: =IF(Delay!CT12="","",Fee*$A12+Vq*Delay!CT12) -> 37.941429
A13: =Quantiles!A13 -> 40 | B13: =IF(Delay!B13="","",Fee*$A13+Vq*Delay!B13) -> 55.507915 | C13: =IF(Delay!C13="","",Fee*$A13+Vq*Delay!C13) -> 51.722681 | D13: =IF(Delay!D13="","",Fee*$A13+Vq*Delay!D13) -> 48.488984 | E13: =IF(Delay!E13="","",Fee*$A13+Vq*Delay!E13) -> 45.987891 | F13: =IF(Delay!F13="","",Fee*$A13+Vq*Delay!F13) -> 43.678386 | G13: =IF(Delay!G13="","",Fee*$A13+Vq*Delay!G13) -> 41.643377 | H13: =IF(Delay!H13="","",Fee*$A13+Vq*Delay!H13) -> 39.590007 | I13: =IF(Delay!I13="","",Fee*$A13+Vq*Delay!I13) -> 37.83863 | ... CT13: =IF(Delay!CT13="","",Fee*$A13+Vq*Delay!CT13) -> 35.958489
A14: =Quantiles!A14 -> 45 | B14: =IF(Delay!B14="","",Fee*$A14+Vq*Delay!B14) -> 53.443216 | C14: =IF(Delay!C14="","",Fee*$A14+Vq*Delay!C14) -> 49.530544 | D14: =IF(Delay!D14="","",Fee*$A14+Vq*Delay!D14) -> 46.243999 | E14: =IF(Delay!E14="","",Fee*$A14+Vq*Delay!E14) -> 43.740537 | F14: =IF(Delay!F14="","",Fee*$A14+Vq*Delay!F14) -> 41.603634 | G14: =IF(Delay!G14="","",Fee*$A14+Vq*Delay!G14) -> 39.402763 | H14: =IF(Delay!H14="","",Fee*$A14+Vq*Delay!H14) -> 37.529214 | I14: =IF(Delay!I14="","",Fee*$A14+Vq*Delay!I14) -> 35.845826 | ... CT14: =IF(Delay!CT14="","",Fee*$A14+Vq*Delay!CT14) -> 34.099283
A15: =Quantiles!A15 -> 50 | B15: =IF(Delay!B15="","",Fee*$A15+Vq*Delay!B15) -> 51.135759 | C15: =IF(Delay!C15="","",Fee*$A15+Vq*Delay!C15) -> 47.231749 | D15: =IF(Delay!D15="","",Fee*$A15+Vq*Delay!D15) -> 44.10085 | E15: =IF(Delay!E15="","",Fee*$A15+Vq*Delay!E15) -> 41.711792 | F15: =IF(Delay!F15="","",Fee*$A15+Vq*Delay!F15) -> 39.379878 | G15: =IF(Delay!G15="","",Fee*$A15+Vq*Delay!G15) -> 37.377541 | H15: =IF(Delay!H15="","",Fee*$A15+Vq*Delay!H15) -> 35.514367 | I15: =IF(Delay!I15="","",Fee*$A15+Vq*Delay!I15) -> 33.806386 | ... CT15: =IF(Delay!CT15="","",Fee*$A15+Vq*Delay!CT15) -> 32.169213
A16: =Quantiles!A16 -> 55 | B16: =IF(Delay!B16="","",Fee*$A16+Vq*Delay!B16) -> 48.796282 | C16: =IF(Delay!C16="","",Fee*$A16+Vq*Delay!C16) -> 45.02425 | D16: =IF(Delay!D16="","",Fee*$A16+Vq*Delay!D16) -> 41.998767 | E16: =IF(Delay!E16="","",Fee*$A16+Vq*Delay!E16) -> 39.58483 | F16: =IF(Delay!F16="","",Fee*$A16+Vq*Delay!F16) -> 37.344382 | G16: =IF(Delay!G16="","",Fee*$A16+Vq*Delay!G16) -> 35.352419 | H16: =IF(Delay!H16="","",Fee*$A16+Vq*Delay!H16) -> 33.610462 | I16: =IF(Delay!I16="","",Fee*$A16+Vq*Delay!I16) -> 31.978609 | ... CT16: =IF(Delay!CT16="","",Fee*$A16+Vq*Delay!CT16) -> 30.351402
... A85: =Quantiles!A85 -> 400 | B85: =IF(Delay!B85="","",Fee*$A85+Vq*Delay!B85) -> 28.344784 | C85: =IF(Delay!C85="","",Fee*$A85+Vq*Delay!C85) -> 26.851111 | D85: =IF(Delay!D85="","",Fee*$A85+Vq*Delay!D85) -> 25.539333 | E85: =IF(Delay!E85="","",Fee*$A85+Vq*Delay!E85) -> 24.443719 | F85: =IF(Delay!F85="","",Fee*$A85+Vq*Delay!F85) -> 23.487344 | G85: =IF(Delay!G85="","",Fee*$A85+Vq*Delay!G85) -> 22.631343 | H85: =IF(Delay!H85="","",Fee*$A85+Vq*Delay!H85) -> 21.885981 | I85: =IF(Delay!I85="","",Fee*$A85+Vq*Delay!I85) -> 21.16097 | ... CT85: =IF(Delay!CT85="","",Fee*$A85+Vq*Delay!CT85) -> 20.535101

Sheet Frontier
A1: The frontier by floors: the least cost of every appetite (Theorem 15.5(iii); Figure 15.2, right; Worked Example 15.1, Step 5; AXIOM Lab 1.15, step 4)
A2: Each row minimizes the levers' cost subject to one appetite (a floor on safety): the column of the Cost sheet, its least value, its line and its delay. Phasing alone is the line-0 row.
A4: Appetite | B4: Least cost | C4: Its line | D4: Its delay | E4: Phasing alone: delay | F4: Phasing alone: cost | H4: Step 5 and Table 15.5 | I4: Value | J4: Reading
A5: =INDEX(Quantiles!$B$4:$CT$4,1,1) -> 0.01 | B5: =MIN(INDEX(Cost!$B$5:$CT$85,0,1)) -> 23.089332 | C5: =INDEX(Cost!$A$5:$A$85,MATCH(B5,INDEX(Cost!$B$5:$CT$85,0,1),0)) -> 190 | D5: =INDEX(Delay!$B$5:$CT$85,MATCH(B5,INDEX(Cost!$B$5:$CT$85,0,1),0),1) -> 2.1736665 | E5: =INDEX(Delay!$B$5:$CT$85,1,1) | F5: =IF(E5="","",Vq*E5) | H5: Line alone at $400 million: odds (engine) | I5: 0.08404 | J5: no line, however large, brings the odds below 8.4 percent
A6: =INDEX(Quantiles!$B$4:$CT$4,1,2) -> 0.0125 | B6: =MIN(INDEX(Cost!$B$5:$CT$85,0,2)) -> 21.337606 | C6: =INDEX(Cost!$A$5:$A$85,MATCH(B6,INDEX(Cost!$B$5:$CT$85,0,2),0)) -> 185 | D6: =INDEX(Delay!$B$5:$CT$85,MATCH(B6,INDEX(Cost!$B$5:$CT$85,0,2),0),2) -> 1.9734507 | E6: =INDEX(Delay!$B$5:$CT$85,1,2) | F6: =IF(E6="","",Vq*E6) | H6: Phasing alone at 5%: delay (quarters) | I6: =E21 -> 5.0946732 | J6: 5.1 quarters
A7: =INDEX(Quantiles!$B$4:$CT$4,1,3) -> 0.015 | B7: =MIN(INDEX(Cost!$B$5:$CT$85,0,3)) -> 20.122368 | C7: =INDEX(Cost!$A$5:$A$85,MATCH(B7,INDEX(Cost!$B$5:$CT$85,0,3),0)) -> 175 | D7: =INDEX(Delay!$B$5:$CT$85,MATCH(B7,INDEX(Cost!$B$5:$CT$85,0,3),0),3) -> 1.859046 | E7: =INDEX(Delay!$B$5:$CT$85,1,3) | F7: =IF(E7="","",Vq*E7) | H7: Phasing alone at 5%: depth | I7: =Depth0-Depth_per_q*I6 -> 7.6213073 | J7: Online Appendix 15.B.4: 7.62
A8: =INDEX(Quantiles!$B$4:$CT$4,1,4) -> 0.0175 | B8: =MIN(INDEX(Cost!$B$5:$CT$85,0,4)) -> 18.880368 | C8: =INDEX(Cost!$A$5:$A$85,MATCH(B8,INDEX(Cost!$B$5:$CT$85,0,4),0)) -> 185 | D8: =INDEX(Delay!$B$5:$CT$85,MATCH(B8,INDEX(Cost!$B$5:$CT$85,0,4),0),4) -> 1.6662959 | E8: =INDEX(Delay!$B$5:$CT$85,1,4) | F8: =IF(E8="","",Vq*E8) | H8: Phasing alone at 5%: cost | I8: =F21 -> 40.757385 | J8: $40.8 million
A9: =INDEX(Quantiles!$B$4:$CT$4,1,5) -> 0.02 | B9: =MIN(INDEX(Cost!$B$5:$CT$85,0,5)) -> 17.860851 | C9: =INDEX(Cost!$A$5:$A$85,MATCH(B9,INDEX(Cost!$B$5:$CT$85,0,5),0)) -> 170 | D9: =INDEX(Delay!$B$5:$CT$85,MATCH(B9,INDEX(Cost!$B$5:$CT$85,0,5),0),5) -> 1.5951064 | E9: =INDEX(Delay!$B$5:$CT$85,1,5) | F9: =IF(E9="","",Vq*E9) | H9: Both levers at 5%: least cost | I9: =B21 -> 10.440611 | J9: $10.4 million
A10: =INDEX(Quantiles!$B$4:$CT$4,1,6) -> 0.0225 | B10: =MIN(INDEX(Cost!$B$5:$CT$85,0,6)) -> 16.870376 | C10: =INDEX(Cost!$A$5:$A$85,MATCH(B10,INDEX(Cost!$B$5:$CT$85,0,6),0)) -> 175 | D10: =INDEX(Delay!$B$5:$CT$85,MATCH(B10,INDEX(Cost!$B$5:$CT$85,0,6),0),6) -> 1.452547 | E10: =INDEX(Delay!$B$5:$CT$85,1,6) | F10: =IF(E10="","",Vq*E10) | H10: Value of coordination (Theorem 15.6(iii)) | I10: =I8-I9 -> 30.316774 | J10: $30 million
A11: =INDEX(Quantiles!$B$4:$CT$4,1,7) -> 0.025 | B11: =MIN(INDEX(Cost!$B$5:$CT$85,0,7)) -> 16.079718 | C11: =INDEX(Cost!$A$5:$A$85,MATCH(B11,INDEX(Cost!$B$5:$CT$85,0,7),0)) -> 175 | D11: =INDEX(Delay!$B$5:$CT$85,MATCH(B11,INDEX(Cost!$B$5:$CT$85,0,7),0),7) -> 1.3537147 | E11: =INDEX(Delay!$B$5:$CT$85,1,7) | F11: =IF(E11="","",Vq*E11)
A12: =INDEX(Quantiles!$B$4:$CT$4,1,8) -> 0.0275 | B12: =MIN(INDEX(Cost!$B$5:$CT$85,0,8)) -> 15.338772 | C12: =INDEX(Cost!$A$5:$A$85,MATCH(B12,INDEX(Cost!$B$5:$CT$85,0,8),0)) -> 170 | D12: =INDEX(Delay!$B$5:$CT$85,MATCH(B12,INDEX(Cost!$B$5:$CT$85,0,8),0),8) -> 1.2798464 | E12: =INDEX(Delay!$B$5:$CT$85,1,8) -> 6.8975476 | F12: =IF(E12="","",Vq*E12) -> 55.180381 | H12: Chapter 8's package: line | I12: 100 | J12: Worked Example 8.1
A13: =INDEX(Quantiles!$B$4:$CT$4,1,9) -> 0.03 | B13: =MIN(INDEX(Cost!$B$5:$CT$85,0,9)) -> 14.684124 | C13: =INDEX(Cost!$A$5:$A$85,MATCH(B13,INDEX(Cost!$B$5:$CT$85,0,9),0)) -> 180 | D13: =INDEX(Delay!$B$5:$CT$85,MATCH(B13,INDEX(Cost!$B$5:$CT$85,0,9),0),9) -> 1.1605155 | E13: =INDEX(Delay!$B$5:$CT$85,1,9) -> 6.6187059 | F13: =IF(E13="","",Vq*E13) -> 52.949647 | H13: Chapter 8's package: delay (quarters) | I13: 2 | J13: the phased build
A14: =INDEX(Quantiles!$B$4:$CT$4,1,10) -> 0.0325 | B14: =MIN(INDEX(Cost!$B$5:$CT$85,0,10)) -> 14.077963 | C14: =INDEX(Cost!$A$5:$A$85,MATCH(B14,INDEX(Cost!$B$5:$CT$85,0,10),0)) -> 170 | D14: =INDEX(Delay!$B$5:$CT$85,MATCH(B14,INDEX(Cost!$B$5:$CT$85,0,10),0),10) -> 1.1222454 | E14: =INDEX(Delay!$B$5:$CT$85,1,10) -> 6.3871892 | F14: =IF(E14="","",Vq*E14) -> 51.097513 | H14: Chapter 8's package: cost | I14: =Fee*I12+Vq*I13 -> 19 | J14: $19.0 million
A15: =INDEX(Quantiles!$B$4:$CT$4,1,11) -> 0.035 | B15: =MIN(INDEX(Cost!$B$5:$CT$85,0,11)) -> 13.476076 | C15: =INDEX(Cost!$A$5:$A$85,MATCH(B15,INDEX(Cost!$B$5:$CT$85,0,11),0)) -> 175 | D15: =INDEX(Delay!$B$5:$CT$85,MATCH(B15,INDEX(Cost!$B$5:$CT$85,0,11),0),11) -> 1.0282595 | E15: =INDEX(Delay!$B$5:$CT$85,1,11) -> 6.1465294 | F15: =IF(E15="","",Vq*E15) -> 49.172235 | H15: Chapter 8's package: odds (engine) | I15: 0.03003 | J15: 3.0 percent
A16: =INDEX(Quantiles!$B$4:$CT$4,1,12) -> 0.0375 | B16: =MIN(INDEX(Cost!$B$5:$CT$85,0,12)) -> 12.906277 | C16: =INDEX(Cost!$A$5:$A$85,MATCH(B16,INDEX(Cost!$B$5:$CT$85,0,12),0)) -> 175 | D16: =INDEX(Delay!$B$5:$CT$85,MATCH(B16,INDEX(Cost!$B$5:$CT$85,0,12),0),12) -> 0.95703458 | E16: =INDEX(Delay!$B$5:$CT$85,1,12) -> 5.9279666 | F16: =IF(E16="","",Vq*E16) -> 47.423733 | H16: The frontier at the same odds: cost | I16: =B101 -> 14.668098 | J16: $14.7 million
A17: =INDEX(Quantiles!$B$4:$CT$4,1,13) -> 0.04 | B17: =MIN(INDEX(Cost!$B$5:$CT$85,0,13)) -> 12.350458 | C17: =INDEX(Cost!$A$5:$A$85,MATCH(B17,INDEX(Cost!$B$5:$CT$85,0,13),0)) -> 165 | D17: =INDEX(Delay!$B$5:$CT$85,MATCH(B17,INDEX(Cost!$B$5:$CT$85,0,13),0),13) -> 0.9250572 | E17: =INDEX(Delay!$B$5:$CT$85,1,13) -> 5.7518968 | F17: =IF(E17="","",Vq*E17) -> 46.015174 | H17: Its line | I17: =C101 -> 180 | J17: 180
A18: =INDEX(Quantiles!$B$4:$CT$4,1,14) -> 0.0425 | B18: =MIN(INDEX(Cost!$B$5:$CT$85,0,14)) -> 11.864847 | C18: =INDEX(Cost!$A$5:$A$85,MATCH(B18,INDEX(Cost!$B$5:$CT$85,0,14),0)) -> 165 | D18: =INDEX(Delay!$B$5:$CT$85,MATCH(B18,INDEX(Cost!$B$5:$CT$85,0,14),0),14) -> 0.86435582 | E18: =INDEX(Delay!$B$5:$CT$85,1,14) -> 5.5648367 | F18: =IF(E18="","",Vq*E18) -> 44.518694 | H18: Its delay | I18: =D101 -> 1.1585123 | J18: 1.16
A19: =INDEX(Quantiles!$B$4:$CT$4,1,15) -> 0.045 | B19: =MIN(INDEX(Cost!$B$5:$CT$85,0,15)) -> 11.388504 | C19: =INDEX(Cost!$A$5:$A$85,MATCH(B19,INDEX(Cost!$B$5:$CT$85,0,15),0)) -> 165 | D19: =INDEX(Delay!$B$5:$CT$85,MATCH(B19,INDEX(Cost!$B$5:$CT$85,0,15),0),15) -> 0.80481304 | E19: =INDEX(Delay!$B$5:$CT$85,1,15) -> 5.4036971 | F19: =IF(E19="","",Vq*E19) -> 43.229577 | H19: Inefficiency of the package at its odds | I19: =I14-I16 -> 4.3319019 | J19: Theorem 15.5(v)
A20: =INDEX(Quantiles!$B$4:$CT$4,1,16) -> 0.0475 | B20: =MIN(INDEX(Cost!$B$5:$CT$85,0,16)) -> 10.876109 | C20: =INDEX(Cost!$A$5:$A$85,MATCH(B20,INDEX(Cost!$B$5:$CT$85,0,16),0)) -> 165 | D20: =INDEX(Delay!$B$5:$CT$85,MATCH(B20,INDEX(Cost!$B$5:$CT$85,0,16),0),16) -> 0.74076357 | E20: =INDEX(Delay!$B$5:$CT$85,1,16) -> 5.2567524 | F20: =IF(E20="","",Vq*E20) -> 42.054019 | H20: The frontier at 1.75%: cost | I20: =B8 -> 18.880368 | J20: about the package's $19.0 million
A21: =INDEX(Quantiles!$B$4:$CT$4,1,17) -> 0.05 | B21: =MIN(INDEX(Cost!$B$5:$CT$85,0,17)) -> 10.440611 | C21: =INDEX(Cost!$A$5:$A$85,MATCH(B21,INDEX(Cost!$B$5:$CT$85,0,17),0)) -> 170 | D21: =INDEX(Delay!$B$5:$CT$85,MATCH(B21,INDEX(Cost!$B$5:$CT$85,0,17),0),17) -> 0.66757636 | E21: =INDEX(Delay!$B$5:$CT$85,1,17) -> 5.0946732 | F21: =IF(E21="","",Vq*E21) -> 40.757385
A22: =INDEX(Quantiles!$B$4:$CT$4,1,18) -> 0.0525 | B22: =MIN(INDEX(Cost!$B$5:$CT$85,0,18)) -> 10.001225 | C22: =INDEX(Cost!$A$5:$A$85,MATCH(B22,INDEX(Cost!$B$5:$CT$85,0,18),0)) -> 165 | D22: =INDEX(Delay!$B$5:$CT$85,MATCH(B22,INDEX(Cost!$B$5:$CT$85,0,18),0),18) -> 0.63140311 | E22: =INDEX(Delay!$B$5:$CT$85,1,18) -> 4.94185 | F22: =IF(E22="","",Vq*E22) -> 39.5348 | H22: The bank's cap on the line ($ million) | I22: 100 | J22: For discussion
A23: =INDEX(Quantiles!$B$4:$CT$4,1,19) -> 0.055 | B23: =MIN(INDEX(Cost!$B$5:$CT$85,0,19)) -> 9.5814895 | C23: =INDEX(Cost!$A$5:$A$85,MATCH(B23,INDEX(Cost!$B$5:$CT$85,0,19),0)) -> 165 | D23: =INDEX(Delay!$B$5:$CT$85,MATCH(B23,INDEX(Cost!$B$5:$CT$85,0,19),0),19) -> 0.57893619 | E23: =INDEX(Delay!$B$5:$CT$85,1,19) -> 4.7977301 | F23: =IF(E23="","",Vq*E23) -> 38.381841 | H23: Least cost at 5% with the line capped | I23: =_xlfn.MINIFS(Cost!$R$5:$R$85,Cost!$A$5:$A$85,"<="&I22) -> 13.296891 | J23: Online Appendix 15.B.4: 13.30
A24: =INDEX(Quantiles!$B$4:$CT$4,1,20) -> 0.0575 | B24: =MIN(INDEX(Cost!$B$5:$CT$85,0,20)) -> 9.1762253 | C24: =INDEX(Cost!$A$5:$A$85,MATCH(B24,INDEX(Cost!$B$5:$CT$85,0,20),0)) -> 165 | D24: =INDEX(Delay!$B$5:$CT$85,MATCH(B24,INDEX(Cost!$B$5:$CT$85,0,20),0),20) -> 0.52827816 | E24: =INDEX(Delay!$B$5:$CT$85,1,20) -> 4.6642486 | F24: =IF(E24="","",Vq*E24) -> 37.313989 | H24: Its delay | I24: =INDEX(Delay!$R$5:$R$85,MATCH(I23,Cost!$R$5:$R$85,0)) -> 1.2871114 | J24: 1.29
A25: =INDEX(Quantiles!$B$4:$CT$4,1,21) -> 0.06 | B25: =MIN(INDEX(Cost!$B$5:$CT$85,0,21)) -> 8.8194117 | C25: =INDEX(Cost!$A$5:$A$85,MATCH(B25,INDEX(Cost!$B$5:$CT$85,0,21),0)) -> 160 | D25: =INDEX(Delay!$B$5:$CT$85,MATCH(B25,INDEX(Cost!$B$5:$CT$85,0,21),0),21) -> 0.50242646 | E25: =INDEX(Delay!$B$5:$CT$85,1,21) -> 4.5214924 | F25: =IF(E25="","",Vq*E25) -> 36.171939 | H25: The cap raises the cheapest cost by | I25: =I23-B21 -> 2.8562802 | J25: $2.9 million
A26: =INDEX(Quantiles!$B$4:$CT$4,1,22) -> 0.0625 | B26: =MIN(INDEX(Cost!$B$5:$CT$85,0,22)) -> 8.4825738 | C26: =INDEX(Cost!$A$5:$A$85,MATCH(B26,INDEX(Cost!$B$5:$CT$85,0,22),0)) -> 160 | D26: =INDEX(Delay!$B$5:$CT$85,MATCH(B26,INDEX(Cost!$B$5:$CT$85,0,22),0),22) -> 0.46032172 | E26: =INDEX(Delay!$B$5:$CT$85,1,22) -> 4.4025059 | F26: =IF(E26="","",Vq*E26) -> 35.220047
A27: =INDEX(Quantiles!$B$4:$CT$4,1,23) -> 0.065 | B27: =MIN(INDEX(Cost!$B$5:$CT$85,0,23)) -> 8.1348391 | C27: =INDEX(Cost!$A$5:$A$85,MATCH(B27,INDEX(Cost!$B$5:$CT$85,0,23),0)) -> 165 | D27: =INDEX(Delay!$B$5:$CT$85,MATCH(B27,INDEX(Cost!$B$5:$CT$85,0,23),0),23) -> 0.39810488 | E27: =INDEX(Delay!$B$5:$CT$85,1,23) -> 4.2864193 | F27: =IF(E27="","",Vq*E27) -> 34.291354
A28: =INDEX(Quantiles!$B$4:$CT$4,1,24) -> 0.0675 | B28: =MIN(INDEX(Cost!$B$5:$CT$85,0,24)) -> 7.7947233 | C28: =INDEX(Cost!$A$5:$A$85,MATCH(B28,INDEX(Cost!$B$5:$CT$85,0,24),0)) -> 160 | D28: =INDEX(Delay!$B$5:$CT$85,MATCH(B28,INDEX(Cost!$B$5:$CT$85,0,24),0),24) -> 0.37434041 | E28: =INDEX(Delay!$B$5:$CT$85,1,24) -> 4.1719112 | F28: =IF(E28="","",Vq*E28) -> 33.37529 | H28: Table 15.5: package | I28: Line | J28: Delay | K28: Cost | L28: Odds
A29: =INDEX(Quantiles!$B$4:$CT$4,1,25) -> 0.07 | B29: =MIN(INDEX(Cost!$B$5:$CT$85,0,25)) -> 7.4625656 | C29: =INDEX(Cost!$A$5:$A$85,MATCH(B29,INDEX(Cost!$B$5:$CT$85,0,25),0)) -> 160 | D29: =INDEX(Delay!$B$5:$CT$85,MATCH(B29,INDEX(Cost!$B$5:$CT$85,0,25),0),25) -> 0.3328207 | E29: =INDEX(Delay!$B$5:$CT$85,1,25) -> 4.0531505 | F29: =IF(E29="","",Vq*E29) -> 32.425204 | H29: Average path (certainty equivalent) | I29: =0 -> 0 | J29: =0 -> 0 | K29: =Fee*I29+Vq*J29 -> 0 | L29: 0.24622
A30: =INDEX(Quantiles!$B$4:$CT$4,1,26) -> 0.0725 | B30: =MIN(INDEX(Cost!$B$5:$CT$85,0,26)) -> 7.1346595 | C30: =INDEX(Cost!$A$5:$A$85,MATCH(B30,INDEX(Cost!$B$5:$CT$85,0,26),0)) -> 160 | D30: =INDEX(Delay!$B$5:$CT$85,MATCH(B30,INDEX(Cost!$B$5:$CT$85,0,26),0),26) -> 0.29183244 | E30: =INDEX(Delay!$B$5:$CT$85,1,26) -> 3.9438282 | F30: =IF(E30="","",Vq*E30) -> 31.550626 | H30: Joint check of Chapter 13 (robust) | I30: =Plan!B31 -> 54.916594 | J30: =0 -> 0 | K30: =Fee*I30+Vq*J30 -> 1.6474978 | L30: 0.17403
A31: =INDEX(Quantiles!$B$4:$CT$4,1,27) -> 0.075 | B31: =MIN(INDEX(Cost!$B$5:$CT$85,0,27)) -> 6.8385558 | C31: =INDEX(Cost!$A$5:$A$85,MATCH(B31,INDEX(Cost!$B$5:$CT$85,0,27),0)) -> 160 | D31: =INDEX(Delay!$B$5:$CT$85,MATCH(B31,INDEX(Cost!$B$5:$CT$85,0,27),0),27) -> 0.25481948 | E31: =INDEX(Delay!$B$5:$CT$85,1,27) -> 3.8494691 | F31: =IF(E31="","",Vq*E31) -> 30.795753 | H31: Phasing alone | I31: =0 -> 0 | J31: =I6 -> 5.0946732 | K31: =Fee*I31+Vq*J31 -> 40.757385 | L31: 0.05
A32: =INDEX(Quantiles!$B$4:$CT$4,1,28) -> 0.0775 | B32: =MIN(INDEX(Cost!$B$5:$CT$85,0,28)) -> 6.5414284 | C32: =INDEX(Cost!$A$5:$A$85,MATCH(B32,INDEX(Cost!$B$5:$CT$85,0,28),0)) -> 160 | D32: =INDEX(Delay!$B$5:$CT$85,MATCH(B32,INDEX(Cost!$B$5:$CT$85,0,28),0),28) -> 0.21767855 | E32: =INDEX(Delay!$B$5:$CT$85,1,28) -> 3.7420058 | F32: =IF(E32="","",Vq*E32) -> 29.936046 | H32: Chapter 8 package | I32: =I12 -> 100 | J32: =I13 -> 2 | K32: =I14 -> 19 | L32: =I15 -> 0.03003
A33: =INDEX(Quantiles!$B$4:$CT$4,1,29) -> 0.08 | B33: =MIN(INDEX(Cost!$B$5:$CT$85,0,29)) -> 6.2536377 | C33: =INDEX(Cost!$A$5:$A$85,MATCH(B33,INDEX(Cost!$B$5:$CT$85,0,29),0)) -> 160 | D33: =INDEX(Delay!$B$5:$CT$85,MATCH(B33,INDEX(Cost!$B$5:$CT$85,0,29),0),29) -> 0.18170472 | E33: =INDEX(Delay!$B$5:$CT$85,1,29) -> 3.6352795 | F33: =IF(E33="","",Vq*E33) -> 29.082236 | H33: Cheapest at 6 percent | I33: =C25 -> 160 | J33: =D25 -> 0.50242646 | K33: =B25 -> 8.8194117 | L33: =A25 -> 0.06
A34: =INDEX(Quantiles!$B$4:$CT$4,1,30) -> 0.0825 | B34: =MIN(INDEX(Cost!$B$5:$CT$85,0,30)) -> 5.9448524 | C34: =INDEX(Cost!$A$5:$A$85,MATCH(B34,INDEX(Cost!$B$5:$CT$85,0,30),0)) -> 165 | D34: =INDEX(Delay!$B$5:$CT$85,MATCH(B34,INDEX(Cost!$B$5:$CT$85,0,30),0),30) -> 0.12435655 | E34: =INDEX(Delay!$B$5:$CT$85,1,30) -> 3.530321 | F34: =IF(E34="","",Vq*E34) -> 28.242568 | H34: Cheapest at the board's 5 percent | I34: =C21 -> 170 | J34: =D21 -> 0.66757636 | K34: =B21 -> 10.440611 | L34: =A21 -> 0.05
A35: =INDEX(Quantiles!$B$4:$CT$4,1,31) -> 0.085 | B35: =MIN(INDEX(Cost!$B$5:$CT$85,0,31)) -> 5.6648231 | C35: =INDEX(Cost!$A$5:$A$85,MATCH(B35,INDEX(Cost!$B$5:$CT$85,0,31),0)) -> 160 | D35: =INDEX(Delay!$B$5:$CT$85,MATCH(B35,INDEX(Cost!$B$5:$CT$85,0,31),0),31) -> 0.10810289 | E35: =INDEX(Delay!$B$5:$CT$85,1,31) -> 3.4365146 | F35: =IF(E35="","",Vq*E35) -> 27.492116 | H35: Cheapest at 4 percent | I35: =C17 -> 165 | J35: =D17 -> 0.9250572 | K35: =B17 -> 12.350458 | L35: =A17 -> 0.04
A36: =INDEX(Quantiles!$B$4:$CT$4,1,32) -> 0.0875 | B36: =MIN(INDEX(Cost!$B$5:$CT$85,0,32)) -> 5.3926826 | C36: =INDEX(Cost!$A$5:$A$85,MATCH(B36,INDEX(Cost!$B$5:$CT$85,0,32),0)) -> 165 | D36: =INDEX(Delay!$B$5:$CT$85,MATCH(B36,INDEX(Cost!$B$5:$CT$85,0,32),0),32) -> 0.055335322 | E36: =INDEX(Delay!$B$5:$CT$85,1,32) -> 3.3422937 | F36: =IF(E36="","",Vq*E36) -> 26.738349 | H36: Cheapest at 3 percent | I36: =C13 -> 180 | J36: =D13 -> 1.1605155 | K36: =B13 -> 14.684124 | L36: =A13 -> 0.03
A37: =INDEX(Quantiles!$B$4:$CT$4,1,33) -> 0.09 | B37: =MIN(INDEX(Cost!$B$5:$CT$85,0,33)) -> 5.111533 | C37: =INDEX(Cost!$A$5:$A$85,MATCH(B37,INDEX(Cost!$B$5:$CT$85,0,33),0)) -> 160 | D37: =INDEX(Delay!$B$5:$CT$85,MATCH(B37,INDEX(Cost!$B$5:$CT$85,0,33),0),33) -> 0.038941624 | E37: =INDEX(Delay!$B$5:$CT$85,1,33) -> 3.2391029 | F37: =IF(E37="","",Vq*E37) -> 25.912823
A38: =INDEX(Quantiles!$B$4:$CT$4,1,34) -> 0.0925 | B38: =MIN(INDEX(Cost!$B$5:$CT$85,0,34)) -> 4.8477685 | C38: =INDEX(Cost!$A$5:$A$85,MATCH(B38,INDEX(Cost!$B$5:$CT$85,0,34),0)) -> 150 | D38: =INDEX(Delay!$B$5:$CT$85,MATCH(B38,INDEX(Cost!$B$5:$CT$85,0,34),0),34) -> 0.043471056 | E38: =INDEX(Delay!$B$5:$CT$85,1,34) -> 3.1634133 | F38: =IF(E38="","",Vq*E38) -> 25.307306 | H38: Odds of the cheapest packages are the appetites they meet; the other odds are the engine's, on the book's paths. Line alone, any size: odds of at least 8.4 percent (I5).
A39: =INDEX(Quantiles!$B$4:$CT$4,1,35) -> 0.095 | B39: =MIN(INDEX(Cost!$B$5:$CT$85,0,35)) -> 4.5868571 | C39: =INDEX(Cost!$A$5:$A$85,MATCH(B39,INDEX(Cost!$B$5:$CT$85,0,35),0)) -> 150 | D39: =INDEX(Delay!$B$5:$CT$85,MATCH(B39,INDEX(Cost!$B$5:$CT$85,0,35),0),35) -> 0.010857139 | E39: =INDEX(Delay!$B$5:$CT$85,1,35) -> 3.0655042 | F39: =IF(E39="","",Vq*E39) -> 24.524033
A40: =INDEX(Quantiles!$B$4:$CT$4,1,36) -> 0.0975 | B40: =MIN(INDEX(Cost!$B$5:$CT$85,0,36)) -> 4.35 | C40: =INDEX(Cost!$A$5:$A$85,MATCH(B40,INDEX(Cost!$B$5:$CT$85,0,36),0)) -> 145 | D40: =INDEX(Delay!$B$5:$CT$85,MATCH(B40,INDEX(Cost!$B$5:$CT$85,0,36),0),36) -> 0 | E40: =INDEX(Delay!$B$5:$CT$85,1,36) -> 2.9796626 | F40: =IF(E40="","",Vq*E40) -> 23.837301
A41: =INDEX(Quantiles!$B$4:$CT$4,1,37) -> 0.1 | B41: =MIN(INDEX(Cost!$B$5:$CT$85,0,37)) -> 4.1713729 | C41: =INDEX(Cost!$A$5:$A$85,MATCH(B41,INDEX(Cost!$B$5:$CT$85,0,37),0)) -> 135 | D41: =INDEX(Delay!$B$5:$CT$85,MATCH(B41,INDEX(Cost!$B$5:$CT$85,0,37),0),37) -> 0.015171616 | E41: =INDEX(Delay!$B$5:$CT$85,1,37) -> 2.900923 | F41: =IF(E41="","",Vq*E41) -> 23.207384
A42: =INDEX(Quantiles!$B$4:$CT$4,1,38) -> 0.1025 | B42: =MIN(INDEX(Cost!$B$5:$CT$85,0,38)) -> 4.0275131 | C42: =INDEX(Cost!$A$5:$A$85,MATCH(B42,INDEX(Cost!$B$5:$CT$85,0,38),0)) -> 130 | D42: =INDEX(Delay!$B$5:$CT$85,MATCH(B42,INDEX(Cost!$B$5:$CT$85,0,38),0),38) -> 0.015939136 | E42: =INDEX(Delay!$B$5:$CT$85,1,38) -> 2.824778 | F42: =IF(E42="","",Vq*E42) -> 22.598224
A43: =INDEX(Quantiles!$B$4:$CT$4,1,39) -> 0.105 | B43: =MIN(INDEX(Cost!$B$5:$CT$85,0,39)) -> 3.8775131 | C43: =INDEX(Cost!$A$5:$A$85,MATCH(B43,INDEX(Cost!$B$5:$CT$85,0,39),0)) -> 125 | D43: =INDEX(Delay!$B$5:$CT$85,MATCH(B43,INDEX(Cost!$B$5:$CT$85,0,39),0),39) -> 0.015939136 | E43: =INDEX(Delay!$B$5:$CT$85,1,39) -> 2.7393859 | F43: =IF(E43="","",Vq*E43) -> 21.915087
A44: =INDEX(Quantiles!$B$4:$CT$4,1,40) -> 0.1075 | B44: =MIN(INDEX(Cost!$B$5:$CT$85,0,40)) -> 3.75 | C44: =INDEX(Cost!$A$5:$A$85,MATCH(B44,INDEX(Cost!$B$5:$CT$85,0,40),0)) -> 125 | D44: =INDEX(Delay!$B$5:$CT$85,MATCH(B44,INDEX(Cost!$B$5:$CT$85,0,40),0),40) -> 0 | E44: =INDEX(Delay!$B$5:$CT$85,1,40) -> 2.658708 | F44: =IF(E44="","",Vq*E44) -> 21.269664
A45: =INDEX(Quantiles!$B$4:$CT$4,1,41) -> 0.11 | B45: =MIN(INDEX(Cost!$B$5:$CT$85,0,41)) -> 3.6 | C45: =INDEX(Cost!$A$5:$A$85,MATCH(B45,INDEX(Cost!$B$5:$CT$85,0,41),0)) -> 120 | D45: =INDEX(Delay!$B$5:$CT$85,MATCH(B45,INDEX(Cost!$B$5:$CT$85,0,41),0),41) -> 0 | E45: =INDEX(Delay!$B$5:$CT$85,1,41) -> 2.5863409 | F45: =IF(E45="","",Vq*E45) -> 20.690727
A46: =INDEX(Quantiles!$B$4:$CT$4,1,42) -> 0.1125 | B46: =MIN(INDEX(Cost!$B$5:$CT$85,0,42)) -> 3.45 | C46: =INDEX(Cost!$A$5:$A$85,MATCH(B46,INDEX(Cost!$B$5:$CT$85,0,42),0)) -> 115 | D46: =INDEX(Delay!$B$5:$CT$85,MATCH(B46,INDEX(Cost!$B$5:$CT$85,0,42),0),42) -> 0 | E46: =INDEX(Delay!$B$5:$CT$85,1,42) -> 2.5098777 | F46: =IF(E46="","",Vq*E46) -> 20.079022
A47: =INDEX(Quantiles!$B$4:$CT$4,1,43) -> 0.115 | B47: =MIN(INDEX(Cost!$B$5:$CT$85,0,43)) -> 3.3644176 | C47: =INDEX(Cost!$A$5:$A$85,MATCH(B47,INDEX(Cost!$B$5:$CT$85,0,43),0)) -> 110 | D47: =INDEX(Delay!$B$5:$CT$85,MATCH(B47,INDEX(Cost!$B$5:$CT$85,0,43),0),43) -> 0.008052198 | E47: =INDEX(Delay!$B$5:$CT$85,1,43) -> 2.4336597 | F47: =IF(E47="","",Vq*E47) -> 19.469277
A48: =INDEX(Quantiles!$B$4:$CT$4,1,44) -> 0.1175 | B48: =MIN(INDEX(Cost!$B$5:$CT$85,0,44)) -> 3.3 | C48: =INDEX(Cost!$A$5:$A$85,MATCH(B48,INDEX(Cost!$B$5:$CT$85,0,44),0)) -> 110 | D48: =INDEX(Delay!$B$5:$CT$85,MATCH(B48,INDEX(Cost!$B$5:$CT$85,0,44),0),44) -> 0 | E48: =INDEX(Delay!$B$5:$CT$85,1,44) -> 2.3604051 | F48: =IF(E48="","",Vq*E48) -> 18.883241
A49: =INDEX(Quantiles!$B$4:$CT$4,1,45) -> 0.12 | B49: =MIN(INDEX(Cost!$B$5:$CT$85,0,45)) -> 3.15 | C49: =INDEX(Cost!$A$5:$A$85,MATCH(B49,INDEX(Cost!$B$5:$CT$85,0,45),0)) -> 105 | D49: =INDEX(Delay!$B$5:$CT$85,MATCH(B49,INDEX(Cost!$B$5:$CT$85,0,45),0),45) -> 0 | E49: =INDEX(Delay!$B$5:$CT$85,1,45) -> 2.2860208 | F49: =IF(E49="","",Vq*E49) -> 18.288167
A50: =INDEX(Quantiles!$B$4:$CT$4,1,46) -> 0.1225 | B50: =MIN(INDEX(Cost!$B$5:$CT$85,0,46)) -> 3.1179341 | C50: =INDEX(Cost!$A$5:$A$85,MATCH(B50,INDEX(Cost!$B$5:$CT$85,0,46),0)) -> 100 | D50: =INDEX(Delay!$B$5:$CT$85,MATCH(B50,INDEX(Cost!$B$5:$CT$85,0,46),0),46) -> 0.014741764 | E50: =INDEX(Delay!$B$5:$CT$85,1,46) -> 2.2095325 | F50: =IF(E50="","",Vq*E50) -> 17.67626
A51: =INDEX(Quantiles!$B$4:$CT$4,1,47) -> 0.125 | B51: =MIN(INDEX(Cost!$B$5:$CT$85,0,47)) -> 3 | C51: =INDEX(Cost!$A$5:$A$85,MATCH(B51,INDEX(Cost!$B$5:$CT$85,0,47),0)) -> 100 | D51: =INDEX(Delay!$B$5:$CT$85,MATCH(B51,INDEX(Cost!$B$5:$CT$85,0,47),0),47) -> 0 | E51: =INDEX(Delay!$B$5:$CT$85,1,47) -> 2.1419366 | F51: =IF(E51="","",Vq*E51) -> 17.135493
A52: =INDEX(Quantiles!$B$4:$CT$4,1,48) -> 0.1275 | B52: =MIN(INDEX(Cost!$B$5:$CT$85,0,48)) -> 2.9065017 | C52: =INDEX(Cost!$A$5:$A$85,MATCH(B52,INDEX(Cost!$B$5:$CT$85,0,48),0)) -> 95 | D52: =INDEX(Delay!$B$5:$CT$85,MATCH(B52,INDEX(Cost!$B$5:$CT$85,0,48),0),48) -> 0.0070627161 | E52: =INDEX(Delay!$B$5:$CT$85,1,48) -> 2.0800488 | F52: =IF(E52="","",Vq*E52) -> 16.640391
A53: =INDEX(Quantiles!$B$4:$CT$4,1,49) -> 0.13 | B53: =MIN(INDEX(Cost!$B$5:$CT$85,0,49)) -> 2.85 | C53: =INDEX(Cost!$A$5:$A$85,MATCH(B53,INDEX(Cost!$B$5:$CT$85,0,49),0)) -> 95 | D53: =INDEX(Delay!$B$5:$CT$85,MATCH(B53,INDEX(Cost!$B$5:$CT$85,0,49),0),49) -> 0 | E53: =INDEX(Delay!$B$5:$CT$85,1,49) -> 2.0168866 | F53: =IF(E53="","",Vq*E53) -> 16.135093
A54: =INDEX(Quantiles!$B$4:$CT$4,1,50) -> 0.1325 | B54: =MIN(INDEX(Cost!$B$5:$CT$85,0,50)) -> 2.7430034 | C54: =INDEX(Cost!$A$5:$A$85,MATCH(B54,INDEX(Cost!$B$5:$CT$85,0,50),0)) -> 90 | D54: =INDEX(Delay!$B$5:$CT$85,MATCH(B54,INDEX(Cost!$B$5:$CT$85,0,50),0),50) -> 0.0053754199 | E54: =INDEX(Delay!$B$5:$CT$85,1,50) -> 1.947569 | F54: =IF(E54="","",Vq*E54) -> 15.580552
A55: =INDEX(Quantiles!$B$4:$CT$4,1,51) -> 0.135 | B55: =MIN(INDEX(Cost!$B$5:$CT$85,0,51)) -> 2.7 | C55: =INDEX(Cost!$A$5:$A$85,MATCH(B55,INDEX(Cost!$B$5:$CT$85,0,51),0)) -> 90 | D55: =INDEX(Delay!$B$5:$CT$85,MATCH(B55,INDEX(Cost!$B$5:$CT$85,0,51),0),51) -> 0 | E55: =INDEX(Delay!$B$5:$CT$85,1,51) -> 1.8890697 | F55: =IF(E55="","",Vq*E55) -> 15.112557
A56: =INDEX(Quantiles!$B$4:$CT$4,1,52) -> 0.1375 | B56: =MIN(INDEX(Cost!$B$5:$CT$85,0,52)) -> 2.606621 | C56: =INDEX(Cost!$A$5:$A$85,MATCH(B56,INDEX(Cost!$B$5:$CT$85,0,52),0)) -> 85 | D56: =INDEX(Delay!$B$5:$CT$85,MATCH(B56,INDEX(Cost!$B$5:$CT$85,0,52),0),52) -> 0.0070776226 | E56: =INDEX(Delay!$B$5:$CT$85,1,52) -> 1.8347779 | F56: =IF(E56="","",Vq*E56) -> 14.678223
A57: =INDEX(Quantiles!$B$4:$CT$4,1,53) -> 0.14 | B57: =MIN(INDEX(Cost!$B$5:$CT$85,0,53)) -> 2.55 | C57: =INDEX(Cost!$A$5:$A$85,MATCH(B57,INDEX(Cost!$B$5:$CT$85,0,53),0)) -> 85 | D57: =INDEX(Delay!$B$5:$CT$85,MATCH(B57,INDEX(Cost!$B$5:$CT$85,0,53),0),53) -> 0 | E57: =INDEX(Delay!$B$5:$CT$85,1,53) -> 1.7754338 | F57: =IF(E57="","",Vq*E57) -> 14.20347
A58: =INDEX(Quantiles!$B$4:$CT$4,1,54) -> 0.1425 | B58: =MIN(INDEX(Cost!$B$5:$CT$85,0,54)) -> 2.4861784 | C58: =INDEX(Cost!$A$5:$A$85,MATCH(B58,INDEX(Cost!$B$5:$CT$85,0,54),0)) -> 80 | D58: =INDEX(Delay!$B$5:$CT$85,MATCH(B58,INDEX(Cost!$B$5:$CT$85,0,54),0),54) -> 0.010772306 | E58: =INDEX(Delay!$B$5:$CT$85,1,54) -> 1.7160888 | F58: =IF(E58="","",Vq*E58) -> 13.728711
A59: =INDEX(Quantiles!$B$4:$CT$4,1,55) -> 0.145 | B59: =MIN(INDEX(Cost!$B$5:$CT$85,0,55)) -> 2.4 | C59: =INDEX(Cost!$A$5:$A$85,MATCH(B59,INDEX(Cost!$B$5:$CT$85,0,55),0)) -> 80 | D59: =INDEX(Delay!$B$5:$CT$85,MATCH(B59,INDEX(Cost!$B$5:$CT$85,0,55),0),55) -> 0 | E59: =INDEX(Delay!$B$5:$CT$85,1,55) -> 1.6514927 | F59: =IF(E59="","",Vq*E59) -> 13.211941
A60: =INDEX(Quantiles!$B$4:$CT$4,1,56) -> 0.1475 | B60: =MIN(INDEX(Cost!$B$5:$CT$85,0,56)) -> 2.4 | C60: =INDEX(Cost!$A$5:$A$85,MATCH(B60,INDEX(Cost!$B$5:$CT$85,0,56),0)) -> 80 | D60: =INDEX(Delay!$B$5:$CT$85,MATCH(B60,INDEX(Cost!$B$5:$CT$85,0,56),0),56) -> 0 | E60: =INDEX(Delay!$B$5:$CT$85,1,56) -> 1.5950285 | F60: =IF(E60="","",Vq*E60) -> 12.760228
A61: =INDEX(Quantiles!$B$4:$CT$4,1,57) -> 0.15 | B61: =MIN(INDEX(Cost!$B$5:$CT$85,0,57)) -> 2.25 | C61: =INDEX(Cost!$A$5:$A$85,MATCH(B61,INDEX(Cost!$B$5:$CT$85,0,57),0)) -> 75 | D61: =INDEX(Delay!$B$5:$CT$85,MATCH(B61,INDEX(Cost!$B$5:$CT$85,0,57),0),57) -> 0 | E61: =INDEX(Delay!$B$5:$CT$85,1,57) -> 1.5393751 | F61: =IF(E61="","",Vq*E61) -> 12.315001
A62: =INDEX(Quantiles!$B$4:$CT$4,1,58) -> 0.1525 | B62: =MIN(INDEX(Cost!$B$5:$CT$85,0,58)) -> 2.25 | C62: =INDEX(Cost!$A$5:$A$85,MATCH(B62,INDEX(Cost!$B$5:$CT$85,0,58),0)) -> 75 | D62: =INDEX(Delay!$B$5:$CT$85,MATCH(B62,INDEX(Cost!$B$5:$CT$85,0,58),0),58) -> 0 | E62: =INDEX(Delay!$B$5:$CT$85,1,58) -> 1.4873648 | F62: =IF(E62="","",Vq*E62) -> 11.898919
A63: =INDEX(Quantiles!$B$4:$CT$4,1,59) -> 0.155 | B63: =MIN(INDEX(Cost!$B$5:$CT$85,0,59)) -> 2.1176841 | C63: =INDEX(Cost!$A$5:$A$85,MATCH(B63,INDEX(Cost!$B$5:$CT$85,0,59),0)) -> 70 | D63: =INDEX(Delay!$B$5:$CT$85,MATCH(B63,INDEX(Cost!$B$5:$CT$85,0,59),0),59) -> 0.002210512 | E63: =INDEX(Delay!$B$5:$CT$85,1,59) -> 1.4350993 | F63: =IF(E63="","",Vq*E63) -> 11.480794
A64: =INDEX(Quantiles!$B$4:$CT$4,1,60) -> 0.1575 | B64: =MIN(INDEX(Cost!$B$5:$CT$85,0,60)) -> 2.1 | C64: =INDEX(Cost!$A$5:$A$85,MATCH(B64,INDEX(Cost!$B$5:$CT$85,0,60),0)) -> 70 | D64: =INDEX(Delay!$B$5:$CT$85,MATCH(B64,INDEX(Cost!$B$5:$CT$85,0,60),0),60) -> 0 | E64: =INDEX(Delay!$B$5:$CT$85,1,60) -> 1.3830971 | F64: =IF(E64="","",Vq*E64) -> 11.064777
A65: =INDEX(Quantiles!$B$4:$CT$4,1,61) -> 0.16 | B65: =MIN(INDEX(Cost!$B$5:$CT$85,0,61)) -> 2.0687156 | C65: =INDEX(Cost!$A$5:$A$85,MATCH(B65,INDEX(Cost!$B$5:$CT$85,0,61),0)) -> 65 | D65: =INDEX(Delay!$B$5:$CT$85,MATCH(B65,INDEX(Cost!$B$5:$CT$85,0,61),0),61) -> 0.014839449 | E65: =INDEX(Delay!$B$5:$CT$85,1,61) -> 1.3348248 | F65: =IF(E65="","",Vq*E65) -> 10.678599
A66: =INDEX(Quantiles!$B$4:$CT$4,1,62) -> 0.1625 | B66: =MIN(INDEX(Cost!$B$5:$CT$85,0,62)) -> 1.95 | C66: =INDEX(Cost!$A$5:$A$85,MATCH(B66,INDEX(Cost!$B$5:$CT$85,0,62),0)) -> 65 | D66: =INDEX(Delay!$B$5:$CT$85,MATCH(B66,INDEX(Cost!$B$5:$CT$85,0,62),0),62) -> 0 | E66: =INDEX(Delay!$B$5:$CT$85,1,62) -> 1.2848509 | F66: =IF(E66="","",Vq*E66) -> 10.278807
A67: =INDEX(Quantiles!$B$4:$CT$4,1,63) -> 0.165 | B67: =MIN(INDEX(Cost!$B$5:$CT$85,0,63)) -> 1.95 | C67: =INDEX(Cost!$A$5:$A$85,MATCH(B67,INDEX(Cost!$B$5:$CT$85,0,63),0)) -> 65 | D67: =INDEX(Delay!$B$5:$CT$85,MATCH(B67,INDEX(Cost!$B$5:$CT$85,0,63),0),63) -> 0 | E67: =INDEX(Delay!$B$5:$CT$85,1,63) -> 1.2392019 | F67: =IF(E67="","",Vq*E67) -> 9.9136156
A68: =INDEX(Quantiles!$B$4:$CT$4,1,64) -> 0.1675 | B68: =MIN(INDEX(Cost!$B$5:$CT$85,0,64)) -> 1.8044117 | C68: =INDEX(Cost!$A$5:$A$85,MATCH(B68,INDEX(Cost!$B$5:$CT$85,0,64),0)) -> 60 | D68: =INDEX(Delay!$B$5:$CT$85,MATCH(B68,INDEX(Cost!$B$5:$CT$85,0,64),0),64) -> 0.00055145706 | E68: =INDEX(Delay!$B$5:$CT$85,1,64) -> 1.1878968 | F68: =IF(E68="","",Vq*E68) -> 9.5031743
A69: =INDEX(Quantiles!$B$4:$CT$4,1,65) -> 0.17 | B69: =MIN(INDEX(Cost!$B$5:$CT$85,0,65)) -> 1.8 | C69: =INDEX(Cost!$A$5:$A$85,MATCH(B69,INDEX(Cost!$B$5:$CT$85,0,65),0)) -> 60 | D69: =INDEX(Delay!$B$5:$CT$85,MATCH(B69,INDEX(Cost!$B$5:$CT$85,0,65),0),65) -> 0 | E69: =INDEX(Delay!$B$5:$CT$85,1,65) -> 1.1351612 | F69: =IF(E69="","",Vq*E69) -> 9.0812895
A70: =INDEX(Quantiles!$B$4:$CT$4,1,66) -> 0.1725 | B70: =MIN(INDEX(Cost!$B$5:$CT$85,0,66)) -> 1.7713729 | C70: =INDEX(Cost!$A$5:$A$85,MATCH(B70,INDEX(Cost!$B$5:$CT$85,0,66),0)) -> 55 | D70: =INDEX(Delay!$B$5:$CT$85,MATCH(B70,INDEX(Cost!$B$5:$CT$85,0,66),0),66) -> 0.015171616 | E70: =INDEX(Delay!$B$5:$CT$85,1,66) -> 1.0894948 | F70: =IF(E70="","",Vq*E70) -> 8.7159581
A71: =INDEX(Quantiles!$B$4:$CT$4,1,67) -> 0.175 | B71: =MIN(INDEX(Cost!$B$5:$CT$85,0,67)) -> 1.65 | C71: =INDEX(Cost!$A$5:$A$85,MATCH(B71,INDEX(Cost!$B$5:$CT$85,0,67),0)) -> 55 | D71: =INDEX(Delay!$B$5:$CT$85,MATCH(B71,INDEX(Cost!$B$5:$CT$85,0,67),0),67) -> 0 | E71: =INDEX(Delay!$B$5:$CT$85,1,67) -> 1.0457427 | F71: =IF(E71="","",Vq*E71) -> 8.3659413
A72: =INDEX(Quantiles!$B$4:$CT$4,1,68) -> 0.1775 | B72: =MIN(INDEX(Cost!$B$5:$CT$85,0,68)) -> 1.65 | C72: =INDEX(Cost!$A$5:$A$85,MATCH(B72,INDEX(Cost!$B$5:$CT$85,0,68),0)) -> 55 | D72: =INDEX(Delay!$B$5:$CT$85,MATCH(B72,INDEX(Cost!$B$5:$CT$85,0,68),0),68) -> 0 | E72: =INDEX(Delay!$B$5:$CT$85,1,68) -> 0.99565249 | F72: =IF(E72="","",Vq*E72) -> 7.96522
A73: =INDEX(Quantiles!$B$4:$CT$4,1,69) -> 0.18 | B73: =MIN(INDEX(Cost!$B$5:$CT$85,0,69)) -> 1.5667815 | C73: =INDEX(Cost!$A$5:$A$85,MATCH(B73,INDEX(Cost!$B$5:$CT$85,0,69),0)) -> 50 | D73: =INDEX(Delay!$B$5:$CT$85,MATCH(B73,INDEX(Cost!$B$5:$CT$85,0,69),0),69) -> 0.0083476832 | E73: =INDEX(Delay!$B$5:$CT$85,1,69) -> 0.95169493 | F73: =IF(E73="","",Vq*E73) -> 7.6135595
A74: =INDEX(Quantiles!$B$4:$CT$4,1,70) -> 0.1825 | B74: =MIN(INDEX(Cost!$B$5:$CT$85,0,70)) -> 1.5 | C74: =INDEX(Cost!$A$5:$A$85,MATCH(B74,INDEX(Cost!$B$5:$CT$85,0,70),0)) -> 50 | D74: =INDEX(Delay!$B$5:$CT$85,MATCH(B74,INDEX(Cost!$B$5:$CT$85,0,70),0),70) -> 0 | E74: =INDEX(Delay!$B$5:$CT$85,1,70) -> 0.90731874 | F74: =IF(E74="","",Vq*E74) -> 7.2585499
A75: =INDEX(Quantiles!$B$4:$CT$4,1,71) -> 0.185 | B75: =MIN(INDEX(Cost!$B$5:$CT$85,0,71)) -> 1.5 | C75: =INDEX(Cost!$A$5:$A$85,MATCH(B75,INDEX(Cost!$B$5:$CT$85,0,71),0)) -> 50 | D75: =INDEX(Delay!$B$5:$CT$85,MATCH(B75,INDEX(Cost!$B$5:$CT$85,0,71),0),71) -> 0 | E75: =INDEX(Delay!$B$5:$CT$85,1,71) -> 0.86814728 | F75: =IF(E75="","",Vq*E75) -> 6.9451782
A76: =INDEX(Quantiles!$B$4:$CT$4,1,72) -> 0.1875 | B76: =MIN(INDEX(Cost!$B$5:$CT$85,0,72)) -> 1.3704637 | C76: =INDEX(Cost!$A$5:$A$85,MATCH(B76,INDEX(Cost!$B$5:$CT$85,0,72),0)) -> 45 | D76: =INDEX(Delay!$B$5:$CT$85,MATCH(B76,INDEX(Cost!$B$5:$CT$85,0,72),0),72) -> 0.0025579591 | E76: =INDEX(Delay!$B$5:$CT$85,1,72) -> 0.82553276 | F76: =IF(E76="","",Vq*E76) -> 6.6042621
A77: =INDEX(Quantiles!$B$4:$CT$4,1,73) -> 0.19 | B77: =MIN(INDEX(Cost!$B$5:$CT$85,0,73)) -> 1.35 | C77: =INDEX(Cost!$A$5:$A$85,MATCH(B77,INDEX(Cost!$B$5:$CT$85,0,73),0)) -> 45 | D77: =INDEX(Delay!$B$5:$CT$85,MATCH(B77,INDEX(Cost!$B$5:$CT$85,0,73),0),73) -> 0 | E77: =INDEX(Delay!$B$5:$CT$85,1,73) -> 0.78165389 | F77: =IF(E77="","",Vq*E77) -> 6.2532311
A78: =INDEX(Quantiles!$B$4:$CT$4,1,74) -> 0.1925 | B78: =MIN(INDEX(Cost!$B$5:$CT$85,0,74)) -> 1.35 | C78: =INDEX(Cost!$A$5:$A$85,MATCH(B78,INDEX(Cost!$B$5:$CT$85,0,74),0)) -> 45 | D78: =INDEX(Delay!$B$5:$CT$85,MATCH(B78,INDEX(Cost!$B$5:$CT$85,0,74),0),74) -> 0 | E78: =INDEX(Delay!$B$5:$CT$85,1,74) -> 0.73784177 | F78: =IF(E78="","",Vq*E78) -> 5.9027341
A79: =INDEX(Quantiles!$B$4:$CT$4,1,75) -> 0.195 | B79: =MIN(INDEX(Cost!$B$5:$CT$85,0,75)) -> 1.2 | C79: =INDEX(Cost!$A$5:$A$85,MATCH(B79,INDEX(Cost!$B$5:$CT$85,0,75),0)) -> 40 | D79: =INDEX(Delay!$B$5:$CT$85,MATCH(B79,INDEX(Cost!$B$5:$CT$85,0,75),0),75) -> 0 | E79: =INDEX(Delay!$B$5:$CT$85,1,75) -> 0.6984772 | F79: =IF(E79="","",Vq*E79) -> 5.5878176
A80: =INDEX(Quantiles!$B$4:$CT$4,1,76) -> 0.1975 | B80: =MIN(INDEX(Cost!$B$5:$CT$85,0,76)) -> 1.2 | C80: =INDEX(Cost!$A$5:$A$85,MATCH(B80,INDEX(Cost!$B$5:$CT$85,0,76),0)) -> 40 | D80: =INDEX(Delay!$B$5:$CT$85,MATCH(B80,INDEX(Cost!$B$5:$CT$85,0,76),0),76) -> 0 | E80: =INDEX(Delay!$B$5:$CT$85,1,76) -> 0.66070232 | F80: =IF(E80="","",Vq*E80) -> 5.2856186
A81: =INDEX(Quantiles!$B$4:$CT$4,1,77) -> 0.2 | B81: =MIN(INDEX(Cost!$B$5:$CT$85,0,77)) -> 1.1859412 | C81: =INDEX(Cost!$A$5:$A$85,MATCH(B81,INDEX(Cost!$B$5:$CT$85,0,77),0)) -> 35 | D81: =INDEX(Delay!$B$5:$CT$85,MATCH(B81,INDEX(Cost!$B$5:$CT$85,0,77),0),77) -> 0.016992644 | E81: =INDEX(Delay!$B$5:$CT$85,1,77) -> 0.62125773 | F81: =IF(E81="","",Vq*E81) -> 4.9700619
A82: =INDEX(Quantiles!$B$4:$CT$4,1,78) -> 0.2025 | B82: =MIN(INDEX(Cost!$B$5:$CT$85,0,78)) -> 1.05 | C82: =INDEX(Cost!$A$5:$A$85,MATCH(B82,INDEX(Cost!$B$5:$CT$85,0,78),0)) -> 35 | D82: =INDEX(Delay!$B$5:$CT$85,MATCH(B82,INDEX(Cost!$B$5:$CT$85,0,78),0),78) -> 0 | E82: =INDEX(Delay!$B$5:$CT$85,1,78) -> 0.58222847 | F82: =IF(E82="","",Vq*E82) -> 4.6578278
A83: =INDEX(Quantiles!$B$4:$CT$4,1,79) -> 0.205 | B83: =MIN(INDEX(Cost!$B$5:$CT$85,0,79)) -> 1.05 | C83: =INDEX(Cost!$A$5:$A$85,MATCH(B83,INDEX(Cost!$B$5:$CT$85,0,79),0)) -> 35 | D83: =INDEX(Delay!$B$5:$CT$85,MATCH(B83,INDEX(Cost!$B$5:$CT$85,0,79),0),79) -> 0 | E83: =INDEX(Delay!$B$5:$CT$85,1,79) -> 0.54541497 | F83: =IF(E83="","",Vq*E83) -> 4.3633197
A84: =INDEX(Quantiles!$B$4:$CT$4,1,80) -> 0.2075 | B84: =MIN(INDEX(Cost!$B$5:$CT$85,0,80)) -> 0.99007505 | C84: =INDEX(Cost!$A$5:$A$85,MATCH(B84,INDEX(Cost!$B$5:$CT$85,0,80),0)) -> 30 | D84: =INDEX(Delay!$B$5:$CT$85,MATCH(B84,INDEX(Cost!$B$5:$CT$85,0,80),0),80) -> 0.011259381 | E84: =INDEX(Delay!$B$5:$CT$85,1,80) -> 0.50968448 | F84: =IF(E84="","",Vq*E84) -> 4.0774759
A85: =INDEX(Quantiles!$B$4:$CT$4,1,81) -> 0.21 | B85: =MIN(INDEX(Cost!$B$5:$CT$85,0,81)) -> 0.9 | C85: =INDEX(Cost!$A$5:$A$85,MATCH(B85,INDEX(Cost!$B$5:$CT$85,0,81),0)) -> 30 | D85: =INDEX(Delay!$B$5:$CT$85,MATCH(B85,INDEX(Cost!$B$5:$CT$85,0,81),0),81) -> 0 | E85: =INDEX(Delay!$B$5:$CT$85,1,81) -> 0.4719352 | F85: =IF(E85="","",Vq*E85) -> 3.7754816
A86: =INDEX(Quantiles!$B$4:$CT$4,1,82) -> 0.2125 | B86: =MIN(INDEX(Cost!$B$5:$CT$85,0,82)) -> 0.9 | C86: =INDEX(Cost!$A$5:$A$85,MATCH(B86,INDEX(Cost!$B$5:$CT$85,0,82),0)) -> 30 | D86: =INDEX(Delay!$B$5:$CT$85,MATCH(B86,INDEX(Cost!$B$5:$CT$85,0,82),0),82) -> 0 | E86: =INDEX(Delay!$B$5:$CT$85,1,82) -> 0.43589747 | F86: =IF(E86="","",Vq*E86) -> 3.4871798
A87: =INDEX(Quantiles!$B$4:$CT$4,1,83) -> 0.215 | B87: =MIN(INDEX(Cost!$B$5:$CT$85,0,83)) -> 0.75 | C87: =INDEX(Cost!$A$5:$A$85,MATCH(B87,INDEX(Cost!$B$5:$CT$85,0,83),0)) -> 25 | D87: =INDEX(Delay!$B$5:$CT$85,MATCH(B87,INDEX(Cost!$B$5:$CT$85,0,83),0),83) -> 0 | E87: =INDEX(Delay!$B$5:$CT$85,1,83) -> 0.40237246 | F87: =IF(E87="","",Vq*E87) -> 3.2189797
A88: =INDEX(Quantiles!$B$4:$CT$4,1,84) -> 0.2175 | B88: =MIN(INDEX(Cost!$B$5:$CT$85,0,84)) -> 0.75 | C88: =INDEX(Cost!$A$5:$A$85,MATCH(B88,INDEX(Cost!$B$5:$CT$85,0,84),0)) -> 25 | D88: =INDEX(Delay!$B$5:$CT$85,MATCH(B88,INDEX(Cost!$B$5:$CT$85,0,84),0),84) -> 0 | E88: =INDEX(Delay!$B$5:$CT$85,1,84) -> 0.3676697 | F88: =IF(E88="","",Vq*E88) -> 2.9413576
A89: =INDEX(Quantiles!$B$4:$CT$4,1,85) -> 0.22 | B89: =MIN(INDEX(Cost!$B$5:$CT$85,0,85)) -> 0.7155435 | C89: =INDEX(Cost!$A$5:$A$85,MATCH(B89,INDEX(Cost!$B$5:$CT$85,0,85),0)) -> 20 | D89: =INDEX(Delay!$B$5:$CT$85,MATCH(B89,INDEX(Cost!$B$5:$CT$85,0,85),0),85) -> 0.014442937 | E89: =INDEX(Delay!$B$5:$CT$85,1,85) -> 0.33439614 | F89: =IF(E89="","",Vq*E89) -> 2.6751691
A90: =INDEX(Quantiles!$B$4:$CT$4,1,86) -> 0.2225 | B90: =MIN(INDEX(Cost!$B$5:$CT$85,0,86)) -> 0.6 | C90: =INDEX(Cost!$A$5:$A$85,MATCH(B90,INDEX(Cost!$B$5:$CT$85,0,86),0)) -> 20 | D90: =INDEX(Delay!$B$5:$CT$85,MATCH(B90,INDEX(Cost!$B$5:$CT$85,0,86),0),86) -> 0 | E90: =INDEX(Delay!$B$5:$CT$85,1,86) -> 0.29916417 | F90: =IF(E90="","",Vq*E90) -> 2.3933134
A91: =INDEX(Quantiles!$B$4:$CT$4,1,87) -> 0.225 | B91: =MIN(INDEX(Cost!$B$5:$CT$85,0,87)) -> 0.6 | C91: =INDEX(Cost!$A$5:$A$85,MATCH(B91,INDEX(Cost!$B$5:$CT$85,0,87),0)) -> 20 | D91: =INDEX(Delay!$B$5:$CT$85,MATCH(B91,INDEX(Cost!$B$5:$CT$85,0,87),0),87) -> 0 | E91: =INDEX(Delay!$B$5:$CT$85,1,87) -> 0.26596644 | F91: =IF(E91="","",Vq*E91) -> 2.1277315
A92: =INDEX(Quantiles!$B$4:$CT$4,1,88) -> 0.2275 | B92: =MIN(INDEX(Cost!$B$5:$CT$85,0,88)) -> 0.47045996 | C92: =INDEX(Cost!$A$5:$A$85,MATCH(B92,INDEX(Cost!$B$5:$CT$85,0,88),0)) -> 15 | D92: =INDEX(Delay!$B$5:$CT$85,MATCH(B92,INDEX(Cost!$B$5:$CT$85,0,88),0),88) -> 0.0025574946 | E92: =INDEX(Delay!$B$5:$CT$85,1,88) -> 0.23392711 | F92: =IF(E92="","",Vq*E92) -> 1.8714169
A93: =INDEX(Quantiles!$B$4:$CT$4,1,89) -> 0.23 | B93: =MIN(INDEX(Cost!$B$5:$CT$85,0,89)) -> 0.45 | C93: =INDEX(Cost!$A$5:$A$85,MATCH(B93,INDEX(Cost!$B$5:$CT$85,0,89),0)) -> 15 | D93: =INDEX(Delay!$B$5:$CT$85,MATCH(B93,INDEX(Cost!$B$5:$CT$85,0,89),0),89) -> 0 | E93: =INDEX(Delay!$B$5:$CT$85,1,89) -> 0.20062462 | F93: =IF(E93="","",Vq*E93) -> 1.604997
A94: =INDEX(Quantiles!$B$4:$CT$4,1,90) -> 0.2325 | B94: =MIN(INDEX(Cost!$B$5:$CT$85,0,90)) -> 0.42751309 | C94: =INDEX(Cost!$A$5:$A$85,MATCH(B94,INDEX(Cost!$B$5:$CT$85,0,90),0)) -> 10 | D94: =INDEX(Delay!$B$5:$CT$85,MATCH(B94,INDEX(Cost!$B$5:$CT$85,0,90),0),90) -> 0.015939136 | E94: =INDEX(Delay!$B$5:$CT$85,1,90) -> 0.1685935 | F94: =IF(E94="","",Vq*E94) -> 1.348748
A95: =INDEX(Quantiles!$B$4:$CT$4,1,91) -> 0.235 | B95: =MIN(INDEX(Cost!$B$5:$CT$85,0,91)) -> 0.3 | C95: =INDEX(Cost!$A$5:$A$85,MATCH(B95,INDEX(Cost!$B$5:$CT$85,0,91),0)) -> 10 | D95: =INDEX(Delay!$B$5:$CT$85,MATCH(B95,INDEX(Cost!$B$5:$CT$85,0,91),0),91) -> 0 | E95: =INDEX(Delay!$B$5:$CT$85,1,91) -> 0.13554636 | F95: =IF(E95="","",Vq*E95) -> 1.0843709
A96: =INDEX(Quantiles!$B$4:$CT$4,1,92) -> 0.2375 | B96: =MIN(INDEX(Cost!$B$5:$CT$85,0,92)) -> 0.3 | C96: =INDEX(Cost!$A$5:$A$85,MATCH(B96,INDEX(Cost!$B$5:$CT$85,0,92),0)) -> 10 | D96: =INDEX(Delay!$B$5:$CT$85,MATCH(B96,INDEX(Cost!$B$5:$CT$85,0,92),0),92) -> 0 | E96: =INDEX(Delay!$B$5:$CT$85,1,92) -> 0.10535895 | F96: =IF(E96="","",Vq*E96) -> 0.84287158
A97: =INDEX(Quantiles!$B$4:$CT$4,1,93) -> 0.24 | B97: =MIN(INDEX(Cost!$B$5:$CT$85,0,93)) -> 0.17169223 | C97: =INDEX(Cost!$A$5:$A$85,MATCH(B97,INDEX(Cost!$B$5:$CT$85,0,93),0)) -> 5 | D97: =INDEX(Delay!$B$5:$CT$85,MATCH(B97,INDEX(Cost!$B$5:$CT$85,0,93),0),93) -> 0.0027115285 | E97: =INDEX(Delay!$B$5:$CT$85,1,93) -> 0.073466404 | F97: =IF(E97="","",Vq*E97) -> 0.58773123
A98: =INDEX(Quantiles!$B$4:$CT$4,1,94) -> 0.2425 | B98: =MIN(INDEX(Cost!$B$5:$CT$85,0,94)) -> 0.15 | C98: =INDEX(Cost!$A$5:$A$85,MATCH(B98,INDEX(Cost!$B$5:$CT$85,0,94),0)) -> 5 | D98: =INDEX(Delay!$B$5:$CT$85,MATCH(B98,INDEX(Cost!$B$5:$CT$85,0,94),0),94) -> 0 | E98: =INDEX(Delay!$B$5:$CT$85,1,94) -> 0.041851915 | F98: =IF(E98="","",Vq*E98) -> 0.33481532
A99: =INDEX(Quantiles!$B$4:$CT$4,1,95) -> 0.245 | B99: =MIN(INDEX(Cost!$B$5:$CT$85,0,95)) -> 0.11564236 | C99: =INDEX(Cost!$A$5:$A$85,MATCH(B99,INDEX(Cost!$B$5:$CT$85,0,95),0)) -> 0 | D99: =INDEX(Delay!$B$5:$CT$85,MATCH(B99,INDEX(Cost!$B$5:$CT$85,0,95),0),95) -> 0.014455295 | E99: =INDEX(Delay!$B$5:$CT$85,1,95) -> 0.014455295 | F99: =IF(E99="","",Vq*E99) -> 0.11564236
A100: =INDEX(Quantiles!$B$4:$CT$4,1,96) -> 0.246 | B100: =MIN(INDEX(Cost!$B$5:$CT$85,0,96)) -> 0.019881727 | C100: =INDEX(Cost!$A$5:$A$85,MATCH(B100,INDEX(Cost!$B$5:$CT$85,0,96),0)) -> 0 | D100: =INDEX(Delay!$B$5:$CT$85,MATCH(B100,INDEX(Cost!$B$5:$CT$85,0,96),0),96) -> 0.0024852159 | E100: =INDEX(Delay!$B$5:$CT$85,1,96) -> 0.0024852159 | F100: =IF(E100="","",Vq*E100) -> 0.019881727
A101: =INDEX(Quantiles!$B$4:$CT$4,1,97) -> 0.03003 | B101: =MIN(INDEX(Cost!$B$5:$CT$85,0,97)) -> 14.668098 | C101: =INDEX(Cost!$A$5:$A$85,MATCH(B101,INDEX(Cost!$B$5:$CT$85,0,97),0)) -> 180 | D101: =INDEX(Delay!$B$5:$CT$85,MATCH(B101,INDEX(Cost!$B$5:$CT$85,0,97),0),97) -> 1.1585123 | E101: =INDEX(Delay!$B$5:$CT$85,1,97) -> 6.6131394 | F101: =IF(E101="","",Vq*E101) -> 52.905115

Sheet Solve
A1: Solve and read the binding set; price the appetite (Worked Example 15.1, Steps 3-4; Theorem 15.3)
A3: The cheapest package at the board's appetite | B3: Value | C3: Reading
A4: Least cost | B4: =Frontier!B21 -> 10.440611 | C4: $10.4 million
A5: Line | B5: =Frontier!C21 -> 170 | C5: about $170 million
A6: Delay (quarters) | B6: =Frontier!D21 -> 0.66757636 | C6: two-thirds of a quarter
A7: Delay (months) | B7: =3*B6 -> 2.0027291 | C7: two months
A8: Depth of the draw, 28 - 4 x delay | B8: =Depth0-Depth_per_q*B6 -> 25.329695 | C8: 25.33
A9: Deepest draw | B9: =Plan!B24 -> 121.63437 | C9: 121.6
A10: Smaller than the plan's by | B10: =Plan!B25 -> 16.41525 | C10: $16 million
A11: Fees | B11: =Fee*B5 -> 5.1 | C11: $5.1 million
A12: Cost of the delay | B12: =Vq*B6 -> 5.3406109 | C12: $5.3 million
A13: Lowest line within $0.5 million of the least cost | B13: =_xlfn.MINIFS(Cost!$A$5:$A$85,Cost!$R$5:$R$85,"<="&(B4+0.5)) -> 140 | C13: $140 million
A14: Highest line within $0.5 million of the least cost | B14: =_xlfn.MAXIFS(Cost!$A$5:$A$85,Cost!$R$5:$R$85,"<="&(B4+0.5)) -> 205 | C14: $205 million: a flat optimum
A16: Net leverage with the line fully drawn | B16: =(Net_debt+B5)/Ebitda -> 3.7430186 | C16: 3.7x: the covenant is slack
A17: Covenant multiplier | B17: =IF(B16<Covenant,0,"binds") -> 0 | C17: zero: complementary slackness
A18: Capability against its floor | B18: =IF(Capability>=Cap_floor,0,"binds") -> 0 | C18: zero: neither lever touches capability
A20: Equal margins at the optimum (Equation 15.4) | B20: Value | C20: Reading
A21: Line step (central difference, $ million) | B21: 20
A22: Odds at the line + step (engine) | B22: 0.04755
A23: Odds at the line - step (engine) | B23: 0.0542
A24: Odds cut per $1 million of line (points) | B24: =-(B22-B23)/(2*B21)*100 -> 0.016625 | C24: 0.0166
A25: Delay step (central difference, quarters) | B25: 0.125
A26: Odds at the delay + step (engine) | B26: 0.04487
A27: Odds at the delay - step (engine) | B27: 0.05616
A28: Odds cut per quarter of delay (points) | B28: =-(B26-B27)/(2*B25)*100 -> 4.516 | C28: 4.52
A29: A point of safety by the line ($ million) | B29: =Fee/B24 -> 1.8045113 | C29: $1.80 million
A30: A point of safety by the delay ($ million) | B30: =Vq/B28 -> 1.7714792 | C30: $1.77 million
A31: Points bought by the last $1 million: line | B31: =B24/Fee -> 0.55416667 | C31: about half a point
A32: Points bought by the last $1 million: delay | B32: =B28/Vq -> 0.5645 | C32: about half a point
A34: The price of the appetite (Step 4; Theorem 15.3(iii)) | B34: Value | C34: Reading
A35: Least cost at 4% | B35: =Frontier!B17 -> 12.350458 | C35: $12.4 million
A36: Least cost at 4.5% | B36: =Frontier!B19 -> 11.388504
A37: Least cost at 5% | B37: =Frontier!B21 -> 10.440611 | C37: $10.4 million
A38: Least cost at 5.5% | B38: =Frontier!B23 -> 9.5814895
A39: Least cost at 6% | B39: =Frontier!B25 -> 8.8194117 | C39: $8.8 million
A40: The appetite's multiplier ($ million a point, 4.5 to 5.5%) | B40: =B36-B38 -> 1.8070148 | C40: $1.8 million a point
A41: The same, 4 to 6% | B41: =(B35-B39)/2 -> 1.765523 | C41: Online Appendix 15.B.4: 1.77
A42: Implied cost of a breach ($ million) | B42: =100*B40 -> 180.70148 | C42: about $180 million
A43: As a share of a year's EBITDA | B43: =B42/Ebitda -> 0.36461154 | C43: a third
A44: Tightening a point costs at least the multiplier | B44: =IF(B35-B37>=B40,"yes","no") -> yes | C44: Theorem 15.3(iii)
A45: Loosening a point gains at most the multiplier | B45: =IF(B37-B39<=B40,"yes","no") -> yes | C45: Theorem 15.3(iii)

Sheet Sensitivity
A1: The price moves with the declared value of delay; the line hardly moves (Worked Example 15.1, Step 4)
A2: The cost of every package at another value of a quarter of delay, for the appetites that set the price.
A3: Value of a quarter of delay | B3: 4 | C3: 4 | D3: 4 | E3: 16 | F3: 16 | G3: 16
A4: Line ($ million) | B4: $4m a quarter, 4.5% | C4: $4m a quarter, 5.0% | D4: $4m a quarter, 5.5% | E4: $16m a quarter, 4.5% | F4: $16m a quarter, 5.0% | G4: $16m a quarter, 5.5%
A5: =Quantiles!A5 -> 0 | B5: =IF(Delay!P5="","",Fee*$A5+B$3*Delay!P5) -> 21.614789 | C5: =IF(Delay!R5="","",Fee*$A5+C$3*Delay!R5) -> 20.378693 | D5: =IF(Delay!T5="","",Fee*$A5+D$3*Delay!T5) -> 19.190921 | E5: =IF(Delay!P5="","",Fee*$A5+E$3*Delay!P5) -> 86.459154 | F5: =IF(Delay!R5="","",Fee*$A5+F$3*Delay!R5) -> 81.514771 | G5: =IF(Delay!T5="","",Fee*$A5+G$3*Delay!T5) -> 76.763682
A6: =Quantiles!A6 -> 5 | B6: =IF(Delay!P6="","",Fee*$A6+B$3*Delay!P6) -> 20.723072 | C6: =IF(Delay!R6="","",Fee*$A6+C$3*Delay!R6) -> 19.472678 | D6: =IF(Delay!T6="","",Fee*$A6+D$3*Delay!T6) -> 18.326676 | E6: =IF(Delay!P6="","",Fee*$A6+E$3*Delay!P6) -> 82.442288 | F6: =IF(Delay!R6="","",Fee*$A6+F$3*Delay!R6) -> 77.440712 | G6: =IF(Delay!T6="","",Fee*$A6+G$3*Delay!T6) -> 72.856703
A7: =Quantiles!A7 -> 10 | B7: =IF(Delay!P7="","",Fee*$A7+B$3*Delay!P7) -> 19.808926 | C7: =IF(Delay!R7="","",Fee*$A7+C$3*Delay!R7) -> 18.619236 | D7: =IF(Delay!T7="","",Fee*$A7+D$3*Delay!T7) -> 17.486958 | E7: =IF(Delay!P7="","",Fee*$A7+E$3*Delay!P7) -> 78.335705 | F7: =IF(Delay!R7="","",Fee*$A7+F$3*Delay!R7) -> 73.576945 | G7: =IF(Delay!T7="","",Fee*$A7+G$3*Delay!T7) -> 69.047832
A8: =Quantiles!A8 -> 15 | B8: =IF(Delay!P8="","",Fee*$A8+B$3*Delay!P8) -> 18.941026 | C8: =IF(Delay!R8="","",Fee*$A8+C$3*Delay!R8) -> 17.764603 | D8: =IF(Delay!T8="","",Fee*$A8+D$3*Delay!T8) -> 16.68563 | E8: =IF(Delay!P8="","",Fee*$A8+E$3*Delay!P8) -> 74.414106 | F8: =IF(Delay!R8="","",Fee*$A8+F$3*Delay!R8) -> 69.708413 | G8: =IF(Delay!T8="","",Fee*$A8+G$3*Delay!T8) -> 65.392519
A9: =Quantiles!A9 -> 20 | B9: =IF(Delay!P9="","",Fee*$A9+B$3*Delay!P9) -> 18.058302 | C9: =IF(Delay!R9="","",Fee*$A9+C$3*Delay!R9) -> 16.874714 | D9: =IF(Delay!T9="","",Fee*$A9+D$3*Delay!T9) -> 15.847266 | E9: =IF(Delay!P9="","",Fee*$A9+E$3*Delay!P9) -> 70.433207 | F9: =IF(Delay!R9="","",Fee*$A9+F$3*Delay!R9) -> 65.698854 | G9: =IF(Delay!T9="","",Fee*$A9+G$3*Delay!T9) -> 61.589066
A10: =Quantiles!A10 -> 25 | B10: =IF(Delay!P10="","",Fee*$A10+B$3*Delay!P10) -> 17.203903 | C10: =IF(Delay!R10="","",Fee*$A10+C$3*Delay!R10) -> 16.01796 | D10: =IF(Delay!T10="","",Fee*$A10+D$3*Delay!T10) -> 15.035163 | E10: =IF(Delay!P10="","",Fee*$A10+E$3*Delay!P10) -> 66.565614 | F10: =IF(Delay!R10="","",Fee*$A10+F$3*Delay!R10) -> 61.821839 | G10: =IF(Delay!T10="","",Fee*$A10+G$3*Delay!T10) -> 57.890654
A11: =Quantiles!A11 -> 30 | B11: =IF(Delay!P11="","",Fee*$A11+B$3*Delay!P11) -> 16.361501 | C11: =IF(Delay!R11="","",Fee*$A11+C$3*Delay!R11) -> 15.215035 | D11: =IF(Delay!T11="","",Fee*$A11+D$3*Delay!T11) -> 14.217649 | E11: =IF(Delay!P11="","",Fee*$A11+E$3*Delay!P11) -> 62.746004 | F11: =IF(Delay!R11="","",Fee*$A11+F$3*Delay!R11) -> 58.160139 | G11: =IF(Delay!T11="","",Fee*$A11+G$3*Delay!T11) -> 54.170598
A12: =Quantiles!A12 -> 35 | B12: =IF(Delay!P12="","",Fee*$A12+B$3*Delay!P12) -> 15.515875 | C12: =IF(Delay!R12="","",Fee*$A12+C$3*Delay!R12) -> 14.43815 | D12: =IF(Delay!T12="","",Fee*$A12+D$3*Delay!T12) -> 13.451463 | E12: =IF(Delay!P12="","",Fee*$A12+E$3*Delay!P12) -> 58.913502 | F12: =IF(Delay!R12="","",Fee*$A12+F$3*Delay!R12) -> 54.602602 | G12: =IF(Delay!T12="","",Fee*$A12+G$3*Delay!T12) -> 50.655854
A13: =Quantiles!A13 -> 40 | B13: =IF(Delay!P13="","",Fee*$A13+B$3*Delay!P13) -> 14.740476 | C13: =IF(Delay!R13="","",Fee*$A13+C$3*Delay!R13) -> 13.626419 | D13: =IF(Delay!T13="","",Fee*$A13+D$3*Delay!T13) -> 12.770644 | E13: =IF(Delay!P13="","",Fee*$A13+E$3*Delay!P13) -> 55.361904 | F13: =IF(Delay!R13="","",Fee*$A13+F$3*Delay!R13) -> 50.905677 | G13: =IF(Delay!T13="","",Fee*$A13+G$3*Delay!T13) -> 47.482574
A14: =Quantiles!A14 -> 45 | B14: =IF(Delay!P14="","",Fee*$A14+B$3*Delay!P14) -> 14.014354 | C14: =IF(Delay!R14="","",Fee*$A14+C$3*Delay!R14) -> 12.960035 | D14: =IF(Delay!T14="","",Fee*$A14+D$3*Delay!T14) -> 12.096659 | E14: =IF(Delay!P14="","",Fee*$A14+E$3*Delay!P14) -> 52.007416 | F14: =IF(Delay!R14="","",Fee*$A14+F$3*Delay!R14) -> 47.79014 | G14: =IF(Delay!T14="","",Fee*$A14+G$3*Delay!T14) -> 44.336635
A15: =Quantiles!A15 -> 50 | B15: =IF(Delay!P15="","",Fee*$A15+B$3*Delay!P15) -> 13.277455 | C15: =IF(Delay!R15="","",Fee*$A15+C$3*Delay!R15) -> 12.303905 | D15: =IF(Delay!T15="","",Fee*$A15+D$3*Delay!T15) -> 11.498926 | E15: =IF(Delay!P15="","",Fee*$A15+E$3*Delay!P15) -> 48.60982 | F15: =IF(Delay!R15="","",Fee*$A15+F$3*Delay!R15) -> 44.715619 | G15: =IF(Delay!T15="","",Fee*$A15+G$3*Delay!T15) -> 41.495704
A16: =Quantiles!A16 -> 55 | B16: =IF(Delay!P16="","",Fee*$A16+B$3*Delay!P16) -> 12.593976 | C16: =IF(Delay!R16="","",Fee*$A16+C$3*Delay!R16) -> 11.698485 | D16: =IF(Delay!T16="","",Fee*$A16+D$3*Delay!T16) -> 10.944872 | E16: =IF(Delay!P16="","",Fee*$A16+E$3*Delay!P16) -> 45.425903 | F16: =IF(Delay!R16="","",Fee*$A16+F$3*Delay!R16) -> 41.84394 | G16: =IF(Delay!T16="","",Fee*$A16+G$3*Delay!T16) -> 38.829487
... A85: =Quantiles!A85 -> 400 | B85: =IF(Delay!P85="","",Fee*$A85+B$3*Delay!P85) -> 14.648551 | C85: =IF(Delay!R85="","",Fee*$A85+C$3*Delay!R85) -> 14.218431 | D85: =IF(Delay!T85="","",Fee*$A85+D$3*Delay!T85) -> 13.836092 | E85: =IF(Delay!P85="","",Fee*$A85+E$3*Delay!P85) -> 22.594202 | F85: =IF(Delay!R85="","",Fee*$A85+F$3*Delay!R85) -> 20.873723 | G85: =IF(Delay!T85="","",Fee*$A85+G$3*Delay!T85) -> 19.344368
A88: Summary | B88: Least cost | C88: Its line | D88: Price ($m a point)
A89: $4 million a quarter, appetite 4.5% | B89: =MIN(B5:B85) -> 7.973004 | C89: =INDEX($A$5:$A$85,MATCH(B89,B5:B85,0)) -> 140
A90: $4 million a quarter, appetite 5.0% | B90: =MIN(C5:C85) -> 7.5246248 | C90: =INDEX($A$5:$A$85,MATCH(B90,C5:C85,0)) -> 140 | D90: =B89-B91 -> 0.9062888
A91: $4 million a quarter, appetite 5.5% | B91: =MIN(D5:D85) -> 7.0667152 | C91: =INDEX($A$5:$A$85,MATCH(B91,D5:D85,0)) -> 140
A92: $16 million a quarter, appetite 4.5% | B92: =MIN(E5:E85) -> 17.331834 | C92: =INDEX($A$5:$A$85,MATCH(B92,E5:E85,0)) -> 190
A93: $16 million a quarter, appetite 5.0% | B93: =MIN(F5:F85) -> 15.512875 | C93: =INDEX($A$5:$A$85,MATCH(B93,F5:F85,0)) -> 195 | D93: =B92-B94 -> 3.4219778
A94: $16 million a quarter, appetite 5.5% | B94: =MIN(G5:G85) -> 13.909856 | C94: =INDEX($A$5:$A$85,MATCH(B94,G5:G85,0)) -> 190
A96: Online Appendix 15.B.4: at $4 million a quarter, line 140, cost 7.52, price 0.91; at $16 million, line 195, cost 15.51, price 3.42 (at $8 million: line 170, price 1.81).

Sheet WeightSweep
A1: The frontier by weight sweeps: minimize cost + weight x odds (Theorem 15.5(ii); AXIOM Lab 1.15, step 4)
A2: Rows: the 95 frontier points by floors (1 to 24.5 percent in quarter points, from the Frontier sheet). Columns: weights in $ million per point of odds. A weight picks the point with the least weighted score; only points on the frontier's convex hull are ever picked.
A3: Weight ($ million a point) | C3: 0.05 | D3: 0.1 | E3: 0.15 | F3: 0.2 | G3: 0.25 | H3: 0.3 | I3: 0.35 | J3: 0.4 | K3: 0.45 | L3: 0.5 | M3: 0.55 | N3: 0.6 | O3: 0.65 | P3: 0.7 | Q3: 0.75 | R3: 0.8 | S3: 0.85 | T3: 0.9 | U3: 0.95 | V3: 1 | W3: 1.05 | X3: 1.1 | Y3: 1.15 | Z3: 1.2 | AA3: 1.25 | AB3: 1.3 | AC3: 1.35 | AD3: 1.4 | AE3: 1.45 | AF3: 1.5 | AG3: 1.55 | AH3: 1.6 | AI3: 1.65 | AJ3: 1.7 | AK3: 1.75 | AL3: 1.8 | AM3: 1.85 | AN3: 1.9 | AO3: 1.95 | AP3: 2 | AQ3: 2.05 | AR3: 2.1 | AS3: 2.15 | AT3: 2.2 | AU3: 2.25 | AV3: 2.3 | AW3: 2.35 | AX3: 2.4 | AY3: 2.45 | AZ3: 2.5 | BA3: 2.55 | BB3: 2.6 | BC3: 2.65 | BD3: 2.7 | BE3: 2.75 | BF3: 2.8 | BG3: 2.85 | BH3: 2.9 | BI3: 2.95 | BJ3: 3 | BK3: 3.05 | BL3: 3.1 | BM3: 3.15 | BN3: 3.2 | BO3: 3.25 | BP3: 3.3 | BQ3: 3.35 | BR3: 3.4 | BS3: 3.45 | BT3: 3.5 | BU3: 3.55 | BV3: 3.6 | BW3: 3.65 | BX3: 3.7 | BY3: 3.75 | BZ3: 3.8 | CA3: 3.85 | CB3: 3.9 | CC3: 3.95 | CD3: 4 | CE3: 4.05 | CF3: 4.1 | CG3: 4.15 | CH3: 4.2 | CI3: 4.25 | CJ3: 4.3 | CK3: 4.35 | CL3: 4.4 | CM3: 4.45 | CN3: 4.5 | CO3: 4.55 | CP3: 4.6 | CQ3: 4.65 | CR3: 4.7 | CS3: 4.75 | CT3: 4.8 | CU3: 4.85 | CV3: 4.9 | CW3: 4.95 | CX3: 5 | CY3: 5.05 | CZ3: 5.1 | DA3: 5.15 | DB3: 5.2 | DC3: 5.25 | DD3: 5.3 | DE3: 5.35 | DF3: 5.4 | DG3: 5.45 | DH3: 5.5 | DI3: 5.55 | DJ3: 5.6 | DK3: 5.65 | DL3: 5.7 | DM3: 5.75 | DN3: 5.8 | DO3: 5.85 | DP3: 5.9 | DQ3: 5.95 | DR3: 6 | DS3: 6.05 | DT3: 6.1 | DU3: 6.15 | DV3: 6.2 | DW3: 6.25 | DX3: 6.3 | DY3: 6.35 | DZ3: 6.4 | EA3: 6.45 | EB3: 6.5 | EC3: 6.55 | ED3: 6.6 | EE3: 6.65 | EF3: 6.7 | EG3: 6.75 | EH3: 6.8 | EI3: 6.85 | EJ3: 6.9 | EK3: 6.95 | EL3: 7 | EM3: 7.05 | EN3: 7.1 | EO3: 7.15 | EP3: 7.2 | EQ3: 7.25 | ER3: 7.3 | ES3: 7.35 | ET3: 7.4 | EU3: 7.45 | EV3: 7.5 | EW3: 7.55 | EX3: 7.6 | EY3: 7.65 | EZ3: 7.7 | FA3: 7.75 | FB3: 7.8 | FC3: 7.85 | FD3: 7.9 | FE3: 7.95 | FF3: 8 | FG3: 8.05 | FH3: 8.1 | FI3: 8.15 | FJ3: 8.2 | FK3: 8.25 | FL3: 8.3 | FM3: 8.35 | FN3: 8.4 | FO3: 8.45 | FP3: 8.5 | FQ3: 8.55 | FR3: 8.6 | FS3: 8.65 | FT3: 8.7 | FU3: 8.75 | FV3: 8.8 | FW3: 8.85 | FX3: 8.9 | FY3: 8.95 | FZ3: 9 | GA3: 9.05 | GB3: 9.1 | GC3: 9.15 | GD3: 9.2 | GE3: 9.25 | GF3: 9.3 | GG3: 9.35 | GH3: 9.4 | GI3: 9.45 | GJ3: 9.5 | GK3: 9.55 | GL3: 9.6 | GM3: 9.65 | GN3: 9.7 | GO3: 9.75 | GP3: 9.8 | GQ3: 9.85 | GR3: 9.9 | GS3: 9.95 | GT3: 10
A4: Least score | C4: =MIN(C7:C101) -> 1.3406424 | D4: =MIN(D7:D101) -> 2.5656424 | E4: =MIN(E7:E101) -> 3.7716922 | F4: =MIN(F7:F101) -> 4.9716922 | G4: =MIN(G7:G101) -> 5.9919117 | H4: =MIN(H7:H101) -> 6.7180034 | I4: =MIN(I7:I101) -> 7.35 | J4: =MIN(J7:J101) -> 7.95 | ... GT4: =MIN(GT7:GT101) -> 33.089332
A5: Appetite picked | C5: =INDEX($A$7:$A$101,MATCH(C4,C7:C101,0)) -> 0.245 | D5: =INDEX($A$7:$A$101,MATCH(D4,D7:D101,0)) -> 0.245 | E5: =INDEX($A$7:$A$101,MATCH(E4,E7:E101,0)) -> 0.24 | F5: =INDEX($A$7:$A$101,MATCH(F4,F7:F101,0)) -> 0.24 | G5: =INDEX($A$7:$A$101,MATCH(G4,G7:G101,0)) -> 0.1675 | H5: =INDEX($A$7:$A$101,MATCH(H4,H7:H101,0)) -> 0.1325 | I5: =INDEX($A$7:$A$101,MATCH(I4,I7:I101,0)) -> 0.12 | J5: =INDEX($A$7:$A$101,MATCH(J4,J7:J101,0)) -> 0.1125 | ... GT5: =INDEX($A$7:$A$101,MATCH(GT4,GT7:GT101,0)) -> 0.01
A6: Appetite | B6: Least cost | C6: score at 0.05 | D6: score at 0.10 | E6: score at 0.15 | F6: score at 0.20 | G6: score at 0.25 | H6: score at 0.30 | I6: score at 0.35 | J6: score at 0.40 | K6: score at 0.45 | L6: score at 0.50 | M6: score at 0.55 | N6: score at 0.60 | O6: score at 0.65 | P6: score at 0.70 | Q6: score at 0.75 | R6: score at 0.80 | S6: score at 0.85 | T6: score at 0.90 | U6: score at 0.95 | V6: score at 1.00 | W6: score at 1.05 | X6: score at 1.10 | Y6: score at 1.15 | Z6: score at 1.20 | AA6: score at 1.25 | AB6: score at 1.30 | AC6: score at 1.35 | AD6: score at 1.40 | AE6: score at 1.45 | AF6: score at 1.50 | AG6: score at 1.55 | AH6: score at 1.60 | AI6: score at 1.65 | AJ6: score at 1.70 | AK6: score at 1.75 | AL6: score at 1.80 | AM6: score at 1.85 | AN6: score at 1.90 | AO6: score at 1.95 | AP6: score at 2.00 | AQ6: score at 2.05 | AR6: score at 2.10 | AS6: score at 2.15 | AT6: score at 2.20 | AU6: score at 2.25 | AV6: score at 2.30 | AW6: score at 2.35 | AX6: score at 2.40 | AY6: score at 2.45 | AZ6: score at 2.50 | BA6: score at 2.55 | BB6: score at 2.60 | BC6: score at 2.65 | BD6: score at 2.70 | BE6: score at 2.75 | BF6: score at 2.80 | BG6: score at 2.85 | BH6: score at 2.90 | BI6: score at 2.95 | BJ6: score at 3.00 | BK6: score at 3.05 | BL6: score at 3.10 | BM6: score at 3.15 | BN6: score at 3.20 | BO6: score at 3.25 | BP6: score at 3.30 | BQ6: score at 3.35 | BR6: score at 3.40 | BS6: score at 3.45 | BT6: score at 3.50 | BU6: score at 3.55 | BV6: score at 3.60 | BW6: score at 3.65 | BX6: score at 3.70 | BY6: score at 3.75 | BZ6: score at 3.80 | CA6: score at 3.85 | CB6: score at 3.90 | CC6: score at 3.95 | CD6: score at 4.00 | CE6: score at 4.05 | CF6: score at 4.10 | CG6: score at 4.15 | CH6: score at 4.20 | CI6: score at 4.25 | CJ6: score at 4.30 | CK6: score at 4.35 | CL6: score at 4.40 | CM6: score at 4.45 | CN6: score at 4.50 | CO6: score at 4.55 | CP6: score at 4.60 | CQ6: score at 4.65 | CR6: score at 4.70 | CS6: score at 4.75 | CT6: score at 4.80 | CU6: score at 4.85 | CV6: score at 4.90 | CW6: score at 4.95 | CX6: score at 5.00 | CY6: score at 5.05 | CZ6: score at 5.10 | DA6: score at 5.15 | DB6: score at 5.20 | DC6: score at 5.25 | DD6: score at 5.30 | DE6: score at 5.35 | DF6: score at 5.40 | DG6: score at 5.45 | DH6: score at 5.50 | DI6: score at 5.55 | DJ6: score at 5.60 | DK6: score at 5.65 | DL6: score at 5.70 | DM6: score at 5.75 | DN6: score at 5.80 | DO6: score at 5.85 | DP6: score at 5.90 | DQ6: score at 5.95 | DR6: score at 6.00 | DS6: score at 6.05 | DT6: score at 6.10 | DU6: score at 6.15 | DV6: score at 6.20 | DW6: score at 6.25 | DX6: score at 6.30 | DY6: score at 6.35 | DZ6: score at 6.40 | EA6: score at 6.45 | EB6: score at 6.50 | EC6: score at 6.55 | ED6: score at 6.60 | EE6: score at 6.65 | EF6: score at 6.70 | EG6: score at 6.75 | EH6: score at 6.80 | EI6: score at 6.85 | EJ6: score at 6.90 | EK6: score at 6.95 | EL6: score at 7.00 | EM6: score at 7.05 | EN6: score at 7.10 | EO6: score at 7.15 | EP6: score at 7.20 | EQ6: score at 7.25 | ER6: score at 7.30 | ES6: score at 7.35 | ET6: score at 7.40 | EU6: score at 7.45 | EV6: score at 7.50 | EW6: score at 7.55 | EX6: score at 7.60 | EY6: score at 7.65 | EZ6: score at 7.70 | FA6: score at 7.75 | FB6: score at 7.80 | FC6: score at 7.85 | FD6: score at 7.90 | FE6: score at 7.95 | FF6: score at 8.00 | FG6: score at 8.05 | FH6: score at 8.10 | FI6: score at 8.15 | FJ6: score at 8.20 | FK6: score at 8.25 | FL6: score at 8.30 | FM6: score at 8.35 | FN6: score at 8.40 | FO6: score at 8.45 | FP6: score at 8.50 | FQ6: score at 8.55 | FR6: score at 8.60 | FS6: score at 8.65 | FT6: score at 8.70 | FU6: score at 8.75 | FV6: score at 8.80 | FW6: score at 8.85 | FX6: score at 8.90 | FY6: score at 8.95 | FZ6: score at 9.00 | GA6: score at 9.05 | GB6: score at 9.10 | GC6: score at 9.15 | GD6: score at 9.20 | GE6: score at 9.25 | GF6: score at 9.30 | GG6: score at 9.35 | GH6: score at 9.40 | GI6: score at 9.45 | GJ6: score at 9.50 | GK6: score at 9.55 | GL6: score at 9.60 | GM6: score at 9.65 | GN6: score at 9.70 | GO6: score at 9.75 | GP6: score at 9.80 | GQ6: score at 9.85 | GR6: score at 9.90 | GS6: score at 9.95 | GT6: score at 10.00
A7: =Frontier!A5 -> 0.01 | B7: =Frontier!B5 -> 23.089332 | C7: =$B7+C$3*100*$A7 -> 23.139332 | D7: =$B7+D$3*100*$A7 -> 23.189332 | E7: =$B7+E$3*100*$A7 -> 23.239332 | F7: =$B7+F$3*100*$A7 -> 23.289332 | G7: =$B7+G$3*100*$A7 -> 23.339332 | H7: =$B7+H$3*100*$A7 -> 23.389332 | I7: =$B7+I$3*100*$A7 -> 23.439332 | J7: =$B7+J$3*100*$A7 -> 23.489332 | ... GT7: =$B7+GT$3*100*$A7 -> 33.089332
A8: =Frontier!A6 -> 0.0125 | B8: =Frontier!B6 -> 21.337606 | C8: =$B8+C$3*100*$A8 -> 21.400106 | D8: =$B8+D$3*100*$A8 -> 21.462606 | E8: =$B8+E$3*100*$A8 -> 21.525106 | F8: =$B8+F$3*100*$A8 -> 21.587606 | G8: =$B8+G$3*100*$A8 -> 21.650106 | H8: =$B8+H$3*100*$A8 -> 21.712606 | I8: =$B8+I$3*100*$A8 -> 21.775106 | J8: =$B8+J$3*100*$A8 -> 21.837606 | ... GT8: =$B8+GT$3*100*$A8 -> 33.837606
A9: =Frontier!A7 -> 0.015 | B9: =Frontier!B7 -> 20.122368 | C9: =$B9+C$3*100*$A9 -> 20.197368 | D9: =$B9+D$3*100*$A9 -> 20.272368 | E9: =$B9+E$3*100*$A9 -> 20.347368 | F9: =$B9+F$3*100*$A9 -> 20.422368 | G9: =$B9+G$3*100*$A9 -> 20.497368 | H9: =$B9+H$3*100*$A9 -> 20.572368 | I9: =$B9+I$3*100*$A9 -> 20.647368 | J9: =$B9+J$3*100*$A9 -> 20.722368 | ... GT9: =$B9+GT$3*100*$A9 -> 35.122368
A10: =Frontier!A8 -> 0.0175 | B10: =Frontier!B8 -> 18.880368 | C10: =$B10+C$3*100*$A10 -> 18.967868 | D10: =$B10+D$3*100*$A10 -> 19.055368 | E10: =$B10+E$3*100*$A10 -> 19.142868 | F10: =$B10+F$3*100*$A10 -> 19.230368 | G10: =$B10+G$3*100*$A10 -> 19.317868 | H10: =$B10+H$3*100*$A10 -> 19.405368 | I10: =$B10+I$3*100*$A10 -> 19.492868 | J10: =$B10+J$3*100*$A10 -> 19.580368 | ... GT10: =$B10+GT$3*100*$A10 -> 36.380368
A11: =Frontier!A9 -> 0.02 | B11: =Frontier!B9 -> 17.860851 | C11: =$B11+C$3*100*$A11 -> 17.960851 | D11: =$B11+D$3*100*$A11 -> 18.060851 | E11: =$B11+E$3*100*$A11 -> 18.160851 | F11: =$B11+F$3*100*$A11 -> 18.260851 | G11: =$B11+G$3*100*$A11 -> 18.360851 | H11: =$B11+H$3*100*$A11 -> 18.460851 | I11: =$B11+I$3*100*$A11 -> 18.560851 | J11: =$B11+J$3*100*$A11 -> 18.660851 | ... GT11: =$B11+GT$3*100*$A11 -> 37.860851
A12: =Frontier!A10 -> 0.0225 | B12: =Frontier!B10 -> 16.870376 | C12: =$B12+C$3*100*$A12 -> 16.982876 | D12: =$B12+D$3*100*$A12 -> 17.095376 | E12: =$B12+E$3*100*$A12 -> 17.207876 | F12: =$B12+F$3*100*$A12 -> 17.320376 | G12: =$B12+G$3*100*$A12 -> 17.432876 | H12: =$B12+H$3*100*$A12 -> 17.545376 | I12: =$B12+I$3*100*$A12 -> 17.657876 | J12: =$B12+J$3*100*$A12 -> 17.770376 | ... GT12: =$B12+GT$3*100*$A12 -> 39.370376
A13: =Frontier!A11 -> 0.025 | B13: =Frontier!B11 -> 16.079718 | C13: =$B13+C$3*100*$A13 -> 16.204718 | D13: =$B13+D$3*100*$A13 -> 16.329718 | E13: =$B13+E$3*100*$A13 -> 16.454718 | F13: =$B13+F$3*100*$A13 -> 16.579718 | G13: =$B13+G$3*100*$A13 -> 16.704718 | H13: =$B13+H$3*100*$A13 -> 16.829718 | I13: =$B13+I$3*100*$A13 -> 16.954718 | J13: =$B13+J$3*100*$A13 -> 17.079718 | ... GT13: =$B13+GT$3*100*$A13 -> 41.079718
A14: =Frontier!A12 -> 0.0275 | B14: =Frontier!B12 -> 15.338772 | C14: =$B14+C$3*100*$A14 -> 15.476272 | D14: =$B14+D$3*100*$A14 -> 15.613772 | E14: =$B14+E$3*100*$A14 -> 15.751272 | F14: =$B14+F$3*100*$A14 -> 15.888772 | G14: =$B14+G$3*100*$A14 -> 16.026272 | H14: =$B14+H$3*100*$A14 -> 16.163772 | I14: =$B14+I$3*100*$A14 -> 16.301272 | J14: =$B14+J$3*100*$A14 -> 16.438772 | ... GT14: =$B14+GT$3*100*$A14 -> 42.838772
A15: =Frontier!A13 -> 0.03 | B15: =Frontier!B13 -> 14.684124 | C15: =$B15+C$3*100*$A15 -> 14.834124 | D15: =$B15+D$3*100*$A15 -> 14.984124 | E15: =$B15+E$3*100*$A15 -> 15.134124 | F15: =$B15+F$3*100*$A15 -> 15.284124 | G15: =$B15+G$3*100*$A15 -> 15.434124 | H15: =$B15+H$3*100*$A15 -> 15.584124 | I15: =$B15+I$3*100*$A15 -> 15.734124 | J15: =$B15+J$3*100*$A15 -> 15.884124 | ... GT15: =$B15+GT$3*100*$A15 -> 44.684124
A16: =Frontier!A14 -> 0.0325 | B16: =Frontier!B14 -> 14.077963 | C16: =$B16+C$3*100*$A16 -> 14.240463 | D16: =$B16+D$3*100*$A16 -> 14.402963 | E16: =$B16+E$3*100*$A16 -> 14.565463 | F16: =$B16+F$3*100*$A16 -> 14.727963 | G16: =$B16+G$3*100*$A16 -> 14.890463 | H16: =$B16+H$3*100*$A16 -> 15.052963 | I16: =$B16+I$3*100*$A16 -> 15.215463 | J16: =$B16+J$3*100*$A16 -> 15.377963 | ... GT16: =$B16+GT$3*100*$A16 -> 46.577963
A17: =Frontier!A15 -> 0.035 | B17: =Frontier!B15 -> 13.476076 | C17: =$B17+C$3*100*$A17 -> 13.651076 | D17: =$B17+D$3*100*$A17 -> 13.826076 | E17: =$B17+E$3*100*$A17 -> 14.001076 | F17: =$B17+F$3*100*$A17 -> 14.176076 | G17: =$B17+G$3*100*$A17 -> 14.351076 | H17: =$B17+H$3*100*$A17 -> 14.526076 | I17: =$B17+I$3*100*$A17 -> 14.701076 | J17: =$B17+J$3*100*$A17 -> 14.876076 | ... GT17: =$B17+GT$3*100*$A17 -> 48.476076
A18: =Frontier!A16 -> 0.0375 | B18: =Frontier!B16 -> 12.906277 | C18: =$B18+C$3*100*$A18 -> 13.093777 | D18: =$B18+D$3*100*$A18 -> 13.281277 | E18: =$B18+E$3*100*$A18 -> 13.468777 | F18: =$B18+F$3*100*$A18 -> 13.656277 | G18: =$B18+G$3*100*$A18 -> 13.843777 | H18: =$B18+H$3*100*$A18 -> 14.031277 | I18: =$B18+I$3*100*$A18 -> 14.218777 | J18: =$B18+J$3*100*$A18 -> 14.406277 | ... GT18: =$B18+GT$3*100*$A18 -> 50.406277
... A101: =Frontier!A99 -> 0.245 | B101: =Frontier!B99 -> 0.11564236 | C101: =$B101+C$3*100*$A101 -> 1.3406424 | D101: =$B101+D$3*100*$A101 -> 2.5656424 | E101: =$B101+E$3*100*$A101 -> 3.7906424 | F101: =$B101+F$3*100*$A101 -> 5.0156424 | G101: =$B101+G$3*100*$A101 -> 6.2406424 | H101: =$B101+H$3*100*$A101 -> 7.4656424 | I101: =$B101+I$3*100*$A101 -> 8.6906424 | J101: =$B101+J$3*100*$A101 -> 9.9156424 | ... GT101: =$B101+GT$3*100*$A101 -> 245.11564
A104: Floors against weights | B104: Value | C104: Reading
A105: Frontier points traced by floors | B105: =COUNT(B7:B101) -> 95 | C105: every one
A106: Distinct points picked by some weight | B106: =SUMPRODUCT(1/COUNTIF($C$5:$GT$5,$C$5:$GT$5)) -> 30 | C106: only the convex hull's points
A107: Lowest weight picking 4.75% | B107: =_xlfn.MINIFS($C$3:$GT$3,$C$5:$GT$5,0.0475) -> 1.75
A108: Highest weight picking 4.75% | B108: =_xlfn.MAXIFS($C$3:$GT$3,$C$5:$GT$5,0.0475) -> 1.95
A109: Weights picking 5.25% | B109: =_xlfn.MAXIFS($C$3:$GT$3,$C$5:$GT$5,0.0525) -> 1.7
A110: Weights picking the board's 5% itself | B110: =COUNTIF($C$5:$GT$5,0.05) -> 0 | C110: none: 5% sits in a small dent
A111: The 5% point above the chord from 4.75 to 5.25% ($ million) | B111: =B23-(B22+B24)/2 -> 0.001944157
A112: Slope of that chord ($ million a point) | B112: =(B22-B24)/0.5 -> 1.7497673 | C112: the exchange rate a weight sweep sees near 5%

Sheet Audit
A1: Audit before optimizing: consistency, viability and the minimal infeasible set (Theorem 15.2; Proposition 15.4; AXIOM Lab 1.15, step 2)
A3: Consistency: Chapter 13's joint check (draw + buffer <= 270) | B3: Draw | C3: Buffer | D3: Total | E3: Passes?
A4: No levers | B4: =Plan!B21 -> 138.04962 | C4: =Plan!B30 -> 186.86698 | D4: =B4+C4 -> 324.91659 | E4: =IF(D4<=Pool,"passes","fails") -> fails
A5: Chapter 8's package | B5: =Plan!B22 -> 89.026083 | C5: =MAX(Plan!B30-100,0) -> 86.866976 | D5: =B5+C5 -> 175.89306 | E5: =IF(D5<=Pool,"passes","fails") -> passes
A6: The cheapest package at 5% | B6: =Plan!B24 -> 121.63437 | C6: =MAX(Plan!B30-Solve!B5,0) -> 16.866976 | D6: =B6+C6 -> 138.50134 | E6: =IF(D6<=Pool,"passes","fails") -> passes
A8: Viability: odds of a breach (engine) | B8: Worst single quarter | C8: Some quarter of the program
A9: No levers | B9: 0.10332 | C9: 0.24622
A10: Cheapest at 5% | B10: 0.00971 | C10: 0.05
A11: The appetite is a promise about the whole path: a quarter-by-quarter reading certifies nothing about the program (Theorem 14.5(iv)).
A13: The capped levers | B13: Value | C13: Reading
A14: Cap on the line ($ million) | B14: 100 | C14: the bank
A15: Cap on the delay (quarters) | B15: 2 | C15: the transformation office
A16: Least odds within the caps: the corner (engine) | B16: 0.03003 | C16: the odds fall with both levers: 3.0 percent
A17: Appetite tightened below 3 percent | B17: 0.02 | C17: AXIOM Lab 1.15, step 2
A18: Delay the line at its cap needs (quarters) | B18: =INDEX(Delay!$F$5:$F$85,MATCH(B14,Cost!$A$5:$A$85,0)) -> 2.6059866
A19: Feasible within the caps? | B19: =IF(AND(B16<=B17,B18<=B15),"yes","no: infeasible") -> no: infeasible
A21: Drop the line cap: least cost with the delay capped | B21: =_xlfn.MINIFS(Cost!$F$5:$F$85,Delay!$F$5:$F$85,"<="&B15) -> 17.860851
A22: its line | B22: =INDEX(Cost!$A$5:$A$85,MATCH(B21,Cost!$F$5:$F$85,0)) -> 170
A23: Drop the delay cap: least cost with the line capped | B23: =_xlfn.MINIFS(Cost!$F$5:$F$85,Cost!$A$5:$A$85,"<="&B14) -> 23.847893
A24: its delay | B24: =INDEX(Delay!$F$5:$F$85,MATCH(B23,Cost!$F$5:$F$85,0)) -> 2.6059866
A25: Drop the appetite: the corner's cost | B25: =Fee*B14+Vq*B15 -> 19 | C25: at 3.0 percent
A26: Minimal infeasible set | B26: line cap, delay cap, appetite | C26: drop any one and the rest can hold
A28: Quarter K | B28: Odds of a breach by quarter K at the corner (engine) | C28: Within the tightened appetite?
A29: 1 | B29: 0.0001 | C29: =IF(B29<=$B$17,"yes","no") -> yes
A30: 2 | B30: 0.00056 | C30: =IF(B30<=$B$17,"yes","no") -> yes
A31: 3 | B31: 0.00199 | C31: =IF(B31<=$B$17,"yes","no") -> yes
A32: 4 | B32: 0.00456 | C32: =IF(B32<=$B$17,"yes","no") -> yes
A33: 5 | B33: 0.00798 | C33: =IF(B33<=$B$17,"yes","no") -> yes
A34: 6 | B34: 0.01121 | C34: =IF(B34<=$B$17,"yes","no") -> yes
A35: 7 | B35: 0.01503 | C35: =IF(B35<=$B$17,"yes","no") -> yes
A36: 8 | B36: 0.01853 | C36: =IF(B36<=$B$17,"yes","no") -> yes
A37: 9 | B37: 0.02201 | C37: =IF(B37<=$B$17,"yes","no") -> no
A38: 10 | B38: 0.02499 | C38: =IF(B38<=$B$17,"yes","no") -> no
A39: 11 | B39: 0.02774 | C39: =IF(B39<=$B$17,"yes","no") -> no
A40: 12 | B40: 0.03003 | C40: =IF(B40<=$B$17,"yes","no") -> no
A42: Emptying date: the last quarter the capped levers honor the tightened appetite | B42: =COUNTIF(B29:B40,"<="&B17) -> 8 | C42: Theorem 15.2(iii): an empty region is witnessed by the periods for which the declaration can be honored.

Sheet Allocation
A1: A small allocation: the corner and its multipliers (Theorem 15.3; Equation 15.4; AXIOM Lab 1.15, step 3)
A2: The preloaded allocation instance of AXIOM Lab 1.15, step 3. The book describes it in words and prints no data; these data are this workbook's declaration, not the book's. Split a budget across three capital stocks to maximize Y = TFP x K_F^a_F x K_H^a_H x K_T^a_T of the stocks after investment, every investment nonnegative.
A4: Quantity | B4: Financial | C4: Human | D4: Technological
A5: Stock | B5: 40 | C5: 30 | D5: 20
A6: Share kept over the period | B6: 0.98 | C6: 0.94 | D6: 0.9
A7: Exponent a | B7: 0.3 | C7: 0.4 | D7: 0.3
A8: Stock before investment | B8: =B5*B6 -> 39.2 | C8: =C5*C6 -> 28.2 | D8: =D5*D6 -> 18
A9: Total factor productivity; budget | B9: 10 | C9: 6
A11: Unconstrained first-order point: a (sum of stocks + budget) - stock | B11: =B7*(SUM($B$8:$D$8)+$C$9)-B8 -> -11.78 | C11: =C7*(SUM($B$8:$D$8)+$C$9)-C8 -> 8.36 | D11: =D7*(SUM($B$8:$D$8)+$C$9)-D8 -> 9.42
A12: Corner: financial investment held at its floor | B12: 0 | C12: =C7/($C$7+$D$7)*($C$8+$D$8+$C$9-$B$12)-C8 -> 1.6285714 | D12: =D7/($C$7+$D$7)*($C$8+$D$8+$C$9-$B$12)-D8 -> 4.3714286
A13: Stock after investment at the corner | B13: =B8+B12 -> 39.2 | C13: =C8+C12 -> 29.828571 | D13: =D8+D12 -> 22.371429
A14: Output at the corner | B14: =$B$9*B13^B7*C13^C7*D13^D7 -> 296.99348
A15: Output of an even split (2, 2, 2) | B15: =$B$9*(B8+2)^B7*(C8+2)^C7*(D8+2)^D7 -> 292.94153
A16: Marginal output of each form: a Y / stock | B16: =B7*$B$14/B13 -> 2.2729093 | C16: =C7*$B$14/C13 -> 3.9826712 | D16: =D7*$B$14/D13 -> 3.9826712
A17: The budget's multiplier lambda (every funded form earns it) | B17: =C16 -> 3.9826712
A18: Nonnegativity's multiplier mu_F = lambda - marginal output of financial capital | B18: =B17-B16 -> 1.7097619
A19: Funded forms earn the same marginal output? | B19: =IF(ABS(C16-D16)<0.000000001,"yes","no") -> yes
A21: Theorem 15.3(iii): a budget larger by 1
A22: Stocks after investment | B22: =B8 -> 39.2 | C22: =C7/($C$7+$D$7)*($C$8+$D$8+$C$9+1) -> 30.4 | D22: =D7/($C$7+$D$7)*($C$8+$D$8+$C$9+1) -> 22.8
A23: Gain in output (at most lambda) | B23: =$B$9*B22^B7*C22^C7*D22^D7-B14 -> 3.9713207
A24: Forcing 1 into financial capital: stocks after investment | B24: =B8+1 -> 40.2 | C24: =C7/($C$7+$D$7)*($C$8+$D$8+$C$9-1) -> 29.257143 | D24: =D7/($C$7+$D$7)*($C$8+$D$8+$C$9-1) -> 21.942857
A25: Loss in output (at least mu_F) | B25: =B14-$B$9*B24^B7*C24^C7*D24^D7 -> 1.7716068

Sheet RollingPlans
A1: Rolling plans need a terminal condition (Theorem 15.4(iv); Figure 15.1; Online Appendix 15.B.2)
A2: The runway of Chapter 14 after its $30 million repair. Each quarter a one-quarter window maximizes the burn kept. Stopping a burn r, cutting at most 10 a quarter, needs N(r) = sum of max(r - 10i, 0) of cash.
A4: Cash above the floor at the start | B4: 150
A5: Burn a quarter at the start | B5: 50
A6: Largest cut a quarter | B6: 10
A7: Cash a burn of 50 needs, N(50) | B7: =SUMPRODUCT((B5-B6*{0,1,2,3,4,5,6})*((B5-B6*{0,1,2,3,4,5,6})>0)) -> 150
A8: The start lies in the kernel {cash >= N(burn)}? | B8: =IF(B4>=B7,"yes, on its edge","no") -> yes, on its edge
A10: Quarter | B10: No end condition: cash | C10: Burn | D10: With the kernel as end condition: cash | E10: Burn
A11: 0 | B11: =B4 -> 150 | C11: =B5 -> 50 | D11: =B4 -> 150 | E11: =B5 -> 50 | J11: Candidate burn | K11: Cash it needs, N
A12: 1 | B12: =IF(B11="","",IF(B11<0,"",B11-C11)) -> 100 | C12: =IF(B12="","",C11) -> 50 | D12: =D11-E11 -> 100 | E12: =_xlfn.MAXIFS($J$12:$J$112,$J$12:$J$112,">="&MAX(E11-$B$6,0),$J$12:$J$112,"<="&E11,$K$12:$K$112,"<="&D12) -> 40 | J12: 0 | K12: =SUMPRODUCT((J12-$B$6*{0,1,2,3,4,5,6})*((J12-$B$6*{0,1,2,3,4,5,6})>0)) -> 0
A13: 2 | B13: =IF(B12="","",IF(B12<0,"",B12-C12)) -> 50 | C13: =IF(B13="","",C12) -> 50 | D13: =D12-E12 -> 60 | E13: =_xlfn.MAXIFS($J$12:$J$112,$J$12:$J$112,">="&MAX(E12-$B$6,0),$J$12:$J$112,"<="&E12,$K$12:$K$112,"<="&D13) -> 30 | J13: 0.5 | K13: =SUMPRODUCT((J13-$B$6*{0,1,2,3,4,5,6})*((J13-$B$6*{0,1,2,3,4,5,6})>0)) -> 0.5
A14: 3 | B14: =IF(B13="","",IF(B13<0,"",B13-C13)) -> 0 | C14: =IF(B14="","",C13) -> 50 | D14: =D13-E13 -> 30 | E14: =_xlfn.MAXIFS($J$12:$J$112,$J$12:$J$112,">="&MAX(E13-$B$6,0),$J$12:$J$112,"<="&E13,$K$12:$K$112,"<="&D14) -> 20 | J14: 1 | K14: =SUMPRODUCT((J14-$B$6*{0,1,2,3,4,5,6})*((J14-$B$6*{0,1,2,3,4,5,6})>0)) -> 1
A15: 4 | B15: =IF(B14="","",IF(B14<0,"",B14-C14)) -> -50 | C15: =IF(B15="","",C14) -> 50 | D15: =D14-E14 -> 10 | E15: =_xlfn.MAXIFS($J$12:$J$112,$J$12:$J$112,">="&MAX(E14-$B$6,0),$J$12:$J$112,"<="&E14,$K$12:$K$112,"<="&D15) -> 10 | J15: 1.5 | K15: =SUMPRODUCT((J15-$B$6*{0,1,2,3,4,5,6})*((J15-$B$6*{0,1,2,3,4,5,6})>0)) -> 1.5
A16: 5 | B16: =IF(B15="","",IF(B15<0,"",B15-C15)) | C16: =IF(B16="","",C15) | D16: =D15-E15 -> 0 | E16: =_xlfn.MAXIFS($J$12:$J$112,$J$12:$J$112,">="&MAX(E15-$B$6,0),$J$12:$J$112,"<="&E15,$K$12:$K$112,"<="&D16) -> 0 | J16: 2 | K16: =SUMPRODUCT((J16-$B$6*{0,1,2,3,4,5,6})*((J16-$B$6*{0,1,2,3,4,5,6})>0)) -> 2
A17: 6 | B17: =IF(B16="","",IF(B16<0,"",B16-C16)) | C17: =IF(B17="","",C16) | D17: =D16-E16 -> 0 | E17: =_xlfn.MAXIFS($J$12:$J$112,$J$12:$J$112,">="&MAX(E16-$B$6,0),$J$12:$J$112,"<="&E16,$K$12:$K$112,"<="&D17) -> 0 | J17: 2.5 | K17: =SUMPRODUCT((J17-$B$6*{0,1,2,3,4,5,6})*((J17-$B$6*{0,1,2,3,4,5,6})>0)) -> 2.5
J18: 3 | K18: =SUMPRODUCT((J18-$B$6*{0,1,2,3,4,5,6})*((J18-$B$6*{0,1,2,3,4,5,6})>0)) -> 3
A19: No end condition: the quarter cash runs out | B19: =COUNTIF(B11:B17,">=0") -> 4 | C19: quarter 4 | J19: 3.5 | K19: =SUMPRODUCT((J19-$B$6*{0,1,2,3,4,5,6})*((J19-$B$6*{0,1,2,3,4,5,6})>0)) -> 3.5
A20: With the kernel: the quarter the burn stops | B20: =MATCH(0,E11:E17,0)-1 -> 5 | C20: quarter 5 | J20: 4 | K20: =SUMPRODUCT((J20-$B$6*{0,1,2,3,4,5,6})*((J20-$B$6*{0,1,2,3,4,5,6})>0)) -> 4
J21: 4.5 | K21: =SUMPRODUCT((J21-$B$6*{0,1,2,3,4,5,6})*((J21-$B$6*{0,1,2,3,4,5,6})>0)) -> 4.5
A22: From $120 million: in the kernel? | B22: =IF(120>=B7,"yes","no: no window with the end condition is feasible") -> no: no window with the end condition is feasible | C22: Chapter 14's runway trap | J22: 5 | K22: =SUMPRODUCT((J22-$B$6*{0,1,2,3,4,5,6})*((J22-$B$6*{0,1,2,3,4,5,6})>0)) -> 5
J23: 5.5 | K23: =SUMPRODUCT((J23-$B$6*{0,1,2,3,4,5,6})*((J23-$B$6*{0,1,2,3,4,5,6})>0)) -> 5.5
J24: 6 | K24: =SUMPRODUCT((J24-$B$6*{0,1,2,3,4,5,6})*((J24-$B$6*{0,1,2,3,4,5,6})>0)) -> 6
J25: 6.5 | K25: =SUMPRODUCT((J25-$B$6*{0,1,2,3,4,5,6})*((J25-$B$6*{0,1,2,3,4,5,6})>0)) -> 6.5
J26: 7 | K26: =SUMPRODUCT((J26-$B$6*{0,1,2,3,4,5,6})*((J26-$B$6*{0,1,2,3,4,5,6})>0)) -> 7
J27: 7.5 | K27: =SUMPRODUCT((J27-$B$6*{0,1,2,3,4,5,6})*((J27-$B$6*{0,1,2,3,4,5,6})>0)) -> 7.5
J28: 8 | K28: =SUMPRODUCT((J28-$B$6*{0,1,2,3,4,5,6})*((J28-$B$6*{0,1,2,3,4,5,6})>0)) -> 8
J29: 8.5 | K29: =SUMPRODUCT((J29-$B$6*{0,1,2,3,4,5,6})*((J29-$B$6*{0,1,2,3,4,5,6})>0)) -> 8.5
J30: 9 | K30: =SUMPRODUCT((J30-$B$6*{0,1,2,3,4,5,6})*((J30-$B$6*{0,1,2,3,4,5,6})>0)) -> 9
J31: 9.5 | K31: =SUMPRODUCT((J31-$B$6*{0,1,2,3,4,5,6})*((J31-$B$6*{0,1,2,3,4,5,6})>0)) -> 9.5
J32: 10 | K32: =SUMPRODUCT((J32-$B$6*{0,1,2,3,4,5,6})*((J32-$B$6*{0,1,2,3,4,5,6})>0)) -> 10
J33: 10.5 | K33: =SUMPRODUCT((J33-$B$6*{0,1,2,3,4,5,6})*((J33-$B$6*{0,1,2,3,4,5,6})>0)) -> 11
J34: 11 | K34: =SUMPRODUCT((J34-$B$6*{0,1,2,3,4,5,6})*((J34-$B$6*{0,1,2,3,4,5,6})>0)) -> 12
... J112: 50 | K112: =SUMPRODUCT((J112-$B$6*{0,1,2,3,4,5,6})*((J112-$B$6*{0,1,2,3,4,5,6})>0)) -> 150

Sheet Architecture
A1: Prices inside the architecture: the stability budget and a twitchy optimum (Proposition 15.9; Theorem 15.6(ii); Proposition 15.5; Online Appendix 15.B.1, 15.B.3)
A2: Meridian's feedback core (Chapter 14): engineering links e, treasury links t, the new Digital-Industrial Systems link h. The board's half-life rule: h r* + 2(e^2 + t^2) <= r*^2, r* = 2^(-1/4).
A4: Board's rule: spectral radius at most r* | B4: =2^(-1/4) -> 0.84089642
A5: Engineering links e | B5: 0.4
A6: Treasury links t | B6: 0.4
A7: The new link can carry at most h | B7: =(B4^2-2*(B5^2+B6^2))/B4 -> 0.079803862
A8: Along the binding budget, dh/de = -4e/r* | B8: =-4*B5/B4 -> -1.9027314
A9: New link freed by trimming 0.01 from both engineering links | B9: =-0.01*B8 -> 0.019027314
A11: Chapter 14's uniform repair with the new link at 0.40: e = t | B11: =SQRT((B4^2-0.4*B4)/4) -> 0.30444549
A12: beta/alpha for which that repair is the company's best | B12: =4*B11/B4 -> 1.448195
A13: The budget's price lambda = alpha/r* (alpha = 1) | B13: =1/B4 -> 1.1892071
A14: Each office alone, charged lambda for 2e^2: e* = beta/(4 lambda) | B14: =B12/(4*B13) -> 0.30444549
A15: The budget then leaves the new link | B15: =(B4^2-4*B14^2)/B4 -> 0.4
A17: A twitchy optimum: u* = 1/(1 - a) | B17: a | C17: Response to the payoff 1/(1 - a) | D17: Elasticity to a: a/(1 - a) | E17: Exact move for a 1% recalibration
A18: carry-over a | B18: 0.5 | C18: =1/(1-B18) -> 2 | D18: =B18/(1-B18) -> 1 | E18: =(1-B18)/(1-1.01*B18)-1 -> 0.01010101
A19: carry-over a | B19: 0.8 | C19: =1/(1-B19) -> 5 | D19: =B19/(1-B19) -> 4 | E19: =(1-B19)/(1-1.01*B19)-1 -> 0.041666667
A20: carry-over a | B20: 0.95 | C20: =1/(1-B20) -> 20 | D20: =B20/(1-B20) -> 19 | E20: =(1-B20)/(1-1.01*B20)-1 -> 0.2345679
A22: Online Appendix 15.B.1: responses 2, 5, 20 and elasticities 1, 4, 19 (a = 0.8 is the spectral radius of Meridian's core today). The elasticity is a first-order rate; column E is the exact move.

Sheet Reference_Values
A1: Checkpoint | B1: Engine value | C1: Meaning (where in the book)
A2: Deepest draw, plan as drawn | B2: 138.04962 | C2: Worked Example 8.1: 138
A3: Deepest draw, phased build | B3: 89.026083 | C3: 89
A4: Certainty equivalent: the mean path's trough | B4: 459.85405 | C4: Step 2: $460 million
A5: 90th-percentile closure | B5: 186.86698 | C5: Chapter 12: 187
A6: Robust: the joint check's least line | B6: 54.916594 | C6: Step 2: $55 million
A7: Robust: its cost | B7: 1.6474978 | C7: Step 2: $1.6 million
A8: Cheapest at 5%: line | B8: 170 | C8: Step 3: about $170 million
A9: Cheapest at 5%: delay | B9: 0.66757636 | C9: Step 3: two-thirds of a quarter
A10: Cheapest at 5%: depth | B10: 25.329695 | C10: 25.33
A11: Cheapest at 5%: deepest draw | B11: 121.63437 | C11: 121.6
A12: Cheapest at 5%: draw smaller by | B12: 16.41525 | C12: Step 3: $16 million
A13: Cheapest at 5%: cost | B13: 10.440611 | C13: Step 3: $10.4 million
... A64: Weight sweep: points found | B64: 30 | C64: Theorem 15.5(ii)
A65: Weight sweep: lowest weight picking 4.75% | B65: 1.75
A66: Weight sweep: highest weight picking 4.75% | B66: 1.95
A67: Weight sweep: weight picking 5.25% | B67: 1.7
A68: Weight sweep: the 5% point above the chord | B68: 0.001944157
A69: Audit: delay the capped line needs at 2% | B69: 2.6059866 | C69: more than the cap of 2
A70: Audit: drop the line cap, least cost | B70: 17.860851
A71: Audit: drop the delay cap, least cost | B71: 23.847893
A72: Audit: emptying date (quarters honored) | B72: 8
A73: Allocation: unconstrained financial investment | B73: -11.78 | C73: negative: infeasible
A74: Allocation: corner, human | B74: 1.6285714
A75: Allocation: corner, technological | B75: 4.3714286
A76: Allocation: output at the corner | B76: 296.99348
A77: Allocation: the budget's multiplier | B77: 3.9826712
A78: Allocation: nonnegativity's multiplier | B78: 1.7097619 | C78: positive: it binds
A79: Allocation: gain from a budget larger by 1 | B79: 3.9713207 | C79: at most lambda
A80: Rolling plans: N(50) | B80: 150 | C80: 150
A81: Rolling plans: the quarter cash runs out | B81: 4 | C81: Figure 15.1: quarter 4
A82: Rolling plans: burn in quarter 1, kernel | B82: 40 | C82: 40
A83: Rolling plans: cash in quarter 2, kernel | B83: 60 | C83: 60
A84: Rolling plans: the quarter the burn stops | B84: 5 | C84: quarter 5
A85: Stability budget: the new link at most | B85: 0.079803862 | C85: Proposition 15.9: 0.080
A86: Stability budget: dh/de | B86: -1.9027314 | C86: -1.903
A87: Stability budget: freed by trimming 0.01 | B87: 0.019027314 | C87: 0.019
A88: Twitchy: response at 0.5 | B88: 2 | C88: 2
A89: Twitchy: response at 0.8 | B89: 5 | C89: 5
... A93: Twitchy: elasticity at 0.95 | B93: 19 | C93: 19

Sheet Checks
A1: Checkpoint | B1: Workbook formula value | C1: Engine value | D1: |diff| | E1: Tolerance | F1: Status
A2: Deepest draw, plan as drawn | B2: =Plan!B21 -> 138.04962 | C2: =Reference_Values!B2 -> 138.04962 | D2: =ABS(B2-C2) -> 0 | E2: 1e-09 | F2: =IF(D2<=E2,"PASS","FAIL") -> PASS
A3: Deepest draw, phased build | B3: =Plan!B22 -> 89.026083 | C3: =Reference_Values!B3 -> 89.026083 | D3: =ABS(B3-C3) -> 0 | E3: 1e-09 | F3: =IF(D3<=E3,"PASS","FAIL") -> PASS
A4: Certainty equivalent: the mean path's trough | B4: =Plan!B27 -> 459.85405 | C4: =Reference_Values!B4 -> 459.85405 | D4: =ABS(B4-C4) -> 0 | E4: 1e-09 | F4: =IF(D4<=E4,"PASS","FAIL") -> PASS
A5: 90th-percentile closure | B5: =Plan!B30 -> 186.86698 | C5: =Reference_Values!B5 -> 186.86698 | D5: =ABS(B5-C5) -> 0 | E5: 1e-06 | F5: =IF(D5<=E5,"PASS","FAIL") -> PASS
A6: Robust: the joint check's least line | B6: =Plan!B31 -> 54.916594 | C6: =Reference_Values!B6 -> 54.916594 | D6: =ABS(B6-C6) -> 0 | E6: 1e-06 | F6: =IF(D6<=E6,"PASS","FAIL") -> PASS
A7: Robust: its cost | B7: =Plan!B32 -> 1.6474978 | C7: =Reference_Values!B7 -> 1.6474978 | D7: =ABS(B7-C7) -> 0 | E7: 1e-06 | F7: =IF(D7<=E7,"PASS","FAIL") -> PASS
A8: Cheapest at 5%: line | B8: =Solve!B5 -> 170 | C8: =Reference_Values!B8 -> 170 | D8: =ABS(B8-C8) -> 0 | E8: 0 | F8: =IF(D8<=E8,"PASS","FAIL") -> PASS
A9: Cheapest at 5%: delay | B9: =Solve!B6 -> 0.66757636 | C9: =Reference_Values!B9 -> 0.66757636 | D9: =ABS(B9-C9) -> 0 | E9: 1e-09 | F9: =IF(D9<=E9,"PASS","FAIL") -> PASS
A10: Cheapest at 5%: depth | B10: =Solve!B8 -> 25.329695 | C10: =Reference_Values!B10 -> 25.329695 | D10: =ABS(B10-C10) -> 0 | E10: 1e-09 | F10: =IF(D10<=E10,"PASS","FAIL") -> PASS
A11: Cheapest at 5%: deepest draw | B11: =Solve!B9 -> 121.63437 | C11: =Reference_Values!B11 -> 121.63437 | D11: =ABS(B11-C11) -> 0 | E11: 1e-09 | F11: =IF(D11<=E11,"PASS","FAIL") -> PASS
A12: Cheapest at 5%: draw smaller by | B12: =Solve!B10 -> 16.41525 | C12: =Reference_Values!B12 -> 16.41525 | D12: =ABS(B12-C12) -> 0 | E12: 1e-09 | F12: =IF(D12<=E12,"PASS","FAIL") -> PASS
A13: Cheapest at 5%: cost | B13: =Solve!B4 -> 10.440611 | C13: =Reference_Values!B13 -> 10.440611 | D13: =ABS(B13-C13) -> 0 | E13: 1e-09 | F13: =IF(D13<=E13,"PASS","FAIL") -> PASS
A14: Cheapest at 5%: fees | B14: =Solve!B11 -> 5.1 | C14: =Reference_Values!B14 -> 5.1 | D14: =ABS(B14-C14) -> 0 | E14: 1e-09 | F14: =IF(D14<=E14,"PASS","FAIL") -> PASS
A15: Cheapest at 5%: cost of the delay | B15: =Solve!B12 -> 5.3406109 | C15: =Reference_Values!B15 -> 5.3406109 | D15: =ABS(B15-C15) -> 0 | E15: 1e-09 | F15: =IF(D15<=E15,"PASS","FAIL") -> PASS
A16: Flat optimum: lowest line within $0.5m | B16: =Solve!B13 -> 140 | C16: =Reference_Values!B16 -> 140 | D16: =ABS(B16-C16) -> 0 | E16: 0 | F16: =IF(D16<=E16,"PASS","FAIL") -> PASS
A17: Flat optimum: highest line within $0.5m | B17: =Solve!B14 -> 205 | C17: =Reference_Values!B17 -> 205 | D17: =ABS(B17-C17) -> 0 | E17: 0 | F17: =IF(D17<=E17,"PASS","FAIL") -> PASS
A18: Leverage with the line fully drawn | B18: =Solve!B16 -> 3.7430186 | C18: =Reference_Values!B18 -> 3.7430186 | D18: =ABS(B18-C18) -> 0 | E18: 1e-09 | F18: =IF(D18<=E18,"PASS","FAIL") -> PASS
A19: Margin: odds cut per $1m of line (points) | B19: =Solve!B24 -> 0.016625 | C19: =Reference_Values!B19 -> 0.016625 | D19: =ABS(B19-C19) -> 0 | E19: 1e-09 | F19: =IF(D19<=E19,"PASS","FAIL") -> PASS
A20: Margin: odds cut per quarter of delay (points) | B20: =Solve!B28 -> 4.516 | C20: =Reference_Values!B20 -> 4.516 | D20: =ABS(B20-C20) -> 0 | E20: 1e-09 | F20: =IF(D20<=E20,"PASS","FAIL") -> PASS
A21: A point of safety by the line | B21: =Solve!B29 -> 1.8045113 | C21: =Reference_Values!B21 -> 1.8045113 | D21: =ABS(B21-C21) -> 0 | E21: 1e-09 | F21: =IF(D21<=E21,"PASS","FAIL") -> PASS
A22: A point of safety by the delay | B22: =Solve!B30 -> 1.7714792 | C22: =Reference_Values!B22 -> 1.7714792 | D22: =ABS(B22-C22) -> 0 | E22: 1e-09 | F22: =IF(D22<=E22,"PASS","FAIL") -> PASS
A23: Least cost at 4% | B23: =Solve!B35 -> 12.350458 | C23: =Reference_Values!B23 -> 12.350458 | D23: =ABS(B23-C23) -> 0 | E23: 1e-09 | F23: =IF(D23<=E23,"PASS","FAIL") -> PASS
A24: Least cost at 4.5% | B24: =Solve!B36 -> 11.388504 | C24: =Reference_Values!B24 -> 11.388504 | D24: =ABS(B24-C24) -> 0 | E24: 1e-09 | F24: =IF(D24<=E24,"PASS","FAIL") -> PASS
A25: Least cost at 5.5% | B25: =Solve!B38 -> 9.5814895 | C25: =Reference_Values!B25 -> 9.5814895 | D25: =ABS(B25-C25) -> 0 | E25: 1e-09 | F25: =IF(D25<=E25,"PASS","FAIL") -> PASS
A26: Least cost at 6% | B26: =Solve!B39 -> 8.8194117 | C26: =Reference_Values!B26 -> 8.8194117 | D26: =ABS(B26-C26) -> 0 | E26: 1e-09 | F26: =IF(D26<=E26,"PASS","FAIL") -> PASS
A27: The appetite's multiplier | B27: =Solve!B40 -> 1.8070148 | C27: =Reference_Values!B27 -> 1.8070148 | D27: =ABS(B27-C27) -> 7.327472e-15 | E27: 1e-09 | F27: =IF(D27<=E27,"PASS","FAIL") -> PASS
A28: The multiplier, 4 to 6% | B28: =Solve!B41 -> 1.765523 | C28: =Reference_Values!B28 -> 1.765523 | D28: =ABS(B28-C28) -> 0 | E28: 1e-09 | F28: =IF(D28<=E28,"PASS","FAIL") -> PASS
A29: Implied cost of a breach | B29: =Solve!B42 -> 180.70148 | C29: =Reference_Values!B29 -> 180.70148 | D29: =ABS(B29-C29) -> 7.1054274e-13 | E29: 1e-06 | F29: =IF(D29<=E29,"PASS","FAIL") -> PASS
A30: $4m a quarter of delay: line | B30: =Sensitivity!C90 -> 140 | C30: =Reference_Values!B30 -> 140 | D30: =ABS(B30-C30) -> 0 | E30: 0 | F30: =IF(D30<=E30,"PASS","FAIL") -> PASS
A31: $4m a quarter of delay: cost | B31: =Sensitivity!B90 -> 7.5246248 | C31: =Reference_Values!B31 -> 7.5246248 | D31: =ABS(B31-C31) -> 0 | E31: 1e-09 | F31: =IF(D31<=E31,"PASS","FAIL") -> PASS
A32: $4m a quarter of delay: price | B32: =Sensitivity!D90 -> 0.9062888 | C32: =Reference_Values!B32 -> 0.9062888 | D32: =ABS(B32-C32) -> 7.1054274e-15 | E32: 1e-09 | F32: =IF(D32<=E32,"PASS","FAIL") -> PASS
A33: $16m a quarter of delay: line | B33: =Sensitivity!C93 -> 195 | C33: =Reference_Values!B33 -> 195 | D33: =ABS(B33-C33) -> 0 | E33: 0 | F33: =IF(D33<=E33,"PASS","FAIL") -> PASS
A34: $16m a quarter of delay: cost | B34: =Sensitivity!B93 -> 15.512875 | C34: =Reference_Values!B34 -> 15.512875 | D34: =ABS(B34-C34) -> 0 | E34: 1e-09 | F34: =IF(D34<=E34,"PASS","FAIL") -> PASS
A35: $16m a quarter of delay: price | B35: =Sensitivity!D93 -> 3.4219778 | C35: =Reference_Values!B35 -> 3.4219778 | D35: =ABS(B35-C35) -> 0 | E35: 1e-09 | F35: =IF(D35<=E35,"PASS","FAIL") -> PASS
A36: Least cost at 1% | B36: =Frontier!B5 -> 23.089332 | C36: =Reference_Values!B36 -> 23.089332 | D36: =ABS(B36-C36) -> 0 | E36: 1e-09 | F36: =IF(D36<=E36,"PASS","FAIL") -> PASS
A37: Least cost at 2% | B37: =Frontier!B9 -> 17.860851 | C37: =Reference_Values!B37 -> 17.860851 | D37: =ABS(B37-C37) -> 0 | E37: 1e-09 | F37: =IF(D37<=E37,"PASS","FAIL") -> PASS
A38: Least cost at 8% | B38: =Frontier!B33 -> 6.2536377 | C38: =Reference_Values!B38 -> 6.2536377 | D38: =ABS(B38-C38) -> 0 | E38: 1e-09 | F38: =IF(D38<=E38,"PASS","FAIL") -> PASS
A39: Least cost at 10% | B39: =Frontier!B41 -> 4.1713729 | C39: =Reference_Values!B39 -> 4.1713729 | D39: =ABS(B39-C39) -> 0 | E39: 1e-09 | F39: =IF(D39<=E39,"PASS","FAIL") -> PASS
A40: Least cost at 12% | B40: =Frontier!B49 -> 3.15 | C40: =Reference_Values!B40 -> 3.15 | D40: =ABS(B40-C40) -> 0 | E40: 1e-09 | F40: =IF(D40<=E40,"PASS","FAIL") -> PASS
A41: Least cost at 15% | B41: =Frontier!B61 -> 2.25 | C41: =Reference_Values!B41 -> 2.25 | D41: =ABS(B41-C41) -> 0 | E41: 1e-09 | F41: =IF(D41<=E41,"PASS","FAIL") -> PASS
A42: Least cost at 20% | B42: =Frontier!B81 -> 1.1859412 | C42: =Reference_Values!B42 -> 1.1859412 | D42: =ABS(B42-C42) -> 7.1054274e-15 | E42: 1e-09 | F42: =IF(D42<=E42,"PASS","FAIL") -> PASS
A43: Least cost at 24.6% | B43: =Frontier!B100 -> 0.019881727 | C43: =Reference_Values!B43 -> 0.019881727 | D43: =ABS(B43-C43) -> 7.1054274e-15 | E43: 1e-09 | F43: =IF(D43<=E43,"PASS","FAIL") -> PASS
A44: Table 15.5: 6%, line | B44: =Frontier!C25 -> 160 | C44: =Reference_Values!B44 -> 160 | D44: =ABS(B44-C44) -> 0 | E44: 0 | F44: =IF(D44<=E44,"PASS","FAIL") -> PASS
A45: Table 15.5: 6%, delay | B45: =Frontier!D25 -> 0.50242646 | C45: =Reference_Values!B45 -> 0.50242646 | D45: =ABS(B45-C45) -> 0 | E45: 1e-09 | F45: =IF(D45<=E45,"PASS","FAIL") -> PASS
A46: Table 15.5: 4%, line | B46: =Frontier!C17 -> 165 | C46: =Reference_Values!B46 -> 165 | D46: =ABS(B46-C46) -> 0 | E46: 0 | F46: =IF(D46<=E46,"PASS","FAIL") -> PASS
A47: Table 15.5: 4%, delay | B47: =Frontier!D17 -> 0.9250572 | C47: =Reference_Values!B47 -> 0.9250572 | D47: =ABS(B47-C47) -> 0 | E47: 1e-09 | F47: =IF(D47<=E47,"PASS","FAIL") -> PASS
A48: Table 15.5: 3%, line | B48: =Frontier!C13 -> 180 | C48: =Reference_Values!B48 -> 180 | D48: =ABS(B48-C48) -> 0 | E48: 0 | F48: =IF(D48<=E48,"PASS","FAIL") -> PASS
A49: Table 15.5: 3%, delay | B49: =Frontier!D13 -> 1.1605155 | C49: =Reference_Values!B49 -> 1.1605155 | D49: =ABS(B49-C49) -> 0 | E49: 1e-09 | F49: =IF(D49<=E49,"PASS","FAIL") -> PASS
A50: Table 15.5: 3%, cost | B50: =Frontier!B13 -> 14.684124 | C50: =Reference_Values!B50 -> 14.684124 | D50: =ABS(B50-C50) -> 0 | E50: 1e-09 | F50: =IF(D50<=E50,"PASS","FAIL") -> PASS
A51: Phasing alone: delay | B51: =Frontier!I6 -> 5.0946732 | C51: =Reference_Values!B51 -> 5.0946732 | D51: =ABS(B51-C51) -> 0 | E51: 1e-09 | F51: =IF(D51<=E51,"PASS","FAIL") -> PASS
A52: Phasing alone: depth | B52: =Frontier!I7 -> 7.6213073 | C52: =Reference_Values!B52 -> 7.6213073 | D52: =ABS(B52-C52) -> 0 | E52: 1e-09 | F52: =IF(D52<=E52,"PASS","FAIL") -> PASS
A53: Phasing alone: cost | B53: =Frontier!I8 -> 40.757385 | C53: =Reference_Values!B53 -> 40.757385 | D53: =ABS(B53-C53) -> 0 | E53: 1e-09 | F53: =IF(D53<=E53,"PASS","FAIL") -> PASS
A54: Value of coordination | B54: =Frontier!I10 -> 30.316774 | C54: =Reference_Values!B54 -> 30.316774 | D54: =ABS(B54-C54) -> 0 | E54: 1e-09 | F54: =IF(D54<=E54,"PASS","FAIL") -> PASS
A55: Chapter 8 package: cost | B55: =Frontier!I14 -> 19 | C55: =Reference_Values!B55 -> 19 | D55: =ABS(B55-C55) -> 0 | E55: 1e-09 | F55: =IF(D55<=E55,"PASS","FAIL") -> PASS
A56: The frontier at the package's odds | B56: =Frontier!I16 -> 14.668098 | C56: =Reference_Values!B56 -> 14.668098 | D56: =ABS(B56-C56) -> 0 | E56: 1e-09 | F56: =IF(D56<=E56,"PASS","FAIL") -> PASS
A57: The frontier at 1.75% | B57: =Frontier!I20 -> 18.880368 | C57: =Reference_Values!B57 -> 18.880368 | D57: =ABS(B57-C57) -> 0 | E57: 1e-09 | F57: =IF(D57<=E57,"PASS","FAIL") -> PASS
A58: Line capped at $100m: cost | B58: =Frontier!I23 -> 13.296891 | C58: =Reference_Values!B58 -> 13.296891 | D58: =ABS(B58-C58) -> 0 | E58: 1e-09 | F58: =IF(D58<=E58,"PASS","FAIL") -> PASS
A59: Line capped at $100m: delay | B59: =Frontier!I24 -> 1.2871114 | C59: =Reference_Values!B59 -> 1.2871114 | D59: =ABS(B59-C59) -> 0 | E59: 1e-09 | F59: =IF(D59<=E59,"PASS","FAIL") -> PASS
A60: Line capped at $100m: extra cost | B60: =Frontier!I25 -> 2.8562802 | C60: =Reference_Values!B60 -> 2.8562802 | D60: =ABS(B60-C60) -> 0 | E60: 1e-09 | F60: =IF(D60<=E60,"PASS","FAIL") -> PASS
A61: 5% contour: delay at line 25 | B61: =Delay!R10 -> 3.8169899 | C61: =Reference_Values!B61 -> 3.8169899 | D61: =ABS(B61-C61) -> 0 | E61: 1e-09 | F61: =IF(D61<=E61,"PASS","FAIL") -> PASS
A62: 5% contour: delay at line 100 | B62: =Delay!R25 -> 1.2871114 | C62: =Reference_Values!B62 -> 1.2871114 | D62: =ABS(B62-C62) -> 0 | E62: 1e-09 | F62: =IF(D62<=E62,"PASS","FAIL") -> PASS
A63: 5% contour: delay at line 250 | B63: =Delay!R55 -> 0.56675859 | C63: =Reference_Values!B63 -> 0.56675859 | D63: =ABS(B63-C63) -> 0 | E63: 1e-09 | F63: =IF(D63<=E63,"PASS","FAIL") -> PASS
A64: Weight sweep: points found | B64: =WeightSweep!B106 -> 30 | C64: =Reference_Values!B64 -> 30 | D64: =ABS(B64-C64) -> 0 | E64: 1e-06 | F64: =IF(D64<=E64,"PASS","FAIL") -> PASS
A65: Weight sweep: lowest weight picking 4.75% | B65: =WeightSweep!B107 -> 1.75 | C65: =Reference_Values!B65 -> 1.75 | D65: =ABS(B65-C65) -> 0 | E65: 1e-09 | F65: =IF(D65<=E65,"PASS","FAIL") -> PASS
A66: Weight sweep: highest weight picking 4.75% | B66: =WeightSweep!B108 -> 1.95 | C66: =Reference_Values!B66 -> 1.95 | D66: =ABS(B66-C66) -> 0 | E66: 1e-09 | F66: =IF(D66<=E66,"PASS","FAIL") -> PASS
A67: Weight sweep: weight picking 5.25% | B67: =WeightSweep!B109 -> 1.7 | C67: =Reference_Values!B67 -> 1.7 | D67: =ABS(B67-C67) -> 0 | E67: 1e-09 | F67: =IF(D67<=E67,"PASS","FAIL") -> PASS
A68: Weight sweep: the 5% point above the chord | B68: =WeightSweep!B111 -> 0.001944157 | C68: =Reference_Values!B68 -> 0.001944157 | D68: =ABS(B68-C68) -> 0 | E68: 1e-09 | F68: =IF(D68<=E68,"PASS","FAIL") -> PASS
A69: Audit: delay the capped line needs at 2% | B69: =Audit!B18 -> 2.6059866 | C69: =Reference_Values!B69 -> 2.6059866 | D69: =ABS(B69-C69) -> 0 | E69: 1e-09 | F69: =IF(D69<=E69,"PASS","FAIL") -> PASS
A70: Audit: drop the line cap, least cost | B70: =Audit!B21 -> 17.860851 | C70: =Reference_Values!B70 -> 17.860851 | D70: =ABS(B70-C70) -> 0 | E70: 1e-09 | F70: =IF(D70<=E70,"PASS","FAIL") -> PASS
A71: Audit: drop the delay cap, least cost | B71: =Audit!B23 -> 23.847893 | C71: =Reference_Values!B71 -> 23.847893 | D71: =ABS(B71-C71) -> 0 | E71: 1e-09 | F71: =IF(D71<=E71,"PASS","FAIL") -> PASS
A72: Audit: emptying date (quarters honored) | B72: =Audit!B42 -> 8 | C72: =Reference_Values!B72 -> 8 | D72: =ABS(B72-C72) -> 0 | E72: 0 | F72: =IF(D72<=E72,"PASS","FAIL") -> PASS
A73: Allocation: unconstrained financial investment | B73: =Allocation!B11 -> -11.78 | C73: =Reference_Values!B73 -> -11.78 | D73: =ABS(B73-C73) -> 0 | E73: 1e-09 | F73: =IF(D73<=E73,"PASS","FAIL") -> PASS
A74: Allocation: corner, human | B74: =Allocation!C12 -> 1.6285714 | C74: =Reference_Values!B74 -> 1.6285714 | D74: =ABS(B74-C74) -> 0 | E74: 1e-09 | F74: =IF(D74<=E74,"PASS","FAIL") -> PASS
A75: Allocation: corner, technological | B75: =Allocation!D12 -> 4.3714286 | C75: =Reference_Values!B75 -> 4.3714286 | D75: =ABS(B75-C75) -> 0 | E75: 1e-09 | F75: =IF(D75<=E75,"PASS","FAIL") -> PASS
A76: Allocation: output at the corner | B76: =Allocation!B14 -> 296.99348 | C76: =Reference_Values!B76 -> 296.99348 | D76: =ABS(B76-C76) -> 0 | E76: 1e-09 | F76: =IF(D76<=E76,"PASS","FAIL") -> PASS
A77: Allocation: the budget's multiplier | B77: =Allocation!B17 -> 3.9826712 | C77: =Reference_Values!B77 -> 3.9826712 | D77: =ABS(B77-C77) -> 0 | E77: 1e-09 | F77: =IF(D77<=E77,"PASS","FAIL") -> PASS
A78: Allocation: nonnegativity's multiplier | B78: =Allocation!B18 -> 1.7097619 | C78: =Reference_Values!B78 -> 1.7097619 | D78: =ABS(B78-C78) -> 0 | E78: 1e-09 | F78: =IF(D78<=E78,"PASS","FAIL") -> PASS
A79: Allocation: gain from a budget larger by 1 | B79: =Allocation!B23 -> 3.9713207 | C79: =Reference_Values!B79 -> 3.9713207 | D79: =ABS(B79-C79) -> 5.639933e-14 | E79: 1e-09 | F79: =IF(D79<=E79,"PASS","FAIL") -> PASS
A80: Rolling plans: N(50) | B80: =RollingPlans!B7 -> 150 | C80: =Reference_Values!B80 -> 150 | D80: =ABS(B80-C80) -> 0 | E80: 1e-09 | F80: =IF(D80<=E80,"PASS","FAIL") -> PASS
A81: Rolling plans: the quarter cash runs out | B81: =RollingPlans!B19 -> 4 | C81: =Reference_Values!B81 -> 4 | D81: =ABS(B81-C81) -> 0 | E81: 0 | F81: =IF(D81<=E81,"PASS","FAIL") -> PASS
A82: Rolling plans: burn in quarter 1, kernel | B82: =RollingPlans!E12 -> 40 | C82: =Reference_Values!B82 -> 40 | D82: =ABS(B82-C82) -> 0 | E82: 1e-06 | F82: =IF(D82<=E82,"PASS","FAIL") -> PASS
A83: Rolling plans: cash in quarter 2, kernel | B83: =RollingPlans!D13 -> 60 | C83: =Reference_Values!B83 -> 60 | D83: =ABS(B83-C83) -> 0 | E83: 1e-06 | F83: =IF(D83<=E83,"PASS","FAIL") -> PASS
A84: Rolling plans: the quarter the burn stops | B84: =RollingPlans!B20 -> 5 | C84: =Reference_Values!B84 -> 5 | D84: =ABS(B84-C84) -> 0 | E84: 0 | F84: =IF(D84<=E84,"PASS","FAIL") -> PASS
A85: Stability budget: the new link at most | B85: =Architecture!B7 -> 0.079803862 | C85: =Reference_Values!B85 -> 0.079803862 | D85: =ABS(B85-C85) -> 0 | E85: 1e-09 | F85: =IF(D85<=E85,"PASS","FAIL") -> PASS
A86: Stability budget: dh/de | B86: =Architecture!B8 -> -1.9027314 | C86: =Reference_Values!B86 -> -1.9027314 | D86: =ABS(B86-C86) -> 0 | E86: 1e-09 | F86: =IF(D86<=E86,"PASS","FAIL") -> PASS
A87: Stability budget: freed by trimming 0.01 | B87: =Architecture!B9 -> 0.019027314 | C87: =Reference_Values!B87 -> 0.019027314 | D87: =ABS(B87-C87) -> 0 | E87: 1e-09 | F87: =IF(D87<=E87,"PASS","FAIL") -> PASS
A88: Twitchy: response at 0.5 | B88: =Architecture!C18 -> 2 | C88: =Reference_Values!B88 -> 2 | D88: =ABS(B88-C88) -> 0 | E88: 1e-09 | F88: =IF(D88<=E88,"PASS","FAIL") -> PASS
A89: Twitchy: response at 0.8 | B89: =Architecture!C19 -> 5 | C89: =Reference_Values!B89 -> 5 | D89: =ABS(B89-C89) -> 0 | E89: 1e-09 | F89: =IF(D89<=E89,"PASS","FAIL") -> PASS
A90: Twitchy: response at 0.95 | B90: =Architecture!C20 -> 20 | C90: =Reference_Values!B90 -> 20 | D90: =ABS(B90-C90) -> 0 | E90: 1e-09 | F90: =IF(D90<=E90,"PASS","FAIL") -> PASS
A91: Twitchy: elasticity at 0.5 | B91: =Architecture!D18 -> 1 | C91: =Reference_Values!B91 -> 1 | D91: =ABS(B91-C91) -> 0 | E91: 1e-09 | F91: =IF(D91<=E91,"PASS","FAIL") -> PASS
A92: Twitchy: elasticity at 0.8 | B92: =Architecture!D19 -> 4 | C92: =Reference_Values!B92 -> 4 | D92: =ABS(B92-C92) -> 0 | E92: 1e-09 | F92: =IF(D92<=E92,"PASS","FAIL") -> PASS
A93: Twitchy: elasticity at 0.95 | B93: =Architecture!D20 -> 19 | C93: =Reference_Values!B93 -> 19 | D93: =ABS(B93-C93) -> 0 | E93: 1e-09 | F93: =IF(D93<=E93,"PASS","FAIL") -> PASS
A95: All checkpoints | F95: =IF(COUNTIF(F2:F93,"PASS")=92,"ALL PASS","CHECK") -> ALL PASS
